public class ryey.easer.plugins.a.d.d extends ryey.easer.plugins.c<ryey.easer.plugins.a.d.a> implements ryey.easer.plugins.b.e$c {
  public ryey.easer.plugins.a.d.d();
    Code:
       0: aload_0
       1: invokespecial #15                 // Method ryey/easer/plugins/c."<init>":()V
       4: return

  public ryey.easer.commons.local_plugin.f a();
    Code:
       0: aload_0
       1: invokevirtual #21                 // Method b:()Lryey/easer/plugins/a/d/a;
       4: areturn

  public void a(java.util.List<ryey.easer.plugins.b.b>);
    Code:
       0: new           #24                 // class java/lang/StringBuilder
       3: dup
       4: aload_0
       5: getfield      #26                 // Field a:Landroid/widget/EditText;
       8: invokevirtual #32                 // Method android/widget/EditText.getText:()Landroid/text/Editable;
      11: invokevirtual #38                 // Method java/lang/Object.toString:()Ljava/lang/String;
      14: invokespecial #41                 // Method java/lang/StringBuilder."<init>":(Ljava/lang/String;)V
      17: astore_2
      18: aload_1
      19: invokeinterface #47,  1           // InterfaceMethod java/util/List.iterator:()Ljava/util/Iterator;
      24: astore_1
      25: aload_1
      26: invokeinterface #53,  1           // InterfaceMethod java/util/Iterator.hasNext:()Z
      31: ifeq          63
      34: aload_1
      35: invokeinterface #57,  1           // InterfaceMethod java/util/Iterator.next:()Ljava/lang/Object;
      40: checkcast     #59                 // class ryey/easer/plugins/b/b
      43: astore_3
      44: aload_2
      45: bipush        10
      47: invokevirtual #63                 // Method java/lang/StringBuilder.append:(C)Ljava/lang/StringBuilder;
      50: pop
      51: aload_2
      52: aload_3
      53: invokevirtual #64                 // Method ryey/easer/plugins/b/b.toString:()Ljava/lang/String;
      56: invokevirtual #67                 // Method java/lang/StringBuilder.append:(Ljava/lang/String;)Ljava/lang/StringBuilder;
      59: pop
      60: goto          25
      63: aload_2
      64: iconst_0
      65: invokevirtual #71                 // Method java/lang/StringBuilder.charAt:(I)C
      68: bipush        10
      70: if_icmpne     79
      73: aload_2
      74: iconst_0
      75: invokevirtual #75                 // Method java/lang/StringBuilder.deleteCharAt:(I)Ljava/lang/StringBuilder;
      78: pop
      79: aload_0
      80: getfield      #26                 // Field a:Landroid/widget/EditText;
      83: aload_2
      84: invokevirtual #76                 // Method java/lang/StringBuilder.toString:()Ljava/lang/String;
      87: invokevirtual #80                 // Method android/widget/EditText.setText:(Ljava/lang/CharSequence;)V
      90: return

  protected void a(ryey.easer.plugins.a.d.a);
    Code:
       0: aload_0
       1: getfield      #26                 // Field a:Landroid/widget/EditText;
       4: aload_1
       5: invokevirtual #86                 // Method ryey/easer/plugins/a/d/a.toString:()Ljava/lang/String;
       8: invokevirtual #80                 // Method android/widget/EditText.setText:(Ljava/lang/CharSequence;)V
      11: return

  public ryey.easer.plugins.a.d.a b();
    Code:
       0: new           #85                 // class ryey/easer/plugins/a/d/a
       3: dup
       4: aload_0
       5: getfield      #26                 // Field a:Landroid/widget/EditText;
       8: invokevirtual #32                 // Method android/widget/EditText.getText:()Landroid/text/Editable;
      11: invokevirtual #38                 // Method java/lang/Object.toString:()Ljava/lang/String;
      14: ldc           #88                 // String \n
      16: invokevirtual #94                 // Method java/lang/String.split:(Ljava/lang/String;)[Ljava/lang/String;
      19: invokespecial #97                 // Method ryey/easer/plugins/a/d/a."<init>":([Ljava/lang/String;)V
      22: astore_1
      23: aload_1
      24: invokevirtual #99                 // Method ryey/easer/plugins/a/d/a.a:()Z
      27: ifeq          32
      30: aload_1
      31: areturn
      32: new           #101                // class ryey/easer/commons/local_plugin/c
      35: dup
      36: invokespecial #102                // Method ryey/easer/commons/local_plugin/c."<init>":()V
      39: athrow

  protected void b(ryey.easer.commons.local_plugin.f);
    Code:
       0: aload_0
       1: aload_1
       2: checkcast     #85                 // class ryey/easer/plugins/a/d/a
       5: invokevirtual #105                // Method a:(Lryey/easer/plugins/a/d/a;)V
       8: return

  public android.view.View onCreateView(android.view.LayoutInflater, android.view.ViewGroup, android.os.Bundle);
    Code:
       0: aload_1
       1: ldc           #108                // int 2131427433
       3: aload_2
       4: iconst_0
       5: invokevirtual #114                // Method android/view/LayoutInflater.inflate:(ILandroid/view/ViewGroup;Z)Landroid/view/View;
       8: astore_1
       9: aload_0
      10: aload_1
      11: ldc           #115                // int 2131296473
      13: invokevirtual #121                // Method android/view/View.findViewById:(I)Landroid/view/View;
      16: checkcast     #28                 // class android/widget/EditText
      19: putfield      #26                 // Field a:Landroid/widget/EditText;
      22: aload_1
      23: ldc           #122                // int 2131296472
      25: invokevirtual #121                // Method android/view/View.findViewById:(I)Landroid/view/View;
      28: new           #9                  // class ryey/easer/plugins/a/d/d$1
      31: dup
      32: aload_0
      33: invokespecial #125                // Method ryey/easer/plugins/a/d/d$1."<init>":(Lryey/easer/plugins/a/d/d;)V
      36: invokevirtual #129                // Method android/view/View.setOnClickListener:(Landroid/view/View$OnClickListener;)V
      39: aload_1
      40: areturn
}
