class ryey.easer.plugins.a.d.e$a extends android.telephony.PhoneStateListener {
  final ryey.easer.plugins.a.d.e a;

  ryey.easer.plugins.a.d.e$a(ryey.easer.plugins.a.d.e);
    Code:
       0: aload_0
       1: aload_1
       2: putfield      #12                 // Field a:Lryey/easer/plugins/a/d/e;
       5: aload_0
       6: invokespecial #15                 // Method android/telephony/PhoneStateListener."<init>":()V
       9: return

  public void onCellLocationChanged(android.telephony.CellLocation);
    Code:
       0: aload_0
       1: monitorenter
       2: aload_0
       3: aload_1
       4: invokespecial #20                 // Method android/telephony/PhoneStateListener.onCellLocationChanged:(Landroid/telephony/CellLocation;)V
       7: aload_0
       8: getfield      #12                 // Field a:Lryey/easer/plugins/a/d/e;
      11: aload_0
      12: getfield      #12                 // Field a:Lryey/easer/plugins/a/d/e;
      15: aload_1
      16: invokestatic  #23                 // Method ryey/easer/plugins/a/d/e.a:(Lryey/easer/plugins/a/d/e;Landroid/telephony/CellLocation;)Ljava/lang/Boolean;
      19: invokestatic  #26                 // Method ryey/easer/plugins/a/d/e.a:(Lryey/easer/plugins/a/d/e;Ljava/lang/Boolean;)V
      22: aload_0
      23: monitorexit
      24: return
      25: astore_1
      26: aload_0
      27: monitorexit
      28: aload_1
      29: athrow
    Exception table:
       from    to  target type
           2    22    25   any
}
