class android.support.v7.widget.aa {
  final android.widget.TextView a;

  android.support.v7.widget.aa(android.widget.TextView);
    Code:
       0: aload_0
       1: invokespecial #26                 // Method java/lang/Object."<init>":()V
       4: aload_0
       5: iconst_0
       6: putfield      #28                 // Field g:I
       9: aload_0
      10: aload_1
      11: putfield      #30                 // Field a:Landroid/widget/TextView;
      14: aload_0
      15: new           #32                 // class android/support/v7/widget/ad
      18: dup
      19: aload_0
      20: getfield      #30                 // Field a:Landroid/widget/TextView;
      23: invokespecial #34                 // Method android/support/v7/widget/ad."<init>":(Landroid/widget/TextView;)V
      26: putfield      #36                 // Field f:Landroid/support/v7/widget/ad;
      29: return

  static android.support.v7.widget.aa a(android.widget.TextView);
    Code:
       0: getstatic     #43                 // Field android/os/Build$VERSION.SDK_INT:I
       3: bipush        17
       5: if_icmplt     17
       8: new           #45                 // class android/support/v7/widget/ab
      11: dup
      12: aload_0
      13: invokespecial #46                 // Method android/support/v7/widget/ab."<init>":(Landroid/widget/TextView;)V
      16: areturn
      17: new           #2                  // class android/support/v7/widget/aa
      20: dup
      21: aload_0
      22: invokespecial #47                 // Method "<init>":(Landroid/widget/TextView;)V
      25: areturn

  protected static android.support.v7.widget.bn a(android.content.Context, android.support.v7.widget.m, int);
    Code:
       0: aload_1
       1: aload_0
       2: iload_2
       3: invokevirtual #53                 // Method android/support/v7/widget/m.b:(Landroid/content/Context;I)Landroid/content/res/ColorStateList;
       6: astore_0
       7: aload_0
       8: ifnull        31
      11: new           #55                 // class android/support/v7/widget/bn
      14: dup
      15: invokespecial #56                 // Method android/support/v7/widget/bn."<init>":()V
      18: astore_1
      19: aload_1
      20: iconst_1
      21: putfield      #58                 // Field android/support/v7/widget/bn.d:Z
      24: aload_1
      25: aload_0
      26: putfield      #61                 // Field android/support/v7/widget/bn.a:Landroid/content/res/ColorStateList;
      29: aload_1
      30: areturn
      31: aconst_null
      32: areturn

  static void a(android.support.v7.widget.aa, java.lang.ref.WeakReference, android.graphics.Typeface);
    Code:
       0: aload_0
       1: aload_1
       2: aload_2
       3: invokespecial #131                // Method a:(Ljava/lang/ref/WeakReference;Landroid/graphics/Typeface;)V
       6: return

  void a();
    Code:
       0: aload_0
       1: getfield      #148                // Field b:Landroid/support/v7/widget/bn;
       4: ifnonnull     28
       7: aload_0
       8: getfield      #150                // Field c:Landroid/support/v7/widget/bn;
      11: ifnonnull     28
      14: aload_0
      15: getfield      #152                // Field d:Landroid/support/v7/widget/bn;
      18: ifnonnull     28
      21: aload_0
      22: getfield      #154                // Field e:Landroid/support/v7/widget/bn;
      25: ifnull        80
      28: aload_0
      29: getfield      #30                 // Field a:Landroid/widget/TextView;
      32: invokevirtual #158                // Method android/widget/TextView.getCompoundDrawables:()[Landroid/graphics/drawable/Drawable;
      35: astore_1
      36: aload_0
      37: aload_1
      38: iconst_0
      39: aaload
      40: aload_0
      41: getfield      #148                // Field b:Landroid/support/v7/widget/bn;
      44: invokevirtual #161                // Method a:(Landroid/graphics/drawable/Drawable;Landroid/support/v7/widget/bn;)V
      47: aload_0
      48: aload_1
      49: iconst_1
      50: aaload
      51: aload_0
      52: getfield      #150                // Field c:Landroid/support/v7/widget/bn;
      55: invokevirtual #161                // Method a:(Landroid/graphics/drawable/Drawable;Landroid/support/v7/widget/bn;)V
      58: aload_0
      59: aload_1
      60: iconst_2
      61: aaload
      62: aload_0
      63: getfield      #152                // Field d:Landroid/support/v7/widget/bn;
      66: invokevirtual #161                // Method a:(Landroid/graphics/drawable/Drawable;Landroid/support/v7/widget/bn;)V
      69: aload_0
      70: aload_1
      71: iconst_3
      72: aaload
      73: aload_0
      74: getfield      #154                // Field e:Landroid/support/v7/widget/bn;
      77: invokevirtual #161                // Method a:(Landroid/graphics/drawable/Drawable;Landroid/support/v7/widget/bn;)V
      80: return

  void a(int);
    Code:
       0: aload_0
       1: getfield      #36                 // Field f:Landroid/support/v7/widget/ad;
       4: iload_1
       5: invokevirtual #164                // Method android/support/v7/widget/ad.a:(I)V
       8: return

  void a(int, float);
    Code:
       0: getstatic     #168                // Field android/support/v4/widget/b.a:Z
       3: ifne          19
       6: aload_0
       7: invokevirtual #170                // Method c:()Z
      10: ifne          19
      13: aload_0
      14: iload_1
      15: fload_2
      16: invokespecial #172                // Method b:(IF)V
      19: return

  void a(int, int, int, int);
    Code:
       0: aload_0
       1: getfield      #36                 // Field f:Landroid/support/v7/widget/ad;
       4: iload_1
       5: iload_2
       6: iload_3
       7: iload         4
       9: invokevirtual #175                // Method android/support/v7/widget/ad.a:(IIII)V
      12: return

  void a(android.content.Context, int);
    Code:
       0: aload_1
       1: iload_2
       2: getstatic     #180                // Field android/support/v7/a/a$j.TextAppearance:[I
       5: invokestatic  #183                // Method android/support/v7/widget/bp.a:(Landroid/content/Context;I[I)Landroid/support/v7/widget/bp;
       8: astore_3
       9: aload_3
      10: getstatic     #186                // Field android/support/v7/a/a$j.TextAppearance_textAllCaps:I
      13: invokevirtual #82                 // Method android/support/v7/widget/bp.g:(I)Z
      16: ifeq          31
      19: aload_0
      20: aload_3
      21: getstatic     #186                // Field android/support/v7/a/a$j.TextAppearance_textAllCaps:I
      24: iconst_0
      25: invokevirtual #189                // Method android/support/v7/widget/bp.a:(IZ)Z
      28: invokevirtual #192                // Method a:(Z)V
      31: getstatic     #43                 // Field android/os/Build$VERSION.SDK_INT:I
      34: bipush        23
      36: if_icmpge     72
      39: aload_3
      40: getstatic     #195                // Field android/support/v7/a/a$j.TextAppearance_android_textColor:I
      43: invokevirtual #82                 // Method android/support/v7/widget/bp.g:(I)Z
      46: ifeq          72
      49: aload_3
      50: getstatic     #195                // Field android/support/v7/a/a$j.TextAppearance_android_textColor:I
      53: invokevirtual #198                // Method android/support/v7/widget/bp.e:(I)Landroid/content/res/ColorStateList;
      56: astore        4
      58: aload         4
      60: ifnull        72
      63: aload_0
      64: getfield      #30                 // Field a:Landroid/widget/TextView;
      67: aload         4
      69: invokevirtual #202                // Method android/widget/TextView.setTextColor:(Landroid/content/res/ColorStateList;)V
      72: aload_0
      73: aload_1
      74: aload_3
      75: invokespecial #204                // Method a:(Landroid/content/Context;Landroid/support/v7/widget/bp;)V
      78: aload_3
      79: invokevirtual #206                // Method android/support/v7/widget/bp.a:()V
      82: aload_0
      83: getfield      #103                // Field h:Landroid/graphics/Typeface;
      86: ifnull        104
      89: aload_0
      90: getfield      #30                 // Field a:Landroid/widget/TextView;
      93: aload_0
      94: getfield      #103                // Field h:Landroid/graphics/Typeface;
      97: aload_0
      98: getfield      #28                 // Field g:I
     101: invokevirtual #141                // Method android/widget/TextView.setTypeface:(Landroid/graphics/Typeface;I)V
     104: return

  final void a(android.graphics.drawable.Drawable, android.support.v7.widget.bn);
    Code:
       0: aload_1
       1: ifnull        20
       4: aload_2
       5: ifnull        20
       8: aload_1
       9: aload_2
      10: aload_0
      11: getfield      #30                 // Field a:Landroid/widget/TextView;
      14: invokevirtual #210                // Method android/widget/TextView.getDrawableState:()[I
      17: invokestatic  #213                // Method android/support/v7/widget/m.a:(Landroid/graphics/drawable/Drawable;Landroid/support/v7/widget/bn;[I)V
      20: return

  void a(android.util.AttributeSet, int);
    Code:
       0: aload_0
       1: getfield      #30                 // Field a:Landroid/widget/TextView;
       4: invokevirtual #221                // Method android/widget/TextView.getContext:()Landroid/content/Context;
       7: astore        14
       9: invokestatic  #224                // Method android/support/v7/widget/m.a:()Landroid/support/v7/widget/m;
      12: astore        8
      14: aload         14
      16: aload_1
      17: getstatic     #227                // Field android/support/v7/a/a$j.AppCompatTextHelper:[I
      20: iload_2
      21: iconst_0
      22: invokestatic  #230                // Method android/support/v7/widget/bp.a:(Landroid/content/Context;Landroid/util/AttributeSet;[III)Landroid/support/v7/widget/bp;
      25: astore        9
      27: aload         9
      29: getstatic     #233                // Field android/support/v7/a/a$j.AppCompatTextHelper_android_textAppearance:I
      32: iconst_m1
      33: invokevirtual #235                // Method android/support/v7/widget/bp.g:(II)I
      36: istore_3
      37: aload         9
      39: getstatic     #238                // Field android/support/v7/a/a$j.AppCompatTextHelper_android_drawableLeft:I
      42: invokevirtual #82                 // Method android/support/v7/widget/bp.g:(I)Z
      45: ifeq          68
      48: aload_0
      49: aload         14
      51: aload         8
      53: aload         9
      55: getstatic     #238                // Field android/support/v7/a/a$j.AppCompatTextHelper_android_drawableLeft:I
      58: iconst_0
      59: invokevirtual #235                // Method android/support/v7/widget/bp.g:(II)I
      62: invokestatic  #240                // Method a:(Landroid/content/Context;Landroid/support/v7/widget/m;I)Landroid/support/v7/widget/bn;
      65: putfield      #148                // Field b:Landroid/support/v7/widget/bn;
      68: aload         9
      70: getstatic     #243                // Field android/support/v7/a/a$j.AppCompatTextHelper_android_drawableTop:I
      73: invokevirtual #82                 // Method android/support/v7/widget/bp.g:(I)Z
      76: ifeq          99
      79: aload_0
      80: aload         14
      82: aload         8
      84: aload         9
      86: getstatic     #243                // Field android/support/v7/a/a$j.AppCompatTextHelper_android_drawableTop:I
      89: iconst_0
      90: invokevirtual #235                // Method android/support/v7/widget/bp.g:(II)I
      93: invokestatic  #240                // Method a:(Landroid/content/Context;Landroid/support/v7/widget/m;I)Landroid/support/v7/widget/bn;
      96: putfield      #150                // Field c:Landroid/support/v7/widget/bn;
      99: aload         9
     101: getstatic     #246                // Field android/support/v7/a/a$j.AppCompatTextHelper_android_drawableRight:I
     104: invokevirtual #82                 // Method android/support/v7/widget/bp.g:(I)Z
     107: ifeq          130
     110: aload_0
     111: aload         14
     113: aload         8
     115: aload         9
     117: getstatic     #246                // Field android/support/v7/a/a$j.AppCompatTextHelper_android_drawableRight:I
     120: iconst_0
     121: invokevirtual #235                // Method android/support/v7/widget/bp.g:(II)I
     124: invokestatic  #240                // Method a:(Landroid/content/Context;Landroid/support/v7/widget/m;I)Landroid/support/v7/widget/bn;
     127: putfield      #152                // Field d:Landroid/support/v7/widget/bn;
     130: aload         9
     132: getstatic     #249                // Field android/support/v7/a/a$j.AppCompatTextHelper_android_drawableBottom:I
     135: invokevirtual #82                 // Method android/support/v7/widget/bp.g:(I)Z
     138: ifeq          161
     141: aload_0
     142: aload         14
     144: aload         8
     146: aload         9
     148: getstatic     #249                // Field android/support/v7/a/a$j.AppCompatTextHelper_android_drawableBottom:I
     151: iconst_0
     152: invokevirtual #235                // Method android/support/v7/widget/bp.g:(II)I
     155: invokestatic  #240                // Method a:(Landroid/content/Context;Landroid/support/v7/widget/m;I)Landroid/support/v7/widget/bn;
     158: putfield      #154                // Field e:Landroid/support/v7/widget/bn;
     161: aload         9
     163: invokevirtual #206                // Method android/support/v7/widget/bp.a:()V
     166: aload_0
     167: getfield      #30                 // Field a:Landroid/widget/TextView;
     170: invokevirtual #253                // Method android/widget/TextView.getTransformationMethod:()Landroid/text/method/TransformationMethod;
     173: instanceof    #255                // class android/text/method/PasswordTransformationMethod
     176: istore        7
     178: aconst_null
     179: astore        9
     181: aconst_null
     182: astore        11
     184: aconst_null
     185: astore        10
     187: iload_3
     188: iconst_m1
     189: if_icmpeq     349
     192: aload         14
     194: iload_3
     195: getstatic     #180                // Field android/support/v7/a/a$j.TextAppearance:[I
     198: invokestatic  #183                // Method android/support/v7/widget/bp.a:(Landroid/content/Context;I[I)Landroid/support/v7/widget/bp;
     201: astore        11
     203: iload         7
     205: ifne          235
     208: aload         11
     210: getstatic     #186                // Field android/support/v7/a/a$j.TextAppearance_textAllCaps:I
     213: invokevirtual #82                 // Method android/support/v7/widget/bp.g:(I)Z
     216: ifeq          235
     219: aload         11
     221: getstatic     #186                // Field android/support/v7/a/a$j.TextAppearance_textAllCaps:I
     224: iconst_0
     225: invokevirtual #189                // Method android/support/v7/widget/bp.a:(IZ)Z
     228: istore        5
     230: iconst_1
     231: istore_3
     232: goto          240
     235: iconst_0
     236: istore_3
     237: iconst_0
     238: istore        5
     240: aload_0
     241: aload         14
     243: aload         11
     245: invokespecial #204                // Method a:(Landroid/content/Context;Landroid/support/v7/widget/bp;)V
     248: getstatic     #43                 // Field android/os/Build$VERSION.SDK_INT:I
     251: bipush        23
     253: if_icmpge     334
     256: aload         11
     258: getstatic     #195                // Field android/support/v7/a/a$j.TextAppearance_android_textColor:I
     261: invokevirtual #82                 // Method android/support/v7/widget/bp.g:(I)Z
     264: ifeq          280
     267: aload         11
     269: getstatic     #195                // Field android/support/v7/a/a$j.TextAppearance_android_textColor:I
     272: invokevirtual #198                // Method android/support/v7/widget/bp.e:(I)Landroid/content/res/ColorStateList;
     275: astore        9
     277: goto          283
     280: aconst_null
     281: astore        9
     283: aload         11
     285: getstatic     #258                // Field android/support/v7/a/a$j.TextAppearance_android_textColorHint:I
     288: invokevirtual #82                 // Method android/support/v7/widget/bp.g:(I)Z
     291: ifeq          307
     294: aload         11
     296: getstatic     #258                // Field android/support/v7/a/a$j.TextAppearance_android_textColorHint:I
     299: invokevirtual #198                // Method android/support/v7/widget/bp.e:(I)Landroid/content/res/ColorStateList;
     302: astore        8
     304: goto          310
     307: aconst_null
     308: astore        8
     310: aload         11
     312: getstatic     #261                // Field android/support/v7/a/a$j.TextAppearance_android_textColorLink:I
     315: invokevirtual #82                 // Method android/support/v7/widget/bp.g:(I)Z
     318: ifeq          331
     321: aload         11
     323: getstatic     #261                // Field android/support/v7/a/a$j.TextAppearance_android_textColorLink:I
     326: invokevirtual #198                // Method android/support/v7/widget/bp.e:(I)Landroid/content/res/ColorStateList;
     329: astore        10
     331: goto          341
     334: aconst_null
     335: astore        10
     337: aload         10
     339: astore        8
     341: aload         11
     343: invokevirtual #206                // Method android/support/v7/widget/bp.a:()V
     346: goto          365
     349: aconst_null
     350: astore        10
     352: aload         10
     354: astore        8
     356: iconst_0
     357: istore_3
     358: iconst_0
     359: istore        5
     361: aload         11
     363: astore        9
     365: aload         14
     367: aload_1
     368: getstatic     #180                // Field android/support/v7/a/a$j.TextAppearance:[I
     371: iload_2
     372: iconst_0
     373: invokestatic  #230                // Method android/support/v7/widget/bp.a:(Landroid/content/Context;Landroid/util/AttributeSet;[III)Landroid/support/v7/widget/bp;
     376: astore        15
     378: iload_3
     379: istore        4
     381: iload         5
     383: istore        6
     385: iload         7
     387: ifne          422
     390: iload_3
     391: istore        4
     393: iload         5
     395: istore        6
     397: aload         15
     399: getstatic     #186                // Field android/support/v7/a/a$j.TextAppearance_textAllCaps:I
     402: invokevirtual #82                 // Method android/support/v7/widget/bp.g:(I)Z
     405: ifeq          422
     408: aload         15
     410: getstatic     #186                // Field android/support/v7/a/a$j.TextAppearance_textAllCaps:I
     413: iconst_0
     414: invokevirtual #189                // Method android/support/v7/widget/bp.a:(IZ)Z
     417: istore        6
     419: iconst_1
     420: istore        4
     422: aload         9
     424: astore        12
     426: aload         10
     428: astore        13
     430: aload         8
     432: astore        11
     434: getstatic     #43                 // Field android/os/Build$VERSION.SDK_INT:I
     437: bipush        23
     439: if_icmpge     525
     442: aload         15
     444: getstatic     #195                // Field android/support/v7/a/a$j.TextAppearance_android_textColor:I
     447: invokevirtual #82                 // Method android/support/v7/widget/bp.g:(I)Z
     450: ifeq          463
     453: aload         15
     455: getstatic     #195                // Field android/support/v7/a/a$j.TextAppearance_android_textColor:I
     458: invokevirtual #198                // Method android/support/v7/widget/bp.e:(I)Landroid/content/res/ColorStateList;
     461: astore        9
     463: aload         15
     465: getstatic     #258                // Field android/support/v7/a/a$j.TextAppearance_android_textColorHint:I
     468: invokevirtual #82                 // Method android/support/v7/widget/bp.g:(I)Z
     471: ifeq          484
     474: aload         15
     476: getstatic     #258                // Field android/support/v7/a/a$j.TextAppearance_android_textColorHint:I
     479: invokevirtual #198                // Method android/support/v7/widget/bp.e:(I)Landroid/content/res/ColorStateList;
     482: astore        8
     484: aload         9
     486: astore        12
     488: aload         10
     490: astore        13
     492: aload         8
     494: astore        11
     496: aload         15
     498: getstatic     #261                // Field android/support/v7/a/a$j.TextAppearance_android_textColorLink:I
     501: invokevirtual #82                 // Method android/support/v7/widget/bp.g:(I)Z
     504: ifeq          525
     507: aload         15
     509: getstatic     #261                // Field android/support/v7/a/a$j.TextAppearance_android_textColorLink:I
     512: invokevirtual #198                // Method android/support/v7/widget/bp.e:(I)Landroid/content/res/ColorStateList;
     515: astore        13
     517: aload         8
     519: astore        11
     521: aload         9
     523: astore        12
     525: aload_0
     526: aload         14
     528: aload         15
     530: invokespecial #204                // Method a:(Landroid/content/Context;Landroid/support/v7/widget/bp;)V
     533: aload         15
     535: invokevirtual #206                // Method android/support/v7/widget/bp.a:()V
     538: aload         12
     540: ifnull        552
     543: aload_0
     544: getfield      #30                 // Field a:Landroid/widget/TextView;
     547: aload         12
     549: invokevirtual #202                // Method android/widget/TextView.setTextColor:(Landroid/content/res/ColorStateList;)V
     552: aload         11
     554: ifnull        566
     557: aload_0
     558: getfield      #30                 // Field a:Landroid/widget/TextView;
     561: aload         11
     563: invokevirtual #264                // Method android/widget/TextView.setHintTextColor:(Landroid/content/res/ColorStateList;)V
     566: aload         13
     568: ifnull        580
     571: aload_0
     572: getfield      #30                 // Field a:Landroid/widget/TextView;
     575: aload         13
     577: invokevirtual #267                // Method android/widget/TextView.setLinkTextColor:(Landroid/content/res/ColorStateList;)V
     580: iload         7
     582: ifne          596
     585: iload         4
     587: ifeq          596
     590: aload_0
     591: iload         6
     593: invokevirtual #192                // Method a:(Z)V
     596: aload_0
     597: getfield      #103                // Field h:Landroid/graphics/Typeface;
     600: ifnull        618
     603: aload_0
     604: getfield      #30                 // Field a:Landroid/widget/TextView;
     607: aload_0
     608: getfield      #103                // Field h:Landroid/graphics/Typeface;
     611: aload_0
     612: getfield      #28                 // Field g:I
     615: invokevirtual #141                // Method android/widget/TextView.setTypeface:(Landroid/graphics/Typeface;I)V
     618: aload_0
     619: getfield      #36                 // Field f:Landroid/support/v7/widget/ad;
     622: aload_1
     623: iload_2
     624: invokevirtual #269                // Method android/support/v7/widget/ad.a:(Landroid/util/AttributeSet;I)V
     627: getstatic     #168                // Field android/support/v4/widget/b.a:Z
     630: ifeq          710
     633: aload_0
     634: getfield      #36                 // Field f:Landroid/support/v7/widget/ad;
     637: invokevirtual #272                // Method android/support/v7/widget/ad.a:()I
     640: ifeq          710
     643: aload_0
     644: getfield      #36                 // Field f:Landroid/support/v7/widget/ad;
     647: invokevirtual #274                // Method android/support/v7/widget/ad.e:()[I
     650: astore_1
     651: aload_1
     652: arraylength
     653: ifle          710
     656: aload_0
     657: getfield      #30                 // Field a:Landroid/widget/TextView;
     660: invokevirtual #277                // Method android/widget/TextView.getAutoSizeStepGranularity:()I
     663: i2f
     664: ldc_w         #278                // float -1.0f
     667: fcmpl
     668: ifeq          701
     671: aload_0
     672: getfield      #30                 // Field a:Landroid/widget/TextView;
     675: aload_0
     676: getfield      #36                 // Field f:Landroid/support/v7/widget/ad;
     679: invokevirtual #280                // Method android/support/v7/widget/ad.c:()I
     682: aload_0
     683: getfield      #36                 // Field f:Landroid/support/v7/widget/ad;
     686: invokevirtual #282                // Method android/support/v7/widget/ad.d:()I
     689: aload_0
     690: getfield      #36                 // Field f:Landroid/support/v7/widget/ad;
     693: invokevirtual #284                // Method android/support/v7/widget/ad.b:()I
     696: iconst_0
     697: invokevirtual #287                // Method android/widget/TextView.setAutoSizeTextTypeUniformWithConfiguration:(IIII)V
     700: return
     701: aload_0
     702: getfield      #30                 // Field a:Landroid/widget/TextView;
     705: aload_1
     706: iconst_0
     707: invokevirtual #291                // Method android/widget/TextView.setAutoSizeTextTypeUniformWithPresetSizes:([II)V
     710: return

  void a(boolean);
    Code:
       0: aload_0
       1: getfield      #30                 // Field a:Landroid/widget/TextView;
       4: iload_1
       5: invokevirtual #295                // Method android/widget/TextView.setAllCaps:(Z)V
       8: return

  void a(boolean, int, int, int, int);
    Code:
       0: getstatic     #168                // Field android/support/v4/widget/b.a:Z
       3: ifne          10
       6: aload_0
       7: invokevirtual #298                // Method b:()V
      10: return

  void a(int[], int);
    Code:
       0: aload_0
       1: getfield      #36                 // Field f:Landroid/support/v7/widget/ad;
       4: aload_1
       5: iload_2
       6: invokevirtual #300                // Method android/support/v7/widget/ad.a:([II)V
       9: return

  void b();
    Code:
       0: aload_0
       1: getfield      #36                 // Field f:Landroid/support/v7/widget/ad;
       4: invokevirtual #302                // Method android/support/v7/widget/ad.f:()V
       7: return

  boolean c();
    Code:
       0: aload_0
       1: getfield      #36                 // Field f:Landroid/support/v7/widget/ad;
       4: invokevirtual #304                // Method android/support/v7/widget/ad.g:()Z
       7: ireturn

  int d();
    Code:
       0: aload_0
       1: getfield      #36                 // Field f:Landroid/support/v7/widget/ad;
       4: invokevirtual #272                // Method android/support/v7/widget/ad.a:()I
       7: ireturn

  int e();
    Code:
       0: aload_0
       1: getfield      #36                 // Field f:Landroid/support/v7/widget/ad;
       4: invokevirtual #284                // Method android/support/v7/widget/ad.b:()I
       7: ireturn

  int f();
    Code:
       0: aload_0
       1: getfield      #36                 // Field f:Landroid/support/v7/widget/ad;
       4: invokevirtual #280                // Method android/support/v7/widget/ad.c:()I
       7: ireturn

  int g();
    Code:
       0: aload_0
       1: getfield      #36                 // Field f:Landroid/support/v7/widget/ad;
       4: invokevirtual #282                // Method android/support/v7/widget/ad.d:()I
       7: ireturn

  int[] h();
    Code:
       0: aload_0
       1: getfield      #36                 // Field f:Landroid/support/v7/widget/ad;
       4: invokevirtual #274                // Method android/support/v7/widget/ad.e:()[I
       7: areturn
}
