public class android.support.v7.widget.ActionMenuView$c extends android.support.v7.widget.av$a {
  public boolean a;

  public int b;

  public int c;

  public boolean d;

  public boolean e;

  boolean f;

  public android.support.v7.widget.ActionMenuView$c(int, int);
    Code:
       0: aload_0
       1: iload_1
       2: iload_2
       3: invokespecial #19                 // Method android/support/v7/widget/av$a."<init>":(II)V
       6: aload_0
       7: iconst_0
       8: putfield      #21                 // Field a:Z
      11: return

  public android.support.v7.widget.ActionMenuView$c(android.content.Context, android.util.AttributeSet);
    Code:
       0: aload_0
       1: aload_1
       2: aload_2
       3: invokespecial #25                 // Method android/support/v7/widget/av$a."<init>":(Landroid/content/Context;Landroid/util/AttributeSet;)V
       6: return

  public android.support.v7.widget.ActionMenuView$c(android.support.v7.widget.ActionMenuView$c);
    Code:
       0: aload_0
       1: aload_1
       2: invokespecial #29                 // Method android/support/v7/widget/av$a."<init>":(Landroid/view/ViewGroup$LayoutParams;)V
       5: aload_0
       6: aload_1
       7: getfield      #21                 // Field a:Z
      10: putfield      #21                 // Field a:Z
      13: return

  public android.support.v7.widget.ActionMenuView$c(android.view.ViewGroup$LayoutParams);
    Code:
       0: aload_0
       1: aload_1
       2: invokespecial #29                 // Method android/support/v7/widget/av$a."<init>":(Landroid/view/ViewGroup$LayoutParams;)V
       5: return
}
