public class android.support.v7.widget.ActionBarOverlayLayout$b extends android.view.ViewGroup$MarginLayoutParams {
  public android.support.v7.widget.ActionBarOverlayLayout$b(int, int);
    Code:
       0: aload_0
       1: iload_1
       2: iload_2
       3: invokespecial #11                 // Method android/view/ViewGroup$MarginLayoutParams."<init>":(II)V
       6: return

  public android.support.v7.widget.ActionBarOverlayLayout$b(android.content.Context, android.util.AttributeSet);
    Code:
       0: aload_0
       1: aload_1
       2: aload_2
       3: invokespecial #15                 // Method android/view/ViewGroup$MarginLayoutParams."<init>":(Landroid/content/Context;Landroid/util/AttributeSet;)V
       6: return

  public android.support.v7.widget.ActionBarOverlayLayout$b(android.view.ViewGroup$LayoutParams);
    Code:
       0: aload_0
       1: aload_1
       2: invokespecial #18                 // Method android/view/ViewGroup$MarginLayoutParams."<init>":(Landroid/view/ViewGroup$LayoutParams;)V
       5: return
}
