class android.support.v7.widget.ActionBarContextView$1 implements android.view.View$OnClickListener {
  final android.support.v7.view.b a;

  final android.support.v7.widget.ActionBarContextView b;

  android.support.v7.widget.ActionBarContextView$1(android.support.v7.widget.ActionBarContextView, android.support.v7.view.b);
    Code:
       0: aload_0
       1: aload_1
       2: putfield      #18                 // Field b:Landroid/support/v7/widget/ActionBarContextView;
       5: aload_0
       6: aload_2
       7: putfield      #20                 // Field a:Landroid/support/v7/view/b;
      10: aload_0
      11: invokespecial #23                 // Method java/lang/Object."<init>":()V
      14: return

  public void onClick(android.view.View);
    Code:
       0: aload_0
       1: getfield      #20                 // Field a:Landroid/support/v7/view/b;
       4: invokevirtual #31                 // Method android/support/v7/view/b.c:()V
       7: return
}
