class android.support.v7.widget.ae$1 implements android.support.v7.widget.be$a {
  final android.support.v7.widget.ae a;

  android.support.v7.widget.ae$1(android.support.v7.widget.ae);
    Code:
       0: aload_0
       1: aload_1
       2: putfield      #16                 // Field a:Landroid/support/v7/widget/ae;
       5: aload_0
       6: invokespecial #18                 // Method java/lang/Object."<init>":()V
       9: return

  public void a(android.graphics.Canvas, android.graphics.RectF, float, android.graphics.Paint);
    Code:
       0: aload_1
       1: aload_2
       2: fload_3
       3: fload_3
       4: aload         4
       6: invokevirtual #26                 // Method android/graphics/Canvas.drawRoundRect:(Landroid/graphics/RectF;FFLandroid/graphics/Paint;)V
       9: return
}
