class android.support.v7.widget.ae extends android.support.v7.widget.ag {
  android.support.v7.widget.ae();
    Code:
       0: aload_0
       1: invokespecial #10                 // Method android/support/v7/widget/ag."<init>":()V
       4: return

  public void a();
    Code:
       0: new           #6                  // class android/support/v7/widget/ae$1
       3: dup
       4: aload_0
       5: invokespecial #15                 // Method android/support/v7/widget/ae$1."<init>":(Landroid/support/v7/widget/ae;)V
       8: putstatic     #20                 // Field android/support/v7/widget/be.a:Landroid/support/v7/widget/be$a;
      11: return
}
