class android.support.v7.widget.am$b {
  public android.support.v7.widget.RecyclerView$x a;

  public int b;

  public int c;

  public int d;

  public int e;

  android.support.v7.widget.am$b(android.support.v7.widget.RecyclerView$x, int, int, int, int);
    Code:
       0: aload_0
       1: invokespecial #18                 // Method java/lang/Object."<init>":()V
       4: aload_0
       5: aload_1
       6: putfield      #20                 // Field a:Landroid/support/v7/widget/RecyclerView$x;
       9: aload_0
      10: iload_2
      11: putfield      #22                 // Field b:I
      14: aload_0
      15: iload_3
      16: putfield      #24                 // Field c:I
      19: aload_0
      20: iload         4
      22: putfield      #26                 // Field d:I
      25: aload_0
      26: iload         5
      28: putfield      #28                 // Field e:I
      31: return
}
