class android.support.v7.widget.ap$b implements java.lang.Runnable {
  final android.support.v7.widget.ap a;

  android.support.v7.widget.ap$b(android.support.v7.widget.ap, android.support.v7.widget.ap$1);
    Code:
       0: aload_0
       1: aload_1
       2: invokespecial #22                 // Method "<init>":(Landroid/support/v7/widget/ap;)V
       5: return

  public void a();
    Code:
       0: aload_0
       1: getfield      #15                 // Field a:Landroid/support/v7/widget/ap;
       4: aconst_null
       5: invokestatic  #25                 // Method android/support/v7/widget/ap.a:(Landroid/support/v7/widget/ap;Landroid/support/v7/widget/ap$b;)Landroid/support/v7/widget/ap$b;
       8: pop
       9: aload_0
      10: getfield      #15                 // Field a:Landroid/support/v7/widget/ap;
      13: aload_0
      14: invokevirtual #29                 // Method android/support/v7/widget/ap.removeCallbacks:(Ljava/lang/Runnable;)Z
      17: pop
      18: return

  public void b();
    Code:
       0: aload_0
       1: getfield      #15                 // Field a:Landroid/support/v7/widget/ap;
       4: aload_0
       5: invokevirtual #32                 // Method android/support/v7/widget/ap.post:(Ljava/lang/Runnable;)Z
       8: pop
       9: return

  public void run();
    Code:
       0: aload_0
       1: getfield      #15                 // Field a:Landroid/support/v7/widget/ap;
       4: aconst_null
       5: invokestatic  #25                 // Method android/support/v7/widget/ap.a:(Landroid/support/v7/widget/ap;Landroid/support/v7/widget/ap$b;)Landroid/support/v7/widget/ap$b;
       8: pop
       9: aload_0
      10: getfield      #15                 // Field a:Landroid/support/v7/widget/ap;
      13: invokevirtual #36                 // Method android/support/v7/widget/ap.drawableStateChanged:()V
      16: return
}
