class android.support.v7.widget.ap extends android.widget.ListView {
  android.support.v7.widget.ap(android.content.Context, boolean);
    Code:
       0: aload_0
       1: aload_1
       2: aconst_null
       3: getstatic     #41                 // Field android/support/v7/a/a$a.dropDownListViewStyle:I
       6: invokespecial #44                 // Method android/widget/ListView."<init>":(Landroid/content/Context;Landroid/util/AttributeSet;I)V
       9: aload_0
      10: new           #46                 // class android/graphics/Rect
      13: dup
      14: invokespecial #49                 // Method android/graphics/Rect."<init>":()V
      17: putfield      #51                 // Field a:Landroid/graphics/Rect;
      20: aload_0
      21: iconst_0
      22: putfield      #53                 // Field b:I
      25: aload_0
      26: iconst_0
      27: putfield      #55                 // Field c:I
      30: aload_0
      31: iconst_0
      32: putfield      #57                 // Field d:I
      35: aload_0
      36: iconst_0
      37: putfield      #59                 // Field e:I
      40: aload_0
      41: iload_2
      42: putfield      #61                 // Field j:Z
      45: aload_0
      46: iconst_0
      47: invokevirtual #65                 // Method setCacheColorHint:(I)V
      50: aload_0
      51: ldc           #67                 // class android/widget/AbsListView
      53: ldc           #69                 // String mIsChildViewEnabled
      55: invokevirtual #75                 // Method java/lang/Class.getDeclaredField:(Ljava/lang/String;)Ljava/lang/reflect/Field;
      58: putfield      #77                 // Field g:Ljava/lang/reflect/Field;
      61: aload_0
      62: getfield      #77                 // Field g:Ljava/lang/reflect/Field;
      65: iconst_1
      66: invokevirtual #83                 // Method java/lang/reflect/Field.setAccessible:(Z)V
      69: return
      70: astore_1
      71: aload_1
      72: invokestatic  #88                 // Method com/google/a/a/a/a/a/a.a:(Ljava/lang/Throwable;)V
      75: return
    Exception table:
       from    to  target type
          50    69    70   Class java/lang/NoSuchFieldException

  static android.support.v7.widget.ap$b a(android.support.v7.widget.ap, android.support.v7.widget.ap$b);
    Code:
       0: aload_0
       1: aload_1
       2: putfield      #92                 // Field n:Landroid/support/v7/widget/ap$b;
       5: aload_1
       6: areturn

  public int a(int, int, int, int, int);
    Code:
       0: aload_0
       1: invokevirtual #261                // Method getListPaddingTop:()I
       4: istore_2
       5: aload_0
       6: invokevirtual #264                // Method getListPaddingBottom:()I
       9: istore_3
      10: aload_0
      11: invokevirtual #267                // Method getListPaddingLeft:()I
      14: pop
      15: aload_0
      16: invokevirtual #270                // Method getListPaddingRight:()I
      19: pop
      20: aload_0
      21: invokevirtual #273                // Method getDividerHeight:()I
      24: istore        6
      26: aload_0
      27: invokevirtual #276                // Method getDivider:()Landroid/graphics/drawable/Drawable;
      30: astore        12
      32: aload_0
      33: invokevirtual #280                // Method getAdapter:()Landroid/widget/ListAdapter;
      36: astore        15
      38: aload         15
      40: ifnonnull     47
      43: iload_2
      44: iload_3
      45: iadd
      46: ireturn
      47: iload         6
      49: ifle          60
      52: aload         12
      54: ifnull        60
      57: goto          63
      60: iconst_0
      61: istore        6
      63: aload         15
      65: invokeinterface #285,  1          // InterfaceMethod android/widget/ListAdapter.getCount:()I
      70: istore        11
      72: iload_2
      73: iload_3
      74: iadd
      75: istore_3
      76: aconst_null
      77: astore        12
      79: iconst_0
      80: istore        7
      82: iconst_0
      83: istore        9
      85: iconst_0
      86: istore_2
      87: iload         7
      89: iload         11
      91: if_icmpge     318
      94: aload         15
      96: iload         7
      98: invokeinterface #289,  2          // InterfaceMethod android/widget/ListAdapter.getItemViewType:(I)I
     103: istore        10
     105: iload         9
     107: istore        8
     109: iload         10
     111: iload         9
     113: if_icmpeq     123
     116: aconst_null
     117: astore        12
     119: iload         10
     121: istore        8
     123: aload         15
     125: iload         7
     127: aload         12
     129: aload_0
     130: invokeinterface #293,  4          // InterfaceMethod android/widget/ListAdapter.getView:(ILandroid/view/View;Landroid/view/ViewGroup;)Landroid/view/View;
     135: astore        13
     137: aload         13
     139: invokevirtual #297                // Method android/view/View.getLayoutParams:()Landroid/view/ViewGroup$LayoutParams;
     142: astore        14
     144: aload         14
     146: astore        12
     148: aload         14
     150: ifnonnull     166
     153: aload_0
     154: invokevirtual #300                // Method generateDefaultLayoutParams:()Landroid/view/ViewGroup$LayoutParams;
     157: astore        12
     159: aload         13
     161: aload         12
     163: invokevirtual #304                // Method android/view/View.setLayoutParams:(Landroid/view/ViewGroup$LayoutParams;)V
     166: aload         12
     168: getfield      #309                // Field android/view/ViewGroup$LayoutParams.height:I
     171: ifle          190
     174: aload         12
     176: getfield      #309                // Field android/view/ViewGroup$LayoutParams.height:I
     179: ldc_w         #310                // int 1073741824
     182: invokestatic  #316                // Method android/view/View$MeasureSpec.makeMeasureSpec:(II)I
     185: istore        9
     187: goto          197
     190: iconst_0
     191: iconst_0
     192: invokestatic  #316                // Method android/view/View$MeasureSpec.makeMeasureSpec:(II)I
     195: istore        9
     197: aload         13
     199: iload_1
     200: iload         9
     202: invokevirtual #320                // Method android/view/View.measure:(II)V
     205: aload         13
     207: invokevirtual #323                // Method android/view/View.forceLayout:()V
     210: iload_3
     211: istore        9
     213: iload         7
     215: ifle          224
     218: iload_3
     219: iload         6
     221: iadd
     222: istore        9
     224: iload         9
     226: aload         13
     228: invokevirtual #326                // Method android/view/View.getMeasuredHeight:()I
     231: iadd
     232: istore_3
     233: iload_3
     234: iload         4
     236: if_icmplt     277
     239: iload         4
     241: istore_1
     242: iload         5
     244: iflt          275
     247: iload         4
     249: istore_1
     250: iload         7
     252: iload         5
     254: if_icmple     275
     257: iload         4
     259: istore_1
     260: iload_2
     261: ifle          275
     264: iload         4
     266: istore_1
     267: iload_3
     268: iload         4
     270: if_icmpeq     275
     273: iload_2
     274: istore_1
     275: iload_1
     276: ireturn
     277: iload_2
     278: istore        10
     280: iload         5
     282: iflt          298
     285: iload_2
     286: istore        10
     288: iload         7
     290: iload         5
     292: if_icmplt     298
     295: iload_3
     296: istore        10
     298: iload         7
     300: iconst_1
     301: iadd
     302: istore        7
     304: iload         8
     306: istore        9
     308: aload         13
     310: astore        12
     312: iload         10
     314: istore_2
     315: goto          87
     318: iload_3
     319: ireturn

  public boolean a(android.view.MotionEvent, int);
    Code:
       0: aload_1
       1: invokevirtual #332                // Method android/view/MotionEvent.getActionMasked:()I
       4: istore_3
       5: iload_3
       6: tableswitch   { // 1 to 3
                     1: 54
                     2: 48
                     3: 40
               default: 32
          }
      32: iconst_0
      33: istore_2
      34: iconst_1
      35: istore        6
      37: goto          151
      40: iconst_0
      41: istore_2
      42: iconst_0
      43: istore        6
      45: goto          151
      48: iconst_1
      49: istore        6
      51: goto          57
      54: iconst_0
      55: istore        6
      57: aload_1
      58: iload_2
      59: invokevirtual #335                // Method android/view/MotionEvent.findPointerIndex:(I)I
      62: istore        4
      64: iload         4
      66: ifge          72
      69: goto          40
      72: aload_1
      73: iload         4
      75: invokevirtual #339                // Method android/view/MotionEvent.getX:(I)F
      78: f2i
      79: istore_2
      80: aload_1
      81: iload         4
      83: invokevirtual #342                // Method android/view/MotionEvent.getY:(I)F
      86: f2i
      87: istore        4
      89: aload_0
      90: iload_2
      91: iload         4
      93: invokevirtual #345                // Method pointToPosition:(II)I
      96: istore        5
      98: iload         5
     100: iconst_m1
     101: if_icmpne     109
     104: iconst_1
     105: istore_2
     106: goto          151
     109: aload_0
     110: iload         5
     112: aload_0
     113: invokevirtual #181                // Method getFirstVisiblePosition:()I
     116: isub
     117: invokevirtual #185                // Method getChildAt:(I)Landroid/view/View;
     120: astore        7
     122: aload_0
     123: aload         7
     125: iload         5
     127: iload_2
     128: i2f
     129: iload         4
     131: i2f
     132: invokespecial #347                // Method a:(Landroid/view/View;IFF)V
     135: iload_3
     136: iconst_1
     137: if_icmpne     32
     140: aload_0
     141: aload         7
     143: iload         5
     145: invokespecial #349                // Method a:(Landroid/view/View;I)V
     148: goto          32
     151: iload         6
     153: ifeq          160
     156: iload_2
     157: ifeq          164
     160: aload_0
     161: invokespecial #350                // Method b:()V
     164: iload         6
     166: ifeq          210
     169: aload_0
     170: getfield      #352                // Field m:Landroid/support/v4/widget/i;
     173: ifnonnull     188
     176: aload_0
     177: new           #354                // class android/support/v4/widget/i
     180: dup
     181: aload_0
     182: invokespecial #357                // Method android/support/v4/widget/i."<init>":(Landroid/widget/ListView;)V
     185: putfield      #352                // Field m:Landroid/support/v4/widget/i;
     188: aload_0
     189: getfield      #352                // Field m:Landroid/support/v4/widget/i;
     192: iconst_1
     193: invokevirtual #360                // Method android/support/v4/widget/i.a:(Z)Landroid/support/v4/widget/a;
     196: pop
     197: aload_0
     198: getfield      #352                // Field m:Landroid/support/v4/widget/i;
     201: aload_0
     202: aload_1
     203: invokevirtual #364                // Method android/support/v4/widget/i.onTouch:(Landroid/view/View;Landroid/view/MotionEvent;)Z
     206: pop
     207: iload         6
     209: ireturn
     210: aload_0
     211: getfield      #352                // Field m:Landroid/support/v4/widget/i;
     214: ifnull        226
     217: aload_0
     218: getfield      #352                // Field m:Landroid/support/v4/widget/i;
     221: iconst_0
     222: invokevirtual #360                // Method android/support/v4/widget/i.a:(Z)Landroid/support/v4/widget/a;
     225: pop
     226: iload         6
     228: ireturn

  protected void dispatchDraw(android.graphics.Canvas);
    Code:
       0: aload_0
       1: aload_1
       2: invokespecial #367                // Method a:(Landroid/graphics/Canvas;)V
       5: aload_0
       6: aload_1
       7: invokespecial #369                // Method android/widget/ListView.dispatchDraw:(Landroid/graphics/Canvas;)V
      10: return

  protected void drawableStateChanged();
    Code:
       0: aload_0
       1: getfield      #92                 // Field n:Landroid/support/v7/widget/ap$b;
       4: ifnull        8
       7: return
       8: aload_0
       9: invokespecial #370                // Method android/widget/ListView.drawableStateChanged:()V
      12: aload_0
      13: iconst_1
      14: invokespecial #201                // Method setSelectorEnabled:(Z)V
      17: aload_0
      18: invokespecial #372                // Method a:()V
      21: return

  public boolean hasFocus();
    Code:
       0: aload_0
       1: getfield      #61                 // Field j:Z
       4: ifne          19
       7: aload_0
       8: invokespecial #375                // Method android/widget/ListView.hasFocus:()Z
      11: ifeq          17
      14: goto          19
      17: iconst_0
      18: ireturn
      19: iconst_1
      20: ireturn

  public boolean hasWindowFocus();
    Code:
       0: aload_0
       1: getfield      #61                 // Field j:Z
       4: ifne          19
       7: aload_0
       8: invokespecial #378                // Method android/widget/ListView.hasWindowFocus:()Z
      11: ifeq          17
      14: goto          19
      17: iconst_0
      18: ireturn
      19: iconst_1
      20: ireturn

  public boolean isFocused();
    Code:
       0: aload_0
       1: getfield      #61                 // Field j:Z
       4: ifne          19
       7: aload_0
       8: invokespecial #381                // Method android/widget/ListView.isFocused:()Z
      11: ifeq          17
      14: goto          19
      17: iconst_0
      18: ireturn
      19: iconst_1
      20: ireturn

  public boolean isInTouchMode();
    Code:
       0: aload_0
       1: getfield      #61                 // Field j:Z
       4: ifeq          14
       7: aload_0
       8: getfield      #384                // Field i:Z
      11: ifne          21
      14: aload_0
      15: invokespecial #386                // Method android/widget/ListView.isInTouchMode:()Z
      18: ifeq          23
      21: iconst_1
      22: ireturn
      23: iconst_0
      24: ireturn

  protected void onDetachedFromWindow();
    Code:
       0: aload_0
       1: aconst_null
       2: putfield      #92                 // Field n:Landroid/support/v7/widget/ap$b;
       5: aload_0
       6: invokespecial #389                // Method android/widget/ListView.onDetachedFromWindow:()V
       9: return

  public boolean onHoverEvent(android.view.MotionEvent);
    Code:
       0: getstatic     #166                // Field android/os/Build$VERSION.SDK_INT:I
       3: bipush        26
       5: if_icmpge     14
       8: aload_0
       9: aload_1
      10: invokespecial #393                // Method android/widget/ListView.onHoverEvent:(Landroid/view/MotionEvent;)Z
      13: ireturn
      14: aload_1
      15: invokevirtual #332                // Method android/view/MotionEvent.getActionMasked:()I
      18: istore_2
      19: iload_2
      20: bipush        10
      22: if_icmpne     52
      25: aload_0
      26: getfield      #92                 // Field n:Landroid/support/v7/widget/ap$b;
      29: ifnonnull     52
      32: aload_0
      33: new           #11                 // class android/support/v7/widget/ap$b
      36: dup
      37: aload_0
      38: aconst_null
      39: invokespecial #396                // Method android/support/v7/widget/ap$b."<init>":(Landroid/support/v7/widget/ap;Landroid/support/v7/widget/ap$1;)V
      42: putfield      #92                 // Field n:Landroid/support/v7/widget/ap$b;
      45: aload_0
      46: getfield      #92                 // Field n:Landroid/support/v7/widget/ap$b;
      49: invokevirtual #397                // Method android/support/v7/widget/ap$b.b:()V
      52: aload_0
      53: aload_1
      54: invokespecial #393                // Method android/widget/ListView.onHoverEvent:(Landroid/view/MotionEvent;)Z
      57: istore_3
      58: iload_2
      59: bipush        9
      61: if_icmpeq     80
      64: iload_2
      65: bipush        7
      67: if_icmpne     73
      70: goto          80
      73: aload_0
      74: iconst_m1
      75: invokevirtual #400                // Method setSelection:(I)V
      78: iload_3
      79: ireturn
      80: aload_0
      81: aload_1
      82: invokevirtual #402                // Method android/view/MotionEvent.getX:()F
      85: f2i
      86: aload_1
      87: invokevirtual #404                // Method android/view/MotionEvent.getY:()F
      90: f2i
      91: invokevirtual #345                // Method pointToPosition:(II)I
      94: istore_2
      95: iload_2
      96: iconst_m1
      97: if_icmpeq     144
     100: iload_2
     101: aload_0
     102: invokevirtual #407                // Method getSelectedItemPosition:()I
     105: if_icmpeq     144
     108: aload_0
     109: iload_2
     110: aload_0
     111: invokevirtual #181                // Method getFirstVisiblePosition:()I
     114: isub
     115: invokevirtual #185                // Method getChildAt:(I)Landroid/view/View;
     118: astore_1
     119: aload_1
     120: invokevirtual #244                // Method android/view/View.isEnabled:()Z
     123: ifeq          140
     126: aload_0
     127: iload_2
     128: aload_1
     129: invokevirtual #195                // Method android/view/View.getTop:()I
     132: aload_0
     133: invokevirtual #408                // Method getTop:()I
     136: isub
     137: invokevirtual #411                // Method setSelectionFromTop:(II)V
     140: aload_0
     141: invokespecial #372                // Method a:()V
     144: iload_3
     145: ireturn

  public boolean onTouchEvent(android.view.MotionEvent);
    Code:
       0: aload_1
       1: invokevirtual #415                // Method android/view/MotionEvent.getAction:()I
       4: ifeq          10
       7: goto          28
      10: aload_0
      11: aload_0
      12: aload_1
      13: invokevirtual #402                // Method android/view/MotionEvent.getX:()F
      16: f2i
      17: aload_1
      18: invokevirtual #404                // Method android/view/MotionEvent.getY:()F
      21: f2i
      22: invokevirtual #345                // Method pointToPosition:(II)I
      25: putfield      #178                // Field f:I
      28: aload_0
      29: getfield      #92                 // Field n:Landroid/support/v7/widget/ap$b;
      32: ifnull        42
      35: aload_0
      36: getfield      #92                 // Field n:Landroid/support/v7/widget/ap$b;
      39: invokevirtual #416                // Method android/support/v7/widget/ap$b.a:()V
      42: aload_0
      43: aload_1
      44: invokespecial #418                // Method android/widget/ListView.onTouchEvent:(Landroid/view/MotionEvent;)Z
      47: ireturn

  void setListSelectionHidden(boolean);
    Code:
       0: aload_0
       1: iload_1
       2: putfield      #384                // Field i:Z
       5: return

  public void setSelector(android.graphics.drawable.Drawable);
    Code:
       0: aload_1
       1: ifnull        16
       4: new           #8                  // class android/support/v7/widget/ap$a
       7: dup
       8: aload_1
       9: invokespecial #423                // Method android/support/v7/widget/ap$a."<init>":(Landroid/graphics/drawable/Drawable;)V
      12: astore_2
      13: goto          18
      16: aconst_null
      17: astore_2
      18: aload_0
      19: aload_2
      20: putfield      #255                // Field h:Landroid/support/v7/widget/ap$a;
      23: aload_0
      24: aload_0
      25: getfield      #255                // Field h:Landroid/support/v7/widget/ap$a;
      28: invokespecial #425                // Method android/widget/ListView.setSelector:(Landroid/graphics/drawable/Drawable;)V
      31: new           #46                 // class android/graphics/Rect
      34: dup
      35: invokespecial #49                 // Method android/graphics/Rect."<init>":()V
      38: astore_2
      39: aload_1
      40: ifnull        49
      43: aload_1
      44: aload_2
      45: invokevirtual #429                // Method android/graphics/drawable/Drawable.getPadding:(Landroid/graphics/Rect;)Z
      48: pop
      49: aload_0
      50: aload_2
      51: getfield      #228                // Field android/graphics/Rect.left:I
      54: putfield      #53                 // Field b:I
      57: aload_0
      58: aload_2
      59: getfield      #231                // Field android/graphics/Rect.top:I
      62: putfield      #55                 // Field c:I
      65: aload_0
      66: aload_2
      67: getfield      #234                // Field android/graphics/Rect.right:I
      70: putfield      #57                 // Field d:I
      73: aload_0
      74: aload_2
      75: getfield      #237                // Field android/graphics/Rect.bottom:I
      78: putfield      #59                 // Field e:I
      81: return
}
