class android.support.v7.widget.as$b implements java.lang.Runnable {
  final android.support.v7.widget.as a;

  android.support.v7.widget.as$b(android.support.v7.widget.as);
    Code:
       0: aload_0
       1: aload_1
       2: putfield      #15                 // Field a:Landroid/support/v7/widget/as;
       5: aload_0
       6: invokespecial #18                 // Method java/lang/Object."<init>":()V
       9: return

  public void run();
    Code:
       0: aload_0
       1: getfield      #15                 // Field a:Landroid/support/v7/widget/as;
       4: invokevirtual #23                 // Method android/support/v7/widget/as.d:()V
       7: return
}
