class android.support.v7.widget.at$b {
  public boolean a;

  public int b;

  public int c;

  public android.support.v7.widget.RecyclerView d;

  public int e;

  android.support.v7.widget.at$b();
    Code:
       0: aload_0
       1: invokespecial #18                 // Method java/lang/Object."<init>":()V
       4: return

  public void a();
    Code:
       0: aload_0
       1: iconst_0
       2: putfield      #21                 // Field a:Z
       5: aload_0
       6: iconst_0
       7: putfield      #23                 // Field b:I
      10: aload_0
      11: iconst_0
      12: putfield      #25                 // Field c:I
      15: aload_0
      16: aconst_null
      17: putfield      #27                 // Field d:Landroid/support/v7/widget/RecyclerView;
      20: aload_0
      21: iconst_0
      22: putfield      #29                 // Field e:I
      25: return
}
