public class android.support.v7.widget.av extends android.view.ViewGroup {
  public android.support.v7.widget.av(android.content.Context);
    Code:
       0: aload_0
       1: aload_1
       2: aconst_null
       3: invokespecial #31                 // Method "<init>":(Landroid/content/Context;Landroid/util/AttributeSet;)V
       6: return

  public android.support.v7.widget.av(android.content.Context, android.util.AttributeSet);
    Code:
       0: aload_0
       1: aload_1
       2: aload_2
       3: iconst_0
       4: invokespecial #35                 // Method "<init>":(Landroid/content/Context;Landroid/util/AttributeSet;I)V
       7: return

  public android.support.v7.widget.av(android.content.Context, android.util.AttributeSet, int);
    Code:
       0: aload_0
       1: aload_1
       2: aload_2
       3: iload_3
       4: invokespecial #36                 // Method android/view/ViewGroup."<init>":(Landroid/content/Context;Landroid/util/AttributeSet;I)V
       7: aload_0
       8: iconst_1
       9: putfield      #38                 // Field a:Z
      12: aload_0
      13: iconst_m1
      14: putfield      #40                 // Field b:I
      17: aload_0
      18: iconst_0
      19: putfield      #42                 // Field c:I
      22: aload_0
      23: ldc           #43                 // int 8388659
      25: putfield      #45                 // Field e:I
      28: aload_1
      29: aload_2
      30: getstatic     #50                 // Field android/support/v7/a/a$j.LinearLayoutCompat:[I
      33: iload_3
      34: iconst_0
      35: invokestatic  #55                 // Method android/support/v7/widget/bp.a:(Landroid/content/Context;Landroid/util/AttributeSet;[III)Landroid/support/v7/widget/bp;
      38: astore_1
      39: aload_1
      40: getstatic     #58                 // Field android/support/v7/a/a$j.LinearLayoutCompat_android_orientation:I
      43: iconst_m1
      44: invokevirtual #61                 // Method android/support/v7/widget/bp.a:(II)I
      47: istore_3
      48: iload_3
      49: iflt          57
      52: aload_0
      53: iload_3
      54: invokevirtual #65                 // Method setOrientation:(I)V
      57: aload_1
      58: getstatic     #68                 // Field android/support/v7/a/a$j.LinearLayoutCompat_android_gravity:I
      61: iconst_m1
      62: invokevirtual #61                 // Method android/support/v7/widget/bp.a:(II)I
      65: istore_3
      66: iload_3
      67: iflt          75
      70: aload_0
      71: iload_3
      72: invokevirtual #71                 // Method setGravity:(I)V
      75: aload_1
      76: getstatic     #74                 // Field android/support/v7/a/a$j.LinearLayoutCompat_android_baselineAligned:I
      79: iconst_1
      80: invokevirtual #77                 // Method android/support/v7/widget/bp.a:(IZ)Z
      83: istore        4
      85: iload         4
      87: ifne          96
      90: aload_0
      91: iload         4
      93: invokevirtual #81                 // Method setBaselineAligned:(Z)V
      96: aload_0
      97: aload_1
      98: getstatic     #84                 // Field android/support/v7/a/a$j.LinearLayoutCompat_android_weightSum:I
     101: ldc           #85                 // float -1.0f
     103: invokevirtual #88                 // Method android/support/v7/widget/bp.a:(IF)F
     106: putfield      #90                 // Field g:F
     109: aload_0
     110: aload_1
     111: getstatic     #93                 // Field android/support/v7/a/a$j.LinearLayoutCompat_android_baselineAlignedChildIndex:I
     114: iconst_m1
     115: invokevirtual #61                 // Method android/support/v7/widget/bp.a:(II)I
     118: putfield      #40                 // Field b:I
     121: aload_0
     122: aload_1
     123: getstatic     #96                 // Field android/support/v7/a/a$j.LinearLayoutCompat_measureWithLargestChild:I
     126: iconst_0
     127: invokevirtual #77                 // Method android/support/v7/widget/bp.a:(IZ)Z
     130: putfield      #98                 // Field h:Z
     133: aload_0
     134: aload_1
     135: getstatic     #101                // Field android/support/v7/a/a$j.LinearLayoutCompat_divider:I
     138: invokevirtual #104                // Method android/support/v7/widget/bp.a:(I)Landroid/graphics/drawable/Drawable;
     141: invokevirtual #108                // Method setDividerDrawable:(Landroid/graphics/drawable/Drawable;)V
     144: aload_0
     145: aload_1
     146: getstatic     #111                // Field android/support/v7/a/a$j.LinearLayoutCompat_showDividers:I
     149: iconst_0
     150: invokevirtual #61                 // Method android/support/v7/widget/bp.a:(II)I
     153: putfield      #113                // Field n:I
     156: aload_0
     157: aload_1
     158: getstatic     #116                // Field android/support/v7/a/a$j.LinearLayoutCompat_dividerPadding:I
     161: iconst_0
     162: invokevirtual #118                // Method android/support/v7/widget/bp.e:(II)I
     165: putfield      #120                // Field o:I
     168: aload_1
     169: invokevirtual #123                // Method android/support/v7/widget/bp.a:()V
     172: return

  int a(android.view.View);
    Code:
       0: iconst_0
       1: ireturn

  int a(android.view.View, int);
    Code:
       0: iconst_0
       1: ireturn

  void a(int, int);
    Code:
       0: aload_0
       1: iconst_0
       2: putfield      #169                // Field f:I
       5: aload_0
       6: invokevirtual #172                // Method getVirtualChildCount:()I
       9: istore        13
      11: iload_1
      12: invokestatic  #176                // Method android/view/View$MeasureSpec.getMode:(I)I
      15: istore        20
      17: iload_2
      18: invokestatic  #176                // Method android/view/View$MeasureSpec.getMode:(I)I
      21: istore        6
      23: aload_0
      24: getfield      #40                 // Field b:I
      27: istore        21
      29: aload_0
      30: getfield      #98                 // Field h:Z
      33: istore        22
      35: fconst_0
      36: fstore_3
      37: iconst_0
      38: istore        10
      40: iconst_0
      41: istore        15
      43: iconst_0
      44: istore        9
      46: iconst_0
      47: istore        5
      49: iconst_0
      50: istore        8
      52: iconst_0
      53: istore        11
      55: iconst_0
      56: istore        14
      58: iconst_1
      59: istore        7
      61: iconst_0
      62: istore        12
      64: iload         11
      66: iload         13
      68: if_icmpge     640
      71: aload_0
      72: iload         11
      74: invokevirtual #144                // Method b:(I)Landroid/view/View;
      77: astore        23
      79: aload         23
      81: ifnonnull     102
      84: aload_0
      85: aload_0
      86: getfield      #169                // Field f:I
      89: aload_0
      90: iload         11
      92: invokevirtual #178                // Method d:(I)I
      95: iadd
      96: putfield      #169                // Field f:I
      99: goto          631
     102: aload         23
     104: invokevirtual #147                // Method android/view/View.getVisibility:()I
     107: bipush        8
     109: if_icmpne     128
     112: iload         11
     114: aload_0
     115: aload         23
     117: iload         11
     119: invokevirtual #180                // Method a:(Landroid/view/View;I)I
     122: iadd
     123: istore        11
     125: goto          631
     128: aload_0
     129: iload         11
     131: invokevirtual #183                // Method c:(I)Z
     134: ifeq          150
     137: aload_0
     138: aload_0
     139: getfield      #169                // Field f:I
     142: aload_0
     143: getfield      #185                // Field m:I
     146: iadd
     147: putfield      #169                // Field f:I
     150: aload         23
     152: invokevirtual #151                // Method android/view/View.getLayoutParams:()Landroid/view/ViewGroup$LayoutParams;
     155: checkcast     #6                  // class android/support/v7/widget/av$a
     158: astore        25
     160: fload_3
     161: aload         25
     163: getfield      #186                // Field android/support/v7/widget/av$a.g:F
     166: fadd
     167: fstore_3
     168: iload         6
     170: ldc           #136                // int 1073741824
     172: if_icmpne     228
     175: aload         25
     177: getfield      #157                // Field android/support/v7/widget/av$a.height:I
     180: ifne          228
     183: aload         25
     185: getfield      #186                // Field android/support/v7/widget/av$a.g:F
     188: fconst_0
     189: fcmpl
     190: ifle          228
     193: aload_0
     194: getfield      #169                // Field f:I
     197: istore        14
     199: aload_0
     200: iload         14
     202: aload         25
     204: getfield      #189                // Field android/support/v7/widget/av$a.topMargin:I
     207: iload         14
     209: iadd
     210: aload         25
     212: getfield      #192                // Field android/support/v7/widget/av$a.bottomMargin:I
     215: iadd
     216: invokestatic  #197                // Method java/lang/Math.max:(II)I
     219: putfield      #169                // Field f:I
     222: iconst_1
     223: istore        14
     225: goto          375
     228: aload         25
     230: getfield      #157                // Field android/support/v7/widget/av$a.height:I
     233: ifne          259
     236: aload         25
     238: getfield      #186                // Field android/support/v7/widget/av$a.g:F
     241: fconst_0
     242: fcmpl
     243: ifle          259
     246: aload         25
     248: bipush        -2
     250: putfield      #157                // Field android/support/v7/widget/av$a.height:I
     253: iconst_0
     254: istore        16
     256: goto          263
     259: ldc           #198                // int -2147483648
     261: istore        16
     263: fload_3
     264: fconst_0
     265: fcmpl
     266: ifne          278
     269: aload_0
     270: getfield      #169                // Field f:I
     273: istore        17
     275: goto          281
     278: iconst_0
     279: istore        17
     281: aload         23
     283: astore        24
     285: aload_0
     286: aload         23
     288: iload         11
     290: iload_1
     291: iconst_0
     292: iload_2
     293: iload         17
     295: invokevirtual #201                // Method a:(Landroid/view/View;IIIII)V
     298: iload         16
     300: ldc           #198                // int -2147483648
     302: if_icmpeq     312
     305: aload         25
     307: iload         16
     309: putfield      #157                // Field android/support/v7/widget/av$a.height:I
     312: aload         24
     314: invokevirtual #160                // Method android/view/View.getMeasuredHeight:()I
     317: istore        16
     319: aload_0
     320: getfield      #169                // Field f:I
     323: istore        17
     325: aload_0
     326: iload         17
     328: iload         17
     330: iload         16
     332: iadd
     333: aload         25
     335: getfield      #189                // Field android/support/v7/widget/av$a.topMargin:I
     338: iadd
     339: aload         25
     341: getfield      #192                // Field android/support/v7/widget/av$a.bottomMargin:I
     344: iadd
     345: aload_0
     346: aload         24
     348: invokevirtual #203                // Method b:(Landroid/view/View;)I
     351: iadd
     352: invokestatic  #197                // Method java/lang/Math.max:(II)I
     355: putfield      #169                // Field f:I
     358: iload         22
     360: ifeq          375
     363: iload         16
     365: iload         9
     367: invokestatic  #197                // Method java/lang/Math.max:(II)I
     370: istore        9
     372: goto          375
     375: iload         5
     377: istore        16
     379: iload         11
     381: istore        19
     383: iload         21
     385: iflt          405
     388: iload         21
     390: iload         19
     392: iconst_1
     393: iadd
     394: if_icmpne     405
     397: aload_0
     398: aload_0
     399: getfield      #169                // Field f:I
     402: putfield      #42                 // Field c:I
     405: iload         19
     407: iload         21
     409: if_icmpge     432
     412: aload         25
     414: getfield      #186                // Field android/support/v7/widget/av$a.g:F
     417: fconst_0
     418: fcmpl
     419: ifle          432
     422: new           #205                // class java/lang/RuntimeException
     425: dup
     426: ldc           #207                // String A child of LinearLayout with index less than mBaselineAlignedChildIndex has weight > 0, which won't work.  Either remove the weight, or don't set mBaselineAlignedChildIndex.
     428: invokespecial #210                // Method java/lang/RuntimeException."<init>":(Ljava/lang/String;)V
     431: athrow
     432: iload         20
     434: ldc           #136                // int 1073741824
     436: if_icmpeq     457
     439: aload         25
     441: getfield      #154                // Field android/support/v7/widget/av$a.width:I
     444: iconst_m1
     445: if_icmpne     457
     448: iconst_1
     449: istore        11
     451: iconst_1
     452: istore        12
     454: goto          460
     457: iconst_0
     458: istore        11
     460: aload         25
     462: getfield      #213                // Field android/support/v7/widget/av$a.leftMargin:I
     465: aload         25
     467: getfield      #216                // Field android/support/v7/widget/av$a.rightMargin:I
     470: iadd
     471: istore        17
     473: aload         23
     475: invokevirtual #165                // Method android/view/View.getMeasuredWidth:()I
     478: iload         17
     480: iadd
     481: istore        18
     483: iload         15
     485: iload         18
     487: invokestatic  #197                // Method java/lang/Math.max:(II)I
     490: istore        15
     492: iload         10
     494: aload         23
     496: invokevirtual #219                // Method android/view/View.getMeasuredState:()I
     499: invokestatic  #222                // Method android/view/View.combineMeasuredStates:(II)I
     502: istore        10
     504: iload         7
     506: ifeq          524
     509: aload         25
     511: getfield      #154                // Field android/support/v7/widget/av$a.width:I
     514: iconst_m1
     515: if_icmpne     524
     518: iconst_1
     519: istore        5
     521: goto          527
     524: iconst_0
     525: istore        5
     527: aload         25
     529: getfield      #186                // Field android/support/v7/widget/av$a.g:F
     532: fconst_0
     533: fcmpl
     534: ifle          572
     537: iload         11
     539: ifeq          545
     542: goto          552
     545: iload         18
     547: istore        17
     549: goto          542
     552: iload         16
     554: iload         17
     556: invokestatic  #197                // Method java/lang/Math.max:(II)I
     559: istore        11
     561: iload         8
     563: istore        7
     565: iload         11
     567: istore        8
     569: goto          594
     572: iload         11
     574: ifeq          581
     577: iload         17
     579: istore        18
     581: iload         8
     583: iload         18
     585: invokestatic  #197                // Method java/lang/Math.max:(II)I
     588: istore        7
     590: iload         16
     592: istore        8
     594: aload_0
     595: aload         23
     597: iload         19
     599: invokevirtual #180                // Method a:(Landroid/view/View;I)I
     602: istore        16
     604: iload         5
     606: istore        11
     608: iload         8
     610: istore        5
     612: iload         16
     614: iload         19
     616: iadd
     617: istore        16
     619: iload         7
     621: istore        8
     623: iload         11
     625: istore        7
     627: iload         16
     629: istore        11
     631: iload         11
     633: iconst_1
     634: iadd
     635: istore        11
     637: goto          64
     640: iload         10
     642: istore        16
     644: iload         15
     646: istore        10
     648: aload_0
     649: getfield      #169                // Field f:I
     652: ifle          680
     655: aload_0
     656: iload         13
     658: invokevirtual #183                // Method c:(I)Z
     661: ifeq          680
     664: aload_0
     665: aload_0
     666: getfield      #169                // Field f:I
     669: aload_0
     670: getfield      #185                // Field m:I
     673: iadd
     674: putfield      #169                // Field f:I
     677: goto          680
     680: iload         13
     682: istore        15
     684: iload         22
     686: ifeq          853
     689: iload         6
     691: istore        11
     693: iload         11
     695: ldc           #198                // int -2147483648
     697: if_icmpeq     719
     700: iload         10
     702: istore        13
     704: iload         11
     706: ifne          712
     709: goto          719
     712: iload         13
     714: istore        10
     716: goto          853
     719: aload_0
     720: iconst_0
     721: putfield      #169                // Field f:I
     724: iconst_0
     725: istore        11
     727: iload         10
     729: istore        13
     731: iload         11
     733: iload         15
     735: if_icmpge     712
     738: aload_0
     739: iload         11
     741: invokevirtual #144                // Method b:(I)Landroid/view/View;
     744: astore        23
     746: aload         23
     748: ifnonnull     769
     751: aload_0
     752: aload_0
     753: getfield      #169                // Field f:I
     756: aload_0
     757: iload         11
     759: invokevirtual #178                // Method d:(I)I
     762: iadd
     763: putfield      #169                // Field f:I
     766: goto          792
     769: aload         23
     771: invokevirtual #147                // Method android/view/View.getVisibility:()I
     774: bipush        8
     776: if_icmpne     795
     779: iload         11
     781: aload_0
     782: aload         23
     784: iload         11
     786: invokevirtual #180                // Method a:(Landroid/view/View;I)I
     789: iadd
     790: istore        11
     792: goto          844
     795: aload         23
     797: invokevirtual #151                // Method android/view/View.getLayoutParams:()Landroid/view/ViewGroup$LayoutParams;
     800: checkcast     #6                  // class android/support/v7/widget/av$a
     803: astore        24
     805: aload_0
     806: getfield      #169                // Field f:I
     809: istore        13
     811: aload_0
     812: iload         13
     814: iload         13
     816: iload         9
     818: iadd
     819: aload         24
     821: getfield      #189                // Field android/support/v7/widget/av$a.topMargin:I
     824: iadd
     825: aload         24
     827: getfield      #192                // Field android/support/v7/widget/av$a.bottomMargin:I
     830: iadd
     831: aload_0
     832: aload         23
     834: invokevirtual #203                // Method b:(Landroid/view/View;)I
     837: iadd
     838: invokestatic  #197                // Method java/lang/Math.max:(II)I
     841: putfield      #169                // Field f:I
     844: iload         11
     846: iconst_1
     847: iadd
     848: istore        11
     850: goto          727
     853: iload         6
     855: istore        13
     857: aload_0
     858: aload_0
     859: getfield      #169                // Field f:I
     862: aload_0
     863: invokevirtual #225                // Method getPaddingTop:()I
     866: aload_0
     867: invokevirtual #228                // Method getPaddingBottom:()I
     870: iadd
     871: iadd
     872: putfield      #169                // Field f:I
     875: aload_0
     876: getfield      #169                // Field f:I
     879: aload_0
     880: invokevirtual #231                // Method getSuggestedMinimumHeight:()I
     883: invokestatic  #197                // Method java/lang/Math.max:(II)I
     886: iload_2
     887: iconst_0
     888: invokestatic  #235                // Method android/view/View.resolveSizeAndState:(III)I
     891: istore        17
     893: ldc           #236                // int 16777215
     895: iload         17
     897: iand
     898: aload_0
     899: getfield      #169                // Field f:I
     902: isub
     903: istore        6
     905: iload         14
     907: ifne          1039
     910: iload         6
     912: ifeq          924
     915: fload_3
     916: fconst_0
     917: fcmpl
     918: ifle          924
     921: goto          1039
     924: iload         8
     926: iload         5
     928: invokestatic  #197                // Method java/lang/Math.max:(II)I
     931: istore        6
     933: iload         22
     935: ifeq          1028
     938: iload         13
     940: ldc           #136                // int 1073741824
     942: if_icmpeq     1028
     945: iconst_0
     946: istore        5
     948: iload         5
     950: iload         15
     952: if_icmpge     1028
     955: aload_0
     956: iload         5
     958: invokevirtual #144                // Method b:(I)Landroid/view/View;
     961: astore        23
     963: aload         23
     965: ifnull        1019
     968: aload         23
     970: invokevirtual #147                // Method android/view/View.getVisibility:()I
     973: bipush        8
     975: if_icmpne     981
     978: goto          1019
     981: aload         23
     983: invokevirtual #151                // Method android/view/View.getLayoutParams:()Landroid/view/ViewGroup$LayoutParams;
     986: checkcast     #6                  // class android/support/v7/widget/av$a
     989: getfield      #186                // Field android/support/v7/widget/av$a.g:F
     992: fconst_0
     993: fcmpl
     994: ifle          1019
     997: aload         23
     999: aload         23
    1001: invokevirtual #165                // Method android/view/View.getMeasuredWidth:()I
    1004: ldc           #136                // int 1073741824
    1006: invokestatic  #141                // Method android/view/View$MeasureSpec.makeMeasureSpec:(II)I
    1009: iload         9
    1011: ldc           #136                // int 1073741824
    1013: invokestatic  #141                // Method android/view/View$MeasureSpec.makeMeasureSpec:(II)I
    1016: invokevirtual #239                // Method android/view/View.measure:(II)V
    1019: iload         5
    1021: iconst_1
    1022: iadd
    1023: istore        5
    1025: goto          948
    1028: iload         10
    1030: istore        8
    1032: iload         6
    1034: istore        5
    1036: goto          1495
    1039: aload_0
    1040: getfield      #90                 // Field g:F
    1043: fconst_0
    1044: fcmpl
    1045: ifle          1053
    1048: aload_0
    1049: getfield      #90                 // Field g:F
    1052: fstore_3
    1053: aload_0
    1054: iconst_0
    1055: putfield      #169                // Field f:I
    1058: iload         6
    1060: istore        9
    1062: iconst_0
    1063: istore        11
    1065: iload         8
    1067: istore        6
    1069: iload         10
    1071: istore        8
    1073: iload         16
    1075: istore        5
    1077: iload         11
    1079: istore        10
    1081: iload         10
    1083: iload         15
    1085: if_icmpge     1469
    1088: aload_0
    1089: iload         10
    1091: invokevirtual #144                // Method b:(I)Landroid/view/View;
    1094: astore        23
    1096: aload         23
    1098: invokevirtual #147                // Method android/view/View.getVisibility:()I
    1101: bipush        8
    1103: if_icmpne     1109
    1106: goto          1460
    1109: aload         23
    1111: invokevirtual #151                // Method android/view/View.getLayoutParams:()Landroid/view/ViewGroup$LayoutParams;
    1114: checkcast     #6                  // class android/support/v7/widget/av$a
    1117: astore        24
    1119: aload         24
    1121: getfield      #186                // Field android/support/v7/widget/av$a.g:F
    1124: fstore        4
    1126: fload         4
    1128: fconst_0
    1129: fcmpl
    1130: ifle          1297
    1133: iload         9
    1135: i2f
    1136: fload         4
    1138: fmul
    1139: fload_3
    1140: fdiv
    1141: f2i
    1142: istore        14
    1144: aload_0
    1145: invokevirtual #242                // Method getPaddingLeft:()I
    1148: istore        16
    1150: aload_0
    1151: invokevirtual #245                // Method getPaddingRight:()I
    1154: istore        18
    1156: iload         9
    1158: iload         14
    1160: isub
    1161: istore        11
    1163: aload         24
    1165: getfield      #213                // Field android/support/v7/widget/av$a.leftMargin:I
    1168: istore        9
    1170: aload         24
    1172: getfield      #216                // Field android/support/v7/widget/av$a.rightMargin:I
    1175: istore        19
    1177: aload         24
    1179: getfield      #154                // Field android/support/v7/widget/av$a.width:I
    1182: istore        21
    1184: fload_3
    1185: fload         4
    1187: fsub
    1188: fstore_3
    1189: iload_1
    1190: iload         16
    1192: iload         18
    1194: iadd
    1195: iload         9
    1197: iadd
    1198: iload         19
    1200: iadd
    1201: iload         21
    1203: invokestatic  #248                // Method getChildMeasureSpec:(III)I
    1206: istore        16
    1208: aload         24
    1210: getfield      #157                // Field android/support/v7/widget/av$a.height:I
    1213: ifne          1238
    1216: iload         13
    1218: ldc           #136                // int 1073741824
    1220: if_icmpeq     1226
    1223: goto          1238
    1226: iload         14
    1228: ifle          1257
    1231: iload         14
    1233: istore        9
    1235: goto          1260
    1238: aload         23
    1240: invokevirtual #160                // Method android/view/View.getMeasuredHeight:()I
    1243: iload         14
    1245: iadd
    1246: istore        14
    1248: iload         14
    1250: istore        9
    1252: iload         14
    1254: ifge          1260
    1257: iconst_0
    1258: istore        9
    1260: aload         23
    1262: iload         16
    1264: iload         9
    1266: ldc           #136                // int 1073741824
    1268: invokestatic  #141                // Method android/view/View$MeasureSpec.makeMeasureSpec:(II)I
    1271: invokevirtual #239                // Method android/view/View.measure:(II)V
    1274: iload         5
    1276: aload         23
    1278: invokevirtual #219                // Method android/view/View.getMeasuredState:()I
    1281: sipush        -256
    1284: iand
    1285: invokestatic  #222                // Method android/view/View.combineMeasuredStates:(II)I
    1288: istore        5
    1290: iload         11
    1292: istore        9
    1294: goto          1297
    1297: aload         24
    1299: getfield      #213                // Field android/support/v7/widget/av$a.leftMargin:I
    1302: aload         24
    1304: getfield      #216                // Field android/support/v7/widget/av$a.rightMargin:I
    1307: iadd
    1308: istore        14
    1310: aload         23
    1312: invokevirtual #165                // Method android/view/View.getMeasuredWidth:()I
    1315: iload         14
    1317: iadd
    1318: istore        16
    1320: iload         8
    1322: iload         16
    1324: invokestatic  #197                // Method java/lang/Math.max:(II)I
    1327: istore        11
    1329: iload         20
    1331: ldc           #136                // int 1073741824
    1333: if_icmpeq     1351
    1336: aload         24
    1338: getfield      #154                // Field android/support/v7/widget/av$a.width:I
    1341: iconst_m1
    1342: if_icmpne     1351
    1345: iconst_1
    1346: istore        8
    1348: goto          1354
    1351: iconst_0
    1352: istore        8
    1354: iload         8
    1356: ifeq          1366
    1359: iload         14
    1361: istore        8
    1363: goto          1370
    1366: iload         16
    1368: istore        8
    1370: iload         6
    1372: iload         8
    1374: invokestatic  #197                // Method java/lang/Math.max:(II)I
    1377: istore        14
    1379: iload         7
    1381: ifeq          1399
    1384: aload         24
    1386: getfield      #154                // Field android/support/v7/widget/av$a.width:I
    1389: iconst_m1
    1390: if_icmpne     1399
    1393: iconst_1
    1394: istore        6
    1396: goto          1402
    1399: iconst_0
    1400: istore        6
    1402: aload_0
    1403: getfield      #169                // Field f:I
    1406: istore        7
    1408: aload_0
    1409: iload         7
    1411: aload         23
    1413: invokevirtual #160                // Method android/view/View.getMeasuredHeight:()I
    1416: iload         7
    1418: iadd
    1419: aload         24
    1421: getfield      #189                // Field android/support/v7/widget/av$a.topMargin:I
    1424: iadd
    1425: aload         24
    1427: getfield      #192                // Field android/support/v7/widget/av$a.bottomMargin:I
    1430: iadd
    1431: aload_0
    1432: aload         23
    1434: invokevirtual #203                // Method b:(Landroid/view/View;)I
    1437: iadd
    1438: invokestatic  #197                // Method java/lang/Math.max:(II)I
    1441: putfield      #169                // Field f:I
    1444: iload         11
    1446: istore        8
    1448: iload         14
    1450: istore        11
    1452: iload         6
    1454: istore        7
    1456: iload         11
    1458: istore        6
    1460: iload         10
    1462: iconst_1
    1463: iadd
    1464: istore        10
    1466: goto          1081
    1469: aload_0
    1470: aload_0
    1471: getfield      #169                // Field f:I
    1474: aload_0
    1475: invokevirtual #225                // Method getPaddingTop:()I
    1478: aload_0
    1479: invokevirtual #228                // Method getPaddingBottom:()I
    1482: iadd
    1483: iadd
    1484: putfield      #169                // Field f:I
    1487: iload         5
    1489: istore        16
    1491: iload         6
    1493: istore        5
    1495: iload         7
    1497: ifne          1510
    1500: iload         20
    1502: ldc           #136                // int 1073741824
    1504: if_icmpeq     1510
    1507: goto          1514
    1510: iload         8
    1512: istore        5
    1514: aload_0
    1515: iload         5
    1517: aload_0
    1518: invokevirtual #242                // Method getPaddingLeft:()I
    1521: aload_0
    1522: invokevirtual #245                // Method getPaddingRight:()I
    1525: iadd
    1526: iadd
    1527: aload_0
    1528: invokevirtual #251                // Method getSuggestedMinimumWidth:()I
    1531: invokestatic  #197                // Method java/lang/Math.max:(II)I
    1534: iload_1
    1535: iload         16
    1537: invokestatic  #235                // Method android/view/View.resolveSizeAndState:(III)I
    1540: iload         17
    1542: invokevirtual #254                // Method setMeasuredDimension:(II)V
    1545: iload         12
    1547: ifeq          1557
    1550: aload_0
    1551: iload         15
    1553: iload_2
    1554: invokespecial #256                // Method c:(II)V
    1557: return

  void a(int, int, int, int);
    Code:
       0: aload_0
       1: invokevirtual #242                // Method getPaddingLeft:()I
       4: istore        5
       6: iload_3
       7: iload_1
       8: isub
       9: istore        6
      11: aload_0
      12: invokevirtual #245                // Method getPaddingRight:()I
      15: istore        7
      17: aload_0
      18: invokevirtual #245                // Method getPaddingRight:()I
      21: istore        8
      23: aload_0
      24: invokevirtual #172                // Method getVirtualChildCount:()I
      27: istore        9
      29: aload_0
      30: getfield      #45                 // Field e:I
      33: bipush        112
      35: iand
      36: istore_1
      37: aload_0
      38: getfield      #45                 // Field e:I
      41: istore        10
      43: iload_1
      44: bipush        16
      46: if_icmpeq     81
      49: iload_1
      50: bipush        80
      52: if_icmpeq     63
      55: aload_0
      56: invokevirtual #225                // Method getPaddingTop:()I
      59: istore_1
      60: goto          100
      63: aload_0
      64: invokevirtual #225                // Method getPaddingTop:()I
      67: iload         4
      69: iadd
      70: iload_2
      71: isub
      72: aload_0
      73: getfield      #169                // Field f:I
      76: isub
      77: istore_1
      78: goto          100
      81: aload_0
      82: invokevirtual #225                // Method getPaddingTop:()I
      85: istore_1
      86: iload         4
      88: iload_2
      89: isub
      90: aload_0
      91: getfield      #169                // Field f:I
      94: isub
      95: iconst_2
      96: idiv
      97: iload_1
      98: iadd
      99: istore_1
     100: iconst_0
     101: istore_2
     102: iload_2
     103: iload         9
     105: if_icmpge     370
     108: aload_0
     109: iload_2
     110: invokevirtual #144                // Method b:(I)Landroid/view/View;
     113: astore        13
     115: aload         13
     117: ifnonnull     134
     120: iload_1
     121: aload_0
     122: iload_2
     123: invokevirtual #178                // Method d:(I)I
     126: iadd
     127: istore_3
     128: iload_2
     129: istore        4
     131: goto          360
     134: iload_1
     135: istore_3
     136: iload_2
     137: istore        4
     139: aload         13
     141: invokevirtual #147                // Method android/view/View.getVisibility:()I
     144: bipush        8
     146: if_icmpeq     131
     149: aload         13
     151: invokevirtual #165                // Method android/view/View.getMeasuredWidth:()I
     154: istore        12
     156: aload         13
     158: invokevirtual #160                // Method android/view/View.getMeasuredHeight:()I
     161: istore        11
     163: aload         13
     165: invokevirtual #151                // Method android/view/View.getLayoutParams:()Landroid/view/ViewGroup$LayoutParams;
     168: checkcast     #6                  // class android/support/v7/widget/av$a
     171: astore        14
     173: aload         14
     175: getfield      #258                // Field android/support/v7/widget/av$a.h:I
     178: istore        4
     180: iload         4
     182: istore_3
     183: iload         4
     185: ifge          195
     188: iload         10
     190: ldc_w         #259                // int 8388615
     193: iand
     194: istore_3
     195: iload_3
     196: aload_0
     197: invokestatic  #263                // Method android/support/v4/view/s.e:(Landroid/view/View;)I
     200: invokestatic  #266                // Method android/support/v4/view/e.a:(II)I
     203: bipush        7
     205: iand
     206: istore_3
     207: iload_3
     208: iconst_1
     209: if_icmpeq     241
     212: iload_3
     213: iconst_5
     214: if_icmpeq     229
     217: aload         14
     219: getfield      #213                // Field android/support/v7/widget/av$a.leftMargin:I
     222: iload         5
     224: iadd
     225: istore_3
     226: goto          275
     229: iload         6
     231: iload         7
     233: isub
     234: iload         12
     236: isub
     237: istore_3
     238: goto          264
     241: iload         6
     243: iload         5
     245: isub
     246: iload         8
     248: isub
     249: iload         12
     251: isub
     252: iconst_2
     253: idiv
     254: iload         5
     256: iadd
     257: aload         14
     259: getfield      #213                // Field android/support/v7/widget/av$a.leftMargin:I
     262: iadd
     263: istore_3
     264: iload_3
     265: aload         14
     267: getfield      #216                // Field android/support/v7/widget/av$a.rightMargin:I
     270: isub
     271: istore_3
     272: goto          226
     275: iload_1
     276: istore        4
     278: aload_0
     279: iload_2
     280: invokevirtual #183                // Method c:(I)Z
     283: ifeq          294
     286: iload_1
     287: aload_0
     288: getfield      #185                // Field m:I
     291: iadd
     292: istore        4
     294: iload         4
     296: aload         14
     298: getfield      #189                // Field android/support/v7/widget/av$a.topMargin:I
     301: iadd
     302: istore_1
     303: aload_0
     304: aload         13
     306: iload_3
     307: iload_1
     308: aload_0
     309: aload         13
     311: invokevirtual #268                // Method a:(Landroid/view/View;)I
     314: iadd
     315: iload         12
     317: iload         11
     319: invokespecial #270                // Method a:(Landroid/view/View;IIII)V
     322: aload         14
     324: getfield      #192                // Field android/support/v7/widget/av$a.bottomMargin:I
     327: istore_3
     328: aload_0
     329: aload         13
     331: invokevirtual #203                // Method b:(Landroid/view/View;)I
     334: istore        12
     336: iload_2
     337: aload_0
     338: aload         13
     340: iload_2
     341: invokevirtual #180                // Method a:(Landroid/view/View;I)I
     344: iadd
     345: istore        4
     347: iload_1
     348: iload         11
     350: iload_3
     351: iadd
     352: iload         12
     354: iadd
     355: iadd
     356: istore_3
     357: goto          131
     360: iload         4
     362: iconst_1
     363: iadd
     364: istore_2
     365: iload_3
     366: istore_1
     367: goto          102
     370: return

  void a(android.graphics.Canvas);
    Code:
       0: aload_0
       1: invokevirtual #172                // Method getVirtualChildCount:()I
       4: istore_3
       5: iconst_0
       6: istore_2
       7: iload_2
       8: iload_3
       9: if_icmpge     80
      12: aload_0
      13: iload_2
      14: invokevirtual #144                // Method b:(I)Landroid/view/View;
      17: astore        4
      19: aload         4
      21: ifnull        73
      24: aload         4
      26: invokevirtual #147                // Method android/view/View.getVisibility:()I
      29: bipush        8
      31: if_icmpeq     73
      34: aload_0
      35: iload_2
      36: invokevirtual #183                // Method c:(I)Z
      39: ifeq          73
      42: aload         4
      44: invokevirtual #151                // Method android/view/View.getLayoutParams:()Landroid/view/ViewGroup$LayoutParams;
      47: checkcast     #6                  // class android/support/v7/widget/av$a
      50: astore        5
      52: aload_0
      53: aload_1
      54: aload         4
      56: invokevirtual #274                // Method android/view/View.getTop:()I
      59: aload         5
      61: getfield      #189                // Field android/support/v7/widget/av$a.topMargin:I
      64: isub
      65: aload_0
      66: getfield      #185                // Field m:I
      69: isub
      70: invokevirtual #277                // Method a:(Landroid/graphics/Canvas;I)V
      73: iload_2
      74: iconst_1
      75: iadd
      76: istore_2
      77: goto          7
      80: aload_0
      81: iload_3
      82: invokevirtual #183                // Method c:(I)Z
      85: ifeq          148
      88: aload_0
      89: iload_3
      90: iconst_1
      91: isub
      92: invokevirtual #144                // Method b:(I)Landroid/view/View;
      95: astore        4
      97: aload         4
      99: ifnonnull     120
     102: aload_0
     103: invokevirtual #280                // Method getHeight:()I
     106: aload_0
     107: invokevirtual #228                // Method getPaddingBottom:()I
     110: isub
     111: aload_0
     112: getfield      #185                // Field m:I
     115: isub
     116: istore_2
     117: goto          142
     120: aload         4
     122: invokevirtual #151                // Method android/view/View.getLayoutParams:()Landroid/view/ViewGroup$LayoutParams;
     125: checkcast     #6                  // class android/support/v7/widget/av$a
     128: astore        5
     130: aload         4
     132: invokevirtual #283                // Method android/view/View.getBottom:()I
     135: aload         5
     137: getfield      #192                // Field android/support/v7/widget/av$a.bottomMargin:I
     140: iadd
     141: istore_2
     142: aload_0
     143: aload_1
     144: iload_2
     145: invokevirtual #277                // Method a:(Landroid/graphics/Canvas;I)V
     148: return

  void a(android.graphics.Canvas, int);
    Code:
       0: aload_0
       1: getfield      #285                // Field k:Landroid/graphics/drawable/Drawable;
       4: aload_0
       5: invokevirtual #242                // Method getPaddingLeft:()I
       8: aload_0
       9: getfield      #120                // Field o:I
      12: iadd
      13: iload_2
      14: aload_0
      15: invokevirtual #288                // Method getWidth:()I
      18: aload_0
      19: invokevirtual #245                // Method getPaddingRight:()I
      22: isub
      23: aload_0
      24: getfield      #120                // Field o:I
      27: isub
      28: aload_0
      29: getfield      #185                // Field m:I
      32: iload_2
      33: iadd
      34: invokevirtual #293                // Method android/graphics/drawable/Drawable.setBounds:(IIII)V
      37: aload_0
      38: getfield      #285                // Field k:Landroid/graphics/drawable/Drawable;
      41: aload_1
      42: invokevirtual #296                // Method android/graphics/drawable/Drawable.draw:(Landroid/graphics/Canvas;)V
      45: return

  void a(android.view.View, int, int, int, int, int);
    Code:
       0: aload_0
       1: aload_1
       2: iload_3
       3: iload         4
       5: iload         5
       7: iload         6
       9: invokevirtual #163                // Method measureChildWithMargins:(Landroid/view/View;IIII)V
      12: return

  int b(android.view.View);
    Code:
       0: iconst_0
       1: ireturn

  public android.support.v7.widget.av$a b(android.util.AttributeSet);
    Code:
       0: new           #6                  // class android/support/v7/widget/av$a
       3: dup
       4: aload_0
       5: invokevirtual #301                // Method getContext:()Landroid/content/Context;
       8: aload_1
       9: invokespecial #302                // Method android/support/v7/widget/av$a."<init>":(Landroid/content/Context;Landroid/util/AttributeSet;)V
      12: areturn

  protected android.support.v7.widget.av$a b(android.view.ViewGroup$LayoutParams);
    Code:
       0: new           #6                  // class android/support/v7/widget/av$a
       3: dup
       4: aload_1
       5: invokespecial #306                // Method android/support/v7/widget/av$a."<init>":(Landroid/view/ViewGroup$LayoutParams;)V
       8: areturn

  android.view.View b(int);
    Code:
       0: aload_0
       1: iload_1
       2: invokevirtual #309                // Method getChildAt:(I)Landroid/view/View;
       5: areturn

  void b(int, int);
    Code:
       0: aload_0
       1: iconst_0
       2: putfield      #169                // Field f:I
       5: aload_0
       6: invokevirtual #172                // Method getVirtualChildCount:()I
       9: istore        19
      11: iload_1
      12: invokestatic  #176                // Method android/view/View$MeasureSpec.getMode:(I)I
      15: istore        21
      17: iload_2
      18: invokestatic  #176                // Method android/view/View$MeasureSpec.getMode:(I)I
      21: istore        20
      23: aload_0
      24: getfield      #311                // Field i:[I
      27: ifnull        37
      30: aload_0
      31: getfield      #313                // Field j:[I
      34: ifnonnull     51
      37: aload_0
      38: iconst_4
      39: newarray       int
      41: putfield      #311                // Field i:[I
      44: aload_0
      45: iconst_4
      46: newarray       int
      48: putfield      #313                // Field j:[I
      51: aload_0
      52: getfield      #311                // Field i:[I
      55: astore        28
      57: aload_0
      58: getfield      #313                // Field j:[I
      61: astore        25
      63: aload         28
      65: iconst_3
      66: iconst_m1
      67: iastore
      68: aload         28
      70: iconst_2
      71: iconst_m1
      72: iastore
      73: aload         28
      75: iconst_1
      76: iconst_m1
      77: iastore
      78: aload         28
      80: iconst_0
      81: iconst_m1
      82: iastore
      83: aload         25
      85: iconst_3
      86: iconst_m1
      87: iastore
      88: aload         25
      90: iconst_2
      91: iconst_m1
      92: iastore
      93: aload         25
      95: iconst_1
      96: iconst_m1
      97: iastore
      98: aload         25
     100: iconst_0
     101: iconst_m1
     102: iastore
     103: aload_0
     104: getfield      #38                 // Field a:Z
     107: istore        23
     109: aload_0
     110: getfield      #98                 // Field h:Z
     113: istore        24
     115: iload         21
     117: ldc           #136                // int 1073741824
     119: if_icmpne     128
     122: iconst_1
     123: istore        15
     125: goto          131
     128: iconst_0
     129: istore        15
     131: fconst_0
     132: fstore_3
     133: iconst_0
     134: istore        8
     136: iconst_0
     137: istore        7
     139: iconst_0
     140: istore        11
     142: iconst_0
     143: istore        12
     145: iconst_0
     146: istore        6
     148: iconst_0
     149: istore        10
     151: iconst_0
     152: istore        13
     154: iconst_1
     155: istore        5
     157: iconst_0
     158: istore        9
     160: iload         8
     162: iload         19
     164: if_icmpge     864
     167: aload_0
     168: iload         8
     170: invokevirtual #144                // Method b:(I)Landroid/view/View;
     173: astore        26
     175: aload         26
     177: ifnonnull     198
     180: aload_0
     181: aload_0
     182: getfield      #169                // Field f:I
     185: aload_0
     186: iload         8
     188: invokevirtual #178                // Method d:(I)I
     191: iadd
     192: putfield      #169                // Field f:I
     195: goto          855
     198: aload         26
     200: invokevirtual #147                // Method android/view/View.getVisibility:()I
     203: bipush        8
     205: if_icmpne     224
     208: iload         8
     210: aload_0
     211: aload         26
     213: iload         8
     215: invokevirtual #180                // Method a:(Landroid/view/View;I)I
     218: iadd
     219: istore        8
     221: goto          195
     224: aload_0
     225: iload         8
     227: invokevirtual #183                // Method c:(I)Z
     230: ifeq          246
     233: aload_0
     234: aload_0
     235: getfield      #169                // Field f:I
     238: aload_0
     239: getfield      #315                // Field l:I
     242: iadd
     243: putfield      #169                // Field f:I
     246: aload         26
     248: invokevirtual #151                // Method android/view/View.getLayoutParams:()Landroid/view/ViewGroup$LayoutParams;
     251: checkcast     #6                  // class android/support/v7/widget/av$a
     254: astore        29
     256: fload_3
     257: aload         29
     259: getfield      #186                // Field android/support/v7/widget/av$a.g:F
     262: fadd
     263: fstore_3
     264: iload         21
     266: ldc           #136                // int 1073741824
     268: if_icmpne     385
     271: aload         29
     273: getfield      #154                // Field android/support/v7/widget/av$a.width:I
     276: ifne          385
     279: aload         29
     281: getfield      #186                // Field android/support/v7/widget/av$a.g:F
     284: fconst_0
     285: fcmpl
     286: ifle          385
     289: iload         15
     291: ifeq          321
     294: aload_0
     295: getfield      #169                // Field f:I
     298: aload         29
     300: getfield      #213                // Field android/support/v7/widget/av$a.leftMargin:I
     303: aload         29
     305: getfield      #216                // Field android/support/v7/widget/av$a.rightMargin:I
     308: iadd
     309: iadd
     310: istore        14
     312: aload_0
     313: iload         14
     315: putfield      #169                // Field f:I
     318: goto          351
     321: aload_0
     322: getfield      #169                // Field f:I
     325: istore        14
     327: iload         14
     329: aload         29
     331: getfield      #213                // Field android/support/v7/widget/av$a.leftMargin:I
     334: iload         14
     336: iadd
     337: aload         29
     339: getfield      #216                // Field android/support/v7/widget/av$a.rightMargin:I
     342: iadd
     343: invokestatic  #197                // Method java/lang/Math.max:(II)I
     346: istore        14
     348: goto          312
     351: iload         23
     353: ifeq          379
     356: iconst_0
     357: iconst_0
     358: invokestatic  #141                // Method android/view/View$MeasureSpec.makeMeasureSpec:(II)I
     361: istore        14
     363: aload         26
     365: iload         14
     367: iload         14
     369: invokevirtual #239                // Method android/view/View.measure:(II)V
     372: iload         7
     374: istore        14
     376: goto          576
     379: iconst_1
     380: istore        12
     382: goto          580
     385: aload         29
     387: getfield      #154                // Field android/support/v7/widget/av$a.width:I
     390: ifne          416
     393: aload         29
     395: getfield      #186                // Field android/support/v7/widget/av$a.g:F
     398: fconst_0
     399: fcmpl
     400: ifle          416
     403: aload         29
     405: bipush        -2
     407: putfield      #154                // Field android/support/v7/widget/av$a.width:I
     410: iconst_0
     411: istore        14
     413: goto          420
     416: ldc           #198                // int -2147483648
     418: istore        14
     420: fload_3
     421: fconst_0
     422: fcmpl
     423: ifne          435
     426: aload_0
     427: getfield      #169                // Field f:I
     430: istore        16
     432: goto          438
     435: iconst_0
     436: istore        16
     438: aload         26
     440: astore        27
     442: aload_0
     443: aload         26
     445: iload         8
     447: iload_1
     448: iload         16
     450: iload_2
     451: iconst_0
     452: invokevirtual #201                // Method a:(Landroid/view/View;IIIII)V
     455: iload         14
     457: ldc           #198                // int -2147483648
     459: if_icmpeq     469
     462: aload         29
     464: iload         14
     466: putfield      #154                // Field android/support/v7/widget/av$a.width:I
     469: aload         27
     471: invokevirtual #165                // Method android/view/View.getMeasuredWidth:()I
     474: istore        16
     476: iload         15
     478: ifeq          518
     481: aload_0
     482: getfield      #169                // Field f:I
     485: aload         29
     487: getfield      #213                // Field android/support/v7/widget/av$a.leftMargin:I
     490: iload         16
     492: iadd
     493: aload         29
     495: getfield      #216                // Field android/support/v7/widget/av$a.rightMargin:I
     498: iadd
     499: aload_0
     500: aload         27
     502: invokevirtual #203                // Method b:(Landroid/view/View;)I
     505: iadd
     506: iadd
     507: istore        14
     509: aload_0
     510: iload         14
     512: putfield      #169                // Field f:I
     515: goto          558
     518: aload_0
     519: getfield      #169                // Field f:I
     522: istore        14
     524: iload         14
     526: iload         14
     528: iload         16
     530: iadd
     531: aload         29
     533: getfield      #213                // Field android/support/v7/widget/av$a.leftMargin:I
     536: iadd
     537: aload         29
     539: getfield      #216                // Field android/support/v7/widget/av$a.rightMargin:I
     542: iadd
     543: aload_0
     544: aload         27
     546: invokevirtual #203                // Method b:(Landroid/view/View;)I
     549: iadd
     550: invokestatic  #197                // Method java/lang/Math.max:(II)I
     553: istore        14
     555: goto          509
     558: iload         7
     560: istore        14
     562: iload         24
     564: ifeq          576
     567: iload         16
     569: iload         7
     571: invokestatic  #197                // Method java/lang/Math.max:(II)I
     574: istore        14
     576: iload         14
     578: istore        7
     580: iload         8
     582: istore        17
     584: iload         20
     586: ldc           #136                // int 1073741824
     588: if_icmpeq     609
     591: aload         29
     593: getfield      #157                // Field android/support/v7/widget/av$a.height:I
     596: iconst_m1
     597: if_icmpne     609
     600: iconst_1
     601: istore        8
     603: iconst_1
     604: istore        9
     606: goto          612
     609: iconst_0
     610: istore        8
     612: aload         29
     614: getfield      #189                // Field android/support/v7/widget/av$a.topMargin:I
     617: aload         29
     619: getfield      #192                // Field android/support/v7/widget/av$a.bottomMargin:I
     622: iadd
     623: istore        14
     625: aload         26
     627: invokevirtual #160                // Method android/view/View.getMeasuredHeight:()I
     630: iload         14
     632: iadd
     633: istore        16
     635: iload         13
     637: aload         26
     639: invokevirtual #219                // Method android/view/View.getMeasuredState:()I
     642: invokestatic  #222                // Method android/view/View.combineMeasuredStates:(II)I
     645: istore        18
     647: iload         23
     649: ifeq          736
     652: aload         26
     654: invokevirtual #318                // Method android/view/View.getBaseline:()I
     657: istore        22
     659: iload         22
     661: iconst_m1
     662: if_icmpeq     736
     665: aload         29
     667: getfield      #258                // Field android/support/v7/widget/av$a.h:I
     670: ifge          682
     673: aload_0
     674: getfield      #45                 // Field e:I
     677: istore        13
     679: goto          689
     682: aload         29
     684: getfield      #258                // Field android/support/v7/widget/av$a.h:I
     687: istore        13
     689: iload         13
     691: bipush        112
     693: iand
     694: iconst_4
     695: ishr
     696: bipush        -2
     698: iand
     699: iconst_1
     700: ishr
     701: istore        13
     703: aload         28
     705: iload         13
     707: aload         28
     709: iload         13
     711: iaload
     712: iload         22
     714: invokestatic  #197                // Method java/lang/Math.max:(II)I
     717: iastore
     718: aload         25
     720: iload         13
     722: aload         25
     724: iload         13
     726: iaload
     727: iload         16
     729: iload         22
     731: isub
     732: invokestatic  #197                // Method java/lang/Math.max:(II)I
     735: iastore
     736: iload         11
     738: iload         16
     740: invokestatic  #197                // Method java/lang/Math.max:(II)I
     743: istore        11
     745: iload         5
     747: ifeq          765
     750: aload         29
     752: getfield      #157                // Field android/support/v7/widget/av$a.height:I
     755: iconst_m1
     756: if_icmpne     765
     759: iconst_1
     760: istore        5
     762: goto          768
     765: iconst_0
     766: istore        5
     768: aload         29
     770: getfield      #186                // Field android/support/v7/widget/av$a.g:F
     773: fconst_0
     774: fcmpl
     775: ifle          805
     778: iload         8
     780: ifeq          786
     783: goto          793
     786: iload         16
     788: istore        14
     790: goto          783
     793: iload         10
     795: iload         14
     797: invokestatic  #197                // Method java/lang/Math.max:(II)I
     800: istore        8
     802: goto          830
     805: iload         8
     807: ifeq          814
     810: iload         14
     812: istore        16
     814: iload         6
     816: iload         16
     818: invokestatic  #197                // Method java/lang/Math.max:(II)I
     821: istore        6
     823: iload         10
     825: istore        8
     827: goto          802
     830: aload_0
     831: aload         26
     833: iload         17
     835: invokevirtual #180                // Method a:(Landroid/view/View;I)I
     838: iload         17
     840: iadd
     841: istore        14
     843: iload         18
     845: istore        13
     847: iload         8
     849: istore        10
     851: iload         14
     853: istore        8
     855: iload         8
     857: iconst_1
     858: iadd
     859: istore        8
     861: goto          160
     864: iload         11
     866: istore        8
     868: aload_0
     869: getfield      #169                // Field f:I
     872: ifle          897
     875: aload_0
     876: iload         19
     878: invokevirtual #183                // Method c:(I)Z
     881: ifeq          897
     884: aload_0
     885: aload_0
     886: getfield      #169                // Field f:I
     889: aload_0
     890: getfield      #315                // Field l:I
     893: iadd
     894: putfield      #169                // Field f:I
     897: aload         28
     899: iconst_1
     900: iaload
     901: iconst_m1
     902: if_icmpne     933
     905: aload         28
     907: iconst_0
     908: iaload
     909: iconst_m1
     910: if_icmpne     933
     913: aload         28
     915: iconst_2
     916: iaload
     917: iconst_m1
     918: if_icmpne     933
     921: iload         8
     923: istore        11
     925: aload         28
     927: iconst_3
     928: iaload
     929: iconst_m1
     930: if_icmpeq     991
     933: iload         8
     935: aload         28
     937: iconst_3
     938: iaload
     939: aload         28
     941: iconst_0
     942: iaload
     943: aload         28
     945: iconst_1
     946: iaload
     947: aload         28
     949: iconst_2
     950: iaload
     951: invokestatic  #197                // Method java/lang/Math.max:(II)I
     954: invokestatic  #197                // Method java/lang/Math.max:(II)I
     957: invokestatic  #197                // Method java/lang/Math.max:(II)I
     960: aload         25
     962: iconst_3
     963: iaload
     964: aload         25
     966: iconst_0
     967: iaload
     968: aload         25
     970: iconst_1
     971: iaload
     972: aload         25
     974: iconst_2
     975: iaload
     976: invokestatic  #197                // Method java/lang/Math.max:(II)I
     979: invokestatic  #197                // Method java/lang/Math.max:(II)I
     982: invokestatic  #197                // Method java/lang/Math.max:(II)I
     985: iadd
     986: invokestatic  #197                // Method java/lang/Math.max:(II)I
     989: istore        11
     991: iload         24
     993: ifeq          1176
     996: iload         21
     998: ldc           #198                // int -2147483648
    1000: if_icmpeq     1008
    1003: iload         21
    1005: ifne          1176
    1008: aload_0
    1009: iconst_0
    1010: putfield      #169                // Field f:I
    1013: iconst_0
    1014: istore        8
    1016: iload         8
    1018: iload         19
    1020: if_icmpge     1176
    1023: aload_0
    1024: iload         8
    1026: invokevirtual #144                // Method b:(I)Landroid/view/View;
    1029: astore        26
    1031: aload         26
    1033: ifnonnull     1054
    1036: aload_0
    1037: aload_0
    1038: getfield      #169                // Field f:I
    1041: aload_0
    1042: iload         8
    1044: invokevirtual #178                // Method d:(I)I
    1047: iadd
    1048: putfield      #169                // Field f:I
    1051: goto          1077
    1054: aload         26
    1056: invokevirtual #147                // Method android/view/View.getVisibility:()I
    1059: bipush        8
    1061: if_icmpne     1080
    1064: iload         8
    1066: aload_0
    1067: aload         26
    1069: iload         8
    1071: invokevirtual #180                // Method a:(Landroid/view/View;I)I
    1074: iadd
    1075: istore        8
    1077: goto          1167
    1080: aload         26
    1082: invokevirtual #151                // Method android/view/View.getLayoutParams:()Landroid/view/ViewGroup$LayoutParams;
    1085: checkcast     #6                  // class android/support/v7/widget/av$a
    1088: astore        27
    1090: iload         15
    1092: ifeq          1128
    1095: aload_0
    1096: aload_0
    1097: getfield      #169                // Field f:I
    1100: aload         27
    1102: getfield      #213                // Field android/support/v7/widget/av$a.leftMargin:I
    1105: iload         7
    1107: iadd
    1108: aload         27
    1110: getfield      #216                // Field android/support/v7/widget/av$a.rightMargin:I
    1113: iadd
    1114: aload_0
    1115: aload         26
    1117: invokevirtual #203                // Method b:(Landroid/view/View;)I
    1120: iadd
    1121: iadd
    1122: putfield      #169                // Field f:I
    1125: goto          1077
    1128: aload_0
    1129: getfield      #169                // Field f:I
    1132: istore        14
    1134: aload_0
    1135: iload         14
    1137: iload         14
    1139: iload         7
    1141: iadd
    1142: aload         27
    1144: getfield      #213                // Field android/support/v7/widget/av$a.leftMargin:I
    1147: iadd
    1148: aload         27
    1150: getfield      #216                // Field android/support/v7/widget/av$a.rightMargin:I
    1153: iadd
    1154: aload_0
    1155: aload         26
    1157: invokevirtual #203                // Method b:(Landroid/view/View;)I
    1160: iadd
    1161: invokestatic  #197                // Method java/lang/Math.max:(II)I
    1164: putfield      #169                // Field f:I
    1167: iload         8
    1169: iconst_1
    1170: iadd
    1171: istore        8
    1173: goto          1016
    1176: aload_0
    1177: aload_0
    1178: getfield      #169                // Field f:I
    1181: aload_0
    1182: invokevirtual #242                // Method getPaddingLeft:()I
    1185: aload_0
    1186: invokevirtual #245                // Method getPaddingRight:()I
    1189: iadd
    1190: iadd
    1191: putfield      #169                // Field f:I
    1194: aload_0
    1195: getfield      #169                // Field f:I
    1198: aload_0
    1199: invokevirtual #251                // Method getSuggestedMinimumWidth:()I
    1202: invokestatic  #197                // Method java/lang/Math.max:(II)I
    1205: iload_1
    1206: iconst_0
    1207: invokestatic  #235                // Method android/view/View.resolveSizeAndState:(III)I
    1210: istore        16
    1212: ldc           #236                // int 16777215
    1214: iload         16
    1216: iand
    1217: aload_0
    1218: getfield      #169                // Field f:I
    1221: isub
    1222: istore        14
    1224: iload         12
    1226: ifne          1358
    1229: iload         14
    1231: ifeq          1243
    1234: fload_3
    1235: fconst_0
    1236: fcmpl
    1237: ifle          1243
    1240: goto          1358
    1243: iload         6
    1245: iload         10
    1247: invokestatic  #197                // Method java/lang/Math.max:(II)I
    1250: istore        8
    1252: iload         24
    1254: ifeq          1347
    1257: iload         21
    1259: ldc           #136                // int 1073741824
    1261: if_icmpeq     1347
    1264: iconst_0
    1265: istore        6
    1267: iload         6
    1269: iload         19
    1271: if_icmpge     1347
    1274: aload_0
    1275: iload         6
    1277: invokevirtual #144                // Method b:(I)Landroid/view/View;
    1280: astore        25
    1282: aload         25
    1284: ifnull        1338
    1287: aload         25
    1289: invokevirtual #147                // Method android/view/View.getVisibility:()I
    1292: bipush        8
    1294: if_icmpne     1300
    1297: goto          1338
    1300: aload         25
    1302: invokevirtual #151                // Method android/view/View.getLayoutParams:()Landroid/view/ViewGroup$LayoutParams;
    1305: checkcast     #6                  // class android/support/v7/widget/av$a
    1308: getfield      #186                // Field android/support/v7/widget/av$a.g:F
    1311: fconst_0
    1312: fcmpl
    1313: ifle          1338
    1316: aload         25
    1318: iload         7
    1320: ldc           #136                // int 1073741824
    1322: invokestatic  #141                // Method android/view/View$MeasureSpec.makeMeasureSpec:(II)I
    1325: aload         25
    1327: invokevirtual #160                // Method android/view/View.getMeasuredHeight:()I
    1330: ldc           #136                // int 1073741824
    1332: invokestatic  #141                // Method android/view/View$MeasureSpec.makeMeasureSpec:(II)I
    1335: invokevirtual #239                // Method android/view/View.measure:(II)V
    1338: iload         6
    1340: iconst_1
    1341: iadd
    1342: istore        6
    1344: goto          1267
    1347: iload         8
    1349: istore        6
    1351: iload         5
    1353: istore        8
    1355: goto          2059
    1358: aload_0
    1359: getfield      #90                 // Field g:F
    1362: fconst_0
    1363: fcmpl
    1364: ifle          1372
    1367: aload_0
    1368: getfield      #90                 // Field g:F
    1371: fstore_3
    1372: aload         28
    1374: iconst_3
    1375: iconst_m1
    1376: iastore
    1377: aload         28
    1379: iconst_2
    1380: iconst_m1
    1381: iastore
    1382: aload         28
    1384: iconst_1
    1385: iconst_m1
    1386: iastore
    1387: aload         28
    1389: iconst_0
    1390: iconst_m1
    1391: iastore
    1392: aload         25
    1394: iconst_3
    1395: iconst_m1
    1396: iastore
    1397: aload         25
    1399: iconst_2
    1400: iconst_m1
    1401: iastore
    1402: aload         25
    1404: iconst_1
    1405: iconst_m1
    1406: iastore
    1407: aload         25
    1409: iconst_0
    1410: iconst_m1
    1411: iastore
    1412: aload_0
    1413: iconst_0
    1414: putfield      #169                // Field f:I
    1417: iconst_m1
    1418: istore        11
    1420: iconst_0
    1421: istore        12
    1423: iload         5
    1425: istore        8
    1427: iload         6
    1429: istore        10
    1431: iload         13
    1433: istore        5
    1435: iload         14
    1437: istore        6
    1439: iload         12
    1441: iload         19
    1443: if_icmpge     1935
    1446: aload_0
    1447: iload         12
    1449: invokevirtual #144                // Method b:(I)Landroid/view/View;
    1452: astore        26
    1454: aload         26
    1456: ifnull        1926
    1459: aload         26
    1461: invokevirtual #147                // Method android/view/View.getVisibility:()I
    1464: bipush        8
    1466: if_icmpne     1472
    1469: goto          1926
    1472: aload         26
    1474: invokevirtual #151                // Method android/view/View.getLayoutParams:()Landroid/view/ViewGroup$LayoutParams;
    1477: checkcast     #6                  // class android/support/v7/widget/av$a
    1480: astore        27
    1482: aload         27
    1484: getfield      #186                // Field android/support/v7/widget/av$a.g:F
    1487: fstore        4
    1489: fload         4
    1491: fconst_0
    1492: fcmpl
    1493: ifle          1636
    1496: iload         6
    1498: i2f
    1499: fload         4
    1501: fmul
    1502: fload_3
    1503: fdiv
    1504: f2i
    1505: istore        13
    1507: iload_2
    1508: aload_0
    1509: invokevirtual #225                // Method getPaddingTop:()I
    1512: aload_0
    1513: invokevirtual #228                // Method getPaddingBottom:()I
    1516: iadd
    1517: aload         27
    1519: getfield      #189                // Field android/support/v7/widget/av$a.topMargin:I
    1522: iadd
    1523: aload         27
    1525: getfield      #192                // Field android/support/v7/widget/av$a.bottomMargin:I
    1528: iadd
    1529: aload         27
    1531: getfield      #157                // Field android/support/v7/widget/av$a.height:I
    1534: invokestatic  #248                // Method getChildMeasureSpec:(III)I
    1537: istore        17
    1539: aload         27
    1541: getfield      #154                // Field android/support/v7/widget/av$a.width:I
    1544: ifne          1569
    1547: iload         21
    1549: ldc           #136                // int 1073741824
    1551: if_icmpeq     1557
    1554: goto          1569
    1557: iload         13
    1559: ifle          1588
    1562: iload         13
    1564: istore        7
    1566: goto          1591
    1569: aload         26
    1571: invokevirtual #165                // Method android/view/View.getMeasuredWidth:()I
    1574: iload         13
    1576: iadd
    1577: istore        14
    1579: iload         14
    1581: istore        7
    1583: iload         14
    1585: ifge          1591
    1588: iconst_0
    1589: istore        7
    1591: aload         26
    1593: iload         7
    1595: ldc           #136                // int 1073741824
    1597: invokestatic  #141                // Method android/view/View$MeasureSpec.makeMeasureSpec:(II)I
    1600: iload         17
    1602: invokevirtual #239                // Method android/view/View.measure:(II)V
    1605: iload         5
    1607: aload         26
    1609: invokevirtual #219                // Method android/view/View.getMeasuredState:()I
    1612: ldc_w         #319                // int -16777216
    1615: iand
    1616: invokestatic  #222                // Method android/view/View.combineMeasuredStates:(II)I
    1619: istore        5
    1621: fload_3
    1622: fload         4
    1624: fsub
    1625: fstore_3
    1626: iload         6
    1628: iload         13
    1630: isub
    1631: istore        6
    1633: goto          1636
    1636: iload         15
    1638: ifeq          1677
    1641: aload_0
    1642: aload_0
    1643: getfield      #169                // Field f:I
    1646: aload         26
    1648: invokevirtual #165                // Method android/view/View.getMeasuredWidth:()I
    1651: aload         27
    1653: getfield      #213                // Field android/support/v7/widget/av$a.leftMargin:I
    1656: iadd
    1657: aload         27
    1659: getfield      #216                // Field android/support/v7/widget/av$a.rightMargin:I
    1662: iadd
    1663: aload_0
    1664: aload         26
    1666: invokevirtual #203                // Method b:(Landroid/view/View;)I
    1669: iadd
    1670: iadd
    1671: putfield      #169                // Field f:I
    1674: goto          1722
    1677: aload_0
    1678: getfield      #169                // Field f:I
    1681: istore        7
    1683: aload_0
    1684: iload         7
    1686: aload         26
    1688: invokevirtual #165                // Method android/view/View.getMeasuredWidth:()I
    1691: iload         7
    1693: iadd
    1694: aload         27
    1696: getfield      #213                // Field android/support/v7/widget/av$a.leftMargin:I
    1699: iadd
    1700: aload         27
    1702: getfield      #216                // Field android/support/v7/widget/av$a.rightMargin:I
    1705: iadd
    1706: aload_0
    1707: aload         26
    1709: invokevirtual #203                // Method b:(Landroid/view/View;)I
    1712: iadd
    1713: invokestatic  #197                // Method java/lang/Math.max:(II)I
    1716: putfield      #169                // Field f:I
    1719: goto          1674
    1722: iload         20
    1724: ldc           #136                // int 1073741824
    1726: if_icmpeq     1744
    1729: aload         27
    1731: getfield      #157                // Field android/support/v7/widget/av$a.height:I
    1734: iconst_m1
    1735: if_icmpne     1744
    1738: iconst_1
    1739: istore        7
    1741: goto          1747
    1744: iconst_0
    1745: istore        7
    1747: aload         27
    1749: getfield      #189                // Field android/support/v7/widget/av$a.topMargin:I
    1752: aload         27
    1754: getfield      #192                // Field android/support/v7/widget/av$a.bottomMargin:I
    1757: iadd
    1758: istore        14
    1760: aload         26
    1762: invokevirtual #160                // Method android/view/View.getMeasuredHeight:()I
    1765: iload         14
    1767: iadd
    1768: istore        13
    1770: iload         11
    1772: iload         13
    1774: invokestatic  #197                // Method java/lang/Math.max:(II)I
    1777: istore        11
    1779: iload         7
    1781: ifeq          1791
    1784: iload         14
    1786: istore        7
    1788: goto          1795
    1791: iload         13
    1793: istore        7
    1795: iload         10
    1797: iload         7
    1799: invokestatic  #197                // Method java/lang/Math.max:(II)I
    1802: istore        10
    1804: iload         8
    1806: ifeq          1824
    1809: aload         27
    1811: getfield      #157                // Field android/support/v7/widget/av$a.height:I
    1814: iconst_m1
    1815: if_icmpne     1824
    1818: iconst_1
    1819: istore        7
    1821: goto          1827
    1824: iconst_0
    1825: istore        7
    1827: iload         23
    1829: ifeq          1919
    1832: aload         26
    1834: invokevirtual #318                // Method android/view/View.getBaseline:()I
    1837: istore        14
    1839: iload         14
    1841: iconst_m1
    1842: if_icmpeq     1919
    1845: aload         27
    1847: getfield      #258                // Field android/support/v7/widget/av$a.h:I
    1850: ifge          1862
    1853: aload_0
    1854: getfield      #45                 // Field e:I
    1857: istore        8
    1859: goto          1869
    1862: aload         27
    1864: getfield      #258                // Field android/support/v7/widget/av$a.h:I
    1867: istore        8
    1869: iload         8
    1871: bipush        112
    1873: iand
    1874: iconst_4
    1875: ishr
    1876: bipush        -2
    1878: iand
    1879: iconst_1
    1880: ishr
    1881: istore        8
    1883: aload         28
    1885: iload         8
    1887: aload         28
    1889: iload         8
    1891: iaload
    1892: iload         14
    1894: invokestatic  #197                // Method java/lang/Math.max:(II)I
    1897: iastore
    1898: aload         25
    1900: iload         8
    1902: aload         25
    1904: iload         8
    1906: iaload
    1907: iload         13
    1909: iload         14
    1911: isub
    1912: invokestatic  #197                // Method java/lang/Math.max:(II)I
    1915: iastore
    1916: goto          1919
    1919: iload         7
    1921: istore        8
    1923: goto          1926
    1926: iload         12
    1928: iconst_1
    1929: iadd
    1930: istore        12
    1932: goto          1439
    1935: aload_0
    1936: aload_0
    1937: getfield      #169                // Field f:I
    1940: aload_0
    1941: invokevirtual #242                // Method getPaddingLeft:()I
    1944: aload_0
    1945: invokevirtual #245                // Method getPaddingRight:()I
    1948: iadd
    1949: iadd
    1950: putfield      #169                // Field f:I
    1953: aload         28
    1955: iconst_1
    1956: iaload
    1957: iconst_m1
    1958: if_icmpne     1989
    1961: aload         28
    1963: iconst_0
    1964: iaload
    1965: iconst_m1
    1966: if_icmpne     1989
    1969: aload         28
    1971: iconst_2
    1972: iaload
    1973: iconst_m1
    1974: if_icmpne     1989
    1977: iload         11
    1979: istore        6
    1981: aload         28
    1983: iconst_3
    1984: iaload
    1985: iconst_m1
    1986: if_icmpeq     2047
    1989: iload         11
    1991: aload         28
    1993: iconst_3
    1994: iaload
    1995: aload         28
    1997: iconst_0
    1998: iaload
    1999: aload         28
    2001: iconst_1
    2002: iaload
    2003: aload         28
    2005: iconst_2
    2006: iaload
    2007: invokestatic  #197                // Method java/lang/Math.max:(II)I
    2010: invokestatic  #197                // Method java/lang/Math.max:(II)I
    2013: invokestatic  #197                // Method java/lang/Math.max:(II)I
    2016: aload         25
    2018: iconst_3
    2019: iaload
    2020: aload         25
    2022: iconst_0
    2023: iaload
    2024: aload         25
    2026: iconst_1
    2027: iaload
    2028: aload         25
    2030: iconst_2
    2031: iaload
    2032: invokestatic  #197                // Method java/lang/Math.max:(II)I
    2035: invokestatic  #197                // Method java/lang/Math.max:(II)I
    2038: invokestatic  #197                // Method java/lang/Math.max:(II)I
    2041: iadd
    2042: invokestatic  #197                // Method java/lang/Math.max:(II)I
    2045: istore        6
    2047: iload         5
    2049: istore        13
    2051: iload         6
    2053: istore        11
    2055: iload         10
    2057: istore        6
    2059: iload         8
    2061: ifne          2074
    2064: iload         20
    2066: ldc           #136                // int 1073741824
    2068: if_icmpeq     2074
    2071: goto          2078
    2074: iload         11
    2076: istore        6
    2078: aload_0
    2079: iload         16
    2081: ldc_w         #319                // int -16777216
    2084: iload         13
    2086: iand
    2087: ior
    2088: iload         6
    2090: aload_0
    2091: invokevirtual #225                // Method getPaddingTop:()I
    2094: aload_0
    2095: invokevirtual #228                // Method getPaddingBottom:()I
    2098: iadd
    2099: iadd
    2100: aload_0
    2101: invokevirtual #231                // Method getSuggestedMinimumHeight:()I
    2104: invokestatic  #197                // Method java/lang/Math.max:(II)I
    2107: iload_2
    2108: iload         13
    2110: bipush        16
    2112: ishl
    2113: invokestatic  #235                // Method android/view/View.resolveSizeAndState:(III)I
    2116: invokevirtual #254                // Method setMeasuredDimension:(II)V
    2119: iload         9
    2121: ifeq          2131
    2124: aload_0
    2125: iload         19
    2127: iload_1
    2128: invokespecial #321                // Method d:(II)V
    2131: return

  void b(int, int, int, int);
    Code:
       0: aload_0
       1: invokestatic  #326                // Method android/support/v7/widget/bx.a:(Landroid/view/View;)Z
       4: istore        18
       6: aload_0
       7: invokevirtual #225                // Method getPaddingTop:()I
      10: istore        10
      12: iload         4
      14: iload_2
      15: isub
      16: istore        12
      18: aload_0
      19: invokevirtual #228                // Method getPaddingBottom:()I
      22: istore        13
      24: aload_0
      25: invokevirtual #228                // Method getPaddingBottom:()I
      28: istore        14
      30: aload_0
      31: invokevirtual #172                // Method getVirtualChildCount:()I
      34: istore        8
      36: aload_0
      37: getfield      #45                 // Field e:I
      40: istore        4
      42: aload_0
      43: getfield      #45                 // Field e:I
      46: bipush        112
      48: iand
      49: istore_2
      50: aload_0
      51: getfield      #38                 // Field a:Z
      54: istore        19
      56: aload_0
      57: getfield      #311                // Field i:[I
      60: astore        20
      62: aload_0
      63: getfield      #313                // Field j:[I
      66: astore        21
      68: iload         4
      70: ldc_w         #259                // int 8388615
      73: iand
      74: aload_0
      75: invokestatic  #263                // Method android/support/v4/view/s.e:(Landroid/view/View;)I
      78: invokestatic  #266                // Method android/support/v4/view/e.a:(II)I
      81: istore        4
      83: iload         4
      85: iconst_1
      86: if_icmpeq     120
      89: iload         4
      91: iconst_5
      92: if_icmpeq     103
      95: aload_0
      96: invokevirtual #242                // Method getPaddingLeft:()I
      99: istore_1
     100: goto          140
     103: aload_0
     104: invokevirtual #242                // Method getPaddingLeft:()I
     107: iload_3
     108: iadd
     109: iload_1
     110: isub
     111: aload_0
     112: getfield      #169                // Field f:I
     115: isub
     116: istore_1
     117: goto          140
     120: aload_0
     121: invokevirtual #242                // Method getPaddingLeft:()I
     124: istore        4
     126: iload_3
     127: iload_1
     128: isub
     129: aload_0
     130: getfield      #169                // Field f:I
     133: isub
     134: iconst_2
     135: idiv
     136: iload         4
     138: iadd
     139: istore_1
     140: iload         18
     142: ifeq          157
     145: iload         8
     147: iconst_1
     148: isub
     149: istore        6
     151: iconst_m1
     152: istore        7
     154: goto          163
     157: iconst_0
     158: istore        6
     160: iconst_1
     161: istore        7
     163: iconst_0
     164: istore        4
     166: iload         10
     168: istore_3
     169: iload         4
     171: iload         8
     173: if_icmpge     541
     176: iload         6
     178: iload         7
     180: iload         4
     182: imul
     183: iadd
     184: istore        16
     186: aload_0
     187: iload         16
     189: invokevirtual #144                // Method b:(I)Landroid/view/View;
     192: astore        22
     194: aload         22
     196: ifnonnull     211
     199: iload_1
     200: aload_0
     201: iload         16
     203: invokevirtual #178                // Method d:(I)I
     206: iadd
     207: istore_1
     208: goto          532
     211: aload         22
     213: invokevirtual #147                // Method android/view/View.getVisibility:()I
     216: bipush        8
     218: if_icmpeq     529
     221: aload         22
     223: invokevirtual #165                // Method android/view/View.getMeasuredWidth:()I
     226: istore        15
     228: aload         22
     230: invokevirtual #160                // Method android/view/View.getMeasuredHeight:()I
     233: istore        17
     235: aload         22
     237: invokevirtual #151                // Method android/view/View.getLayoutParams:()Landroid/view/ViewGroup$LayoutParams;
     240: checkcast     #6                  // class android/support/v7/widget/av$a
     243: astore        23
     245: iload         19
     247: ifeq          269
     250: aload         23
     252: getfield      #157                // Field android/support/v7/widget/av$a.height:I
     255: iconst_m1
     256: if_icmpeq     269
     259: aload         22
     261: invokevirtual #318                // Method android/view/View.getBaseline:()I
     264: istore        9
     266: goto          272
     269: iconst_m1
     270: istore        9
     272: aload         23
     274: getfield      #258                // Field android/support/v7/widget/av$a.h:I
     277: istore        11
     279: iload         11
     281: istore        5
     283: iload         11
     285: ifge          291
     288: iload_2
     289: istore        5
     291: iload         5
     293: bipush        112
     295: iand
     296: istore        5
     298: iload         5
     300: bipush        16
     302: if_icmpeq     409
     305: iload         5
     307: bipush        48
     309: if_icmpeq     376
     312: iload         5
     314: bipush        80
     316: if_icmpeq     325
     319: iload_3
     320: istore        5
     322: goto          438
     325: iload         12
     327: iload         13
     329: isub
     330: iload         17
     332: isub
     333: aload         23
     335: getfield      #192                // Field android/support/v7/widget/av$a.bottomMargin:I
     338: isub
     339: istore        11
     341: iload         11
     343: istore        5
     345: iload         9
     347: iconst_m1
     348: if_icmpeq     373
     351: aload         22
     353: invokevirtual #160                // Method android/view/View.getMeasuredHeight:()I
     356: istore        5
     358: iload         11
     360: aload         21
     362: iconst_2
     363: iaload
     364: iload         5
     366: iload         9
     368: isub
     369: isub
     370: isub
     371: istore        5
     373: goto          322
     376: aload         23
     378: getfield      #189                // Field android/support/v7/widget/av$a.topMargin:I
     381: iload_3
     382: iadd
     383: istore        5
     385: iload         9
     387: iconst_m1
     388: if_icmpeq     406
     391: iload         5
     393: aload         20
     395: iconst_1
     396: iaload
     397: iload         9
     399: isub
     400: iadd
     401: istore        5
     403: goto          406
     406: goto          438
     409: iload         12
     411: iload         10
     413: isub
     414: iload         14
     416: isub
     417: iload         17
     419: isub
     420: iconst_2
     421: idiv
     422: iload_3
     423: iadd
     424: aload         23
     426: getfield      #189                // Field android/support/v7/widget/av$a.topMargin:I
     429: iadd
     430: aload         23
     432: getfield      #192                // Field android/support/v7/widget/av$a.bottomMargin:I
     435: isub
     436: istore        5
     438: iload_1
     439: istore        9
     441: aload_0
     442: iload         16
     444: invokevirtual #183                // Method c:(I)Z
     447: ifeq          458
     450: iload_1
     451: aload_0
     452: getfield      #315                // Field l:I
     455: iadd
     456: istore        9
     458: aload         23
     460: getfield      #213                // Field android/support/v7/widget/av$a.leftMargin:I
     463: iload         9
     465: iadd
     466: istore_1
     467: aload_0
     468: aload         22
     470: iload_1
     471: aload_0
     472: aload         22
     474: invokevirtual #268                // Method a:(Landroid/view/View;)I
     477: iadd
     478: iload         5
     480: iload         15
     482: iload         17
     484: invokespecial #270                // Method a:(Landroid/view/View;IIII)V
     487: aload         23
     489: getfield      #216                // Field android/support/v7/widget/av$a.rightMargin:I
     492: istore        5
     494: aload_0
     495: aload         22
     497: invokevirtual #203                // Method b:(Landroid/view/View;)I
     500: istore        9
     502: iload         4
     504: aload_0
     505: aload         22
     507: iload         16
     509: invokevirtual #180                // Method a:(Landroid/view/View;I)I
     512: iadd
     513: istore        4
     515: iload_1
     516: iload         15
     518: iload         5
     520: iadd
     521: iload         9
     523: iadd
     524: iadd
     525: istore_1
     526: goto          532
     529: goto          208
     532: iload         4
     534: iconst_1
     535: iadd
     536: istore        4
     538: goto          169
     541: return

  void b(android.graphics.Canvas);
    Code:
       0: aload_0
       1: invokevirtual #172                // Method getVirtualChildCount:()I
       4: istore        4
       6: aload_0
       7: invokestatic  #326                // Method android/support/v7/widget/bx.a:(Landroid/view/View;)Z
      10: istore        5
      12: iconst_0
      13: istore_2
      14: iload_2
      15: iload         4
      17: if_icmpge     110
      20: aload_0
      21: iload_2
      22: invokevirtual #144                // Method b:(I)Landroid/view/View;
      25: astore        6
      27: aload         6
      29: ifnull        103
      32: aload         6
      34: invokevirtual #147                // Method android/view/View.getVisibility:()I
      37: bipush        8
      39: if_icmpeq     103
      42: aload_0
      43: iload_2
      44: invokevirtual #183                // Method c:(I)Z
      47: ifeq          103
      50: aload         6
      52: invokevirtual #151                // Method android/view/View.getLayoutParams:()Landroid/view/ViewGroup$LayoutParams;
      55: checkcast     #6                  // class android/support/v7/widget/av$a
      58: astore        7
      60: iload         5
      62: ifeq          80
      65: aload         6
      67: invokevirtual #329                // Method android/view/View.getRight:()I
      70: aload         7
      72: getfield      #216                // Field android/support/v7/widget/av$a.rightMargin:I
      75: iadd
      76: istore_3
      77: goto          97
      80: aload         6
      82: invokevirtual #332                // Method android/view/View.getLeft:()I
      85: aload         7
      87: getfield      #213                // Field android/support/v7/widget/av$a.leftMargin:I
      90: isub
      91: aload_0
      92: getfield      #315                // Field l:I
      95: isub
      96: istore_3
      97: aload_0
      98: aload_1
      99: iload_3
     100: invokevirtual #334                // Method b:(Landroid/graphics/Canvas;I)V
     103: iload_2
     104: iconst_1
     105: iadd
     106: istore_2
     107: goto          14
     110: aload_0
     111: iload         4
     113: invokevirtual #183                // Method c:(I)Z
     116: ifeq          217
     119: aload_0
     120: iload         4
     122: iconst_1
     123: isub
     124: invokevirtual #144                // Method b:(I)Landroid/view/View;
     127: astore        6
     129: aload         6
     131: ifnonnull     169
     134: iload         5
     136: ifeq          147
     139: aload_0
     140: invokevirtual #242                // Method getPaddingLeft:()I
     143: istore_2
     144: goto          211
     147: aload_0
     148: invokevirtual #288                // Method getWidth:()I
     151: istore_2
     152: aload_0
     153: invokevirtual #245                // Method getPaddingRight:()I
     156: istore_3
     157: iload_2
     158: iload_3
     159: isub
     160: aload_0
     161: getfield      #315                // Field l:I
     164: isub
     165: istore_2
     166: goto          211
     169: aload         6
     171: invokevirtual #151                // Method android/view/View.getLayoutParams:()Landroid/view/ViewGroup$LayoutParams;
     174: checkcast     #6                  // class android/support/v7/widget/av$a
     177: astore        7
     179: iload         5
     181: ifeq          199
     184: aload         6
     186: invokevirtual #332                // Method android/view/View.getLeft:()I
     189: istore_2
     190: aload         7
     192: getfield      #213                // Field android/support/v7/widget/av$a.leftMargin:I
     195: istore_3
     196: goto          157
     199: aload         6
     201: invokevirtual #329                // Method android/view/View.getRight:()I
     204: aload         7
     206: getfield      #216                // Field android/support/v7/widget/av$a.rightMargin:I
     209: iadd
     210: istore_2
     211: aload_0
     212: aload_1
     213: iload_2
     214: invokevirtual #334                // Method b:(Landroid/graphics/Canvas;I)V
     217: return

  void b(android.graphics.Canvas, int);
    Code:
       0: aload_0
       1: getfield      #285                // Field k:Landroid/graphics/drawable/Drawable;
       4: iload_2
       5: aload_0
       6: invokevirtual #225                // Method getPaddingTop:()I
       9: aload_0
      10: getfield      #120                // Field o:I
      13: iadd
      14: aload_0
      15: getfield      #315                // Field l:I
      18: iload_2
      19: iadd
      20: aload_0
      21: invokevirtual #280                // Method getHeight:()I
      24: aload_0
      25: invokevirtual #228                // Method getPaddingBottom:()I
      28: isub
      29: aload_0
      30: getfield      #120                // Field o:I
      33: isub
      34: invokevirtual #293                // Method android/graphics/drawable/Drawable.setBounds:(IIII)V
      37: aload_0
      38: getfield      #285                // Field k:Landroid/graphics/drawable/Drawable;
      41: aload_1
      42: invokevirtual #296                // Method android/graphics/drawable/Drawable.draw:(Landroid/graphics/Canvas;)V
      45: return

  protected boolean c(int);
    Code:
       0: iconst_0
       1: istore_3
       2: iconst_0
       3: istore_2
       4: iload_1
       5: ifne          21
       8: aload_0
       9: getfield      #113                // Field n:I
      12: iconst_1
      13: iand
      14: ifeq          19
      17: iconst_1
      18: istore_2
      19: iload_2
      20: ireturn
      21: iload_1
      22: aload_0
      23: invokevirtual #337                // Method getChildCount:()I
      26: if_icmpne     44
      29: iload_3
      30: istore_2
      31: aload_0
      32: getfield      #113                // Field n:I
      35: iconst_4
      36: iand
      37: ifeq          42
      40: iconst_1
      41: istore_2
      42: iload_2
      43: ireturn
      44: aload_0
      45: getfield      #113                // Field n:I
      48: iconst_2
      49: iand
      50: ifeq          83
      53: iload_1
      54: iconst_1
      55: isub
      56: istore_1
      57: iload_1
      58: iflt          83
      61: aload_0
      62: iload_1
      63: invokevirtual #309                // Method getChildAt:(I)Landroid/view/View;
      66: invokevirtual #147                // Method android/view/View.getVisibility:()I
      69: bipush        8
      71: if_icmpeq     76
      74: iconst_1
      75: ireturn
      76: iload_1
      77: iconst_1
      78: isub
      79: istore_1
      80: goto          57
      83: iconst_0
      84: ireturn

  protected boolean checkLayoutParams(android.view.ViewGroup$LayoutParams);
    Code:
       0: aload_1
       1: instanceof    #6                  // class android/support/v7/widget/av$a
       4: ireturn

  int d(int);
    Code:
       0: iconst_0
       1: ireturn

  protected android.view.ViewGroup$LayoutParams generateDefaultLayoutParams();
    Code:
       0: aload_0
       1: invokevirtual #343                // Method j:()Landroid/support/v7/widget/av$a;
       4: areturn

  public android.view.ViewGroup$LayoutParams generateLayoutParams(android.util.AttributeSet);
    Code:
       0: aload_0
       1: aload_1
       2: invokevirtual #347                // Method b:(Landroid/util/AttributeSet;)Landroid/support/v7/widget/av$a;
       5: areturn

  protected android.view.ViewGroup$LayoutParams generateLayoutParams(android.view.ViewGroup$LayoutParams);
    Code:
       0: aload_0
       1: aload_1
       2: invokevirtual #350                // Method b:(Landroid/view/ViewGroup$LayoutParams;)Landroid/support/v7/widget/av$a;
       5: areturn

  public int getBaseline();
    Code:
       0: aload_0
       1: getfield      #40                 // Field b:I
       4: ifge          12
       7: aload_0
       8: invokespecial #351                // Method android/view/ViewGroup.getBaseline:()I
      11: ireturn
      12: aload_0
      13: invokevirtual #337                // Method getChildCount:()I
      16: aload_0
      17: getfield      #40                 // Field b:I
      20: if_icmpgt     34
      23: new           #205                // class java/lang/RuntimeException
      26: dup
      27: ldc_w         #353                // String mBaselineAlignedChildIndex of LinearLayout set to an index that is out of bounds.
      30: invokespecial #210                // Method java/lang/RuntimeException."<init>":(Ljava/lang/String;)V
      33: athrow
      34: aload_0
      35: aload_0
      36: getfield      #40                 // Field b:I
      39: invokevirtual #309                // Method getChildAt:(I)Landroid/view/View;
      42: astore        5
      44: aload         5
      46: invokevirtual #318                // Method android/view/View.getBaseline:()I
      49: istore_3
      50: iload_3
      51: iconst_m1
      52: if_icmpne     75
      55: aload_0
      56: getfield      #40                 // Field b:I
      59: ifne          64
      62: iconst_m1
      63: ireturn
      64: new           #205                // class java/lang/RuntimeException
      67: dup
      68: ldc_w         #355                // String mBaselineAlignedChildIndex of LinearLayout points to a View that doesn't know how to get its baseline.
      71: invokespecial #210                // Method java/lang/RuntimeException."<init>":(Ljava/lang/String;)V
      74: athrow
      75: aload_0
      76: getfield      #42                 // Field c:I
      79: istore_2
      80: iload_2
      81: istore_1
      82: aload_0
      83: getfield      #357                // Field d:I
      86: iconst_1
      87: if_icmpne     179
      90: aload_0
      91: getfield      #45                 // Field e:I
      94: bipush        112
      96: iand
      97: istore        4
      99: iload_2
     100: istore_1
     101: iload         4
     103: bipush        48
     105: if_icmpeq     179
     108: iload         4
     110: bipush        16
     112: if_icmpeq     150
     115: iload         4
     117: bipush        80
     119: if_icmpeq     127
     122: iload_2
     123: istore_1
     124: goto          179
     127: aload_0
     128: invokevirtual #358                // Method getBottom:()I
     131: aload_0
     132: invokevirtual #359                // Method getTop:()I
     135: isub
     136: aload_0
     137: invokevirtual #228                // Method getPaddingBottom:()I
     140: isub
     141: aload_0
     142: getfield      #169                // Field f:I
     145: isub
     146: istore_1
     147: goto          179
     150: iload_2
     151: aload_0
     152: invokevirtual #358                // Method getBottom:()I
     155: aload_0
     156: invokevirtual #359                // Method getTop:()I
     159: isub
     160: aload_0
     161: invokevirtual #225                // Method getPaddingTop:()I
     164: isub
     165: aload_0
     166: invokevirtual #228                // Method getPaddingBottom:()I
     169: isub
     170: aload_0
     171: getfield      #169                // Field f:I
     174: isub
     175: iconst_2
     176: idiv
     177: iadd
     178: istore_1
     179: iload_1
     180: aload         5
     182: invokevirtual #151                // Method android/view/View.getLayoutParams:()Landroid/view/ViewGroup$LayoutParams;
     185: checkcast     #6                  // class android/support/v7/widget/av$a
     188: getfield      #189                // Field android/support/v7/widget/av$a.topMargin:I
     191: iadd
     192: iload_3
     193: iadd
     194: ireturn

  public int getBaselineAlignedChildIndex();
    Code:
       0: aload_0
       1: getfield      #40                 // Field b:I
       4: ireturn

  public android.graphics.drawable.Drawable getDividerDrawable();
    Code:
       0: aload_0
       1: getfield      #285                // Field k:Landroid/graphics/drawable/Drawable;
       4: areturn

  public int getDividerPadding();
    Code:
       0: aload_0
       1: getfield      #120                // Field o:I
       4: ireturn

  public int getDividerWidth();
    Code:
       0: aload_0
       1: getfield      #315                // Field l:I
       4: ireturn

  public int getGravity();
    Code:
       0: aload_0
       1: getfield      #45                 // Field e:I
       4: ireturn

  public int getOrientation();
    Code:
       0: aload_0
       1: getfield      #357                // Field d:I
       4: ireturn

  public int getShowDividers();
    Code:
       0: aload_0
       1: getfield      #113                // Field n:I
       4: ireturn

  int getVirtualChildCount();
    Code:
       0: aload_0
       1: invokevirtual #337                // Method getChildCount:()I
       4: ireturn

  public float getWeightSum();
    Code:
       0: aload_0
       1: getfield      #90                 // Field g:F
       4: freturn

  protected android.support.v7.widget.av$a j();
    Code:
       0: aload_0
       1: getfield      #357                // Field d:I
       4: ifne          19
       7: new           #6                  // class android/support/v7/widget/av$a
      10: dup
      11: bipush        -2
      13: bipush        -2
      15: invokespecial #371                // Method android/support/v7/widget/av$a."<init>":(II)V
      18: areturn
      19: aload_0
      20: getfield      #357                // Field d:I
      23: iconst_1
      24: if_icmpne     38
      27: new           #6                  // class android/support/v7/widget/av$a
      30: dup
      31: iconst_m1
      32: bipush        -2
      34: invokespecial #371                // Method android/support/v7/widget/av$a."<init>":(II)V
      37: areturn
      38: aconst_null
      39: areturn

  protected void onDraw(android.graphics.Canvas);
    Code:
       0: aload_0
       1: getfield      #285                // Field k:Landroid/graphics/drawable/Drawable;
       4: ifnonnull     8
       7: return
       8: aload_0
       9: getfield      #357                // Field d:I
      12: iconst_1
      13: if_icmpne     22
      16: aload_0
      17: aload_1
      18: invokevirtual #374                // Method a:(Landroid/graphics/Canvas;)V
      21: return
      22: aload_0
      23: aload_1
      24: invokevirtual #376                // Method b:(Landroid/graphics/Canvas;)V
      27: return

  public void onInitializeAccessibilityEvent(android.view.accessibility.AccessibilityEvent);
    Code:
       0: aload_0
       1: aload_1
       2: invokespecial #380                // Method android/view/ViewGroup.onInitializeAccessibilityEvent:(Landroid/view/accessibility/AccessibilityEvent;)V
       5: aload_1
       6: ldc           #2                  // class android/support/v7/widget/av
       8: invokevirtual #386                // Method java/lang/Class.getName:()Ljava/lang/String;
      11: invokevirtual #392                // Method android/view/accessibility/AccessibilityEvent.setClassName:(Ljava/lang/CharSequence;)V
      14: return

  public void onInitializeAccessibilityNodeInfo(android.view.accessibility.AccessibilityNodeInfo);
    Code:
       0: aload_0
       1: aload_1
       2: invokespecial #396                // Method android/view/ViewGroup.onInitializeAccessibilityNodeInfo:(Landroid/view/accessibility/AccessibilityNodeInfo;)V
       5: aload_1
       6: ldc           #2                  // class android/support/v7/widget/av
       8: invokevirtual #386                // Method java/lang/Class.getName:()Ljava/lang/String;
      11: invokevirtual #399                // Method android/view/accessibility/AccessibilityNodeInfo.setClassName:(Ljava/lang/CharSequence;)V
      14: return

  protected void onLayout(boolean, int, int, int, int);
    Code:
       0: aload_0
       1: getfield      #357                // Field d:I
       4: iconst_1
       5: if_icmpne     19
       8: aload_0
       9: iload_2
      10: iload_3
      11: iload         4
      13: iload         5
      15: invokevirtual #403                // Method a:(IIII)V
      18: return
      19: aload_0
      20: iload_2
      21: iload_3
      22: iload         4
      24: iload         5
      26: invokevirtual #405                // Method b:(IIII)V
      29: return

  protected void onMeasure(int, int);
    Code:
       0: aload_0
       1: getfield      #357                // Field d:I
       4: iconst_1
       5: if_icmpne     15
       8: aload_0
       9: iload_1
      10: iload_2
      11: invokevirtual #408                // Method a:(II)V
      14: return
      15: aload_0
      16: iload_1
      17: iload_2
      18: invokevirtual #410                // Method b:(II)V
      21: return

  public void setBaselineAligned(boolean);
    Code:
       0: aload_0
       1: iload_1
       2: putfield      #38                 // Field a:Z
       5: return

  public void setBaselineAlignedChildIndex(int);
    Code:
       0: iload_1
       1: iflt          21
       4: iload_1
       5: aload_0
       6: invokevirtual #337                // Method getChildCount:()I
       9: if_icmplt     15
      12: goto          21
      15: aload_0
      16: iload_1
      17: putfield      #40                 // Field b:I
      20: return
      21: new           #413                // class java/lang/StringBuilder
      24: dup
      25: invokespecial #415                // Method java/lang/StringBuilder."<init>":()V
      28: astore_2
      29: aload_2
      30: ldc_w         #417                // String base aligned child index out of range (0,
      33: invokevirtual #421                // Method java/lang/StringBuilder.append:(Ljava/lang/String;)Ljava/lang/StringBuilder;
      36: pop
      37: aload_2
      38: aload_0
      39: invokevirtual #337                // Method getChildCount:()I
      42: invokevirtual #424                // Method java/lang/StringBuilder.append:(I)Ljava/lang/StringBuilder;
      45: pop
      46: aload_2
      47: ldc_w         #426                // String )
      50: invokevirtual #421                // Method java/lang/StringBuilder.append:(Ljava/lang/String;)Ljava/lang/StringBuilder;
      53: pop
      54: new           #428                // class java/lang/IllegalArgumentException
      57: dup
      58: aload_2
      59: invokevirtual #431                // Method java/lang/StringBuilder.toString:()Ljava/lang/String;
      62: invokespecial #432                // Method java/lang/IllegalArgumentException."<init>":(Ljava/lang/String;)V
      65: athrow

  public void setDividerDrawable(android.graphics.drawable.Drawable);
    Code:
       0: aload_1
       1: aload_0
       2: getfield      #285                // Field k:Landroid/graphics/drawable/Drawable;
       5: if_acmpne     9
       8: return
       9: aload_0
      10: aload_1
      11: putfield      #285                // Field k:Landroid/graphics/drawable/Drawable;
      14: iconst_0
      15: istore_2
      16: aload_1
      17: ifnull        39
      20: aload_0
      21: aload_1
      22: invokevirtual #435                // Method android/graphics/drawable/Drawable.getIntrinsicWidth:()I
      25: putfield      #315                // Field l:I
      28: aload_0
      29: aload_1
      30: invokevirtual #438                // Method android/graphics/drawable/Drawable.getIntrinsicHeight:()I
      33: putfield      #185                // Field m:I
      36: goto          49
      39: aload_0
      40: iconst_0
      41: putfield      #315                // Field l:I
      44: aload_0
      45: iconst_0
      46: putfield      #185                // Field m:I
      49: aload_1
      50: ifnonnull     55
      53: iconst_1
      54: istore_2
      55: aload_0
      56: iload_2
      57: invokevirtual #441                // Method setWillNotDraw:(Z)V
      60: aload_0
      61: invokevirtual #444                // Method requestLayout:()V
      64: return

  public void setDividerPadding(int);
    Code:
       0: aload_0
       1: iload_1
       2: putfield      #120                // Field o:I
       5: return

  public void setGravity(int);
    Code:
       0: aload_0
       1: getfield      #45                 // Field e:I
       4: iload_1
       5: if_icmpeq     47
       8: iload_1
       9: istore_2
      10: ldc_w         #259                // int 8388615
      13: iload_1
      14: iand
      15: ifne          24
      18: iload_1
      19: ldc_w         #446                // int 8388611
      22: ior
      23: istore_2
      24: iload_2
      25: istore_1
      26: iload_2
      27: bipush        112
      29: iand
      30: ifne          38
      33: iload_2
      34: bipush        48
      36: ior
      37: istore_1
      38: aload_0
      39: iload_1
      40: putfield      #45                 // Field e:I
      43: aload_0
      44: invokevirtual #444                // Method requestLayout:()V
      47: return

  public void setHorizontalGravity(int);
    Code:
       0: iload_1
       1: ldc_w         #259                // int 8388615
       4: iand
       5: istore_1
       6: ldc_w         #259                // int 8388615
       9: aload_0
      10: getfield      #45                 // Field e:I
      13: iand
      14: iload_1
      15: if_icmpeq     36
      18: aload_0
      19: iload_1
      20: aload_0
      21: getfield      #45                 // Field e:I
      24: ldc_w         #448                // int -8388616
      27: iand
      28: ior
      29: putfield      #45                 // Field e:I
      32: aload_0
      33: invokevirtual #444                // Method requestLayout:()V
      36: return

  public void setMeasureWithLargestChildEnabled(boolean);
    Code:
       0: aload_0
       1: iload_1
       2: putfield      #98                 // Field h:Z
       5: return

  public void setOrientation(int);
    Code:
       0: aload_0
       1: getfield      #357                // Field d:I
       4: iload_1
       5: if_icmpeq     17
       8: aload_0
       9: iload_1
      10: putfield      #357                // Field d:I
      13: aload_0
      14: invokevirtual #444                // Method requestLayout:()V
      17: return

  public void setShowDividers(int);
    Code:
       0: iload_1
       1: aload_0
       2: getfield      #113                // Field n:I
       5: if_icmpeq     12
       8: aload_0
       9: invokevirtual #444                // Method requestLayout:()V
      12: aload_0
      13: iload_1
      14: putfield      #113                // Field n:I
      17: return

  public void setVerticalGravity(int);
    Code:
       0: iload_1
       1: bipush        112
       3: iand
       4: istore_1
       5: aload_0
       6: getfield      #45                 // Field e:I
       9: bipush        112
      11: iand
      12: iload_1
      13: if_icmpeq     33
      16: aload_0
      17: iload_1
      18: aload_0
      19: getfield      #45                 // Field e:I
      22: bipush        -113
      24: iand
      25: ior
      26: putfield      #45                 // Field e:I
      29: aload_0
      30: invokevirtual #444                // Method requestLayout:()V
      33: return

  public void setWeightSum(float);
    Code:
       0: aload_0
       1: fconst_0
       2: fload_1
       3: invokestatic  #456                // Method java/lang/Math.max:(FF)F
       6: putfield      #90                 // Field g:F
       9: return

  public boolean shouldDelayChildPressedState();
    Code:
       0: iconst_0
       1: ireturn
}
