class android.support.v7.widget.aw$e implements java.lang.Runnable {
  final android.support.v7.widget.aw a;

  android.support.v7.widget.aw$e(android.support.v7.widget.aw);
    Code:
       0: aload_0
       1: aload_1
       2: putfield      #15                 // Field a:Landroid/support/v7/widget/aw;
       5: aload_0
       6: invokespecial #18                 // Method java/lang/Object."<init>":()V
       9: return

  public void run();
    Code:
       0: aload_0
       1: getfield      #15                 // Field a:Landroid/support/v7/widget/aw;
       4: getfield      #24                 // Field android/support/v7/widget/aw.c:Landroid/support/v7/widget/ap;
       7: ifnull        84
      10: aload_0
      11: getfield      #15                 // Field a:Landroid/support/v7/widget/aw;
      14: getfield      #24                 // Field android/support/v7/widget/aw.c:Landroid/support/v7/widget/ap;
      17: invokestatic  #30                 // Method android/support/v4/view/s.z:(Landroid/view/View;)Z
      20: ifeq          84
      23: aload_0
      24: getfield      #15                 // Field a:Landroid/support/v7/widget/aw;
      27: getfield      #24                 // Field android/support/v7/widget/aw.c:Landroid/support/v7/widget/ap;
      30: invokevirtual #36                 // Method android/support/v7/widget/ap.getCount:()I
      33: aload_0
      34: getfield      #15                 // Field a:Landroid/support/v7/widget/aw;
      37: getfield      #24                 // Field android/support/v7/widget/aw.c:Landroid/support/v7/widget/ap;
      40: invokevirtual #39                 // Method android/support/v7/widget/ap.getChildCount:()I
      43: if_icmple     84
      46: aload_0
      47: getfield      #15                 // Field a:Landroid/support/v7/widget/aw;
      50: getfield      #24                 // Field android/support/v7/widget/aw.c:Landroid/support/v7/widget/ap;
      53: invokevirtual #39                 // Method android/support/v7/widget/ap.getChildCount:()I
      56: aload_0
      57: getfield      #15                 // Field a:Landroid/support/v7/widget/aw;
      60: getfield      #43                 // Field android/support/v7/widget/aw.d:I
      63: if_icmpgt     84
      66: aload_0
      67: getfield      #15                 // Field a:Landroid/support/v7/widget/aw;
      70: getfield      #47                 // Field android/support/v7/widget/aw.g:Landroid/widget/PopupWindow;
      73: iconst_2
      74: invokevirtual #53                 // Method android/widget/PopupWindow.setInputMethodMode:(I)V
      77: aload_0
      78: getfield      #15                 // Field a:Landroid/support/v7/widget/aw;
      81: invokevirtual #55                 // Method android/support/v7/widget/aw.d:()V
      84: return
}
