public class android.support.v7.widget.aw implements android.support.v7.view.menu.s {
  android.support.v7.widget.ap c;

  int d;

  final android.support.v7.widget.aw$e e;

  final android.os.Handler f;

  android.widget.PopupWindow g;

  static {};
    Code:
       0: ldc           #80                 // class android/widget/PopupWindow
       2: ldc           #82                 // String setClipToScreenEnabled
       4: iconst_1
       5: anewarray     #84                 // class java/lang/Class
       8: dup
       9: iconst_0
      10: getstatic     #90                 // Field java/lang/Boolean.TYPE:Ljava/lang/Class;
      13: aastore
      14: invokevirtual #94                 // Method java/lang/Class.getDeclaredMethod:(Ljava/lang/String;[Ljava/lang/Class;)Ljava/lang/reflect/Method;
      17: putstatic     #96                 // Field a:Ljava/lang/reflect/Method;
      20: goto          31
      23: ldc           #98                 // String ListPopupWindow
      25: ldc           #100                // String Could not find method setClipToScreenEnabled() on PopupWindow. Oh well.
      27: invokestatic  #105                // Method android/util/Log.i:(Ljava/lang/String;Ljava/lang/String;)I
      30: pop
      31: ldc           #80                 // class android/widget/PopupWindow
      33: ldc           #107                // String getMaxAvailableHeight
      35: iconst_3
      36: anewarray     #84                 // class java/lang/Class
      39: dup
      40: iconst_0
      41: ldc           #109                // class android/view/View
      43: aastore
      44: dup
      45: iconst_1
      46: getstatic     #112                // Field java/lang/Integer.TYPE:Ljava/lang/Class;
      49: aastore
      50: dup
      51: iconst_2
      52: getstatic     #90                 // Field java/lang/Boolean.TYPE:Ljava/lang/Class;
      55: aastore
      56: invokevirtual #94                 // Method java/lang/Class.getDeclaredMethod:(Ljava/lang/String;[Ljava/lang/Class;)Ljava/lang/reflect/Method;
      59: putstatic     #114                // Field b:Ljava/lang/reflect/Method;
      62: goto          73
      65: ldc           #98                 // String ListPopupWindow
      67: ldc           #116                // String Could not find method getMaxAvailableHeight(View, int, boolean) on PopupWindow. Oh well.
      69: invokestatic  #105                // Method android/util/Log.i:(Ljava/lang/String;Ljava/lang/String;)I
      72: pop
      73: ldc           #80                 // class android/widget/PopupWindow
      75: ldc           #118                // String setEpicenterBounds
      77: iconst_1
      78: anewarray     #84                 // class java/lang/Class
      81: dup
      82: iconst_0
      83: ldc           #120                // class android/graphics/Rect
      85: aastore
      86: invokevirtual #94                 // Method java/lang/Class.getDeclaredMethod:(Ljava/lang/String;[Ljava/lang/Class;)Ljava/lang/reflect/Method;
      89: putstatic     #122                // Field h:Ljava/lang/reflect/Method;
      92: return
      93: ldc           #98                 // String ListPopupWindow
      95: ldc           #124                // String Could not find method setEpicenterBounds(Rect) on PopupWindow. Oh well.
      97: invokestatic  #105                // Method android/util/Log.i:(Ljava/lang/String;Ljava/lang/String;)I
     100: pop
     101: return
     102: astore_0
     103: goto          23
     106: astore_0
     107: goto          65
     110: astore_0
     111: goto          93
    Exception table:
       from    to  target type
           0    20   102   Class java/lang/NoSuchMethodException
          31    62   106   Class java/lang/NoSuchMethodException
          73    92   110   Class java/lang/NoSuchMethodException

  public android.support.v7.widget.aw(android.content.Context);
    Code:
       0: aload_0
       1: aload_1
       2: aconst_null
       3: getstatic     #132                // Field android/support/v7/a/a$a.listPopupWindowStyle:I
       6: invokespecial #135                // Method "<init>":(Landroid/content/Context;Landroid/util/AttributeSet;I)V
       9: return

  public android.support.v7.widget.aw(android.content.Context, android.util.AttributeSet, int);
    Code:
       0: aload_0
       1: aload_1
       2: aload_2
       3: iload_3
       4: iconst_0
       5: invokespecial #138                // Method "<init>":(Landroid/content/Context;Landroid/util/AttributeSet;II)V
       8: return

  public android.support.v7.widget.aw(android.content.Context, android.util.AttributeSet, int, int);
    Code:
       0: aload_0
       1: invokespecial #140                // Method java/lang/Object."<init>":()V
       4: aload_0
       5: bipush        -2
       7: putfield      #142                // Field k:I
      10: aload_0
      11: bipush        -2
      13: putfield      #144                // Field l:I
      16: aload_0
      17: sipush        1002
      20: putfield      #146                // Field o:I
      23: aload_0
      24: iconst_1
      25: putfield      #148                // Field q:Z
      28: aload_0
      29: iconst_0
      30: putfield      #150                // Field t:I
      33: aload_0
      34: iconst_0
      35: putfield      #152                // Field u:Z
      38: aload_0
      39: iconst_0
      40: putfield      #154                // Field v:Z
      43: aload_0
      44: ldc           #155                // int 2147483647
      46: putfield      #157                // Field d:I
      49: aload_0
      50: iconst_0
      51: putfield      #159                // Field x:I
      54: aload_0
      55: new           #24                 // class android/support/v7/widget/aw$e
      58: dup
      59: aload_0
      60: invokespecial #162                // Method android/support/v7/widget/aw$e."<init>":(Landroid/support/v7/widget/aw;)V
      63: putfield      #164                // Field e:Landroid/support/v7/widget/aw$e;
      66: aload_0
      67: new           #21                 // class android/support/v7/widget/aw$d
      70: dup
      71: aload_0
      72: invokespecial #165                // Method android/support/v7/widget/aw$d."<init>":(Landroid/support/v7/widget/aw;)V
      75: putfield      #167                // Field D:Landroid/support/v7/widget/aw$d;
      78: aload_0
      79: new           #18                 // class android/support/v7/widget/aw$c
      82: dup
      83: aload_0
      84: invokespecial #168                // Method android/support/v7/widget/aw$c."<init>":(Landroid/support/v7/widget/aw;)V
      87: putfield      #170                // Field E:Landroid/support/v7/widget/aw$c;
      90: aload_0
      91: new           #12                 // class android/support/v7/widget/aw$a
      94: dup
      95: aload_0
      96: invokespecial #171                // Method android/support/v7/widget/aw$a."<init>":(Landroid/support/v7/widget/aw;)V
      99: putfield      #173                // Field F:Landroid/support/v7/widget/aw$a;
     102: aload_0
     103: new           #120                // class android/graphics/Rect
     106: dup
     107: invokespecial #174                // Method android/graphics/Rect."<init>":()V
     110: putfield      #176                // Field H:Landroid/graphics/Rect;
     113: aload_0
     114: aload_1
     115: putfield      #178                // Field i:Landroid/content/Context;
     118: aload_0
     119: new           #180                // class android/os/Handler
     122: dup
     123: aload_1
     124: invokevirtual #186                // Method android/content/Context.getMainLooper:()Landroid/os/Looper;
     127: invokespecial #189                // Method android/os/Handler."<init>":(Landroid/os/Looper;)V
     130: putfield      #191                // Field f:Landroid/os/Handler;
     133: aload_1
     134: aload_2
     135: getstatic     #196                // Field android/support/v7/a/a$j.ListPopupWindow:[I
     138: iload_3
     139: iload         4
     141: invokevirtual #200                // Method android/content/Context.obtainStyledAttributes:(Landroid/util/AttributeSet;[III)Landroid/content/res/TypedArray;
     144: astore        5
     146: aload_0
     147: aload         5
     149: getstatic     #203                // Field android/support/v7/a/a$j.ListPopupWindow_android_dropDownHorizontalOffset:I
     152: iconst_0
     153: invokevirtual #209                // Method android/content/res/TypedArray.getDimensionPixelOffset:(II)I
     156: putfield      #211                // Field m:I
     159: aload_0
     160: aload         5
     162: getstatic     #214                // Field android/support/v7/a/a$j.ListPopupWindow_android_dropDownVerticalOffset:I
     165: iconst_0
     166: invokevirtual #209                // Method android/content/res/TypedArray.getDimensionPixelOffset:(II)I
     169: putfield      #216                // Field n:I
     172: aload_0
     173: getfield      #216                // Field n:I
     176: ifeq          184
     179: aload_0
     180: iconst_1
     181: putfield      #218                // Field p:Z
     184: aload         5
     186: invokevirtual #221                // Method android/content/res/TypedArray.recycle:()V
     189: aload_0
     190: new           #223                // class android/support/v7/widget/t
     193: dup
     194: aload_1
     195: aload_2
     196: iload_3
     197: iload         4
     199: invokespecial #224                // Method android/support/v7/widget/t."<init>":(Landroid/content/Context;Landroid/util/AttributeSet;II)V
     202: putfield      #226                // Field g:Landroid/widget/PopupWindow;
     205: aload_0
     206: getfield      #226                // Field g:Landroid/widget/PopupWindow;
     209: iconst_1
     210: invokevirtual #230                // Method android/widget/PopupWindow.setInputMethodMode:(I)V
     213: return

  android.support.v7.widget.ap a(android.content.Context, boolean);
    Code:
       0: new           #281                // class android/support/v7/widget/ap
       3: dup
       4: aload_1
       5: iload_2
       6: invokespecial #443                // Method android/support/v7/widget/ap."<init>":(Landroid/content/Context;Z)V
       9: areturn

  public void a(int);
    Code:
       0: aload_0
       1: iload_1
       2: putfield      #159                // Field x:I
       5: return

  public void a(android.graphics.Rect);
    Code:
       0: aload_0
       1: aload_1
       2: putfield      #446                // Field I:Landroid/graphics/Rect;
       5: return

  public void a(android.graphics.drawable.Drawable);
    Code:
       0: aload_0
       1: getfield      #226                // Field g:Landroid/widget/PopupWindow;
       4: aload_1
       5: invokevirtual #449                // Method android/widget/PopupWindow.setBackgroundDrawable:(Landroid/graphics/drawable/Drawable;)V
       8: return

  public void a(android.widget.AdapterView$OnItemClickListener);
    Code:
       0: aload_0
       1: aload_1
       2: putfield      #293                // Field B:Landroid/widget/AdapterView$OnItemClickListener;
       5: return

  public void a(android.widget.ListAdapter);
    Code:
       0: aload_0
       1: getfield      #451                // Field y:Landroid/database/DataSetObserver;
       4: ifnonnull     22
       7: aload_0
       8: new           #15                 // class android/support/v7/widget/aw$b
      11: dup
      12: aload_0
      13: invokespecial #452                // Method android/support/v7/widget/aw$b."<init>":(Landroid/support/v7/widget/aw;)V
      16: putfield      #451                // Field y:Landroid/database/DataSetObserver;
      19: goto          42
      22: aload_0
      23: getfield      #287                // Field j:Landroid/widget/ListAdapter;
      26: ifnull        42
      29: aload_0
      30: getfield      #287                // Field j:Landroid/widget/ListAdapter;
      33: aload_0
      34: getfield      #451                // Field y:Landroid/database/DataSetObserver;
      37: invokeinterface #458,  2          // InterfaceMethod android/widget/ListAdapter.unregisterDataSetObserver:(Landroid/database/DataSetObserver;)V
      42: aload_0
      43: aload_1
      44: putfield      #287                // Field j:Landroid/widget/ListAdapter;
      47: aload_1
      48: ifnull        61
      51: aload_1
      52: aload_0
      53: getfield      #451                // Field y:Landroid/database/DataSetObserver;
      56: invokeinterface #461,  2          // InterfaceMethod android/widget/ListAdapter.registerDataSetObserver:(Landroid/database/DataSetObserver;)V
      61: aload_0
      62: getfield      #269                // Field c:Landroid/support/v7/widget/ap;
      65: ifnull        79
      68: aload_0
      69: getfield      #269                // Field c:Landroid/support/v7/widget/ap;
      72: aload_0
      73: getfield      #287                // Field j:Landroid/widget/ListAdapter;
      76: invokevirtual #291                // Method android/support/v7/widget/ap.setAdapter:(Landroid/widget/ListAdapter;)V
      79: return

  public void a(android.widget.PopupWindow$OnDismissListener);
    Code:
       0: aload_0
       1: getfield      #226                // Field g:Landroid/widget/PopupWindow;
       4: aload_1
       5: invokevirtual #465                // Method android/widget/PopupWindow.setOnDismissListener:(Landroid/widget/PopupWindow$OnDismissListener;)V
       8: return

  public void a(boolean);
    Code:
       0: aload_0
       1: iload_1
       2: putfield      #274                // Field J:Z
       5: aload_0
       6: getfield      #226                // Field g:Landroid/widget/PopupWindow;
       9: iload_1
      10: invokevirtual #466                // Method android/widget/PopupWindow.setFocusable:(Z)V
      13: return

  public void b(int);
    Code:
       0: aload_0
       1: getfield      #226                // Field g:Landroid/widget/PopupWindow;
       4: iload_1
       5: invokevirtual #469                // Method android/widget/PopupWindow.setAnimationStyle:(I)V
       8: return

  public void b(android.view.View);
    Code:
       0: aload_0
       1: aload_1
       2: putfield      #471                // Field z:Landroid/view/View;
       5: return

  public void b(boolean);
    Code:
       0: aload_0
       1: iconst_1
       2: putfield      #473                // Field s:Z
       5: aload_0
       6: iload_1
       7: putfield      #475                // Field r:Z
      10: return

  public void c(int);
    Code:
       0: aload_0
       1: iload_1
       2: putfield      #211                // Field m:I
       5: return

  public boolean c();
    Code:
       0: aload_0
       1: getfield      #274                // Field J:Z
       4: ireturn

  public void d();
    Code:
       0: aload_0
       1: invokespecial #478                // Method b:()I
       4: istore_2
       5: aload_0
       6: invokevirtual #480                // Method n:()Z
       9: istore        6
      11: aload_0
      12: getfield      #226                // Field g:Landroid/widget/PopupWindow;
      15: aload_0
      16: getfield      #146                // Field o:I
      19: invokestatic  #485                // Method android/support/v4/widget/k.a:(Landroid/widget/PopupWindow;I)V
      22: aload_0
      23: getfield      #226                // Field g:Landroid/widget/PopupWindow;
      26: invokevirtual #488                // Method android/widget/PopupWindow.isShowing:()Z
      29: istore        7
      31: iconst_1
      32: istore        5
      34: iload         7
      36: ifeq          291
      39: aload_0
      40: invokevirtual #405                // Method i:()Landroid/view/View;
      43: invokestatic  #493                // Method android/support/v4/view/s.z:(Landroid/view/View;)Z
      46: ifne          50
      49: return
      50: aload_0
      51: getfield      #144                // Field l:I
      54: iconst_m1
      55: if_icmpne     63
      58: iconst_m1
      59: istore_1
      60: goto          88
      63: aload_0
      64: getfield      #144                // Field l:I
      67: bipush        -2
      69: if_icmpne     83
      72: aload_0
      73: invokevirtual #405                // Method i:()Landroid/view/View;
      76: invokevirtual #496                // Method android/view/View.getWidth:()I
      79: istore_1
      80: goto          88
      83: aload_0
      84: getfield      #144                // Field l:I
      87: istore_1
      88: aload_0
      89: getfield      #142                // Field k:I
      92: iconst_m1
      93: if_icmpne     187
      96: iload         6
      98: ifeq          104
     101: goto          106
     104: iconst_m1
     105: istore_2
     106: iload         6
     108: ifeq          149
     111: aload_0
     112: getfield      #226                // Field g:Landroid/widget/PopupWindow;
     115: astore        8
     117: aload_0
     118: getfield      #144                // Field l:I
     121: iconst_m1
     122: if_icmpne     130
     125: iconst_m1
     126: istore_3
     127: goto          132
     130: iconst_0
     131: istore_3
     132: aload         8
     134: iload_3
     135: invokevirtual #499                // Method android/widget/PopupWindow.setWidth:(I)V
     138: aload_0
     139: getfield      #226                // Field g:Landroid/widget/PopupWindow;
     142: iconst_0
     143: invokevirtual #502                // Method android/widget/PopupWindow.setHeight:(I)V
     146: goto          204
     149: aload_0
     150: getfield      #226                // Field g:Landroid/widget/PopupWindow;
     153: astore        8
     155: aload_0
     156: getfield      #144                // Field l:I
     159: iconst_m1
     160: if_icmpne     168
     163: iconst_m1
     164: istore_3
     165: goto          170
     168: iconst_0
     169: istore_3
     170: aload         8
     172: iload_3
     173: invokevirtual #499                // Method android/widget/PopupWindow.setWidth:(I)V
     176: aload_0
     177: getfield      #226                // Field g:Landroid/widget/PopupWindow;
     180: iconst_m1
     181: invokevirtual #502                // Method android/widget/PopupWindow.setHeight:(I)V
     184: goto          204
     187: aload_0
     188: getfield      #142                // Field k:I
     191: bipush        -2
     193: if_icmpne     199
     196: goto          204
     199: aload_0
     200: getfield      #142                // Field k:I
     203: istore_2
     204: aload_0
     205: getfield      #226                // Field g:Landroid/widget/PopupWindow;
     208: astore        8
     210: aload_0
     211: getfield      #154                // Field v:Z
     214: ifne          227
     217: aload_0
     218: getfield      #152                // Field u:Z
     221: ifne          227
     224: goto          230
     227: iconst_0
     228: istore        5
     230: aload         8
     232: iload         5
     234: invokevirtual #505                // Method android/widget/PopupWindow.setOutsideTouchable:(Z)V
     237: aload_0
     238: getfield      #226                // Field g:Landroid/widget/PopupWindow;
     241: astore        8
     243: aload_0
     244: invokevirtual #405                // Method i:()Landroid/view/View;
     247: astore        9
     249: aload_0
     250: getfield      #211                // Field m:I
     253: istore_3
     254: aload_0
     255: getfield      #216                // Field n:I
     258: istore        4
     260: iload_1
     261: ifge          269
     264: iconst_m1
     265: istore_1
     266: goto          269
     269: iload_2
     270: ifge          278
     273: iconst_m1
     274: istore_2
     275: goto          278
     278: aload         8
     280: aload         9
     282: iload_3
     283: iload         4
     285: iload_1
     286: iload_2
     287: invokevirtual #509                // Method android/widget/PopupWindow.update:(Landroid/view/View;IIII)V
     290: return
     291: aload_0
     292: getfield      #144                // Field l:I
     295: iconst_m1
     296: if_icmpne     304
     299: iconst_m1
     300: istore_1
     301: goto          329
     304: aload_0
     305: getfield      #144                // Field l:I
     308: bipush        -2
     310: if_icmpne     324
     313: aload_0
     314: invokevirtual #405                // Method i:()Landroid/view/View;
     317: invokevirtual #496                // Method android/view/View.getWidth:()I
     320: istore_1
     321: goto          329
     324: aload_0
     325: getfield      #144                // Field l:I
     328: istore_1
     329: aload_0
     330: getfield      #142                // Field k:I
     333: iconst_m1
     334: if_icmpne     342
     337: iconst_m1
     338: istore_2
     339: goto          359
     342: aload_0
     343: getfield      #142                // Field k:I
     346: bipush        -2
     348: if_icmpne     354
     351: goto          359
     354: aload_0
     355: getfield      #142                // Field k:I
     358: istore_2
     359: aload_0
     360: getfield      #226                // Field g:Landroid/widget/PopupWindow;
     363: iload_1
     364: invokevirtual #499                // Method android/widget/PopupWindow.setWidth:(I)V
     367: aload_0
     368: getfield      #226                // Field g:Landroid/widget/PopupWindow;
     371: iload_2
     372: invokevirtual #502                // Method android/widget/PopupWindow.setHeight:(I)V
     375: aload_0
     376: iconst_1
     377: invokespecial #511                // Method c:(Z)V
     380: aload_0
     381: getfield      #226                // Field g:Landroid/widget/PopupWindow;
     384: astore        8
     386: aload_0
     387: getfield      #154                // Field v:Z
     390: ifne          406
     393: aload_0
     394: getfield      #152                // Field u:Z
     397: ifne          406
     400: iconst_1
     401: istore        5
     403: goto          409
     406: iconst_0
     407: istore        5
     409: aload         8
     411: iload         5
     413: invokevirtual #505                // Method android/widget/PopupWindow.setOutsideTouchable:(Z)V
     416: aload_0
     417: getfield      #226                // Field g:Landroid/widget/PopupWindow;
     420: aload_0
     421: getfield      #167                // Field D:Landroid/support/v7/widget/aw$d;
     424: invokevirtual #515                // Method android/widget/PopupWindow.setTouchInterceptor:(Landroid/view/View$OnTouchListener;)V
     427: aload_0
     428: getfield      #473                // Field s:Z
     431: ifeq          445
     434: aload_0
     435: getfield      #226                // Field g:Landroid/widget/PopupWindow;
     438: aload_0
     439: getfield      #475                // Field r:Z
     442: invokestatic  #518                // Method android/support/v4/widget/k.a:(Landroid/widget/PopupWindow;Z)V
     445: getstatic     #122                // Field h:Ljava/lang/reflect/Method;
     448: ifnull        489
     451: getstatic     #122                // Field h:Ljava/lang/reflect/Method;
     454: aload_0
     455: getfield      #226                // Field g:Landroid/widget/PopupWindow;
     458: iconst_1
     459: anewarray     #4                  // class java/lang/Object
     462: dup
     463: iconst_0
     464: aload_0
     465: getfield      #446                // Field I:Landroid/graphics/Rect;
     468: aastore
     469: invokevirtual #246                // Method java/lang/reflect/Method.invoke:(Ljava/lang/Object;[Ljava/lang/Object;)Ljava/lang/Object;
     472: pop
     473: goto          489
     476: astore        8
     478: ldc           #98                 // String ListPopupWindow
     480: ldc_w         #520                // String Could not invoke setEpicenterBounds on PopupWindow
     483: aload         8
     485: invokestatic  #523                // Method android/util/Log.e:(Ljava/lang/String;Ljava/lang/String;Ljava/lang/Throwable;)I
     488: pop
     489: aload_0
     490: getfield      #226                // Field g:Landroid/widget/PopupWindow;
     493: aload_0
     494: invokevirtual #405                // Method i:()Landroid/view/View;
     497: aload_0
     498: getfield      #211                // Field m:I
     501: aload_0
     502: getfield      #216                // Field n:I
     505: aload_0
     506: getfield      #150                // Field t:I
     509: invokestatic  #526                // Method android/support/v4/widget/k.a:(Landroid/widget/PopupWindow;Landroid/view/View;III)V
     512: aload_0
     513: getfield      #269                // Field c:Landroid/support/v7/widget/ap;
     516: iconst_m1
     517: invokevirtual #529                // Method android/support/v7/widget/ap.setSelection:(I)V
     520: aload_0
     521: getfield      #274                // Field J:Z
     524: ifeq          537
     527: aload_0
     528: getfield      #269                // Field c:Landroid/support/v7/widget/ap;
     531: invokevirtual #532                // Method android/support/v7/widget/ap.isInTouchMode:()Z
     534: ifeq          541
     537: aload_0
     538: invokevirtual #534                // Method m:()V
     541: aload_0
     542: getfield      #274                // Field J:Z
     545: ifne          560
     548: aload_0
     549: getfield      #191                // Field f:Landroid/os/Handler;
     552: aload_0
     553: getfield      #173                // Field F:Landroid/support/v7/widget/aw$a;
     556: invokevirtual #538                // Method android/os/Handler.post:(Ljava/lang/Runnable;)Z
     559: pop
     560: return
    Exception table:
       from    to  target type
         451   473   476   Class java/lang/Exception

  public void d(int);
    Code:
       0: aload_0
       1: iload_1
       2: putfield      #216                // Field n:I
       5: aload_0
       6: iconst_1
       7: putfield      #218                // Field p:Z
      10: return

  public void e();
    Code:
       0: aload_0
       1: getfield      #226                // Field g:Landroid/widget/PopupWindow;
       4: invokevirtual #541                // Method android/widget/PopupWindow.dismiss:()V
       7: aload_0
       8: invokespecial #543                // Method a:()V
      11: aload_0
      12: getfield      #226                // Field g:Landroid/widget/PopupWindow;
      15: aconst_null
      16: invokevirtual #377                // Method android/widget/PopupWindow.setContentView:(Landroid/view/View;)V
      19: aload_0
      20: aconst_null
      21: putfield      #269                // Field c:Landroid/support/v7/widget/ap;
      24: aload_0
      25: getfield      #191                // Field f:Landroid/os/Handler;
      28: aload_0
      29: getfield      #164                // Field e:Landroid/support/v7/widget/aw$e;
      32: invokevirtual #547                // Method android/os/Handler.removeCallbacks:(Ljava/lang/Runnable;)V
      35: return

  public void e(int);
    Code:
       0: aload_0
       1: iload_1
       2: putfield      #150                // Field t:I
       5: return

  public void f(int);
    Code:
       0: aload_0
       1: iload_1
       2: putfield      #144                // Field l:I
       5: return

  public boolean f();
    Code:
       0: aload_0
       1: getfield      #226                // Field g:Landroid/widget/PopupWindow;
       4: invokevirtual #488                // Method android/widget/PopupWindow.isShowing:()Z
       7: ireturn

  public android.widget.ListView g();
    Code:
       0: aload_0
       1: getfield      #269                // Field c:Landroid/support/v7/widget/ap;
       4: areturn

  public void g(int);
    Code:
       0: aload_0
       1: getfield      #226                // Field g:Landroid/widget/PopupWindow;
       4: invokevirtual #385                // Method android/widget/PopupWindow.getBackground:()Landroid/graphics/drawable/Drawable;
       7: astore_2
       8: aload_2
       9: ifnull        43
      12: aload_2
      13: aload_0
      14: getfield      #176                // Field H:Landroid/graphics/Rect;
      17: invokevirtual #391                // Method android/graphics/drawable/Drawable.getPadding:(Landroid/graphics/Rect;)Z
      20: pop
      21: aload_0
      22: aload_0
      23: getfield      #176                // Field H:Landroid/graphics/Rect;
      26: getfield      #426                // Field android/graphics/Rect.left:I
      29: aload_0
      30: getfield      #176                // Field H:Landroid/graphics/Rect;
      33: getfield      #429                // Field android/graphics/Rect.right:I
      36: iadd
      37: iload_1
      38: iadd
      39: putfield      #144                // Field l:I
      42: return
      43: aload_0
      44: iload_1
      45: invokevirtual #550                // Method f:(I)V
      48: return

  public android.graphics.drawable.Drawable h();
    Code:
       0: aload_0
       1: getfield      #226                // Field g:Landroid/widget/PopupWindow;
       4: invokevirtual #385                // Method android/widget/PopupWindow.getBackground:()Landroid/graphics/drawable/Drawable;
       7: areturn

  public void h(int);
    Code:
       0: aload_0
       1: getfield      #226                // Field g:Landroid/widget/PopupWindow;
       4: iload_1
       5: invokevirtual #230                // Method android/widget/PopupWindow.setInputMethodMode:(I)V
       8: return

  public android.view.View i();
    Code:
       0: aload_0
       1: getfield      #471                // Field z:Landroid/view/View;
       4: areturn

  public void i(int);
    Code:
       0: aload_0
       1: getfield      #269                // Field c:Landroid/support/v7/widget/ap;
       4: astore_2
       5: aload_0
       6: invokevirtual #552                // Method f:()Z
       9: ifeq          39
      12: aload_2
      13: ifnull        39
      16: aload_2
      17: iconst_0
      18: invokevirtual #555                // Method android/support/v7/widget/ap.setListSelectionHidden:(Z)V
      21: aload_2
      22: iload_1
      23: invokevirtual #529                // Method android/support/v7/widget/ap.setSelection:(I)V
      26: aload_2
      27: invokevirtual #558                // Method android/support/v7/widget/ap.getChoiceMode:()I
      30: ifeq          39
      33: aload_2
      34: iload_1
      35: iconst_1
      36: invokevirtual #562                // Method android/support/v7/widget/ap.setItemChecked:(IZ)V
      39: return

  public int j();
    Code:
       0: aload_0
       1: getfield      #211                // Field m:I
       4: ireturn

  public int k();
    Code:
       0: aload_0
       1: getfield      #218                // Field p:Z
       4: ifne          9
       7: iconst_0
       8: ireturn
       9: aload_0
      10: getfield      #216                // Field n:I
      13: ireturn

  public int l();
    Code:
       0: aload_0
       1: getfield      #144                // Field l:I
       4: ireturn

  public void m();
    Code:
       0: aload_0
       1: getfield      #269                // Field c:Landroid/support/v7/widget/ap;
       4: astore_1
       5: aload_1
       6: ifnull        18
       9: aload_1
      10: iconst_1
      11: invokevirtual #555                // Method android/support/v7/widget/ap.setListSelectionHidden:(Z)V
      14: aload_1
      15: invokevirtual #565                // Method android/support/v7/widget/ap.requestLayout:()V
      18: return

  public boolean n();
    Code:
       0: aload_0
       1: getfield      #226                // Field g:Landroid/widget/PopupWindow;
       4: invokevirtual #403                // Method android/widget/PopupWindow.getInputMethodMode:()I
       7: iconst_2
       8: if_icmpne     13
      11: iconst_1
      12: ireturn
      13: iconst_0
      14: ireturn
}
