class android.support.v7.widget.bd extends android.graphics.drawable.Drawable {
  android.support.v7.widget.bd(android.content.res.ColorStateList, float);
    Code:
       0: aload_0
       1: invokespecial #28                 // Method android/graphics/drawable/Drawable."<init>":()V
       4: aload_0
       5: iconst_0
       6: putfield      #30                 // Field f:Z
       9: aload_0
      10: iconst_1
      11: putfield      #32                 // Field g:Z
      14: aload_0
      15: getstatic     #37                 // Field android/graphics/PorterDuff$Mode.SRC_IN:Landroid/graphics/PorterDuff$Mode;
      18: putfield      #39                 // Field k:Landroid/graphics/PorterDuff$Mode;
      21: aload_0
      22: fload_2
      23: putfield      #41                 // Field a:F
      26: aload_0
      27: new           #43                 // class android/graphics/Paint
      30: dup
      31: iconst_5
      32: invokespecial #46                 // Method android/graphics/Paint."<init>":(I)V
      35: putfield      #48                 // Field b:Landroid/graphics/Paint;
      38: aload_0
      39: aload_1
      40: invokespecial #51                 // Method b:(Landroid/content/res/ColorStateList;)V
      43: aload_0
      44: new           #53                 // class android/graphics/RectF
      47: dup
      48: invokespecial #54                 // Method android/graphics/RectF."<init>":()V
      51: putfield      #56                 // Field c:Landroid/graphics/RectF;
      54: aload_0
      55: new           #58                 // class android/graphics/Rect
      58: dup
      59: invokespecial #59                 // Method android/graphics/Rect."<init>":()V
      62: putfield      #61                 // Field d:Landroid/graphics/Rect;
      65: return

  float a();
    Code:
       0: aload_0
       1: getfield      #104                // Field e:F
       4: freturn

  void a(float);
    Code:
       0: fload_1
       1: aload_0
       2: getfield      #41                 // Field a:F
       5: fcmpl
       6: ifne          10
       9: return
      10: aload_0
      11: fload_1
      12: putfield      #41                 // Field a:F
      15: aload_0
      16: aconst_null
      17: invokespecial #139                // Method a:(Landroid/graphics/Rect;)V
      20: aload_0
      21: invokevirtual #142                // Method invalidateSelf:()V
      24: return

  void a(float, boolean, boolean);
    Code:
       0: fload_1
       1: aload_0
       2: getfield      #104                // Field e:F
       5: fcmpl
       6: ifne          26
       9: aload_0
      10: getfield      #30                 // Field f:Z
      13: iload_2
      14: if_icmpne     26
      17: aload_0
      18: getfield      #32                 // Field g:Z
      21: iload_3
      22: if_icmpne     26
      25: return
      26: aload_0
      27: fload_1
      28: putfield      #104                // Field e:F
      31: aload_0
      32: iload_2
      33: putfield      #30                 // Field f:Z
      36: aload_0
      37: iload_3
      38: putfield      #32                 // Field g:Z
      41: aload_0
      42: aconst_null
      43: invokespecial #139                // Method a:(Landroid/graphics/Rect;)V
      46: aload_0
      47: invokevirtual #142                // Method invalidateSelf:()V
      50: return

  public void a(android.content.res.ColorStateList);
    Code:
       0: aload_0
       1: aload_1
       2: invokespecial #51                 // Method b:(Landroid/content/res/ColorStateList;)V
       5: aload_0
       6: invokevirtual #142                // Method invalidateSelf:()V
       9: return

  public float b();
    Code:
       0: aload_0
       1: getfield      #41                 // Field a:F
       4: freturn

  public android.content.res.ColorStateList c();
    Code:
       0: aload_0
       1: getfield      #128                // Field h:Landroid/content/res/ColorStateList;
       4: areturn

  public void draw(android.graphics.Canvas);
    Code:
       0: aload_0
       1: getfield      #48                 // Field b:Landroid/graphics/Paint;
       4: astore_3
       5: aload_0
       6: getfield      #148                // Field i:Landroid/graphics/PorterDuffColorFilter;
       9: ifnull        33
      12: aload_3
      13: invokevirtual #152                // Method android/graphics/Paint.getColorFilter:()Landroid/graphics/ColorFilter;
      16: ifnonnull     33
      19: aload_3
      20: aload_0
      21: getfield      #148                // Field i:Landroid/graphics/PorterDuffColorFilter;
      24: invokevirtual #156                // Method android/graphics/Paint.setColorFilter:(Landroid/graphics/ColorFilter;)Landroid/graphics/ColorFilter;
      27: pop
      28: iconst_1
      29: istore_2
      30: goto          35
      33: iconst_0
      34: istore_2
      35: aload_1
      36: aload_0
      37: getfield      #56                 // Field c:Landroid/graphics/RectF;
      40: aload_0
      41: getfield      #41                 // Field a:F
      44: aload_0
      45: getfield      #41                 // Field a:F
      48: aload_3
      49: invokevirtual #162                // Method android/graphics/Canvas.drawRoundRect:(Landroid/graphics/RectF;FFLandroid/graphics/Paint;)V
      52: iload_2
      53: ifeq          62
      56: aload_3
      57: aconst_null
      58: invokevirtual #156                // Method android/graphics/Paint.setColorFilter:(Landroid/graphics/ColorFilter;)Landroid/graphics/ColorFilter;
      61: pop
      62: return

  public int getOpacity();
    Code:
       0: bipush        -3
       2: ireturn

  public void getOutline(android.graphics.Outline);
    Code:
       0: aload_1
       1: aload_0
       2: getfield      #61                 // Field d:Landroid/graphics/Rect;
       5: aload_0
       6: getfield      #41                 // Field a:F
       9: invokevirtual #171                // Method android/graphics/Outline.setRoundRect:(Landroid/graphics/Rect;F)V
      12: return

  public boolean isStateful();
    Code:
       0: aload_0
       1: getfield      #175                // Field j:Landroid/content/res/ColorStateList;
       4: ifnull        17
       7: aload_0
       8: getfield      #175                // Field j:Landroid/content/res/ColorStateList;
      11: invokevirtual #177                // Method android/content/res/ColorStateList.isStateful:()Z
      14: ifne          41
      17: aload_0
      18: getfield      #128                // Field h:Landroid/content/res/ColorStateList;
      21: ifnull        34
      24: aload_0
      25: getfield      #128                // Field h:Landroid/content/res/ColorStateList;
      28: invokevirtual #177                // Method android/content/res/ColorStateList.isStateful:()Z
      31: ifne          41
      34: aload_0
      35: invokespecial #178                // Method android/graphics/drawable/Drawable.isStateful:()Z
      38: ifeq          43
      41: iconst_1
      42: ireturn
      43: iconst_0
      44: ireturn

  protected void onBoundsChange(android.graphics.Rect);
    Code:
       0: aload_0
       1: aload_1
       2: invokespecial #181                // Method android/graphics/drawable/Drawable.onBoundsChange:(Landroid/graphics/Rect;)V
       5: aload_0
       6: aload_1
       7: invokespecial #139                // Method a:(Landroid/graphics/Rect;)V
      10: return

  protected boolean onStateChange(int[]);
    Code:
       0: aload_0
       1: getfield      #128                // Field h:Landroid/content/res/ColorStateList;
       4: aload_1
       5: aload_0
       6: getfield      #128                // Field h:Landroid/content/res/ColorStateList;
       9: invokevirtual #132                // Method android/content/res/ColorStateList.getDefaultColor:()I
      12: invokevirtual #75                 // Method android/content/res/ColorStateList.getColorForState:([II)I
      15: istore_2
      16: iload_2
      17: aload_0
      18: getfield      #48                 // Field b:Landroid/graphics/Paint;
      21: invokevirtual #186                // Method android/graphics/Paint.getColor:()I
      24: if_icmpeq     32
      27: iconst_1
      28: istore_3
      29: goto          34
      32: iconst_0
      33: istore_3
      34: iload_3
      35: ifeq          46
      38: aload_0
      39: getfield      #48                 // Field b:Landroid/graphics/Paint;
      42: iload_2
      43: invokevirtual #135                // Method android/graphics/Paint.setColor:(I)V
      46: aload_0
      47: getfield      #175                // Field j:Landroid/content/res/ColorStateList;
      50: ifnull        78
      53: aload_0
      54: getfield      #39                 // Field k:Landroid/graphics/PorterDuff$Mode;
      57: ifnull        78
      60: aload_0
      61: aload_0
      62: aload_0
      63: getfield      #175                // Field j:Landroid/content/res/ColorStateList;
      66: aload_0
      67: getfield      #39                 // Field k:Landroid/graphics/PorterDuff$Mode;
      70: invokespecial #188                // Method a:(Landroid/content/res/ColorStateList;Landroid/graphics/PorterDuff$Mode;)Landroid/graphics/PorterDuffColorFilter;
      73: putfield      #148                // Field i:Landroid/graphics/PorterDuffColorFilter;
      76: iconst_1
      77: ireturn
      78: iload_3
      79: ireturn

  public void setAlpha(int);
    Code:
       0: aload_0
       1: getfield      #48                 // Field b:Landroid/graphics/Paint;
       4: iload_1
       5: invokevirtual #191                // Method android/graphics/Paint.setAlpha:(I)V
       8: return

  public void setColorFilter(android.graphics.ColorFilter);
    Code:
       0: aload_0
       1: getfield      #48                 // Field b:Landroid/graphics/Paint;
       4: aload_1
       5: invokevirtual #156                // Method android/graphics/Paint.setColorFilter:(Landroid/graphics/ColorFilter;)Landroid/graphics/ColorFilter;
       8: pop
       9: return

  public void setTintList(android.content.res.ColorStateList);
    Code:
       0: aload_0
       1: aload_1
       2: putfield      #175                // Field j:Landroid/content/res/ColorStateList;
       5: aload_0
       6: aload_0
       7: aload_0
       8: getfield      #175                // Field j:Landroid/content/res/ColorStateList;
      11: aload_0
      12: getfield      #39                 // Field k:Landroid/graphics/PorterDuff$Mode;
      15: invokespecial #188                // Method a:(Landroid/content/res/ColorStateList;Landroid/graphics/PorterDuff$Mode;)Landroid/graphics/PorterDuffColorFilter;
      18: putfield      #148                // Field i:Landroid/graphics/PorterDuffColorFilter;
      21: aload_0
      22: invokevirtual #142                // Method invalidateSelf:()V
      25: return

  public void setTintMode(android.graphics.PorterDuff$Mode);
    Code:
       0: aload_0
       1: aload_1
       2: putfield      #39                 // Field k:Landroid/graphics/PorterDuff$Mode;
       5: aload_0
       6: aload_0
       7: aload_0
       8: getfield      #175                // Field j:Landroid/content/res/ColorStateList;
      11: aload_0
      12: getfield      #39                 // Field k:Landroid/graphics/PorterDuff$Mode;
      15: invokespecial #188                // Method a:(Landroid/content/res/ColorStateList;Landroid/graphics/PorterDuff$Mode;)Landroid/graphics/PorterDuffColorFilter;
      18: putfield      #148                // Field i:Landroid/graphics/PorterDuffColorFilter;
      21: aload_0
      22: invokevirtual #142                // Method invalidateSelf:()V
      25: return
}
