final class android.support.v7.widget.bj$a {
  public final android.widget.TextView a;

  public final android.widget.TextView b;

  public final android.widget.ImageView c;

  public final android.widget.ImageView d;

  public final android.widget.ImageView e;

  public android.support.v7.widget.bj$a(android.view.View);
    Code:
       0: aload_0
       1: invokespecial #18                 // Method java/lang/Object."<init>":()V
       4: aload_0
       5: aload_1
       6: ldc           #19                 // int 16908308
       8: invokevirtual #25                 // Method android/view/View.findViewById:(I)Landroid/view/View;
      11: checkcast     #27                 // class android/widget/TextView
      14: putfield      #29                 // Field a:Landroid/widget/TextView;
      17: aload_0
      18: aload_1
      19: ldc           #30                 // int 16908309
      21: invokevirtual #25                 // Method android/view/View.findViewById:(I)Landroid/view/View;
      24: checkcast     #27                 // class android/widget/TextView
      27: putfield      #32                 // Field b:Landroid/widget/TextView;
      30: aload_0
      31: aload_1
      32: ldc           #33                 // int 16908295
      34: invokevirtual #25                 // Method android/view/View.findViewById:(I)Landroid/view/View;
      37: checkcast     #35                 // class android/widget/ImageView
      40: putfield      #37                 // Field c:Landroid/widget/ImageView;
      43: aload_0
      44: aload_1
      45: ldc           #38                 // int 16908296
      47: invokevirtual #25                 // Method android/view/View.findViewById:(I)Landroid/view/View;
      50: checkcast     #35                 // class android/widget/ImageView
      53: putfield      #40                 // Field d:Landroid/widget/ImageView;
      56: aload_0
      57: aload_1
      58: getstatic     #46                 // Field android/support/v7/a/a$f.edit_query:I
      61: invokevirtual #25                 // Method android/view/View.findViewById:(I)Landroid/view/View;
      64: checkcast     #35                 // class android/widget/ImageView
      67: putfield      #48                 // Field e:Landroid/widget/ImageView;
      70: return
}
