class android.support.v7.widget.bk {
  static final int[] a;

  static final int[] b;

  static final int[] c;

  static final int[] d;

  static final int[] e;

  static final int[] f;

  static final int[] g;

  static final int[] h;

  static {};
    Code:
       0: new           #21                 // class java/lang/ThreadLocal
       3: dup
       4: invokespecial #24                 // Method java/lang/ThreadLocal."<init>":()V
       7: putstatic     #26                 // Field i:Ljava/lang/ThreadLocal;
      10: iconst_1
      11: newarray       int
      13: dup
      14: iconst_0
      15: ldc           #27                 // int -16842910
      17: iastore
      18: putstatic     #29                 // Field a:[I
      21: iconst_1
      22: newarray       int
      24: dup
      25: iconst_0
      26: ldc           #30                 // int 16842908
      28: iastore
      29: putstatic     #32                 // Field b:[I
      32: iconst_1
      33: newarray       int
      35: dup
      36: iconst_0
      37: ldc           #33                 // int 16843518
      39: iastore
      40: putstatic     #35                 // Field c:[I
      43: iconst_1
      44: newarray       int
      46: dup
      47: iconst_0
      48: ldc           #36                 // int 16842919
      50: iastore
      51: putstatic     #38                 // Field d:[I
      54: iconst_1
      55: newarray       int
      57: dup
      58: iconst_0
      59: ldc           #39                 // int 16842912
      61: iastore
      62: putstatic     #41                 // Field e:[I
      65: iconst_1
      66: newarray       int
      68: dup
      69: iconst_0
      70: ldc           #42                 // int 16842913
      72: iastore
      73: putstatic     #44                 // Field f:[I
      76: iconst_2
      77: newarray       int
      79: dup
      80: iconst_0
      81: ldc           #45                 // int -16842919
      83: iastore
      84: dup
      85: iconst_1
      86: ldc           #46                 // int -16842908
      88: iastore
      89: putstatic     #48                 // Field g:[I
      92: iconst_0
      93: newarray       int
      95: putstatic     #50                 // Field h:[I
      98: iconst_1
      99: newarray       int
     101: putstatic     #52                 // Field j:[I
     104: return

  public static int a(android.content.Context, int);
    Code:
       0: getstatic     #52                 // Field j:[I
       3: iconst_0
       4: iload_1
       5: iastore
       6: aload_0
       7: aconst_null
       8: getstatic     #52                 // Field j:[I
      11: invokestatic  #59                 // Method android/support/v7/widget/bp.a:(Landroid/content/Context;Landroid/util/AttributeSet;[I)Landroid/support/v7/widget/bp;
      14: astore_0
      15: aload_0
      16: iconst_0
      17: iconst_0
      18: invokevirtual #62                 // Method android/support/v7/widget/bp.b:(II)I
      21: istore_1
      22: aload_0
      23: invokevirtual #64                 // Method android/support/v7/widget/bp.a:()V
      26: iload_1
      27: ireturn
      28: astore_2
      29: aload_0
      30: invokevirtual #64                 // Method android/support/v7/widget/bp.a:()V
      33: aload_2
      34: athrow
    Exception table:
       from    to  target type
          15    22    28   any

  static int a(android.content.Context, int, float);
    Code:
       0: aload_0
       1: iload_1
       2: invokestatic  #67                 // Method a:(Landroid/content/Context;I)I
       5: istore_1
       6: iload_1
       7: iload_1
       8: invokestatic  #73                 // Method android/graphics/Color.alpha:(I)I
      11: i2f
      12: fload_2
      13: fmul
      14: invokestatic  #79                 // Method java/lang/Math.round:(F)I
      17: invokestatic  #82                 // Method android/support/v4/b/a.b:(II)I
      20: ireturn

  public static android.content.res.ColorStateList b(android.content.Context, int);
    Code:
       0: getstatic     #52                 // Field j:[I
       3: iconst_0
       4: iload_1
       5: iastore
       6: aload_0
       7: aconst_null
       8: getstatic     #52                 // Field j:[I
      11: invokestatic  #59                 // Method android/support/v7/widget/bp.a:(Landroid/content/Context;Landroid/util/AttributeSet;[I)Landroid/support/v7/widget/bp;
      14: astore_0
      15: aload_0
      16: iconst_0
      17: invokevirtual #98                 // Method android/support/v7/widget/bp.e:(I)Landroid/content/res/ColorStateList;
      20: astore_2
      21: aload_0
      22: invokevirtual #64                 // Method android/support/v7/widget/bp.a:()V
      25: aload_2
      26: areturn
      27: astore_2
      28: aload_0
      29: invokevirtual #64                 // Method android/support/v7/widget/bp.a:()V
      32: aload_2
      33: athrow
    Exception table:
       from    to  target type
          15    21    27   any

  public static int c(android.content.Context, int);
    Code:
       0: aload_0
       1: iload_1
       2: invokestatic  #100                // Method b:(Landroid/content/Context;I)Landroid/content/res/ColorStateList;
       5: astore_2
       6: aload_2
       7: ifnull        29
      10: aload_2
      11: invokevirtual #106                // Method android/content/res/ColorStateList.isStateful:()Z
      14: ifeq          29
      17: aload_2
      18: getstatic     #29                 // Field a:[I
      21: aload_2
      22: invokevirtual #110                // Method android/content/res/ColorStateList.getDefaultColor:()I
      25: invokevirtual #114                // Method android/content/res/ColorStateList.getColorForState:([II)I
      28: ireturn
      29: invokestatic  #116                // Method a:()Landroid/util/TypedValue;
      32: astore_2
      33: aload_0
      34: invokevirtual #122                // Method android/content/Context.getTheme:()Landroid/content/res/Resources$Theme;
      37: ldc           #123                // int 16842803
      39: aload_2
      40: iconst_1
      41: invokevirtual #129                // Method android/content/res/Resources$Theme.resolveAttribute:(ILandroid/util/TypedValue;Z)Z
      44: pop
      45: aload_0
      46: iload_1
      47: aload_2
      48: invokevirtual #133                // Method android/util/TypedValue.getFloat:()F
      51: invokestatic  #135                // Method a:(Landroid/content/Context;IF)I
      54: ireturn
}
