class android.support.v7.widget.bn {
  public android.content.res.ColorStateList a;

  public android.graphics.PorterDuff$Mode b;

  public boolean c;

  public boolean d;

  android.support.v7.widget.bn();
    Code:
       0: aload_0
       1: invokespecial #15                 // Method java/lang/Object."<init>":()V
       4: return

  void a();
    Code:
       0: aload_0
       1: aconst_null
       2: putfield      #18                 // Field a:Landroid/content/res/ColorStateList;
       5: aload_0
       6: iconst_0
       7: putfield      #20                 // Field d:Z
      10: aload_0
      11: aconst_null
      12: putfield      #22                 // Field b:Landroid/graphics/PorterDuff$Mode;
      15: aload_0
      16: iconst_0
      17: putfield      #24                 // Field c:Z
      20: return
}
