public class android.support.v7.widget.bp {
  public static android.support.v7.widget.bp a(android.content.Context, int, int[]);
    Code:
       0: new           #2                  // class android/support/v7/widget/bp
       3: dup
       4: aload_0
       5: aload_0
       6: iload_1
       7: aload_2
       8: invokevirtual #27                 // Method android/content/Context.obtainStyledAttributes:(I[I)Landroid/content/res/TypedArray;
      11: invokespecial #29                 // Method "<init>":(Landroid/content/Context;Landroid/content/res/TypedArray;)V
      14: areturn

  public static android.support.v7.widget.bp a(android.content.Context, android.util.AttributeSet, int[]);
    Code:
       0: new           #2                  // class android/support/v7/widget/bp
       3: dup
       4: aload_0
       5: aload_0
       6: aload_1
       7: aload_2
       8: invokevirtual #33                 // Method android/content/Context.obtainStyledAttributes:(Landroid/util/AttributeSet;[I)Landroid/content/res/TypedArray;
      11: invokespecial #29                 // Method "<init>":(Landroid/content/Context;Landroid/content/res/TypedArray;)V
      14: areturn

  public static android.support.v7.widget.bp a(android.content.Context, android.util.AttributeSet, int[], int, int);
    Code:
       0: new           #2                  // class android/support/v7/widget/bp
       3: dup
       4: aload_0
       5: aload_0
       6: aload_1
       7: aload_2
       8: iload_3
       9: iload         4
      11: invokevirtual #37                 // Method android/content/Context.obtainStyledAttributes:(Landroid/util/AttributeSet;[III)Landroid/content/res/TypedArray;
      14: invokespecial #29                 // Method "<init>":(Landroid/content/Context;Landroid/content/res/TypedArray;)V
      17: areturn

  public float a(int, float);
    Code:
       0: aload_0
       1: getfield      #19                 // Field b:Landroid/content/res/TypedArray;
       4: iload_1
       5: fload_2
       6: invokevirtual #43                 // Method android/content/res/TypedArray.getFloat:(IF)F
       9: freturn

  public int a(int, int);
    Code:
       0: aload_0
       1: getfield      #19                 // Field b:Landroid/content/res/TypedArray;
       4: iload_1
       5: iload_2
       6: invokevirtual #47                 // Method android/content/res/TypedArray.getInt:(II)I
       9: ireturn

  public android.graphics.Typeface a(int, int, android.support.v4.a.a.b$a);
    Code:
       0: aload_0
       1: getfield      #19                 // Field b:Landroid/content/res/TypedArray;
       4: iload_1
       5: iconst_0
       6: invokevirtual #51                 // Method android/content/res/TypedArray.getResourceId:(II)I
       9: istore_1
      10: iload_1
      11: ifne          16
      14: aconst_null
      15: areturn
      16: aload_0
      17: getfield      #53                 // Field c:Landroid/util/TypedValue;
      20: ifnonnull     34
      23: aload_0
      24: new           #55                 // class android/util/TypedValue
      27: dup
      28: invokespecial #56                 // Method android/util/TypedValue."<init>":()V
      31: putfield      #53                 // Field c:Landroid/util/TypedValue;
      34: aload_0
      35: getfield      #17                 // Field a:Landroid/content/Context;
      38: iload_1
      39: aload_0
      40: getfield      #53                 // Field c:Landroid/util/TypedValue;
      43: iload_2
      44: aload_3
      45: invokestatic  #61                 // Method android/support/v4/a/a/b.a:(Landroid/content/Context;ILandroid/util/TypedValue;ILandroid/support/v4/a/a/b$a;)Landroid/graphics/Typeface;
      48: areturn

  public android.graphics.drawable.Drawable a(int);
    Code:
       0: aload_0
       1: getfield      #19                 // Field b:Landroid/content/res/TypedArray;
       4: iload_1
       5: invokevirtual #66                 // Method android/content/res/TypedArray.hasValue:(I)Z
       8: ifeq          34
      11: aload_0
      12: getfield      #19                 // Field b:Landroid/content/res/TypedArray;
      15: iload_1
      16: iconst_0
      17: invokevirtual #51                 // Method android/content/res/TypedArray.getResourceId:(II)I
      20: istore_2
      21: iload_2
      22: ifeq          34
      25: aload_0
      26: getfield      #17                 // Field a:Landroid/content/Context;
      29: iload_2
      30: invokestatic  #71                 // Method android/support/v7/c/a/b.b:(Landroid/content/Context;I)Landroid/graphics/drawable/Drawable;
      33: areturn
      34: aload_0
      35: getfield      #19                 // Field b:Landroid/content/res/TypedArray;
      38: iload_1
      39: invokevirtual #74                 // Method android/content/res/TypedArray.getDrawable:(I)Landroid/graphics/drawable/Drawable;
      42: areturn

  public void a();
    Code:
       0: aload_0
       1: getfield      #19                 // Field b:Landroid/content/res/TypedArray;
       4: invokevirtual #77                 // Method android/content/res/TypedArray.recycle:()V
       7: return

  public boolean a(int, boolean);
    Code:
       0: aload_0
       1: getfield      #19                 // Field b:Landroid/content/res/TypedArray;
       4: iload_1
       5: iload_2
       6: invokevirtual #81                 // Method android/content/res/TypedArray.getBoolean:(IZ)Z
       9: ireturn

  public int b(int, int);
    Code:
       0: aload_0
       1: getfield      #19                 // Field b:Landroid/content/res/TypedArray;
       4: iload_1
       5: iload_2
       6: invokevirtual #84                 // Method android/content/res/TypedArray.getColor:(II)I
       9: ireturn

  public android.graphics.drawable.Drawable b(int);
    Code:
       0: aload_0
       1: getfield      #19                 // Field b:Landroid/content/res/TypedArray;
       4: iload_1
       5: invokevirtual #66                 // Method android/content/res/TypedArray.hasValue:(I)Z
       8: ifeq          38
      11: aload_0
      12: getfield      #19                 // Field b:Landroid/content/res/TypedArray;
      15: iload_1
      16: iconst_0
      17: invokevirtual #51                 // Method android/content/res/TypedArray.getResourceId:(II)I
      20: istore_1
      21: iload_1
      22: ifeq          38
      25: invokestatic  #89                 // Method android/support/v7/widget/m.a:()Landroid/support/v7/widget/m;
      28: aload_0
      29: getfield      #17                 // Field a:Landroid/content/Context;
      32: iload_1
      33: iconst_1
      34: invokevirtual #92                 // Method android/support/v7/widget/m.a:(Landroid/content/Context;IZ)Landroid/graphics/drawable/Drawable;
      37: areturn
      38: aconst_null
      39: areturn

  public int c(int, int);
    Code:
       0: aload_0
       1: getfield      #19                 // Field b:Landroid/content/res/TypedArray;
       4: iload_1
       5: iload_2
       6: invokevirtual #95                 // Method android/content/res/TypedArray.getInteger:(II)I
       9: ireturn

  public java.lang.CharSequence c(int);
    Code:
       0: aload_0
       1: getfield      #19                 // Field b:Landroid/content/res/TypedArray;
       4: iload_1
       5: invokevirtual #99                 // Method android/content/res/TypedArray.getText:(I)Ljava/lang/CharSequence;
       8: areturn

  public int d(int, int);
    Code:
       0: aload_0
       1: getfield      #19                 // Field b:Landroid/content/res/TypedArray;
       4: iload_1
       5: iload_2
       6: invokevirtual #103                // Method android/content/res/TypedArray.getDimensionPixelOffset:(II)I
       9: ireturn

  public java.lang.String d(int);
    Code:
       0: aload_0
       1: getfield      #19                 // Field b:Landroid/content/res/TypedArray;
       4: iload_1
       5: invokevirtual #107                // Method android/content/res/TypedArray.getString:(I)Ljava/lang/String;
       8: areturn

  public int e(int, int);
    Code:
       0: aload_0
       1: getfield      #19                 // Field b:Landroid/content/res/TypedArray;
       4: iload_1
       5: iload_2
       6: invokevirtual #111                // Method android/content/res/TypedArray.getDimensionPixelSize:(II)I
       9: ireturn

  public android.content.res.ColorStateList e(int);
    Code:
       0: aload_0
       1: getfield      #19                 // Field b:Landroid/content/res/TypedArray;
       4: iload_1
       5: invokevirtual #66                 // Method android/content/res/TypedArray.hasValue:(I)Z
       8: ifeq          40
      11: aload_0
      12: getfield      #19                 // Field b:Landroid/content/res/TypedArray;
      15: iload_1
      16: iconst_0
      17: invokevirtual #51                 // Method android/content/res/TypedArray.getResourceId:(II)I
      20: istore_2
      21: iload_2
      22: ifeq          40
      25: aload_0
      26: getfield      #17                 // Field a:Landroid/content/Context;
      29: iload_2
      30: invokestatic  #115                // Method android/support/v7/c/a/b.a:(Landroid/content/Context;I)Landroid/content/res/ColorStateList;
      33: astore_3
      34: aload_3
      35: ifnull        40
      38: aload_3
      39: areturn
      40: aload_0
      41: getfield      #19                 // Field b:Landroid/content/res/TypedArray;
      44: iload_1
      45: invokevirtual #118                // Method android/content/res/TypedArray.getColorStateList:(I)Landroid/content/res/ColorStateList;
      48: areturn

  public int f(int, int);
    Code:
       0: aload_0
       1: getfield      #19                 // Field b:Landroid/content/res/TypedArray;
       4: iload_1
       5: iload_2
       6: invokevirtual #122                // Method android/content/res/TypedArray.getLayoutDimension:(II)I
       9: ireturn

  public java.lang.CharSequence[] f(int);
    Code:
       0: aload_0
       1: getfield      #19                 // Field b:Landroid/content/res/TypedArray;
       4: iload_1
       5: invokevirtual #126                // Method android/content/res/TypedArray.getTextArray:(I)[Ljava/lang/CharSequence;
       8: areturn

  public int g(int, int);
    Code:
       0: aload_0
       1: getfield      #19                 // Field b:Landroid/content/res/TypedArray;
       4: iload_1
       5: iload_2
       6: invokevirtual #51                 // Method android/content/res/TypedArray.getResourceId:(II)I
       9: ireturn

  public boolean g(int);
    Code:
       0: aload_0
       1: getfield      #19                 // Field b:Landroid/content/res/TypedArray;
       4: iload_1
       5: invokevirtual #66                 // Method android/content/res/TypedArray.hasValue:(I)Z
       8: ireturn
}
