class android.support.v7.widget.bv {
  final android.support.v7.widget.bv$b a;

  android.support.v7.widget.bv$a b;

  android.support.v7.widget.bv(android.support.v7.widget.bv$b);
    Code:
       0: aload_0
       1: invokespecial #17                 // Method java/lang/Object."<init>":()V
       4: aload_0
       5: aload_1
       6: putfield      #19                 // Field a:Landroid/support/v7/widget/bv$b;
       9: aload_0
      10: new           #6                  // class android/support/v7/widget/bv$a
      13: dup
      14: invokespecial #20                 // Method android/support/v7/widget/bv$a."<init>":()V
      17: putfield      #22                 // Field b:Landroid/support/v7/widget/bv$a;
      20: return

  android.view.View a(int, int, int, int);
    Code:
       0: aload_0
       1: getfield      #19                 // Field a:Landroid/support/v7/widget/bv$b;
       4: invokeinterface #27,  1           // InterfaceMethod android/support/v7/widget/bv$b.a:()I
       9: istore        6
      11: aload_0
      12: getfield      #19                 // Field a:Landroid/support/v7/widget/bv$b;
      15: invokeinterface #29,  1           // InterfaceMethod android/support/v7/widget/bv$b.b:()I
      20: istore        7
      22: iload_2
      23: iload_1
      24: if_icmple     33
      27: iconst_1
      28: istore        5
      30: goto          36
      33: iconst_m1
      34: istore        5
      36: aconst_null
      37: astore        10
      39: iload_1
      40: iload_2
      41: if_icmpeq     184
      44: aload_0
      45: getfield      #19                 // Field a:Landroid/support/v7/widget/bv$b;
      48: iload_1
      49: invokeinterface #32,  2           // InterfaceMethod android/support/v7/widget/bv$b.a:(I)Landroid/view/View;
      54: astore        12
      56: aload_0
      57: getfield      #19                 // Field a:Landroid/support/v7/widget/bv$b;
      60: aload         12
      62: invokeinterface #35,  2           // InterfaceMethod android/support/v7/widget/bv$b.a:(Landroid/view/View;)I
      67: istore        8
      69: aload_0
      70: getfield      #19                 // Field a:Landroid/support/v7/widget/bv$b;
      73: aload         12
      75: invokeinterface #37,  2           // InterfaceMethod android/support/v7/widget/bv$b.b:(Landroid/view/View;)I
      80: istore        9
      82: aload_0
      83: getfield      #22                 // Field b:Landroid/support/v7/widget/bv$a;
      86: iload         6
      88: iload         7
      90: iload         8
      92: iload         9
      94: invokevirtual #40                 // Method android/support/v7/widget/bv$a.a:(IIII)V
      97: iload_3
      98: ifeq          129
     101: aload_0
     102: getfield      #22                 // Field b:Landroid/support/v7/widget/bv$a;
     105: invokevirtual #42                 // Method android/support/v7/widget/bv$a.a:()V
     108: aload_0
     109: getfield      #22                 // Field b:Landroid/support/v7/widget/bv$a;
     112: iload_3
     113: invokevirtual #45                 // Method android/support/v7/widget/bv$a.a:(I)V
     116: aload_0
     117: getfield      #22                 // Field b:Landroid/support/v7/widget/bv$a;
     120: invokevirtual #48                 // Method android/support/v7/widget/bv$a.b:()Z
     123: ifeq          129
     126: aload         12
     128: areturn
     129: aload         10
     131: astore        11
     133: iload         4
     135: ifeq          172
     138: aload_0
     139: getfield      #22                 // Field b:Landroid/support/v7/widget/bv$a;
     142: invokevirtual #42                 // Method android/support/v7/widget/bv$a.a:()V
     145: aload_0
     146: getfield      #22                 // Field b:Landroid/support/v7/widget/bv$a;
     149: iload         4
     151: invokevirtual #45                 // Method android/support/v7/widget/bv$a.a:(I)V
     154: aload         10
     156: astore        11
     158: aload_0
     159: getfield      #22                 // Field b:Landroid/support/v7/widget/bv$a;
     162: invokevirtual #48                 // Method android/support/v7/widget/bv$a.b:()Z
     165: ifeq          172
     168: aload         12
     170: astore        11
     172: iload_1
     173: iload         5
     175: iadd
     176: istore_1
     177: aload         11
     179: astore        10
     181: goto          39
     184: aload         10
     186: areturn

  boolean a(android.view.View, int);
    Code:
       0: aload_0
       1: getfield      #22                 // Field b:Landroid/support/v7/widget/bv$a;
       4: aload_0
       5: getfield      #19                 // Field a:Landroid/support/v7/widget/bv$b;
       8: invokeinterface #27,  1           // InterfaceMethod android/support/v7/widget/bv$b.a:()I
      13: aload_0
      14: getfield      #19                 // Field a:Landroid/support/v7/widget/bv$b;
      17: invokeinterface #29,  1           // InterfaceMethod android/support/v7/widget/bv$b.b:()I
      22: aload_0
      23: getfield      #19                 // Field a:Landroid/support/v7/widget/bv$b;
      26: aload_1
      27: invokeinterface #35,  2           // InterfaceMethod android/support/v7/widget/bv$b.a:(Landroid/view/View;)I
      32: aload_0
      33: getfield      #19                 // Field a:Landroid/support/v7/widget/bv$b;
      36: aload_1
      37: invokeinterface #37,  2           // InterfaceMethod android/support/v7/widget/bv$b.b:(Landroid/view/View;)I
      42: invokevirtual #40                 // Method android/support/v7/widget/bv$a.a:(IIII)V
      45: iload_2
      46: ifeq          72
      49: aload_0
      50: getfield      #22                 // Field b:Landroid/support/v7/widget/bv$a;
      53: invokevirtual #42                 // Method android/support/v7/widget/bv$a.a:()V
      56: aload_0
      57: getfield      #22                 // Field b:Landroid/support/v7/widget/bv$a;
      60: iload_2
      61: invokevirtual #45                 // Method android/support/v7/widget/bv$a.a:(I)V
      64: aload_0
      65: getfield      #22                 // Field b:Landroid/support/v7/widget/bv$a;
      68: invokevirtual #48                 // Method android/support/v7/widget/bv$a.b:()Z
      71: ireturn
      72: iconst_0
      73: ireturn
}
