class android.support.v7.widget.c extends android.support.v7.widget.b {
  public android.support.v7.widget.c(android.support.v7.widget.ActionBarContainer);
    Code:
       0: aload_0
       1: aload_1
       2: invokespecial #8                  // Method android/support/v7/widget/b."<init>":(Landroid/support/v7/widget/ActionBarContainer;)V
       5: return

  public void getOutline(android.graphics.Outline);
    Code:
       0: aload_0
       1: getfield      #15                 // Field a:Landroid/support/v7/widget/ActionBarContainer;
       4: getfield      #21                 // Field android/support/v7/widget/ActionBarContainer.d:Z
       7: ifeq          34
      10: aload_0
      11: getfield      #15                 // Field a:Landroid/support/v7/widget/ActionBarContainer;
      14: getfield      #25                 // Field android/support/v7/widget/ActionBarContainer.c:Landroid/graphics/drawable/Drawable;
      17: ifnull        55
      20: aload_0
      21: getfield      #15                 // Field a:Landroid/support/v7/widget/ActionBarContainer;
      24: getfield      #25                 // Field android/support/v7/widget/ActionBarContainer.c:Landroid/graphics/drawable/Drawable;
      27: astore_2
      28: aload_2
      29: aload_1
      30: invokevirtual #29                 // Method android/graphics/drawable/Drawable.getOutline:(Landroid/graphics/Outline;)V
      33: return
      34: aload_0
      35: getfield      #15                 // Field a:Landroid/support/v7/widget/ActionBarContainer;
      38: getfield      #31                 // Field android/support/v7/widget/ActionBarContainer.a:Landroid/graphics/drawable/Drawable;
      41: ifnull        55
      44: aload_0
      45: getfield      #15                 // Field a:Landroid/support/v7/widget/ActionBarContainer;
      48: getfield      #31                 // Field android/support/v7/widget/ActionBarContainer.a:Landroid/graphics/drawable/Drawable;
      51: astore_2
      52: goto          28
      55: return
}
