public class android.support.v7.widget.CardView extends android.widget.FrameLayout {
  int a;

  int b;

  final android.graphics.Rect c;

  final android.graphics.Rect d;

  static {};
    Code:
       0: iconst_1
       1: newarray       int
       3: dup
       4: iconst_0
       5: ldc           #24                 // int 16842801
       7: iastore
       8: putstatic     #26                 // Field e:[I
      11: getstatic     #31                 // Field android/os/Build$VERSION.SDK_INT:I
      14: bipush        21
      16: if_icmplt     34
      19: new           #33                 // class android/support/v7/widget/af
      22: dup
      23: invokespecial #36                 // Method android/support/v7/widget/af."<init>":()V
      26: astore_0
      27: aload_0
      28: putstatic     #38                 // Field f:Landroid/support/v7/widget/ai;
      31: goto          64
      34: getstatic     #31                 // Field android/os/Build$VERSION.SDK_INT:I
      37: bipush        17
      39: if_icmplt     53
      42: new           #40                 // class android/support/v7/widget/ae
      45: dup
      46: invokespecial #41                 // Method android/support/v7/widget/ae."<init>":()V
      49: astore_0
      50: goto          27
      53: new           #43                 // class android/support/v7/widget/ag
      56: dup
      57: invokespecial #44                 // Method android/support/v7/widget/ag."<init>":()V
      60: astore_0
      61: goto          27
      64: getstatic     #38                 // Field f:Landroid/support/v7/widget/ai;
      67: invokeinterface #48,  1           // InterfaceMethod android/support/v7/widget/ai.a:()V
      72: return

  public android.support.v7.widget.CardView(android.content.Context);
    Code:
       0: aload_0
       1: aload_1
       2: aconst_null
       3: invokespecial #53                 // Method "<init>":(Landroid/content/Context;Landroid/util/AttributeSet;)V
       6: return

  public android.support.v7.widget.CardView(android.content.Context, android.util.AttributeSet);
    Code:
       0: aload_0
       1: aload_1
       2: aload_2
       3: getstatic     #58                 // Field android/support/v7/b/a$a.cardViewStyle:I
       6: invokespecial #61                 // Method "<init>":(Landroid/content/Context;Landroid/util/AttributeSet;I)V
       9: return

  public android.support.v7.widget.CardView(android.content.Context, android.util.AttributeSet, int);
    Code:
       0: aload_0
       1: aload_1
       2: aload_2
       3: iload_3
       4: invokespecial #62                 // Method android/widget/FrameLayout."<init>":(Landroid/content/Context;Landroid/util/AttributeSet;I)V
       7: aload_0
       8: new           #64                 // class android/graphics/Rect
      11: dup
      12: invokespecial #65                 // Method android/graphics/Rect."<init>":()V
      15: putfield      #67                 // Field c:Landroid/graphics/Rect;
      18: aload_0
      19: new           #64                 // class android/graphics/Rect
      22: dup
      23: invokespecial #65                 // Method android/graphics/Rect."<init>":()V
      26: putfield      #69                 // Field d:Landroid/graphics/Rect;
      29: aload_0
      30: new           #6                  // class android/support/v7/widget/CardView$1
      33: dup
      34: aload_0
      35: invokespecial #72                 // Method android/support/v7/widget/CardView$1."<init>":(Landroid/support/v7/widget/CardView;)V
      38: putfield      #74                 // Field i:Landroid/support/v7/widget/ah;
      41: aload_1
      42: aload_2
      43: getstatic     #79                 // Field android/support/v7/b/a$e.CardView:[I
      46: iload_3
      47: getstatic     #83                 // Field android/support/v7/b/a$d.CardView:I
      50: invokevirtual #89                 // Method android/content/Context.obtainStyledAttributes:(Landroid/util/AttributeSet;[III)Landroid/content/res/TypedArray;
      53: astore        7
      55: aload         7
      57: getstatic     #92                 // Field android/support/v7/b/a$e.CardView_cardBackgroundColor:I
      60: invokevirtual #98                 // Method android/content/res/TypedArray.hasValue:(I)Z
      63: ifeq          78
      66: aload         7
      68: getstatic     #92                 // Field android/support/v7/b/a$e.CardView_cardBackgroundColor:I
      71: invokevirtual #102                // Method android/content/res/TypedArray.getColorStateList:(I)Landroid/content/res/ColorStateList;
      74: astore_2
      75: goto          156
      78: aload_0
      79: invokevirtual #106                // Method getContext:()Landroid/content/Context;
      82: getstatic     #26                 // Field e:[I
      85: invokevirtual #109                // Method android/content/Context.obtainStyledAttributes:([I)Landroid/content/res/TypedArray;
      88: astore_2
      89: aload_2
      90: iconst_0
      91: iconst_0
      92: invokevirtual #113                // Method android/content/res/TypedArray.getColor:(II)I
      95: istore_3
      96: aload_2
      97: invokevirtual #116                // Method android/content/res/TypedArray.recycle:()V
     100: iconst_3
     101: newarray       float
     103: astore_2
     104: iload_3
     105: aload_2
     106: invokestatic  #122                // Method android/graphics/Color.colorToHSV:(I[F)V
     109: aload_2
     110: iconst_2
     111: faload
     112: ldc           #123                // float 0.5f
     114: fcmpl
     115: ifle          136
     118: aload_0
     119: invokevirtual #127                // Method getResources:()Landroid/content/res/Resources;
     122: astore_2
     123: getstatic     #132                // Field android/support/v7/b/a$b.cardview_light_background:I
     126: istore_3
     127: aload_2
     128: iload_3
     129: invokevirtual #137                // Method android/content/res/Resources.getColor:(I)I
     132: istore_3
     133: goto          148
     136: aload_0
     137: invokevirtual #127                // Method getResources:()Landroid/content/res/Resources;
     140: astore_2
     141: getstatic     #140                // Field android/support/v7/b/a$b.cardview_dark_background:I
     144: istore_3
     145: goto          127
     148: iload_3
     149: invokestatic  #145                // Method android/content/res/ColorStateList.valueOf:(I)Landroid/content/res/ColorStateList;
     152: astore_2
     153: goto          75
     156: aload         7
     158: getstatic     #148                // Field android/support/v7/b/a$e.CardView_cardCornerRadius:I
     161: fconst_0
     162: invokevirtual #152                // Method android/content/res/TypedArray.getDimension:(IF)F
     165: fstore        6
     167: aload         7
     169: getstatic     #155                // Field android/support/v7/b/a$e.CardView_cardElevation:I
     172: fconst_0
     173: invokevirtual #152                // Method android/content/res/TypedArray.getDimension:(IF)F
     176: fstore        5
     178: aload         7
     180: getstatic     #158                // Field android/support/v7/b/a$e.CardView_cardMaxElevation:I
     183: fconst_0
     184: invokevirtual #152                // Method android/content/res/TypedArray.getDimension:(IF)F
     187: fstore        4
     189: aload_0
     190: aload         7
     192: getstatic     #161                // Field android/support/v7/b/a$e.CardView_cardUseCompatPadding:I
     195: iconst_0
     196: invokevirtual #165                // Method android/content/res/TypedArray.getBoolean:(IZ)Z
     199: putfield      #167                // Field g:Z
     202: aload_0
     203: aload         7
     205: getstatic     #170                // Field android/support/v7/b/a$e.CardView_cardPreventCornerOverlap:I
     208: iconst_1
     209: invokevirtual #165                // Method android/content/res/TypedArray.getBoolean:(IZ)Z
     212: putfield      #172                // Field h:Z
     215: aload         7
     217: getstatic     #175                // Field android/support/v7/b/a$e.CardView_contentPadding:I
     220: iconst_0
     221: invokevirtual #178                // Method android/content/res/TypedArray.getDimensionPixelSize:(II)I
     224: istore_3
     225: aload_0
     226: getfield      #67                 // Field c:Landroid/graphics/Rect;
     229: aload         7
     231: getstatic     #181                // Field android/support/v7/b/a$e.CardView_contentPaddingLeft:I
     234: iload_3
     235: invokevirtual #178                // Method android/content/res/TypedArray.getDimensionPixelSize:(II)I
     238: putfield      #184                // Field android/graphics/Rect.left:I
     241: aload_0
     242: getfield      #67                 // Field c:Landroid/graphics/Rect;
     245: aload         7
     247: getstatic     #187                // Field android/support/v7/b/a$e.CardView_contentPaddingTop:I
     250: iload_3
     251: invokevirtual #178                // Method android/content/res/TypedArray.getDimensionPixelSize:(II)I
     254: putfield      #190                // Field android/graphics/Rect.top:I
     257: aload_0
     258: getfield      #67                 // Field c:Landroid/graphics/Rect;
     261: aload         7
     263: getstatic     #193                // Field android/support/v7/b/a$e.CardView_contentPaddingRight:I
     266: iload_3
     267: invokevirtual #178                // Method android/content/res/TypedArray.getDimensionPixelSize:(II)I
     270: putfield      #196                // Field android/graphics/Rect.right:I
     273: aload_0
     274: getfield      #67                 // Field c:Landroid/graphics/Rect;
     277: aload         7
     279: getstatic     #199                // Field android/support/v7/b/a$e.CardView_contentPaddingBottom:I
     282: iload_3
     283: invokevirtual #178                // Method android/content/res/TypedArray.getDimensionPixelSize:(II)I
     286: putfield      #202                // Field android/graphics/Rect.bottom:I
     289: fload         5
     291: fload         4
     293: fcmpl
     294: ifle          304
     297: fload         5
     299: fstore        4
     301: goto          304
     304: aload_0
     305: aload         7
     307: getstatic     #205                // Field android/support/v7/b/a$e.CardView_android_minWidth:I
     310: iconst_0
     311: invokevirtual #178                // Method android/content/res/TypedArray.getDimensionPixelSize:(II)I
     314: putfield      #207                // Field a:I
     317: aload_0
     318: aload         7
     320: getstatic     #210                // Field android/support/v7/b/a$e.CardView_android_minHeight:I
     323: iconst_0
     324: invokevirtual #178                // Method android/content/res/TypedArray.getDimensionPixelSize:(II)I
     327: putfield      #212                // Field b:I
     330: aload         7
     332: invokevirtual #116                // Method android/content/res/TypedArray.recycle:()V
     335: getstatic     #38                 // Field f:Landroid/support/v7/widget/ai;
     338: aload_0
     339: getfield      #74                 // Field i:Landroid/support/v7/widget/ah;
     342: aload_1
     343: aload_2
     344: fload         6
     346: fload         5
     348: fload         4
     350: invokeinterface #215,  7          // InterfaceMethod android/support/v7/widget/ai.a:(Landroid/support/v7/widget/ah;Landroid/content/Context;Landroid/content/res/ColorStateList;FFF)V
     355: return

  static void a(android.support.v7.widget.CardView, int);
    Code:
       0: aload_0
       1: iload_1
       2: invokespecial #220                // Method android/widget/FrameLayout.setMinimumWidth:(I)V
       5: return

  static void a(android.support.v7.widget.CardView, int, int, int, int);
    Code:
       0: aload_0
       1: iload_1
       2: iload_2
       3: iload_3
       4: iload         4
       6: invokespecial #225                // Method android/widget/FrameLayout.setPadding:(IIII)V
       9: return

  static void b(android.support.v7.widget.CardView, int);
    Code:
       0: aload_0
       1: iload_1
       2: invokespecial #228                // Method android/widget/FrameLayout.setMinimumHeight:(I)V
       5: return

  public android.content.res.ColorStateList getCardBackgroundColor();
    Code:
       0: getstatic     #38                 // Field f:Landroid/support/v7/widget/ai;
       3: aload_0
       4: getfield      #74                 // Field i:Landroid/support/v7/widget/ah;
       7: invokeinterface #233,  2          // InterfaceMethod android/support/v7/widget/ai.i:(Landroid/support/v7/widget/ah;)Landroid/content/res/ColorStateList;
      12: areturn

  public float getCardElevation();
    Code:
       0: getstatic     #38                 // Field f:Landroid/support/v7/widget/ai;
       3: aload_0
       4: getfield      #74                 // Field i:Landroid/support/v7/widget/ah;
       7: invokeinterface #238,  2          // InterfaceMethod android/support/v7/widget/ai.e:(Landroid/support/v7/widget/ah;)F
      12: freturn

  public int getContentPaddingBottom();
    Code:
       0: aload_0
       1: getfield      #67                 // Field c:Landroid/graphics/Rect;
       4: getfield      #202                // Field android/graphics/Rect.bottom:I
       7: ireturn

  public int getContentPaddingLeft();
    Code:
       0: aload_0
       1: getfield      #67                 // Field c:Landroid/graphics/Rect;
       4: getfield      #184                // Field android/graphics/Rect.left:I
       7: ireturn

  public int getContentPaddingRight();
    Code:
       0: aload_0
       1: getfield      #67                 // Field c:Landroid/graphics/Rect;
       4: getfield      #196                // Field android/graphics/Rect.right:I
       7: ireturn

  public int getContentPaddingTop();
    Code:
       0: aload_0
       1: getfield      #67                 // Field c:Landroid/graphics/Rect;
       4: getfield      #190                // Field android/graphics/Rect.top:I
       7: ireturn

  public float getMaxCardElevation();
    Code:
       0: getstatic     #38                 // Field f:Landroid/support/v7/widget/ai;
       3: aload_0
       4: getfield      #74                 // Field i:Landroid/support/v7/widget/ah;
       7: invokeinterface #246,  2          // InterfaceMethod android/support/v7/widget/ai.a:(Landroid/support/v7/widget/ah;)F
      12: freturn

  public boolean getPreventCornerOverlap();
    Code:
       0: aload_0
       1: getfield      #172                // Field h:Z
       4: ireturn

  public float getRadius();
    Code:
       0: getstatic     #38                 // Field f:Landroid/support/v7/widget/ai;
       3: aload_0
       4: getfield      #74                 // Field i:Landroid/support/v7/widget/ah;
       7: invokeinterface #251,  2          // InterfaceMethod android/support/v7/widget/ai.d:(Landroid/support/v7/widget/ah;)F
      12: freturn

  public boolean getUseCompatPadding();
    Code:
       0: aload_0
       1: getfield      #167                // Field g:Z
       4: ireturn

  protected void onMeasure(int, int);
    Code:
       0: iload_1
       1: istore        4
       3: iload_2
       4: istore_3
       5: getstatic     #38                 // Field f:Landroid/support/v7/widget/ai;
       8: instanceof    #33                 // class android/support/v7/widget/af
      11: ifne          124
      14: iload_1
      15: invokestatic  #259                // Method android/view/View$MeasureSpec.getMode:(I)I
      18: istore_3
      19: iload_3
      20: ldc_w         #260                // int -2147483648
      23: if_icmpeq     36
      26: iload_3
      27: ldc_w         #261                // int 1073741824
      30: if_icmpeq     36
      33: goto          65
      36: getstatic     #38                 // Field f:Landroid/support/v7/widget/ai;
      39: aload_0
      40: getfield      #74                 // Field i:Landroid/support/v7/widget/ah;
      43: invokeinterface #263,  2          // InterfaceMethod android/support/v7/widget/ai.b:(Landroid/support/v7/widget/ah;)F
      48: f2d
      49: invokestatic  #269                // Method java/lang/Math.ceil:(D)D
      52: d2i
      53: iload_1
      54: invokestatic  #272                // Method android/view/View$MeasureSpec.getSize:(I)I
      57: invokestatic  #275                // Method java/lang/Math.max:(II)I
      60: iload_3
      61: invokestatic  #278                // Method android/view/View$MeasureSpec.makeMeasureSpec:(II)I
      64: istore_1
      65: iload_2
      66: invokestatic  #259                // Method android/view/View$MeasureSpec.getMode:(I)I
      69: istore_3
      70: iload_3
      71: ldc_w         #260                // int -2147483648
      74: if_icmpeq     92
      77: iload_3
      78: ldc_w         #261                // int 1073741824
      81: if_icmpeq     92
      84: iload_1
      85: istore        4
      87: iload_2
      88: istore_3
      89: goto          124
      92: getstatic     #38                 // Field f:Landroid/support/v7/widget/ai;
      95: aload_0
      96: getfield      #74                 // Field i:Landroid/support/v7/widget/ah;
      99: invokeinterface #280,  2          // InterfaceMethod android/support/v7/widget/ai.c:(Landroid/support/v7/widget/ah;)F
     104: f2d
     105: invokestatic  #269                // Method java/lang/Math.ceil:(D)D
     108: d2i
     109: iload_2
     110: invokestatic  #272                // Method android/view/View$MeasureSpec.getSize:(I)I
     113: invokestatic  #275                // Method java/lang/Math.max:(II)I
     116: iload_3
     117: invokestatic  #278                // Method android/view/View$MeasureSpec.makeMeasureSpec:(II)I
     120: istore_3
     121: iload_1
     122: istore        4
     124: aload_0
     125: iload         4
     127: iload_3
     128: invokespecial #282                // Method android/widget/FrameLayout.onMeasure:(II)V
     131: return

  public void setCardBackgroundColor(int);
    Code:
       0: getstatic     #38                 // Field f:Landroid/support/v7/widget/ai;
       3: aload_0
       4: getfield      #74                 // Field i:Landroid/support/v7/widget/ah;
       7: iload_1
       8: invokestatic  #145                // Method android/content/res/ColorStateList.valueOf:(I)Landroid/content/res/ColorStateList;
      11: invokeinterface #286,  3          // InterfaceMethod android/support/v7/widget/ai.a:(Landroid/support/v7/widget/ah;Landroid/content/res/ColorStateList;)V
      16: return

  public void setCardBackgroundColor(android.content.res.ColorStateList);
    Code:
       0: getstatic     #38                 // Field f:Landroid/support/v7/widget/ai;
       3: aload_0
       4: getfield      #74                 // Field i:Landroid/support/v7/widget/ah;
       7: aload_1
       8: invokeinterface #286,  3          // InterfaceMethod android/support/v7/widget/ai.a:(Landroid/support/v7/widget/ah;Landroid/content/res/ColorStateList;)V
      13: return

  public void setCardElevation(float);
    Code:
       0: getstatic     #38                 // Field f:Landroid/support/v7/widget/ai;
       3: aload_0
       4: getfield      #74                 // Field i:Landroid/support/v7/widget/ah;
       7: fload_1
       8: invokeinterface #292,  3          // InterfaceMethod android/support/v7/widget/ai.c:(Landroid/support/v7/widget/ah;F)V
      13: return

  public void setMaxCardElevation(float);
    Code:
       0: getstatic     #38                 // Field f:Landroid/support/v7/widget/ai;
       3: aload_0
       4: getfield      #74                 // Field i:Landroid/support/v7/widget/ah;
       7: fload_1
       8: invokeinterface #295,  3          // InterfaceMethod android/support/v7/widget/ai.b:(Landroid/support/v7/widget/ah;F)V
      13: return

  public void setMinimumHeight(int);
    Code:
       0: aload_0
       1: iload_1
       2: putfield      #212                // Field b:I
       5: aload_0
       6: iload_1
       7: invokespecial #228                // Method android/widget/FrameLayout.setMinimumHeight:(I)V
      10: return

  public void setMinimumWidth(int);
    Code:
       0: aload_0
       1: iload_1
       2: putfield      #207                // Field a:I
       5: aload_0
       6: iload_1
       7: invokespecial #220                // Method android/widget/FrameLayout.setMinimumWidth:(I)V
      10: return

  public void setPadding(int, int, int, int);
    Code:
       0: return

  public void setPaddingRelative(int, int, int, int);
    Code:
       0: return

  public void setPreventCornerOverlap(boolean);
    Code:
       0: iload_1
       1: aload_0
       2: getfield      #172                // Field h:Z
       5: if_icmpeq     25
       8: aload_0
       9: iload_1
      10: putfield      #172                // Field h:Z
      13: getstatic     #38                 // Field f:Landroid/support/v7/widget/ai;
      16: aload_0
      17: getfield      #74                 // Field i:Landroid/support/v7/widget/ah;
      20: invokeinterface #301,  2          // InterfaceMethod android/support/v7/widget/ai.h:(Landroid/support/v7/widget/ah;)V
      25: return

  public void setRadius(float);
    Code:
       0: getstatic     #38                 // Field f:Landroid/support/v7/widget/ai;
       3: aload_0
       4: getfield      #74                 // Field i:Landroid/support/v7/widget/ah;
       7: fload_1
       8: invokeinterface #304,  3          // InterfaceMethod android/support/v7/widget/ai.a:(Landroid/support/v7/widget/ah;F)V
      13: return

  public void setUseCompatPadding(boolean);
    Code:
       0: aload_0
       1: getfield      #167                // Field g:Z
       4: iload_1
       5: if_icmpeq     25
       8: aload_0
       9: iload_1
      10: putfield      #167                // Field g:Z
      13: getstatic     #38                 // Field f:Landroid/support/v7/widget/ai;
      16: aload_0
      17: getfield      #74                 // Field i:Landroid/support/v7/widget/ah;
      20: invokeinterface #307,  2          // InterfaceMethod android/support/v7/widget/ai.g:(Landroid/support/v7/widget/ah;)V
      25: return
}
