class android.support.v7.widget.CardView$1 implements android.support.v7.widget.ah {
  final android.support.v7.widget.CardView a;

  android.support.v7.widget.CardView$1(android.support.v7.widget.CardView);
    Code:
       0: aload_0
       1: aload_1
       2: putfield      #16                 // Field a:Landroid/support/v7/widget/CardView;
       5: aload_0
       6: invokespecial #19                 // Method java/lang/Object."<init>":()V
       9: return

  public void a(int, int);
    Code:
       0: iload_1
       1: aload_0
       2: getfield      #16                 // Field a:Landroid/support/v7/widget/CardView;
       5: getfield      #24                 // Field android/support/v7/widget/CardView.a:I
       8: if_icmple     19
      11: aload_0
      12: getfield      #16                 // Field a:Landroid/support/v7/widget/CardView;
      15: iload_1
      16: invokestatic  #27                 // Method android/support/v7/widget/CardView.a:(Landroid/support/v7/widget/CardView;I)V
      19: iload_2
      20: aload_0
      21: getfield      #16                 // Field a:Landroid/support/v7/widget/CardView;
      24: getfield      #29                 // Field android/support/v7/widget/CardView.b:I
      27: if_icmple     38
      30: aload_0
      31: getfield      #16                 // Field a:Landroid/support/v7/widget/CardView;
      34: iload_2
      35: invokestatic  #31                 // Method android/support/v7/widget/CardView.b:(Landroid/support/v7/widget/CardView;I)V
      38: return

  public void a(int, int, int, int);
    Code:
       0: aload_0
       1: getfield      #16                 // Field a:Landroid/support/v7/widget/CardView;
       4: getfield      #36                 // Field android/support/v7/widget/CardView.d:Landroid/graphics/Rect;
       7: iload_1
       8: iload_2
       9: iload_3
      10: iload         4
      12: invokevirtual #41                 // Method android/graphics/Rect.set:(IIII)V
      15: aload_0
      16: getfield      #16                 // Field a:Landroid/support/v7/widget/CardView;
      19: iload_1
      20: aload_0
      21: getfield      #16                 // Field a:Landroid/support/v7/widget/CardView;
      24: getfield      #44                 // Field android/support/v7/widget/CardView.c:Landroid/graphics/Rect;
      27: getfield      #47                 // Field android/graphics/Rect.left:I
      30: iadd
      31: iload_2
      32: aload_0
      33: getfield      #16                 // Field a:Landroid/support/v7/widget/CardView;
      36: getfield      #44                 // Field android/support/v7/widget/CardView.c:Landroid/graphics/Rect;
      39: getfield      #50                 // Field android/graphics/Rect.top:I
      42: iadd
      43: iload_3
      44: aload_0
      45: getfield      #16                 // Field a:Landroid/support/v7/widget/CardView;
      48: getfield      #44                 // Field android/support/v7/widget/CardView.c:Landroid/graphics/Rect;
      51: getfield      #53                 // Field android/graphics/Rect.right:I
      54: iadd
      55: iload         4
      57: aload_0
      58: getfield      #16                 // Field a:Landroid/support/v7/widget/CardView;
      61: getfield      #44                 // Field android/support/v7/widget/CardView.c:Landroid/graphics/Rect;
      64: getfield      #56                 // Field android/graphics/Rect.bottom:I
      67: iadd
      68: invokestatic  #59                 // Method android/support/v7/widget/CardView.a:(Landroid/support/v7/widget/CardView;IIII)V
      71: return

  public void a(android.graphics.drawable.Drawable);
    Code:
       0: aload_0
       1: aload_1
       2: putfield      #62                 // Field b:Landroid/graphics/drawable/Drawable;
       5: aload_0
       6: getfield      #16                 // Field a:Landroid/support/v7/widget/CardView;
       9: aload_1
      10: invokevirtual #65                 // Method android/support/v7/widget/CardView.setBackgroundDrawable:(Landroid/graphics/drawable/Drawable;)V
      13: return

  public boolean a();
    Code:
       0: aload_0
       1: getfield      #16                 // Field a:Landroid/support/v7/widget/CardView;
       4: invokevirtual #69                 // Method android/support/v7/widget/CardView.getUseCompatPadding:()Z
       7: ireturn

  public boolean b();
    Code:
       0: aload_0
       1: getfield      #16                 // Field a:Landroid/support/v7/widget/CardView;
       4: invokevirtual #72                 // Method android/support/v7/widget/CardView.getPreventCornerOverlap:()Z
       7: ireturn

  public android.graphics.drawable.Drawable c();
    Code:
       0: aload_0
       1: getfield      #62                 // Field b:Landroid/graphics/drawable/Drawable;
       4: areturn

  public android.view.View d();
    Code:
       0: aload_0
       1: getfield      #16                 // Field a:Landroid/support/v7/widget/CardView;
       4: areturn
}
