class android.support.v7.widget.d extends android.support.v7.view.menu.b implements android.support.v4.view.c$a {
  android.support.v7.widget.d$d g;

  android.support.v7.widget.d$e h;

  android.support.v7.widget.d$a i;

  android.support.v7.widget.d$c j;

  final android.support.v7.widget.d$f k;

  int l;

  public android.support.v7.widget.d(android.content.Context);
    Code:
       0: aload_0
       1: aload_1
       2: getstatic     #69                 // Field android/support/v7/a/a$g.abc_action_menu_layout:I
       5: getstatic     #72                 // Field android/support/v7/a/a$g.abc_action_menu_item_layout:I
       8: invokespecial #75                 // Method android/support/v7/view/menu/b."<init>":(Landroid/content/Context;II)V
      11: aload_0
      12: new           #77                 // class android/util/SparseBooleanArray
      15: dup
      16: invokespecial #80                 // Method android/util/SparseBooleanArray."<init>":()V
      19: putfield      #82                 // Field y:Landroid/util/SparseBooleanArray;
      22: aload_0
      23: new           #25                 // class android/support/v7/widget/d$f
      26: dup
      27: aload_0
      28: invokespecial #85                 // Method android/support/v7/widget/d$f."<init>":(Landroid/support/v7/widget/d;)V
      31: putfield      #87                 // Field k:Landroid/support/v7/widget/d$f;
      34: return

  static android.support.v7.view.menu.h a(android.support.v7.widget.d);
    Code:
       0: aload_0
       1: getfield      #92                 // Field c:Landroid/support/v7/view/menu/h;
       4: areturn

  static android.support.v7.view.menu.h b(android.support.v7.widget.d);
    Code:
       0: aload_0
       1: getfield      #92                 // Field c:Landroid/support/v7/view/menu/h;
       4: areturn

  static android.support.v7.view.menu.p c(android.support.v7.widget.d);
    Code:
       0: aload_0
       1: getfield      #96                 // Field f:Landroid/support/v7/view/menu/p;
       4: areturn

  static android.support.v7.view.menu.h d(android.support.v7.widget.d);
    Code:
       0: aload_0
       1: getfield      #92                 // Field c:Landroid/support/v7/view/menu/h;
       4: areturn

  static android.support.v7.view.menu.h e(android.support.v7.widget.d);
    Code:
       0: aload_0
       1: getfield      #92                 // Field c:Landroid/support/v7/view/menu/h;
       4: areturn

  static android.support.v7.view.menu.p f(android.support.v7.widget.d);
    Code:
       0: aload_0
       1: getfield      #96                 // Field f:Landroid/support/v7/view/menu/p;
       4: areturn

  public android.support.v7.view.menu.p a(android.view.ViewGroup);
    Code:
       0: aload_0
       1: getfield      #96                 // Field f:Landroid/support/v7/view/menu/p;
       4: astore_2
       5: aload_0
       6: aload_1
       7: invokespecial #116                // Method android/support/v7/view/menu/b.a:(Landroid/view/ViewGroup;)Landroid/support/v7/view/menu/p;
      10: astore_1
      11: aload_2
      12: aload_1
      13: if_acmpeq     24
      16: aload_1
      17: checkcast     #118                // class android/support/v7/widget/ActionMenuView
      20: aload_0
      21: invokevirtual #121                // Method android/support/v7/widget/ActionMenuView.setPresenter:(Landroid/support/v7/widget/d;)V
      24: aload_1
      25: areturn

  public android.view.View a(android.support.v7.view.menu.j, android.view.View, android.view.ViewGroup);
    Code:
       0: aload_1
       1: invokevirtual #128                // Method android/support/v7/view/menu/j.getActionView:()Landroid/view/View;
       4: astore        5
       6: aload         5
       8: ifnull        18
      11: aload_1
      12: invokevirtual #131                // Method android/support/v7/view/menu/j.n:()Z
      15: ifeq          27
      18: aload_0
      19: aload_1
      20: aload_2
      21: aload_3
      22: invokespecial #133                // Method android/support/v7/view/menu/b.a:(Landroid/support/v7/view/menu/j;Landroid/view/View;Landroid/view/ViewGroup;)Landroid/view/View;
      25: astore        5
      27: aload_1
      28: invokevirtual #136                // Method android/support/v7/view/menu/j.isActionViewExpanded:()Z
      31: ifeq          41
      34: bipush        8
      36: istore        4
      38: goto          44
      41: iconst_0
      42: istore        4
      44: aload         5
      46: iload         4
      48: invokevirtual #142                // Method android/view/View.setVisibility:(I)V
      51: aload_3
      52: checkcast     #118                // class android/support/v7/widget/ActionMenuView
      55: astore_1
      56: aload         5
      58: invokevirtual #146                // Method android/view/View.getLayoutParams:()Landroid/view/ViewGroup$LayoutParams;
      61: astore_2
      62: aload_1
      63: aload_2
      64: invokevirtual #150                // Method android/support/v7/widget/ActionMenuView.checkLayoutParams:(Landroid/view/ViewGroup$LayoutParams;)Z
      67: ifne          80
      70: aload         5
      72: aload_1
      73: aload_2
      74: invokevirtual #153                // Method android/support/v7/widget/ActionMenuView.a:(Landroid/view/ViewGroup$LayoutParams;)Landroid/support/v7/widget/ActionMenuView$c;
      77: invokevirtual #157                // Method android/view/View.setLayoutParams:(Landroid/view/ViewGroup$LayoutParams;)V
      80: aload         5
      82: areturn

  public void a(android.content.Context, android.support.v7.view.menu.h);
    Code:
       0: aload_0
       1: aload_1
       2: aload_2
       3: invokespecial #160                // Method android/support/v7/view/menu/b.a:(Landroid/content/Context;Landroid/support/v7/view/menu/h;)V
       6: aload_1
       7: invokevirtual #166                // Method android/content/Context.getResources:()Landroid/content/res/Resources;
      10: astore_2
      11: aload_1
      12: invokestatic  #171                // Method android/support/v7/view/a.a:(Landroid/content/Context;)Landroid/support/v7/view/a;
      15: astore_1
      16: aload_0
      17: getfield      #173                // Field p:Z
      20: ifne          31
      23: aload_0
      24: aload_1
      25: invokevirtual #175                // Method android/support/v7/view/a.b:()Z
      28: putfield      #177                // Field o:Z
      31: aload_0
      32: getfield      #179                // Field v:Z
      35: ifne          46
      38: aload_0
      39: aload_1
      40: invokevirtual #181                // Method android/support/v7/view/a.c:()I
      43: putfield      #183                // Field q:I
      46: aload_0
      47: getfield      #185                // Field t:Z
      50: ifne          61
      53: aload_0
      54: aload_1
      55: invokevirtual #187                // Method android/support/v7/view/a.a:()I
      58: putfield      #189                // Field s:I
      61: aload_0
      62: getfield      #183                // Field q:I
      65: istore_3
      66: aload_0
      67: getfield      #177                // Field o:Z
      70: ifeq          155
      73: aload_0
      74: getfield      #191                // Field g:Landroid/support/v7/widget/d$d;
      77: ifnonnull     142
      80: aload_0
      81: new           #17                 // class android/support/v7/widget/d$d
      84: dup
      85: aload_0
      86: aload_0
      87: getfield      #194                // Field a:Landroid/content/Context;
      90: invokespecial #197                // Method android/support/v7/widget/d$d."<init>":(Landroid/support/v7/widget/d;Landroid/content/Context;)V
      93: putfield      #191                // Field g:Landroid/support/v7/widget/d$d;
      96: aload_0
      97: getfield      #199                // Field n:Z
     100: ifeq          124
     103: aload_0
     104: getfield      #191                // Field g:Landroid/support/v7/widget/d$d;
     107: aload_0
     108: getfield      #201                // Field m:Landroid/graphics/drawable/Drawable;
     111: invokevirtual #205                // Method android/support/v7/widget/d$d.setImageDrawable:(Landroid/graphics/drawable/Drawable;)V
     114: aload_0
     115: aconst_null
     116: putfield      #201                // Field m:Landroid/graphics/drawable/Drawable;
     119: aload_0
     120: iconst_0
     121: putfield      #199                // Field n:Z
     124: iconst_0
     125: iconst_0
     126: invokestatic  #211                // Method android/view/View$MeasureSpec.makeMeasureSpec:(II)I
     129: istore        4
     131: aload_0
     132: getfield      #191                // Field g:Landroid/support/v7/widget/d$d;
     135: iload         4
     137: iload         4
     139: invokevirtual #215                // Method android/support/v7/widget/d$d.measure:(II)V
     142: iload_3
     143: aload_0
     144: getfield      #191                // Field g:Landroid/support/v7/widget/d$d;
     147: invokevirtual #218                // Method android/support/v7/widget/d$d.getMeasuredWidth:()I
     150: isub
     151: istore_3
     152: goto          160
     155: aload_0
     156: aconst_null
     157: putfield      #191                // Field g:Landroid/support/v7/widget/d$d;
     160: aload_0
     161: iload_3
     162: putfield      #220                // Field r:I
     165: aload_0
     166: aload_2
     167: invokevirtual #226                // Method android/content/res/Resources.getDisplayMetrics:()Landroid/util/DisplayMetrics;
     170: getfield      #232                // Field android/util/DisplayMetrics.density:F
     173: ldc           #233                // float 56.0f
     175: fmul
     176: f2i
     177: putfield      #235                // Field x:I
     180: aload_0
     181: aconst_null
     182: putfield      #237                // Field z:Landroid/view/View;
     185: return

  public void a(android.content.res.Configuration);
    Code:
       0: aload_0
       1: getfield      #185                // Field t:Z
       4: ifne          21
       7: aload_0
       8: aload_0
       9: getfield      #240                // Field b:Landroid/content/Context;
      12: invokestatic  #171                // Method android/support/v7/view/a.a:(Landroid/content/Context;)Landroid/support/v7/view/a;
      15: invokevirtual #187                // Method android/support/v7/view/a.a:()I
      18: putfield      #189                // Field s:I
      21: aload_0
      22: getfield      #92                 // Field c:Landroid/support/v7/view/menu/h;
      25: ifnull        36
      28: aload_0
      29: getfield      #92                 // Field c:Landroid/support/v7/view/menu/h;
      32: iconst_1
      33: invokevirtual #245                // Method android/support/v7/view/menu/h.a:(Z)V
      36: return

  public void a(android.graphics.drawable.Drawable);
    Code:
       0: aload_0
       1: getfield      #191                // Field g:Landroid/support/v7/widget/d$d;
       4: ifnull        16
       7: aload_0
       8: getfield      #191                // Field g:Landroid/support/v7/widget/d$d;
      11: aload_1
      12: invokevirtual #205                // Method android/support/v7/widget/d$d.setImageDrawable:(Landroid/graphics/drawable/Drawable;)V
      15: return
      16: aload_0
      17: iconst_1
      18: putfield      #199                // Field n:Z
      21: aload_0
      22: aload_1
      23: putfield      #201                // Field m:Landroid/graphics/drawable/Drawable;
      26: return

  public void a(android.os.Parcelable);
    Code:
       0: aload_1
       1: instanceof    #28                 // class android/support/v7/widget/d$g
       4: ifne          8
       7: return
       8: aload_1
       9: checkcast     #28                 // class android/support/v7/widget/d$g
      12: astore_1
      13: aload_1
      14: getfield      #248                // Field android/support/v7/widget/d$g.a:I
      17: ifle          50
      20: aload_0
      21: getfield      #92                 // Field c:Landroid/support/v7/view/menu/h;
      24: aload_1
      25: getfield      #248                // Field android/support/v7/widget/d$g.a:I
      28: invokevirtual #252                // Method android/support/v7/view/menu/h.findItem:(I)Landroid/view/MenuItem;
      31: astore_1
      32: aload_1
      33: ifnull        50
      36: aload_0
      37: aload_1
      38: invokeinterface #258,  1          // InterfaceMethod android/view/MenuItem.getSubMenu:()Landroid/view/SubMenu;
      43: checkcast     #260                // class android/support/v7/view/menu/u
      46: invokevirtual #263                // Method a:(Landroid/support/v7/view/menu/u;)Z
      49: pop
      50: return

  public void a(android.support.v7.view.menu.h, boolean);
    Code:
       0: aload_0
       1: invokevirtual #266                // Method h:()Z
       4: pop
       5: aload_0
       6: aload_1
       7: iload_2
       8: invokespecial #268                // Method android/support/v7/view/menu/b.a:(Landroid/support/v7/view/menu/h;Z)V
      11: return

  public void a(android.support.v7.view.menu.j, android.support.v7.view.menu.p$a);
    Code:
       0: aload_2
       1: aload_1
       2: iconst_0
       3: invokeinterface #272,  3          // InterfaceMethod android/support/v7/view/menu/p$a.a:(Landroid/support/v7/view/menu/j;I)V
       8: aload_0
       9: getfield      #96                 // Field f:Landroid/support/v7/view/menu/p;
      12: checkcast     #118                // class android/support/v7/widget/ActionMenuView
      15: astore_1
      16: aload_2
      17: checkcast     #274                // class android/support/v7/view/menu/ActionMenuItemView
      20: astore_2
      21: aload_2
      22: aload_1
      23: invokevirtual #278                // Method android/support/v7/view/menu/ActionMenuItemView.setItemInvoker:(Landroid/support/v7/view/menu/h$b;)V
      26: aload_0
      27: getfield      #280                // Field A:Landroid/support/v7/widget/d$b;
      30: ifnonnull     45
      33: aload_0
      34: new           #11                 // class android/support/v7/widget/d$b
      37: dup
      38: aload_0
      39: invokespecial #281                // Method android/support/v7/widget/d$b."<init>":(Landroid/support/v7/widget/d;)V
      42: putfield      #280                // Field A:Landroid/support/v7/widget/d$b;
      45: aload_2
      46: aload_0
      47: getfield      #280                // Field A:Landroid/support/v7/widget/d$b;
      50: invokevirtual #285                // Method android/support/v7/view/menu/ActionMenuItemView.setPopupCallback:(Landroid/support/v7/view/menu/ActionMenuItemView$b;)V
      53: return

  public void a(android.support.v7.widget.ActionMenuView);
    Code:
       0: aload_0
       1: aload_1
       2: putfield      #96                 // Field f:Landroid/support/v7/view/menu/p;
       5: aload_1
       6: aload_0
       7: getfield      #92                 // Field c:Landroid/support/v7/view/menu/h;
      10: invokevirtual #289                // Method android/support/v7/widget/ActionMenuView.a:(Landroid/support/v7/view/menu/h;)V
      13: return

  public void a(boolean);
    Code:
       0: aload_0
       1: iload_1
       2: invokespecial #290                // Method android/support/v7/view/menu/b.a:(Z)V
       5: aload_0
       6: getfield      #96                 // Field f:Landroid/support/v7/view/menu/p;
       9: checkcast     #138                // class android/view/View
      12: invokevirtual #293                // Method android/view/View.requestLayout:()V
      15: aload_0
      16: getfield      #92                 // Field c:Landroid/support/v7/view/menu/h;
      19: astore        5
      21: iconst_0
      22: istore_3
      23: aload         5
      25: ifnull        84
      28: aload_0
      29: getfield      #92                 // Field c:Landroid/support/v7/view/menu/h;
      32: invokevirtual #296                // Method android/support/v7/view/menu/h.k:()Ljava/util/ArrayList;
      35: astore        5
      37: aload         5
      39: invokevirtual #301                // Method java/util/ArrayList.size:()I
      42: istore        4
      44: iconst_0
      45: istore_2
      46: iload_2
      47: iload         4
      49: if_icmpge     84
      52: aload         5
      54: iload_2
      55: invokevirtual #305                // Method java/util/ArrayList.get:(I)Ljava/lang/Object;
      58: checkcast     #124                // class android/support/v7/view/menu/j
      61: invokevirtual #308                // Method android/support/v7/view/menu/j.a:()Landroid/support/v4/view/c;
      64: astore        6
      66: aload         6
      68: ifnull        77
      71: aload         6
      73: aload_0
      74: invokevirtual #313                // Method android/support/v4/view/c.a:(Landroid/support/v4/view/c$a;)V
      77: iload_2
      78: iconst_1
      79: iadd
      80: istore_2
      81: goto          46
      84: aload_0
      85: getfield      #92                 // Field c:Landroid/support/v7/view/menu/h;
      88: ifnull        103
      91: aload_0
      92: getfield      #92                 // Field c:Landroid/support/v7/view/menu/h;
      95: invokevirtual #315                // Method android/support/v7/view/menu/h.l:()Ljava/util/ArrayList;
      98: astore        5
     100: goto          106
     103: aconst_null
     104: astore        5
     106: iload_3
     107: istore_2
     108: aload_0
     109: getfield      #177                // Field o:Z
     112: ifeq          162
     115: iload_3
     116: istore_2
     117: aload         5
     119: ifnull        162
     122: aload         5
     124: invokevirtual #301                // Method java/util/ArrayList.size:()I
     127: istore        4
     129: iload         4
     131: iconst_1
     132: if_icmpne     153
     135: aload         5
     137: iconst_0
     138: invokevirtual #305                // Method java/util/ArrayList.get:(I)Ljava/lang/Object;
     141: checkcast     #124                // class android/support/v7/view/menu/j
     144: invokevirtual #136                // Method android/support/v7/view/menu/j.isActionViewExpanded:()Z
     147: iconst_1
     148: ixor
     149: istore_2
     150: goto          162
     153: iload_3
     154: istore_2
     155: iload         4
     157: ifle          162
     160: iconst_1
     161: istore_2
     162: iload_2
     163: ifeq          250
     166: aload_0
     167: getfield      #191                // Field g:Landroid/support/v7/widget/d$d;
     170: ifnonnull     189
     173: aload_0
     174: new           #17                 // class android/support/v7/widget/d$d
     177: dup
     178: aload_0
     179: aload_0
     180: getfield      #194                // Field a:Landroid/content/Context;
     183: invokespecial #197                // Method android/support/v7/widget/d$d."<init>":(Landroid/support/v7/widget/d;Landroid/content/Context;)V
     186: putfield      #191                // Field g:Landroid/support/v7/widget/d$d;
     189: aload_0
     190: getfield      #191                // Field g:Landroid/support/v7/widget/d$d;
     193: invokevirtual #319                // Method android/support/v7/widget/d$d.getParent:()Landroid/view/ViewParent;
     196: checkcast     #98                 // class android/view/ViewGroup
     199: astore        5
     201: aload         5
     203: aload_0
     204: getfield      #96                 // Field f:Landroid/support/v7/view/menu/p;
     207: if_acmpeq     285
     210: aload         5
     212: ifnull        224
     215: aload         5
     217: aload_0
     218: getfield      #191                // Field g:Landroid/support/v7/widget/d$d;
     221: invokevirtual #323                // Method android/view/ViewGroup.removeView:(Landroid/view/View;)V
     224: aload_0
     225: getfield      #96                 // Field f:Landroid/support/v7/view/menu/p;
     228: checkcast     #118                // class android/support/v7/widget/ActionMenuView
     231: astore        5
     233: aload         5
     235: aload_0
     236: getfield      #191                // Field g:Landroid/support/v7/widget/d$d;
     239: aload         5
     241: invokevirtual #326                // Method android/support/v7/widget/ActionMenuView.c:()Landroid/support/v7/widget/ActionMenuView$c;
     244: invokevirtual #330                // Method android/support/v7/widget/ActionMenuView.addView:(Landroid/view/View;Landroid/view/ViewGroup$LayoutParams;)V
     247: goto          285
     250: aload_0
     251: getfield      #191                // Field g:Landroid/support/v7/widget/d$d;
     254: ifnull        285
     257: aload_0
     258: getfield      #191                // Field g:Landroid/support/v7/widget/d$d;
     261: invokevirtual #319                // Method android/support/v7/widget/d$d.getParent:()Landroid/view/ViewParent;
     264: aload_0
     265: getfield      #96                 // Field f:Landroid/support/v7/view/menu/p;
     268: if_acmpne     285
     271: aload_0
     272: getfield      #96                 // Field f:Landroid/support/v7/view/menu/p;
     275: checkcast     #98                 // class android/view/ViewGroup
     278: aload_0
     279: getfield      #191                // Field g:Landroid/support/v7/widget/d$d;
     282: invokevirtual #323                // Method android/view/ViewGroup.removeView:(Landroid/view/View;)V
     285: aload_0
     286: getfield      #96                 // Field f:Landroid/support/v7/view/menu/p;
     289: checkcast     #118                // class android/support/v7/widget/ActionMenuView
     292: aload_0
     293: getfield      #177                // Field o:Z
     296: invokevirtual #333                // Method android/support/v7/widget/ActionMenuView.setOverflowReserved:(Z)V
     299: return

  public boolean a();
    Code:
       0: aload_0
       1: astore        15
       3: aload         15
       5: getfield      #92                 // Field c:Landroid/support/v7/view/menu/h;
       8: ifnull        31
      11: aload         15
      13: getfield      #92                 // Field c:Landroid/support/v7/view/menu/h;
      16: invokevirtual #335                // Method android/support/v7/view/menu/h.i:()Ljava/util/ArrayList;
      19: astore        14
      21: aload         14
      23: invokevirtual #301                // Method java/util/ArrayList.size:()I
      26: istore        4
      28: goto          37
      31: aconst_null
      32: astore        14
      34: iconst_0
      35: istore        4
      37: aload         15
      39: getfield      #189                // Field s:I
      42: istore_1
      43: aload         15
      45: getfield      #220                // Field r:I
      48: istore        8
      50: iconst_0
      51: iconst_0
      52: invokestatic  #211                // Method android/view/View$MeasureSpec.makeMeasureSpec:(II)I
      55: istore        10
      57: aload         15
      59: getfield      #96                 // Field f:Landroid/support/v7/view/menu/p;
      62: checkcast     #98                 // class android/view/ViewGroup
      65: astore        16
      67: iconst_0
      68: istore_3
      69: iconst_0
      70: istore        5
      72: iconst_0
      73: istore        6
      75: iconst_0
      76: istore_2
      77: iload_3
      78: iload         4
      80: if_icmpge     164
      83: aload         14
      85: iload_3
      86: invokevirtual #305                // Method java/util/ArrayList.get:(I)Ljava/lang/Object;
      89: checkcast     #124                // class android/support/v7/view/menu/j
      92: astore        17
      94: aload         17
      96: invokevirtual #337                // Method android/support/v7/view/menu/j.l:()Z
      99: ifeq          111
     102: iload         5
     104: iconst_1
     105: iadd
     106: istore        5
     108: goto          129
     111: aload         17
     113: invokevirtual #339                // Method android/support/v7/view/menu/j.k:()Z
     116: ifeq          126
     119: iload_2
     120: iconst_1
     121: iadd
     122: istore_2
     123: goto          129
     126: iconst_1
     127: istore        6
     129: iload_1
     130: istore        7
     132: aload         15
     134: getfield      #341                // Field w:Z
     137: ifeq          154
     140: iload_1
     141: istore        7
     143: aload         17
     145: invokevirtual #136                // Method android/support/v7/view/menu/j.isActionViewExpanded:()Z
     148: ifeq          154
     151: iconst_0
     152: istore        7
     154: iload_3
     155: iconst_1
     156: iadd
     157: istore_3
     158: iload         7
     160: istore_1
     161: goto          77
     164: iload_1
     165: istore_3
     166: aload         15
     168: getfield      #177                // Field o:Z
     171: ifeq          193
     174: iload         6
     176: ifne          189
     179: iload_1
     180: istore_3
     181: iload_2
     182: iload         5
     184: iadd
     185: iload_1
     186: if_icmple     193
     189: iload_1
     190: iconst_1
     191: isub
     192: istore_3
     193: iload_3
     194: iload         5
     196: isub
     197: istore_1
     198: aload         15
     200: getfield      #82                 // Field y:Landroid/util/SparseBooleanArray;
     203: astore        17
     205: aload         17
     207: invokevirtual #344                // Method android/util/SparseBooleanArray.clear:()V
     210: aload         15
     212: getfield      #346                // Field u:Z
     215: ifeq          254
     218: iload         8
     220: aload         15
     222: getfield      #235                // Field x:I
     225: idiv
     226: istore_3
     227: aload         15
     229: getfield      #235                // Field x:I
     232: istore_2
     233: aload         15
     235: getfield      #235                // Field x:I
     238: istore        5
     240: iload         8
     242: iload_2
     243: irem
     244: iload_3
     245: idiv
     246: iload         5
     248: iadd
     249: istore        6
     251: goto          259
     254: iconst_0
     255: istore_3
     256: iconst_0
     257: istore        6
     259: iload         8
     261: istore        5
     263: iconst_0
     264: istore        8
     266: iconst_0
     267: istore_2
     268: iload         4
     270: istore        7
     272: aload_0
     273: astore        15
     275: iload         8
     277: iload         7
     279: if_icmpge     790
     282: aload         14
     284: iload         8
     286: invokevirtual #305                // Method java/util/ArrayList.get:(I)Ljava/lang/Object;
     289: checkcast     #124                // class android/support/v7/view/menu/j
     292: astore        18
     294: aload         18
     296: invokevirtual #337                // Method android/support/v7/view/menu/j.l:()Z
     299: ifeq          424
     302: aload         15
     304: aload         18
     306: aload         15
     308: getfield      #237                // Field z:Landroid/view/View;
     311: aload         16
     313: invokevirtual #347                // Method a:(Landroid/support/v7/view/menu/j;Landroid/view/View;Landroid/view/ViewGroup;)Landroid/view/View;
     316: astore        19
     318: aload         15
     320: getfield      #237                // Field z:Landroid/view/View;
     323: ifnonnull     333
     326: aload         15
     328: aload         19
     330: putfield      #237                // Field z:Landroid/view/View;
     333: aload         15
     335: getfield      #346                // Field u:Z
     338: ifeq          358
     341: iload_3
     342: aload         19
     344: iload         6
     346: iload_3
     347: iload         10
     349: iconst_0
     350: invokestatic  #350                // Method android/support/v7/widget/ActionMenuView.a:(Landroid/view/View;IIII)I
     353: isub
     354: istore_3
     355: goto          367
     358: aload         19
     360: iload         10
     362: iload         10
     364: invokevirtual #351                // Method android/view/View.measure:(II)V
     367: aload         19
     369: invokevirtual #352                // Method android/view/View.getMeasuredWidth:()I
     372: istore        9
     374: iload         5
     376: iload         9
     378: isub
     379: istore        5
     381: iload_2
     382: istore        4
     384: iload_2
     385: ifne          392
     388: iload         9
     390: istore        4
     392: aload         18
     394: invokevirtual #355                // Method android/support/v7/view/menu/j.getGroupId:()I
     397: istore_2
     398: iload_2
     399: ifeq          412
     402: aload         17
     404: iload_2
     405: iconst_1
     406: invokevirtual #359                // Method android/util/SparseBooleanArray.put:(IZ)V
     409: goto          412
     412: aload         18
     414: iconst_1
     415: invokevirtual #361                // Method android/support/v7/view/menu/j.d:(Z)V
     418: iload         4
     420: istore_2
     421: goto          781
     424: aload         18
     426: invokevirtual #339                // Method android/support/v7/view/menu/j.k:()Z
     429: ifeq          775
     432: aload         18
     434: invokevirtual #355                // Method android/support/v7/view/menu/j.getGroupId:()I
     437: istore        11
     439: aload         17
     441: iload         11
     443: invokevirtual #364                // Method android/util/SparseBooleanArray.get:(I)Z
     446: istore        13
     448: iload_1
     449: ifgt          457
     452: iload         13
     454: ifeq          480
     457: iload         5
     459: ifle          480
     462: aload         15
     464: getfield      #346                // Field u:Z
     467: ifeq          474
     470: iload_3
     471: ifle          480
     474: iconst_1
     475: istore        12
     477: goto          483
     480: iconst_0
     481: istore        12
     483: iload         12
     485: ifeq          640
     488: aload         15
     490: aload         18
     492: aload         15
     494: getfield      #237                // Field z:Landroid/view/View;
     497: aload         16
     499: invokevirtual #347                // Method a:(Landroid/support/v7/view/menu/j;Landroid/view/View;Landroid/view/ViewGroup;)Landroid/view/View;
     502: astore        19
     504: aload         15
     506: getfield      #237                // Field z:Landroid/view/View;
     509: ifnonnull     519
     512: aload         15
     514: aload         19
     516: putfield      #237                // Field z:Landroid/view/View;
     519: aload         15
     521: getfield      #346                // Field u:Z
     524: ifeq          563
     527: aload         19
     529: iload         6
     531: iload_3
     532: iload         10
     534: iconst_0
     535: invokestatic  #350                // Method android/support/v7/widget/ActionMenuView.a:(Landroid/view/View;IIII)I
     538: istore        9
     540: iload_3
     541: iload         9
     543: isub
     544: istore        4
     546: iload         4
     548: istore_3
     549: iload         9
     551: ifne          572
     554: iconst_0
     555: istore        12
     557: iload         4
     559: istore_3
     560: goto          572
     563: aload         19
     565: iload         10
     567: iload         10
     569: invokevirtual #351                // Method android/view/View.measure:(II)V
     572: aload         19
     574: invokevirtual #352                // Method android/view/View.getMeasuredWidth:()I
     577: istore        9
     579: iload         5
     581: iload         9
     583: isub
     584: istore        5
     586: iload_2
     587: istore        4
     589: iload_2
     590: ifne          597
     593: iload         9
     595: istore        4
     597: aload         15
     599: getfield      #346                // Field u:Z
     602: ifeq          629
     605: iload         5
     607: iflt          615
     610: iconst_1
     611: istore_2
     612: goto          617
     615: iconst_0
     616: istore_2
     617: iload         12
     619: iload_2
     620: iand
     621: istore        12
     623: iload         4
     625: istore_2
     626: goto          640
     629: iload         5
     631: iload         4
     633: iadd
     634: ifle          615
     637: goto          610
     640: iload         12
     642: ifeq          664
     645: iload         11
     647: ifeq          664
     650: aload         17
     652: iload         11
     654: iconst_1
     655: invokevirtual #359                // Method android/util/SparseBooleanArray.put:(IZ)V
     658: iload_1
     659: istore        4
     661: goto          752
     664: iload_1
     665: istore        4
     667: iload         13
     669: ifeq          752
     672: aload         17
     674: iload         11
     676: iconst_0
     677: invokevirtual #359                // Method android/util/SparseBooleanArray.put:(IZ)V
     680: iconst_0
     681: istore        9
     683: iload_1
     684: istore        4
     686: iload         9
     688: iload         8
     690: if_icmpge     752
     693: aload         14
     695: iload         9
     697: invokevirtual #305                // Method java/util/ArrayList.get:(I)Ljava/lang/Object;
     700: checkcast     #124                // class android/support/v7/view/menu/j
     703: astore        15
     705: iload_1
     706: istore        4
     708: aload         15
     710: invokevirtual #355                // Method android/support/v7/view/menu/j.getGroupId:()I
     713: iload         11
     715: if_icmpne     740
     718: iload_1
     719: istore        4
     721: aload         15
     723: invokevirtual #366                // Method android/support/v7/view/menu/j.j:()Z
     726: ifeq          734
     729: iload_1
     730: iconst_1
     731: iadd
     732: istore        4
     734: aload         15
     736: iconst_0
     737: invokevirtual #361                // Method android/support/v7/view/menu/j.d:(Z)V
     740: iload         9
     742: iconst_1
     743: iadd
     744: istore        9
     746: iload         4
     748: istore_1
     749: goto          683
     752: iload         4
     754: istore_1
     755: iload         12
     757: ifeq          765
     760: iload         4
     762: iconst_1
     763: isub
     764: istore_1
     765: aload         18
     767: iload         12
     769: invokevirtual #361                // Method android/support/v7/view/menu/j.d:(Z)V
     772: goto          421
     775: aload         18
     777: iconst_0
     778: invokevirtual #361                // Method android/support/v7/view/menu/j.d:(Z)V
     781: iload         8
     783: iconst_1
     784: iadd
     785: istore        8
     787: goto          272
     790: iconst_1
     791: ireturn

  public boolean a(int, android.support.v7.view.menu.j);
    Code:
       0: aload_2
       1: invokevirtual #366                // Method android/support/v7/view/menu/j.j:()Z
       4: ireturn

  public boolean a(android.support.v7.view.menu.u);
    Code:
       0: aload_1
       1: invokevirtual #370                // Method android/support/v7/view/menu/u.hasVisibleItems:()Z
       4: istore        4
       6: iconst_0
       7: istore        5
       9: iload         4
      11: ifne          16
      14: iconst_0
      15: ireturn
      16: aload_1
      17: astore        6
      19: aload         6
      21: invokevirtual #373                // Method android/support/v7/view/menu/u.s:()Landroid/view/Menu;
      24: aload_0
      25: getfield      #92                 // Field c:Landroid/support/v7/view/menu/h;
      28: if_acmpeq     44
      31: aload         6
      33: invokevirtual #373                // Method android/support/v7/view/menu/u.s:()Landroid/view/Menu;
      36: checkcast     #260                // class android/support/v7/view/menu/u
      39: astore        6
      41: goto          19
      44: aload_0
      45: aload         6
      47: invokevirtual #377                // Method android/support/v7/view/menu/u.getItem:()Landroid/view/MenuItem;
      50: invokespecial #379                // Method a:(Landroid/view/MenuItem;)Landroid/view/View;
      53: astore        6
      55: aload         6
      57: ifnonnull     62
      60: iconst_0
      61: ireturn
      62: aload_0
      63: aload_1
      64: invokevirtual #377                // Method android/support/v7/view/menu/u.getItem:()Landroid/view/MenuItem;
      67: invokeinterface #382,  1          // InterfaceMethod android/view/MenuItem.getItemId:()I
      72: putfield      #384                // Field l:I
      75: aload_1
      76: invokevirtual #385                // Method android/support/v7/view/menu/u.size:()I
      79: istore_3
      80: iconst_0
      81: istore_2
      82: iload         5
      84: istore        4
      86: iload_2
      87: iload_3
      88: if_icmpge     131
      91: aload_1
      92: iload_2
      93: invokevirtual #387                // Method android/support/v7/view/menu/u.getItem:(I)Landroid/view/MenuItem;
      96: astore        7
      98: aload         7
     100: invokeinterface #390,  1          // InterfaceMethod android/view/MenuItem.isVisible:()Z
     105: ifeq          124
     108: aload         7
     110: invokeinterface #394,  1          // InterfaceMethod android/view/MenuItem.getIcon:()Landroid/graphics/drawable/Drawable;
     115: ifnull        124
     118: iconst_1
     119: istore        4
     121: goto          131
     124: iload_2
     125: iconst_1
     126: iadd
     127: istore_2
     128: goto          82
     131: aload_0
     132: new           #8                  // class android/support/v7/widget/d$a
     135: dup
     136: aload_0
     137: aload_0
     138: getfield      #240                // Field b:Landroid/content/Context;
     141: aload_1
     142: aload         6
     144: invokespecial #397                // Method android/support/v7/widget/d$a."<init>":(Landroid/support/v7/widget/d;Landroid/content/Context;Landroid/support/v7/view/menu/u;Landroid/view/View;)V
     147: putfield      #399                // Field i:Landroid/support/v7/widget/d$a;
     150: aload_0
     151: getfield      #399                // Field i:Landroid/support/v7/widget/d$a;
     154: iload         4
     156: invokevirtual #400                // Method android/support/v7/widget/d$a.a:(Z)V
     159: aload_0
     160: getfield      #399                // Field i:Landroid/support/v7/widget/d$a;
     163: invokevirtual #402                // Method android/support/v7/widget/d$a.a:()V
     166: aload_0
     167: aload_1
     168: invokespecial #403                // Method android/support/v7/view/menu/b.a:(Landroid/support/v7/view/menu/u;)Z
     171: pop
     172: iconst_1
     173: ireturn

  public boolean a(android.view.ViewGroup, int);
    Code:
       0: aload_1
       1: iload_2
       2: invokevirtual #106                // Method android/view/ViewGroup.getChildAt:(I)Landroid/view/View;
       5: aload_0
       6: getfield      #191                // Field g:Landroid/support/v7/widget/d$d;
       9: if_acmpne     14
      12: iconst_0
      13: ireturn
      14: aload_0
      15: aload_1
      16: iload_2
      17: invokespecial #406                // Method android/support/v7/view/menu/b.a:(Landroid/view/ViewGroup;I)Z
      20: ireturn

  public void b(boolean);
    Code:
       0: iload_1
       1: ifeq          11
       4: aload_0
       5: aconst_null
       6: invokespecial #403                // Method android/support/v7/view/menu/b.a:(Landroid/support/v7/view/menu/u;)Z
       9: pop
      10: return
      11: aload_0
      12: getfield      #92                 // Field c:Landroid/support/v7/view/menu/h;
      15: ifnull        26
      18: aload_0
      19: getfield      #92                 // Field c:Landroid/support/v7/view/menu/h;
      22: iconst_0
      23: invokevirtual #408                // Method android/support/v7/view/menu/h.b:(Z)V
      26: return

  public android.os.Parcelable c();
    Code:
       0: new           #28                 // class android/support/v7/widget/d$g
       3: dup
       4: invokespecial #410                // Method android/support/v7/widget/d$g."<init>":()V
       7: astore_1
       8: aload_1
       9: aload_0
      10: getfield      #384                // Field l:I
      13: putfield      #248                // Field android/support/v7/widget/d$g.a:I
      16: aload_1
      17: areturn

  public void c(boolean);
    Code:
       0: aload_0
       1: iload_1
       2: putfield      #177                // Field o:Z
       5: aload_0
       6: iconst_1
       7: putfield      #173                // Field p:Z
      10: return

  public void d(boolean);
    Code:
       0: aload_0
       1: iload_1
       2: putfield      #341                // Field w:Z
       5: return

  public android.graphics.drawable.Drawable e();
    Code:
       0: aload_0
       1: getfield      #191                // Field g:Landroid/support/v7/widget/d$d;
       4: ifnull        15
       7: aload_0
       8: getfield      #191                // Field g:Landroid/support/v7/widget/d$d;
      11: invokevirtual #413                // Method android/support/v7/widget/d$d.getDrawable:()Landroid/graphics/drawable/Drawable;
      14: areturn
      15: aload_0
      16: getfield      #199                // Field n:Z
      19: ifeq          27
      22: aload_0
      23: getfield      #201                // Field m:Landroid/graphics/drawable/Drawable;
      26: areturn
      27: aconst_null
      28: areturn

  public boolean f();
    Code:
       0: aload_0
       1: getfield      #177                // Field o:Z
       4: ifeq          104
       7: aload_0
       8: invokevirtual #414                // Method j:()Z
      11: ifne          104
      14: aload_0
      15: getfield      #92                 // Field c:Landroid/support/v7/view/menu/h;
      18: ifnull        104
      21: aload_0
      22: getfield      #96                 // Field f:Landroid/support/v7/view/menu/p;
      25: ifnull        104
      28: aload_0
      29: getfield      #416                // Field j:Landroid/support/v7/widget/d$c;
      32: ifnonnull     104
      35: aload_0
      36: getfield      #92                 // Field c:Landroid/support/v7/view/menu/h;
      39: invokevirtual #315                // Method android/support/v7/view/menu/h.l:()Ljava/util/ArrayList;
      42: invokevirtual #419                // Method java/util/ArrayList.isEmpty:()Z
      45: ifne          104
      48: aload_0
      49: new           #14                 // class android/support/v7/widget/d$c
      52: dup
      53: aload_0
      54: new           #22                 // class android/support/v7/widget/d$e
      57: dup
      58: aload_0
      59: aload_0
      60: getfield      #240                // Field b:Landroid/content/Context;
      63: aload_0
      64: getfield      #92                 // Field c:Landroid/support/v7/view/menu/h;
      67: aload_0
      68: getfield      #191                // Field g:Landroid/support/v7/widget/d$d;
      71: iconst_1
      72: invokespecial #422                // Method android/support/v7/widget/d$e."<init>":(Landroid/support/v7/widget/d;Landroid/content/Context;Landroid/support/v7/view/menu/h;Landroid/view/View;Z)V
      75: invokespecial #425                // Method android/support/v7/widget/d$c."<init>":(Landroid/support/v7/widget/d;Landroid/support/v7/widget/d$e;)V
      78: putfield      #416                // Field j:Landroid/support/v7/widget/d$c;
      81: aload_0
      82: getfield      #96                 // Field f:Landroid/support/v7/view/menu/p;
      85: checkcast     #138                // class android/view/View
      88: aload_0
      89: getfield      #416                // Field j:Landroid/support/v7/widget/d$c;
      92: invokevirtual #429                // Method android/view/View.post:(Ljava/lang/Runnable;)Z
      95: pop
      96: aload_0
      97: aconst_null
      98: invokespecial #403                // Method android/support/v7/view/menu/b.a:(Landroid/support/v7/view/menu/u;)Z
     101: pop
     102: iconst_1
     103: ireturn
     104: iconst_0
     105: ireturn

  public boolean g();
    Code:
       0: aload_0
       1: getfield      #416                // Field j:Landroid/support/v7/widget/d$c;
       4: ifnull        36
       7: aload_0
       8: getfield      #96                 // Field f:Landroid/support/v7/view/menu/p;
      11: ifnull        36
      14: aload_0
      15: getfield      #96                 // Field f:Landroid/support/v7/view/menu/p;
      18: checkcast     #138                // class android/view/View
      21: aload_0
      22: getfield      #416                // Field j:Landroid/support/v7/widget/d$c;
      25: invokevirtual #432                // Method android/view/View.removeCallbacks:(Ljava/lang/Runnable;)Z
      28: pop
      29: aload_0
      30: aconst_null
      31: putfield      #416                // Field j:Landroid/support/v7/widget/d$c;
      34: iconst_1
      35: ireturn
      36: aload_0
      37: getfield      #434                // Field h:Landroid/support/v7/widget/d$e;
      40: astore_1
      41: aload_1
      42: ifnull        51
      45: aload_1
      46: invokevirtual #438                // Method android/support/v7/view/menu/n.d:()V
      49: iconst_1
      50: ireturn
      51: iconst_0
      52: ireturn

  public boolean h();
    Code:
       0: aload_0
       1: invokevirtual #440                // Method g:()Z
       4: aload_0
       5: invokevirtual #442                // Method i:()Z
       8: ior
       9: ireturn

  public boolean i();
    Code:
       0: aload_0
       1: getfield      #399                // Field i:Landroid/support/v7/widget/d$a;
       4: ifnull        16
       7: aload_0
       8: getfield      #399                // Field i:Landroid/support/v7/widget/d$a;
      11: invokevirtual #443                // Method android/support/v7/widget/d$a.d:()V
      14: iconst_1
      15: ireturn
      16: iconst_0
      17: ireturn

  public boolean j();
    Code:
       0: aload_0
       1: getfield      #434                // Field h:Landroid/support/v7/widget/d$e;
       4: ifnull        19
       7: aload_0
       8: getfield      #434                // Field h:Landroid/support/v7/widget/d$e;
      11: invokevirtual #445                // Method android/support/v7/widget/d$e.f:()Z
      14: ifeq          19
      17: iconst_1
      18: ireturn
      19: iconst_0
      20: ireturn

  public boolean k();
    Code:
       0: aload_0
       1: getfield      #416                // Field j:Landroid/support/v7/widget/d$c;
       4: ifnonnull     19
       7: aload_0
       8: invokevirtual #414                // Method j:()Z
      11: ifeq          17
      14: goto          19
      17: iconst_0
      18: ireturn
      19: iconst_1
      20: ireturn
}
