final class android.support.v7.widget.e$e extends android.os.AsyncTask<java.lang.Object, java.lang.Void, java.lang.Void> {
  final android.support.v7.widget.e a;

  android.support.v7.widget.e$e(android.support.v7.widget.e);
    Code:
       0: aload_0
       1: aload_1
       2: putfield      #14                 // Field a:Landroid/support/v7/widget/e;
       5: aload_0
       6: invokespecial #17                 // Method android/os/AsyncTask."<init>":()V
       9: return

  public java.lang.Void a(java.lang.Object...);
    Code:
       0: aload_1
       1: iconst_0
       2: aaload
       3: checkcast     #29                 // class java/util/List
       6: astore        4
       8: aload_1
       9: iconst_1
      10: aaload
      11: checkcast     #31                 // class java/lang/String
      14: astore        5
      16: aload_0
      17: getfield      #14                 // Field a:Landroid/support/v7/widget/e;
      20: getfield      #35                 // Field android/support/v7/widget/e.b:Landroid/content/Context;
      23: aload         5
      25: iconst_0
      26: invokevirtual #41                 // Method android/content/Context.openFileOutput:(Ljava/lang/String;I)Ljava/io/FileOutputStream;
      29: astore_1
      30: invokestatic  #47                 // Method android/util/Xml.newSerializer:()Lorg/xmlpull/v1/XmlSerializer;
      33: astore        5
      35: aload         5
      37: aload_1
      38: aconst_null
      39: invokeinterface #53,  3           // InterfaceMethod org/xmlpull/v1/XmlSerializer.setOutput:(Ljava/io/OutputStream;Ljava/lang/String;)V
      44: aload         5
      46: ldc           #55                 // String UTF-8
      48: iconst_1
      49: invokestatic  #61                 // Method java/lang/Boolean.valueOf:(Z)Ljava/lang/Boolean;
      52: invokeinterface #65,  3           // InterfaceMethod org/xmlpull/v1/XmlSerializer.startDocument:(Ljava/lang/String;Ljava/lang/Boolean;)V
      57: aload         5
      59: aconst_null
      60: ldc           #67                 // String historical-records
      62: invokeinterface #71,  3           // InterfaceMethod org/xmlpull/v1/XmlSerializer.startTag:(Ljava/lang/String;Ljava/lang/String;)Lorg/xmlpull/v1/XmlSerializer;
      67: pop
      68: aload         4
      70: invokeinterface #75,  1           // InterfaceMethod java/util/List.size:()I
      75: istore_3
      76: iconst_0
      77: istore_2
      78: iload_2
      79: iload_3
      80: if_icmpge     182
      83: aload         4
      85: iconst_0
      86: invokeinterface #79,  2           // InterfaceMethod java/util/List.remove:(I)Ljava/lang/Object;
      91: checkcast     #81                 // class android/support/v7/widget/e$c
      94: astore        6
      96: aload         5
      98: aconst_null
      99: ldc           #83                 // String historical-record
     101: invokeinterface #71,  3           // InterfaceMethod org/xmlpull/v1/XmlSerializer.startTag:(Ljava/lang/String;Ljava/lang/String;)Lorg/xmlpull/v1/XmlSerializer;
     106: pop
     107: aload         5
     109: aconst_null
     110: ldc           #85                 // String activity
     112: aload         6
     114: getfield      #88                 // Field android/support/v7/widget/e$c.a:Landroid/content/ComponentName;
     117: invokevirtual #94                 // Method android/content/ComponentName.flattenToString:()Ljava/lang/String;
     120: invokeinterface #98,  4           // InterfaceMethod org/xmlpull/v1/XmlSerializer.attribute:(Ljava/lang/String;Ljava/lang/String;Ljava/lang/String;)Lorg/xmlpull/v1/XmlSerializer;
     125: pop
     126: aload         5
     128: aconst_null
     129: ldc           #100                // String time
     131: aload         6
     133: getfield      #103                // Field android/support/v7/widget/e$c.b:J
     136: invokestatic  #106                // Method java/lang/String.valueOf:(J)Ljava/lang/String;
     139: invokeinterface #98,  4           // InterfaceMethod org/xmlpull/v1/XmlSerializer.attribute:(Ljava/lang/String;Ljava/lang/String;Ljava/lang/String;)Lorg/xmlpull/v1/XmlSerializer;
     144: pop
     145: aload         5
     147: aconst_null
     148: ldc           #108                // String weight
     150: aload         6
     152: getfield      #112                // Field android/support/v7/widget/e$c.c:F
     155: invokestatic  #115                // Method java/lang/String.valueOf:(F)Ljava/lang/String;
     158: invokeinterface #98,  4           // InterfaceMethod org/xmlpull/v1/XmlSerializer.attribute:(Ljava/lang/String;Ljava/lang/String;Ljava/lang/String;)Lorg/xmlpull/v1/XmlSerializer;
     163: pop
     164: aload         5
     166: aconst_null
     167: ldc           #83                 // String historical-record
     169: invokeinterface #118,  3          // InterfaceMethod org/xmlpull/v1/XmlSerializer.endTag:(Ljava/lang/String;Ljava/lang/String;)Lorg/xmlpull/v1/XmlSerializer;
     174: pop
     175: iload_2
     176: iconst_1
     177: iadd
     178: istore_2
     179: goto          78
     182: aload         5
     184: aconst_null
     185: ldc           #67                 // String historical-records
     187: invokeinterface #118,  3          // InterfaceMethod org/xmlpull/v1/XmlSerializer.endTag:(Ljava/lang/String;Ljava/lang/String;)Lorg/xmlpull/v1/XmlSerializer;
     192: pop
     193: aload         5
     195: invokeinterface #121,  1          // InterfaceMethod org/xmlpull/v1/XmlSerializer.endDocument:()V
     200: aload_0
     201: getfield      #14                 // Field a:Landroid/support/v7/widget/e;
     204: iconst_1
     205: putfield      #125                // Field android/support/v7/widget/e.d:Z
     208: aload_1
     209: ifnull        418
     212: aload_1
     213: invokevirtual #130                // Method java/io/FileOutputStream.close:()V
     216: aconst_null
     217: areturn
     218: astore        4
     220: goto          420
     223: astore        4
     225: getstatic     #133                // Field android/support/v7/widget/e.a:Ljava/lang/String;
     228: astore        5
     230: new           #135                // class java/lang/StringBuilder
     233: dup
     234: invokespecial #136                // Method java/lang/StringBuilder."<init>":()V
     237: astore        6
     239: aload         6
     241: ldc           #138                // String Error writing historical record file:
     243: invokevirtual #142                // Method java/lang/StringBuilder.append:(Ljava/lang/String;)Ljava/lang/StringBuilder;
     246: pop
     247: aload         6
     249: aload_0
     250: getfield      #14                 // Field a:Landroid/support/v7/widget/e;
     253: getfield      #144                // Field android/support/v7/widget/e.c:Ljava/lang/String;
     256: invokevirtual #142                // Method java/lang/StringBuilder.append:(Ljava/lang/String;)Ljava/lang/StringBuilder;
     259: pop
     260: aload         5
     262: aload         6
     264: invokevirtual #147                // Method java/lang/StringBuilder.toString:()Ljava/lang/String;
     267: aload         4
     269: invokestatic  #152                // Method android/util/Log.e:(Ljava/lang/String;Ljava/lang/String;Ljava/lang/Throwable;)I
     272: pop
     273: aload_0
     274: getfield      #14                 // Field a:Landroid/support/v7/widget/e;
     277: iconst_1
     278: putfield      #125                // Field android/support/v7/widget/e.d:Z
     281: aload_1
     282: ifnull        418
     285: goto          212
     288: astore        4
     290: getstatic     #133                // Field android/support/v7/widget/e.a:Ljava/lang/String;
     293: astore        5
     295: new           #135                // class java/lang/StringBuilder
     298: dup
     299: invokespecial #136                // Method java/lang/StringBuilder."<init>":()V
     302: astore        6
     304: aload         6
     306: ldc           #138                // String Error writing historical record file:
     308: invokevirtual #142                // Method java/lang/StringBuilder.append:(Ljava/lang/String;)Ljava/lang/StringBuilder;
     311: pop
     312: aload         6
     314: aload_0
     315: getfield      #14                 // Field a:Landroid/support/v7/widget/e;
     318: getfield      #144                // Field android/support/v7/widget/e.c:Ljava/lang/String;
     321: invokevirtual #142                // Method java/lang/StringBuilder.append:(Ljava/lang/String;)Ljava/lang/StringBuilder;
     324: pop
     325: aload         5
     327: aload         6
     329: invokevirtual #147                // Method java/lang/StringBuilder.toString:()Ljava/lang/String;
     332: aload         4
     334: invokestatic  #152                // Method android/util/Log.e:(Ljava/lang/String;Ljava/lang/String;Ljava/lang/Throwable;)I
     337: pop
     338: aload_0
     339: getfield      #14                 // Field a:Landroid/support/v7/widget/e;
     342: iconst_1
     343: putfield      #125                // Field android/support/v7/widget/e.d:Z
     346: aload_1
     347: ifnull        418
     350: goto          212
     353: astore        4
     355: getstatic     #133                // Field android/support/v7/widget/e.a:Ljava/lang/String;
     358: astore        5
     360: new           #135                // class java/lang/StringBuilder
     363: dup
     364: invokespecial #136                // Method java/lang/StringBuilder."<init>":()V
     367: astore        6
     369: aload         6
     371: ldc           #138                // String Error writing historical record file:
     373: invokevirtual #142                // Method java/lang/StringBuilder.append:(Ljava/lang/String;)Ljava/lang/StringBuilder;
     376: pop
     377: aload         6
     379: aload_0
     380: getfield      #14                 // Field a:Landroid/support/v7/widget/e;
     383: getfield      #144                // Field android/support/v7/widget/e.c:Ljava/lang/String;
     386: invokevirtual #142                // Method java/lang/StringBuilder.append:(Ljava/lang/String;)Ljava/lang/StringBuilder;
     389: pop
     390: aload         5
     392: aload         6
     394: invokevirtual #147                // Method java/lang/StringBuilder.toString:()Ljava/lang/String;
     397: aload         4
     399: invokestatic  #152                // Method android/util/Log.e:(Ljava/lang/String;Ljava/lang/String;Ljava/lang/Throwable;)I
     402: pop
     403: aload_0
     404: getfield      #14                 // Field a:Landroid/support/v7/widget/e;
     407: iconst_1
     408: putfield      #125                // Field android/support/v7/widget/e.d:Z
     411: aload_1
     412: ifnull        418
     415: goto          212
     418: aconst_null
     419: areturn
     420: aload_0
     421: getfield      #14                 // Field a:Landroid/support/v7/widget/e;
     424: iconst_1
     425: putfield      #125                // Field android/support/v7/widget/e.d:Z
     428: aload_1
     429: ifnull        436
     432: aload_1
     433: invokevirtual #130                // Method java/io/FileOutputStream.close:()V
     436: aload         4
     438: athrow
     439: astore_1
     440: getstatic     #133                // Field android/support/v7/widget/e.a:Ljava/lang/String;
     443: astore        4
     445: new           #135                // class java/lang/StringBuilder
     448: dup
     449: invokespecial #136                // Method java/lang/StringBuilder."<init>":()V
     452: astore        6
     454: aload         6
     456: ldc           #138                // String Error writing historical record file:
     458: invokevirtual #142                // Method java/lang/StringBuilder.append:(Ljava/lang/String;)Ljava/lang/StringBuilder;
     461: pop
     462: aload         6
     464: aload         5
     466: invokevirtual #142                // Method java/lang/StringBuilder.append:(Ljava/lang/String;)Ljava/lang/StringBuilder;
     469: pop
     470: aload         4
     472: aload         6
     474: invokevirtual #147                // Method java/lang/StringBuilder.toString:()Ljava/lang/String;
     477: aload_1
     478: invokestatic  #152                // Method android/util/Log.e:(Ljava/lang/String;Ljava/lang/String;Ljava/lang/Throwable;)I
     481: pop
     482: aconst_null
     483: areturn
     484: astore_1
     485: aconst_null
     486: areturn
     487: astore_1
     488: goto          436
    Exception table:
       from    to  target type
          16    30   439   Class java/io/FileNotFoundException
          35    76   353   Class java/lang/IllegalArgumentException
          35    76   288   Class java/lang/IllegalStateException
          35    76   223   Class java/io/IOException
          35    76   218   any
          83   175   353   Class java/lang/IllegalArgumentException
          83   175   288   Class java/lang/IllegalStateException
          83   175   223   Class java/io/IOException
          83   175   218   any
         182   200   353   Class java/lang/IllegalArgumentException
         182   200   288   Class java/lang/IllegalStateException
         182   200   223   Class java/io/IOException
         182   200   218   any
         212   216   484   Class java/io/IOException
         225   273   218   any
         290   338   218   any
         355   403   218   any
         432   436   487   Class java/io/IOException

  public java.lang.Object doInBackground(java.lang.Object[]);
    Code:
       0: aload_0
       1: aload_1
       2: invokevirtual #156                // Method a:([Ljava/lang/Object;)Ljava/lang/Void;
       5: areturn
}
