public final class android.support.v7.widget.GridLayoutManager$a extends android.support.v7.widget.GridLayoutManager$c {
  public android.support.v7.widget.GridLayoutManager$a();
    Code:
       0: aload_0
       1: invokespecial #11                 // Method android/support/v7/widget/GridLayoutManager$c."<init>":()V
       4: return

  public int a(int);
    Code:
       0: iconst_1
       1: ireturn

  public int a(int, int);
    Code:
       0: iload_1
       1: iload_2
       2: irem
       3: ireturn
}
