class android.support.v7.widget.h {
  android.support.v7.widget.h(android.view.View);
    Code:
       0: aload_0
       1: invokespecial #19                 // Method java/lang/Object."<init>":()V
       4: aload_0
       5: iconst_m1
       6: putfield      #21                 // Field c:I
       9: aload_0
      10: aload_1
      11: putfield      #23                 // Field a:Landroid/view/View;
      14: aload_0
      15: invokestatic  #28                 // Method android/support/v7/widget/m.a:()Landroid/support/v7/widget/m;
      18: putfield      #30                 // Field b:Landroid/support/v7/widget/m;
      21: return

  android.content.res.ColorStateList a();
    Code:
       0: aload_0
       1: getfield      #80                 // Field e:Landroid/support/v7/widget/bn;
       4: ifnull        15
       7: aload_0
       8: getfield      #80                 // Field e:Landroid/support/v7/widget/bn;
      11: getfield      #51                 // Field android/support/v7/widget/bn.a:Landroid/content/res/ColorStateList;
      14: areturn
      15: aconst_null
      16: areturn

  void a(int);
    Code:
       0: aload_0
       1: iload_1
       2: putfield      #21                 // Field c:I
       5: aload_0
       6: getfield      #30                 // Field b:Landroid/support/v7/widget/m;
       9: ifnull        31
      12: aload_0
      13: getfield      #30                 // Field b:Landroid/support/v7/widget/m;
      16: aload_0
      17: getfield      #23                 // Field a:Landroid/view/View;
      20: invokevirtual #85                 // Method android/view/View.getContext:()Landroid/content/Context;
      23: iload_1
      24: invokevirtual #88                 // Method android/support/v7/widget/m.b:(Landroid/content/Context;I)Landroid/content/res/ColorStateList;
      27: astore_2
      28: goto          33
      31: aconst_null
      32: astore_2
      33: aload_0
      34: aload_2
      35: invokevirtual #91                 // Method b:(Landroid/content/res/ColorStateList;)V
      38: aload_0
      39: invokevirtual #93                 // Method c:()V
      42: return

  void a(android.content.res.ColorStateList);
    Code:
       0: aload_0
       1: getfield      #80                 // Field e:Landroid/support/v7/widget/bn;
       4: ifnonnull     18
       7: aload_0
       8: new           #36                 // class android/support/v7/widget/bn
      11: dup
      12: invokespecial #37                 // Method android/support/v7/widget/bn."<init>":()V
      15: putfield      #80                 // Field e:Landroid/support/v7/widget/bn;
      18: aload_0
      19: getfield      #80                 // Field e:Landroid/support/v7/widget/bn;
      22: aload_1
      23: putfield      #51                 // Field android/support/v7/widget/bn.a:Landroid/content/res/ColorStateList;
      26: aload_0
      27: getfield      #80                 // Field e:Landroid/support/v7/widget/bn;
      30: iconst_1
      31: putfield      #48                 // Field android/support/v7/widget/bn.d:Z
      34: aload_0
      35: invokevirtual #93                 // Method c:()V
      38: return

  void a(android.graphics.PorterDuff$Mode);
    Code:
       0: aload_0
       1: getfield      #80                 // Field e:Landroid/support/v7/widget/bn;
       4: ifnonnull     18
       7: aload_0
       8: new           #36                 // class android/support/v7/widget/bn
      11: dup
      12: invokespecial #37                 // Method android/support/v7/widget/bn."<init>":()V
      15: putfield      #80                 // Field e:Landroid/support/v7/widget/bn;
      18: aload_0
      19: getfield      #80                 // Field e:Landroid/support/v7/widget/bn;
      22: aload_1
      23: putfield      #60                 // Field android/support/v7/widget/bn.b:Landroid/graphics/PorterDuff$Mode;
      26: aload_0
      27: getfield      #80                 // Field e:Landroid/support/v7/widget/bn;
      30: iconst_1
      31: putfield      #57                 // Field android/support/v7/widget/bn.c:Z
      34: aload_0
      35: invokevirtual #93                 // Method c:()V
      38: return

  void a(android.graphics.drawable.Drawable);
    Code:
       0: aload_0
       1: iconst_m1
       2: putfield      #21                 // Field c:I
       5: aload_0
       6: aconst_null
       7: invokevirtual #91                 // Method b:(Landroid/content/res/ColorStateList;)V
      10: aload_0
      11: invokevirtual #93                 // Method c:()V
      14: return

  void a(android.util.AttributeSet, int);
    Code:
       0: aload_0
       1: getfield      #23                 // Field a:Landroid/view/View;
       4: invokevirtual #85                 // Method android/view/View.getContext:()Landroid/content/Context;
       7: aload_1
       8: getstatic     #102                // Field android/support/v7/a/a$j.ViewBackgroundHelper:[I
      11: iload_2
      12: iconst_0
      13: invokestatic  #107                // Method android/support/v7/widget/bp.a:(Landroid/content/Context;Landroid/util/AttributeSet;[III)Landroid/support/v7/widget/bp;
      16: astore_1
      17: aload_1
      18: getstatic     #110                // Field android/support/v7/a/a$j.ViewBackgroundHelper_android_background:I
      21: invokevirtual #114                // Method android/support/v7/widget/bp.g:(I)Z
      24: ifeq          67
      27: aload_0
      28: aload_1
      29: getstatic     #110                // Field android/support/v7/a/a$j.ViewBackgroundHelper_android_background:I
      32: iconst_m1
      33: invokevirtual #117                // Method android/support/v7/widget/bp.g:(II)I
      36: putfield      #21                 // Field c:I
      39: aload_0
      40: getfield      #30                 // Field b:Landroid/support/v7/widget/m;
      43: aload_0
      44: getfield      #23                 // Field a:Landroid/view/View;
      47: invokevirtual #85                 // Method android/view/View.getContext:()Landroid/content/Context;
      50: aload_0
      51: getfield      #21                 // Field c:I
      54: invokevirtual #88                 // Method android/support/v7/widget/m.b:(Landroid/content/Context;I)Landroid/content/res/ColorStateList;
      57: astore_3
      58: aload_3
      59: ifnull        67
      62: aload_0
      63: aload_3
      64: invokevirtual #91                 // Method b:(Landroid/content/res/ColorStateList;)V
      67: aload_1
      68: getstatic     #120                // Field android/support/v7/a/a$j.ViewBackgroundHelper_backgroundTint:I
      71: invokevirtual #114                // Method android/support/v7/widget/bp.g:(I)Z
      74: ifeq          91
      77: aload_0
      78: getfield      #23                 // Field a:Landroid/view/View;
      81: aload_1
      82: getstatic     #120                // Field android/support/v7/a/a$j.ViewBackgroundHelper_backgroundTint:I
      85: invokevirtual #123                // Method android/support/v7/widget/bp.e:(I)Landroid/content/res/ColorStateList;
      88: invokestatic  #126                // Method android/support/v4/view/s.a:(Landroid/view/View;Landroid/content/res/ColorStateList;)V
      91: aload_1
      92: getstatic     #129                // Field android/support/v7/a/a$j.ViewBackgroundHelper_backgroundTintMode:I
      95: invokevirtual #114                // Method android/support/v7/widget/bp.g:(I)Z
      98: ifeq          120
     101: aload_0
     102: getfield      #23                 // Field a:Landroid/view/View;
     105: aload_1
     106: getstatic     #129                // Field android/support/v7/a/a$j.ViewBackgroundHelper_backgroundTintMode:I
     109: iconst_m1
     110: invokevirtual #131                // Method android/support/v7/widget/bp.a:(II)I
     113: aconst_null
     114: invokestatic  #136                // Method android/support/v7/widget/ao.a:(ILandroid/graphics/PorterDuff$Mode;)Landroid/graphics/PorterDuff$Mode;
     117: invokestatic  #139                // Method android/support/v4/view/s.a:(Landroid/view/View;Landroid/graphics/PorterDuff$Mode;)V
     120: aload_1
     121: invokevirtual #140                // Method android/support/v7/widget/bp.a:()V
     124: return
     125: astore_3
     126: aload_1
     127: invokevirtual #140                // Method android/support/v7/widget/bp.a:()V
     130: aload_3
     131: athrow
    Exception table:
       from    to  target type
          17    58   125   any
          62    67   125   any
          67    91   125   any
          91   120   125   any

  android.graphics.PorterDuff$Mode b();
    Code:
       0: aload_0
       1: getfield      #80                 // Field e:Landroid/support/v7/widget/bn;
       4: ifnull        15
       7: aload_0
       8: getfield      #80                 // Field e:Landroid/support/v7/widget/bn;
      11: getfield      #60                 // Field android/support/v7/widget/bn.b:Landroid/graphics/PorterDuff$Mode;
      14: areturn
      15: aconst_null
      16: areturn

  void b(android.content.res.ColorStateList);
    Code:
       0: aload_1
       1: ifnull        41
       4: aload_0
       5: getfield      #77                 // Field d:Landroid/support/v7/widget/bn;
       8: ifnonnull     22
      11: aload_0
      12: new           #36                 // class android/support/v7/widget/bn
      15: dup
      16: invokespecial #37                 // Method android/support/v7/widget/bn."<init>":()V
      19: putfield      #77                 // Field d:Landroid/support/v7/widget/bn;
      22: aload_0
      23: getfield      #77                 // Field d:Landroid/support/v7/widget/bn;
      26: aload_1
      27: putfield      #51                 // Field android/support/v7/widget/bn.a:Landroid/content/res/ColorStateList;
      30: aload_0
      31: getfield      #77                 // Field d:Landroid/support/v7/widget/bn;
      34: iconst_1
      35: putfield      #48                 // Field android/support/v7/widget/bn.d:Z
      38: goto          46
      41: aload_0
      42: aconst_null
      43: putfield      #77                 // Field d:Landroid/support/v7/widget/bn;
      46: aload_0
      47: invokevirtual #93                 // Method c:()V
      50: return

  void c();
    Code:
       0: aload_0
       1: getfield      #23                 // Field a:Landroid/view/View;
       4: invokevirtual #145                // Method android/view/View.getBackground:()Landroid/graphics/drawable/Drawable;
       7: astore_2
       8: aload_2
       9: ifnull        68
      12: aload_0
      13: invokespecial #147                // Method d:()Z
      16: ifeq          28
      19: aload_0
      20: aload_2
      21: invokespecial #149                // Method b:(Landroid/graphics/drawable/Drawable;)Z
      24: ifeq          28
      27: return
      28: aload_0
      29: getfield      #80                 // Field e:Landroid/support/v7/widget/bn;
      32: ifnull        53
      35: aload_0
      36: getfield      #80                 // Field e:Landroid/support/v7/widget/bn;
      39: astore_1
      40: aload_2
      41: aload_1
      42: aload_0
      43: getfield      #23                 // Field a:Landroid/view/View;
      46: invokevirtual #66                 // Method android/view/View.getDrawableState:()[I
      49: invokestatic  #69                 // Method android/support/v7/widget/m.a:(Landroid/graphics/drawable/Drawable;Landroid/support/v7/widget/bn;[I)V
      52: return
      53: aload_0
      54: getfield      #77                 // Field d:Landroid/support/v7/widget/bn;
      57: ifnull        68
      60: aload_0
      61: getfield      #77                 // Field d:Landroid/support/v7/widget/bn;
      64: astore_1
      65: goto          40
      68: return
}
