public class android.support.v7.widget.k extends android.widget.CheckedTextView {
  static {};
    Code:
       0: iconst_1
       1: newarray       int
       3: dup
       4: iconst_0
       5: ldc           #11                 // int 16843016
       7: iastore
       8: putstatic     #13                 // Field a:[I
      11: return

  public android.support.v7.widget.k(android.content.Context, android.util.AttributeSet);
    Code:
       0: aload_0
       1: aload_1
       2: aload_2
       3: ldc           #17                 // int 16843720
       5: invokespecial #20                 // Method "<init>":(Landroid/content/Context;Landroid/util/AttributeSet;I)V
       8: return

  public android.support.v7.widget.k(android.content.Context, android.util.AttributeSet, int);
    Code:
       0: aload_0
       1: aload_1
       2: invokestatic  #25                 // Method android/support/v7/widget/bm.a:(Landroid/content/Context;)Landroid/content/Context;
       5: aload_2
       6: iload_3
       7: invokespecial #26                 // Method android/widget/CheckedTextView."<init>":(Landroid/content/Context;Landroid/util/AttributeSet;I)V
      10: aload_0
      11: aload_0
      12: invokestatic  #31                 // Method android/support/v7/widget/aa.a:(Landroid/widget/TextView;)Landroid/support/v7/widget/aa;
      15: putfield      #33                 // Field b:Landroid/support/v7/widget/aa;
      18: aload_0
      19: getfield      #33                 // Field b:Landroid/support/v7/widget/aa;
      22: aload_2
      23: iload_3
      24: invokevirtual #36                 // Method android/support/v7/widget/aa.a:(Landroid/util/AttributeSet;I)V
      27: aload_0
      28: getfield      #33                 // Field b:Landroid/support/v7/widget/aa;
      31: invokevirtual #38                 // Method android/support/v7/widget/aa.a:()V
      34: aload_0
      35: invokevirtual #42                 // Method getContext:()Landroid/content/Context;
      38: aload_2
      39: getstatic     #13                 // Field a:[I
      42: iload_3
      43: iconst_0
      44: invokestatic  #47                 // Method android/support/v7/widget/bp.a:(Landroid/content/Context;Landroid/util/AttributeSet;[III)Landroid/support/v7/widget/bp;
      47: astore_1
      48: aload_0
      49: aload_1
      50: iconst_0
      51: invokevirtual #50                 // Method android/support/v7/widget/bp.a:(I)Landroid/graphics/drawable/Drawable;
      54: invokevirtual #54                 // Method setCheckMarkDrawable:(Landroid/graphics/drawable/Drawable;)V
      57: aload_1
      58: invokevirtual #55                 // Method android/support/v7/widget/bp.a:()V
      61: return

  protected void drawableStateChanged();
    Code:
       0: aload_0
       1: invokespecial #58                 // Method android/widget/CheckedTextView.drawableStateChanged:()V
       4: aload_0
       5: getfield      #33                 // Field b:Landroid/support/v7/widget/aa;
       8: ifnull        18
      11: aload_0
      12: getfield      #33                 // Field b:Landroid/support/v7/widget/aa;
      15: invokevirtual #38                 // Method android/support/v7/widget/aa.a:()V
      18: return

  public android.view.inputmethod.InputConnection onCreateInputConnection(android.view.inputmethod.EditorInfo);
    Code:
       0: aload_0
       1: aload_1
       2: invokespecial #62                 // Method android/widget/CheckedTextView.onCreateInputConnection:(Landroid/view/inputmethod/EditorInfo;)Landroid/view/inputmethod/InputConnection;
       5: aload_1
       6: aload_0
       7: invokestatic  #67                 // Method android/support/v7/widget/o.a:(Landroid/view/inputmethod/InputConnection;Landroid/view/inputmethod/EditorInfo;Landroid/view/View;)Landroid/view/inputmethod/InputConnection;
      10: areturn

  public void setCheckMarkDrawable(int);
    Code:
       0: aload_0
       1: aload_0
       2: invokevirtual #42                 // Method getContext:()Landroid/content/Context;
       5: iload_1
       6: invokestatic  #73                 // Method android/support/v7/c/a/b.b:(Landroid/content/Context;I)Landroid/graphics/drawable/Drawable;
       9: invokevirtual #54                 // Method setCheckMarkDrawable:(Landroid/graphics/drawable/Drawable;)V
      12: return

  public void setTextAppearance(android.content.Context, int);
    Code:
       0: aload_0
       1: aload_1
       2: iload_2
       3: invokespecial #77                 // Method android/widget/CheckedTextView.setTextAppearance:(Landroid/content/Context;I)V
       6: aload_0
       7: getfield      #33                 // Field b:Landroid/support/v7/widget/aa;
      10: ifnull        22
      13: aload_0
      14: getfield      #33                 // Field b:Landroid/support/v7/widget/aa;
      17: aload_1
      18: iload_2
      19: invokevirtual #79                 // Method android/support/v7/widget/aa.a:(Landroid/content/Context;I)V
      22: return
}
