class android.support.v7.widget.l {
  android.support.v7.widget.l(android.widget.CompoundButton);
    Code:
       0: aload_0
       1: invokespecial #19                 // Method java/lang/Object."<init>":()V
       4: aload_0
       5: aconst_null
       6: putfield      #21                 // Field b:Landroid/content/res/ColorStateList;
       9: aload_0
      10: aconst_null
      11: putfield      #23                 // Field c:Landroid/graphics/PorterDuff$Mode;
      14: aload_0
      15: iconst_0
      16: putfield      #25                 // Field d:Z
      19: aload_0
      20: iconst_0
      21: putfield      #27                 // Field e:Z
      24: aload_0
      25: aload_1
      26: putfield      #29                 // Field a:Landroid/widget/CompoundButton;
      29: return

  int a(int);
    Code:
       0: iload_1
       1: istore_2
       2: getstatic     #37                 // Field android/os/Build$VERSION.SDK_INT:I
       5: bipush        17
       7: if_icmpge     31
      10: aload_0
      11: getfield      #29                 // Field a:Landroid/widget/CompoundButton;
      14: invokestatic  #42                 // Method android/support/v4/widget/c.a:(Landroid/widget/CompoundButton;)Landroid/graphics/drawable/Drawable;
      17: astore_3
      18: iload_1
      19: istore_2
      20: aload_3
      21: ifnull        31
      24: iload_1
      25: aload_3
      26: invokevirtual #48                 // Method android/graphics/drawable/Drawable.getIntrinsicWidth:()I
      29: iadd
      30: istore_2
      31: iload_2
      32: ireturn

  android.content.res.ColorStateList a();
    Code:
       0: aload_0
       1: getfield      #21                 // Field b:Landroid/content/res/ColorStateList;
       4: areturn

  void a(android.content.res.ColorStateList);
    Code:
       0: aload_0
       1: aload_1
       2: putfield      #21                 // Field b:Landroid/content/res/ColorStateList;
       5: aload_0
       6: iconst_1
       7: putfield      #25                 // Field d:Z
      10: aload_0
      11: invokevirtual #52                 // Method d:()V
      14: return

  void a(android.graphics.PorterDuff$Mode);
    Code:
       0: aload_0
       1: aload_1
       2: putfield      #23                 // Field c:Landroid/graphics/PorterDuff$Mode;
       5: aload_0
       6: iconst_1
       7: putfield      #27                 // Field e:Z
      10: aload_0
      11: invokevirtual #52                 // Method d:()V
      14: return

  void a(android.util.AttributeSet, int);
    Code:
       0: aload_0
       1: getfield      #29                 // Field a:Landroid/widget/CompoundButton;
       4: invokevirtual #60                 // Method android/widget/CompoundButton.getContext:()Landroid/content/Context;
       7: aload_1
       8: getstatic     #66                 // Field android/support/v7/a/a$j.CompoundButton:[I
      11: iload_2
      12: iconst_0
      13: invokevirtual #72                 // Method android/content/Context.obtainStyledAttributes:(Landroid/util/AttributeSet;[III)Landroid/content/res/TypedArray;
      16: astore_1
      17: aload_1
      18: getstatic     #75                 // Field android/support/v7/a/a$j.CompoundButton_android_button:I
      21: invokevirtual #81                 // Method android/content/res/TypedArray.hasValue:(I)Z
      24: ifeq          58
      27: aload_1
      28: getstatic     #75                 // Field android/support/v7/a/a$j.CompoundButton_android_button:I
      31: iconst_0
      32: invokevirtual #85                 // Method android/content/res/TypedArray.getResourceId:(II)I
      35: istore_2
      36: iload_2
      37: ifeq          58
      40: aload_0
      41: getfield      #29                 // Field a:Landroid/widget/CompoundButton;
      44: aload_0
      45: getfield      #29                 // Field a:Landroid/widget/CompoundButton;
      48: invokevirtual #60                 // Method android/widget/CompoundButton.getContext:()Landroid/content/Context;
      51: iload_2
      52: invokestatic  #90                 // Method android/support/v7/c/a/b.b:(Landroid/content/Context;I)Landroid/graphics/drawable/Drawable;
      55: invokevirtual #94                 // Method android/widget/CompoundButton.setButtonDrawable:(Landroid/graphics/drawable/Drawable;)V
      58: aload_1
      59: getstatic     #97                 // Field android/support/v7/a/a$j.CompoundButton_buttonTint:I
      62: invokevirtual #81                 // Method android/content/res/TypedArray.hasValue:(I)Z
      65: ifeq          82
      68: aload_0
      69: getfield      #29                 // Field a:Landroid/widget/CompoundButton;
      72: aload_1
      73: getstatic     #97                 // Field android/support/v7/a/a$j.CompoundButton_buttonTint:I
      76: invokevirtual #101                // Method android/content/res/TypedArray.getColorStateList:(I)Landroid/content/res/ColorStateList;
      79: invokestatic  #104                // Method android/support/v4/widget/c.a:(Landroid/widget/CompoundButton;Landroid/content/res/ColorStateList;)V
      82: aload_1
      83: getstatic     #107                // Field android/support/v7/a/a$j.CompoundButton_buttonTintMode:I
      86: invokevirtual #81                 // Method android/content/res/TypedArray.hasValue:(I)Z
      89: ifeq          111
      92: aload_0
      93: getfield      #29                 // Field a:Landroid/widget/CompoundButton;
      96: aload_1
      97: getstatic     #107                // Field android/support/v7/a/a$j.CompoundButton_buttonTintMode:I
     100: iconst_m1
     101: invokevirtual #110                // Method android/content/res/TypedArray.getInt:(II)I
     104: aconst_null
     105: invokestatic  #115                // Method android/support/v7/widget/ao.a:(ILandroid/graphics/PorterDuff$Mode;)Landroid/graphics/PorterDuff$Mode;
     108: invokestatic  #118                // Method android/support/v4/widget/c.a:(Landroid/widget/CompoundButton;Landroid/graphics/PorterDuff$Mode;)V
     111: aload_1
     112: invokevirtual #121                // Method android/content/res/TypedArray.recycle:()V
     115: return
     116: astore_3
     117: aload_1
     118: invokevirtual #121                // Method android/content/res/TypedArray.recycle:()V
     121: aload_3
     122: athrow
    Exception table:
       from    to  target type
          17    36   116   any
          40    58   116   any
          58    82   116   any
          82   111   116   any

  android.graphics.PorterDuff$Mode b();
    Code:
       0: aload_0
       1: getfield      #23                 // Field c:Landroid/graphics/PorterDuff$Mode;
       4: areturn

  void c();
    Code:
       0: aload_0
       1: getfield      #124                // Field f:Z
       4: ifeq          13
       7: aload_0
       8: iconst_0
       9: putfield      #124                // Field f:Z
      12: return
      13: aload_0
      14: iconst_1
      15: putfield      #124                // Field f:Z
      18: aload_0
      19: invokevirtual #52                 // Method d:()V
      22: return

  void d();
    Code:
       0: aload_0
       1: getfield      #29                 // Field a:Landroid/widget/CompoundButton;
       4: invokestatic  #42                 // Method android/support/v4/widget/c.a:(Landroid/widget/CompoundButton;)Landroid/graphics/drawable/Drawable;
       7: astore_1
       8: aload_1
       9: ifnull        91
      12: aload_0
      13: getfield      #25                 // Field d:Z
      16: ifne          26
      19: aload_0
      20: getfield      #27                 // Field e:Z
      23: ifeq          91
      26: aload_1
      27: invokestatic  #129                // Method android/support/v4/b/a/a.f:(Landroid/graphics/drawable/Drawable;)Landroid/graphics/drawable/Drawable;
      30: invokevirtual #133                // Method android/graphics/drawable/Drawable.mutate:()Landroid/graphics/drawable/Drawable;
      33: astore_1
      34: aload_0
      35: getfield      #25                 // Field d:Z
      38: ifeq          49
      41: aload_1
      42: aload_0
      43: getfield      #21                 // Field b:Landroid/content/res/ColorStateList;
      46: invokestatic  #136                // Method android/support/v4/b/a/a.a:(Landroid/graphics/drawable/Drawable;Landroid/content/res/ColorStateList;)V
      49: aload_0
      50: getfield      #27                 // Field e:Z
      53: ifeq          64
      56: aload_1
      57: aload_0
      58: getfield      #23                 // Field c:Landroid/graphics/PorterDuff$Mode;
      61: invokestatic  #139                // Method android/support/v4/b/a/a.a:(Landroid/graphics/drawable/Drawable;Landroid/graphics/PorterDuff$Mode;)V
      64: aload_1
      65: invokevirtual #143                // Method android/graphics/drawable/Drawable.isStateful:()Z
      68: ifeq          83
      71: aload_1
      72: aload_0
      73: getfield      #29                 // Field a:Landroid/widget/CompoundButton;
      76: invokevirtual #147                // Method android/widget/CompoundButton.getDrawableState:()[I
      79: invokevirtual #151                // Method android/graphics/drawable/Drawable.setState:([I)Z
      82: pop
      83: aload_0
      84: getfield      #29                 // Field a:Landroid/widget/CompoundButton;
      87: aload_1
      88: invokevirtual #94                 // Method android/widget/CompoundButton.setButtonDrawable:(Landroid/graphics/drawable/Drawable;)V
      91: return
}
