public class android.support.v7.widget.LinearLayoutManager$b {
  public int a;

  public boolean b;

  public boolean c;

  public boolean d;

  protected android.support.v7.widget.LinearLayoutManager$b();
    Code:
       0: aload_0
       1: invokespecial #16                 // Method java/lang/Object."<init>":()V
       4: return

  void a();
    Code:
       0: aload_0
       1: iconst_0
       2: putfield      #19                 // Field a:I
       5: aload_0
       6: iconst_0
       7: putfield      #21                 // Field b:Z
      10: aload_0
      11: iconst_0
      12: putfield      #23                 // Field c:Z
      15: aload_0
      16: iconst_0
      17: putfield      #25                 // Field d:Z
      20: return
}
