public class android.support.v7.widget.LinearLayoutManager extends android.support.v7.widget.RecyclerView$i {
  int i;

  android.support.v7.widget.ba j;

  boolean k;

  int l;

  int m;

  android.support.v7.widget.LinearLayoutManager$d n;

  final android.support.v7.widget.LinearLayoutManager$a o;

  public android.support.v7.widget.LinearLayoutManager(android.content.Context);
    Code:
       0: aload_0
       1: aload_1
       2: iconst_1
       3: iconst_0
       4: invokespecial #41                 // Method "<init>":(Landroid/content/Context;IZ)V
       7: return

  public android.support.v7.widget.LinearLayoutManager(android.content.Context, int, boolean);
    Code:
       0: aload_0
       1: invokespecial #45                 // Method android/support/v7/widget/RecyclerView$i."<init>":()V
       4: aload_0
       5: iconst_1
       6: putfield      #47                 // Field i:I
       9: aload_0
      10: iconst_0
      11: putfield      #49                 // Field c:Z
      14: aload_0
      15: iconst_0
      16: putfield      #51                 // Field k:Z
      19: aload_0
      20: iconst_0
      21: putfield      #53                 // Field d:Z
      24: aload_0
      25: iconst_1
      26: putfield      #55                 // Field e:Z
      29: aload_0
      30: iconst_m1
      31: putfield      #57                 // Field l:I
      34: aload_0
      35: ldc           #58                 // int -2147483648
      37: putfield      #60                 // Field m:I
      40: aload_0
      41: aconst_null
      42: putfield      #62                 // Field n:Landroid/support/v7/widget/LinearLayoutManager$d;
      45: aload_0
      46: new           #6                  // class android/support/v7/widget/LinearLayoutManager$a
      49: dup
      50: invokespecial #63                 // Method android/support/v7/widget/LinearLayoutManager$a."<init>":()V
      53: putfield      #65                 // Field o:Landroid/support/v7/widget/LinearLayoutManager$a;
      56: aload_0
      57: new           #9                  // class android/support/v7/widget/LinearLayoutManager$b
      60: dup
      61: invokespecial #66                 // Method android/support/v7/widget/LinearLayoutManager$b."<init>":()V
      64: putfield      #68                 // Field g:Landroid/support/v7/widget/LinearLayoutManager$b;
      67: aload_0
      68: iconst_2
      69: putfield      #70                 // Field h:I
      72: aload_0
      73: iload_2
      74: invokevirtual #73                 // Method b:(I)V
      77: aload_0
      78: iload_3
      79: invokevirtual #76                 // Method b:(Z)V
      82: return

  public android.support.v7.widget.LinearLayoutManager(android.content.Context, android.util.AttributeSet, int, int);
    Code:
       0: aload_0
       1: invokespecial #45                 // Method android/support/v7/widget/RecyclerView$i."<init>":()V
       4: aload_0
       5: iconst_1
       6: putfield      #47                 // Field i:I
       9: aload_0
      10: iconst_0
      11: putfield      #49                 // Field c:Z
      14: aload_0
      15: iconst_0
      16: putfield      #51                 // Field k:Z
      19: aload_0
      20: iconst_0
      21: putfield      #53                 // Field d:Z
      24: aload_0
      25: iconst_1
      26: putfield      #55                 // Field e:Z
      29: aload_0
      30: iconst_m1
      31: putfield      #57                 // Field l:I
      34: aload_0
      35: ldc           #58                 // int -2147483648
      37: putfield      #60                 // Field m:I
      40: aload_0
      41: aconst_null
      42: putfield      #62                 // Field n:Landroid/support/v7/widget/LinearLayoutManager$d;
      45: aload_0
      46: new           #6                  // class android/support/v7/widget/LinearLayoutManager$a
      49: dup
      50: invokespecial #63                 // Method android/support/v7/widget/LinearLayoutManager$a."<init>":()V
      53: putfield      #65                 // Field o:Landroid/support/v7/widget/LinearLayoutManager$a;
      56: aload_0
      57: new           #9                  // class android/support/v7/widget/LinearLayoutManager$b
      60: dup
      61: invokespecial #66                 // Method android/support/v7/widget/LinearLayoutManager$b."<init>":()V
      64: putfield      #68                 // Field g:Landroid/support/v7/widget/LinearLayoutManager$b;
      67: aload_0
      68: iconst_2
      69: putfield      #70                 // Field h:I
      72: aload_1
      73: aload_2
      74: iload_3
      75: iload         4
      77: invokestatic  #80                 // Method a:(Landroid/content/Context;Landroid/util/AttributeSet;II)Landroid/support/v7/widget/RecyclerView$i$b;
      80: astore_1
      81: aload_0
      82: aload_1
      83: getfield      #84                 // Field android/support/v7/widget/RecyclerView$i$b.a:I
      86: invokevirtual #73                 // Method b:(I)V
      89: aload_0
      90: aload_1
      91: getfield      #85                 // Field android/support/v7/widget/RecyclerView$i$b.c:Z
      94: invokevirtual #76                 // Method b:(Z)V
      97: aload_0
      98: aload_1
      99: getfield      #86                 // Field android/support/v7/widget/RecyclerView$i$b.d:Z
     102: invokevirtual #88                 // Method a:(Z)V
     105: return

  public int a(int, android.support.v7.widget.RecyclerView$p, android.support.v7.widget.RecyclerView$u);
    Code:
       0: aload_0
       1: getfield      #47                 // Field i:I
       4: iconst_1
       5: if_icmpne     10
       8: iconst_0
       9: ireturn
      10: aload_0
      11: iload_1
      12: aload_2
      13: aload_3
      14: invokevirtual #112                // Method c:(ILandroid/support/v7/widget/RecyclerView$p;Landroid/support/v7/widget/RecyclerView$u;)I
      17: ireturn

  int a(android.support.v7.widget.RecyclerView$p, android.support.v7.widget.LinearLayoutManager$c, android.support.v7.widget.RecyclerView$u, boolean);
    Code:
       0: aload_2
       1: getfield      #123                // Field android/support/v7/widget/LinearLayoutManager$c.c:I
       4: istore        7
       6: aload_2
       7: getfield      #133                // Field android/support/v7/widget/LinearLayoutManager$c.g:I
      10: ldc           #58                 // int -2147483648
      12: if_icmpeq     41
      15: aload_2
      16: getfield      #123                // Field android/support/v7/widget/LinearLayoutManager$c.c:I
      19: ifge          35
      22: aload_2
      23: aload_2
      24: getfield      #133                // Field android/support/v7/widget/LinearLayoutManager$c.g:I
      27: aload_2
      28: getfield      #123                // Field android/support/v7/widget/LinearLayoutManager$c.c:I
      31: iadd
      32: putfield      #133                // Field android/support/v7/widget/LinearLayoutManager$c.g:I
      35: aload_0
      36: aload_1
      37: aload_2
      38: invokespecial #294                // Method a:(Landroid/support/v7/widget/RecyclerView$p;Landroid/support/v7/widget/LinearLayoutManager$c;)V
      41: aload_2
      42: getfield      #123                // Field android/support/v7/widget/LinearLayoutManager$c.c:I
      45: aload_2
      46: getfield      #142                // Field android/support/v7/widget/LinearLayoutManager$c.h:I
      49: iadd
      50: istore        5
      52: aload_0
      53: getfield      #68                 // Field g:Landroid/support/v7/widget/LinearLayoutManager$b;
      56: astore        8
      58: aload_2
      59: getfield      #138                // Field android/support/v7/widget/LinearLayoutManager$c.l:Z
      62: ifne          70
      65: iload         5
      67: ifle          245
      70: aload_2
      71: aload_3
      72: invokevirtual #297                // Method android/support/v7/widget/LinearLayoutManager$c.a:(Landroid/support/v7/widget/RecyclerView$u;)Z
      75: ifeq          245
      78: aload         8
      80: invokevirtual #298                // Method android/support/v7/widget/LinearLayoutManager$b.a:()V
      83: aload_0
      84: aload_1
      85: aload_3
      86: aload_2
      87: aload         8
      89: invokevirtual #301                // Method a:(Landroid/support/v7/widget/RecyclerView$p;Landroid/support/v7/widget/RecyclerView$u;Landroid/support/v7/widget/LinearLayoutManager$c;Landroid/support/v7/widget/LinearLayoutManager$b;)V
      92: aload         8
      94: getfield      #302                // Field android/support/v7/widget/LinearLayoutManager$b.b:Z
      97: ifeq          103
     100: goto          245
     103: aload_2
     104: aload_2
     105: getfield      #131                // Field android/support/v7/widget/LinearLayoutManager$c.b:I
     108: aload         8
     110: getfield      #303                // Field android/support/v7/widget/LinearLayoutManager$b.a:I
     113: aload_2
     114: getfield      #129                // Field android/support/v7/widget/LinearLayoutManager$c.f:I
     117: imul
     118: iadd
     119: putfield      #131                // Field android/support/v7/widget/LinearLayoutManager$c.b:I
     122: aload         8
     124: getfield      #304                // Field android/support/v7/widget/LinearLayoutManager$b.c:Z
     127: ifeq          151
     130: aload_0
     131: getfield      #121                // Field a:Landroid/support/v7/widget/LinearLayoutManager$c;
     134: getfield      #239                // Field android/support/v7/widget/LinearLayoutManager$c.k:Ljava/util/List;
     137: ifnonnull     151
     140: iload         5
     142: istore        6
     144: aload_3
     145: invokevirtual #193                // Method android/support/v7/widget/RecyclerView$u.a:()Z
     148: ifne          175
     151: aload_2
     152: aload_2
     153: getfield      #123                // Field android/support/v7/widget/LinearLayoutManager$c.c:I
     156: aload         8
     158: getfield      #303                // Field android/support/v7/widget/LinearLayoutManager$b.a:I
     161: isub
     162: putfield      #123                // Field android/support/v7/widget/LinearLayoutManager$c.c:I
     165: iload         5
     167: aload         8
     169: getfield      #303                // Field android/support/v7/widget/LinearLayoutManager$b.a:I
     172: isub
     173: istore        6
     175: aload_2
     176: getfield      #133                // Field android/support/v7/widget/LinearLayoutManager$c.g:I
     179: ldc           #58                 // int -2147483648
     181: if_icmpeq     224
     184: aload_2
     185: aload_2
     186: getfield      #133                // Field android/support/v7/widget/LinearLayoutManager$c.g:I
     189: aload         8
     191: getfield      #303                // Field android/support/v7/widget/LinearLayoutManager$b.a:I
     194: iadd
     195: putfield      #133                // Field android/support/v7/widget/LinearLayoutManager$c.g:I
     198: aload_2
     199: getfield      #123                // Field android/support/v7/widget/LinearLayoutManager$c.c:I
     202: ifge          218
     205: aload_2
     206: aload_2
     207: getfield      #133                // Field android/support/v7/widget/LinearLayoutManager$c.g:I
     210: aload_2
     211: getfield      #123                // Field android/support/v7/widget/LinearLayoutManager$c.c:I
     214: iadd
     215: putfield      #133                // Field android/support/v7/widget/LinearLayoutManager$c.g:I
     218: aload_0
     219: aload_1
     220: aload_2
     221: invokespecial #294                // Method a:(Landroid/support/v7/widget/RecyclerView$p;Landroid/support/v7/widget/LinearLayoutManager$c;)V
     224: iload         6
     226: istore        5
     228: iload         4
     230: ifeq          58
     233: iload         6
     235: istore        5
     237: aload         8
     239: getfield      #305                // Field android/support/v7/widget/LinearLayoutManager$b.d:Z
     242: ifeq          58
     245: iload         7
     247: aload_2
     248: getfield      #123                // Field android/support/v7/widget/LinearLayoutManager$c.c:I
     251: isub
     252: ireturn

  public android.support.v7.widget.RecyclerView$j a();
    Code:
       0: new           #308                // class android/support/v7/widget/RecyclerView$j
       3: dup
       4: bipush        -2
       6: bipush        -2
       8: invokespecial #310                // Method android/support/v7/widget/RecyclerView$j."<init>":(II)V
      11: areturn

  android.view.View a(int, int, boolean, boolean);
    Code:
       0: aload_0
       1: invokevirtual #271                // Method i:()V
       4: sipush        320
       7: istore        6
       9: iload_3
      10: ifeq          21
      13: sipush        24579
      16: istore        5
      18: goto          26
      21: sipush        320
      24: istore        5
      26: iload         4
      28: ifeq          34
      31: goto          37
      34: iconst_0
      35: istore        6
      37: aload_0
      38: getfield      #47                 // Field i:I
      41: ifne          62
      44: aload_0
      45: getfield      #314                // Field r:Landroid/support/v7/widget/bv;
      48: astore        7
      50: aload         7
      52: iload_1
      53: iload_2
      54: iload         5
      56: iload         6
      58: invokevirtual #319                // Method android/support/v7/widget/bv.a:(IIII)Landroid/view/View;
      61: areturn
      62: aload_0
      63: getfield      #322                // Field s:Landroid/support/v7/widget/bv;
      66: astore        7
      68: goto          50

  android.view.View a(android.support.v7.widget.RecyclerView$p, android.support.v7.widget.RecyclerView$u, int, int, int);
    Code:
       0: aload_0
       1: invokevirtual #271                // Method i:()V
       4: aload_0
       5: getfield      #105                // Field j:Landroid/support/v7/widget/ba;
       8: invokevirtual #155                // Method android/support/v7/widget/ba.c:()I
      11: istore        7
      13: aload_0
      14: getfield      #105                // Field j:Landroid/support/v7/widget/ba;
      17: invokevirtual #109                // Method android/support/v7/widget/ba.d:()I
      20: istore        8
      22: iload         4
      24: iload_3
      25: if_icmple     34
      28: iconst_1
      29: istore        6
      31: goto          37
      34: iconst_m1
      35: istore        6
      37: aconst_null
      38: astore_2
      39: aconst_null
      40: astore_1
      41: iload_3
      42: iload         4
      44: if_icmpeq     185
      47: aload_0
      48: iload_3
      49: invokevirtual #101                // Method h:(I)Landroid/view/View;
      52: astore        12
      54: aload_0
      55: aload         12
      57: invokevirtual #149                // Method d:(Landroid/view/View;)I
      60: istore        9
      62: aload_2
      63: astore        10
      65: aload_1
      66: astore        11
      68: iload         9
      70: iflt          171
      73: aload_2
      74: astore        10
      76: aload_1
      77: astore        11
      79: iload         9
      81: iload         5
      83: if_icmpge     171
      86: aload         12
      88: invokevirtual #328                // Method android/view/View.getLayoutParams:()Landroid/view/ViewGroup$LayoutParams;
      91: checkcast     #308                // class android/support/v7/widget/RecyclerView$j
      94: invokevirtual #330                // Method android/support/v7/widget/RecyclerView$j.d:()Z
      97: ifeq          120
     100: aload_2
     101: astore        10
     103: aload_1
     104: astore        11
     106: aload_1
     107: ifnonnull     171
     110: aload         12
     112: astore        11
     114: aload_2
     115: astore        10
     117: goto          171
     120: aload_0
     121: getfield      #105                // Field j:Landroid/support/v7/widget/ba;
     124: aload         12
     126: invokevirtual #157                // Method android/support/v7/widget/ba.a:(Landroid/view/View;)I
     129: iload         8
     131: if_icmpge     154
     134: aload_0
     135: getfield      #105                // Field j:Landroid/support/v7/widget/ba;
     138: aload         12
     140: invokevirtual #151                // Method android/support/v7/widget/ba.b:(Landroid/view/View;)I
     143: iload         7
     145: if_icmpge     151
     148: goto          154
     151: aload         12
     153: areturn
     154: aload_2
     155: astore        10
     157: aload_1
     158: astore        11
     160: aload_2
     161: ifnonnull     171
     164: aload         12
     166: astore        10
     168: aload_1
     169: astore        11
     171: iload_3
     172: iload         6
     174: iadd
     175: istore_3
     176: aload         10
     178: astore_2
     179: aload         11
     181: astore_1
     182: goto          41
     185: aload_2
     186: ifnull        191
     189: aload_2
     190: areturn
     191: aload_1
     192: areturn

  public android.view.View a(android.view.View, int, android.support.v7.widget.RecyclerView$p, android.support.v7.widget.RecyclerView$u);
    Code:
       0: aload_0
       1: invokespecial #333                // Method K:()V
       4: aload_0
       5: invokevirtual #98                 // Method v:()I
       8: ifne          13
      11: aconst_null
      12: areturn
      13: aload_0
      14: iload_2
      15: invokevirtual #336                // Method e:(I)I
      18: istore_2
      19: iload_2
      20: ldc           #58                 // int -2147483648
      22: if_icmpne     27
      25: aconst_null
      26: areturn
      27: aload_0
      28: invokevirtual #271                // Method i:()V
      31: aload_0
      32: invokevirtual #271                // Method i:()V
      35: aload_0
      36: iload_2
      37: aload_0
      38: getfield      #105                // Field j:Landroid/support/v7/widget/ba;
      41: invokevirtual #203                // Method android/support/v7/widget/ba.f:()I
      44: i2f
      45: ldc_w         #337                // float 0.33333334f
      48: fmul
      49: f2i
      50: iconst_0
      51: aload         4
      53: invokespecial #339                // Method a:(IIZLandroid/support/v7/widget/RecyclerView$u;)V
      56: aload_0
      57: getfield      #121                // Field a:Landroid/support/v7/widget/LinearLayoutManager$c;
      60: ldc           #58                 // int -2147483648
      62: putfield      #133                // Field android/support/v7/widget/LinearLayoutManager$c.g:I
      65: aload_0
      66: getfield      #121                // Field a:Landroid/support/v7/widget/LinearLayoutManager$c;
      69: iconst_0
      70: putfield      #174                // Field android/support/v7/widget/LinearLayoutManager$c.a:Z
      73: aload_0
      74: aload_3
      75: aload_0
      76: getfield      #121                // Field a:Landroid/support/v7/widget/LinearLayoutManager$c;
      79: aload         4
      81: iconst_1
      82: invokevirtual #244                // Method a:(Landroid/support/v7/widget/RecyclerView$p;Landroid/support/v7/widget/LinearLayoutManager$c;Landroid/support/v7/widget/RecyclerView$u;Z)I
      85: pop
      86: iload_2
      87: iconst_m1
      88: if_icmpne     102
      91: aload_0
      92: aload_3
      93: aload         4
      95: invokespecial #341                // Method k:(Landroid/support/v7/widget/RecyclerView$p;Landroid/support/v7/widget/RecyclerView$u;)Landroid/view/View;
      98: astore_1
      99: goto          110
     102: aload_0
     103: aload_3
     104: aload         4
     106: invokespecial #343                // Method j:(Landroid/support/v7/widget/RecyclerView$p;Landroid/support/v7/widget/RecyclerView$u;)Landroid/view/View;
     109: astore_1
     110: iload_2
     111: iconst_m1
     112: if_icmpne     123
     115: aload_0
     116: invokespecial #153                // Method L:()Landroid/view/View;
     119: astore_3
     120: goto          128
     123: aload_0
     124: invokespecial #146                // Method M:()Landroid/view/View;
     127: astore_3
     128: aload_3
     129: invokevirtual #346                // Method android/view/View.hasFocusable:()Z
     132: ifeq          143
     135: aload_1
     136: ifnonnull     141
     139: aconst_null
     140: areturn
     141: aload_3
     142: areturn
     143: aload_1
     144: areturn

  public void a(int, int, android.support.v7.widget.RecyclerView$u, android.support.v7.widget.RecyclerView$i$a);
    Code:
       0: aload_0
       1: getfield      #47                 // Field i:I
       4: ifne          10
       7: goto          12
      10: iload_2
      11: istore_1
      12: aload_0
      13: invokevirtual #98                 // Method v:()I
      16: ifeq          61
      19: iload_1
      20: ifne          24
      23: return
      24: aload_0
      25: invokevirtual #271                // Method i:()V
      28: iload_1
      29: ifle          37
      32: iconst_1
      33: istore_2
      34: goto          39
      37: iconst_m1
      38: istore_2
      39: aload_0
      40: iload_2
      41: iload_1
      42: invokestatic  #352                // Method java/lang/Math.abs:(I)I
      45: iconst_1
      46: aload_3
      47: invokespecial #339                // Method a:(IIZLandroid/support/v7/widget/RecyclerView$u;)V
      50: aload_0
      51: aload_3
      52: aload_0
      53: getfield      #121                // Field a:Landroid/support/v7/widget/LinearLayoutManager$c;
      56: aload         4
      58: invokevirtual #355                // Method a:(Landroid/support/v7/widget/RecyclerView$u;Landroid/support/v7/widget/LinearLayoutManager$c;Landroid/support/v7/widget/RecyclerView$i$a;)V
      61: return

  public void a(int, android.support.v7.widget.RecyclerView$i$a);
    Code:
       0: aload_0
       1: getfield      #62                 // Field n:Landroid/support/v7/widget/LinearLayoutManager$d;
       4: astore        8
       6: iconst_m1
       7: istore        4
       9: aload         8
      11: ifnull        44
      14: aload_0
      15: getfield      #62                 // Field n:Landroid/support/v7/widget/LinearLayoutManager$d;
      18: invokevirtual #194                // Method android/support/v7/widget/LinearLayoutManager$d.a:()Z
      21: ifeq          44
      24: aload_0
      25: getfield      #62                 // Field n:Landroid/support/v7/widget/LinearLayoutManager$d;
      28: getfield      #195                // Field android/support/v7/widget/LinearLayoutManager$d.c:Z
      31: istore        7
      33: aload_0
      34: getfield      #62                 // Field n:Landroid/support/v7/widget/LinearLayoutManager$d;
      37: getfield      #357                // Field android/support/v7/widget/LinearLayoutManager$d.a:I
      40: istore_3
      41: goto          84
      44: aload_0
      45: invokespecial #333                // Method K:()V
      48: aload_0
      49: getfield      #51                 // Field k:Z
      52: istore        7
      54: aload_0
      55: getfield      #57                 // Field l:I
      58: iconst_m1
      59: if_icmpne     79
      62: iload         7
      64: ifeq          74
      67: iload_1
      68: iconst_1
      69: isub
      70: istore_3
      71: goto          84
      74: iconst_0
      75: istore_3
      76: goto          84
      79: aload_0
      80: getfield      #57                 // Field l:I
      83: istore_3
      84: iload         7
      86: ifeq          92
      89: goto          95
      92: iconst_1
      93: istore        4
      95: iconst_0
      96: istore        6
      98: iload_3
      99: istore        5
     101: iload         6
     103: istore_3
     104: iload_3
     105: aload_0
     106: getfield      #70                 // Field h:I
     109: if_icmpge     146
     112: iload         5
     114: iflt          146
     117: iload         5
     119: iload_1
     120: if_icmpge     146
     123: aload_2
     124: iload         5
     126: iconst_0
     127: invokeinterface #361,  3          // InterfaceMethod android/support/v7/widget/RecyclerView$i$a.b:(II)V
     132: iload         5
     134: iload         4
     136: iadd
     137: istore        5
     139: iload_3
     140: iconst_1
     141: iadd
     142: istore_3
     143: goto          104
     146: return

  public void a(android.os.Parcelable);
    Code:
       0: aload_1
       1: instanceof    #15                 // class android/support/v7/widget/LinearLayoutManager$d
       4: ifeq          19
       7: aload_0
       8: aload_1
       9: checkcast     #15                 // class android/support/v7/widget/LinearLayoutManager$d
      12: putfield      #62                 // Field n:Landroid/support/v7/widget/LinearLayoutManager$d;
      15: aload_0
      16: invokevirtual #364                // Method o:()V
      19: return

  void a(android.support.v7.widget.RecyclerView$p, android.support.v7.widget.RecyclerView$u, android.support.v7.widget.LinearLayoutManager$a, int);
    Code:
       0: return

  void a(android.support.v7.widget.RecyclerView$p, android.support.v7.widget.RecyclerView$u, android.support.v7.widget.LinearLayoutManager$c, android.support.v7.widget.LinearLayoutManager$b);
    Code:
       0: aload_3
       1: aload_1
       2: invokevirtual #368                // Method android/support/v7/widget/LinearLayoutManager$c.a:(Landroid/support/v7/widget/RecyclerView$p;)Landroid/view/View;
       5: astore_1
       6: aload_1
       7: ifnonnull     17
      10: aload         4
      12: iconst_1
      13: putfield      #302                // Field android/support/v7/widget/LinearLayoutManager$b.b:Z
      16: return
      17: aload_1
      18: invokevirtual #328                // Method android/view/View.getLayoutParams:()Landroid/view/ViewGroup$LayoutParams;
      21: checkcast     #308                // class android/support/v7/widget/RecyclerView$j
      24: astore_2
      25: aload_3
      26: getfield      #239                // Field android/support/v7/widget/LinearLayoutManager$c.k:Ljava/util/List;
      29: ifnonnull     79
      32: aload_0
      33: getfield      #51                 // Field k:Z
      36: istore        12
      38: aload_3
      39: getfield      #129                // Field android/support/v7/widget/LinearLayoutManager$c.f:I
      42: iconst_m1
      43: if_icmpne     52
      46: iconst_1
      47: istore        11
      49: goto          55
      52: iconst_0
      53: istore        11
      55: iload         12
      57: iload         11
      59: if_icmpne     70
      62: aload_0
      63: aload_1
      64: invokevirtual #371                // Method b:(Landroid/view/View;)V
      67: goto          123
      70: aload_0
      71: aload_1
      72: iconst_0
      73: invokevirtual #372                // Method b:(Landroid/view/View;I)V
      76: goto          123
      79: aload_0
      80: getfield      #51                 // Field k:Z
      83: istore        12
      85: aload_3
      86: getfield      #129                // Field android/support/v7/widget/LinearLayoutManager$c.f:I
      89: iconst_m1
      90: if_icmpne     99
      93: iconst_1
      94: istore        11
      96: goto          102
      99: iconst_0
     100: istore        11
     102: iload         12
     104: iload         11
     106: if_icmpne     117
     109: aload_0
     110: aload_1
     111: invokevirtual #374                // Method a:(Landroid/view/View;)V
     114: goto          123
     117: aload_0
     118: aload_1
     119: iconst_0
     120: invokevirtual #375                // Method a:(Landroid/view/View;I)V
     123: aload_0
     124: aload_1
     125: iconst_0
     126: iconst_0
     127: invokevirtual #378                // Method a:(Landroid/view/View;II)V
     130: aload         4
     132: aload_0
     133: getfield      #105                // Field j:Landroid/support/v7/widget/ba;
     136: aload_1
     137: invokevirtual #201                // Method android/support/v7/widget/ba.e:(Landroid/view/View;)I
     140: putfield      #303                // Field android/support/v7/widget/LinearLayoutManager$b.a:I
     143: aload_0
     144: getfield      #47                 // Field i:I
     147: iconst_1
     148: if_icmpne     270
     151: aload_0
     152: invokevirtual #92                 // Method h:()Z
     155: ifeq          185
     158: aload_0
     159: invokevirtual #381                // Method y:()I
     162: aload_0
     163: invokevirtual #384                // Method C:()I
     166: isub
     167: istore        5
     169: iload         5
     171: aload_0
     172: getfield      #105                // Field j:Landroid/support/v7/widget/ba;
     175: aload_1
     176: invokevirtual #386                // Method android/support/v7/widget/ba.f:(Landroid/view/View;)I
     179: isub
     180: istore        8
     182: goto          204
     185: aload_0
     186: invokevirtual #389                // Method A:()I
     189: istore        8
     191: aload_0
     192: getfield      #105                // Field j:Landroid/support/v7/widget/ba;
     195: aload_1
     196: invokevirtual #386                // Method android/support/v7/widget/ba.f:(Landroid/view/View;)I
     199: iload         8
     201: iadd
     202: istore        5
     204: aload_3
     205: getfield      #129                // Field android/support/v7/widget/LinearLayoutManager$c.f:I
     208: iconst_m1
     209: if_icmpne     241
     212: aload_3
     213: getfield      #131                // Field android/support/v7/widget/LinearLayoutManager$c.b:I
     216: istore        7
     218: aload_3
     219: getfield      #131                // Field android/support/v7/widget/LinearLayoutManager$c.b:I
     222: aload         4
     224: getfield      #303                // Field android/support/v7/widget/LinearLayoutManager$b.a:I
     227: isub
     228: istore        9
     230: iload         5
     232: istore        6
     234: iload         9
     236: istore        5
     238: goto          380
     241: aload_3
     242: getfield      #131                // Field android/support/v7/widget/LinearLayoutManager$c.b:I
     245: istore        9
     247: aload_3
     248: getfield      #131                // Field android/support/v7/widget/LinearLayoutManager$c.b:I
     251: aload         4
     253: getfield      #303                // Field android/support/v7/widget/LinearLayoutManager$b.a:I
     256: iadd
     257: istore        7
     259: iload         5
     261: istore        6
     263: iload         9
     265: istore        5
     267: goto          380
     270: aload_0
     271: invokevirtual #392                // Method B:()I
     274: istore        6
     276: aload_0
     277: getfield      #105                // Field j:Landroid/support/v7/widget/ba;
     280: aload_1
     281: invokevirtual #386                // Method android/support/v7/widget/ba.f:(Landroid/view/View;)I
     284: iload         6
     286: iadd
     287: istore        5
     289: aload_3
     290: getfield      #129                // Field android/support/v7/widget/LinearLayoutManager$c.f:I
     293: iconst_m1
     294: if_icmpne     342
     297: aload_3
     298: getfield      #131                // Field android/support/v7/widget/LinearLayoutManager$c.b:I
     301: istore        7
     303: aload_3
     304: getfield      #131                // Field android/support/v7/widget/LinearLayoutManager$c.b:I
     307: istore        8
     309: aload         4
     311: getfield      #303                // Field android/support/v7/widget/LinearLayoutManager$b.a:I
     314: istore        10
     316: iload         5
     318: istore        9
     320: iload         8
     322: iload         10
     324: isub
     325: istore        8
     327: iload         6
     329: istore        5
     331: iload         7
     333: istore        6
     335: iload         9
     337: istore        7
     339: goto          380
     342: aload_3
     343: getfield      #131                // Field android/support/v7/widget/LinearLayoutManager$c.b:I
     346: istore        9
     348: aload_3
     349: getfield      #131                // Field android/support/v7/widget/LinearLayoutManager$c.b:I
     352: aload         4
     354: getfield      #303                // Field android/support/v7/widget/LinearLayoutManager$b.a:I
     357: iadd
     358: istore        10
     360: iload         6
     362: istore        8
     364: iload         5
     366: istore        7
     368: iload         10
     370: istore        6
     372: iload         8
     374: istore        5
     376: iload         9
     378: istore        8
     380: aload_0
     381: aload_1
     382: iload         8
     384: iload         5
     386: iload         6
     388: iload         7
     390: invokevirtual #395                // Method a:(Landroid/view/View;IIII)V
     393: aload_2
     394: invokevirtual #330                // Method android/support/v7/widget/RecyclerView$j.d:()Z
     397: ifne          407
     400: aload_2
     401: invokevirtual #397                // Method android/support/v7/widget/RecyclerView$j.e:()Z
     404: ifeq          413
     407: aload         4
     409: iconst_1
     410: putfield      #304                // Field android/support/v7/widget/LinearLayoutManager$b.c:Z
     413: aload         4
     415: aload_1
     416: invokevirtual #346                // Method android/view/View.hasFocusable:()Z
     419: putfield      #305                // Field android/support/v7/widget/LinearLayoutManager$b.d:Z
     422: return

  public void a(android.support.v7.widget.RecyclerView$u);
    Code:
       0: aload_0
       1: aload_1
       2: invokespecial #400                // Method android/support/v7/widget/RecyclerView$i.a:(Landroid/support/v7/widget/RecyclerView$u;)V
       5: aload_0
       6: aconst_null
       7: putfield      #62                 // Field n:Landroid/support/v7/widget/LinearLayoutManager$d;
      10: aload_0
      11: iconst_m1
      12: putfield      #57                 // Field l:I
      15: aload_0
      16: ldc           #58                 // int -2147483648
      18: putfield      #60                 // Field m:I
      21: aload_0
      22: getfield      #65                 // Field o:Landroid/support/v7/widget/LinearLayoutManager$a;
      25: invokevirtual #401                // Method android/support/v7/widget/LinearLayoutManager$a.a:()V
      28: return

  void a(android.support.v7.widget.RecyclerView$u, android.support.v7.widget.LinearLayoutManager$c, android.support.v7.widget.RecyclerView$i$a);
    Code:
       0: aload_2
       1: getfield      #127                // Field android/support/v7/widget/LinearLayoutManager$c.d:I
       4: istore        4
       6: iload         4
       8: iflt          36
      11: iload         4
      13: aload_1
      14: invokevirtual #191                // Method android/support/v7/widget/RecyclerView$u.e:()I
      17: if_icmpge     36
      20: aload_3
      21: iload         4
      23: iconst_0
      24: aload_2
      25: getfield      #133                // Field android/support/v7/widget/LinearLayoutManager$c.g:I
      28: invokestatic  #405                // Method java/lang/Math.max:(II)I
      31: invokeinterface #361,  3          // InterfaceMethod android/support/v7/widget/RecyclerView$i$a.b:(II)V
      36: return

  public void a(android.support.v7.widget.RecyclerView, android.support.v7.widget.RecyclerView$p);
    Code:
       0: aload_0
       1: aload_1
       2: aload_2
       3: invokespecial #408                // Method android/support/v7/widget/RecyclerView$i.a:(Landroid/support/v7/widget/RecyclerView;Landroid/support/v7/widget/RecyclerView$p;)V
       6: aload_0
       7: getfield      #410                // Field f:Z
      10: ifeq          22
      13: aload_0
      14: aload_2
      15: invokevirtual #413                // Method c:(Landroid/support/v7/widget/RecyclerView$p;)V
      18: aload_2
      19: invokevirtual #414                // Method android/support/v7/widget/RecyclerView$p.a:()V
      22: return

  public void a(android.view.accessibility.AccessibilityEvent);
    Code:
       0: aload_0
       1: aload_1
       2: invokespecial #417                // Method android/support/v7/widget/RecyclerView$i.a:(Landroid/view/accessibility/AccessibilityEvent;)V
       5: aload_0
       6: invokevirtual #98                 // Method v:()I
       9: ifle          28
      12: aload_1
      13: aload_0
      14: invokevirtual #419                // Method m:()I
      17: invokevirtual #424                // Method android/view/accessibility/AccessibilityEvent.setFromIndex:(I)V
      20: aload_1
      21: aload_0
      22: invokevirtual #426                // Method n:()I
      25: invokevirtual #429                // Method android/view/accessibility/AccessibilityEvent.setToIndex:(I)V
      28: return

  public void a(java.lang.String);
    Code:
       0: aload_0
       1: getfield      #62                 // Field n:Landroid/support/v7/widget/LinearLayoutManager$d;
       4: ifnonnull     12
       7: aload_0
       8: aload_1
       9: invokespecial #432                // Method android/support/v7/widget/RecyclerView$i.a:(Ljava/lang/String;)V
      12: return

  public void a(boolean);
    Code:
       0: aload_0
       1: aconst_null
       2: invokevirtual #433                // Method a:(Ljava/lang/String;)V
       5: aload_0
       6: getfield      #53                 // Field d:Z
       9: iload_1
      10: if_icmpne     14
      13: return
      14: aload_0
      15: iload_1
      16: putfield      #53                 // Field d:Z
      19: aload_0
      20: invokevirtual #364                // Method o:()V
      23: return

  public int b(int, android.support.v7.widget.RecyclerView$p, android.support.v7.widget.RecyclerView$u);
    Code:
       0: aload_0
       1: getfield      #47                 // Field i:I
       4: ifne          9
       7: iconst_0
       8: ireturn
       9: aload_0
      10: iload_1
      11: aload_2
      12: aload_3
      13: invokevirtual #112                // Method c:(ILandroid/support/v7/widget/RecyclerView$p;Landroid/support/v7/widget/RecyclerView$u;)I
      16: ireturn

  protected int b(android.support.v7.widget.RecyclerView$u);
    Code:
       0: aload_1
       1: invokevirtual #434                // Method android/support/v7/widget/RecyclerView$u.d:()Z
       4: ifeq          15
       7: aload_0
       8: getfield      #105                // Field j:Landroid/support/v7/widget/ba;
      11: invokevirtual #203                // Method android/support/v7/widget/ba.f:()I
      14: ireturn
      15: iconst_0
      16: ireturn

  android.view.View b(int, int);
    Code:
       0: aload_0
       1: invokevirtual #271                // Method i:()V
       4: iload_2
       5: iload_1
       6: if_icmple     14
       9: iconst_1
      10: istore_3
      11: goto          26
      14: iload_2
      15: iload_1
      16: if_icmpge     24
      19: iconst_m1
      20: istore_3
      21: goto          26
      24: iconst_0
      25: istore_3
      26: iload_3
      27: ifne          36
      30: aload_0
      31: iload_1
      32: invokevirtual #101                // Method h:(I)Landroid/view/View;
      35: areturn
      36: aload_0
      37: getfield      #105                // Field j:Landroid/support/v7/widget/ba;
      40: aload_0
      41: iload_1
      42: invokevirtual #101                // Method h:(I)Landroid/view/View;
      45: invokevirtual #157                // Method android/support/v7/widget/ba.a:(Landroid/view/View;)I
      48: aload_0
      49: getfield      #105                // Field j:Landroid/support/v7/widget/ba;
      52: invokevirtual #155                // Method android/support/v7/widget/ba.c:()I
      55: if_icmpge     70
      58: sipush        16644
      61: istore_3
      62: sipush        16388
      65: istore        4
      67: goto          79
      70: sipush        4161
      73: istore_3
      74: sipush        4097
      77: istore        4
      79: aload_0
      80: getfield      #47                 // Field i:I
      83: ifne          103
      86: aload_0
      87: getfield      #314                // Field r:Landroid/support/v7/widget/bv;
      90: astore        5
      92: aload         5
      94: iload_1
      95: iload_2
      96: iload_3
      97: iload         4
      99: invokevirtual #319                // Method android/support/v7/widget/bv.a:(IIII)Landroid/view/View;
     102: areturn
     103: aload_0
     104: getfield      #322                // Field s:Landroid/support/v7/widget/bv;
     107: astore        5
     109: goto          92

  public void b(int);
    Code:
       0: iload_1
       1: ifeq          43
       4: iload_1
       5: iconst_1
       6: if_icmpeq     43
       9: new           #436                // class java/lang/StringBuilder
      12: dup
      13: invokespecial #437                // Method java/lang/StringBuilder."<init>":()V
      16: astore_2
      17: aload_2
      18: ldc_w         #439                // String invalid orientation:
      21: invokevirtual #443                // Method java/lang/StringBuilder.append:(Ljava/lang/String;)Ljava/lang/StringBuilder;
      24: pop
      25: aload_2
      26: iload_1
      27: invokevirtual #446                // Method java/lang/StringBuilder.append:(I)Ljava/lang/StringBuilder;
      30: pop
      31: new           #448                // class java/lang/IllegalArgumentException
      34: dup
      35: aload_2
      36: invokevirtual #452                // Method java/lang/StringBuilder.toString:()Ljava/lang/String;
      39: invokespecial #454                // Method java/lang/IllegalArgumentException."<init>":(Ljava/lang/String;)V
      42: athrow
      43: aload_0
      44: aconst_null
      45: invokevirtual #433                // Method a:(Ljava/lang/String;)V
      48: iload_1
      49: aload_0
      50: getfield      #47                 // Field i:I
      53: if_icmpne     63
      56: aload_0
      57: getfield      #105                // Field j:Landroid/support/v7/widget/ba;
      60: ifnonnull     92
      63: aload_0
      64: aload_0
      65: iload_1
      66: invokestatic  #457                // Method android/support/v7/widget/ba.a:(Landroid/support/v7/widget/RecyclerView$i;I)Landroid/support/v7/widget/ba;
      69: putfield      #105                // Field j:Landroid/support/v7/widget/ba;
      72: aload_0
      73: getfield      #65                 // Field o:Landroid/support/v7/widget/LinearLayoutManager$a;
      76: aload_0
      77: getfield      #105                // Field j:Landroid/support/v7/widget/ba;
      80: putfield      #459                // Field android/support/v7/widget/LinearLayoutManager$a.a:Landroid/support/v7/widget/ba;
      83: aload_0
      84: iload_1
      85: putfield      #47                 // Field i:I
      88: aload_0
      89: invokevirtual #364                // Method o:()V
      92: return

  public void b(boolean);
    Code:
       0: aload_0
       1: aconst_null
       2: invokevirtual #433                // Method a:(Ljava/lang/String;)V
       5: iload_1
       6: aload_0
       7: getfield      #49                 // Field c:Z
      10: if_icmpne     14
      13: return
      14: aload_0
      15: iload_1
      16: putfield      #49                 // Field c:Z
      19: aload_0
      20: invokevirtual #364                // Method o:()V
      23: return

  public boolean b();
    Code:
       0: aload_0
       1: getfield      #62                 // Field n:Landroid/support/v7/widget/LinearLayoutManager$d;
       4: ifnonnull     20
       7: aload_0
       8: getfield      #255                // Field b:Z
      11: aload_0
      12: getfield      #53                 // Field d:Z
      15: if_icmpne     20
      18: iconst_1
      19: ireturn
      20: iconst_0
      21: ireturn

  int c(int, android.support.v7.widget.RecyclerView$p, android.support.v7.widget.RecyclerView$u);
    Code:
       0: aload_0
       1: invokevirtual #98                 // Method v:()I
       4: ifeq          114
       7: iload_1
       8: ifne          13
      11: iconst_0
      12: ireturn
      13: aload_0
      14: getfield      #121                // Field a:Landroid/support/v7/widget/LinearLayoutManager$c;
      17: iconst_1
      18: putfield      #174                // Field android/support/v7/widget/LinearLayoutManager$c.a:Z
      21: aload_0
      22: invokevirtual #271                // Method i:()V
      25: iload_1
      26: ifle          35
      29: iconst_1
      30: istore        4
      32: goto          38
      35: iconst_m1
      36: istore        4
      38: iload_1
      39: invokestatic  #352                // Method java/lang/Math.abs:(I)I
      42: istore        5
      44: aload_0
      45: iload         4
      47: iload         5
      49: iconst_1
      50: aload_3
      51: invokespecial #339                // Method a:(IIZLandroid/support/v7/widget/RecyclerView$u;)V
      54: aload_0
      55: getfield      #121                // Field a:Landroid/support/v7/widget/LinearLayoutManager$c;
      58: getfield      #133                // Field android/support/v7/widget/LinearLayoutManager$c.g:I
      61: aload_0
      62: aload_2
      63: aload_0
      64: getfield      #121                // Field a:Landroid/support/v7/widget/LinearLayoutManager$c;
      67: aload_3
      68: iconst_0
      69: invokevirtual #244                // Method a:(Landroid/support/v7/widget/RecyclerView$p;Landroid/support/v7/widget/LinearLayoutManager$c;Landroid/support/v7/widget/RecyclerView$u;Z)I
      72: iadd
      73: istore        6
      75: iload         6
      77: ifge          82
      80: iconst_0
      81: ireturn
      82: iload         5
      84: iload         6
      86: if_icmple     95
      89: iload         4
      91: iload         6
      93: imul
      94: istore_1
      95: aload_0
      96: getfield      #105                // Field j:Landroid/support/v7/widget/ba;
      99: iload_1
     100: ineg
     101: invokevirtual #114                // Method android/support/v7/widget/ba.a:(I)V
     104: aload_0
     105: getfield      #121                // Field a:Landroid/support/v7/widget/LinearLayoutManager$c;
     108: iload_1
     109: putfield      #461                // Field android/support/v7/widget/LinearLayoutManager$c.j:I
     112: iload_1
     113: ireturn
     114: iconst_0
     115: ireturn

  public int c(android.support.v7.widget.RecyclerView$u);
    Code:
       0: aload_0
       1: aload_1
       2: invokespecial #463                // Method i:(Landroid/support/v7/widget/RecyclerView$u;)I
       5: ireturn

  public android.view.View c(int);
    Code:
       0: aload_0
       1: invokevirtual #98                 // Method v:()I
       4: istore_2
       5: iload_2
       6: ifne          11
       9: aconst_null
      10: areturn
      11: iload_1
      12: aload_0
      13: aload_0
      14: iconst_0
      15: invokevirtual #101                // Method h:(I)Landroid/view/View;
      18: invokevirtual #149                // Method d:(Landroid/view/View;)I
      21: isub
      22: istore_3
      23: iload_3
      24: iflt          52
      27: iload_3
      28: iload_2
      29: if_icmpge     52
      32: aload_0
      33: iload_3
      34: invokevirtual #101                // Method h:(I)Landroid/view/View;
      37: astore        4
      39: aload_0
      40: aload         4
      42: invokevirtual #149                // Method d:(Landroid/view/View;)I
      45: iload_1
      46: if_icmpne     52
      49: aload         4
      51: areturn
      52: aload_0
      53: iload_1
      54: invokespecial #464                // Method android/support/v7/widget/RecyclerView$i.c:(I)Landroid/view/View;
      57: areturn

  public void c(android.support.v7.widget.RecyclerView$p, android.support.v7.widget.RecyclerView$u);
    Code:
       0: aload_0
       1: getfield      #62                 // Field n:Landroid/support/v7/widget/LinearLayoutManager$d;
       4: astore        8
       6: iconst_m1
       7: istore        5
       9: aload         8
      11: ifnonnull     22
      14: aload_0
      15: getfield      #57                 // Field l:I
      18: iconst_m1
      19: if_icmpeq     35
      22: aload_2
      23: invokevirtual #191                // Method android/support/v7/widget/RecyclerView$u.e:()I
      26: ifne          35
      29: aload_0
      30: aload_1
      31: invokevirtual #413                // Method c:(Landroid/support/v7/widget/RecyclerView$p;)V
      34: return
      35: aload_0
      36: getfield      #62                 // Field n:Landroid/support/v7/widget/LinearLayoutManager$d;
      39: ifnull        63
      42: aload_0
      43: getfield      #62                 // Field n:Landroid/support/v7/widget/LinearLayoutManager$d;
      46: invokevirtual #194                // Method android/support/v7/widget/LinearLayoutManager$d.a:()Z
      49: ifeq          63
      52: aload_0
      53: aload_0
      54: getfield      #62                 // Field n:Landroid/support/v7/widget/LinearLayoutManager$d;
      57: getfield      #357                // Field android/support/v7/widget/LinearLayoutManager$d.a:I
      60: putfield      #57                 // Field l:I
      63: aload_0
      64: invokevirtual #271                // Method i:()V
      67: aload_0
      68: getfield      #121                // Field a:Landroid/support/v7/widget/LinearLayoutManager$c;
      71: iconst_0
      72: putfield      #174                // Field android/support/v7/widget/LinearLayoutManager$c.a:Z
      75: aload_0
      76: invokespecial #333                // Method K:()V
      79: aload_0
      80: invokevirtual #247                // Method E:()Landroid/view/View;
      83: astore        8
      85: aload_0
      86: getfield      #65                 // Field o:Landroid/support/v7/widget/LinearLayoutManager$a;
      89: getfield      #466                // Field android/support/v7/widget/LinearLayoutManager$a.e:Z
      92: ifeq          174
      95: aload_0
      96: getfield      #57                 // Field l:I
      99: iconst_m1
     100: if_icmpne     174
     103: aload_0
     104: getfield      #62                 // Field n:Landroid/support/v7/widget/LinearLayoutManager$d;
     107: ifnull        113
     110: goto          174
     113: aload         8
     115: ifnull        215
     118: aload_0
     119: getfield      #105                // Field j:Landroid/support/v7/widget/ba;
     122: aload         8
     124: invokevirtual #157                // Method android/support/v7/widget/ba.a:(Landroid/view/View;)I
     127: aload_0
     128: getfield      #105                // Field j:Landroid/support/v7/widget/ba;
     131: invokevirtual #109                // Method android/support/v7/widget/ba.d:()I
     134: if_icmpge     156
     137: aload_0
     138: getfield      #105                // Field j:Landroid/support/v7/widget/ba;
     141: aload         8
     143: invokevirtual #151                // Method android/support/v7/widget/ba.b:(Landroid/view/View;)I
     146: aload_0
     147: getfield      #105                // Field j:Landroid/support/v7/widget/ba;
     150: invokevirtual #155                // Method android/support/v7/widget/ba.c:()I
     153: if_icmpgt     215
     156: aload_0
     157: getfield      #65                 // Field o:Landroid/support/v7/widget/LinearLayoutManager$a;
     160: aload         8
     162: aload_0
     163: aload         8
     165: invokevirtual #149                // Method d:(Landroid/view/View;)I
     168: invokevirtual #253                // Method android/support/v7/widget/LinearLayoutManager$a.a:(Landroid/view/View;I)V
     171: goto          215
     174: aload_0
     175: getfield      #65                 // Field o:Landroid/support/v7/widget/LinearLayoutManager$a;
     178: invokevirtual #401                // Method android/support/v7/widget/LinearLayoutManager$a.a:()V
     181: aload_0
     182: getfield      #65                 // Field o:Landroid/support/v7/widget/LinearLayoutManager$a;
     185: aload_0
     186: getfield      #51                 // Field k:Z
     189: aload_0
     190: getfield      #53                 // Field d:Z
     193: ixor
     194: putfield      #196                // Field android/support/v7/widget/LinearLayoutManager$a.d:Z
     197: aload_0
     198: aload_1
     199: aload_2
     200: aload_0
     201: getfield      #65                 // Field o:Landroid/support/v7/widget/LinearLayoutManager$a;
     204: invokespecial #468                // Method a:(Landroid/support/v7/widget/RecyclerView$p;Landroid/support/v7/widget/RecyclerView$u;Landroid/support/v7/widget/LinearLayoutManager$a;)V
     207: aload_0
     208: getfield      #65                 // Field o:Landroid/support/v7/widget/LinearLayoutManager$a;
     211: iconst_1
     212: putfield      #466                // Field android/support/v7/widget/LinearLayoutManager$a.e:Z
     215: aload_0
     216: aload_2
     217: invokevirtual #141                // Method b:(Landroid/support/v7/widget/RecyclerView$u;)I
     220: istore        4
     222: aload_0
     223: getfield      #121                // Field a:Landroid/support/v7/widget/LinearLayoutManager$c;
     226: getfield      #461                // Field android/support/v7/widget/LinearLayoutManager$c.j:I
     229: iflt          241
     232: iload         4
     234: istore_3
     235: iconst_0
     236: istore        4
     238: goto          243
     241: iconst_0
     242: istore_3
     243: iload         4
     245: aload_0
     246: getfield      #105                // Field j:Landroid/support/v7/widget/ba;
     249: invokevirtual #155                // Method android/support/v7/widget/ba.c:()I
     252: iadd
     253: istore        6
     255: iload_3
     256: aload_0
     257: getfield      #105                // Field j:Landroid/support/v7/widget/ba;
     260: invokevirtual #144                // Method android/support/v7/widget/ba.g:()I
     263: iadd
     264: istore        7
     266: iload         6
     268: istore_3
     269: iload         7
     271: istore        4
     273: aload_2
     274: invokevirtual #193                // Method android/support/v7/widget/RecyclerView$u.a:()Z
     277: ifeq          424
     280: iload         6
     282: istore_3
     283: iload         7
     285: istore        4
     287: aload_0
     288: getfield      #57                 // Field l:I
     291: iconst_m1
     292: if_icmpeq     424
     295: iload         6
     297: istore_3
     298: iload         7
     300: istore        4
     302: aload_0
     303: getfield      #60                 // Field m:I
     306: ldc           #58                 // int -2147483648
     308: if_icmpeq     424
     311: aload_0
     312: aload_0
     313: getfield      #57                 // Field l:I
     316: invokevirtual #199                // Method c:(I)Landroid/view/View;
     319: astore        8
     321: iload         6
     323: istore_3
     324: iload         7
     326: istore        4
     328: aload         8
     330: ifnull        424
     333: aload_0
     334: getfield      #51                 // Field k:Z
     337: ifeq          372
     340: aload_0
     341: getfield      #105                // Field j:Landroid/support/v7/widget/ba;
     344: invokevirtual #109                // Method android/support/v7/widget/ba.d:()I
     347: aload_0
     348: getfield      #105                // Field j:Landroid/support/v7/widget/ba;
     351: aload         8
     353: invokevirtual #151                // Method android/support/v7/widget/ba.b:(Landroid/view/View;)I
     356: isub
     357: istore        4
     359: aload_0
     360: getfield      #60                 // Field m:I
     363: istore_3
     364: iload         4
     366: iload_3
     367: isub
     368: istore_3
     369: goto          399
     372: aload_0
     373: getfield      #105                // Field j:Landroid/support/v7/widget/ba;
     376: aload         8
     378: invokevirtual #157                // Method android/support/v7/widget/ba.a:(Landroid/view/View;)I
     381: aload_0
     382: getfield      #105                // Field j:Landroid/support/v7/widget/ba;
     385: invokevirtual #155                // Method android/support/v7/widget/ba.c:()I
     388: isub
     389: istore_3
     390: aload_0
     391: getfield      #60                 // Field m:I
     394: istore        4
     396: goto          364
     399: iload_3
     400: ifle          415
     403: iload         6
     405: iload_3
     406: iadd
     407: istore_3
     408: iload         7
     410: istore        4
     412: goto          424
     415: iload         7
     417: iload_3
     418: isub
     419: istore        4
     421: iload         6
     423: istore_3
     424: aload_0
     425: getfield      #65                 // Field o:Landroid/support/v7/widget/LinearLayoutManager$a;
     428: getfield      #196                // Field android/support/v7/widget/LinearLayoutManager$a.d:Z
     431: ifeq          447
     434: aload_0
     435: getfield      #51                 // Field k:Z
     438: ifeq          454
     441: iconst_1
     442: istore        5
     444: goto          454
     447: aload_0
     448: getfield      #51                 // Field k:Z
     451: ifeq          441
     454: aload_0
     455: aload_1
     456: aload_2
     457: aload_0
     458: getfield      #65                 // Field o:Landroid/support/v7/widget/LinearLayoutManager$a;
     461: iload         5
     463: invokevirtual #470                // Method a:(Landroid/support/v7/widget/RecyclerView$p;Landroid/support/v7/widget/RecyclerView$u;Landroid/support/v7/widget/LinearLayoutManager$a;I)V
     466: aload_0
     467: aload_1
     468: invokevirtual #472                // Method a:(Landroid/support/v7/widget/RecyclerView$p;)V
     471: aload_0
     472: getfield      #121                // Field a:Landroid/support/v7/widget/LinearLayoutManager$c;
     475: aload_0
     476: invokevirtual #136                // Method k:()Z
     479: putfield      #138                // Field android/support/v7/widget/LinearLayoutManager$c.l:Z
     482: aload_0
     483: getfield      #121                // Field a:Landroid/support/v7/widget/LinearLayoutManager$c;
     486: aload_2
     487: invokevirtual #193                // Method android/support/v7/widget/RecyclerView$u.a:()Z
     490: putfield      #474                // Field android/support/v7/widget/LinearLayoutManager$c.i:Z
     493: aload_0
     494: getfield      #65                 // Field o:Landroid/support/v7/widget/LinearLayoutManager$a;
     497: getfield      #196                // Field android/support/v7/widget/LinearLayoutManager$a.d:Z
     500: ifeq          702
     503: aload_0
     504: aload_0
     505: getfield      #65                 // Field o:Landroid/support/v7/widget/LinearLayoutManager$a;
     508: invokespecial #476                // Method b:(Landroid/support/v7/widget/LinearLayoutManager$a;)V
     511: aload_0
     512: getfield      #121                // Field a:Landroid/support/v7/widget/LinearLayoutManager$c;
     515: iload_3
     516: putfield      #142                // Field android/support/v7/widget/LinearLayoutManager$c.h:I
     519: aload_0
     520: aload_1
     521: aload_0
     522: getfield      #121                // Field a:Landroid/support/v7/widget/LinearLayoutManager$c;
     525: aload_2
     526: iconst_0
     527: invokevirtual #244                // Method a:(Landroid/support/v7/widget/RecyclerView$p;Landroid/support/v7/widget/LinearLayoutManager$c;Landroid/support/v7/widget/RecyclerView$u;Z)I
     530: pop
     531: aload_0
     532: getfield      #121                // Field a:Landroid/support/v7/widget/LinearLayoutManager$c;
     535: getfield      #131                // Field android/support/v7/widget/LinearLayoutManager$c.b:I
     538: istore        5
     540: aload_0
     541: getfield      #121                // Field a:Landroid/support/v7/widget/LinearLayoutManager$c;
     544: getfield      #127                // Field android/support/v7/widget/LinearLayoutManager$c.d:I
     547: istore        7
     549: iload         4
     551: istore_3
     552: aload_0
     553: getfield      #121                // Field a:Landroid/support/v7/widget/LinearLayoutManager$c;
     556: getfield      #123                // Field android/support/v7/widget/LinearLayoutManager$c.c:I
     559: ifle          573
     562: iload         4
     564: aload_0
     565: getfield      #121                // Field a:Landroid/support/v7/widget/LinearLayoutManager$c;
     568: getfield      #123                // Field android/support/v7/widget/LinearLayoutManager$c.c:I
     571: iadd
     572: istore_3
     573: aload_0
     574: aload_0
     575: getfield      #65                 // Field o:Landroid/support/v7/widget/LinearLayoutManager$a;
     578: invokespecial #478                // Method a:(Landroid/support/v7/widget/LinearLayoutManager$a;)V
     581: aload_0
     582: getfield      #121                // Field a:Landroid/support/v7/widget/LinearLayoutManager$c;
     585: iload_3
     586: putfield      #142                // Field android/support/v7/widget/LinearLayoutManager$c.h:I
     589: aload_0
     590: getfield      #121                // Field a:Landroid/support/v7/widget/LinearLayoutManager$c;
     593: astore        8
     595: aload         8
     597: aload         8
     599: getfield      #127                // Field android/support/v7/widget/LinearLayoutManager$c.d:I
     602: aload_0
     603: getfield      #121                // Field a:Landroid/support/v7/widget/LinearLayoutManager$c;
     606: getfield      #125                // Field android/support/v7/widget/LinearLayoutManager$c.e:I
     609: iadd
     610: putfield      #127                // Field android/support/v7/widget/LinearLayoutManager$c.d:I
     613: aload_0
     614: aload_1
     615: aload_0
     616: getfield      #121                // Field a:Landroid/support/v7/widget/LinearLayoutManager$c;
     619: aload_2
     620: iconst_0
     621: invokevirtual #244                // Method a:(Landroid/support/v7/widget/RecyclerView$p;Landroid/support/v7/widget/LinearLayoutManager$c;Landroid/support/v7/widget/RecyclerView$u;Z)I
     624: pop
     625: aload_0
     626: getfield      #121                // Field a:Landroid/support/v7/widget/LinearLayoutManager$c;
     629: getfield      #131                // Field android/support/v7/widget/LinearLayoutManager$c.b:I
     632: istore        6
     634: iload         5
     636: istore        4
     638: iload         6
     640: istore_3
     641: aload_0
     642: getfield      #121                // Field a:Landroid/support/v7/widget/LinearLayoutManager$c;
     645: getfield      #123                // Field android/support/v7/widget/LinearLayoutManager$c.c:I
     648: ifle          900
     651: aload_0
     652: getfield      #121                // Field a:Landroid/support/v7/widget/LinearLayoutManager$c;
     655: getfield      #123                // Field android/support/v7/widget/LinearLayoutManager$c.c:I
     658: istore_3
     659: aload_0
     660: iload         7
     662: iload         5
     664: invokespecial #207                // Method g:(II)V
     667: aload_0
     668: getfield      #121                // Field a:Landroid/support/v7/widget/LinearLayoutManager$c;
     671: iload_3
     672: putfield      #142                // Field android/support/v7/widget/LinearLayoutManager$c.h:I
     675: aload_0
     676: aload_1
     677: aload_0
     678: getfield      #121                // Field a:Landroid/support/v7/widget/LinearLayoutManager$c;
     681: aload_2
     682: iconst_0
     683: invokevirtual #244                // Method a:(Landroid/support/v7/widget/RecyclerView$p;Landroid/support/v7/widget/LinearLayoutManager$c;Landroid/support/v7/widget/RecyclerView$u;Z)I
     686: pop
     687: aload_0
     688: getfield      #121                // Field a:Landroid/support/v7/widget/LinearLayoutManager$c;
     691: getfield      #131                // Field android/support/v7/widget/LinearLayoutManager$c.b:I
     694: istore        4
     696: iload         6
     698: istore_3
     699: goto          900
     702: aload_0
     703: aload_0
     704: getfield      #65                 // Field o:Landroid/support/v7/widget/LinearLayoutManager$a;
     707: invokespecial #478                // Method a:(Landroid/support/v7/widget/LinearLayoutManager$a;)V
     710: aload_0
     711: getfield      #121                // Field a:Landroid/support/v7/widget/LinearLayoutManager$c;
     714: iload         4
     716: putfield      #142                // Field android/support/v7/widget/LinearLayoutManager$c.h:I
     719: aload_0
     720: aload_1
     721: aload_0
     722: getfield      #121                // Field a:Landroid/support/v7/widget/LinearLayoutManager$c;
     725: aload_2
     726: iconst_0
     727: invokevirtual #244                // Method a:(Landroid/support/v7/widget/RecyclerView$p;Landroid/support/v7/widget/LinearLayoutManager$c;Landroid/support/v7/widget/RecyclerView$u;Z)I
     730: pop
     731: aload_0
     732: getfield      #121                // Field a:Landroid/support/v7/widget/LinearLayoutManager$c;
     735: getfield      #131                // Field android/support/v7/widget/LinearLayoutManager$c.b:I
     738: istore        5
     740: aload_0
     741: getfield      #121                // Field a:Landroid/support/v7/widget/LinearLayoutManager$c;
     744: getfield      #127                // Field android/support/v7/widget/LinearLayoutManager$c.d:I
     747: istore        7
     749: iload_3
     750: istore        4
     752: aload_0
     753: getfield      #121                // Field a:Landroid/support/v7/widget/LinearLayoutManager$c;
     756: getfield      #123                // Field android/support/v7/widget/LinearLayoutManager$c.c:I
     759: ifle          773
     762: iload_3
     763: aload_0
     764: getfield      #121                // Field a:Landroid/support/v7/widget/LinearLayoutManager$c;
     767: getfield      #123                // Field android/support/v7/widget/LinearLayoutManager$c.c:I
     770: iadd
     771: istore        4
     773: aload_0
     774: aload_0
     775: getfield      #65                 // Field o:Landroid/support/v7/widget/LinearLayoutManager$a;
     778: invokespecial #476                // Method b:(Landroid/support/v7/widget/LinearLayoutManager$a;)V
     781: aload_0
     782: getfield      #121                // Field a:Landroid/support/v7/widget/LinearLayoutManager$c;
     785: iload         4
     787: putfield      #142                // Field android/support/v7/widget/LinearLayoutManager$c.h:I
     790: aload_0
     791: getfield      #121                // Field a:Landroid/support/v7/widget/LinearLayoutManager$c;
     794: astore        8
     796: aload         8
     798: aload         8
     800: getfield      #127                // Field android/support/v7/widget/LinearLayoutManager$c.d:I
     803: aload_0
     804: getfield      #121                // Field a:Landroid/support/v7/widget/LinearLayoutManager$c;
     807: getfield      #125                // Field android/support/v7/widget/LinearLayoutManager$c.e:I
     810: iadd
     811: putfield      #127                // Field android/support/v7/widget/LinearLayoutManager$c.d:I
     814: aload_0
     815: aload_1
     816: aload_0
     817: getfield      #121                // Field a:Landroid/support/v7/widget/LinearLayoutManager$c;
     820: aload_2
     821: iconst_0
     822: invokevirtual #244                // Method a:(Landroid/support/v7/widget/RecyclerView$p;Landroid/support/v7/widget/LinearLayoutManager$c;Landroid/support/v7/widget/RecyclerView$u;Z)I
     825: pop
     826: aload_0
     827: getfield      #121                // Field a:Landroid/support/v7/widget/LinearLayoutManager$c;
     830: getfield      #131                // Field android/support/v7/widget/LinearLayoutManager$c.b:I
     833: istore        6
     835: iload         6
     837: istore        4
     839: iload         5
     841: istore_3
     842: aload_0
     843: getfield      #121                // Field a:Landroid/support/v7/widget/LinearLayoutManager$c;
     846: getfield      #123                // Field android/support/v7/widget/LinearLayoutManager$c.c:I
     849: ifle          900
     852: aload_0
     853: getfield      #121                // Field a:Landroid/support/v7/widget/LinearLayoutManager$c;
     856: getfield      #123                // Field android/support/v7/widget/LinearLayoutManager$c.c:I
     859: istore_3
     860: aload_0
     861: iload         7
     863: iload         5
     865: invokespecial #162                // Method a:(II)V
     868: aload_0
     869: getfield      #121                // Field a:Landroid/support/v7/widget/LinearLayoutManager$c;
     872: iload_3
     873: putfield      #142                // Field android/support/v7/widget/LinearLayoutManager$c.h:I
     876: aload_0
     877: aload_1
     878: aload_0
     879: getfield      #121                // Field a:Landroid/support/v7/widget/LinearLayoutManager$c;
     882: aload_2
     883: iconst_0
     884: invokevirtual #244                // Method a:(Landroid/support/v7/widget/RecyclerView$p;Landroid/support/v7/widget/LinearLayoutManager$c;Landroid/support/v7/widget/RecyclerView$u;Z)I
     887: pop
     888: aload_0
     889: getfield      #121                // Field a:Landroid/support/v7/widget/LinearLayoutManager$c;
     892: getfield      #131                // Field android/support/v7/widget/LinearLayoutManager$c.b:I
     895: istore_3
     896: iload         6
     898: istore        4
     900: iload         4
     902: istore        5
     904: iload_3
     905: istore        6
     907: aload_0
     908: invokevirtual #98                 // Method v:()I
     911: ifle          1011
     914: aload_0
     915: getfield      #51                 // Field k:Z
     918: aload_0
     919: getfield      #53                 // Field d:Z
     922: ixor
     923: ifeq          974
     926: aload_0
     927: iload_3
     928: aload_1
     929: aload_2
     930: iconst_1
     931: invokespecial #480                // Method a:(ILandroid/support/v7/widget/RecyclerView$p;Landroid/support/v7/widget/RecyclerView$u;Z)I
     934: istore        6
     936: iload         4
     938: iload         6
     940: iadd
     941: istore        5
     943: iload_3
     944: iload         6
     946: iadd
     947: istore        4
     949: aload_0
     950: iload         5
     952: aload_1
     953: aload_2
     954: iconst_0
     955: invokespecial #482                // Method b:(ILandroid/support/v7/widget/RecyclerView$p;Landroid/support/v7/widget/RecyclerView$u;Z)I
     958: istore_3
     959: iload         5
     961: iload_3
     962: iadd
     963: istore        5
     965: iload         4
     967: iload_3
     968: iadd
     969: istore        6
     971: goto          1011
     974: aload_0
     975: iload         4
     977: aload_1
     978: aload_2
     979: iconst_1
     980: invokespecial #482                // Method b:(ILandroid/support/v7/widget/RecyclerView$p;Landroid/support/v7/widget/RecyclerView$u;Z)I
     983: istore        6
     985: iload         4
     987: iload         6
     989: iadd
     990: istore        5
     992: iload_3
     993: iload         6
     995: iadd
     996: istore        4
     998: aload_0
     999: iload         4
    1001: aload_1
    1002: aload_2
    1003: iconst_0
    1004: invokespecial #480                // Method a:(ILandroid/support/v7/widget/RecyclerView$p;Landroid/support/v7/widget/RecyclerView$u;Z)I
    1007: istore_3
    1008: goto          959
    1011: aload_0
    1012: aload_1
    1013: aload_2
    1014: iload         5
    1016: iload         6
    1018: invokespecial #484                // Method b:(Landroid/support/v7/widget/RecyclerView$p;Landroid/support/v7/widget/RecyclerView$u;II)V
    1021: aload_2
    1022: invokevirtual #193                // Method android/support/v7/widget/RecyclerView$u.a:()Z
    1025: ifne          1038
    1028: aload_0
    1029: getfield      #105                // Field j:Landroid/support/v7/widget/ba;
    1032: invokevirtual #485                // Method android/support/v7/widget/ba.a:()V
    1035: goto          1045
    1038: aload_0
    1039: getfield      #65                 // Field o:Landroid/support/v7/widget/LinearLayoutManager$a;
    1042: invokevirtual #401                // Method android/support/v7/widget/LinearLayoutManager$a.a:()V
    1045: aload_0
    1046: aload_0
    1047: getfield      #53                 // Field d:Z
    1050: putfield      #255                // Field b:Z
    1053: return

  public boolean c();
    Code:
       0: iconst_1
       1: ireturn

  public int d(android.support.v7.widget.RecyclerView$u);
    Code:
       0: aload_0
       1: aload_1
       2: invokespecial #463                // Method i:(Landroid/support/v7/widget/RecyclerView$u;)I
       5: ireturn

  public android.os.Parcelable d();
    Code:
       0: aload_0
       1: getfield      #62                 // Field n:Landroid/support/v7/widget/LinearLayoutManager$d;
       4: ifnull        19
       7: new           #15                 // class android/support/v7/widget/LinearLayoutManager$d
      10: dup
      11: aload_0
      12: getfield      #62                 // Field n:Landroid/support/v7/widget/LinearLayoutManager$d;
      15: invokespecial #489                // Method android/support/v7/widget/LinearLayoutManager$d."<init>":(Landroid/support/v7/widget/LinearLayoutManager$d;)V
      18: areturn
      19: new           #15                 // class android/support/v7/widget/LinearLayoutManager$d
      22: dup
      23: invokespecial #490                // Method android/support/v7/widget/LinearLayoutManager$d."<init>":()V
      26: astore_2
      27: aload_0
      28: invokevirtual #98                 // Method v:()I
      31: ifle          129
      34: aload_0
      35: invokevirtual #271                // Method i:()V
      38: aload_0
      39: getfield      #255                // Field b:Z
      42: aload_0
      43: getfield      #51                 // Field k:Z
      46: ixor
      47: istore_1
      48: aload_2
      49: iload_1
      50: putfield      #195                // Field android/support/v7/widget/LinearLayoutManager$d.c:Z
      53: iload_1
      54: ifeq          93
      57: aload_0
      58: invokespecial #146                // Method M:()Landroid/view/View;
      61: astore_3
      62: aload_2
      63: aload_0
      64: getfield      #105                // Field j:Landroid/support/v7/widget/ba;
      67: invokevirtual #109                // Method android/support/v7/widget/ba.d:()I
      70: aload_0
      71: getfield      #105                // Field j:Landroid/support/v7/widget/ba;
      74: aload_3
      75: invokevirtual #151                // Method android/support/v7/widget/ba.b:(Landroid/view/View;)I
      78: isub
      79: putfield      #197                // Field android/support/v7/widget/LinearLayoutManager$d.b:I
      82: aload_2
      83: aload_0
      84: aload_3
      85: invokevirtual #149                // Method d:(Landroid/view/View;)I
      88: putfield      #357                // Field android/support/v7/widget/LinearLayoutManager$d.a:I
      91: aload_2
      92: areturn
      93: aload_0
      94: invokespecial #153                // Method L:()Landroid/view/View;
      97: astore_3
      98: aload_2
      99: aload_0
     100: aload_3
     101: invokevirtual #149                // Method d:(Landroid/view/View;)I
     104: putfield      #357                // Field android/support/v7/widget/LinearLayoutManager$d.a:I
     107: aload_2
     108: aload_0
     109: getfield      #105                // Field j:Landroid/support/v7/widget/ba;
     112: aload_3
     113: invokevirtual #157                // Method android/support/v7/widget/ba.a:(Landroid/view/View;)I
     116: aload_0
     117: getfield      #105                // Field j:Landroid/support/v7/widget/ba;
     120: invokevirtual #155                // Method android/support/v7/widget/ba.c:()I
     123: isub
     124: putfield      #197                // Field android/support/v7/widget/LinearLayoutManager$d.b:I
     127: aload_2
     128: areturn
     129: aload_2
     130: invokevirtual #491                // Method android/support/v7/widget/LinearLayoutManager$d.b:()V
     133: aload_2
     134: areturn

  public void d(int);
    Code:
       0: aload_0
       1: iload_1
       2: putfield      #57                 // Field l:I
       5: aload_0
       6: ldc           #58                 // int -2147483648
       8: putfield      #60                 // Field m:I
      11: aload_0
      12: getfield      #62                 // Field n:Landroid/support/v7/widget/LinearLayoutManager$d;
      15: ifnull        25
      18: aload_0
      19: getfield      #62                 // Field n:Landroid/support/v7/widget/LinearLayoutManager$d;
      22: invokevirtual #491                // Method android/support/v7/widget/LinearLayoutManager$d.b:()V
      25: aload_0
      26: invokevirtual #364                // Method o:()V
      29: return

  int e(int);
    Code:
       0: ldc           #58                 // int -2147483648
       2: istore_2
       3: iload_1
       4: bipush        17
       6: if_icmpeq     133
       9: iload_1
      10: bipush        33
      12: if_icmpeq     120
      15: iload_1
      16: bipush        66
      18: if_icmpeq     109
      21: iload_1
      22: sipush        130
      25: if_icmpeq     97
      28: iload_1
      29: tableswitch   { // 1 to 2
                     1: 76
                     2: 55
               default: 52
          }
      52: ldc           #58                 // int -2147483648
      54: ireturn
      55: aload_0
      56: getfield      #47                 // Field i:I
      59: iconst_1
      60: if_icmpne     65
      63: iconst_1
      64: ireturn
      65: aload_0
      66: invokevirtual #92                 // Method h:()Z
      69: ifeq          74
      72: iconst_m1
      73: ireturn
      74: iconst_1
      75: ireturn
      76: aload_0
      77: getfield      #47                 // Field i:I
      80: iconst_1
      81: if_icmpne     86
      84: iconst_m1
      85: ireturn
      86: aload_0
      87: invokevirtual #92                 // Method h:()Z
      90: ifeq          95
      93: iconst_1
      94: ireturn
      95: iconst_m1
      96: ireturn
      97: aload_0
      98: getfield      #47                 // Field i:I
     101: iconst_1
     102: if_icmpne     107
     105: iconst_1
     106: istore_2
     107: iload_2
     108: ireturn
     109: aload_0
     110: getfield      #47                 // Field i:I
     113: ifne          118
     116: iconst_1
     117: istore_2
     118: iload_2
     119: ireturn
     120: aload_0
     121: getfield      #47                 // Field i:I
     124: iconst_1
     125: if_icmpne     130
     128: iconst_m1
     129: ireturn
     130: ldc           #58                 // int -2147483648
     132: ireturn
     133: aload_0
     134: getfield      #47                 // Field i:I
     137: ifne          142
     140: iconst_m1
     141: ireturn
     142: ldc           #58                 // int -2147483648
     144: ireturn

  public int e(android.support.v7.widget.RecyclerView$u);
    Code:
       0: aload_0
       1: aload_1
       2: invokespecial #493                // Method j:(Landroid/support/v7/widget/RecyclerView$u;)I
       5: ireturn

  public boolean e();
    Code:
       0: aload_0
       1: getfield      #47                 // Field i:I
       4: ifne          9
       7: iconst_1
       8: ireturn
       9: iconst_0
      10: ireturn

  public int f(android.support.v7.widget.RecyclerView$u);
    Code:
       0: aload_0
       1: aload_1
       2: invokespecial #493                // Method j:(Landroid/support/v7/widget/RecyclerView$u;)I
       5: ireturn

  public boolean f();
    Code:
       0: aload_0
       1: getfield      #47                 // Field i:I
       4: iconst_1
       5: if_icmpne     10
       8: iconst_1
       9: ireturn
      10: iconst_0
      11: ireturn

  public int g();
    Code:
       0: aload_0
       1: getfield      #47                 // Field i:I
       4: ireturn

  public int g(android.support.v7.widget.RecyclerView$u);
    Code:
       0: aload_0
       1: aload_1
       2: invokespecial #495                // Method k:(Landroid/support/v7/widget/RecyclerView$u;)I
       5: ireturn

  public int h(android.support.v7.widget.RecyclerView$u);
    Code:
       0: aload_0
       1: aload_1
       2: invokespecial #495                // Method k:(Landroid/support/v7/widget/RecyclerView$u;)I
       5: ireturn

  protected boolean h();
    Code:
       0: aload_0
       1: invokevirtual #498                // Method t:()I
       4: iconst_1
       5: if_icmpne     10
       8: iconst_1
       9: ireturn
      10: iconst_0
      11: ireturn

  void i();
    Code:
       0: aload_0
       1: getfield      #121                // Field a:Landroid/support/v7/widget/LinearLayoutManager$c;
       4: ifnonnull     15
       7: aload_0
       8: aload_0
       9: invokevirtual #501                // Method j:()Landroid/support/v7/widget/LinearLayoutManager$c;
      12: putfield      #121                // Field a:Landroid/support/v7/widget/LinearLayoutManager$c;
      15: return

  android.support.v7.widget.LinearLayoutManager$c j();
    Code:
       0: new           #12                 // class android/support/v7/widget/LinearLayoutManager$c
       3: dup
       4: invokespecial #502                // Method android/support/v7/widget/LinearLayoutManager$c."<init>":()V
       7: areturn

  boolean k();
    Code:
       0: aload_0
       1: getfield      #105                // Field j:Landroid/support/v7/widget/ba;
       4: invokevirtual #504                // Method android/support/v7/widget/ba.h:()I
       7: ifne          22
      10: aload_0
      11: getfield      #105                // Field j:Landroid/support/v7/widget/ba;
      14: invokevirtual #208                // Method android/support/v7/widget/ba.e:()I
      17: ifne          22
      20: iconst_1
      21: ireturn
      22: iconst_0
      23: ireturn

  boolean l();
    Code:
       0: aload_0
       1: invokevirtual #507                // Method x:()I
       4: ldc_w         #508                // int 1073741824
       7: if_icmpeq     29
      10: aload_0
      11: invokevirtual #511                // Method w:()I
      14: ldc_w         #508                // int 1073741824
      17: if_icmpeq     29
      20: aload_0
      21: invokevirtual #514                // Method J:()Z
      24: ifeq          29
      27: iconst_1
      28: ireturn
      29: iconst_0
      30: ireturn

  public int m();
    Code:
       0: aload_0
       1: iconst_0
       2: aload_0
       3: invokevirtual #98                 // Method v:()I
       6: iconst_0
       7: iconst_1
       8: invokevirtual #118                // Method a:(IIZZ)Landroid/view/View;
      11: astore_1
      12: aload_1
      13: ifnonnull     18
      16: iconst_m1
      17: ireturn
      18: aload_0
      19: aload_1
      20: invokevirtual #149                // Method d:(Landroid/view/View;)I
      23: ireturn

  public int n();
    Code:
       0: aload_0
       1: aload_0
       2: invokevirtual #98                 // Method v:()I
       5: iconst_1
       6: isub
       7: iconst_m1
       8: iconst_0
       9: iconst_1
      10: invokevirtual #118                // Method a:(IIZZ)Landroid/view/View;
      13: astore_1
      14: aload_1
      15: ifnonnull     20
      18: iconst_m1
      19: ireturn
      20: aload_0
      21: aload_1
      22: invokevirtual #149                // Method d:(Landroid/view/View;)I
      25: ireturn
}
