public final class android.support.v7.widget.m {
  static {};
    Code:
       0: getstatic     #49                 // Field android/graphics/PorterDuff$Mode.SRC_IN:Landroid/graphics/PorterDuff$Mode;
       3: putstatic     #51                 // Field a:Landroid/graphics/PorterDuff$Mode;
       6: new           #9                  // class android/support/v7/widget/m$b
       9: dup
      10: bipush        6
      12: invokespecial #55                 // Method android/support/v7/widget/m$b."<init>":(I)V
      15: putstatic     #57                 // Field c:Landroid/support/v7/widget/m$b;
      18: iconst_3
      19: newarray       int
      21: dup
      22: iconst_0
      23: getstatic     #63                 // Field android/support/v7/a/a$e.abc_textfield_search_default_mtrl_alpha:I
      26: iastore
      27: dup
      28: iconst_1
      29: getstatic     #66                 // Field android/support/v7/a/a$e.abc_textfield_default_mtrl_alpha:I
      32: iastore
      33: dup
      34: iconst_2
      35: getstatic     #69                 // Field android/support/v7/a/a$e.abc_ab_share_pack_mtrl_alpha:I
      38: iastore
      39: putstatic     #71                 // Field d:[I
      42: bipush        7
      44: newarray       int
      46: dup
      47: iconst_0
      48: getstatic     #74                 // Field android/support/v7/a/a$e.abc_ic_commit_search_api_mtrl_alpha:I
      51: iastore
      52: dup
      53: iconst_1
      54: getstatic     #77                 // Field android/support/v7/a/a$e.abc_seekbar_tick_mark_material:I
      57: iastore
      58: dup
      59: iconst_2
      60: getstatic     #80                 // Field android/support/v7/a/a$e.abc_ic_menu_share_mtrl_alpha:I
      63: iastore
      64: dup
      65: iconst_3
      66: getstatic     #83                 // Field android/support/v7/a/a$e.abc_ic_menu_copy_mtrl_am_alpha:I
      69: iastore
      70: dup
      71: iconst_4
      72: getstatic     #86                 // Field android/support/v7/a/a$e.abc_ic_menu_cut_mtrl_alpha:I
      75: iastore
      76: dup
      77: iconst_5
      78: getstatic     #89                 // Field android/support/v7/a/a$e.abc_ic_menu_selectall_mtrl_alpha:I
      81: iastore
      82: dup
      83: bipush        6
      85: getstatic     #92                 // Field android/support/v7/a/a$e.abc_ic_menu_paste_mtrl_am_alpha:I
      88: iastore
      89: putstatic     #94                 // Field e:[I
      92: bipush        10
      94: newarray       int
      96: dup
      97: iconst_0
      98: getstatic     #97                 // Field android/support/v7/a/a$e.abc_textfield_activated_mtrl_alpha:I
     101: iastore
     102: dup
     103: iconst_1
     104: getstatic     #100                // Field android/support/v7/a/a$e.abc_textfield_search_activated_mtrl_alpha:I
     107: iastore
     108: dup
     109: iconst_2
     110: getstatic     #103                // Field android/support/v7/a/a$e.abc_cab_background_top_mtrl_alpha:I
     113: iastore
     114: dup
     115: iconst_3
     116: getstatic     #106                // Field android/support/v7/a/a$e.abc_text_cursor_material:I
     119: iastore
     120: dup
     121: iconst_4
     122: getstatic     #109                // Field android/support/v7/a/a$e.abc_text_select_handle_left_mtrl_dark:I
     125: iastore
     126: dup
     127: iconst_5
     128: getstatic     #112                // Field android/support/v7/a/a$e.abc_text_select_handle_middle_mtrl_dark:I
     131: iastore
     132: dup
     133: bipush        6
     135: getstatic     #115                // Field android/support/v7/a/a$e.abc_text_select_handle_right_mtrl_dark:I
     138: iastore
     139: dup
     140: bipush        7
     142: getstatic     #118                // Field android/support/v7/a/a$e.abc_text_select_handle_left_mtrl_light:I
     145: iastore
     146: dup
     147: bipush        8
     149: getstatic     #121                // Field android/support/v7/a/a$e.abc_text_select_handle_middle_mtrl_light:I
     152: iastore
     153: dup
     154: bipush        9
     156: getstatic     #124                // Field android/support/v7/a/a$e.abc_text_select_handle_right_mtrl_light:I
     159: iastore
     160: putstatic     #126                // Field f:[I
     163: iconst_3
     164: newarray       int
     166: dup
     167: iconst_0
     168: getstatic     #129                // Field android/support/v7/a/a$e.abc_popup_background_mtrl_mult:I
     171: iastore
     172: dup
     173: iconst_1
     174: getstatic     #132                // Field android/support/v7/a/a$e.abc_cab_background_internal_bg:I
     177: iastore
     178: dup
     179: iconst_2
     180: getstatic     #135                // Field android/support/v7/a/a$e.abc_menu_hardkey_panel_mtrl_mult:I
     183: iastore
     184: putstatic     #137                // Field g:[I
     187: iconst_2
     188: newarray       int
     190: dup
     191: iconst_0
     192: getstatic     #140                // Field android/support/v7/a/a$e.abc_tab_indicator_material:I
     195: iastore
     196: dup
     197: iconst_1
     198: getstatic     #143                // Field android/support/v7/a/a$e.abc_textfield_search_material:I
     201: iastore
     202: putstatic     #145                // Field h:[I
     205: iconst_2
     206: newarray       int
     208: dup
     209: iconst_0
     210: getstatic     #148                // Field android/support/v7/a/a$e.abc_btn_check_material:I
     213: iastore
     214: dup
     215: iconst_1
     216: getstatic     #151                // Field android/support/v7/a/a$e.abc_btn_radio_material:I
     219: iastore
     220: putstatic     #153                // Field i:[I
     223: return

  public android.support.v7.widget.m();
    Code:
       0: aload_0
       1: invokespecial #156                // Method java/lang/Object."<init>":()V
       4: aload_0
       5: new           #4                  // class java/lang/Object
       8: dup
       9: invokespecial #156                // Method java/lang/Object."<init>":()V
      12: putfield      #158                // Field m:Ljava/lang/Object;
      15: aload_0
      16: new           #160                // class java/util/WeakHashMap
      19: dup
      20: iconst_0
      21: invokespecial #161                // Method java/util/WeakHashMap."<init>":(I)V
      24: putfield      #163                // Field n:Ljava/util/WeakHashMap;
      27: return

  static android.graphics.PorterDuff$Mode a(int);
    Code:
       0: iload_0
       1: getstatic     #176                // Field android/support/v7/a/a$e.abc_switch_thumb_material:I
       4: if_icmpne     11
       7: getstatic     #179                // Field android/graphics/PorterDuff$Mode.MULTIPLY:Landroid/graphics/PorterDuff$Mode;
      10: areturn
      11: aconst_null
      12: areturn

  public static android.graphics.PorterDuffColorFilter a(int, android.graphics.PorterDuff$Mode);
    Code:
       0: getstatic     #57                 // Field c:Landroid/support/v7/widget/m$b;
       3: iload_0
       4: aload_1
       5: invokevirtual #182                // Method android/support/v7/widget/m$b.a:(ILandroid/graphics/PorterDuff$Mode;)Landroid/graphics/PorterDuffColorFilter;
       8: astore_3
       9: aload_3
      10: astore_2
      11: aload_3
      12: ifnonnull     35
      15: new           #184                // class android/graphics/PorterDuffColorFilter
      18: dup
      19: iload_0
      20: aload_1
      21: invokespecial #187                // Method android/graphics/PorterDuffColorFilter."<init>":(ILandroid/graphics/PorterDuff$Mode;)V
      24: astore_2
      25: getstatic     #57                 // Field c:Landroid/support/v7/widget/m$b;
      28: iload_0
      29: aload_1
      30: aload_2
      31: invokevirtual #190                // Method android/support/v7/widget/m$b.a:(ILandroid/graphics/PorterDuff$Mode;Landroid/graphics/PorterDuffColorFilter;)Landroid/graphics/PorterDuffColorFilter;
      34: pop
      35: aload_2
      36: areturn

  public static android.support.v7.widget.m a();
    Code:
       0: getstatic     #301                // Field b:Landroid/support/v7/widget/m;
       3: ifnonnull     22
       6: new           #2                  // class android/support/v7/widget/m
       9: dup
      10: invokespecial #302                // Method "<init>":()V
      13: putstatic     #301                // Field b:Landroid/support/v7/widget/m;
      16: getstatic     #301                // Field b:Landroid/support/v7/widget/m;
      19: invokestatic  #305                // Method a:(Landroid/support/v7/widget/m;)V
      22: getstatic     #301                // Field b:Landroid/support/v7/widget/m;
      25: areturn

  static void a(android.graphics.drawable.Drawable, android.support.v7.widget.bn, int[]);
    Code:
       0: aload_0
       1: invokestatic  #207                // Method android/support/v7/widget/ao.c:(Landroid/graphics/drawable/Drawable;)Z
       4: ifeq          26
       7: aload_0
       8: invokevirtual #213                // Method android/graphics/drawable/Drawable.mutate:()Landroid/graphics/drawable/Drawable;
      11: aload_0
      12: if_acmpeq     26
      15: ldc_w         #326                // String AppCompatDrawableManag
      18: ldc_w         #328                // String Mutated drawable is not the same instance as the input.
      21: invokestatic  #333                // Method android/util/Log.d:(Ljava/lang/String;Ljava/lang/String;)I
      24: pop
      25: return
      26: aload_1
      27: getfield      #337                // Field android/support/v7/widget/bn.d:Z
      30: ifne          50
      33: aload_1
      34: getfield      #339                // Field android/support/v7/widget/bn.c:Z
      37: ifeq          43
      40: goto          50
      43: aload_0
      44: invokevirtual #342                // Method android/graphics/drawable/Drawable.clearColorFilter:()V
      47: goto          96
      50: aload_1
      51: getfield      #337                // Field android/support/v7/widget/bn.d:Z
      54: ifeq          65
      57: aload_1
      58: getfield      #345                // Field android/support/v7/widget/bn.a:Landroid/content/res/ColorStateList;
      61: astore_3
      62: goto          67
      65: aconst_null
      66: astore_3
      67: aload_1
      68: getfield      #339                // Field android/support/v7/widget/bn.c:Z
      71: ifeq          82
      74: aload_1
      75: getfield      #347                // Field android/support/v7/widget/bn.b:Landroid/graphics/PorterDuff$Mode;
      78: astore_1
      79: goto          86
      82: getstatic     #51                 // Field a:Landroid/graphics/PorterDuff$Mode;
      85: astore_1
      86: aload_0
      87: aload_3
      88: aload_1
      89: aload_2
      90: invokestatic  #349                // Method a:(Landroid/content/res/ColorStateList;Landroid/graphics/PorterDuff$Mode;[I)Landroid/graphics/PorterDuffColorFilter;
      93: invokevirtual #323                // Method android/graphics/drawable/Drawable.setColorFilter:(Landroid/graphics/ColorFilter;)V
      96: getstatic     #354                // Field android/os/Build$VERSION.SDK_INT:I
      99: bipush        23
     101: if_icmpgt     108
     104: aload_0
     105: invokevirtual #357                // Method android/graphics/drawable/Drawable.invalidateSelf:()V
     108: return

  static boolean a(android.content.Context, int, android.graphics.drawable.Drawable);
    Code:
       0: getstatic     #51                 // Field a:Landroid/graphics/PorterDuff$Mode;
       3: astore        6
       5: getstatic     #71                 // Field d:[I
       8: iload_1
       9: invokestatic  #375                // Method a:([II)Z
      12: istore        5
      14: ldc_w         #376                // int 16842801
      17: istore_3
      18: iload         5
      20: ifeq          35
      23: getstatic     #241                // Field android/support/v7/a/a$a.colorControlNormal:I
      26: istore_1
      27: iconst_1
      28: istore        4
      30: iconst_m1
      31: istore_3
      32: goto          115
      35: getstatic     #126                // Field f:[I
      38: iload_1
      39: invokestatic  #375                // Method a:([II)Z
      42: ifeq          52
      45: getstatic     #254                // Field android/support/v7/a/a$a.colorControlActivated:I
      48: istore_1
      49: goto          27
      52: getstatic     #137                // Field g:[I
      55: iload_1
      56: invokestatic  #375                // Method a:([II)Z
      59: ifeq          72
      62: getstatic     #179                // Field android/graphics/PorterDuff$Mode.MULTIPLY:Landroid/graphics/PorterDuff$Mode;
      65: astore        6
      67: iload_3
      68: istore_1
      69: goto          27
      72: iload_1
      73: getstatic     #379                // Field android/support/v7/a/a$e.abc_list_divider_mtrl_alpha:I
      76: if_icmpne     96
      79: ldc_w         #380                // int 16842800
      82: istore_1
      83: ldc_w         #381                // float 40.8f
      86: invokestatic  #387                // Method java/lang/Math.round:(F)I
      89: istore_3
      90: iconst_1
      91: istore        4
      93: goto          115
      96: iload_1
      97: getstatic     #390                // Field android/support/v7/a/a$e.abc_dialog_material_background:I
     100: if_icmpne     108
     103: iload_3
     104: istore_1
     105: goto          27
     108: iconst_0
     109: istore        4
     111: iconst_m1
     112: istore_3
     113: iconst_0
     114: istore_1
     115: iload         4
     117: ifeq          164
     120: aload_2
     121: astore        7
     123: aload_2
     124: invokestatic  #207                // Method android/support/v7/widget/ao.c:(Landroid/graphics/drawable/Drawable;)Z
     127: ifeq          136
     130: aload_2
     131: invokevirtual #213                // Method android/graphics/drawable/Drawable.mutate:()Landroid/graphics/drawable/Drawable;
     134: astore        7
     136: aload         7
     138: aload_0
     139: iload_1
     140: invokestatic  #246                // Method android/support/v7/widget/bk.a:(Landroid/content/Context;I)I
     143: aload         6
     145: invokestatic  #198                // Method a:(ILandroid/graphics/PorterDuff$Mode;)Landroid/graphics/PorterDuffColorFilter;
     148: invokevirtual #323                // Method android/graphics/drawable/Drawable.setColorFilter:(Landroid/graphics/ColorFilter;)V
     151: iload_3
     152: iconst_m1
     153: if_icmpeq     162
     156: aload         7
     158: iload_3
     159: invokevirtual #393                // Method android/graphics/drawable/Drawable.setAlpha:(I)V
     162: iconst_1
     163: ireturn
     164: iconst_0
     165: ireturn

  public android.graphics.drawable.Drawable a(android.content.Context, int);
    Code:
       0: aload_0
       1: aload_1
       2: iload_2
       3: iconst_0
       4: invokevirtual #574                // Method a:(Landroid/content/Context;IZ)Landroid/graphics/drawable/Drawable;
       7: areturn

  android.graphics.drawable.Drawable a(android.content.Context, int, boolean);
    Code:
       0: aload_0
       1: aload_1
       2: invokespecial #576                // Method f:(Landroid/content/Context;)V
       5: aload_0
       6: aload_1
       7: iload_2
       8: invokespecial #578                // Method d:(Landroid/content/Context;I)Landroid/graphics/drawable/Drawable;
      11: astore        5
      13: aload         5
      15: astore        4
      17: aload         5
      19: ifnonnull     30
      22: aload_0
      23: aload_1
      24: iload_2
      25: invokespecial #580                // Method c:(Landroid/content/Context;I)Landroid/graphics/drawable/Drawable;
      28: astore        4
      30: aload         4
      32: astore        5
      34: aload         4
      36: ifnonnull     46
      39: aload_1
      40: iload_2
      41: invokestatic  #583                // Method android/support/v4/a/a.a:(Landroid/content/Context;I)Landroid/graphics/drawable/Drawable;
      44: astore        5
      46: aload         5
      48: astore        4
      50: aload         5
      52: ifnull        66
      55: aload_0
      56: aload_1
      57: iload_2
      58: iload_3
      59: aload         5
      61: invokespecial #585                // Method a:(Landroid/content/Context;IZLandroid/graphics/drawable/Drawable;)Landroid/graphics/drawable/Drawable;
      64: astore        4
      66: aload         4
      68: ifnull        76
      71: aload         4
      73: invokestatic  #588                // Method android/support/v7/widget/ao.b:(Landroid/graphics/drawable/Drawable;)V
      76: aload         4
      78: areturn

  android.graphics.drawable.Drawable a(android.content.Context, android.support.v7.widget.bu, int);
    Code:
       0: aload_0
       1: aload_1
       2: iload_3
       3: invokespecial #578                // Method d:(Landroid/content/Context;I)Landroid/graphics/drawable/Drawable;
       6: astore        5
       8: aload         5
      10: astore        4
      12: aload         5
      14: ifnonnull     24
      17: aload_2
      18: iload_3
      19: invokevirtual #593                // Method android/support/v7/widget/bu.a:(I)Landroid/graphics/drawable/Drawable;
      22: astore        4
      24: aload         4
      26: ifnull        39
      29: aload_0
      30: aload_1
      31: iload_3
      32: iconst_0
      33: aload         4
      35: invokespecial #585                // Method a:(Landroid/content/Context;IZLandroid/graphics/drawable/Drawable;)Landroid/graphics/drawable/Drawable;
      38: areturn
      39: aconst_null
      40: areturn

  public void a(android.content.Context);
    Code:
       0: aload_0
       1: getfield      #158                // Field m:Ljava/lang/Object;
       4: astore_2
       5: aload_2
       6: monitorenter
       7: aload_0
       8: getfield      #163                // Field n:Ljava/util/WeakHashMap;
      11: aload_1
      12: invokevirtual #273                // Method java/util/WeakHashMap.get:(Ljava/lang/Object;)Ljava/lang/Object;
      15: checkcast     #275                // class android/support/v4/g/f
      18: astore_1
      19: aload_1
      20: ifnull        27
      23: aload_1
      24: invokevirtual #595                // Method android/support/v4/g/f.c:()V
      27: aload_2
      28: monitorexit
      29: return
      30: astore_1
      31: aload_2
      32: monitorexit
      33: aload_1
      34: athrow
    Exception table:
       from    to  target type
           7    19    30   any
          23    27    30   any
          27    29    30   any
          31    33    30   any

  android.content.res.ColorStateList b(android.content.Context, int);
    Code:
       0: aload_0
       1: aload_1
       2: iload_2
       3: invokespecial #597                // Method e:(Landroid/content/Context;I)Landroid/content/res/ColorStateList;
       6: astore        4
       8: aload         4
      10: astore        5
      12: aload         4
      14: ifnonnull     235
      17: iload_2
      18: getstatic     #600                // Field android/support/v7/a/a$e.abc_edit_text_material:I
      21: if_icmpne     38
      24: getstatic     #605                // Field android/support/v7/a/a$c.abc_tint_edittext:I
      27: istore_3
      28: aload_1
      29: iload_3
      30: invokestatic  #609                // Method android/support/v7/c/a/b.a:(Landroid/content/Context;I)Landroid/content/res/ColorStateList;
      33: astore        4
      35: goto          214
      38: iload_2
      39: getstatic     #612                // Field android/support/v7/a/a$e.abc_switch_track_mtrl_alpha:I
      42: if_icmpne     52
      45: getstatic     #615                // Field android/support/v7/a/a$c.abc_tint_switch_track:I
      48: istore_3
      49: goto          28
      52: iload_2
      53: getstatic     #176                // Field android/support/v7/a/a$e.abc_switch_thumb_material:I
      56: if_icmpne     69
      59: aload_0
      60: aload_1
      61: invokespecial #617                // Method e:(Landroid/content/Context;)Landroid/content/res/ColorStateList;
      64: astore        4
      66: goto          214
      69: iload_2
      70: getstatic     #620                // Field android/support/v7/a/a$e.abc_btn_default_mtrl_shape:I
      73: if_icmpne     86
      76: aload_0
      77: aload_1
      78: invokespecial #622                // Method b:(Landroid/content/Context;)Landroid/content/res/ColorStateList;
      81: astore        4
      83: goto          214
      86: iload_2
      87: getstatic     #625                // Field android/support/v7/a/a$e.abc_btn_borderless_material:I
      90: if_icmpne     103
      93: aload_0
      94: aload_1
      95: invokespecial #627                // Method c:(Landroid/content/Context;)Landroid/content/res/ColorStateList;
      98: astore        4
     100: goto          214
     103: iload_2
     104: getstatic     #630                // Field android/support/v7/a/a$e.abc_btn_colored_material:I
     107: if_icmpne     120
     110: aload_0
     111: aload_1
     112: invokespecial #632                // Method d:(Landroid/content/Context;)Landroid/content/res/ColorStateList;
     115: astore        4
     117: goto          214
     120: iload_2
     121: getstatic     #635                // Field android/support/v7/a/a$e.abc_spinner_mtrl_am_alpha:I
     124: if_icmpeq     207
     127: iload_2
     128: getstatic     #638                // Field android/support/v7/a/a$e.abc_spinner_textfield_background_material:I
     131: if_icmpne     137
     134: goto          207
     137: getstatic     #94                 // Field e:[I
     140: iload_2
     141: invokestatic  #375                // Method a:([II)Z
     144: ifeq          159
     147: aload_1
     148: getstatic     #241                // Field android/support/v7/a/a$a.colorControlNormal:I
     151: invokestatic  #534                // Method android/support/v7/widget/bk.b:(Landroid/content/Context;I)Landroid/content/res/ColorStateList;
     154: astore        4
     156: goto          214
     159: getstatic     #145                // Field h:[I
     162: iload_2
     163: invokestatic  #375                // Method a:([II)Z
     166: ifeq          176
     169: getstatic     #641                // Field android/support/v7/a/a$c.abc_tint_default:I
     172: istore_3
     173: goto          28
     176: getstatic     #153                // Field i:[I
     179: iload_2
     180: invokestatic  #375                // Method a:([II)Z
     183: ifeq          193
     186: getstatic     #644                // Field android/support/v7/a/a$c.abc_tint_btn_checkable:I
     189: istore_3
     190: goto          28
     193: iload_2
     194: getstatic     #647                // Field android/support/v7/a/a$e.abc_seekbar_thumb_material:I
     197: if_icmpne     214
     200: getstatic     #650                // Field android/support/v7/a/a$c.abc_tint_seek_thumb:I
     203: istore_3
     204: goto          28
     207: getstatic     #653                // Field android/support/v7/a/a$c.abc_tint_spinner:I
     210: istore_3
     211: goto          28
     214: aload         4
     216: astore        5
     218: aload         4
     220: ifnull        235
     223: aload_0
     224: aload_1
     225: iload_2
     226: aload         4
     228: invokespecial #655                // Method a:(Landroid/content/Context;ILandroid/content/res/ColorStateList;)V
     231: aload         4
     233: astore        5
     235: aload         5
     237: areturn
}
