public class android.support.v7.widget.r extends android.widget.ImageView implements android.support.v4.view.r,android.support.v4.widget.o {
  public android.support.v7.widget.r(android.content.Context);
    Code:
       0: aload_0
       1: aload_1
       2: aconst_null
       3: invokespecial #17                 // Method "<init>":(Landroid/content/Context;Landroid/util/AttributeSet;)V
       6: return

  public android.support.v7.widget.r(android.content.Context, android.util.AttributeSet);
    Code:
       0: aload_0
       1: aload_1
       2: aload_2
       3: iconst_0
       4: invokespecial #21                 // Method "<init>":(Landroid/content/Context;Landroid/util/AttributeSet;I)V
       7: return

  public android.support.v7.widget.r(android.content.Context, android.util.AttributeSet, int);
    Code:
       0: aload_0
       1: aload_1
       2: invokestatic  #26                 // Method android/support/v7/widget/bm.a:(Landroid/content/Context;)Landroid/content/Context;
       5: aload_2
       6: iload_3
       7: invokespecial #27                 // Method android/widget/ImageView."<init>":(Landroid/content/Context;Landroid/util/AttributeSet;I)V
      10: aload_0
      11: new           #29                 // class android/support/v7/widget/h
      14: dup
      15: aload_0
      16: invokespecial #32                 // Method android/support/v7/widget/h."<init>":(Landroid/view/View;)V
      19: putfield      #34                 // Field a:Landroid/support/v7/widget/h;
      22: aload_0
      23: getfield      #34                 // Field a:Landroid/support/v7/widget/h;
      26: aload_2
      27: iload_3
      28: invokevirtual #37                 // Method android/support/v7/widget/h.a:(Landroid/util/AttributeSet;I)V
      31: aload_0
      32: new           #39                 // class android/support/v7/widget/q
      35: dup
      36: aload_0
      37: invokespecial #42                 // Method android/support/v7/widget/q."<init>":(Landroid/widget/ImageView;)V
      40: putfield      #44                 // Field b:Landroid/support/v7/widget/q;
      43: aload_0
      44: getfield      #44                 // Field b:Landroid/support/v7/widget/q;
      47: aload_2
      48: iload_3
      49: invokevirtual #45                 // Method android/support/v7/widget/q.a:(Landroid/util/AttributeSet;I)V
      52: return

  protected void drawableStateChanged();
    Code:
       0: aload_0
       1: invokespecial #49                 // Method android/widget/ImageView.drawableStateChanged:()V
       4: aload_0
       5: getfield      #34                 // Field a:Landroid/support/v7/widget/h;
       8: ifnull        18
      11: aload_0
      12: getfield      #34                 // Field a:Landroid/support/v7/widget/h;
      15: invokevirtual #52                 // Method android/support/v7/widget/h.c:()V
      18: aload_0
      19: getfield      #44                 // Field b:Landroid/support/v7/widget/q;
      22: ifnull        32
      25: aload_0
      26: getfield      #44                 // Field b:Landroid/support/v7/widget/q;
      29: invokevirtual #55                 // Method android/support/v7/widget/q.d:()V
      32: return

  public android.content.res.ColorStateList getSupportBackgroundTintList();
    Code:
       0: aload_0
       1: getfield      #34                 // Field a:Landroid/support/v7/widget/h;
       4: ifnull        15
       7: aload_0
       8: getfield      #34                 // Field a:Landroid/support/v7/widget/h;
      11: invokevirtual #59                 // Method android/support/v7/widget/h.a:()Landroid/content/res/ColorStateList;
      14: areturn
      15: aconst_null
      16: areturn

  public android.graphics.PorterDuff$Mode getSupportBackgroundTintMode();
    Code:
       0: aload_0
       1: getfield      #34                 // Field a:Landroid/support/v7/widget/h;
       4: ifnull        15
       7: aload_0
       8: getfield      #34                 // Field a:Landroid/support/v7/widget/h;
      11: invokevirtual #63                 // Method android/support/v7/widget/h.b:()Landroid/graphics/PorterDuff$Mode;
      14: areturn
      15: aconst_null
      16: areturn

  public android.content.res.ColorStateList getSupportImageTintList();
    Code:
       0: aload_0
       1: getfield      #44                 // Field b:Landroid/support/v7/widget/q;
       4: ifnull        15
       7: aload_0
       8: getfield      #44                 // Field b:Landroid/support/v7/widget/q;
      11: invokevirtual #66                 // Method android/support/v7/widget/q.b:()Landroid/content/res/ColorStateList;
      14: areturn
      15: aconst_null
      16: areturn

  public android.graphics.PorterDuff$Mode getSupportImageTintMode();
    Code:
       0: aload_0
       1: getfield      #44                 // Field b:Landroid/support/v7/widget/q;
       4: ifnull        15
       7: aload_0
       8: getfield      #44                 // Field b:Landroid/support/v7/widget/q;
      11: invokevirtual #69                 // Method android/support/v7/widget/q.c:()Landroid/graphics/PorterDuff$Mode;
      14: areturn
      15: aconst_null
      16: areturn

  public boolean hasOverlappingRendering();
    Code:
       0: aload_0
       1: getfield      #44                 // Field b:Landroid/support/v7/widget/q;
       4: invokevirtual #73                 // Method android/support/v7/widget/q.a:()Z
       7: ifeq          19
      10: aload_0
      11: invokespecial #75                 // Method android/widget/ImageView.hasOverlappingRendering:()Z
      14: ifeq          19
      17: iconst_1
      18: ireturn
      19: iconst_0
      20: ireturn

  public void setBackgroundDrawable(android.graphics.drawable.Drawable);
    Code:
       0: aload_0
       1: aload_1
       2: invokespecial #79                 // Method android/widget/ImageView.setBackgroundDrawable:(Landroid/graphics/drawable/Drawable;)V
       5: aload_0
       6: getfield      #34                 // Field a:Landroid/support/v7/widget/h;
       9: ifnull        20
      12: aload_0
      13: getfield      #34                 // Field a:Landroid/support/v7/widget/h;
      16: aload_1
      17: invokevirtual #81                 // Method android/support/v7/widget/h.a:(Landroid/graphics/drawable/Drawable;)V
      20: return

  public void setBackgroundResource(int);
    Code:
       0: aload_0
       1: iload_1
       2: invokespecial #85                 // Method android/widget/ImageView.setBackgroundResource:(I)V
       5: aload_0
       6: getfield      #34                 // Field a:Landroid/support/v7/widget/h;
       9: ifnull        20
      12: aload_0
      13: getfield      #34                 // Field a:Landroid/support/v7/widget/h;
      16: iload_1
      17: invokevirtual #87                 // Method android/support/v7/widget/h.a:(I)V
      20: return

  public void setImageBitmap(android.graphics.Bitmap);
    Code:
       0: aload_0
       1: aload_1
       2: invokespecial #91                 // Method android/widget/ImageView.setImageBitmap:(Landroid/graphics/Bitmap;)V
       5: aload_0
       6: getfield      #44                 // Field b:Landroid/support/v7/widget/q;
       9: ifnull        19
      12: aload_0
      13: getfield      #44                 // Field b:Landroid/support/v7/widget/q;
      16: invokevirtual #55                 // Method android/support/v7/widget/q.d:()V
      19: return

  public void setImageDrawable(android.graphics.drawable.Drawable);
    Code:
       0: aload_0
       1: aload_1
       2: invokespecial #94                 // Method android/widget/ImageView.setImageDrawable:(Landroid/graphics/drawable/Drawable;)V
       5: aload_0
       6: getfield      #44                 // Field b:Landroid/support/v7/widget/q;
       9: ifnull        19
      12: aload_0
      13: getfield      #44                 // Field b:Landroid/support/v7/widget/q;
      16: invokevirtual #55                 // Method android/support/v7/widget/q.d:()V
      19: return

  public void setImageResource(int);
    Code:
       0: aload_0
       1: getfield      #44                 // Field b:Landroid/support/v7/widget/q;
       4: ifnull        15
       7: aload_0
       8: getfield      #44                 // Field b:Landroid/support/v7/widget/q;
      11: iload_1
      12: invokevirtual #96                 // Method android/support/v7/widget/q.a:(I)V
      15: return

  public void setImageURI(android.net.Uri);
    Code:
       0: aload_0
       1: aload_1
       2: invokespecial #100                // Method android/widget/ImageView.setImageURI:(Landroid/net/Uri;)V
       5: aload_0
       6: getfield      #44                 // Field b:Landroid/support/v7/widget/q;
       9: ifnull        19
      12: aload_0
      13: getfield      #44                 // Field b:Landroid/support/v7/widget/q;
      16: invokevirtual #55                 // Method android/support/v7/widget/q.d:()V
      19: return

  public void setSupportBackgroundTintList(android.content.res.ColorStateList);
    Code:
       0: aload_0
       1: getfield      #34                 // Field a:Landroid/support/v7/widget/h;
       4: ifnull        15
       7: aload_0
       8: getfield      #34                 // Field a:Landroid/support/v7/widget/h;
      11: aload_1
      12: invokevirtual #104                // Method android/support/v7/widget/h.a:(Landroid/content/res/ColorStateList;)V
      15: return

  public void setSupportBackgroundTintMode(android.graphics.PorterDuff$Mode);
    Code:
       0: aload_0
       1: getfield      #34                 // Field a:Landroid/support/v7/widget/h;
       4: ifnull        15
       7: aload_0
       8: getfield      #34                 // Field a:Landroid/support/v7/widget/h;
      11: aload_1
      12: invokevirtual #108                // Method android/support/v7/widget/h.a:(Landroid/graphics/PorterDuff$Mode;)V
      15: return

  public void setSupportImageTintList(android.content.res.ColorStateList);
    Code:
       0: aload_0
       1: getfield      #44                 // Field b:Landroid/support/v7/widget/q;
       4: ifnull        15
       7: aload_0
       8: getfield      #44                 // Field b:Landroid/support/v7/widget/q;
      11: aload_1
      12: invokevirtual #110                // Method android/support/v7/widget/q.a:(Landroid/content/res/ColorStateList;)V
      15: return

  public void setSupportImageTintMode(android.graphics.PorterDuff$Mode);
    Code:
       0: aload_0
       1: getfield      #44                 // Field b:Landroid/support/v7/widget/q;
       4: ifnull        15
       7: aload_0
       8: getfield      #44                 // Field b:Landroid/support/v7/widget/q;
      11: aload_1
      12: invokevirtual #112                // Method android/support/v7/widget/q.a:(Landroid/graphics/PorterDuff$Mode;)V
      15: return
}
