public abstract class android.support.v7.widget.RecyclerView$h {
  public android.support.v7.widget.RecyclerView$h();
    Code:
       0: aload_0
       1: invokespecial #11                 // Method java/lang/Object."<init>":()V
       4: return

  public void a(android.graphics.Canvas, android.support.v7.widget.RecyclerView);
    Code:
       0: return

  public void a(android.graphics.Canvas, android.support.v7.widget.RecyclerView, android.support.v7.widget.RecyclerView$u);
    Code:
       0: aload_0
       1: aload_1
       2: aload_2
       3: invokevirtual #19                 // Method a:(Landroid/graphics/Canvas;Landroid/support/v7/widget/RecyclerView;)V
       6: return

  public void a(android.graphics.Rect, int, android.support.v7.widget.RecyclerView);
    Code:
       0: aload_1
       1: iconst_0
       2: iconst_0
       3: iconst_0
       4: iconst_0
       5: invokevirtual #26                 // Method android/graphics/Rect.set:(IIII)V
       8: return

  public void a(android.graphics.Rect, android.view.View, android.support.v7.widget.RecyclerView, android.support.v7.widget.RecyclerView$u);
    Code:
       0: aload_0
       1: aload_1
       2: aload_2
       3: invokevirtual #33                 // Method android/view/View.getLayoutParams:()Landroid/view/ViewGroup$LayoutParams;
       6: checkcast     #35                 // class android/support/v7/widget/RecyclerView$j
       9: invokevirtual #39                 // Method android/support/v7/widget/RecyclerView$j.f:()I
      12: aload_3
      13: invokevirtual #41                 // Method a:(Landroid/graphics/Rect;ILandroid/support/v7/widget/RecyclerView;)V
      16: return

  public void b(android.graphics.Canvas, android.support.v7.widget.RecyclerView);
    Code:
       0: return

  public void b(android.graphics.Canvas, android.support.v7.widget.RecyclerView, android.support.v7.widget.RecyclerView$u);
    Code:
       0: aload_0
       1: aload_1
       2: aload_2
       3: invokevirtual #44                 // Method b:(Landroid/graphics/Canvas;Landroid/support/v7/widget/RecyclerView;)V
       6: return
}
