class android.support.v7.widget.RecyclerView$o$a {
  final java.util.ArrayList<android.support.v7.widget.RecyclerView$x> a;

  int b;

  long c;

  long d;

  android.support.v7.widget.RecyclerView$o$a();
    Code:
       0: aload_0
       1: invokespecial #21                 // Method java/lang/Object."<init>":()V
       4: aload_0
       5: new           #23                 // class java/util/ArrayList
       8: dup
       9: invokespecial #24                 // Method java/util/ArrayList."<init>":()V
      12: putfield      #26                 // Field a:Ljava/util/ArrayList;
      15: aload_0
      16: iconst_5
      17: putfield      #28                 // Field b:I
      20: aload_0
      21: lconst_0
      22: putfield      #30                 // Field c:J
      25: aload_0
      26: lconst_0
      27: putfield      #32                 // Field d:J
      30: return
}
