final class android.support.v7.widget.RecyclerView$3 implements android.view.animation.Interpolator {
  android.support.v7.widget.RecyclerView$3();
    Code:
       0: aload_0
       1: invokespecial #12                 // Method java/lang/Object."<init>":()V
       4: return

  public float getInterpolation(float);
    Code:
       0: fload_1
       1: fconst_1
       2: fsub
       3: fstore_1
       4: fload_1
       5: fload_1
       6: fmul
       7: fload_1
       8: fmul
       9: fload_1
      10: fmul
      11: fload_1
      12: fmul
      13: fconst_1
      14: fadd
      15: freturn
}
