public abstract class android.support.v7.widget.RecyclerView$c {
  public android.support.v7.widget.RecyclerView$c();
    Code:
       0: aload_0
       1: invokespecial #11                 // Method java/lang/Object."<init>":()V
       4: return

  public void a();
    Code:
       0: return

  public void a(int, int);
    Code:
       0: return

  public void a(int, int, int);
    Code:
       0: return

  public void a(int, int, java.lang.Object);
    Code:
       0: aload_0
       1: iload_1
       2: iload_2
       3: invokevirtual #18                 // Method a:(II)V
       6: return

  public void b(int, int);
    Code:
       0: return

  public void c(int, int);
    Code:
       0: return
}
