public class android.support.v7.widget.RecyclerView$e {
  public android.support.v7.widget.RecyclerView$e();
    Code:
       0: aload_0
       1: invokespecial #11                 // Method java/lang/Object."<init>":()V
       4: return

  protected android.widget.EdgeEffect a(android.support.v7.widget.RecyclerView, int);
    Code:
       0: new           #16                 // class android/widget/EdgeEffect
       3: dup
       4: aload_1
       5: invokevirtual #20                 // Method android/support/v7/widget/RecyclerView.getContext:()Landroid/content/Context;
       8: invokespecial #23                 // Method android/widget/EdgeEffect."<init>":(Landroid/content/Context;)V
      11: areturn
}
