public class android.support.v7.widget.StaggeredGridLayoutManager extends android.support.v7.widget.RecyclerView$i {
  android.support.v7.widget.StaggeredGridLayoutManager$e[] a;

  android.support.v7.widget.ba b;

  android.support.v7.widget.ba c;

  boolean d;

  boolean e;

  int f;

  int g;

  android.support.v7.widget.StaggeredGridLayoutManager$c h;

  public android.support.v7.widget.StaggeredGridLayoutManager(int, int);
    Code:
       0: aload_0
       1: invokespecial #63                 // Method android/support/v7/widget/RecyclerView$i."<init>":()V
       4: aload_0
       5: iconst_m1
       6: putfield      #65                 // Field i:I
       9: aload_0
      10: iconst_0
      11: putfield      #67                 // Field d:Z
      14: aload_0
      15: iconst_0
      16: putfield      #69                 // Field e:Z
      19: aload_0
      20: iconst_m1
      21: putfield      #71                 // Field f:I
      24: aload_0
      25: ldc           #72                 // int -2147483648
      27: putfield      #74                 // Field g:I
      30: aload_0
      31: new           #14                 // class android/support/v7/widget/StaggeredGridLayoutManager$c
      34: dup
      35: invokespecial #75                 // Method android/support/v7/widget/StaggeredGridLayoutManager$c."<init>":()V
      38: putfield      #77                 // Field h:Landroid/support/v7/widget/StaggeredGridLayoutManager$c;
      41: aload_0
      42: iconst_2
      43: putfield      #79                 // Field n:I
      46: aload_0
      47: new           #81                 // class android/graphics/Rect
      50: dup
      51: invokespecial #82                 // Method android/graphics/Rect."<init>":()V
      54: putfield      #84                 // Field C:Landroid/graphics/Rect;
      57: aload_0
      58: new           #8                  // class android/support/v7/widget/StaggeredGridLayoutManager$a
      61: dup
      62: aload_0
      63: invokespecial #87                 // Method android/support/v7/widget/StaggeredGridLayoutManager$a."<init>":(Landroid/support/v7/widget/StaggeredGridLayoutManager;)V
      66: putfield      #89                 // Field D:Landroid/support/v7/widget/StaggeredGridLayoutManager$a;
      69: aload_0
      70: iconst_0
      71: putfield      #91                 // Field E:Z
      74: aload_0
      75: iconst_1
      76: putfield      #93                 // Field F:Z
      79: aload_0
      80: new           #6                  // class android/support/v7/widget/StaggeredGridLayoutManager$1
      83: dup
      84: aload_0
      85: invokespecial #94                 // Method android/support/v7/widget/StaggeredGridLayoutManager$1."<init>":(Landroid/support/v7/widget/StaggeredGridLayoutManager;)V
      88: putfield      #96                 // Field H:Ljava/lang/Runnable;
      91: aload_0
      92: iload_2
      93: putfield      #98                 // Field j:I
      96: aload_0
      97: iload_1
      98: invokevirtual #101                // Method a:(I)V
     101: aload_0
     102: new           #103                // class android/support/v7/widget/au
     105: dup
     106: invokespecial #104                // Method android/support/v7/widget/au."<init>":()V
     109: putfield      #106                // Field l:Landroid/support/v7/widget/au;
     112: aload_0
     113: invokespecial #109                // Method M:()V
     116: return

  public android.support.v7.widget.StaggeredGridLayoutManager(android.content.Context, android.util.AttributeSet, int, int);
    Code:
       0: aload_0
       1: invokespecial #63                 // Method android/support/v7/widget/RecyclerView$i."<init>":()V
       4: aload_0
       5: iconst_m1
       6: putfield      #65                 // Field i:I
       9: aload_0
      10: iconst_0
      11: putfield      #67                 // Field d:Z
      14: aload_0
      15: iconst_0
      16: putfield      #69                 // Field e:Z
      19: aload_0
      20: iconst_m1
      21: putfield      #71                 // Field f:I
      24: aload_0
      25: ldc           #72                 // int -2147483648
      27: putfield      #74                 // Field g:I
      30: aload_0
      31: new           #14                 // class android/support/v7/widget/StaggeredGridLayoutManager$c
      34: dup
      35: invokespecial #75                 // Method android/support/v7/widget/StaggeredGridLayoutManager$c."<init>":()V
      38: putfield      #77                 // Field h:Landroid/support/v7/widget/StaggeredGridLayoutManager$c;
      41: aload_0
      42: iconst_2
      43: putfield      #79                 // Field n:I
      46: aload_0
      47: new           #81                 // class android/graphics/Rect
      50: dup
      51: invokespecial #82                 // Method android/graphics/Rect."<init>":()V
      54: putfield      #84                 // Field C:Landroid/graphics/Rect;
      57: aload_0
      58: new           #8                  // class android/support/v7/widget/StaggeredGridLayoutManager$a
      61: dup
      62: aload_0
      63: invokespecial #87                 // Method android/support/v7/widget/StaggeredGridLayoutManager$a."<init>":(Landroid/support/v7/widget/StaggeredGridLayoutManager;)V
      66: putfield      #89                 // Field D:Landroid/support/v7/widget/StaggeredGridLayoutManager$a;
      69: aload_0
      70: iconst_0
      71: putfield      #91                 // Field E:Z
      74: aload_0
      75: iconst_1
      76: putfield      #93                 // Field F:Z
      79: aload_0
      80: new           #6                  // class android/support/v7/widget/StaggeredGridLayoutManager$1
      83: dup
      84: aload_0
      85: invokespecial #94                 // Method android/support/v7/widget/StaggeredGridLayoutManager$1."<init>":(Landroid/support/v7/widget/StaggeredGridLayoutManager;)V
      88: putfield      #96                 // Field H:Ljava/lang/Runnable;
      91: aload_1
      92: aload_2
      93: iload_3
      94: iload         4
      96: invokestatic  #114                // Method a:(Landroid/content/Context;Landroid/util/AttributeSet;II)Landroid/support/v7/widget/RecyclerView$i$b;
      99: astore_1
     100: aload_0
     101: aload_1
     102: getfield      #118                // Field android/support/v7/widget/RecyclerView$i$b.a:I
     105: invokevirtual #120                // Method b:(I)V
     108: aload_0
     109: aload_1
     110: getfield      #122                // Field android/support/v7/widget/RecyclerView$i$b.b:I
     113: invokevirtual #101                // Method a:(I)V
     116: aload_0
     117: aload_1
     118: getfield      #124                // Field android/support/v7/widget/RecyclerView$i$b.c:Z
     121: invokevirtual #127                // Method a:(Z)V
     124: aload_0
     125: new           #103                // class android/support/v7/widget/au
     128: dup
     129: invokespecial #104                // Method android/support/v7/widget/au."<init>":()V
     132: putfield      #106                // Field l:Landroid/support/v7/widget/au;
     135: aload_0
     136: invokespecial #109                // Method M:()V
     139: return

  int K();
    Code:
       0: aload_0
       1: invokevirtual #148                // Method v:()I
       4: istore_1
       5: iload_1
       6: ifne          11
       9: iconst_0
      10: ireturn
      11: aload_0
      12: aload_0
      13: iload_1
      14: iconst_1
      15: isub
      16: invokevirtual #151                // Method h:(I)Landroid/view/View;
      19: invokevirtual #582                // Method d:(Landroid/view/View;)I
      22: ireturn

  int L();
    Code:
       0: aload_0
       1: invokevirtual #148                // Method v:()I
       4: ifne          9
       7: iconst_0
       8: ireturn
       9: aload_0
      10: aload_0
      11: iconst_0
      12: invokevirtual #151                // Method h:(I)Landroid/view/View;
      15: invokevirtual #582                // Method d:(Landroid/view/View;)I
      18: ireturn

  public int a(int, android.support.v7.widget.RecyclerView$p, android.support.v7.widget.RecyclerView$u);
    Code:
       0: aload_0
       1: iload_1
       2: aload_2
       3: aload_3
       4: invokevirtual #552                // Method c:(ILandroid/support/v7/widget/RecyclerView$p;Landroid/support/v7/widget/RecyclerView$u;)I
       7: ireturn

  public int a(android.support.v7.widget.RecyclerView$p, android.support.v7.widget.RecyclerView$u);
    Code:
       0: aload_0
       1: getfield      #98                 // Field j:I
       4: ifne          12
       7: aload_0
       8: getfield      #65                 // Field i:I
      11: ireturn
      12: aload_0
      13: aload_1
      14: aload_2
      15: invokespecial #585                // Method android/support/v7/widget/RecyclerView$i.a:(Landroid/support/v7/widget/RecyclerView$p;Landroid/support/v7/widget/RecyclerView$u;)I
      18: ireturn

  public android.support.v7.widget.RecyclerView$j a();
    Code:
       0: aload_0
       1: getfield      #98                 // Field j:I
       4: ifne          18
       7: new           #11                 // class android/support/v7/widget/StaggeredGridLayoutManager$b
      10: dup
      11: bipush        -2
      13: iconst_m1
      14: invokespecial #588                // Method android/support/v7/widget/StaggeredGridLayoutManager$b."<init>":(II)V
      17: areturn
      18: new           #11                 // class android/support/v7/widget/StaggeredGridLayoutManager$b
      21: dup
      22: iconst_m1
      23: bipush        -2
      25: invokespecial #588                // Method android/support/v7/widget/StaggeredGridLayoutManager$b."<init>":(II)V
      28: areturn

  public android.support.v7.widget.RecyclerView$j a(android.content.Context, android.util.AttributeSet);
    Code:
       0: new           #11                 // class android/support/v7/widget/StaggeredGridLayoutManager$b
       3: dup
       4: aload_1
       5: aload_2
       6: invokespecial #592                // Method android/support/v7/widget/StaggeredGridLayoutManager$b."<init>":(Landroid/content/Context;Landroid/util/AttributeSet;)V
       9: areturn

  public android.support.v7.widget.RecyclerView$j a(android.view.ViewGroup$LayoutParams);
    Code:
       0: aload_1
       1: instanceof    #595                // class android/view/ViewGroup$MarginLayoutParams
       4: ifeq          19
       7: new           #11                 // class android/support/v7/widget/StaggeredGridLayoutManager$b
      10: dup
      11: aload_1
      12: checkcast     #595                // class android/view/ViewGroup$MarginLayoutParams
      15: invokespecial #598                // Method android/support/v7/widget/StaggeredGridLayoutManager$b."<init>":(Landroid/view/ViewGroup$MarginLayoutParams;)V
      18: areturn
      19: new           #11                 // class android/support/v7/widget/StaggeredGridLayoutManager$b
      22: dup
      23: aload_1
      24: invokespecial #601                // Method android/support/v7/widget/StaggeredGridLayoutManager$b."<init>":(Landroid/view/ViewGroup$LayoutParams;)V
      27: areturn

  public android.view.View a(android.view.View, int, android.support.v7.widget.RecyclerView$p, android.support.v7.widget.RecyclerView$u);
    Code:
       0: aload_0
       1: invokevirtual #148                // Method v:()I
       4: ifne          9
       7: aconst_null
       8: areturn
       9: aload_0
      10: aload_1
      11: invokevirtual #605                // Method e:(Landroid/view/View;)Landroid/view/View;
      14: astore_1
      15: aload_1
      16: ifnonnull     21
      19: aconst_null
      20: areturn
      21: aload_0
      22: invokespecial #340                // Method N:()V
      25: aload_0
      26: iload_2
      27: invokespecial #607                // Method w:(I)I
      30: istore        7
      32: iload         7
      34: ldc           #72                 // int -2147483648
      36: if_icmpne     41
      39: aconst_null
      40: areturn
      41: aload_1
      42: invokevirtual #160                // Method android/view/View.getLayoutParams:()Landroid/view/ViewGroup$LayoutParams;
      45: checkcast     #11                 // class android/support/v7/widget/StaggeredGridLayoutManager$b
      48: astore        10
      50: aload         10
      52: getfield      #184                // Field android/support/v7/widget/StaggeredGridLayoutManager$b.b:Z
      55: istore        8
      57: aload         10
      59: getfield      #187                // Field android/support/v7/widget/StaggeredGridLayoutManager$b.a:Landroid/support/v7/widget/StaggeredGridLayoutManager$e;
      62: astore        10
      64: iload         7
      66: iconst_1
      67: if_icmpne     78
      70: aload_0
      71: invokevirtual #557                // Method K:()I
      74: istore_2
      75: goto          83
      78: aload_0
      79: invokevirtual #560                // Method L:()I
      82: istore_2
      83: aload_0
      84: iload_2
      85: aload         4
      87: invokespecial #373                // Method b:(ILandroid/support/v7/widget/RecyclerView$u;)V
      90: aload_0
      91: iload         7
      93: invokespecial #375                // Method l:(I)V
      96: aload_0
      97: getfield      #106                // Field l:Landroid/support/v7/widget/au;
     100: aload_0
     101: getfield      #106                // Field l:Landroid/support/v7/widget/au;
     104: getfield      #269                // Field android/support/v7/widget/au.d:I
     107: iload_2
     108: iadd
     109: putfield      #378                // Field android/support/v7/widget/au.c:I
     112: aload_0
     113: getfield      #106                // Field l:Landroid/support/v7/widget/au;
     116: aload_0
     117: getfield      #134                // Field b:Landroid/support/v7/widget/ba;
     120: invokevirtual #176                // Method android/support/v7/widget/ba.f:()I
     123: i2f
     124: ldc_w         #608                // float 0.33333334f
     127: fmul
     128: f2i
     129: putfield      #210                // Field android/support/v7/widget/au.b:I
     132: aload_0
     133: getfield      #106                // Field l:Landroid/support/v7/widget/au;
     136: iconst_1
     137: putfield      #290                // Field android/support/v7/widget/au.h:Z
     140: aload_0
     141: getfield      #106                // Field l:Landroid/support/v7/widget/au;
     144: astore        11
     146: iconst_0
     147: istore        6
     149: aload         11
     151: iconst_0
     152: putfield      #369                // Field android/support/v7/widget/au.a:Z
     155: aload_0
     156: aload_3
     157: aload_0
     158: getfield      #106                // Field l:Landroid/support/v7/widget/au;
     161: aload         4
     163: invokespecial #377                // Method a:(Landroid/support/v7/widget/RecyclerView$p;Landroid/support/v7/widget/au;Landroid/support/v7/widget/RecyclerView$u;)I
     166: pop
     167: aload_0
     168: aload_0
     169: getfield      #69                 // Field e:Z
     172: putfield      #346                // Field o:Z
     175: iload         8
     177: ifne          200
     180: aload         10
     182: iload_2
     183: iload         7
     185: invokevirtual #611                // Method android/support/v7/widget/StaggeredGridLayoutManager$e.a:(II)Landroid/view/View;
     188: astore_3
     189: aload_3
     190: ifnull        200
     193: aload_3
     194: aload_1
     195: if_acmpeq     200
     198: aload_3
     199: areturn
     200: aload_0
     201: iload         7
     203: invokespecial #303                // Method s:(I)Z
     206: ifeq          256
     209: aload_0
     210: getfield      #65                 // Field i:I
     213: iconst_1
     214: isub
     215: istore        5
     217: iload         5
     219: iflt          302
     222: aload_0
     223: getfield      #232                // Field a:[Landroid/support/v7/widget/StaggeredGridLayoutManager$e;
     226: iload         5
     228: aaload
     229: iload_2
     230: iload         7
     232: invokevirtual #611                // Method android/support/v7/widget/StaggeredGridLayoutManager$e.a:(II)Landroid/view/View;
     235: astore_3
     236: aload_3
     237: ifnull        247
     240: aload_3
     241: aload_1
     242: if_acmpeq     247
     245: aload_3
     246: areturn
     247: iload         5
     249: iconst_1
     250: isub
     251: istore        5
     253: goto          217
     256: iconst_0
     257: istore        5
     259: iload         5
     261: aload_0
     262: getfield      #65                 // Field i:I
     265: if_icmpge     302
     268: aload_0
     269: getfield      #232                // Field a:[Landroid/support/v7/widget/StaggeredGridLayoutManager$e;
     272: iload         5
     274: aaload
     275: iload_2
     276: iload         7
     278: invokevirtual #611                // Method android/support/v7/widget/StaggeredGridLayoutManager$e.a:(II)Landroid/view/View;
     281: astore_3
     282: aload_3
     283: ifnull        293
     286: aload_3
     287: aload_1
     288: if_acmpeq     293
     291: aload_3
     292: areturn
     293: iload         5
     295: iconst_1
     296: iadd
     297: istore        5
     299: goto          259
     302: aload_0
     303: getfield      #67                 // Field d:Z
     306: istore        9
     308: iload         7
     310: iconst_m1
     311: if_icmpne     319
     314: iconst_1
     315: istore_2
     316: goto          321
     319: iconst_0
     320: istore_2
     321: iload         9
     323: iconst_1
     324: ixor
     325: iload_2
     326: if_icmpne     334
     329: iconst_1
     330: istore_2
     331: goto          336
     334: iconst_0
     335: istore_2
     336: iload         8
     338: ifne          380
     341: iload_2
     342: ifeq          355
     345: aload         10
     347: invokevirtual #613                // Method android/support/v7/widget/StaggeredGridLayoutManager$e.j:()I
     350: istore        5
     352: goto          362
     355: aload         10
     357: invokevirtual #615                // Method android/support/v7/widget/StaggeredGridLayoutManager$e.k:()I
     360: istore        5
     362: aload_0
     363: iload         5
     365: invokevirtual #617                // Method c:(I)Landroid/view/View;
     368: astore_3
     369: aload_3
     370: ifnull        380
     373: aload_3
     374: aload_1
     375: if_acmpeq     380
     378: aload_3
     379: areturn
     380: iload         6
     382: istore        5
     384: aload_0
     385: iload         7
     387: invokespecial #303                // Method s:(I)Z
     390: ifeq          477
     393: aload_0
     394: getfield      #65                 // Field i:I
     397: iconst_1
     398: isub
     399: istore        5
     401: iload         5
     403: iflt          544
     406: iload         5
     408: aload         10
     410: getfield      #189                // Field android/support/v7/widget/StaggeredGridLayoutManager$e.e:I
     413: if_icmpne     419
     416: goto          468
     419: iload_2
     420: ifeq          438
     423: aload_0
     424: getfield      #232                // Field a:[Landroid/support/v7/widget/StaggeredGridLayoutManager$e;
     427: iload         5
     429: aaload
     430: invokevirtual #613                // Method android/support/v7/widget/StaggeredGridLayoutManager$e.j:()I
     433: istore        6
     435: goto          450
     438: aload_0
     439: getfield      #232                // Field a:[Landroid/support/v7/widget/StaggeredGridLayoutManager$e;
     442: iload         5
     444: aaload
     445: invokevirtual #615                // Method android/support/v7/widget/StaggeredGridLayoutManager$e.k:()I
     448: istore        6
     450: aload_0
     451: iload         6
     453: invokevirtual #617                // Method c:(I)Landroid/view/View;
     456: astore_3
     457: aload_3
     458: ifnull        468
     461: aload_3
     462: aload_1
     463: if_acmpeq     468
     466: aload_3
     467: areturn
     468: iload         5
     470: iconst_1
     471: isub
     472: istore        5
     474: goto          401
     477: iload         5
     479: aload_0
     480: getfield      #65                 // Field i:I
     483: if_icmpge     544
     486: iload_2
     487: ifeq          505
     490: aload_0
     491: getfield      #232                // Field a:[Landroid/support/v7/widget/StaggeredGridLayoutManager$e;
     494: iload         5
     496: aaload
     497: invokevirtual #613                // Method android/support/v7/widget/StaggeredGridLayoutManager$e.j:()I
     500: istore        6
     502: goto          517
     505: aload_0
     506: getfield      #232                // Field a:[Landroid/support/v7/widget/StaggeredGridLayoutManager$e;
     509: iload         5
     511: aaload
     512: invokevirtual #615                // Method android/support/v7/widget/StaggeredGridLayoutManager$e.k:()I
     515: istore        6
     517: aload_0
     518: iload         6
     520: invokevirtual #617                // Method c:(I)Landroid/view/View;
     523: astore_3
     524: aload_3
     525: ifnull        535
     528: aload_3
     529: aload_1
     530: if_acmpeq     535
     533: aload_3
     534: areturn
     535: iload         5
     537: iconst_1
     538: iadd
     539: istore        5
     541: goto          477
     544: aconst_null
     545: areturn

  public void a(int);
    Code:
       0: aload_0
       1: aconst_null
       2: invokevirtual #620                // Method a:(Ljava/lang/String;)V
       5: iload_1
       6: aload_0
       7: getfield      #65                 // Field i:I
      10: if_icmpeq     84
      13: aload_0
      14: invokevirtual #622                // Method i:()V
      17: aload_0
      18: iload_1
      19: putfield      #65                 // Field i:I
      22: aload_0
      23: new           #200                // class java/util/BitSet
      26: dup
      27: aload_0
      28: getfield      #65                 // Field i:I
      31: invokespecial #624                // Method java/util/BitSet."<init>":(I)V
      34: putfield      #198                // Field m:Ljava/util/BitSet;
      37: aload_0
      38: aload_0
      39: getfield      #65                 // Field i:I
      42: anewarray     #26                 // class android/support/v7/widget/StaggeredGridLayoutManager$e
      45: putfield      #232                // Field a:[Landroid/support/v7/widget/StaggeredGridLayoutManager$e;
      48: iconst_0
      49: istore_1
      50: iload_1
      51: aload_0
      52: getfield      #65                 // Field i:I
      55: if_icmpge     80
      58: aload_0
      59: getfield      #232                // Field a:[Landroid/support/v7/widget/StaggeredGridLayoutManager$e;
      62: iload_1
      63: new           #26                 // class android/support/v7/widget/StaggeredGridLayoutManager$e
      66: dup
      67: aload_0
      68: iload_1
      69: invokespecial #627                // Method android/support/v7/widget/StaggeredGridLayoutManager$e."<init>":(Landroid/support/v7/widget/StaggeredGridLayoutManager;I)V
      72: aastore
      73: iload_1
      74: iconst_1
      75: iadd
      76: istore_1
      77: goto          50
      80: aload_0
      81: invokevirtual #566                // Method o:()V
      84: return

  public void a(int, int, android.support.v7.widget.RecyclerView$u, android.support.v7.widget.RecyclerView$i$a);
    Code:
       0: aload_0
       1: getfield      #98                 // Field j:I
       4: ifne          10
       7: goto          12
      10: iload_2
      11: istore_1
      12: aload_0
      13: invokevirtual #148                // Method v:()I
      16: ifeq          262
      19: iload_1
      20: ifne          24
      23: return
      24: aload_0
      25: iload_1
      26: aload_3
      27: invokevirtual #630                // Method a:(ILandroid/support/v7/widget/RecyclerView$u;)V
      30: aload_0
      31: getfield      #632                // Field G:[I
      34: ifnull        49
      37: aload_0
      38: getfield      #632                // Field G:[I
      41: arraylength
      42: aload_0
      43: getfield      #65                 // Field i:I
      46: if_icmpge     59
      49: aload_0
      50: aload_0
      51: getfield      #65                 // Field i:I
      54: newarray       int
      56: putfield      #632                // Field G:[I
      59: iconst_0
      60: istore        7
      62: iconst_0
      63: istore_2
      64: iconst_0
      65: istore_1
      66: iload_2
      67: aload_0
      68: getfield      #65                 // Field i:I
      71: if_icmpge     183
      74: aload_0
      75: getfield      #106                // Field l:Landroid/support/v7/widget/au;
      78: getfield      #269                // Field android/support/v7/widget/au.d:I
      81: iconst_m1
      82: if_icmpne     122
      85: aload_0
      86: getfield      #106                // Field l:Landroid/support/v7/widget/au;
      89: getfield      #211                // Field android/support/v7/widget/au.f:I
      92: istore        5
      94: aload_0
      95: getfield      #232                // Field a:[Landroid/support/v7/widget/StaggeredGridLayoutManager$e;
      98: iload_2
      99: aaload
     100: aload_0
     101: getfield      #106                // Field l:Landroid/support/v7/widget/au;
     104: getfield      #211                // Field android/support/v7/widget/au.f:I
     107: invokevirtual #265                // Method android/support/v7/widget/StaggeredGridLayoutManager$e.a:(I)I
     110: istore        6
     112: iload         5
     114: iload         6
     116: isub
     117: istore        6
     119: goto          152
     122: aload_0
     123: getfield      #232                // Field a:[Landroid/support/v7/widget/StaggeredGridLayoutManager$e;
     126: iload_2
     127: aaload
     128: aload_0
     129: getfield      #106                // Field l:Landroid/support/v7/widget/au;
     132: getfield      #209                // Field android/support/v7/widget/au.g:I
     135: invokevirtual #252                // Method android/support/v7/widget/StaggeredGridLayoutManager$e.b:(I)I
     138: istore        5
     140: aload_0
     141: getfield      #106                // Field l:Landroid/support/v7/widget/au;
     144: getfield      #209                // Field android/support/v7/widget/au.g:I
     147: istore        6
     149: goto          112
     152: iload_1
     153: istore        5
     155: iload         6
     157: iflt          173
     160: aload_0
     161: getfield      #632                // Field G:[I
     164: iload_1
     165: iload         6
     167: iastore
     168: iload_1
     169: iconst_1
     170: iadd
     171: istore        5
     173: iload_2
     174: iconst_1
     175: iadd
     176: istore_2
     177: iload         5
     179: istore_1
     180: goto          66
     183: aload_0
     184: getfield      #632                // Field G:[I
     187: iconst_0
     188: iload_1
     189: invokestatic  #638                // Method java/util/Arrays.sort:([III)V
     192: iload         7
     194: istore_2
     195: iload_2
     196: iload_1
     197: if_icmpge     262
     200: aload_0
     201: getfield      #106                // Field l:Landroid/support/v7/widget/au;
     204: aload_3
     205: invokevirtual #220                // Method android/support/v7/widget/au.a:(Landroid/support/v7/widget/RecyclerView$u;)Z
     208: ifeq          262
     211: aload         4
     213: aload_0
     214: getfield      #106                // Field l:Landroid/support/v7/widget/au;
     217: getfield      #378                // Field android/support/v7/widget/au.c:I
     220: aload_0
     221: getfield      #632                // Field G:[I
     224: iload_2
     225: iaload
     226: invokeinterface #641,  3          // InterfaceMethod android/support/v7/widget/RecyclerView$i$a.b:(II)V
     231: aload_0
     232: getfield      #106                // Field l:Landroid/support/v7/widget/au;
     235: astore        8
     237: aload         8
     239: aload         8
     241: getfield      #378                // Field android/support/v7/widget/au.c:I
     244: aload_0
     245: getfield      #106                // Field l:Landroid/support/v7/widget/au;
     248: getfield      #269                // Field android/support/v7/widget/au.d:I
     251: iadd
     252: putfield      #378                // Field android/support/v7/widget/au.c:I
     255: iload_2
     256: iconst_1
     257: iadd
     258: istore_2
     259: goto          195
     262: return

  void a(int, android.support.v7.widget.RecyclerView$u);
    Code:
       0: iload_1
       1: ifle          15
       4: aload_0
       5: invokevirtual #557                // Method K:()I
       8: istore_3
       9: iconst_1
      10: istore        4
      12: goto          23
      15: aload_0
      16: invokevirtual #560                // Method L:()I
      19: istore_3
      20: iconst_m1
      21: istore        4
      23: aload_0
      24: getfield      #106                // Field l:Landroid/support/v7/widget/au;
      27: iconst_1
      28: putfield      #369                // Field android/support/v7/widget/au.a:Z
      31: aload_0
      32: iload_3
      33: aload_2
      34: invokespecial #373                // Method b:(ILandroid/support/v7/widget/RecyclerView$u;)V
      37: aload_0
      38: iload         4
      40: invokespecial #375                // Method l:(I)V
      43: aload_0
      44: getfield      #106                // Field l:Landroid/support/v7/widget/au;
      47: iload_3
      48: aload_0
      49: getfield      #106                // Field l:Landroid/support/v7/widget/au;
      52: getfield      #269                // Field android/support/v7/widget/au.d:I
      55: iadd
      56: putfield      #378                // Field android/support/v7/widget/au.c:I
      59: aload_0
      60: getfield      #106                // Field l:Landroid/support/v7/widget/au;
      63: iload_1
      64: invokestatic  #644                // Method java/lang/Math.abs:(I)I
      67: putfield      #210                // Field android/support/v7/widget/au.b:I
      70: return

  public void a(android.graphics.Rect, int, int);
    Code:
       0: aload_0
       1: invokevirtual #500                // Method A:()I
       4: aload_0
       5: invokevirtual #502                // Method C:()I
       8: iadd
       9: istore        4
      11: aload_0
      12: invokevirtual #482                // Method B:()I
      15: aload_0
      16: invokevirtual #484                // Method D:()I
      19: iadd
      20: istore        5
      22: aload_0
      23: getfield      #98                 // Field j:I
      26: iconst_1
      27: if_icmpne     76
      30: iload_3
      31: aload_1
      32: invokevirtual #647                // Method android/graphics/Rect.height:()I
      35: iload         5
      37: iadd
      38: aload_0
      39: invokevirtual #649                // Method G:()I
      42: invokestatic  #651                // Method a:(III)I
      45: istore_3
      46: iload_2
      47: aload_0
      48: getfield      #170                // Field k:I
      51: aload_0
      52: getfield      #65                 // Field i:I
      55: imul
      56: iload         4
      58: iadd
      59: aload_0
      60: invokevirtual #653                // Method F:()I
      63: invokestatic  #651                // Method a:(III)I
      66: istore        4
      68: iload_3
      69: istore_2
      70: iload         4
      72: istore_3
      73: goto          119
      76: iload_2
      77: aload_1
      78: invokevirtual #655                // Method android/graphics/Rect.width:()I
      81: iload         4
      83: iadd
      84: aload_0
      85: invokevirtual #653                // Method F:()I
      88: invokestatic  #651                // Method a:(III)I
      91: istore_2
      92: iload_3
      93: aload_0
      94: getfield      #170                // Field k:I
      97: aload_0
      98: getfield      #65                 // Field i:I
     101: imul
     102: iload         5
     104: iadd
     105: aload_0
     106: invokevirtual #649                // Method G:()I
     109: invokestatic  #651                // Method a:(III)I
     112: istore        4
     114: iload_2
     115: istore_3
     116: iload         4
     118: istore_2
     119: aload_0
     120: iload_3
     121: iload_2
     122: invokevirtual #657                // Method f:(II)V
     125: return

  public void a(android.os.Parcelable);
    Code:
       0: aload_1
       1: instanceof    #21                 // class android/support/v7/widget/StaggeredGridLayoutManager$d
       4: ifeq          19
       7: aload_0
       8: aload_1
       9: checkcast     #21                 // class android/support/v7/widget/StaggeredGridLayoutManager$d
      12: putfield      #325                // Field A:Landroid/support/v7/widget/StaggeredGridLayoutManager$d;
      15: aload_0
      16: invokevirtual #566                // Method o:()V
      19: return

  public void a(android.support.v7.widget.RecyclerView$p, android.support.v7.widget.RecyclerView$u, android.view.View, android.support.v4.view.a.b);
    Code:
       0: aload_3
       1: invokevirtual #160                // Method android/view/View.getLayoutParams:()Landroid/view/ViewGroup$LayoutParams;
       4: astore_1
       5: aload_1
       6: instanceof    #11                 // class android/support/v7/widget/StaggeredGridLayoutManager$b
       9: ifne          20
      12: aload_0
      13: aload_3
      14: aload         4
      16: invokespecial #662                // Method android/support/v7/widget/RecyclerView$i.a:(Landroid/view/View;Landroid/support/v4/view/a/b;)V
      19: return
      20: aload_1
      21: checkcast     #11                 // class android/support/v7/widget/StaggeredGridLayoutManager$b
      24: astore_1
      25: aload_0
      26: getfield      #98                 // Field j:I
      29: ifne          93
      32: aload_1
      33: invokevirtual #663                // Method android/support/v7/widget/StaggeredGridLayoutManager$b.b:()I
      36: istore        9
      38: aload_1
      39: getfield      #184                // Field android/support/v7/widget/StaggeredGridLayoutManager$b.b:Z
      42: ifeq          54
      45: aload_0
      46: getfield      #65                 // Field i:I
      49: istore        6
      51: goto          57
      54: iconst_1
      55: istore        6
      57: iconst_m1
      58: istore        8
      60: iconst_m1
      61: istore        5
      63: iload         6
      65: istore        7
      67: iload         9
      69: istore        6
      71: aload         4
      73: iload         6
      75: iload         7
      77: iload         8
      79: iload         5
      81: aload_1
      82: getfield      #184                // Field android/support/v7/widget/StaggeredGridLayoutManager$b.b:Z
      85: iconst_0
      86: invokestatic  #668                // Method android/support/v4/view/a/b$c.a:(IIIIZZ)Landroid/support/v4/view/a/b$c;
      89: invokevirtual #673                // Method android/support/v4/view/a/b.b:(Ljava/lang/Object;)V
      92: return
      93: iconst_m1
      94: istore        6
      96: iconst_m1
      97: istore        7
      99: aload_1
     100: invokevirtual #663                // Method android/support/v7/widget/StaggeredGridLayoutManager$b.b:()I
     103: istore        8
     105: aload_1
     106: getfield      #184                // Field android/support/v7/widget/StaggeredGridLayoutManager$b.b:Z
     109: ifeq          121
     112: aload_0
     113: getfield      #65                 // Field i:I
     116: istore        5
     118: goto          71
     121: iconst_1
     122: istore        5
     124: goto          71

  public void a(android.support.v7.widget.RecyclerView$u);
    Code:
       0: aload_0
       1: aload_1
       2: invokespecial #676                // Method android/support/v7/widget/RecyclerView$i.a:(Landroid/support/v7/widget/RecyclerView$u;)V
       5: aload_0
       6: iconst_m1
       7: putfield      #71                 // Field f:I
      10: aload_0
      11: ldc           #72                 // int -2147483648
      13: putfield      #74                 // Field g:I
      16: aload_0
      17: aconst_null
      18: putfield      #325                // Field A:Landroid/support/v7/widget/StaggeredGridLayoutManager$d;
      21: aload_0
      22: getfield      #89                 // Field D:Landroid/support/v7/widget/StaggeredGridLayoutManager$a;
      25: invokevirtual #334                // Method android/support/v7/widget/StaggeredGridLayoutManager$a.a:()V
      28: return

  void a(android.support.v7.widget.RecyclerView$u, android.support.v7.widget.StaggeredGridLayoutManager$a);
    Code:
       0: aload_0
       1: aload_1
       2: aload_2
       3: invokevirtual #678                // Method b:(Landroid/support/v7/widget/RecyclerView$u;Landroid/support/v7/widget/StaggeredGridLayoutManager$a;)Z
       6: ifeq          10
       9: return
      10: aload_0
      11: aload_1
      12: aload_2
      13: invokespecial #680                // Method c:(Landroid/support/v7/widget/RecyclerView$u;Landroid/support/v7/widget/StaggeredGridLayoutManager$a;)Z
      16: ifeq          20
      19: return
      20: aload_2
      21: invokevirtual #682                // Method android/support/v7/widget/StaggeredGridLayoutManager$a.b:()V
      24: aload_2
      25: iconst_0
      26: putfield      #370                // Field android/support/v7/widget/StaggeredGridLayoutManager$a.a:I
      29: return

  public void a(android.support.v7.widget.RecyclerView);
    Code:
       0: aload_0
       1: getfield      #77                 // Field h:Landroid/support/v7/widget/StaggeredGridLayoutManager$c;
       4: invokevirtual #349                // Method android/support/v7/widget/StaggeredGridLayoutManager$c.a:()V
       7: aload_0
       8: invokevirtual #566                // Method o:()V
      11: return

  public void a(android.support.v7.widget.RecyclerView, int, int);
    Code:
       0: aload_0
       1: iload_2
       2: iload_3
       3: iconst_1
       4: invokespecial #686                // Method c:(III)V
       7: return

  public void a(android.support.v7.widget.RecyclerView, int, int, int);
    Code:
       0: aload_0
       1: iload_2
       2: iload_3
       3: bipush        8
       5: invokespecial #686                // Method c:(III)V
       8: return

  public void a(android.support.v7.widget.RecyclerView, int, int, java.lang.Object);
    Code:
       0: aload_0
       1: iload_2
       2: iload_3
       3: iconst_4
       4: invokespecial #686                // Method c:(III)V
       7: return

  public void a(android.support.v7.widget.RecyclerView, android.support.v7.widget.RecyclerView$p);
    Code:
       0: aload_0
       1: aload_1
       2: aload_2
       3: invokespecial #691                // Method android/support/v7/widget/RecyclerView$i.a:(Landroid/support/v7/widget/RecyclerView;Landroid/support/v7/widget/RecyclerView$p;)V
       6: aload_0
       7: aload_0
       8: getfield      #96                 // Field H:Ljava/lang/Runnable;
      11: invokevirtual #391                // Method a:(Ljava/lang/Runnable;)Z
      14: pop
      15: iconst_0
      16: istore_3
      17: iload_3
      18: aload_0
      19: getfield      #65                 // Field i:I
      22: if_icmpge     41
      25: aload_0
      26: getfield      #232                // Field a:[Landroid/support/v7/widget/StaggeredGridLayoutManager$e;
      29: iload_3
      30: aaload
      31: invokevirtual #354                // Method android/support/v7/widget/StaggeredGridLayoutManager$e.e:()V
      34: iload_3
      35: iconst_1
      36: iadd
      37: istore_3
      38: goto          17
      41: aload_1
      42: invokevirtual #696                // Method android/support/v7/widget/RecyclerView.requestLayout:()V
      45: return

  public void a(android.view.accessibility.AccessibilityEvent);
    Code:
       0: aload_0
       1: aload_1
       2: invokespecial #699                // Method android/support/v7/widget/RecyclerView$i.a:(Landroid/view/accessibility/AccessibilityEvent;)V
       5: aload_0
       6: invokevirtual #148                // Method v:()I
       9: ifle          78
      12: aload_0
      13: iconst_0
      14: invokevirtual #530                // Method b:(Z)Landroid/view/View;
      17: astore        4
      19: aload_0
      20: iconst_0
      21: invokevirtual #532                // Method c:(Z)Landroid/view/View;
      24: astore        5
      26: aload         4
      28: ifnull        78
      31: aload         5
      33: ifnonnull     37
      36: return
      37: aload_0
      38: aload         4
      40: invokevirtual #582                // Method d:(Landroid/view/View;)I
      43: istore_2
      44: aload_0
      45: aload         5
      47: invokevirtual #582                // Method d:(Landroid/view/View;)I
      50: istore_3
      51: iload_2
      52: iload_3
      53: if_icmpge     67
      56: aload_1
      57: iload_2
      58: invokevirtual #704                // Method android/view/accessibility/AccessibilityEvent.setFromIndex:(I)V
      61: aload_1
      62: iload_3
      63: invokevirtual #707                // Method android/view/accessibility/AccessibilityEvent.setToIndex:(I)V
      66: return
      67: aload_1
      68: iload_3
      69: invokevirtual #704                // Method android/view/accessibility/AccessibilityEvent.setFromIndex:(I)V
      72: aload_1
      73: iload_2
      74: invokevirtual #707                // Method android/view/accessibility/AccessibilityEvent.setToIndex:(I)V
      77: return
      78: return

  public void a(java.lang.String);
    Code:
       0: aload_0
       1: getfield      #325                // Field A:Landroid/support/v7/widget/StaggeredGridLayoutManager$d;
       4: ifnonnull     12
       7: aload_0
       8: aload_1
       9: invokespecial #708                // Method android/support/v7/widget/RecyclerView$i.a:(Ljava/lang/String;)V
      12: return

  public void a(boolean);
    Code:
       0: aload_0
       1: aconst_null
       2: invokevirtual #620                // Method a:(Ljava/lang/String;)V
       5: aload_0
       6: getfield      #325                // Field A:Landroid/support/v7/widget/StaggeredGridLayoutManager$d;
       9: ifnull        31
      12: aload_0
      13: getfield      #325                // Field A:Landroid/support/v7/widget/StaggeredGridLayoutManager$d;
      16: getfield      #413                // Field android/support/v7/widget/StaggeredGridLayoutManager$d.h:Z
      19: iload_1
      20: if_icmpeq     31
      23: aload_0
      24: getfield      #325                // Field A:Landroid/support/v7/widget/StaggeredGridLayoutManager$d;
      27: iload_1
      28: putfield      #413                // Field android/support/v7/widget/StaggeredGridLayoutManager$d.h:Z
      31: aload_0
      32: iload_1
      33: putfield      #67                 // Field d:Z
      36: aload_0
      37: invokevirtual #566                // Method o:()V
      40: return

  public boolean a(android.support.v7.widget.RecyclerView$j);
    Code:
       0: aload_1
       1: instanceof    #11                 // class android/support/v7/widget/StaggeredGridLayoutManager$b
       4: ireturn

  public int b(int, android.support.v7.widget.RecyclerView$p, android.support.v7.widget.RecyclerView$u);
    Code:
       0: aload_0
       1: iload_1
       2: aload_2
       3: aload_3
       4: invokevirtual #552                // Method c:(ILandroid/support/v7/widget/RecyclerView$p;Landroid/support/v7/widget/RecyclerView$u;)I
       7: ireturn

  public int b(android.support.v7.widget.RecyclerView$p, android.support.v7.widget.RecyclerView$u);
    Code:
       0: aload_0
       1: getfield      #98                 // Field j:I
       4: iconst_1
       5: if_icmpne     13
       8: aload_0
       9: getfield      #65                 // Field i:I
      12: ireturn
      13: aload_0
      14: aload_1
      15: aload_2
      16: invokespecial #711                // Method android/support/v7/widget/RecyclerView$i.b:(Landroid/support/v7/widget/RecyclerView$p;Landroid/support/v7/widget/RecyclerView$u;)I
      19: ireturn

  android.view.View b(boolean);
    Code:
       0: aload_0
       1: getfield      #134                // Field b:Landroid/support/v7/widget/ba;
       4: invokevirtual #217                // Method android/support/v7/widget/ba.c:()I
       7: istore_3
       8: aload_0
       9: getfield      #134                // Field b:Landroid/support/v7/widget/ba;
      12: invokevirtual #215                // Method android/support/v7/widget/ba.d:()I
      15: istore        4
      17: aload_0
      18: invokevirtual #148                // Method v:()I
      21: istore        5
      23: aconst_null
      24: astore        7
      26: iconst_0
      27: istore_2
      28: iload_2
      29: iload         5
      31: if_icmpge     126
      34: aload_0
      35: iload_2
      36: invokevirtual #151                // Method h:(I)Landroid/view/View;
      39: astore        9
      41: aload_0
      42: getfield      #134                // Field b:Landroid/support/v7/widget/ba;
      45: aload         9
      47: invokevirtual #545                // Method android/support/v7/widget/ba.a:(Landroid/view/View;)I
      50: istore        6
      52: aload         7
      54: astore        8
      56: aload_0
      57: getfield      #134                // Field b:Landroid/support/v7/widget/ba;
      60: aload         9
      62: invokevirtual #312                // Method android/support/v7/widget/ba.b:(Landroid/view/View;)I
      65: iload_3
      66: if_icmple     115
      69: iload         6
      71: iload         4
      73: if_icmplt     83
      76: aload         7
      78: astore        8
      80: goto          115
      83: iload         6
      85: iload_3
      86: if_icmpge     112
      89: iload_1
      90: ifne          96
      93: aload         9
      95: areturn
      96: aload         7
      98: astore        8
     100: aload         7
     102: ifnonnull     115
     105: aload         9
     107: astore        8
     109: goto          115
     112: aload         9
     114: areturn
     115: iload_2
     116: iconst_1
     117: iadd
     118: istore_2
     119: aload         8
     121: astore        7
     123: goto          28
     126: aload         7
     128: areturn

  public void b(int);
    Code:
       0: iload_1
       1: ifeq          20
       4: iload_1
       5: iconst_1
       6: if_icmpeq     20
       9: new           #713                // class java/lang/IllegalArgumentException
      12: dup
      13: ldc_w         #715                // String invalid orientation.
      16: invokespecial #717                // Method java/lang/IllegalArgumentException."<init>":(Ljava/lang/String;)V
      19: athrow
      20: aload_0
      21: aconst_null
      22: invokevirtual #620                // Method a:(Ljava/lang/String;)V
      25: iload_1
      26: aload_0
      27: getfield      #98                 // Field j:I
      30: if_icmpne     34
      33: return
      34: aload_0
      35: iload_1
      36: putfield      #98                 // Field j:I
      39: aload_0
      40: getfield      #134                // Field b:Landroid/support/v7/widget/ba;
      43: astore_2
      44: aload_0
      45: aload_0
      46: getfield      #136                // Field c:Landroid/support/v7/widget/ba;
      49: putfield      #134                // Field b:Landroid/support/v7/widget/ba;
      52: aload_0
      53: aload_2
      54: putfield      #136                // Field c:Landroid/support/v7/widget/ba;
      57: aload_0
      58: invokevirtual #566                // Method o:()V
      61: return

  public void b(android.support.v7.widget.RecyclerView, int, int);
    Code:
       0: aload_0
       1: iload_2
       2: iload_3
       3: iconst_2
       4: invokespecial #686                // Method c:(III)V
       7: return

  public boolean b();
    Code:
       0: aload_0
       1: getfield      #325                // Field A:Landroid/support/v7/widget/StaggeredGridLayoutManager$d;
       4: ifnonnull     9
       7: iconst_1
       8: ireturn
       9: iconst_0
      10: ireturn

  boolean b(android.support.v7.widget.RecyclerView$u, android.support.v7.widget.StaggeredGridLayoutManager$a);
    Code:
       0: aload_1
       1: invokevirtual #385                // Method android/support/v7/widget/RecyclerView$u.a:()Z
       4: istore        6
       6: iconst_0
       7: istore        5
       9: iload         6
      11: ifne          393
      14: aload_0
      15: getfield      #71                 // Field f:I
      18: iconst_m1
      19: if_icmpne     24
      22: iconst_0
      23: ireturn
      24: aload_0
      25: getfield      #71                 // Field f:I
      28: iflt          382
      31: aload_0
      32: getfield      #71                 // Field f:I
      35: aload_1
      36: invokevirtual #329                // Method android/support/v7/widget/RecyclerView$u.e:()I
      39: if_icmplt     45
      42: goto          382
      45: aload_0
      46: getfield      #325                // Field A:Landroid/support/v7/widget/StaggeredGridLayoutManager$d;
      49: ifnull        93
      52: aload_0
      53: getfield      #325                // Field A:Landroid/support/v7/widget/StaggeredGridLayoutManager$d;
      56: getfield      #410                // Field android/support/v7/widget/StaggeredGridLayoutManager$d.a:I
      59: iconst_m1
      60: if_icmpeq     93
      63: aload_0
      64: getfield      #325                // Field A:Landroid/support/v7/widget/StaggeredGridLayoutManager$d;
      67: getfield      #352                // Field android/support/v7/widget/StaggeredGridLayoutManager$d.c:I
      70: iconst_1
      71: if_icmpge     77
      74: goto          93
      77: aload_2
      78: ldc           #72                 // int -2147483648
      80: putfield      #355                // Field android/support/v7/widget/StaggeredGridLayoutManager$a.b:I
      83: aload_2
      84: aload_0
      85: getfield      #71                 // Field f:I
      88: putfield      #370                // Field android/support/v7/widget/StaggeredGridLayoutManager$a.a:I
      91: iconst_1
      92: ireturn
      93: aload_0
      94: aload_0
      95: getfield      #71                 // Field f:I
      98: invokevirtual #617                // Method c:(I)Landroid/view/View;
     101: astore_1
     102: aload_1
     103: ifnull        322
     106: aload_0
     107: getfield      #69                 // Field e:Z
     110: ifeq          121
     113: aload_0
     114: invokevirtual #557                // Method K:()I
     117: istore_3
     118: goto          126
     121: aload_0
     122: invokevirtual #560                // Method L:()I
     125: istore_3
     126: aload_2
     127: iload_3
     128: putfield      #370                // Field android/support/v7/widget/StaggeredGridLayoutManager$a.a:I
     131: aload_0
     132: getfield      #74                 // Field g:I
     135: ldc           #72                 // int -2147483648
     137: if_icmpeq     206
     140: aload_2
     141: getfield      #341                // Field android/support/v7/widget/StaggeredGridLayoutManager$a.c:Z
     144: ifeq          180
     147: aload_0
     148: getfield      #134                // Field b:Landroid/support/v7/widget/ba;
     151: invokevirtual #215                // Method android/support/v7/widget/ba.d:()I
     154: aload_0
     155: getfield      #74                 // Field g:I
     158: isub
     159: istore_3
     160: aload_0
     161: getfield      #134                // Field b:Landroid/support/v7/widget/ba;
     164: aload_1
     165: invokevirtual #312                // Method android/support/v7/widget/ba.b:(Landroid/view/View;)I
     168: istore        4
     170: aload_2
     171: iload_3
     172: iload         4
     174: isub
     175: putfield      #355                // Field android/support/v7/widget/StaggeredGridLayoutManager$a.b:I
     178: iconst_1
     179: ireturn
     180: aload_0
     181: getfield      #134                // Field b:Landroid/support/v7/widget/ba;
     184: invokevirtual #217                // Method android/support/v7/widget/ba.c:()I
     187: aload_0
     188: getfield      #74                 // Field g:I
     191: iadd
     192: istore_3
     193: aload_0
     194: getfield      #134                // Field b:Landroid/support/v7/widget/ba;
     197: aload_1
     198: invokevirtual #545                // Method android/support/v7/widget/ba.a:(Landroid/view/View;)I
     201: istore        4
     203: goto          170
     206: aload_0
     207: getfield      #134                // Field b:Landroid/support/v7/widget/ba;
     210: aload_1
     211: invokevirtual #154                // Method android/support/v7/widget/ba.e:(Landroid/view/View;)I
     214: aload_0
     215: getfield      #134                // Field b:Landroid/support/v7/widget/ba;
     218: invokevirtual #176                // Method android/support/v7/widget/ba.f:()I
     221: if_icmple     257
     224: aload_2
     225: getfield      #341                // Field android/support/v7/widget/StaggeredGridLayoutManager$a.c:Z
     228: ifeq          242
     231: aload_0
     232: getfield      #134                // Field b:Landroid/support/v7/widget/ba;
     235: invokevirtual #215                // Method android/support/v7/widget/ba.d:()I
     238: istore_3
     239: goto          250
     242: aload_0
     243: getfield      #134                // Field b:Landroid/support/v7/widget/ba;
     246: invokevirtual #217                // Method android/support/v7/widget/ba.c:()I
     249: istore_3
     250: aload_2
     251: iload_3
     252: putfield      #355                // Field android/support/v7/widget/StaggeredGridLayoutManager$a.b:I
     255: iconst_1
     256: ireturn
     257: aload_0
     258: getfield      #134                // Field b:Landroid/support/v7/widget/ba;
     261: aload_1
     262: invokevirtual #545                // Method android/support/v7/widget/ba.a:(Landroid/view/View;)I
     265: aload_0
     266: getfield      #134                // Field b:Landroid/support/v7/widget/ba;
     269: invokevirtual #217                // Method android/support/v7/widget/ba.c:()I
     272: isub
     273: istore_3
     274: iload_3
     275: ifge          286
     278: aload_2
     279: iload_3
     280: ineg
     281: putfield      #355                // Field android/support/v7/widget/StaggeredGridLayoutManager$a.b:I
     284: iconst_1
     285: ireturn
     286: aload_0
     287: getfield      #134                // Field b:Landroid/support/v7/widget/ba;
     290: invokevirtual #215                // Method android/support/v7/widget/ba.d:()I
     293: aload_0
     294: getfield      #134                // Field b:Landroid/support/v7/widget/ba;
     297: aload_1
     298: invokevirtual #312                // Method android/support/v7/widget/ba.b:(Landroid/view/View;)I
     301: isub
     302: istore_3
     303: iload_3
     304: ifge          314
     307: aload_2
     308: iload_3
     309: putfield      #355                // Field android/support/v7/widget/StaggeredGridLayoutManager$a.b:I
     312: iconst_1
     313: ireturn
     314: aload_2
     315: ldc           #72                 // int -2147483648
     317: putfield      #355                // Field android/support/v7/widget/StaggeredGridLayoutManager$a.b:I
     320: iconst_1
     321: ireturn
     322: aload_2
     323: aload_0
     324: getfield      #71                 // Field f:I
     327: putfield      #370                // Field android/support/v7/widget/StaggeredGridLayoutManager$a.a:I
     330: aload_0
     331: getfield      #74                 // Field g:I
     334: ldc           #72                 // int -2147483648
     336: if_icmpne     367
     339: aload_0
     340: aload_2
     341: getfield      #370                // Field android/support/v7/widget/StaggeredGridLayoutManager$a.a:I
     344: invokespecial #719                // Method t:(I)I
     347: iconst_1
     348: if_icmpne     354
     351: iconst_1
     352: istore        5
     354: aload_2
     355: iload         5
     357: putfield      #341                // Field android/support/v7/widget/StaggeredGridLayoutManager$a.c:Z
     360: aload_2
     361: invokevirtual #682                // Method android/support/v7/widget/StaggeredGridLayoutManager$a.b:()V
     364: goto          375
     367: aload_2
     368: aload_0
     369: getfield      #74                 // Field g:I
     372: invokevirtual #720                // Method android/support/v7/widget/StaggeredGridLayoutManager$a.a:(I)V
     375: aload_2
     376: iconst_1
     377: putfield      #350                // Field android/support/v7/widget/StaggeredGridLayoutManager$a.d:Z
     380: iconst_1
     381: ireturn
     382: aload_0
     383: iconst_m1
     384: putfield      #71                 // Field f:I
     387: aload_0
     388: ldc           #72                 // int -2147483648
     390: putfield      #74                 // Field g:I
     393: iconst_0
     394: ireturn

  int c(int, android.support.v7.widget.RecyclerView$p, android.support.v7.widget.RecyclerView$u);
    Code:
       0: aload_0
       1: invokevirtual #148                // Method v:()I
       4: ifeq          96
       7: iload_1
       8: ifne          13
      11: iconst_0
      12: ireturn
      13: aload_0
      14: iload_1
      15: aload_3
      16: invokevirtual #630                // Method a:(ILandroid/support/v7/widget/RecyclerView$u;)V
      19: aload_0
      20: aload_2
      21: aload_0
      22: getfield      #106                // Field l:Landroid/support/v7/widget/au;
      25: aload_3
      26: invokespecial #377                // Method a:(Landroid/support/v7/widget/RecyclerView$p;Landroid/support/v7/widget/au;Landroid/support/v7/widget/RecyclerView$u;)I
      29: istore        4
      31: aload_0
      32: getfield      #106                // Field l:Landroid/support/v7/widget/au;
      35: getfield      #210                // Field android/support/v7/widget/au.b:I
      38: iload         4
      40: if_icmpge     46
      43: goto          60
      46: iload_1
      47: ifge          57
      50: iload         4
      52: ineg
      53: istore_1
      54: goto          60
      57: iload         4
      59: istore_1
      60: aload_0
      61: getfield      #134                // Field b:Landroid/support/v7/widget/ba;
      64: iload_1
      65: ineg
      66: invokevirtual #553                // Method android/support/v7/widget/ba.a:(I)V
      69: aload_0
      70: aload_0
      71: getfield      #69                 // Field e:Z
      74: putfield      #346                // Field o:Z
      77: aload_0
      78: getfield      #106                // Field l:Landroid/support/v7/widget/au;
      81: iconst_0
      82: putfield      #210                // Field android/support/v7/widget/au.b:I
      85: aload_0
      86: aload_2
      87: aload_0
      88: getfield      #106                // Field l:Landroid/support/v7/widget/au;
      91: invokespecial #288                // Method a:(Landroid/support/v7/widget/RecyclerView$p;Landroid/support/v7/widget/au;)V
      94: iload_1
      95: ireturn
      96: iconst_0
      97: ireturn

  public int c(android.support.v7.widget.RecyclerView$u);
    Code:
       0: aload_0
       1: aload_1
       2: invokespecial #722                // Method b:(Landroid/support/v7/widget/RecyclerView$u;)I
       5: ireturn

  android.view.View c(boolean);
    Code:
       0: aload_0
       1: getfield      #134                // Field b:Landroid/support/v7/widget/ba;
       4: invokevirtual #217                // Method android/support/v7/widget/ba.c:()I
       7: istore_3
       8: aload_0
       9: getfield      #134                // Field b:Landroid/support/v7/widget/ba;
      12: invokevirtual #215                // Method android/support/v7/widget/ba.d:()I
      15: istore        4
      17: aload_0
      18: invokevirtual #148                // Method v:()I
      21: iconst_1
      22: isub
      23: istore_2
      24: aconst_null
      25: astore        7
      27: iload_2
      28: iflt          128
      31: aload_0
      32: iload_2
      33: invokevirtual #151                // Method h:(I)Landroid/view/View;
      36: astore        9
      38: aload_0
      39: getfield      #134                // Field b:Landroid/support/v7/widget/ba;
      42: aload         9
      44: invokevirtual #545                // Method android/support/v7/widget/ba.a:(Landroid/view/View;)I
      47: istore        5
      49: aload_0
      50: getfield      #134                // Field b:Landroid/support/v7/widget/ba;
      53: aload         9
      55: invokevirtual #312                // Method android/support/v7/widget/ba.b:(Landroid/view/View;)I
      58: istore        6
      60: aload         7
      62: astore        8
      64: iload         6
      66: iload_3
      67: if_icmple     117
      70: iload         5
      72: iload         4
      74: if_icmplt     84
      77: aload         7
      79: astore        8
      81: goto          117
      84: iload         6
      86: iload         4
      88: if_icmple     114
      91: iload_1
      92: ifne          98
      95: aload         9
      97: areturn
      98: aload         7
     100: astore        8
     102: aload         7
     104: ifnonnull     117
     107: aload         9
     109: astore        8
     111: goto          117
     114: aload         9
     116: areturn
     117: iload_2
     118: iconst_1
     119: isub
     120: istore_2
     121: aload         8
     123: astore        7
     125: goto          27
     128: aload         7
     130: areturn

  public void c(android.support.v7.widget.RecyclerView$p, android.support.v7.widget.RecyclerView$u);
    Code:
       0: aload_0
       1: aload_1
       2: aload_2
       3: iconst_1
       4: invokespecial #395                // Method a:(Landroid/support/v7/widget/RecyclerView$p;Landroid/support/v7/widget/RecyclerView$u;Z)V
       7: return

  public boolean c();
    Code:
       0: aload_0
       1: getfield      #79                 // Field n:I
       4: ifeq          9
       7: iconst_1
       8: ireturn
       9: iconst_0
      10: ireturn

  public int d(android.support.v7.widget.RecyclerView$u);
    Code:
       0: aload_0
       1: aload_1
       2: invokespecial #722                // Method b:(Landroid/support/v7/widget/RecyclerView$u;)I
       5: ireturn

  public android.os.Parcelable d();
    Code:
       0: aload_0
       1: getfield      #325                // Field A:Landroid/support/v7/widget/StaggeredGridLayoutManager$d;
       4: ifnull        19
       7: new           #21                 // class android/support/v7/widget/StaggeredGridLayoutManager$d
      10: dup
      11: aload_0
      12: getfield      #325                // Field A:Landroid/support/v7/widget/StaggeredGridLayoutManager$d;
      15: invokespecial #727                // Method android/support/v7/widget/StaggeredGridLayoutManager$d."<init>":(Landroid/support/v7/widget/StaggeredGridLayoutManager$d;)V
      18: areturn
      19: new           #21                 // class android/support/v7/widget/StaggeredGridLayoutManager$d
      22: dup
      23: invokespecial #728                // Method android/support/v7/widget/StaggeredGridLayoutManager$d."<init>":()V
      26: astore        4
      28: aload         4
      30: aload_0
      31: getfield      #67                 // Field d:Z
      34: putfield      #413                // Field android/support/v7/widget/StaggeredGridLayoutManager$d.h:Z
      37: aload         4
      39: aload_0
      40: getfield      #346                // Field o:Z
      43: putfield      #407                // Field android/support/v7/widget/StaggeredGridLayoutManager$d.i:Z
      46: aload         4
      48: aload_0
      49: getfield      #348                // Field z:Z
      52: putfield      #412                // Field android/support/v7/widget/StaggeredGridLayoutManager$d.j:Z
      55: aload_0
      56: getfield      #77                 // Field h:Landroid/support/v7/widget/StaggeredGridLayoutManager$c;
      59: astore        5
      61: iconst_0
      62: istore_2
      63: aload         5
      65: ifnull        116
      68: aload_0
      69: getfield      #77                 // Field h:Landroid/support/v7/widget/StaggeredGridLayoutManager$c;
      72: getfield      #417                // Field android/support/v7/widget/StaggeredGridLayoutManager$c.a:[I
      75: ifnull        116
      78: aload         4
      80: aload_0
      81: getfield      #77                 // Field h:Landroid/support/v7/widget/StaggeredGridLayoutManager$c;
      84: getfield      #417                // Field android/support/v7/widget/StaggeredGridLayoutManager$c.a:[I
      87: putfield      #415                // Field android/support/v7/widget/StaggeredGridLayoutManager$d.f:[I
      90: aload         4
      92: aload         4
      94: getfield      #415                // Field android/support/v7/widget/StaggeredGridLayoutManager$d.f:[I
      97: arraylength
      98: putfield      #414                // Field android/support/v7/widget/StaggeredGridLayoutManager$d.e:I
     101: aload         4
     103: aload_0
     104: getfield      #77                 // Field h:Landroid/support/v7/widget/StaggeredGridLayoutManager$c;
     107: getfield      #422                // Field android/support/v7/widget/StaggeredGridLayoutManager$c.b:Ljava/util/List;
     110: putfield      #420                // Field android/support/v7/widget/StaggeredGridLayoutManager$d.g:Ljava/util/List;
     113: goto          122
     116: aload         4
     118: iconst_0
     119: putfield      #414                // Field android/support/v7/widget/StaggeredGridLayoutManager$d.e:I
     122: aload_0
     123: invokevirtual #148                // Method v:()I
     126: ifle          280
     129: aload_0
     130: getfield      #346                // Field o:Z
     133: ifeq          144
     136: aload_0
     137: invokevirtual #557                // Method K:()I
     140: istore_1
     141: goto          149
     144: aload_0
     145: invokevirtual #560                // Method L:()I
     148: istore_1
     149: aload         4
     151: iload_1
     152: putfield      #410                // Field android/support/v7/widget/StaggeredGridLayoutManager$d.a:I
     155: aload         4
     157: aload_0
     158: invokevirtual #729                // Method k:()I
     161: putfield      #409                // Field android/support/v7/widget/StaggeredGridLayoutManager$d.b:I
     164: aload         4
     166: aload_0
     167: getfield      #65                 // Field i:I
     170: putfield      #352                // Field android/support/v7/widget/StaggeredGridLayoutManager$d.c:I
     173: aload         4
     175: aload_0
     176: getfield      #65                 // Field i:I
     179: newarray       int
     181: putfield      #406                // Field android/support/v7/widget/StaggeredGridLayoutManager$d.d:[I
     184: iload_2
     185: aload_0
     186: getfield      #65                 // Field i:I
     189: if_icmpge     298
     192: aload_0
     193: getfield      #346                // Field o:Z
     196: ifeq          234
     199: aload_0
     200: getfield      #232                // Field a:[Landroid/support/v7/widget/StaggeredGridLayoutManager$e;
     203: iload_2
     204: aaload
     205: ldc           #72                 // int -2147483648
     207: invokevirtual #252                // Method android/support/v7/widget/StaggeredGridLayoutManager$e.b:(I)I
     210: istore_3
     211: iload_3
     212: istore_1
     213: iload_3
     214: ldc           #72                 // int -2147483648
     216: if_icmpeq     265
     219: aload_0
     220: getfield      #134                // Field b:Landroid/support/v7/widget/ba;
     223: invokevirtual #215                // Method android/support/v7/widget/ba.d:()I
     226: istore_1
     227: iload_3
     228: iload_1
     229: isub
     230: istore_1
     231: goto          265
     234: aload_0
     235: getfield      #232                // Field a:[Landroid/support/v7/widget/StaggeredGridLayoutManager$e;
     238: iload_2
     239: aaload
     240: ldc           #72                 // int -2147483648
     242: invokevirtual #265                // Method android/support/v7/widget/StaggeredGridLayoutManager$e.a:(I)I
     245: istore_3
     246: iload_3
     247: istore_1
     248: iload_3
     249: ldc           #72                 // int -2147483648
     251: if_icmpeq     265
     254: aload_0
     255: getfield      #134                // Field b:Landroid/support/v7/widget/ba;
     258: invokevirtual #217                // Method android/support/v7/widget/ba.c:()I
     261: istore_1
     262: goto          227
     265: aload         4
     267: getfield      #406                // Field android/support/v7/widget/StaggeredGridLayoutManager$d.d:[I
     270: iload_2
     271: iload_1
     272: iastore
     273: iload_2
     274: iconst_1
     275: iadd
     276: istore_2
     277: goto          184
     280: aload         4
     282: iconst_m1
     283: putfield      #410                // Field android/support/v7/widget/StaggeredGridLayoutManager$d.a:I
     286: aload         4
     288: iconst_m1
     289: putfield      #409                // Field android/support/v7/widget/StaggeredGridLayoutManager$d.b:I
     292: aload         4
     294: iconst_0
     295: putfield      #352                // Field android/support/v7/widget/StaggeredGridLayoutManager$d.c:I
     298: aload         4
     300: areturn

  public void d(int);
    Code:
       0: aload_0
       1: getfield      #325                // Field A:Landroid/support/v7/widget/StaggeredGridLayoutManager$d;
       4: ifnull        25
       7: aload_0
       8: getfield      #325                // Field A:Landroid/support/v7/widget/StaggeredGridLayoutManager$d;
      11: getfield      #410                // Field android/support/v7/widget/StaggeredGridLayoutManager$d.a:I
      14: iload_1
      15: if_icmpeq     25
      18: aload_0
      19: getfield      #325                // Field A:Landroid/support/v7/widget/StaggeredGridLayoutManager$d;
      22: invokevirtual #730                // Method android/support/v7/widget/StaggeredGridLayoutManager$d.b:()V
      25: aload_0
      26: iload_1
      27: putfield      #71                 // Field f:I
      30: aload_0
      31: ldc           #72                 // int -2147483648
      33: putfield      #74                 // Field g:I
      36: aload_0
      37: invokevirtual #566                // Method o:()V
      40: return

  public int e(android.support.v7.widget.RecyclerView$u);
    Code:
       0: aload_0
       1: aload_1
       2: invokespecial #732                // Method i:(Landroid/support/v7/widget/RecyclerView$u;)I
       5: ireturn

  void e(int);
    Code:
       0: aload_0
       1: iload_1
       2: aload_0
       3: getfield      #65                 // Field i:I
       6: idiv
       7: putfield      #170                // Field k:I
      10: aload_0
      11: iload_1
      12: aload_0
      13: getfield      #136                // Field c:Landroid/support/v7/widget/ba;
      16: invokevirtual #144                // Method android/support/v7/widget/ba.h:()I
      19: invokestatic  #526                // Method android/view/View$MeasureSpec.makeMeasureSpec:(II)I
      22: putfield      #475                // Field B:I
      25: return

  public boolean e();
    Code:
       0: aload_0
       1: getfield      #98                 // Field j:I
       4: ifne          9
       7: iconst_1
       8: ireturn
       9: iconst_0
      10: ireturn

  public int f(android.support.v7.widget.RecyclerView$u);
    Code:
       0: aload_0
       1: aload_1
       2: invokespecial #732                // Method i:(Landroid/support/v7/widget/RecyclerView$u;)I
       5: ireturn

  public boolean f();
    Code:
       0: aload_0
       1: getfield      #98                 // Field j:I
       4: iconst_1
       5: if_icmpne     10
       8: iconst_1
       9: ireturn
      10: iconst_0
      11: ireturn

  public int g(android.support.v7.widget.RecyclerView$u);
    Code:
       0: aload_0
       1: aload_1
       2: invokespecial #734                // Method j:(Landroid/support/v7/widget/RecyclerView$u;)I
       5: ireturn

  boolean g();
    Code:
       0: aload_0
       1: invokevirtual #148                // Method v:()I
       4: ifeq          204
       7: aload_0
       8: getfield      #79                 // Field n:I
      11: ifeq          204
      14: aload_0
      15: invokevirtual #736                // Method q:()Z
      18: ifne          23
      21: iconst_0
      22: ireturn
      23: aload_0
      24: getfield      #69                 // Field e:Z
      27: ifeq          43
      30: aload_0
      31: invokevirtual #557                // Method K:()I
      34: istore_1
      35: aload_0
      36: invokevirtual #560                // Method L:()I
      39: istore_2
      40: goto          53
      43: aload_0
      44: invokevirtual #560                // Method L:()I
      47: istore_1
      48: aload_0
      49: invokevirtual #557                // Method K:()I
      52: istore_2
      53: iload_1
      54: ifne          81
      57: aload_0
      58: invokevirtual #388                // Method h:()Landroid/view/View;
      61: ifnull        81
      64: aload_0
      65: getfield      #77                 // Field h:Landroid/support/v7/widget/StaggeredGridLayoutManager$c;
      68: invokevirtual #349                // Method android/support/v7/widget/StaggeredGridLayoutManager$c.a:()V
      71: aload_0
      72: invokevirtual #738                // Method I:()V
      75: aload_0
      76: invokevirtual #566                // Method o:()V
      79: iconst_1
      80: ireturn
      81: aload_0
      82: getfield      #91                 // Field E:Z
      85: ifne          90
      88: iconst_0
      89: ireturn
      90: aload_0
      91: getfield      #69                 // Field e:Z
      94: ifeq          102
      97: iconst_m1
      98: istore_3
      99: goto          104
     102: iconst_1
     103: istore_3
     104: aload_0
     105: getfield      #77                 // Field h:Landroid/support/v7/widget/StaggeredGridLayoutManager$c;
     108: astore        4
     110: iload_2
     111: iconst_1
     112: iadd
     113: istore_2
     114: aload         4
     116: iload_1
     117: iload_2
     118: iload_3
     119: iconst_1
     120: invokevirtual #741                // Method android/support/v7/widget/StaggeredGridLayoutManager$c.a:(IIIZ)Landroid/support/v7/widget/StaggeredGridLayoutManager$c$a;
     123: astore        4
     125: aload         4
     127: ifnonnull     146
     130: aload_0
     131: iconst_0
     132: putfield      #91                 // Field E:Z
     135: aload_0
     136: getfield      #77                 // Field h:Landroid/support/v7/widget/StaggeredGridLayoutManager$c;
     139: iload_2
     140: invokevirtual #742                // Method android/support/v7/widget/StaggeredGridLayoutManager$c.a:(I)I
     143: pop
     144: iconst_0
     145: ireturn
     146: aload_0
     147: getfield      #77                 // Field h:Landroid/support/v7/widget/StaggeredGridLayoutManager$c;
     150: iload_1
     151: aload         4
     153: getfield      #257                // Field android/support/v7/widget/StaggeredGridLayoutManager$c$a.a:I
     156: iload_3
     157: iconst_m1
     158: imul
     159: iconst_1
     160: invokevirtual #741                // Method android/support/v7/widget/StaggeredGridLayoutManager$c.a:(IIIZ)Landroid/support/v7/widget/StaggeredGridLayoutManager$c$a;
     163: astore        5
     165: aload         5
     167: ifnonnull     186
     170: aload_0
     171: getfield      #77                 // Field h:Landroid/support/v7/widget/StaggeredGridLayoutManager$c;
     174: aload         4
     176: getfield      #257                // Field android/support/v7/widget/StaggeredGridLayoutManager$c$a.a:I
     179: invokevirtual #742                // Method android/support/v7/widget/StaggeredGridLayoutManager$c.a:(I)I
     182: pop
     183: goto          71
     186: aload_0
     187: getfield      #77                 // Field h:Landroid/support/v7/widget/StaggeredGridLayoutManager$c;
     190: aload         5
     192: getfield      #257                // Field android/support/v7/widget/StaggeredGridLayoutManager$c$a.a:I
     195: iconst_1
     196: iadd
     197: invokevirtual #742                // Method android/support/v7/widget/StaggeredGridLayoutManager$c.a:(I)I
     200: pop
     201: goto          71
     204: iconst_0
     205: ireturn

  public int h(android.support.v7.widget.RecyclerView$u);
    Code:
       0: aload_0
       1: aload_1
       2: invokespecial #734                // Method j:(Landroid/support/v7/widget/RecyclerView$u;)I
       5: ireturn

  android.view.View h();
    Code:
       0: aload_0
       1: invokevirtual #148                // Method v:()I
       4: iconst_1
       5: isub
       6: istore_1
       7: new           #200                // class java/util/BitSet
      10: dup
      11: aload_0
      12: getfield      #65                 // Field i:I
      15: invokespecial #624                // Method java/util/BitSet."<init>":(I)V
      18: astore        7
      20: aload         7
      22: iconst_0
      23: aload_0
      24: getfield      #65                 // Field i:I
      27: iconst_1
      28: invokevirtual #204                // Method java/util/BitSet.set:(IIZ)V
      31: aload_0
      32: getfield      #98                 // Field j:I
      35: istore_2
      36: iconst_m1
      37: istore        5
      39: iload_2
      40: iconst_1
      41: if_icmpne     56
      44: aload_0
      45: invokevirtual #140                // Method j:()Z
      48: ifeq          56
      51: iconst_1
      52: istore_2
      53: goto          58
      56: iconst_m1
      57: istore_2
      58: aload_0
      59: getfield      #69                 // Field e:Z
      62: ifeq          70
      65: iconst_m1
      66: istore_3
      67: goto          76
      70: iload_1
      71: iconst_1
      72: iadd
      73: istore_3
      74: iconst_0
      75: istore_1
      76: iload_1
      77: istore        4
      79: iload_1
      80: iload_3
      81: if_icmpge     90
      84: iconst_1
      85: istore        5
      87: iload_1
      88: istore        4
      90: iload         4
      92: iload_3
      93: if_icmpeq     349
      96: aload_0
      97: iload         4
      99: invokevirtual #151                // Method h:(I)Landroid/view/View;
     102: astore        8
     104: aload         8
     106: invokevirtual #160                // Method android/view/View.getLayoutParams:()Landroid/view/ViewGroup$LayoutParams;
     109: checkcast     #11                 // class android/support/v7/widget/StaggeredGridLayoutManager$b
     112: astore        9
     114: aload         7
     116: aload         9
     118: getfield      #187                // Field android/support/v7/widget/StaggeredGridLayoutManager$b.a:Landroid/support/v7/widget/StaggeredGridLayoutManager$e;
     121: getfield      #189                // Field android/support/v7/widget/StaggeredGridLayoutManager$e.e:I
     124: invokevirtual #744                // Method java/util/BitSet.get:(I)Z
     127: ifeq          158
     130: aload_0
     131: aload         9
     133: getfield      #187                // Field android/support/v7/widget/StaggeredGridLayoutManager$b.a:Landroid/support/v7/widget/StaggeredGridLayoutManager$e;
     136: invokespecial #746                // Method a:(Landroid/support/v7/widget/StaggeredGridLayoutManager$e;)Z
     139: ifeq          145
     142: aload         8
     144: areturn
     145: aload         7
     147: aload         9
     149: getfield      #187                // Field android/support/v7/widget/StaggeredGridLayoutManager$b.a:Landroid/support/v7/widget/StaggeredGridLayoutManager$e;
     152: getfield      #189                // Field android/support/v7/widget/StaggeredGridLayoutManager$e.e:I
     155: invokevirtual #748                // Method java/util/BitSet.clear:(I)V
     158: aload         9
     160: getfield      #184                // Field android/support/v7/widget/StaggeredGridLayoutManager$b.b:Z
     163: ifeq          169
     166: goto          339
     169: iload         4
     171: iload         5
     173: iadd
     174: istore_1
     175: iload_1
     176: iload_3
     177: if_icmpeq     339
     180: aload_0
     181: iload_1
     182: invokevirtual #151                // Method h:(I)Landroid/view/View;
     185: astore        10
     187: aload_0
     188: getfield      #69                 // Field e:Z
     191: ifeq          233
     194: aload_0
     195: getfield      #134                // Field b:Landroid/support/v7/widget/ba;
     198: aload         8
     200: invokevirtual #312                // Method android/support/v7/widget/ba.b:(Landroid/view/View;)I
     203: istore_1
     204: aload_0
     205: getfield      #134                // Field b:Landroid/support/v7/widget/ba;
     208: aload         10
     210: invokevirtual #312                // Method android/support/v7/widget/ba.b:(Landroid/view/View;)I
     213: istore        6
     215: iload_1
     216: iload         6
     218: if_icmpge     224
     221: aload         8
     223: areturn
     224: iload_1
     225: iload         6
     227: if_icmpne     274
     230: goto          269
     233: aload_0
     234: getfield      #134                // Field b:Landroid/support/v7/widget/ba;
     237: aload         8
     239: invokevirtual #545                // Method android/support/v7/widget/ba.a:(Landroid/view/View;)I
     242: istore_1
     243: aload_0
     244: getfield      #134                // Field b:Landroid/support/v7/widget/ba;
     247: aload         10
     249: invokevirtual #545                // Method android/support/v7/widget/ba.a:(Landroid/view/View;)I
     252: istore        6
     254: iload_1
     255: iload         6
     257: if_icmple     263
     260: aload         8
     262: areturn
     263: iload_1
     264: iload         6
     266: if_icmpne     274
     269: iconst_1
     270: istore_1
     271: goto          276
     274: iconst_0
     275: istore_1
     276: iload_1
     277: ifeq          339
     280: aload         10
     282: invokevirtual #160                // Method android/view/View.getLayoutParams:()Landroid/view/ViewGroup$LayoutParams;
     285: checkcast     #11                 // class android/support/v7/widget/StaggeredGridLayoutManager$b
     288: astore        10
     290: aload         9
     292: getfield      #187                // Field android/support/v7/widget/StaggeredGridLayoutManager$b.a:Landroid/support/v7/widget/StaggeredGridLayoutManager$e;
     295: getfield      #189                // Field android/support/v7/widget/StaggeredGridLayoutManager$e.e:I
     298: aload         10
     300: getfield      #187                // Field android/support/v7/widget/StaggeredGridLayoutManager$b.a:Landroid/support/v7/widget/StaggeredGridLayoutManager$e;
     303: getfield      #189                // Field android/support/v7/widget/StaggeredGridLayoutManager$e.e:I
     306: isub
     307: ifge          315
     310: iconst_1
     311: istore_1
     312: goto          317
     315: iconst_0
     316: istore_1
     317: iload_2
     318: ifge          327
     321: iconst_1
     322: istore        6
     324: goto          330
     327: iconst_0
     328: istore        6
     330: iload_1
     331: iload         6
     333: if_icmpeq     339
     336: aload         8
     338: areturn
     339: iload         4
     341: iload         5
     343: iadd
     344: istore        4
     346: goto          90
     349: aconst_null
     350: areturn

  public void i();
    Code:
       0: aload_0
       1: getfield      #77                 // Field h:Landroid/support/v7/widget/StaggeredGridLayoutManager$c;
       4: invokevirtual #349                // Method android/support/v7/widget/StaggeredGridLayoutManager$c.a:()V
       7: aload_0
       8: invokevirtual #566                // Method o:()V
      11: return

  public void i(int);
    Code:
       0: aload_0
       1: iload_1
       2: invokespecial #750                // Method android/support/v7/widget/RecyclerView$i.i:(I)V
       5: iconst_0
       6: istore_2
       7: iload_2
       8: aload_0
       9: getfield      #65                 // Field i:I
      12: if_icmpge     32
      15: aload_0
      16: getfield      #232                // Field a:[Landroid/support/v7/widget/StaggeredGridLayoutManager$e;
      19: iload_2
      20: aaload
      21: iload_1
      22: invokevirtual #752                // Method android/support/v7/widget/StaggeredGridLayoutManager$e.d:(I)V
      25: iload_2
      26: iconst_1
      27: iadd
      28: istore_2
      29: goto          7
      32: return

  public void j(int);
    Code:
       0: aload_0
       1: iload_1
       2: invokespecial #754                // Method android/support/v7/widget/RecyclerView$i.j:(I)V
       5: iconst_0
       6: istore_2
       7: iload_2
       8: aload_0
       9: getfield      #65                 // Field i:I
      12: if_icmpge     32
      15: aload_0
      16: getfield      #232                // Field a:[Landroid/support/v7/widget/StaggeredGridLayoutManager$e;
      19: iload_2
      20: aaload
      21: iload_1
      22: invokevirtual #752                // Method android/support/v7/widget/StaggeredGridLayoutManager$e.d:(I)V
      25: iload_2
      26: iconst_1
      27: iadd
      28: istore_2
      29: goto          7
      32: return

  boolean j();
    Code:
       0: aload_0
       1: invokevirtual #756                // Method t:()I
       4: iconst_1
       5: if_icmpne     10
       8: iconst_1
       9: ireturn
      10: iconst_0
      11: ireturn

  int k();
    Code:
       0: aload_0
       1: getfield      #69                 // Field e:Z
       4: ifeq          16
       7: aload_0
       8: iconst_1
       9: invokevirtual #532                // Method c:(Z)Landroid/view/View;
      12: astore_1
      13: goto          22
      16: aload_0
      17: iconst_1
      18: invokevirtual #530                // Method b:(Z)Landroid/view/View;
      21: astore_1
      22: aload_1
      23: ifnonnull     28
      26: iconst_m1
      27: ireturn
      28: aload_0
      29: aload_1
      30: invokevirtual #582                // Method d:(Landroid/view/View;)I
      33: ireturn

  public void k(int);
    Code:
       0: iload_1
       1: ifne          9
       4: aload_0
       5: invokevirtual #393                // Method g:()Z
       8: pop
       9: return

  boolean m();
    Code:
       0: aload_0
       1: getfield      #232                // Field a:[Landroid/support/v7/widget/StaggeredGridLayoutManager$e;
       4: iconst_0
       5: aaload
       6: ldc           #72                 // int -2147483648
       8: invokevirtual #252                // Method android/support/v7/widget/StaggeredGridLayoutManager$e.b:(I)I
      11: istore_2
      12: iconst_1
      13: istore_1
      14: iload_1
      15: aload_0
      16: getfield      #65                 // Field i:I
      19: if_icmpge     46
      22: aload_0
      23: getfield      #232                // Field a:[Landroid/support/v7/widget/StaggeredGridLayoutManager$e;
      26: iload_1
      27: aaload
      28: ldc           #72                 // int -2147483648
      30: invokevirtual #252                // Method android/support/v7/widget/StaggeredGridLayoutManager$e.b:(I)I
      33: iload_2
      34: if_icmpeq     39
      37: iconst_0
      38: ireturn
      39: iload_1
      40: iconst_1
      41: iadd
      42: istore_1
      43: goto          14
      46: iconst_1
      47: ireturn

  boolean n();
    Code:
       0: aload_0
       1: getfield      #232                // Field a:[Landroid/support/v7/widget/StaggeredGridLayoutManager$e;
       4: iconst_0
       5: aaload
       6: ldc           #72                 // int -2147483648
       8: invokevirtual #265                // Method android/support/v7/widget/StaggeredGridLayoutManager$e.a:(I)I
      11: istore_2
      12: iconst_1
      13: istore_1
      14: iload_1
      15: aload_0
      16: getfield      #65                 // Field i:I
      19: if_icmpge     46
      22: aload_0
      23: getfield      #232                // Field a:[Landroid/support/v7/widget/StaggeredGridLayoutManager$e;
      26: iload_1
      27: aaload
      28: ldc           #72                 // int -2147483648
      30: invokevirtual #265                // Method android/support/v7/widget/StaggeredGridLayoutManager$e.a:(I)I
      33: iload_2
      34: if_icmpeq     39
      37: iconst_0
      38: ireturn
      39: iload_1
      40: iconst_1
      41: iadd
      42: istore_1
      43: goto          14
      46: iconst_1
      47: ireturn
}
