class android.support.v7.widget.Toolbar$3 implements android.view.View$OnClickListener {
  final android.support.v7.widget.Toolbar a;

  android.support.v7.widget.Toolbar$3(android.support.v7.widget.Toolbar);
    Code:
       0: aload_0
       1: aload_1
       2: putfield      #17                 // Field a:Landroid/support/v7/widget/Toolbar;
       5: aload_0
       6: invokespecial #19                 // Method java/lang/Object."<init>":()V
       9: return

  public void onClick(android.view.View);
    Code:
       0: aload_0
       1: getfield      #17                 // Field a:Landroid/support/v7/widget/Toolbar;
       4: invokevirtual #25                 // Method android/support/v7/widget/Toolbar.h:()V
       7: return
}
