public class android.support.v7.widget.Toolbar extends android.view.ViewGroup {
  android.widget.ImageButton a;

  android.view.View b;

  int c;

  android.support.v7.widget.Toolbar$c d;

  public android.support.v7.widget.Toolbar(android.content.Context);
    Code:
       0: aload_0
       1: aload_1
       2: aconst_null
       3: invokespecial #87                 // Method "<init>":(Landroid/content/Context;Landroid/util/AttributeSet;)V
       6: return

  public android.support.v7.widget.Toolbar(android.content.Context, android.util.AttributeSet);
    Code:
       0: aload_0
       1: aload_1
       2: aload_2
       3: getstatic     #93                 // Field android/support/v7/a/a$a.toolbarStyle:I
       6: invokespecial #96                 // Method "<init>":(Landroid/content/Context;Landroid/util/AttributeSet;I)V
       9: return

  public android.support.v7.widget.Toolbar(android.content.Context, android.util.AttributeSet, int);
    Code:
       0: aload_0
       1: aload_1
       2: aload_2
       3: iload_3
       4: invokespecial #97                 // Method android/view/ViewGroup."<init>":(Landroid/content/Context;Landroid/util/AttributeSet;I)V
       7: aload_0
       8: ldc           #98                 // int 8388627
      10: putfield      #100                // Field x:I
      13: aload_0
      14: new           #102                // class java/util/ArrayList
      17: dup
      18: invokespecial #105                // Method java/util/ArrayList."<init>":()V
      21: putfield      #107                // Field E:Ljava/util/ArrayList;
      24: aload_0
      25: new           #102                // class java/util/ArrayList
      28: dup
      29: invokespecial #105                // Method java/util/ArrayList."<init>":()V
      32: putfield      #109                // Field F:Ljava/util/ArrayList;
      35: aload_0
      36: iconst_2
      37: newarray       int
      39: putfield      #111                // Field G:[I
      42: aload_0
      43: new           #6                  // class android/support/v7/widget/Toolbar$1
      46: dup
      47: aload_0
      48: invokespecial #114                // Method android/support/v7/widget/Toolbar$1."<init>":(Landroid/support/v7/widget/Toolbar;)V
      51: putfield      #116                // Field H:Landroid/support/v7/widget/ActionMenuView$e;
      54: aload_0
      55: new           #8                  // class android/support/v7/widget/Toolbar$2
      58: dup
      59: aload_0
      60: invokespecial #117                // Method android/support/v7/widget/Toolbar$2."<init>":(Landroid/support/v7/widget/Toolbar;)V
      63: putfield      #119                // Field O:Ljava/lang/Runnable;
      66: aload_0
      67: invokevirtual #123                // Method getContext:()Landroid/content/Context;
      70: aload_2
      71: getstatic     #128                // Field android/support/v7/a/a$j.Toolbar:[I
      74: iload_3
      75: iconst_0
      76: invokestatic  #133                // Method android/support/v7/widget/bp.a:(Landroid/content/Context;Landroid/util/AttributeSet;[III)Landroid/support/v7/widget/bp;
      79: astore_1
      80: aload_0
      81: aload_1
      82: getstatic     #136                // Field android/support/v7/a/a$j.Toolbar_titleTextAppearance:I
      85: iconst_0
      86: invokevirtual #139                // Method android/support/v7/widget/bp.g:(II)I
      89: putfield      #141                // Field n:I
      92: aload_0
      93: aload_1
      94: getstatic     #144                // Field android/support/v7/a/a$j.Toolbar_subtitleTextAppearance:I
      97: iconst_0
      98: invokevirtual #139                // Method android/support/v7/widget/bp.g:(II)I
     101: putfield      #146                // Field o:I
     104: aload_0
     105: aload_1
     106: getstatic     #149                // Field android/support/v7/a/a$j.Toolbar_android_gravity:I
     109: aload_0
     110: getfield      #100                // Field x:I
     113: invokevirtual #151                // Method android/support/v7/widget/bp.c:(II)I
     116: putfield      #100                // Field x:I
     119: aload_0
     120: aload_1
     121: getstatic     #154                // Field android/support/v7/a/a$j.Toolbar_buttonGravity:I
     124: bipush        48
     126: invokevirtual #151                // Method android/support/v7/widget/bp.c:(II)I
     129: putfield      #156                // Field c:I
     132: aload_1
     133: getstatic     #159                // Field android/support/v7/a/a$j.Toolbar_titleMargin:I
     136: iconst_0
     137: invokevirtual #161                // Method android/support/v7/widget/bp.d:(II)I
     140: istore        4
     142: iload         4
     144: istore_3
     145: aload_1
     146: getstatic     #164                // Field android/support/v7/a/a$j.Toolbar_titleMargins:I
     149: invokevirtual #167                // Method android/support/v7/widget/bp.g:(I)Z
     152: ifeq          165
     155: aload_1
     156: getstatic     #164                // Field android/support/v7/a/a$j.Toolbar_titleMargins:I
     159: iload         4
     161: invokevirtual #161                // Method android/support/v7/widget/bp.d:(II)I
     164: istore_3
     165: aload_0
     166: iload_3
     167: putfield      #169                // Field t:I
     170: aload_0
     171: iload_3
     172: putfield      #171                // Field s:I
     175: aload_0
     176: iload_3
     177: putfield      #173                // Field r:I
     180: aload_0
     181: iload_3
     182: putfield      #175                // Field q:I
     185: aload_1
     186: getstatic     #178                // Field android/support/v7/a/a$j.Toolbar_titleMarginStart:I
     189: iconst_m1
     190: invokevirtual #161                // Method android/support/v7/widget/bp.d:(II)I
     193: istore_3
     194: iload_3
     195: iflt          203
     198: aload_0
     199: iload_3
     200: putfield      #175                // Field q:I
     203: aload_1
     204: getstatic     #181                // Field android/support/v7/a/a$j.Toolbar_titleMarginEnd:I
     207: iconst_m1
     208: invokevirtual #161                // Method android/support/v7/widget/bp.d:(II)I
     211: istore_3
     212: iload_3
     213: iflt          221
     216: aload_0
     217: iload_3
     218: putfield      #173                // Field r:I
     221: aload_1
     222: getstatic     #184                // Field android/support/v7/a/a$j.Toolbar_titleMarginTop:I
     225: iconst_m1
     226: invokevirtual #161                // Method android/support/v7/widget/bp.d:(II)I
     229: istore_3
     230: iload_3
     231: iflt          239
     234: aload_0
     235: iload_3
     236: putfield      #171                // Field s:I
     239: aload_1
     240: getstatic     #187                // Field android/support/v7/a/a$j.Toolbar_titleMarginBottom:I
     243: iconst_m1
     244: invokevirtual #161                // Method android/support/v7/widget/bp.d:(II)I
     247: istore_3
     248: iload_3
     249: iflt          257
     252: aload_0
     253: iload_3
     254: putfield      #169                // Field t:I
     257: aload_0
     258: aload_1
     259: getstatic     #190                // Field android/support/v7/a/a$j.Toolbar_maxButtonHeight:I
     262: iconst_m1
     263: invokevirtual #192                // Method android/support/v7/widget/bp.e:(II)I
     266: putfield      #194                // Field p:I
     269: aload_1
     270: getstatic     #197                // Field android/support/v7/a/a$j.Toolbar_contentInsetStart:I
     273: ldc           #198                // int -2147483648
     275: invokevirtual #161                // Method android/support/v7/widget/bp.d:(II)I
     278: istore_3
     279: aload_1
     280: getstatic     #201                // Field android/support/v7/a/a$j.Toolbar_contentInsetEnd:I
     283: ldc           #198                // int -2147483648
     285: invokevirtual #161                // Method android/support/v7/widget/bp.d:(II)I
     288: istore        4
     290: aload_1
     291: getstatic     #204                // Field android/support/v7/a/a$j.Toolbar_contentInsetLeft:I
     294: iconst_0
     295: invokevirtual #192                // Method android/support/v7/widget/bp.e:(II)I
     298: istore        5
     300: aload_1
     301: getstatic     #207                // Field android/support/v7/a/a$j.Toolbar_contentInsetRight:I
     304: iconst_0
     305: invokevirtual #192                // Method android/support/v7/widget/bp.e:(II)I
     308: istore        6
     310: aload_0
     311: invokespecial #209                // Method s:()V
     314: aload_0
     315: getfield      #211                // Field u:Landroid/support/v7/widget/bf;
     318: iload         5
     320: iload         6
     322: invokevirtual #216                // Method android/support/v7/widget/bf.b:(II)V
     325: iload_3
     326: ldc           #198                // int -2147483648
     328: if_icmpne     338
     331: iload         4
     333: ldc           #198                // int -2147483648
     335: if_icmpeq     348
     338: aload_0
     339: getfield      #211                // Field u:Landroid/support/v7/widget/bf;
     342: iload_3
     343: iload         4
     345: invokevirtual #218                // Method android/support/v7/widget/bf.a:(II)V
     348: aload_0
     349: aload_1
     350: getstatic     #221                // Field android/support/v7/a/a$j.Toolbar_contentInsetStartWithNavigation:I
     353: ldc           #198                // int -2147483648
     355: invokevirtual #161                // Method android/support/v7/widget/bp.d:(II)I
     358: putfield      #223                // Field v:I
     361: aload_0
     362: aload_1
     363: getstatic     #226                // Field android/support/v7/a/a$j.Toolbar_contentInsetEndWithActions:I
     366: ldc           #198                // int -2147483648
     368: invokevirtual #161                // Method android/support/v7/widget/bp.d:(II)I
     371: putfield      #228                // Field w:I
     374: aload_0
     375: aload_1
     376: getstatic     #231                // Field android/support/v7/a/a$j.Toolbar_collapseIcon:I
     379: invokevirtual #234                // Method android/support/v7/widget/bp.a:(I)Landroid/graphics/drawable/Drawable;
     382: putfield      #236                // Field j:Landroid/graphics/drawable/Drawable;
     385: aload_0
     386: aload_1
     387: getstatic     #239                // Field android/support/v7/a/a$j.Toolbar_collapseContentDescription:I
     390: invokevirtual #242                // Method android/support/v7/widget/bp.c:(I)Ljava/lang/CharSequence;
     393: putfield      #244                // Field k:Ljava/lang/CharSequence;
     396: aload_1
     397: getstatic     #247                // Field android/support/v7/a/a$j.Toolbar_title:I
     400: invokevirtual #242                // Method android/support/v7/widget/bp.c:(I)Ljava/lang/CharSequence;
     403: astore_2
     404: aload_2
     405: invokestatic  #253                // Method android/text/TextUtils.isEmpty:(Ljava/lang/CharSequence;)Z
     408: ifne          416
     411: aload_0
     412: aload_2
     413: invokevirtual #257                // Method setTitle:(Ljava/lang/CharSequence;)V
     416: aload_1
     417: getstatic     #260                // Field android/support/v7/a/a$j.Toolbar_subtitle:I
     420: invokevirtual #242                // Method android/support/v7/widget/bp.c:(I)Ljava/lang/CharSequence;
     423: astore_2
     424: aload_2
     425: invokestatic  #253                // Method android/text/TextUtils.isEmpty:(Ljava/lang/CharSequence;)Z
     428: ifne          436
     431: aload_0
     432: aload_2
     433: invokevirtual #263                // Method setSubtitle:(Ljava/lang/CharSequence;)V
     436: aload_0
     437: aload_0
     438: invokevirtual #123                // Method getContext:()Landroid/content/Context;
     441: putfield      #265                // Field l:Landroid/content/Context;
     444: aload_0
     445: aload_1
     446: getstatic     #268                // Field android/support/v7/a/a$j.Toolbar_popupTheme:I
     449: iconst_0
     450: invokevirtual #139                // Method android/support/v7/widget/bp.g:(II)I
     453: invokevirtual #272                // Method setPopupTheme:(I)V
     456: aload_1
     457: getstatic     #275                // Field android/support/v7/a/a$j.Toolbar_navigationIcon:I
     460: invokevirtual #234                // Method android/support/v7/widget/bp.a:(I)Landroid/graphics/drawable/Drawable;
     463: astore_2
     464: aload_2
     465: ifnull        473
     468: aload_0
     469: aload_2
     470: invokevirtual #279                // Method setNavigationIcon:(Landroid/graphics/drawable/Drawable;)V
     473: aload_1
     474: getstatic     #282                // Field android/support/v7/a/a$j.Toolbar_navigationContentDescription:I
     477: invokevirtual #242                // Method android/support/v7/widget/bp.c:(I)Ljava/lang/CharSequence;
     480: astore_2
     481: aload_2
     482: invokestatic  #253                // Method android/text/TextUtils.isEmpty:(Ljava/lang/CharSequence;)Z
     485: ifne          493
     488: aload_0
     489: aload_2
     490: invokevirtual #285                // Method setNavigationContentDescription:(Ljava/lang/CharSequence;)V
     493: aload_1
     494: getstatic     #288                // Field android/support/v7/a/a$j.Toolbar_logo:I
     497: invokevirtual #234                // Method android/support/v7/widget/bp.a:(I)Landroid/graphics/drawable/Drawable;
     500: astore_2
     501: aload_2
     502: ifnull        510
     505: aload_0
     506: aload_2
     507: invokevirtual #291                // Method setLogo:(Landroid/graphics/drawable/Drawable;)V
     510: aload_1
     511: getstatic     #294                // Field android/support/v7/a/a$j.Toolbar_logoDescription:I
     514: invokevirtual #242                // Method android/support/v7/widget/bp.c:(I)Ljava/lang/CharSequence;
     517: astore_2
     518: aload_2
     519: invokestatic  #253                // Method android/text/TextUtils.isEmpty:(Ljava/lang/CharSequence;)Z
     522: ifne          530
     525: aload_0
     526: aload_2
     527: invokevirtual #297                // Method setLogoDescription:(Ljava/lang/CharSequence;)V
     530: aload_1
     531: getstatic     #300                // Field android/support/v7/a/a$j.Toolbar_titleTextColor:I
     534: invokevirtual #167                // Method android/support/v7/widget/bp.g:(I)Z
     537: ifeq          552
     540: aload_0
     541: aload_1
     542: getstatic     #300                // Field android/support/v7/a/a$j.Toolbar_titleTextColor:I
     545: iconst_m1
     546: invokevirtual #302                // Method android/support/v7/widget/bp.b:(II)I
     549: invokevirtual #305                // Method setTitleTextColor:(I)V
     552: aload_1
     553: getstatic     #308                // Field android/support/v7/a/a$j.Toolbar_subtitleTextColor:I
     556: invokevirtual #167                // Method android/support/v7/widget/bp.g:(I)Z
     559: ifeq          574
     562: aload_0
     563: aload_1
     564: getstatic     #308                // Field android/support/v7/a/a$j.Toolbar_subtitleTextColor:I
     567: iconst_m1
     568: invokevirtual #302                // Method android/support/v7/widget/bp.b:(II)I
     571: invokevirtual #311                // Method setSubtitleTextColor:(I)V
     574: aload_1
     575: invokevirtual #313                // Method android/support/v7/widget/bp.a:()V
     578: return

  public android.support.v7.widget.Toolbar$b a(android.util.AttributeSet);
    Code:
       0: new           #15                 // class android/support/v7/widget/Toolbar$b
       3: dup
       4: aload_0
       5: invokevirtual #123                // Method getContext:()Landroid/content/Context;
       8: aload_1
       9: invokespecial #570                // Method android/support/v7/widget/Toolbar$b."<init>":(Landroid/content/Context;Landroid/util/AttributeSet;)V
      12: areturn

  protected android.support.v7.widget.Toolbar$b a(android.view.ViewGroup$LayoutParams);
    Code:
       0: aload_1
       1: instanceof    #15                 // class android/support/v7/widget/Toolbar$b
       4: ifeq          19
       7: new           #15                 // class android/support/v7/widget/Toolbar$b
      10: dup
      11: aload_1
      12: checkcast     #15                 // class android/support/v7/widget/Toolbar$b
      15: invokespecial #573                // Method android/support/v7/widget/Toolbar$b."<init>":(Landroid/support/v7/widget/Toolbar$b;)V
      18: areturn
      19: aload_1
      20: instanceof    #575                // class android/support/v7/app/a$a
      23: ifeq          38
      26: new           #15                 // class android/support/v7/widget/Toolbar$b
      29: dup
      30: aload_1
      31: checkcast     #575                // class android/support/v7/app/a$a
      34: invokespecial #578                // Method android/support/v7/widget/Toolbar$b."<init>":(Landroid/support/v7/app/a$a;)V
      37: areturn
      38: aload_1
      39: instanceof    #352                // class android/view/ViewGroup$MarginLayoutParams
      42: ifeq          57
      45: new           #15                 // class android/support/v7/widget/Toolbar$b
      48: dup
      49: aload_1
      50: checkcast     #352                // class android/view/ViewGroup$MarginLayoutParams
      53: invokespecial #581                // Method android/support/v7/widget/Toolbar$b."<init>":(Landroid/view/ViewGroup$MarginLayoutParams;)V
      56: areturn
      57: new           #15                 // class android/support/v7/widget/Toolbar$b
      60: dup
      61: aload_1
      62: invokespecial #583                // Method android/support/v7/widget/Toolbar$b."<init>":(Landroid/view/ViewGroup$LayoutParams;)V
      65: areturn

  public void a(int, int);
    Code:
       0: aload_0
       1: invokespecial #209                // Method s:()V
       4: aload_0
       5: getfield      #211                // Field u:Landroid/support/v7/widget/bf;
       8: iload_1
       9: iload_2
      10: invokevirtual #218                // Method android/support/v7/widget/bf.a:(II)V
      13: return

  public void a(android.content.Context, int);
    Code:
       0: aload_0
       1: iload_2
       2: putfield      #141                // Field n:I
       5: aload_0
       6: getfield      #586                // Field f:Landroid/widget/TextView;
       9: ifnull        21
      12: aload_0
      13: getfield      #586                // Field f:Landroid/widget/TextView;
      16: aload_1
      17: iload_2
      18: invokevirtual #591                // Method android/widget/TextView.setTextAppearance:(Landroid/content/Context;I)V
      21: return

  public void a(android.support.v7.view.menu.h, android.support.v7.widget.d);
    Code:
       0: aload_1
       1: ifnonnull     12
       4: aload_0
       5: getfield      #505                // Field e:Landroid/support/v7/widget/ActionMenuView;
       8: ifnonnull     12
      11: return
      12: aload_0
      13: invokespecial #503                // Method o:()V
      16: aload_0
      17: getfield      #505                // Field e:Landroid/support/v7/widget/ActionMenuView;
      20: invokevirtual #510                // Method android/support/v7/widget/ActionMenuView.d:()Landroid/support/v7/view/menu/h;
      23: astore_3
      24: aload_3
      25: aload_1
      26: if_acmpne     30
      29: return
      30: aload_3
      31: ifnull        50
      34: aload_3
      35: aload_0
      36: getfield      #594                // Field J:Landroid/support/v7/widget/d;
      39: invokevirtual #597                // Method android/support/v7/view/menu/h.b:(Landroid/support/v7/view/menu/o;)V
      42: aload_3
      43: aload_0
      44: getfield      #518                // Field K:Landroid/support/v7/widget/Toolbar$a;
      47: invokevirtual #597                // Method android/support/v7/view/menu/h.b:(Landroid/support/v7/view/menu/o;)V
      50: aload_0
      51: getfield      #518                // Field K:Landroid/support/v7/widget/Toolbar$a;
      54: ifnonnull     69
      57: aload_0
      58: new           #12                 // class android/support/v7/widget/Toolbar$a
      61: dup
      62: aload_0
      63: invokespecial #519                // Method android/support/v7/widget/Toolbar$a."<init>":(Landroid/support/v7/widget/Toolbar;)V
      66: putfield      #518                // Field K:Landroid/support/v7/widget/Toolbar$a;
      69: aload_2
      70: iconst_1
      71: invokevirtual #601                // Method android/support/v7/widget/d.d:(Z)V
      74: aload_1
      75: ifnull        102
      78: aload_1
      79: aload_2
      80: aload_0
      81: getfield      #265                // Field l:Landroid/content/Context;
      84: invokevirtual #526                // Method android/support/v7/view/menu/h.a:(Landroid/support/v7/view/menu/o;Landroid/content/Context;)V
      87: aload_1
      88: aload_0
      89: getfield      #518                // Field K:Landroid/support/v7/widget/Toolbar$a;
      92: aload_0
      93: getfield      #265                // Field l:Landroid/content/Context;
      96: invokevirtual #526                // Method android/support/v7/view/menu/h.a:(Landroid/support/v7/view/menu/o;Landroid/content/Context;)V
      99: goto          136
     102: aload_2
     103: aload_0
     104: getfield      #265                // Field l:Landroid/content/Context;
     107: aconst_null
     108: invokevirtual #604                // Method android/support/v7/widget/d.a:(Landroid/content/Context;Landroid/support/v7/view/menu/h;)V
     111: aload_0
     112: getfield      #518                // Field K:Landroid/support/v7/widget/Toolbar$a;
     115: aload_0
     116: getfield      #265                // Field l:Landroid/content/Context;
     119: aconst_null
     120: invokevirtual #605                // Method android/support/v7/widget/Toolbar$a.a:(Landroid/content/Context;Landroid/support/v7/view/menu/h;)V
     123: aload_2
     124: iconst_1
     125: invokevirtual #607                // Method android/support/v7/widget/d.a:(Z)V
     128: aload_0
     129: getfield      #518                // Field K:Landroid/support/v7/widget/Toolbar$a;
     132: iconst_1
     133: invokevirtual #608                // Method android/support/v7/widget/Toolbar$a.a:(Z)V
     136: aload_0
     137: getfield      #505                // Field e:Landroid/support/v7/widget/ActionMenuView;
     140: aload_0
     141: getfield      #529                // Field m:I
     144: invokevirtual #530                // Method android/support/v7/widget/ActionMenuView.setPopupTheme:(I)V
     147: aload_0
     148: getfield      #505                // Field e:Landroid/support/v7/widget/ActionMenuView;
     151: aload_2
     152: invokevirtual #612                // Method android/support/v7/widget/ActionMenuView.setPresenter:(Landroid/support/v7/widget/d;)V
     155: aload_0
     156: aload_2
     157: putfield      #594                // Field J:Landroid/support/v7/widget/d;
     160: return

  public void a(android.support.v7.view.menu.o$a, android.support.v7.view.menu.h$a);
    Code:
       0: aload_0
       1: aload_1
       2: putfield      #536                // Field L:Landroid/support/v7/view/menu/o$a;
       5: aload_0
       6: aload_2
       7: putfield      #538                // Field M:Landroid/support/v7/view/menu/h$a;
      10: aload_0
      11: getfield      #505                // Field e:Landroid/support/v7/widget/ActionMenuView;
      14: ifnull        26
      17: aload_0
      18: getfield      #505                // Field e:Landroid/support/v7/widget/ActionMenuView;
      21: aload_1
      22: aload_2
      23: invokevirtual #541                // Method android/support/v7/widget/ActionMenuView.a:(Landroid/support/v7/view/menu/o$a;Landroid/support/v7/view/menu/h$a;)V
      26: return

  public boolean a();
    Code:
       0: aload_0
       1: invokevirtual #613                // Method getVisibility:()I
       4: ifne          26
       7: aload_0
       8: getfield      #505                // Field e:Landroid/support/v7/widget/ActionMenuView;
      11: ifnull        26
      14: aload_0
      15: getfield      #505                // Field e:Landroid/support/v7/widget/ActionMenuView;
      18: invokevirtual #615                // Method android/support/v7/widget/ActionMenuView.a:()Z
      21: ifeq          26
      24: iconst_1
      25: ireturn
      26: iconst_0
      27: ireturn

  public void b(android.content.Context, int);
    Code:
       0: aload_0
       1: iload_2
       2: putfield      #146                // Field o:I
       5: aload_0
       6: getfield      #617                // Field g:Landroid/widget/TextView;
       9: ifnull        21
      12: aload_0
      13: getfield      #617                // Field g:Landroid/widget/TextView;
      16: aload_1
      17: iload_2
      18: invokevirtual #591                // Method android/widget/TextView.setTextAppearance:(Landroid/content/Context;I)V
      21: return

  public boolean b();
    Code:
       0: aload_0
       1: getfield      #505                // Field e:Landroid/support/v7/widget/ActionMenuView;
       4: ifnull        19
       7: aload_0
       8: getfield      #505                // Field e:Landroid/support/v7/widget/ActionMenuView;
      11: invokevirtual #619                // Method android/support/v7/widget/ActionMenuView.g:()Z
      14: ifeq          19
      17: iconst_1
      18: ireturn
      19: iconst_0
      20: ireturn

  public boolean c();
    Code:
       0: aload_0
       1: getfield      #505                // Field e:Landroid/support/v7/widget/ActionMenuView;
       4: ifnull        19
       7: aload_0
       8: getfield      #505                // Field e:Landroid/support/v7/widget/ActionMenuView;
      11: invokevirtual #621                // Method android/support/v7/widget/ActionMenuView.h:()Z
      14: ifeq          19
      17: iconst_1
      18: ireturn
      19: iconst_0
      20: ireturn

  protected boolean checkLayoutParams(android.view.ViewGroup$LayoutParams);
    Code:
       0: aload_0
       1: aload_1
       2: invokespecial #622                // Method android/view/ViewGroup.checkLayoutParams:(Landroid/view/ViewGroup$LayoutParams;)Z
       5: ifeq          17
       8: aload_1
       9: instanceof    #15                 // class android/support/v7/widget/Toolbar$b
      12: ifeq          17
      15: iconst_1
      16: ireturn
      17: iconst_0
      18: ireturn

  public boolean d();
    Code:
       0: aload_0
       1: getfield      #505                // Field e:Landroid/support/v7/widget/ActionMenuView;
       4: ifnull        19
       7: aload_0
       8: getfield      #505                // Field e:Landroid/support/v7/widget/ActionMenuView;
      11: invokevirtual #624                // Method android/support/v7/widget/ActionMenuView.e:()Z
      14: ifeq          19
      17: iconst_1
      18: ireturn
      19: iconst_0
      20: ireturn

  public boolean e();
    Code:
       0: aload_0
       1: getfield      #505                // Field e:Landroid/support/v7/widget/ActionMenuView;
       4: ifnull        19
       7: aload_0
       8: getfield      #505                // Field e:Landroid/support/v7/widget/ActionMenuView;
      11: invokevirtual #626                // Method android/support/v7/widget/ActionMenuView.f:()Z
      14: ifeq          19
      17: iconst_1
      18: ireturn
      19: iconst_0
      20: ireturn

  public void f();
    Code:
       0: aload_0
       1: getfield      #505                // Field e:Landroid/support/v7/widget/ActionMenuView;
       4: ifnull        14
       7: aload_0
       8: getfield      #505                // Field e:Landroid/support/v7/widget/ActionMenuView;
      11: invokevirtual #628                // Method android/support/v7/widget/ActionMenuView.i:()V
      14: return

  public boolean g();
    Code:
       0: aload_0
       1: getfield      #518                // Field K:Landroid/support/v7/widget/Toolbar$a;
       4: ifnull        19
       7: aload_0
       8: getfield      #518                // Field K:Landroid/support/v7/widget/Toolbar$a;
      11: getfield      #631                // Field android/support/v7/widget/Toolbar$a.b:Landroid/support/v7/view/menu/j;
      14: ifnull        19
      17: iconst_1
      18: ireturn
      19: iconst_0
      20: ireturn

  protected android.view.ViewGroup$LayoutParams generateDefaultLayoutParams();
    Code:
       0: aload_0
       1: invokevirtual #423                // Method j:()Landroid/support/v7/widget/Toolbar$b;
       4: areturn

  public android.view.ViewGroup$LayoutParams generateLayoutParams(android.util.AttributeSet);
    Code:
       0: aload_0
       1: aload_1
       2: invokevirtual #636                // Method a:(Landroid/util/AttributeSet;)Landroid/support/v7/widget/Toolbar$b;
       5: areturn

  protected android.view.ViewGroup$LayoutParams generateLayoutParams(android.view.ViewGroup$LayoutParams);
    Code:
       0: aload_0
       1: aload_1
       2: invokevirtual #430                // Method a:(Landroid/view/ViewGroup$LayoutParams;)Landroid/support/v7/widget/Toolbar$b;
       5: areturn

  public int getContentInsetEnd();
    Code:
       0: aload_0
       1: getfield      #211                // Field u:Landroid/support/v7/widget/bf;
       4: ifnull        15
       7: aload_0
       8: getfield      #211                // Field u:Landroid/support/v7/widget/bf;
      11: invokevirtual #640                // Method android/support/v7/widget/bf.d:()I
      14: ireturn
      15: iconst_0
      16: ireturn

  public int getContentInsetEndWithActions();
    Code:
       0: aload_0
       1: getfield      #228                // Field w:I
       4: ldc           #198                // int -2147483648
       6: if_icmpeq     14
       9: aload_0
      10: getfield      #228                // Field w:I
      13: ireturn
      14: aload_0
      15: invokevirtual #643                // Method getContentInsetEnd:()I
      18: ireturn

  public int getContentInsetLeft();
    Code:
       0: aload_0
       1: getfield      #211                // Field u:Landroid/support/v7/widget/bf;
       4: ifnull        15
       7: aload_0
       8: getfield      #211                // Field u:Landroid/support/v7/widget/bf;
      11: invokevirtual #646                // Method android/support/v7/widget/bf.a:()I
      14: ireturn
      15: iconst_0
      16: ireturn

  public int getContentInsetRight();
    Code:
       0: aload_0
       1: getfield      #211                // Field u:Landroid/support/v7/widget/bf;
       4: ifnull        15
       7: aload_0
       8: getfield      #211                // Field u:Landroid/support/v7/widget/bf;
      11: invokevirtual #649                // Method android/support/v7/widget/bf.b:()I
      14: ireturn
      15: iconst_0
      16: ireturn

  public int getContentInsetStart();
    Code:
       0: aload_0
       1: getfield      #211                // Field u:Landroid/support/v7/widget/bf;
       4: ifnull        15
       7: aload_0
       8: getfield      #211                // Field u:Landroid/support/v7/widget/bf;
      11: invokevirtual #652                // Method android/support/v7/widget/bf.c:()I
      14: ireturn
      15: iconst_0
      16: ireturn

  public int getContentInsetStartWithNavigation();
    Code:
       0: aload_0
       1: getfield      #223                // Field v:I
       4: ldc           #198                // int -2147483648
       6: if_icmpeq     14
       9: aload_0
      10: getfield      #223                // Field v:I
      13: ireturn
      14: aload_0
      15: invokevirtual #655                // Method getContentInsetStart:()I
      18: ireturn

  public int getCurrentContentInsetEnd();
    Code:
       0: aload_0
       1: getfield      #505                // Field e:Landroid/support/v7/widget/ActionMenuView;
       4: ifnull        31
       7: aload_0
       8: getfield      #505                // Field e:Landroid/support/v7/widget/ActionMenuView;
      11: invokevirtual #510                // Method android/support/v7/widget/ActionMenuView.d:()Landroid/support/v7/view/menu/h;
      14: astore_2
      15: aload_2
      16: ifnull        31
      19: aload_2
      20: invokevirtual #659                // Method android/support/v7/view/menu/h.hasVisibleItems:()Z
      23: ifeq          31
      26: iconst_1
      27: istore_1
      28: goto          33
      31: iconst_0
      32: istore_1
      33: iload_1
      34: ifeq          53
      37: aload_0
      38: invokevirtual #643                // Method getContentInsetEnd:()I
      41: aload_0
      42: getfield      #228                // Field w:I
      45: iconst_0
      46: invokestatic  #349                // Method java/lang/Math.max:(II)I
      49: invokestatic  #349                // Method java/lang/Math.max:(II)I
      52: ireturn
      53: aload_0
      54: invokevirtual #643                // Method getContentInsetEnd:()I
      57: ireturn

  public int getCurrentContentInsetLeft();
    Code:
       0: aload_0
       1: invokestatic  #452                // Method android/support/v4/view/s.e:(Landroid/view/View;)I
       4: iconst_1
       5: if_icmpne     13
       8: aload_0
       9: invokevirtual #662                // Method getCurrentContentInsetEnd:()I
      12: ireturn
      13: aload_0
      14: invokevirtual #665                // Method getCurrentContentInsetStart:()I
      17: ireturn

  public int getCurrentContentInsetRight();
    Code:
       0: aload_0
       1: invokestatic  #452                // Method android/support/v4/view/s.e:(Landroid/view/View;)I
       4: iconst_1
       5: if_icmpne     13
       8: aload_0
       9: invokevirtual #665                // Method getCurrentContentInsetStart:()I
      12: ireturn
      13: aload_0
      14: invokevirtual #662                // Method getCurrentContentInsetEnd:()I
      17: ireturn

  public int getCurrentContentInsetStart();
    Code:
       0: aload_0
       1: invokevirtual #670                // Method getNavigationIcon:()Landroid/graphics/drawable/Drawable;
       4: ifnull        23
       7: aload_0
       8: invokevirtual #655                // Method getContentInsetStart:()I
      11: aload_0
      12: getfield      #223                // Field v:I
      15: iconst_0
      16: invokestatic  #349                // Method java/lang/Math.max:(II)I
      19: invokestatic  #349                // Method java/lang/Math.max:(II)I
      22: ireturn
      23: aload_0
      24: invokevirtual #655                // Method getContentInsetStart:()I
      27: ireturn

  public android.graphics.drawable.Drawable getLogo();
    Code:
       0: aload_0
       1: getfield      #498                // Field i:Landroid/widget/ImageView;
       4: ifnull        15
       7: aload_0
       8: getfield      #498                // Field i:Landroid/widget/ImageView;
      11: invokevirtual #676                // Method android/widget/ImageView.getDrawable:()Landroid/graphics/drawable/Drawable;
      14: areturn
      15: aconst_null
      16: areturn

  public java.lang.CharSequence getLogoDescription();
    Code:
       0: aload_0
       1: getfield      #498                // Field i:Landroid/widget/ImageView;
       4: ifnull        15
       7: aload_0
       8: getfield      #498                // Field i:Landroid/widget/ImageView;
      11: invokevirtual #681                // Method android/widget/ImageView.getContentDescription:()Ljava/lang/CharSequence;
      14: areturn
      15: aconst_null
      16: areturn

  public android.view.Menu getMenu();
    Code:
       0: aload_0
       1: invokespecial #683                // Method n:()V
       4: aload_0
       5: getfield      #505                // Field e:Landroid/support/v7/widget/ActionMenuView;
       8: invokevirtual #514                // Method android/support/v7/widget/ActionMenuView.getMenu:()Landroid/view/Menu;
      11: areturn

  public java.lang.CharSequence getNavigationContentDescription();
    Code:
       0: aload_0
       1: getfield      #547                // Field h:Landroid/widget/ImageButton;
       4: ifnull        15
       7: aload_0
       8: getfield      #547                // Field h:Landroid/widget/ImageButton;
      11: invokevirtual #685                // Method android/widget/ImageButton.getContentDescription:()Ljava/lang/CharSequence;
      14: areturn
      15: aconst_null
      16: areturn

  public android.graphics.drawable.Drawable getNavigationIcon();
    Code:
       0: aload_0
       1: getfield      #547                // Field h:Landroid/widget/ImageButton;
       4: ifnull        15
       7: aload_0
       8: getfield      #547                // Field h:Landroid/widget/ImageButton;
      11: invokevirtual #686                // Method android/widget/ImageButton.getDrawable:()Landroid/graphics/drawable/Drawable;
      14: areturn
      15: aconst_null
      16: areturn

  android.support.v7.widget.d getOuterActionMenuPresenter();
    Code:
       0: aload_0
       1: getfield      #594                // Field J:Landroid/support/v7/widget/d;
       4: areturn

  public android.graphics.drawable.Drawable getOverflowIcon();
    Code:
       0: aload_0
       1: invokespecial #683                // Method n:()V
       4: aload_0
       5: getfield      #505                // Field e:Landroid/support/v7/widget/ActionMenuView;
       8: invokevirtual #691                // Method android/support/v7/widget/ActionMenuView.getOverflowIcon:()Landroid/graphics/drawable/Drawable;
      11: areturn

  android.content.Context getPopupContext();
    Code:
       0: aload_0
       1: getfield      #265                // Field l:Landroid/content/Context;
       4: areturn

  public int getPopupTheme();
    Code:
       0: aload_0
       1: getfield      #529                // Field m:I
       4: ireturn

  public java.lang.CharSequence getSubtitle();
    Code:
       0: aload_0
       1: getfield      #696                // Field z:Ljava/lang/CharSequence;
       4: areturn

  public java.lang.CharSequence getTitle();
    Code:
       0: aload_0
       1: getfield      #699                // Field y:Ljava/lang/CharSequence;
       4: areturn

  public int getTitleMarginBottom();
    Code:
       0: aload_0
       1: getfield      #169                // Field t:I
       4: ireturn

  public int getTitleMarginEnd();
    Code:
       0: aload_0
       1: getfield      #173                // Field r:I
       4: ireturn

  public int getTitleMarginStart();
    Code:
       0: aload_0
       1: getfield      #175                // Field q:I
       4: ireturn

  public int getTitleMarginTop();
    Code:
       0: aload_0
       1: getfield      #171                // Field s:I
       4: ireturn

  public android.support.v7.widget.al getWrapper();
    Code:
       0: aload_0
       1: getfield      #707                // Field I:Landroid/support/v7/widget/bq;
       4: ifnonnull     20
       7: aload_0
       8: new           #709                // class android/support/v7/widget/bq
      11: dup
      12: aload_0
      13: iconst_1
      14: invokespecial #712                // Method android/support/v7/widget/bq."<init>":(Landroid/support/v7/widget/Toolbar;Z)V
      17: putfield      #707                // Field I:Landroid/support/v7/widget/bq;
      20: aload_0
      21: getfield      #707                // Field I:Landroid/support/v7/widget/bq;
      24: areturn

  public void h();
    Code:
       0: aload_0
       1: getfield      #518                // Field K:Landroid/support/v7/widget/Toolbar$a;
       4: ifnonnull     12
       7: aconst_null
       8: astore_1
       9: goto          20
      12: aload_0
      13: getfield      #518                // Field K:Landroid/support/v7/widget/Toolbar$a;
      16: getfield      #631                // Field android/support/v7/widget/Toolbar$a.b:Landroid/support/v7/view/menu/j;
      19: astore_1
      20: aload_1
      21: ifnull        29
      24: aload_1
      25: invokevirtual #717                // Method android/support/v7/view/menu/j.collapseActionView:()Z
      28: pop
      29: return

  void i();
    Code:
       0: aload_0
       1: getfield      #719                // Field a:Landroid/widget/ImageButton;
       4: ifnonnull     96
       7: aload_0
       8: new           #549                // class android/support/v7/widget/p
      11: dup
      12: aload_0
      13: invokevirtual #123                // Method getContext:()Landroid/content/Context;
      16: aconst_null
      17: getstatic     #552                // Field android/support/v7/a/a$a.toolbarNavigationButtonStyle:I
      20: invokespecial #553                // Method android/support/v7/widget/p."<init>":(Landroid/content/Context;Landroid/util/AttributeSet;I)V
      23: putfield      #719                // Field a:Landroid/widget/ImageButton;
      26: aload_0
      27: getfield      #719                // Field a:Landroid/widget/ImageButton;
      30: aload_0
      31: getfield      #236                // Field j:Landroid/graphics/drawable/Drawable;
      34: invokevirtual #722                // Method android/widget/ImageButton.setImageDrawable:(Landroid/graphics/drawable/Drawable;)V
      37: aload_0
      38: getfield      #719                // Field a:Landroid/widget/ImageButton;
      41: aload_0
      42: getfield      #244                // Field k:Ljava/lang/CharSequence;
      45: invokevirtual #725                // Method android/widget/ImageButton.setContentDescription:(Ljava/lang/CharSequence;)V
      48: aload_0
      49: invokevirtual #423                // Method j:()Landroid/support/v7/widget/Toolbar$b;
      52: astore_1
      53: aload_1
      54: ldc_w         #554                // int 8388611
      57: aload_0
      58: getfield      #156                // Field c:I
      61: bipush        112
      63: iand
      64: ior
      65: putfield      #327                // Field android/support/v7/widget/Toolbar$b.a:I
      68: aload_1
      69: iconst_2
      70: putfield      #432                // Field android/support/v7/widget/Toolbar$b.b:I
      73: aload_0
      74: getfield      #719                // Field a:Landroid/widget/ImageButton;
      77: aload_1
      78: invokevirtual #557                // Method android/widget/ImageButton.setLayoutParams:(Landroid/view/ViewGroup$LayoutParams;)V
      81: aload_0
      82: getfield      #719                // Field a:Landroid/widget/ImageButton;
      85: new           #10                 // class android/support/v7/widget/Toolbar$3
      88: dup
      89: aload_0
      90: invokespecial #726                // Method android/support/v7/widget/Toolbar$3."<init>":(Landroid/support/v7/widget/Toolbar;)V
      93: invokevirtual #730                // Method android/widget/ImageButton.setOnClickListener:(Landroid/view/View$OnClickListener;)V
      96: return

  protected android.support.v7.widget.Toolbar$b j();
    Code:
       0: new           #15                 // class android/support/v7/widget/Toolbar$b
       3: dup
       4: bipush        -2
       6: bipush        -2
       8: invokespecial #732                // Method android/support/v7/widget/Toolbar$b."<init>":(II)V
      11: areturn

  void k();
    Code:
       0: aload_0
       1: invokevirtual #455                // Method getChildCount:()I
       4: iconst_1
       5: isub
       6: istore_1
       7: iload_1
       8: iflt          60
      11: aload_0
      12: iload_1
      13: invokevirtual #466                // Method getChildAt:(I)Landroid/view/View;
      16: astore_2
      17: aload_2
      18: invokevirtual #321                // Method android/view/View.getLayoutParams:()Landroid/view/ViewGroup$LayoutParams;
      21: checkcast     #15                 // class android/support/v7/widget/Toolbar$b
      24: getfield      #432                // Field android/support/v7/widget/Toolbar$b.b:I
      27: iconst_2
      28: if_icmpeq     53
      31: aload_2
      32: aload_0
      33: getfield      #505                // Field e:Landroid/support/v7/widget/ActionMenuView;
      36: if_acmpeq     53
      39: aload_0
      40: iload_1
      41: invokevirtual #735                // Method removeViewAt:(I)V
      44: aload_0
      45: getfield      #109                // Field F:Ljava/util/ArrayList;
      48: aload_2
      49: invokevirtual #442                // Method java/util/ArrayList.add:(Ljava/lang/Object;)Z
      52: pop
      53: iload_1
      54: iconst_1
      55: isub
      56: istore_1
      57: goto          7
      60: return

  void l();
    Code:
       0: aload_0
       1: getfield      #109                // Field F:Ljava/util/ArrayList;
       4: invokevirtual #736                // Method java/util/ArrayList.size:()I
       7: iconst_1
       8: isub
       9: istore_1
      10: iload_1
      11: iflt          36
      14: aload_0
      15: aload_0
      16: getfield      #109                // Field F:Ljava/util/ArrayList;
      19: iload_1
      20: invokevirtual #737                // Method java/util/ArrayList.get:(I)Ljava/lang/Object;
      23: checkcast     #317                // class android/view/View
      26: invokevirtual #740                // Method addView:(Landroid/view/View;)V
      29: iload_1
      30: iconst_1
      31: isub
      32: istore_1
      33: goto          10
      36: aload_0
      37: getfield      #109                // Field F:Ljava/util/ArrayList;
      40: invokevirtual #741                // Method java/util/ArrayList.clear:()V
      43: return

  protected void onDetachedFromWindow();
    Code:
       0: aload_0
       1: invokespecial #744                // Method android/view/ViewGroup.onDetachedFromWindow:()V
       4: aload_0
       5: aload_0
       6: getfield      #119                // Field O:Ljava/lang/Runnable;
       9: invokevirtual #561                // Method removeCallbacks:(Ljava/lang/Runnable;)Z
      12: pop
      13: return

  public boolean onHoverEvent(android.view.MotionEvent);
    Code:
       0: aload_1
       1: invokevirtual #751                // Method android/view/MotionEvent.getActionMasked:()I
       4: istore_2
       5: iload_2
       6: bipush        9
       8: if_icmpne     16
      11: aload_0
      12: iconst_0
      13: putfield      #753                // Field D:Z
      16: aload_0
      17: getfield      #753                // Field D:Z
      20: ifne          44
      23: aload_0
      24: aload_1
      25: invokespecial #755                // Method android/view/ViewGroup.onHoverEvent:(Landroid/view/MotionEvent;)Z
      28: istore_3
      29: iload_2
      30: bipush        9
      32: if_icmpne     44
      35: iload_3
      36: ifne          44
      39: aload_0
      40: iconst_1
      41: putfield      #753                // Field D:Z
      44: iload_2
      45: bipush        10
      47: if_icmpeq     55
      50: iload_2
      51: iconst_3
      52: if_icmpne     60
      55: aload_0
      56: iconst_0
      57: putfield      #753                // Field D:Z
      60: iconst_1
      61: ireturn

  protected void onLayout(boolean, int, int, int, int);
    Code:
       0: aload_0
       1: invokestatic  #452                // Method android/support/v4/view/s.e:(Landroid/view/View;)I
       4: iconst_1
       5: if_icmpne     14
       8: iconst_1
       9: istore        8
      11: goto          17
      14: iconst_0
      15: istore        8
      17: aload_0
      18: invokevirtual #760                // Method getWidth:()I
      21: istore        10
      23: aload_0
      24: invokevirtual #338                // Method getHeight:()I
      27: istore        13
      29: aload_0
      30: invokevirtual #361                // Method getPaddingLeft:()I
      33: istore        6
      35: aload_0
      36: invokevirtual #364                // Method getPaddingRight:()I
      39: istore        11
      41: aload_0
      42: invokevirtual #332                // Method getPaddingTop:()I
      45: istore        12
      47: aload_0
      48: invokevirtual #335                // Method getPaddingBottom:()I
      51: istore        14
      53: iload         10
      55: iload         11
      57: isub
      58: istore        9
      60: aload_0
      61: getfield      #111                // Field G:[I
      64: astore        18
      66: aload         18
      68: iconst_1
      69: iconst_0
      70: iastore
      71: aload         18
      73: iconst_0
      74: iconst_0
      75: iastore
      76: aload_0
      77: invokestatic  #762                // Method android/support/v4/view/s.j:(Landroid/view/View;)I
      80: istore_2
      81: iload_2
      82: iflt          98
      85: iload_2
      86: iload         5
      88: iload_3
      89: isub
      90: invokestatic  #416                // Method java/lang/Math.min:(II)I
      93: istore        5
      95: goto          101
      98: iconst_0
      99: istore        5
     101: aload_0
     102: aload_0
     103: getfield      #547                // Field h:Landroid/widget/ImageButton;
     106: invokespecial #469                // Method a:(Landroid/view/View;)Z
     109: ifeq          159
     112: iload         8
     114: ifeq          140
     117: aload_0
     118: aload_0
     119: getfield      #547                // Field h:Landroid/widget/ImageButton;
     122: iload         9
     124: aload         18
     126: iload         5
     128: invokespecial #764                // Method b:(Landroid/view/View;I[II)I
     131: istore        4
     133: iload         6
     135: istore        7
     137: goto          167
     140: aload_0
     141: aload_0
     142: getfield      #547                // Field h:Landroid/widget/ImageButton;
     145: iload         6
     147: aload         18
     149: iload         5
     151: invokespecial #766                // Method a:(Landroid/view/View;I[II)I
     154: istore        7
     156: goto          163
     159: iload         6
     161: istore        7
     163: iload         9
     165: istore        4
     167: iload         4
     169: istore_2
     170: iload         7
     172: istore_3
     173: aload_0
     174: aload_0
     175: getfield      #719                // Field a:Landroid/widget/ImageButton;
     178: invokespecial #469                // Method a:(Landroid/view/View;)Z
     181: ifeq          228
     184: iload         8
     186: ifeq          210
     189: aload_0
     190: aload_0
     191: getfield      #719                // Field a:Landroid/widget/ImageButton;
     194: iload         4
     196: aload         18
     198: iload         5
     200: invokespecial #764                // Method b:(Landroid/view/View;I[II)I
     203: istore_2
     204: iload         7
     206: istore_3
     207: goto          228
     210: aload_0
     211: aload_0
     212: getfield      #719                // Field a:Landroid/widget/ImageButton;
     215: iload         7
     217: aload         18
     219: iload         5
     221: invokespecial #766                // Method a:(Landroid/view/View;I[II)I
     224: istore_3
     225: iload         4
     227: istore_2
     228: iload_2
     229: istore        4
     231: iload_3
     232: istore        7
     234: aload_0
     235: aload_0
     236: getfield      #505                // Field e:Landroid/support/v7/widget/ActionMenuView;
     239: invokespecial #469                // Method a:(Landroid/view/View;)Z
     242: ifeq          289
     245: iload         8
     247: ifeq          271
     250: aload_0
     251: aload_0
     252: getfield      #505                // Field e:Landroid/support/v7/widget/ActionMenuView;
     255: iload_3
     256: aload         18
     258: iload         5
     260: invokespecial #766                // Method a:(Landroid/view/View;I[II)I
     263: istore        7
     265: iload_2
     266: istore        4
     268: goto          289
     271: aload_0
     272: aload_0
     273: getfield      #505                // Field e:Landroid/support/v7/widget/ActionMenuView;
     276: iload_2
     277: aload         18
     279: iload         5
     281: invokespecial #764                // Method b:(Landroid/view/View;I[II)I
     284: istore        4
     286: iload_3
     287: istore        7
     289: aload_0
     290: invokevirtual #768                // Method getCurrentContentInsetLeft:()I
     293: istore_3
     294: aload_0
     295: invokevirtual #770                // Method getCurrentContentInsetRight:()I
     298: istore_2
     299: aload         18
     301: iconst_0
     302: iconst_0
     303: iload_3
     304: iload         7
     306: isub
     307: invokestatic  #349                // Method java/lang/Math.max:(II)I
     310: iastore
     311: aload         18
     313: iconst_1
     314: iconst_0
     315: iload_2
     316: iload         9
     318: iload         4
     320: isub
     321: isub
     322: invokestatic  #349                // Method java/lang/Math.max:(II)I
     325: iastore
     326: iload         7
     328: iload_3
     329: invokestatic  #349                // Method java/lang/Math.max:(II)I
     332: istore_3
     333: iload         4
     335: iload         9
     337: iload_2
     338: isub
     339: invokestatic  #416                // Method java/lang/Math.min:(II)I
     342: istore        4
     344: iload_3
     345: istore_2
     346: iload         4
     348: istore        7
     350: aload_0
     351: aload_0
     352: getfield      #434                // Field b:Landroid/view/View;
     355: invokespecial #469                // Method a:(Landroid/view/View;)Z
     358: ifeq          405
     361: iload         8
     363: ifeq          387
     366: aload_0
     367: aload_0
     368: getfield      #434                // Field b:Landroid/view/View;
     371: iload         4
     373: aload         18
     375: iload         5
     377: invokespecial #764                // Method b:(Landroid/view/View;I[II)I
     380: istore        7
     382: iload_3
     383: istore_2
     384: goto          405
     387: aload_0
     388: aload_0
     389: getfield      #434                // Field b:Landroid/view/View;
     392: iload_3
     393: aload         18
     395: iload         5
     397: invokespecial #766                // Method a:(Landroid/view/View;I[II)I
     400: istore_2
     401: iload         4
     403: istore        7
     405: iload_2
     406: istore        4
     408: iload         7
     410: istore_3
     411: aload_0
     412: aload_0
     413: getfield      #498                // Field i:Landroid/widget/ImageView;
     416: invokespecial #469                // Method a:(Landroid/view/View;)Z
     419: ifeq          466
     422: iload         8
     424: ifeq          448
     427: aload_0
     428: aload_0
     429: getfield      #498                // Field i:Landroid/widget/ImageView;
     432: iload         7
     434: aload         18
     436: iload         5
     438: invokespecial #764                // Method b:(Landroid/view/View;I[II)I
     441: istore_3
     442: iload_2
     443: istore        4
     445: goto          466
     448: aload_0
     449: aload_0
     450: getfield      #498                // Field i:Landroid/widget/ImageView;
     453: iload_2
     454: aload         18
     456: iload         5
     458: invokespecial #766                // Method a:(Landroid/view/View;I[II)I
     461: istore        4
     463: iload         7
     465: istore_3
     466: aload_0
     467: aload_0
     468: getfield      #586                // Field f:Landroid/widget/TextView;
     471: invokespecial #469                // Method a:(Landroid/view/View;)Z
     474: istore_1
     475: aload_0
     476: aload_0
     477: getfield      #617                // Field g:Landroid/widget/TextView;
     480: invokespecial #469                // Method a:(Landroid/view/View;)Z
     483: istore        15
     485: iload_1
     486: ifeq          526
     489: aload_0
     490: getfield      #586                // Field f:Landroid/widget/TextView;
     493: invokevirtual #771                // Method android/widget/TextView.getLayoutParams:()Landroid/view/ViewGroup$LayoutParams;
     496: checkcast     #15                 // class android/support/v7/widget/Toolbar$b
     499: astore        16
     501: aload         16
     503: getfield      #341                // Field android/support/v7/widget/Toolbar$b.topMargin:I
     506: aload_0
     507: getfield      #586                // Field f:Landroid/widget/TextView;
     510: invokevirtual #772                // Method android/widget/TextView.getMeasuredHeight:()I
     513: iadd
     514: aload         16
     516: getfield      #344                // Field android/support/v7/widget/Toolbar$b.bottomMargin:I
     519: iadd
     520: iconst_0
     521: iadd
     522: istore_2
     523: goto          528
     526: iconst_0
     527: istore_2
     528: iload         15
     530: ifeq          570
     533: aload_0
     534: getfield      #617                // Field g:Landroid/widget/TextView;
     537: invokevirtual #771                // Method android/widget/TextView.getLayoutParams:()Landroid/view/ViewGroup$LayoutParams;
     540: checkcast     #15                 // class android/support/v7/widget/Toolbar$b
     543: astore        16
     545: iload_2
     546: aload         16
     548: getfield      #341                // Field android/support/v7/widget/Toolbar$b.topMargin:I
     551: aload_0
     552: getfield      #617                // Field g:Landroid/widget/TextView;
     555: invokevirtual #772                // Method android/widget/TextView.getMeasuredHeight:()I
     558: iadd
     559: aload         16
     561: getfield      #344                // Field android/support/v7/widget/Toolbar$b.bottomMargin:I
     564: iadd
     565: iadd
     566: istore_2
     567: goto          570
     570: iload_1
     571: ifne          591
     574: iload         15
     576: ifeq          582
     579: goto          591
     582: iload         4
     584: istore_2
     585: iload_3
     586: istore        4
     588: goto          1321
     591: iload_1
     592: ifeq          604
     595: aload_0
     596: getfield      #586                // Field f:Landroid/widget/TextView;
     599: astore        16
     601: goto          610
     604: aload_0
     605: getfield      #617                // Field g:Landroid/widget/TextView;
     608: astore        16
     610: iload         15
     612: ifeq          624
     615: aload_0
     616: getfield      #617                // Field g:Landroid/widget/TextView;
     619: astore        17
     621: goto          630
     624: aload_0
     625: getfield      #586                // Field f:Landroid/widget/TextView;
     628: astore        17
     630: aload         16
     632: invokevirtual #321                // Method android/view/View.getLayoutParams:()Landroid/view/ViewGroup$LayoutParams;
     635: checkcast     #15                 // class android/support/v7/widget/Toolbar$b
     638: astore        16
     640: aload         17
     642: invokevirtual #321                // Method android/view/View.getLayoutParams:()Landroid/view/ViewGroup$LayoutParams;
     645: checkcast     #15                 // class android/support/v7/widget/Toolbar$b
     648: astore        17
     650: iload_1
     651: ifeq          664
     654: aload_0
     655: getfield      #586                // Field f:Landroid/widget/TextView;
     658: invokevirtual #773                // Method android/widget/TextView.getMeasuredWidth:()I
     661: ifgt          679
     664: iload         15
     666: ifeq          685
     669: aload_0
     670: getfield      #617                // Field g:Landroid/widget/TextView;
     673: invokevirtual #773                // Method android/widget/TextView.getMeasuredWidth:()I
     676: ifle          685
     679: iconst_1
     680: istore        7
     682: goto          688
     685: iconst_0
     686: istore        7
     688: aload_0
     689: getfield      #100                // Field x:I
     692: bipush        112
     694: iand
     695: istore        9
     697: iload         9
     699: bipush        48
     701: if_icmpeq     838
     704: iload         9
     706: bipush        80
     708: if_icmpeq     816
     711: iload         13
     713: iload         12
     715: isub
     716: iload         14
     718: isub
     719: iload_2
     720: isub
     721: iconst_2
     722: idiv
     723: istore        9
     725: iload         9
     727: aload         16
     729: getfield      #341                // Field android/support/v7/widget/Toolbar$b.topMargin:I
     732: aload_0
     733: getfield      #171                // Field s:I
     736: iadd
     737: if_icmpge     754
     740: aload         16
     742: getfield      #341                // Field android/support/v7/widget/Toolbar$b.topMargin:I
     745: aload_0
     746: getfield      #171                // Field s:I
     749: iadd
     750: istore_2
     751: goto          808
     754: iload         13
     756: iload         14
     758: isub
     759: iload_2
     760: isub
     761: iload         9
     763: isub
     764: iload         12
     766: isub
     767: istore        13
     769: iload         9
     771: istore_2
     772: iload         13
     774: aload         16
     776: getfield      #344                // Field android/support/v7/widget/Toolbar$b.bottomMargin:I
     779: aload_0
     780: getfield      #169                // Field t:I
     783: iadd
     784: if_icmpge     808
     787: iconst_0
     788: iload         9
     790: aload         17
     792: getfield      #344                // Field android/support/v7/widget/Toolbar$b.bottomMargin:I
     795: aload_0
     796: getfield      #169                // Field t:I
     799: iadd
     800: iload         13
     802: isub
     803: isub
     804: invokestatic  #349                // Method java/lang/Math.max:(II)I
     807: istore_2
     808: iload         12
     810: iload_2
     811: iadd
     812: istore_2
     813: goto          854
     816: iload         13
     818: iload         14
     820: isub
     821: aload         17
     823: getfield      #344                // Field android/support/v7/widget/Toolbar$b.bottomMargin:I
     826: isub
     827: aload_0
     828: getfield      #169                // Field t:I
     831: isub
     832: iload_2
     833: isub
     834: istore_2
     835: goto          854
     838: aload_0
     839: invokevirtual #332                // Method getPaddingTop:()I
     842: aload         16
     844: getfield      #341                // Field android/support/v7/widget/Toolbar$b.topMargin:I
     847: iadd
     848: aload_0
     849: getfield      #171                // Field s:I
     852: iadd
     853: istore_2
     854: iload         8
     856: ifeq          1089
     859: iload         7
     861: ifeq          873
     864: aload_0
     865: getfield      #175                // Field q:I
     868: istore        8
     870: goto          876
     873: iconst_0
     874: istore        8
     876: iload         8
     878: aload         18
     880: iconst_1
     881: iaload
     882: isub
     883: istore        8
     885: iload_3
     886: iconst_0
     887: iload         8
     889: invokestatic  #349                // Method java/lang/Math.max:(II)I
     892: isub
     893: istore_3
     894: aload         18
     896: iconst_1
     897: iconst_0
     898: iload         8
     900: ineg
     901: invokestatic  #349                // Method java/lang/Math.max:(II)I
     904: iastore
     905: iload_1
     906: ifeq          977
     909: aload_0
     910: getfield      #586                // Field f:Landroid/widget/TextView;
     913: invokevirtual #771                // Method android/widget/TextView.getLayoutParams:()Landroid/view/ViewGroup$LayoutParams;
     916: checkcast     #15                 // class android/support/v7/widget/Toolbar$b
     919: astore        16
     921: iload_3
     922: aload_0
     923: getfield      #586                // Field f:Landroid/widget/TextView;
     926: invokevirtual #773                // Method android/widget/TextView.getMeasuredWidth:()I
     929: isub
     930: istore        9
     932: aload_0
     933: getfield      #586                // Field f:Landroid/widget/TextView;
     936: invokevirtual #772                // Method android/widget/TextView.getMeasuredHeight:()I
     939: iload_2
     940: iadd
     941: istore        8
     943: aload_0
     944: getfield      #586                // Field f:Landroid/widget/TextView;
     947: iload         9
     949: iload_2
     950: iload_3
     951: iload         8
     953: invokevirtual #774                // Method android/widget/TextView.layout:(IIII)V
     956: iload         9
     958: aload_0
     959: getfield      #173                // Field r:I
     962: isub
     963: istore_2
     964: iload         8
     966: aload         16
     968: getfield      #344                // Field android/support/v7/widget/Toolbar$b.bottomMargin:I
     971: iadd
     972: istore        9
     974: goto          986
     977: iload_3
     978: istore        8
     980: iload_2
     981: istore        9
     983: iload         8
     985: istore_2
     986: iload         15
     988: ifeq          1068
     991: aload_0
     992: getfield      #617                // Field g:Landroid/widget/TextView;
     995: invokevirtual #771                // Method android/widget/TextView.getLayoutParams:()Landroid/view/ViewGroup$LayoutParams;
     998: checkcast     #15                 // class android/support/v7/widget/Toolbar$b
    1001: astore        16
    1003: iload         9
    1005: aload         16
    1007: getfield      #341                // Field android/support/v7/widget/Toolbar$b.topMargin:I
    1010: iadd
    1011: istore        8
    1013: aload_0
    1014: getfield      #617                // Field g:Landroid/widget/TextView;
    1017: invokevirtual #773                // Method android/widget/TextView.getMeasuredWidth:()I
    1020: istore        9
    1022: aload_0
    1023: getfield      #617                // Field g:Landroid/widget/TextView;
    1026: invokevirtual #772                // Method android/widget/TextView.getMeasuredHeight:()I
    1029: istore        12
    1031: aload_0
    1032: getfield      #617                // Field g:Landroid/widget/TextView;
    1035: iload_3
    1036: iload         9
    1038: isub
    1039: iload         8
    1041: iload_3
    1042: iload         12
    1044: iload         8
    1046: iadd
    1047: invokevirtual #774                // Method android/widget/TextView.layout:(IIII)V
    1050: iload_3
    1051: aload_0
    1052: getfield      #173                // Field r:I
    1055: isub
    1056: istore        8
    1058: aload         16
    1060: getfield      #344                // Field android/support/v7/widget/Toolbar$b.bottomMargin:I
    1063: istore        9
    1065: goto          1071
    1068: iload_3
    1069: istore        8
    1071: iload         7
    1073: ifeq          1083
    1076: iload_2
    1077: iload         8
    1079: invokestatic  #416                // Method java/lang/Math.min:(II)I
    1082: istore_3
    1083: iload         4
    1085: istore_2
    1086: goto          585
    1089: iload         7
    1091: ifeq          1103
    1094: aload_0
    1095: getfield      #175                // Field q:I
    1098: istore        8
    1100: goto          1106
    1103: iconst_0
    1104: istore        8
    1106: iload         8
    1108: aload         18
    1110: iconst_0
    1111: iaload
    1112: isub
    1113: istore        8
    1115: iload         4
    1117: iconst_0
    1118: iload         8
    1120: invokestatic  #349                // Method java/lang/Math.max:(II)I
    1123: iadd
    1124: istore        4
    1126: aload         18
    1128: iconst_0
    1129: iconst_0
    1130: iload         8
    1132: ineg
    1133: invokestatic  #349                // Method java/lang/Math.max:(II)I
    1136: iastore
    1137: iload_1
    1138: ifeq          1211
    1141: aload_0
    1142: getfield      #586                // Field f:Landroid/widget/TextView;
    1145: invokevirtual #771                // Method android/widget/TextView.getLayoutParams:()Landroid/view/ViewGroup$LayoutParams;
    1148: checkcast     #15                 // class android/support/v7/widget/Toolbar$b
    1151: astore        16
    1153: aload_0
    1154: getfield      #586                // Field f:Landroid/widget/TextView;
    1157: invokevirtual #773                // Method android/widget/TextView.getMeasuredWidth:()I
    1160: iload         4
    1162: iadd
    1163: istore        8
    1165: aload_0
    1166: getfield      #586                // Field f:Landroid/widget/TextView;
    1169: invokevirtual #772                // Method android/widget/TextView.getMeasuredHeight:()I
    1172: iload_2
    1173: iadd
    1174: istore        9
    1176: aload_0
    1177: getfield      #586                // Field f:Landroid/widget/TextView;
    1180: iload         4
    1182: iload_2
    1183: iload         8
    1185: iload         9
    1187: invokevirtual #774                // Method android/widget/TextView.layout:(IIII)V
    1190: iload         8
    1192: aload_0
    1193: getfield      #173                // Field r:I
    1196: iadd
    1197: istore        8
    1199: iload         9
    1201: aload         16
    1203: getfield      #344                // Field android/support/v7/widget/Toolbar$b.bottomMargin:I
    1206: iadd
    1207: istore_2
    1208: goto          1215
    1211: iload         4
    1213: istore        8
    1215: iload         15
    1217: ifeq          1295
    1220: aload_0
    1221: getfield      #617                // Field g:Landroid/widget/TextView;
    1224: invokevirtual #771                // Method android/widget/TextView.getLayoutParams:()Landroid/view/ViewGroup$LayoutParams;
    1227: checkcast     #15                 // class android/support/v7/widget/Toolbar$b
    1230: astore        16
    1232: iload_2
    1233: aload         16
    1235: getfield      #341                // Field android/support/v7/widget/Toolbar$b.topMargin:I
    1238: iadd
    1239: istore_2
    1240: aload_0
    1241: getfield      #617                // Field g:Landroid/widget/TextView;
    1244: invokevirtual #773                // Method android/widget/TextView.getMeasuredWidth:()I
    1247: iload         4
    1249: iadd
    1250: istore        9
    1252: aload_0
    1253: getfield      #617                // Field g:Landroid/widget/TextView;
    1256: invokevirtual #772                // Method android/widget/TextView.getMeasuredHeight:()I
    1259: istore        12
    1261: aload_0
    1262: getfield      #617                // Field g:Landroid/widget/TextView;
    1265: iload         4
    1267: iload_2
    1268: iload         9
    1270: iload         12
    1272: iload_2
    1273: iadd
    1274: invokevirtual #774                // Method android/widget/TextView.layout:(IIII)V
    1277: iload         9
    1279: aload_0
    1280: getfield      #173                // Field r:I
    1283: iadd
    1284: istore        9
    1286: aload         16
    1288: getfield      #344                // Field android/support/v7/widget/Toolbar$b.bottomMargin:I
    1291: istore_2
    1292: goto          1299
    1295: iload         4
    1297: istore        9
    1299: iload         4
    1301: istore_2
    1302: iload_3
    1303: istore        4
    1305: iload         7
    1307: ifeq          1321
    1310: iload         8
    1312: iload         9
    1314: invokestatic  #349                // Method java/lang/Math.max:(II)I
    1317: istore_2
    1318: iload_3
    1319: istore        4
    1321: iload         6
    1323: istore        7
    1325: iconst_0
    1326: istore        6
    1328: aload_0
    1329: aload_0
    1330: getfield      #107                // Field E:Ljava/util/ArrayList;
    1333: iconst_3
    1334: invokespecial #776                // Method a:(Ljava/util/List;I)V
    1337: aload_0
    1338: getfield      #107                // Field E:Ljava/util/ArrayList;
    1341: invokevirtual #736                // Method java/util/ArrayList.size:()I
    1344: istore        8
    1346: iconst_0
    1347: istore_3
    1348: iload_3
    1349: iload         8
    1351: if_icmpge     1382
    1354: aload_0
    1355: aload_0
    1356: getfield      #107                // Field E:Ljava/util/ArrayList;
    1359: iload_3
    1360: invokevirtual #737                // Method java/util/ArrayList.get:(I)Ljava/lang/Object;
    1363: checkcast     #317                // class android/view/View
    1366: iload_2
    1367: aload         18
    1369: iload         5
    1371: invokespecial #766                // Method a:(Landroid/view/View;I[II)I
    1374: istore_2
    1375: iload_3
    1376: iconst_1
    1377: iadd
    1378: istore_3
    1379: goto          1348
    1382: aload_0
    1383: aload_0
    1384: getfield      #107                // Field E:Ljava/util/ArrayList;
    1387: iconst_5
    1388: invokespecial #776                // Method a:(Ljava/util/List;I)V
    1391: aload_0
    1392: getfield      #107                // Field E:Ljava/util/ArrayList;
    1395: invokevirtual #736                // Method java/util/ArrayList.size:()I
    1398: istore        8
    1400: iconst_0
    1401: istore_3
    1402: iload_3
    1403: iload         8
    1405: if_icmpge     1438
    1408: aload_0
    1409: aload_0
    1410: getfield      #107                // Field E:Ljava/util/ArrayList;
    1413: iload_3
    1414: invokevirtual #737                // Method java/util/ArrayList.get:(I)Ljava/lang/Object;
    1417: checkcast     #317                // class android/view/View
    1420: iload         4
    1422: aload         18
    1424: iload         5
    1426: invokespecial #764                // Method b:(Landroid/view/View;I[II)I
    1429: istore        4
    1431: iload_3
    1432: iconst_1
    1433: iadd
    1434: istore_3
    1435: goto          1402
    1438: aload_0
    1439: aload_0
    1440: getfield      #107                // Field E:Ljava/util/ArrayList;
    1443: iconst_1
    1444: invokespecial #776                // Method a:(Ljava/util/List;I)V
    1447: aload_0
    1448: aload_0
    1449: getfield      #107                // Field E:Ljava/util/ArrayList;
    1452: aload         18
    1454: invokespecial #778                // Method a:(Ljava/util/List;[I)I
    1457: istore        8
    1459: iload         7
    1461: iload         10
    1463: iload         7
    1465: isub
    1466: iload         11
    1468: isub
    1469: iconst_2
    1470: idiv
    1471: iadd
    1472: iload         8
    1474: iconst_2
    1475: idiv
    1476: isub
    1477: istore_3
    1478: iload         8
    1480: iload_3
    1481: iadd
    1482: istore        7
    1484: iload_3
    1485: iload_2
    1486: if_icmpge     1492
    1489: goto          1512
    1492: iload         7
    1494: iload         4
    1496: if_icmple     1510
    1499: iload_3
    1500: iload         7
    1502: iload         4
    1504: isub
    1505: isub
    1506: istore_2
    1507: goto          1512
    1510: iload_3
    1511: istore_2
    1512: aload_0
    1513: getfield      #107                // Field E:Ljava/util/ArrayList;
    1516: invokevirtual #736                // Method java/util/ArrayList.size:()I
    1519: istore        4
    1521: iload         6
    1523: istore_3
    1524: iload_3
    1525: iload         4
    1527: if_icmpge     1558
    1530: aload_0
    1531: aload_0
    1532: getfield      #107                // Field E:Ljava/util/ArrayList;
    1535: iload_3
    1536: invokevirtual #737                // Method java/util/ArrayList.get:(I)Ljava/lang/Object;
    1539: checkcast     #317                // class android/view/View
    1542: iload_2
    1543: aload         18
    1545: iload         5
    1547: invokespecial #766                // Method a:(Landroid/view/View;I[II)I
    1550: istore_2
    1551: iload_3
    1552: iconst_1
    1553: iadd
    1554: istore_3
    1555: goto          1524
    1558: aload_0
    1559: getfield      #107                // Field E:Ljava/util/ArrayList;
    1562: invokevirtual #741                // Method java/util/ArrayList.clear:()V
    1565: return

  protected void onMeasure(int, int);
    Code:
       0: aload_0
       1: getfield      #111                // Field G:[I
       4: astore        12
       6: aload_0
       7: invokestatic  #782                // Method android/support/v7/widget/bx.a:(Landroid/view/View;)Z
      10: ifeq          22
      13: iconst_1
      14: istore        8
      16: iconst_0
      17: istore        7
      19: goto          28
      22: iconst_0
      23: istore        8
      25: iconst_1
      26: istore        7
      28: aload_0
      29: aload_0
      30: getfield      #547                // Field h:Landroid/widget/ImageButton;
      33: invokespecial #469                // Method a:(Landroid/view/View;)Z
      36: ifeq          110
      39: aload_0
      40: aload_0
      41: getfield      #547                // Field h:Landroid/widget/ImageButton;
      44: iload_1
      45: iconst_0
      46: iload_2
      47: iconst_0
      48: aload_0
      49: getfield      #194                // Field p:I
      52: invokespecial #784                // Method a:(Landroid/view/View;IIIII)V
      55: aload_0
      56: getfield      #547                // Field h:Landroid/widget/ImageButton;
      59: invokevirtual #785                // Method android/widget/ImageButton.getMeasuredWidth:()I
      62: aload_0
      63: aload_0
      64: getfield      #547                // Field h:Landroid/widget/ImageButton;
      67: invokespecial #787                // Method b:(Landroid/view/View;)I
      70: iadd
      71: istore_3
      72: iconst_0
      73: aload_0
      74: getfield      #547                // Field h:Landroid/widget/ImageButton;
      77: invokevirtual #788                // Method android/widget/ImageButton.getMeasuredHeight:()I
      80: aload_0
      81: aload_0
      82: getfield      #547                // Field h:Landroid/widget/ImageButton;
      85: invokespecial #790                // Method c:(Landroid/view/View;)I
      88: iadd
      89: invokestatic  #349                // Method java/lang/Math.max:(II)I
      92: istore        6
      94: iconst_0
      95: aload_0
      96: getfield      #547                // Field h:Landroid/widget/ImageButton;
      99: invokevirtual #793                // Method android/widget/ImageButton.getMeasuredState:()I
     102: invokestatic  #796                // Method android/view/View.combineMeasuredStates:(II)I
     105: istore        5
     107: goto          118
     110: iconst_0
     111: istore_3
     112: iconst_0
     113: istore        6
     115: iconst_0
     116: istore        5
     118: iload_3
     119: istore        9
     121: iload         6
     123: istore        4
     125: iload         5
     127: istore_3
     128: aload_0
     129: aload_0
     130: getfield      #719                // Field a:Landroid/widget/ImageButton;
     133: invokespecial #469                // Method a:(Landroid/view/View;)Z
     136: ifeq          209
     139: aload_0
     140: aload_0
     141: getfield      #719                // Field a:Landroid/widget/ImageButton;
     144: iload_1
     145: iconst_0
     146: iload_2
     147: iconst_0
     148: aload_0
     149: getfield      #194                // Field p:I
     152: invokespecial #784                // Method a:(Landroid/view/View;IIIII)V
     155: aload_0
     156: getfield      #719                // Field a:Landroid/widget/ImageButton;
     159: invokevirtual #785                // Method android/widget/ImageButton.getMeasuredWidth:()I
     162: aload_0
     163: aload_0
     164: getfield      #719                // Field a:Landroid/widget/ImageButton;
     167: invokespecial #787                // Method b:(Landroid/view/View;)I
     170: iadd
     171: istore        9
     173: iload         6
     175: aload_0
     176: getfield      #719                // Field a:Landroid/widget/ImageButton;
     179: invokevirtual #788                // Method android/widget/ImageButton.getMeasuredHeight:()I
     182: aload_0
     183: aload_0
     184: getfield      #719                // Field a:Landroid/widget/ImageButton;
     187: invokespecial #790                // Method c:(Landroid/view/View;)I
     190: iadd
     191: invokestatic  #349                // Method java/lang/Math.max:(II)I
     194: istore        4
     196: iload         5
     198: aload_0
     199: getfield      #719                // Field a:Landroid/widget/ImageButton;
     202: invokevirtual #793                // Method android/widget/ImageButton.getMeasuredState:()I
     205: invokestatic  #796                // Method android/view/View.combineMeasuredStates:(II)I
     208: istore_3
     209: aload_0
     210: invokevirtual #665                // Method getCurrentContentInsetStart:()I
     213: istore        5
     215: iload         5
     217: iload         9
     219: invokestatic  #349                // Method java/lang/Math.max:(II)I
     222: iconst_0
     223: iadd
     224: istore        6
     226: aload         12
     228: iload         8
     230: iconst_0
     231: iload         5
     233: iload         9
     235: isub
     236: invokestatic  #349                // Method java/lang/Math.max:(II)I
     239: iastore
     240: aload_0
     241: aload_0
     242: getfield      #505                // Field e:Landroid/support/v7/widget/ActionMenuView;
     245: invokespecial #469                // Method a:(Landroid/view/View;)Z
     248: ifeq          324
     251: aload_0
     252: aload_0
     253: getfield      #505                // Field e:Landroid/support/v7/widget/ActionMenuView;
     256: iload_1
     257: iload         6
     259: iload_2
     260: iconst_0
     261: aload_0
     262: getfield      #194                // Field p:I
     265: invokespecial #784                // Method a:(Landroid/view/View;IIIII)V
     268: aload_0
     269: getfield      #505                // Field e:Landroid/support/v7/widget/ActionMenuView;
     272: invokevirtual #797                // Method android/support/v7/widget/ActionMenuView.getMeasuredWidth:()I
     275: aload_0
     276: aload_0
     277: getfield      #505                // Field e:Landroid/support/v7/widget/ActionMenuView;
     280: invokespecial #787                // Method b:(Landroid/view/View;)I
     283: iadd
     284: istore        5
     286: iload         4
     288: aload_0
     289: getfield      #505                // Field e:Landroid/support/v7/widget/ActionMenuView;
     292: invokevirtual #798                // Method android/support/v7/widget/ActionMenuView.getMeasuredHeight:()I
     295: aload_0
     296: aload_0
     297: getfield      #505                // Field e:Landroid/support/v7/widget/ActionMenuView;
     300: invokespecial #790                // Method c:(Landroid/view/View;)I
     303: iadd
     304: invokestatic  #349                // Method java/lang/Math.max:(II)I
     307: istore        4
     309: iload_3
     310: aload_0
     311: getfield      #505                // Field e:Landroid/support/v7/widget/ActionMenuView;
     314: invokevirtual #799                // Method android/support/v7/widget/ActionMenuView.getMeasuredState:()I
     317: invokestatic  #796                // Method android/view/View.combineMeasuredStates:(II)I
     320: istore_3
     321: goto          327
     324: iconst_0
     325: istore        5
     327: aload_0
     328: invokevirtual #662                // Method getCurrentContentInsetEnd:()I
     331: istore        9
     333: iload         6
     335: iload         9
     337: iload         5
     339: invokestatic  #349                // Method java/lang/Math.max:(II)I
     342: iadd
     343: istore        8
     345: aload         12
     347: iload         7
     349: iconst_0
     350: iload         9
     352: iload         5
     354: isub
     355: invokestatic  #349                // Method java/lang/Math.max:(II)I
     358: iastore
     359: iload         8
     361: istore        7
     363: iload         4
     365: istore        6
     367: iload_3
     368: istore        5
     370: aload_0
     371: aload_0
     372: getfield      #434                // Field b:Landroid/view/View;
     375: invokespecial #469                // Method a:(Landroid/view/View;)Z
     378: ifeq          437
     381: iload         8
     383: aload_0
     384: aload_0
     385: getfield      #434                // Field b:Landroid/view/View;
     388: iload_1
     389: iload         8
     391: iload_2
     392: iconst_0
     393: aload         12
     395: invokespecial #801                // Method a:(Landroid/view/View;IIII[I)I
     398: iadd
     399: istore        7
     401: iload         4
     403: aload_0
     404: getfield      #434                // Field b:Landroid/view/View;
     407: invokevirtual #325                // Method android/view/View.getMeasuredHeight:()I
     410: aload_0
     411: aload_0
     412: getfield      #434                // Field b:Landroid/view/View;
     415: invokespecial #790                // Method c:(Landroid/view/View;)I
     418: iadd
     419: invokestatic  #349                // Method java/lang/Math.max:(II)I
     422: istore        6
     424: iload_3
     425: aload_0
     426: getfield      #434                // Field b:Landroid/view/View;
     429: invokevirtual #802                // Method android/view/View.getMeasuredState:()I
     432: invokestatic  #796                // Method android/view/View.combineMeasuredStates:(II)I
     435: istore        5
     437: iload         7
     439: istore        4
     441: iload         6
     443: istore        8
     445: iload         5
     447: istore_3
     448: aload_0
     449: aload_0
     450: getfield      #498                // Field i:Landroid/widget/ImageView;
     453: invokespecial #469                // Method a:(Landroid/view/View;)Z
     456: ifeq          515
     459: iload         7
     461: aload_0
     462: aload_0
     463: getfield      #498                // Field i:Landroid/widget/ImageView;
     466: iload_1
     467: iload         7
     469: iload_2
     470: iconst_0
     471: aload         12
     473: invokespecial #801                // Method a:(Landroid/view/View;IIII[I)I
     476: iadd
     477: istore        4
     479: iload         6
     481: aload_0
     482: getfield      #498                // Field i:Landroid/widget/ImageView;
     485: invokevirtual #803                // Method android/widget/ImageView.getMeasuredHeight:()I
     488: aload_0
     489: aload_0
     490: getfield      #498                // Field i:Landroid/widget/ImageView;
     493: invokespecial #790                // Method c:(Landroid/view/View;)I
     496: iadd
     497: invokestatic  #349                // Method java/lang/Math.max:(II)I
     500: istore        8
     502: iload         5
     504: aload_0
     505: getfield      #498                // Field i:Landroid/widget/ImageView;
     508: invokevirtual #804                // Method android/widget/ImageView.getMeasuredState:()I
     511: invokestatic  #796                // Method android/view/View.combineMeasuredStates:(II)I
     514: istore_3
     515: aload_0
     516: invokevirtual #455                // Method getChildCount:()I
     519: istore        10
     521: iload         8
     523: istore        7
     525: iconst_0
     526: istore        5
     528: iload         4
     530: istore        6
     532: iload         5
     534: istore        4
     536: iload         4
     538: iload         10
     540: if_icmpge     667
     543: aload_0
     544: iload         4
     546: invokevirtual #466                // Method getChildAt:(I)Landroid/view/View;
     549: astore        13
     551: iload         6
     553: istore        9
     555: iload_3
     556: istore        8
     558: iload         7
     560: istore        5
     562: aload         13
     564: invokevirtual #321                // Method android/view/View.getLayoutParams:()Landroid/view/ViewGroup$LayoutParams;
     567: checkcast     #15                 // class android/support/v7/widget/Toolbar$b
     570: getfield      #432                // Field android/support/v7/widget/Toolbar$b.b:I
     573: ifne          647
     576: aload_0
     577: aload         13
     579: invokespecial #469                // Method a:(Landroid/view/View;)Z
     582: ifne          599
     585: iload         6
     587: istore        9
     589: iload_3
     590: istore        8
     592: iload         7
     594: istore        5
     596: goto          647
     599: iload         6
     601: aload_0
     602: aload         13
     604: iload_1
     605: iload         6
     607: iload_2
     608: iconst_0
     609: aload         12
     611: invokespecial #801                // Method a:(Landroid/view/View;IIII[I)I
     614: iadd
     615: istore        9
     617: iload         7
     619: aload         13
     621: invokevirtual #325                // Method android/view/View.getMeasuredHeight:()I
     624: aload_0
     625: aload         13
     627: invokespecial #790                // Method c:(Landroid/view/View;)I
     630: iadd
     631: invokestatic  #349                // Method java/lang/Math.max:(II)I
     634: istore        5
     636: iload_3
     637: aload         13
     639: invokevirtual #802                // Method android/view/View.getMeasuredState:()I
     642: invokestatic  #796                // Method android/view/View.combineMeasuredStates:(II)I
     645: istore        8
     647: iload         4
     649: iconst_1
     650: iadd
     651: istore        4
     653: iload         9
     655: istore        6
     657: iload         8
     659: istore_3
     660: iload         5
     662: istore        7
     664: goto          536
     667: aload_0
     668: getfield      #171                // Field s:I
     671: aload_0
     672: getfield      #169                // Field t:I
     675: iadd
     676: istore        8
     678: aload_0
     679: getfield      #175                // Field q:I
     682: aload_0
     683: getfield      #173                // Field r:I
     686: iadd
     687: istore        9
     689: aload_0
     690: aload_0
     691: getfield      #586                // Field f:Landroid/widget/TextView;
     694: invokespecial #469                // Method a:(Landroid/view/View;)Z
     697: ifeq          787
     700: aload_0
     701: aload_0
     702: getfield      #586                // Field f:Landroid/widget/TextView;
     705: iload_1
     706: iload         6
     708: iload         9
     710: iadd
     711: iload_2
     712: iload         8
     714: aload         12
     716: invokespecial #801                // Method a:(Landroid/view/View;IIII[I)I
     719: pop
     720: aload_0
     721: getfield      #586                // Field f:Landroid/widget/TextView;
     724: invokevirtual #773                // Method android/widget/TextView.getMeasuredWidth:()I
     727: istore        4
     729: aload_0
     730: aload_0
     731: getfield      #586                // Field f:Landroid/widget/TextView;
     734: invokespecial #787                // Method b:(Landroid/view/View;)I
     737: istore        10
     739: aload_0
     740: getfield      #586                // Field f:Landroid/widget/TextView;
     743: invokevirtual #772                // Method android/widget/TextView.getMeasuredHeight:()I
     746: istore        5
     748: aload_0
     749: aload_0
     750: getfield      #586                // Field f:Landroid/widget/TextView;
     753: invokespecial #790                // Method c:(Landroid/view/View;)I
     756: istore        11
     758: iload_3
     759: aload_0
     760: getfield      #586                // Field f:Landroid/widget/TextView;
     763: invokevirtual #805                // Method android/widget/TextView.getMeasuredState:()I
     766: invokestatic  #796                // Method android/view/View.combineMeasuredStates:(II)I
     769: istore_3
     770: iload         5
     772: iload         11
     774: iadd
     775: istore        5
     777: iload         4
     779: iload         10
     781: iadd
     782: istore        4
     784: goto          793
     787: iconst_0
     788: istore        4
     790: iconst_0
     791: istore        5
     793: aload_0
     794: aload_0
     795: getfield      #617                // Field g:Landroid/widget/TextView;
     798: invokespecial #469                // Method a:(Landroid/view/View;)Z
     801: ifeq          869
     804: iload         4
     806: aload_0
     807: aload_0
     808: getfield      #617                // Field g:Landroid/widget/TextView;
     811: iload_1
     812: iload         6
     814: iload         9
     816: iadd
     817: iload_2
     818: iload         5
     820: iload         8
     822: iadd
     823: aload         12
     825: invokespecial #801                // Method a:(Landroid/view/View;IIII[I)I
     828: invokestatic  #349                // Method java/lang/Math.max:(II)I
     831: istore        4
     833: iload         5
     835: aload_0
     836: getfield      #617                // Field g:Landroid/widget/TextView;
     839: invokevirtual #772                // Method android/widget/TextView.getMeasuredHeight:()I
     842: aload_0
     843: aload_0
     844: getfield      #617                // Field g:Landroid/widget/TextView;
     847: invokespecial #790                // Method c:(Landroid/view/View;)I
     850: iadd
     851: iadd
     852: istore        5
     854: iload_3
     855: aload_0
     856: getfield      #617                // Field g:Landroid/widget/TextView;
     859: invokevirtual #805                // Method android/widget/TextView.getMeasuredState:()I
     862: invokestatic  #796                // Method android/view/View.combineMeasuredStates:(II)I
     865: istore_3
     866: goto          869
     869: iload         7
     871: iload         5
     873: invokestatic  #349                // Method java/lang/Math.max:(II)I
     876: istore        5
     878: aload_0
     879: invokevirtual #361                // Method getPaddingLeft:()I
     882: istore        9
     884: aload_0
     885: invokevirtual #364                // Method getPaddingRight:()I
     888: istore        10
     890: aload_0
     891: invokevirtual #332                // Method getPaddingTop:()I
     894: istore        7
     896: aload_0
     897: invokevirtual #335                // Method getPaddingBottom:()I
     900: istore        8
     902: iload         6
     904: iload         4
     906: iadd
     907: iload         9
     909: iload         10
     911: iadd
     912: iadd
     913: aload_0
     914: invokevirtual #808                // Method getSuggestedMinimumWidth:()I
     917: invokestatic  #349                // Method java/lang/Math.max:(II)I
     920: iload_1
     921: ldc_w         #809                // int -16777216
     924: iload_3
     925: iand
     926: invokestatic  #812                // Method android/view/View.resolveSizeAndState:(III)I
     929: istore        4
     931: iload         5
     933: iload         7
     935: iload         8
     937: iadd
     938: iadd
     939: aload_0
     940: invokevirtual #815                // Method getSuggestedMinimumHeight:()I
     943: invokestatic  #349                // Method java/lang/Math.max:(II)I
     946: iload_2
     947: iload_3
     948: bipush        16
     950: ishl
     951: invokestatic  #812                // Method android/view/View.resolveSizeAndState:(III)I
     954: istore_1
     955: aload_0
     956: invokespecial #817                // Method r:()Z
     959: ifeq          964
     962: iconst_0
     963: istore_1
     964: aload_0
     965: iload         4
     967: iload_1
     968: invokevirtual #820                // Method setMeasuredDimension:(II)V
     971: return

  protected void onRestoreInstanceState(android.os.Parcelable);
    Code:
       0: aload_1
       1: instanceof    #21                 // class android/support/v7/widget/Toolbar$d
       4: ifne          13
       7: aload_0
       8: aload_1
       9: invokespecial #824                // Method android/view/ViewGroup.onRestoreInstanceState:(Landroid/os/Parcelable;)V
      12: return
      13: aload_1
      14: checkcast     #21                 // class android/support/v7/widget/Toolbar$d
      17: astore_2
      18: aload_0
      19: aload_2
      20: invokevirtual #827                // Method android/support/v7/widget/Toolbar$d.a:()Landroid/os/Parcelable;
      23: invokespecial #824                // Method android/view/ViewGroup.onRestoreInstanceState:(Landroid/os/Parcelable;)V
      26: aload_0
      27: getfield      #505                // Field e:Landroid/support/v7/widget/ActionMenuView;
      30: ifnull        44
      33: aload_0
      34: getfield      #505                // Field e:Landroid/support/v7/widget/ActionMenuView;
      37: invokevirtual #510                // Method android/support/v7/widget/ActionMenuView.d:()Landroid/support/v7/view/menu/h;
      40: astore_1
      41: goto          46
      44: aconst_null
      45: astore_1
      46: aload_2
      47: getfield      #828                // Field android/support/v7/widget/Toolbar$d.a:I
      50: ifeq          86
      53: aload_0
      54: getfield      #518                // Field K:Landroid/support/v7/widget/Toolbar$a;
      57: ifnull        86
      60: aload_1
      61: ifnull        86
      64: aload_1
      65: aload_2
      66: getfield      #828                // Field android/support/v7/widget/Toolbar$d.a:I
      69: invokeinterface #834,  2          // InterfaceMethod android/view/Menu.findItem:(I)Landroid/view/MenuItem;
      74: astore_1
      75: aload_1
      76: ifnull        86
      79: aload_1
      80: invokeinterface #839,  1          // InterfaceMethod android/view/MenuItem.expandActionView:()Z
      85: pop
      86: aload_2
      87: getfield      #841                // Field android/support/v7/widget/Toolbar$d.b:Z
      90: ifeq          97
      93: aload_0
      94: invokespecial #843                // Method q:()V
      97: return

  public void onRtlPropertiesChanged(int);
    Code:
       0: getstatic     #849                // Field android/os/Build$VERSION.SDK_INT:I
       3: bipush        17
       5: if_icmplt     13
       8: aload_0
       9: iload_1
      10: invokespecial #851                // Method android/view/ViewGroup.onRtlPropertiesChanged:(I)V
      13: aload_0
      14: invokespecial #209                // Method s:()V
      17: aload_0
      18: getfield      #211                // Field u:Landroid/support/v7/widget/bf;
      21: astore_3
      22: iconst_1
      23: istore_2
      24: iload_1
      25: iconst_1
      26: if_icmpne     32
      29: goto          34
      32: iconst_0
      33: istore_2
      34: aload_3
      35: iload_2
      36: invokevirtual #852                // Method android/support/v7/widget/bf.a:(Z)V
      39: return

  protected android.os.Parcelable onSaveInstanceState();
    Code:
       0: new           #21                 // class android/support/v7/widget/Toolbar$d
       3: dup
       4: aload_0
       5: invokespecial #855                // Method android/view/ViewGroup.onSaveInstanceState:()Landroid/os/Parcelable;
       8: invokespecial #857                // Method android/support/v7/widget/Toolbar$d."<init>":(Landroid/os/Parcelable;)V
      11: astore_1
      12: aload_0
      13: getfield      #518                // Field K:Landroid/support/v7/widget/Toolbar$a;
      16: ifnull        43
      19: aload_0
      20: getfield      #518                // Field K:Landroid/support/v7/widget/Toolbar$a;
      23: getfield      #631                // Field android/support/v7/widget/Toolbar$a.b:Landroid/support/v7/view/menu/j;
      26: ifnull        43
      29: aload_1
      30: aload_0
      31: getfield      #518                // Field K:Landroid/support/v7/widget/Toolbar$a;
      34: getfield      #631                // Field android/support/v7/widget/Toolbar$a.b:Landroid/support/v7/view/menu/j;
      37: invokevirtual #860                // Method android/support/v7/view/menu/j.getItemId:()I
      40: putfield      #828                // Field android/support/v7/widget/Toolbar$d.a:I
      43: aload_1
      44: aload_0
      45: invokevirtual #862                // Method b:()Z
      48: putfield      #841                // Field android/support/v7/widget/Toolbar$d.b:Z
      51: aload_1
      52: areturn

  public boolean onTouchEvent(android.view.MotionEvent);
    Code:
       0: aload_1
       1: invokevirtual #751                // Method android/view/MotionEvent.getActionMasked:()I
       4: istore_2
       5: iload_2
       6: ifne          14
       9: aload_0
      10: iconst_0
      11: putfield      #865                // Field C:Z
      14: aload_0
      15: getfield      #865                // Field C:Z
      18: ifne          40
      21: aload_0
      22: aload_1
      23: invokespecial #867                // Method android/view/ViewGroup.onTouchEvent:(Landroid/view/MotionEvent;)Z
      26: istore_3
      27: iload_2
      28: ifne          40
      31: iload_3
      32: ifne          40
      35: aload_0
      36: iconst_1
      37: putfield      #865                // Field C:Z
      40: iload_2
      41: iconst_1
      42: if_icmpeq     50
      45: iload_2
      46: iconst_3
      47: if_icmpne     55
      50: aload_0
      51: iconst_0
      52: putfield      #865                // Field C:Z
      55: iconst_1
      56: ireturn

  public void setCollapsible(boolean);
    Code:
       0: aload_0
       1: iload_1
       2: putfield      #567                // Field N:Z
       5: aload_0
       6: invokevirtual #871                // Method requestLayout:()V
       9: return

  public void setContentInsetEndWithActions(int);
    Code:
       0: iload_1
       1: istore_2
       2: iload_1
       3: ifge          9
       6: ldc           #198                // int -2147483648
       8: istore_2
       9: iload_2
      10: aload_0
      11: getfield      #228                // Field w:I
      14: if_icmpeq     33
      17: aload_0
      18: iload_2
      19: putfield      #228                // Field w:I
      22: aload_0
      23: invokevirtual #670                // Method getNavigationIcon:()Landroid/graphics/drawable/Drawable;
      26: ifnull        33
      29: aload_0
      30: invokevirtual #871                // Method requestLayout:()V
      33: return

  public void setContentInsetStartWithNavigation(int);
    Code:
       0: iload_1
       1: istore_2
       2: iload_1
       3: ifge          9
       6: ldc           #198                // int -2147483648
       8: istore_2
       9: iload_2
      10: aload_0
      11: getfield      #223                // Field v:I
      14: if_icmpeq     33
      17: aload_0
      18: iload_2
      19: putfield      #223                // Field v:I
      22: aload_0
      23: invokevirtual #670                // Method getNavigationIcon:()Landroid/graphics/drawable/Drawable;
      26: ifnull        33
      29: aload_0
      30: invokevirtual #871                // Method requestLayout:()V
      33: return

  public void setLogo(int);
    Code:
       0: aload_0
       1: aload_0
       2: invokevirtual #123                // Method getContext:()Landroid/content/Context;
       5: iload_1
       6: invokestatic  #878                // Method android/support/v7/c/a/b.b:(Landroid/content/Context;I)Landroid/graphics/drawable/Drawable;
       9: invokevirtual #291                // Method setLogo:(Landroid/graphics/drawable/Drawable;)V
      12: return

  public void setLogo(android.graphics.drawable.Drawable);
    Code:
       0: aload_1
       1: ifnull        31
       4: aload_0
       5: invokespecial #880                // Method m:()V
       8: aload_0
       9: aload_0
      10: getfield      #498                // Field i:Landroid/widget/ImageView;
      13: invokespecial #882                // Method d:(Landroid/view/View;)Z
      16: ifne          69
      19: aload_0
      20: aload_0
      21: getfield      #498                // Field i:Landroid/widget/ImageView;
      24: iconst_1
      25: invokespecial #545                // Method a:(Landroid/view/View;Z)V
      28: goto          69
      31: aload_0
      32: getfield      #498                // Field i:Landroid/widget/ImageView;
      35: ifnull        69
      38: aload_0
      39: aload_0
      40: getfield      #498                // Field i:Landroid/widget/ImageView;
      43: invokespecial #882                // Method d:(Landroid/view/View;)Z
      46: ifeq          69
      49: aload_0
      50: aload_0
      51: getfield      #498                // Field i:Landroid/widget/ImageView;
      54: invokevirtual #885                // Method removeView:(Landroid/view/View;)V
      57: aload_0
      58: getfield      #109                // Field F:Ljava/util/ArrayList;
      61: aload_0
      62: getfield      #498                // Field i:Landroid/widget/ImageView;
      65: invokevirtual #888                // Method java/util/ArrayList.remove:(Ljava/lang/Object;)Z
      68: pop
      69: aload_0
      70: getfield      #498                // Field i:Landroid/widget/ImageView;
      73: ifnull        84
      76: aload_0
      77: getfield      #498                // Field i:Landroid/widget/ImageView;
      80: aload_1
      81: invokevirtual #889                // Method android/widget/ImageView.setImageDrawable:(Landroid/graphics/drawable/Drawable;)V
      84: return

  public void setLogoDescription(int);
    Code:
       0: aload_0
       1: aload_0
       2: invokevirtual #123                // Method getContext:()Landroid/content/Context;
       5: iload_1
       6: invokevirtual #894                // Method android/content/Context.getText:(I)Ljava/lang/CharSequence;
       9: invokevirtual #297                // Method setLogoDescription:(Ljava/lang/CharSequence;)V
      12: return

  public void setLogoDescription(java.lang.CharSequence);
    Code:
       0: aload_1
       1: invokestatic  #253                // Method android/text/TextUtils.isEmpty:(Ljava/lang/CharSequence;)Z
       4: ifne          11
       7: aload_0
       8: invokespecial #880                // Method m:()V
      11: aload_0
      12: getfield      #498                // Field i:Landroid/widget/ImageView;
      15: ifnull        26
      18: aload_0
      19: getfield      #498                // Field i:Landroid/widget/ImageView;
      22: aload_1
      23: invokevirtual #895                // Method android/widget/ImageView.setContentDescription:(Ljava/lang/CharSequence;)V
      26: return

  public void setNavigationContentDescription(int);
    Code:
       0: iload_1
       1: ifeq          16
       4: aload_0
       5: invokevirtual #123                // Method getContext:()Landroid/content/Context;
       8: iload_1
       9: invokevirtual #894                // Method android/content/Context.getText:(I)Ljava/lang/CharSequence;
      12: astore_2
      13: goto          18
      16: aconst_null
      17: astore_2
      18: aload_0
      19: aload_2
      20: invokevirtual #285                // Method setNavigationContentDescription:(Ljava/lang/CharSequence;)V
      23: return

  public void setNavigationContentDescription(java.lang.CharSequence);
    Code:
       0: aload_1
       1: invokestatic  #253                // Method android/text/TextUtils.isEmpty:(Ljava/lang/CharSequence;)Z
       4: ifne          11
       7: aload_0
       8: invokespecial #897                // Method p:()V
      11: aload_0
      12: getfield      #547                // Field h:Landroid/widget/ImageButton;
      15: ifnull        26
      18: aload_0
      19: getfield      #547                // Field h:Landroid/widget/ImageButton;
      22: aload_1
      23: invokevirtual #725                // Method android/widget/ImageButton.setContentDescription:(Ljava/lang/CharSequence;)V
      26: return

  public void setNavigationIcon(int);
    Code:
       0: aload_0
       1: aload_0
       2: invokevirtual #123                // Method getContext:()Landroid/content/Context;
       5: iload_1
       6: invokestatic  #878                // Method android/support/v7/c/a/b.b:(Landroid/content/Context;I)Landroid/graphics/drawable/Drawable;
       9: invokevirtual #279                // Method setNavigationIcon:(Landroid/graphics/drawable/Drawable;)V
      12: return

  public void setNavigationIcon(android.graphics.drawable.Drawable);
    Code:
       0: aload_1
       1: ifnull        31
       4: aload_0
       5: invokespecial #897                // Method p:()V
       8: aload_0
       9: aload_0
      10: getfield      #547                // Field h:Landroid/widget/ImageButton;
      13: invokespecial #882                // Method d:(Landroid/view/View;)Z
      16: ifne          69
      19: aload_0
      20: aload_0
      21: getfield      #547                // Field h:Landroid/widget/ImageButton;
      24: iconst_1
      25: invokespecial #545                // Method a:(Landroid/view/View;Z)V
      28: goto          69
      31: aload_0
      32: getfield      #547                // Field h:Landroid/widget/ImageButton;
      35: ifnull        69
      38: aload_0
      39: aload_0
      40: getfield      #547                // Field h:Landroid/widget/ImageButton;
      43: invokespecial #882                // Method d:(Landroid/view/View;)Z
      46: ifeq          69
      49: aload_0
      50: aload_0
      51: getfield      #547                // Field h:Landroid/widget/ImageButton;
      54: invokevirtual #885                // Method removeView:(Landroid/view/View;)V
      57: aload_0
      58: getfield      #109                // Field F:Ljava/util/ArrayList;
      61: aload_0
      62: getfield      #547                // Field h:Landroid/widget/ImageButton;
      65: invokevirtual #888                // Method java/util/ArrayList.remove:(Ljava/lang/Object;)Z
      68: pop
      69: aload_0
      70: getfield      #547                // Field h:Landroid/widget/ImageButton;
      73: ifnull        84
      76: aload_0
      77: getfield      #547                // Field h:Landroid/widget/ImageButton;
      80: aload_1
      81: invokevirtual #722                // Method android/widget/ImageButton.setImageDrawable:(Landroid/graphics/drawable/Drawable;)V
      84: return

  public void setNavigationOnClickListener(android.view.View$OnClickListener);
    Code:
       0: aload_0
       1: invokespecial #897                // Method p:()V
       4: aload_0
       5: getfield      #547                // Field h:Landroid/widget/ImageButton;
       8: aload_1
       9: invokevirtual #730                // Method android/widget/ImageButton.setOnClickListener:(Landroid/view/View$OnClickListener;)V
      12: return

  public void setOnMenuItemClickListener(android.support.v7.widget.Toolbar$c);
    Code:
       0: aload_0
       1: aload_1
       2: putfield      #901                // Field d:Landroid/support/v7/widget/Toolbar$c;
       5: return

  public void setOverflowIcon(android.graphics.drawable.Drawable);
    Code:
       0: aload_0
       1: invokespecial #683                // Method n:()V
       4: aload_0
       5: getfield      #505                // Field e:Landroid/support/v7/widget/ActionMenuView;
       8: aload_1
       9: invokevirtual #904                // Method android/support/v7/widget/ActionMenuView.setOverflowIcon:(Landroid/graphics/drawable/Drawable;)V
      12: return

  public void setPopupTheme(int);
    Code:
       0: aload_0
       1: getfield      #529                // Field m:I
       4: iload_1
       5: if_icmpeq     42
       8: aload_0
       9: iload_1
      10: putfield      #529                // Field m:I
      13: iload_1
      14: ifne          26
      17: aload_0
      18: aload_0
      19: invokevirtual #123                // Method getContext:()Landroid/content/Context;
      22: putfield      #265                // Field l:Landroid/content/Context;
      25: return
      26: aload_0
      27: new           #906                // class android/view/ContextThemeWrapper
      30: dup
      31: aload_0
      32: invokevirtual #123                // Method getContext:()Landroid/content/Context;
      35: iload_1
      36: invokespecial #908                // Method android/view/ContextThemeWrapper."<init>":(Landroid/content/Context;I)V
      39: putfield      #265                // Field l:Landroid/content/Context;
      42: return

  public void setSubtitle(int);
    Code:
       0: aload_0
       1: aload_0
       2: invokevirtual #123                // Method getContext:()Landroid/content/Context;
       5: iload_1
       6: invokevirtual #894                // Method android/content/Context.getText:(I)Ljava/lang/CharSequence;
       9: invokevirtual #263                // Method setSubtitle:(Ljava/lang/CharSequence;)V
      12: return

  public void setSubtitle(java.lang.CharSequence);
    Code:
       0: aload_1
       1: invokestatic  #253                // Method android/text/TextUtils.isEmpty:(Ljava/lang/CharSequence;)Z
       4: ifne          108
       7: aload_0
       8: getfield      #617                // Field g:Landroid/widget/TextView;
      11: ifnonnull     85
      14: aload_0
      15: invokevirtual #123                // Method getContext:()Landroid/content/Context;
      18: astore_2
      19: aload_0
      20: new           #910                // class android/support/v7/widget/ac
      23: dup
      24: aload_2
      25: invokespecial #911                // Method android/support/v7/widget/ac."<init>":(Landroid/content/Context;)V
      28: putfield      #617                // Field g:Landroid/widget/TextView;
      31: aload_0
      32: getfield      #617                // Field g:Landroid/widget/TextView;
      35: invokevirtual #914                // Method android/widget/TextView.setSingleLine:()V
      38: aload_0
      39: getfield      #617                // Field g:Landroid/widget/TextView;
      42: getstatic     #920                // Field android/text/TextUtils$TruncateAt.END:Landroid/text/TextUtils$TruncateAt;
      45: invokevirtual #924                // Method android/widget/TextView.setEllipsize:(Landroid/text/TextUtils$TruncateAt;)V
      48: aload_0
      49: getfield      #146                // Field o:I
      52: ifeq          67
      55: aload_0
      56: getfield      #617                // Field g:Landroid/widget/TextView;
      59: aload_2
      60: aload_0
      61: getfield      #146                // Field o:I
      64: invokevirtual #591                // Method android/widget/TextView.setTextAppearance:(Landroid/content/Context;I)V
      67: aload_0
      68: getfield      #926                // Field B:I
      71: ifeq          85
      74: aload_0
      75: getfield      #617                // Field g:Landroid/widget/TextView;
      78: aload_0
      79: getfield      #926                // Field B:I
      82: invokevirtual #929                // Method android/widget/TextView.setTextColor:(I)V
      85: aload_0
      86: aload_0
      87: getfield      #617                // Field g:Landroid/widget/TextView;
      90: invokespecial #882                // Method d:(Landroid/view/View;)Z
      93: ifne          146
      96: aload_0
      97: aload_0
      98: getfield      #617                // Field g:Landroid/widget/TextView;
     101: iconst_1
     102: invokespecial #545                // Method a:(Landroid/view/View;Z)V
     105: goto          146
     108: aload_0
     109: getfield      #617                // Field g:Landroid/widget/TextView;
     112: ifnull        146
     115: aload_0
     116: aload_0
     117: getfield      #617                // Field g:Landroid/widget/TextView;
     120: invokespecial #882                // Method d:(Landroid/view/View;)Z
     123: ifeq          146
     126: aload_0
     127: aload_0
     128: getfield      #617                // Field g:Landroid/widget/TextView;
     131: invokevirtual #885                // Method removeView:(Landroid/view/View;)V
     134: aload_0
     135: getfield      #109                // Field F:Ljava/util/ArrayList;
     138: aload_0
     139: getfield      #617                // Field g:Landroid/widget/TextView;
     142: invokevirtual #888                // Method java/util/ArrayList.remove:(Ljava/lang/Object;)Z
     145: pop
     146: aload_0
     147: getfield      #617                // Field g:Landroid/widget/TextView;
     150: ifnull        161
     153: aload_0
     154: getfield      #617                // Field g:Landroid/widget/TextView;
     157: aload_1
     158: invokevirtual #932                // Method android/widget/TextView.setText:(Ljava/lang/CharSequence;)V
     161: aload_0
     162: aload_1
     163: putfield      #696                // Field z:Ljava/lang/CharSequence;
     166: return

  public void setSubtitleTextColor(int);
    Code:
       0: aload_0
       1: iload_1
       2: putfield      #926                // Field B:I
       5: aload_0
       6: getfield      #617                // Field g:Landroid/widget/TextView;
       9: ifnull        20
      12: aload_0
      13: getfield      #617                // Field g:Landroid/widget/TextView;
      16: iload_1
      17: invokevirtual #929                // Method android/widget/TextView.setTextColor:(I)V
      20: return

  public void setTitle(int);
    Code:
       0: aload_0
       1: aload_0
       2: invokevirtual #123                // Method getContext:()Landroid/content/Context;
       5: iload_1
       6: invokevirtual #894                // Method android/content/Context.getText:(I)Ljava/lang/CharSequence;
       9: invokevirtual #257                // Method setTitle:(Ljava/lang/CharSequence;)V
      12: return

  public void setTitle(java.lang.CharSequence);
    Code:
       0: aload_1
       1: invokestatic  #253                // Method android/text/TextUtils.isEmpty:(Ljava/lang/CharSequence;)Z
       4: ifne          108
       7: aload_0
       8: getfield      #586                // Field f:Landroid/widget/TextView;
      11: ifnonnull     85
      14: aload_0
      15: invokevirtual #123                // Method getContext:()Landroid/content/Context;
      18: astore_2
      19: aload_0
      20: new           #910                // class android/support/v7/widget/ac
      23: dup
      24: aload_2
      25: invokespecial #911                // Method android/support/v7/widget/ac."<init>":(Landroid/content/Context;)V
      28: putfield      #586                // Field f:Landroid/widget/TextView;
      31: aload_0
      32: getfield      #586                // Field f:Landroid/widget/TextView;
      35: invokevirtual #914                // Method android/widget/TextView.setSingleLine:()V
      38: aload_0
      39: getfield      #586                // Field f:Landroid/widget/TextView;
      42: getstatic     #920                // Field android/text/TextUtils$TruncateAt.END:Landroid/text/TextUtils$TruncateAt;
      45: invokevirtual #924                // Method android/widget/TextView.setEllipsize:(Landroid/text/TextUtils$TruncateAt;)V
      48: aload_0
      49: getfield      #141                // Field n:I
      52: ifeq          67
      55: aload_0
      56: getfield      #586                // Field f:Landroid/widget/TextView;
      59: aload_2
      60: aload_0
      61: getfield      #141                // Field n:I
      64: invokevirtual #591                // Method android/widget/TextView.setTextAppearance:(Landroid/content/Context;I)V
      67: aload_0
      68: getfield      #934                // Field A:I
      71: ifeq          85
      74: aload_0
      75: getfield      #586                // Field f:Landroid/widget/TextView;
      78: aload_0
      79: getfield      #934                // Field A:I
      82: invokevirtual #929                // Method android/widget/TextView.setTextColor:(I)V
      85: aload_0
      86: aload_0
      87: getfield      #586                // Field f:Landroid/widget/TextView;
      90: invokespecial #882                // Method d:(Landroid/view/View;)Z
      93: ifne          146
      96: aload_0
      97: aload_0
      98: getfield      #586                // Field f:Landroid/widget/TextView;
     101: iconst_1
     102: invokespecial #545                // Method a:(Landroid/view/View;Z)V
     105: goto          146
     108: aload_0
     109: getfield      #586                // Field f:Landroid/widget/TextView;
     112: ifnull        146
     115: aload_0
     116: aload_0
     117: getfield      #586                // Field f:Landroid/widget/TextView;
     120: invokespecial #882                // Method d:(Landroid/view/View;)Z
     123: ifeq          146
     126: aload_0
     127: aload_0
     128: getfield      #586                // Field f:Landroid/widget/TextView;
     131: invokevirtual #885                // Method removeView:(Landroid/view/View;)V
     134: aload_0
     135: getfield      #109                // Field F:Ljava/util/ArrayList;
     138: aload_0
     139: getfield      #586                // Field f:Landroid/widget/TextView;
     142: invokevirtual #888                // Method java/util/ArrayList.remove:(Ljava/lang/Object;)Z
     145: pop
     146: aload_0
     147: getfield      #586                // Field f:Landroid/widget/TextView;
     150: ifnull        161
     153: aload_0
     154: getfield      #586                // Field f:Landroid/widget/TextView;
     157: aload_1
     158: invokevirtual #932                // Method android/widget/TextView.setText:(Ljava/lang/CharSequence;)V
     161: aload_0
     162: aload_1
     163: putfield      #699                // Field y:Ljava/lang/CharSequence;
     166: return

  public void setTitleMarginBottom(int);
    Code:
       0: aload_0
       1: iload_1
       2: putfield      #169                // Field t:I
       5: aload_0
       6: invokevirtual #871                // Method requestLayout:()V
       9: return

  public void setTitleMarginEnd(int);
    Code:
       0: aload_0
       1: iload_1
       2: putfield      #173                // Field r:I
       5: aload_0
       6: invokevirtual #871                // Method requestLayout:()V
       9: return

  public void setTitleMarginStart(int);
    Code:
       0: aload_0
       1: iload_1
       2: putfield      #175                // Field q:I
       5: aload_0
       6: invokevirtual #871                // Method requestLayout:()V
       9: return

  public void setTitleMarginTop(int);
    Code:
       0: aload_0
       1: iload_1
       2: putfield      #171                // Field s:I
       5: aload_0
       6: invokevirtual #871                // Method requestLayout:()V
       9: return

  public void setTitleTextColor(int);
    Code:
       0: aload_0
       1: iload_1
       2: putfield      #934                // Field A:I
       5: aload_0
       6: getfield      #586                // Field f:Landroid/widget/TextView;
       9: ifnull        20
      12: aload_0
      13: getfield      #586                // Field f:Landroid/widget/TextView;
      16: iload_1
      17: invokevirtual #929                // Method android/widget/TextView.setTextColor:(I)V
      20: return
}
