public class android.support.v7.widget.v extends android.widget.RadioButton implements android.support.v4.widget.n {
  public android.support.v7.widget.v(android.content.Context, android.util.AttributeSet);
    Code:
       0: aload_0
       1: aload_1
       2: aload_2
       3: getstatic     #18                 // Field android/support/v7/a/a$a.radioButtonStyle:I
       6: invokespecial #21                 // Method "<init>":(Landroid/content/Context;Landroid/util/AttributeSet;I)V
       9: return

  public android.support.v7.widget.v(android.content.Context, android.util.AttributeSet, int);
    Code:
       0: aload_0
       1: aload_1
       2: invokestatic  #27                 // Method android/support/v7/widget/bm.a:(Landroid/content/Context;)Landroid/content/Context;
       5: aload_2
       6: iload_3
       7: invokespecial #28                 // Method android/widget/RadioButton."<init>":(Landroid/content/Context;Landroid/util/AttributeSet;I)V
      10: aload_0
      11: new           #30                 // class android/support/v7/widget/l
      14: dup
      15: aload_0
      16: invokespecial #33                 // Method android/support/v7/widget/l."<init>":(Landroid/widget/CompoundButton;)V
      19: putfield      #35                 // Field a:Landroid/support/v7/widget/l;
      22: aload_0
      23: getfield      #35                 // Field a:Landroid/support/v7/widget/l;
      26: aload_2
      27: iload_3
      28: invokevirtual #38                 // Method android/support/v7/widget/l.a:(Landroid/util/AttributeSet;I)V
      31: aload_0
      32: new           #40                 // class android/support/v7/widget/aa
      35: dup
      36: aload_0
      37: invokespecial #43                 // Method android/support/v7/widget/aa."<init>":(Landroid/widget/TextView;)V
      40: putfield      #45                 // Field b:Landroid/support/v7/widget/aa;
      43: aload_0
      44: getfield      #45                 // Field b:Landroid/support/v7/widget/aa;
      47: aload_2
      48: iload_3
      49: invokevirtual #46                 // Method android/support/v7/widget/aa.a:(Landroid/util/AttributeSet;I)V
      52: return

  public int getCompoundPaddingLeft();
    Code:
       0: aload_0
       1: invokespecial #50                 // Method android/widget/RadioButton.getCompoundPaddingLeft:()I
       4: istore_2
       5: iload_2
       6: istore_1
       7: aload_0
       8: getfield      #35                 // Field a:Landroid/support/v7/widget/l;
      11: ifnull        23
      14: aload_0
      15: getfield      #35                 // Field a:Landroid/support/v7/widget/l;
      18: iload_2
      19: invokevirtual #53                 // Method android/support/v7/widget/l.a:(I)I
      22: istore_1
      23: iload_1
      24: ireturn

  public android.content.res.ColorStateList getSupportButtonTintList();
    Code:
       0: aload_0
       1: getfield      #35                 // Field a:Landroid/support/v7/widget/l;
       4: ifnull        15
       7: aload_0
       8: getfield      #35                 // Field a:Landroid/support/v7/widget/l;
      11: invokevirtual #57                 // Method android/support/v7/widget/l.a:()Landroid/content/res/ColorStateList;
      14: areturn
      15: aconst_null
      16: areturn

  public android.graphics.PorterDuff$Mode getSupportButtonTintMode();
    Code:
       0: aload_0
       1: getfield      #35                 // Field a:Landroid/support/v7/widget/l;
       4: ifnull        15
       7: aload_0
       8: getfield      #35                 // Field a:Landroid/support/v7/widget/l;
      11: invokevirtual #61                 // Method android/support/v7/widget/l.b:()Landroid/graphics/PorterDuff$Mode;
      14: areturn
      15: aconst_null
      16: areturn

  public void setButtonDrawable(int);
    Code:
       0: aload_0
       1: aload_0
       2: invokevirtual #67                 // Method getContext:()Landroid/content/Context;
       5: iload_1
       6: invokestatic  #72                 // Method android/support/v7/c/a/b.b:(Landroid/content/Context;I)Landroid/graphics/drawable/Drawable;
       9: invokevirtual #75                 // Method setButtonDrawable:(Landroid/graphics/drawable/Drawable;)V
      12: return

  public void setButtonDrawable(android.graphics.drawable.Drawable);
    Code:
       0: aload_0
       1: aload_1
       2: invokespecial #76                 // Method android/widget/RadioButton.setButtonDrawable:(Landroid/graphics/drawable/Drawable;)V
       5: aload_0
       6: getfield      #35                 // Field a:Landroid/support/v7/widget/l;
       9: ifnull        19
      12: aload_0
      13: getfield      #35                 // Field a:Landroid/support/v7/widget/l;
      16: invokevirtual #80                 // Method android/support/v7/widget/l.c:()V
      19: return

  public void setSupportButtonTintList(android.content.res.ColorStateList);
    Code:
       0: aload_0
       1: getfield      #35                 // Field a:Landroid/support/v7/widget/l;
       4: ifnull        15
       7: aload_0
       8: getfield      #35                 // Field a:Landroid/support/v7/widget/l;
      11: aload_1
      12: invokevirtual #84                 // Method android/support/v7/widget/l.a:(Landroid/content/res/ColorStateList;)V
      15: return

  public void setSupportButtonTintMode(android.graphics.PorterDuff$Mode);
    Code:
       0: aload_0
       1: getfield      #35                 // Field a:Landroid/support/v7/widget/l;
       4: ifnull        15
       7: aload_0
       8: getfield      #35                 // Field a:Landroid/support/v7/widget/l;
      11: aload_1
      12: invokevirtual #88                 // Method android/support/v7/widget/l.a:(Landroid/graphics/PorterDuff$Mode;)V
      15: return
}
