public class android.support.v7.widget.x extends android.widget.SeekBar {
  public android.support.v7.widget.x(android.content.Context, android.util.AttributeSet);
    Code:
       0: aload_0
       1: aload_1
       2: aload_2
       3: getstatic     #14                 // Field android/support/v7/a/a$a.seekBarStyle:I
       6: invokespecial #17                 // Method "<init>":(Landroid/content/Context;Landroid/util/AttributeSet;I)V
       9: return

  public android.support.v7.widget.x(android.content.Context, android.util.AttributeSet, int);
    Code:
       0: aload_0
       1: aload_1
       2: aload_2
       3: iload_3
       4: invokespecial #19                 // Method android/widget/SeekBar."<init>":(Landroid/content/Context;Landroid/util/AttributeSet;I)V
       7: aload_0
       8: new           #21                 // class android/support/v7/widget/y
      11: dup
      12: aload_0
      13: invokespecial #24                 // Method android/support/v7/widget/y."<init>":(Landroid/widget/SeekBar;)V
      16: putfield      #26                 // Field a:Landroid/support/v7/widget/y;
      19: aload_0
      20: getfield      #26                 // Field a:Landroid/support/v7/widget/y;
      23: aload_2
      24: iload_3
      25: invokevirtual #29                 // Method android/support/v7/widget/y.a:(Landroid/util/AttributeSet;I)V
      28: return

  protected void drawableStateChanged();
    Code:
       0: aload_0
       1: invokespecial #33                 // Method android/widget/SeekBar.drawableStateChanged:()V
       4: aload_0
       5: getfield      #26                 // Field a:Landroid/support/v7/widget/y;
       8: invokevirtual #36                 // Method android/support/v7/widget/y.c:()V
      11: return

  public void jumpDrawablesToCurrentState();
    Code:
       0: aload_0
       1: invokespecial #39                 // Method android/widget/SeekBar.jumpDrawablesToCurrentState:()V
       4: aload_0
       5: getfield      #26                 // Field a:Landroid/support/v7/widget/y;
       8: invokevirtual #42                 // Method android/support/v7/widget/y.b:()V
      11: return

  protected void onDraw(android.graphics.Canvas);
    Code:
       0: aload_0
       1: monitorenter
       2: aload_0
       3: aload_1
       4: invokespecial #46                 // Method android/widget/SeekBar.onDraw:(Landroid/graphics/Canvas;)V
       7: aload_0
       8: getfield      #26                 // Field a:Landroid/support/v7/widget/y;
      11: aload_1
      12: invokevirtual #48                 // Method android/support/v7/widget/y.a:(Landroid/graphics/Canvas;)V
      15: aload_0
      16: monitorexit
      17: return
      18: astore_1
      19: aload_0
      20: monitorexit
      21: aload_1
      22: athrow
    Exception table:
       from    to  target type
           2    15    18   any
}
