class android.support.v7.widget.y extends android.support.v7.widget.u {
  android.support.v7.widget.y(android.widget.SeekBar);
    Code:
       0: aload_0
       1: aload_1
       2: invokespecial #20                 // Method android/support/v7/widget/u."<init>":(Landroid/widget/ProgressBar;)V
       5: aload_0
       6: aconst_null
       7: putfield      #22                 // Field c:Landroid/content/res/ColorStateList;
      10: aload_0
      11: aconst_null
      12: putfield      #24                 // Field d:Landroid/graphics/PorterDuff$Mode;
      15: aload_0
      16: iconst_0
      17: putfield      #26                 // Field e:Z
      20: aload_0
      21: iconst_0
      22: putfield      #28                 // Field f:Z
      25: aload_0
      26: aload_1
      27: putfield      #30                 // Field a:Landroid/widget/SeekBar;
      30: return

  void a(android.graphics.Canvas);
    Code:
       0: aload_0
       1: getfield      #34                 // Field b:Landroid/graphics/drawable/Drawable;
       4: ifnull        173
       7: aload_0
       8: getfield      #30                 // Field a:Landroid/widget/SeekBar;
      11: invokevirtual #70                 // Method android/widget/SeekBar.getMax:()I
      14: istore        5
      16: iconst_1
      17: istore        4
      19: iload         5
      21: iconst_1
      22: if_icmple     173
      25: aload_0
      26: getfield      #34                 // Field b:Landroid/graphics/drawable/Drawable;
      29: invokevirtual #73                 // Method android/graphics/drawable/Drawable.getIntrinsicWidth:()I
      32: istore_3
      33: aload_0
      34: getfield      #34                 // Field b:Landroid/graphics/drawable/Drawable;
      37: invokevirtual #76                 // Method android/graphics/drawable/Drawable.getIntrinsicHeight:()I
      40: istore        6
      42: iload_3
      43: iflt          53
      46: iload_3
      47: iconst_2
      48: idiv
      49: istore_3
      50: goto          55
      53: iconst_1
      54: istore_3
      55: iload         6
      57: iflt          66
      60: iload         6
      62: iconst_2
      63: idiv
      64: istore        4
      66: aload_0
      67: getfield      #34                 // Field b:Landroid/graphics/drawable/Drawable;
      70: iload_3
      71: ineg
      72: iload         4
      74: ineg
      75: iload_3
      76: iload         4
      78: invokevirtual #80                 // Method android/graphics/drawable/Drawable.setBounds:(IIII)V
      81: aload_0
      82: getfield      #30                 // Field a:Landroid/widget/SeekBar;
      85: invokevirtual #83                 // Method android/widget/SeekBar.getWidth:()I
      88: aload_0
      89: getfield      #30                 // Field a:Landroid/widget/SeekBar;
      92: invokevirtual #86                 // Method android/widget/SeekBar.getPaddingLeft:()I
      95: isub
      96: aload_0
      97: getfield      #30                 // Field a:Landroid/widget/SeekBar;
     100: invokevirtual #89                 // Method android/widget/SeekBar.getPaddingRight:()I
     103: isub
     104: i2f
     105: iload         5
     107: i2f
     108: fdiv
     109: fstore_2
     110: aload_1
     111: invokevirtual #94                 // Method android/graphics/Canvas.save:()I
     114: istore        4
     116: aload_1
     117: aload_0
     118: getfield      #30                 // Field a:Landroid/widget/SeekBar;
     121: invokevirtual #86                 // Method android/widget/SeekBar.getPaddingLeft:()I
     124: i2f
     125: aload_0
     126: getfield      #30                 // Field a:Landroid/widget/SeekBar;
     129: invokevirtual #97                 // Method android/widget/SeekBar.getHeight:()I
     132: iconst_2
     133: idiv
     134: i2f
     135: invokevirtual #101                // Method android/graphics/Canvas.translate:(FF)V
     138: iconst_0
     139: istore_3
     140: iload_3
     141: iload         5
     143: if_icmpgt     167
     146: aload_0
     147: getfield      #34                 // Field b:Landroid/graphics/drawable/Drawable;
     150: aload_1
     151: invokevirtual #104                // Method android/graphics/drawable/Drawable.draw:(Landroid/graphics/Canvas;)V
     154: aload_1
     155: fload_2
     156: fconst_0
     157: invokevirtual #101                // Method android/graphics/Canvas.translate:(FF)V
     160: iload_3
     161: iconst_1
     162: iadd
     163: istore_3
     164: goto          140
     167: aload_1
     168: iload         4
     170: invokevirtual #108                // Method android/graphics/Canvas.restoreToCount:(I)V
     173: return

  void a(android.graphics.drawable.Drawable);
    Code:
       0: aload_0
       1: getfield      #34                 // Field b:Landroid/graphics/drawable/Drawable;
       4: ifnull        15
       7: aload_0
       8: getfield      #34                 // Field b:Landroid/graphics/drawable/Drawable;
      11: aconst_null
      12: invokevirtual #113                // Method android/graphics/drawable/Drawable.setCallback:(Landroid/graphics/drawable/Drawable$Callback;)V
      15: aload_0
      16: aload_1
      17: putfield      #34                 // Field b:Landroid/graphics/drawable/Drawable;
      20: aload_1
      21: ifnull        67
      24: aload_1
      25: aload_0
      26: getfield      #30                 // Field a:Landroid/widget/SeekBar;
      29: invokevirtual #113                // Method android/graphics/drawable/Drawable.setCallback:(Landroid/graphics/drawable/Drawable$Callback;)V
      32: aload_1
      33: aload_0
      34: getfield      #30                 // Field a:Landroid/widget/SeekBar;
      37: invokestatic  #118                // Method android/support/v4/view/s.e:(Landroid/view/View;)I
      40: invokestatic  #121                // Method android/support/v4/b/a/a.b:(Landroid/graphics/drawable/Drawable;I)Z
      43: pop
      44: aload_1
      45: invokevirtual #55                 // Method android/graphics/drawable/Drawable.isStateful:()Z
      48: ifeq          63
      51: aload_1
      52: aload_0
      53: getfield      #30                 // Field a:Landroid/widget/SeekBar;
      56: invokevirtual #61                 // Method android/widget/SeekBar.getDrawableState:()[I
      59: invokevirtual #65                 // Method android/graphics/drawable/Drawable.setState:([I)Z
      62: pop
      63: aload_0
      64: invokespecial #123                // Method d:()V
      67: aload_0
      68: getfield      #30                 // Field a:Landroid/widget/SeekBar;
      71: invokevirtual #126                // Method android/widget/SeekBar.invalidate:()V
      74: return

  void a(android.util.AttributeSet, int);
    Code:
       0: aload_0
       1: aload_1
       2: iload_2
       3: invokespecial #129                // Method android/support/v7/widget/u.a:(Landroid/util/AttributeSet;I)V
       6: aload_0
       7: getfield      #30                 // Field a:Landroid/widget/SeekBar;
      10: invokevirtual #133                // Method android/widget/SeekBar.getContext:()Landroid/content/Context;
      13: aload_1
      14: getstatic     #139                // Field android/support/v7/a/a$j.AppCompatSeekBar:[I
      17: iload_2
      18: iconst_0
      19: invokestatic  #144                // Method android/support/v7/widget/bp.a:(Landroid/content/Context;Landroid/util/AttributeSet;[III)Landroid/support/v7/widget/bp;
      22: astore_1
      23: aload_1
      24: getstatic     #148                // Field android/support/v7/a/a$j.AppCompatSeekBar_android_thumb:I
      27: invokevirtual #151                // Method android/support/v7/widget/bp.b:(I)Landroid/graphics/drawable/Drawable;
      30: astore_3
      31: aload_3
      32: ifnull        43
      35: aload_0
      36: getfield      #30                 // Field a:Landroid/widget/SeekBar;
      39: aload_3
      40: invokevirtual #154                // Method android/widget/SeekBar.setThumb:(Landroid/graphics/drawable/Drawable;)V
      43: aload_0
      44: aload_1
      45: getstatic     #157                // Field android/support/v7/a/a$j.AppCompatSeekBar_tickMark:I
      48: invokevirtual #159                // Method android/support/v7/widget/bp.a:(I)Landroid/graphics/drawable/Drawable;
      51: invokevirtual #161                // Method a:(Landroid/graphics/drawable/Drawable;)V
      54: aload_1
      55: getstatic     #164                // Field android/support/v7/a/a$j.AppCompatSeekBar_tickMarkTintMode:I
      58: invokevirtual #168                // Method android/support/v7/widget/bp.g:(I)Z
      61: ifeq          88
      64: aload_0
      65: aload_1
      66: getstatic     #164                // Field android/support/v7/a/a$j.AppCompatSeekBar_tickMarkTintMode:I
      69: iconst_m1
      70: invokevirtual #171                // Method android/support/v7/widget/bp.a:(II)I
      73: aload_0
      74: getfield      #24                 // Field d:Landroid/graphics/PorterDuff$Mode;
      77: invokestatic  #176                // Method android/support/v7/widget/ao.a:(ILandroid/graphics/PorterDuff$Mode;)Landroid/graphics/PorterDuff$Mode;
      80: putfield      #24                 // Field d:Landroid/graphics/PorterDuff$Mode;
      83: aload_0
      84: iconst_1
      85: putfield      #28                 // Field f:Z
      88: aload_1
      89: getstatic     #179                // Field android/support/v7/a/a$j.AppCompatSeekBar_tickMarkTint:I
      92: invokevirtual #168                // Method android/support/v7/widget/bp.g:(I)Z
      95: ifeq          114
      98: aload_0
      99: aload_1
     100: getstatic     #179                // Field android/support/v7/a/a$j.AppCompatSeekBar_tickMarkTint:I
     103: invokevirtual #182                // Method android/support/v7/widget/bp.e:(I)Landroid/content/res/ColorStateList;
     106: putfield      #22                 // Field c:Landroid/content/res/ColorStateList;
     109: aload_0
     110: iconst_1
     111: putfield      #26                 // Field e:Z
     114: aload_1
     115: invokevirtual #184                // Method android/support/v7/widget/bp.a:()V
     118: aload_0
     119: invokespecial #123                // Method d:()V
     122: return

  void b();
    Code:
       0: aload_0
       1: getfield      #34                 // Field b:Landroid/graphics/drawable/Drawable;
       4: ifnull        14
       7: aload_0
       8: getfield      #34                 // Field b:Landroid/graphics/drawable/Drawable;
      11: invokevirtual #187                // Method android/graphics/drawable/Drawable.jumpToCurrentState:()V
      14: return

  void c();
    Code:
       0: aload_0
       1: getfield      #34                 // Field b:Landroid/graphics/drawable/Drawable;
       4: astore_1
       5: aload_1
       6: ifnull        38
       9: aload_1
      10: invokevirtual #55                 // Method android/graphics/drawable/Drawable.isStateful:()Z
      13: ifeq          38
      16: aload_1
      17: aload_0
      18: getfield      #30                 // Field a:Landroid/widget/SeekBar;
      21: invokevirtual #61                 // Method android/widget/SeekBar.getDrawableState:()[I
      24: invokevirtual #65                 // Method android/graphics/drawable/Drawable.setState:([I)Z
      27: ifeq          38
      30: aload_0
      31: getfield      #30                 // Field a:Landroid/widget/SeekBar;
      34: aload_1
      35: invokevirtual #190                // Method android/widget/SeekBar.invalidateDrawable:(Landroid/graphics/drawable/Drawable;)V
      38: return
}
