public class android.support.v7.widget.z extends android.widget.Spinner implements android.support.v4.view.r {
  static {};
    Code:
       0: iconst_1
       1: newarray       int
       3: dup
       4: iconst_0
       5: ldc           #39                 // int 16843505
       7: iastore
       8: putstatic     #41                 // Field a:[I
      11: return

  public android.support.v7.widget.z(android.content.Context, android.util.AttributeSet);
    Code:
       0: aload_0
       1: aload_1
       2: aload_2
       3: getstatic     #49                 // Field android/support/v7/a/a$a.spinnerStyle:I
       6: invokespecial #52                 // Method "<init>":(Landroid/content/Context;Landroid/util/AttributeSet;I)V
       9: return

  public android.support.v7.widget.z(android.content.Context, android.util.AttributeSet, int);
    Code:
       0: aload_0
       1: aload_1
       2: aload_2
       3: iload_3
       4: iconst_m1
       5: invokespecial #55                 // Method "<init>":(Landroid/content/Context;Landroid/util/AttributeSet;II)V
       8: return

  public android.support.v7.widget.z(android.content.Context, android.util.AttributeSet, int, int);
    Code:
       0: aload_0
       1: aload_1
       2: aload_2
       3: iload_3
       4: iload         4
       6: aconst_null
       7: invokespecial #58                 // Method "<init>":(Landroid/content/Context;Landroid/util/AttributeSet;IILandroid/content/res/Resources$Theme;)V
      10: return

  public android.support.v7.widget.z(android.content.Context, android.util.AttributeSet, int, int, android.content.res.Resources$Theme);
    Code:
       0: aload_0
       1: aload_1
       2: aload_2
       3: iload_3
       4: invokespecial #61                 // Method android/widget/Spinner."<init>":(Landroid/content/Context;Landroid/util/AttributeSet;I)V
       7: aload_0
       8: new           #63                 // class android/graphics/Rect
      11: dup
      12: invokespecial #65                 // Method android/graphics/Rect."<init>":()V
      15: putfield      #67                 // Field i:Landroid/graphics/Rect;
      18: aload_1
      19: aload_2
      20: getstatic     #72                 // Field android/support/v7/a/a$j.Spinner:[I
      23: iload_3
      24: iconst_0
      25: invokestatic  #77                 // Method android/support/v7/widget/bp.a:(Landroid/content/Context;Landroid/util/AttributeSet;[III)Landroid/support/v7/widget/bp;
      28: astore        10
      30: aload_0
      31: new           #79                 // class android/support/v7/widget/h
      34: dup
      35: aload_0
      36: invokespecial #82                 // Method android/support/v7/widget/h."<init>":(Landroid/view/View;)V
      39: putfield      #84                 // Field b:Landroid/support/v7/widget/h;
      42: aload         5
      44: ifnull        68
      47: new           #86                 // class android/support/v7/view/d
      50: dup
      51: aload_1
      52: aload         5
      54: invokespecial #89                 // Method android/support/v7/view/d."<init>":(Landroid/content/Context;Landroid/content/res/Resources$Theme;)V
      57: astore        5
      59: aload_0
      60: aload         5
      62: putfield      #91                 // Field c:Landroid/content/Context;
      65: goto          122
      68: aload         10
      70: getstatic     #94                 // Field android/support/v7/a/a$j.Spinner_popupTheme:I
      73: iconst_0
      74: invokevirtual #97                 // Method android/support/v7/widget/bp.g:(II)I
      77: istore        6
      79: iload         6
      81: ifeq          99
      84: new           #86                 // class android/support/v7/view/d
      87: dup
      88: aload_1
      89: iload         6
      91: invokespecial #100                // Method android/support/v7/view/d."<init>":(Landroid/content/Context;I)V
      94: astore        5
      96: goto          59
      99: getstatic     #105                // Field android/os/Build$VERSION.SDK_INT:I
     102: bipush        23
     104: if_icmpge     113
     107: aload_1
     108: astore        5
     110: goto          116
     113: aconst_null
     114: astore        5
     116: aload_0
     117: aload         5
     119: putfield      #91                 // Field c:Landroid/content/Context;
     122: aload_0
     123: getfield      #91                 // Field c:Landroid/content/Context;
     126: ifnull        365
     129: iload         4
     131: istore        7
     133: iload         4
     135: iconst_m1
     136: if_icmpne     262
     139: aload_1
     140: aload_2
     141: getstatic     #41                 // Field a:[I
     144: iload_3
     145: iconst_0
     146: invokevirtual #111                // Method android/content/Context.obtainStyledAttributes:(Landroid/util/AttributeSet;[III)Landroid/content/res/TypedArray;
     149: astore        5
     151: iload         4
     153: istore        6
     155: aload         5
     157: astore        8
     159: aload         5
     161: iconst_0
     162: invokevirtual #117                // Method android/content/res/TypedArray.hasValue:(I)Z
     165: ifeq          181
     168: aload         5
     170: astore        8
     172: aload         5
     174: iconst_0
     175: iconst_0
     176: invokevirtual #120                // Method android/content/res/TypedArray.getInt:(II)I
     179: istore        6
     181: iload         6
     183: istore        7
     185: aload         5
     187: ifnull        262
     190: iload         6
     192: istore        4
     194: aload         5
     196: invokevirtual #123                // Method android/content/res/TypedArray.recycle:()V
     199: iload         4
     201: istore        7
     203: goto          262
     206: astore        9
     208: goto          223
     211: astore_1
     212: aconst_null
     213: astore        8
     215: goto          250
     218: astore        9
     220: aconst_null
     221: astore        5
     223: aload         5
     225: astore        8
     227: ldc           #125                // String AppCompatSpinner
     229: ldc           #127                // String Could not read android:spinnerMode
     231: aload         9
     233: invokestatic  #132                // Method android/util/Log.i:(Ljava/lang/String;Ljava/lang/String;Ljava/lang/Throwable;)I
     236: pop
     237: iload         4
     239: istore        7
     241: aload         5
     243: ifnull        262
     246: goto          194
     249: astore_1
     250: aload         8
     252: ifnull        260
     255: aload         8
     257: invokevirtual #123                // Method android/content/res/TypedArray.recycle:()V
     260: aload_1
     261: athrow
     262: iload         7
     264: iconst_1
     265: if_icmpne     365
     268: new           #13                 // class android/support/v7/widget/z$b
     271: dup
     272: aload_0
     273: aload_0
     274: getfield      #91                 // Field c:Landroid/content/Context;
     277: aload_2
     278: iload_3
     279: invokespecial #135                // Method android/support/v7/widget/z$b."<init>":(Landroid/support/v7/widget/z;Landroid/content/Context;Landroid/util/AttributeSet;I)V
     282: astore        5
     284: aload_0
     285: getfield      #91                 // Field c:Landroid/content/Context;
     288: aload_2
     289: getstatic     #72                 // Field android/support/v7/a/a$j.Spinner:[I
     292: iload_3
     293: iconst_0
     294: invokestatic  #77                 // Method android/support/v7/widget/bp.a:(Landroid/content/Context;Landroid/util/AttributeSet;[III)Landroid/support/v7/widget/bp;
     297: astore        8
     299: aload_0
     300: aload         8
     302: getstatic     #138                // Field android/support/v7/a/a$j.Spinner_android_dropDownWidth:I
     305: bipush        -2
     307: invokevirtual #140                // Method android/support/v7/widget/bp.f:(II)I
     310: putfield      #142                // Field h:I
     313: aload         5
     315: aload         8
     317: getstatic     #145                // Field android/support/v7/a/a$j.Spinner_android_popupBackground:I
     320: invokevirtual #148                // Method android/support/v7/widget/bp.a:(I)Landroid/graphics/drawable/Drawable;
     323: invokevirtual #151                // Method android/support/v7/widget/z$b.a:(Landroid/graphics/drawable/Drawable;)V
     326: aload         5
     328: aload         10
     330: getstatic     #154                // Field android/support/v7/a/a$j.Spinner_android_prompt:I
     333: invokevirtual #157                // Method android/support/v7/widget/bp.d:(I)Ljava/lang/String;
     336: invokevirtual #160                // Method android/support/v7/widget/z$b.a:(Ljava/lang/CharSequence;)V
     339: aload         8
     341: invokevirtual #162                // Method android/support/v7/widget/bp.a:()V
     344: aload_0
     345: aload         5
     347: putfield      #164                // Field g:Landroid/support/v7/widget/z$b;
     350: aload_0
     351: new           #8                  // class android/support/v7/widget/z$1
     354: dup
     355: aload_0
     356: aload_0
     357: aload         5
     359: invokespecial #167                // Method android/support/v7/widget/z$1."<init>":(Landroid/support/v7/widget/z;Landroid/view/View;Landroid/support/v7/widget/z$b;)V
     362: putfield      #169                // Field d:Landroid/support/v7/widget/as;
     365: aload         10
     367: getstatic     #172                // Field android/support/v7/a/a$j.Spinner_android_entries:I
     370: invokevirtual #175                // Method android/support/v7/widget/bp.f:(I)[Ljava/lang/CharSequence;
     373: astore        5
     375: aload         5
     377: ifnull        405
     380: new           #177                // class android/widget/ArrayAdapter
     383: dup
     384: aload_1
     385: ldc           #178                // int 17367048
     387: aload         5
     389: invokespecial #181                // Method android/widget/ArrayAdapter."<init>":(Landroid/content/Context;I[Ljava/lang/Object;)V
     392: astore_1
     393: aload_1
     394: getstatic     #186                // Field android/support/v7/a/a$g.support_simple_spinner_dropdown_item:I
     397: invokevirtual #190                // Method android/widget/ArrayAdapter.setDropDownViewResource:(I)V
     400: aload_0
     401: aload_1
     402: invokevirtual #194                // Method setAdapter:(Landroid/widget/SpinnerAdapter;)V
     405: aload         10
     407: invokevirtual #162                // Method android/support/v7/widget/bp.a:()V
     410: aload_0
     411: iconst_1
     412: putfield      #196                // Field f:Z
     415: aload_0
     416: getfield      #198                // Field e:Landroid/widget/SpinnerAdapter;
     419: ifnull        435
     422: aload_0
     423: aload_0
     424: getfield      #198                // Field e:Landroid/widget/SpinnerAdapter;
     427: invokevirtual #194                // Method setAdapter:(Landroid/widget/SpinnerAdapter;)V
     430: aload_0
     431: aconst_null
     432: putfield      #198                // Field e:Landroid/widget/SpinnerAdapter;
     435: aload_0
     436: getfield      #84                 // Field b:Landroid/support/v7/widget/h;
     439: aload_2
     440: iload_3
     441: invokevirtual #201                // Method android/support/v7/widget/h.a:(Landroid/util/AttributeSet;I)V
     444: return
    Exception table:
       from    to  target type
         139   151   218   Class java/lang/Exception
         139   151   211   any
         159   168   206   Class java/lang/Exception
         159   168   249   any
         172   181   206   Class java/lang/Exception
         172   181   249   any
         227   237   249   any

  static android.support.v7.widget.z$b a(android.support.v7.widget.z);
    Code:
       0: aload_0
       1: getfield      #164                // Field g:Landroid/support/v7/widget/z$b;
       4: areturn

  static android.graphics.Rect b(android.support.v7.widget.z);
    Code:
       0: aload_0
       1: getfield      #67                 // Field i:Landroid/graphics/Rect;
       4: areturn

  static int c(android.support.v7.widget.z);
    Code:
       0: aload_0
       1: getfield      #142                // Field h:I
       4: ireturn

  int a(android.widget.SpinnerAdapter, android.graphics.drawable.Drawable);
    Code:
       0: iconst_0
       1: istore        5
       3: aload_1
       4: ifnonnull     9
       7: iconst_0
       8: ireturn
       9: aload_0
      10: invokevirtual #209                // Method getMeasuredWidth:()I
      13: iconst_0
      14: invokestatic  #214                // Method android/view/View$MeasureSpec.makeMeasureSpec:(II)I
      17: istore        8
      19: aload_0
      20: invokevirtual #217                // Method getMeasuredHeight:()I
      23: iconst_0
      24: invokestatic  #214                // Method android/view/View$MeasureSpec.makeMeasureSpec:(II)I
      27: istore        9
      29: iconst_0
      30: aload_0
      31: invokevirtual #220                // Method getSelectedItemPosition:()I
      34: invokestatic  #225                // Method java/lang/Math.max:(II)I
      37: istore_3
      38: aload_1
      39: invokeinterface #230,  1          // InterfaceMethod android/widget/SpinnerAdapter.getCount:()I
      44: iload_3
      45: bipush        15
      47: iadd
      48: invokestatic  #233                // Method java/lang/Math.min:(II)I
      51: istore        10
      53: iconst_0
      54: iload_3
      55: bipush        15
      57: iload         10
      59: iload_3
      60: isub
      61: isub
      62: isub
      63: invokestatic  #225                // Method java/lang/Math.max:(II)I
      66: istore        4
      68: aconst_null
      69: astore        11
      71: iconst_0
      72: istore_3
      73: iload         4
      75: iload         10
      77: if_icmpge     177
      80: aload_1
      81: iload         4
      83: invokeinterface #237,  2          // InterfaceMethod android/widget/SpinnerAdapter.getItemViewType:(I)I
      88: istore        7
      90: iload         5
      92: istore        6
      94: iload         7
      96: iload         5
      98: if_icmpeq     108
     101: aconst_null
     102: astore        11
     104: iload         7
     106: istore        6
     108: aload_1
     109: iload         4
     111: aload         11
     113: aload_0
     114: invokeinterface #241,  4          // InterfaceMethod android/widget/SpinnerAdapter.getView:(ILandroid/view/View;Landroid/view/ViewGroup;)Landroid/view/View;
     119: astore        11
     121: aload         11
     123: invokevirtual #247                // Method android/view/View.getLayoutParams:()Landroid/view/ViewGroup$LayoutParams;
     126: ifnonnull     145
     129: aload         11
     131: new           #249                // class android/view/ViewGroup$LayoutParams
     134: dup
     135: bipush        -2
     137: bipush        -2
     139: invokespecial #252                // Method android/view/ViewGroup$LayoutParams."<init>":(II)V
     142: invokevirtual #256                // Method android/view/View.setLayoutParams:(Landroid/view/ViewGroup$LayoutParams;)V
     145: aload         11
     147: iload         8
     149: iload         9
     151: invokevirtual #259                // Method android/view/View.measure:(II)V
     154: iload_3
     155: aload         11
     157: invokevirtual #260                // Method android/view/View.getMeasuredWidth:()I
     160: invokestatic  #225                // Method java/lang/Math.max:(II)I
     163: istore_3
     164: iload         4
     166: iconst_1
     167: iadd
     168: istore        4
     170: iload         6
     172: istore        5
     174: goto          73
     177: iload_3
     178: istore        4
     180: aload_2
     181: ifnull        212
     184: aload_2
     185: aload_0
     186: getfield      #67                 // Field i:Landroid/graphics/Rect;
     189: invokevirtual #266                // Method android/graphics/drawable/Drawable.getPadding:(Landroid/graphics/Rect;)Z
     192: pop
     193: iload_3
     194: aload_0
     195: getfield      #67                 // Field i:Landroid/graphics/Rect;
     198: getfield      #269                // Field android/graphics/Rect.left:I
     201: aload_0
     202: getfield      #67                 // Field i:Landroid/graphics/Rect;
     205: getfield      #272                // Field android/graphics/Rect.right:I
     208: iadd
     209: iadd
     210: istore        4
     212: iload         4
     214: ireturn

  protected void drawableStateChanged();
    Code:
       0: aload_0
       1: invokespecial #275                // Method android/widget/Spinner.drawableStateChanged:()V
       4: aload_0
       5: getfield      #84                 // Field b:Landroid/support/v7/widget/h;
       8: ifnull        18
      11: aload_0
      12: getfield      #84                 // Field b:Landroid/support/v7/widget/h;
      15: invokevirtual #277                // Method android/support/v7/widget/h.c:()V
      18: return

  public int getDropDownHorizontalOffset();
    Code:
       0: aload_0
       1: getfield      #164                // Field g:Landroid/support/v7/widget/z$b;
       4: ifnull        15
       7: aload_0
       8: getfield      #164                // Field g:Landroid/support/v7/widget/z$b;
      11: invokevirtual #281                // Method android/support/v7/widget/z$b.j:()I
      14: ireturn
      15: getstatic     #105                // Field android/os/Build$VERSION.SDK_INT:I
      18: bipush        16
      20: if_icmplt     28
      23: aload_0
      24: invokespecial #283                // Method android/widget/Spinner.getDropDownHorizontalOffset:()I
      27: ireturn
      28: iconst_0
      29: ireturn

  public int getDropDownVerticalOffset();
    Code:
       0: aload_0
       1: getfield      #164                // Field g:Landroid/support/v7/widget/z$b;
       4: ifnull        15
       7: aload_0
       8: getfield      #164                // Field g:Landroid/support/v7/widget/z$b;
      11: invokevirtual #287                // Method android/support/v7/widget/z$b.k:()I
      14: ireturn
      15: getstatic     #105                // Field android/os/Build$VERSION.SDK_INT:I
      18: bipush        16
      20: if_icmplt     28
      23: aload_0
      24: invokespecial #289                // Method android/widget/Spinner.getDropDownVerticalOffset:()I
      27: ireturn
      28: iconst_0
      29: ireturn

  public int getDropDownWidth();
    Code:
       0: aload_0
       1: getfield      #164                // Field g:Landroid/support/v7/widget/z$b;
       4: ifnull        12
       7: aload_0
       8: getfield      #142                // Field h:I
      11: ireturn
      12: getstatic     #105                // Field android/os/Build$VERSION.SDK_INT:I
      15: bipush        16
      17: if_icmplt     25
      20: aload_0
      21: invokespecial #292                // Method android/widget/Spinner.getDropDownWidth:()I
      24: ireturn
      25: iconst_0
      26: ireturn

  public android.graphics.drawable.Drawable getPopupBackground();
    Code:
       0: aload_0
       1: getfield      #164                // Field g:Landroid/support/v7/widget/z$b;
       4: ifnull        15
       7: aload_0
       8: getfield      #164                // Field g:Landroid/support/v7/widget/z$b;
      11: invokevirtual #296                // Method android/support/v7/widget/z$b.h:()Landroid/graphics/drawable/Drawable;
      14: areturn
      15: getstatic     #105                // Field android/os/Build$VERSION.SDK_INT:I
      18: bipush        16
      20: if_icmplt     28
      23: aload_0
      24: invokespecial #298                // Method android/widget/Spinner.getPopupBackground:()Landroid/graphics/drawable/Drawable;
      27: areturn
      28: aconst_null
      29: areturn

  public android.content.Context getPopupContext();
    Code:
       0: aload_0
       1: getfield      #164                // Field g:Landroid/support/v7/widget/z$b;
       4: ifnull        12
       7: aload_0
       8: getfield      #91                 // Field c:Landroid/content/Context;
      11: areturn
      12: getstatic     #105                // Field android/os/Build$VERSION.SDK_INT:I
      15: bipush        23
      17: if_icmplt     25
      20: aload_0
      21: invokespecial #302                // Method android/widget/Spinner.getPopupContext:()Landroid/content/Context;
      24: areturn
      25: aconst_null
      26: areturn

  public java.lang.CharSequence getPrompt();
    Code:
       0: aload_0
       1: getfield      #164                // Field g:Landroid/support/v7/widget/z$b;
       4: ifnull        15
       7: aload_0
       8: getfield      #164                // Field g:Landroid/support/v7/widget/z$b;
      11: invokevirtual #306                // Method android/support/v7/widget/z$b.a:()Ljava/lang/CharSequence;
      14: areturn
      15: aload_0
      16: invokespecial #308                // Method android/widget/Spinner.getPrompt:()Ljava/lang/CharSequence;
      19: areturn

  public android.content.res.ColorStateList getSupportBackgroundTintList();
    Code:
       0: aload_0
       1: getfield      #84                 // Field b:Landroid/support/v7/widget/h;
       4: ifnull        15
       7: aload_0
       8: getfield      #84                 // Field b:Landroid/support/v7/widget/h;
      11: invokevirtual #312                // Method android/support/v7/widget/h.a:()Landroid/content/res/ColorStateList;
      14: areturn
      15: aconst_null
      16: areturn

  public android.graphics.PorterDuff$Mode getSupportBackgroundTintMode();
    Code:
       0: aload_0
       1: getfield      #84                 // Field b:Landroid/support/v7/widget/h;
       4: ifnull        15
       7: aload_0
       8: getfield      #84                 // Field b:Landroid/support/v7/widget/h;
      11: invokevirtual #316                // Method android/support/v7/widget/h.b:()Landroid/graphics/PorterDuff$Mode;
      14: areturn
      15: aconst_null
      16: areturn

  protected void onDetachedFromWindow();
    Code:
       0: aload_0
       1: invokespecial #319                // Method android/widget/Spinner.onDetachedFromWindow:()V
       4: aload_0
       5: getfield      #164                // Field g:Landroid/support/v7/widget/z$b;
       8: ifnull        28
      11: aload_0
      12: getfield      #164                // Field g:Landroid/support/v7/widget/z$b;
      15: invokevirtual #322                // Method android/support/v7/widget/z$b.f:()Z
      18: ifeq          28
      21: aload_0
      22: getfield      #164                // Field g:Landroid/support/v7/widget/z$b;
      25: invokevirtual #324                // Method android/support/v7/widget/z$b.e:()V
      28: return

  protected void onMeasure(int, int);
    Code:
       0: aload_0
       1: iload_1
       2: iload_2
       3: invokespecial #327                // Method android/widget/Spinner.onMeasure:(II)V
       6: aload_0
       7: getfield      #164                // Field g:Landroid/support/v7/widget/z$b;
      10: ifnull        57
      13: iload_1
      14: invokestatic  #330                // Method android/view/View$MeasureSpec.getMode:(I)I
      17: ldc_w         #331                // int -2147483648
      20: if_icmpne     57
      23: aload_0
      24: aload_0
      25: invokevirtual #209                // Method getMeasuredWidth:()I
      28: aload_0
      29: aload_0
      30: invokevirtual #335                // Method getAdapter:()Landroid/widget/SpinnerAdapter;
      33: aload_0
      34: invokevirtual #338                // Method getBackground:()Landroid/graphics/drawable/Drawable;
      37: invokevirtual #340                // Method a:(Landroid/widget/SpinnerAdapter;Landroid/graphics/drawable/Drawable;)I
      40: invokestatic  #225                // Method java/lang/Math.max:(II)I
      43: iload_1
      44: invokestatic  #343                // Method android/view/View$MeasureSpec.getSize:(I)I
      47: invokestatic  #233                // Method java/lang/Math.min:(II)I
      50: aload_0
      51: invokevirtual #217                // Method getMeasuredHeight:()I
      54: invokevirtual #346                // Method setMeasuredDimension:(II)V
      57: return

  public boolean onTouchEvent(android.view.MotionEvent);
    Code:
       0: aload_0
       1: getfield      #169                // Field d:Landroid/support/v7/widget/as;
       4: ifnull        21
       7: aload_0
       8: getfield      #169                // Field d:Landroid/support/v7/widget/as;
      11: aload_0
      12: aload_1
      13: invokevirtual #354                // Method android/support/v7/widget/as.onTouch:(Landroid/view/View;Landroid/view/MotionEvent;)Z
      16: ifeq          21
      19: iconst_1
      20: ireturn
      21: aload_0
      22: aload_1
      23: invokespecial #356                // Method android/widget/Spinner.onTouchEvent:(Landroid/view/MotionEvent;)Z
      26: ireturn

  public boolean performClick();
    Code:
       0: aload_0
       1: getfield      #164                // Field g:Landroid/support/v7/widget/z$b;
       4: ifnull        26
       7: aload_0
       8: getfield      #164                // Field g:Landroid/support/v7/widget/z$b;
      11: invokevirtual #322                // Method android/support/v7/widget/z$b.f:()Z
      14: ifne          24
      17: aload_0
      18: getfield      #164                // Field g:Landroid/support/v7/widget/z$b;
      21: invokevirtual #359                // Method android/support/v7/widget/z$b.d:()V
      24: iconst_1
      25: ireturn
      26: aload_0
      27: invokespecial #361                // Method android/widget/Spinner.performClick:()Z
      30: ireturn

  public void setAdapter(android.widget.Adapter);
    Code:
       0: aload_0
       1: aload_1
       2: checkcast     #227                // class android/widget/SpinnerAdapter
       5: invokevirtual #194                // Method setAdapter:(Landroid/widget/SpinnerAdapter;)V
       8: return

  public void setAdapter(android.widget.SpinnerAdapter);
    Code:
       0: aload_0
       1: getfield      #196                // Field f:Z
       4: ifne          13
       7: aload_0
       8: aload_1
       9: putfield      #198                // Field e:Landroid/widget/SpinnerAdapter;
      12: return
      13: aload_0
      14: aload_1
      15: invokespecial #363                // Method android/widget/Spinner.setAdapter:(Landroid/widget/SpinnerAdapter;)V
      18: aload_0
      19: getfield      #164                // Field g:Landroid/support/v7/widget/z$b;
      22: ifnull        64
      25: aload_0
      26: getfield      #91                 // Field c:Landroid/content/Context;
      29: ifnonnull     40
      32: aload_0
      33: invokevirtual #366                // Method getContext:()Landroid/content/Context;
      36: astore_2
      37: goto          45
      40: aload_0
      41: getfield      #91                 // Field c:Landroid/content/Context;
      44: astore_2
      45: aload_0
      46: getfield      #164                // Field g:Landroid/support/v7/widget/z$b;
      49: new           #10                 // class android/support/v7/widget/z$a
      52: dup
      53: aload_1
      54: aload_2
      55: invokevirtual #370                // Method android/content/Context.getTheme:()Landroid/content/res/Resources$Theme;
      58: invokespecial #373                // Method android/support/v7/widget/z$a."<init>":(Landroid/widget/SpinnerAdapter;Landroid/content/res/Resources$Theme;)V
      61: invokevirtual #376                // Method android/support/v7/widget/z$b.a:(Landroid/widget/ListAdapter;)V
      64: return

  public void setBackgroundDrawable(android.graphics.drawable.Drawable);
    Code:
       0: aload_0
       1: aload_1
       2: invokespecial #379                // Method android/widget/Spinner.setBackgroundDrawable:(Landroid/graphics/drawable/Drawable;)V
       5: aload_0
       6: getfield      #84                 // Field b:Landroid/support/v7/widget/h;
       9: ifnull        20
      12: aload_0
      13: getfield      #84                 // Field b:Landroid/support/v7/widget/h;
      16: aload_1
      17: invokevirtual #380                // Method android/support/v7/widget/h.a:(Landroid/graphics/drawable/Drawable;)V
      20: return

  public void setBackgroundResource(int);
    Code:
       0: aload_0
       1: iload_1
       2: invokespecial #383                // Method android/widget/Spinner.setBackgroundResource:(I)V
       5: aload_0
       6: getfield      #84                 // Field b:Landroid/support/v7/widget/h;
       9: ifnull        20
      12: aload_0
      13: getfield      #84                 // Field b:Landroid/support/v7/widget/h;
      16: iload_1
      17: invokevirtual #385                // Method android/support/v7/widget/h.a:(I)V
      20: return

  public void setDropDownHorizontalOffset(int);
    Code:
       0: aload_0
       1: getfield      #164                // Field g:Landroid/support/v7/widget/z$b;
       4: ifnull        16
       7: aload_0
       8: getfield      #164                // Field g:Landroid/support/v7/widget/z$b;
      11: iload_1
      12: invokevirtual #388                // Method android/support/v7/widget/z$b.c:(I)V
      15: return
      16: getstatic     #105                // Field android/os/Build$VERSION.SDK_INT:I
      19: bipush        16
      21: if_icmplt     29
      24: aload_0
      25: iload_1
      26: invokespecial #390                // Method android/widget/Spinner.setDropDownHorizontalOffset:(I)V
      29: return

  public void setDropDownVerticalOffset(int);
    Code:
       0: aload_0
       1: getfield      #164                // Field g:Landroid/support/v7/widget/z$b;
       4: ifnull        16
       7: aload_0
       8: getfield      #164                // Field g:Landroid/support/v7/widget/z$b;
      11: iload_1
      12: invokevirtual #393                // Method android/support/v7/widget/z$b.d:(I)V
      15: return
      16: getstatic     #105                // Field android/os/Build$VERSION.SDK_INT:I
      19: bipush        16
      21: if_icmplt     29
      24: aload_0
      25: iload_1
      26: invokespecial #395                // Method android/widget/Spinner.setDropDownVerticalOffset:(I)V
      29: return

  public void setDropDownWidth(int);
    Code:
       0: aload_0
       1: getfield      #164                // Field g:Landroid/support/v7/widget/z$b;
       4: ifnull        13
       7: aload_0
       8: iload_1
       9: putfield      #142                // Field h:I
      12: return
      13: getstatic     #105                // Field android/os/Build$VERSION.SDK_INT:I
      16: bipush        16
      18: if_icmplt     26
      21: aload_0
      22: iload_1
      23: invokespecial #398                // Method android/widget/Spinner.setDropDownWidth:(I)V
      26: return

  public void setPopupBackgroundDrawable(android.graphics.drawable.Drawable);
    Code:
       0: aload_0
       1: getfield      #164                // Field g:Landroid/support/v7/widget/z$b;
       4: ifnull        16
       7: aload_0
       8: getfield      #164                // Field g:Landroid/support/v7/widget/z$b;
      11: aload_1
      12: invokevirtual #151                // Method android/support/v7/widget/z$b.a:(Landroid/graphics/drawable/Drawable;)V
      15: return
      16: getstatic     #105                // Field android/os/Build$VERSION.SDK_INT:I
      19: bipush        16
      21: if_icmplt     29
      24: aload_0
      25: aload_1
      26: invokespecial #401                // Method android/widget/Spinner.setPopupBackgroundDrawable:(Landroid/graphics/drawable/Drawable;)V
      29: return

  public void setPopupBackgroundResource(int);
    Code:
       0: aload_0
       1: aload_0
       2: invokevirtual #403                // Method getPopupContext:()Landroid/content/Context;
       5: iload_1
       6: invokestatic  #408                // Method android/support/v7/c/a/b.b:(Landroid/content/Context;I)Landroid/graphics/drawable/Drawable;
       9: invokevirtual #409                // Method setPopupBackgroundDrawable:(Landroid/graphics/drawable/Drawable;)V
      12: return

  public void setPrompt(java.lang.CharSequence);
    Code:
       0: aload_0
       1: getfield      #164                // Field g:Landroid/support/v7/widget/z$b;
       4: ifnull        16
       7: aload_0
       8: getfield      #164                // Field g:Landroid/support/v7/widget/z$b;
      11: aload_1
      12: invokevirtual #160                // Method android/support/v7/widget/z$b.a:(Ljava/lang/CharSequence;)V
      15: return
      16: aload_0
      17: aload_1
      18: invokespecial #412                // Method android/widget/Spinner.setPrompt:(Ljava/lang/CharSequence;)V
      21: return

  public void setSupportBackgroundTintList(android.content.res.ColorStateList);
    Code:
       0: aload_0
       1: getfield      #84                 // Field b:Landroid/support/v7/widget/h;
       4: ifnull        15
       7: aload_0
       8: getfield      #84                 // Field b:Landroid/support/v7/widget/h;
      11: aload_1
      12: invokevirtual #416                // Method android/support/v7/widget/h.a:(Landroid/content/res/ColorStateList;)V
      15: return

  public void setSupportBackgroundTintMode(android.graphics.PorterDuff$Mode);
    Code:
       0: aload_0
       1: getfield      #84                 // Field b:Landroid/support/v7/widget/h;
       4: ifnull        15
       7: aload_0
       8: getfield      #84                 // Field b:Landroid/support/v7/widget/h;
      11: aload_1
      12: invokevirtual #420                // Method android/support/v7/widget/h.a:(Landroid/graphics/PorterDuff$Mode;)V
      15: return
}
