public final class android.support.v4.a.a.a$b implements android.support.v4.a.a.a$a {
  public android.support.v4.a.a.a$b(android.support.v4.a.a.a$c[]);
    Code:
       0: aload_0
       1: invokespecial #16                 // Method java/lang/Object."<init>":()V
       4: aload_0
       5: aload_1
       6: putfield      #18                 // Field a:[Landroid/support/v4/a/a/a$c;
       9: return

  public android.support.v4.a.a.a$c[] a();
    Code:
       0: aload_0
       1: getfield      #18                 // Field a:[Landroid/support/v4/a/a/a$c;
       4: areturn
}
