public final class android.support.v4.a.a.a$c {
  public android.support.v4.a.a.a$c(java.lang.String, int, boolean, int);
    Code:
       0: aload_0
       1: invokespecial #18                 // Method java/lang/Object."<init>":()V
       4: aload_0
       5: aload_1
       6: putfield      #20                 // Field a:Ljava/lang/String;
       9: aload_0
      10: iload_2
      11: putfield      #22                 // Field b:I
      14: aload_0
      15: iload_3
      16: putfield      #24                 // Field c:Z
      19: aload_0
      20: iload         4
      22: putfield      #26                 // Field d:I
      25: return

  public java.lang.String a();
    Code:
       0: aload_0
       1: getfield      #20                 // Field a:Ljava/lang/String;
       4: areturn

  public int b();
    Code:
       0: aload_0
       1: getfield      #22                 // Field b:I
       4: ireturn

  public boolean c();
    Code:
       0: aload_0
       1: getfield      #24                 // Field c:Z
       4: ireturn

  public int d();
    Code:
       0: aload_0
       1: getfield      #26                 // Field d:I
       4: ireturn
}
