public final class android.support.v4.a.a.a$d implements android.support.v4.a.a.a$a {
  public android.support.v4.a.a.a$d(android.support.v4.f.a, int, int);
    Code:
       0: aload_0
       1: invokespecial #19                 // Method java/lang/Object."<init>":()V
       4: aload_0
       5: aload_1
       6: putfield      #21                 // Field a:Landroid/support/v4/f/a;
       9: aload_0
      10: iload_2
      11: putfield      #23                 // Field c:I
      14: aload_0
      15: iload_3
      16: putfield      #25                 // Field b:I
      19: return

  public android.support.v4.f.a a();
    Code:
       0: aload_0
       1: getfield      #21                 // Field a:Landroid/support/v4/f/a;
       4: areturn

  public int b();
    Code:
       0: aload_0
       1: getfield      #23                 // Field c:I
       4: ireturn

  public int c();
    Code:
       0: aload_0
       1: getfield      #25                 // Field b:I
       4: ireturn
}
