class ryey.easer.plugins.operation.ringer_mode.InterruptionFilterSwitcherService$1 extends android.content.BroadcastReceiver {
  final ryey.easer.plugins.operation.ringer_mode.InterruptionFilterSwitcherService a;

  ryey.easer.plugins.operation.ringer_mode.InterruptionFilterSwitcherService$1(ryey.easer.plugins.operation.ringer_mode.InterruptionFilterSwitcherService);
    Code:
       0: aload_0
       1: aload_1
       2: putfield      #12                 // Field a:Lryey/easer/plugins/operation/ringer_mode/InterruptionFilterSwitcherService;
       5: aload_0
       6: invokespecial #15                 // Method android/content/BroadcastReceiver."<init>":()V
       9: return

  public void onReceive(android.content.Context, android.content.Intent);
    Code:
       0: aload_2
       1: invokevirtual #24                 // Method android/content/Intent.getAction:()Ljava/lang/String;
       4: astore_1
       5: aload_1
       6: ifnull        48
       9: aload_1
      10: ldc           #26                 // String ryey.easer.plugins.operation.ringer_mode.action.CHANGE
      12: invokevirtual #32                 // Method java/lang/String.equals:(Ljava/lang/Object;)Z
      15: ifne          21
      18: goto          48
      21: aload_2
      22: ldc           #34                 // String ryey.easer.plugins.operation.ringer_mode.extra.MODE
      24: iconst_m1
      25: invokevirtual #38                 // Method android/content/Intent.getIntExtra:(Ljava/lang/String;I)I
      28: istore_3
      29: aload_0
      30: getfield      #12                 // Field a:Lryey/easer/plugins/operation/ringer_mode/InterruptionFilterSwitcherService;
      33: invokestatic  #41                 // Method ryey/easer/plugins/operation/ringer_mode/InterruptionFilterSwitcherService.a:(Lryey/easer/plugins/operation/ringer_mode/InterruptionFilterSwitcherService;)Landroid/os/ConditionVariable;
      36: invokevirtual #46                 // Method android/os/ConditionVariable.block:()V
      39: aload_0
      40: getfield      #12                 // Field a:Lryey/easer/plugins/operation/ringer_mode/InterruptionFilterSwitcherService;
      43: iload_3
      44: invokevirtual #50                 // Method ryey/easer/plugins/operation/ringer_mode/InterruptionFilterSwitcherService.requestInterruptionFilter:(I)V
      47: return
      48: new           #52                 // class java/lang/IllegalAccessError
      51: dup
      52: invokespecial #53                 // Method java/lang/IllegalAccessError."<init>":()V
      55: athrow
}
