public class android.support.constraint.a.a {
  int a;

  android.support.constraint.a.a(android.support.constraint.a.b, android.support.constraint.a.c);
    Code:
       0: aload_0
       1: invokespecial #27                 // Method java/lang/Object."<init>":()V
       4: aload_0
       5: iconst_0
       6: putfield      #29                 // Field a:I
       9: aload_0
      10: bipush        8
      12: putfield      #31                 // Field d:I
      15: aload_0
      16: aconst_null
      17: putfield      #33                 // Field e:Landroid/support/constraint/a/h;
      20: aload_0
      21: aload_0
      22: getfield      #31                 // Field d:I
      25: newarray       int
      27: putfield      #35                 // Field f:[I
      30: aload_0
      31: aload_0
      32: getfield      #31                 // Field d:I
      35: newarray       int
      37: putfield      #37                 // Field g:[I
      40: aload_0
      41: aload_0
      42: getfield      #31                 // Field d:I
      45: newarray       float
      47: putfield      #39                 // Field h:[F
      50: aload_0
      51: iconst_m1
      52: putfield      #41                 // Field i:I
      55: aload_0
      56: iconst_m1
      57: putfield      #43                 // Field j:I
      60: aload_0
      61: iconst_0
      62: putfield      #45                 // Field k:Z
      65: aload_0
      66: aload_1
      67: putfield      #47                 // Field b:Landroid/support/constraint/a/b;
      70: aload_0
      71: aload_2
      72: putfield      #49                 // Field c:Landroid/support/constraint/a/c;
      75: return

  public final float a(android.support.constraint.a.h, boolean);
    Code:
       0: aload_0
       1: getfield      #33                 // Field e:Landroid/support/constraint/a/h;
       4: aload_1
       5: if_acmpne     13
       8: aload_0
       9: aconst_null
      10: putfield      #33                 // Field e:Landroid/support/constraint/a/h;
      13: aload_0
      14: getfield      #41                 // Field i:I
      17: iconst_m1
      18: if_icmpne     23
      21: fconst_0
      22: freturn
      23: aload_0
      24: getfield      #41                 // Field i:I
      27: istore_3
      28: iconst_0
      29: istore        4
      31: iconst_m1
      32: istore        5
      34: iload_3
      35: iconst_m1
      36: if_icmpeq     176
      39: iload         4
      41: aload_0
      42: getfield      #29                 // Field a:I
      45: if_icmpge     176
      48: aload_0
      49: getfield      #35                 // Field f:[I
      52: iload_3
      53: iaload
      54: aload_1
      55: getfield      #56                 // Field android/support/constraint/a/h.a:I
      58: if_icmpne     153
      61: iload_3
      62: aload_0
      63: getfield      #41                 // Field i:I
      66: if_icmpne     82
      69: aload_0
      70: aload_0
      71: getfield      #37                 // Field g:[I
      74: iload_3
      75: iaload
      76: putfield      #41                 // Field i:I
      79: goto          95
      82: aload_0
      83: getfield      #37                 // Field g:[I
      86: iload         5
      88: aload_0
      89: getfield      #37                 // Field g:[I
      92: iload_3
      93: iaload
      94: iastore
      95: iload_2
      96: ifeq          107
      99: aload_1
     100: aload_0
     101: getfield      #47                 // Field b:Landroid/support/constraint/a/b;
     104: invokevirtual #59                 // Method android/support/constraint/a/h.b:(Landroid/support/constraint/a/b;)V
     107: aload_1
     108: aload_1
     109: getfield      #54                 // Field android/support/constraint/a/h.i:I
     112: iconst_1
     113: isub
     114: putfield      #54                 // Field android/support/constraint/a/h.i:I
     117: aload_0
     118: aload_0
     119: getfield      #29                 // Field a:I
     122: iconst_1
     123: isub
     124: putfield      #29                 // Field a:I
     127: aload_0
     128: getfield      #35                 // Field f:[I
     131: iload_3
     132: iconst_m1
     133: iastore
     134: aload_0
     135: getfield      #45                 // Field k:Z
     138: ifeq          146
     141: aload_0
     142: iload_3
     143: putfield      #43                 // Field j:I
     146: aload_0
     147: getfield      #39                 // Field h:[F
     150: iload_3
     151: faload
     152: freturn
     153: aload_0
     154: getfield      #37                 // Field g:[I
     157: iload_3
     158: iaload
     159: istore        6
     161: iload         4
     163: iconst_1
     164: iadd
     165: istore        4
     167: iload_3
     168: istore        5
     170: iload         6
     172: istore_3
     173: goto          34
     176: fconst_0
     177: freturn

  final android.support.constraint.a.h a(int);
    Code:
       0: aload_0
       1: getfield      #41                 // Field i:I
       4: istore_3
       5: iconst_0
       6: istore_2
       7: iload_3
       8: iconst_m1
       9: if_icmpeq     54
      12: iload_2
      13: aload_0
      14: getfield      #29                 // Field a:I
      17: if_icmpge     54
      20: iload_2
      21: iload_1
      22: if_icmpne     40
      25: aload_0
      26: getfield      #49                 // Field c:Landroid/support/constraint/a/c;
      29: getfield      #65                 // Field android/support/constraint/a/c.c:[Landroid/support/constraint/a/h;
      32: aload_0
      33: getfield      #35                 // Field f:[I
      36: iload_3
      37: iaload
      38: aaload
      39: areturn
      40: aload_0
      41: getfield      #37                 // Field g:[I
      44: iload_3
      45: iaload
      46: istore_3
      47: iload_2
      48: iconst_1
      49: iadd
      50: istore_2
      51: goto          7
      54: aconst_null
      55: areturn

  android.support.constraint.a.h a(android.support.constraint.a.e);
    Code:
       0: aload_0
       1: getfield      #41                 // Field i:I
       4: istore        8
       6: aconst_null
       7: astore        17
       9: iconst_0
      10: istore        7
      12: aconst_null
      13: astore        16
      15: fconst_0
      16: fstore        6
      18: iconst_0
      19: istore        12
      21: fconst_0
      22: fstore        5
      24: iconst_0
      25: istore        11
      27: iload         8
      29: iconst_m1
      30: if_icmpeq     519
      33: iload         7
      35: aload_0
      36: getfield      #29                 // Field a:I
      39: if_icmpge     519
      42: aload_0
      43: getfield      #39                 // Field h:[F
      46: iload         8
      48: faload
      49: fstore_3
      50: aload_0
      51: getfield      #49                 // Field c:Landroid/support/constraint/a/c;
      54: getfield      #65                 // Field android/support/constraint/a/c.c:[Landroid/support/constraint/a/h;
      57: aload_0
      58: getfield      #35                 // Field f:[I
      61: iload         8
      63: iaload
      64: aaload
      65: astore        13
      67: fload_3
      68: fconst_0
      69: fcmpg
      70: ifge          104
      73: fload_3
      74: fstore_2
      75: fload_3
      76: ldc           #67                 // float -0.001f
      78: fcmpl
      79: ifle          124
      82: aload_0
      83: getfield      #39                 // Field h:[F
      86: iload         8
      88: fconst_0
      89: fastore
      90: aload         13
      92: aload_0
      93: getfield      #47                 // Field b:Landroid/support/constraint/a/b;
      96: invokevirtual #59                 // Method android/support/constraint/a/h.b:(Landroid/support/constraint/a/b;)V
      99: fconst_0
     100: fstore_2
     101: goto          124
     104: fload_3
     105: fstore_2
     106: fload_3
     107: ldc           #68                 // float 0.001f
     109: fcmpg
     110: ifge          124
     113: aload_0
     114: getfield      #39                 // Field h:[F
     117: iload         8
     119: fconst_0
     120: fastore
     121: goto          90
     124: aload         17
     126: astore        14
     128: aload         16
     130: astore        15
     132: fload         6
     134: fstore_3
     135: iload         12
     137: istore        9
     139: fload         5
     141: fstore        4
     143: iload         11
     145: istore        10
     147: fload_2
     148: fconst_0
     149: fcmpl
     150: ifeq          478
     153: aload         13
     155: getfield      #71                 // Field android/support/constraint/a/h.f:Landroid/support/constraint/a/h$a;
     158: getstatic     #75                 // Field android/support/constraint/a/h$a.a:Landroid/support/constraint/a/h$a;
     161: if_acmpne     294
     164: aload         17
     166: ifnonnull     199
     169: aload_0
     170: aload         13
     172: aload_1
     173: invokespecial #77                 // Method a:(Landroid/support/constraint/a/h;Landroid/support/constraint/a/e;)Z
     176: istore        9
     178: aload         13
     180: astore        14
     182: aload         16
     184: astore        15
     186: fload_2
     187: fstore_3
     188: fload         5
     190: fstore        4
     192: iload         11
     194: istore        10
     196: goto          478
     199: fload         6
     201: fload_2
     202: fcmpl
     203: ifle          209
     206: goto          169
     209: aload         17
     211: astore        14
     213: aload         16
     215: astore        15
     217: fload         6
     219: fstore_3
     220: iload         12
     222: istore        9
     224: fload         5
     226: fstore        4
     228: iload         11
     230: istore        10
     232: iload         12
     234: ifne          478
     237: aload         17
     239: astore        14
     241: aload         16
     243: astore        15
     245: fload         6
     247: fstore_3
     248: iload         12
     250: istore        9
     252: fload         5
     254: fstore        4
     256: iload         11
     258: istore        10
     260: aload_0
     261: aload         13
     263: aload_1
     264: invokespecial #77                 // Method a:(Landroid/support/constraint/a/h;Landroid/support/constraint/a/e;)Z
     267: ifeq          478
     270: iconst_1
     271: istore        9
     273: aload         13
     275: astore        14
     277: aload         16
     279: astore        15
     281: fload_2
     282: fstore_3
     283: fload         5
     285: fstore        4
     287: iload         11
     289: istore        10
     291: goto          478
     294: aload         17
     296: astore        14
     298: aload         16
     300: astore        15
     302: fload         6
     304: fstore_3
     305: iload         12
     307: istore        9
     309: fload         5
     311: fstore        4
     313: iload         11
     315: istore        10
     317: aload         17
     319: ifnonnull     478
     322: aload         17
     324: astore        14
     326: aload         16
     328: astore        15
     330: fload         6
     332: fstore_3
     333: iload         12
     335: istore        9
     337: fload         5
     339: fstore        4
     341: iload         11
     343: istore        10
     345: fload_2
     346: fconst_0
     347: fcmpg
     348: ifge          478
     351: aload         16
     353: ifnonnull     386
     356: aload_0
     357: aload         13
     359: aload_1
     360: invokespecial #77                 // Method a:(Landroid/support/constraint/a/h;Landroid/support/constraint/a/e;)Z
     363: istore        10
     365: aload         17
     367: astore        14
     369: aload         13
     371: astore        15
     373: fload         6
     375: fstore_3
     376: iload         12
     378: istore        9
     380: fload_2
     381: fstore        4
     383: goto          478
     386: fload         5
     388: fload_2
     389: fcmpl
     390: ifle          396
     393: goto          356
     396: aload         17
     398: astore        14
     400: aload         16
     402: astore        15
     404: fload         6
     406: fstore_3
     407: iload         12
     409: istore        9
     411: fload         5
     413: fstore        4
     415: iload         11
     417: istore        10
     419: iload         11
     421: ifne          478
     424: aload         17
     426: astore        14
     428: aload         16
     430: astore        15
     432: fload         6
     434: fstore_3
     435: iload         12
     437: istore        9
     439: fload         5
     441: fstore        4
     443: iload         11
     445: istore        10
     447: aload_0
     448: aload         13
     450: aload_1
     451: invokespecial #77                 // Method a:(Landroid/support/constraint/a/h;Landroid/support/constraint/a/e;)Z
     454: ifeq          478
     457: iconst_1
     458: istore        10
     460: fload_2
     461: fstore        4
     463: iload         12
     465: istore        9
     467: fload         6
     469: fstore_3
     470: aload         13
     472: astore        15
     474: aload         17
     476: astore        14
     478: aload_0
     479: getfield      #37                 // Field g:[I
     482: iload         8
     484: iaload
     485: istore        8
     487: iload         7
     489: iconst_1
     490: iadd
     491: istore        7
     493: aload         14
     495: astore        17
     497: aload         15
     499: astore        16
     501: fload_3
     502: fstore        6
     504: iload         9
     506: istore        12
     508: fload         4
     510: fstore        5
     512: iload         10
     514: istore        11
     516: goto          27
     519: aload         17
     521: ifnull        527
     524: aload         17
     526: areturn
     527: aload         16
     529: areturn

  android.support.constraint.a.h a(boolean[], android.support.constraint.a.h);
    Code:
       0: aload_0
       1: getfield      #41                 // Field i:I
       4: istore        7
       6: iconst_0
       7: istore        6
       9: aconst_null
      10: astore        8
      12: fconst_0
      13: fstore_3
      14: iload         7
      16: iconst_m1
      17: if_icmpeq     184
      20: iload         6
      22: aload_0
      23: getfield      #29                 // Field a:I
      26: if_icmpge     184
      29: aload         8
      31: astore        9
      33: fload_3
      34: fstore        4
      36: aload_0
      37: getfield      #39                 // Field h:[F
      40: iload         7
      42: faload
      43: fconst_0
      44: fcmpg
      45: ifge          159
      48: aload_0
      49: getfield      #49                 // Field c:Landroid/support/constraint/a/c;
      52: getfield      #65                 // Field android/support/constraint/a/c.c:[Landroid/support/constraint/a/h;
      55: aload_0
      56: getfield      #35                 // Field f:[I
      59: iload         7
      61: iaload
      62: aaload
      63: astore        10
      65: aload_1
      66: ifnull        86
      69: aload         8
      71: astore        9
      73: fload_3
      74: fstore        4
      76: aload_1
      77: aload         10
      79: getfield      #56                 // Field android/support/constraint/a/h.a:I
      82: baload
      83: ifne          159
      86: aload         8
      88: astore        9
      90: fload_3
      91: fstore        4
      93: aload         10
      95: aload_2
      96: if_acmpeq     159
      99: aload         10
     101: getfield      #71                 // Field android/support/constraint/a/h.f:Landroid/support/constraint/a/h$a;
     104: getstatic     #80                 // Field android/support/constraint/a/h$a.c:Landroid/support/constraint/a/h$a;
     107: if_acmpeq     128
     110: aload         8
     112: astore        9
     114: fload_3
     115: fstore        4
     117: aload         10
     119: getfield      #71                 // Field android/support/constraint/a/h.f:Landroid/support/constraint/a/h$a;
     122: getstatic     #82                 // Field android/support/constraint/a/h$a.d:Landroid/support/constraint/a/h$a;
     125: if_acmpne     159
     128: aload_0
     129: getfield      #39                 // Field h:[F
     132: iload         7
     134: faload
     135: fstore        5
     137: aload         8
     139: astore        9
     141: fload_3
     142: fstore        4
     144: fload         5
     146: fload_3
     147: fcmpg
     148: ifge          159
     151: aload         10
     153: astore        9
     155: fload         5
     157: fstore        4
     159: aload_0
     160: getfield      #37                 // Field g:[I
     163: iload         7
     165: iaload
     166: istore        7
     168: iload         6
     170: iconst_1
     171: iadd
     172: istore        6
     174: aload         9
     176: astore        8
     178: fload         4
     180: fstore_3
     181: goto          14
     184: aload         8
     186: areturn

  public final void a();
    Code:
       0: aload_0
       1: getfield      #41                 // Field i:I
       4: istore_2
       5: iconst_0
       6: istore_1
       7: iload_2
       8: iconst_m1
       9: if_icmpeq     61
      12: iload_1
      13: aload_0
      14: getfield      #29                 // Field a:I
      17: if_icmpge     61
      20: aload_0
      21: getfield      #49                 // Field c:Landroid/support/constraint/a/c;
      24: getfield      #65                 // Field android/support/constraint/a/c.c:[Landroid/support/constraint/a/h;
      27: aload_0
      28: getfield      #35                 // Field f:[I
      31: iload_2
      32: iaload
      33: aaload
      34: astore_3
      35: aload_3
      36: ifnull        47
      39: aload_3
      40: aload_0
      41: getfield      #47                 // Field b:Landroid/support/constraint/a/b;
      44: invokevirtual #59                 // Method android/support/constraint/a/h.b:(Landroid/support/constraint/a/b;)V
      47: aload_0
      48: getfield      #37                 // Field g:[I
      51: iload_2
      52: iaload
      53: istore_2
      54: iload_1
      55: iconst_1
      56: iadd
      57: istore_1
      58: goto          7
      61: aload_0
      62: iconst_m1
      63: putfield      #41                 // Field i:I
      66: aload_0
      67: iconst_m1
      68: putfield      #43                 // Field j:I
      71: aload_0
      72: iconst_0
      73: putfield      #45                 // Field k:Z
      76: aload_0
      77: iconst_0
      78: putfield      #29                 // Field a:I
      81: return

  void a(float);
    Code:
       0: aload_0
       1: getfield      #41                 // Field i:I
       4: istore_3
       5: iconst_0
       6: istore_2
       7: iload_3
       8: iconst_m1
       9: if_icmpeq     50
      12: iload_2
      13: aload_0
      14: getfield      #29                 // Field a:I
      17: if_icmpge     50
      20: aload_0
      21: getfield      #39                 // Field h:[F
      24: astore        4
      26: aload         4
      28: iload_3
      29: aload         4
      31: iload_3
      32: faload
      33: fload_1
      34: fdiv
      35: fastore
      36: aload_0
      37: getfield      #37                 // Field g:[I
      40: iload_3
      41: iaload
      42: istore_3
      43: iload_2
      44: iconst_1
      45: iadd
      46: istore_2
      47: goto          7
      50: return

  final void a(android.support.constraint.a.b, android.support.constraint.a.b, boolean);
    Code:
       0: aload_0
       1: getfield      #41                 // Field i:I
       4: istore        5
       6: iconst_0
       7: istore        6
       9: iload         5
      11: iconst_m1
      12: if_icmpeq     201
      15: iload         6
      17: aload_0
      18: getfield      #29                 // Field a:I
      21: if_icmpge     201
      24: aload_0
      25: getfield      #35                 // Field f:[I
      28: iload         5
      30: iaload
      31: aload_2
      32: getfield      #88                 // Field android/support/constraint/a/b.a:Landroid/support/constraint/a/h;
      35: getfield      #56                 // Field android/support/constraint/a/h.a:I
      38: if_icmpne     183
      41: aload_0
      42: getfield      #39                 // Field h:[F
      45: iload         5
      47: faload
      48: fstore        4
      50: aload_0
      51: aload_2
      52: getfield      #88                 // Field android/support/constraint/a/b.a:Landroid/support/constraint/a/h;
      55: iload_3
      56: invokevirtual #90                 // Method a:(Landroid/support/constraint/a/h;Z)F
      59: pop
      60: aload_2
      61: getfield      #93                 // Field android/support/constraint/a/b.d:Landroid/support/constraint/a/a;
      64: checkcast     #2                  // class android/support/constraint/a/a
      67: astore        7
      69: aload         7
      71: getfield      #41                 // Field i:I
      74: istore        6
      76: iconst_0
      77: istore        5
      79: iload         6
      81: iconst_m1
      82: if_icmpeq     146
      85: iload         5
      87: aload         7
      89: getfield      #29                 // Field a:I
      92: if_icmpge     146
      95: aload_0
      96: aload_0
      97: getfield      #49                 // Field c:Landroid/support/constraint/a/c;
     100: getfield      #65                 // Field android/support/constraint/a/c.c:[Landroid/support/constraint/a/h;
     103: aload         7
     105: getfield      #35                 // Field f:[I
     108: iload         6
     110: iaload
     111: aaload
     112: aload         7
     114: getfield      #39                 // Field h:[F
     117: iload         6
     119: faload
     120: fload         4
     122: fmul
     123: iload_3
     124: invokevirtual #96                 // Method a:(Landroid/support/constraint/a/h;FZ)V
     127: aload         7
     129: getfield      #37                 // Field g:[I
     132: iload         6
     134: iaload
     135: istore        6
     137: iload         5
     139: iconst_1
     140: iadd
     141: istore        5
     143: goto          79
     146: aload_1
     147: aload_1
     148: getfield      #99                 // Field android/support/constraint/a/b.b:F
     151: aload_2
     152: getfield      #99                 // Field android/support/constraint/a/b.b:F
     155: fload         4
     157: fmul
     158: fadd
     159: putfield      #99                 // Field android/support/constraint/a/b.b:F
     162: iload_3
     163: ifeq          174
     166: aload_2
     167: getfield      #88                 // Field android/support/constraint/a/b.a:Landroid/support/constraint/a/h;
     170: aload_1
     171: invokevirtual #59                 // Method android/support/constraint/a/h.b:(Landroid/support/constraint/a/b;)V
     174: aload_0
     175: getfield      #41                 // Field i:I
     178: istore        5
     180: goto          6
     183: aload_0
     184: getfield      #37                 // Field g:[I
     187: iload         5
     189: iaload
     190: istore        5
     192: iload         6
     194: iconst_1
     195: iadd
     196: istore        6
     198: goto          9
     201: return

  void a(android.support.constraint.a.b, android.support.constraint.a.b[]);
    Code:
       0: aload_0
       1: getfield      #41                 // Field i:I
       4: istore        4
       6: iconst_0
       7: istore        5
       9: iload         4
      11: iconst_m1
      12: if_icmpeq     221
      15: iload         5
      17: aload_0
      18: getfield      #29                 // Field a:I
      21: if_icmpge     221
      24: aload_0
      25: getfield      #49                 // Field c:Landroid/support/constraint/a/c;
      28: getfield      #65                 // Field android/support/constraint/a/c.c:[Landroid/support/constraint/a/h;
      31: aload_0
      32: getfield      #35                 // Field f:[I
      35: iload         4
      37: iaload
      38: aaload
      39: astore        6
      41: aload         6
      43: getfield      #102                // Field android/support/constraint/a/h.b:I
      46: iconst_m1
      47: if_icmpeq     203
      50: aload_0
      51: getfield      #39                 // Field h:[F
      54: iload         4
      56: faload
      57: fstore_3
      58: aload_0
      59: aload         6
      61: iconst_1
      62: invokevirtual #90                 // Method a:(Landroid/support/constraint/a/h;Z)F
      65: pop
      66: aload_2
      67: aload         6
      69: getfield      #102                // Field android/support/constraint/a/h.b:I
      72: aaload
      73: astore        6
      75: aload         6
      77: getfield      #104                // Field android/support/constraint/a/b.e:Z
      80: ifne          169
      83: aload         6
      85: getfield      #93                 // Field android/support/constraint/a/b.d:Landroid/support/constraint/a/a;
      88: checkcast     #2                  // class android/support/constraint/a/a
      91: astore        7
      93: aload         7
      95: getfield      #41                 // Field i:I
      98: istore        5
     100: iconst_0
     101: istore        4
     103: iload         5
     105: iconst_m1
     106: if_icmpeq     169
     109: iload         4
     111: aload         7
     113: getfield      #29                 // Field a:I
     116: if_icmpge     169
     119: aload_0
     120: aload_0
     121: getfield      #49                 // Field c:Landroid/support/constraint/a/c;
     124: getfield      #65                 // Field android/support/constraint/a/c.c:[Landroid/support/constraint/a/h;
     127: aload         7
     129: getfield      #35                 // Field f:[I
     132: iload         5
     134: iaload
     135: aaload
     136: aload         7
     138: getfield      #39                 // Field h:[F
     141: iload         5
     143: faload
     144: fload_3
     145: fmul
     146: iconst_1
     147: invokevirtual #96                 // Method a:(Landroid/support/constraint/a/h;FZ)V
     150: aload         7
     152: getfield      #37                 // Field g:[I
     155: iload         5
     157: iaload
     158: istore        5
     160: iload         4
     162: iconst_1
     163: iadd
     164: istore        4
     166: goto          103
     169: aload_1
     170: aload_1
     171: getfield      #99                 // Field android/support/constraint/a/b.b:F
     174: aload         6
     176: getfield      #99                 // Field android/support/constraint/a/b.b:F
     179: fload_3
     180: fmul
     181: fadd
     182: putfield      #99                 // Field android/support/constraint/a/b.b:F
     185: aload         6
     187: getfield      #88                 // Field android/support/constraint/a/b.a:Landroid/support/constraint/a/h;
     190: aload_1
     191: invokevirtual #59                 // Method android/support/constraint/a/h.b:(Landroid/support/constraint/a/b;)V
     194: aload_0
     195: getfield      #41                 // Field i:I
     198: istore        4
     200: goto          6
     203: aload_0
     204: getfield      #37                 // Field g:[I
     207: iload         4
     209: iaload
     210: istore        4
     212: iload         5
     214: iconst_1
     215: iadd
     216: istore        5
     218: goto          9
     221: return

  public final void a(android.support.constraint.a.h, float);
    Code:
       0: fload_2
       1: fconst_0
       2: fcmpl
       3: ifne          14
       6: aload_0
       7: aload_1
       8: iconst_1
       9: invokevirtual #90                 // Method a:(Landroid/support/constraint/a/h;Z)F
      12: pop
      13: return
      14: aload_0
      15: getfield      #41                 // Field i:I
      18: iconst_m1
      19: if_icmpne     134
      22: aload_0
      23: iconst_0
      24: putfield      #41                 // Field i:I
      27: aload_0
      28: getfield      #39                 // Field h:[F
      31: aload_0
      32: getfield      #41                 // Field i:I
      35: fload_2
      36: fastore
      37: aload_0
      38: getfield      #35                 // Field f:[I
      41: aload_0
      42: getfield      #41                 // Field i:I
      45: aload_1
      46: getfield      #56                 // Field android/support/constraint/a/h.a:I
      49: iastore
      50: aload_0
      51: getfield      #37                 // Field g:[I
      54: aload_0
      55: getfield      #41                 // Field i:I
      58: iconst_m1
      59: iastore
      60: aload_1
      61: aload_1
      62: getfield      #54                 // Field android/support/constraint/a/h.i:I
      65: iconst_1
      66: iadd
      67: putfield      #54                 // Field android/support/constraint/a/h.i:I
      70: aload_1
      71: aload_0
      72: getfield      #47                 // Field b:Landroid/support/constraint/a/b;
      75: invokevirtual #107                // Method android/support/constraint/a/h.a:(Landroid/support/constraint/a/b;)V
      78: aload_0
      79: aload_0
      80: getfield      #29                 // Field a:I
      83: iconst_1
      84: iadd
      85: putfield      #29                 // Field a:I
      88: aload_0
      89: getfield      #45                 // Field k:Z
      92: ifne          133
      95: aload_0
      96: aload_0
      97: getfield      #43                 // Field j:I
     100: iconst_1
     101: iadd
     102: putfield      #43                 // Field j:I
     105: aload_0
     106: getfield      #43                 // Field j:I
     109: aload_0
     110: getfield      #35                 // Field f:[I
     113: arraylength
     114: if_icmplt     133
     117: aload_0
     118: iconst_1
     119: putfield      #45                 // Field k:Z
     122: aload_0
     123: aload_0
     124: getfield      #35                 // Field f:[I
     127: arraylength
     128: iconst_1
     129: isub
     130: putfield      #43                 // Field j:I
     133: return
     134: aload_0
     135: getfield      #41                 // Field i:I
     138: istore_3
     139: iconst_0
     140: istore        4
     142: iconst_m1
     143: istore        6
     145: iload_3
     146: iconst_m1
     147: if_icmpeq     212
     150: iload         4
     152: aload_0
     153: getfield      #29                 // Field a:I
     156: if_icmpge     212
     159: aload_0
     160: getfield      #35                 // Field f:[I
     163: iload_3
     164: iaload
     165: aload_1
     166: getfield      #56                 // Field android/support/constraint/a/h.a:I
     169: if_icmpne     180
     172: aload_0
     173: getfield      #39                 // Field h:[F
     176: iload_3
     177: fload_2
     178: fastore
     179: return
     180: aload_0
     181: getfield      #35                 // Field f:[I
     184: iload_3
     185: iaload
     186: aload_1
     187: getfield      #56                 // Field android/support/constraint/a/h.a:I
     190: if_icmpge     196
     193: iload_3
     194: istore        6
     196: aload_0
     197: getfield      #37                 // Field g:[I
     200: iload_3
     201: iaload
     202: istore_3
     203: iload         4
     205: iconst_1
     206: iadd
     207: istore        4
     209: goto          145
     212: aload_0
     213: getfield      #43                 // Field j:I
     216: iconst_1
     217: iadd
     218: istore_3
     219: aload_0
     220: getfield      #45                 // Field k:Z
     223: ifeq          253
     226: aload_0
     227: getfield      #35                 // Field f:[I
     230: aload_0
     231: getfield      #43                 // Field j:I
     234: iaload
     235: iconst_m1
     236: if_icmpne     247
     239: aload_0
     240: getfield      #43                 // Field j:I
     243: istore_3
     244: goto          253
     247: aload_0
     248: getfield      #35                 // Field f:[I
     251: arraylength
     252: istore_3
     253: iload_3
     254: istore        4
     256: iload_3
     257: aload_0
     258: getfield      #35                 // Field f:[I
     261: arraylength
     262: if_icmplt     323
     265: iload_3
     266: istore        4
     268: aload_0
     269: getfield      #29                 // Field a:I
     272: aload_0
     273: getfield      #35                 // Field f:[I
     276: arraylength
     277: if_icmpge     323
     280: iconst_0
     281: istore        5
     283: iload_3
     284: istore        4
     286: iload         5
     288: aload_0
     289: getfield      #35                 // Field f:[I
     292: arraylength
     293: if_icmpge     323
     296: aload_0
     297: getfield      #35                 // Field f:[I
     300: iload         5
     302: iaload
     303: iconst_m1
     304: if_icmpne     314
     307: iload         5
     309: istore        4
     311: goto          323
     314: iload         5
     316: iconst_1
     317: iadd
     318: istore        5
     320: goto          283
     323: iload         4
     325: istore_3
     326: iload         4
     328: aload_0
     329: getfield      #35                 // Field f:[I
     332: arraylength
     333: if_icmplt     409
     336: aload_0
     337: getfield      #35                 // Field f:[I
     340: arraylength
     341: istore_3
     342: aload_0
     343: aload_0
     344: getfield      #31                 // Field d:I
     347: iconst_2
     348: imul
     349: putfield      #31                 // Field d:I
     352: aload_0
     353: iconst_0
     354: putfield      #45                 // Field k:Z
     357: aload_0
     358: iload_3
     359: iconst_1
     360: isub
     361: putfield      #43                 // Field j:I
     364: aload_0
     365: aload_0
     366: getfield      #39                 // Field h:[F
     369: aload_0
     370: getfield      #31                 // Field d:I
     373: invokestatic  #113                // Method java/util/Arrays.copyOf:([FI)[F
     376: putfield      #39                 // Field h:[F
     379: aload_0
     380: aload_0
     381: getfield      #35                 // Field f:[I
     384: aload_0
     385: getfield      #31                 // Field d:I
     388: invokestatic  #116                // Method java/util/Arrays.copyOf:([II)[I
     391: putfield      #35                 // Field f:[I
     394: aload_0
     395: aload_0
     396: getfield      #37                 // Field g:[I
     399: aload_0
     400: getfield      #31                 // Field d:I
     403: invokestatic  #116                // Method java/util/Arrays.copyOf:([II)[I
     406: putfield      #37                 // Field g:[I
     409: aload_0
     410: getfield      #35                 // Field f:[I
     413: iload_3
     414: aload_1
     415: getfield      #56                 // Field android/support/constraint/a/h.a:I
     418: iastore
     419: aload_0
     420: getfield      #39                 // Field h:[F
     423: iload_3
     424: fload_2
     425: fastore
     426: iload         6
     428: iconst_m1
     429: if_icmpeq     456
     432: aload_0
     433: getfield      #37                 // Field g:[I
     436: iload_3
     437: aload_0
     438: getfield      #37                 // Field g:[I
     441: iload         6
     443: iaload
     444: iastore
     445: aload_0
     446: getfield      #37                 // Field g:[I
     449: iload         6
     451: iload_3
     452: iastore
     453: goto          471
     456: aload_0
     457: getfield      #37                 // Field g:[I
     460: iload_3
     461: aload_0
     462: getfield      #41                 // Field i:I
     465: iastore
     466: aload_0
     467: iload_3
     468: putfield      #41                 // Field i:I
     471: aload_1
     472: aload_1
     473: getfield      #54                 // Field android/support/constraint/a/h.i:I
     476: iconst_1
     477: iadd
     478: putfield      #54                 // Field android/support/constraint/a/h.i:I
     481: aload_1
     482: aload_0
     483: getfield      #47                 // Field b:Landroid/support/constraint/a/b;
     486: invokevirtual #107                // Method android/support/constraint/a/h.a:(Landroid/support/constraint/a/b;)V
     489: aload_0
     490: aload_0
     491: getfield      #29                 // Field a:I
     494: iconst_1
     495: iadd
     496: putfield      #29                 // Field a:I
     499: aload_0
     500: getfield      #45                 // Field k:Z
     503: ifne          516
     506: aload_0
     507: aload_0
     508: getfield      #43                 // Field j:I
     511: iconst_1
     512: iadd
     513: putfield      #43                 // Field j:I
     516: aload_0
     517: getfield      #29                 // Field a:I
     520: aload_0
     521: getfield      #35                 // Field f:[I
     524: arraylength
     525: if_icmplt     533
     528: aload_0
     529: iconst_1
     530: putfield      #45                 // Field k:Z
     533: aload_0
     534: getfield      #43                 // Field j:I
     537: aload_0
     538: getfield      #35                 // Field f:[I
     541: arraylength
     542: if_icmplt     561
     545: aload_0
     546: iconst_1
     547: putfield      #45                 // Field k:Z
     550: aload_0
     551: aload_0
     552: getfield      #35                 // Field f:[I
     555: arraylength
     556: iconst_1
     557: isub
     558: putfield      #43                 // Field j:I
     561: return

  final void a(android.support.constraint.a.h, float, boolean);
    Code:
       0: fload_2
       1: fconst_0
       2: fcmpl
       3: ifne          7
       6: return
       7: aload_0
       8: getfield      #41                 // Field i:I
      11: iconst_m1
      12: if_icmpne     127
      15: aload_0
      16: iconst_0
      17: putfield      #41                 // Field i:I
      20: aload_0
      21: getfield      #39                 // Field h:[F
      24: aload_0
      25: getfield      #41                 // Field i:I
      28: fload_2
      29: fastore
      30: aload_0
      31: getfield      #35                 // Field f:[I
      34: aload_0
      35: getfield      #41                 // Field i:I
      38: aload_1
      39: getfield      #56                 // Field android/support/constraint/a/h.a:I
      42: iastore
      43: aload_0
      44: getfield      #37                 // Field g:[I
      47: aload_0
      48: getfield      #41                 // Field i:I
      51: iconst_m1
      52: iastore
      53: aload_1
      54: aload_1
      55: getfield      #54                 // Field android/support/constraint/a/h.i:I
      58: iconst_1
      59: iadd
      60: putfield      #54                 // Field android/support/constraint/a/h.i:I
      63: aload_1
      64: aload_0
      65: getfield      #47                 // Field b:Landroid/support/constraint/a/b;
      68: invokevirtual #107                // Method android/support/constraint/a/h.a:(Landroid/support/constraint/a/b;)V
      71: aload_0
      72: aload_0
      73: getfield      #29                 // Field a:I
      76: iconst_1
      77: iadd
      78: putfield      #29                 // Field a:I
      81: aload_0
      82: getfield      #45                 // Field k:Z
      85: ifne          126
      88: aload_0
      89: aload_0
      90: getfield      #43                 // Field j:I
      93: iconst_1
      94: iadd
      95: putfield      #43                 // Field j:I
      98: aload_0
      99: getfield      #43                 // Field j:I
     102: aload_0
     103: getfield      #35                 // Field f:[I
     106: arraylength
     107: if_icmplt     126
     110: aload_0
     111: iconst_1
     112: putfield      #45                 // Field k:Z
     115: aload_0
     116: aload_0
     117: getfield      #35                 // Field f:[I
     120: arraylength
     121: iconst_1
     122: isub
     123: putfield      #43                 // Field j:I
     126: return
     127: aload_0
     128: getfield      #41                 // Field i:I
     131: istore        4
     133: iconst_0
     134: istore        5
     136: iconst_m1
     137: istore        7
     139: iload         4
     141: iconst_m1
     142: if_icmpeq     317
     145: iload         5
     147: aload_0
     148: getfield      #29                 // Field a:I
     151: if_icmpge     317
     154: aload_0
     155: getfield      #35                 // Field f:[I
     158: iload         4
     160: iaload
     161: aload_1
     162: getfield      #56                 // Field android/support/constraint/a/h.a:I
     165: if_icmpne     281
     168: aload_0
     169: getfield      #39                 // Field h:[F
     172: astore        8
     174: aload         8
     176: iload         4
     178: aload         8
     180: iload         4
     182: faload
     183: fload_2
     184: fadd
     185: fastore
     186: aload_0
     187: getfield      #39                 // Field h:[F
     190: iload         4
     192: faload
     193: fconst_0
     194: fcmpl
     195: ifne          280
     198: iload         4
     200: aload_0
     201: getfield      #41                 // Field i:I
     204: if_icmpne     221
     207: aload_0
     208: aload_0
     209: getfield      #37                 // Field g:[I
     212: iload         4
     214: iaload
     215: putfield      #41                 // Field i:I
     218: goto          235
     221: aload_0
     222: getfield      #37                 // Field g:[I
     225: iload         7
     227: aload_0
     228: getfield      #37                 // Field g:[I
     231: iload         4
     233: iaload
     234: iastore
     235: iload_3
     236: ifeq          247
     239: aload_1
     240: aload_0
     241: getfield      #47                 // Field b:Landroid/support/constraint/a/b;
     244: invokevirtual #59                 // Method android/support/constraint/a/h.b:(Landroid/support/constraint/a/b;)V
     247: aload_0
     248: getfield      #45                 // Field k:Z
     251: ifeq          260
     254: aload_0
     255: iload         4
     257: putfield      #43                 // Field j:I
     260: aload_1
     261: aload_1
     262: getfield      #54                 // Field android/support/constraint/a/h.i:I
     265: iconst_1
     266: isub
     267: putfield      #54                 // Field android/support/constraint/a/h.i:I
     270: aload_0
     271: aload_0
     272: getfield      #29                 // Field a:I
     275: iconst_1
     276: isub
     277: putfield      #29                 // Field a:I
     280: return
     281: aload_0
     282: getfield      #35                 // Field f:[I
     285: iload         4
     287: iaload
     288: aload_1
     289: getfield      #56                 // Field android/support/constraint/a/h.a:I
     292: if_icmpge     299
     295: iload         4
     297: istore        7
     299: aload_0
     300: getfield      #37                 // Field g:[I
     303: iload         4
     305: iaload
     306: istore        4
     308: iload         5
     310: iconst_1
     311: iadd
     312: istore        5
     314: goto          139
     317: aload_0
     318: getfield      #43                 // Field j:I
     321: iconst_1
     322: iadd
     323: istore        4
     325: aload_0
     326: getfield      #45                 // Field k:Z
     329: ifeq          361
     332: aload_0
     333: getfield      #35                 // Field f:[I
     336: aload_0
     337: getfield      #43                 // Field j:I
     340: iaload
     341: iconst_m1
     342: if_icmpne     354
     345: aload_0
     346: getfield      #43                 // Field j:I
     349: istore        4
     351: goto          361
     354: aload_0
     355: getfield      #35                 // Field f:[I
     358: arraylength
     359: istore        4
     361: iload         4
     363: istore        5
     365: iload         4
     367: aload_0
     368: getfield      #35                 // Field f:[I
     371: arraylength
     372: if_icmplt     435
     375: iload         4
     377: istore        5
     379: aload_0
     380: getfield      #29                 // Field a:I
     383: aload_0
     384: getfield      #35                 // Field f:[I
     387: arraylength
     388: if_icmpge     435
     391: iconst_0
     392: istore        6
     394: iload         4
     396: istore        5
     398: iload         6
     400: aload_0
     401: getfield      #35                 // Field f:[I
     404: arraylength
     405: if_icmpge     435
     408: aload_0
     409: getfield      #35                 // Field f:[I
     412: iload         6
     414: iaload
     415: iconst_m1
     416: if_icmpne     426
     419: iload         6
     421: istore        5
     423: goto          435
     426: iload         6
     428: iconst_1
     429: iadd
     430: istore        6
     432: goto          394
     435: iload         5
     437: istore        4
     439: iload         5
     441: aload_0
     442: getfield      #35                 // Field f:[I
     445: arraylength
     446: if_icmplt     524
     449: aload_0
     450: getfield      #35                 // Field f:[I
     453: arraylength
     454: istore        4
     456: aload_0
     457: aload_0
     458: getfield      #31                 // Field d:I
     461: iconst_2
     462: imul
     463: putfield      #31                 // Field d:I
     466: aload_0
     467: iconst_0
     468: putfield      #45                 // Field k:Z
     471: aload_0
     472: iload         4
     474: iconst_1
     475: isub
     476: putfield      #43                 // Field j:I
     479: aload_0
     480: aload_0
     481: getfield      #39                 // Field h:[F
     484: aload_0
     485: getfield      #31                 // Field d:I
     488: invokestatic  #113                // Method java/util/Arrays.copyOf:([FI)[F
     491: putfield      #39                 // Field h:[F
     494: aload_0
     495: aload_0
     496: getfield      #35                 // Field f:[I
     499: aload_0
     500: getfield      #31                 // Field d:I
     503: invokestatic  #116                // Method java/util/Arrays.copyOf:([II)[I
     506: putfield      #35                 // Field f:[I
     509: aload_0
     510: aload_0
     511: getfield      #37                 // Field g:[I
     514: aload_0
     515: getfield      #31                 // Field d:I
     518: invokestatic  #116                // Method java/util/Arrays.copyOf:([II)[I
     521: putfield      #37                 // Field g:[I
     524: aload_0
     525: getfield      #35                 // Field f:[I
     528: iload         4
     530: aload_1
     531: getfield      #56                 // Field android/support/constraint/a/h.a:I
     534: iastore
     535: aload_0
     536: getfield      #39                 // Field h:[F
     539: iload         4
     541: fload_2
     542: fastore
     543: iload         7
     545: iconst_m1
     546: if_icmpeq     575
     549: aload_0
     550: getfield      #37                 // Field g:[I
     553: iload         4
     555: aload_0
     556: getfield      #37                 // Field g:[I
     559: iload         7
     561: iaload
     562: iastore
     563: aload_0
     564: getfield      #37                 // Field g:[I
     567: iload         7
     569: iload         4
     571: iastore
     572: goto          592
     575: aload_0
     576: getfield      #37                 // Field g:[I
     579: iload         4
     581: aload_0
     582: getfield      #41                 // Field i:I
     585: iastore
     586: aload_0
     587: iload         4
     589: putfield      #41                 // Field i:I
     592: aload_1
     593: aload_1
     594: getfield      #54                 // Field android/support/constraint/a/h.i:I
     597: iconst_1
     598: iadd
     599: putfield      #54                 // Field android/support/constraint/a/h.i:I
     602: aload_1
     603: aload_0
     604: getfield      #47                 // Field b:Landroid/support/constraint/a/b;
     607: invokevirtual #107                // Method android/support/constraint/a/h.a:(Landroid/support/constraint/a/b;)V
     610: aload_0
     611: aload_0
     612: getfield      #29                 // Field a:I
     615: iconst_1
     616: iadd
     617: putfield      #29                 // Field a:I
     620: aload_0
     621: getfield      #45                 // Field k:Z
     624: ifne          637
     627: aload_0
     628: aload_0
     629: getfield      #43                 // Field j:I
     632: iconst_1
     633: iadd
     634: putfield      #43                 // Field j:I
     637: aload_0
     638: getfield      #43                 // Field j:I
     641: aload_0
     642: getfield      #35                 // Field f:[I
     645: arraylength
     646: if_icmplt     665
     649: aload_0
     650: iconst_1
     651: putfield      #45                 // Field k:Z
     654: aload_0
     655: aload_0
     656: getfield      #35                 // Field f:[I
     659: arraylength
     660: iconst_1
     661: isub
     662: putfield      #43                 // Field j:I
     665: return

  final boolean a(android.support.constraint.a.h);
    Code:
       0: aload_0
       1: getfield      #41                 // Field i:I
       4: iconst_m1
       5: if_icmpne     10
       8: iconst_0
       9: ireturn
      10: aload_0
      11: getfield      #41                 // Field i:I
      14: istore_3
      15: iconst_0
      16: istore_2
      17: iload_3
      18: iconst_m1
      19: if_icmpeq     59
      22: iload_2
      23: aload_0
      24: getfield      #29                 // Field a:I
      27: if_icmpge     59
      30: aload_0
      31: getfield      #35                 // Field f:[I
      34: iload_3
      35: iaload
      36: aload_1
      37: getfield      #56                 // Field android/support/constraint/a/h.a:I
      40: if_icmpne     45
      43: iconst_1
      44: ireturn
      45: aload_0
      46: getfield      #37                 // Field g:[I
      49: iload_3
      50: iaload
      51: istore_3
      52: iload_2
      53: iconst_1
      54: iadd
      55: istore_2
      56: goto          17
      59: iconst_0
      60: ireturn

  final float b(int);
    Code:
       0: aload_0
       1: getfield      #41                 // Field i:I
       4: istore_3
       5: iconst_0
       6: istore_2
       7: iload_3
       8: iconst_m1
       9: if_icmpeq     46
      12: iload_2
      13: aload_0
      14: getfield      #29                 // Field a:I
      17: if_icmpge     46
      20: iload_2
      21: iload_1
      22: if_icmpne     32
      25: aload_0
      26: getfield      #39                 // Field h:[F
      29: iload_3
      30: faload
      31: freturn
      32: aload_0
      33: getfield      #37                 // Field g:[I
      36: iload_3
      37: iaload
      38: istore_3
      39: iload_2
      40: iconst_1
      41: iadd
      42: istore_2
      43: goto          7
      46: fconst_0
      47: freturn

  public final float b(android.support.constraint.a.h);
    Code:
       0: aload_0
       1: getfield      #41                 // Field i:I
       4: istore_3
       5: iconst_0
       6: istore_2
       7: iload_3
       8: iconst_m1
       9: if_icmpeq     54
      12: iload_2
      13: aload_0
      14: getfield      #29                 // Field a:I
      17: if_icmpge     54
      20: aload_0
      21: getfield      #35                 // Field f:[I
      24: iload_3
      25: iaload
      26: aload_1
      27: getfield      #56                 // Field android/support/constraint/a/h.a:I
      30: if_icmpne     40
      33: aload_0
      34: getfield      #39                 // Field h:[F
      37: iload_3
      38: faload
      39: freturn
      40: aload_0
      41: getfield      #37                 // Field g:[I
      44: iload_3
      45: iaload
      46: istore_3
      47: iload_2
      48: iconst_1
      49: iadd
      50: istore_2
      51: goto          7
      54: fconst_0
      55: freturn

  void b();
    Code:
       0: aload_0
       1: getfield      #41                 // Field i:I
       4: istore_2
       5: iconst_0
       6: istore_1
       7: iload_2
       8: iconst_m1
       9: if_icmpeq     48
      12: iload_1
      13: aload_0
      14: getfield      #29                 // Field a:I
      17: if_icmpge     48
      20: aload_0
      21: getfield      #39                 // Field h:[F
      24: astore_3
      25: aload_3
      26: iload_2
      27: aload_3
      28: iload_2
      29: faload
      30: ldc           #120                // float -1.0f
      32: fmul
      33: fastore
      34: aload_0
      35: getfield      #37                 // Field g:[I
      38: iload_2
      39: iaload
      40: istore_2
      41: iload_1
      42: iconst_1
      43: iadd
      44: istore_1
      45: goto          7
      48: return

  public java.lang.String toString();
    Code:
       0: ldc           #124                // String
       2: astore_3
       3: aload_0
       4: getfield      #41                 // Field i:I
       7: istore_2
       8: iconst_0
       9: istore_1
      10: iload_2
      11: iconst_m1
      12: if_icmpeq     151
      15: iload_1
      16: aload_0
      17: getfield      #29                 // Field a:I
      20: if_icmpge     151
      23: new           #126                // class java/lang/StringBuilder
      26: dup
      27: invokespecial #127                // Method java/lang/StringBuilder."<init>":()V
      30: astore        4
      32: aload         4
      34: aload_3
      35: invokevirtual #131                // Method java/lang/StringBuilder.append:(Ljava/lang/String;)Ljava/lang/StringBuilder;
      38: pop
      39: aload         4
      41: ldc           #133                // String  ->
      43: invokevirtual #131                // Method java/lang/StringBuilder.append:(Ljava/lang/String;)Ljava/lang/StringBuilder;
      46: pop
      47: aload         4
      49: invokevirtual #135                // Method java/lang/StringBuilder.toString:()Ljava/lang/String;
      52: astore_3
      53: new           #126                // class java/lang/StringBuilder
      56: dup
      57: invokespecial #127                // Method java/lang/StringBuilder."<init>":()V
      60: astore        4
      62: aload         4
      64: aload_3
      65: invokevirtual #131                // Method java/lang/StringBuilder.append:(Ljava/lang/String;)Ljava/lang/StringBuilder;
      68: pop
      69: aload         4
      71: aload_0
      72: getfield      #39                 // Field h:[F
      75: iload_2
      76: faload
      77: invokevirtual #138                // Method java/lang/StringBuilder.append:(F)Ljava/lang/StringBuilder;
      80: pop
      81: aload         4
      83: ldc           #140                // String  :
      85: invokevirtual #131                // Method java/lang/StringBuilder.append:(Ljava/lang/String;)Ljava/lang/StringBuilder;
      88: pop
      89: aload         4
      91: invokevirtual #135                // Method java/lang/StringBuilder.toString:()Ljava/lang/String;
      94: astore_3
      95: new           #126                // class java/lang/StringBuilder
      98: dup
      99: invokespecial #127                // Method java/lang/StringBuilder."<init>":()V
     102: astore        4
     104: aload         4
     106: aload_3
     107: invokevirtual #131                // Method java/lang/StringBuilder.append:(Ljava/lang/String;)Ljava/lang/StringBuilder;
     110: pop
     111: aload         4
     113: aload_0
     114: getfield      #49                 // Field c:Landroid/support/constraint/a/c;
     117: getfield      #65                 // Field android/support/constraint/a/c.c:[Landroid/support/constraint/a/h;
     120: aload_0
     121: getfield      #35                 // Field f:[I
     124: iload_2
     125: iaload
     126: aaload
     127: invokevirtual #143                // Method java/lang/StringBuilder.append:(Ljava/lang/Object;)Ljava/lang/StringBuilder;
     130: pop
     131: aload         4
     133: invokevirtual #135                // Method java/lang/StringBuilder.toString:()Ljava/lang/String;
     136: astore_3
     137: aload_0
     138: getfield      #37                 // Field g:[I
     141: iload_2
     142: iaload
     143: istore_2
     144: iload_1
     145: iconst_1
     146: iadd
     147: istore_1
     148: goto          10
     151: aload_3
     152: areturn
}
