public class android.support.constraint.a.b implements android.support.constraint.a.e$a {
  android.support.constraint.a.h a;

  float b;

  boolean c;

  public final android.support.constraint.a.a d;

  boolean e;

  public android.support.constraint.a.b(android.support.constraint.a.c);
    Code:
       0: aload_0
       1: invokespecial #20                 // Method java/lang/Object."<init>":()V
       4: aload_0
       5: aconst_null
       6: putfield      #22                 // Field a:Landroid/support/constraint/a/h;
       9: aload_0
      10: fconst_0
      11: putfield      #24                 // Field b:F
      14: aload_0
      15: iconst_0
      16: putfield      #26                 // Field c:Z
      19: aload_0
      20: iconst_0
      21: putfield      #28                 // Field e:Z
      24: aload_0
      25: new           #30                 // class android/support/constraint/a/a
      28: dup
      29: aload_0
      30: aload_1
      31: invokespecial #33                 // Method android/support/constraint/a/a."<init>":(Landroid/support/constraint/a/b;Landroid/support/constraint/a/c;)V
      34: putfield      #35                 // Field d:Landroid/support/constraint/a/a;
      37: return

  public android.support.constraint.a.b a(float, float, float, android.support.constraint.a.h, android.support.constraint.a.h, android.support.constraint.a.h, android.support.constraint.a.h);
    Code:
       0: fload_2
       1: fconst_0
       2: fcmpl
       3: ifeq          72
       6: fload_1
       7: fload_3
       8: fcmpl
       9: ifne          15
      12: goto          72
      15: fload_1
      16: fload_2
      17: fdiv
      18: fload_3
      19: fload_2
      20: fdiv
      21: fdiv
      22: fstore_1
      23: aload_0
      24: fconst_0
      25: putfield      #24                 // Field b:F
      28: aload_0
      29: getfield      #35                 // Field d:Landroid/support/constraint/a/a;
      32: aload         4
      34: fconst_1
      35: invokevirtual #40                 // Method android/support/constraint/a/a.a:(Landroid/support/constraint/a/h;F)V
      38: aload_0
      39: getfield      #35                 // Field d:Landroid/support/constraint/a/a;
      42: aload         5
      44: ldc           #41                 // float -1.0f
      46: invokevirtual #40                 // Method android/support/constraint/a/a.a:(Landroid/support/constraint/a/h;F)V
      49: aload_0
      50: getfield      #35                 // Field d:Landroid/support/constraint/a/a;
      53: aload         7
      55: fload_1
      56: invokevirtual #40                 // Method android/support/constraint/a/a.a:(Landroid/support/constraint/a/h;F)V
      59: aload_0
      60: getfield      #35                 // Field d:Landroid/support/constraint/a/a;
      63: aload         6
      65: fload_1
      66: fneg
      67: invokevirtual #40                 // Method android/support/constraint/a/a.a:(Landroid/support/constraint/a/h;F)V
      70: aload_0
      71: areturn
      72: aload_0
      73: fconst_0
      74: putfield      #24                 // Field b:F
      77: aload_0
      78: getfield      #35                 // Field d:Landroid/support/constraint/a/a;
      81: aload         4
      83: fconst_1
      84: invokevirtual #40                 // Method android/support/constraint/a/a.a:(Landroid/support/constraint/a/h;F)V
      87: aload_0
      88: getfield      #35                 // Field d:Landroid/support/constraint/a/a;
      91: aload         5
      93: ldc           #41                 // float -1.0f
      95: invokevirtual #40                 // Method android/support/constraint/a/a.a:(Landroid/support/constraint/a/h;F)V
      98: aload_0
      99: getfield      #35                 // Field d:Landroid/support/constraint/a/a;
     102: aload         7
     104: fconst_1
     105: invokevirtual #40                 // Method android/support/constraint/a/a.a:(Landroid/support/constraint/a/h;F)V
     108: aload_0
     109: getfield      #35                 // Field d:Landroid/support/constraint/a/a;
     112: aload         6
     114: ldc           #41                 // float -1.0f
     116: invokevirtual #40                 // Method android/support/constraint/a/a.a:(Landroid/support/constraint/a/h;F)V
     119: aload_0
     120: areturn

  public android.support.constraint.a.b a(android.support.constraint.a.e, int);
    Code:
       0: aload_0
       1: getfield      #35                 // Field d:Landroid/support/constraint/a/a;
       4: aload_1
       5: iload_2
       6: ldc           #44                 // String ep
       8: invokevirtual #49                 // Method android/support/constraint/a/e.a:(ILjava/lang/String;)Landroid/support/constraint/a/h;
      11: fconst_1
      12: invokevirtual #40                 // Method android/support/constraint/a/a.a:(Landroid/support/constraint/a/h;F)V
      15: aload_0
      16: getfield      #35                 // Field d:Landroid/support/constraint/a/a;
      19: aload_1
      20: iload_2
      21: ldc           #51                 // String em
      23: invokevirtual #49                 // Method android/support/constraint/a/e.a:(ILjava/lang/String;)Landroid/support/constraint/a/h;
      26: ldc           #41                 // float -1.0f
      28: invokevirtual #40                 // Method android/support/constraint/a/a.a:(Landroid/support/constraint/a/h;F)V
      31: aload_0
      32: areturn

  android.support.constraint.a.b a(android.support.constraint.a.h, int);
    Code:
       0: aload_0
       1: aload_1
       2: putfield      #22                 // Field a:Landroid/support/constraint/a/h;
       5: iload_2
       6: i2f
       7: fstore_3
       8: aload_1
       9: fload_3
      10: putfield      #56                 // Field android/support/constraint/a/h.d:F
      13: aload_0
      14: fload_3
      15: putfield      #24                 // Field b:F
      18: aload_0
      19: iconst_1
      20: putfield      #28                 // Field e:Z
      23: aload_0
      24: areturn

  public android.support.constraint.a.b a(android.support.constraint.a.h, android.support.constraint.a.h, int);
    Code:
       0: iconst_0
       1: istore        4
       3: iconst_0
       4: istore        5
       6: iload_3
       7: ifeq          36
      10: iload         5
      12: istore        4
      14: iload_3
      15: istore        5
      17: iload_3
      18: ifge          29
      21: iload_3
      22: iconst_m1
      23: imul
      24: istore        5
      26: iconst_1
      27: istore        4
      29: aload_0
      30: iload         5
      32: i2f
      33: putfield      #24                 // Field b:F
      36: iload         4
      38: ifne          62
      41: aload_0
      42: getfield      #35                 // Field d:Landroid/support/constraint/a/a;
      45: aload_1
      46: ldc           #41                 // float -1.0f
      48: invokevirtual #40                 // Method android/support/constraint/a/a.a:(Landroid/support/constraint/a/h;F)V
      51: aload_0
      52: getfield      #35                 // Field d:Landroid/support/constraint/a/a;
      55: aload_2
      56: fconst_1
      57: invokevirtual #40                 // Method android/support/constraint/a/a.a:(Landroid/support/constraint/a/h;F)V
      60: aload_0
      61: areturn
      62: aload_0
      63: getfield      #35                 // Field d:Landroid/support/constraint/a/a;
      66: aload_1
      67: fconst_1
      68: invokevirtual #40                 // Method android/support/constraint/a/a.a:(Landroid/support/constraint/a/h;F)V
      71: aload_0
      72: getfield      #35                 // Field d:Landroid/support/constraint/a/a;
      75: aload_2
      76: ldc           #41                 // float -1.0f
      78: invokevirtual #40                 // Method android/support/constraint/a/a.a:(Landroid/support/constraint/a/h;F)V
      81: aload_0
      82: areturn

  android.support.constraint.a.b a(android.support.constraint.a.h, android.support.constraint.a.h, int, float, android.support.constraint.a.h, android.support.constraint.a.h, int);
    Code:
       0: aload_2
       1: aload         5
       3: if_acmpne     37
       6: aload_0
       7: getfield      #35                 // Field d:Landroid/support/constraint/a/a;
      10: aload_1
      11: fconst_1
      12: invokevirtual #40                 // Method android/support/constraint/a/a.a:(Landroid/support/constraint/a/h;F)V
      15: aload_0
      16: getfield      #35                 // Field d:Landroid/support/constraint/a/a;
      19: aload         6
      21: fconst_1
      22: invokevirtual #40                 // Method android/support/constraint/a/a.a:(Landroid/support/constraint/a/h;F)V
      25: aload_0
      26: getfield      #35                 // Field d:Landroid/support/constraint/a/a;
      29: aload_2
      30: ldc           #59                 // float -2.0f
      32: invokevirtual #40                 // Method android/support/constraint/a/a.a:(Landroid/support/constraint/a/h;F)V
      35: aload_0
      36: areturn
      37: fload         4
      39: ldc           #60                 // float 0.5f
      41: fcmpl
      42: ifne          110
      45: aload_0
      46: getfield      #35                 // Field d:Landroid/support/constraint/a/a;
      49: aload_1
      50: fconst_1
      51: invokevirtual #40                 // Method android/support/constraint/a/a.a:(Landroid/support/constraint/a/h;F)V
      54: aload_0
      55: getfield      #35                 // Field d:Landroid/support/constraint/a/a;
      58: aload_2
      59: ldc           #41                 // float -1.0f
      61: invokevirtual #40                 // Method android/support/constraint/a/a.a:(Landroid/support/constraint/a/h;F)V
      64: aload_0
      65: getfield      #35                 // Field d:Landroid/support/constraint/a/a;
      68: aload         5
      70: ldc           #41                 // float -1.0f
      72: invokevirtual #40                 // Method android/support/constraint/a/a.a:(Landroid/support/constraint/a/h;F)V
      75: aload_0
      76: getfield      #35                 // Field d:Landroid/support/constraint/a/a;
      79: aload         6
      81: fconst_1
      82: invokevirtual #40                 // Method android/support/constraint/a/a.a:(Landroid/support/constraint/a/h;F)V
      85: iload_3
      86: ifgt          94
      89: iload         7
      91: ifle          268
      94: iload_3
      95: ineg
      96: iload         7
      98: iadd
      99: i2f
     100: fstore        4
     102: aload_0
     103: fload         4
     105: putfield      #24                 // Field b:F
     108: aload_0
     109: areturn
     110: fload         4
     112: fconst_0
     113: fcmpg
     114: ifgt          143
     117: aload_0
     118: getfield      #35                 // Field d:Landroid/support/constraint/a/a;
     121: aload_1
     122: ldc           #41                 // float -1.0f
     124: invokevirtual #40                 // Method android/support/constraint/a/a.a:(Landroid/support/constraint/a/h;F)V
     127: aload_0
     128: getfield      #35                 // Field d:Landroid/support/constraint/a/a;
     131: aload_2
     132: fconst_1
     133: invokevirtual #40                 // Method android/support/constraint/a/a.a:(Landroid/support/constraint/a/h;F)V
     136: iload_3
     137: i2f
     138: fstore        4
     140: goto          102
     143: fload         4
     145: fconst_1
     146: fcmpl
     147: iflt          179
     150: aload_0
     151: getfield      #35                 // Field d:Landroid/support/constraint/a/a;
     154: aload         5
     156: ldc           #41                 // float -1.0f
     158: invokevirtual #40                 // Method android/support/constraint/a/a.a:(Landroid/support/constraint/a/h;F)V
     161: aload_0
     162: getfield      #35                 // Field d:Landroid/support/constraint/a/a;
     165: aload         6
     167: fconst_1
     168: invokevirtual #40                 // Method android/support/constraint/a/a.a:(Landroid/support/constraint/a/h;F)V
     171: iload         7
     173: i2f
     174: fstore        4
     176: goto          102
     179: aload_0
     180: getfield      #35                 // Field d:Landroid/support/constraint/a/a;
     183: astore        9
     185: fconst_1
     186: fload         4
     188: fsub
     189: fstore        8
     191: aload         9
     193: aload_1
     194: fload         8
     196: fconst_1
     197: fmul
     198: invokevirtual #40                 // Method android/support/constraint/a/a.a:(Landroid/support/constraint/a/h;F)V
     201: aload_0
     202: getfield      #35                 // Field d:Landroid/support/constraint/a/a;
     205: aload_2
     206: fload         8
     208: ldc           #41                 // float -1.0f
     210: fmul
     211: invokevirtual #40                 // Method android/support/constraint/a/a.a:(Landroid/support/constraint/a/h;F)V
     214: aload_0
     215: getfield      #35                 // Field d:Landroid/support/constraint/a/a;
     218: aload         5
     220: ldc           #41                 // float -1.0f
     222: fload         4
     224: fmul
     225: invokevirtual #40                 // Method android/support/constraint/a/a.a:(Landroid/support/constraint/a/h;F)V
     228: aload_0
     229: getfield      #35                 // Field d:Landroid/support/constraint/a/a;
     232: aload         6
     234: fconst_1
     235: fload         4
     237: fmul
     238: invokevirtual #40                 // Method android/support/constraint/a/a.a:(Landroid/support/constraint/a/h;F)V
     241: iload_3
     242: ifgt          250
     245: iload         7
     247: ifle          268
     250: iload_3
     251: ineg
     252: i2f
     253: fload         8
     255: fmul
     256: iload         7
     258: i2f
     259: fload         4
     261: fmul
     262: fadd
     263: fstore        4
     265: goto          102
     268: aload_0
     269: areturn

  android.support.constraint.a.b a(android.support.constraint.a.h, android.support.constraint.a.h, android.support.constraint.a.h, float);
    Code:
       0: aload_0
       1: getfield      #35                 // Field d:Landroid/support/constraint/a/a;
       4: aload_1
       5: ldc           #41                 // float -1.0f
       7: invokevirtual #40                 // Method android/support/constraint/a/a.a:(Landroid/support/constraint/a/h;F)V
      10: aload_0
      11: getfield      #35                 // Field d:Landroid/support/constraint/a/a;
      14: aload_2
      15: fconst_1
      16: fload         4
      18: fsub
      19: invokevirtual #40                 // Method android/support/constraint/a/a.a:(Landroid/support/constraint/a/h;F)V
      22: aload_0
      23: getfield      #35                 // Field d:Landroid/support/constraint/a/a;
      26: aload_3
      27: fload         4
      29: invokevirtual #40                 // Method android/support/constraint/a/a.a:(Landroid/support/constraint/a/h;F)V
      32: aload_0
      33: areturn

  public android.support.constraint.a.b a(android.support.constraint.a.h, android.support.constraint.a.h, android.support.constraint.a.h, int);
    Code:
       0: iconst_0
       1: istore        5
       3: iconst_0
       4: istore        6
       6: iload         4
       8: ifeq          40
      11: iload         6
      13: istore        5
      15: iload         4
      17: istore        6
      19: iload         4
      21: ifge          33
      24: iload         4
      26: iconst_m1
      27: imul
      28: istore        6
      30: iconst_1
      31: istore        5
      33: aload_0
      34: iload         6
      36: i2f
      37: putfield      #24                 // Field b:F
      40: iload         5
      42: ifne          75
      45: aload_0
      46: getfield      #35                 // Field d:Landroid/support/constraint/a/a;
      49: aload_1
      50: ldc           #41                 // float -1.0f
      52: invokevirtual #40                 // Method android/support/constraint/a/a.a:(Landroid/support/constraint/a/h;F)V
      55: aload_0
      56: getfield      #35                 // Field d:Landroid/support/constraint/a/a;
      59: aload_2
      60: fconst_1
      61: invokevirtual #40                 // Method android/support/constraint/a/a.a:(Landroid/support/constraint/a/h;F)V
      64: aload_0
      65: getfield      #35                 // Field d:Landroid/support/constraint/a/a;
      68: aload_3
      69: fconst_1
      70: invokevirtual #40                 // Method android/support/constraint/a/a.a:(Landroid/support/constraint/a/h;F)V
      73: aload_0
      74: areturn
      75: aload_0
      76: getfield      #35                 // Field d:Landroid/support/constraint/a/a;
      79: aload_1
      80: fconst_1
      81: invokevirtual #40                 // Method android/support/constraint/a/a.a:(Landroid/support/constraint/a/h;F)V
      84: aload_0
      85: getfield      #35                 // Field d:Landroid/support/constraint/a/a;
      88: aload_2
      89: ldc           #41                 // float -1.0f
      91: invokevirtual #40                 // Method android/support/constraint/a/a.a:(Landroid/support/constraint/a/h;F)V
      94: aload_0
      95: getfield      #35                 // Field d:Landroid/support/constraint/a/a;
      98: aload_3
      99: ldc           #41                 // float -1.0f
     101: invokevirtual #40                 // Method android/support/constraint/a/a.a:(Landroid/support/constraint/a/h;F)V
     104: aload_0
     105: areturn

  public android.support.constraint.a.b a(android.support.constraint.a.h, android.support.constraint.a.h, android.support.constraint.a.h, android.support.constraint.a.h, float);
    Code:
       0: aload_0
       1: getfield      #35                 // Field d:Landroid/support/constraint/a/a;
       4: aload_1
       5: ldc           #41                 // float -1.0f
       7: invokevirtual #40                 // Method android/support/constraint/a/a.a:(Landroid/support/constraint/a/h;F)V
      10: aload_0
      11: getfield      #35                 // Field d:Landroid/support/constraint/a/a;
      14: aload_2
      15: fconst_1
      16: invokevirtual #40                 // Method android/support/constraint/a/a.a:(Landroid/support/constraint/a/h;F)V
      19: aload_0
      20: getfield      #35                 // Field d:Landroid/support/constraint/a/a;
      23: aload_3
      24: fload         5
      26: invokevirtual #40                 // Method android/support/constraint/a/a.a:(Landroid/support/constraint/a/h;F)V
      29: aload_0
      30: getfield      #35                 // Field d:Landroid/support/constraint/a/a;
      33: aload         4
      35: fload         5
      37: fneg
      38: invokevirtual #40                 // Method android/support/constraint/a/a.a:(Landroid/support/constraint/a/h;F)V
      41: aload_0
      42: areturn

  public android.support.constraint.a.h a(android.support.constraint.a.e, boolean[]);
    Code:
       0: aload_0
       1: getfield      #35                 // Field d:Landroid/support/constraint/a/a;
       4: aload_2
       5: aconst_null
       6: invokevirtual #67                 // Method android/support/constraint/a/a.a:([ZLandroid/support/constraint/a/h;)Landroid/support/constraint/a/h;
       9: areturn

  public void a(android.support.constraint.a.e$a);
    Code:
       0: aload_1
       1: instanceof    #2                  // class android/support/constraint/a/b
       4: ifeq          74
       7: aload_1
       8: checkcast     #2                  // class android/support/constraint/a/b
      11: astore_1
      12: aload_0
      13: aconst_null
      14: putfield      #22                 // Field a:Landroid/support/constraint/a/h;
      17: aload_0
      18: getfield      #35                 // Field d:Landroid/support/constraint/a/a;
      21: invokevirtual #70                 // Method android/support/constraint/a/a.a:()V
      24: iconst_0
      25: istore_3
      26: iload_3
      27: aload_1
      28: getfield      #35                 // Field d:Landroid/support/constraint/a/a;
      31: getfield      #73                 // Field android/support/constraint/a/a.a:I
      34: if_icmpge     74
      37: aload_1
      38: getfield      #35                 // Field d:Landroid/support/constraint/a/a;
      41: iload_3
      42: invokevirtual #76                 // Method android/support/constraint/a/a.a:(I)Landroid/support/constraint/a/h;
      45: astore        4
      47: aload_1
      48: getfield      #35                 // Field d:Landroid/support/constraint/a/a;
      51: iload_3
      52: invokevirtual #79                 // Method android/support/constraint/a/a.b:(I)F
      55: fstore_2
      56: aload_0
      57: getfield      #35                 // Field d:Landroid/support/constraint/a/a;
      60: aload         4
      62: fload_2
      63: iconst_1
      64: invokevirtual #82                 // Method android/support/constraint/a/a.a:(Landroid/support/constraint/a/h;FZ)V
      67: iload_3
      68: iconst_1
      69: iadd
      70: istore_3
      71: goto          26
      74: return

  boolean a();
    Code:
       0: aload_0
       1: getfield      #22                 // Field a:Landroid/support/constraint/a/h;
       4: ifnull        31
       7: aload_0
       8: getfield      #22                 // Field a:Landroid/support/constraint/a/h;
      11: getfield      #87                 // Field android/support/constraint/a/h.f:Landroid/support/constraint/a/h$a;
      14: getstatic     #91                 // Field android/support/constraint/a/h$a.a:Landroid/support/constraint/a/h$a;
      17: if_acmpeq     29
      20: aload_0
      21: getfield      #24                 // Field b:F
      24: fconst_0
      25: fcmpg
      26: iflt          31
      29: iconst_1
      30: ireturn
      31: iconst_0
      32: ireturn

  boolean a(android.support.constraint.a.e);
    Code:
       0: aload_0
       1: getfield      #35                 // Field d:Landroid/support/constraint/a/a;
       4: aload_1
       5: invokevirtual #95                 // Method android/support/constraint/a/a.a:(Landroid/support/constraint/a/e;)Landroid/support/constraint/a/h;
       8: astore_1
       9: aload_1
      10: ifnonnull     18
      13: iconst_1
      14: istore_2
      15: goto          25
      18: aload_0
      19: aload_1
      20: invokevirtual #98                 // Method c:(Landroid/support/constraint/a/h;)V
      23: iconst_0
      24: istore_2
      25: aload_0
      26: getfield      #35                 // Field d:Landroid/support/constraint/a/a;
      29: getfield      #73                 // Field android/support/constraint/a/a.a:I
      32: ifne          40
      35: aload_0
      36: iconst_1
      37: putfield      #28                 // Field e:Z
      40: iload_2
      41: ireturn

  boolean a(android.support.constraint.a.h);
    Code:
       0: aload_0
       1: getfield      #35                 // Field d:Landroid/support/constraint/a/a;
       4: aload_1
       5: invokevirtual #101                // Method android/support/constraint/a/a.a:(Landroid/support/constraint/a/h;)Z
       8: ireturn

  public android.support.constraint.a.b b(android.support.constraint.a.h, int);
    Code:
       0: iload_2
       1: ifge          29
       4: aload_0
       5: iload_2
       6: iconst_m1
       7: imul
       8: i2f
       9: putfield      #24                 // Field b:F
      12: aload_0
      13: getfield      #35                 // Field d:Landroid/support/constraint/a/a;
      16: astore        4
      18: fconst_1
      19: fstore_3
      20: aload         4
      22: aload_1
      23: fload_3
      24: invokevirtual #40                 // Method android/support/constraint/a/a.a:(Landroid/support/constraint/a/h;F)V
      27: aload_0
      28: areturn
      29: aload_0
      30: iload_2
      31: i2f
      32: putfield      #24                 // Field b:F
      35: aload_0
      36: getfield      #35                 // Field d:Landroid/support/constraint/a/a;
      39: astore        4
      41: ldc           #41                 // float -1.0f
      43: fstore_3
      44: goto          20

  public android.support.constraint.a.b b(android.support.constraint.a.h, android.support.constraint.a.h, android.support.constraint.a.h, int);
    Code:
       0: iconst_0
       1: istore        5
       3: iconst_0
       4: istore        6
       6: iload         4
       8: ifeq          40
      11: iload         6
      13: istore        5
      15: iload         4
      17: istore        6
      19: iload         4
      21: ifge          33
      24: iload         4
      26: iconst_m1
      27: imul
      28: istore        6
      30: iconst_1
      31: istore        5
      33: aload_0
      34: iload         6
      36: i2f
      37: putfield      #24                 // Field b:F
      40: iload         5
      42: ifne          76
      45: aload_0
      46: getfield      #35                 // Field d:Landroid/support/constraint/a/a;
      49: aload_1
      50: ldc           #41                 // float -1.0f
      52: invokevirtual #40                 // Method android/support/constraint/a/a.a:(Landroid/support/constraint/a/h;F)V
      55: aload_0
      56: getfield      #35                 // Field d:Landroid/support/constraint/a/a;
      59: aload_2
      60: fconst_1
      61: invokevirtual #40                 // Method android/support/constraint/a/a.a:(Landroid/support/constraint/a/h;F)V
      64: aload_0
      65: getfield      #35                 // Field d:Landroid/support/constraint/a/a;
      68: aload_3
      69: ldc           #41                 // float -1.0f
      71: invokevirtual #40                 // Method android/support/constraint/a/a.a:(Landroid/support/constraint/a/h;F)V
      74: aload_0
      75: areturn
      76: aload_0
      77: getfield      #35                 // Field d:Landroid/support/constraint/a/a;
      80: aload_1
      81: fconst_1
      82: invokevirtual #40                 // Method android/support/constraint/a/a.a:(Landroid/support/constraint/a/h;F)V
      85: aload_0
      86: getfield      #35                 // Field d:Landroid/support/constraint/a/a;
      89: aload_2
      90: ldc           #41                 // float -1.0f
      92: invokevirtual #40                 // Method android/support/constraint/a/a.a:(Landroid/support/constraint/a/h;F)V
      95: aload_0
      96: getfield      #35                 // Field d:Landroid/support/constraint/a/a;
      99: aload_3
     100: fconst_1
     101: invokevirtual #40                 // Method android/support/constraint/a/a.a:(Landroid/support/constraint/a/h;F)V
     104: aload_0
     105: areturn

  public android.support.constraint.a.b b(android.support.constraint.a.h, android.support.constraint.a.h, android.support.constraint.a.h, android.support.constraint.a.h, float);
    Code:
       0: aload_0
       1: getfield      #35                 // Field d:Landroid/support/constraint/a/a;
       4: aload_3
       5: ldc           #60                 // float 0.5f
       7: invokevirtual #40                 // Method android/support/constraint/a/a.a:(Landroid/support/constraint/a/h;F)V
      10: aload_0
      11: getfield      #35                 // Field d:Landroid/support/constraint/a/a;
      14: aload         4
      16: ldc           #60                 // float 0.5f
      18: invokevirtual #40                 // Method android/support/constraint/a/a.a:(Landroid/support/constraint/a/h;F)V
      21: aload_0
      22: getfield      #35                 // Field d:Landroid/support/constraint/a/a;
      25: aload_1
      26: ldc           #102                // float -0.5f
      28: invokevirtual #40                 // Method android/support/constraint/a/a.a:(Landroid/support/constraint/a/h;F)V
      31: aload_0
      32: getfield      #35                 // Field d:Landroid/support/constraint/a/a;
      35: aload_2
      36: ldc           #102                // float -0.5f
      38: invokevirtual #40                 // Method android/support/constraint/a/a.a:(Landroid/support/constraint/a/h;F)V
      41: aload_0
      42: fload         5
      44: fneg
      45: putfield      #24                 // Field b:F
      48: aload_0
      49: areturn

  android.support.constraint.a.h b(android.support.constraint.a.h);
    Code:
       0: aload_0
       1: getfield      #35                 // Field d:Landroid/support/constraint/a/a;
       4: aconst_null
       5: aload_1
       6: invokevirtual #67                 // Method android/support/constraint/a/a.a:([ZLandroid/support/constraint/a/h;)Landroid/support/constraint/a/h;
       9: areturn

  java.lang.String b();
    Code:
       0: aload_0
       1: getfield      #22                 // Field a:Landroid/support/constraint/a/h;
       4: ifnonnull     42
       7: new           #106                // class java/lang/StringBuilder
      10: dup
      11: invokespecial #107                // Method java/lang/StringBuilder."<init>":()V
      14: astore        6
      16: aload         6
      18: ldc           #109                // String
      20: invokevirtual #113                // Method java/lang/StringBuilder.append:(Ljava/lang/String;)Ljava/lang/StringBuilder;
      23: pop
      24: aload         6
      26: ldc           #115                // String 0
      28: invokevirtual #113                // Method java/lang/StringBuilder.append:(Ljava/lang/String;)Ljava/lang/StringBuilder;
      31: pop
      32: aload         6
      34: invokevirtual #118                // Method java/lang/StringBuilder.toString:()Ljava/lang/String;
      37: astore        6
      39: goto          72
      42: new           #106                // class java/lang/StringBuilder
      45: dup
      46: invokespecial #107                // Method java/lang/StringBuilder."<init>":()V
      49: astore        6
      51: aload         6
      53: ldc           #109                // String
      55: invokevirtual #113                // Method java/lang/StringBuilder.append:(Ljava/lang/String;)Ljava/lang/StringBuilder;
      58: pop
      59: aload         6
      61: aload_0
      62: getfield      #22                 // Field a:Landroid/support/constraint/a/h;
      65: invokevirtual #121                // Method java/lang/StringBuilder.append:(Ljava/lang/Object;)Ljava/lang/StringBuilder;
      68: pop
      69: goto          32
      72: new           #106                // class java/lang/StringBuilder
      75: dup
      76: invokespecial #107                // Method java/lang/StringBuilder."<init>":()V
      79: astore        7
      81: aload         7
      83: aload         6
      85: invokevirtual #113                // Method java/lang/StringBuilder.append:(Ljava/lang/String;)Ljava/lang/StringBuilder;
      88: pop
      89: aload         7
      91: ldc           #123                // String  =
      93: invokevirtual #113                // Method java/lang/StringBuilder.append:(Ljava/lang/String;)Ljava/lang/StringBuilder;
      96: pop
      97: aload         7
      99: invokevirtual #118                // Method java/lang/StringBuilder.toString:()Ljava/lang/String;
     102: astore        6
     104: aload_0
     105: getfield      #24                 // Field b:F
     108: fstore_1
     109: iconst_0
     110: istore        4
     112: fload_1
     113: fconst_0
     114: fcmpl
     115: ifeq          157
     118: new           #106                // class java/lang/StringBuilder
     121: dup
     122: invokespecial #107                // Method java/lang/StringBuilder."<init>":()V
     125: astore        7
     127: aload         7
     129: aload         6
     131: invokevirtual #113                // Method java/lang/StringBuilder.append:(Ljava/lang/String;)Ljava/lang/StringBuilder;
     134: pop
     135: aload         7
     137: aload_0
     138: getfield      #24                 // Field b:F
     141: invokevirtual #126                // Method java/lang/StringBuilder.append:(F)Ljava/lang/StringBuilder;
     144: pop
     145: aload         7
     147: invokevirtual #118                // Method java/lang/StringBuilder.toString:()Ljava/lang/String;
     150: astore        6
     152: iconst_1
     153: istore_3
     154: goto          159
     157: iconst_0
     158: istore_3
     159: aload_0
     160: getfield      #35                 // Field d:Landroid/support/constraint/a/a;
     163: getfield      #73                 // Field android/support/constraint/a/a.a:I
     166: istore        5
     168: iload         4
     170: iload         5
     172: if_icmpge     430
     175: aload_0
     176: getfield      #35                 // Field d:Landroid/support/constraint/a/a;
     179: iload         4
     181: invokevirtual #76                 // Method android/support/constraint/a/a.a:(I)Landroid/support/constraint/a/h;
     184: astore        7
     186: aload         7
     188: ifnonnull     194
     191: goto          421
     194: aload_0
     195: getfield      #35                 // Field d:Landroid/support/constraint/a/a;
     198: iload         4
     200: invokevirtual #79                 // Method android/support/constraint/a/a.b:(I)F
     203: fstore_2
     204: fload_2
     205: fconst_0
     206: fcmpl
     207: ifne          213
     210: goto          421
     213: aload         7
     215: invokevirtual #127                // Method android/support/constraint/a/h.toString:()Ljava/lang/String;
     218: astore        8
     220: iload_3
     221: ifne          280
     224: aload         6
     226: astore        7
     228: fload_2
     229: fstore_1
     230: fload_2
     231: fconst_0
     232: fcmpg
     233: ifge          347
     236: new           #106                // class java/lang/StringBuilder
     239: dup
     240: invokespecial #107                // Method java/lang/StringBuilder."<init>":()V
     243: astore        7
     245: aload         7
     247: aload         6
     249: invokevirtual #113                // Method java/lang/StringBuilder.append:(Ljava/lang/String;)Ljava/lang/StringBuilder;
     252: pop
     253: ldc           #129                // String -
     255: astore        6
     257: aload         7
     259: aload         6
     261: invokevirtual #113                // Method java/lang/StringBuilder.append:(Ljava/lang/String;)Ljava/lang/StringBuilder;
     264: pop
     265: aload         7
     267: invokevirtual #118                // Method java/lang/StringBuilder.toString:()Ljava/lang/String;
     270: astore        7
     272: fload_2
     273: ldc           #41                 // float -1.0f
     275: fmul
     276: fstore_1
     277: goto          347
     280: fload_2
     281: fconst_0
     282: fcmpl
     283: ifle          323
     286: new           #106                // class java/lang/StringBuilder
     289: dup
     290: invokespecial #107                // Method java/lang/StringBuilder."<init>":()V
     293: astore        7
     295: aload         7
     297: aload         6
     299: invokevirtual #113                // Method java/lang/StringBuilder.append:(Ljava/lang/String;)Ljava/lang/StringBuilder;
     302: pop
     303: aload         7
     305: ldc           #131                // String  +
     307: invokevirtual #113                // Method java/lang/StringBuilder.append:(Ljava/lang/String;)Ljava/lang/StringBuilder;
     310: pop
     311: aload         7
     313: invokevirtual #118                // Method java/lang/StringBuilder.toString:()Ljava/lang/String;
     316: astore        7
     318: fload_2
     319: fstore_1
     320: goto          347
     323: new           #106                // class java/lang/StringBuilder
     326: dup
     327: invokespecial #107                // Method java/lang/StringBuilder."<init>":()V
     330: astore        7
     332: aload         7
     334: aload         6
     336: invokevirtual #113                // Method java/lang/StringBuilder.append:(Ljava/lang/String;)Ljava/lang/StringBuilder;
     339: pop
     340: ldc           #133                // String  -
     342: astore        6
     344: goto          257
     347: fload_1
     348: fconst_1
     349: fcmpl
     350: ifne          388
     353: new           #106                // class java/lang/StringBuilder
     356: dup
     357: invokespecial #107                // Method java/lang/StringBuilder."<init>":()V
     360: astore        6
     362: aload         6
     364: aload         7
     366: invokevirtual #113                // Method java/lang/StringBuilder.append:(Ljava/lang/String;)Ljava/lang/StringBuilder;
     369: pop
     370: aload         6
     372: aload         8
     374: invokevirtual #113                // Method java/lang/StringBuilder.append:(Ljava/lang/String;)Ljava/lang/StringBuilder;
     377: pop
     378: aload         6
     380: invokevirtual #118                // Method java/lang/StringBuilder.toString:()Ljava/lang/String;
     383: astore        6
     385: goto          419
     388: new           #106                // class java/lang/StringBuilder
     391: dup
     392: invokespecial #107                // Method java/lang/StringBuilder."<init>":()V
     395: astore        6
     397: aload         6
     399: aload         7
     401: invokevirtual #113                // Method java/lang/StringBuilder.append:(Ljava/lang/String;)Ljava/lang/StringBuilder;
     404: pop
     405: aload         6
     407: fload_1
     408: invokevirtual #126                // Method java/lang/StringBuilder.append:(F)Ljava/lang/StringBuilder;
     411: pop
     412: ldc           #135                // String
     414: astore        7
     416: goto          362
     419: iconst_1
     420: istore_3
     421: iload         4
     423: iconst_1
     424: iadd
     425: istore        4
     427: goto          168
     430: aload         6
     432: astore        7
     434: iload_3
     435: ifne          470
     438: new           #106                // class java/lang/StringBuilder
     441: dup
     442: invokespecial #107                // Method java/lang/StringBuilder."<init>":()V
     445: astore        7
     447: aload         7
     449: aload         6
     451: invokevirtual #113                // Method java/lang/StringBuilder.append:(Ljava/lang/String;)Ljava/lang/StringBuilder;
     454: pop
     455: aload         7
     457: ldc           #137                // String 0.0
     459: invokevirtual #113                // Method java/lang/StringBuilder.append:(Ljava/lang/String;)Ljava/lang/StringBuilder;
     462: pop
     463: aload         7
     465: invokevirtual #118                // Method java/lang/StringBuilder.toString:()Ljava/lang/String;
     468: astore        7
     470: aload         7
     472: areturn

  android.support.constraint.a.b c(android.support.constraint.a.h, int);
    Code:
       0: aload_0
       1: getfield      #35                 // Field d:Landroid/support/constraint/a/a;
       4: aload_1
       5: iload_2
       6: i2f
       7: invokevirtual #40                 // Method android/support/constraint/a/a.a:(Landroid/support/constraint/a/h;F)V
      10: aload_0
      11: areturn

  public void c();
    Code:
       0: aload_0
       1: aconst_null
       2: putfield      #22                 // Field a:Landroid/support/constraint/a/h;
       5: aload_0
       6: getfield      #35                 // Field d:Landroid/support/constraint/a/a;
       9: invokevirtual #70                 // Method android/support/constraint/a/a.a:()V
      12: aload_0
      13: fconst_0
      14: putfield      #24                 // Field b:F
      17: aload_0
      18: iconst_0
      19: putfield      #28                 // Field e:Z
      22: return

  void c(android.support.constraint.a.h);
    Code:
       0: aload_0
       1: getfield      #22                 // Field a:Landroid/support/constraint/a/h;
       4: ifnull        25
       7: aload_0
       8: getfield      #35                 // Field d:Landroid/support/constraint/a/a;
      11: aload_0
      12: getfield      #22                 // Field a:Landroid/support/constraint/a/h;
      15: ldc           #41                 // float -1.0f
      17: invokevirtual #40                 // Method android/support/constraint/a/a.a:(Landroid/support/constraint/a/h;F)V
      20: aload_0
      21: aconst_null
      22: putfield      #22                 // Field a:Landroid/support/constraint/a/h;
      25: aload_0
      26: getfield      #35                 // Field d:Landroid/support/constraint/a/a;
      29: aload_1
      30: iconst_1
      31: invokevirtual #140                // Method android/support/constraint/a/a.a:(Landroid/support/constraint/a/h;Z)F
      34: ldc           #41                 // float -1.0f
      36: fmul
      37: fstore_2
      38: aload_0
      39: aload_1
      40: putfield      #22                 // Field a:Landroid/support/constraint/a/h;
      43: fload_2
      44: fconst_1
      45: fcmpl
      46: ifne          50
      49: return
      50: aload_0
      51: aload_0
      52: getfield      #24                 // Field b:F
      55: fload_2
      56: fdiv
      57: putfield      #24                 // Field b:F
      60: aload_0
      61: getfield      #35                 // Field d:Landroid/support/constraint/a/a;
      64: fload_2
      65: invokevirtual #143                // Method android/support/constraint/a/a.a:(F)V
      68: return

  void d();
    Code:
       0: aload_0
       1: getfield      #24                 // Field b:F
       4: fconst_0
       5: fcmpg
       6: ifge          27
       9: aload_0
      10: aload_0
      11: getfield      #24                 // Field b:F
      14: ldc           #41                 // float -1.0f
      16: fmul
      17: putfield      #24                 // Field b:F
      20: aload_0
      21: getfield      #35                 // Field d:Landroid/support/constraint/a/a;
      24: invokevirtual #145                // Method android/support/constraint/a/a.b:()V
      27: return

  public void d(android.support.constraint.a.h);
    Code:
       0: aload_1
       1: getfield      #147                // Field android/support/constraint/a/h.c:I
       4: istore_3
       5: fconst_1
       6: fstore_2
       7: iload_3
       8: iconst_1
       9: if_icmpne     15
      12: goto          68
      15: aload_1
      16: getfield      #147                // Field android/support/constraint/a/h.c:I
      19: iconst_2
      20: if_icmpne     29
      23: ldc           #148                // float 1000.0f
      25: fstore_2
      26: goto          68
      29: aload_1
      30: getfield      #147                // Field android/support/constraint/a/h.c:I
      33: iconst_3
      34: if_icmpne     43
      37: ldc           #149                // float 1000000.0f
      39: fstore_2
      40: goto          68
      43: aload_1
      44: getfield      #147                // Field android/support/constraint/a/h.c:I
      47: iconst_4
      48: if_icmpne     57
      51: ldc           #150                // float 1.0E9f
      53: fstore_2
      54: goto          68
      57: aload_1
      58: getfield      #147                // Field android/support/constraint/a/h.c:I
      61: iconst_5
      62: if_icmpne     68
      65: ldc           #151                // float 1.0E12f
      67: fstore_2
      68: aload_0
      69: getfield      #35                 // Field d:Landroid/support/constraint/a/a;
      72: aload_1
      73: fload_2
      74: invokevirtual #40                 // Method android/support/constraint/a/a.a:(Landroid/support/constraint/a/h;F)V
      77: return

  public boolean e();
    Code:
       0: aload_0
       1: getfield      #22                 // Field a:Landroid/support/constraint/a/h;
       4: ifnonnull     28
       7: aload_0
       8: getfield      #24                 // Field b:F
      11: fconst_0
      12: fcmpl
      13: ifne          28
      16: aload_0
      17: getfield      #35                 // Field d:Landroid/support/constraint/a/a;
      20: getfield      #73                 // Field android/support/constraint/a/a.a:I
      23: ifne          28
      26: iconst_1
      27: ireturn
      28: iconst_0
      29: ireturn

  public void f();
    Code:
       0: aload_0
       1: getfield      #35                 // Field d:Landroid/support/constraint/a/a;
       4: invokevirtual #70                 // Method android/support/constraint/a/a.a:()V
       7: aload_0
       8: aconst_null
       9: putfield      #22                 // Field a:Landroid/support/constraint/a/h;
      12: aload_0
      13: fconst_0
      14: putfield      #24                 // Field b:F
      17: return

  public android.support.constraint.a.h g();
    Code:
       0: aload_0
       1: getfield      #22                 // Field a:Landroid/support/constraint/a/h;
       4: areturn

  public java.lang.String toString();
    Code:
       0: aload_0
       1: invokevirtual #155                // Method b:()Ljava/lang/String;
       4: areturn
}
