public class android.support.constraint.a.c {
  android.support.constraint.a.g$a<android.support.constraint.a.b> a;

  android.support.constraint.a.g$a<android.support.constraint.a.h> b;

  android.support.constraint.a.h[] c;

  public android.support.constraint.a.c();
    Code:
       0: aload_0
       1: invokespecial #15                 // Method java/lang/Object."<init>":()V
       4: aload_0
       5: new           #17                 // class android/support/constraint/a/g$b
       8: dup
       9: sipush        256
      12: invokespecial #20                 // Method android/support/constraint/a/g$b."<init>":(I)V
      15: putfield      #22                 // Field a:Landroid/support/constraint/a/g$a;
      18: aload_0
      19: new           #17                 // class android/support/constraint/a/g$b
      22: dup
      23: sipush        256
      26: invokespecial #20                 // Method android/support/constraint/a/g$b."<init>":(I)V
      29: putfield      #24                 // Field b:Landroid/support/constraint/a/g$a;
      32: aload_0
      33: bipush        32
      35: anewarray     #26                 // class android/support/constraint/a/h
      38: putfield      #28                 // Field c:[Landroid/support/constraint/a/h;
      41: return
}
