public class android.support.constraint.a.d extends android.support.constraint.a.b {
  public android.support.constraint.a.d(android.support.constraint.a.c);
    Code:
       0: aload_0
       1: aload_1
       2: invokespecial #8                  // Method android/support/constraint/a/b."<init>":(Landroid/support/constraint/a/c;)V
       5: return

  public void d(android.support.constraint.a.h);
    Code:
       0: aload_0
       1: aload_1
       2: invokespecial #13                 // Method android/support/constraint/a/b.d:(Landroid/support/constraint/a/h;)V
       5: aload_1
       6: aload_1
       7: getfield      #19                 // Field android/support/constraint/a/h.i:I
      10: iconst_1
      11: isub
      12: putfield      #19                 // Field android/support/constraint/a/h.i:I
      15: return
}
