public class android.support.constraint.a.e {
  public static android.support.constraint.a.f g;

  int a;

  android.support.constraint.a.b[] b;

  public boolean c;

  int d;

  int e;

  final android.support.constraint.a.c f;

  static {};
    Code:
       0: return

  public android.support.constraint.a.e();
    Code:
       0: aload_0
       1: invokespecial #41                 // Method java/lang/Object."<init>":()V
       4: aload_0
       5: iconst_0
       6: putfield      #43                 // Field a:I
       9: aload_0
      10: aconst_null
      11: putfield      #45                 // Field i:Ljava/util/HashMap;
      14: aload_0
      15: bipush        32
      17: putfield      #47                 // Field k:I
      20: aload_0
      21: aload_0
      22: getfield      #47                 // Field k:I
      25: putfield      #49                 // Field l:I
      28: aload_0
      29: aconst_null
      30: putfield      #51                 // Field b:[Landroid/support/constraint/a/b;
      33: aload_0
      34: iconst_0
      35: putfield      #53                 // Field c:Z
      38: aload_0
      39: aload_0
      40: getfield      #47                 // Field k:I
      43: newarray       boolean
      45: putfield      #55                 // Field m:[Z
      48: aload_0
      49: iconst_1
      50: putfield      #57                 // Field d:I
      53: aload_0
      54: iconst_0
      55: putfield      #59                 // Field e:I
      58: aload_0
      59: aload_0
      60: getfield      #47                 // Field k:I
      63: putfield      #61                 // Field n:I
      66: aload_0
      67: getstatic     #63                 // Field h:I
      70: anewarray     #65                 // class android/support/constraint/a/h
      73: putfield      #67                 // Field o:[Landroid/support/constraint/a/h;
      76: aload_0
      77: iconst_0
      78: putfield      #69                 // Field p:I
      81: aload_0
      82: aload_0
      83: getfield      #47                 // Field k:I
      86: anewarray     #71                 // class android/support/constraint/a/b
      89: putfield      #73                 // Field q:[Landroid/support/constraint/a/b;
      92: aload_0
      93: aload_0
      94: getfield      #47                 // Field k:I
      97: anewarray     #71                 // class android/support/constraint/a/b
     100: putfield      #51                 // Field b:[Landroid/support/constraint/a/b;
     103: aload_0
     104: invokespecial #75                 // Method i:()V
     107: aload_0
     108: new           #77                 // class android/support/constraint/a/c
     111: dup
     112: invokespecial #78                 // Method android/support/constraint/a/c."<init>":()V
     115: putfield      #80                 // Field f:Landroid/support/constraint/a/c;
     118: aload_0
     119: new           #82                 // class android/support/constraint/a/d
     122: dup
     123: aload_0
     124: getfield      #80                 // Field f:Landroid/support/constraint/a/c;
     127: invokespecial #85                 // Method android/support/constraint/a/d."<init>":(Landroid/support/constraint/a/c;)V
     130: putfield      #87                 // Field j:Landroid/support/constraint/a/e$a;
     133: aload_0
     134: new           #71                 // class android/support/constraint/a/b
     137: dup
     138: aload_0
     139: getfield      #80                 // Field f:Landroid/support/constraint/a/c;
     142: invokespecial #88                 // Method android/support/constraint/a/b."<init>":(Landroid/support/constraint/a/c;)V
     145: putfield      #90                 // Field r:Landroid/support/constraint/a/e$a;
     148: return

  public static android.support.constraint.a.b a(android.support.constraint.a.e, android.support.constraint.a.h, android.support.constraint.a.h, android.support.constraint.a.h, float, boolean);
    Code:
       0: aload_0
       1: invokevirtual #148                // Method c:()Landroid/support/constraint/a/b;
       4: astore        6
       6: iload         5
       8: ifeq          17
      11: aload_0
      12: aload         6
      14: invokespecial #150                // Method b:(Landroid/support/constraint/a/b;)V
      17: aload         6
      19: aload_1
      20: aload_2
      21: aload_3
      22: fload         4
      24: invokevirtual #153                // Method android/support/constraint/a/b.a:(Landroid/support/constraint/a/h;Landroid/support/constraint/a/h;Landroid/support/constraint/a/h;F)Landroid/support/constraint/a/b;
      27: areturn

  public static android.support.constraint.a.f a();
    Code:
       0: getstatic     #93                 // Field g:Landroid/support/constraint/a/f;
       3: areturn

  public android.support.constraint.a.h a(int, java.lang.String);
    Code:
       0: getstatic     #93                 // Field g:Landroid/support/constraint/a/f;
       3: ifnull        20
       6: getstatic     #93                 // Field g:Landroid/support/constraint/a/f;
       9: astore_3
      10: aload_3
      11: aload_3
      12: getfield      #216                // Field android/support/constraint/a/f.m:J
      15: lconst_1
      16: ladd
      17: putfield      #216                // Field android/support/constraint/a/f.m:J
      20: aload_0
      21: getfield      #57                 // Field d:I
      24: iconst_1
      25: iadd
      26: aload_0
      27: getfield      #49                 // Field l:I
      30: if_icmplt     37
      33: aload_0
      34: invokespecial #218                // Method h:()V
      37: aload_0
      38: getstatic     #220                // Field android/support/constraint/a/h$a.d:Landroid/support/constraint/a/h$a;
      41: aload_2
      42: invokespecial #222                // Method a:(Landroid/support/constraint/a/h$a;Ljava/lang/String;)Landroid/support/constraint/a/h;
      45: astore_2
      46: aload_0
      47: aload_0
      48: getfield      #43                 // Field a:I
      51: iconst_1
      52: iadd
      53: putfield      #43                 // Field a:I
      56: aload_0
      57: aload_0
      58: getfield      #57                 // Field d:I
      61: iconst_1
      62: iadd
      63: putfield      #57                 // Field d:I
      66: aload_2
      67: aload_0
      68: getfield      #43                 // Field a:I
      71: putfield      #104                // Field android/support/constraint/a/h.a:I
      74: aload_2
      75: iload_1
      76: putfield      #224                // Field android/support/constraint/a/h.c:I
      79: aload_0
      80: getfield      #80                 // Field f:Landroid/support/constraint/a/c;
      83: getfield      #182                // Field android/support/constraint/a/c.c:[Landroid/support/constraint/a/h;
      86: aload_0
      87: getfield      #43                 // Field a:I
      90: aload_2
      91: aastore
      92: aload_0
      93: getfield      #87                 // Field j:Landroid/support/constraint/a/e$a;
      96: aload_2
      97: invokeinterface #226,  2          // InterfaceMethod android/support/constraint/a/e$a.d:(Landroid/support/constraint/a/h;)V
     102: aload_2
     103: areturn

  public android.support.constraint.a.h a(java.lang.Object);
    Code:
       0: aconst_null
       1: astore_2
       2: aload_1
       3: ifnonnull     8
       6: aconst_null
       7: areturn
       8: aload_0
       9: getfield      #57                 // Field d:I
      12: iconst_1
      13: iadd
      14: aload_0
      15: getfield      #49                 // Field l:I
      18: if_icmplt     25
      21: aload_0
      22: invokespecial #218                // Method h:()V
      25: aload_1
      26: instanceof    #229                // class android/support/constraint/a/a/c
      29: ifeq          159
      32: aload_1
      33: checkcast     #229                // class android/support/constraint/a/a/c
      36: astore_3
      37: aload_3
      38: invokevirtual #231                // Method android/support/constraint/a/a/c.b:()Landroid/support/constraint/a/h;
      41: astore_2
      42: aload_2
      43: astore_1
      44: aload_2
      45: ifnonnull     61
      48: aload_3
      49: aload_0
      50: getfield      #80                 // Field f:Landroid/support/constraint/a/c;
      53: invokevirtual #233                // Method android/support/constraint/a/a/c.a:(Landroid/support/constraint/a/c;)V
      56: aload_3
      57: invokevirtual #231                // Method android/support/constraint/a/a/c.b:()Landroid/support/constraint/a/h;
      60: astore_1
      61: aload_1
      62: getfield      #104                // Field android/support/constraint/a/h.a:I
      65: iconst_m1
      66: if_icmpeq     97
      69: aload_1
      70: getfield      #104                // Field android/support/constraint/a/h.a:I
      73: aload_0
      74: getfield      #43                 // Field a:I
      77: if_icmpgt     97
      80: aload_1
      81: astore_2
      82: aload_0
      83: getfield      #80                 // Field f:Landroid/support/constraint/a/c;
      86: getfield      #182                // Field android/support/constraint/a/c.c:[Landroid/support/constraint/a/h;
      89: aload_1
      90: getfield      #104                // Field android/support/constraint/a/h.a:I
      93: aaload
      94: ifnonnull     159
      97: aload_1
      98: getfield      #104                // Field android/support/constraint/a/h.a:I
     101: iconst_m1
     102: if_icmpeq     109
     105: aload_1
     106: invokevirtual #170                // Method android/support/constraint/a/h.b:()V
     109: aload_0
     110: aload_0
     111: getfield      #43                 // Field a:I
     114: iconst_1
     115: iadd
     116: putfield      #43                 // Field a:I
     119: aload_0
     120: aload_0
     121: getfield      #57                 // Field d:I
     124: iconst_1
     125: iadd
     126: putfield      #57                 // Field d:I
     129: aload_1
     130: aload_0
     131: getfield      #43                 // Field a:I
     134: putfield      #104                // Field android/support/constraint/a/h.a:I
     137: aload_1
     138: getstatic     #118                // Field android/support/constraint/a/h$a.a:Landroid/support/constraint/a/h$a;
     141: putfield      #114                // Field android/support/constraint/a/h.f:Landroid/support/constraint/a/h$a;
     144: aload_0
     145: getfield      #80                 // Field f:Landroid/support/constraint/a/c;
     148: getfield      #182                // Field android/support/constraint/a/c.c:[Landroid/support/constraint/a/h;
     151: aload_0
     152: getfield      #43                 // Field a:I
     155: aload_1
     156: aastore
     157: aload_1
     158: astore_2
     159: aload_2
     160: areturn

  public void a(android.support.constraint.a.a.d, android.support.constraint.a.a.d, float, int);
    Code:
       0: aload_0
       1: aload_1
       2: getstatic     #239                // Field android/support/constraint/a/a/c$c.b:Landroid/support/constraint/a/a/c$c;
       5: invokevirtual #244                // Method android/support/constraint/a/a/d.a:(Landroid/support/constraint/a/a/c$c;)Landroid/support/constraint/a/a/c;
       8: invokevirtual #246                // Method a:(Ljava/lang/Object;)Landroid/support/constraint/a/h;
      11: astore        11
      13: aload_0
      14: aload_1
      15: getstatic     #248                // Field android/support/constraint/a/a/c$c.c:Landroid/support/constraint/a/a/c$c;
      18: invokevirtual #244                // Method android/support/constraint/a/a/d.a:(Landroid/support/constraint/a/a/c$c;)Landroid/support/constraint/a/a/c;
      21: invokevirtual #246                // Method a:(Ljava/lang/Object;)Landroid/support/constraint/a/h;
      24: astore        13
      26: aload_0
      27: aload_1
      28: getstatic     #250                // Field android/support/constraint/a/a/c$c.d:Landroid/support/constraint/a/a/c$c;
      31: invokevirtual #244                // Method android/support/constraint/a/a/d.a:(Landroid/support/constraint/a/a/c$c;)Landroid/support/constraint/a/a/c;
      34: invokevirtual #246                // Method a:(Ljava/lang/Object;)Landroid/support/constraint/a/h;
      37: astore        12
      39: aload_0
      40: aload_1
      41: getstatic     #252                // Field android/support/constraint/a/a/c$c.e:Landroid/support/constraint/a/a/c$c;
      44: invokevirtual #244                // Method android/support/constraint/a/a/d.a:(Landroid/support/constraint/a/a/c$c;)Landroid/support/constraint/a/a/c;
      47: invokevirtual #246                // Method a:(Ljava/lang/Object;)Landroid/support/constraint/a/h;
      50: astore        15
      52: aload_0
      53: aload_2
      54: getstatic     #239                // Field android/support/constraint/a/a/c$c.b:Landroid/support/constraint/a/a/c$c;
      57: invokevirtual #244                // Method android/support/constraint/a/a/d.a:(Landroid/support/constraint/a/a/c$c;)Landroid/support/constraint/a/a/c;
      60: invokevirtual #246                // Method a:(Ljava/lang/Object;)Landroid/support/constraint/a/h;
      63: astore_1
      64: aload_0
      65: aload_2
      66: getstatic     #248                // Field android/support/constraint/a/a/c$c.c:Landroid/support/constraint/a/a/c$c;
      69: invokevirtual #244                // Method android/support/constraint/a/a/d.a:(Landroid/support/constraint/a/a/c$c;)Landroid/support/constraint/a/a/c;
      72: invokevirtual #246                // Method a:(Ljava/lang/Object;)Landroid/support/constraint/a/h;
      75: astore        16
      77: aload_0
      78: aload_2
      79: getstatic     #250                // Field android/support/constraint/a/a/c$c.d:Landroid/support/constraint/a/a/c$c;
      82: invokevirtual #244                // Method android/support/constraint/a/a/d.a:(Landroid/support/constraint/a/a/c$c;)Landroid/support/constraint/a/a/c;
      85: invokevirtual #246                // Method a:(Ljava/lang/Object;)Landroid/support/constraint/a/h;
      88: astore        14
      90: aload_0
      91: aload_2
      92: getstatic     #252                // Field android/support/constraint/a/a/c$c.e:Landroid/support/constraint/a/a/c$c;
      95: invokevirtual #244                // Method android/support/constraint/a/a/d.a:(Landroid/support/constraint/a/a/c$c;)Landroid/support/constraint/a/a/c;
      98: invokevirtual #246                // Method a:(Ljava/lang/Object;)Landroid/support/constraint/a/h;
     101: astore_2
     102: aload_0
     103: invokevirtual #148                // Method c:()Landroid/support/constraint/a/b;
     106: astore        17
     108: fload_3
     109: f2d
     110: dstore        5
     112: dload         5
     114: invokestatic  #256                // Method java/lang/Math.sin:(D)D
     117: dstore        7
     119: iload         4
     121: i2d
     122: dstore        9
     124: aload         17
     126: aload         13
     128: aload         15
     130: aload         16
     132: aload_2
     133: dload         7
     135: dload         9
     137: dmul
     138: d2f
     139: invokevirtual #259                // Method android/support/constraint/a/b.b:(Landroid/support/constraint/a/h;Landroid/support/constraint/a/h;Landroid/support/constraint/a/h;Landroid/support/constraint/a/h;F)Landroid/support/constraint/a/b;
     142: pop
     143: aload_0
     144: aload         17
     146: invokevirtual #261                // Method a:(Landroid/support/constraint/a/b;)V
     149: aload_0
     150: invokevirtual #148                // Method c:()Landroid/support/constraint/a/b;
     153: astore_2
     154: aload_2
     155: aload         11
     157: aload         12
     159: aload_1
     160: aload         14
     162: dload         5
     164: invokestatic  #264                // Method java/lang/Math.cos:(D)D
     167: dload         9
     169: dmul
     170: d2f
     171: invokevirtual #259                // Method android/support/constraint/a/b.b:(Landroid/support/constraint/a/h;Landroid/support/constraint/a/h;Landroid/support/constraint/a/h;Landroid/support/constraint/a/h;F)Landroid/support/constraint/a/b;
     174: pop
     175: aload_0
     176: aload_2
     177: invokevirtual #261                // Method a:(Landroid/support/constraint/a/b;)V
     180: return

  public void a(android.support.constraint.a.b);
    Code:
       0: aload_1
       1: ifnonnull     5
       4: return
       5: getstatic     #93                 // Field g:Landroid/support/constraint/a/f;
       8: ifnull        52
      11: getstatic     #93                 // Field g:Landroid/support/constraint/a/f;
      14: astore        4
      16: aload         4
      18: aload         4
      20: getfield      #266                // Field android/support/constraint/a/f.f:J
      23: lconst_1
      24: ladd
      25: putfield      #266                // Field android/support/constraint/a/f.f:J
      28: aload_1
      29: getfield      #120                // Field android/support/constraint/a/b.e:Z
      32: ifeq          52
      35: getstatic     #93                 // Field g:Landroid/support/constraint/a/f;
      38: astore        4
      40: aload         4
      42: aload         4
      44: getfield      #268                // Field android/support/constraint/a/f.g:J
      47: lconst_1
      48: ladd
      49: putfield      #268                // Field android/support/constraint/a/f.g:J
      52: aload_0
      53: getfield      #59                 // Field e:I
      56: iconst_1
      57: iadd
      58: aload_0
      59: getfield      #61                 // Field n:I
      62: if_icmpge     78
      65: aload_0
      66: getfield      #57                 // Field d:I
      69: iconst_1
      70: iadd
      71: aload_0
      72: getfield      #49                 // Field l:I
      75: if_icmplt     82
      78: aload_0
      79: invokespecial #218                // Method h:()V
      82: iconst_0
      83: istore_2
      84: iconst_0
      85: istore_3
      86: aload_1
      87: getfield      #120                // Field android/support/constraint/a/b.e:Z
      90: ifne          252
      93: aload_0
      94: aload_1
      95: invokespecial #269                // Method c:(Landroid/support/constraint/a/b;)V
      98: aload_1
      99: invokevirtual #272                // Method android/support/constraint/a/b.e:()Z
     102: ifeq          106
     105: return
     106: aload_1
     107: invokevirtual #274                // Method android/support/constraint/a/b.d:()V
     110: iload_3
     111: istore_2
     112: aload_1
     113: aload_0
     114: invokevirtual #277                // Method android/support/constraint/a/b.a:(Landroid/support/constraint/a/e;)Z
     117: ifeq          244
     120: aload_0
     121: invokevirtual #279                // Method e:()Landroid/support/constraint/a/h;
     124: astore        4
     126: aload_1
     127: aload         4
     129: putfield      #111                // Field android/support/constraint/a/b.a:Landroid/support/constraint/a/h;
     132: aload_0
     133: aload_1
     134: invokespecial #281                // Method d:(Landroid/support/constraint/a/b;)V
     137: aload_0
     138: getfield      #90                 // Field r:Landroid/support/constraint/a/e$a;
     141: aload_1
     142: invokeinterface #284,  2          // InterfaceMethod android/support/constraint/a/e$a.a:(Landroid/support/constraint/a/e$a;)V
     147: aload_0
     148: aload_0
     149: getfield      #90                 // Field r:Landroid/support/constraint/a/e$a;
     152: iconst_1
     153: invokespecial #286                // Method a:(Landroid/support/constraint/a/e$a;Z)I
     156: pop
     157: aload         4
     159: getfield      #136                // Field android/support/constraint/a/h.b:I
     162: iconst_m1
     163: if_icmpne     242
     166: aload_1
     167: getfield      #111                // Field android/support/constraint/a/b.a:Landroid/support/constraint/a/h;
     170: aload         4
     172: if_acmpne     217
     175: aload_1
     176: aload         4
     178: invokevirtual #289                // Method android/support/constraint/a/b.b:(Landroid/support/constraint/a/h;)Landroid/support/constraint/a/h;
     181: astore        4
     183: aload         4
     185: ifnull        217
     188: getstatic     #93                 // Field g:Landroid/support/constraint/a/f;
     191: ifnull        211
     194: getstatic     #93                 // Field g:Landroid/support/constraint/a/f;
     197: astore        5
     199: aload         5
     201: aload         5
     203: getfield      #138                // Field android/support/constraint/a/f.j:J
     206: lconst_1
     207: ladd
     208: putfield      #138                // Field android/support/constraint/a/f.j:J
     211: aload_1
     212: aload         4
     214: invokevirtual #141                // Method android/support/constraint/a/b.c:(Landroid/support/constraint/a/h;)V
     217: aload_1
     218: getfield      #120                // Field android/support/constraint/a/b.e:Z
     221: ifne          232
     224: aload_1
     225: getfield      #111                // Field android/support/constraint/a/b.a:Landroid/support/constraint/a/h;
     228: aload_1
     229: invokevirtual #144                // Method android/support/constraint/a/h.c:(Landroid/support/constraint/a/b;)V
     232: aload_0
     233: aload_0
     234: getfield      #59                 // Field e:I
     237: iconst_1
     238: isub
     239: putfield      #59                 // Field e:I
     242: iconst_1
     243: istore_2
     244: aload_1
     245: invokevirtual #291                // Method android/support/constraint/a/b.a:()Z
     248: ifne          252
     251: return
     252: iload_2
     253: ifne          261
     256: aload_0
     257: aload_1
     258: invokespecial #281                // Method d:(Landroid/support/constraint/a/b;)V
     261: return

  void a(android.support.constraint.a.b, int, int);
    Code:
       0: aload_1
       1: aload_0
       2: iload_3
       3: aconst_null
       4: invokevirtual #294                // Method a:(ILjava/lang/String;)Landroid/support/constraint/a/h;
       7: iload_2
       8: invokevirtual #297                // Method android/support/constraint/a/b.c:(Landroid/support/constraint/a/h;I)Landroid/support/constraint/a/b;
      11: pop
      12: return

  void a(android.support.constraint.a.e$a);
    Code:
       0: getstatic     #93                 // Field g:Landroid/support/constraint/a/f;
       3: ifnull        60
       6: getstatic     #93                 // Field g:Landroid/support/constraint/a/f;
       9: astore_2
      10: aload_2
      11: aload_2
      12: getfield      #300                // Field android/support/constraint/a/f.t:J
      15: lconst_1
      16: ladd
      17: putfield      #300                // Field android/support/constraint/a/f.t:J
      20: getstatic     #93                 // Field g:Landroid/support/constraint/a/f;
      23: getstatic     #93                 // Field g:Landroid/support/constraint/a/f;
      26: getfield      #303                // Field android/support/constraint/a/f.u:J
      29: aload_0
      30: getfield      #57                 // Field d:I
      33: i2l
      34: invokestatic  #208                // Method java/lang/Math.max:(JJ)J
      37: putfield      #303                // Field android/support/constraint/a/f.u:J
      40: getstatic     #93                 // Field g:Landroid/support/constraint/a/f;
      43: getstatic     #93                 // Field g:Landroid/support/constraint/a/f;
      46: getfield      #306                // Field android/support/constraint/a/f.v:J
      49: aload_0
      50: getfield      #59                 // Field e:I
      53: i2l
      54: invokestatic  #208                // Method java/lang/Math.max:(JJ)J
      57: putfield      #306                // Field android/support/constraint/a/f.v:J
      60: aload_0
      61: aload_1
      62: checkcast     #71                 // class android/support/constraint/a/b
      65: invokespecial #269                // Method c:(Landroid/support/constraint/a/b;)V
      68: aload_0
      69: aload_1
      70: invokespecial #308                // Method b:(Landroid/support/constraint/a/e$a;)I
      73: pop
      74: aload_0
      75: aload_1
      76: iconst_0
      77: invokespecial #286                // Method a:(Landroid/support/constraint/a/e$a;Z)I
      80: pop
      81: aload_0
      82: invokespecial #310                // Method j:()V
      85: return

  public void a(android.support.constraint.a.h, int);
    Code:
       0: aload_1
       1: getfield      #136                // Field android/support/constraint/a/h.b:I
       4: istore_3
       5: aload_1
       6: getfield      #136                // Field android/support/constraint/a/h.b:I
       9: iconst_m1
      10: if_icmpeq     77
      13: aload_0
      14: getfield      #51                 // Field b:[Landroid/support/constraint/a/b;
      17: iload_3
      18: aaload
      19: astore        4
      21: aload         4
      23: getfield      #120                // Field android/support/constraint/a/b.e:Z
      26: ifeq          37
      29: aload         4
      31: iload_2
      32: i2f
      33: putfield      #134                // Field android/support/constraint/a/b.b:F
      36: return
      37: aload         4
      39: getfield      #126                // Field android/support/constraint/a/b.d:Landroid/support/constraint/a/a;
      42: getfield      #192                // Field android/support/constraint/a/a.a:I
      45: ifne          57
      48: aload         4
      50: iconst_1
      51: putfield      #120                // Field android/support/constraint/a/b.e:Z
      54: goto          29
      57: aload_0
      58: invokevirtual #148                // Method c:()Landroid/support/constraint/a/b;
      61: astore        4
      63: aload         4
      65: aload_1
      66: iload_2
      67: invokevirtual #313                // Method android/support/constraint/a/b.b:(Landroid/support/constraint/a/h;I)Landroid/support/constraint/a/b;
      70: pop
      71: aload         4
      73: astore_1
      74: goto          94
      77: aload_0
      78: invokevirtual #148                // Method c:()Landroid/support/constraint/a/b;
      81: astore        4
      83: aload         4
      85: aload_1
      86: iload_2
      87: invokevirtual #315                // Method android/support/constraint/a/b.a:(Landroid/support/constraint/a/h;I)Landroid/support/constraint/a/b;
      90: pop
      91: aload         4
      93: astore_1
      94: aload_0
      95: aload_1
      96: invokevirtual #261                // Method a:(Landroid/support/constraint/a/b;)V
      99: return

  public void a(android.support.constraint.a.h, android.support.constraint.a.h, int, float, android.support.constraint.a.h, android.support.constraint.a.h, int, int);
    Code:
       0: aload_0
       1: invokevirtual #148                // Method c:()Landroid/support/constraint/a/b;
       4: astore        9
       6: aload         9
       8: aload_1
       9: aload_2
      10: iload_3
      11: fload         4
      13: aload         5
      15: aload         6
      17: iload         7
      19: invokevirtual #319                // Method android/support/constraint/a/b.a:(Landroid/support/constraint/a/h;Landroid/support/constraint/a/h;IFLandroid/support/constraint/a/h;Landroid/support/constraint/a/h;I)Landroid/support/constraint/a/b;
      22: pop
      23: iload         8
      25: bipush        6
      27: if_icmpeq     39
      30: aload         9
      32: aload_0
      33: iload         8
      35: invokevirtual #188                // Method android/support/constraint/a/b.a:(Landroid/support/constraint/a/e;I)Landroid/support/constraint/a/b;
      38: pop
      39: aload_0
      40: aload         9
      42: invokevirtual #261                // Method a:(Landroid/support/constraint/a/b;)V
      45: return

  public void a(android.support.constraint.a.h, android.support.constraint.a.h, int, int);
    Code:
       0: aload_0
       1: invokevirtual #148                // Method c:()Landroid/support/constraint/a/b;
       4: astore        5
       6: aload_0
       7: invokevirtual #322                // Method d:()Landroid/support/constraint/a/h;
      10: astore        6
      12: aload         6
      14: iconst_0
      15: putfield      #224                // Field android/support/constraint/a/h.c:I
      18: aload         5
      20: aload_1
      21: aload_2
      22: aload         6
      24: iload_3
      25: invokevirtual #325                // Method android/support/constraint/a/b.a:(Landroid/support/constraint/a/h;Landroid/support/constraint/a/h;Landroid/support/constraint/a/h;I)Landroid/support/constraint/a/b;
      28: pop
      29: iload         4
      31: bipush        6
      33: if_icmpeq     59
      36: aload_0
      37: aload         5
      39: aload         5
      41: getfield      #126                // Field android/support/constraint/a/b.d:Landroid/support/constraint/a/a;
      44: aload         6
      46: invokevirtual #131                // Method android/support/constraint/a/a.b:(Landroid/support/constraint/a/h;)F
      49: ldc_w         #326                // float -1.0f
      52: fmul
      53: f2i
      54: iload         4
      56: invokevirtual #328                // Method a:(Landroid/support/constraint/a/b;II)V
      59: aload_0
      60: aload         5
      62: invokevirtual #261                // Method a:(Landroid/support/constraint/a/b;)V
      65: return

  public void a(android.support.constraint.a.h, android.support.constraint.a.h, android.support.constraint.a.h, android.support.constraint.a.h, float, int);
    Code:
       0: aload_0
       1: invokevirtual #148                // Method c:()Landroid/support/constraint/a/b;
       4: astore        7
       6: aload         7
       8: aload_1
       9: aload_2
      10: aload_3
      11: aload         4
      13: fload         5
      15: invokevirtual #331                // Method android/support/constraint/a/b.a:(Landroid/support/constraint/a/h;Landroid/support/constraint/a/h;Landroid/support/constraint/a/h;Landroid/support/constraint/a/h;F)Landroid/support/constraint/a/b;
      18: pop
      19: iload         6
      21: bipush        6
      23: if_icmpeq     35
      26: aload         7
      28: aload_0
      29: iload         6
      31: invokevirtual #188                // Method android/support/constraint/a/b.a:(Landroid/support/constraint/a/e;I)Landroid/support/constraint/a/b;
      34: pop
      35: aload_0
      36: aload         7
      38: invokevirtual #261                // Method a:(Landroid/support/constraint/a/b;)V
      41: return

  public void a(android.support.constraint.a.h, android.support.constraint.a.h, boolean);
    Code:
       0: aload_0
       1: invokevirtual #148                // Method c:()Landroid/support/constraint/a/b;
       4: astore        4
       6: aload_0
       7: invokevirtual #322                // Method d:()Landroid/support/constraint/a/h;
      10: astore        5
      12: aload         5
      14: iconst_0
      15: putfield      #224                // Field android/support/constraint/a/h.c:I
      18: aload         4
      20: aload_1
      21: aload_2
      22: aload         5
      24: iconst_0
      25: invokevirtual #325                // Method android/support/constraint/a/b.a:(Landroid/support/constraint/a/h;Landroid/support/constraint/a/h;Landroid/support/constraint/a/h;I)Landroid/support/constraint/a/b;
      28: pop
      29: iload_3
      30: ifeq          55
      33: aload_0
      34: aload         4
      36: aload         4
      38: getfield      #126                // Field android/support/constraint/a/b.d:Landroid/support/constraint/a/a;
      41: aload         5
      43: invokevirtual #131                // Method android/support/constraint/a/a.b:(Landroid/support/constraint/a/h;)F
      46: ldc_w         #326                // float -1.0f
      49: fmul
      50: f2i
      51: iconst_1
      52: invokevirtual #328                // Method a:(Landroid/support/constraint/a/b;II)V
      55: aload_0
      56: aload         4
      58: invokevirtual #261                // Method a:(Landroid/support/constraint/a/b;)V
      61: return

  public int b(java.lang.Object);
    Code:
       0: aload_1
       1: checkcast     #229                // class android/support/constraint/a/a/c
       4: invokevirtual #231                // Method android/support/constraint/a/a/c.b:()Landroid/support/constraint/a/h;
       7: astore_1
       8: aload_1
       9: ifnull        22
      12: aload_1
      13: getfield      #213                // Field android/support/constraint/a/h.d:F
      16: ldc_w         #334                // float 0.5f
      19: fadd
      20: f2i
      21: ireturn
      22: iconst_0
      23: ireturn

  public void b();
    Code:
       0: iconst_0
       1: istore_1
       2: iload_1
       3: aload_0
       4: getfield      #80                 // Field f:Landroid/support/constraint/a/c;
       7: getfield      #182                // Field android/support/constraint/a/c.c:[Landroid/support/constraint/a/h;
      10: arraylength
      11: if_icmpge     39
      14: aload_0
      15: getfield      #80                 // Field f:Landroid/support/constraint/a/c;
      18: getfield      #182                // Field android/support/constraint/a/c.c:[Landroid/support/constraint/a/h;
      21: iload_1
      22: aaload
      23: astore_2
      24: aload_2
      25: ifnull        32
      28: aload_2
      29: invokevirtual #170                // Method android/support/constraint/a/h.b:()V
      32: iload_1
      33: iconst_1
      34: iadd
      35: istore_1
      36: goto          2
      39: aload_0
      40: getfield      #80                 // Field f:Landroid/support/constraint/a/c;
      43: getfield      #158                // Field android/support/constraint/a/c.b:Landroid/support/constraint/a/g$a;
      46: aload_0
      47: getfield      #67                 // Field o:[Landroid/support/constraint/a/h;
      50: aload_0
      51: getfield      #69                 // Field p:I
      54: invokeinterface #337,  3          // InterfaceMethod android/support/constraint/a/g$a.a:([Ljava/lang/Object;I)V
      59: aload_0
      60: iconst_0
      61: putfield      #69                 // Field p:I
      64: aload_0
      65: getfield      #80                 // Field f:Landroid/support/constraint/a/c;
      68: getfield      #182                // Field android/support/constraint/a/c.c:[Landroid/support/constraint/a/h;
      71: aconst_null
      72: invokestatic  #341                // Method java/util/Arrays.fill:([Ljava/lang/Object;Ljava/lang/Object;)V
      75: aload_0
      76: getfield      #45                 // Field i:Ljava/util/HashMap;
      79: ifnull        89
      82: aload_0
      83: getfield      #45                 // Field i:Ljava/util/HashMap;
      86: invokevirtual #346                // Method java/util/HashMap.clear:()V
      89: aload_0
      90: iconst_0
      91: putfield      #43                 // Field a:I
      94: aload_0
      95: getfield      #87                 // Field j:Landroid/support/constraint/a/e$a;
      98: invokeinterface #348,  1          // InterfaceMethod android/support/constraint/a/e$a.f:()V
     103: aload_0
     104: iconst_1
     105: putfield      #57                 // Field d:I
     108: iconst_0
     109: istore_1
     110: iload_1
     111: aload_0
     112: getfield      #59                 // Field e:I
     115: if_icmpge     135
     118: aload_0
     119: getfield      #51                 // Field b:[Landroid/support/constraint/a/b;
     122: iload_1
     123: aaload
     124: iconst_0
     125: putfield      #349                // Field android/support/constraint/a/b.c:Z
     128: iload_1
     129: iconst_1
     130: iadd
     131: istore_1
     132: goto          110
     135: aload_0
     136: invokespecial #75                 // Method i:()V
     139: aload_0
     140: iconst_0
     141: putfield      #59                 // Field e:I
     144: return

  public void b(android.support.constraint.a.h, android.support.constraint.a.h, int, int);
    Code:
       0: aload_0
       1: invokevirtual #148                // Method c:()Landroid/support/constraint/a/b;
       4: astore        5
       6: aload_0
       7: invokevirtual #322                // Method d:()Landroid/support/constraint/a/h;
      10: astore        6
      12: aload         6
      14: iconst_0
      15: putfield      #224                // Field android/support/constraint/a/h.c:I
      18: aload         5
      20: aload_1
      21: aload_2
      22: aload         6
      24: iload_3
      25: invokevirtual #351                // Method android/support/constraint/a/b.b:(Landroid/support/constraint/a/h;Landroid/support/constraint/a/h;Landroid/support/constraint/a/h;I)Landroid/support/constraint/a/b;
      28: pop
      29: iload         4
      31: bipush        6
      33: if_icmpeq     59
      36: aload_0
      37: aload         5
      39: aload         5
      41: getfield      #126                // Field android/support/constraint/a/b.d:Landroid/support/constraint/a/a;
      44: aload         6
      46: invokevirtual #131                // Method android/support/constraint/a/a.b:(Landroid/support/constraint/a/h;)F
      49: ldc_w         #326                // float -1.0f
      52: fmul
      53: f2i
      54: iload         4
      56: invokevirtual #328                // Method a:(Landroid/support/constraint/a/b;II)V
      59: aload_0
      60: aload         5
      62: invokevirtual #261                // Method a:(Landroid/support/constraint/a/b;)V
      65: return

  public void b(android.support.constraint.a.h, android.support.constraint.a.h, boolean);
    Code:
       0: aload_0
       1: invokevirtual #148                // Method c:()Landroid/support/constraint/a/b;
       4: astore        4
       6: aload_0
       7: invokevirtual #322                // Method d:()Landroid/support/constraint/a/h;
      10: astore        5
      12: aload         5
      14: iconst_0
      15: putfield      #224                // Field android/support/constraint/a/h.c:I
      18: aload         4
      20: aload_1
      21: aload_2
      22: aload         5
      24: iconst_0
      25: invokevirtual #351                // Method android/support/constraint/a/b.b:(Landroid/support/constraint/a/h;Landroid/support/constraint/a/h;Landroid/support/constraint/a/h;I)Landroid/support/constraint/a/b;
      28: pop
      29: iload_3
      30: ifeq          55
      33: aload_0
      34: aload         4
      36: aload         4
      38: getfield      #126                // Field android/support/constraint/a/b.d:Landroid/support/constraint/a/a;
      41: aload         5
      43: invokevirtual #131                // Method android/support/constraint/a/a.b:(Landroid/support/constraint/a/h;)F
      46: ldc_w         #326                // float -1.0f
      49: fmul
      50: f2i
      51: iconst_1
      52: invokevirtual #328                // Method a:(Landroid/support/constraint/a/b;II)V
      55: aload_0
      56: aload         4
      58: invokevirtual #261                // Method a:(Landroid/support/constraint/a/b;)V
      61: return

  public android.support.constraint.a.b c();
    Code:
       0: aload_0
       1: getfield      #80                 // Field f:Landroid/support/constraint/a/c;
       4: getfield      #194                // Field android/support/constraint/a/c.a:Landroid/support/constraint/a/g$a;
       7: invokeinterface #163,  1          // InterfaceMethod android/support/constraint/a/g$a.a:()Ljava/lang/Object;
      12: checkcast     #71                 // class android/support/constraint/a/b
      15: astore_1
      16: aload_1
      17: ifnonnull     35
      20: new           #71                 // class android/support/constraint/a/b
      23: dup
      24: aload_0
      25: getfield      #80                 // Field f:Landroid/support/constraint/a/c;
      28: invokespecial #88                 // Method android/support/constraint/a/b."<init>":(Landroid/support/constraint/a/c;)V
      31: astore_1
      32: goto          39
      35: aload_1
      36: invokevirtual #353                // Method android/support/constraint/a/b.c:()V
      39: invokestatic  #355                // Method android/support/constraint/a/h.a:()V
      42: aload_1
      43: areturn

  public android.support.constraint.a.b c(android.support.constraint.a.h, android.support.constraint.a.h, int, int);
    Code:
       0: aload_0
       1: invokevirtual #148                // Method c:()Landroid/support/constraint/a/b;
       4: astore        5
       6: aload         5
       8: aload_1
       9: aload_2
      10: iload_3
      11: invokevirtual #359                // Method android/support/constraint/a/b.a:(Landroid/support/constraint/a/h;Landroid/support/constraint/a/h;I)Landroid/support/constraint/a/b;
      14: pop
      15: iload         4
      17: bipush        6
      19: if_icmpeq     31
      22: aload         5
      24: aload_0
      25: iload         4
      27: invokevirtual #188                // Method android/support/constraint/a/b.a:(Landroid/support/constraint/a/e;I)Landroid/support/constraint/a/b;
      30: pop
      31: aload_0
      32: aload         5
      34: invokevirtual #261                // Method a:(Landroid/support/constraint/a/b;)V
      37: aload         5
      39: areturn

  public android.support.constraint.a.h d();
    Code:
       0: getstatic     #93                 // Field g:Landroid/support/constraint/a/f;
       3: ifnull        20
       6: getstatic     #93                 // Field g:Landroid/support/constraint/a/f;
       9: astore_1
      10: aload_1
      11: aload_1
      12: getfield      #361                // Field android/support/constraint/a/f.n:J
      15: lconst_1
      16: ladd
      17: putfield      #361                // Field android/support/constraint/a/f.n:J
      20: aload_0
      21: getfield      #57                 // Field d:I
      24: iconst_1
      25: iadd
      26: aload_0
      27: getfield      #49                 // Field l:I
      30: if_icmplt     37
      33: aload_0
      34: invokespecial #218                // Method h:()V
      37: aload_0
      38: getstatic     #363                // Field android/support/constraint/a/h$a.c:Landroid/support/constraint/a/h$a;
      41: aconst_null
      42: invokespecial #222                // Method a:(Landroid/support/constraint/a/h$a;Ljava/lang/String;)Landroid/support/constraint/a/h;
      45: astore_1
      46: aload_0
      47: aload_0
      48: getfield      #43                 // Field a:I
      51: iconst_1
      52: iadd
      53: putfield      #43                 // Field a:I
      56: aload_0
      57: aload_0
      58: getfield      #57                 // Field d:I
      61: iconst_1
      62: iadd
      63: putfield      #57                 // Field d:I
      66: aload_1
      67: aload_0
      68: getfield      #43                 // Field a:I
      71: putfield      #104                // Field android/support/constraint/a/h.a:I
      74: aload_0
      75: getfield      #80                 // Field f:Landroid/support/constraint/a/c;
      78: getfield      #182                // Field android/support/constraint/a/c.c:[Landroid/support/constraint/a/h;
      81: aload_0
      82: getfield      #43                 // Field a:I
      85: aload_1
      86: aastore
      87: aload_1
      88: areturn

  public android.support.constraint.a.h e();
    Code:
       0: getstatic     #93                 // Field g:Landroid/support/constraint/a/f;
       3: ifnull        20
       6: getstatic     #93                 // Field g:Landroid/support/constraint/a/f;
       9: astore_1
      10: aload_1
      11: aload_1
      12: getfield      #365                // Field android/support/constraint/a/f.o:J
      15: lconst_1
      16: ladd
      17: putfield      #365                // Field android/support/constraint/a/f.o:J
      20: aload_0
      21: getfield      #57                 // Field d:I
      24: iconst_1
      25: iadd
      26: aload_0
      27: getfield      #49                 // Field l:I
      30: if_icmplt     37
      33: aload_0
      34: invokespecial #218                // Method h:()V
      37: aload_0
      38: getstatic     #363                // Field android/support/constraint/a/h$a.c:Landroid/support/constraint/a/h$a;
      41: aconst_null
      42: invokespecial #222                // Method a:(Landroid/support/constraint/a/h$a;Ljava/lang/String;)Landroid/support/constraint/a/h;
      45: astore_1
      46: aload_0
      47: aload_0
      48: getfield      #43                 // Field a:I
      51: iconst_1
      52: iadd
      53: putfield      #43                 // Field a:I
      56: aload_0
      57: aload_0
      58: getfield      #57                 // Field d:I
      61: iconst_1
      62: iadd
      63: putfield      #57                 // Field d:I
      66: aload_1
      67: aload_0
      68: getfield      #43                 // Field a:I
      71: putfield      #104                // Field android/support/constraint/a/h.a:I
      74: aload_0
      75: getfield      #80                 // Field f:Landroid/support/constraint/a/c;
      78: getfield      #182                // Field android/support/constraint/a/c.c:[Landroid/support/constraint/a/h;
      81: aload_0
      82: getfield      #43                 // Field a:I
      85: aload_1
      86: aastore
      87: aload_1
      88: areturn

  public void f();
    Code:
       0: getstatic     #93                 // Field g:Landroid/support/constraint/a/f;
       3: ifnull        20
       6: getstatic     #93                 // Field g:Landroid/support/constraint/a/f;
       9: astore_3
      10: aload_3
      11: aload_3
      12: getfield      #367                // Field android/support/constraint/a/f.e:J
      15: lconst_1
      16: ladd
      17: putfield      #367                // Field android/support/constraint/a/f.e:J
      20: aload_0
      21: getfield      #53                 // Field c:Z
      24: ifeq          117
      27: getstatic     #93                 // Field g:Landroid/support/constraint/a/f;
      30: ifnull        47
      33: getstatic     #93                 // Field g:Landroid/support/constraint/a/f;
      36: astore_3
      37: aload_3
      38: aload_3
      39: getfield      #369                // Field android/support/constraint/a/f.r:J
      42: lconst_1
      43: ladd
      44: putfield      #369                // Field android/support/constraint/a/f.r:J
      47: iconst_0
      48: istore_2
      49: iconst_0
      50: istore_1
      51: iload_1
      52: aload_0
      53: getfield      #59                 // Field e:I
      56: if_icmpge     83
      59: aload_0
      60: getfield      #51                 // Field b:[Landroid/support/constraint/a/b;
      63: iload_1
      64: aaload
      65: getfield      #120                // Field android/support/constraint/a/b.e:Z
      68: ifne          76
      71: iload_2
      72: istore_1
      73: goto          85
      76: iload_1
      77: iconst_1
      78: iadd
      79: istore_1
      80: goto          51
      83: iconst_1
      84: istore_1
      85: iload_1
      86: ifne          92
      89: goto          117
      92: getstatic     #93                 // Field g:Landroid/support/constraint/a/f;
      95: ifnull        112
      98: getstatic     #93                 // Field g:Landroid/support/constraint/a/f;
     101: astore_3
     102: aload_3
     103: aload_3
     104: getfield      #371                // Field android/support/constraint/a/f.q:J
     107: lconst_1
     108: ladd
     109: putfield      #371                // Field android/support/constraint/a/f.q:J
     112: aload_0
     113: invokespecial #310                // Method j:()V
     116: return
     117: aload_0
     118: aload_0
     119: getfield      #87                 // Field j:Landroid/support/constraint/a/e$a;
     122: invokevirtual #372                // Method a:(Landroid/support/constraint/a/e$a;)V
     125: return

  public android.support.constraint.a.c g();
    Code:
       0: aload_0
       1: getfield      #80                 // Field f:Landroid/support/constraint/a/c;
       4: areturn
}
