public class android.support.constraint.a.f {
  public long A;

  public long B;

  public java.util.ArrayList<java.lang.String> C;

  public long D;

  public long a;

  public long b;

  public long c;

  public long d;

  public long e;

  public long f;

  public long g;

  public long h;

  public long i;

  public long j;

  public long k;

  public long l;

  public long m;

  public long n;

  public long o;

  public long p;

  public long q;

  public long r;

  public long s;

  public long t;

  public long u;

  public long v;

  public long w;

  public long x;

  public long y;

  public long z;

  public java.lang.String toString();
    Code:
       0: new           #41                 // class java/lang/StringBuilder
       3: dup
       4: invokespecial #45                 // Method java/lang/StringBuilder."<init>":()V
       7: astore_1
       8: aload_1
       9: ldc           #47                 // String \n*** Metrics ***\nmeasures:
      11: invokevirtual #51                 // Method java/lang/StringBuilder.append:(Ljava/lang/String;)Ljava/lang/StringBuilder;
      14: pop
      15: aload_1
      16: aload_0
      17: getfield      #53                 // Field a:J
      20: invokevirtual #56                 // Method java/lang/StringBuilder.append:(J)Ljava/lang/StringBuilder;
      23: pop
      24: aload_1
      25: ldc           #58                 // String \nadditionalMeasures:
      27: invokevirtual #51                 // Method java/lang/StringBuilder.append:(Ljava/lang/String;)Ljava/lang/StringBuilder;
      30: pop
      31: aload_1
      32: aload_0
      33: getfield      #60                 // Field b:J
      36: invokevirtual #56                 // Method java/lang/StringBuilder.append:(J)Ljava/lang/StringBuilder;
      39: pop
      40: aload_1
      41: ldc           #62                 // String \nresolutions passes:
      43: invokevirtual #51                 // Method java/lang/StringBuilder.append:(Ljava/lang/String;)Ljava/lang/StringBuilder;
      46: pop
      47: aload_1
      48: aload_0
      49: getfield      #64                 // Field c:J
      52: invokevirtual #56                 // Method java/lang/StringBuilder.append:(J)Ljava/lang/StringBuilder;
      55: pop
      56: aload_1
      57: ldc           #66                 // String \ntable increases:
      59: invokevirtual #51                 // Method java/lang/StringBuilder.append:(Ljava/lang/String;)Ljava/lang/StringBuilder;
      62: pop
      63: aload_1
      64: aload_0
      65: getfield      #68                 // Field d:J
      68: invokevirtual #56                 // Method java/lang/StringBuilder.append:(J)Ljava/lang/StringBuilder;
      71: pop
      72: aload_1
      73: ldc           #70                 // String \nmaxTableSize:
      75: invokevirtual #51                 // Method java/lang/StringBuilder.append:(Ljava/lang/String;)Ljava/lang/StringBuilder;
      78: pop
      79: aload_1
      80: aload_0
      81: getfield      #72                 // Field p:J
      84: invokevirtual #56                 // Method java/lang/StringBuilder.append:(J)Ljava/lang/StringBuilder;
      87: pop
      88: aload_1
      89: ldc           #74                 // String \nmaxVariables:
      91: invokevirtual #51                 // Method java/lang/StringBuilder.append:(Ljava/lang/String;)Ljava/lang/StringBuilder;
      94: pop
      95: aload_1
      96: aload_0
      97: getfield      #76                 // Field u:J
     100: invokevirtual #56                 // Method java/lang/StringBuilder.append:(J)Ljava/lang/StringBuilder;
     103: pop
     104: aload_1
     105: ldc           #78                 // String \nmaxRows:
     107: invokevirtual #51                 // Method java/lang/StringBuilder.append:(Ljava/lang/String;)Ljava/lang/StringBuilder;
     110: pop
     111: aload_1
     112: aload_0
     113: getfield      #80                 // Field v:J
     116: invokevirtual #56                 // Method java/lang/StringBuilder.append:(J)Ljava/lang/StringBuilder;
     119: pop
     120: aload_1
     121: ldc           #82                 // String \n\nminimize:
     123: invokevirtual #51                 // Method java/lang/StringBuilder.append:(Ljava/lang/String;)Ljava/lang/StringBuilder;
     126: pop
     127: aload_1
     128: aload_0
     129: getfield      #84                 // Field e:J
     132: invokevirtual #56                 // Method java/lang/StringBuilder.append:(J)Ljava/lang/StringBuilder;
     135: pop
     136: aload_1
     137: ldc           #86                 // String \nminimizeGoal:
     139: invokevirtual #51                 // Method java/lang/StringBuilder.append:(Ljava/lang/String;)Ljava/lang/StringBuilder;
     142: pop
     143: aload_1
     144: aload_0
     145: getfield      #88                 // Field t:J
     148: invokevirtual #56                 // Method java/lang/StringBuilder.append:(J)Ljava/lang/StringBuilder;
     151: pop
     152: aload_1
     153: ldc           #90                 // String \nconstraints:
     155: invokevirtual #51                 // Method java/lang/StringBuilder.append:(Ljava/lang/String;)Ljava/lang/StringBuilder;
     158: pop
     159: aload_1
     160: aload_0
     161: getfield      #92                 // Field f:J
     164: invokevirtual #56                 // Method java/lang/StringBuilder.append:(J)Ljava/lang/StringBuilder;
     167: pop
     168: aload_1
     169: ldc           #94                 // String \nsimpleconstraints:
     171: invokevirtual #51                 // Method java/lang/StringBuilder.append:(Ljava/lang/String;)Ljava/lang/StringBuilder;
     174: pop
     175: aload_1
     176: aload_0
     177: getfield      #96                 // Field g:J
     180: invokevirtual #56                 // Method java/lang/StringBuilder.append:(J)Ljava/lang/StringBuilder;
     183: pop
     184: aload_1
     185: ldc           #98                 // String \noptimize:
     187: invokevirtual #51                 // Method java/lang/StringBuilder.append:(Ljava/lang/String;)Ljava/lang/StringBuilder;
     190: pop
     191: aload_1
     192: aload_0
     193: getfield      #100                // Field h:J
     196: invokevirtual #56                 // Method java/lang/StringBuilder.append:(J)Ljava/lang/StringBuilder;
     199: pop
     200: aload_1
     201: ldc           #102                // String \niterations:
     203: invokevirtual #51                 // Method java/lang/StringBuilder.append:(Ljava/lang/String;)Ljava/lang/StringBuilder;
     206: pop
     207: aload_1
     208: aload_0
     209: getfield      #104                // Field i:J
     212: invokevirtual #56                 // Method java/lang/StringBuilder.append:(J)Ljava/lang/StringBuilder;
     215: pop
     216: aload_1
     217: ldc           #106                // String \npivots:
     219: invokevirtual #51                 // Method java/lang/StringBuilder.append:(Ljava/lang/String;)Ljava/lang/StringBuilder;
     222: pop
     223: aload_1
     224: aload_0
     225: getfield      #108                // Field j:J
     228: invokevirtual #56                 // Method java/lang/StringBuilder.append:(J)Ljava/lang/StringBuilder;
     231: pop
     232: aload_1
     233: ldc           #110                // String \nbfs:
     235: invokevirtual #51                 // Method java/lang/StringBuilder.append:(Ljava/lang/String;)Ljava/lang/StringBuilder;
     238: pop
     239: aload_1
     240: aload_0
     241: getfield      #112                // Field k:J
     244: invokevirtual #56                 // Method java/lang/StringBuilder.append:(J)Ljava/lang/StringBuilder;
     247: pop
     248: aload_1
     249: ldc           #114                // String \nvariables:
     251: invokevirtual #51                 // Method java/lang/StringBuilder.append:(Ljava/lang/String;)Ljava/lang/StringBuilder;
     254: pop
     255: aload_1
     256: aload_0
     257: getfield      #116                // Field l:J
     260: invokevirtual #56                 // Method java/lang/StringBuilder.append:(J)Ljava/lang/StringBuilder;
     263: pop
     264: aload_1
     265: ldc           #118                // String \nerrors:
     267: invokevirtual #51                 // Method java/lang/StringBuilder.append:(Ljava/lang/String;)Ljava/lang/StringBuilder;
     270: pop
     271: aload_1
     272: aload_0
     273: getfield      #120                // Field m:J
     276: invokevirtual #56                 // Method java/lang/StringBuilder.append:(J)Ljava/lang/StringBuilder;
     279: pop
     280: aload_1
     281: ldc           #122                // String \nslackvariables:
     283: invokevirtual #51                 // Method java/lang/StringBuilder.append:(Ljava/lang/String;)Ljava/lang/StringBuilder;
     286: pop
     287: aload_1
     288: aload_0
     289: getfield      #124                // Field n:J
     292: invokevirtual #56                 // Method java/lang/StringBuilder.append:(J)Ljava/lang/StringBuilder;
     295: pop
     296: aload_1
     297: ldc           #126                // String \nextravariables:
     299: invokevirtual #51                 // Method java/lang/StringBuilder.append:(Ljava/lang/String;)Ljava/lang/StringBuilder;
     302: pop
     303: aload_1
     304: aload_0
     305: getfield      #128                // Field o:J
     308: invokevirtual #56                 // Method java/lang/StringBuilder.append:(J)Ljava/lang/StringBuilder;
     311: pop
     312: aload_1
     313: ldc           #130                // String \nfullySolved:
     315: invokevirtual #51                 // Method java/lang/StringBuilder.append:(Ljava/lang/String;)Ljava/lang/StringBuilder;
     318: pop
     319: aload_1
     320: aload_0
     321: getfield      #132                // Field q:J
     324: invokevirtual #56                 // Method java/lang/StringBuilder.append:(J)Ljava/lang/StringBuilder;
     327: pop
     328: aload_1
     329: ldc           #134                // String \ngraphOptimizer:
     331: invokevirtual #51                 // Method java/lang/StringBuilder.append:(Ljava/lang/String;)Ljava/lang/StringBuilder;
     334: pop
     335: aload_1
     336: aload_0
     337: getfield      #136                // Field r:J
     340: invokevirtual #56                 // Method java/lang/StringBuilder.append:(J)Ljava/lang/StringBuilder;
     343: pop
     344: aload_1
     345: ldc           #138                // String \nresolvedWidgets:
     347: invokevirtual #51                 // Method java/lang/StringBuilder.append:(Ljava/lang/String;)Ljava/lang/StringBuilder;
     350: pop
     351: aload_1
     352: aload_0
     353: getfield      #140                // Field s:J
     356: invokevirtual #56                 // Method java/lang/StringBuilder.append:(J)Ljava/lang/StringBuilder;
     359: pop
     360: aload_1
     361: ldc           #142                // String \noldresolvedWidgets:
     363: invokevirtual #51                 // Method java/lang/StringBuilder.append:(Ljava/lang/String;)Ljava/lang/StringBuilder;
     366: pop
     367: aload_1
     368: aload_0
     369: getfield      #144                // Field A:J
     372: invokevirtual #56                 // Method java/lang/StringBuilder.append:(J)Ljava/lang/StringBuilder;
     375: pop
     376: aload_1
     377: ldc           #146                // String \nnonresolvedWidgets:
     379: invokevirtual #51                 // Method java/lang/StringBuilder.append:(Ljava/lang/String;)Ljava/lang/StringBuilder;
     382: pop
     383: aload_1
     384: aload_0
     385: getfield      #148                // Field B:J
     388: invokevirtual #56                 // Method java/lang/StringBuilder.append:(J)Ljava/lang/StringBuilder;
     391: pop
     392: aload_1
     393: ldc           #150                // String \ncenterConnectionResolved:
     395: invokevirtual #51                 // Method java/lang/StringBuilder.append:(Ljava/lang/String;)Ljava/lang/StringBuilder;
     398: pop
     399: aload_1
     400: aload_0
     401: getfield      #152                // Field w:J
     404: invokevirtual #56                 // Method java/lang/StringBuilder.append:(J)Ljava/lang/StringBuilder;
     407: pop
     408: aload_1
     409: ldc           #154                // String \nmatchConnectionResolved:
     411: invokevirtual #51                 // Method java/lang/StringBuilder.append:(Ljava/lang/String;)Ljava/lang/StringBuilder;
     414: pop
     415: aload_1
     416: aload_0
     417: getfield      #156                // Field x:J
     420: invokevirtual #56                 // Method java/lang/StringBuilder.append:(J)Ljava/lang/StringBuilder;
     423: pop
     424: aload_1
     425: ldc           #158                // String \nchainConnectionResolved:
     427: invokevirtual #51                 // Method java/lang/StringBuilder.append:(Ljava/lang/String;)Ljava/lang/StringBuilder;
     430: pop
     431: aload_1
     432: aload_0
     433: getfield      #160                // Field y:J
     436: invokevirtual #56                 // Method java/lang/StringBuilder.append:(J)Ljava/lang/StringBuilder;
     439: pop
     440: aload_1
     441: ldc           #162                // String \nbarrierConnectionResolved:
     443: invokevirtual #51                 // Method java/lang/StringBuilder.append:(Ljava/lang/String;)Ljava/lang/StringBuilder;
     446: pop
     447: aload_1
     448: aload_0
     449: getfield      #164                // Field z:J
     452: invokevirtual #56                 // Method java/lang/StringBuilder.append:(J)Ljava/lang/StringBuilder;
     455: pop
     456: aload_1
     457: ldc           #166                // String \nproblematicsLayouts:
     459: invokevirtual #51                 // Method java/lang/StringBuilder.append:(Ljava/lang/String;)Ljava/lang/StringBuilder;
     462: pop
     463: aload_1
     464: aload_0
     465: getfield      #168                // Field C:Ljava/util/ArrayList;
     468: invokevirtual #171                // Method java/lang/StringBuilder.append:(Ljava/lang/Object;)Ljava/lang/StringBuilder;
     471: pop
     472: aload_1
     473: ldc           #173                // String \n
     475: invokevirtual #51                 // Method java/lang/StringBuilder.append:(Ljava/lang/String;)Ljava/lang/StringBuilder;
     478: pop
     479: aload_1
     480: invokevirtual #175                // Method java/lang/StringBuilder.toString:()Ljava/lang/String;
     483: areturn
}
