class ryey.easer.plugins.event.notification.NotificationEventListenerService$1 extends android.content.BroadcastReceiver {
  final ryey.easer.plugins.event.notification.NotificationEventListenerService a;

  ryey.easer.plugins.event.notification.NotificationEventListenerService$1(ryey.easer.plugins.event.notification.NotificationEventListenerService);
    Code:
       0: aload_0
       1: aload_1
       2: putfield      #12                 // Field a:Lryey/easer/plugins/event/notification/NotificationEventListenerService;
       5: aload_0
       6: invokespecial #15                 // Method android/content/BroadcastReceiver."<init>":()V
       9: return

  public void onReceive(android.content.Context, android.content.Intent);
    Code:
       0: aload_2
       1: invokevirtual #24                 // Method android/content/Intent.getAction:()Ljava/lang/String;
       4: astore_1
       5: aload_1
       6: ifnonnull     10
       9: return
      10: aload_1
      11: ldc           #26                 // String ryey.easer.plugins.event.notification.action.LISTEN
      13: invokevirtual #32                 // Method java/lang/String.equals:(Ljava/lang/Object;)Z
      16: ifne          29
      19: aload_1
      20: ldc           #34                 // String ryey.easer.plugins.event.notification.action.CANCEL
      22: invokevirtual #32                 // Method java/lang/String.equals:(Ljava/lang/Object;)Z
      25: ifne          29
      28: return
      29: ldc           #36                 // String broadcast received
      31: invokestatic  #41                 // Method com/b/a/i.a:(Ljava/lang/Object;)V
      34: aload_2
      35: ldc           #43                 // String ryey.easer.plugins.event.notification.extra.DATA
      37: invokevirtual #47                 // Method android/content/Intent.getParcelableExtra:(Ljava/lang/String;)Landroid/os/Parcelable;
      40: checkcast     #49                 // class ryey/easer/plugins/event/notification/a
      43: astore_3
      44: aload_2
      45: ldc           #51                 // String ryey.easer.plugins.event.notification.extra.URI
      47: invokevirtual #47                 // Method android/content/Intent.getParcelableExtra:(Ljava/lang/String;)Landroid/os/Parcelable;
      50: checkcast     #53                 // class android/net/Uri
      53: astore_2
      54: aload_1
      55: ldc           #26                 // String ryey.easer.plugins.event.notification.action.LISTEN
      57: invokevirtual #32                 // Method java/lang/String.equals:(Ljava/lang/Object;)Z
      60: ifeq          73
      63: aload_0
      64: getfield      #12                 // Field a:Lryey/easer/plugins/event/notification/NotificationEventListenerService;
      67: aload_3
      68: aload_2
      69: invokestatic  #56                 // Method ryey/easer/plugins/event/notification/NotificationEventListenerService.a:(Lryey/easer/plugins/event/notification/NotificationEventListenerService;Lryey/easer/plugins/event/notification/a;Landroid/net/Uri;)V
      72: return
      73: aload_1
      74: ldc           #34                 // String ryey.easer.plugins.event.notification.action.CANCEL
      76: invokevirtual #32                 // Method java/lang/String.equals:(Ljava/lang/Object;)Z
      79: ifeq          91
      82: aload_0
      83: getfield      #12                 // Field a:Lryey/easer/plugins/event/notification/NotificationEventListenerService;
      86: aload_3
      87: aload_2
      88: invokestatic  #59                 // Method ryey/easer/plugins/event/notification/NotificationEventListenerService.b:(Lryey/easer/plugins/event/notification/NotificationEventListenerService;Lryey/easer/plugins/event/notification/a;Landroid/net/Uri;)V
      91: return
}
