class android.support.v7.app.AlertController {
  final android.support.v7.app.m a;

  android.widget.ListView b;

  android.widget.Button c;

  android.os.Message d;

  android.widget.Button e;

  android.os.Message f;

  android.widget.Button g;

  android.os.Message h;

  android.support.v4.widget.NestedScrollView i;

  android.widget.ListAdapter j;

  int k;

  int l;

  int m;

  int n;

  int o;

  android.os.Handler p;

  public android.support.v7.app.AlertController(android.content.Context, android.support.v7.app.m, android.view.Window);
    Code:
       0: aload_0
       1: invokespecial #99                 // Method java/lang/Object."<init>":()V
       4: aload_0
       5: iconst_0
       6: putfield      #101                // Field B:Z
       9: aload_0
      10: iconst_0
      11: putfield      #103                // Field I:I
      14: aload_0
      15: iconst_m1
      16: putfield      #105                // Field k:I
      19: aload_0
      20: iconst_0
      21: putfield      #107                // Field R:I
      24: aload_0
      25: new           #6                  // class android/support/v7/app/AlertController$1
      28: dup
      29: aload_0
      30: invokespecial #110                // Method android/support/v7/app/AlertController$1."<init>":(Landroid/support/v7/app/AlertController;)V
      33: putfield      #112                // Field S:Landroid/view/View$OnClickListener;
      36: aload_0
      37: aload_1
      38: putfield      #114                // Field q:Landroid/content/Context;
      41: aload_0
      42: aload_2
      43: putfield      #116                // Field a:Landroid/support/v7/app/m;
      46: aload_0
      47: aload_3
      48: putfield      #118                // Field r:Landroid/view/Window;
      51: aload_0
      52: new           #32                 // class android/support/v7/app/AlertController$b
      55: dup
      56: aload_2
      57: invokespecial #121                // Method android/support/v7/app/AlertController$b."<init>":(Landroid/content/DialogInterface;)V
      60: putfield      #123                // Field p:Landroid/os/Handler;
      63: aload_1
      64: aconst_null
      65: getstatic     #129                // Field android/support/v7/a/a$j.AlertDialog:[I
      68: getstatic     #134                // Field android/support/v7/a/a$a.alertDialogStyle:I
      71: iconst_0
      72: invokevirtual #140                // Method android/content/Context.obtainStyledAttributes:(Landroid/util/AttributeSet;[III)Landroid/content/res/TypedArray;
      75: astore_1
      76: aload_0
      77: aload_1
      78: getstatic     #143                // Field android/support/v7/a/a$j.AlertDialog_android_layout:I
      81: iconst_0
      82: invokevirtual #149                // Method android/content/res/TypedArray.getResourceId:(II)I
      85: putfield      #151                // Field O:I
      88: aload_0
      89: aload_1
      90: getstatic     #154                // Field android/support/v7/a/a$j.AlertDialog_buttonPanelSideLayout:I
      93: iconst_0
      94: invokevirtual #149                // Method android/content/res/TypedArray.getResourceId:(II)I
      97: putfield      #156                // Field P:I
     100: aload_0
     101: aload_1
     102: getstatic     #159                // Field android/support/v7/a/a$j.AlertDialog_listLayout:I
     105: iconst_0
     106: invokevirtual #149                // Method android/content/res/TypedArray.getResourceId:(II)I
     109: putfield      #161                // Field l:I
     112: aload_0
     113: aload_1
     114: getstatic     #164                // Field android/support/v7/a/a$j.AlertDialog_multiChoiceItemLayout:I
     117: iconst_0
     118: invokevirtual #149                // Method android/content/res/TypedArray.getResourceId:(II)I
     121: putfield      #166                // Field m:I
     124: aload_0
     125: aload_1
     126: getstatic     #169                // Field android/support/v7/a/a$j.AlertDialog_singleChoiceItemLayout:I
     129: iconst_0
     130: invokevirtual #149                // Method android/content/res/TypedArray.getResourceId:(II)I
     133: putfield      #171                // Field n:I
     136: aload_0
     137: aload_1
     138: getstatic     #174                // Field android/support/v7/a/a$j.AlertDialog_listItemLayout:I
     141: iconst_0
     142: invokevirtual #149                // Method android/content/res/TypedArray.getResourceId:(II)I
     145: putfield      #176                // Field o:I
     148: aload_0
     149: aload_1
     150: getstatic     #179                // Field android/support/v7/a/a$j.AlertDialog_showTitle:I
     153: iconst_1
     154: invokevirtual #183                // Method android/content/res/TypedArray.getBoolean:(IZ)Z
     157: putfield      #185                // Field Q:Z
     160: aload_0
     161: aload_1
     162: getstatic     #188                // Field android/support/v7/a/a$j.AlertDialog_buttonIconDimen:I
     165: iconst_0
     166: invokevirtual #191                // Method android/content/res/TypedArray.getDimensionPixelSize:(II)I
     169: putfield      #193                // Field s:I
     172: aload_1
     173: invokevirtual #196                // Method android/content/res/TypedArray.recycle:()V
     176: aload_2
     177: iconst_1
     178: invokevirtual #201                // Method android/support/v7/app/m.a:(I)Z
     181: pop
     182: return

  static void a(android.view.View, android.view.View, android.view.View);
    Code:
       0: iconst_4
       1: istore        4
       3: aload_1
       4: ifnull        27
       7: aload_0
       8: iconst_m1
       9: invokevirtual #225                // Method android/view/View.canScrollVertically:(I)Z
      12: ifeq          20
      15: iconst_0
      16: istore_3
      17: goto          22
      20: iconst_4
      21: istore_3
      22: aload_1
      23: iload_3
      24: invokevirtual #229                // Method android/view/View.setVisibility:(I)V
      27: aload_2
      28: ifnull        49
      31: iload         4
      33: istore_3
      34: aload_0
      35: iconst_1
      36: invokevirtual #225                // Method android/view/View.canScrollVertically:(I)Z
      39: ifeq          44
      42: iconst_0
      43: istore_3
      44: aload_2
      45: iload_3
      46: invokevirtual #229                // Method android/view/View.setVisibility:(I)V
      49: return

  static boolean a(android.view.View);
    Code:
       0: aload_0
       1: invokevirtual #380                // Method android/view/View.onCheckIsTextEditor:()Z
       4: ifeq          9
       7: iconst_1
       8: ireturn
       9: aload_0
      10: instanceof    #211                // class android/view/ViewGroup
      13: ifne          18
      16: iconst_0
      17: ireturn
      18: aload_0
      19: checkcast     #211                // class android/view/ViewGroup
      22: astore_0
      23: aload_0
      24: invokevirtual #384                // Method android/view/ViewGroup.getChildCount:()I
      27: istore_1
      28: iload_1
      29: ifle          51
      32: iload_1
      33: iconst_1
      34: isub
      35: istore_2
      36: iload_2
      37: istore_1
      38: aload_0
      39: iload_2
      40: invokevirtual #387                // Method android/view/ViewGroup.getChildAt:(I)Landroid/view/View;
      43: invokestatic  #246                // Method a:(Landroid/view/View;)Z
      46: ifeq          28
      49: iconst_1
      50: ireturn
      51: iconst_0
      52: ireturn

  public void a();
    Code:
       0: aload_0
       1: invokespecial #567                // Method b:()I
       4: istore_1
       5: aload_0
       6: getfield      #116                // Field a:Landroid/support/v7/app/m;
       9: iload_1
      10: invokevirtual #570                // Method android/support/v7/app/m.setContentView:(I)V
      13: aload_0
      14: invokespecial #572                // Method c:()V
      17: return

  public void a(int);
    Code:
       0: aload_0
       1: aconst_null
       2: putfield      #232                // Field v:Landroid/view/View;
       5: aload_0
       6: iload_1
       7: putfield      #234                // Field w:I
      10: aload_0
      11: iconst_0
      12: putfield      #101                // Field B:Z
      15: return

  public void a(int, java.lang.CharSequence, android.content.DialogInterface$OnClickListener, android.os.Message, android.graphics.drawable.Drawable);
    Code:
       0: aload         4
       2: astore        6
       4: aload         4
       6: ifnonnull     28
       9: aload         4
      11: astore        6
      13: aload_3
      14: ifnull        28
      17: aload_0
      18: getfield      #123                // Field p:Landroid/os/Handler;
      21: iload_1
      22: aload_3
      23: invokevirtual #579                // Method android/os/Handler.obtainMessage:(ILjava/lang/Object;)Landroid/os/Message;
      26: astore        6
      28: iload_1
      29: tableswitch   { // -3 to -1
                    -3: 103
                    -2: 85
                    -1: 67
               default: 56
          }
      56: new           #581                // class java/lang/IllegalArgumentException
      59: dup
      60: ldc_w         #583                // String Button does not exist
      63: invokespecial #586                // Method java/lang/IllegalArgumentException."<init>":(Ljava/lang/String;)V
      66: athrow
      67: aload_0
      68: aload_2
      69: putfield      #534                // Field C:Ljava/lang/CharSequence;
      72: aload_0
      73: aload         6
      75: putfield      #588                // Field d:Landroid/os/Message;
      78: aload_0
      79: aload         5
      81: putfield      #536                // Field D:Landroid/graphics/drawable/Drawable;
      84: return
      85: aload_0
      86: aload_2
      87: putfield      #552                // Field E:Ljava/lang/CharSequence;
      90: aload_0
      91: aload         6
      93: putfield      #590                // Field f:Landroid/os/Message;
      96: aload_0
      97: aload         5
      99: putfield      #554                // Field F:Landroid/graphics/drawable/Drawable;
     102: return
     103: aload_0
     104: aload_2
     105: putfield      #559                // Field G:Ljava/lang/CharSequence;
     108: aload_0
     109: aload         6
     111: putfield      #592                // Field h:Landroid/os/Message;
     114: aload_0
     115: aload         5
     117: putfield      #561                // Field H:Landroid/graphics/drawable/Drawable;
     120: return

  public void a(android.graphics.drawable.Drawable);
    Code:
       0: aload_0
       1: aload_1
       2: putfield      #424                // Field J:Landroid/graphics/drawable/Drawable;
       5: aload_0
       6: iconst_0
       7: putfield      #103                // Field I:I
      10: aload_0
      11: getfield      #400                // Field K:Landroid/widget/ImageView;
      14: ifnull        47
      17: aload_1
      18: ifnull        38
      21: aload_0
      22: getfield      #400                // Field K:Landroid/widget/ImageView;
      25: iconst_0
      26: invokevirtual #442                // Method android/widget/ImageView.setVisibility:(I)V
      29: aload_0
      30: getfield      #400                // Field K:Landroid/widget/ImageView;
      33: aload_1
      34: invokevirtual #428                // Method android/widget/ImageView.setImageDrawable:(Landroid/graphics/drawable/Drawable;)V
      37: return
      38: aload_0
      39: getfield      #400                // Field K:Landroid/widget/ImageView;
      42: bipush        8
      44: invokevirtual #442                // Method android/widget/ImageView.setVisibility:(I)V
      47: return

  public void a(android.view.View, int, int, int, int);
    Code:
       0: aload_0
       1: aload_1
       2: putfield      #232                // Field v:Landroid/view/View;
       5: aload_0
       6: iconst_0
       7: putfield      #234                // Field w:I
      10: aload_0
      11: iconst_1
      12: putfield      #101                // Field B:Z
      15: aload_0
      16: iload_2
      17: putfield      #274                // Field x:I
      20: aload_0
      21: iload_3
      22: putfield      #276                // Field y:I
      25: aload_0
      26: iload         4
      28: putfield      #278                // Field z:I
      31: aload_0
      32: iload         5
      34: putfield      #280                // Field A:I
      37: return

  public void a(java.lang.CharSequence);
    Code:
       0: aload_0
       1: aload_1
       2: putfield      #402                // Field t:Ljava/lang/CharSequence;
       5: aload_0
       6: getfield      #415                // Field L:Landroid/widget/TextView;
       9: ifnull        20
      12: aload_0
      13: getfield      #415                // Field L:Landroid/widget/TextView;
      16: aload_1
      17: invokevirtual #419                // Method android/widget/TextView.setText:(Ljava/lang/CharSequence;)V
      20: return

  public boolean a(int, android.view.KeyEvent);
    Code:
       0: aload_0
       1: getfield      #316                // Field i:Landroid/support/v4/widget/NestedScrollView;
       4: ifnull        20
       7: aload_0
       8: getfield      #316                // Field i:Landroid/support/v4/widget/NestedScrollView;
      11: aload_2
      12: invokevirtual #597                // Method android/support/v4/widget/NestedScrollView.a:(Landroid/view/KeyEvent;)Z
      15: ifeq          20
      18: iconst_1
      19: ireturn
      20: iconst_0
      21: ireturn

  public void b(int);
    Code:
       0: aload_0
       1: aconst_null
       2: putfield      #424                // Field J:Landroid/graphics/drawable/Drawable;
       5: aload_0
       6: iload_1
       7: putfield      #103                // Field I:I
      10: aload_0
      11: getfield      #400                // Field K:Landroid/widget/ImageView;
      14: ifnull        50
      17: iload_1
      18: ifeq          41
      21: aload_0
      22: getfield      #400                // Field K:Landroid/widget/ImageView;
      25: iconst_0
      26: invokevirtual #442                // Method android/widget/ImageView.setVisibility:(I)V
      29: aload_0
      30: getfield      #400                // Field K:Landroid/widget/ImageView;
      33: aload_0
      34: getfield      #103                // Field I:I
      37: invokevirtual #422                // Method android/widget/ImageView.setImageResource:(I)V
      40: return
      41: aload_0
      42: getfield      #400                // Field K:Landroid/widget/ImageView;
      45: bipush        8
      47: invokevirtual #442                // Method android/widget/ImageView.setVisibility:(I)V
      50: return

  public void b(android.view.View);
    Code:
       0: aload_0
       1: aload_1
       2: putfield      #389                // Field N:Landroid/view/View;
       5: return

  public void b(java.lang.CharSequence);
    Code:
       0: aload_0
       1: aload_1
       2: putfield      #314                // Field u:Ljava/lang/CharSequence;
       5: aload_0
       6: getfield      #515                // Field M:Landroid/widget/TextView;
       9: ifnull        20
      12: aload_0
      13: getfield      #515                // Field M:Landroid/widget/TextView;
      16: aload_1
      17: invokevirtual #419                // Method android/widget/TextView.setText:(Ljava/lang/CharSequence;)V
      20: return

  public boolean b(int, android.view.KeyEvent);
    Code:
       0: aload_0
       1: getfield      #316                // Field i:Landroid/support/v4/widget/NestedScrollView;
       4: ifnull        20
       7: aload_0
       8: getfield      #316                // Field i:Landroid/support/v4/widget/NestedScrollView;
      11: aload_2
      12: invokevirtual #597                // Method android/support/v4/widget/NestedScrollView.a:(Landroid/view/KeyEvent;)Z
      15: ifeq          20
      18: iconst_1
      19: ireturn
      20: iconst_0
      21: ireturn

  public int c(int);
    Code:
       0: new           #359                // class android/util/TypedValue
       3: dup
       4: invokespecial #360                // Method android/util/TypedValue."<init>":()V
       7: astore_2
       8: aload_0
       9: getfield      #114                // Field q:Landroid/content/Context;
      12: invokevirtual #364                // Method android/content/Context.getTheme:()Landroid/content/res/Resources$Theme;
      15: iload_1
      16: aload_2
      17: iconst_1
      18: invokevirtual #373                // Method android/content/res/Resources$Theme.resolveAttribute:(ILandroid/util/TypedValue;Z)Z
      21: pop
      22: aload_2
      23: getfield      #601                // Field android/util/TypedValue.resourceId:I
      26: ireturn

  public void c(android.view.View);
    Code:
       0: aload_0
       1: aload_1
       2: putfield      #232                // Field v:Landroid/view/View;
       5: aload_0
       6: iconst_0
       7: putfield      #234                // Field w:I
      10: aload_0
      11: iconst_0
      12: putfield      #101                // Field B:Z
      15: return
}
