class android.support.v7.app.AlertController$1 implements android.view.View$OnClickListener {
  final android.support.v7.app.AlertController a;

  android.support.v7.app.AlertController$1(android.support.v7.app.AlertController);
    Code:
       0: aload_0
       1: aload_1
       2: putfield      #14                 // Field a:Landroid/support/v7/app/AlertController;
       5: aload_0
       6: invokespecial #17                 // Method java/lang/Object."<init>":()V
       9: return

  public void onClick(android.view.View);
    Code:
       0: aload_1
       1: aload_0
       2: getfield      #14                 // Field a:Landroid/support/v7/app/AlertController;
       5: getfield      #24                 // Field android/support/v7/app/AlertController.c:Landroid/widget/Button;
       8: if_acmpne     37
      11: aload_0
      12: getfield      #14                 // Field a:Landroid/support/v7/app/AlertController;
      15: getfield      #28                 // Field android/support/v7/app/AlertController.d:Landroid/os/Message;
      18: ifnull        37
      21: aload_0
      22: getfield      #14                 // Field a:Landroid/support/v7/app/AlertController;
      25: getfield      #28                 // Field android/support/v7/app/AlertController.d:Landroid/os/Message;
      28: astore_1
      29: aload_1
      30: invokestatic  #34                 // Method android/os/Message.obtain:(Landroid/os/Message;)Landroid/os/Message;
      33: astore_1
      34: goto          103
      37: aload_1
      38: aload_0
      39: getfield      #14                 // Field a:Landroid/support/v7/app/AlertController;
      42: getfield      #37                 // Field android/support/v7/app/AlertController.e:Landroid/widget/Button;
      45: if_acmpne     69
      48: aload_0
      49: getfield      #14                 // Field a:Landroid/support/v7/app/AlertController;
      52: getfield      #40                 // Field android/support/v7/app/AlertController.f:Landroid/os/Message;
      55: ifnull        69
      58: aload_0
      59: getfield      #14                 // Field a:Landroid/support/v7/app/AlertController;
      62: getfield      #40                 // Field android/support/v7/app/AlertController.f:Landroid/os/Message;
      65: astore_1
      66: goto          29
      69: aload_1
      70: aload_0
      71: getfield      #14                 // Field a:Landroid/support/v7/app/AlertController;
      74: getfield      #43                 // Field android/support/v7/app/AlertController.g:Landroid/widget/Button;
      77: if_acmpne     101
      80: aload_0
      81: getfield      #14                 // Field a:Landroid/support/v7/app/AlertController;
      84: getfield      #46                 // Field android/support/v7/app/AlertController.h:Landroid/os/Message;
      87: ifnull        101
      90: aload_0
      91: getfield      #14                 // Field a:Landroid/support/v7/app/AlertController;
      94: getfield      #46                 // Field android/support/v7/app/AlertController.h:Landroid/os/Message;
      97: astore_1
      98: goto          29
     101: aconst_null
     102: astore_1
     103: aload_1
     104: ifnull        111
     107: aload_1
     108: invokevirtual #49                 // Method android/os/Message.sendToTarget:()V
     111: aload_0
     112: getfield      #14                 // Field a:Landroid/support/v7/app/AlertController;
     115: getfield      #53                 // Field android/support/v7/app/AlertController.p:Landroid/os/Handler;
     118: iconst_1
     119: aload_0
     120: getfield      #14                 // Field a:Landroid/support/v7/app/AlertController;
     123: getfield      #56                 // Field android/support/v7/app/AlertController.a:Landroid/support/v7/app/m;
     126: invokevirtual #62                 // Method android/os/Handler.obtainMessage:(ILjava/lang/Object;)Landroid/os/Message;
     129: invokevirtual #49                 // Method android/os/Message.sendToTarget:()V
     132: return
}
