public class android.support.v7.app.AlertController$a {
  public int A;

  public int B;

  public int C;

  public int D;

  public boolean E;

  public boolean[] F;

  public boolean G;

  public boolean H;

  public int I;

  public android.content.DialogInterface$OnMultiChoiceClickListener J;

  public android.database.Cursor K;

  public java.lang.String L;

  public java.lang.String M;

  public android.widget.AdapterView$OnItemSelectedListener N;

  public android.support.v7.app.AlertController$a$a O;

  public boolean P;

  public final android.content.Context a;

  public final android.view.LayoutInflater b;

  public int c;

  public android.graphics.drawable.Drawable d;

  public int e;

  public java.lang.CharSequence f;

  public android.view.View g;

  public java.lang.CharSequence h;

  public java.lang.CharSequence i;

  public android.graphics.drawable.Drawable j;

  public android.content.DialogInterface$OnClickListener k;

  public java.lang.CharSequence l;

  public android.graphics.drawable.Drawable m;

  public android.content.DialogInterface$OnClickListener n;

  public java.lang.CharSequence o;

  public android.graphics.drawable.Drawable p;

  public android.content.DialogInterface$OnClickListener q;

  public boolean r;

  public android.content.DialogInterface$OnCancelListener s;

  public android.content.DialogInterface$OnDismissListener t;

  public android.content.DialogInterface$OnKeyListener u;

  public java.lang.CharSequence[] v;

  public android.widget.ListAdapter w;

  public android.content.DialogInterface$OnClickListener x;

  public int y;

  public android.view.View z;

  public android.support.v7.app.AlertController$a(android.content.Context);
    Code:
       0: aload_0
       1: invokespecial #81                 // Method java/lang/Object."<init>":()V
       4: aload_0
       5: iconst_0
       6: putfield      #83                 // Field c:I
       9: aload_0
      10: iconst_0
      11: putfield      #85                 // Field e:I
      14: aload_0
      15: iconst_0
      16: putfield      #87                 // Field E:Z
      19: aload_0
      20: iconst_m1
      21: putfield      #89                 // Field I:I
      24: aload_0
      25: iconst_1
      26: putfield      #91                 // Field P:Z
      29: aload_0
      30: aload_1
      31: putfield      #93                 // Field a:Landroid/content/Context;
      34: aload_0
      35: iconst_1
      36: putfield      #95                 // Field r:Z
      39: aload_0
      40: aload_1
      41: ldc           #97                 // String layout_inflater
      43: invokevirtual #103                // Method android/content/Context.getSystemService:(Ljava/lang/String;)Ljava/lang/Object;
      46: checkcast     #105                // class android/view/LayoutInflater
      49: putfield      #107                // Field b:Landroid/view/LayoutInflater;
      52: return

  public void a(android.support.v7.app.AlertController);
    Code:
       0: aload_0
       1: getfield      #192                // Field g:Landroid/view/View;
       4: ifnull        18
       7: aload_1
       8: aload_0
       9: getfield      #192                // Field g:Landroid/view/View;
      12: invokevirtual #195                // Method android/support/v7/app/AlertController.b:(Landroid/view/View;)V
      15: goto          82
      18: aload_0
      19: getfield      #197                // Field f:Ljava/lang/CharSequence;
      22: ifnull        33
      25: aload_1
      26: aload_0
      27: getfield      #197                // Field f:Ljava/lang/CharSequence;
      30: invokevirtual #200                // Method android/support/v7/app/AlertController.a:(Ljava/lang/CharSequence;)V
      33: aload_0
      34: getfield      #202                // Field d:Landroid/graphics/drawable/Drawable;
      37: ifnull        48
      40: aload_1
      41: aload_0
      42: getfield      #202                // Field d:Landroid/graphics/drawable/Drawable;
      45: invokevirtual #205                // Method android/support/v7/app/AlertController.a:(Landroid/graphics/drawable/Drawable;)V
      48: aload_0
      49: getfield      #83                 // Field c:I
      52: ifeq          63
      55: aload_1
      56: aload_0
      57: getfield      #83                 // Field c:I
      60: invokevirtual #207                // Method android/support/v7/app/AlertController.b:(I)V
      63: aload_0
      64: getfield      #85                 // Field e:I
      67: ifeq          82
      70: aload_1
      71: aload_1
      72: aload_0
      73: getfield      #85                 // Field e:I
      76: invokevirtual #210                // Method android/support/v7/app/AlertController.c:(I)I
      79: invokevirtual #207                // Method android/support/v7/app/AlertController.b:(I)V
      82: aload_0
      83: getfield      #212                // Field h:Ljava/lang/CharSequence;
      86: ifnull        97
      89: aload_1
      90: aload_0
      91: getfield      #212                // Field h:Ljava/lang/CharSequence;
      94: invokevirtual #214                // Method android/support/v7/app/AlertController.b:(Ljava/lang/CharSequence;)V
      97: aload_0
      98: getfield      #216                // Field i:Ljava/lang/CharSequence;
     101: ifnonnull     111
     104: aload_0
     105: getfield      #218                // Field j:Landroid/graphics/drawable/Drawable;
     108: ifnull        129
     111: aload_1
     112: iconst_m1
     113: aload_0
     114: getfield      #216                // Field i:Ljava/lang/CharSequence;
     117: aload_0
     118: getfield      #220                // Field k:Landroid/content/DialogInterface$OnClickListener;
     121: aconst_null
     122: aload_0
     123: getfield      #218                // Field j:Landroid/graphics/drawable/Drawable;
     126: invokevirtual #223                // Method android/support/v7/app/AlertController.a:(ILjava/lang/CharSequence;Landroid/content/DialogInterface$OnClickListener;Landroid/os/Message;Landroid/graphics/drawable/Drawable;)V
     129: aload_0
     130: getfield      #225                // Field l:Ljava/lang/CharSequence;
     133: ifnonnull     143
     136: aload_0
     137: getfield      #227                // Field m:Landroid/graphics/drawable/Drawable;
     140: ifnull        162
     143: aload_1
     144: bipush        -2
     146: aload_0
     147: getfield      #225                // Field l:Ljava/lang/CharSequence;
     150: aload_0
     151: getfield      #229                // Field n:Landroid/content/DialogInterface$OnClickListener;
     154: aconst_null
     155: aload_0
     156: getfield      #227                // Field m:Landroid/graphics/drawable/Drawable;
     159: invokevirtual #223                // Method android/support/v7/app/AlertController.a:(ILjava/lang/CharSequence;Landroid/content/DialogInterface$OnClickListener;Landroid/os/Message;Landroid/graphics/drawable/Drawable;)V
     162: aload_0
     163: getfield      #231                // Field o:Ljava/lang/CharSequence;
     166: ifnonnull     176
     169: aload_0
     170: getfield      #233                // Field p:Landroid/graphics/drawable/Drawable;
     173: ifnull        195
     176: aload_1
     177: bipush        -3
     179: aload_0
     180: getfield      #231                // Field o:Ljava/lang/CharSequence;
     183: aload_0
     184: getfield      #235                // Field q:Landroid/content/DialogInterface$OnClickListener;
     187: aconst_null
     188: aload_0
     189: getfield      #233                // Field p:Landroid/graphics/drawable/Drawable;
     192: invokevirtual #223                // Method android/support/v7/app/AlertController.a:(ILjava/lang/CharSequence;Landroid/content/DialogInterface$OnClickListener;Landroid/os/Message;Landroid/graphics/drawable/Drawable;)V
     195: aload_0
     196: getfield      #126                // Field v:[Ljava/lang/CharSequence;
     199: ifnonnull     216
     202: aload_0
     203: getfield      #121                // Field K:Landroid/database/Cursor;
     206: ifnonnull     216
     209: aload_0
     210: getfield      #149                // Field w:Landroid/widget/ListAdapter;
     213: ifnull        221
     216: aload_0
     217: aload_1
     218: invokespecial #237                // Method b:(Landroid/support/v7/app/AlertController;)V
     221: aload_0
     222: getfield      #239                // Field z:Landroid/view/View;
     225: ifnull        269
     228: aload_0
     229: getfield      #87                 // Field E:Z
     232: ifeq          260
     235: aload_1
     236: aload_0
     237: getfield      #239                // Field z:Landroid/view/View;
     240: aload_0
     241: getfield      #241                // Field A:I
     244: aload_0
     245: getfield      #243                // Field B:I
     248: aload_0
     249: getfield      #245                // Field C:I
     252: aload_0
     253: getfield      #247                // Field D:I
     256: invokevirtual #250                // Method android/support/v7/app/AlertController.a:(Landroid/view/View;IIII)V
     259: return
     260: aload_1
     261: aload_0
     262: getfield      #239                // Field z:Landroid/view/View;
     265: invokevirtual #252                // Method android/support/v7/app/AlertController.c:(Landroid/view/View;)V
     268: return
     269: aload_0
     270: getfield      #254                // Field y:I
     273: ifeq          284
     276: aload_1
     277: aload_0
     278: getfield      #254                // Field y:I
     281: invokevirtual #256                // Method android/support/v7/app/AlertController.a:(I)V
     284: return
}
