public class android.support.v7.app.d$a {
  public android.support.v7.app.d$a(android.content.Context);
    Code:
       0: aload_0
       1: aload_1
       2: aload_1
       3: iconst_0
       4: invokestatic  #15                 // Method android/support/v7/app/d.a:(Landroid/content/Context;I)I
       7: invokespecial #18                 // Method "<init>":(Landroid/content/Context;I)V
      10: return

  public android.support.v7.app.d$a(android.content.Context, int);
    Code:
       0: aload_0
       1: invokespecial #22                 // Method java/lang/Object."<init>":()V
       4: aload_0
       5: new           #24                 // class android/support/v7/app/AlertController$a
       8: dup
       9: new           #26                 // class android/view/ContextThemeWrapper
      12: dup
      13: aload_1
      14: aload_1
      15: iload_2
      16: invokestatic  #15                 // Method android/support/v7/app/d.a:(Landroid/content/Context;I)I
      19: invokespecial #27                 // Method android/view/ContextThemeWrapper."<init>":(Landroid/content/Context;I)V
      22: invokespecial #29                 // Method android/support/v7/app/AlertController$a."<init>":(Landroid/content/Context;)V
      25: putfield      #31                 // Field a:Landroid/support/v7/app/AlertController$a;
      28: aload_0
      29: iload_2
      30: putfield      #33                 // Field b:I
      33: return

  public android.content.Context a();
    Code:
       0: aload_0
       1: getfield      #31                 // Field a:Landroid/support/v7/app/AlertController$a;
       4: getfield      #37                 // Field android/support/v7/app/AlertController$a.a:Landroid/content/Context;
       7: areturn

  public android.support.v7.app.d$a a(int);
    Code:
       0: aload_0
       1: getfield      #31                 // Field a:Landroid/support/v7/app/AlertController$a;
       4: aload_0
       5: getfield      #31                 // Field a:Landroid/support/v7/app/AlertController$a;
       8: getfield      #37                 // Field android/support/v7/app/AlertController$a.a:Landroid/content/Context;
      11: iload_1
      12: invokevirtual #44                 // Method android/content/Context.getText:(I)Ljava/lang/CharSequence;
      15: putfield      #48                 // Field android/support/v7/app/AlertController$a.h:Ljava/lang/CharSequence;
      18: aload_0
      19: areturn

  public android.support.v7.app.d$a a(int, android.content.DialogInterface$OnClickListener);
    Code:
       0: aload_0
       1: getfield      #31                 // Field a:Landroid/support/v7/app/AlertController$a;
       4: aload_0
       5: getfield      #31                 // Field a:Landroid/support/v7/app/AlertController$a;
       8: getfield      #37                 // Field android/support/v7/app/AlertController$a.a:Landroid/content/Context;
      11: iload_1
      12: invokevirtual #44                 // Method android/content/Context.getText:(I)Ljava/lang/CharSequence;
      15: putfield      #52                 // Field android/support/v7/app/AlertController$a.i:Ljava/lang/CharSequence;
      18: aload_0
      19: getfield      #31                 // Field a:Landroid/support/v7/app/AlertController$a;
      22: aload_2
      23: putfield      #56                 // Field android/support/v7/app/AlertController$a.k:Landroid/content/DialogInterface$OnClickListener;
      26: aload_0
      27: areturn

  public android.support.v7.app.d$a a(android.content.DialogInterface$OnKeyListener);
    Code:
       0: aload_0
       1: getfield      #31                 // Field a:Landroid/support/v7/app/AlertController$a;
       4: aload_1
       5: putfield      #61                 // Field android/support/v7/app/AlertController$a.u:Landroid/content/DialogInterface$OnKeyListener;
       8: aload_0
       9: areturn

  public android.support.v7.app.d$a a(android.graphics.drawable.Drawable);
    Code:
       0: aload_0
       1: getfield      #31                 // Field a:Landroid/support/v7/app/AlertController$a;
       4: aload_1
       5: putfield      #66                 // Field android/support/v7/app/AlertController$a.d:Landroid/graphics/drawable/Drawable;
       8: aload_0
       9: areturn

  public android.support.v7.app.d$a a(android.view.View);
    Code:
       0: aload_0
       1: getfield      #31                 // Field a:Landroid/support/v7/app/AlertController$a;
       4: aload_1
       5: putfield      #71                 // Field android/support/v7/app/AlertController$a.g:Landroid/view/View;
       8: aload_0
       9: areturn

  public android.support.v7.app.d$a a(android.widget.ListAdapter, android.content.DialogInterface$OnClickListener);
    Code:
       0: aload_0
       1: getfield      #31                 // Field a:Landroid/support/v7/app/AlertController$a;
       4: aload_1
       5: putfield      #76                 // Field android/support/v7/app/AlertController$a.w:Landroid/widget/ListAdapter;
       8: aload_0
       9: getfield      #31                 // Field a:Landroid/support/v7/app/AlertController$a;
      12: aload_2
      13: putfield      #79                 // Field android/support/v7/app/AlertController$a.x:Landroid/content/DialogInterface$OnClickListener;
      16: aload_0
      17: areturn

  public android.support.v7.app.d$a a(java.lang.CharSequence);
    Code:
       0: aload_0
       1: getfield      #31                 // Field a:Landroid/support/v7/app/AlertController$a;
       4: aload_1
       5: putfield      #83                 // Field android/support/v7/app/AlertController$a.f:Ljava/lang/CharSequence;
       8: aload_0
       9: areturn

  public android.support.v7.app.d$a b(int, android.content.DialogInterface$OnClickListener);
    Code:
       0: aload_0
       1: getfield      #31                 // Field a:Landroid/support/v7/app/AlertController$a;
       4: aload_0
       5: getfield      #31                 // Field a:Landroid/support/v7/app/AlertController$a;
       8: getfield      #37                 // Field android/support/v7/app/AlertController$a.a:Landroid/content/Context;
      11: iload_1
      12: invokevirtual #44                 // Method android/content/Context.getText:(I)Ljava/lang/CharSequence;
      15: putfield      #86                 // Field android/support/v7/app/AlertController$a.l:Ljava/lang/CharSequence;
      18: aload_0
      19: getfield      #31                 // Field a:Landroid/support/v7/app/AlertController$a;
      22: aload_2
      23: putfield      #89                 // Field android/support/v7/app/AlertController$a.n:Landroid/content/DialogInterface$OnClickListener;
      26: aload_0
      27: areturn

  public android.support.v7.app.d$a b(android.view.View);
    Code:
       0: aload_0
       1: getfield      #31                 // Field a:Landroid/support/v7/app/AlertController$a;
       4: aload_1
       5: putfield      #92                 // Field android/support/v7/app/AlertController$a.z:Landroid/view/View;
       8: aload_0
       9: getfield      #31                 // Field a:Landroid/support/v7/app/AlertController$a;
      12: iconst_0
      13: putfield      #95                 // Field android/support/v7/app/AlertController$a.y:I
      16: aload_0
      17: getfield      #31                 // Field a:Landroid/support/v7/app/AlertController$a;
      20: iconst_0
      21: putfield      #99                 // Field android/support/v7/app/AlertController$a.E:Z
      24: aload_0
      25: areturn

  public android.support.v7.app.d$a b(java.lang.CharSequence);
    Code:
       0: aload_0
       1: getfield      #31                 // Field a:Landroid/support/v7/app/AlertController$a;
       4: aload_1
       5: putfield      #48                 // Field android/support/v7/app/AlertController$a.h:Ljava/lang/CharSequence;
       8: aload_0
       9: areturn

  public android.support.v7.app.d b();
    Code:
       0: new           #6                  // class android/support/v7/app/d
       3: dup
       4: aload_0
       5: getfield      #31                 // Field a:Landroid/support/v7/app/AlertController$a;
       8: getfield      #37                 // Field android/support/v7/app/AlertController$a.a:Landroid/content/Context;
      11: aload_0
      12: getfield      #33                 // Field b:I
      15: invokespecial #101                // Method android/support/v7/app/d."<init>":(Landroid/content/Context;I)V
      18: astore_1
      19: aload_0
      20: getfield      #31                 // Field a:Landroid/support/v7/app/AlertController$a;
      23: aload_1
      24: getfield      #104                // Field android/support/v7/app/d.a:Landroid/support/v7/app/AlertController;
      27: invokevirtual #107                // Method android/support/v7/app/AlertController$a.a:(Landroid/support/v7/app/AlertController;)V
      30: aload_1
      31: aload_0
      32: getfield      #31                 // Field a:Landroid/support/v7/app/AlertController$a;
      35: getfield      #110                // Field android/support/v7/app/AlertController$a.r:Z
      38: invokevirtual #114                // Method android/support/v7/app/d.setCancelable:(Z)V
      41: aload_0
      42: getfield      #31                 // Field a:Landroid/support/v7/app/AlertController$a;
      45: getfield      #110                // Field android/support/v7/app/AlertController$a.r:Z
      48: ifeq          56
      51: aload_1
      52: iconst_1
      53: invokevirtual #117                // Method android/support/v7/app/d.setCanceledOnTouchOutside:(Z)V
      56: aload_1
      57: aload_0
      58: getfield      #31                 // Field a:Landroid/support/v7/app/AlertController$a;
      61: getfield      #121                // Field android/support/v7/app/AlertController$a.s:Landroid/content/DialogInterface$OnCancelListener;
      64: invokevirtual #125                // Method android/support/v7/app/d.setOnCancelListener:(Landroid/content/DialogInterface$OnCancelListener;)V
      67: aload_1
      68: aload_0
      69: getfield      #31                 // Field a:Landroid/support/v7/app/AlertController$a;
      72: getfield      #129                // Field android/support/v7/app/AlertController$a.t:Landroid/content/DialogInterface$OnDismissListener;
      75: invokevirtual #133                // Method android/support/v7/app/d.setOnDismissListener:(Landroid/content/DialogInterface$OnDismissListener;)V
      78: aload_0
      79: getfield      #31                 // Field a:Landroid/support/v7/app/AlertController$a;
      82: getfield      #61                 // Field android/support/v7/app/AlertController$a.u:Landroid/content/DialogInterface$OnKeyListener;
      85: ifnull        99
      88: aload_1
      89: aload_0
      90: getfield      #31                 // Field a:Landroid/support/v7/app/AlertController$a;
      93: getfield      #61                 // Field android/support/v7/app/AlertController$a.u:Landroid/content/DialogInterface$OnKeyListener;
      96: invokevirtual #137                // Method android/support/v7/app/d.setOnKeyListener:(Landroid/content/DialogInterface$OnKeyListener;)V
      99: aload_1
     100: areturn

  public android.support.v7.app.d$a c(int, android.content.DialogInterface$OnClickListener);
    Code:
       0: aload_0
       1: getfield      #31                 // Field a:Landroid/support/v7/app/AlertController$a;
       4: aload_0
       5: getfield      #31                 // Field a:Landroid/support/v7/app/AlertController$a;
       8: getfield      #37                 // Field android/support/v7/app/AlertController$a.a:Landroid/content/Context;
      11: iload_1
      12: invokevirtual #44                 // Method android/content/Context.getText:(I)Ljava/lang/CharSequence;
      15: putfield      #141                // Field android/support/v7/app/AlertController$a.o:Ljava/lang/CharSequence;
      18: aload_0
      19: getfield      #31                 // Field a:Landroid/support/v7/app/AlertController$a;
      22: aload_2
      23: putfield      #144                // Field android/support/v7/app/AlertController$a.q:Landroid/content/DialogInterface$OnClickListener;
      26: aload_0
      27: areturn

  public android.support.v7.app.d c();
    Code:
       0: aload_0
       1: invokevirtual #146                // Method b:()Landroid/support/v7/app/d;
       4: astore_1
       5: aload_1
       6: invokevirtual #149                // Method android/support/v7/app/d.show:()V
       9: aload_1
      10: areturn
}
