public class android.support.v7.app.d extends android.support.v7.app.m implements android.content.DialogInterface {
  final android.support.v7.app.AlertController a;

  protected android.support.v7.app.d(android.content.Context, int);
    Code:
       0: aload_0
       1: aload_1
       2: aload_1
       3: iload_2
       4: invokestatic  #15                 // Method a:(Landroid/content/Context;I)I
       7: invokespecial #17                 // Method android/support/v7/app/m."<init>":(Landroid/content/Context;I)V
      10: aload_0
      11: new           #19                 // class android/support/v7/app/AlertController
      14: dup
      15: aload_0
      16: invokevirtual #23                 // Method getContext:()Landroid/content/Context;
      19: aload_0
      20: aload_0
      21: invokevirtual #27                 // Method getWindow:()Landroid/view/Window;
      24: invokespecial #30                 // Method android/support/v7/app/AlertController."<init>":(Landroid/content/Context;Landroid/support/v7/app/m;Landroid/view/Window;)V
      27: putfield      #32                 // Field a:Landroid/support/v7/app/AlertController;
      30: return

  static int a(android.content.Context, int);
    Code:
       0: iload_1
       1: bipush        24
       3: iushr
       4: sipush        255
       7: iand
       8: iconst_1
       9: if_icmplt     14
      12: iload_1
      13: ireturn
      14: new           #35                 // class android/util/TypedValue
      17: dup
      18: invokespecial #38                 // Method android/util/TypedValue."<init>":()V
      21: astore_2
      22: aload_0
      23: invokevirtual #44                 // Method android/content/Context.getTheme:()Landroid/content/res/Resources$Theme;
      26: getstatic     #50                 // Field android/support/v7/a/a$a.alertDialogTheme:I
      29: aload_2
      30: iconst_1
      31: invokevirtual #56                 // Method android/content/res/Resources$Theme.resolveAttribute:(ILandroid/util/TypedValue;Z)Z
      34: pop
      35: aload_2
      36: getfield      #59                 // Field android/util/TypedValue.resourceId:I
      39: ireturn

  protected void onCreate(android.os.Bundle);
    Code:
       0: aload_0
       1: aload_1
       2: invokespecial #63                 // Method android/support/v7/app/m.onCreate:(Landroid/os/Bundle;)V
       5: aload_0
       6: getfield      #32                 // Field a:Landroid/support/v7/app/AlertController;
       9: invokevirtual #65                 // Method android/support/v7/app/AlertController.a:()V
      12: return

  public boolean onKeyDown(int, android.view.KeyEvent);
    Code:
       0: aload_0
       1: getfield      #32                 // Field a:Landroid/support/v7/app/AlertController;
       4: iload_1
       5: aload_2
       6: invokevirtual #69                 // Method android/support/v7/app/AlertController.a:(ILandroid/view/KeyEvent;)Z
       9: ifeq          14
      12: iconst_1
      13: ireturn
      14: aload_0
      15: iload_1
      16: aload_2
      17: invokespecial #71                 // Method android/support/v7/app/m.onKeyDown:(ILandroid/view/KeyEvent;)Z
      20: ireturn

  public boolean onKeyUp(int, android.view.KeyEvent);
    Code:
       0: aload_0
       1: getfield      #32                 // Field a:Landroid/support/v7/app/AlertController;
       4: iload_1
       5: aload_2
       6: invokevirtual #75                 // Method android/support/v7/app/AlertController.b:(ILandroid/view/KeyEvent;)Z
       9: ifeq          14
      12: iconst_1
      13: ireturn
      14: aload_0
      15: iload_1
      16: aload_2
      17: invokespecial #77                 // Method android/support/v7/app/m.onKeyUp:(ILandroid/view/KeyEvent;)Z
      20: ireturn

  public void setTitle(java.lang.CharSequence);
    Code:
       0: aload_0
       1: aload_1
       2: invokespecial #81                 // Method android/support/v7/app/m.setTitle:(Ljava/lang/CharSequence;)V
       5: aload_0
       6: getfield      #32                 // Field a:Landroid/support/v7/app/AlertController;
       9: aload_1
      10: invokevirtual #83                 // Method android/support/v7/app/AlertController.a:(Ljava/lang/CharSequence;)V
      13: return
}
