public class android.support.v7.app.e extends android.support.v4.app.j implements android.support.v4.app.ak$a,android.support.v7.app.b$b,android.support.v7.app.f {
  public android.support.v7.app.e();
    Code:
       0: aload_0
       1: invokespecial #20                 // Method android/support/v4/app/j."<init>":()V
       4: aload_0
       5: iconst_0
       6: putfield      #22                 // Field mThemeId:I
       9: return

  public void addContentView(android.view.View, android.view.ViewGroup$LayoutParams);
    Code:
       0: aload_0
       1: invokevirtual #75                 // Method getDelegate:()Landroid/support/v7/app/g;
       4: aload_1
       5: aload_2
       6: invokevirtual #80                 // Method android/support/v7/app/g.b:(Landroid/view/View;Landroid/view/ViewGroup$LayoutParams;)V
       9: return

  public void closeOptionsMenu();
    Code:
       0: aload_0
       1: invokevirtual #85                 // Method getSupportActionBar:()Landroid/support/v7/app/a;
       4: astore_1
       5: aload_0
       6: invokevirtual #57                 // Method getWindow:()Landroid/view/Window;
       9: iconst_0
      10: invokevirtual #88                 // Method android/view/Window.hasFeature:(I)Z
      13: ifeq          31
      16: aload_1
      17: ifnull        27
      20: aload_1
      21: invokevirtual #93                 // Method android/support/v7/app/a.d:()Z
      24: ifne          31
      27: aload_0
      28: invokespecial #95                 // Method android/support/v4/app/j.closeOptionsMenu:()V
      31: return

  public boolean dispatchKeyEvent(android.view.KeyEvent);
    Code:
       0: aload_1
       1: invokevirtual #50                 // Method android/view/KeyEvent.getKeyCode:()I
       4: istore_2
       5: aload_0
       6: invokevirtual #85                 // Method getSupportActionBar:()Landroid/support/v7/app/a;
       9: astore_3
      10: iload_2
      11: bipush        82
      13: if_icmpne     30
      16: aload_3
      17: ifnull        30
      20: aload_3
      21: aload_1
      22: invokevirtual #99                 // Method android/support/v7/app/a.a:(Landroid/view/KeyEvent;)Z
      25: ifeq          30
      28: iconst_1
      29: ireturn
      30: aload_0
      31: aload_1
      32: invokespecial #101                // Method android/support/v4/app/j.dispatchKeyEvent:(Landroid/view/KeyEvent;)Z
      35: ireturn

  public <T extends android.view.View> T findViewById(int);
    Code:
       0: aload_0
       1: invokevirtual #75                 // Method getDelegate:()Landroid/support/v7/app/g;
       4: iload_1
       5: invokevirtual #105                // Method android/support/v7/app/g.a:(I)Landroid/view/View;
       8: areturn

  public android.support.v7.app.g getDelegate();
    Code:
       0: aload_0
       1: getfield      #109                // Field mDelegate:Landroid/support/v7/app/g;
       4: ifnonnull     16
       7: aload_0
       8: aload_0
       9: aload_0
      10: invokestatic  #112                // Method android/support/v7/app/g.a:(Landroid/app/Activity;Landroid/support/v7/app/f;)Landroid/support/v7/app/g;
      13: putfield      #109                // Field mDelegate:Landroid/support/v7/app/g;
      16: aload_0
      17: getfield      #109                // Field mDelegate:Landroid/support/v7/app/g;
      20: areturn

  public android.support.v7.app.b$a getDrawerToggleDelegate();
    Code:
       0: aload_0
       1: invokevirtual #75                 // Method getDelegate:()Landroid/support/v7/app/g;
       4: invokevirtual #117                // Method android/support/v7/app/g.h:()Landroid/support/v7/app/b$a;
       7: areturn

  public android.view.MenuInflater getMenuInflater();
    Code:
       0: aload_0
       1: invokevirtual #75                 // Method getDelegate:()Landroid/support/v7/app/g;
       4: invokevirtual #121                // Method android/support/v7/app/g.b:()Landroid/view/MenuInflater;
       7: areturn

  public android.content.res.Resources getResources();
    Code:
       0: aload_0
       1: getfield      #125                // Field mResources:Landroid/content/res/Resources;
       4: ifnonnull     29
       7: invokestatic  #129                // Method android/support/v7/widget/bu.a:()Z
      10: ifeq          29
      13: aload_0
      14: new           #127                // class android/support/v7/widget/bu
      17: dup
      18: aload_0
      19: aload_0
      20: invokespecial #131                // Method android/support/v4/app/j.getResources:()Landroid/content/res/Resources;
      23: invokespecial #134                // Method android/support/v7/widget/bu."<init>":(Landroid/content/Context;Landroid/content/res/Resources;)V
      26: putfield      #125                // Field mResources:Landroid/content/res/Resources;
      29: aload_0
      30: getfield      #125                // Field mResources:Landroid/content/res/Resources;
      33: ifnonnull     41
      36: aload_0
      37: invokespecial #131                // Method android/support/v4/app/j.getResources:()Landroid/content/res/Resources;
      40: areturn
      41: aload_0
      42: getfield      #125                // Field mResources:Landroid/content/res/Resources;
      45: areturn

  public android.support.v7.app.a getSupportActionBar();
    Code:
       0: aload_0
       1: invokevirtual #75                 // Method getDelegate:()Landroid/support/v7/app/g;
       4: invokevirtual #136                // Method android/support/v7/app/g.a:()Landroid/support/v7/app/a;
       7: areturn

  public android.content.Intent getSupportParentActivityIntent();
    Code:
       0: aload_0
       1: invokestatic  #143                // Method android/support/v4/app/aa.a:(Landroid/app/Activity;)Landroid/content/Intent;
       4: areturn

  public void invalidateOptionsMenu();
    Code:
       0: aload_0
       1: invokevirtual #75                 // Method getDelegate:()Landroid/support/v7/app/g;
       4: invokevirtual #147                // Method android/support/v7/app/g.f:()V
       7: return

  public void onConfigurationChanged(android.content.res.Configuration);
    Code:
       0: aload_0
       1: aload_1
       2: invokespecial #151                // Method android/support/v4/app/j.onConfigurationChanged:(Landroid/content/res/Configuration;)V
       5: aload_0
       6: invokevirtual #75                 // Method getDelegate:()Landroid/support/v7/app/g;
       9: aload_1
      10: invokevirtual #153                // Method android/support/v7/app/g.a:(Landroid/content/res/Configuration;)V
      13: aload_0
      14: getfield      #125                // Field mResources:Landroid/content/res/Resources;
      17: ifnull        37
      20: aload_0
      21: invokespecial #131                // Method android/support/v4/app/j.getResources:()Landroid/content/res/Resources;
      24: invokevirtual #159                // Method android/content/res/Resources.getDisplayMetrics:()Landroid/util/DisplayMetrics;
      27: astore_2
      28: aload_0
      29: getfield      #125                // Field mResources:Landroid/content/res/Resources;
      32: aload_1
      33: aload_2
      34: invokevirtual #163                // Method android/content/res/Resources.updateConfiguration:(Landroid/content/res/Configuration;Landroid/util/DisplayMetrics;)V
      37: return

  public void onContentChanged();
    Code:
       0: aload_0
       1: invokevirtual #167                // Method onSupportContentChanged:()V
       4: return

  protected void onCreate(android.os.Bundle);
    Code:
       0: aload_0
       1: invokevirtual #75                 // Method getDelegate:()Landroid/support/v7/app/g;
       4: astore_2
       5: aload_2
       6: invokevirtual #172                // Method android/support/v7/app/g.i:()V
       9: aload_2
      10: aload_1
      11: invokevirtual #174                // Method android/support/v7/app/g.a:(Landroid/os/Bundle;)V
      14: aload_2
      15: invokevirtual #177                // Method android/support/v7/app/g.j:()Z
      18: ifeq          60
      21: aload_0
      22: getfield      #22                 // Field mThemeId:I
      25: ifeq          60
      28: getstatic     #30                 // Field android/os/Build$VERSION.SDK_INT:I
      31: bipush        23
      33: if_icmplt     52
      36: aload_0
      37: aload_0
      38: invokevirtual #181                // Method getTheme:()Landroid/content/res/Resources$Theme;
      41: aload_0
      42: getfield      #22                 // Field mThemeId:I
      45: iconst_0
      46: invokevirtual #185                // Method onApplyThemeResource:(Landroid/content/res/Resources$Theme;IZ)V
      49: goto          60
      52: aload_0
      53: aload_0
      54: getfield      #22                 // Field mThemeId:I
      57: invokevirtual #189                // Method setTheme:(I)V
      60: aload_0
      61: aload_1
      62: invokespecial #191                // Method android/support/v4/app/j.onCreate:(Landroid/os/Bundle;)V
      65: return

  public void onCreateSupportNavigateUpTaskStack(android.support.v4.app.ak);
    Code:
       0: aload_1
       1: aload_0
       2: invokevirtual #198                // Method android/support/v4/app/ak.a:(Landroid/app/Activity;)Landroid/support/v4/app/ak;
       5: pop
       6: return

  protected void onDestroy();
    Code:
       0: aload_0
       1: invokespecial #201                // Method android/support/v4/app/j.onDestroy:()V
       4: aload_0
       5: invokevirtual #75                 // Method getDelegate:()Landroid/support/v7/app/g;
       8: invokevirtual #204                // Method android/support/v7/app/g.g:()V
      11: return

  public boolean onKeyDown(int, android.view.KeyEvent);
    Code:
       0: aload_0
       1: iload_1
       2: aload_2
       3: invokespecial #207                // Method performMenuItemShortcut:(ILandroid/view/KeyEvent;)Z
       6: ifeq          11
       9: iconst_1
      10: ireturn
      11: aload_0
      12: iload_1
      13: aload_2
      14: invokespecial #209                // Method android/support/v4/app/j.onKeyDown:(ILandroid/view/KeyEvent;)Z
      17: ireturn

  public final boolean onMenuItemSelected(int, android.view.MenuItem);
    Code:
       0: aload_0
       1: iload_1
       2: aload_2
       3: invokespecial #213                // Method android/support/v4/app/j.onMenuItemSelected:(ILandroid/view/MenuItem;)Z
       6: ifeq          11
       9: iconst_1
      10: ireturn
      11: aload_0
      12: invokevirtual #85                 // Method getSupportActionBar:()Landroid/support/v7/app/a;
      15: astore_3
      16: aload_2
      17: invokeinterface #218,  1          // InterfaceMethod android/view/MenuItem.getItemId:()I
      22: ldc           #219                // int 16908332
      24: if_icmpne     45
      27: aload_3
      28: ifnull        45
      31: aload_3
      32: invokevirtual #221                // Method android/support/v7/app/a.a:()I
      35: iconst_4
      36: iand
      37: ifeq          45
      40: aload_0
      41: invokevirtual #224                // Method onSupportNavigateUp:()Z
      44: ireturn
      45: iconst_0
      46: ireturn

  public boolean onMenuOpened(int, android.view.Menu);
    Code:
       0: aload_0
       1: iload_1
       2: aload_2
       3: invokespecial #228                // Method android/support/v4/app/j.onMenuOpened:(ILandroid/view/Menu;)Z
       6: ireturn

  public void onPanelClosed(int, android.view.Menu);
    Code:
       0: aload_0
       1: iload_1
       2: aload_2
       3: invokespecial #232                // Method android/support/v4/app/j.onPanelClosed:(ILandroid/view/Menu;)V
       6: return

  protected void onPostCreate(android.os.Bundle);
    Code:
       0: aload_0
       1: aload_1
       2: invokespecial #235                // Method android/support/v4/app/j.onPostCreate:(Landroid/os/Bundle;)V
       5: aload_0
       6: invokevirtual #75                 // Method getDelegate:()Landroid/support/v7/app/g;
       9: aload_1
      10: invokevirtual #237                // Method android/support/v7/app/g.b:(Landroid/os/Bundle;)V
      13: return

  protected void onPostResume();
    Code:
       0: aload_0
       1: invokespecial #240                // Method android/support/v4/app/j.onPostResume:()V
       4: aload_0
       5: invokevirtual #75                 // Method getDelegate:()Landroid/support/v7/app/g;
       8: invokevirtual #243                // Method android/support/v7/app/g.e:()V
      11: return

  public void onPrepareSupportNavigateUpTaskStack(android.support.v4.app.ak);
    Code:
       0: return

  protected void onSaveInstanceState(android.os.Bundle);
    Code:
       0: aload_0
       1: aload_1
       2: invokespecial #247                // Method android/support/v4/app/j.onSaveInstanceState:(Landroid/os/Bundle;)V
       5: aload_0
       6: invokevirtual #75                 // Method getDelegate:()Landroid/support/v7/app/g;
       9: aload_1
      10: invokevirtual #250                // Method android/support/v7/app/g.c:(Landroid/os/Bundle;)V
      13: return

  protected void onStart();
    Code:
       0: aload_0
       1: invokespecial #253                // Method android/support/v4/app/j.onStart:()V
       4: aload_0
       5: invokevirtual #75                 // Method getDelegate:()Landroid/support/v7/app/g;
       8: invokevirtual #255                // Method android/support/v7/app/g.c:()V
      11: return

  protected void onStop();
    Code:
       0: aload_0
       1: invokespecial #258                // Method android/support/v4/app/j.onStop:()V
       4: aload_0
       5: invokevirtual #75                 // Method getDelegate:()Landroid/support/v7/app/g;
       8: invokevirtual #260                // Method android/support/v7/app/g.d:()V
      11: return

  public void onSupportActionModeFinished(android.support.v7.view.b);
    Code:
       0: return

  public void onSupportActionModeStarted(android.support.v7.view.b);
    Code:
       0: return

  public void onSupportContentChanged();
    Code:
       0: return

  public boolean onSupportNavigateUp();
    Code:
       0: aload_0
       1: invokevirtual #269                // Method getSupportParentActivityIntent:()Landroid/content/Intent;
       4: astore_1
       5: aload_1
       6: ifnull        57
       9: aload_0
      10: aload_1
      11: invokevirtual #273                // Method supportShouldUpRecreateTask:(Landroid/content/Intent;)Z
      14: ifeq          50
      17: aload_0
      18: invokestatic  #276                // Method android/support/v4/app/ak.a:(Landroid/content/Context;)Landroid/support/v4/app/ak;
      21: astore_1
      22: aload_0
      23: aload_1
      24: invokevirtual #278                // Method onCreateSupportNavigateUpTaskStack:(Landroid/support/v4/app/ak;)V
      27: aload_0
      28: aload_1
      29: invokevirtual #280                // Method onPrepareSupportNavigateUpTaskStack:(Landroid/support/v4/app/ak;)V
      32: aload_1
      33: invokevirtual #282                // Method android/support/v4/app/ak.a:()V
      36: aload_0
      37: invokestatic  #287                // Method android/support/v4/app/a.a:(Landroid/app/Activity;)V
      40: goto          55
      43: aload_0
      44: invokevirtual #290                // Method finish:()V
      47: goto          55
      50: aload_0
      51: aload_1
      52: invokevirtual #294                // Method supportNavigateUpTo:(Landroid/content/Intent;)V
      55: iconst_1
      56: ireturn
      57: iconst_0
      58: ireturn
      59: astore_1
      60: goto          43
    Exception table:
       from    to  target type
          36    40    59   Class java/lang/IllegalStateException

  protected void onTitleChanged(java.lang.CharSequence, int);
    Code:
       0: aload_0
       1: aload_1
       2: iload_2
       3: invokespecial #298                // Method android/support/v4/app/j.onTitleChanged:(Ljava/lang/CharSequence;I)V
       6: aload_0
       7: invokevirtual #75                 // Method getDelegate:()Landroid/support/v7/app/g;
      10: aload_1
      11: invokevirtual #301                // Method android/support/v7/app/g.a:(Ljava/lang/CharSequence;)V
      14: return

  public android.support.v7.view.b onWindowStartingSupportActionMode(android.support.v7.view.b$a);
    Code:
       0: aconst_null
       1: areturn

  public void openOptionsMenu();
    Code:
       0: aload_0
       1: invokevirtual #85                 // Method getSupportActionBar:()Landroid/support/v7/app/a;
       4: astore_1
       5: aload_0
       6: invokevirtual #57                 // Method getWindow:()Landroid/view/Window;
       9: iconst_0
      10: invokevirtual #88                 // Method android/view/Window.hasFeature:(I)Z
      13: ifeq          31
      16: aload_1
      17: ifnull        27
      20: aload_1
      21: invokevirtual #306                // Method android/support/v7/app/a.c:()Z
      24: ifne          31
      27: aload_0
      28: invokespecial #308                // Method android/support/v4/app/j.openOptionsMenu:()V
      31: return

  public void setContentView(int);
    Code:
       0: aload_0
       1: invokevirtual #75                 // Method getDelegate:()Landroid/support/v7/app/g;
       4: iload_1
       5: invokevirtual #311                // Method android/support/v7/app/g.b:(I)V
       8: return

  public void setContentView(android.view.View);
    Code:
       0: aload_0
       1: invokevirtual #75                 // Method getDelegate:()Landroid/support/v7/app/g;
       4: aload_1
       5: invokevirtual #314                // Method android/support/v7/app/g.a:(Landroid/view/View;)V
       8: return

  public void setContentView(android.view.View, android.view.ViewGroup$LayoutParams);
    Code:
       0: aload_0
       1: invokevirtual #75                 // Method getDelegate:()Landroid/support/v7/app/g;
       4: aload_1
       5: aload_2
       6: invokevirtual #316                // Method android/support/v7/app/g.a:(Landroid/view/View;Landroid/view/ViewGroup$LayoutParams;)V
       9: return

  public void setSupportActionBar(android.support.v7.widget.Toolbar);
    Code:
       0: aload_0
       1: invokevirtual #75                 // Method getDelegate:()Landroid/support/v7/app/g;
       4: aload_1
       5: invokevirtual #320                // Method android/support/v7/app/g.a:(Landroid/support/v7/widget/Toolbar;)V
       8: return

  public void setSupportProgress(int);
    Code:
       0: return

  public void setSupportProgressBarIndeterminate(boolean);
    Code:
       0: return

  public void setSupportProgressBarIndeterminateVisibility(boolean);
    Code:
       0: return

  public void setSupportProgressBarVisibility(boolean);
    Code:
       0: return

  public void setTheme(int);
    Code:
       0: aload_0
       1: iload_1
       2: invokespecial #326                // Method android/support/v4/app/j.setTheme:(I)V
       5: aload_0
       6: iload_1
       7: putfield      #22                 // Field mThemeId:I
      10: return

  public android.support.v7.view.b startSupportActionMode(android.support.v7.view.b$a);
    Code:
       0: aload_0
       1: invokevirtual #75                 // Method getDelegate:()Landroid/support/v7/app/g;
       4: aload_1
       5: invokevirtual #329                // Method android/support/v7/app/g.a:(Landroid/support/v7/view/b$a;)Landroid/support/v7/view/b;
       8: areturn

  public void supportInvalidateOptionsMenu();
    Code:
       0: aload_0
       1: invokevirtual #75                 // Method getDelegate:()Landroid/support/v7/app/g;
       4: invokevirtual #147                // Method android/support/v7/app/g.f:()V
       7: return

  public void supportNavigateUpTo(android.content.Intent);
    Code:
       0: aload_0
       1: aload_1
       2: invokestatic  #333                // Method android/support/v4/app/aa.b:(Landroid/app/Activity;Landroid/content/Intent;)V
       5: return

  public boolean supportRequestWindowFeature(int);
    Code:
       0: aload_0
       1: invokevirtual #75                 // Method getDelegate:()Landroid/support/v7/app/g;
       4: iload_1
       5: invokevirtual #336                // Method android/support/v7/app/g.c:(I)Z
       8: ireturn

  public boolean supportShouldUpRecreateTask(android.content.Intent);
    Code:
       0: aload_0
       1: aload_1
       2: invokestatic  #339                // Method android/support/v4/app/aa.a:(Landroid/app/Activity;Landroid/content/Intent;)Z
       5: ireturn
}
