class android.support.v7.app.i extends android.support.v7.app.k {
  android.support.v7.app.i(android.content.Context, android.view.Window, android.support.v7.app.f);
    Code:
       0: aload_0
       1: aload_1
       2: aload_2
       3: aload_3
       4: invokespecial #11                 // Method android/support/v7/app/k."<init>":(Landroid/content/Context;Landroid/view/Window;Landroid/support/v7/app/f;)V
       7: return

  android.view.Window$Callback a(android.view.Window$Callback);
    Code:
       0: new           #6                  // class android/support/v7/app/i$a
       3: dup
       4: aload_0
       5: aload_1
       6: invokespecial #16                 // Method android/support/v7/app/i$a."<init>":(Landroid/support/v7/app/i;Landroid/view/Window$Callback;)V
       9: areturn
}
