class android.support.v7.app.j$b$1 extends android.content.BroadcastReceiver {
  final android.support.v7.app.j$b a;

  android.support.v7.app.j$b$1(android.support.v7.app.j$b);
    Code:
       0: aload_0
       1: aload_1
       2: putfield      #18                 // Field a:Landroid/support/v7/app/j$b;
       5: aload_0
       6: invokespecial #20                 // Method android/content/BroadcastReceiver."<init>":()V
       9: return

  public void onReceive(android.content.Context, android.content.Intent);
    Code:
       0: aload_0
       1: getfield      #18                 // Field a:Landroid/support/v7/app/j$b;
       4: invokevirtual #25                 // Method android/support/v7/app/j$b.b:()V
       7: return
}
