class android.support.v7.app.j extends android.support.v7.app.l {
  android.support.v7.app.j(android.content.Context, android.view.Window, android.support.v7.app.f);
    Code:
       0: aload_0
       1: aload_1
       2: aload_2
       3: aload_3
       4: invokespecial #23                 // Method android/support/v7/app/l."<init>":(Landroid/content/Context;Landroid/view/Window;Landroid/support/v7/app/f;)V
       7: aload_0
       8: bipush        -100
      10: putfield      #25                 // Field t:I
      13: aload_0
      14: iconst_1
      15: putfield      #27                 // Field v:Z
      18: return

  android.view.View a(android.view.View, java.lang.String, android.content.Context, android.util.AttributeSet);
    Code:
       0: aconst_null
       1: areturn

  android.view.Window$Callback a(android.view.Window$Callback);
    Code:
       0: new           #6                  // class android/support/v7/app/j$a
       3: dup
       4: aload_0
       5: aload_1
       6: invokespecial #142                // Method android/support/v7/app/j$a."<init>":(Landroid/support/v7/app/j;Landroid/view/Window$Callback;)V
       9: areturn

  public void a(android.os.Bundle);
    Code:
       0: aload_0
       1: aload_1
       2: invokespecial #145                // Method android/support/v7/app/l.a:(Landroid/os/Bundle;)V
       5: aload_1
       6: ifnull        30
       9: aload_0
      10: getfield      #25                 // Field t:I
      13: bipush        -100
      15: if_icmpne     30
      18: aload_0
      19: aload_1
      20: ldc           #147                // String appcompat:local_night_mode
      22: bipush        -100
      24: invokevirtual #153                // Method android/os/Bundle.getInt:(Ljava/lang/String;I)I
      27: putfield      #25                 // Field t:I
      30: return

  public void c();
    Code:
       0: aload_0
       1: invokespecial #156                // Method android/support/v7/app/l.c:()V
       4: aload_0
       5: invokevirtual #159                // Method j:()Z
       8: pop
       9: return

  public void c(android.os.Bundle);
    Code:
       0: aload_0
       1: aload_1
       2: invokespecial #161                // Method android/support/v7/app/l.c:(Landroid/os/Bundle;)V
       5: aload_0
       6: getfield      #25                 // Field t:I
       9: bipush        -100
      11: if_icmpeq     24
      14: aload_1
      15: ldc           #147                // String appcompat:local_night_mode
      17: aload_0
      18: getfield      #25                 // Field t:I
      21: invokevirtual #165                // Method android/os/Bundle.putInt:(Ljava/lang/String;I)V
      24: return

  int d(int);
    Code:
       0: iload_1
       1: bipush        -100
       3: if_icmpeq     24
       6: iload_1
       7: ifeq          12
      10: iload_1
      11: ireturn
      12: aload_0
      13: invokespecial #168                // Method y:()V
      16: aload_0
      17: getfield      #89                 // Field w:Landroid/support/v7/app/j$b;
      20: invokevirtual #170                // Method android/support/v7/app/j$b.a:()I
      23: ireturn
      24: iconst_m1
      25: ireturn

  public void d();
    Code:
       0: aload_0
       1: invokespecial #172                // Method android/support/v7/app/l.d:()V
       4: aload_0
       5: getfield      #89                 // Field w:Landroid/support/v7/app/j$b;
       8: ifnull        18
      11: aload_0
      12: getfield      #89                 // Field w:Landroid/support/v7/app/j$b;
      15: invokevirtual #173                // Method android/support/v7/app/j$b.d:()V
      18: return

  public void g();
    Code:
       0: aload_0
       1: invokespecial #176                // Method android/support/v7/app/l.g:()V
       4: aload_0
       5: getfield      #89                 // Field w:Landroid/support/v7/app/j$b;
       8: ifnull        18
      11: aload_0
      12: getfield      #89                 // Field w:Landroid/support/v7/app/j$b;
      15: invokevirtual #173                // Method android/support/v7/app/j$b.d:()V
      18: return

  public boolean j();
    Code:
       0: aload_0
       1: invokespecial #178                // Method x:()I
       4: istore_1
       5: aload_0
       6: iload_1
       7: invokevirtual #180                // Method d:(I)I
      10: istore_2
      11: iload_2
      12: iconst_m1
      13: if_icmpeq     25
      16: aload_0
      17: iload_2
      18: invokespecial #182                // Method h:(I)Z
      21: istore_3
      22: goto          27
      25: iconst_0
      26: istore_3
      27: iload_1
      28: ifne          42
      31: aload_0
      32: invokespecial #168                // Method y:()V
      35: aload_0
      36: getfield      #89                 // Field w:Landroid/support/v7/app/j$b;
      39: invokevirtual #183                // Method android/support/v7/app/j$b.c:()V
      42: aload_0
      43: iconst_1
      44: putfield      #101                // Field u:Z
      47: iload_3
      48: ireturn

  public boolean p();
    Code:
       0: aload_0
       1: getfield      #27                 // Field v:Z
       4: ireturn
}
