class android.support.v7.app.l$3 implements android.support.v7.widget.ar$a {
  final android.support.v7.app.l a;

  android.support.v7.app.l$3(android.support.v7.app.l);
    Code:
       0: aload_0
       1: aload_1
       2: putfield      #17                 // Field a:Landroid/support/v7/app/l;
       5: aload_0
       6: invokespecial #20                 // Method java/lang/Object."<init>":()V
       9: return

  public void a(android.graphics.Rect);
    Code:
       0: aload_1
       1: aload_0
       2: getfield      #17                 // Field a:Landroid/support/v7/app/l;
       5: aload_1
       6: getfield      #28                 // Field android/graphics/Rect.top:I
       9: invokevirtual #32                 // Method android/support/v7/app/l.g:(I)I
      12: putfield      #28                 // Field android/graphics/Rect.top:I
      15: return
}
