class android.support.v7.app.l$4 implements android.support.v7.widget.ContentFrameLayout$a {
  final android.support.v7.app.l a;

  android.support.v7.app.l$4(android.support.v7.app.l);
    Code:
       0: aload_0
       1: aload_1
       2: putfield      #17                 // Field a:Landroid/support/v7/app/l;
       5: aload_0
       6: invokespecial #20                 // Method java/lang/Object."<init>":()V
       9: return

  public void a();
    Code:
       0: return

  public void b();
    Code:
       0: aload_0
       1: getfield      #17                 // Field a:Landroid/support/v7/app/l;
       4: invokevirtual #25                 // Method android/support/v7/app/l.w:()V
       7: return
}
