class android.support.v7.app.l$c extends android.support.v7.widget.ContentFrameLayout {
  final android.support.v7.app.l a;

  public android.support.v7.app.l$c(android.support.v7.app.l, android.content.Context);
    Code:
       0: aload_0
       1: aload_1
       2: putfield      #13                 // Field a:Landroid/support/v7/app/l;
       5: aload_0
       6: aload_2
       7: invokespecial #16                 // Method android/support/v7/widget/ContentFrameLayout."<init>":(Landroid/content/Context;)V
      10: return

  public boolean dispatchKeyEvent(android.view.KeyEvent);
    Code:
       0: aload_0
       1: getfield      #13                 // Field a:Landroid/support/v7/app/l;
       4: aload_1
       5: invokevirtual #29                 // Method android/support/v7/app/l.a:(Landroid/view/KeyEvent;)Z
       8: ifne          24
      11: aload_0
      12: aload_1
      13: invokespecial #31                 // Method android/support/v7/widget/ContentFrameLayout.dispatchKeyEvent:(Landroid/view/KeyEvent;)Z
      16: ifeq          22
      19: goto          24
      22: iconst_0
      23: ireturn
      24: iconst_1
      25: ireturn

  public boolean onInterceptTouchEvent(android.view.MotionEvent);
    Code:
       0: aload_1
       1: invokevirtual #38                 // Method android/view/MotionEvent.getAction:()I
       4: ifne          34
       7: aload_0
       8: aload_1
       9: invokevirtual #42                 // Method android/view/MotionEvent.getX:()F
      12: f2i
      13: aload_1
      14: invokevirtual #45                 // Method android/view/MotionEvent.getY:()F
      17: f2i
      18: invokespecial #47                 // Method a:(II)Z
      21: ifeq          34
      24: aload_0
      25: getfield      #13                 // Field a:Landroid/support/v7/app/l;
      28: iconst_0
      29: invokevirtual #51                 // Method android/support/v7/app/l.e:(I)V
      32: iconst_1
      33: ireturn
      34: aload_0
      35: aload_1
      36: invokespecial #53                 // Method android/support/v7/widget/ContentFrameLayout.onInterceptTouchEvent:(Landroid/view/MotionEvent;)Z
      39: ireturn

  public void setBackgroundResource(int);
    Code:
       0: aload_0
       1: aload_0
       2: invokevirtual #58                 // Method getContext:()Landroid/content/Context;
       5: iload_1
       6: invokestatic  #64                 // Method android/support/v7/c/a/b.b:(Landroid/content/Context;I)Landroid/graphics/drawable/Drawable;
       9: invokevirtual #68                 // Method setBackgroundDrawable:(Landroid/graphics/drawable/Drawable;)V
      12: return
}
