class android.support.v7.app.l extends android.support.v7.app.h implements android.support.v7.view.menu.h$a,android.view.LayoutInflater$Factory2 {
  android.support.v7.view.b m;

  android.support.v7.widget.ActionBarContextView n;

  android.widget.PopupWindow o;

  java.lang.Runnable p;

  android.support.v4.view.x q;

  boolean r;

  int s;

  static {};
    Code:
       0: getstatic     #88                 // Field android/os/Build$VERSION.SDK_INT:I
       3: bipush        21
       5: if_icmpge     13
       8: iconst_1
       9: istore_0
      10: goto          15
      13: iconst_0
      14: istore_0
      15: iload_0
      16: putstatic     #90                 // Field t:Z
      19: return

  android.support.v7.app.l(android.content.Context, android.view.Window, android.support.v7.app.f);
    Code:
       0: aload_0
       1: aload_1
       2: aload_2
       3: aload_3
       4: invokespecial #95                 // Method android/support/v7/app/h."<init>":(Landroid/content/Context;Landroid/view/Window;Landroid/support/v7/app/f;)V
       7: aload_0
       8: aconst_null
       9: putfield      #97                 // Field q:Landroid/support/v4/view/x;
      12: aload_0
      13: new           #10                 // class android/support/v7/app/l$1
      16: dup
      17: aload_0
      18: invokespecial #100                // Method android/support/v7/app/l$1."<init>":(Landroid/support/v7/app/l;)V
      21: putfield      #102                // Field H:Ljava/lang/Runnable;
      24: return

  protected android.support.v7.app.l$d a(int, boolean);
    Code:
       0: aload_0
       1: getfield      #756                // Field E:[Landroid/support/v7/app/l$d;
       4: astore        4
       6: aload         4
       8: ifnull        21
      11: aload         4
      13: astore_3
      14: aload         4
      16: arraylength
      17: iload_1
      18: if_icmpgt     49
      21: iload_1
      22: iconst_1
      23: iadd
      24: anewarray     #35                 // class android/support/v7/app/l$d
      27: astore_3
      28: aload         4
      30: ifnull        44
      33: aload         4
      35: iconst_0
      36: aload_3
      37: iconst_0
      38: aload         4
      40: arraylength
      41: invokestatic  #762                // Method java/lang/System.arraycopy:(Ljava/lang/Object;ILjava/lang/Object;II)V
      44: aload_0
      45: aload_3
      46: putfield      #756                // Field E:[Landroid/support/v7/app/l$d;
      49: aload_3
      50: iload_1
      51: aaload
      52: astore        5
      54: aload         5
      56: astore        4
      58: aload         5
      60: ifnonnull     78
      63: new           #35                 // class android/support/v7/app/l$d
      66: dup
      67: iload_1
      68: invokespecial #764                // Method android/support/v7/app/l$d."<init>":(I)V
      71: astore        4
      73: aload_3
      74: iload_1
      75: aload         4
      77: aastore
      78: aload         4
      80: areturn

  android.support.v7.app.l$d a(android.view.Menu);
    Code:
       0: aload_0
       1: getfield      #756                // Field E:[Landroid/support/v7/app/l$d;
       4: astore        4
       6: iconst_0
       7: istore_3
       8: aload         4
      10: ifnull        20
      13: aload         4
      15: arraylength
      16: istore_2
      17: goto          22
      20: iconst_0
      21: istore_2
      22: iload_3
      23: iload_2
      24: if_icmpge     57
      27: aload         4
      29: iload_3
      30: aaload
      31: astore        5
      33: aload         5
      35: ifnull        50
      38: aload         5
      40: getfield      #146                // Field android/support/v7/app/l$d.j:Landroid/support/v7/view/menu/h;
      43: aload_1
      44: if_acmpne     50
      47: aload         5
      49: areturn
      50: iload_3
      51: iconst_1
      52: iadd
      53: istore_3
      54: goto          22
      57: aconst_null
      58: areturn

  public android.support.v7.view.b a(android.support.v7.view.b$a);
    Code:
       0: aload_1
       1: ifnonnull     15
       4: new           #646                // class java/lang/IllegalArgumentException
       7: dup
       8: ldc_w         #768                // String ActionMode callback can not be null.
      11: invokespecial #651                // Method java/lang/IllegalArgumentException."<init>":(Ljava/lang/String;)V
      14: athrow
      15: aload_0
      16: getfield      #466                // Field m:Landroid/support/v7/view/b;
      19: ifnull        29
      22: aload_0
      23: getfield      #466                // Field m:Landroid/support/v7/view/b;
      26: invokevirtual #772                // Method android/support/v7/view/b.c:()V
      29: new           #27                 // class android/support/v7/app/l$b
      32: dup
      33: aload_0
      34: aload_1
      35: invokespecial #775                // Method android/support/v7/app/l$b."<init>":(Landroid/support/v7/app/l;Landroid/support/v7/view/b$a;)V
      38: astore_1
      39: aload_0
      40: invokevirtual #777                // Method a:()Landroid/support/v7/app/a;
      43: astore_2
      44: aload_2
      45: ifnull        84
      48: aload_0
      49: aload_2
      50: aload_1
      51: invokevirtual #781                // Method android/support/v7/app/a.a:(Landroid/support/v7/view/b$a;)Landroid/support/v7/view/b;
      54: putfield      #466                // Field m:Landroid/support/v7/view/b;
      57: aload_0
      58: getfield      #466                // Field m:Landroid/support/v7/view/b;
      61: ifnull        84
      64: aload_0
      65: getfield      #784                // Field e:Landroid/support/v7/app/f;
      68: ifnull        84
      71: aload_0
      72: getfield      #784                // Field e:Landroid/support/v7/app/f;
      75: aload_0
      76: getfield      #466                // Field m:Landroid/support/v7/view/b;
      79: invokeinterface #790,  2          // InterfaceMethod android/support/v7/app/f.onSupportActionModeStarted:(Landroid/support/v7/view/b;)V
      84: aload_0
      85: getfield      #466                // Field m:Landroid/support/v7/view/b;
      88: ifnonnull     100
      91: aload_0
      92: aload_0
      93: aload_1
      94: invokevirtual #792                // Method b:(Landroid/support/v7/view/b$a;)Landroid/support/v7/view/b;
      97: putfield      #466                // Field m:Landroid/support/v7/view/b;
     100: aload_0
     101: getfield      #466                // Field m:Landroid/support/v7/view/b;
     104: areturn

  public <T extends android.view.View> T a(int);
    Code:
       0: aload_0
       1: invokespecial #794                // Method x:()V
       4: aload_0
       5: getfield      #291                // Field b:Landroid/view/Window;
       8: iload_1
       9: invokevirtual #669                // Method android/view/Window.findViewById:(I)Landroid/view/View;
      12: areturn

  android.view.View a(android.view.View, java.lang.String, android.content.Context, android.util.AttributeSet);
    Code:
       0: aload_0
       1: getfield      #800                // Field c:Landroid/view/Window$Callback;
       4: instanceof    #802                // class android/view/LayoutInflater$Factory
       7: ifeq          33
      10: aload_0
      11: getfield      #800                // Field c:Landroid/view/Window$Callback;
      14: checkcast     #802                // class android/view/LayoutInflater$Factory
      17: aload_2
      18: aload_3
      19: aload         4
      21: invokeinterface #806,  4          // InterfaceMethod android/view/LayoutInflater$Factory.onCreateView:(Ljava/lang/String;Landroid/content/Context;Landroid/util/AttributeSet;)Landroid/view/View;
      26: astore_1
      27: aload_1
      28: ifnull        33
      31: aload_1
      32: areturn
      33: aconst_null
      34: areturn

  void a(int, android.support.v7.app.l$d, android.view.Menu);
    Code:
       0: aload_2
       1: astore        5
       3: aload_3
       4: astore        6
       6: aload_3
       7: ifnonnull     67
      10: aload_2
      11: astore        4
      13: aload_2
      14: ifnonnull     44
      17: aload_2
      18: astore        4
      20: iload_1
      21: iflt          44
      24: aload_2
      25: astore        4
      27: iload_1
      28: aload_0
      29: getfield      #756                // Field E:[Landroid/support/v7/app/l$d;
      32: arraylength
      33: if_icmpge     44
      36: aload_0
      37: getfield      #756                // Field E:[Landroid/support/v7/app/l$d;
      40: iload_1
      41: aaload
      42: astore        4
      44: aload         4
      46: astore        5
      48: aload_3
      49: astore        6
      51: aload         4
      53: ifnull        67
      56: aload         4
      58: getfield      #146                // Field android/support/v7/app/l$d.j:Landroid/support/v7/view/menu/h;
      61: astore        6
      63: aload         4
      65: astore        5
      67: aload         5
      69: ifnull        81
      72: aload         5
      74: getfield      #114                // Field android/support/v7/app/l$d.o:Z
      77: ifne          81
      80: return
      81: aload_0
      82: invokevirtual #117                // Method q:()Z
      85: ifne          100
      88: aload_0
      89: getfield      #800                // Field c:Landroid/view/Window$Callback;
      92: iload_1
      93: aload         6
      95: invokeinterface #284,  3          // InterfaceMethod android/view/Window$Callback.onPanelClosed:(ILandroid/view/Menu;)V
     100: return

  void a(int, android.view.Menu);
    Code:
       0: iload_1
       1: bipush        108
       3: if_icmpne     21
       6: aload_0
       7: invokevirtual #777                // Method a:()Landroid/support/v7/app/a;
      10: astore_2
      11: aload_2
      12: ifnull        45
      15: aload_2
      16: iconst_0
      17: invokevirtual #809                // Method android/support/v7/app/a.g:(Z)V
      20: return
      21: iload_1
      22: ifne          45
      25: aload_0
      26: iload_1
      27: iconst_1
      28: invokevirtual #280                // Method a:(IZ)Landroid/support/v7/app/l$d;
      31: astore_2
      32: aload_2
      33: getfield      #114                // Field android/support/v7/app/l$d.o:Z
      36: ifeq          45
      39: aload_0
      40: aload_2
      41: iconst_0
      42: invokevirtual #155                // Method a:(Landroid/support/v7/app/l$d;Z)V
      45: return

  public void a(android.content.res.Configuration);
    Code:
       0: aload_0
       1: getfield      #582                // Field h:Z
       4: ifeq          28
       7: aload_0
       8: getfield      #104                // Field x:Z
      11: ifeq          28
      14: aload_0
      15: invokevirtual #777                // Method a:()Landroid/support/v7/app/a;
      18: astore_2
      19: aload_2
      20: ifnull        28
      23: aload_2
      24: aload_1
      25: invokevirtual #812                // Method android/support/v7/app/a.a:(Landroid/content/res/Configuration;)V
      28: invokestatic  #817                // Method android/support/v7/widget/m.a:()Landroid/support/v7/widget/m;
      31: aload_0
      32: getfield      #122                // Field a:Landroid/content/Context;
      35: invokevirtual #818                // Method android/support/v7/widget/m.a:(Landroid/content/Context;)V
      38: aload_0
      39: invokevirtual #820                // Method j:()Z
      42: pop
      43: return

  public void a(android.os.Bundle);
    Code:
       0: aload_0
       1: getfield      #800                // Field c:Landroid/view/Window$Callback;
       4: instanceof    #822                // class android/app/Activity
       7: ifeq          43
      10: aload_0
      11: getfield      #800                // Field c:Landroid/view/Window$Callback;
      14: checkcast     #822                // class android/app/Activity
      17: invokestatic  #827                // Method android/support/v4/app/aa.b:(Landroid/app/Activity;)Ljava/lang/String;
      20: ifnull        43
      23: aload_0
      24: invokevirtual #410                // Method n:()Landroid/support/v7/app/a;
      27: astore_1
      28: aload_1
      29: ifnonnull     38
      32: aload_0
      33: iconst_1
      34: putfield      #829                // Field I:Z
      37: return
      38: aload_1
      39: iconst_1
      40: invokevirtual #831                // Method android/support/v7/app/a.e:(Z)V
      43: return

  void a(android.support.v7.app.l$d, boolean);
    Code:
       0: iload_2
       1: ifeq          39
       4: aload_1
       5: getfield      #119                // Field android/support/v7/app/l$d.a:I
       8: ifne          39
      11: aload_0
      12: getfield      #258                // Field u:Landroid/support/v7/widget/ak;
      15: ifnull        39
      18: aload_0
      19: getfield      #258                // Field u:Landroid/support/v7/widget/ak;
      22: invokeinterface #275,  1          // InterfaceMethod android/support/v7/widget/ak.f:()Z
      27: ifeq          39
      30: aload_0
      31: aload_1
      32: getfield      #146                // Field android/support/v7/app/l$d.j:Landroid/support/v7/view/menu/h;
      35: invokevirtual #833                // Method b:(Landroid/support/v7/view/menu/h;)V
      38: return
      39: aload_0
      40: getfield      #122                // Field a:Landroid/content/Context;
      43: ldc           #157                // String window
      45: invokevirtual #161                // Method android/content/Context.getSystemService:(Ljava/lang/String;)Ljava/lang/Object;
      48: checkcast     #163                // class android/view/WindowManager
      51: astore_3
      52: aload_3
      53: ifnull        94
      56: aload_1
      57: getfield      #114                // Field android/support/v7/app/l$d.o:Z
      60: ifeq          94
      63: aload_1
      64: getfield      #169                // Field android/support/v7/app/l$d.g:Landroid/view/ViewGroup;
      67: ifnull        94
      70: aload_3
      71: aload_1
      72: getfield      #169                // Field android/support/v7/app/l$d.g:Landroid/view/ViewGroup;
      75: invokeinterface #834,  2          // InterfaceMethod android/view/WindowManager.removeView:(Landroid/view/View;)V
      80: iload_2
      81: ifeq          94
      84: aload_0
      85: aload_1
      86: getfield      #119                // Field android/support/v7/app/l$d.a:I
      89: aload_1
      90: aconst_null
      91: invokevirtual #836                // Method a:(ILandroid/support/v7/app/l$d;Landroid/view/Menu;)V
      94: aload_1
      95: iconst_0
      96: putfield      #335                // Field android/support/v7/app/l$d.m:Z
      99: aload_1
     100: iconst_0
     101: putfield      #233                // Field android/support/v7/app/l$d.n:Z
     104: aload_1
     105: iconst_0
     106: putfield      #114                // Field android/support/v7/app/l$d.o:Z
     109: aload_1
     110: aconst_null
     111: putfield      #204                // Field android/support/v7/app/l$d.h:Landroid/view/View;
     114: aload_1
     115: iconst_1
     116: putfield      #171                // Field android/support/v7/app/l$d.q:Z
     119: aload_0
     120: getfield      #401                // Field F:Landroid/support/v7/app/l$d;
     123: aload_1
     124: if_acmpne     132
     127: aload_0
     128: aconst_null
     129: putfield      #401                // Field F:Landroid/support/v7/app/l$d;
     132: return

  public void a(android.support.v7.view.menu.h);
    Code:
       0: aload_0
       1: aload_1
       2: iconst_1
       3: invokespecial #838                // Method a:(Landroid/support/v7/view/menu/h;Z)V
       6: return

  public void a(android.support.v7.widget.Toolbar);
    Code:
       0: aload_0
       1: getfield      #800                // Field c:Landroid/view/Window$Callback;
       4: instanceof    #822                // class android/app/Activity
       7: ifne          11
      10: return
      11: aload_0
      12: invokevirtual #777                // Method a:()Landroid/support/v7/app/a;
      15: astore_2
      16: aload_2
      17: instanceof    #841                // class android/support/v7/app/r
      20: ifeq          34
      23: new           #537                // class java/lang/IllegalStateException
      26: dup
      27: ldc_w         #843                // String This Activity already has an action bar supplied by the window decor. Do not request Window.FEATURE_SUPPORT_ACTION_BAR and set windowActionBar to false in your theme to use a Toolbar instead.
      30: invokespecial #540                // Method java/lang/IllegalStateException."<init>":(Ljava/lang/String;)V
      33: athrow
      34: aload_0
      35: aconst_null
      36: putfield      #846                // Field g:Landroid/view/MenuInflater;
      39: aload_2
      40: ifnull        47
      43: aload_2
      44: invokevirtual #847                // Method android/support/v7/app/a.g:()V
      47: aload_1
      48: ifnull        97
      51: new           #412                // class android/support/v7/app/o
      54: dup
      55: aload_1
      56: aload_0
      57: getfield      #800                // Field c:Landroid/view/Window$Callback;
      60: checkcast     #822                // class android/app/Activity
      63: invokevirtual #850                // Method android/app/Activity.getTitle:()Ljava/lang/CharSequence;
      66: aload_0
      67: getfield      #852                // Field d:Landroid/view/Window$Callback;
      70: invokespecial #855                // Method android/support/v7/app/o."<init>":(Landroid/support/v7/widget/Toolbar;Ljava/lang/CharSequence;Landroid/view/Window$Callback;)V
      73: astore_1
      74: aload_0
      75: aload_1
      76: putfield      #858                // Field f:Landroid/support/v7/app/a;
      79: aload_0
      80: getfield      #291                // Field b:Landroid/view/Window;
      83: astore_2
      84: aload_1
      85: invokevirtual #860                // Method android/support/v7/app/o.h:()Landroid/view/Window$Callback;
      88: astore_1
      89: aload_2
      90: aload_1
      91: invokevirtual #863                // Method android/view/Window.setCallback:(Landroid/view/Window$Callback;)V
      94: goto          115
      97: aload_0
      98: aconst_null
      99: putfield      #858                // Field f:Landroid/support/v7/app/a;
     102: aload_0
     103: getfield      #291                // Field b:Landroid/view/Window;
     106: astore_2
     107: aload_0
     108: getfield      #852                // Field d:Landroid/view/Window$Callback;
     111: astore_1
     112: goto          89
     115: aload_0
     116: invokevirtual #865                // Method f:()V
     119: return

  public void a(android.view.View);
    Code:
       0: aload_0
       1: invokespecial #794                // Method x:()V
       4: aload_0
       5: getfield      #494                // Field y:Landroid/view/ViewGroup;
       8: ldc_w         #668                // int 16908290
      11: invokevirtual #593                // Method android/view/ViewGroup.findViewById:(I)Landroid/view/View;
      14: checkcast     #190                // class android/view/ViewGroup
      17: astore_2
      18: aload_2
      19: invokevirtual #197                // Method android/view/ViewGroup.removeAllViews:()V
      22: aload_2
      23: aload_1
      24: invokevirtual #866                // Method android/view/ViewGroup.addView:(Landroid/view/View;)V
      27: aload_0
      28: getfield      #800                // Field c:Landroid/view/Window$Callback;
      31: invokeinterface #869,  1          // InterfaceMethod android/view/Window$Callback.onContentChanged:()V
      36: return

  public void a(android.view.View, android.view.ViewGroup$LayoutParams);
    Code:
       0: aload_0
       1: invokespecial #794                // Method x:()V
       4: aload_0
       5: getfield      #494                // Field y:Landroid/view/ViewGroup;
       8: ldc_w         #668                // int 16908290
      11: invokevirtual #593                // Method android/view/ViewGroup.findViewById:(I)Landroid/view/View;
      14: checkcast     #190                // class android/view/ViewGroup
      17: astore_3
      18: aload_3
      19: invokevirtual #197                // Method android/view/ViewGroup.removeAllViews:()V
      22: aload_3
      23: aload_1
      24: aload_2
      25: invokevirtual #225                // Method android/view/ViewGroup.addView:(Landroid/view/View;Landroid/view/ViewGroup$LayoutParams;)V
      28: aload_0
      29: getfield      #800                // Field c:Landroid/view/Window$Callback;
      32: invokeinterface #869,  1          // InterfaceMethod android/view/Window$Callback.onContentChanged:()V
      37: return

  void a(android.view.ViewGroup);
    Code:
       0: return

  boolean a(int, android.view.KeyEvent);
    Code:
       0: aload_0
       1: invokevirtual #777                // Method a:()Landroid/support/v7/app/a;
       4: astore        4
       6: aload         4
       8: ifnull        23
      11: aload         4
      13: iload_1
      14: aload_2
      15: invokevirtual #871                // Method android/support/v7/app/a.a:(ILandroid/view/KeyEvent;)Z
      18: ifeq          23
      21: iconst_1
      22: ireturn
      23: aload_0
      24: getfield      #401                // Field F:Landroid/support/v7/app/l$d;
      27: ifnull        64
      30: aload_0
      31: aload_0
      32: getfield      #401                // Field F:Landroid/support/v7/app/l$d;
      35: aload_2
      36: invokevirtual #874                // Method android/view/KeyEvent.getKeyCode:()I
      39: aload_2
      40: iconst_1
      41: invokespecial #876                // Method a:(Landroid/support/v7/app/l$d;ILandroid/view/KeyEvent;I)Z
      44: ifeq          64
      47: aload_0
      48: getfield      #401                // Field F:Landroid/support/v7/app/l$d;
      51: ifnull        62
      54: aload_0
      55: getfield      #401                // Field F:Landroid/support/v7/app/l$d;
      58: iconst_1
      59: putfield      #233                // Field android/support/v7/app/l$d.n:Z
      62: iconst_1
      63: ireturn
      64: aload_0
      65: getfield      #401                // Field F:Landroid/support/v7/app/l$d;
      68: ifnonnull     112
      71: aload_0
      72: iconst_0
      73: iconst_1
      74: invokevirtual #280                // Method a:(IZ)Landroid/support/v7/app/l$d;
      77: astore        4
      79: aload_0
      80: aload         4
      82: aload_2
      83: invokespecial #166                // Method b:(Landroid/support/v7/app/l$d;Landroid/view/KeyEvent;)Z
      86: pop
      87: aload_0
      88: aload         4
      90: aload_2
      91: invokevirtual #874                // Method android/view/KeyEvent.getKeyCode:()I
      94: aload_2
      95: iconst_1
      96: invokespecial #876                // Method a:(Landroid/support/v7/app/l$d;ILandroid/view/KeyEvent;I)Z
      99: istore_3
     100: aload         4
     102: iconst_0
     103: putfield      #335                // Field android/support/v7/app/l$d.m:Z
     106: iload_3
     107: ifeq          112
     110: iconst_1
     111: ireturn
     112: iconst_0
     113: ireturn

  public boolean a(android.support.v7.view.menu.h, android.view.MenuItem);
    Code:
       0: aload_0
       1: invokevirtual #142                // Method r:()Landroid/view/Window$Callback;
       4: astore_3
       5: aload_3
       6: ifnull        41
       9: aload_0
      10: invokevirtual #117                // Method q:()Z
      13: ifne          41
      16: aload_0
      17: aload_1
      18: invokevirtual #880                // Method android/support/v7/view/menu/h.p:()Landroid/support/v7/view/menu/h;
      21: invokevirtual #882                // Method a:(Landroid/view/Menu;)Landroid/support/v7/app/l$d;
      24: astore_1
      25: aload_1
      26: ifnull        41
      29: aload_3
      30: aload_1
      31: getfield      #119                // Field android/support/v7/app/l$d.a:I
      34: aload_2
      35: invokeinterface #886,  3          // InterfaceMethod android/view/Window$Callback.onMenuItemSelected:(ILandroid/view/MenuItem;)Z
      40: ireturn
      41: iconst_0
      42: ireturn

  boolean a(android.view.KeyEvent);
    Code:
       0: aload_1
       1: invokevirtual #874                // Method android/view/KeyEvent.getKeyCode:()I
       4: istore_3
       5: iconst_1
       6: istore_2
       7: iload_3
       8: bipush        82
      10: if_icmpne     28
      13: aload_0
      14: getfield      #800                // Field c:Landroid/view/Window$Callback;
      17: aload_1
      18: invokeinterface #890,  2          // InterfaceMethod android/view/Window$Callback.dispatchKeyEvent:(Landroid/view/KeyEvent;)Z
      23: ifeq          28
      26: iconst_1
      27: ireturn
      28: aload_1
      29: invokevirtual #874                // Method android/view/KeyEvent.getKeyCode:()I
      32: istore_3
      33: aload_1
      34: invokevirtual #893                // Method android/view/KeyEvent.getAction:()I
      37: ifne          43
      40: goto          45
      43: iconst_0
      44: istore_2
      45: iload_2
      46: ifeq          56
      49: aload_0
      50: iload_3
      51: aload_1
      52: invokevirtual #895                // Method c:(ILandroid/view/KeyEvent;)Z
      55: ireturn
      56: aload_0
      57: iload_3
      58: aload_1
      59: invokevirtual #897                // Method b:(ILandroid/view/KeyEvent;)Z
      62: ireturn

  android.support.v7.view.b b(android.support.v7.view.b$a);
    Code:
       0: aload_0
       1: invokevirtual #901                // Method u:()V
       4: aload_0
       5: getfield      #466                // Field m:Landroid/support/v7/view/b;
       8: ifnull        18
      11: aload_0
      12: getfield      #466                // Field m:Landroid/support/v7/view/b;
      15: invokevirtual #772                // Method android/support/v7/view/b.c:()V
      18: aload_1
      19: astore        4
      21: aload_1
      22: instanceof    #27                 // class android/support/v7/app/l$b
      25: ifne          39
      28: new           #27                 // class android/support/v7/app/l$b
      31: dup
      32: aload_0
      33: aload_1
      34: invokespecial #775                // Method android/support/v7/app/l$b."<init>":(Landroid/support/v7/app/l;Landroid/support/v7/view/b$a;)V
      37: astore        4
      39: aload_0
      40: getfield      #784                // Field e:Landroid/support/v7/app/f;
      43: ifnull        68
      46: aload_0
      47: invokevirtual #117                // Method q:()Z
      50: ifne          68
      53: aload_0
      54: getfield      #784                // Field e:Landroid/support/v7/app/f;
      57: aload         4
      59: invokeinterface #904,  2          // InterfaceMethod android/support/v7/app/f.onWindowStartingSupportActionMode:(Landroid/support/v7/view/b$a;)Landroid/support/v7/view/b;
      64: astore_1
      65: goto          70
      68: aconst_null
      69: astore_1
      70: aload_1
      71: ifnull        82
      74: aload_0
      75: aload_1
      76: putfield      #466                // Field m:Landroid/support/v7/view/b;
      79: goto          572
      82: aload_0
      83: getfield      #906                // Field n:Landroid/support/v7/widget/ActionBarContextView;
      86: astore_1
      87: iconst_1
      88: istore_3
      89: aload_1
      90: ifnonnull     352
      93: aload_0
      94: getfield      #561                // Field k:Z
      97: ifeq          312
     100: new           #352                // class android/util/TypedValue
     103: dup
     104: invokespecial #354                // Method android/util/TypedValue."<init>":()V
     107: astore        5
     109: aload_0
     110: getfield      #122                // Field a:Landroid/content/Context;
     113: invokevirtual #358                // Method android/content/Context.getTheme:()Landroid/content/res/Resources$Theme;
     116: astore_1
     117: aload_1
     118: getstatic     #363                // Field android/support/v7/a/a$a.actionBarTheme:I
     121: aload         5
     123: iconst_1
     124: invokevirtual #369                // Method android/content/res/Resources$Theme.resolveAttribute:(ILandroid/util/TypedValue;Z)Z
     127: pop
     128: aload         5
     130: getfield      #372                // Field android/util/TypedValue.resourceId:I
     133: ifeq          190
     136: aload_0
     137: getfield      #122                // Field a:Landroid/content/Context;
     140: invokevirtual #128                // Method android/content/Context.getResources:()Landroid/content/res/Resources;
     143: invokevirtual #375                // Method android/content/res/Resources.newTheme:()Landroid/content/res/Resources$Theme;
     146: astore        6
     148: aload         6
     150: aload_1
     151: invokevirtual #379                // Method android/content/res/Resources$Theme.setTo:(Landroid/content/res/Resources$Theme;)V
     154: aload         6
     156: aload         5
     158: getfield      #372                // Field android/util/TypedValue.resourceId:I
     161: iconst_1
     162: invokevirtual #383                // Method android/content/res/Resources$Theme.applyStyle:(IZ)V
     165: new           #388                // class android/support/v7/view/d
     168: dup
     169: aload_0
     170: getfield      #122                // Field a:Landroid/content/Context;
     173: iconst_0
     174: invokespecial #391                // Method android/support/v7/view/d."<init>":(Landroid/content/Context;I)V
     177: astore_1
     178: aload_1
     179: invokevirtual #358                // Method android/content/Context.getTheme:()Landroid/content/res/Resources$Theme;
     182: aload         6
     184: invokevirtual #379                // Method android/content/res/Resources$Theme.setTo:(Landroid/content/res/Resources$Theme;)V
     187: goto          195
     190: aload_0
     191: getfield      #122                // Field a:Landroid/content/Context;
     194: astore_1
     195: aload_0
     196: new           #908                // class android/support/v7/widget/ActionBarContextView
     199: dup
     200: aload_1
     201: invokespecial #909                // Method android/support/v7/widget/ActionBarContextView."<init>":(Landroid/content/Context;)V
     204: putfield      #906                // Field n:Landroid/support/v7/widget/ActionBarContextView;
     207: aload_0
     208: new           #911                // class android/widget/PopupWindow
     211: dup
     212: aload_1
     213: aconst_null
     214: getstatic     #914                // Field android/support/v7/a/a$a.actionModePopupWindowStyle:I
     217: invokespecial #917                // Method android/widget/PopupWindow."<init>":(Landroid/content/Context;Landroid/util/AttributeSet;I)V
     220: putfield      #919                // Field o:Landroid/widget/PopupWindow;
     223: aload_0
     224: getfield      #919                // Field o:Landroid/widget/PopupWindow;
     227: iconst_2
     228: invokestatic  #924                // Method android/support/v4/widget/k.a:(Landroid/widget/PopupWindow;I)V
     231: aload_0
     232: getfield      #919                // Field o:Landroid/widget/PopupWindow;
     235: aload_0
     236: getfield      #906                // Field n:Landroid/support/v7/widget/ActionBarContextView;
     239: invokevirtual #925                // Method android/widget/PopupWindow.setContentView:(Landroid/view/View;)V
     242: aload_0
     243: getfield      #919                // Field o:Landroid/widget/PopupWindow;
     246: iconst_m1
     247: invokevirtual #928                // Method android/widget/PopupWindow.setWidth:(I)V
     250: aload_1
     251: invokevirtual #358                // Method android/content/Context.getTheme:()Landroid/content/res/Resources$Theme;
     254: getstatic     #931                // Field android/support/v7/a/a$a.actionBarSize:I
     257: aload         5
     259: iconst_1
     260: invokevirtual #369                // Method android/content/res/Resources$Theme.resolveAttribute:(ILandroid/util/TypedValue;Z)Z
     263: pop
     264: aload         5
     266: getfield      #934                // Field android/util/TypedValue.data:I
     269: aload_1
     270: invokevirtual #128                // Method android/content/Context.getResources:()Landroid/content/res/Resources;
     273: invokevirtual #938                // Method android/content/res/Resources.getDisplayMetrics:()Landroid/util/DisplayMetrics;
     276: invokestatic  #942                // Method android/util/TypedValue.complexToDimensionPixelSize:(ILandroid/util/DisplayMetrics;)I
     279: istore_2
     280: aload_0
     281: getfield      #906                // Field n:Landroid/support/v7/widget/ActionBarContextView;
     284: iload_2
     285: invokevirtual #945                // Method android/support/v7/widget/ActionBarContextView.setContentHeight:(I)V
     288: aload_0
     289: getfield      #919                // Field o:Landroid/widget/PopupWindow;
     292: bipush        -2
     294: invokevirtual #948                // Method android/widget/PopupWindow.setHeight:(I)V
     297: aload_0
     298: new           #18                 // class android/support/v7/app/l$5
     301: dup
     302: aload_0
     303: invokespecial #949                // Method android/support/v7/app/l$5."<init>":(Landroid/support/v7/app/l;)V
     306: putfield      #951                // Field p:Ljava/lang/Runnable;
     309: goto          352
     312: aload_0
     313: getfield      #494                // Field y:Landroid/view/ViewGroup;
     316: getstatic     #954                // Field android/support/v7/a/a$f.action_mode_bar_stub:I
     319: invokevirtual #593                // Method android/view/ViewGroup.findViewById:(I)Landroid/view/View;
     322: checkcast     #956                // class android/support/v7/widget/ViewStubCompat
     325: astore_1
     326: aload_1
     327: ifnull        352
     330: aload_1
     331: aload_0
     332: invokevirtual #318                // Method o:()Landroid/content/Context;
     335: invokestatic  #567                // Method android/view/LayoutInflater.from:(Landroid/content/Context;)Landroid/view/LayoutInflater;
     338: invokevirtual #960                // Method android/support/v7/widget/ViewStubCompat.setLayoutInflater:(Landroid/view/LayoutInflater;)V
     341: aload_0
     342: aload_1
     343: invokevirtual #962                // Method android/support/v7/widget/ViewStubCompat.a:()Landroid/view/View;
     346: checkcast     #908                // class android/support/v7/widget/ActionBarContextView
     349: putfield      #906                // Field n:Landroid/support/v7/widget/ActionBarContextView;
     352: aload_0
     353: getfield      #906                // Field n:Landroid/support/v7/widget/ActionBarContextView;
     356: ifnull        572
     359: aload_0
     360: invokevirtual #901                // Method u:()V
     363: aload_0
     364: getfield      #906                // Field n:Landroid/support/v7/widget/ActionBarContextView;
     367: invokevirtual #963                // Method android/support/v7/widget/ActionBarContextView.c:()V
     370: aload_0
     371: getfield      #906                // Field n:Landroid/support/v7/widget/ActionBarContextView;
     374: invokevirtual #966                // Method android/support/v7/widget/ActionBarContextView.getContext:()Landroid/content/Context;
     377: astore_1
     378: aload_0
     379: getfield      #906                // Field n:Landroid/support/v7/widget/ActionBarContextView;
     382: astore        5
     384: aload_0
     385: getfield      #919                // Field o:Landroid/widget/PopupWindow;
     388: ifnonnull     394
     391: goto          396
     394: iconst_0
     395: istore_3
     396: new           #968                // class android/support/v7/view/e
     399: dup
     400: aload_1
     401: aload         5
     403: aload         4
     405: iload_3
     406: invokespecial #971                // Method android/support/v7/view/e."<init>":(Landroid/content/Context;Landroid/support/v7/widget/ActionBarContextView;Landroid/support/v7/view/b$a;Z)V
     409: astore_1
     410: aload         4
     412: aload_1
     413: aload_1
     414: invokevirtual #974                // Method android/support/v7/view/b.b:()Landroid/view/Menu;
     417: invokeinterface #979,  3          // InterfaceMethod android/support/v7/view/b$a.a:(Landroid/support/v7/view/b;Landroid/view/Menu;)Z
     422: ifeq          567
     425: aload_1
     426: invokevirtual #981                // Method android/support/v7/view/b.d:()V
     429: aload_0
     430: getfield      #906                // Field n:Landroid/support/v7/widget/ActionBarContextView;
     433: aload_1
     434: invokevirtual #983                // Method android/support/v7/widget/ActionBarContextView.a:(Landroid/support/v7/view/b;)V
     437: aload_0
     438: aload_1
     439: putfield      #466                // Field m:Landroid/support/v7/view/b;
     442: aload_0
     443: invokevirtual #985                // Method t:()Z
     446: ifeq          491
     449: aload_0
     450: getfield      #906                // Field n:Landroid/support/v7/widget/ActionBarContextView;
     453: fconst_0
     454: invokevirtual #989                // Method android/support/v7/widget/ActionBarContextView.setAlpha:(F)V
     457: aload_0
     458: aload_0
     459: getfield      #906                // Field n:Landroid/support/v7/widget/ActionBarContextView;
     462: invokestatic  #992                // Method android/support/v4/view/s.k:(Landroid/view/View;)Landroid/support/v4/view/x;
     465: fconst_1
     466: invokevirtual #997                // Method android/support/v4/view/x.a:(F)Landroid/support/v4/view/x;
     469: putfield      #97                 // Field q:Landroid/support/v4/view/x;
     472: aload_0
     473: getfield      #97                 // Field q:Landroid/support/v4/view/x;
     476: new           #22                 // class android/support/v7/app/l$6
     479: dup
     480: aload_0
     481: invokespecial #998                // Method android/support/v7/app/l$6."<init>":(Landroid/support/v7/app/l;)V
     484: invokevirtual #1001               // Method android/support/v4/view/x.a:(Landroid/support/v4/view/y;)Landroid/support/v4/view/x;
     487: pop
     488: goto          542
     491: aload_0
     492: getfield      #906                // Field n:Landroid/support/v7/widget/ActionBarContextView;
     495: fconst_1
     496: invokevirtual #989                // Method android/support/v7/widget/ActionBarContextView.setAlpha:(F)V
     499: aload_0
     500: getfield      #906                // Field n:Landroid/support/v7/widget/ActionBarContextView;
     503: iconst_0
     504: invokevirtual #1004               // Method android/support/v7/widget/ActionBarContextView.setVisibility:(I)V
     507: aload_0
     508: getfield      #906                // Field n:Landroid/support/v7/widget/ActionBarContextView;
     511: bipush        32
     513: invokevirtual #1007               // Method android/support/v7/widget/ActionBarContextView.sendAccessibilityEvent:(I)V
     516: aload_0
     517: getfield      #906                // Field n:Landroid/support/v7/widget/ActionBarContextView;
     520: invokevirtual #1008               // Method android/support/v7/widget/ActionBarContextView.getParent:()Landroid/view/ViewParent;
     523: instanceof    #176                // class android/view/View
     526: ifeq          542
     529: aload_0
     530: getfield      #906                // Field n:Landroid/support/v7/widget/ActionBarContextView;
     533: invokevirtual #1008               // Method android/support/v7/widget/ActionBarContextView.getParent:()Landroid/view/ViewParent;
     536: checkcast     #176                // class android/view/View
     539: invokestatic  #1010               // Method android/support/v4/view/s.o:(Landroid/view/View;)V
     542: aload_0
     543: getfield      #919                // Field o:Landroid/widget/PopupWindow;
     546: ifnull        572
     549: aload_0
     550: getfield      #291                // Field b:Landroid/view/Window;
     553: invokevirtual #297                // Method android/view/Window.getDecorView:()Landroid/view/View;
     556: aload_0
     557: getfield      #951                // Field p:Ljava/lang/Runnable;
     560: invokevirtual #1013               // Method android/view/View.post:(Ljava/lang/Runnable;)Z
     563: pop
     564: goto          572
     567: aload_0
     568: aconst_null
     569: putfield      #466                // Field m:Landroid/support/v7/view/b;
     572: aload_0
     573: getfield      #466                // Field m:Landroid/support/v7/view/b;
     576: ifnull        599
     579: aload_0
     580: getfield      #784                // Field e:Landroid/support/v7/app/f;
     583: ifnull        599
     586: aload_0
     587: getfield      #784                // Field e:Landroid/support/v7/app/f;
     590: aload_0
     591: getfield      #466                // Field m:Landroid/support/v7/view/b;
     594: invokeinterface #790,  2          // InterfaceMethod android/support/v7/app/f.onSupportActionModeStarted:(Landroid/support/v7/view/b;)V
     599: aload_0
     600: getfield      #466                // Field m:Landroid/support/v7/view/b;
     603: areturn
     604: astore_1
     605: goto          68
    Exception table:
       from    to  target type
          53    65   604   Class java/lang/AbstractMethodError

  public android.view.View b(android.view.View, java.lang.String, android.content.Context, android.util.AttributeSet);
    Code:
       0: aload_0
       1: getfield      #1017               // Field L:Landroid/support/v7/app/AppCompatViewInflater;
       4: astore        6
       6: iconst_0
       7: istore        5
       9: aload         6
      11: ifnonnull     161
      14: aload_0
      15: getfield      #122                // Field a:Landroid/content/Context;
      18: getstatic     #519                // Field android/support/v7/a/a$j.AppCompatTheme:[I
      21: invokevirtual #523                // Method android/content/Context.obtainStyledAttributes:([I)Landroid/content/res/TypedArray;
      24: getstatic     #1020               // Field android/support/v7/a/a$j.AppCompatTheme_viewInflaterClass:I
      27: invokevirtual #1024               // Method android/content/res/TypedArray.getString:(I)Ljava/lang/String;
      30: astore        6
      32: aload         6
      34: ifnull        146
      37: ldc_w         #1026               // class android/support/v7/app/AppCompatViewInflater
      40: invokevirtual #1031               // Method java/lang/Class.getName:()Ljava/lang/String;
      43: aload         6
      45: invokevirtual #1037               // Method java/lang/String.equals:(Ljava/lang/Object;)Z
      48: ifeq          54
      51: goto          146
      54: aload_0
      55: aload         6
      57: invokestatic  #1041               // Method java/lang/Class.forName:(Ljava/lang/String;)Ljava/lang/Class;
      60: iconst_0
      61: anewarray     #1028               // class java/lang/Class
      64: invokevirtual #1045               // Method java/lang/Class.getDeclaredConstructor:([Ljava/lang/Class;)Ljava/lang/reflect/Constructor;
      67: iconst_0
      68: anewarray     #1047               // class java/lang/Object
      71: invokevirtual #1053               // Method java/lang/reflect/Constructor.newInstance:([Ljava/lang/Object;)Ljava/lang/Object;
      74: checkcast     #1026               // class android/support/v7/app/AppCompatViewInflater
      77: putfield      #1017               // Field L:Landroid/support/v7/app/AppCompatViewInflater;
      80: goto          161
      83: astore        7
      85: new           #624                // class java/lang/StringBuilder
      88: dup
      89: invokespecial #625                // Method java/lang/StringBuilder."<init>":()V
      92: astore        8
      94: aload         8
      96: ldc_w         #1055               // String Failed to instantiate custom view inflater
      99: invokevirtual #631                // Method java/lang/StringBuilder.append:(Ljava/lang/String;)Ljava/lang/StringBuilder;
     102: pop
     103: aload         8
     105: aload         6
     107: invokevirtual #631                // Method java/lang/StringBuilder.append:(Ljava/lang/String;)Ljava/lang/StringBuilder;
     110: pop
     111: aload         8
     113: ldc_w         #1057               // String . Falling back to default.
     116: invokevirtual #631                // Method java/lang/StringBuilder.append:(Ljava/lang/String;)Ljava/lang/StringBuilder;
     119: pop
     120: ldc_w         #475                // String AppCompatDelegate
     123: aload         8
     125: invokevirtual #650                // Method java/lang/StringBuilder.toString:()Ljava/lang/String;
     128: aload         7
     130: invokestatic  #1060               // Method android/util/Log.i:(Ljava/lang/String;Ljava/lang/String;Ljava/lang/Throwable;)I
     133: pop
     134: new           #1026               // class android/support/v7/app/AppCompatViewInflater
     137: dup
     138: invokespecial #1061               // Method android/support/v7/app/AppCompatViewInflater."<init>":()V
     141: astore        6
     143: goto          155
     146: new           #1026               // class android/support/v7/app/AppCompatViewInflater
     149: dup
     150: invokespecial #1061               // Method android/support/v7/app/AppCompatViewInflater."<init>":()V
     153: astore        6
     155: aload_0
     156: aload         6
     158: putfield      #1017               // Field L:Landroid/support/v7/app/AppCompatViewInflater;
     161: getstatic     #90                 // Field t:Z
     164: ifeq          208
     167: aload         4
     169: instanceof    #1063               // class org/xmlpull/v1/XmlPullParser
     172: ifeq          195
     175: aload         4
     177: checkcast     #1063               // class org/xmlpull/v1/XmlPullParser
     180: invokeinterface #1066,  1         // InterfaceMethod org/xmlpull/v1/XmlPullParser.getDepth:()I
     185: iconst_1
     186: if_icmple     205
     189: iconst_1
     190: istore        5
     192: goto          205
     195: aload_0
     196: aload_1
     197: checkcast     #349                // class android/view/ViewParent
     200: invokespecial #1068               // Method a:(Landroid/view/ViewParent;)Z
     203: istore        5
     205: goto          211
     208: iconst_0
     209: istore        5
     211: aload_0
     212: getfield      #1017               // Field L:Landroid/support/v7/app/AppCompatViewInflater;
     215: aload_1
     216: aload_2
     217: aload_3
     218: aload         4
     220: iload         5
     222: getstatic     #90                 // Field t:Z
     225: iconst_1
     226: invokestatic  #1071               // Method android/support/v7/widget/bu.a:()Z
     229: invokevirtual #1074               // Method android/support/v7/app/AppCompatViewInflater.a:(Landroid/view/View;Ljava/lang/String;Landroid/content/Context;Landroid/util/AttributeSet;ZZZZ)Landroid/view/View;
     232: areturn
    Exception table:
       from    to  target type
          54    80    83   Class java/lang/Throwable

  public void b(int);
    Code:
       0: aload_0
       1: invokespecial #794                // Method x:()V
       4: aload_0
       5: getfield      #494                // Field y:Landroid/view/ViewGroup;
       8: ldc_w         #668                // int 16908290
      11: invokevirtual #593                // Method android/view/ViewGroup.findViewById:(I)Landroid/view/View;
      14: checkcast     #190                // class android/view/ViewGroup
      17: astore_2
      18: aload_2
      19: invokevirtual #197                // Method android/view/ViewGroup.removeAllViews:()V
      22: aload_0
      23: getfield      #122                // Field a:Landroid/content/Context;
      26: invokestatic  #567                // Method android/view/LayoutInflater.from:(Landroid/content/Context;)Landroid/view/LayoutInflater;
      29: iload_1
      30: aload_2
      31: invokevirtual #578                // Method android/view/LayoutInflater.inflate:(ILandroid/view/ViewGroup;)Landroid/view/View;
      34: pop
      35: aload_0
      36: getfield      #800                // Field c:Landroid/view/Window$Callback;
      39: invokeinterface #869,  1          // InterfaceMethod android/view/Window$Callback.onContentChanged:()V
      44: return

  public void b(android.os.Bundle);
    Code:
       0: aload_0
       1: invokespecial #794                // Method x:()V
       4: return

  void b(android.support.v7.view.menu.h);
    Code:
       0: aload_0
       1: getfield      #1076               // Field D:Z
       4: ifeq          8
       7: return
       8: aload_0
       9: iconst_1
      10: putfield      #1076               // Field D:Z
      13: aload_0
      14: getfield      #258                // Field u:Landroid/support/v7/widget/ak;
      17: invokeinterface #1078,  1         // InterfaceMethod android/support/v7/widget/ak.k:()V
      22: aload_0
      23: invokevirtual #142                // Method r:()Landroid/view/Window$Callback;
      26: astore_2
      27: aload_2
      28: ifnull        47
      31: aload_0
      32: invokevirtual #117                // Method q:()Z
      35: ifne          47
      38: aload_2
      39: bipush        108
      41: aload_1
      42: invokeinterface #284,  3          // InterfaceMethod android/view/Window$Callback.onPanelClosed:(ILandroid/view/Menu;)V
      47: aload_0
      48: iconst_0
      49: putfield      #1076               // Field D:Z
      52: return

  public void b(android.view.View, android.view.ViewGroup$LayoutParams);
    Code:
       0: aload_0
       1: invokespecial #794                // Method x:()V
       4: aload_0
       5: getfield      #494                // Field y:Landroid/view/ViewGroup;
       8: ldc_w         #668                // int 16908290
      11: invokevirtual #593                // Method android/view/ViewGroup.findViewById:(I)Landroid/view/View;
      14: checkcast     #190                // class android/view/ViewGroup
      17: aload_1
      18: aload_2
      19: invokevirtual #225                // Method android/view/ViewGroup.addView:(Landroid/view/View;Landroid/view/ViewGroup$LayoutParams;)V
      22: aload_0
      23: getfield      #800                // Field c:Landroid/view/Window$Callback;
      26: invokeinterface #869,  1          // InterfaceMethod android/view/Window$Callback.onContentChanged:()V
      31: return

  void b(java.lang.CharSequence);
    Code:
       0: aload_0
       1: getfield      #258                // Field u:Landroid/support/v7/widget/ak;
       4: ifnull        18
       7: aload_0
       8: getfield      #258                // Field u:Landroid/support/v7/widget/ak;
      11: aload_1
      12: invokeinterface #1081,  2         // InterfaceMethod android/support/v7/widget/ak.setWindowTitle:(Ljava/lang/CharSequence;)V
      17: return
      18: aload_0
      19: invokevirtual #410                // Method n:()Landroid/support/v7/app/a;
      22: ifnull        34
      25: aload_0
      26: invokevirtual #410                // Method n:()Landroid/support/v7/app/a;
      29: aload_1
      30: invokevirtual #1083               // Method android/support/v7/app/a.a:(Ljava/lang/CharSequence;)V
      33: return
      34: aload_0
      35: getfield      #658                // Field z:Landroid/widget/TextView;
      38: ifnull        49
      41: aload_0
      42: getfield      #658                // Field z:Landroid/widget/TextView;
      45: aload_1
      46: invokevirtual #1086               // Method android/widget/TextView.setText:(Ljava/lang/CharSequence;)V
      49: return

  boolean b(int, android.view.KeyEvent);
    Code:
       0: iload_1
       1: iconst_4
       2: if_icmpeq     22
       5: iload_1
       6: bipush        82
       8: if_icmpeq     13
      11: iconst_0
      12: ireturn
      13: aload_0
      14: iconst_0
      15: aload_2
      16: invokespecial #1088               // Method e:(ILandroid/view/KeyEvent;)Z
      19: pop
      20: iconst_1
      21: ireturn
      22: aload_0
      23: getfield      #1090               // Field G:Z
      26: istore_3
      27: aload_0
      28: iconst_0
      29: putfield      #1090               // Field G:Z
      32: aload_0
      33: iconst_0
      34: iconst_0
      35: invokevirtual #280                // Method a:(IZ)Landroid/support/v7/app/l$d;
      38: astore_2
      39: aload_2
      40: ifnull        62
      43: aload_2
      44: getfield      #114                // Field android/support/v7/app/l$d.o:Z
      47: ifeq          62
      50: iload_3
      51: ifne          60
      54: aload_0
      55: aload_2
      56: iconst_1
      57: invokevirtual #155                // Method a:(Landroid/support/v7/app/l$d;Z)V
      60: iconst_1
      61: ireturn
      62: aload_0
      63: invokevirtual #1092               // Method v:()Z
      66: ifeq          71
      69: iconst_1
      70: ireturn
      71: iconst_0
      72: ireturn

  boolean b(int, android.view.Menu);
    Code:
       0: iload_1
       1: bipush        108
       3: if_icmpne     22
       6: aload_0
       7: invokevirtual #777                // Method a:()Landroid/support/v7/app/a;
      10: astore_2
      11: aload_2
      12: ifnull        20
      15: aload_2
      16: iconst_1
      17: invokevirtual #809                // Method android/support/v7/app/a.g:(Z)V
      20: iconst_1
      21: ireturn
      22: iconst_0
      23: ireturn

  public boolean c(int);
    Code:
       0: aload_0
       1: iload_1
       2: invokespecial #1094               // Method h:(I)I
       5: istore_1
       6: aload_0
       7: getfield      #569                // Field l:Z
      10: ifeq          21
      13: iload_1
      14: bipush        108
      16: if_icmpne     21
      19: iconst_0
      20: ireturn
      21: aload_0
      22: getfield      #582                // Field h:Z
      25: ifeq          38
      28: iload_1
      29: iconst_1
      30: if_icmpne     38
      33: aload_0
      34: iconst_0
      35: putfield      #582                // Field h:Z
      38: iload_1
      39: lookupswitch  { // 6
                     1: 160
                     2: 149
                     5: 138
                    10: 127
                   108: 116
                   109: 105
               default: 96
          }
      96: aload_0
      97: getfield      #291                // Field b:Landroid/view/Window;
     100: iload_1
     101: invokevirtual #1097               // Method android/view/Window.requestFeature:(I)Z
     104: ireturn
     105: aload_0
     106: invokespecial #1099               // Method A:()V
     109: aload_0
     110: iconst_1
     111: putfield      #580                // Field i:Z
     114: iconst_1
     115: ireturn
     116: aload_0
     117: invokespecial #1099               // Method A:()V
     120: aload_0
     121: iconst_1
     122: putfield      #582                // Field h:Z
     125: iconst_1
     126: ireturn
     127: aload_0
     128: invokespecial #1099               // Method A:()V
     131: aload_0
     132: iconst_1
     133: putfield      #605                // Field j:Z
     136: iconst_1
     137: ireturn
     138: aload_0
     139: invokespecial #1099               // Method A:()V
     142: aload_0
     143: iconst_1
     144: putfield      #603                // Field C:Z
     147: iconst_1
     148: ireturn
     149: aload_0
     150: invokespecial #1099               // Method A:()V
     153: aload_0
     154: iconst_1
     155: putfield      #601                // Field B:Z
     158: iconst_1
     159: ireturn
     160: aload_0
     161: invokespecial #1099               // Method A:()V
     164: aload_0
     165: iconst_1
     166: putfield      #569                // Field l:Z
     169: iconst_1
     170: ireturn

  boolean c(int, android.view.KeyEvent);
    Code:
       0: iconst_1
       1: istore_3
       2: iload_1
       3: iconst_4
       4: if_icmpeq     24
       7: iload_1
       8: bipush        82
      10: if_icmpeq     15
      13: iconst_0
      14: ireturn
      15: aload_0
      16: iconst_0
      17: aload_2
      18: invokespecial #1101               // Method d:(ILandroid/view/KeyEvent;)Z
      21: pop
      22: iconst_1
      23: ireturn
      24: aload_2
      25: invokevirtual #1104               // Method android/view/KeyEvent.getFlags:()I
      28: sipush        128
      31: iand
      32: ifeq          38
      35: goto          40
      38: iconst_0
      39: istore_3
      40: aload_0
      41: iload_3
      42: putfield      #1090               // Field G:Z
      45: iconst_0
      46: ireturn

  public void d();
    Code:
       0: aload_0
       1: invokevirtual #777                // Method a:()Landroid/support/v7/app/a;
       4: astore_1
       5: aload_1
       6: ifnull        14
       9: aload_1
      10: iconst_0
      11: invokevirtual #1106               // Method android/support/v7/app/a.f:(Z)V
      14: return

  public void e();
    Code:
       0: aload_0
       1: invokevirtual #777                // Method a:()Landroid/support/v7/app/a;
       4: astore_1
       5: aload_1
       6: ifnull        14
       9: aload_1
      10: iconst_1
      11: invokevirtual #1106               // Method android/support/v7/app/a.f:(Z)V
      14: return

  void e(int);
    Code:
       0: aload_0
       1: aload_0
       2: iload_1
       3: iconst_1
       4: invokevirtual #280                // Method a:(IZ)Landroid/support/v7/app/l$d;
       7: iconst_1
       8: invokevirtual #155                // Method a:(Landroid/support/v7/app/l$d;Z)V
      11: return

  public void f();
    Code:
       0: aload_0
       1: invokevirtual #777                // Method a:()Landroid/support/v7/app/a;
       4: astore_1
       5: aload_1
       6: ifnull        17
       9: aload_1
      10: invokevirtual #1107               // Method android/support/v7/app/a.e:()Z
      13: ifeq          17
      16: return
      17: aload_0
      18: iconst_0
      19: invokespecial #513                // Method d:(I)V
      22: return

  void f(int);
    Code:
       0: aload_0
       1: iload_1
       2: iconst_1
       3: invokevirtual #280                // Method a:(IZ)Landroid/support/v7/app/l$d;
       6: astore_2
       7: aload_2
       8: getfield      #146                // Field android/support/v7/app/l$d.j:Landroid/support/v7/view/menu/h;
      11: ifnull        56
      14: new           #1109               // class android/os/Bundle
      17: dup
      18: invokespecial #1110               // Method android/os/Bundle."<init>":()V
      21: astore_3
      22: aload_2
      23: getfield      #146                // Field android/support/v7/app/l$d.j:Landroid/support/v7/view/menu/h;
      26: aload_3
      27: invokevirtual #1112               // Method android/support/v7/view/menu/h.c:(Landroid/os/Bundle;)V
      30: aload_3
      31: invokevirtual #1115               // Method android/os/Bundle.size:()I
      34: ifle          42
      37: aload_2
      38: aload_3
      39: putfield      #428                // Field android/support/v7/app/l$d.s:Landroid/os/Bundle;
      42: aload_2
      43: getfield      #146                // Field android/support/v7/app/l$d.j:Landroid/support/v7/view/menu/h;
      46: invokevirtual #422                // Method android/support/v7/view/menu/h.g:()V
      49: aload_2
      50: getfield      #146                // Field android/support/v7/app/l$d.j:Landroid/support/v7/view/menu/h;
      53: invokevirtual #1118               // Method android/support/v7/view/menu/h.clear:()V
      56: aload_2
      57: iconst_1
      58: putfield      #307                // Field android/support/v7/app/l$d.r:Z
      61: aload_2
      62: iconst_1
      63: putfield      #171                // Field android/support/v7/app/l$d.q:Z
      66: iload_1
      67: bipush        108
      69: if_icmpeq     76
      72: iload_1
      73: ifne          106
      76: aload_0
      77: getfield      #258                // Field u:Landroid/support/v7/widget/ak;
      80: ifnull        106
      83: aload_0
      84: iconst_0
      85: iconst_0
      86: invokevirtual #280                // Method a:(IZ)Landroid/support/v7/app/l$d;
      89: astore_2
      90: aload_2
      91: ifnull        106
      94: aload_2
      95: iconst_0
      96: putfield      #335                // Field android/support/v7/app/l$d.m:Z
      99: aload_0
     100: aload_2
     101: aconst_null
     102: invokespecial #166                // Method b:(Landroid/support/v7/app/l$d;Landroid/view/KeyEvent;)Z
     105: pop
     106: return

  int g(int);
    Code:
       0: aload_0
       1: getfield      #906                // Field n:Landroid/support/v7/widget/ActionBarContextView;
       4: astore        9
       6: iconst_0
       7: istore        7
       9: aload         9
      11: ifnull        368
      14: aload_0
      15: getfield      #906                // Field n:Landroid/support/v7/widget/ActionBarContextView;
      18: invokevirtual #1119               // Method android/support/v7/widget/ActionBarContextView.getLayoutParams:()Landroid/view/ViewGroup$LayoutParams;
      21: instanceof    #1121               // class android/view/ViewGroup$MarginLayoutParams
      24: ifeq          368
      27: aload_0
      28: getfield      #906                // Field n:Landroid/support/v7/widget/ActionBarContextView;
      31: invokevirtual #1119               // Method android/support/v7/widget/ActionBarContextView.getLayoutParams:()Landroid/view/ViewGroup$LayoutParams;
      34: checkcast     #1121               // class android/view/ViewGroup$MarginLayoutParams
      37: astore        9
      39: aload_0
      40: getfield      #906                // Field n:Landroid/support/v7/widget/ActionBarContextView;
      43: invokevirtual #1124               // Method android/support/v7/widget/ActionBarContextView.isShown:()Z
      46: istore        8
      48: iconst_1
      49: istore        5
      51: iload         8
      53: ifeq          310
      56: aload_0
      57: getfield      #1126               // Field J:Landroid/graphics/Rect;
      60: ifnonnull     85
      63: aload_0
      64: new           #1128               // class android/graphics/Rect
      67: dup
      68: invokespecial #1129               // Method android/graphics/Rect."<init>":()V
      71: putfield      #1126               // Field J:Landroid/graphics/Rect;
      74: aload_0
      75: new           #1128               // class android/graphics/Rect
      78: dup
      79: invokespecial #1129               // Method android/graphics/Rect."<init>":()V
      82: putfield      #1131               // Field K:Landroid/graphics/Rect;
      85: aload_0
      86: getfield      #1126               // Field J:Landroid/graphics/Rect;
      89: astore        10
      91: aload_0
      92: getfield      #1131               // Field K:Landroid/graphics/Rect;
      95: astore        11
      97: aload         10
      99: iconst_0
     100: iload_1
     101: iconst_0
     102: iconst_0
     103: invokevirtual #1134               // Method android/graphics/Rect.set:(IIII)V
     106: aload_0
     107: getfield      #494                // Field y:Landroid/view/ViewGroup;
     110: aload         10
     112: aload         11
     114: invokestatic  #1137               // Method android/support/v7/widget/bx.a:(Landroid/view/View;Landroid/graphics/Rect;Landroid/graphics/Rect;)V
     117: aload         11
     119: getfield      #1140               // Field android/graphics/Rect.top:I
     122: ifne          130
     125: iload_1
     126: istore_2
     127: goto          132
     130: iconst_0
     131: istore_2
     132: aload         9
     134: getfield      #1143               // Field android/view/ViewGroup$MarginLayoutParams.topMargin:I
     137: iload_2
     138: if_icmpeq     252
     141: aload         9
     143: iload_1
     144: putfield      #1143               // Field android/view/ViewGroup$MarginLayoutParams.topMargin:I
     147: aload_0
     148: getfield      #1145               // Field A:Landroid/view/View;
     151: ifnonnull     213
     154: aload_0
     155: new           #176                // class android/view/View
     158: dup
     159: aload_0
     160: getfield      #122                // Field a:Landroid/content/Context;
     163: invokespecial #1146               // Method android/view/View."<init>":(Landroid/content/Context;)V
     166: putfield      #1145               // Field A:Landroid/view/View;
     169: aload_0
     170: getfield      #1145               // Field A:Landroid/view/View;
     173: aload_0
     174: getfield      #122                // Field a:Landroid/content/Context;
     177: invokevirtual #128                // Method android/content/Context.getResources:()Landroid/content/res/Resources;
     180: getstatic     #1151               // Field android/support/v7/a/a$c.abc_input_method_navigation_guard:I
     183: invokevirtual #1154               // Method android/content/res/Resources.getColor:(I)I
     186: invokevirtual #1157               // Method android/view/View.setBackgroundColor:(I)V
     189: aload_0
     190: getfield      #494                // Field y:Landroid/view/ViewGroup;
     193: aload_0
     194: getfield      #1145               // Field A:Landroid/view/View;
     197: iconst_m1
     198: new           #182                // class android/view/ViewGroup$LayoutParams
     201: dup
     202: iconst_m1
     203: iload_1
     204: invokespecial #207                // Method android/view/ViewGroup$LayoutParams."<init>":(II)V
     207: invokevirtual #1160               // Method android/view/ViewGroup.addView:(Landroid/view/View;ILandroid/view/ViewGroup$LayoutParams;)V
     210: goto          246
     213: aload_0
     214: getfield      #1145               // Field A:Landroid/view/View;
     217: invokevirtual #180                // Method android/view/View.getLayoutParams:()Landroid/view/ViewGroup$LayoutParams;
     220: astore        10
     222: aload         10
     224: getfield      #1163               // Field android/view/ViewGroup$LayoutParams.height:I
     227: iload_1
     228: if_icmpeq     246
     231: aload         10
     233: iload_1
     234: putfield      #1163               // Field android/view/ViewGroup$LayoutParams.height:I
     237: aload_0
     238: getfield      #1145               // Field A:Landroid/view/View;
     241: aload         10
     243: invokevirtual #1167               // Method android/view/View.setLayoutParams:(Landroid/view/ViewGroup$LayoutParams;)V
     246: iconst_1
     247: istore        4
     249: goto          255
     252: iconst_0
     253: istore        4
     255: aload_0
     256: getfield      #1145               // Field A:Landroid/view/View;
     259: ifnull        265
     262: goto          268
     265: iconst_0
     266: istore        5
     268: iload         4
     270: istore        6
     272: iload         5
     274: istore_2
     275: iload_1
     276: istore_3
     277: aload_0
     278: getfield      #605                // Field j:Z
     281: ifne          341
     284: iload         4
     286: istore        6
     288: iload         5
     290: istore_2
     291: iload_1
     292: istore_3
     293: iload         5
     295: ifeq          341
     298: iconst_0
     299: istore_3
     300: iload         4
     302: istore        6
     304: iload         5
     306: istore_2
     307: goto          341
     310: aload         9
     312: getfield      #1143               // Field android/view/ViewGroup$MarginLayoutParams.topMargin:I
     315: ifeq          330
     318: aload         9
     320: iconst_0
     321: putfield      #1143               // Field android/view/ViewGroup$MarginLayoutParams.topMargin:I
     324: iconst_1
     325: istore        4
     327: goto          333
     330: iconst_0
     331: istore        4
     333: iconst_0
     334: istore_2
     335: iload_1
     336: istore_3
     337: iload         4
     339: istore        6
     341: iload_2
     342: istore        4
     344: iload_3
     345: istore_1
     346: iload         6
     348: ifeq          371
     351: aload_0
     352: getfield      #906                // Field n:Landroid/support/v7/widget/ActionBarContextView;
     355: aload         9
     357: invokevirtual #1168               // Method android/support/v7/widget/ActionBarContextView.setLayoutParams:(Landroid/view/ViewGroup$LayoutParams;)V
     360: iload_2
     361: istore        4
     363: iload_3
     364: istore_1
     365: goto          371
     368: iconst_0
     369: istore        4
     371: aload_0
     372: getfield      #1145               // Field A:Landroid/view/View;
     375: ifnull        404
     378: aload_0
     379: getfield      #1145               // Field A:Landroid/view/View;
     382: astore        9
     384: iload         4
     386: ifeq          395
     389: iload         7
     391: istore_2
     392: goto          398
     395: bipush        8
     397: istore_2
     398: aload         9
     400: iload_2
     401: invokevirtual #1169               // Method android/view/View.setVisibility:(I)V
     404: iload_1
     405: ireturn

  public void g();
    Code:
       0: aload_0
       1: getfield      #286                // Field r:Z
       4: ifeq          22
       7: aload_0
       8: getfield      #291                // Field b:Landroid/view/Window;
      11: invokevirtual #297                // Method android/view/Window.getDecorView:()Landroid/view/View;
      14: aload_0
      15: getfield      #102                // Field H:Ljava/lang/Runnable;
      18: invokevirtual #301                // Method android/view/View.removeCallbacks:(Ljava/lang/Runnable;)Z
      21: pop
      22: aload_0
      23: invokespecial #1170               // Method android/support/v7/app/h.g:()V
      26: aload_0
      27: getfield      #858                // Field f:Landroid/support/v7/app/a;
      30: ifnull        40
      33: aload_0
      34: getfield      #858                // Field f:Landroid/support/v7/app/a;
      37: invokevirtual #847                // Method android/support/v7/app/a.g:()V
      40: return

  public void i();
    Code:
       0: aload_0
       1: getfield      #122                // Field a:Landroid/content/Context;
       4: invokestatic  #567                // Method android/view/LayoutInflater.from:(Landroid/content/Context;)Landroid/view/LayoutInflater;
       7: astore_1
       8: aload_1
       9: invokevirtual #1174               // Method android/view/LayoutInflater.getFactory:()Landroid/view/LayoutInflater$Factory;
      12: ifnonnull     21
      15: aload_1
      16: aload_0
      17: invokestatic  #1179               // Method android/support/v4/view/f.b:(Landroid/view/LayoutInflater;Landroid/view/LayoutInflater$Factory2;)V
      20: return
      21: aload_1
      22: invokevirtual #1183               // Method android/view/LayoutInflater.getFactory2:()Landroid/view/LayoutInflater$Factory2;
      25: instanceof    #2                  // class android/support/v7/app/l
      28: ifne          41
      31: ldc_w         #475                // String AppCompatDelegate
      34: ldc_w         #1185               // String The Activity's LayoutInflater already has a Factory installed so we can not install AppCompat's
      37: invokestatic  #487                // Method android/util/Log.i:(Ljava/lang/String;Ljava/lang/String;)I
      40: pop
      41: return

  public void m();
    Code:
       0: aload_0
       1: invokespecial #794                // Method x:()V
       4: aload_0
       5: getfield      #582                // Field h:Z
       8: ifeq          102
      11: aload_0
      12: getfield      #858                // Field f:Landroid/support/v7/app/a;
      15: ifnull        19
      18: return
      19: aload_0
      20: getfield      #800                // Field c:Landroid/view/Window$Callback;
      23: instanceof    #822                // class android/app/Activity
      26: ifeq          56
      29: new           #841                // class android/support/v7/app/r
      32: dup
      33: aload_0
      34: getfield      #800                // Field c:Landroid/view/Window$Callback;
      37: checkcast     #822                // class android/app/Activity
      40: aload_0
      41: getfield      #580                // Field i:Z
      44: invokespecial #1188               // Method android/support/v7/app/r."<init>":(Landroid/app/Activity;Z)V
      47: astore_1
      48: aload_0
      49: aload_1
      50: putfield      #858                // Field f:Landroid/support/v7/app/a;
      53: goto          84
      56: aload_0
      57: getfield      #800                // Field c:Landroid/view/Window$Callback;
      60: instanceof    #1190               // class android/app/Dialog
      63: ifeq          84
      66: new           #841                // class android/support/v7/app/r
      69: dup
      70: aload_0
      71: getfield      #800                // Field c:Landroid/view/Window$Callback;
      74: checkcast     #1190               // class android/app/Dialog
      77: invokespecial #1193               // Method android/support/v7/app/r."<init>":(Landroid/app/Dialog;)V
      80: astore_1
      81: goto          48
      84: aload_0
      85: getfield      #858                // Field f:Landroid/support/v7/app/a;
      88: ifnull        102
      91: aload_0
      92: getfield      #858                // Field f:Landroid/support/v7/app/a;
      95: aload_0
      96: getfield      #829                // Field I:Z
      99: invokevirtual #831                // Method android/support/v7/app/a.e:(Z)V
     102: return

  public final android.view.View onCreateView(android.view.View, java.lang.String, android.content.Context, android.util.AttributeSet);
    Code:
       0: aload_0
       1: aload_1
       2: aload_2
       3: aload_3
       4: aload         4
       6: invokevirtual #1195               // Method a:(Landroid/view/View;Ljava/lang/String;Landroid/content/Context;Landroid/util/AttributeSet;)Landroid/view/View;
       9: astore        5
      11: aload         5
      13: ifnull        19
      16: aload         5
      18: areturn
      19: aload_0
      20: aload_1
      21: aload_2
      22: aload_3
      23: aload         4
      25: invokevirtual #1197               // Method b:(Landroid/view/View;Ljava/lang/String;Landroid/content/Context;Landroid/util/AttributeSet;)Landroid/view/View;
      28: areturn

  public android.view.View onCreateView(java.lang.String, android.content.Context, android.util.AttributeSet);
    Code:
       0: aload_0
       1: aconst_null
       2: aload_1
       3: aload_2
       4: aload_3
       5: invokevirtual #1199               // Method onCreateView:(Landroid/view/View;Ljava/lang/String;Landroid/content/Context;Landroid/util/AttributeSet;)Landroid/view/View;
       8: areturn

  final boolean t();
    Code:
       0: aload_0
       1: getfield      #104                // Field x:Z
       4: ifeq          26
       7: aload_0
       8: getfield      #494                // Field y:Landroid/view/ViewGroup;
      11: ifnull        26
      14: aload_0
      15: getfield      #494                // Field y:Landroid/view/ViewGroup;
      18: invokestatic  #1201               // Method android/support/v4/view/s.w:(Landroid/view/View;)Z
      21: ifeq          26
      24: iconst_1
      25: ireturn
      26: iconst_0
      27: ireturn

  void u();
    Code:
       0: aload_0
       1: getfield      #97                 // Field q:Landroid/support/v4/view/x;
       4: ifnull        14
       7: aload_0
       8: getfield      #97                 // Field q:Landroid/support/v4/view/x;
      11: invokevirtual #1203               // Method android/support/v4/view/x.b:()V
      14: return

  boolean v();
    Code:
       0: aload_0
       1: getfield      #466                // Field m:Landroid/support/v7/view/b;
       4: ifnull        16
       7: aload_0
       8: getfield      #466                // Field m:Landroid/support/v7/view/b;
      11: invokevirtual #772                // Method android/support/v7/view/b.c:()V
      14: iconst_1
      15: ireturn
      16: aload_0
      17: invokevirtual #777                // Method a:()Landroid/support/v7/app/a;
      20: astore_1
      21: aload_1
      22: ifnull        34
      25: aload_1
      26: invokevirtual #1204               // Method android/support/v7/app/a.f:()Z
      29: ifeq          34
      32: iconst_1
      33: ireturn
      34: iconst_0
      35: ireturn

  void w();
    Code:
       0: aload_0
       1: getfield      #258                // Field u:Landroid/support/v7/widget/ak;
       4: ifnull        16
       7: aload_0
       8: getfield      #258                // Field u:Landroid/support/v7/widget/ak;
      11: invokeinterface #1078,  1         // InterfaceMethod android/support/v7/widget/ak.k:()V
      16: aload_0
      17: getfield      #919                // Field o:Landroid/widget/PopupWindow;
      20: ifnull        60
      23: aload_0
      24: getfield      #291                // Field b:Landroid/view/Window;
      27: invokevirtual #297                // Method android/view/Window.getDecorView:()Landroid/view/View;
      30: aload_0
      31: getfield      #951                // Field p:Ljava/lang/Runnable;
      34: invokevirtual #301                // Method android/view/View.removeCallbacks:(Ljava/lang/Runnable;)Z
      37: pop
      38: aload_0
      39: getfield      #919                // Field o:Landroid/widget/PopupWindow;
      42: invokevirtual #1207               // Method android/widget/PopupWindow.isShowing:()Z
      45: ifeq          55
      48: aload_0
      49: getfield      #919                // Field o:Landroid/widget/PopupWindow;
      52: invokevirtual #1210               // Method android/widget/PopupWindow.dismiss:()V
      55: aload_0
      56: aconst_null
      57: putfield      #919                // Field o:Landroid/widget/PopupWindow;
      60: aload_0
      61: invokevirtual #901                // Method u:()V
      64: aload_0
      65: iconst_0
      66: iconst_0
      67: invokevirtual #280                // Method a:(IZ)Landroid/support/v7/app/l$d;
      70: astore_1
      71: aload_1
      72: ifnull        89
      75: aload_1
      76: getfield      #146                // Field android/support/v7/app/l$d.j:Landroid/support/v7/view/menu/h;
      79: ifnull        89
      82: aload_1
      83: getfield      #146                // Field android/support/v7/app/l$d.j:Landroid/support/v7/view/menu/h;
      86: invokevirtual #1213               // Method android/support/v7/view/menu/h.close:()V
      89: return
      90: astore_1
      91: goto          55
    Exception table:
       from    to  target type
          48    55    90   Class java/lang/IllegalArgumentException
}
