public class android.support.v7.app.r extends android.support.v7.app.a implements android.support.v7.widget.ActionBarOverlayLayout$a {
  static final boolean s;

  android.content.Context a;

  android.support.v7.widget.ActionBarOverlayLayout b;

  android.support.v7.widget.ActionBarContainer c;

  android.support.v7.widget.al d;

  android.support.v7.widget.ActionBarContextView e;

  android.view.View f;

  android.support.v7.widget.bh g;

  android.support.v7.app.r$a h;

  android.support.v7.view.b i;

  android.support.v7.view.b$a j;

  boolean k;

  boolean l;

  boolean m;

  android.support.v7.view.h n;

  boolean o;

  final android.support.v4.view.y p;

  final android.support.v4.view.y q;

  final android.support.v4.view.aa r;

  static {};
    Code:
       0: new           #74                 // class android/view/animation/AccelerateInterpolator
       3: dup
       4: invokespecial #77                 // Method android/view/animation/AccelerateInterpolator."<init>":()V
       7: putstatic     #79                 // Field t:Landroid/view/animation/Interpolator;
      10: new           #81                 // class android/view/animation/DecelerateInterpolator
      13: dup
      14: invokespecial #82                 // Method android/view/animation/DecelerateInterpolator."<init>":()V
      17: putstatic     #84                 // Field u:Landroid/view/animation/Interpolator;
      20: return

  public android.support.v7.app.r(android.app.Activity, boolean);
    Code:
       0: aload_0
       1: invokespecial #87                 // Method android/support/v7/app/a."<init>":()V
       4: aload_0
       5: new           #89                 // class java/util/ArrayList
       8: dup
       9: invokespecial #90                 // Method java/util/ArrayList."<init>":()V
      12: putfield      #92                 // Field y:Ljava/util/ArrayList;
      15: aload_0
      16: iconst_m1
      17: putfield      #94                 // Field z:I
      20: aload_0
      21: new           #89                 // class java/util/ArrayList
      24: dup
      25: invokespecial #90                 // Method java/util/ArrayList."<init>":()V
      28: putfield      #96                 // Field C:Ljava/util/ArrayList;
      31: aload_0
      32: iconst_0
      33: putfield      #98                 // Field E:I
      36: aload_0
      37: iconst_1
      38: putfield      #100                // Field k:Z
      41: aload_0
      42: iconst_1
      43: putfield      #102                // Field G:Z
      46: aload_0
      47: new           #8                  // class android/support/v7/app/r$1
      50: dup
      51: aload_0
      52: invokespecial #105                // Method android/support/v7/app/r$1."<init>":(Landroid/support/v7/app/r;)V
      55: putfield      #107                // Field p:Landroid/support/v4/view/y;
      58: aload_0
      59: new           #10                 // class android/support/v7/app/r$2
      62: dup
      63: aload_0
      64: invokespecial #108                // Method android/support/v7/app/r$2."<init>":(Landroid/support/v7/app/r;)V
      67: putfield      #110                // Field q:Landroid/support/v4/view/y;
      70: aload_0
      71: new           #12                 // class android/support/v7/app/r$3
      74: dup
      75: aload_0
      76: invokespecial #111                // Method android/support/v7/app/r$3."<init>":(Landroid/support/v7/app/r;)V
      79: putfield      #113                // Field r:Landroid/support/v4/view/aa;
      82: aload_0
      83: aload_1
      84: putfield      #115                // Field w:Landroid/app/Activity;
      87: aload_1
      88: invokevirtual #121                // Method android/app/Activity.getWindow:()Landroid/view/Window;
      91: invokevirtual #127                // Method android/view/Window.getDecorView:()Landroid/view/View;
      94: astore_1
      95: aload_0
      96: aload_1
      97: invokespecial #130                // Method a:(Landroid/view/View;)V
     100: iload_2
     101: ifne          114
     104: aload_0
     105: aload_1
     106: ldc           #131                // int 16908290
     108: invokevirtual #137                // Method android/view/View.findViewById:(I)Landroid/view/View;
     111: putfield      #139                // Field f:Landroid/view/View;
     114: return

  public android.support.v7.app.r(android.app.Dialog);
    Code:
       0: aload_0
       1: invokespecial #87                 // Method android/support/v7/app/a."<init>":()V
       4: aload_0
       5: new           #89                 // class java/util/ArrayList
       8: dup
       9: invokespecial #90                 // Method java/util/ArrayList."<init>":()V
      12: putfield      #92                 // Field y:Ljava/util/ArrayList;
      15: aload_0
      16: iconst_m1
      17: putfield      #94                 // Field z:I
      20: aload_0
      21: new           #89                 // class java/util/ArrayList
      24: dup
      25: invokespecial #90                 // Method java/util/ArrayList."<init>":()V
      28: putfield      #96                 // Field C:Ljava/util/ArrayList;
      31: aload_0
      32: iconst_0
      33: putfield      #98                 // Field E:I
      36: aload_0
      37: iconst_1
      38: putfield      #100                // Field k:Z
      41: aload_0
      42: iconst_1
      43: putfield      #102                // Field G:Z
      46: aload_0
      47: new           #8                  // class android/support/v7/app/r$1
      50: dup
      51: aload_0
      52: invokespecial #105                // Method android/support/v7/app/r$1."<init>":(Landroid/support/v7/app/r;)V
      55: putfield      #107                // Field p:Landroid/support/v4/view/y;
      58: aload_0
      59: new           #10                 // class android/support/v7/app/r$2
      62: dup
      63: aload_0
      64: invokespecial #108                // Method android/support/v7/app/r$2."<init>":(Landroid/support/v7/app/r;)V
      67: putfield      #110                // Field q:Landroid/support/v4/view/y;
      70: aload_0
      71: new           #12                 // class android/support/v7/app/r$3
      74: dup
      75: aload_0
      76: invokespecial #111                // Method android/support/v7/app/r$3."<init>":(Landroid/support/v7/app/r;)V
      79: putfield      #113                // Field r:Landroid/support/v4/view/aa;
      82: aload_0
      83: aload_1
      84: putfield      #142                // Field x:Landroid/app/Dialog;
      87: aload_0
      88: aload_1
      89: invokevirtual #145                // Method android/app/Dialog.getWindow:()Landroid/view/Window;
      92: invokevirtual #127                // Method android/view/Window.getDecorView:()Landroid/view/View;
      95: invokespecial #130                // Method a:(Landroid/view/View;)V
      98: return

  static boolean a(boolean, boolean, boolean);
    Code:
       0: iload_2
       1: ifeq          6
       4: iconst_1
       5: ireturn
       6: iload_0
       7: ifne          19
      10: iload_1
      11: ifeq          17
      14: goto          19
      17: iconst_1
      18: ireturn
      19: iconst_0
      20: ireturn

  public int a();
    Code:
       0: aload_0
       1: getfield      #166                // Field d:Landroid/support/v7/widget/al;
       4: invokeinterface #190,  1          // InterfaceMethod android/support/v7/widget/al.o:()I
       9: ireturn

  public android.support.v7.view.b a(android.support.v7.view.b$a);
    Code:
       0: aload_0
       1: getfield      #343                // Field h:Landroid/support/v7/app/r$a;
       4: ifnull        14
       7: aload_0
       8: getfield      #343                // Field h:Landroid/support/v7/app/r$a;
      11: invokevirtual #345                // Method android/support/v7/app/r$a.c:()V
      14: aload_0
      15: getfield      #154                // Field b:Landroid/support/v7/widget/ActionBarOverlayLayout;
      18: iconst_0
      19: invokevirtual #348                // Method android/support/v7/widget/ActionBarOverlayLayout.setHideOnContentScrollEnabled:(Z)V
      22: aload_0
      23: getfield      #173                // Field e:Landroid/support/v7/widget/ActionBarContextView;
      26: invokevirtual #349                // Method android/support/v7/widget/ActionBarContextView.c:()V
      29: new           #14                 // class android/support/v7/app/r$a
      32: dup
      33: aload_0
      34: aload_0
      35: getfield      #173                // Field e:Landroid/support/v7/widget/ActionBarContextView;
      38: invokevirtual #352                // Method android/support/v7/widget/ActionBarContextView.getContext:()Landroid/content/Context;
      41: aload_1
      42: invokespecial #355                // Method android/support/v7/app/r$a."<init>":(Landroid/support/v7/app/r;Landroid/content/Context;Landroid/support/v7/view/b$a;)V
      45: astore_1
      46: aload_1
      47: invokevirtual #357                // Method android/support/v7/app/r$a.e:()Z
      50: ifeq          86
      53: aload_0
      54: aload_1
      55: putfield      #343                // Field h:Landroid/support/v7/app/r$a;
      58: aload_1
      59: invokevirtual #359                // Method android/support/v7/app/r$a.d:()V
      62: aload_0
      63: getfield      #173                // Field e:Landroid/support/v7/widget/ActionBarContextView;
      66: aload_1
      67: invokevirtual #362                // Method android/support/v7/widget/ActionBarContextView.a:(Landroid/support/v7/view/b;)V
      70: aload_0
      71: iconst_1
      72: invokevirtual #364                // Method k:(Z)V
      75: aload_0
      76: getfield      #173                // Field e:Landroid/support/v7/widget/ActionBarContextView;
      79: bipush        32
      81: invokevirtual #367                // Method android/support/v7/widget/ActionBarContextView.sendAccessibilityEvent:(I)V
      84: aload_1
      85: areturn
      86: aconst_null
      87: areturn

  public void a(float);
    Code:
       0: aload_0
       1: getfield      #180                // Field c:Landroid/support/v7/widget/ActionBarContainer;
       4: fload_1
       5: invokestatic  #370                // Method android/support/v4/view/s.a:(Landroid/view/View;F)V
       8: return

  public void a(int);
    Code:
       0: aload_0
       1: getfield      #166                // Field d:Landroid/support/v7/widget/al;
       4: iload_1
       5: invokeinterface #372,  2          // InterfaceMethod android/support/v7/widget/al.d:(I)V
      10: return

  public void a(int, int);
    Code:
       0: aload_0
       1: getfield      #166                // Field d:Landroid/support/v7/widget/al;
       4: invokeinterface #190,  1          // InterfaceMethod android/support/v7/widget/al.o:()I
       9: istore_3
      10: iload_2
      11: iconst_4
      12: iand
      13: ifeq          21
      16: aload_0
      17: iconst_1
      18: putfield      #192                // Field A:Z
      21: aload_0
      22: getfield      #166                // Field d:Landroid/support/v7/widget/al;
      25: iload_1
      26: iload_2
      27: iand
      28: iload_2
      29: iconst_m1
      30: ixor
      31: iload_3
      32: iand
      33: ior
      34: invokeinterface #375,  2          // InterfaceMethod android/support/v7/widget/al.c:(I)V
      39: return

  public void a(android.content.res.Configuration);
    Code:
       0: aload_0
       1: aload_0
       2: getfield      #187                // Field a:Landroid/content/Context;
       5: invokestatic  #197                // Method android/support/v7/view/a.a:(Landroid/content/Context;)Landroid/support/v7/view/a;
       8: invokevirtual #205                // Method android/support/v7/view/a.d:()Z
      11: invokespecial #207                // Method l:(Z)V
      14: return

  public void a(android.graphics.drawable.Drawable);
    Code:
       0: aload_0
       1: getfield      #166                // Field d:Landroid/support/v7/widget/al;
       4: aload_1
       5: invokeinterface #379,  2          // InterfaceMethod android/support/v7/widget/al.b:(Landroid/graphics/drawable/Drawable;)V
      10: return

  public void a(java.lang.CharSequence);
    Code:
       0: aload_0
       1: getfield      #166                // Field d:Landroid/support/v7/widget/al;
       4: aload_1
       5: invokeinterface #382,  2          // InterfaceMethod android/support/v7/widget/al.a:(Ljava/lang/CharSequence;)V
      10: return

  public void a(boolean);
    Code:
       0: iload_1
       1: ifeq          9
       4: iconst_2
       5: istore_2
       6: goto          11
       9: iconst_0
      10: istore_2
      11: aload_0
      12: iload_2
      13: iconst_2
      14: invokevirtual #384                // Method a:(II)V
      17: return

  public boolean a(int, android.view.KeyEvent);
    Code:
       0: aload_0
       1: getfield      #343                // Field h:Landroid/support/v7/app/r$a;
       4: ifnonnull     9
       7: iconst_0
       8: ireturn
       9: aload_0
      10: getfield      #343                // Field h:Landroid/support/v7/app/r$a;
      13: invokevirtual #388                // Method android/support/v7/app/r$a.b:()Landroid/view/Menu;
      16: astore        5
      18: aload         5
      20: ifnull        79
      23: aload_2
      24: ifnull        35
      27: aload_2
      28: invokevirtual #393                // Method android/view/KeyEvent.getDeviceId:()I
      31: istore_3
      32: goto          37
      35: iconst_m1
      36: istore_3
      37: iload_3
      38: invokestatic  #399                // Method android/view/KeyCharacterMap.load:(I)Landroid/view/KeyCharacterMap;
      41: invokevirtual #402                // Method android/view/KeyCharacterMap.getKeyboardType:()I
      44: istore_3
      45: iconst_1
      46: istore        4
      48: iload_3
      49: iconst_1
      50: if_icmpeq     56
      53: goto          59
      56: iconst_0
      57: istore        4
      59: aload         5
      61: iload         4
      63: invokeinterface #407,  2          // InterfaceMethod android/view/Menu.setQwertyMode:(Z)V
      68: aload         5
      70: iload_1
      71: aload_2
      72: iconst_0
      73: invokeinterface #411,  4          // InterfaceMethod android/view/Menu.performShortcut:(ILandroid/view/KeyEvent;I)Z
      78: ireturn
      79: iconst_0
      80: ireturn

  public android.content.Context b();
    Code:
       0: aload_0
       1: getfield      #413                // Field v:Landroid/content/Context;
       4: ifnonnull     67
       7: new           #415                // class android/util/TypedValue
      10: dup
      11: invokespecial #416                // Method android/util/TypedValue."<init>":()V
      14: astore_2
      15: aload_0
      16: getfield      #187                // Field a:Landroid/content/Context;
      19: invokevirtual #420                // Method android/content/Context.getTheme:()Landroid/content/res/Resources$Theme;
      22: getstatic     #423                // Field android/support/v7/a/a$a.actionBarWidgetTheme:I
      25: aload_2
      26: iconst_1
      27: invokevirtual #429                // Method android/content/res/Resources$Theme.resolveAttribute:(ILandroid/util/TypedValue;Z)Z
      30: pop
      31: aload_2
      32: getfield      #432                // Field android/util/TypedValue.resourceId:I
      35: istore_1
      36: iload_1
      37: ifeq          59
      40: aload_0
      41: new           #434                // class android/view/ContextThemeWrapper
      44: dup
      45: aload_0
      46: getfield      #187                // Field a:Landroid/content/Context;
      49: iload_1
      50: invokespecial #437                // Method android/view/ContextThemeWrapper."<init>":(Landroid/content/Context;I)V
      53: putfield      #413                // Field v:Landroid/content/Context;
      56: goto          67
      59: aload_0
      60: aload_0
      61: getfield      #187                // Field a:Landroid/content/Context;
      64: putfield      #413                // Field v:Landroid/content/Context;
      67: aload_0
      68: getfield      #413                // Field v:Landroid/content/Context;
      71: areturn

  public void b(int);
    Code:
       0: aload_0
       1: getfield      #166                // Field d:Landroid/support/v7/widget/al;
       4: iload_1
       5: invokeinterface #439,  2          // InterfaceMethod android/support/v7/widget/al.e:(I)V
      10: return

  public void b(boolean);
    Code:
       0: iload_1
       1: ifeq          9
       4: iconst_4
       5: istore_2
       6: goto          11
       9: iconst_0
      10: istore_2
      11: aload_0
      12: iload_2
      13: iconst_4
      14: invokevirtual #384                // Method a:(II)V
      17: return

  public void c(int);
    Code:
       0: aload_0
       1: iload_1
       2: putfield      #98                 // Field E:I
       5: return

  public void c(boolean);
    Code:
       0: aload_0
       1: getfield      #166                // Field d:Landroid/support/v7/widget/al;
       4: iload_1
       5: invokeinterface #441,  2          // InterfaceMethod android/support/v7/widget/al.b:(Z)V
      10: return

  public void d(boolean);
    Code:
       0: iload_1
       1: ifeq          25
       4: aload_0
       5: getfield      #154                // Field b:Landroid/support/v7/widget/ActionBarOverlayLayout;
       8: invokevirtual #443                // Method android/support/v7/widget/ActionBarOverlayLayout.a:()Z
      11: ifne          25
      14: new           #273                // class java/lang/IllegalStateException
      17: dup
      18: ldc_w         #445                // String Action bar must be in overlay mode (Window.FEATURE_OVERLAY_ACTION_BAR) to enable hide on content scroll
      21: invokespecial #279                // Method java/lang/IllegalStateException."<init>":(Ljava/lang/String;)V
      24: athrow
      25: aload_0
      26: iload_1
      27: putfield      #447                // Field o:Z
      30: aload_0
      31: getfield      #154                // Field b:Landroid/support/v7/widget/ActionBarOverlayLayout;
      34: iload_1
      35: invokevirtual #348                // Method android/support/v7/widget/ActionBarOverlayLayout.setHideOnContentScrollEnabled:(Z)V
      38: return

  public void e(boolean);
    Code:
       0: aload_0
       1: getfield      #192                // Field A:Z
       4: ifne          12
       7: aload_0
       8: iload_1
       9: invokevirtual #448                // Method b:(Z)V
      12: return

  public void f(boolean);
    Code:
       0: aload_0
       1: iload_1
       2: putfield      #450                // Field H:Z
       5: iload_1
       6: ifne          23
       9: aload_0
      10: getfield      #452                // Field n:Landroid/support/v7/view/h;
      13: ifnull        23
      16: aload_0
      17: getfield      #452                // Field n:Landroid/support/v7/view/h;
      20: invokevirtual #455                // Method android/support/v7/view/h.c:()V
      23: return

  public boolean f();
    Code:
       0: aload_0
       1: getfield      #166                // Field d:Landroid/support/v7/widget/al;
       4: ifnull        30
       7: aload_0
       8: getfield      #166                // Field d:Landroid/support/v7/widget/al;
      11: invokeinterface #457,  1          // InterfaceMethod android/support/v7/widget/al.c:()Z
      16: ifeq          30
      19: aload_0
      20: getfield      #166                // Field d:Landroid/support/v7/widget/al;
      23: invokeinterface #458,  1          // InterfaceMethod android/support/v7/widget/al.d:()V
      28: iconst_1
      29: ireturn
      30: iconst_0
      31: ireturn

  public void g(boolean);
    Code:
       0: iload_1
       1: aload_0
       2: getfield      #460                // Field B:Z
       5: if_icmpne     9
       8: return
       9: aload_0
      10: iload_1
      11: putfield      #460                // Field B:Z
      14: aload_0
      15: getfield      #96                 // Field C:Ljava/util/ArrayList;
      18: invokevirtual #463                // Method java/util/ArrayList.size:()I
      21: istore_3
      22: iconst_0
      23: istore_2
      24: iload_2
      25: iload_3
      26: if_icmpge     53
      29: aload_0
      30: getfield      #96                 // Field C:Ljava/util/ArrayList;
      33: iload_2
      34: invokevirtual #467                // Method java/util/ArrayList.get:(I)Ljava/lang/Object;
      37: checkcast     #469                // class android/support/v7/app/a$b
      40: iload_1
      41: invokeinterface #470,  2          // InterfaceMethod android/support/v7/app/a$b.a:(Z)V
      46: iload_2
      47: iconst_1
      48: iadd
      49: istore_2
      50: goto          24
      53: return

  void h();
    Code:
       0: aload_0
       1: getfield      #472                // Field j:Landroid/support/v7/view/b$a;
       4: ifnull        30
       7: aload_0
       8: getfield      #472                // Field j:Landroid/support/v7/view/b$a;
      11: aload_0
      12: getfield      #474                // Field i:Landroid/support/v7/view/b;
      15: invokeinterface #477,  2          // InterfaceMethod android/support/v7/view/b$a.a:(Landroid/support/v7/view/b;)V
      20: aload_0
      21: aconst_null
      22: putfield      #474                // Field i:Landroid/support/v7/view/b;
      25: aload_0
      26: aconst_null
      27: putfield      #472                // Field j:Landroid/support/v7/view/b$a;
      30: return

  public void h(boolean);
    Code:
       0: aload_0
       1: iload_1
       2: putfield      #100                // Field k:Z
       5: return

  public int i();
    Code:
       0: aload_0
       1: getfield      #166                // Field d:Landroid/support/v7/widget/al;
       4: invokeinterface #479,  1          // InterfaceMethod android/support/v7/widget/al.p:()I
       9: ireturn

  public void i(boolean);
    Code:
       0: aload_0
       1: getfield      #452                // Field n:Landroid/support/v7/view/h;
       4: ifnull        14
       7: aload_0
       8: getfield      #452                // Field n:Landroid/support/v7/view/h;
      11: invokevirtual #455                // Method android/support/v7/view/h.c:()V
      14: aload_0
      15: getfield      #180                // Field c:Landroid/support/v7/widget/ActionBarContainer;
      18: iconst_0
      19: invokevirtual #480                // Method android/support/v7/widget/ActionBarContainer.setVisibility:(I)V
      22: aload_0
      23: getfield      #98                 // Field E:I
      26: ifne          226
      29: aload_0
      30: getfield      #450                // Field H:Z
      33: ifne          40
      36: iload_1
      37: ifeq          226
      40: aload_0
      41: getfield      #180                // Field c:Landroid/support/v7/widget/ActionBarContainer;
      44: fconst_0
      45: invokevirtual #483                // Method android/support/v7/widget/ActionBarContainer.setTranslationY:(F)V
      48: aload_0
      49: getfield      #180                // Field c:Landroid/support/v7/widget/ActionBarContainer;
      52: invokevirtual #486                // Method android/support/v7/widget/ActionBarContainer.getHeight:()I
      55: ineg
      56: i2f
      57: fstore_3
      58: fload_3
      59: fstore_2
      60: iload_1
      61: ifeq          97
      64: iconst_2
      65: newarray       int
      67: astore        4
      69: aload         4
      71: dup
      72: iconst_0
      73: iconst_0
      74: iastore
      75: dup
      76: iconst_1
      77: iconst_0
      78: iastore
      79: pop
      80: aload_0
      81: getfield      #180                // Field c:Landroid/support/v7/widget/ActionBarContainer;
      84: aload         4
      86: invokevirtual #490                // Method android/support/v7/widget/ActionBarContainer.getLocationInWindow:([I)V
      89: fload_3
      90: aload         4
      92: iconst_1
      93: iaload
      94: i2f
      95: fsub
      96: fstore_2
      97: aload_0
      98: getfield      #180                // Field c:Landroid/support/v7/widget/ActionBarContainer;
     101: fload_2
     102: invokevirtual #483                // Method android/support/v7/widget/ActionBarContainer.setTranslationY:(F)V
     105: new           #454                // class android/support/v7/view/h
     108: dup
     109: invokespecial #491                // Method android/support/v7/view/h."<init>":()V
     112: astore        4
     114: aload_0
     115: getfield      #180                // Field c:Landroid/support/v7/widget/ActionBarContainer;
     118: invokestatic  #494                // Method android/support/v4/view/s.k:(Landroid/view/View;)Landroid/support/v4/view/x;
     121: fconst_0
     122: invokevirtual #499                // Method android/support/v4/view/x.b:(F)Landroid/support/v4/view/x;
     125: astore        5
     127: aload         5
     129: aload_0
     130: getfield      #113                // Field r:Landroid/support/v4/view/aa;
     133: invokevirtual #502                // Method android/support/v4/view/x.a:(Landroid/support/v4/view/aa;)Landroid/support/v4/view/x;
     136: pop
     137: aload         4
     139: aload         5
     141: invokevirtual #505                // Method android/support/v7/view/h.a:(Landroid/support/v4/view/x;)Landroid/support/v7/view/h;
     144: pop
     145: aload_0
     146: getfield      #100                // Field k:Z
     149: ifeq          184
     152: aload_0
     153: getfield      #139                // Field f:Landroid/view/View;
     156: ifnull        184
     159: aload_0
     160: getfield      #139                // Field f:Landroid/view/View;
     163: fload_2
     164: invokevirtual #506                // Method android/view/View.setTranslationY:(F)V
     167: aload         4
     169: aload_0
     170: getfield      #139                // Field f:Landroid/view/View;
     173: invokestatic  #494                // Method android/support/v4/view/s.k:(Landroid/view/View;)Landroid/support/v4/view/x;
     176: fconst_0
     177: invokevirtual #499                // Method android/support/v4/view/x.b:(F)Landroid/support/v4/view/x;
     180: invokevirtual #505                // Method android/support/v7/view/h.a:(Landroid/support/v4/view/x;)Landroid/support/v7/view/h;
     183: pop
     184: aload         4
     186: getstatic     #84                 // Field u:Landroid/view/animation/Interpolator;
     189: invokevirtual #509                // Method android/support/v7/view/h.a:(Landroid/view/animation/Interpolator;)Landroid/support/v7/view/h;
     192: pop
     193: aload         4
     195: ldc2_w        #510                // long 250l
     198: invokevirtual #514                // Method android/support/v7/view/h.a:(J)Landroid/support/v7/view/h;
     201: pop
     202: aload         4
     204: aload_0
     205: getfield      #110                // Field q:Landroid/support/v4/view/y;
     208: invokevirtual #517                // Method android/support/v7/view/h.a:(Landroid/support/v4/view/y;)Landroid/support/v7/view/h;
     211: pop
     212: aload_0
     213: aload         4
     215: putfield      #452                // Field n:Landroid/support/v7/view/h;
     218: aload         4
     220: invokevirtual #519                // Method android/support/v7/view/h.a:()V
     223: goto          274
     226: aload_0
     227: getfield      #180                // Field c:Landroid/support/v7/widget/ActionBarContainer;
     230: fconst_1
     231: invokevirtual #522                // Method android/support/v7/widget/ActionBarContainer.setAlpha:(F)V
     234: aload_0
     235: getfield      #180                // Field c:Landroid/support/v7/widget/ActionBarContainer;
     238: fconst_0
     239: invokevirtual #483                // Method android/support/v7/widget/ActionBarContainer.setTranslationY:(F)V
     242: aload_0
     243: getfield      #100                // Field k:Z
     246: ifeq          264
     249: aload_0
     250: getfield      #139                // Field f:Landroid/view/View;
     253: ifnull        264
     256: aload_0
     257: getfield      #139                // Field f:Landroid/view/View;
     260: fconst_0
     261: invokevirtual #506                // Method android/view/View.setTranslationY:(F)V
     264: aload_0
     265: getfield      #110                // Field q:Landroid/support/v4/view/y;
     268: aconst_null
     269: invokeinterface #526,  2          // InterfaceMethod android/support/v4/view/y.b:(Landroid/view/View;)V
     274: aload_0
     275: getfield      #154                // Field b:Landroid/support/v7/widget/ActionBarOverlayLayout;
     278: ifnull        288
     281: aload_0
     282: getfield      #154                // Field b:Landroid/support/v7/widget/ActionBarOverlayLayout;
     285: invokestatic  #315                // Method android/support/v4/view/s.o:(Landroid/view/View;)V
     288: return

  public void j();
    Code:
       0: aload_0
       1: getfield      #324                // Field m:Z
       4: ifeq          17
       7: aload_0
       8: iconst_0
       9: putfield      #324                // Field m:Z
      12: aload_0
      13: iconst_1
      14: invokespecial #337                // Method m:(Z)V
      17: return

  public void j(boolean);
    Code:
       0: aload_0
       1: getfield      #452                // Field n:Landroid/support/v7/view/h;
       4: ifnull        14
       7: aload_0
       8: getfield      #452                // Field n:Landroid/support/v7/view/h;
      11: invokevirtual #455                // Method android/support/v7/view/h.c:()V
      14: aload_0
      15: getfield      #98                 // Field E:I
      18: ifne          208
      21: aload_0
      22: getfield      #450                // Field H:Z
      25: ifne          32
      28: iload_1
      29: ifeq          208
      32: aload_0
      33: getfield      #180                // Field c:Landroid/support/v7/widget/ActionBarContainer;
      36: fconst_1
      37: invokevirtual #522                // Method android/support/v7/widget/ActionBarContainer.setAlpha:(F)V
      40: aload_0
      41: getfield      #180                // Field c:Landroid/support/v7/widget/ActionBarContainer;
      44: iconst_1
      45: invokevirtual #529                // Method android/support/v7/widget/ActionBarContainer.setTransitioning:(Z)V
      48: new           #454                // class android/support/v7/view/h
      51: dup
      52: invokespecial #491                // Method android/support/v7/view/h."<init>":()V
      55: astore        4
      57: aload_0
      58: getfield      #180                // Field c:Landroid/support/v7/widget/ActionBarContainer;
      61: invokevirtual #486                // Method android/support/v7/widget/ActionBarContainer.getHeight:()I
      64: ineg
      65: i2f
      66: fstore_3
      67: fload_3
      68: fstore_2
      69: iload_1
      70: ifeq          106
      73: iconst_2
      74: newarray       int
      76: astore        5
      78: aload         5
      80: dup
      81: iconst_0
      82: iconst_0
      83: iastore
      84: dup
      85: iconst_1
      86: iconst_0
      87: iastore
      88: pop
      89: aload_0
      90: getfield      #180                // Field c:Landroid/support/v7/widget/ActionBarContainer;
      93: aload         5
      95: invokevirtual #490                // Method android/support/v7/widget/ActionBarContainer.getLocationInWindow:([I)V
      98: fload_3
      99: aload         5
     101: iconst_1
     102: iaload
     103: i2f
     104: fsub
     105: fstore_2
     106: aload_0
     107: getfield      #180                // Field c:Landroid/support/v7/widget/ActionBarContainer;
     110: invokestatic  #494                // Method android/support/v4/view/s.k:(Landroid/view/View;)Landroid/support/v4/view/x;
     113: fload_2
     114: invokevirtual #499                // Method android/support/v4/view/x.b:(F)Landroid/support/v4/view/x;
     117: astore        5
     119: aload         5
     121: aload_0
     122: getfield      #113                // Field r:Landroid/support/v4/view/aa;
     125: invokevirtual #502                // Method android/support/v4/view/x.a:(Landroid/support/v4/view/aa;)Landroid/support/v4/view/x;
     128: pop
     129: aload         4
     131: aload         5
     133: invokevirtual #505                // Method android/support/v7/view/h.a:(Landroid/support/v4/view/x;)Landroid/support/v7/view/h;
     136: pop
     137: aload_0
     138: getfield      #100                // Field k:Z
     141: ifeq          168
     144: aload_0
     145: getfield      #139                // Field f:Landroid/view/View;
     148: ifnull        168
     151: aload         4
     153: aload_0
     154: getfield      #139                // Field f:Landroid/view/View;
     157: invokestatic  #494                // Method android/support/v4/view/s.k:(Landroid/view/View;)Landroid/support/v4/view/x;
     160: fload_2
     161: invokevirtual #499                // Method android/support/v4/view/x.b:(F)Landroid/support/v4/view/x;
     164: invokevirtual #505                // Method android/support/v7/view/h.a:(Landroid/support/v4/view/x;)Landroid/support/v7/view/h;
     167: pop
     168: aload         4
     170: getstatic     #79                 // Field t:Landroid/view/animation/Interpolator;
     173: invokevirtual #509                // Method android/support/v7/view/h.a:(Landroid/view/animation/Interpolator;)Landroid/support/v7/view/h;
     176: pop
     177: aload         4
     179: ldc2_w        #510                // long 250l
     182: invokevirtual #514                // Method android/support/v7/view/h.a:(J)Landroid/support/v7/view/h;
     185: pop
     186: aload         4
     188: aload_0
     189: getfield      #107                // Field p:Landroid/support/v4/view/y;
     192: invokevirtual #517                // Method android/support/v7/view/h.a:(Landroid/support/v4/view/y;)Landroid/support/v7/view/h;
     195: pop
     196: aload_0
     197: aload         4
     199: putfield      #452                // Field n:Landroid/support/v7/view/h;
     202: aload         4
     204: invokevirtual #519                // Method android/support/v7/view/h.a:()V
     207: return
     208: aload_0
     209: getfield      #107                // Field p:Landroid/support/v4/view/y;
     212: aconst_null
     213: invokeinterface #526,  2          // InterfaceMethod android/support/v4/view/y.b:(Landroid/view/View;)V
     218: return

  public void k();
    Code:
       0: aload_0
       1: getfield      #324                // Field m:Z
       4: ifne          17
       7: aload_0
       8: iconst_1
       9: putfield      #324                // Field m:Z
      12: aload_0
      13: iconst_1
      14: invokespecial #337                // Method m:(Z)V
      17: return

  public void k(boolean);
    Code:
       0: iload_1
       1: ifeq          11
       4: aload_0
       5: invokespecial #531                // Method n:()V
       8: goto          15
      11: aload_0
      12: invokespecial #533                // Method o:()V
      15: aload_0
      16: invokespecial #535                // Method p:()Z
      19: ifeq          105
      22: iload_1
      23: ifeq          55
      26: aload_0
      27: getfield      #166                // Field d:Landroid/support/v7/widget/al;
      30: iconst_4
      31: ldc2_w        #536                // long 100l
      34: invokeinterface #540,  4          // InterfaceMethod android/support/v7/widget/al.a:(IJ)Landroid/support/v4/view/x;
      39: astore_3
      40: aload_0
      41: getfield      #173                // Field e:Landroid/support/v7/widget/ActionBarContextView;
      44: iconst_0
      45: ldc2_w        #541                // long 200l
      48: invokevirtual #543                // Method android/support/v7/widget/ActionBarContextView.a:(IJ)Landroid/support/v4/view/x;
      51: astore_2
      52: goto          82
      55: aload_0
      56: getfield      #166                // Field d:Landroid/support/v7/widget/al;
      59: iconst_0
      60: ldc2_w        #541                // long 200l
      63: invokeinterface #540,  4          // InterfaceMethod android/support/v7/widget/al.a:(IJ)Landroid/support/v4/view/x;
      68: astore_2
      69: aload_0
      70: getfield      #173                // Field e:Landroid/support/v7/widget/ActionBarContextView;
      73: bipush        8
      75: ldc2_w        #536                // long 100l
      78: invokevirtual #543                // Method android/support/v7/widget/ActionBarContextView.a:(IJ)Landroid/support/v4/view/x;
      81: astore_3
      82: new           #454                // class android/support/v7/view/h
      85: dup
      86: invokespecial #491                // Method android/support/v7/view/h."<init>":()V
      89: astore        4
      91: aload         4
      93: aload_3
      94: aload_2
      95: invokevirtual #546                // Method android/support/v7/view/h.a:(Landroid/support/v4/view/x;Landroid/support/v4/view/x;)Landroid/support/v7/view/h;
      98: pop
      99: aload         4
     101: invokevirtual #519                // Method android/support/v7/view/h.a:()V
     104: return
     105: iload_1
     106: ifeq          128
     109: aload_0
     110: getfield      #166                // Field d:Landroid/support/v7/widget/al;
     113: iconst_4
     114: invokeinterface #548,  2          // InterfaceMethod android/support/v7/widget/al.f:(I)V
     119: aload_0
     120: getfield      #173                // Field e:Landroid/support/v7/widget/ActionBarContextView;
     123: iconst_0
     124: invokevirtual #549                // Method android/support/v7/widget/ActionBarContextView.setVisibility:(I)V
     127: return
     128: aload_0
     129: getfield      #166                // Field d:Landroid/support/v7/widget/al;
     132: iconst_0
     133: invokeinterface #548,  2          // InterfaceMethod android/support/v7/widget/al.f:(I)V
     138: aload_0
     139: getfield      #173                // Field e:Landroid/support/v7/widget/ActionBarContextView;
     142: bipush        8
     144: invokevirtual #549                // Method android/support/v7/widget/ActionBarContextView.setVisibility:(I)V
     147: return

  public void l();
    Code:
       0: aload_0
       1: getfield      #452                // Field n:Landroid/support/v7/view/h;
       4: ifnull        19
       7: aload_0
       8: getfield      #452                // Field n:Landroid/support/v7/view/h;
      11: invokevirtual #455                // Method android/support/v7/view/h.c:()V
      14: aload_0
      15: aconst_null
      16: putfield      #452                // Field n:Landroid/support/v7/view/h;
      19: return

  public void m();
    Code:
       0: return
}
