public class ryey.easer.plugins.operation.k.a extends ryey.easer.plugins.operation.c<ryey.easer.plugins.operation.k.b> {
  public ryey.easer.plugins.operation.k.a(android.content.Context);
    Code:
       0: aload_0
       1: aload_1
       2: invokespecial #9                  // Method ryey/easer/plugins/operation/c."<init>":(Landroid/content/Context;)V
       5: return

  public boolean a(ryey.easer.commons.local_plugin.c.b);
    Code:
       0: aload_0
       1: aload_1
       2: checkcast     #14                 // class ryey/easer/plugins/operation/k/b
       5: invokevirtual #17                 // Method a:(Lryey/easer/plugins/operation/k/b;)Z
       8: ireturn

  public boolean a(ryey.easer.plugins.operation.k.b);
    Code:
       0: new           #19                 // class java/lang/RuntimeException
       3: dup
       4: ldc           #21                 // String d2j fail translate: java.lang.RuntimeException: can not merge I and Z\n\tat com.googlecode.dex2jar.ir.TypeClass.merge(TypeClass.java:100)\n\tat com.googlecode.dex2jar.ir.ts.TypeTransformer$TypeRef.updateTypeClass(TypeTransformer.java:174)\n\tat com.googlecode.dex2jar.ir.ts.TypeTransformer$TypeAnalyze.provideAs(TypeTransformer.java:780)\n\tat com.googlecode.dex2jar.ir.ts.TypeTransformer$TypeAnalyze.enexpr(TypeTransformer.java:659)\n\tat com.googlecode.dex2jar.ir.ts.TypeTransformer$TypeAnalyze.exExpr(TypeTransformer.java:719)\n\tat com.googlecode.dex2jar.ir.ts.TypeTransformer$TypeAnalyze.exExpr(TypeTransformer.java:703)\n\tat com.googlecode.dex2jar.ir.ts.TypeTransformer$TypeAnalyze.enexpr(TypeTransformer.java:698)\n\tat com.googlecode.dex2jar.ir.ts.TypeTransformer$TypeAnalyze.exExpr(TypeTransformer.java:719)\n\tat com.googlecode.dex2jar.ir.ts.TypeTransformer$TypeAnalyze.exExpr(TypeTransformer.java:703)\n\tat com.googlecode.dex2jar.ir.ts.TypeTransformer$TypeAnalyze.s1stmt(TypeTransformer.java:810)\n\tat com.googlecode.dex2jar.ir.ts.TypeTransformer$TypeAnalyze.sxStmt(TypeTransformer.java:840)\n\tat com.googlecode.dex2jar.ir.ts.TypeTransformer$TypeAnalyze.analyze(TypeTransformer.java:206)\n\tat com.googlecode.dex2jar.ir.ts.TypeTransformer.transform(TypeTransformer.java:44)\n\tat com.googlecode.d2j.dex.Dex2jar$2.optimize(Dex2jar.java:162)\n\tat com.googlecode.d2j.dex.Dex2Asm.convertCode(Dex2Asm.java:414)\n\tat com.googlecode.d2j.dex.ExDex2Asm.convertCode(ExDex2Asm.java:42)\n\tat com.googlecode.d2j.dex.Dex2jar$2.convertCode(Dex2jar.java:128)\n\tat com.googlecode.d2j.dex.Dex2Asm.convertMethod(Dex2Asm.java:509)\n\tat com.googlecode.d2j.dex.Dex2Asm.convertClass(Dex2Asm.java:406)\n\tat com.googlecode.d2j.dex.Dex2Asm.convertDex(Dex2Asm.java:422)\n\tat com.googlecode.d2j.dex.Dex2jar.doTranslate(Dex2jar.java:172)\n\tat com.googlecode.d2j.dex.Dex2jar.to(Dex2jar.java:272)\n\tat com.googlecode.dex2jar.tools.Dex2jarCmd.doCommandLine(Dex2jarCmd.java:108)\n\tat com.googlecode.dex2jar.tools.BaseCmd.doMain(BaseCmd.java:288)\n\tat com.googlecode.dex2jar.tools.Dex2jarCmd.main(Dex2jarCmd.java:32)\n
       6: invokespecial #26                 // Method java/lang/Runtime."<init>":(Ljava/lang/String;)V
       9: athrow
}
