public class ryey.easer.plugins.operation.k.b extends ryey.easer.plugins.operation.a {
  public static final android.os.Parcelable$Creator<ryey.easer.plugins.operation.k.b> CREATOR;

  static {};
    Code:
       0: new           #6                  // class ryey/easer/plugins/operation/k/b$1
       3: dup
       4: invokespecial #14                 // Method ryey/easer/plugins/operation/k/b$1."<init>":()V
       7: putstatic     #16                 // Field CREATOR:Landroid/os/Parcelable$Creator;
      10: return

  ryey.easer.plugins.operation.k.b(android.os.Parcel, ryey.easer.plugins.operation.k.b$1);
    Code:
       0: aload_0
       1: aload_1
       2: invokespecial #22                 // Method "<init>":(Landroid/os/Parcel;)V
       5: return

  ryey.easer.plugins.operation.k.b(java.lang.Boolean);
    Code:
       0: aload_0
       1: aload_1
       2: invokespecial #25                 // Method ryey/easer/plugins/operation/a."<init>":(Ljava/lang/Boolean;)V
       5: return

  ryey.easer.plugins.operation.k.b(java.lang.String, ryey.easer.b.a, int);
    Code:
       0: aload_0
       1: aload_1
       2: aload_2
       3: iload_3
       4: invokespecial #28                 // Method ryey/easer/plugins/operation/a."<init>":(Ljava/lang/String;Lryey/easer/b/a;I)V
       7: return
}
