public class ryey.easer.a.a extends android.databinding.ViewDataBinding {
  public final android.widget.TableRow c;

  public final android.widget.TableRow d;

  public final android.widget.TableRow e;

  public final android.widget.TableRow f;

  public final android.widget.TableRow g;

  public final android.widget.TableRow h;

  public final android.widget.TextView i;

  public final android.widget.TextView j;

  public final android.widget.TextView k;

  public final android.widget.TextView l;

  public final android.widget.TextView m;

  public final android.widget.TextView n;

  static {};
    Code:
       0: new           #30                 // class android/util/SparseIntArray
       3: dup
       4: invokespecial #33                 // Method android/util/SparseIntArray."<init>":()V
       7: putstatic     #35                 // Field p:Landroid/util/SparseIntArray;
      10: getstatic     #35                 // Field p:Landroid/util/SparseIntArray;
      13: ldc           #36                 // int 2131296319
      15: iconst_1
      16: invokevirtual #40                 // Method android/util/SparseIntArray.put:(II)V
      19: getstatic     #35                 // Field p:Landroid/util/SparseIntArray;
      22: ldc           #41                 // int 2131296742
      24: iconst_2
      25: invokevirtual #40                 // Method android/util/SparseIntArray.put:(II)V
      28: getstatic     #35                 // Field p:Landroid/util/SparseIntArray;
      31: ldc           #42                 // int 2131296320
      33: iconst_3
      34: invokevirtual #40                 // Method android/util/SparseIntArray.put:(II)V
      37: getstatic     #35                 // Field p:Landroid/util/SparseIntArray;
      40: ldc           #43                 // int 2131296743
      42: iconst_4
      43: invokevirtual #40                 // Method android/util/SparseIntArray.put:(II)V
      46: getstatic     #35                 // Field p:Landroid/util/SparseIntArray;
      49: ldc           #44                 // int 2131296321
      51: iconst_5
      52: invokevirtual #40                 // Method android/util/SparseIntArray.put:(II)V
      55: getstatic     #35                 // Field p:Landroid/util/SparseIntArray;
      58: ldc           #45                 // int 2131296744
      60: bipush        6
      62: invokevirtual #40                 // Method android/util/SparseIntArray.put:(II)V
      65: getstatic     #35                 // Field p:Landroid/util/SparseIntArray;
      68: ldc           #46                 // int 2131296318
      70: bipush        7
      72: invokevirtual #40                 // Method android/util/SparseIntArray.put:(II)V
      75: getstatic     #35                 // Field p:Landroid/util/SparseIntArray;
      78: ldc           #47                 // int 2131296741
      80: bipush        8
      82: invokevirtual #40                 // Method android/util/SparseIntArray.put:(II)V
      85: getstatic     #35                 // Field p:Landroid/util/SparseIntArray;
      88: ldc           #48                 // int 2131296317
      90: bipush        9
      92: invokevirtual #40                 // Method android/util/SparseIntArray.put:(II)V
      95: getstatic     #35                 // Field p:Landroid/util/SparseIntArray;
      98: ldc           #49                 // int 2131296736
     100: bipush        10
     102: invokevirtual #40                 // Method android/util/SparseIntArray.put:(II)V
     105: getstatic     #35                 // Field p:Landroid/util/SparseIntArray;
     108: ldc           #50                 // int 2131296322
     110: bipush        11
     112: invokevirtual #40                 // Method android/util/SparseIntArray.put:(II)V
     115: getstatic     #35                 // Field p:Landroid/util/SparseIntArray;
     118: ldc           #51                 // int 2131296745
     120: bipush        12
     122: invokevirtual #40                 // Method android/util/SparseIntArray.put:(II)V
     125: return

  public ryey.easer.a.a(android.databinding.e, android.view.View);
    Code:
       0: aload_0
       1: aload_1
       2: aload_2
       3: iconst_0
       4: invokespecial #56                 // Method android/databinding/ViewDataBinding."<init>":(Landroid/databinding/e;Landroid/view/View;I)V
       7: aload_0
       8: ldc2_w        #57                 // long -1l
      11: putfield      #60                 // Field r:J
      14: aload_1
      15: aload_2
      16: bipush        13
      18: getstatic     #62                 // Field o:Landroid/databinding/ViewDataBinding$b;
      21: getstatic     #35                 // Field p:Landroid/util/SparseIntArray;
      24: invokestatic  #66                 // Method a:(Landroid/databinding/e;Landroid/view/View;ILandroid/databinding/ViewDataBinding$b;Landroid/util/SparseIntArray;)[Ljava/lang/Object;
      27: astore_1
      28: aload_0
      29: aload_1
      30: bipush        9
      32: aaload
      33: checkcast     #68                 // class android/widget/TableRow
      36: putfield      #70                 // Field c:Landroid/widget/TableRow;
      39: aload_0
      40: aload_1
      41: bipush        7
      43: aaload
      44: checkcast     #68                 // class android/widget/TableRow
      47: putfield      #72                 // Field d:Landroid/widget/TableRow;
      50: aload_0
      51: aload_1
      52: iconst_1
      53: aaload
      54: checkcast     #68                 // class android/widget/TableRow
      57: putfield      #74                 // Field e:Landroid/widget/TableRow;
      60: aload_0
      61: aload_1
      62: iconst_3
      63: aaload
      64: checkcast     #68                 // class android/widget/TableRow
      67: putfield      #76                 // Field f:Landroid/widget/TableRow;
      70: aload_0
      71: aload_1
      72: iconst_5
      73: aaload
      74: checkcast     #68                 // class android/widget/TableRow
      77: putfield      #78                 // Field g:Landroid/widget/TableRow;
      80: aload_0
      81: aload_1
      82: bipush        11
      84: aaload
      85: checkcast     #68                 // class android/widget/TableRow
      88: putfield      #80                 // Field h:Landroid/widget/TableRow;
      91: aload_0
      92: aload_1
      93: iconst_0
      94: aaload
      95: checkcast     #82                 // class android/widget/FrameLayout
      98: putfield      #84                 // Field q:Landroid/widget/FrameLayout;
     101: aload_0
     102: getfield      #84                 // Field q:Landroid/widget/FrameLayout;
     105: aconst_null
     106: invokevirtual #88                 // Method android/widget/FrameLayout.setTag:(Ljava/lang/Object;)V
     109: aload_0
     110: aload_1
     111: bipush        10
     113: aaload
     114: checkcast     #90                 // class android/widget/TextView
     117: putfield      #92                 // Field i:Landroid/widget/TextView;
     120: aload_0
     121: aload_1
     122: bipush        8
     124: aaload
     125: checkcast     #90                 // class android/widget/TextView
     128: putfield      #94                 // Field j:Landroid/widget/TextView;
     131: aload_0
     132: aload_1
     133: iconst_2
     134: aaload
     135: checkcast     #90                 // class android/widget/TextView
     138: putfield      #96                 // Field k:Landroid/widget/TextView;
     141: aload_0
     142: aload_1
     143: iconst_4
     144: aaload
     145: checkcast     #90                 // class android/widget/TextView
     148: putfield      #98                 // Field l:Landroid/widget/TextView;
     151: aload_0
     152: aload_1
     153: bipush        6
     155: aaload
     156: checkcast     #90                 // class android/widget/TextView
     159: putfield      #100                // Field m:Landroid/widget/TextView;
     162: aload_0
     163: aload_1
     164: bipush        12
     166: aaload
     167: checkcast     #90                 // class android/widget/TextView
     170: putfield      #102                // Field n:Landroid/widget/TextView;
     173: aload_0
     174: aload_2
     175: invokevirtual #105                // Method a:(Landroid/view/View;)V
     178: aload_0
     179: invokevirtual #107                // Method g:()V
     182: return

  protected void b();
    Code:
       0: aload_0
       1: monitorenter
       2: aload_0
       3: getfield      #60                 // Field r:J
       6: lstore_1
       7: aload_0
       8: lconst_0
       9: putfield      #60                 // Field r:J
      12: aload_0
      13: monitorexit
      14: return
      15: astore_3
      16: aload_0
      17: monitorexit
      18: aload_3
      19: athrow
    Exception table:
       from    to  target type
           2    14    15   any
          16    18    15   any

  public boolean c();
    Code:
       0: aload_0
       1: monitorenter
       2: aload_0
       3: getfield      #60                 // Field r:J
       6: lconst_0
       7: lcmp
       8: ifeq          15
      11: aload_0
      12: monitorexit
      13: iconst_1
      14: ireturn
      15: aload_0
      16: monitorexit
      17: iconst_0
      18: ireturn
      19: astore_1
      20: aload_0
      21: monitorexit
      22: aload_1
      23: athrow
    Exception table:
       from    to  target type
           2    13    19   any
          15    17    19   any
          20    22    19   any

  public void g();
    Code:
       0: aload_0
       1: monitorenter
       2: aload_0
       3: lconst_1
       4: putfield      #60                 // Field r:J
       7: aload_0
       8: monitorexit
       9: aload_0
      10: invokevirtual #111                // Method d:()V
      13: return
      14: astore_1
      15: aload_0
      16: monitorexit
      17: aload_1
      18: athrow
    Exception table:
       from    to  target type
           2     9    14   any
          15    17    14   any
}
