class ryey.easer.plugins.event.o.d$1 implements android.widget.CompoundButton$OnCheckedChangeListener {
  final ryey.easer.plugins.event.o.d a;

  ryey.easer.plugins.event.o.d$1(ryey.easer.plugins.event.o.d);
    Code:
       0: aload_0
       1: aload_1
       2: putfield      #17                 // Field a:Lryey/easer/plugins/event/o/d;
       5: aload_0
       6: invokespecial #20                 // Method java/lang/Object."<init>":()V
       9: return

  public void onCheckedChanged(android.widget.CompoundButton, boolean);
    Code:
       0: aload_0
       1: getfield      #17                 // Field a:Lryey/easer/plugins/event/o/d;
       4: invokestatic  #26                 // Method ryey/easer/plugins/event/o/d.a:(Lryey/easer/plugins/event/o/d;)Landroid/widget/RadioButton;
       7: astore        4
       9: bipush        8
      11: istore_3
      12: aload_1
      13: aload         4
      15: if_acmpne     58
      18: aload_0
      19: getfield      #17                 // Field a:Lryey/easer/plugins/event/o/d;
      22: invokestatic  #29                 // Method ryey/easer/plugins/event/o/d.b:(Lryey/easer/plugins/event/o/d;)Landroid/widget/RadioButton;
      25: iload_2
      26: iconst_1
      27: ixor
      28: invokevirtual #35                 // Method android/widget/RadioButton.setChecked:(Z)V
      31: aload_0
      32: getfield      #17                 // Field a:Lryey/easer/plugins/event/o/d;
      35: getfield      #38                 // Field ryey/easer/plugins/event/o/d.a:Landroid/support/constraint/Group;
      38: astore        4
      40: aload         4
      42: astore_1
      43: iload_2
      44: ifeq          52
      47: aload         4
      49: astore_1
      50: iconst_0
      51: istore_3
      52: aload_1
      53: iload_3
      54: invokevirtual #44                 // Method android/support/constraint/Group.setVisibility:(I)V
      57: return
      58: aload_1
      59: aload_0
      60: getfield      #17                 // Field a:Lryey/easer/plugins/event/o/d;
      63: invokestatic  #29                 // Method ryey/easer/plugins/event/o/d.b:(Lryey/easer/plugins/event/o/d;)Landroid/widget/RadioButton;
      66: if_acmpne     104
      69: aload_0
      70: getfield      #17                 // Field a:Lryey/easer/plugins/event/o/d;
      73: invokestatic  #26                 // Method ryey/easer/plugins/event/o/d.a:(Lryey/easer/plugins/event/o/d;)Landroid/widget/RadioButton;
      76: iload_2
      77: iconst_1
      78: ixor
      79: invokevirtual #35                 // Method android/widget/RadioButton.setChecked:(Z)V
      82: aload_0
      83: getfield      #17                 // Field a:Lryey/easer/plugins/event/o/d;
      86: getfield      #46                 // Field ryey/easer/plugins/event/o/d.b:Landroid/support/constraint/Group;
      89: astore        4
      91: aload         4
      93: astore_1
      94: iload_2
      95: ifeq          52
      98: aload         4
     100: astore_1
     101: goto          50
     104: new           #48                 // class java/lang/IllegalStateException
     107: dup
     108: ldc           #50                 // String This OnCheckedChangeListener shouldn't be used elsewhere.
     110: invokespecial #53                 // Method java/lang/IllegalStateException."<init>":(Ljava/lang/String;)V
     113: athrow
}
