public class ryey.easer.plugins.event.o.d extends ryey.easer.plugins.c<ryey.easer.plugins.event.o.a> {
  android.support.constraint.Group a;

  android.support.constraint.Group b;

  public ryey.easer.plugins.event.o.d();
    Code:
       0: aload_0
       1: invokespecial #24                 // Method ryey/easer/plugins/c."<init>":()V
       4: return

  static android.widget.RadioButton a(ryey.easer.plugins.event.o.d);
    Code:
       0: aload_0
       1: getfield      #28                 // Field c:Landroid/widget/RadioButton;
       4: areturn

  static android.widget.RadioButton b(ryey.easer.plugins.event.o.d);
    Code:
       0: aload_0
       1: getfield      #30                 // Field d:Landroid/widget/RadioButton;
       4: areturn

  public ryey.easer.commons.local_plugin.f a();
    Code:
       0: aload_0
       1: invokevirtual #34                 // Method b:()Lryey/easer/plugins/event/o/a;
       4: areturn

  protected void a(ryey.easer.plugins.event.o.a);
    Code:
       0: aload_1
       1: getfield      #40                 // Field ryey/easer/plugins/event/o/a.a:Z
       4: ifeq          32
       7: aload_0
       8: getfield      #28                 // Field c:Landroid/widget/RadioButton;
      11: iconst_1
      12: invokevirtual #46                 // Method android/widget/RadioButton.setChecked:(Z)V
      15: aload_0
      16: getfield      #48                 // Field f:Landroid/widget/EditText;
      19: aload_1
      20: getfield      #51                 // Field ryey/easer/plugins/event/o/a.b:I
      23: invokestatic  #57                 // Method java/lang/String.valueOf:(I)Ljava/lang/String;
      26: invokevirtual #63                 // Method android/widget/EditText.setText:(Ljava/lang/CharSequence;)V
      29: goto          77
      32: aload_0
      33: getfield      #65                 // Field e:Landroid/widget/EditText;
      36: aload_1
      37: getfield      #51                 // Field ryey/easer/plugins/event/o/a.b:I
      40: invokestatic  #57                 // Method java/lang/String.valueOf:(I)Ljava/lang/String;
      43: invokevirtual #63                 // Method android/widget/EditText.setText:(Ljava/lang/CharSequence;)V
      46: aload_1
      47: getfield      #68                 // Field ryey/easer/plugins/event/o/a.c:Ljava/lang/Boolean;
      50: invokevirtual #74                 // Method java/lang/Boolean.booleanValue:()Z
      53: ifeq          69
      56: aload_0
      57: getfield      #76                 // Field g:Landroid/widget/RadioButton;
      60: astore_2
      61: aload_2
      62: iconst_1
      63: invokevirtual #46                 // Method android/widget/RadioButton.setChecked:(Z)V
      66: goto          77
      69: aload_0
      70: getfield      #78                 // Field h:Landroid/widget/RadioButton;
      73: astore_2
      74: goto          61
      77: aload_1
      78: getfield      #80                 // Field ryey/easer/plugins/event/o/a.d:Z
      81: ifeq          95
      84: aload_0
      85: getfield      #82                 // Field i:Landroid/widget/RadioButton;
      88: astore_1
      89: aload_1
      90: iconst_1
      91: invokevirtual #46                 // Method android/widget/RadioButton.setChecked:(Z)V
      94: return
      95: aload_0
      96: getfield      #84                 // Field j:Landroid/widget/RadioButton;
      99: astore_1
     100: goto          89

  public ryey.easer.plugins.event.o.a b();
    Code:
       0: aload_0
       1: getfield      #28                 // Field c:Landroid/widget/RadioButton;
       4: invokevirtual #89                 // Method android/widget/RadioButton.isChecked:()Z
       7: istore_1
       8: aload_0
       9: getfield      #82                 // Field i:Landroid/widget/RadioButton;
      12: invokevirtual #89                 // Method android/widget/RadioButton.isChecked:()Z
      15: istore_2
      16: iload_1
      17: ifeq          42
      20: new           #37                 // class ryey/easer/plugins/event/o/a
      23: dup
      24: aload_0
      25: getfield      #48                 // Field f:Landroid/widget/EditText;
      28: invokevirtual #93                 // Method android/widget/EditText.getText:()Landroid/text/Editable;
      31: invokevirtual #99                 // Method java/lang/Object.toString:()Ljava/lang/String;
      34: invokestatic  #105                // Method java/lang/Integer.parseInt:(Ljava/lang/String;)I
      37: iload_2
      38: invokespecial #108                // Method ryey/easer/plugins/event/o/a."<init>":(IZ)V
      41: areturn
      42: new           #37                 // class ryey/easer/plugins/event/o/a
      45: dup
      46: aload_0
      47: getfield      #65                 // Field e:Landroid/widget/EditText;
      50: invokevirtual #93                 // Method android/widget/EditText.getText:()Landroid/text/Editable;
      53: invokevirtual #99                 // Method java/lang/Object.toString:()Ljava/lang/String;
      56: invokestatic  #105                // Method java/lang/Integer.parseInt:(Ljava/lang/String;)I
      59: aload_0
      60: getfield      #76                 // Field g:Landroid/widget/RadioButton;
      63: invokevirtual #89                 // Method android/widget/RadioButton.isChecked:()Z
      66: iload_2
      67: invokespecial #111                // Method ryey/easer/plugins/event/o/a."<init>":(IZZ)V
      70: astore_3
      71: aload_3
      72: areturn
      73: astore_3
      74: new           #113                // class ryey/easer/commons/local_plugin/c
      77: dup
      78: aload_3
      79: invokevirtual #116                // Method java/lang/NumberFormatException.getMessage:()Ljava/lang/String;
      82: invokespecial #119                // Method ryey/easer/commons/local_plugin/c."<init>":(Ljava/lang/String;)V
      85: athrow
    Exception table:
       from    to  target type
           0    16    73   Class java/lang/NumberFormatException
          20    42    73   Class java/lang/NumberFormatException
          42    71    73   Class java/lang/NumberFormatException

  protected void b(ryey.easer.commons.local_plugin.f);
    Code:
       0: aload_0
       1: aload_1
       2: checkcast     #37                 // class ryey/easer/plugins/event/o/a
       5: invokevirtual #122                // Method a:(Lryey/easer/plugins/event/o/a;)V
       8: return

  public android.view.View onCreateView(android.view.LayoutInflater, android.view.ViewGroup, android.os.Bundle);
    Code:
       0: aload_1
       1: ldc           #125                // int 2131427442
       3: aload_2
       4: iconst_0
       5: invokevirtual #131                // Method android/view/LayoutInflater.inflate:(ILandroid/view/ViewGroup;Z)Landroid/view/View;
       8: astore_1
       9: aload_0
      10: aload_1
      11: ldc           #132                // int 2131296425
      13: invokevirtual #138                // Method android/view/View.findViewById:(I)Landroid/view/View;
      16: checkcast     #140                // class android/support/constraint/Group
      19: putfield      #142                // Field a:Landroid/support/constraint/Group;
      22: aload_0
      23: aload_1
      24: ldc           #143                // int 2131296424
      26: invokevirtual #138                // Method android/view/View.findViewById:(I)Landroid/view/View;
      29: checkcast     #140                // class android/support/constraint/Group
      32: putfield      #145                // Field b:Landroid/support/constraint/Group;
      35: aload_0
      36: aload_1
      37: ldc           #146                // int 2131296553
      39: invokevirtual #138                // Method android/view/View.findViewById:(I)Landroid/view/View;
      42: checkcast     #42                 // class android/widget/RadioButton
      45: putfield      #28                 // Field c:Landroid/widget/RadioButton;
      48: aload_0
      49: aload_1
      50: ldc           #147                // int 2131296532
      52: invokevirtual #138                // Method android/view/View.findViewById:(I)Landroid/view/View;
      55: checkcast     #42                 // class android/widget/RadioButton
      58: putfield      #30                 // Field d:Landroid/widget/RadioButton;
      61: new           #7                  // class ryey/easer/plugins/event/o/d$1
      64: dup
      65: aload_0
      66: invokespecial #150                // Method ryey/easer/plugins/event/o/d$1."<init>":(Lryey/easer/plugins/event/o/d;)V
      69: astore_2
      70: aload_0
      71: getfield      #28                 // Field c:Landroid/widget/RadioButton;
      74: aload_2
      75: invokevirtual #154                // Method android/widget/RadioButton.setOnCheckedChangeListener:(Landroid/widget/CompoundButton$OnCheckedChangeListener;)V
      78: aload_0
      79: getfield      #30                 // Field d:Landroid/widget/RadioButton;
      82: aload_2
      83: invokevirtual #154                // Method android/widget/RadioButton.setOnCheckedChangeListener:(Landroid/widget/CompoundButton$OnCheckedChangeListener;)V
      86: aload_0
      87: aload_1
      88: ldc           #155                // int 2131296396
      90: invokevirtual #138                // Method android/view/View.findViewById:(I)Landroid/view/View;
      93: checkcast     #59                 // class android/widget/EditText
      96: putfield      #48                 // Field f:Landroid/widget/EditText;
      99: aload_0
     100: aload_1
     101: ldc           #156                // int 2131296387
     103: invokevirtual #138                // Method android/view/View.findViewById:(I)Landroid/view/View;
     106: checkcast     #59                 // class android/widget/EditText
     109: putfield      #65                 // Field e:Landroid/widget/EditText;
     112: aload_0
     113: aload_1
     114: ldc           #157                // int 2131296529
     116: invokevirtual #138                // Method android/view/View.findViewById:(I)Landroid/view/View;
     119: checkcast     #42                 // class android/widget/RadioButton
     122: putfield      #76                 // Field g:Landroid/widget/RadioButton;
     125: aload_0
     126: aload_1
     127: ldc           #158                // int 2131296530
     129: invokevirtual #138                // Method android/view/View.findViewById:(I)Landroid/view/View;
     132: checkcast     #42                 // class android/widget/RadioButton
     135: putfield      #78                 // Field h:Landroid/widget/RadioButton;
     138: aload_0
     139: aload_1
     140: ldc           #159                // int 2131296548
     142: invokevirtual #138                // Method android/view/View.findViewById:(I)Landroid/view/View;
     145: checkcast     #42                 // class android/widget/RadioButton
     148: putfield      #82                 // Field i:Landroid/widget/RadioButton;
     151: aload_0
     152: aload_1
     153: ldc           #160                // int 2131296539
     155: invokevirtual #138                // Method android/view/View.findViewById:(I)Landroid/view/View;
     158: checkcast     #42                 // class android/widget/RadioButton
     161: putfield      #84                 // Field j:Landroid/widget/RadioButton;
     164: aload_1
     165: areturn
}
