class ryey.easer.plugins.event.o.e$1 implements java.lang.Runnable {
  final ryey.easer.plugins.event.o.e a;

  ryey.easer.plugins.event.o.e$1(ryey.easer.plugins.event.o.e);
    Code:
       0: aload_0
       1: aload_1
       2: putfield      #16                 // Field a:Lryey/easer/plugins/event/o/e;
       5: aload_0
       6: invokespecial #18                 // Method java/lang/Object."<init>":()V
       9: return

  public void run();
    Code:
       0: aload_0
       1: getfield      #16                 // Field a:Lryey/easer/plugins/event/o/e;
       4: iconst_1
       5: invokestatic  #23                 // Method ryey/easer/plugins/event/o/e.a:(Lryey/easer/plugins/event/o/e;Z)V
       8: aload_0
       9: getfield      #16                 // Field a:Lryey/easer/plugins/event/o/e;
      12: invokestatic  #26                 // Method ryey/easer/plugins/event/o/e.a:(Lryey/easer/plugins/event/o/e;)Lryey/easer/commons/local_plugin/eventplugin/EventData;
      15: checkcast     #28                 // class ryey/easer/plugins/event/o/a
      18: getfield      #32                 // Field ryey/easer/plugins/event/o/a.d:Z
      21: ifeq          60
      24: aload_0
      25: getfield      #16                 // Field a:Lryey/easer/plugins/event/o/e;
      28: invokestatic  #35                 // Method ryey/easer/plugins/event/o/e.d:(Lryey/easer/plugins/event/o/e;)Landroid/os/Handler;
      31: aload_0
      32: getfield      #16                 // Field a:Lryey/easer/plugins/event/o/e;
      35: invokestatic  #39                 // Method ryey/easer/plugins/event/o/e.b:(Lryey/easer/plugins/event/o/e;)Ljava/lang/Runnable;
      38: aload_0
      39: getfield      #16                 // Field a:Lryey/easer/plugins/event/o/e;
      42: invokestatic  #42                 // Method ryey/easer/plugins/event/o/e.c:(Lryey/easer/plugins/event/o/e;)Lryey/easer/commons/local_plugin/eventplugin/EventData;
      45: checkcast     #28                 // class ryey/easer/plugins/event/o/a
      48: getfield      #45                 // Field ryey/easer/plugins/event/o/a.b:I
      51: sipush        1000
      54: imul
      55: i2l
      56: invokevirtual #51                 // Method android/os/Handler.postDelayed:(Ljava/lang/Runnable;J)Z
      59: pop
      60: return
}
