final class android.support.v4.f.b$3 implements android.support.v4.f.c$a<android.support.v4.f.b$c> {
  final java.lang.String a;

  android.support.v4.f.b$3(java.lang.String);
    Code:
       0: aload_0
       1: aload_1
       2: putfield      #17                 // Field a:Ljava/lang/String;
       5: aload_0
       6: invokespecial #20                 // Method java/lang/Object."<init>":()V
       9: return

  public void a(android.support.v4.f.b$c);
    Code:
       0: invokestatic  #26                 // Method android/support/v4/f/b.b:()Ljava/lang/Object;
       3: astore_3
       4: aload_3
       5: monitorenter
       6: invokestatic  #30                 // Method android/support/v4/f/b.c:()Landroid/support/v4/g/m;
       9: aload_0
      10: getfield      #17                 // Field a:Ljava/lang/String;
      13: invokevirtual #36                 // Method android/support/v4/g/m.get:(Ljava/lang/Object;)Ljava/lang/Object;
      16: checkcast     #38                 // class java/util/ArrayList
      19: astore        4
      21: aload         4
      23: ifnonnull     29
      26: aload_3
      27: monitorexit
      28: return
      29: invokestatic  #30                 // Method android/support/v4/f/b.c:()Landroid/support/v4/g/m;
      32: aload_0
      33: getfield      #17                 // Field a:Ljava/lang/String;
      36: invokevirtual #41                 // Method android/support/v4/g/m.remove:(Ljava/lang/Object;)Ljava/lang/Object;
      39: pop
      40: aload_3
      41: monitorexit
      42: iconst_0
      43: istore_2
      44: iload_2
      45: aload         4
      47: invokevirtual #45                 // Method java/util/ArrayList.size:()I
      50: if_icmpge     75
      53: aload         4
      55: iload_2
      56: invokevirtual #48                 // Method java/util/ArrayList.get:(I)Ljava/lang/Object;
      59: checkcast     #7                  // class android/support/v4/f/c$a
      62: aload_1
      63: invokeinterface #51,  2           // InterfaceMethod android/support/v4/f/c$a.a:(Ljava/lang/Object;)V
      68: iload_2
      69: iconst_1
      70: iadd
      71: istore_2
      72: goto          44
      75: return
      76: astore_1
      77: aload_3
      78: monitorexit
      79: aload_1
      80: athrow
    Exception table:
       from    to  target type
           6    21    76   any
          26    28    76   any
          29    42    76   any
          77    79    76   any

  public void a(java.lang.Object);
    Code:
       0: aload_0
       1: aload_1
       2: checkcast     #53                 // class android/support/v4/f/b$c
       5: invokevirtual #55                 // Method a:(Landroid/support/v4/f/b$c;)V
       8: return
}
