public class android.support.v4.f.b$a {
  public android.support.v4.f.b$a(int, android.support.v4.f.b$b[]);
    Code:
       0: aload_0
       1: invokespecial #15                 // Method java/lang/Object."<init>":()V
       4: aload_0
       5: iload_1
       6: putfield      #17                 // Field a:I
       9: aload_0
      10: aload_2
      11: putfield      #19                 // Field b:[Landroid/support/v4/f/b$b;
      14: return

  public int a();
    Code:
       0: aload_0
       1: getfield      #17                 // Field a:I
       4: ireturn

  public android.support.v4.f.b$b[] b();
    Code:
       0: aload_0
       1: getfield      #19                 // Field b:[Landroid/support/v4/f/b$b;
       4: areturn
}
