class android.support.v4.f.c$2 implements java.lang.Runnable {
  final java.util.concurrent.Callable a;

  final android.os.Handler b;

  final android.support.v4.f.c$a c;

  final android.support.v4.f.c d;

  android.support.v4.f.c$2(android.support.v4.f.c, java.util.concurrent.Callable, android.os.Handler, android.support.v4.f.c$a);
    Code:
       0: aload_0
       1: aload_1
       2: putfield      #24                 // Field d:Landroid/support/v4/f/c;
       5: aload_0
       6: aload_2
       7: putfield      #26                 // Field a:Ljava/util/concurrent/Callable;
      10: aload_0
      11: aload_3
      12: putfield      #28                 // Field b:Landroid/os/Handler;
      15: aload_0
      16: aload         4
      18: putfield      #30                 // Field c:Landroid/support/v4/f/c$a;
      21: aload_0
      22: invokespecial #33                 // Method java/lang/Object."<init>":()V
      25: return

  public void run();
    Code:
       0: aload_0
       1: getfield      #26                 // Field a:Ljava/util/concurrent/Callable;
       4: invokeinterface #43,  1           // InterfaceMethod java/util/concurrent/Callable.call:()Ljava/lang/Object;
       9: astore_1
      10: goto          15
      13: aconst_null
      14: astore_1
      15: aload_0
      16: getfield      #28                 // Field b:Landroid/os/Handler;
      19: new           #13                 // class android/support/v4/f/c$2$1
      22: dup
      23: aload_0
      24: aload_1
      25: invokespecial #46                 // Method android/support/v4/f/c$2$1."<init>":(Landroid/support/v4/f/c$2;Ljava/lang/Object;)V
      28: invokevirtual #52                 // Method android/os/Handler.post:(Ljava/lang/Runnable;)Z
      31: pop
      32: return
      33: astore_1
      34: goto          13
    Exception table:
       from    to  target type
           0    10    33   Class java/lang/Exception
}
