class android.support.v4.f.c$3 implements java.lang.Runnable {
  final java.util.concurrent.atomic.AtomicReference a;

  final java.util.concurrent.Callable b;

  final java.util.concurrent.locks.ReentrantLock c;

  final java.util.concurrent.atomic.AtomicBoolean d;

  final java.util.concurrent.locks.Condition e;

  final android.support.v4.f.c f;

  android.support.v4.f.c$3(android.support.v4.f.c, java.util.concurrent.atomic.AtomicReference, java.util.concurrent.Callable, java.util.concurrent.locks.ReentrantLock, java.util.concurrent.atomic.AtomicBoolean, java.util.concurrent.locks.Condition);
    Code:
       0: aload_0
       1: aload_1
       2: putfield      #26                 // Field f:Landroid/support/v4/f/c;
       5: aload_0
       6: aload_2
       7: putfield      #28                 // Field a:Ljava/util/concurrent/atomic/AtomicReference;
      10: aload_0
      11: aload_3
      12: putfield      #30                 // Field b:Ljava/util/concurrent/Callable;
      15: aload_0
      16: aload         4
      18: putfield      #32                 // Field c:Ljava/util/concurrent/locks/ReentrantLock;
      21: aload_0
      22: aload         5
      24: putfield      #34                 // Field d:Ljava/util/concurrent/atomic/AtomicBoolean;
      27: aload_0
      28: aload         6
      30: putfield      #36                 // Field e:Ljava/util/concurrent/locks/Condition;
      33: aload_0
      34: invokespecial #39                 // Method java/lang/Object."<init>":()V
      37: return

  public void run();
    Code:
       0: aload_0
       1: getfield      #28                 // Field a:Ljava/util/concurrent/atomic/AtomicReference;
       4: aload_0
       5: getfield      #30                 // Field b:Ljava/util/concurrent/Callable;
       8: invokeinterface #49,  1           // InterfaceMethod java/util/concurrent/Callable.call:()Ljava/lang/Object;
      13: invokevirtual #55                 // Method java/util/concurrent/atomic/AtomicReference.set:(Ljava/lang/Object;)V
      16: aload_0
      17: getfield      #32                 // Field c:Ljava/util/concurrent/locks/ReentrantLock;
      20: invokevirtual #60                 // Method java/util/concurrent/locks/ReentrantLock.lock:()V
      23: aload_0
      24: getfield      #34                 // Field d:Ljava/util/concurrent/atomic/AtomicBoolean;
      27: iconst_0
      28: invokevirtual #65                 // Method java/util/concurrent/atomic/AtomicBoolean.set:(Z)V
      31: aload_0
      32: getfield      #36                 // Field e:Ljava/util/concurrent/locks/Condition;
      35: invokeinterface #70,  1           // InterfaceMethod java/util/concurrent/locks/Condition.signal:()V
      40: aload_0
      41: getfield      #32                 // Field c:Ljava/util/concurrent/locks/ReentrantLock;
      44: invokevirtual #73                 // Method java/util/concurrent/locks/ReentrantLock.unlock:()V
      47: return
      48: astore_1
      49: aload_0
      50: getfield      #32                 // Field c:Ljava/util/concurrent/locks/ReentrantLock;
      53: invokevirtual #73                 // Method java/util/concurrent/locks/ReentrantLock.unlock:()V
      56: aload_1
      57: athrow
      58: astore_1
      59: goto          16
    Exception table:
       from    to  target type
           0    16    58   Class java/lang/Exception
          23    40    48   any
}
