class android.support.constraint.c$a {
  public int A;

  public int B;

  public int C;

  public int D;

  public int E;

  public int F;

  public int G;

  public int H;

  public int I;

  public int J;

  public int K;

  public int L;

  public int M;

  public int N;

  public int O;

  public int P;

  public float Q;

  public float R;

  public int S;

  public int T;

  public float U;

  public boolean V;

  public float W;

  public float X;

  public float Y;

  public float Z;

  boolean a;

  public float aa;

  public float ab;

  public float ac;

  public float ad;

  public float ae;

  public float af;

  public float ag;

  public boolean ah;

  public boolean ai;

  public int aj;

  public int ak;

  public int al;

  public int am;

  public int an;

  public int ao;

  public float ap;

  public float aq;

  public int ar;

  public int as;

  public int[] at;

  public int b;

  public int c;

  int d;

  public int e;

  public int f;

  public float g;

  public int h;

  public int i;

  public int j;

  public int k;

  public int l;

  public int m;

  public int n;

  public int o;

  public int p;

  public int q;

  public int r;

  public int s;

  public int t;

  public float u;

  public float v;

  public java.lang.String w;

  public int x;

  public int y;

  public float z;

  android.support.constraint.c$a(android.support.constraint.c$1);
    Code:
       0: aload_0
       1: invokespecial #226                // Method "<init>":()V
       4: return

  static void a(android.support.constraint.c$a, int, android.support.constraint.d$a);
    Code:
       0: aload_0
       1: iload_1
       2: aload_2
       3: invokespecial #356                // Method a:(ILandroid/support/constraint/d$a;)V
       6: return

  static void a(android.support.constraint.c$a, android.support.constraint.b, int, android.support.constraint.d$a);
    Code:
       0: aload_0
       1: aload_1
       2: iload_2
       3: aload_3
       4: invokespecial #371                // Method a:(Landroid/support/constraint/b;ILandroid/support/constraint/d$a;)V
       7: return

  public android.support.constraint.c$a a();
    Code:
       0: new           #2                  // class android/support/constraint/c$a
       3: dup
       4: invokespecial #226                // Method "<init>":()V
       7: astore_1
       8: aload_1
       9: aload_0
      10: getfield      #86                 // Field a:Z
      13: putfield      #86                 // Field a:Z
      16: aload_1
      17: aload_0
      18: getfield      #269                // Field b:I
      21: putfield      #269                // Field b:I
      24: aload_1
      25: aload_0
      26: getfield      #274                // Field c:I
      29: putfield      #274                // Field c:I
      32: aload_1
      33: aload_0
      34: getfield      #88                 // Field e:I
      37: putfield      #88                 // Field e:I
      40: aload_1
      41: aload_0
      42: getfield      #90                 // Field f:I
      45: putfield      #90                 // Field f:I
      48: aload_1
      49: aload_0
      50: getfield      #93                 // Field g:F
      53: putfield      #93                 // Field g:F
      56: aload_1
      57: aload_0
      58: getfield      #95                 // Field h:I
      61: putfield      #95                 // Field h:I
      64: aload_1
      65: aload_0
      66: getfield      #97                 // Field i:I
      69: putfield      #97                 // Field i:I
      72: aload_1
      73: aload_0
      74: getfield      #99                 // Field j:I
      77: putfield      #99                 // Field j:I
      80: aload_1
      81: aload_0
      82: getfield      #101                // Field k:I
      85: putfield      #101                // Field k:I
      88: aload_1
      89: aload_0
      90: getfield      #103                // Field l:I
      93: putfield      #103                // Field l:I
      96: aload_1
      97: aload_0
      98: getfield      #105                // Field m:I
     101: putfield      #105                // Field m:I
     104: aload_1
     105: aload_0
     106: getfield      #107                // Field n:I
     109: putfield      #107                // Field n:I
     112: aload_1
     113: aload_0
     114: getfield      #109                // Field o:I
     117: putfield      #109                // Field o:I
     120: aload_1
     121: aload_0
     122: getfield      #111                // Field p:I
     125: putfield      #111                // Field p:I
     128: aload_1
     129: aload_0
     130: getfield      #113                // Field q:I
     133: putfield      #113                // Field q:I
     136: aload_1
     137: aload_0
     138: getfield      #115                // Field r:I
     141: putfield      #115                // Field r:I
     144: aload_1
     145: aload_0
     146: getfield      #117                // Field s:I
     149: putfield      #117                // Field s:I
     152: aload_1
     153: aload_0
     154: getfield      #119                // Field t:I
     157: putfield      #119                // Field t:I
     160: aload_1
     161: aload_0
     162: getfield      #122                // Field u:F
     165: putfield      #122                // Field u:F
     168: aload_1
     169: aload_0
     170: getfield      #124                // Field v:F
     173: putfield      #124                // Field v:F
     176: aload_1
     177: aload_0
     178: getfield      #126                // Field w:Ljava/lang/String;
     181: putfield      #126                // Field w:Ljava/lang/String;
     184: aload_1
     185: aload_0
     186: getfield      #134                // Field A:I
     189: putfield      #134                // Field A:I
     192: aload_1
     193: aload_0
     194: getfield      #136                // Field B:I
     197: putfield      #136                // Field B:I
     200: aload_1
     201: aload_0
     202: getfield      #122                // Field u:F
     205: putfield      #122                // Field u:F
     208: aload_1
     209: aload_0
     210: getfield      #122                // Field u:F
     213: putfield      #122                // Field u:F
     216: aload_1
     217: aload_0
     218: getfield      #122                // Field u:F
     221: putfield      #122                // Field u:F
     224: aload_1
     225: aload_0
     226: getfield      #122                // Field u:F
     229: putfield      #122                // Field u:F
     232: aload_1
     233: aload_0
     234: getfield      #122                // Field u:F
     237: putfield      #122                // Field u:F
     240: aload_1
     241: aload_0
     242: getfield      #138                // Field C:I
     245: putfield      #138                // Field C:I
     248: aload_1
     249: aload_0
     250: getfield      #140                // Field D:I
     253: putfield      #140                // Field D:I
     256: aload_1
     257: aload_0
     258: getfield      #142                // Field E:I
     261: putfield      #142                // Field E:I
     264: aload_1
     265: aload_0
     266: getfield      #144                // Field F:I
     269: putfield      #144                // Field F:I
     272: aload_1
     273: aload_0
     274: getfield      #146                // Field G:I
     277: putfield      #146                // Field G:I
     280: aload_1
     281: aload_0
     282: getfield      #148                // Field H:I
     285: putfield      #148                // Field H:I
     288: aload_1
     289: aload_0
     290: getfield      #150                // Field I:I
     293: putfield      #150                // Field I:I
     296: aload_1
     297: aload_0
     298: getfield      #152                // Field J:I
     301: putfield      #152                // Field J:I
     304: aload_1
     305: aload_0
     306: getfield      #154                // Field K:I
     309: putfield      #154                // Field K:I
     312: aload_1
     313: aload_0
     314: getfield      #156                // Field L:I
     317: putfield      #156                // Field L:I
     320: aload_1
     321: aload_0
     322: getfield      #158                // Field M:I
     325: putfield      #158                // Field M:I
     328: aload_1
     329: aload_0
     330: getfield      #160                // Field N:I
     333: putfield      #160                // Field N:I
     336: aload_1
     337: aload_0
     338: getfield      #162                // Field O:I
     341: putfield      #162                // Field O:I
     344: aload_1
     345: aload_0
     346: getfield      #164                // Field P:I
     349: putfield      #164                // Field P:I
     352: aload_1
     353: aload_0
     354: getfield      #166                // Field Q:F
     357: putfield      #166                // Field Q:F
     360: aload_1
     361: aload_0
     362: getfield      #168                // Field R:F
     365: putfield      #168                // Field R:F
     368: aload_1
     369: aload_0
     370: getfield      #170                // Field S:I
     373: putfield      #170                // Field S:I
     376: aload_1
     377: aload_0
     378: getfield      #172                // Field T:I
     381: putfield      #172                // Field T:I
     384: aload_1
     385: aload_0
     386: getfield      #174                // Field U:F
     389: putfield      #174                // Field U:F
     392: aload_1
     393: aload_0
     394: getfield      #176                // Field V:Z
     397: putfield      #176                // Field V:Z
     400: aload_1
     401: aload_0
     402: getfield      #178                // Field W:F
     405: putfield      #178                // Field W:F
     408: aload_1
     409: aload_0
     410: getfield      #180                // Field X:F
     413: putfield      #180                // Field X:F
     416: aload_1
     417: aload_0
     418: getfield      #182                // Field Y:F
     421: putfield      #182                // Field Y:F
     424: aload_1
     425: aload_0
     426: getfield      #184                // Field Z:F
     429: putfield      #184                // Field Z:F
     432: aload_1
     433: aload_0
     434: getfield      #186                // Field aa:F
     437: putfield      #186                // Field aa:F
     440: aload_1
     441: aload_0
     442: getfield      #188                // Field ab:F
     445: putfield      #188                // Field ab:F
     448: aload_1
     449: aload_0
     450: getfield      #191                // Field ac:F
     453: putfield      #191                // Field ac:F
     456: aload_1
     457: aload_0
     458: getfield      #193                // Field ad:F
     461: putfield      #193                // Field ad:F
     464: aload_1
     465: aload_0
     466: getfield      #195                // Field ae:F
     469: putfield      #195                // Field ae:F
     472: aload_1
     473: aload_0
     474: getfield      #197                // Field af:F
     477: putfield      #197                // Field af:F
     480: aload_1
     481: aload_0
     482: getfield      #199                // Field ag:F
     485: putfield      #199                // Field ag:F
     488: aload_1
     489: aload_0
     490: getfield      #201                // Field ah:Z
     493: putfield      #201                // Field ah:Z
     496: aload_1
     497: aload_0
     498: getfield      #203                // Field ai:Z
     501: putfield      #203                // Field ai:Z
     504: aload_1
     505: aload_0
     506: getfield      #205                // Field aj:I
     509: putfield      #205                // Field aj:I
     512: aload_1
     513: aload_0
     514: getfield      #207                // Field ak:I
     517: putfield      #207                // Field ak:I
     520: aload_1
     521: aload_0
     522: getfield      #209                // Field al:I
     525: putfield      #209                // Field al:I
     528: aload_1
     529: aload_0
     530: getfield      #211                // Field am:I
     533: putfield      #211                // Field am:I
     536: aload_1
     537: aload_0
     538: getfield      #213                // Field an:I
     541: putfield      #213                // Field an:I
     544: aload_1
     545: aload_0
     546: getfield      #215                // Field ao:I
     549: putfield      #215                // Field ao:I
     552: aload_1
     553: aload_0
     554: getfield      #217                // Field ap:F
     557: putfield      #217                // Field ap:F
     560: aload_1
     561: aload_0
     562: getfield      #219                // Field aq:F
     565: putfield      #219                // Field aq:F
     568: aload_1
     569: aload_0
     570: getfield      #221                // Field ar:I
     573: putfield      #221                // Field ar:I
     576: aload_1
     577: aload_0
     578: getfield      #223                // Field as:I
     581: putfield      #223                // Field as:I
     584: aload_0
     585: getfield      #367                // Field at:[I
     588: ifnull        607
     591: aload_1
     592: aload_0
     593: getfield      #367                // Field at:[I
     596: aload_0
     597: getfield      #367                // Field at:[I
     600: arraylength
     601: invokestatic  #378                // Method java/util/Arrays.copyOf:([II)[I
     604: putfield      #367                // Field at:[I
     607: aload_1
     608: aload_0
     609: getfield      #128                // Field x:I
     612: putfield      #128                // Field x:I
     615: aload_1
     616: aload_0
     617: getfield      #130                // Field y:I
     620: putfield      #130                // Field y:I
     623: aload_1
     624: aload_0
     625: getfield      #132                // Field z:F
     628: putfield      #132                // Field z:F
     631: aload_1
     632: areturn

  public void a(android.support.constraint.ConstraintLayout$a);
    Code:
       0: aload_1
       1: aload_0
       2: getfield      #95                 // Field h:I
       5: putfield      #232                // Field android/support/constraint/ConstraintLayout$a.d:I
       8: aload_1
       9: aload_0
      10: getfield      #97                 // Field i:I
      13: putfield      #233                // Field android/support/constraint/ConstraintLayout$a.e:I
      16: aload_1
      17: aload_0
      18: getfield      #99                 // Field j:I
      21: putfield      #234                // Field android/support/constraint/ConstraintLayout$a.f:I
      24: aload_1
      25: aload_0
      26: getfield      #101                // Field k:I
      29: putfield      #236                // Field android/support/constraint/ConstraintLayout$a.g:I
      32: aload_1
      33: aload_0
      34: getfield      #103                // Field l:I
      37: putfield      #237                // Field android/support/constraint/ConstraintLayout$a.h:I
      40: aload_1
      41: aload_0
      42: getfield      #105                // Field m:I
      45: putfield      #238                // Field android/support/constraint/ConstraintLayout$a.i:I
      48: aload_1
      49: aload_0
      50: getfield      #107                // Field n:I
      53: putfield      #239                // Field android/support/constraint/ConstraintLayout$a.j:I
      56: aload_1
      57: aload_0
      58: getfield      #109                // Field o:I
      61: putfield      #240                // Field android/support/constraint/ConstraintLayout$a.k:I
      64: aload_1
      65: aload_0
      66: getfield      #111                // Field p:I
      69: putfield      #241                // Field android/support/constraint/ConstraintLayout$a.l:I
      72: aload_1
      73: aload_0
      74: getfield      #113                // Field q:I
      77: putfield      #242                // Field android/support/constraint/ConstraintLayout$a.p:I
      80: aload_1
      81: aload_0
      82: getfield      #115                // Field r:I
      85: putfield      #243                // Field android/support/constraint/ConstraintLayout$a.q:I
      88: aload_1
      89: aload_0
      90: getfield      #117                // Field s:I
      93: putfield      #244                // Field android/support/constraint/ConstraintLayout$a.r:I
      96: aload_1
      97: aload_0
      98: getfield      #119                // Field t:I
     101: putfield      #245                // Field android/support/constraint/ConstraintLayout$a.s:I
     104: aload_1
     105: aload_0
     106: getfield      #140                // Field D:I
     109: putfield      #277                // Field android/support/constraint/ConstraintLayout$a.leftMargin:I
     112: aload_1
     113: aload_0
     114: getfield      #142                // Field E:I
     117: putfield      #280                // Field android/support/constraint/ConstraintLayout$a.rightMargin:I
     120: aload_1
     121: aload_0
     122: getfield      #144                // Field F:I
     125: putfield      #283                // Field android/support/constraint/ConstraintLayout$a.topMargin:I
     128: aload_1
     129: aload_0
     130: getfield      #146                // Field G:I
     133: putfield      #286                // Field android/support/constraint/ConstraintLayout$a.bottomMargin:I
     136: aload_1
     137: aload_0
     138: getfield      #164                // Field P:I
     141: putfield      #380                // Field android/support/constraint/ConstraintLayout$a.x:I
     144: aload_1
     145: aload_0
     146: getfield      #162                // Field O:I
     149: putfield      #381                // Field android/support/constraint/ConstraintLayout$a.y:I
     152: aload_1
     153: aload_0
     154: getfield      #122                // Field u:F
     157: putfield      #246                // Field android/support/constraint/ConstraintLayout$a.z:F
     160: aload_1
     161: aload_0
     162: getfield      #124                // Field v:F
     165: putfield      #248                // Field android/support/constraint/ConstraintLayout$a.A:F
     168: aload_1
     169: aload_0
     170: getfield      #128                // Field x:I
     173: putfield      #251                // Field android/support/constraint/ConstraintLayout$a.m:I
     176: aload_1
     177: aload_0
     178: getfield      #130                // Field y:I
     181: putfield      #252                // Field android/support/constraint/ConstraintLayout$a.n:I
     184: aload_1
     185: aload_0
     186: getfield      #132                // Field z:F
     189: putfield      #254                // Field android/support/constraint/ConstraintLayout$a.o:F
     192: aload_1
     193: aload_0
     194: getfield      #126                // Field w:Ljava/lang/String;
     197: putfield      #250                // Field android/support/constraint/ConstraintLayout$a.B:Ljava/lang/String;
     200: aload_1
     201: aload_0
     202: getfield      #134                // Field A:I
     205: putfield      #256                // Field android/support/constraint/ConstraintLayout$a.Q:I
     208: aload_1
     209: aload_0
     210: getfield      #136                // Field B:I
     213: putfield      #258                // Field android/support/constraint/ConstraintLayout$a.R:I
     216: aload_1
     217: aload_0
     218: getfield      #166                // Field Q:F
     221: putfield      #288                // Field android/support/constraint/ConstraintLayout$a.F:F
     224: aload_1
     225: aload_0
     226: getfield      #168                // Field R:F
     229: putfield      #290                // Field android/support/constraint/ConstraintLayout$a.E:F
     232: aload_1
     233: aload_0
     234: getfield      #172                // Field T:I
     237: putfield      #291                // Field android/support/constraint/ConstraintLayout$a.H:I
     240: aload_1
     241: aload_0
     242: getfield      #170                // Field S:I
     245: putfield      #292                // Field android/support/constraint/ConstraintLayout$a.G:I
     248: aload_1
     249: aload_0
     250: getfield      #201                // Field ah:Z
     253: putfield      #294                // Field android/support/constraint/ConstraintLayout$a.T:Z
     256: aload_1
     257: aload_0
     258: getfield      #203                // Field ai:Z
     261: putfield      #296                // Field android/support/constraint/ConstraintLayout$a.U:Z
     264: aload_1
     265: aload_0
     266: getfield      #205                // Field aj:I
     269: putfield      #297                // Field android/support/constraint/ConstraintLayout$a.I:I
     272: aload_1
     273: aload_0
     274: getfield      #207                // Field ak:I
     277: putfield      #298                // Field android/support/constraint/ConstraintLayout$a.J:I
     280: aload_1
     281: aload_0
     282: getfield      #209                // Field al:I
     285: putfield      #299                // Field android/support/constraint/ConstraintLayout$a.M:I
     288: aload_1
     289: aload_0
     290: getfield      #211                // Field am:I
     293: putfield      #300                // Field android/support/constraint/ConstraintLayout$a.N:I
     296: aload_1
     297: aload_0
     298: getfield      #213                // Field an:I
     301: putfield      #301                // Field android/support/constraint/ConstraintLayout$a.K:I
     304: aload_1
     305: aload_0
     306: getfield      #215                // Field ao:I
     309: putfield      #302                // Field android/support/constraint/ConstraintLayout$a.L:I
     312: aload_1
     313: aload_0
     314: getfield      #217                // Field ap:F
     317: putfield      #304                // Field android/support/constraint/ConstraintLayout$a.O:F
     320: aload_1
     321: aload_0
     322: getfield      #219                // Field aq:F
     325: putfield      #306                // Field android/support/constraint/ConstraintLayout$a.P:F
     328: aload_1
     329: aload_0
     330: getfield      #138                // Field C:I
     333: putfield      #259                // Field android/support/constraint/ConstraintLayout$a.S:I
     336: aload_1
     337: aload_0
     338: getfield      #93                 // Field g:F
     341: putfield      #261                // Field android/support/constraint/ConstraintLayout$a.c:F
     344: aload_1
     345: aload_0
     346: getfield      #88                 // Field e:I
     349: putfield      #263                // Field android/support/constraint/ConstraintLayout$a.a:I
     352: aload_1
     353: aload_0
     354: getfield      #90                 // Field f:I
     357: putfield      #265                // Field android/support/constraint/ConstraintLayout$a.b:I
     360: aload_1
     361: aload_0
     362: getfield      #269                // Field b:I
     365: putfield      #268                // Field android/support/constraint/ConstraintLayout$a.width:I
     368: aload_1
     369: aload_0
     370: getfield      #274                // Field c:I
     373: putfield      #272                // Field android/support/constraint/ConstraintLayout$a.height:I
     376: getstatic     #311                // Field android/os/Build$VERSION.SDK_INT:I
     379: bipush        17
     381: if_icmplt     400
     384: aload_1
     385: aload_0
     386: getfield      #150                // Field I:I
     389: invokevirtual #385                // Method android/support/constraint/ConstraintLayout$a.setMarginStart:(I)V
     392: aload_1
     393: aload_0
     394: getfield      #148                // Field H:I
     397: invokevirtual #388                // Method android/support/constraint/ConstraintLayout$a.setMarginEnd:(I)V
     400: aload_1
     401: invokevirtual #390                // Method android/support/constraint/ConstraintLayout$a.a:()V
     404: return

  public java.lang.Object clone();
    Code:
       0: aload_0
       1: invokevirtual #394                // Method a:()Landroid/support/constraint/c$a;
       4: areturn
}
