public class android.support.constraint.c {
  static {};
    Code:
       0: iconst_3
       1: newarray       int
       3: dup
       4: iconst_0
       5: iconst_0
       6: iastore
       7: dup
       8: iconst_1
       9: iconst_4
      10: iastore
      11: dup
      12: iconst_2
      13: bipush        8
      15: iastore
      16: putstatic     #19                 // Field a:[I
      19: new           #21                 // class android/util/SparseIntArray
      22: dup
      23: invokespecial #24                 // Method android/util/SparseIntArray."<init>":()V
      26: putstatic     #26                 // Field c:Landroid/util/SparseIntArray;
      29: getstatic     #26                 // Field c:Landroid/util/SparseIntArray;
      32: getstatic     #32                 // Field android/support/constraint/f$b.ConstraintSet_layout_constraintLeft_toLeftOf:I
      35: bipush        25
      37: invokevirtual #36                 // Method android/util/SparseIntArray.append:(II)V
      40: getstatic     #26                 // Field c:Landroid/util/SparseIntArray;
      43: getstatic     #39                 // Field android/support/constraint/f$b.ConstraintSet_layout_constraintLeft_toRightOf:I
      46: bipush        26
      48: invokevirtual #36                 // Method android/util/SparseIntArray.append:(II)V
      51: getstatic     #26                 // Field c:Landroid/util/SparseIntArray;
      54: getstatic     #42                 // Field android/support/constraint/f$b.ConstraintSet_layout_constraintRight_toLeftOf:I
      57: bipush        29
      59: invokevirtual #36                 // Method android/util/SparseIntArray.append:(II)V
      62: getstatic     #26                 // Field c:Landroid/util/SparseIntArray;
      65: getstatic     #45                 // Field android/support/constraint/f$b.ConstraintSet_layout_constraintRight_toRightOf:I
      68: bipush        30
      70: invokevirtual #36                 // Method android/util/SparseIntArray.append:(II)V
      73: getstatic     #26                 // Field c:Landroid/util/SparseIntArray;
      76: getstatic     #48                 // Field android/support/constraint/f$b.ConstraintSet_layout_constraintTop_toTopOf:I
      79: bipush        36
      81: invokevirtual #36                 // Method android/util/SparseIntArray.append:(II)V
      84: getstatic     #26                 // Field c:Landroid/util/SparseIntArray;
      87: getstatic     #51                 // Field android/support/constraint/f$b.ConstraintSet_layout_constraintTop_toBottomOf:I
      90: bipush        35
      92: invokevirtual #36                 // Method android/util/SparseIntArray.append:(II)V
      95: getstatic     #26                 // Field c:Landroid/util/SparseIntArray;
      98: getstatic     #54                 // Field android/support/constraint/f$b.ConstraintSet_layout_constraintBottom_toTopOf:I
     101: iconst_4
     102: invokevirtual #36                 // Method android/util/SparseIntArray.append:(II)V
     105: getstatic     #26                 // Field c:Landroid/util/SparseIntArray;
     108: getstatic     #57                 // Field android/support/constraint/f$b.ConstraintSet_layout_constraintBottom_toBottomOf:I
     111: iconst_3
     112: invokevirtual #36                 // Method android/util/SparseIntArray.append:(II)V
     115: getstatic     #26                 // Field c:Landroid/util/SparseIntArray;
     118: getstatic     #60                 // Field android/support/constraint/f$b.ConstraintSet_layout_constraintBaseline_toBaselineOf:I
     121: iconst_1
     122: invokevirtual #36                 // Method android/util/SparseIntArray.append:(II)V
     125: getstatic     #26                 // Field c:Landroid/util/SparseIntArray;
     128: getstatic     #63                 // Field android/support/constraint/f$b.ConstraintSet_layout_editor_absoluteX:I
     131: bipush        6
     133: invokevirtual #36                 // Method android/util/SparseIntArray.append:(II)V
     136: getstatic     #26                 // Field c:Landroid/util/SparseIntArray;
     139: getstatic     #66                 // Field android/support/constraint/f$b.ConstraintSet_layout_editor_absoluteY:I
     142: bipush        7
     144: invokevirtual #36                 // Method android/util/SparseIntArray.append:(II)V
     147: getstatic     #26                 // Field c:Landroid/util/SparseIntArray;
     150: getstatic     #69                 // Field android/support/constraint/f$b.ConstraintSet_layout_constraintGuide_begin:I
     153: bipush        17
     155: invokevirtual #36                 // Method android/util/SparseIntArray.append:(II)V
     158: getstatic     #26                 // Field c:Landroid/util/SparseIntArray;
     161: getstatic     #72                 // Field android/support/constraint/f$b.ConstraintSet_layout_constraintGuide_end:I
     164: bipush        18
     166: invokevirtual #36                 // Method android/util/SparseIntArray.append:(II)V
     169: getstatic     #26                 // Field c:Landroid/util/SparseIntArray;
     172: getstatic     #75                 // Field android/support/constraint/f$b.ConstraintSet_layout_constraintGuide_percent:I
     175: bipush        19
     177: invokevirtual #36                 // Method android/util/SparseIntArray.append:(II)V
     180: getstatic     #26                 // Field c:Landroid/util/SparseIntArray;
     183: getstatic     #78                 // Field android/support/constraint/f$b.ConstraintSet_android_orientation:I
     186: bipush        27
     188: invokevirtual #36                 // Method android/util/SparseIntArray.append:(II)V
     191: getstatic     #26                 // Field c:Landroid/util/SparseIntArray;
     194: getstatic     #81                 // Field android/support/constraint/f$b.ConstraintSet_layout_constraintStart_toEndOf:I
     197: bipush        32
     199: invokevirtual #36                 // Method android/util/SparseIntArray.append:(II)V
     202: getstatic     #26                 // Field c:Landroid/util/SparseIntArray;
     205: getstatic     #84                 // Field android/support/constraint/f$b.ConstraintSet_layout_constraintStart_toStartOf:I
     208: bipush        33
     210: invokevirtual #36                 // Method android/util/SparseIntArray.append:(II)V
     213: getstatic     #26                 // Field c:Landroid/util/SparseIntArray;
     216: getstatic     #87                 // Field android/support/constraint/f$b.ConstraintSet_layout_constraintEnd_toStartOf:I
     219: bipush        10
     221: invokevirtual #36                 // Method android/util/SparseIntArray.append:(II)V
     224: getstatic     #26                 // Field c:Landroid/util/SparseIntArray;
     227: getstatic     #90                 // Field android/support/constraint/f$b.ConstraintSet_layout_constraintEnd_toEndOf:I
     230: bipush        9
     232: invokevirtual #36                 // Method android/util/SparseIntArray.append:(II)V
     235: getstatic     #26                 // Field c:Landroid/util/SparseIntArray;
     238: getstatic     #93                 // Field android/support/constraint/f$b.ConstraintSet_layout_goneMarginLeft:I
     241: bipush        13
     243: invokevirtual #36                 // Method android/util/SparseIntArray.append:(II)V
     246: getstatic     #26                 // Field c:Landroid/util/SparseIntArray;
     249: getstatic     #96                 // Field android/support/constraint/f$b.ConstraintSet_layout_goneMarginTop:I
     252: bipush        16
     254: invokevirtual #36                 // Method android/util/SparseIntArray.append:(II)V
     257: getstatic     #26                 // Field c:Landroid/util/SparseIntArray;
     260: getstatic     #99                 // Field android/support/constraint/f$b.ConstraintSet_layout_goneMarginRight:I
     263: bipush        14
     265: invokevirtual #36                 // Method android/util/SparseIntArray.append:(II)V
     268: getstatic     #26                 // Field c:Landroid/util/SparseIntArray;
     271: getstatic     #102                // Field android/support/constraint/f$b.ConstraintSet_layout_goneMarginBottom:I
     274: bipush        11
     276: invokevirtual #36                 // Method android/util/SparseIntArray.append:(II)V
     279: getstatic     #26                 // Field c:Landroid/util/SparseIntArray;
     282: getstatic     #105                // Field android/support/constraint/f$b.ConstraintSet_layout_goneMarginStart:I
     285: bipush        15
     287: invokevirtual #36                 // Method android/util/SparseIntArray.append:(II)V
     290: getstatic     #26                 // Field c:Landroid/util/SparseIntArray;
     293: getstatic     #108                // Field android/support/constraint/f$b.ConstraintSet_layout_goneMarginEnd:I
     296: bipush        12
     298: invokevirtual #36                 // Method android/util/SparseIntArray.append:(II)V
     301: getstatic     #26                 // Field c:Landroid/util/SparseIntArray;
     304: getstatic     #111                // Field android/support/constraint/f$b.ConstraintSet_layout_constraintVertical_weight:I
     307: bipush        40
     309: invokevirtual #36                 // Method android/util/SparseIntArray.append:(II)V
     312: getstatic     #26                 // Field c:Landroid/util/SparseIntArray;
     315: getstatic     #114                // Field android/support/constraint/f$b.ConstraintSet_layout_constraintHorizontal_weight:I
     318: bipush        39
     320: invokevirtual #36                 // Method android/util/SparseIntArray.append:(II)V
     323: getstatic     #26                 // Field c:Landroid/util/SparseIntArray;
     326: getstatic     #117                // Field android/support/constraint/f$b.ConstraintSet_layout_constraintHorizontal_chainStyle:I
     329: bipush        41
     331: invokevirtual #36                 // Method android/util/SparseIntArray.append:(II)V
     334: getstatic     #26                 // Field c:Landroid/util/SparseIntArray;
     337: getstatic     #120                // Field android/support/constraint/f$b.ConstraintSet_layout_constraintVertical_chainStyle:I
     340: bipush        42
     342: invokevirtual #36                 // Method android/util/SparseIntArray.append:(II)V
     345: getstatic     #26                 // Field c:Landroid/util/SparseIntArray;
     348: getstatic     #123                // Field android/support/constraint/f$b.ConstraintSet_layout_constraintHorizontal_bias:I
     351: bipush        20
     353: invokevirtual #36                 // Method android/util/SparseIntArray.append:(II)V
     356: getstatic     #26                 // Field c:Landroid/util/SparseIntArray;
     359: getstatic     #126                // Field android/support/constraint/f$b.ConstraintSet_layout_constraintVertical_bias:I
     362: bipush        37
     364: invokevirtual #36                 // Method android/util/SparseIntArray.append:(II)V
     367: getstatic     #26                 // Field c:Landroid/util/SparseIntArray;
     370: getstatic     #129                // Field android/support/constraint/f$b.ConstraintSet_layout_constraintDimensionRatio:I
     373: iconst_5
     374: invokevirtual #36                 // Method android/util/SparseIntArray.append:(II)V
     377: getstatic     #26                 // Field c:Landroid/util/SparseIntArray;
     380: getstatic     #132                // Field android/support/constraint/f$b.ConstraintSet_layout_constraintLeft_creator:I
     383: bipush        64
     385: invokevirtual #36                 // Method android/util/SparseIntArray.append:(II)V
     388: getstatic     #26                 // Field c:Landroid/util/SparseIntArray;
     391: getstatic     #135                // Field android/support/constraint/f$b.ConstraintSet_layout_constraintTop_creator:I
     394: bipush        64
     396: invokevirtual #36                 // Method android/util/SparseIntArray.append:(II)V
     399: getstatic     #26                 // Field c:Landroid/util/SparseIntArray;
     402: getstatic     #138                // Field android/support/constraint/f$b.ConstraintSet_layout_constraintRight_creator:I
     405: bipush        64
     407: invokevirtual #36                 // Method android/util/SparseIntArray.append:(II)V
     410: getstatic     #26                 // Field c:Landroid/util/SparseIntArray;
     413: getstatic     #141                // Field android/support/constraint/f$b.ConstraintSet_layout_constraintBottom_creator:I
     416: bipush        64
     418: invokevirtual #36                 // Method android/util/SparseIntArray.append:(II)V
     421: getstatic     #26                 // Field c:Landroid/util/SparseIntArray;
     424: getstatic     #144                // Field android/support/constraint/f$b.ConstraintSet_layout_constraintBaseline_creator:I
     427: bipush        64
     429: invokevirtual #36                 // Method android/util/SparseIntArray.append:(II)V
     432: getstatic     #26                 // Field c:Landroid/util/SparseIntArray;
     435: getstatic     #147                // Field android/support/constraint/f$b.ConstraintSet_android_layout_marginLeft:I
     438: bipush        24
     440: invokevirtual #36                 // Method android/util/SparseIntArray.append:(II)V
     443: getstatic     #26                 // Field c:Landroid/util/SparseIntArray;
     446: getstatic     #150                // Field android/support/constraint/f$b.ConstraintSet_android_layout_marginRight:I
     449: bipush        28
     451: invokevirtual #36                 // Method android/util/SparseIntArray.append:(II)V
     454: getstatic     #26                 // Field c:Landroid/util/SparseIntArray;
     457: getstatic     #153                // Field android/support/constraint/f$b.ConstraintSet_android_layout_marginStart:I
     460: bipush        31
     462: invokevirtual #36                 // Method android/util/SparseIntArray.append:(II)V
     465: getstatic     #26                 // Field c:Landroid/util/SparseIntArray;
     468: getstatic     #156                // Field android/support/constraint/f$b.ConstraintSet_android_layout_marginEnd:I
     471: bipush        8
     473: invokevirtual #36                 // Method android/util/SparseIntArray.append:(II)V
     476: getstatic     #26                 // Field c:Landroid/util/SparseIntArray;
     479: getstatic     #159                // Field android/support/constraint/f$b.ConstraintSet_android_layout_marginTop:I
     482: bipush        34
     484: invokevirtual #36                 // Method android/util/SparseIntArray.append:(II)V
     487: getstatic     #26                 // Field c:Landroid/util/SparseIntArray;
     490: getstatic     #162                // Field android/support/constraint/f$b.ConstraintSet_android_layout_marginBottom:I
     493: iconst_2
     494: invokevirtual #36                 // Method android/util/SparseIntArray.append:(II)V
     497: getstatic     #26                 // Field c:Landroid/util/SparseIntArray;
     500: getstatic     #165                // Field android/support/constraint/f$b.ConstraintSet_android_layout_width:I
     503: bipush        23
     505: invokevirtual #36                 // Method android/util/SparseIntArray.append:(II)V
     508: getstatic     #26                 // Field c:Landroid/util/SparseIntArray;
     511: getstatic     #168                // Field android/support/constraint/f$b.ConstraintSet_android_layout_height:I
     514: bipush        21
     516: invokevirtual #36                 // Method android/util/SparseIntArray.append:(II)V
     519: getstatic     #26                 // Field c:Landroid/util/SparseIntArray;
     522: getstatic     #171                // Field android/support/constraint/f$b.ConstraintSet_android_visibility:I
     525: bipush        22
     527: invokevirtual #36                 // Method android/util/SparseIntArray.append:(II)V
     530: getstatic     #26                 // Field c:Landroid/util/SparseIntArray;
     533: getstatic     #174                // Field android/support/constraint/f$b.ConstraintSet_android_alpha:I
     536: bipush        43
     538: invokevirtual #36                 // Method android/util/SparseIntArray.append:(II)V
     541: getstatic     #26                 // Field c:Landroid/util/SparseIntArray;
     544: getstatic     #177                // Field android/support/constraint/f$b.ConstraintSet_android_elevation:I
     547: bipush        44
     549: invokevirtual #36                 // Method android/util/SparseIntArray.append:(II)V
     552: getstatic     #26                 // Field c:Landroid/util/SparseIntArray;
     555: getstatic     #180                // Field android/support/constraint/f$b.ConstraintSet_android_rotationX:I
     558: bipush        45
     560: invokevirtual #36                 // Method android/util/SparseIntArray.append:(II)V
     563: getstatic     #26                 // Field c:Landroid/util/SparseIntArray;
     566: getstatic     #183                // Field android/support/constraint/f$b.ConstraintSet_android_rotationY:I
     569: bipush        46
     571: invokevirtual #36                 // Method android/util/SparseIntArray.append:(II)V
     574: getstatic     #26                 // Field c:Landroid/util/SparseIntArray;
     577: getstatic     #186                // Field android/support/constraint/f$b.ConstraintSet_android_rotation:I
     580: bipush        60
     582: invokevirtual #36                 // Method android/util/SparseIntArray.append:(II)V
     585: getstatic     #26                 // Field c:Landroid/util/SparseIntArray;
     588: getstatic     #189                // Field android/support/constraint/f$b.ConstraintSet_android_scaleX:I
     591: bipush        47
     593: invokevirtual #36                 // Method android/util/SparseIntArray.append:(II)V
     596: getstatic     #26                 // Field c:Landroid/util/SparseIntArray;
     599: getstatic     #192                // Field android/support/constraint/f$b.ConstraintSet_android_scaleY:I
     602: bipush        48
     604: invokevirtual #36                 // Method android/util/SparseIntArray.append:(II)V
     607: getstatic     #26                 // Field c:Landroid/util/SparseIntArray;
     610: getstatic     #195                // Field android/support/constraint/f$b.ConstraintSet_android_transformPivotX:I
     613: bipush        49
     615: invokevirtual #36                 // Method android/util/SparseIntArray.append:(II)V
     618: getstatic     #26                 // Field c:Landroid/util/SparseIntArray;
     621: getstatic     #198                // Field android/support/constraint/f$b.ConstraintSet_android_transformPivotY:I
     624: bipush        50
     626: invokevirtual #36                 // Method android/util/SparseIntArray.append:(II)V
     629: getstatic     #26                 // Field c:Landroid/util/SparseIntArray;
     632: getstatic     #201                // Field android/support/constraint/f$b.ConstraintSet_android_translationX:I
     635: bipush        51
     637: invokevirtual #36                 // Method android/util/SparseIntArray.append:(II)V
     640: getstatic     #26                 // Field c:Landroid/util/SparseIntArray;
     643: getstatic     #204                // Field android/support/constraint/f$b.ConstraintSet_android_translationY:I
     646: bipush        52
     648: invokevirtual #36                 // Method android/util/SparseIntArray.append:(II)V
     651: getstatic     #26                 // Field c:Landroid/util/SparseIntArray;
     654: getstatic     #207                // Field android/support/constraint/f$b.ConstraintSet_android_translationZ:I
     657: bipush        53
     659: invokevirtual #36                 // Method android/util/SparseIntArray.append:(II)V
     662: getstatic     #26                 // Field c:Landroid/util/SparseIntArray;
     665: getstatic     #210                // Field android/support/constraint/f$b.ConstraintSet_layout_constraintWidth_default:I
     668: bipush        54
     670: invokevirtual #36                 // Method android/util/SparseIntArray.append:(II)V
     673: getstatic     #26                 // Field c:Landroid/util/SparseIntArray;
     676: getstatic     #213                // Field android/support/constraint/f$b.ConstraintSet_layout_constraintHeight_default:I
     679: bipush        55
     681: invokevirtual #36                 // Method android/util/SparseIntArray.append:(II)V
     684: getstatic     #26                 // Field c:Landroid/util/SparseIntArray;
     687: getstatic     #216                // Field android/support/constraint/f$b.ConstraintSet_layout_constraintWidth_max:I
     690: bipush        56
     692: invokevirtual #36                 // Method android/util/SparseIntArray.append:(II)V
     695: getstatic     #26                 // Field c:Landroid/util/SparseIntArray;
     698: getstatic     #219                // Field android/support/constraint/f$b.ConstraintSet_layout_constraintHeight_max:I
     701: bipush        57
     703: invokevirtual #36                 // Method android/util/SparseIntArray.append:(II)V
     706: getstatic     #26                 // Field c:Landroid/util/SparseIntArray;
     709: getstatic     #222                // Field android/support/constraint/f$b.ConstraintSet_layout_constraintWidth_min:I
     712: bipush        58
     714: invokevirtual #36                 // Method android/util/SparseIntArray.append:(II)V
     717: getstatic     #26                 // Field c:Landroid/util/SparseIntArray;
     720: getstatic     #225                // Field android/support/constraint/f$b.ConstraintSet_layout_constraintHeight_min:I
     723: bipush        59
     725: invokevirtual #36                 // Method android/util/SparseIntArray.append:(II)V
     728: getstatic     #26                 // Field c:Landroid/util/SparseIntArray;
     731: getstatic     #228                // Field android/support/constraint/f$b.ConstraintSet_layout_constraintCircle:I
     734: bipush        61
     736: invokevirtual #36                 // Method android/util/SparseIntArray.append:(II)V
     739: getstatic     #26                 // Field c:Landroid/util/SparseIntArray;
     742: getstatic     #231                // Field android/support/constraint/f$b.ConstraintSet_layout_constraintCircleRadius:I
     745: bipush        62
     747: invokevirtual #36                 // Method android/util/SparseIntArray.append:(II)V
     750: getstatic     #26                 // Field c:Landroid/util/SparseIntArray;
     753: getstatic     #234                // Field android/support/constraint/f$b.ConstraintSet_layout_constraintCircleAngle:I
     756: bipush        63
     758: invokevirtual #36                 // Method android/util/SparseIntArray.append:(II)V
     761: getstatic     #26                 // Field c:Landroid/util/SparseIntArray;
     764: getstatic     #237                // Field android/support/constraint/f$b.ConstraintSet_android_id:I
     767: bipush        38
     769: invokevirtual #36                 // Method android/util/SparseIntArray.append:(II)V
     772: return

  public android.support.constraint.c();
    Code:
       0: aload_0
       1: invokespecial #239                // Method java/lang/Object."<init>":()V
       4: aload_0
       5: new           #241                // class java/util/HashMap
       8: dup
       9: invokespecial #242                // Method java/util/HashMap."<init>":()V
      12: putfield      #244                // Field b:Ljava/util/HashMap;
      15: return

  public void a(android.content.Context, int);
    Code:
       0: aload_1
       1: invokevirtual #517                // Method android/content/Context.getResources:()Landroid/content/res/Resources;
       4: iload_2
       5: invokevirtual #523                // Method android/content/res/Resources.getXml:(I)Landroid/content/res/XmlResourceParser;
       8: astore_3
       9: aload_3
      10: invokeinterface #528,  1          // InterfaceMethod org/xmlpull/v1/XmlPullParser.getEventType:()I
      15: istore_2
      16: goto          99
      19: aload_3
      20: invokeinterface #531,  1          // InterfaceMethod org/xmlpull/v1/XmlPullParser.getName:()Ljava/lang/String;
      25: astore        4
      27: aload_0
      28: aload_1
      29: aload_3
      30: invokestatic  #537                // Method android/util/Xml.asAttributeSet:(Lorg/xmlpull/v1/XmlPullParser;)Landroid/util/AttributeSet;
      33: invokespecial #539                // Method a:(Landroid/content/Context;Landroid/util/AttributeSet;)Landroid/support/constraint/c$a;
      36: astore        5
      38: aload         4
      40: ldc_w         #541                // String Guideline
      43: invokevirtual #547                // Method java/lang/String.equalsIgnoreCase:(Ljava/lang/String;)Z
      46: ifeq          55
      49: aload         5
      51: iconst_1
      52: putfield      #549                // Field android/support/constraint/c$a.a:Z
      55: aload_0
      56: getfield      #244                // Field b:Ljava/util/HashMap;
      59: aload         5
      61: getfield      #392                // Field android/support/constraint/c$a.d:I
      64: invokestatic  #553                // Method java/lang/Integer.valueOf:(I)Ljava/lang/Integer;
      67: aload         5
      69: invokevirtual #557                // Method java/util/HashMap.put:(Ljava/lang/Object;Ljava/lang/Object;)Ljava/lang/Object;
      72: pop
      73: goto          83
      76: aload_3
      77: invokeinterface #531,  1          // InterfaceMethod org/xmlpull/v1/XmlPullParser.getName:()Ljava/lang/String;
      82: pop
      83: aload_3
      84: invokeinterface #560,  1          // InterfaceMethod org/xmlpull/v1/XmlPullParser.next:()I
      89: istore_2
      90: goto          99
      93: astore_1
      94: aload_1
      95: invokestatic  #565                // Method com/google/a/a/a/a/a/a.a:(Ljava/lang/Throwable;)V
      98: return
      99: iload_2
     100: iconst_1
     101: if_icmpeq     98
     104: iload_2
     105: ifeq          76
     108: iload_2
     109: tableswitch   { // 2 to 3
                     2: 19
                     3: 83
               default: 132
          }
     132: goto          83
    Exception table:
       from    to  target type
           9    16    93   Class org/xmlpull/v1/XmlPullParserException
           9    16    93   Class java/io/IOException
          19    55    93   Class org/xmlpull/v1/XmlPullParserException
          19    55    93   Class java/io/IOException
          55    73    93   Class org/xmlpull/v1/XmlPullParserException
          55    73    93   Class java/io/IOException
          76    83    93   Class org/xmlpull/v1/XmlPullParserException
          76    83    93   Class java/io/IOException
          83    90    93   Class org/xmlpull/v1/XmlPullParserException
          83    90    93   Class java/io/IOException

  void a(android.support.constraint.ConstraintLayout);
    Code:
       0: aload_1
       1: invokevirtual #571                // Method android/support/constraint/ConstraintLayout.getChildCount:()I
       4: istore_3
       5: new           #573                // class java/util/HashSet
       8: dup
       9: aload_0
      10: getfield      #244                // Field b:Ljava/util/HashMap;
      13: invokevirtual #577                // Method java/util/HashMap.keySet:()Ljava/util/Set;
      16: invokespecial #580                // Method java/util/HashSet."<init>":(Ljava/util/Collection;)V
      19: astore        5
      21: iconst_0
      22: istore_2
      23: iload_2
      24: iload_3
      25: if_icmpge     373
      28: aload_1
      29: iload_2
      30: invokevirtual #584                // Method android/support/constraint/ConstraintLayout.getChildAt:(I)Landroid/view/View;
      33: astore        6
      35: aload         6
      37: invokevirtual #589                // Method android/view/View.getId:()I
      40: istore        4
      42: iload         4
      44: iconst_m1
      45: if_icmpne     59
      48: new           #591                // class java/lang/RuntimeException
      51: dup
      52: ldc_w         #593                // String All children of ConstraintLayout must have ids to use ConstraintSet
      55: invokespecial #596                // Method java/lang/RuntimeException."<init>":(Ljava/lang/String;)V
      58: athrow
      59: aload_0
      60: getfield      #244                // Field b:Ljava/util/HashMap;
      63: iload         4
      65: invokestatic  #553                // Method java/lang/Integer.valueOf:(I)Ljava/lang/Integer;
      68: invokevirtual #600                // Method java/util/HashMap.containsKey:(Ljava/lang/Object;)Z
      71: ifeq          366
      74: aload         5
      76: iload         4
      78: invokestatic  #553                // Method java/lang/Integer.valueOf:(I)Ljava/lang/Integer;
      81: invokevirtual #603                // Method java/util/HashSet.remove:(Ljava/lang/Object;)Z
      84: pop
      85: aload_0
      86: getfield      #244                // Field b:Ljava/util/HashMap;
      89: iload         4
      91: invokestatic  #553                // Method java/lang/Integer.valueOf:(I)Ljava/lang/Integer;
      94: invokevirtual #606                // Method java/util/HashMap.get:(Ljava/lang/Object;)Ljava/lang/Object;
      97: checkcast     #8                  // class android/support/constraint/c$a
     100: astore        7
     102: aload         7
     104: getfield      #609                // Field android/support/constraint/c$a.as:I
     107: iconst_m1
     108: if_icmpeq     166
     111: aload         7
     113: getfield      #609                // Field android/support/constraint/c$a.as:I
     116: iconst_1
     117: if_icmpeq     123
     120: goto          166
     123: aload         6
     125: checkcast     #611                // class android/support/constraint/a
     128: astore        8
     130: aload         8
     132: iload         4
     134: invokevirtual #615                // Method android/support/constraint/a.setId:(I)V
     137: aload         8
     139: aload         7
     141: getfield      #618                // Field android/support/constraint/c$a.at:[I
     144: invokevirtual #622                // Method android/support/constraint/a.setReferencedIds:([I)V
     147: aload         8
     149: aload         7
     151: getfield      #625                // Field android/support/constraint/c$a.ar:I
     154: invokevirtual #628                // Method android/support/constraint/a.setType:(I)V
     157: aload         7
     159: aload_1
     160: invokevirtual #631                // Method android/support/constraint/ConstraintLayout.a:()Landroid/support/constraint/ConstraintLayout$a;
     163: invokevirtual #634                // Method android/support/constraint/c$a.a:(Landroid/support/constraint/ConstraintLayout$a;)V
     166: aload         6
     168: invokevirtual #638                // Method android/view/View.getLayoutParams:()Landroid/view/ViewGroup$LayoutParams;
     171: checkcast     #640                // class android/support/constraint/ConstraintLayout$a
     174: astore        8
     176: aload         7
     178: aload         8
     180: invokevirtual #634                // Method android/support/constraint/c$a.a:(Landroid/support/constraint/ConstraintLayout$a;)V
     183: aload         6
     185: aload         8
     187: invokevirtual #644                // Method android/view/View.setLayoutParams:(Landroid/view/ViewGroup$LayoutParams;)V
     190: aload         6
     192: aload         7
     194: getfield      #440                // Field android/support/constraint/c$a.J:I
     197: invokevirtual #647                // Method android/view/View.setVisibility:(I)V
     200: getstatic     #652                // Field android/os/Build$VERSION.SDK_INT:I
     203: bipush        17
     205: if_icmplt     366
     208: aload         6
     210: aload         7
     212: getfield      #377                // Field android/support/constraint/c$a.U:F
     215: invokevirtual #656                // Method android/view/View.setAlpha:(F)V
     218: aload         6
     220: aload         7
     222: getfield      #338                // Field android/support/constraint/c$a.X:F
     225: invokevirtual #659                // Method android/view/View.setRotation:(F)V
     228: aload         6
     230: aload         7
     232: getfield      #368                // Field android/support/constraint/c$a.Y:F
     235: invokevirtual #662                // Method android/view/View.setRotationX:(F)V
     238: aload         6
     240: aload         7
     242: getfield      #365                // Field android/support/constraint/c$a.Z:F
     245: invokevirtual #665                // Method android/view/View.setRotationY:(F)V
     248: aload         6
     250: aload         7
     252: getfield      #362                // Field android/support/constraint/c$a.aa:F
     255: invokevirtual #668                // Method android/view/View.setScaleX:(F)V
     258: aload         6
     260: aload         7
     262: getfield      #359                // Field android/support/constraint/c$a.ab:F
     265: invokevirtual #671                // Method android/view/View.setScaleY:(F)V
     268: aload         7
     270: getfield      #356                // Field android/support/constraint/c$a.ac:F
     273: invokestatic  #677                // Method java/lang/Float.isNaN:(F)Z
     276: ifne          289
     279: aload         6
     281: aload         7
     283: getfield      #356                // Field android/support/constraint/c$a.ac:F
     286: invokevirtual #680                // Method android/view/View.setPivotX:(F)V
     289: aload         7
     291: getfield      #353                // Field android/support/constraint/c$a.ad:F
     294: invokestatic  #677                // Method java/lang/Float.isNaN:(F)Z
     297: ifne          310
     300: aload         6
     302: aload         7
     304: getfield      #353                // Field android/support/constraint/c$a.ad:F
     307: invokevirtual #683                // Method android/view/View.setPivotY:(F)V
     310: aload         6
     312: aload         7
     314: getfield      #350                // Field android/support/constraint/c$a.ae:F
     317: invokevirtual #686                // Method android/view/View.setTranslationX:(F)V
     320: aload         6
     322: aload         7
     324: getfield      #347                // Field android/support/constraint/c$a.af:F
     327: invokevirtual #689                // Method android/view/View.setTranslationY:(F)V
     330: getstatic     #652                // Field android/os/Build$VERSION.SDK_INT:I
     333: bipush        21
     335: if_icmplt     366
     338: aload         6
     340: aload         7
     342: getfield      #341                // Field android/support/constraint/c$a.ag:F
     345: invokevirtual #692                // Method android/view/View.setTranslationZ:(F)V
     348: aload         7
     350: getfield      #371                // Field android/support/constraint/c$a.V:Z
     353: ifeq          366
     356: aload         6
     358: aload         7
     360: getfield      #374                // Field android/support/constraint/c$a.W:F
     363: invokevirtual #695                // Method android/view/View.setElevation:(F)V
     366: iload_2
     367: iconst_1
     368: iadd
     369: istore_2
     370: goto          23
     373: aload         5
     375: invokevirtual #699                // Method java/util/HashSet.iterator:()Ljava/util/Iterator;
     378: astore        5
     380: aload         5
     382: invokeinterface #705,  1          // InterfaceMethod java/util/Iterator.hasNext:()Z
     387: ifeq          556
     390: aload         5
     392: invokeinterface #708,  1          // InterfaceMethod java/util/Iterator.next:()Ljava/lang/Object;
     397: checkcast     #294                // class java/lang/Integer
     400: astore        7
     402: aload_0
     403: getfield      #244                // Field b:Ljava/util/HashMap;
     406: aload         7
     408: invokevirtual #606                // Method java/util/HashMap.get:(Ljava/lang/Object;)Ljava/lang/Object;
     411: checkcast     #8                  // class android/support/constraint/c$a
     414: astore        6
     416: aload         6
     418: getfield      #609                // Field android/support/constraint/c$a.as:I
     421: iconst_m1
     422: if_icmpeq     501
     425: aload         6
     427: getfield      #609                // Field android/support/constraint/c$a.as:I
     430: iconst_1
     431: if_icmpeq     437
     434: goto          501
     437: new           #611                // class android/support/constraint/a
     440: dup
     441: aload_1
     442: invokevirtual #712                // Method android/support/constraint/ConstraintLayout.getContext:()Landroid/content/Context;
     445: invokespecial #715                // Method android/support/constraint/a."<init>":(Landroid/content/Context;)V
     448: astore        8
     450: aload         8
     452: aload         7
     454: invokevirtual #718                // Method java/lang/Integer.intValue:()I
     457: invokevirtual #615                // Method android/support/constraint/a.setId:(I)V
     460: aload         8
     462: aload         6
     464: getfield      #618                // Field android/support/constraint/c$a.at:[I
     467: invokevirtual #622                // Method android/support/constraint/a.setReferencedIds:([I)V
     470: aload         8
     472: aload         6
     474: getfield      #625                // Field android/support/constraint/c$a.ar:I
     477: invokevirtual #628                // Method android/support/constraint/a.setType:(I)V
     480: aload_1
     481: invokevirtual #631                // Method android/support/constraint/ConstraintLayout.a:()Landroid/support/constraint/ConstraintLayout$a;
     484: astore        9
     486: aload         6
     488: aload         9
     490: invokevirtual #634                // Method android/support/constraint/c$a.a:(Landroid/support/constraint/ConstraintLayout$a;)V
     493: aload_1
     494: aload         8
     496: aload         9
     498: invokevirtual #722                // Method android/support/constraint/ConstraintLayout.addView:(Landroid/view/View;Landroid/view/ViewGroup$LayoutParams;)V
     501: aload         6
     503: getfield      #549                // Field android/support/constraint/c$a.a:Z
     506: ifeq          380
     509: new           #724                // class android/support/constraint/Guideline
     512: dup
     513: aload_1
     514: invokevirtual #712                // Method android/support/constraint/ConstraintLayout.getContext:()Landroid/content/Context;
     517: invokespecial #725                // Method android/support/constraint/Guideline."<init>":(Landroid/content/Context;)V
     520: astore        8
     522: aload         8
     524: aload         7
     526: invokevirtual #718                // Method java/lang/Integer.intValue:()I
     529: invokevirtual #726                // Method android/support/constraint/Guideline.setId:(I)V
     532: aload_1
     533: invokevirtual #631                // Method android/support/constraint/ConstraintLayout.a:()Landroid/support/constraint/ConstraintLayout$a;
     536: astore        7
     538: aload         6
     540: aload         7
     542: invokevirtual #634                // Method android/support/constraint/c$a.a:(Landroid/support/constraint/ConstraintLayout$a;)V
     545: aload_1
     546: aload         8
     548: aload         7
     550: invokevirtual #722                // Method android/support/constraint/ConstraintLayout.addView:(Landroid/view/View;Landroid/view/ViewGroup$LayoutParams;)V
     553: goto          380
     556: return

  public void a(android.support.constraint.d);
    Code:
       0: aload_1
       1: invokevirtual #730                // Method android/support/constraint/d.getChildCount:()I
       4: istore_3
       5: aload_0
       6: getfield      #244                // Field b:Ljava/util/HashMap;
       9: invokevirtual #733                // Method java/util/HashMap.clear:()V
      12: iconst_0
      13: istore_2
      14: iload_2
      15: iload_3
      16: if_icmpge     151
      19: aload_1
      20: iload_2
      21: invokevirtual #734                // Method android/support/constraint/d.getChildAt:(I)Landroid/view/View;
      24: astore        5
      26: aload         5
      28: invokevirtual #638                // Method android/view/View.getLayoutParams:()Landroid/view/ViewGroup$LayoutParams;
      31: checkcast     #736                // class android/support/constraint/d$a
      34: astore        6
      36: aload         5
      38: invokevirtual #589                // Method android/view/View.getId:()I
      41: istore        4
      43: iload         4
      45: iconst_m1
      46: if_icmpne     60
      49: new           #591                // class java/lang/RuntimeException
      52: dup
      53: ldc_w         #593                // String All children of ConstraintLayout must have ids to use ConstraintSet
      56: invokespecial #596                // Method java/lang/RuntimeException."<init>":(Ljava/lang/String;)V
      59: athrow
      60: aload_0
      61: getfield      #244                // Field b:Ljava/util/HashMap;
      64: iload         4
      66: invokestatic  #553                // Method java/lang/Integer.valueOf:(I)Ljava/lang/Integer;
      69: invokevirtual #600                // Method java/util/HashMap.containsKey:(Ljava/lang/Object;)Z
      72: ifne          96
      75: aload_0
      76: getfield      #244                // Field b:Ljava/util/HashMap;
      79: iload         4
      81: invokestatic  #553                // Method java/lang/Integer.valueOf:(I)Ljava/lang/Integer;
      84: new           #8                  // class android/support/constraint/c$a
      87: dup
      88: aconst_null
      89: invokespecial #258                // Method android/support/constraint/c$a."<init>":(Landroid/support/constraint/c$1;)V
      92: invokevirtual #557                // Method java/util/HashMap.put:(Ljava/lang/Object;Ljava/lang/Object;)Ljava/lang/Object;
      95: pop
      96: aload_0
      97: getfield      #244                // Field b:Ljava/util/HashMap;
     100: iload         4
     102: invokestatic  #553                // Method java/lang/Integer.valueOf:(I)Ljava/lang/Integer;
     105: invokevirtual #606                // Method java/util/HashMap.get:(Ljava/lang/Object;)Ljava/lang/Object;
     108: checkcast     #8                  // class android/support/constraint/c$a
     111: astore        7
     113: aload         5
     115: instanceof    #738                // class android/support/constraint/b
     118: ifeq          135
     121: aload         7
     123: aload         5
     125: checkcast     #738                // class android/support/constraint/b
     128: iload         4
     130: aload         6
     132: invokestatic  #741                // Method android/support/constraint/c$a.a:(Landroid/support/constraint/c$a;Landroid/support/constraint/b;ILandroid/support/constraint/d$a;)V
     135: aload         7
     137: iload         4
     139: aload         6
     141: invokestatic  #744                // Method android/support/constraint/c$a.a:(Landroid/support/constraint/c$a;ILandroid/support/constraint/d$a;)V
     144: iload_2
     145: iconst_1
     146: iadd
     147: istore_2
     148: goto          14
     151: return
}
