class android.support.constraint.ConstraintLayout$a$a {
  public static final android.util.SparseIntArray a;

  static {};
    Code:
       0: new           #14                 // class android/util/SparseIntArray
       3: dup
       4: invokespecial #17                 // Method android/util/SparseIntArray."<init>":()V
       7: putstatic     #19                 // Field a:Landroid/util/SparseIntArray;
      10: getstatic     #19                 // Field a:Landroid/util/SparseIntArray;
      13: getstatic     #25                 // Field android/support/constraint/f$b.ConstraintLayout_Layout_layout_constraintLeft_toLeftOf:I
      16: bipush        8
      18: invokevirtual #29                 // Method android/util/SparseIntArray.append:(II)V
      21: getstatic     #19                 // Field a:Landroid/util/SparseIntArray;
      24: getstatic     #32                 // Field android/support/constraint/f$b.ConstraintLayout_Layout_layout_constraintLeft_toRightOf:I
      27: bipush        9
      29: invokevirtual #29                 // Method android/util/SparseIntArray.append:(II)V
      32: getstatic     #19                 // Field a:Landroid/util/SparseIntArray;
      35: getstatic     #35                 // Field android/support/constraint/f$b.ConstraintLayout_Layout_layout_constraintRight_toLeftOf:I
      38: bipush        10
      40: invokevirtual #29                 // Method android/util/SparseIntArray.append:(II)V
      43: getstatic     #19                 // Field a:Landroid/util/SparseIntArray;
      46: getstatic     #38                 // Field android/support/constraint/f$b.ConstraintLayout_Layout_layout_constraintRight_toRightOf:I
      49: bipush        11
      51: invokevirtual #29                 // Method android/util/SparseIntArray.append:(II)V
      54: getstatic     #19                 // Field a:Landroid/util/SparseIntArray;
      57: getstatic     #41                 // Field android/support/constraint/f$b.ConstraintLayout_Layout_layout_constraintTop_toTopOf:I
      60: bipush        12
      62: invokevirtual #29                 // Method android/util/SparseIntArray.append:(II)V
      65: getstatic     #19                 // Field a:Landroid/util/SparseIntArray;
      68: getstatic     #44                 // Field android/support/constraint/f$b.ConstraintLayout_Layout_layout_constraintTop_toBottomOf:I
      71: bipush        13
      73: invokevirtual #29                 // Method android/util/SparseIntArray.append:(II)V
      76: getstatic     #19                 // Field a:Landroid/util/SparseIntArray;
      79: getstatic     #47                 // Field android/support/constraint/f$b.ConstraintLayout_Layout_layout_constraintBottom_toTopOf:I
      82: bipush        14
      84: invokevirtual #29                 // Method android/util/SparseIntArray.append:(II)V
      87: getstatic     #19                 // Field a:Landroid/util/SparseIntArray;
      90: getstatic     #50                 // Field android/support/constraint/f$b.ConstraintLayout_Layout_layout_constraintBottom_toBottomOf:I
      93: bipush        15
      95: invokevirtual #29                 // Method android/util/SparseIntArray.append:(II)V
      98: getstatic     #19                 // Field a:Landroid/util/SparseIntArray;
     101: getstatic     #53                 // Field android/support/constraint/f$b.ConstraintLayout_Layout_layout_constraintBaseline_toBaselineOf:I
     104: bipush        16
     106: invokevirtual #29                 // Method android/util/SparseIntArray.append:(II)V
     109: getstatic     #19                 // Field a:Landroid/util/SparseIntArray;
     112: getstatic     #56                 // Field android/support/constraint/f$b.ConstraintLayout_Layout_layout_constraintCircle:I
     115: iconst_2
     116: invokevirtual #29                 // Method android/util/SparseIntArray.append:(II)V
     119: getstatic     #19                 // Field a:Landroid/util/SparseIntArray;
     122: getstatic     #59                 // Field android/support/constraint/f$b.ConstraintLayout_Layout_layout_constraintCircleRadius:I
     125: iconst_3
     126: invokevirtual #29                 // Method android/util/SparseIntArray.append:(II)V
     129: getstatic     #19                 // Field a:Landroid/util/SparseIntArray;
     132: getstatic     #62                 // Field android/support/constraint/f$b.ConstraintLayout_Layout_layout_constraintCircleAngle:I
     135: iconst_4
     136: invokevirtual #29                 // Method android/util/SparseIntArray.append:(II)V
     139: getstatic     #19                 // Field a:Landroid/util/SparseIntArray;
     142: getstatic     #65                 // Field android/support/constraint/f$b.ConstraintLayout_Layout_layout_editor_absoluteX:I
     145: bipush        49
     147: invokevirtual #29                 // Method android/util/SparseIntArray.append:(II)V
     150: getstatic     #19                 // Field a:Landroid/util/SparseIntArray;
     153: getstatic     #68                 // Field android/support/constraint/f$b.ConstraintLayout_Layout_layout_editor_absoluteY:I
     156: bipush        50
     158: invokevirtual #29                 // Method android/util/SparseIntArray.append:(II)V
     161: getstatic     #19                 // Field a:Landroid/util/SparseIntArray;
     164: getstatic     #71                 // Field android/support/constraint/f$b.ConstraintLayout_Layout_layout_constraintGuide_begin:I
     167: iconst_5
     168: invokevirtual #29                 // Method android/util/SparseIntArray.append:(II)V
     171: getstatic     #19                 // Field a:Landroid/util/SparseIntArray;
     174: getstatic     #74                 // Field android/support/constraint/f$b.ConstraintLayout_Layout_layout_constraintGuide_end:I
     177: bipush        6
     179: invokevirtual #29                 // Method android/util/SparseIntArray.append:(II)V
     182: getstatic     #19                 // Field a:Landroid/util/SparseIntArray;
     185: getstatic     #77                 // Field android/support/constraint/f$b.ConstraintLayout_Layout_layout_constraintGuide_percent:I
     188: bipush        7
     190: invokevirtual #29                 // Method android/util/SparseIntArray.append:(II)V
     193: getstatic     #19                 // Field a:Landroid/util/SparseIntArray;
     196: getstatic     #80                 // Field android/support/constraint/f$b.ConstraintLayout_Layout_android_orientation:I
     199: iconst_1
     200: invokevirtual #29                 // Method android/util/SparseIntArray.append:(II)V
     203: getstatic     #19                 // Field a:Landroid/util/SparseIntArray;
     206: getstatic     #83                 // Field android/support/constraint/f$b.ConstraintLayout_Layout_layout_constraintStart_toEndOf:I
     209: bipush        17
     211: invokevirtual #29                 // Method android/util/SparseIntArray.append:(II)V
     214: getstatic     #19                 // Field a:Landroid/util/SparseIntArray;
     217: getstatic     #86                 // Field android/support/constraint/f$b.ConstraintLayout_Layout_layout_constraintStart_toStartOf:I
     220: bipush        18
     222: invokevirtual #29                 // Method android/util/SparseIntArray.append:(II)V
     225: getstatic     #19                 // Field a:Landroid/util/SparseIntArray;
     228: getstatic     #89                 // Field android/support/constraint/f$b.ConstraintLayout_Layout_layout_constraintEnd_toStartOf:I
     231: bipush        19
     233: invokevirtual #29                 // Method android/util/SparseIntArray.append:(II)V
     236: getstatic     #19                 // Field a:Landroid/util/SparseIntArray;
     239: getstatic     #92                 // Field android/support/constraint/f$b.ConstraintLayout_Layout_layout_constraintEnd_toEndOf:I
     242: bipush        20
     244: invokevirtual #29                 // Method android/util/SparseIntArray.append:(II)V
     247: getstatic     #19                 // Field a:Landroid/util/SparseIntArray;
     250: getstatic     #95                 // Field android/support/constraint/f$b.ConstraintLayout_Layout_layout_goneMarginLeft:I
     253: bipush        21
     255: invokevirtual #29                 // Method android/util/SparseIntArray.append:(II)V
     258: getstatic     #19                 // Field a:Landroid/util/SparseIntArray;
     261: getstatic     #98                 // Field android/support/constraint/f$b.ConstraintLayout_Layout_layout_goneMarginTop:I
     264: bipush        22
     266: invokevirtual #29                 // Method android/util/SparseIntArray.append:(II)V
     269: getstatic     #19                 // Field a:Landroid/util/SparseIntArray;
     272: getstatic     #101                // Field android/support/constraint/f$b.ConstraintLayout_Layout_layout_goneMarginRight:I
     275: bipush        23
     277: invokevirtual #29                 // Method android/util/SparseIntArray.append:(II)V
     280: getstatic     #19                 // Field a:Landroid/util/SparseIntArray;
     283: getstatic     #104                // Field android/support/constraint/f$b.ConstraintLayout_Layout_layout_goneMarginBottom:I
     286: bipush        24
     288: invokevirtual #29                 // Method android/util/SparseIntArray.append:(II)V
     291: getstatic     #19                 // Field a:Landroid/util/SparseIntArray;
     294: getstatic     #107                // Field android/support/constraint/f$b.ConstraintLayout_Layout_layout_goneMarginStart:I
     297: bipush        25
     299: invokevirtual #29                 // Method android/util/SparseIntArray.append:(II)V
     302: getstatic     #19                 // Field a:Landroid/util/SparseIntArray;
     305: getstatic     #110                // Field android/support/constraint/f$b.ConstraintLayout_Layout_layout_goneMarginEnd:I
     308: bipush        26
     310: invokevirtual #29                 // Method android/util/SparseIntArray.append:(II)V
     313: getstatic     #19                 // Field a:Landroid/util/SparseIntArray;
     316: getstatic     #113                // Field android/support/constraint/f$b.ConstraintLayout_Layout_layout_constraintHorizontal_bias:I
     319: bipush        29
     321: invokevirtual #29                 // Method android/util/SparseIntArray.append:(II)V
     324: getstatic     #19                 // Field a:Landroid/util/SparseIntArray;
     327: getstatic     #116                // Field android/support/constraint/f$b.ConstraintLayout_Layout_layout_constraintVertical_bias:I
     330: bipush        30
     332: invokevirtual #29                 // Method android/util/SparseIntArray.append:(II)V
     335: getstatic     #19                 // Field a:Landroid/util/SparseIntArray;
     338: getstatic     #119                // Field android/support/constraint/f$b.ConstraintLayout_Layout_layout_constraintDimensionRatio:I
     341: bipush        44
     343: invokevirtual #29                 // Method android/util/SparseIntArray.append:(II)V
     346: getstatic     #19                 // Field a:Landroid/util/SparseIntArray;
     349: getstatic     #122                // Field android/support/constraint/f$b.ConstraintLayout_Layout_layout_constraintHorizontal_weight:I
     352: bipush        45
     354: invokevirtual #29                 // Method android/util/SparseIntArray.append:(II)V
     357: getstatic     #19                 // Field a:Landroid/util/SparseIntArray;
     360: getstatic     #125                // Field android/support/constraint/f$b.ConstraintLayout_Layout_layout_constraintVertical_weight:I
     363: bipush        46
     365: invokevirtual #29                 // Method android/util/SparseIntArray.append:(II)V
     368: getstatic     #19                 // Field a:Landroid/util/SparseIntArray;
     371: getstatic     #128                // Field android/support/constraint/f$b.ConstraintLayout_Layout_layout_constraintHorizontal_chainStyle:I
     374: bipush        47
     376: invokevirtual #29                 // Method android/util/SparseIntArray.append:(II)V
     379: getstatic     #19                 // Field a:Landroid/util/SparseIntArray;
     382: getstatic     #131                // Field android/support/constraint/f$b.ConstraintLayout_Layout_layout_constraintVertical_chainStyle:I
     385: bipush        48
     387: invokevirtual #29                 // Method android/util/SparseIntArray.append:(II)V
     390: getstatic     #19                 // Field a:Landroid/util/SparseIntArray;
     393: getstatic     #134                // Field android/support/constraint/f$b.ConstraintLayout_Layout_layout_constrainedWidth:I
     396: bipush        27
     398: invokevirtual #29                 // Method android/util/SparseIntArray.append:(II)V
     401: getstatic     #19                 // Field a:Landroid/util/SparseIntArray;
     404: getstatic     #137                // Field android/support/constraint/f$b.ConstraintLayout_Layout_layout_constrainedHeight:I
     407: bipush        28
     409: invokevirtual #29                 // Method android/util/SparseIntArray.append:(II)V
     412: getstatic     #19                 // Field a:Landroid/util/SparseIntArray;
     415: getstatic     #140                // Field android/support/constraint/f$b.ConstraintLayout_Layout_layout_constraintWidth_default:I
     418: bipush        31
     420: invokevirtual #29                 // Method android/util/SparseIntArray.append:(II)V
     423: getstatic     #19                 // Field a:Landroid/util/SparseIntArray;
     426: getstatic     #143                // Field android/support/constraint/f$b.ConstraintLayout_Layout_layout_constraintHeight_default:I
     429: bipush        32
     431: invokevirtual #29                 // Method android/util/SparseIntArray.append:(II)V
     434: getstatic     #19                 // Field a:Landroid/util/SparseIntArray;
     437: getstatic     #146                // Field android/support/constraint/f$b.ConstraintLayout_Layout_layout_constraintWidth_min:I
     440: bipush        33
     442: invokevirtual #29                 // Method android/util/SparseIntArray.append:(II)V
     445: getstatic     #19                 // Field a:Landroid/util/SparseIntArray;
     448: getstatic     #149                // Field android/support/constraint/f$b.ConstraintLayout_Layout_layout_constraintWidth_max:I
     451: bipush        34
     453: invokevirtual #29                 // Method android/util/SparseIntArray.append:(II)V
     456: getstatic     #19                 // Field a:Landroid/util/SparseIntArray;
     459: getstatic     #152                // Field android/support/constraint/f$b.ConstraintLayout_Layout_layout_constraintWidth_percent:I
     462: bipush        35
     464: invokevirtual #29                 // Method android/util/SparseIntArray.append:(II)V
     467: getstatic     #19                 // Field a:Landroid/util/SparseIntArray;
     470: getstatic     #155                // Field android/support/constraint/f$b.ConstraintLayout_Layout_layout_constraintHeight_min:I
     473: bipush        36
     475: invokevirtual #29                 // Method android/util/SparseIntArray.append:(II)V
     478: getstatic     #19                 // Field a:Landroid/util/SparseIntArray;
     481: getstatic     #158                // Field android/support/constraint/f$b.ConstraintLayout_Layout_layout_constraintHeight_max:I
     484: bipush        37
     486: invokevirtual #29                 // Method android/util/SparseIntArray.append:(II)V
     489: getstatic     #19                 // Field a:Landroid/util/SparseIntArray;
     492: getstatic     #161                // Field android/support/constraint/f$b.ConstraintLayout_Layout_layout_constraintHeight_percent:I
     495: bipush        38
     497: invokevirtual #29                 // Method android/util/SparseIntArray.append:(II)V
     500: getstatic     #19                 // Field a:Landroid/util/SparseIntArray;
     503: getstatic     #164                // Field android/support/constraint/f$b.ConstraintLayout_Layout_layout_constraintLeft_creator:I
     506: bipush        39
     508: invokevirtual #29                 // Method android/util/SparseIntArray.append:(II)V
     511: getstatic     #19                 // Field a:Landroid/util/SparseIntArray;
     514: getstatic     #167                // Field android/support/constraint/f$b.ConstraintLayout_Layout_layout_constraintTop_creator:I
     517: bipush        40
     519: invokevirtual #29                 // Method android/util/SparseIntArray.append:(II)V
     522: getstatic     #19                 // Field a:Landroid/util/SparseIntArray;
     525: getstatic     #170                // Field android/support/constraint/f$b.ConstraintLayout_Layout_layout_constraintRight_creator:I
     528: bipush        41
     530: invokevirtual #29                 // Method android/util/SparseIntArray.append:(II)V
     533: getstatic     #19                 // Field a:Landroid/util/SparseIntArray;
     536: getstatic     #173                // Field android/support/constraint/f$b.ConstraintLayout_Layout_layout_constraintBottom_creator:I
     539: bipush        42
     541: invokevirtual #29                 // Method android/util/SparseIntArray.append:(II)V
     544: getstatic     #19                 // Field a:Landroid/util/SparseIntArray;
     547: getstatic     #176                // Field android/support/constraint/f$b.ConstraintLayout_Layout_layout_constraintBaseline_creator:I
     550: bipush        43
     552: invokevirtual #29                 // Method android/util/SparseIntArray.append:(II)V
     555: return
}
