public class android.support.constraint.ConstraintLayout extends android.view.ViewGroup {
  android.util.SparseArray<android.view.View> a;

  android.support.constraint.a.a.e b;

  int c;

  int d;

  int e;

  int f;

  public android.support.constraint.ConstraintLayout(android.content.Context);
    Code:
       0: aload_0
       1: aload_1
       2: invokespecial #44                 // Method android/view/ViewGroup."<init>":(Landroid/content/Context;)V
       5: aload_0
       6: new           #46                 // class android/util/SparseArray
       9: dup
      10: invokespecial #49                 // Method android/util/SparseArray."<init>":()V
      13: putfield      #51                 // Field a:Landroid/util/SparseArray;
      16: aload_0
      17: new           #53                 // class java/util/ArrayList
      20: dup
      21: iconst_4
      22: invokespecial #56                 // Method java/util/ArrayList."<init>":(I)V
      25: putfield      #58                 // Field g:Ljava/util/ArrayList;
      28: aload_0
      29: new           #53                 // class java/util/ArrayList
      32: dup
      33: bipush        100
      35: invokespecial #56                 // Method java/util/ArrayList."<init>":(I)V
      38: putfield      #60                 // Field h:Ljava/util/ArrayList;
      41: aload_0
      42: new           #62                 // class android/support/constraint/a/a/e
      45: dup
      46: invokespecial #63                 // Method android/support/constraint/a/a/e."<init>":()V
      49: putfield      #65                 // Field b:Landroid/support/constraint/a/a/e;
      52: aload_0
      53: iconst_0
      54: putfield      #67                 // Field i:I
      57: aload_0
      58: iconst_0
      59: putfield      #69                 // Field j:I
      62: aload_0
      63: ldc           #70                 // int 2147483647
      65: putfield      #72                 // Field k:I
      68: aload_0
      69: ldc           #70                 // int 2147483647
      71: putfield      #74                 // Field l:I
      74: aload_0
      75: iconst_1
      76: putfield      #76                 // Field m:Z
      79: aload_0
      80: iconst_3
      81: putfield      #78                 // Field n:I
      84: aload_0
      85: aconst_null
      86: putfield      #80                 // Field o:Landroid/support/constraint/c;
      89: aload_0
      90: iconst_m1
      91: putfield      #82                 // Field p:I
      94: aload_0
      95: new           #84                 // class java/util/HashMap
      98: dup
      99: invokespecial #85                 // Method java/util/HashMap."<init>":()V
     102: putfield      #87                 // Field q:Ljava/util/HashMap;
     105: aload_0
     106: iconst_m1
     107: putfield      #89                 // Field r:I
     110: aload_0
     111: iconst_m1
     112: putfield      #91                 // Field s:I
     115: aload_0
     116: iconst_m1
     117: putfield      #93                 // Field c:I
     120: aload_0
     121: iconst_m1
     122: putfield      #95                 // Field d:I
     125: aload_0
     126: iconst_0
     127: putfield      #97                 // Field e:I
     130: aload_0
     131: iconst_0
     132: putfield      #99                 // Field f:I
     135: aload_0
     136: aconst_null
     137: invokespecial #102                // Method b:(Landroid/util/AttributeSet;)V
     140: return

  public android.support.constraint.ConstraintLayout(android.content.Context, android.util.AttributeSet);
    Code:
       0: aload_0
       1: aload_1
       2: aload_2
       3: invokespecial #106                // Method android/view/ViewGroup."<init>":(Landroid/content/Context;Landroid/util/AttributeSet;)V
       6: aload_0
       7: new           #46                 // class android/util/SparseArray
      10: dup
      11: invokespecial #49                 // Method android/util/SparseArray."<init>":()V
      14: putfield      #51                 // Field a:Landroid/util/SparseArray;
      17: aload_0
      18: new           #53                 // class java/util/ArrayList
      21: dup
      22: iconst_4
      23: invokespecial #56                 // Method java/util/ArrayList."<init>":(I)V
      26: putfield      #58                 // Field g:Ljava/util/ArrayList;
      29: aload_0
      30: new           #53                 // class java/util/ArrayList
      33: dup
      34: bipush        100
      36: invokespecial #56                 // Method java/util/ArrayList."<init>":(I)V
      39: putfield      #60                 // Field h:Ljava/util/ArrayList;
      42: aload_0
      43: new           #62                 // class android/support/constraint/a/a/e
      46: dup
      47: invokespecial #63                 // Method android/support/constraint/a/a/e."<init>":()V
      50: putfield      #65                 // Field b:Landroid/support/constraint/a/a/e;
      53: aload_0
      54: iconst_0
      55: putfield      #67                 // Field i:I
      58: aload_0
      59: iconst_0
      60: putfield      #69                 // Field j:I
      63: aload_0
      64: ldc           #70                 // int 2147483647
      66: putfield      #72                 // Field k:I
      69: aload_0
      70: ldc           #70                 // int 2147483647
      72: putfield      #74                 // Field l:I
      75: aload_0
      76: iconst_1
      77: putfield      #76                 // Field m:Z
      80: aload_0
      81: iconst_3
      82: putfield      #78                 // Field n:I
      85: aload_0
      86: aconst_null
      87: putfield      #80                 // Field o:Landroid/support/constraint/c;
      90: aload_0
      91: iconst_m1
      92: putfield      #82                 // Field p:I
      95: aload_0
      96: new           #84                 // class java/util/HashMap
      99: dup
     100: invokespecial #85                 // Method java/util/HashMap."<init>":()V
     103: putfield      #87                 // Field q:Ljava/util/HashMap;
     106: aload_0
     107: iconst_m1
     108: putfield      #89                 // Field r:I
     111: aload_0
     112: iconst_m1
     113: putfield      #91                 // Field s:I
     116: aload_0
     117: iconst_m1
     118: putfield      #93                 // Field c:I
     121: aload_0
     122: iconst_m1
     123: putfield      #95                 // Field d:I
     126: aload_0
     127: iconst_0
     128: putfield      #97                 // Field e:I
     131: aload_0
     132: iconst_0
     133: putfield      #99                 // Field f:I
     136: aload_0
     137: aload_2
     138: invokespecial #102                // Method b:(Landroid/util/AttributeSet;)V
     141: return

  public android.support.constraint.ConstraintLayout(android.content.Context, android.util.AttributeSet, int);
    Code:
       0: aload_0
       1: aload_1
       2: aload_2
       3: iload_3
       4: invokespecial #109                // Method android/view/ViewGroup."<init>":(Landroid/content/Context;Landroid/util/AttributeSet;I)V
       7: aload_0
       8: new           #46                 // class android/util/SparseArray
      11: dup
      12: invokespecial #49                 // Method android/util/SparseArray."<init>":()V
      15: putfield      #51                 // Field a:Landroid/util/SparseArray;
      18: aload_0
      19: new           #53                 // class java/util/ArrayList
      22: dup
      23: iconst_4
      24: invokespecial #56                 // Method java/util/ArrayList."<init>":(I)V
      27: putfield      #58                 // Field g:Ljava/util/ArrayList;
      30: aload_0
      31: new           #53                 // class java/util/ArrayList
      34: dup
      35: bipush        100
      37: invokespecial #56                 // Method java/util/ArrayList."<init>":(I)V
      40: putfield      #60                 // Field h:Ljava/util/ArrayList;
      43: aload_0
      44: new           #62                 // class android/support/constraint/a/a/e
      47: dup
      48: invokespecial #63                 // Method android/support/constraint/a/a/e."<init>":()V
      51: putfield      #65                 // Field b:Landroid/support/constraint/a/a/e;
      54: aload_0
      55: iconst_0
      56: putfield      #67                 // Field i:I
      59: aload_0
      60: iconst_0
      61: putfield      #69                 // Field j:I
      64: aload_0
      65: ldc           #70                 // int 2147483647
      67: putfield      #72                 // Field k:I
      70: aload_0
      71: ldc           #70                 // int 2147483647
      73: putfield      #74                 // Field l:I
      76: aload_0
      77: iconst_1
      78: putfield      #76                 // Field m:Z
      81: aload_0
      82: iconst_3
      83: putfield      #78                 // Field n:I
      86: aload_0
      87: aconst_null
      88: putfield      #80                 // Field o:Landroid/support/constraint/c;
      91: aload_0
      92: iconst_m1
      93: putfield      #82                 // Field p:I
      96: aload_0
      97: new           #84                 // class java/util/HashMap
     100: dup
     101: invokespecial #85                 // Method java/util/HashMap."<init>":()V
     104: putfield      #87                 // Field q:Ljava/util/HashMap;
     107: aload_0
     108: iconst_m1
     109: putfield      #89                 // Field r:I
     112: aload_0
     113: iconst_m1
     114: putfield      #91                 // Field s:I
     117: aload_0
     118: iconst_m1
     119: putfield      #93                 // Field c:I
     122: aload_0
     123: iconst_m1
     124: putfield      #95                 // Field d:I
     127: aload_0
     128: iconst_0
     129: putfield      #97                 // Field e:I
     132: aload_0
     133: iconst_0
     134: putfield      #99                 // Field f:I
     137: aload_0
     138: aload_2
     139: invokespecial #102                // Method b:(Landroid/util/AttributeSet;)V
     142: return

  protected android.support.constraint.ConstraintLayout$a a();
    Code:
       0: new           #6                  // class android/support/constraint/ConstraintLayout$a
       3: dup
       4: bipush        -2
       6: bipush        -2
       8: invokespecial #412                // Method android/support/constraint/ConstraintLayout$a."<init>":(II)V
      11: areturn

  public android.support.constraint.ConstraintLayout$a a(android.util.AttributeSet);
    Code:
       0: new           #6                  // class android/support/constraint/ConstraintLayout$a
       3: dup
       4: aload_0
       5: invokevirtual #299                // Method getContext:()Landroid/content/Context;
       8: aload_1
       9: invokespecial #414                // Method android/support/constraint/ConstraintLayout$a."<init>":(Landroid/content/Context;Landroid/util/AttributeSet;)V
      12: areturn

  public final android.support.constraint.a.a.d a(android.view.View);
    Code:
       0: aload_1
       1: aload_0
       2: if_acmpne     10
       5: aload_0
       6: getfield      #65                 // Field b:Landroid/support/constraint/a/a/e;
       9: areturn
      10: aload_1
      11: ifnonnull     16
      14: aconst_null
      15: areturn
      16: aload_1
      17: invokevirtual #139                // Method android/view/View.getLayoutParams:()Landroid/view/ViewGroup$LayoutParams;
      20: checkcast     #6                  // class android/support/constraint/ConstraintLayout$a
      23: getfield      #143                // Field android/support/constraint/ConstraintLayout$a.al:Landroid/support/constraint/a/a/d;
      26: areturn

  public android.view.View a(int);
    Code:
       0: aload_0
       1: getfield      #51                 // Field a:Landroid/util/SparseArray;
       4: iload_1
       5: invokevirtual #214                // Method android/util/SparseArray.get:(I)Ljava/lang/Object;
       8: checkcast     #132                // class android/view/View
      11: areturn

  public java.lang.Object a(int, java.lang.Object);
    Code:
       0: iload_1
       1: ifne          43
       4: aload_2
       5: instanceof    #418                // class java/lang/String
       8: ifeq          43
      11: aload_2
      12: checkcast     #418                // class java/lang/String
      15: astore_2
      16: aload_0
      17: getfield      #87                 // Field q:Ljava/util/HashMap;
      20: ifnull        43
      23: aload_0
      24: getfield      #87                 // Field q:Ljava/util/HashMap;
      27: aload_2
      28: invokevirtual #422                // Method java/util/HashMap.containsKey:(Ljava/lang/Object;)Z
      31: ifeq          43
      34: aload_0
      35: getfield      #87                 // Field q:Ljava/util/HashMap;
      38: aload_2
      39: invokevirtual #425                // Method java/util/HashMap.get:(Ljava/lang/Object;)Ljava/lang/Object;
      42: areturn
      43: aconst_null
      44: areturn

  public void a(int, java.lang.Object, java.lang.Object);
    Code:
       0: iload_1
       1: ifne          89
       4: aload_2
       5: instanceof    #418                // class java/lang/String
       8: ifeq          89
      11: aload_3
      12: instanceof    #428                // class java/lang/Integer
      15: ifeq          89
      18: aload_0
      19: getfield      #87                 // Field q:Ljava/util/HashMap;
      22: ifnonnull     36
      25: aload_0
      26: new           #84                 // class java/util/HashMap
      29: dup
      30: invokespecial #85                 // Method java/util/HashMap."<init>":()V
      33: putfield      #87                 // Field q:Ljava/util/HashMap;
      36: aload_2
      37: checkcast     #418                // class java/lang/String
      40: astore        4
      42: aload         4
      44: ldc_w         #430                // String /
      47: invokevirtual #434                // Method java/lang/String.indexOf:(Ljava/lang/String;)I
      50: istore_1
      51: aload         4
      53: astore_2
      54: iload_1
      55: iconst_m1
      56: if_icmpeq     68
      59: aload         4
      61: iload_1
      62: iconst_1
      63: iadd
      64: invokevirtual #438                // Method java/lang/String.substring:(I)Ljava/lang/String;
      67: astore_2
      68: aload_3
      69: checkcast     #428                // class java/lang/Integer
      72: invokevirtual #441                // Method java/lang/Integer.intValue:()I
      75: istore_1
      76: aload_0
      77: getfield      #87                 // Field q:Ljava/util/HashMap;
      80: aload_2
      81: iload_1
      82: invokestatic  #445                // Method java/lang/Integer.valueOf:(I)Ljava/lang/Integer;
      85: invokevirtual #448                // Method java/util/HashMap.put:(Ljava/lang/Object;Ljava/lang/Object;)Ljava/lang/Object;
      88: pop
      89: return

  protected void a(java.lang.String);
    Code:
       0: aload_0
       1: getfield      #65                 // Field b:Landroid/support/constraint/a/a/e;
       4: invokevirtual #451                // Method android/support/constraint/a/a/e.L:()V
       7: aload_0
       8: getfield      #178                // Field t:Landroid/support/constraint/a/f;
      11: ifnull        29
      14: aload_0
      15: getfield      #178                // Field t:Landroid/support/constraint/a/f;
      18: astore_1
      19: aload_1
      20: aload_1
      21: getfield      #453                // Field android/support/constraint/a/f.c:J
      24: lconst_1
      25: ladd
      26: putfield      #453                // Field android/support/constraint/a/f.c:J
      29: return

  public void addView(android.view.View, int, android.view.ViewGroup$LayoutParams);
    Code:
       0: aload_0
       1: aload_1
       2: iload_2
       3: aload_3
       4: invokespecial #457                // Method android/view/ViewGroup.addView:(Landroid/view/View;ILandroid/view/ViewGroup$LayoutParams;)V
       7: getstatic     #462                // Field android/os/Build$VERSION.SDK_INT:I
      10: bipush        14
      12: if_icmpge     20
      15: aload_0
      16: aload_1
      17: invokevirtual #466                // Method onViewAdded:(Landroid/view/View;)V
      20: return

  protected boolean checkLayoutParams(android.view.ViewGroup$LayoutParams);
    Code:
       0: aload_1
       1: instanceof    #6                  // class android/support/constraint/ConstraintLayout$a
       4: ireturn

  public void dispatchDraw(android.graphics.Canvas);
    Code:
       0: aload_0
       1: aload_1
       2: invokespecial #472                // Method android/view/ViewGroup.dispatchDraw:(Landroid/graphics/Canvas;)V
       5: aload_0
       6: invokevirtual #475                // Method isInEditMode:()Z
       9: ifeq          329
      12: aload_0
      13: invokevirtual #126                // Method getChildCount:()I
      16: istore        9
      18: aload_0
      19: invokevirtual #478                // Method getWidth:()I
      22: i2f
      23: fstore_2
      24: aload_0
      25: invokevirtual #481                // Method getHeight:()I
      28: i2f
      29: fstore_3
      30: iconst_0
      31: istore        8
      33: iload         8
      35: iload         9
      37: if_icmpge     329
      40: aload_0
      41: iload         8
      43: invokevirtual #130                // Method getChildAt:(I)Landroid/view/View;
      46: astore        14
      48: aload         14
      50: invokevirtual #135                // Method android/view/View.getVisibility:()I
      53: bipush        8
      55: if_icmpne     61
      58: goto          320
      61: aload         14
      63: invokevirtual #485                // Method android/view/View.getTag:()Ljava/lang/Object;
      66: astore        14
      68: aload         14
      70: ifnull        320
      73: aload         14
      75: instanceof    #418                // class java/lang/String
      78: ifeq          320
      81: aload         14
      83: checkcast     #418                // class java/lang/String
      86: ldc_w         #487                // String ,
      89: invokevirtual #491                // Method java/lang/String.split:(Ljava/lang/String;)[Ljava/lang/String;
      92: astore        14
      94: aload         14
      96: arraylength
      97: iconst_4
      98: if_icmpne     320
     101: aload         14
     103: iconst_0
     104: aaload
     105: invokestatic  #494                // Method java/lang/Integer.parseInt:(Ljava/lang/String;)I
     108: istore        11
     110: aload         14
     112: iconst_1
     113: aaload
     114: invokestatic  #494                // Method java/lang/Integer.parseInt:(Ljava/lang/String;)I
     117: istore        13
     119: aload         14
     121: iconst_2
     122: aaload
     123: invokestatic  #494                // Method java/lang/Integer.parseInt:(Ljava/lang/String;)I
     126: istore        12
     128: aload         14
     130: iconst_3
     131: aaload
     132: invokestatic  #494                // Method java/lang/Integer.parseInt:(Ljava/lang/String;)I
     135: istore        10
     137: iload         11
     139: i2f
     140: ldc_w         #495                // float 1080.0f
     143: fdiv
     144: fload_2
     145: fmul
     146: f2i
     147: istore        11
     149: iload         13
     151: i2f
     152: ldc_w         #496                // float 1920.0f
     155: fdiv
     156: fload_3
     157: fmul
     158: f2i
     159: istore        13
     161: iload         12
     163: i2f
     164: ldc_w         #495                // float 1080.0f
     167: fdiv
     168: fload_2
     169: fmul
     170: f2i
     171: istore        12
     173: iload         10
     175: i2f
     176: ldc_w         #496                // float 1920.0f
     179: fdiv
     180: fload_3
     181: fmul
     182: f2i
     183: istore        10
     185: new           #498                // class android/graphics/Paint
     188: dup
     189: invokespecial #499                // Method android/graphics/Paint."<init>":()V
     192: astore        14
     194: aload         14
     196: ldc_w         #500                // int -65536
     199: invokevirtual #503                // Method android/graphics/Paint.setColor:(I)V
     202: iload         11
     204: i2f
     205: fstore        4
     207: iload         13
     209: i2f
     210: fstore        5
     212: iload         11
     214: iload         12
     216: iadd
     217: i2f
     218: fstore        6
     220: aload_1
     221: fload         4
     223: fload         5
     225: fload         6
     227: fload         5
     229: aload         14
     231: invokevirtual #509                // Method android/graphics/Canvas.drawLine:(FFFFLandroid/graphics/Paint;)V
     234: iload         13
     236: iload         10
     238: iadd
     239: i2f
     240: fstore        7
     242: aload_1
     243: fload         6
     245: fload         5
     247: fload         6
     249: fload         7
     251: aload         14
     253: invokevirtual #509                // Method android/graphics/Canvas.drawLine:(FFFFLandroid/graphics/Paint;)V
     256: aload_1
     257: fload         6
     259: fload         7
     261: fload         4
     263: fload         7
     265: aload         14
     267: invokevirtual #509                // Method android/graphics/Canvas.drawLine:(FFFFLandroid/graphics/Paint;)V
     270: aload_1
     271: fload         4
     273: fload         7
     275: fload         4
     277: fload         5
     279: aload         14
     281: invokevirtual #509                // Method android/graphics/Canvas.drawLine:(FFFFLandroid/graphics/Paint;)V
     284: aload         14
     286: ldc_w         #510                // int -16711936
     289: invokevirtual #503                // Method android/graphics/Paint.setColor:(I)V
     292: aload_1
     293: fload         4
     295: fload         5
     297: fload         6
     299: fload         7
     301: aload         14
     303: invokevirtual #509                // Method android/graphics/Canvas.drawLine:(FFFFLandroid/graphics/Paint;)V
     306: aload_1
     307: fload         4
     309: fload         7
     311: fload         6
     313: fload         5
     315: aload         14
     317: invokevirtual #509                // Method android/graphics/Canvas.drawLine:(FFFFLandroid/graphics/Paint;)V
     320: iload         8
     322: iconst_1
     323: iadd
     324: istore        8
     326: goto          33
     329: return

  protected android.view.ViewGroup$LayoutParams generateDefaultLayoutParams();
    Code:
       0: aload_0
       1: invokevirtual #513                // Method a:()Landroid/support/constraint/ConstraintLayout$a;
       4: areturn

  public android.view.ViewGroup$LayoutParams generateLayoutParams(android.util.AttributeSet);
    Code:
       0: aload_0
       1: aload_1
       2: invokevirtual #517                // Method a:(Landroid/util/AttributeSet;)Landroid/support/constraint/ConstraintLayout$a;
       5: areturn

  protected android.view.ViewGroup$LayoutParams generateLayoutParams(android.view.ViewGroup$LayoutParams);
    Code:
       0: new           #6                  // class android/support/constraint/ConstraintLayout$a
       3: dup
       4: aload_1
       5: invokespecial #521                // Method android/support/constraint/ConstraintLayout$a."<init>":(Landroid/view/ViewGroup$LayoutParams;)V
       8: areturn

  public int getMaxHeight();
    Code:
       0: aload_0
       1: getfield      #74                 // Field l:I
       4: ireturn

  public int getMaxWidth();
    Code:
       0: aload_0
       1: getfield      #72                 // Field k:I
       4: ireturn

  public int getMinHeight();
    Code:
       0: aload_0
       1: getfield      #69                 // Field j:I
       4: ireturn

  public int getMinWidth();
    Code:
       0: aload_0
       1: getfield      #67                 // Field i:I
       4: ireturn

  public int getOptimizationLevel();
    Code:
       0: aload_0
       1: getfield      #65                 // Field b:Landroid/support/constraint/a/a/e;
       4: invokevirtual #529                // Method android/support/constraint/a/a/e.H:()I
       7: ireturn

  protected void onLayout(boolean, int, int, int, int);
    Code:
       0: aload_0
       1: invokevirtual #126                // Method getChildCount:()I
       4: istore        4
       6: aload_0
       7: invokevirtual #475                // Method isInEditMode:()Z
      10: istore_1
      11: iconst_0
      12: istore_3
      13: iconst_0
      14: istore_2
      15: iload_2
      16: iload         4
      18: if_icmpge     185
      21: aload_0
      22: iload_2
      23: invokevirtual #130                // Method getChildAt:(I)Landroid/view/View;
      26: astore        9
      28: aload         9
      30: invokevirtual #139                // Method android/view/View.getLayoutParams:()Landroid/view/ViewGroup$LayoutParams;
      33: checkcast     #6                  // class android/support/constraint/ConstraintLayout$a
      36: astore        10
      38: aload         10
      40: getfield      #143                // Field android/support/constraint/ConstraintLayout$a.al:Landroid/support/constraint/a/a/d;
      43: astore        11
      45: aload         9
      47: invokevirtual #135                // Method android/view/View.getVisibility:()I
      50: bipush        8
      52: if_icmpne     78
      55: aload         10
      57: getfield      #146                // Field android/support/constraint/ConstraintLayout$a.Y:Z
      60: ifne          78
      63: aload         10
      65: getfield      #148                // Field android/support/constraint/ConstraintLayout$a.Z:Z
      68: ifne          78
      71: iload_1
      72: ifne          78
      75: goto          178
      78: aload         10
      80: getfield      #534                // Field android/support/constraint/ConstraintLayout$a.aa:Z
      83: ifeq          89
      86: goto          178
      89: aload         11
      91: invokevirtual #536                // Method android/support/constraint/a/a/d.s:()I
      94: istore        5
      96: aload         11
      98: invokevirtual #538                // Method android/support/constraint/a/a/d.t:()I
     101: istore        6
     103: aload         11
     105: invokevirtual #540                // Method android/support/constraint/a/a/d.o:()I
     108: iload         5
     110: iadd
     111: istore        7
     113: aload         11
     115: invokevirtual #542                // Method android/support/constraint/a/a/d.q:()I
     118: iload         6
     120: iadd
     121: istore        8
     123: aload         9
     125: iload         5
     127: iload         6
     129: iload         7
     131: iload         8
     133: invokevirtual #546                // Method android/view/View.layout:(IIII)V
     136: aload         9
     138: instanceof    #398                // class android/support/constraint/e
     141: ifeq          178
     144: aload         9
     146: checkcast     #398                // class android/support/constraint/e
     149: invokevirtual #550                // Method android/support/constraint/e.getContent:()Landroid/view/View;
     152: astore        9
     154: aload         9
     156: ifnull        178
     159: aload         9
     161: iconst_0
     162: invokevirtual #553                // Method android/view/View.setVisibility:(I)V
     165: aload         9
     167: iload         5
     169: iload         6
     171: iload         7
     173: iload         8
     175: invokevirtual #546                // Method android/view/View.layout:(IIII)V
     178: iload_2
     179: iconst_1
     180: iadd
     181: istore_2
     182: goto          15
     185: aload_0
     186: getfield      #58                 // Field g:Ljava/util/ArrayList;
     189: invokevirtual #404                // Method java/util/ArrayList.size:()I
     192: istore        4
     194: iload         4
     196: ifle          229
     199: iload_3
     200: istore_2
     201: iload_2
     202: iload         4
     204: if_icmpge     229
     207: aload_0
     208: getfield      #58                 // Field g:Ljava/util/ArrayList;
     211: iload_2
     212: invokevirtual #405                // Method java/util/ArrayList.get:(I)Ljava/lang/Object;
     215: checkcast     #407                // class android/support/constraint/b
     218: aload_0
     219: invokevirtual #554                // Method android/support/constraint/b.b:(Landroid/support/constraint/ConstraintLayout;)V
     222: iload_2
     223: iconst_1
     224: iadd
     225: istore_2
     226: goto          201
     229: return

  protected void onMeasure(int, int);
    Code:
       0: invokestatic  #561                // Method java/lang/System.currentTimeMillis:()J
       3: pop2
       4: iload_1
       5: invokestatic  #372                // Method android/view/View$MeasureSpec.getMode:(I)I
       8: istore        4
      10: iload_1
      11: invokestatic  #375                // Method android/view/View$MeasureSpec.getSize:(I)I
      14: istore        5
      16: iload_2
      17: invokestatic  #372                // Method android/view/View$MeasureSpec.getMode:(I)I
      20: istore        6
      22: iload_2
      23: invokestatic  #375                // Method android/view/View$MeasureSpec.getSize:(I)I
      26: istore        7
      28: aload_0
      29: getfield      #89                 // Field r:I
      32: iconst_m1
      33: if_icmpeq     41
      36: aload_0
      37: getfield      #91                 // Field s:I
      40: istore_3
      41: iload         4
      43: ldc_w         #380                // int 1073741824
      46: if_icmpne     71
      49: iload         6
      51: ldc_w         #380                // int 1073741824
      54: if_icmpne     71
      57: iload         5
      59: aload_0
      60: getfield      #89                 // Field r:I
      63: if_icmpne     71
      66: aload_0
      67: getfield      #91                 // Field s:I
      70: istore_3
      71: iload         4
      73: aload_0
      74: getfield      #97                 // Field e:I
      77: if_icmpne     94
      80: iload         6
      82: aload_0
      83: getfield      #99                 // Field f:I
      86: if_icmpne     94
      89: iconst_1
      90: istore_3
      91: goto          96
      94: iconst_0
      95: istore_3
      96: iload_3
      97: ifeq          115
     100: iload         5
     102: aload_0
     103: getfield      #93                 // Field c:I
     106: if_icmpne     115
     109: aload_0
     110: getfield      #95                 // Field d:I
     113: istore        8
     115: iload_3
     116: ifeq          150
     119: iload         4
     121: ldc_w         #379                // int -2147483648
     124: if_icmpne     150
     127: iload         6
     129: ldc_w         #380                // int 1073741824
     132: if_icmpne     150
     135: iload         5
     137: aload_0
     138: getfield      #89                 // Field r:I
     141: if_icmplt     150
     144: aload_0
     145: getfield      #91                 // Field s:I
     148: istore        8
     150: iload_3
     151: ifeq          184
     154: iload         4
     156: ldc_w         #380                // int 1073741824
     159: if_icmpne     184
     162: iload         6
     164: ldc_w         #379                // int -2147483648
     167: if_icmpne     184
     170: iload         5
     172: aload_0
     173: getfield      #89                 // Field r:I
     176: if_icmpne     184
     179: aload_0
     180: getfield      #91                 // Field s:I
     183: istore_3
     184: aload_0
     185: iload         4
     187: putfield      #97                 // Field e:I
     190: aload_0
     191: iload         6
     193: putfield      #99                 // Field f:I
     196: aload_0
     197: iload         5
     199: putfield      #93                 // Field c:I
     202: aload_0
     203: iload         7
     205: putfield      #95                 // Field d:I
     208: aload_0
     209: invokevirtual #120                // Method getPaddingLeft:()I
     212: istore_3
     213: aload_0
     214: invokevirtual #114                // Method getPaddingTop:()I
     217: istore        4
     219: aload_0
     220: getfield      #65                 // Field b:Landroid/support/constraint/a/a/e;
     223: iload_3
     224: invokevirtual #563                // Method android/support/constraint/a/a/e.f:(I)V
     227: aload_0
     228: getfield      #65                 // Field b:Landroid/support/constraint/a/a/e;
     231: iload         4
     233: invokevirtual #565                // Method android/support/constraint/a/a/e.g:(I)V
     236: aload_0
     237: getfield      #65                 // Field b:Landroid/support/constraint/a/a/e;
     240: aload_0
     241: getfield      #72                 // Field k:I
     244: invokevirtual #567                // Method android/support/constraint/a/a/e.c:(I)V
     247: aload_0
     248: getfield      #65                 // Field b:Landroid/support/constraint/a/a/e;
     251: aload_0
     252: getfield      #74                 // Field l:I
     255: invokevirtual #569                // Method android/support/constraint/a/a/e.d:(I)V
     258: getstatic     #462                // Field android/os/Build$VERSION.SDK_INT:I
     261: bipush        17
     263: if_icmplt     296
     266: aload_0
     267: getfield      #65                 // Field b:Landroid/support/constraint/a/a/e;
     270: astore        20
     272: aload_0
     273: invokevirtual #572                // Method getLayoutDirection:()I
     276: iconst_1
     277: if_icmpne     286
     280: iconst_1
     281: istore        19
     283: goto          289
     286: iconst_0
     287: istore        19
     289: aload         20
     291: iload         19
     293: invokevirtual #574                // Method android/support/constraint/a/a/e.a:(Z)V
     296: aload_0
     297: iload_1
     298: iload_2
     299: invokespecial #576                // Method c:(II)V
     302: aload_0
     303: getfield      #65                 // Field b:Landroid/support/constraint/a/a/e;
     306: invokevirtual #577                // Method android/support/constraint/a/a/e.o:()I
     309: istore        13
     311: aload_0
     312: getfield      #65                 // Field b:Landroid/support/constraint/a/a/e;
     315: invokevirtual #578                // Method android/support/constraint/a/a/e.q:()I
     318: istore        14
     320: aload_0
     321: getfield      #76                 // Field m:Z
     324: ifeq          336
     327: aload_0
     328: iconst_0
     329: putfield      #76                 // Field m:Z
     332: aload_0
     333: invokespecial #580                // Method b:()V
     336: aload_0
     337: getfield      #78                 // Field n:I
     340: bipush        8
     342: iand
     343: bipush        8
     345: if_icmpne     354
     348: iconst_1
     349: istore        9
     351: goto          357
     354: iconst_0
     355: istore        9
     357: iload         9
     359: ifeq          389
     362: aload_0
     363: getfield      #65                 // Field b:Landroid/support/constraint/a/a/e;
     366: invokevirtual #583                // Method android/support/constraint/a/a/e.M:()V
     369: aload_0
     370: getfield      #65                 // Field b:Landroid/support/constraint/a/a/e;
     373: iload         13
     375: iload         14
     377: invokevirtual #585                // Method android/support/constraint/a/a/e.e:(II)V
     380: aload_0
     381: iload_1
     382: iload_2
     383: invokespecial #587                // Method b:(II)V
     386: goto          395
     389: aload_0
     390: iload_1
     391: iload_2
     392: invokespecial #589                // Method a:(II)V
     395: aload_0
     396: invokespecial #591                // Method d:()V
     399: aload_0
     400: invokevirtual #126                // Method getChildCount:()I
     403: ifle          413
     406: aload_0
     407: ldc_w         #593                // String First pass
     410: invokevirtual #595                // Method a:(Ljava/lang/String;)V
     413: aload_0
     414: getfield      #60                 // Field h:Ljava/util/ArrayList;
     417: invokevirtual #404                // Method java/util/ArrayList.size:()I
     420: istore        11
     422: iload         4
     424: aload_0
     425: invokevirtual #117                // Method getPaddingBottom:()I
     428: iadd
     429: istore        17
     431: iload_3
     432: aload_0
     433: invokevirtual #123                // Method getPaddingRight:()I
     436: iadd
     437: istore        6
     439: iload         11
     441: ifle          1326
     444: aload_0
     445: getfield      #65                 // Field b:Landroid/support/constraint/a/a/e;
     448: invokevirtual #263                // Method android/support/constraint/a/a/e.F:()Landroid/support/constraint/a/a/d$a;
     451: getstatic     #268                // Field android/support/constraint/a/a/d$a.b:Landroid/support/constraint/a/a/d$a;
     454: if_acmpne     463
     457: iconst_1
     458: istore        10
     460: goto          466
     463: iconst_0
     464: istore        10
     466: aload_0
     467: getfield      #65                 // Field b:Landroid/support/constraint/a/a/e;
     470: invokevirtual #271                // Method android/support/constraint/a/a/e.G:()Landroid/support/constraint/a/a/d$a;
     473: getstatic     #268                // Field android/support/constraint/a/a/d$a.b:Landroid/support/constraint/a/a/d$a;
     476: if_acmpne     485
     479: iconst_1
     480: istore        12
     482: goto          488
     485: iconst_0
     486: istore        12
     488: aload_0
     489: getfield      #65                 // Field b:Landroid/support/constraint/a/a/e;
     492: invokevirtual #577                // Method android/support/constraint/a/a/e.o:()I
     495: aload_0
     496: getfield      #67                 // Field i:I
     499: invokestatic  #598                // Method java/lang/Math.max:(II)I
     502: istore        5
     504: aload_0
     505: getfield      #65                 // Field b:Landroid/support/constraint/a/a/e;
     508: invokevirtual #578                // Method android/support/constraint/a/a/e.q:()I
     511: aload_0
     512: getfield      #69                 // Field j:I
     515: invokestatic  #598                // Method java/lang/Math.max:(II)I
     518: istore_3
     519: iconst_0
     520: istore        15
     522: iconst_0
     523: istore        7
     525: iconst_0
     526: istore        4
     528: iload         15
     530: iload         11
     532: if_icmpge     1074
     535: aload_0
     536: getfield      #60                 // Field h:Ljava/util/ArrayList;
     539: iload         15
     541: invokevirtual #405                // Method java/util/ArrayList.get:(I)Ljava/lang/Object;
     544: checkcast     #150                // class android/support/constraint/a/a/d
     547: astore        20
     549: aload         20
     551: invokevirtual #601                // Method android/support/constraint/a/a/d.B:()Ljava/lang/Object;
     554: checkcast     #132                // class android/view/View
     557: astore        21
     559: aload         21
     561: ifnonnull     567
     564: goto          1049
     567: aload         21
     569: invokevirtual #139                // Method android/view/View.getLayoutParams:()Landroid/view/ViewGroup$LayoutParams;
     572: checkcast     #6                  // class android/support/constraint/ConstraintLayout$a
     575: astore        22
     577: aload         22
     579: getfield      #148                // Field android/support/constraint/ConstraintLayout$a.Z:Z
     582: ifne          1046
     585: aload         22
     587: getfield      #146                // Field android/support/constraint/ConstraintLayout$a.Y:Z
     590: ifeq          596
     593: goto          1046
     596: aload         21
     598: invokevirtual #135                // Method android/view/View.getVisibility:()I
     601: bipush        8
     603: if_icmpne     609
     606: goto          564
     609: iload         9
     611: ifeq          639
     614: aload         20
     616: invokevirtual #226                // Method android/support/constraint/a/a/d.h:()Landroid/support/constraint/a/a/k;
     619: invokevirtual #602                // Method android/support/constraint/a/a/k.g:()Z
     622: ifeq          639
     625: aload         20
     627: invokevirtual #232                // Method android/support/constraint/a/a/d.i:()Landroid/support/constraint/a/a/k;
     630: invokevirtual #602                // Method android/support/constraint/a/a/k.g:()Z
     633: ifeq          639
     636: goto          606
     639: aload         22
     641: getfield      #155                // Field android/support/constraint/ConstraintLayout$a.width:I
     644: bipush        -2
     646: if_icmpne     673
     649: aload         22
     651: getfield      #161                // Field android/support/constraint/ConstraintLayout$a.V:Z
     654: ifeq          673
     657: iload_1
     658: iload         6
     660: aload         22
     662: getfield      #155                // Field android/support/constraint/ConstraintLayout$a.width:I
     665: invokestatic  #173                // Method getChildMeasureSpec:(III)I
     668: istore        8
     670: goto          686
     673: aload         20
     675: invokevirtual #540                // Method android/support/constraint/a/a/d.o:()I
     678: ldc_w         #380                // int 1073741824
     681: invokestatic  #605                // Method android/view/View$MeasureSpec.makeMeasureSpec:(II)I
     684: istore        8
     686: aload         22
     688: getfield      #158                // Field android/support/constraint/ConstraintLayout$a.height:I
     691: bipush        -2
     693: if_icmpne     720
     696: aload         22
     698: getfield      #164                // Field android/support/constraint/ConstraintLayout$a.W:Z
     701: ifeq          720
     704: iload_2
     705: iload         17
     707: aload         22
     709: getfield      #158                // Field android/support/constraint/ConstraintLayout$a.height:I
     712: invokestatic  #173                // Method getChildMeasureSpec:(III)I
     715: istore        16
     717: goto          733
     720: aload         20
     722: invokevirtual #542                // Method android/support/constraint/a/a/d.q:()I
     725: ldc_w         #380                // int 1073741824
     728: invokestatic  #605                // Method android/view/View$MeasureSpec.makeMeasureSpec:(II)I
     731: istore        16
     733: aload         21
     735: iload         8
     737: iload         16
     739: invokevirtual #176                // Method android/view/View.measure:(II)V
     742: aload_0
     743: getfield      #178                // Field t:Landroid/support/constraint/a/f;
     746: ifnull        770
     749: aload_0
     750: getfield      #178                // Field t:Landroid/support/constraint/a/f;
     753: astore        23
     755: aload         23
     757: aload         23
     759: getfield      #607                // Field android/support/constraint/a/f.b:J
     762: lconst_1
     763: ladd
     764: putfield      #607                // Field android/support/constraint/a/f.b:J
     767: goto          770
     770: aload         21
     772: invokevirtual #190                // Method android/view/View.getMeasuredWidth:()I
     775: istore        18
     777: aload         21
     779: invokevirtual #193                // Method android/view/View.getMeasuredHeight:()I
     782: istore        16
     784: iload         7
     786: istore        8
     788: iload         5
     790: istore        7
     792: iload         18
     794: aload         20
     796: invokevirtual #540                // Method android/support/constraint/a/a/d.o:()I
     799: if_icmpeq     874
     802: aload         20
     804: iload         18
     806: invokevirtual #195                // Method android/support/constraint/a/a/d.h:(I)V
     809: iload         9
     811: ifeq          824
     814: aload         20
     816: invokevirtual #226                // Method android/support/constraint/a/a/d.h:()Landroid/support/constraint/a/a/k;
     819: iload         18
     821: invokevirtual #230                // Method android/support/constraint/a/a/k.a:(I)V
     824: iload         5
     826: istore        7
     828: iload         10
     830: ifeq          871
     833: iload         5
     835: istore        7
     837: aload         20
     839: invokevirtual #610                // Method android/support/constraint/a/a/d.w:()I
     842: iload         5
     844: if_icmple     871
     847: iload         5
     849: aload         20
     851: invokevirtual #610                // Method android/support/constraint/a/a/d.w:()I
     854: aload         20
     856: getstatic     #252                // Field android/support/constraint/a/a/c$c.d:Landroid/support/constraint/a/a/c$c;
     859: invokevirtual #245                // Method android/support/constraint/a/a/d.a:(Landroid/support/constraint/a/a/c$c;)Landroid/support/constraint/a/a/c;
     862: invokevirtual #612                // Method android/support/constraint/a/a/c.e:()I
     865: iadd
     866: invokestatic  #598                // Method java/lang/Math.max:(II)I
     869: istore        7
     871: iconst_1
     872: istore        8
     874: iload         16
     876: aload         20
     878: invokevirtual #542                // Method android/support/constraint/a/a/d.q:()I
     881: if_icmpeq     960
     884: aload         20
     886: iload         16
     888: invokevirtual #197                // Method android/support/constraint/a/a/d.i:(I)V
     891: iload         9
     893: ifeq          906
     896: aload         20
     898: invokevirtual #232                // Method android/support/constraint/a/a/d.i:()Landroid/support/constraint/a/a/k;
     901: iload         16
     903: invokevirtual #230                // Method android/support/constraint/a/a/k.a:(I)V
     906: iload         12
     908: ifeq          954
     911: aload         20
     913: invokevirtual #615                // Method android/support/constraint/a/a/d.x:()I
     916: istore        8
     918: iload_3
     919: istore        5
     921: iload         8
     923: iload         5
     925: if_icmple     954
     928: iload         5
     930: aload         20
     932: invokevirtual #615                // Method android/support/constraint/a/a/d.x:()I
     935: aload         20
     937: getstatic     #259                // Field android/support/constraint/a/a/c$c.e:Landroid/support/constraint/a/a/c$c;
     940: invokevirtual #245                // Method android/support/constraint/a/a/d.a:(Landroid/support/constraint/a/a/c$c;)Landroid/support/constraint/a/a/c;
     943: invokevirtual #612                // Method android/support/constraint/a/a/c.e:()I
     946: iadd
     947: invokestatic  #598                // Method java/lang/Math.max:(II)I
     950: istore_3
     951: goto          954
     954: iconst_1
     955: istore        8
     957: goto          960
     960: aload         22
     962: getfield      #204                // Field android/support/constraint/ConstraintLayout$a.X:Z
     965: ifeq          1012
     968: aload         21
     970: invokevirtual #207                // Method android/view/View.getBaseline:()I
     973: istore        16
     975: iload         8
     977: istore        5
     979: iload         16
     981: iconst_m1
     982: if_icmpeq     1016
     985: iload         8
     987: istore        5
     989: iload         16
     991: aload         20
     993: invokevirtual #618                // Method android/support/constraint/a/a/d.A:()I
     996: if_icmpeq     1016
     999: aload         20
    1001: iload         16
    1003: invokevirtual #209                // Method android/support/constraint/a/a/d.n:(I)V
    1006: iconst_1
    1007: istore        5
    1009: goto          1016
    1012: iload         8
    1014: istore        5
    1016: getstatic     #462                // Field android/os/Build$VERSION.SDK_INT:I
    1019: bipush        11
    1021: if_icmplt     1039
    1024: iload         4
    1026: aload         21
    1028: invokevirtual #621                // Method android/view/View.getMeasuredState:()I
    1031: invokestatic  #624                // Method combineMeasuredStates:(II)I
    1034: istore        4
    1036: goto          1039
    1039: iload         7
    1041: istore        8
    1043: goto          1057
    1046: goto          564
    1049: iload         5
    1051: istore        8
    1053: iload         7
    1055: istore        5
    1057: iload         15
    1059: iconst_1
    1060: iadd
    1061: istore        15
    1063: iload         5
    1065: istore        7
    1067: iload         8
    1069: istore        5
    1071: goto          528
    1074: iload         4
    1076: istore        8
    1078: iload         7
    1080: ifeq          1184
    1083: aload_0
    1084: getfield      #65                 // Field b:Landroid/support/constraint/a/a/e;
    1087: iload         13
    1089: invokevirtual #393                // Method android/support/constraint/a/a/e.h:(I)V
    1092: aload_0
    1093: getfield      #65                 // Field b:Landroid/support/constraint/a/a/e;
    1096: iload         14
    1098: invokevirtual #396                // Method android/support/constraint/a/a/e.i:(I)V
    1101: iload         9
    1103: ifeq          1113
    1106: aload_0
    1107: getfield      #65                 // Field b:Landroid/support/constraint/a/a/e;
    1110: invokevirtual #237                // Method android/support/constraint/a/a/e.N:()V
    1113: aload_0
    1114: ldc_w         #626                // String 2nd pass
    1117: invokevirtual #595                // Method a:(Ljava/lang/String;)V
    1120: aload_0
    1121: getfield      #65                 // Field b:Landroid/support/constraint/a/a/e;
    1124: invokevirtual #577                // Method android/support/constraint/a/a/e.o:()I
    1127: iload         5
    1129: if_icmpge     1147
    1132: aload_0
    1133: getfield      #65                 // Field b:Landroid/support/constraint/a/a/e;
    1136: iload         5
    1138: invokevirtual #393                // Method android/support/constraint/a/a/e.h:(I)V
    1141: iconst_1
    1142: istore        4
    1144: goto          1150
    1147: iconst_0
    1148: istore        4
    1150: aload_0
    1151: getfield      #65                 // Field b:Landroid/support/constraint/a/a/e;
    1154: invokevirtual #578                // Method android/support/constraint/a/a/e.q:()I
    1157: iload_3
    1158: if_icmpge     1172
    1161: aload_0
    1162: getfield      #65                 // Field b:Landroid/support/constraint/a/a/e;
    1165: iload_3
    1166: invokevirtual #396                // Method android/support/constraint/a/a/e.i:(I)V
    1169: iconst_1
    1170: istore        4
    1172: iload         4
    1174: ifeq          1184
    1177: aload_0
    1178: ldc_w         #628                // String 3rd pass
    1181: invokevirtual #595                // Method a:(Ljava/lang/String;)V
    1184: iconst_0
    1185: istore        5
    1187: iload         8
    1189: istore        4
    1191: iload         6
    1193: istore_3
    1194: iload         5
    1196: iload         11
    1198: if_icmpge     1332
    1201: aload_0
    1202: getfield      #60                 // Field h:Ljava/util/ArrayList;
    1205: iload         5
    1207: invokevirtual #405                // Method java/util/ArrayList.get:(I)Ljava/lang/Object;
    1210: checkcast     #150                // class android/support/constraint/a/a/d
    1213: astore        20
    1215: aload         20
    1217: invokevirtual #601                // Method android/support/constraint/a/a/d.B:()Ljava/lang/Object;
    1220: checkcast     #132                // class android/view/View
    1223: astore        21
    1225: aload         21
    1227: ifnonnull     1233
    1230: goto          1262
    1233: aload         21
    1235: invokevirtual #190                // Method android/view/View.getMeasuredWidth:()I
    1238: aload         20
    1240: invokevirtual #540                // Method android/support/constraint/a/a/d.o:()I
    1243: if_icmpne     1265
    1246: aload         21
    1248: invokevirtual #193                // Method android/view/View.getMeasuredHeight:()I
    1251: aload         20
    1253: invokevirtual #542                // Method android/support/constraint/a/a/d.q:()I
    1256: if_icmpeq     1262
    1259: goto          1265
    1262: goto          1317
    1265: aload         21
    1267: aload         20
    1269: invokevirtual #540                // Method android/support/constraint/a/a/d.o:()I
    1272: ldc_w         #380                // int 1073741824
    1275: invokestatic  #605                // Method android/view/View$MeasureSpec.makeMeasureSpec:(II)I
    1278: aload         20
    1280: invokevirtual #542                // Method android/support/constraint/a/a/d.q:()I
    1283: ldc_w         #380                // int 1073741824
    1286: invokestatic  #605                // Method android/view/View$MeasureSpec.makeMeasureSpec:(II)I
    1289: invokevirtual #176                // Method android/view/View.measure:(II)V
    1292: aload_0
    1293: getfield      #178                // Field t:Landroid/support/constraint/a/f;
    1296: ifnull        1317
    1299: aload_0
    1300: getfield      #178                // Field t:Landroid/support/constraint/a/f;
    1303: astore        20
    1305: aload         20
    1307: aload         20
    1309: getfield      #607                // Field android/support/constraint/a/f.b:J
    1312: lconst_1
    1313: ladd
    1314: putfield      #607                // Field android/support/constraint/a/f.b:J
    1317: iload         5
    1319: iconst_1
    1320: iadd
    1321: istore        5
    1323: goto          1187
    1326: iload         6
    1328: istore_3
    1329: iconst_0
    1330: istore        4
    1332: aload_0
    1333: getfield      #65                 // Field b:Landroid/support/constraint/a/a/e;
    1336: invokevirtual #577                // Method android/support/constraint/a/a/e.o:()I
    1339: iload_3
    1340: iadd
    1341: istore        6
    1343: aload_0
    1344: getfield      #65                 // Field b:Landroid/support/constraint/a/a/e;
    1347: invokevirtual #578                // Method android/support/constraint/a/a/e.q:()I
    1350: iload         17
    1352: iadd
    1353: istore        7
    1355: iload         6
    1357: istore        5
    1359: iload         7
    1361: istore_3
    1362: getstatic     #462                // Field android/os/Build$VERSION.SDK_INT:I
    1365: bipush        11
    1367: if_icmplt     1459
    1370: iload         6
    1372: iload_1
    1373: iload         4
    1375: invokestatic  #631                // Method resolveSizeAndState:(III)I
    1378: istore_1
    1379: iload         7
    1381: iload_2
    1382: iload         4
    1384: bipush        16
    1386: ishl
    1387: invokestatic  #631                // Method resolveSizeAndState:(III)I
    1390: istore_2
    1391: aload_0
    1392: getfield      #72                 // Field k:I
    1395: iload_1
    1396: ldc_w         #632                // int 16777215
    1399: iand
    1400: invokestatic  #385                // Method java/lang/Math.min:(II)I
    1403: istore_3
    1404: aload_0
    1405: getfield      #74                 // Field l:I
    1408: iload_2
    1409: ldc_w         #632                // int 16777215
    1412: iand
    1413: invokestatic  #385                // Method java/lang/Math.min:(II)I
    1416: istore_2
    1417: iload_3
    1418: istore_1
    1419: aload_0
    1420: getfield      #65                 // Field b:Landroid/support/constraint/a/a/e;
    1423: invokevirtual #634                // Method android/support/constraint/a/a/e.I:()Z
    1426: ifeq          1435
    1429: iload_3
    1430: ldc_w         #635                // int 16777216
    1433: ior
    1434: istore_1
    1435: iload_1
    1436: istore        5
    1438: iload_2
    1439: istore_3
    1440: aload_0
    1441: getfield      #65                 // Field b:Landroid/support/constraint/a/a/e;
    1444: invokevirtual #637                // Method android/support/constraint/a/a/e.J:()Z
    1447: ifeq          1459
    1450: iload_2
    1451: ldc_w         #635                // int 16777216
    1454: ior
    1455: istore_3
    1456: iload_1
    1457: istore        5
    1459: aload_0
    1460: iload         5
    1462: iload_3
    1463: invokevirtual #640                // Method setMeasuredDimension:(II)V
    1466: aload_0
    1467: iload         5
    1469: putfield      #89                 // Field r:I
    1472: aload_0
    1473: iload_3
    1474: putfield      #91                 // Field s:I
    1477: return

  public void onViewAdded(android.view.View);
    Code:
       0: getstatic     #462                // Field android/os/Build$VERSION.SDK_INT:I
       3: bipush        14
       5: if_icmplt     13
       8: aload_0
       9: aload_1
      10: invokespecial #641                // Method android/view/ViewGroup.onViewAdded:(Landroid/view/View;)V
      13: aload_0
      14: aload_1
      15: invokevirtual #643                // Method a:(Landroid/view/View;)Landroid/support/constraint/a/a/d;
      18: astore_2
      19: aload_1
      20: instanceof    #645                // class android/support/constraint/Guideline
      23: ifeq          71
      26: aload_2
      27: instanceof    #647                // class android/support/constraint/a/a/f
      30: ifne          71
      33: aload_1
      34: invokevirtual #139                // Method android/view/View.getLayoutParams:()Landroid/view/ViewGroup$LayoutParams;
      37: checkcast     #6                  // class android/support/constraint/ConstraintLayout$a
      40: astore_2
      41: aload_2
      42: new           #647                // class android/support/constraint/a/a/f
      45: dup
      46: invokespecial #648                // Method android/support/constraint/a/a/f."<init>":()V
      49: putfield      #143                // Field android/support/constraint/ConstraintLayout$a.al:Landroid/support/constraint/a/a/d;
      52: aload_2
      53: iconst_1
      54: putfield      #146                // Field android/support/constraint/ConstraintLayout$a.Y:Z
      57: aload_2
      58: getfield      #143                // Field android/support/constraint/ConstraintLayout$a.al:Landroid/support/constraint/a/a/d;
      61: checkcast     #647                // class android/support/constraint/a/a/f
      64: aload_2
      65: getfield      #651                // Field android/support/constraint/ConstraintLayout$a.S:I
      68: invokevirtual #652                // Method android/support/constraint/a/a/f.a:(I)V
      71: aload_1
      72: instanceof    #407                // class android/support/constraint/b
      75: ifeq          118
      78: aload_1
      79: checkcast     #407                // class android/support/constraint/b
      82: astore_2
      83: aload_2
      84: invokevirtual #654                // Method android/support/constraint/b.a:()V
      87: aload_1
      88: invokevirtual #139                // Method android/view/View.getLayoutParams:()Landroid/view/ViewGroup$LayoutParams;
      91: checkcast     #6                  // class android/support/constraint/ConstraintLayout$a
      94: iconst_1
      95: putfield      #148                // Field android/support/constraint/ConstraintLayout$a.Z:Z
      98: aload_0
      99: getfield      #58                 // Field g:Ljava/util/ArrayList;
     102: aload_2
     103: invokevirtual #657                // Method java/util/ArrayList.contains:(Ljava/lang/Object;)Z
     106: ifne          118
     109: aload_0
     110: getfield      #58                 // Field g:Ljava/util/ArrayList;
     113: aload_2
     114: invokevirtual #660                // Method java/util/ArrayList.add:(Ljava/lang/Object;)Z
     117: pop
     118: aload_0
     119: getfield      #51                 // Field a:Landroid/util/SparseArray;
     122: aload_1
     123: invokevirtual #661                // Method android/view/View.getId:()I
     126: aload_1
     127: invokevirtual #295                // Method android/util/SparseArray.put:(ILjava/lang/Object;)V
     130: aload_0
     131: iconst_1
     132: putfield      #76                 // Field m:Z
     135: return

  public void onViewRemoved(android.view.View);
    Code:
       0: getstatic     #462                // Field android/os/Build$VERSION.SDK_INT:I
       3: bipush        14
       5: if_icmplt     13
       8: aload_0
       9: aload_1
      10: invokespecial #664                // Method android/view/ViewGroup.onViewRemoved:(Landroid/view/View;)V
      13: aload_0
      14: getfield      #51                 // Field a:Landroid/util/SparseArray;
      17: aload_1
      18: invokevirtual #661                // Method android/view/View.getId:()I
      21: invokevirtual #667                // Method android/util/SparseArray.remove:(I)V
      24: aload_0
      25: aload_1
      26: invokevirtual #643                // Method a:(Landroid/view/View;)Landroid/support/constraint/a/a/d;
      29: astore_2
      30: aload_0
      31: getfield      #65                 // Field b:Landroid/support/constraint/a/a/e;
      34: aload_2
      35: invokevirtual #670                // Method android/support/constraint/a/a/e.c:(Landroid/support/constraint/a/a/d;)V
      38: aload_0
      39: getfield      #58                 // Field g:Ljava/util/ArrayList;
      42: aload_1
      43: invokevirtual #672                // Method java/util/ArrayList.remove:(Ljava/lang/Object;)Z
      46: pop
      47: aload_0
      48: getfield      #60                 // Field h:Ljava/util/ArrayList;
      51: aload_2
      52: invokevirtual #672                // Method java/util/ArrayList.remove:(Ljava/lang/Object;)Z
      55: pop
      56: aload_0
      57: iconst_1
      58: putfield      #76                 // Field m:Z
      61: return

  public void removeView(android.view.View);
    Code:
       0: aload_0
       1: aload_1
       2: invokespecial #675                // Method android/view/ViewGroup.removeView:(Landroid/view/View;)V
       5: getstatic     #462                // Field android/os/Build$VERSION.SDK_INT:I
       8: bipush        14
      10: if_icmpge     18
      13: aload_0
      14: aload_1
      15: invokevirtual #676                // Method onViewRemoved:(Landroid/view/View;)V
      18: return

  public void requestLayout();
    Code:
       0: aload_0
       1: invokespecial #679                // Method android/view/ViewGroup.requestLayout:()V
       4: aload_0
       5: iconst_1
       6: putfield      #76                 // Field m:Z
       9: aload_0
      10: iconst_m1
      11: putfield      #89                 // Field r:I
      14: aload_0
      15: iconst_m1
      16: putfield      #91                 // Field s:I
      19: aload_0
      20: iconst_m1
      21: putfield      #93                 // Field c:I
      24: aload_0
      25: iconst_m1
      26: putfield      #95                 // Field d:I
      29: aload_0
      30: iconst_0
      31: putfield      #97                 // Field e:I
      34: aload_0
      35: iconst_0
      36: putfield      #99                 // Field f:I
      39: return

  public void setConstraintSet(android.support.constraint.c);
    Code:
       0: aload_0
       1: aload_1
       2: putfield      #80                 // Field o:Landroid/support/constraint/c;
       5: return

  public void setId(int);
    Code:
       0: aload_0
       1: getfield      #51                 // Field a:Landroid/util/SparseArray;
       4: aload_0
       5: invokevirtual #291                // Method getId:()I
       8: invokevirtual #667                // Method android/util/SparseArray.remove:(I)V
      11: aload_0
      12: iload_1
      13: invokespecial #684                // Method android/view/ViewGroup.setId:(I)V
      16: aload_0
      17: getfield      #51                 // Field a:Landroid/util/SparseArray;
      20: aload_0
      21: invokevirtual #291                // Method getId:()I
      24: aload_0
      25: invokevirtual #295                // Method android/util/SparseArray.put:(ILjava/lang/Object;)V
      28: return

  public void setMaxHeight(int);
    Code:
       0: iload_1
       1: aload_0
       2: getfield      #74                 // Field l:I
       5: if_icmpne     9
       8: return
       9: aload_0
      10: iload_1
      11: putfield      #74                 // Field l:I
      14: aload_0
      15: invokevirtual #686                // Method requestLayout:()V
      18: return

  public void setMaxWidth(int);
    Code:
       0: iload_1
       1: aload_0
       2: getfield      #72                 // Field k:I
       5: if_icmpne     9
       8: return
       9: aload_0
      10: iload_1
      11: putfield      #72                 // Field k:I
      14: aload_0
      15: invokevirtual #686                // Method requestLayout:()V
      18: return

  public void setMinHeight(int);
    Code:
       0: iload_1
       1: aload_0
       2: getfield      #69                 // Field j:I
       5: if_icmpne     9
       8: return
       9: aload_0
      10: iload_1
      11: putfield      #69                 // Field j:I
      14: aload_0
      15: invokevirtual #686                // Method requestLayout:()V
      18: return

  public void setMinWidth(int);
    Code:
       0: iload_1
       1: aload_0
       2: getfield      #67                 // Field i:I
       5: if_icmpne     9
       8: return
       9: aload_0
      10: iload_1
      11: putfield      #67                 // Field i:I
      14: aload_0
      15: invokevirtual #686                // Method requestLayout:()V
      18: return

  public void setOptimizationLevel(int);
    Code:
       0: aload_0
       1: getfield      #65                 // Field b:Landroid/support/constraint/a/a/e;
       4: iload_1
       5: invokevirtual #358                // Method android/support/constraint/a/a/e.a:(I)V
       8: return

  public boolean shouldDelayChildPressedState();
    Code:
       0: iconst_0
       1: ireturn
}
