public class android.support.constraint.ConstraintLayout$a extends android.view.ViewGroup$MarginLayoutParams {
  public float A;

  public java.lang.String B;

  float C;

  int D;

  public float E;

  public float F;

  public int G;

  public int H;

  public int I;

  public int J;

  public int K;

  public int L;

  public int M;

  public int N;

  public float O;

  public float P;

  public int Q;

  public int R;

  public int S;

  public boolean T;

  public boolean U;

  boolean V;

  boolean W;

  boolean X;

  boolean Y;

  boolean Z;

  public int a;

  boolean aa;

  int ab;

  int ac;

  int ad;

  int ae;

  int af;

  int ag;

  float ah;

  int ai;

  int aj;

  float ak;

  android.support.constraint.a.a.d al;

  public boolean am;

  public int b;

  public float c;

  public int d;

  public int e;

  public int f;

  public int g;

  public int h;

  public int i;

  public int j;

  public int k;

  public int l;

  public int m;

  public int n;

  public float o;

  public int p;

  public int q;

  public int r;

  public int s;

  public int t;

  public int u;

  public int v;

  public int w;

  public int x;

  public int y;

  public float z;

  public android.support.constraint.ConstraintLayout$a(int, int);
    Code:
       0: aload_0
       1: iload_1
       2: iload_2
       3: invokespecial #79                 // Method android/view/ViewGroup$MarginLayoutParams."<init>":(II)V
       6: aload_0
       7: iconst_m1
       8: putfield      #81                 // Field a:I
      11: aload_0
      12: iconst_m1
      13: putfield      #83                 // Field b:I
      16: aload_0
      17: ldc           #84                 // float -1.0f
      19: putfield      #86                 // Field c:F
      22: aload_0
      23: iconst_m1
      24: putfield      #88                 // Field d:I
      27: aload_0
      28: iconst_m1
      29: putfield      #90                 // Field e:I
      32: aload_0
      33: iconst_m1
      34: putfield      #92                 // Field f:I
      37: aload_0
      38: iconst_m1
      39: putfield      #94                 // Field g:I
      42: aload_0
      43: iconst_m1
      44: putfield      #96                 // Field h:I
      47: aload_0
      48: iconst_m1
      49: putfield      #98                 // Field i:I
      52: aload_0
      53: iconst_m1
      54: putfield      #100                // Field j:I
      57: aload_0
      58: iconst_m1
      59: putfield      #102                // Field k:I
      62: aload_0
      63: iconst_m1
      64: putfield      #104                // Field l:I
      67: aload_0
      68: iconst_m1
      69: putfield      #106                // Field m:I
      72: aload_0
      73: iconst_0
      74: putfield      #108                // Field n:I
      77: aload_0
      78: fconst_0
      79: putfield      #110                // Field o:F
      82: aload_0
      83: iconst_m1
      84: putfield      #112                // Field p:I
      87: aload_0
      88: iconst_m1
      89: putfield      #114                // Field q:I
      92: aload_0
      93: iconst_m1
      94: putfield      #116                // Field r:I
      97: aload_0
      98: iconst_m1
      99: putfield      #118                // Field s:I
     102: aload_0
     103: iconst_m1
     104: putfield      #120                // Field t:I
     107: aload_0
     108: iconst_m1
     109: putfield      #122                // Field u:I
     112: aload_0
     113: iconst_m1
     114: putfield      #124                // Field v:I
     117: aload_0
     118: iconst_m1
     119: putfield      #126                // Field w:I
     122: aload_0
     123: iconst_m1
     124: putfield      #128                // Field x:I
     127: aload_0
     128: iconst_m1
     129: putfield      #130                // Field y:I
     132: aload_0
     133: ldc           #131                // float 0.5f
     135: putfield      #133                // Field z:F
     138: aload_0
     139: ldc           #131                // float 0.5f
     141: putfield      #135                // Field A:F
     144: aload_0
     145: aconst_null
     146: putfield      #137                // Field B:Ljava/lang/String;
     149: aload_0
     150: fconst_0
     151: putfield      #139                // Field C:F
     154: aload_0
     155: iconst_1
     156: putfield      #141                // Field D:I
     159: aload_0
     160: fconst_0
     161: putfield      #143                // Field E:F
     164: aload_0
     165: fconst_0
     166: putfield      #145                // Field F:F
     169: aload_0
     170: iconst_0
     171: putfield      #147                // Field G:I
     174: aload_0
     175: iconst_0
     176: putfield      #149                // Field H:I
     179: aload_0
     180: iconst_0
     181: putfield      #151                // Field I:I
     184: aload_0
     185: iconst_0
     186: putfield      #153                // Field J:I
     189: aload_0
     190: iconst_0
     191: putfield      #155                // Field K:I
     194: aload_0
     195: iconst_0
     196: putfield      #157                // Field L:I
     199: aload_0
     200: iconst_0
     201: putfield      #159                // Field M:I
     204: aload_0
     205: iconst_0
     206: putfield      #161                // Field N:I
     209: aload_0
     210: fconst_1
     211: putfield      #163                // Field O:F
     214: aload_0
     215: fconst_1
     216: putfield      #165                // Field P:F
     219: aload_0
     220: iconst_m1
     221: putfield      #167                // Field Q:I
     224: aload_0
     225: iconst_m1
     226: putfield      #169                // Field R:I
     229: aload_0
     230: iconst_m1
     231: putfield      #171                // Field S:I
     234: aload_0
     235: iconst_0
     236: putfield      #173                // Field T:Z
     239: aload_0
     240: iconst_0
     241: putfield      #175                // Field U:Z
     244: aload_0
     245: iconst_1
     246: putfield      #177                // Field V:Z
     249: aload_0
     250: iconst_1
     251: putfield      #179                // Field W:Z
     254: aload_0
     255: iconst_0
     256: putfield      #181                // Field X:Z
     259: aload_0
     260: iconst_0
     261: putfield      #183                // Field Y:Z
     264: aload_0
     265: iconst_0
     266: putfield      #185                // Field Z:Z
     269: aload_0
     270: iconst_0
     271: putfield      #187                // Field aa:Z
     274: aload_0
     275: iconst_m1
     276: putfield      #189                // Field ab:I
     279: aload_0
     280: iconst_m1
     281: putfield      #191                // Field ac:I
     284: aload_0
     285: iconst_m1
     286: putfield      #193                // Field ad:I
     289: aload_0
     290: iconst_m1
     291: putfield      #195                // Field ae:I
     294: aload_0
     295: iconst_m1
     296: putfield      #197                // Field af:I
     299: aload_0
     300: iconst_m1
     301: putfield      #199                // Field ag:I
     304: aload_0
     305: ldc           #131                // float 0.5f
     307: putfield      #201                // Field ah:F
     310: aload_0
     311: new           #203                // class android/support/constraint/a/a/d
     314: dup
     315: invokespecial #206                // Method android/support/constraint/a/a/d."<init>":()V
     318: putfield      #208                // Field al:Landroid/support/constraint/a/a/d;
     321: aload_0
     322: iconst_0
     323: putfield      #210                // Field am:Z
     326: return

  public android.support.constraint.ConstraintLayout$a(android.content.Context, android.util.AttributeSet);
    Code:
       0: aload_0
       1: aload_1
       2: aload_2
       3: invokespecial #218                // Method android/view/ViewGroup$MarginLayoutParams."<init>":(Landroid/content/Context;Landroid/util/AttributeSet;)V
       6: aload_0
       7: iconst_m1
       8: putfield      #81                 // Field a:I
      11: aload_0
      12: iconst_m1
      13: putfield      #83                 // Field b:I
      16: aload_0
      17: ldc           #84                 // float -1.0f
      19: putfield      #86                 // Field c:F
      22: aload_0
      23: iconst_m1
      24: putfield      #88                 // Field d:I
      27: aload_0
      28: iconst_m1
      29: putfield      #90                 // Field e:I
      32: aload_0
      33: iconst_m1
      34: putfield      #92                 // Field f:I
      37: aload_0
      38: iconst_m1
      39: putfield      #94                 // Field g:I
      42: aload_0
      43: iconst_m1
      44: putfield      #96                 // Field h:I
      47: aload_0
      48: iconst_m1
      49: putfield      #98                 // Field i:I
      52: aload_0
      53: iconst_m1
      54: putfield      #100                // Field j:I
      57: aload_0
      58: iconst_m1
      59: putfield      #102                // Field k:I
      62: aload_0
      63: iconst_m1
      64: putfield      #104                // Field l:I
      67: aload_0
      68: iconst_m1
      69: putfield      #106                // Field m:I
      72: aload_0
      73: iconst_0
      74: putfield      #108                // Field n:I
      77: aload_0
      78: fconst_0
      79: putfield      #110                // Field o:F
      82: aload_0
      83: iconst_m1
      84: putfield      #112                // Field p:I
      87: aload_0
      88: iconst_m1
      89: putfield      #114                // Field q:I
      92: aload_0
      93: iconst_m1
      94: putfield      #116                // Field r:I
      97: aload_0
      98: iconst_m1
      99: putfield      #118                // Field s:I
     102: aload_0
     103: iconst_m1
     104: putfield      #120                // Field t:I
     107: aload_0
     108: iconst_m1
     109: putfield      #122                // Field u:I
     112: aload_0
     113: iconst_m1
     114: putfield      #124                // Field v:I
     117: aload_0
     118: iconst_m1
     119: putfield      #126                // Field w:I
     122: aload_0
     123: iconst_m1
     124: putfield      #128                // Field x:I
     127: aload_0
     128: iconst_m1
     129: putfield      #130                // Field y:I
     132: aload_0
     133: ldc           #131                // float 0.5f
     135: putfield      #133                // Field z:F
     138: aload_0
     139: ldc           #131                // float 0.5f
     141: putfield      #135                // Field A:F
     144: aload_0
     145: aconst_null
     146: putfield      #137                // Field B:Ljava/lang/String;
     149: aload_0
     150: fconst_0
     151: putfield      #139                // Field C:F
     154: aload_0
     155: iconst_1
     156: putfield      #141                // Field D:I
     159: aload_0
     160: fconst_0
     161: putfield      #143                // Field E:F
     164: aload_0
     165: fconst_0
     166: putfield      #145                // Field F:F
     169: aload_0
     170: iconst_0
     171: putfield      #147                // Field G:I
     174: aload_0
     175: iconst_0
     176: putfield      #149                // Field H:I
     179: aload_0
     180: iconst_0
     181: putfield      #151                // Field I:I
     184: aload_0
     185: iconst_0
     186: putfield      #153                // Field J:I
     189: aload_0
     190: iconst_0
     191: putfield      #155                // Field K:I
     194: aload_0
     195: iconst_0
     196: putfield      #157                // Field L:I
     199: aload_0
     200: iconst_0
     201: putfield      #159                // Field M:I
     204: aload_0
     205: iconst_0
     206: putfield      #161                // Field N:I
     209: aload_0
     210: fconst_1
     211: putfield      #163                // Field O:F
     214: aload_0
     215: fconst_1
     216: putfield      #165                // Field P:F
     219: aload_0
     220: iconst_m1
     221: putfield      #167                // Field Q:I
     224: aload_0
     225: iconst_m1
     226: putfield      #169                // Field R:I
     229: aload_0
     230: iconst_m1
     231: putfield      #171                // Field S:I
     234: aload_0
     235: iconst_0
     236: putfield      #173                // Field T:Z
     239: aload_0
     240: iconst_0
     241: putfield      #175                // Field U:Z
     244: aload_0
     245: iconst_1
     246: putfield      #177                // Field V:Z
     249: aload_0
     250: iconst_1
     251: putfield      #179                // Field W:Z
     254: aload_0
     255: iconst_0
     256: putfield      #181                // Field X:Z
     259: aload_0
     260: iconst_0
     261: putfield      #183                // Field Y:Z
     264: aload_0
     265: iconst_0
     266: putfield      #185                // Field Z:Z
     269: aload_0
     270: iconst_0
     271: putfield      #187                // Field aa:Z
     274: aload_0
     275: iconst_m1
     276: putfield      #189                // Field ab:I
     279: aload_0
     280: iconst_m1
     281: putfield      #191                // Field ac:I
     284: aload_0
     285: iconst_m1
     286: putfield      #193                // Field ad:I
     289: aload_0
     290: iconst_m1
     291: putfield      #195                // Field ae:I
     294: aload_0
     295: iconst_m1
     296: putfield      #197                // Field af:I
     299: aload_0
     300: iconst_m1
     301: putfield      #199                // Field ag:I
     304: aload_0
     305: ldc           #131                // float 0.5f
     307: putfield      #201                // Field ah:F
     310: aload_0
     311: new           #203                // class android/support/constraint/a/a/d
     314: dup
     315: invokespecial #206                // Method android/support/constraint/a/a/d."<init>":()V
     318: putfield      #208                // Field al:Landroid/support/constraint/a/a/d;
     321: aload_0
     322: iconst_0
     323: putfield      #210                // Field am:Z
     326: aload_1
     327: aload_2
     328: getstatic     #224                // Field android/support/constraint/f$b.ConstraintLayout_Layout:[I
     331: invokevirtual #230                // Method android/content/Context.obtainStyledAttributes:(Landroid/util/AttributeSet;[I)Landroid/content/res/TypedArray;
     334: astore_2
     335: aload_2
     336: invokevirtual #236                // Method android/content/res/TypedArray.getIndexCount:()I
     339: istore        7
     341: iconst_0
     342: istore        5
     344: iload         5
     346: iload         7
     348: if_icmpge     2023
     351: aload_2
     352: iload         5
     354: invokevirtual #240                // Method android/content/res/TypedArray.getIndex:(I)I
     357: istore        6
     359: getstatic     #243                // Field android/support/constraint/ConstraintLayout$a$a.a:Landroid/util/SparseIntArray;
     362: iload         6
     364: invokevirtual #248                // Method android/util/SparseIntArray.get:(I)I
     367: tableswitch   { // 0 to 50
                     0: 2014
                     1: 2000
                     2: 1964
                     3: 1947
                     4: 1901
                     5: 1884
                     6: 1867
                     7: 1850
                     8: 1814
                     9: 1778
                    10: 1742
                    11: 1706
                    12: 1670
                    13: 1634
                    14: 1598
                    15: 1562
                    16: 1526
                    17: 1490
                    18: 1454
                    19: 1418
                    20: 1382
                    21: 1365
                    22: 1348
                    23: 1331
                    24: 1314
                    25: 1297
                    26: 1280
                    27: 1263
                    28: 1246
                    29: 1229
                    30: 1212
                    31: 1178
                    32: 1152
                    33: 1111
                    34: 1070
                    35: 1049
                    36: 1008
                    37: 967
                    38: 946
                    39: 2014
                    40: 2014
                    41: 2014
                    42: 2014
                    43: 584
                    44: 677
                    45: 663
                    46: 649
                    47: 635
                    48: 621
                    49: 604
                    50: 587
               default: 584
          }
     584: goto          2014
     587: aload_0
     588: aload_2
     589: iload         6
     591: aload_0
     592: getfield      #169                // Field R:I
     595: invokevirtual #252                // Method android/content/res/TypedArray.getDimensionPixelOffset:(II)I
     598: putfield      #169                // Field R:I
     601: goto          2014
     604: aload_0
     605: aload_2
     606: iload         6
     608: aload_0
     609: getfield      #167                // Field Q:I
     612: invokevirtual #252                // Method android/content/res/TypedArray.getDimensionPixelOffset:(II)I
     615: putfield      #167                // Field Q:I
     618: goto          2014
     621: aload_0
     622: aload_2
     623: iload         6
     625: iconst_0
     626: invokevirtual #255                // Method android/content/res/TypedArray.getInt:(II)I
     629: putfield      #149                // Field H:I
     632: goto          2014
     635: aload_0
     636: aload_2
     637: iload         6
     639: iconst_0
     640: invokevirtual #255                // Method android/content/res/TypedArray.getInt:(II)I
     643: putfield      #147                // Field G:I
     646: goto          2014
     649: aload_0
     650: aload_2
     651: iload         6
     653: fconst_0
     654: invokevirtual #259                // Method android/content/res/TypedArray.getFloat:(IF)F
     657: putfield      #145                // Field F:F
     660: goto          2014
     663: aload_0
     664: aload_2
     665: iload         6
     667: fconst_0
     668: invokevirtual #259                // Method android/content/res/TypedArray.getFloat:(IF)F
     671: putfield      #143                // Field E:F
     674: goto          2014
     677: aload_0
     678: aload_2
     679: iload         6
     681: invokevirtual #263                // Method android/content/res/TypedArray.getString:(I)Ljava/lang/String;
     684: putfield      #137                // Field B:Ljava/lang/String;
     687: aload_0
     688: ldc_w         #264                // float NaNf
     691: putfield      #139                // Field C:F
     694: aload_0
     695: iconst_m1
     696: putfield      #141                // Field D:I
     699: aload_0
     700: getfield      #137                // Field B:Ljava/lang/String;
     703: ifnull        2014
     706: aload_0
     707: getfield      #137                // Field B:Ljava/lang/String;
     710: invokevirtual #269                // Method java/lang/String.length:()I
     713: istore        8
     715: aload_0
     716: getfield      #137                // Field B:Ljava/lang/String;
     719: bipush        44
     721: invokevirtual #272                // Method java/lang/String.indexOf:(I)I
     724: istore        6
     726: iload         6
     728: ifle          793
     731: iload         6
     733: iload         8
     735: iconst_1
     736: isub
     737: if_icmpge     793
     740: aload_0
     741: getfield      #137                // Field B:Ljava/lang/String;
     744: iconst_0
     745: iload         6
     747: invokevirtual #276                // Method java/lang/String.substring:(II)Ljava/lang/String;
     750: astore_1
     751: aload_1
     752: ldc_w         #277                // String W
     755: invokevirtual #281                // Method java/lang/String.equalsIgnoreCase:(Ljava/lang/String;)Z
     758: ifeq          769
     761: aload_0
     762: iconst_0
     763: putfield      #141                // Field D:I
     766: goto          784
     769: aload_1
     770: ldc_w         #282                // String H
     773: invokevirtual #281                // Method java/lang/String.equalsIgnoreCase:(Ljava/lang/String;)Z
     776: ifeq          784
     779: aload_0
     780: iconst_1
     781: putfield      #141                // Field D:I
     784: iload         6
     786: iconst_1
     787: iadd
     788: istore        6
     790: goto          796
     793: iconst_0
     794: istore        6
     796: aload_0
     797: getfield      #137                // Field B:Ljava/lang/String;
     800: bipush        58
     802: invokevirtual #272                // Method java/lang/String.indexOf:(I)I
     805: istore        9
     807: iload         9
     809: iflt          921
     812: iload         9
     814: iload         8
     816: iconst_1
     817: isub
     818: if_icmpge     921
     821: aload_0
     822: getfield      #137                // Field B:Ljava/lang/String;
     825: iload         6
     827: iload         9
     829: invokevirtual #276                // Method java/lang/String.substring:(II)Ljava/lang/String;
     832: astore_1
     833: aload_0
     834: getfield      #137                // Field B:Ljava/lang/String;
     837: iload         9
     839: iconst_1
     840: iadd
     841: invokevirtual #284                // Method java/lang/String.substring:(I)Ljava/lang/String;
     844: astore        10
     846: aload_1
     847: invokevirtual #269                // Method java/lang/String.length:()I
     850: ifle          2014
     853: aload         10
     855: invokevirtual #269                // Method java/lang/String.length:()I
     858: ifle          2014
     861: aload_1
     862: invokestatic  #290                // Method java/lang/Float.parseFloat:(Ljava/lang/String;)F
     865: fstore_3
     866: aload         10
     868: invokestatic  #290                // Method java/lang/Float.parseFloat:(Ljava/lang/String;)F
     871: fstore        4
     873: fload_3
     874: fconst_0
     875: fcmpl
     876: ifle          2014
     879: fload         4
     881: fconst_0
     882: fcmpl
     883: ifle          2014
     886: aload_0
     887: getfield      #141                // Field D:I
     890: iconst_1
     891: if_icmpne     910
     894: fload         4
     896: fload_3
     897: fdiv
     898: invokestatic  #296                // Method java/lang/Math.abs:(F)F
     901: fstore_3
     902: aload_0
     903: fload_3
     904: putfield      #139                // Field C:F
     907: goto          2014
     910: fload_3
     911: fload         4
     913: fdiv
     914: invokestatic  #296                // Method java/lang/Math.abs:(F)F
     917: fstore_3
     918: goto          902
     921: aload_0
     922: getfield      #137                // Field B:Ljava/lang/String;
     925: iload         6
     927: invokevirtual #284                // Method java/lang/String.substring:(I)Ljava/lang/String;
     930: astore_1
     931: aload_1
     932: invokevirtual #269                // Method java/lang/String.length:()I
     935: ifle          2014
     938: aload_1
     939: invokestatic  #290                // Method java/lang/Float.parseFloat:(Ljava/lang/String;)F
     942: fstore_3
     943: goto          902
     946: aload_0
     947: fconst_0
     948: aload_2
     949: iload         6
     951: aload_0
     952: getfield      #165                // Field P:F
     955: invokevirtual #259                // Method android/content/res/TypedArray.getFloat:(IF)F
     958: invokestatic  #300                // Method java/lang/Math.max:(FF)F
     961: putfield      #165                // Field P:F
     964: goto          2014
     967: aload_0
     968: aload_2
     969: iload         6
     971: aload_0
     972: getfield      #161                // Field N:I
     975: invokevirtual #303                // Method android/content/res/TypedArray.getDimensionPixelSize:(II)I
     978: putfield      #161                // Field N:I
     981: goto          2014
     984: aload_2
     985: iload         6
     987: aload_0
     988: getfield      #161                // Field N:I
     991: invokevirtual #255                // Method android/content/res/TypedArray.getInt:(II)I
     994: bipush        -2
     996: if_icmpne     2014
     999: aload_0
    1000: bipush        -2
    1002: putfield      #161                // Field N:I
    1005: goto          2014
    1008: aload_0
    1009: aload_2
    1010: iload         6
    1012: aload_0
    1013: getfield      #157                // Field L:I
    1016: invokevirtual #303                // Method android/content/res/TypedArray.getDimensionPixelSize:(II)I
    1019: putfield      #157                // Field L:I
    1022: goto          2014
    1025: aload_2
    1026: iload         6
    1028: aload_0
    1029: getfield      #157                // Field L:I
    1032: invokevirtual #255                // Method android/content/res/TypedArray.getInt:(II)I
    1035: bipush        -2
    1037: if_icmpne     2014
    1040: aload_0
    1041: bipush        -2
    1043: putfield      #157                // Field L:I
    1046: goto          2014
    1049: aload_0
    1050: fconst_0
    1051: aload_2
    1052: iload         6
    1054: aload_0
    1055: getfield      #163                // Field O:F
    1058: invokevirtual #259                // Method android/content/res/TypedArray.getFloat:(IF)F
    1061: invokestatic  #300                // Method java/lang/Math.max:(FF)F
    1064: putfield      #163                // Field O:F
    1067: goto          2014
    1070: aload_0
    1071: aload_2
    1072: iload         6
    1074: aload_0
    1075: getfield      #159                // Field M:I
    1078: invokevirtual #303                // Method android/content/res/TypedArray.getDimensionPixelSize:(II)I
    1081: putfield      #159                // Field M:I
    1084: goto          2014
    1087: aload_2
    1088: iload         6
    1090: aload_0
    1091: getfield      #159                // Field M:I
    1094: invokevirtual #255                // Method android/content/res/TypedArray.getInt:(II)I
    1097: bipush        -2
    1099: if_icmpne     2014
    1102: aload_0
    1103: bipush        -2
    1105: putfield      #159                // Field M:I
    1108: goto          2014
    1111: aload_0
    1112: aload_2
    1113: iload         6
    1115: aload_0
    1116: getfield      #155                // Field K:I
    1119: invokevirtual #303                // Method android/content/res/TypedArray.getDimensionPixelSize:(II)I
    1122: putfield      #155                // Field K:I
    1125: goto          2014
    1128: aload_2
    1129: iload         6
    1131: aload_0
    1132: getfield      #155                // Field K:I
    1135: invokevirtual #255                // Method android/content/res/TypedArray.getInt:(II)I
    1138: bipush        -2
    1140: if_icmpne     2014
    1143: aload_0
    1144: bipush        -2
    1146: putfield      #155                // Field K:I
    1149: goto          2014
    1152: aload_0
    1153: aload_2
    1154: iload         6
    1156: iconst_0
    1157: invokevirtual #255                // Method android/content/res/TypedArray.getInt:(II)I
    1160: putfield      #153                // Field J:I
    1163: aload_0
    1164: getfield      #153                // Field J:I
    1167: iconst_1
    1168: if_icmpne     2014
    1171: ldc_w         #305                // String layout_constraintHeight_default=\"wrap\" is deprecated.\nUse layout_height=\"WRAP_CONTENT\" and layout_constrainedHeight=\"true\" instead.
    1174: astore_1
    1175: goto          1201
    1178: aload_0
    1179: aload_2
    1180: iload         6
    1182: iconst_0
    1183: invokevirtual #255                // Method android/content/res/TypedArray.getInt:(II)I
    1186: putfield      #151                // Field I:I
    1189: aload_0
    1190: getfield      #151                // Field I:I
    1193: iconst_1
    1194: if_icmpne     2014
    1197: ldc_w         #307                // String layout_constraintWidth_default=\"wrap\" is deprecated.\nUse layout_width=\"WRAP_CONTENT\" and layout_constrainedWidth=\"true\" instead.
    1200: astore_1
    1201: ldc_w         #309                // String ConstraintLayout
    1204: aload_1
    1205: invokestatic  #314                // Method android/util/Log.e:(Ljava/lang/String;Ljava/lang/String;)I
    1208: pop
    1209: goto          2014
    1212: aload_0
    1213: aload_2
    1214: iload         6
    1216: aload_0
    1217: getfield      #135                // Field A:F
    1220: invokevirtual #259                // Method android/content/res/TypedArray.getFloat:(IF)F
    1223: putfield      #135                // Field A:F
    1226: goto          2014
    1229: aload_0
    1230: aload_2
    1231: iload         6
    1233: aload_0
    1234: getfield      #133                // Field z:F
    1237: invokevirtual #259                // Method android/content/res/TypedArray.getFloat:(IF)F
    1240: putfield      #133                // Field z:F
    1243: goto          2014
    1246: aload_0
    1247: aload_2
    1248: iload         6
    1250: aload_0
    1251: getfield      #175                // Field U:Z
    1254: invokevirtual #318                // Method android/content/res/TypedArray.getBoolean:(IZ)Z
    1257: putfield      #175                // Field U:Z
    1260: goto          2014
    1263: aload_0
    1264: aload_2
    1265: iload         6
    1267: aload_0
    1268: getfield      #173                // Field T:Z
    1271: invokevirtual #318                // Method android/content/res/TypedArray.getBoolean:(IZ)Z
    1274: putfield      #173                // Field T:Z
    1277: goto          2014
    1280: aload_0
    1281: aload_2
    1282: iload         6
    1284: aload_0
    1285: getfield      #130                // Field y:I
    1288: invokevirtual #303                // Method android/content/res/TypedArray.getDimensionPixelSize:(II)I
    1291: putfield      #130                // Field y:I
    1294: goto          2014
    1297: aload_0
    1298: aload_2
    1299: iload         6
    1301: aload_0
    1302: getfield      #128                // Field x:I
    1305: invokevirtual #303                // Method android/content/res/TypedArray.getDimensionPixelSize:(II)I
    1308: putfield      #128                // Field x:I
    1311: goto          2014
    1314: aload_0
    1315: aload_2
    1316: iload         6
    1318: aload_0
    1319: getfield      #126                // Field w:I
    1322: invokevirtual #303                // Method android/content/res/TypedArray.getDimensionPixelSize:(II)I
    1325: putfield      #126                // Field w:I
    1328: goto          2014
    1331: aload_0
    1332: aload_2
    1333: iload         6
    1335: aload_0
    1336: getfield      #124                // Field v:I
    1339: invokevirtual #303                // Method android/content/res/TypedArray.getDimensionPixelSize:(II)I
    1342: putfield      #124                // Field v:I
    1345: goto          2014
    1348: aload_0
    1349: aload_2
    1350: iload         6
    1352: aload_0
    1353: getfield      #122                // Field u:I
    1356: invokevirtual #303                // Method android/content/res/TypedArray.getDimensionPixelSize:(II)I
    1359: putfield      #122                // Field u:I
    1362: goto          2014
    1365: aload_0
    1366: aload_2
    1367: iload         6
    1369: aload_0
    1370: getfield      #120                // Field t:I
    1373: invokevirtual #303                // Method android/content/res/TypedArray.getDimensionPixelSize:(II)I
    1376: putfield      #120                // Field t:I
    1379: goto          2014
    1382: aload_0
    1383: aload_2
    1384: iload         6
    1386: aload_0
    1387: getfield      #118                // Field s:I
    1390: invokevirtual #321                // Method android/content/res/TypedArray.getResourceId:(II)I
    1393: putfield      #118                // Field s:I
    1396: aload_0
    1397: getfield      #118                // Field s:I
    1400: iconst_m1
    1401: if_icmpne     2014
    1404: aload_0
    1405: aload_2
    1406: iload         6
    1408: iconst_m1
    1409: invokevirtual #255                // Method android/content/res/TypedArray.getInt:(II)I
    1412: putfield      #118                // Field s:I
    1415: goto          2014
    1418: aload_0
    1419: aload_2
    1420: iload         6
    1422: aload_0
    1423: getfield      #116                // Field r:I
    1426: invokevirtual #321                // Method android/content/res/TypedArray.getResourceId:(II)I
    1429: putfield      #116                // Field r:I
    1432: aload_0
    1433: getfield      #116                // Field r:I
    1436: iconst_m1
    1437: if_icmpne     2014
    1440: aload_0
    1441: aload_2
    1442: iload         6
    1444: iconst_m1
    1445: invokevirtual #255                // Method android/content/res/TypedArray.getInt:(II)I
    1448: putfield      #116                // Field r:I
    1451: goto          2014
    1454: aload_0
    1455: aload_2
    1456: iload         6
    1458: aload_0
    1459: getfield      #114                // Field q:I
    1462: invokevirtual #321                // Method android/content/res/TypedArray.getResourceId:(II)I
    1465: putfield      #114                // Field q:I
    1468: aload_0
    1469: getfield      #114                // Field q:I
    1472: iconst_m1
    1473: if_icmpne     2014
    1476: aload_0
    1477: aload_2
    1478: iload         6
    1480: iconst_m1
    1481: invokevirtual #255                // Method android/content/res/TypedArray.getInt:(II)I
    1484: putfield      #114                // Field q:I
    1487: goto          2014
    1490: aload_0
    1491: aload_2
    1492: iload         6
    1494: aload_0
    1495: getfield      #112                // Field p:I
    1498: invokevirtual #321                // Method android/content/res/TypedArray.getResourceId:(II)I
    1501: putfield      #112                // Field p:I
    1504: aload_0
    1505: getfield      #112                // Field p:I
    1508: iconst_m1
    1509: if_icmpne     2014
    1512: aload_0
    1513: aload_2
    1514: iload         6
    1516: iconst_m1
    1517: invokevirtual #255                // Method android/content/res/TypedArray.getInt:(II)I
    1520: putfield      #112                // Field p:I
    1523: goto          2014
    1526: aload_0
    1527: aload_2
    1528: iload         6
    1530: aload_0
    1531: getfield      #104                // Field l:I
    1534: invokevirtual #321                // Method android/content/res/TypedArray.getResourceId:(II)I
    1537: putfield      #104                // Field l:I
    1540: aload_0
    1541: getfield      #104                // Field l:I
    1544: iconst_m1
    1545: if_icmpne     2014
    1548: aload_0
    1549: aload_2
    1550: iload         6
    1552: iconst_m1
    1553: invokevirtual #255                // Method android/content/res/TypedArray.getInt:(II)I
    1556: putfield      #104                // Field l:I
    1559: goto          2014
    1562: aload_0
    1563: aload_2
    1564: iload         6
    1566: aload_0
    1567: getfield      #102                // Field k:I
    1570: invokevirtual #321                // Method android/content/res/TypedArray.getResourceId:(II)I
    1573: putfield      #102                // Field k:I
    1576: aload_0
    1577: getfield      #102                // Field k:I
    1580: iconst_m1
    1581: if_icmpne     2014
    1584: aload_0
    1585: aload_2
    1586: iload         6
    1588: iconst_m1
    1589: invokevirtual #255                // Method android/content/res/TypedArray.getInt:(II)I
    1592: putfield      #102                // Field k:I
    1595: goto          2014
    1598: aload_0
    1599: aload_2
    1600: iload         6
    1602: aload_0
    1603: getfield      #100                // Field j:I
    1606: invokevirtual #321                // Method android/content/res/TypedArray.getResourceId:(II)I
    1609: putfield      #100                // Field j:I
    1612: aload_0
    1613: getfield      #100                // Field j:I
    1616: iconst_m1
    1617: if_icmpne     2014
    1620: aload_0
    1621: aload_2
    1622: iload         6
    1624: iconst_m1
    1625: invokevirtual #255                // Method android/content/res/TypedArray.getInt:(II)I
    1628: putfield      #100                // Field j:I
    1631: goto          2014
    1634: aload_0
    1635: aload_2
    1636: iload         6
    1638: aload_0
    1639: getfield      #98                 // Field i:I
    1642: invokevirtual #321                // Method android/content/res/TypedArray.getResourceId:(II)I
    1645: putfield      #98                 // Field i:I
    1648: aload_0
    1649: getfield      #98                 // Field i:I
    1652: iconst_m1
    1653: if_icmpne     2014
    1656: aload_0
    1657: aload_2
    1658: iload         6
    1660: iconst_m1
    1661: invokevirtual #255                // Method android/content/res/TypedArray.getInt:(II)I
    1664: putfield      #98                 // Field i:I
    1667: goto          2014
    1670: aload_0
    1671: aload_2
    1672: iload         6
    1674: aload_0
    1675: getfield      #96                 // Field h:I
    1678: invokevirtual #321                // Method android/content/res/TypedArray.getResourceId:(II)I
    1681: putfield      #96                 // Field h:I
    1684: aload_0
    1685: getfield      #96                 // Field h:I
    1688: iconst_m1
    1689: if_icmpne     2014
    1692: aload_0
    1693: aload_2
    1694: iload         6
    1696: iconst_m1
    1697: invokevirtual #255                // Method android/content/res/TypedArray.getInt:(II)I
    1700: putfield      #96                 // Field h:I
    1703: goto          2014
    1706: aload_0
    1707: aload_2
    1708: iload         6
    1710: aload_0
    1711: getfield      #94                 // Field g:I
    1714: invokevirtual #321                // Method android/content/res/TypedArray.getResourceId:(II)I
    1717: putfield      #94                 // Field g:I
    1720: aload_0
    1721: getfield      #94                 // Field g:I
    1724: iconst_m1
    1725: if_icmpne     2014
    1728: aload_0
    1729: aload_2
    1730: iload         6
    1732: iconst_m1
    1733: invokevirtual #255                // Method android/content/res/TypedArray.getInt:(II)I
    1736: putfield      #94                 // Field g:I
    1739: goto          2014
    1742: aload_0
    1743: aload_2
    1744: iload         6
    1746: aload_0
    1747: getfield      #92                 // Field f:I
    1750: invokevirtual #321                // Method android/content/res/TypedArray.getResourceId:(II)I
    1753: putfield      #92                 // Field f:I
    1756: aload_0
    1757: getfield      #92                 // Field f:I
    1760: iconst_m1
    1761: if_icmpne     2014
    1764: aload_0
    1765: aload_2
    1766: iload         6
    1768: iconst_m1
    1769: invokevirtual #255                // Method android/content/res/TypedArray.getInt:(II)I
    1772: putfield      #92                 // Field f:I
    1775: goto          2014
    1778: aload_0
    1779: aload_2
    1780: iload         6
    1782: aload_0
    1783: getfield      #90                 // Field e:I
    1786: invokevirtual #321                // Method android/content/res/TypedArray.getResourceId:(II)I
    1789: putfield      #90                 // Field e:I
    1792: aload_0
    1793: getfield      #90                 // Field e:I
    1796: iconst_m1
    1797: if_icmpne     2014
    1800: aload_0
    1801: aload_2
    1802: iload         6
    1804: iconst_m1
    1805: invokevirtual #255                // Method android/content/res/TypedArray.getInt:(II)I
    1808: putfield      #90                 // Field e:I
    1811: goto          2014
    1814: aload_0
    1815: aload_2
    1816: iload         6
    1818: aload_0
    1819: getfield      #88                 // Field d:I
    1822: invokevirtual #321                // Method android/content/res/TypedArray.getResourceId:(II)I
    1825: putfield      #88                 // Field d:I
    1828: aload_0
    1829: getfield      #88                 // Field d:I
    1832: iconst_m1
    1833: if_icmpne     2014
    1836: aload_0
    1837: aload_2
    1838: iload         6
    1840: iconst_m1
    1841: invokevirtual #255                // Method android/content/res/TypedArray.getInt:(II)I
    1844: putfield      #88                 // Field d:I
    1847: goto          2014
    1850: aload_0
    1851: aload_2
    1852: iload         6
    1854: aload_0
    1855: getfield      #86                 // Field c:F
    1858: invokevirtual #259                // Method android/content/res/TypedArray.getFloat:(IF)F
    1861: putfield      #86                 // Field c:F
    1864: goto          2014
    1867: aload_0
    1868: aload_2
    1869: iload         6
    1871: aload_0
    1872: getfield      #83                 // Field b:I
    1875: invokevirtual #252                // Method android/content/res/TypedArray.getDimensionPixelOffset:(II)I
    1878: putfield      #83                 // Field b:I
    1881: goto          2014
    1884: aload_0
    1885: aload_2
    1886: iload         6
    1888: aload_0
    1889: getfield      #81                 // Field a:I
    1892: invokevirtual #252                // Method android/content/res/TypedArray.getDimensionPixelOffset:(II)I
    1895: putfield      #81                 // Field a:I
    1898: goto          2014
    1901: aload_0
    1902: aload_2
    1903: iload         6
    1905: aload_0
    1906: getfield      #110                // Field o:F
    1909: invokevirtual #259                // Method android/content/res/TypedArray.getFloat:(IF)F
    1912: ldc_w         #322                // float 360.0f
    1915: frem
    1916: putfield      #110                // Field o:F
    1919: aload_0
    1920: getfield      #110                // Field o:F
    1923: fconst_0
    1924: fcmpg
    1925: ifge          2014
    1928: aload_0
    1929: ldc_w         #322                // float 360.0f
    1932: aload_0
    1933: getfield      #110                // Field o:F
    1936: fsub
    1937: ldc_w         #322                // float 360.0f
    1940: frem
    1941: putfield      #110                // Field o:F
    1944: goto          2014
    1947: aload_0
    1948: aload_2
    1949: iload         6
    1951: aload_0
    1952: getfield      #108                // Field n:I
    1955: invokevirtual #303                // Method android/content/res/TypedArray.getDimensionPixelSize:(II)I
    1958: putfield      #108                // Field n:I
    1961: goto          2014
    1964: aload_0
    1965: aload_2
    1966: iload         6
    1968: aload_0
    1969: getfield      #106                // Field m:I
    1972: invokevirtual #321                // Method android/content/res/TypedArray.getResourceId:(II)I
    1975: putfield      #106                // Field m:I
    1978: aload_0
    1979: getfield      #106                // Field m:I
    1982: iconst_m1
    1983: if_icmpne     2014
    1986: aload_0
    1987: aload_2
    1988: iload         6
    1990: iconst_m1
    1991: invokevirtual #255                // Method android/content/res/TypedArray.getInt:(II)I
    1994: putfield      #106                // Field m:I
    1997: goto          2014
    2000: aload_0
    2001: aload_2
    2002: iload         6
    2004: aload_0
    2005: getfield      #171                // Field S:I
    2008: invokevirtual #255                // Method android/content/res/TypedArray.getInt:(II)I
    2011: putfield      #171                // Field S:I
    2014: iload         5
    2016: iconst_1
    2017: iadd
    2018: istore        5
    2020: goto          344
    2023: aload_2
    2024: invokevirtual #325                // Method android/content/res/TypedArray.recycle:()V
    2027: aload_0
    2028: invokevirtual #327                // Method a:()V
    2031: return
    2032: astore_1
    2033: goto          2014
    2036: astore_1
    2037: goto          984
    2040: astore_1
    2041: goto          1025
    2044: astore_1
    2045: goto          1087
    2048: astore_1
    2049: goto          1128
    Exception table:
       from    to  target type
         861   873  2032   Class java/lang/NumberFormatException
         886   902  2032   Class java/lang/NumberFormatException
         902   907  2032   Class java/lang/NumberFormatException
         910   918  2032   Class java/lang/NumberFormatException
         938   943  2032   Class java/lang/NumberFormatException
         967   981  2036   Class java/lang/Exception
        1008  1022  2040   Class java/lang/Exception
        1070  1084  2044   Class java/lang/Exception
        1111  1125  2048   Class java/lang/Exception

  public android.support.constraint.ConstraintLayout$a(android.view.ViewGroup$LayoutParams);
    Code:
       0: aload_0
       1: aload_1
       2: invokespecial #330                // Method android/view/ViewGroup$MarginLayoutParams."<init>":(Landroid/view/ViewGroup$LayoutParams;)V
       5: aload_0
       6: iconst_m1
       7: putfield      #81                 // Field a:I
      10: aload_0
      11: iconst_m1
      12: putfield      #83                 // Field b:I
      15: aload_0
      16: ldc           #84                 // float -1.0f
      18: putfield      #86                 // Field c:F
      21: aload_0
      22: iconst_m1
      23: putfield      #88                 // Field d:I
      26: aload_0
      27: iconst_m1
      28: putfield      #90                 // Field e:I
      31: aload_0
      32: iconst_m1
      33: putfield      #92                 // Field f:I
      36: aload_0
      37: iconst_m1
      38: putfield      #94                 // Field g:I
      41: aload_0
      42: iconst_m1
      43: putfield      #96                 // Field h:I
      46: aload_0
      47: iconst_m1
      48: putfield      #98                 // Field i:I
      51: aload_0
      52: iconst_m1
      53: putfield      #100                // Field j:I
      56: aload_0
      57: iconst_m1
      58: putfield      #102                // Field k:I
      61: aload_0
      62: iconst_m1
      63: putfield      #104                // Field l:I
      66: aload_0
      67: iconst_m1
      68: putfield      #106                // Field m:I
      71: aload_0
      72: iconst_0
      73: putfield      #108                // Field n:I
      76: aload_0
      77: fconst_0
      78: putfield      #110                // Field o:F
      81: aload_0
      82: iconst_m1
      83: putfield      #112                // Field p:I
      86: aload_0
      87: iconst_m1
      88: putfield      #114                // Field q:I
      91: aload_0
      92: iconst_m1
      93: putfield      #116                // Field r:I
      96: aload_0
      97: iconst_m1
      98: putfield      #118                // Field s:I
     101: aload_0
     102: iconst_m1
     103: putfield      #120                // Field t:I
     106: aload_0
     107: iconst_m1
     108: putfield      #122                // Field u:I
     111: aload_0
     112: iconst_m1
     113: putfield      #124                // Field v:I
     116: aload_0
     117: iconst_m1
     118: putfield      #126                // Field w:I
     121: aload_0
     122: iconst_m1
     123: putfield      #128                // Field x:I
     126: aload_0
     127: iconst_m1
     128: putfield      #130                // Field y:I
     131: aload_0
     132: ldc           #131                // float 0.5f
     134: putfield      #133                // Field z:F
     137: aload_0
     138: ldc           #131                // float 0.5f
     140: putfield      #135                // Field A:F
     143: aload_0
     144: aconst_null
     145: putfield      #137                // Field B:Ljava/lang/String;
     148: aload_0
     149: fconst_0
     150: putfield      #139                // Field C:F
     153: aload_0
     154: iconst_1
     155: putfield      #141                // Field D:I
     158: aload_0
     159: fconst_0
     160: putfield      #143                // Field E:F
     163: aload_0
     164: fconst_0
     165: putfield      #145                // Field F:F
     168: aload_0
     169: iconst_0
     170: putfield      #147                // Field G:I
     173: aload_0
     174: iconst_0
     175: putfield      #149                // Field H:I
     178: aload_0
     179: iconst_0
     180: putfield      #151                // Field I:I
     183: aload_0
     184: iconst_0
     185: putfield      #153                // Field J:I
     188: aload_0
     189: iconst_0
     190: putfield      #155                // Field K:I
     193: aload_0
     194: iconst_0
     195: putfield      #157                // Field L:I
     198: aload_0
     199: iconst_0
     200: putfield      #159                // Field M:I
     203: aload_0
     204: iconst_0
     205: putfield      #161                // Field N:I
     208: aload_0
     209: fconst_1
     210: putfield      #163                // Field O:F
     213: aload_0
     214: fconst_1
     215: putfield      #165                // Field P:F
     218: aload_0
     219: iconst_m1
     220: putfield      #167                // Field Q:I
     223: aload_0
     224: iconst_m1
     225: putfield      #169                // Field R:I
     228: aload_0
     229: iconst_m1
     230: putfield      #171                // Field S:I
     233: aload_0
     234: iconst_0
     235: putfield      #173                // Field T:Z
     238: aload_0
     239: iconst_0
     240: putfield      #175                // Field U:Z
     243: aload_0
     244: iconst_1
     245: putfield      #177                // Field V:Z
     248: aload_0
     249: iconst_1
     250: putfield      #179                // Field W:Z
     253: aload_0
     254: iconst_0
     255: putfield      #181                // Field X:Z
     258: aload_0
     259: iconst_0
     260: putfield      #183                // Field Y:Z
     263: aload_0
     264: iconst_0
     265: putfield      #185                // Field Z:Z
     268: aload_0
     269: iconst_0
     270: putfield      #187                // Field aa:Z
     273: aload_0
     274: iconst_m1
     275: putfield      #189                // Field ab:I
     278: aload_0
     279: iconst_m1
     280: putfield      #191                // Field ac:I
     283: aload_0
     284: iconst_m1
     285: putfield      #193                // Field ad:I
     288: aload_0
     289: iconst_m1
     290: putfield      #195                // Field ae:I
     293: aload_0
     294: iconst_m1
     295: putfield      #197                // Field af:I
     298: aload_0
     299: iconst_m1
     300: putfield      #199                // Field ag:I
     303: aload_0
     304: ldc           #131                // float 0.5f
     306: putfield      #201                // Field ah:F
     309: aload_0
     310: new           #203                // class android/support/constraint/a/a/d
     313: dup
     314: invokespecial #206                // Method android/support/constraint/a/a/d."<init>":()V
     317: putfield      #208                // Field al:Landroid/support/constraint/a/a/d;
     320: aload_0
     321: iconst_0
     322: putfield      #210                // Field am:Z
     325: return

  public void a();
    Code:
       0: aload_0
       1: iconst_0
       2: putfield      #183                // Field Y:Z
       5: aload_0
       6: iconst_1
       7: putfield      #177                // Field V:Z
      10: aload_0
      11: iconst_1
      12: putfield      #179                // Field W:Z
      15: aload_0
      16: getfield      #333                // Field width:I
      19: bipush        -2
      21: if_icmpne     41
      24: aload_0
      25: getfield      #173                // Field T:Z
      28: ifeq          41
      31: aload_0
      32: iconst_0
      33: putfield      #177                // Field V:Z
      36: aload_0
      37: iconst_1
      38: putfield      #151                // Field I:I
      41: aload_0
      42: getfield      #336                // Field height:I
      45: bipush        -2
      47: if_icmpne     67
      50: aload_0
      51: getfield      #175                // Field U:Z
      54: ifeq          67
      57: aload_0
      58: iconst_0
      59: putfield      #179                // Field W:Z
      62: aload_0
      63: iconst_1
      64: putfield      #153                // Field J:I
      67: aload_0
      68: getfield      #333                // Field width:I
      71: ifeq          82
      74: aload_0
      75: getfield      #333                // Field width:I
      78: iconst_m1
      79: if_icmpne     113
      82: aload_0
      83: iconst_0
      84: putfield      #177                // Field V:Z
      87: aload_0
      88: getfield      #333                // Field width:I
      91: ifne          113
      94: aload_0
      95: getfield      #151                // Field I:I
      98: iconst_1
      99: if_icmpne     113
     102: aload_0
     103: bipush        -2
     105: putfield      #333                // Field width:I
     108: aload_0
     109: iconst_1
     110: putfield      #173                // Field T:Z
     113: aload_0
     114: getfield      #336                // Field height:I
     117: ifeq          128
     120: aload_0
     121: getfield      #336                // Field height:I
     124: iconst_m1
     125: if_icmpne     159
     128: aload_0
     129: iconst_0
     130: putfield      #179                // Field W:Z
     133: aload_0
     134: getfield      #336                // Field height:I
     137: ifne          159
     140: aload_0
     141: getfield      #153                // Field J:I
     144: iconst_1
     145: if_icmpne     159
     148: aload_0
     149: bipush        -2
     151: putfield      #336                // Field height:I
     154: aload_0
     155: iconst_1
     156: putfield      #175                // Field U:Z
     159: aload_0
     160: getfield      #86                 // Field c:F
     163: ldc           #84                 // float -1.0f
     165: fcmpl
     166: ifne          185
     169: aload_0
     170: getfield      #81                 // Field a:I
     173: iconst_m1
     174: if_icmpne     185
     177: aload_0
     178: getfield      #83                 // Field b:I
     181: iconst_m1
     182: if_icmpeq     235
     185: aload_0
     186: iconst_1
     187: putfield      #183                // Field Y:Z
     190: aload_0
     191: iconst_1
     192: putfield      #177                // Field V:Z
     195: aload_0
     196: iconst_1
     197: putfield      #179                // Field W:Z
     200: aload_0
     201: getfield      #208                // Field al:Landroid/support/constraint/a/a/d;
     204: instanceof    #338                // class android/support/constraint/a/a/f
     207: ifne          221
     210: aload_0
     211: new           #338                // class android/support/constraint/a/a/f
     214: dup
     215: invokespecial #339                // Method android/support/constraint/a/a/f."<init>":()V
     218: putfield      #208                // Field al:Landroid/support/constraint/a/a/d;
     221: aload_0
     222: getfield      #208                // Field al:Landroid/support/constraint/a/a/d;
     225: checkcast     #338                // class android/support/constraint/a/a/f
     228: aload_0
     229: getfield      #171                // Field S:I
     232: invokevirtual #342                // Method android/support/constraint/a/a/f.a:(I)V
     235: return

  public void resolveLayoutDirection(int);
    Code:
       0: aload_0
       1: getfield      #349                // Field leftMargin:I
       4: istore_3
       5: aload_0
       6: getfield      #352                // Field rightMargin:I
       9: istore        4
      11: aload_0
      12: iload_1
      13: invokespecial #354                // Method android/view/ViewGroup$MarginLayoutParams.resolveLayoutDirection:(I)V
      16: aload_0
      17: iconst_m1
      18: putfield      #193                // Field ad:I
      21: aload_0
      22: iconst_m1
      23: putfield      #195                // Field ae:I
      26: aload_0
      27: iconst_m1
      28: putfield      #189                // Field ab:I
      31: aload_0
      32: iconst_m1
      33: putfield      #191                // Field ac:I
      36: aload_0
      37: iconst_m1
      38: putfield      #197                // Field af:I
      41: aload_0
      42: iconst_m1
      43: putfield      #199                // Field ag:I
      46: aload_0
      47: aload_0
      48: getfield      #120                // Field t:I
      51: putfield      #197                // Field af:I
      54: aload_0
      55: aload_0
      56: getfield      #124                // Field v:I
      59: putfield      #199                // Field ag:I
      62: aload_0
      63: aload_0
      64: getfield      #133                // Field z:F
      67: putfield      #201                // Field ah:F
      70: aload_0
      71: aload_0
      72: getfield      #81                 // Field a:I
      75: putfield      #356                // Field ai:I
      78: aload_0
      79: aload_0
      80: getfield      #83                 // Field b:I
      83: putfield      #358                // Field aj:I
      86: aload_0
      87: aload_0
      88: getfield      #86                 // Field c:F
      91: putfield      #360                // Field ak:F
      94: aload_0
      95: invokevirtual #363                // Method getLayoutDirection:()I
      98: istore_1
      99: iconst_0
     100: istore_2
     101: iconst_1
     102: iload_1
     103: if_icmpne     111
     106: iconst_1
     107: istore_1
     108: goto          113
     111: iconst_0
     112: istore_1
     113: iload_1
     114: ifeq          343
     117: aload_0
     118: getfield      #112                // Field p:I
     121: iconst_m1
     122: if_icmpeq     138
     125: aload_0
     126: aload_0
     127: getfield      #112                // Field p:I
     130: putfield      #193                // Field ad:I
     133: iconst_1
     134: istore_1
     135: goto          159
     138: iload_2
     139: istore_1
     140: aload_0
     141: getfield      #114                // Field q:I
     144: iconst_m1
     145: if_icmpeq     159
     148: aload_0
     149: aload_0
     150: getfield      #114                // Field q:I
     153: putfield      #195                // Field ae:I
     156: goto          133
     159: aload_0
     160: getfield      #116                // Field r:I
     163: iconst_m1
     164: if_icmpeq     177
     167: aload_0
     168: aload_0
     169: getfield      #116                // Field r:I
     172: putfield      #191                // Field ac:I
     175: iconst_1
     176: istore_1
     177: aload_0
     178: getfield      #118                // Field s:I
     181: iconst_m1
     182: if_icmpeq     195
     185: aload_0
     186: aload_0
     187: getfield      #118                // Field s:I
     190: putfield      #189                // Field ab:I
     193: iconst_1
     194: istore_1
     195: aload_0
     196: getfield      #128                // Field x:I
     199: iconst_m1
     200: if_icmpeq     211
     203: aload_0
     204: aload_0
     205: getfield      #128                // Field x:I
     208: putfield      #199                // Field ag:I
     211: aload_0
     212: getfield      #130                // Field y:I
     215: iconst_m1
     216: if_icmpeq     227
     219: aload_0
     220: aload_0
     221: getfield      #130                // Field y:I
     224: putfield      #197                // Field af:I
     227: iload_1
     228: ifeq          241
     231: aload_0
     232: fconst_1
     233: aload_0
     234: getfield      #133                // Field z:F
     237: fsub
     238: putfield      #201                // Field ah:F
     241: aload_0
     242: getfield      #183                // Field Y:Z
     245: ifeq          439
     248: aload_0
     249: getfield      #171                // Field S:I
     252: iconst_1
     253: if_icmpne     439
     256: aload_0
     257: getfield      #86                 // Field c:F
     260: ldc           #84                 // float -1.0f
     262: fcmpl
     263: ifeq          289
     266: aload_0
     267: fconst_1
     268: aload_0
     269: getfield      #86                 // Field c:F
     272: fsub
     273: putfield      #360                // Field ak:F
     276: aload_0
     277: iconst_m1
     278: putfield      #356                // Field ai:I
     281: aload_0
     282: iconst_m1
     283: putfield      #358                // Field aj:I
     286: goto          439
     289: aload_0
     290: getfield      #81                 // Field a:I
     293: iconst_m1
     294: if_icmpeq     319
     297: aload_0
     298: aload_0
     299: getfield      #81                 // Field a:I
     302: putfield      #358                // Field aj:I
     305: aload_0
     306: iconst_m1
     307: putfield      #356                // Field ai:I
     310: aload_0
     311: ldc           #84                 // float -1.0f
     313: putfield      #360                // Field ak:F
     316: goto          439
     319: aload_0
     320: getfield      #83                 // Field b:I
     323: iconst_m1
     324: if_icmpeq     439
     327: aload_0
     328: aload_0
     329: getfield      #83                 // Field b:I
     332: putfield      #356                // Field ai:I
     335: aload_0
     336: iconst_m1
     337: putfield      #358                // Field aj:I
     340: goto          310
     343: aload_0
     344: getfield      #112                // Field p:I
     347: iconst_m1
     348: if_icmpeq     359
     351: aload_0
     352: aload_0
     353: getfield      #112                // Field p:I
     356: putfield      #191                // Field ac:I
     359: aload_0
     360: getfield      #114                // Field q:I
     363: iconst_m1
     364: if_icmpeq     375
     367: aload_0
     368: aload_0
     369: getfield      #114                // Field q:I
     372: putfield      #189                // Field ab:I
     375: aload_0
     376: getfield      #116                // Field r:I
     379: iconst_m1
     380: if_icmpeq     391
     383: aload_0
     384: aload_0
     385: getfield      #116                // Field r:I
     388: putfield      #193                // Field ad:I
     391: aload_0
     392: getfield      #118                // Field s:I
     395: iconst_m1
     396: if_icmpeq     407
     399: aload_0
     400: aload_0
     401: getfield      #118                // Field s:I
     404: putfield      #195                // Field ae:I
     407: aload_0
     408: getfield      #128                // Field x:I
     411: iconst_m1
     412: if_icmpeq     423
     415: aload_0
     416: aload_0
     417: getfield      #128                // Field x:I
     420: putfield      #197                // Field af:I
     423: aload_0
     424: getfield      #130                // Field y:I
     427: iconst_m1
     428: if_icmpeq     439
     431: aload_0
     432: aload_0
     433: getfield      #130                // Field y:I
     436: putfield      #199                // Field ag:I
     439: aload_0
     440: getfield      #116                // Field r:I
     443: iconst_m1
     444: if_icmpne     602
     447: aload_0
     448: getfield      #118                // Field s:I
     451: iconst_m1
     452: if_icmpne     602
     455: aload_0
     456: getfield      #114                // Field q:I
     459: iconst_m1
     460: if_icmpne     602
     463: aload_0
     464: getfield      #112                // Field p:I
     467: iconst_m1
     468: if_icmpne     602
     471: aload_0
     472: getfield      #92                 // Field f:I
     475: iconst_m1
     476: if_icmpeq     508
     479: aload_0
     480: aload_0
     481: getfield      #92                 // Field f:I
     484: putfield      #193                // Field ad:I
     487: aload_0
     488: getfield      #352                // Field rightMargin:I
     491: ifgt          539
     494: iload         4
     496: ifle          539
     499: aload_0
     500: iload         4
     502: putfield      #352                // Field rightMargin:I
     505: goto          539
     508: aload_0
     509: getfield      #94                 // Field g:I
     512: iconst_m1
     513: if_icmpeq     539
     516: aload_0
     517: aload_0
     518: getfield      #94                 // Field g:I
     521: putfield      #195                // Field ae:I
     524: aload_0
     525: getfield      #352                // Field rightMargin:I
     528: ifgt          539
     531: iload         4
     533: ifle          539
     536: goto          499
     539: aload_0
     540: getfield      #88                 // Field d:I
     543: iconst_m1
     544: if_icmpeq     572
     547: aload_0
     548: aload_0
     549: getfield      #88                 // Field d:I
     552: putfield      #189                // Field ab:I
     555: aload_0
     556: getfield      #349                // Field leftMargin:I
     559: ifgt          602
     562: iload_3
     563: ifle          602
     566: aload_0
     567: iload_3
     568: putfield      #349                // Field leftMargin:I
     571: return
     572: aload_0
     573: getfield      #90                 // Field e:I
     576: iconst_m1
     577: if_icmpeq     602
     580: aload_0
     581: aload_0
     582: getfield      #90                 // Field e:I
     585: putfield      #191                // Field ac:I
     588: aload_0
     589: getfield      #349                // Field leftMargin:I
     592: ifgt          602
     595: iload_3
     596: ifle          602
     599: goto          566
     602: return
}
