public class android.support.constraint.d$a extends android.support.constraint.ConstraintLayout$a {
  public float an;

  public boolean ao;

  public float ap;

  public float aq;

  public float ar;

  public float as;

  public float at;

  public float au;

  public float av;

  public float aw;

  public float ax;

  public float ay;

  public float az;

  public android.support.constraint.d$a(int, int);
    Code:
       0: aload_0
       1: iload_1
       2: iload_2
       3: invokespecial #26                 // Method android/support/constraint/ConstraintLayout$a."<init>":(II)V
       6: aload_0
       7: fconst_1
       8: putfield      #28                 // Field an:F
      11: aload_0
      12: iconst_0
      13: putfield      #30                 // Field ao:Z
      16: aload_0
      17: fconst_0
      18: putfield      #32                 // Field ap:F
      21: aload_0
      22: fconst_0
      23: putfield      #34                 // Field aq:F
      26: aload_0
      27: fconst_0
      28: putfield      #36                 // Field ar:F
      31: aload_0
      32: fconst_0
      33: putfield      #38                 // Field as:F
      36: aload_0
      37: fconst_1
      38: putfield      #40                 // Field at:F
      41: aload_0
      42: fconst_1
      43: putfield      #42                 // Field au:F
      46: aload_0
      47: fconst_0
      48: putfield      #44                 // Field av:F
      51: aload_0
      52: fconst_0
      53: putfield      #46                 // Field aw:F
      56: aload_0
      57: fconst_0
      58: putfield      #48                 // Field ax:F
      61: aload_0
      62: fconst_0
      63: putfield      #50                 // Field ay:F
      66: aload_0
      67: fconst_0
      68: putfield      #52                 // Field az:F
      71: return

  public android.support.constraint.d$a(android.content.Context, android.util.AttributeSet);
    Code:
       0: aload_0
       1: aload_1
       2: aload_2
       3: invokespecial #56                 // Method android/support/constraint/ConstraintLayout$a."<init>":(Landroid/content/Context;Landroid/util/AttributeSet;)V
       6: aload_0
       7: fconst_1
       8: putfield      #28                 // Field an:F
      11: iconst_0
      12: istore        4
      14: aload_0
      15: iconst_0
      16: putfield      #30                 // Field ao:Z
      19: aload_0
      20: fconst_0
      21: putfield      #32                 // Field ap:F
      24: aload_0
      25: fconst_0
      26: putfield      #34                 // Field aq:F
      29: aload_0
      30: fconst_0
      31: putfield      #36                 // Field ar:F
      34: aload_0
      35: fconst_0
      36: putfield      #38                 // Field as:F
      39: aload_0
      40: fconst_1
      41: putfield      #40                 // Field at:F
      44: aload_0
      45: fconst_1
      46: putfield      #42                 // Field au:F
      49: aload_0
      50: fconst_0
      51: putfield      #44                 // Field av:F
      54: aload_0
      55: fconst_0
      56: putfield      #46                 // Field aw:F
      59: aload_0
      60: fconst_0
      61: putfield      #48                 // Field ax:F
      64: aload_0
      65: fconst_0
      66: putfield      #50                 // Field ay:F
      69: aload_0
      70: fconst_0
      71: putfield      #52                 // Field az:F
      74: aload_1
      75: aload_2
      76: getstatic     #62                 // Field android/support/constraint/f$b.ConstraintSet:[I
      79: invokevirtual #68                 // Method android/content/Context.obtainStyledAttributes:(Landroid/util/AttributeSet;[I)Landroid/content/res/TypedArray;
      82: astore_1
      83: aload_1
      84: invokevirtual #74                 // Method android/content/res/TypedArray.getIndexCount:()I
      87: istore        5
      89: iload         4
      91: iload         5
      93: if_icmpge     411
      96: aload_1
      97: iload         4
      99: invokevirtual #78                 // Method android/content/res/TypedArray.getIndex:(I)I
     102: istore        6
     104: iload         6
     106: getstatic     #82                 // Field android/support/constraint/f$b.ConstraintSet_android_alpha:I
     109: if_icmpne     129
     112: aload_0
     113: aload_1
     114: iload         6
     116: aload_0
     117: getfield      #28                 // Field an:F
     120: invokevirtual #86                 // Method android/content/res/TypedArray.getFloat:(IF)F
     123: putfield      #28                 // Field an:F
     126: goto          402
     129: iload         6
     131: getstatic     #89                 // Field android/support/constraint/f$b.ConstraintSet_android_elevation:I
     134: if_icmpne     159
     137: aload_0
     138: aload_1
     139: iload         6
     141: aload_0
     142: getfield      #32                 // Field ap:F
     145: invokevirtual #86                 // Method android/content/res/TypedArray.getFloat:(IF)F
     148: putfield      #32                 // Field ap:F
     151: aload_0
     152: iconst_1
     153: putfield      #30                 // Field ao:Z
     156: goto          402
     159: iload         6
     161: getstatic     #92                 // Field android/support/constraint/f$b.ConstraintSet_android_rotationX:I
     164: if_icmpne     184
     167: aload_0
     168: aload_1
     169: iload         6
     171: aload_0
     172: getfield      #36                 // Field ar:F
     175: invokevirtual #86                 // Method android/content/res/TypedArray.getFloat:(IF)F
     178: putfield      #36                 // Field ar:F
     181: goto          402
     184: iload         6
     186: getstatic     #95                 // Field android/support/constraint/f$b.ConstraintSet_android_rotationY:I
     189: if_icmpne     209
     192: aload_0
     193: aload_1
     194: iload         6
     196: aload_0
     197: getfield      #38                 // Field as:F
     200: invokevirtual #86                 // Method android/content/res/TypedArray.getFloat:(IF)F
     203: putfield      #38                 // Field as:F
     206: goto          402
     209: iload         6
     211: getstatic     #98                 // Field android/support/constraint/f$b.ConstraintSet_android_rotation:I
     214: if_icmpne     234
     217: aload_0
     218: aload_1
     219: iload         6
     221: aload_0
     222: getfield      #34                 // Field aq:F
     225: invokevirtual #86                 // Method android/content/res/TypedArray.getFloat:(IF)F
     228: putfield      #34                 // Field aq:F
     231: goto          402
     234: iload         6
     236: getstatic     #101                // Field android/support/constraint/f$b.ConstraintSet_android_scaleX:I
     239: if_icmpne     259
     242: aload_0
     243: aload_1
     244: iload         6
     246: aload_0
     247: getfield      #40                 // Field at:F
     250: invokevirtual #86                 // Method android/content/res/TypedArray.getFloat:(IF)F
     253: putfield      #40                 // Field at:F
     256: goto          402
     259: iload         6
     261: getstatic     #104                // Field android/support/constraint/f$b.ConstraintSet_android_scaleY:I
     264: if_icmpne     284
     267: aload_0
     268: aload_1
     269: iload         6
     271: aload_0
     272: getfield      #42                 // Field au:F
     275: invokevirtual #86                 // Method android/content/res/TypedArray.getFloat:(IF)F
     278: putfield      #42                 // Field au:F
     281: goto          402
     284: iload         6
     286: getstatic     #107                // Field android/support/constraint/f$b.ConstraintSet_android_transformPivotX:I
     289: if_icmpne     309
     292: aload_0
     293: aload_1
     294: iload         6
     296: aload_0
     297: getfield      #44                 // Field av:F
     300: invokevirtual #86                 // Method android/content/res/TypedArray.getFloat:(IF)F
     303: putfield      #44                 // Field av:F
     306: goto          402
     309: iload         6
     311: getstatic     #110                // Field android/support/constraint/f$b.ConstraintSet_android_transformPivotY:I
     314: if_icmpne     334
     317: aload_0
     318: aload_1
     319: iload         6
     321: aload_0
     322: getfield      #46                 // Field aw:F
     325: invokevirtual #86                 // Method android/content/res/TypedArray.getFloat:(IF)F
     328: putfield      #46                 // Field aw:F
     331: goto          402
     334: iload         6
     336: getstatic     #113                // Field android/support/constraint/f$b.ConstraintSet_android_translationX:I
     339: if_icmpne     361
     342: aload_0
     343: getfield      #48                 // Field ax:F
     346: fstore_3
     347: aload_0
     348: aload_1
     349: iload         6
     351: fload_3
     352: invokevirtual #86                 // Method android/content/res/TypedArray.getFloat:(IF)F
     355: putfield      #48                 // Field ax:F
     358: goto          402
     361: iload         6
     363: getstatic     #116                // Field android/support/constraint/f$b.ConstraintSet_android_translationY:I
     366: if_icmpne     386
     369: aload_0
     370: aload_1
     371: iload         6
     373: aload_0
     374: getfield      #50                 // Field ay:F
     377: invokevirtual #86                 // Method android/content/res/TypedArray.getFloat:(IF)F
     380: putfield      #50                 // Field ay:F
     383: goto          402
     386: iload         6
     388: getstatic     #119                // Field android/support/constraint/f$b.ConstraintSet_android_translationZ:I
     391: if_icmpne     402
     394: aload_0
     395: getfield      #52                 // Field az:F
     398: fstore_3
     399: goto          347
     402: iload         4
     404: iconst_1
     405: iadd
     406: istore        4
     408: goto          89
     411: return
}
