public class android.support.constraint.d extends android.view.ViewGroup {
  android.support.constraint.c a;

  protected android.support.constraint.d$a a();
    Code:
       0: new           #6                  // class android/support/constraint/d$a
       3: dup
       4: bipush        -2
       6: bipush        -2
       8: invokespecial #13                 // Method android/support/constraint/d$a."<init>":(II)V
      11: areturn

  public android.support.constraint.d$a a(android.util.AttributeSet);
    Code:
       0: new           #6                  // class android/support/constraint/d$a
       3: dup
       4: aload_0
       5: invokevirtual #19                 // Method getContext:()Landroid/content/Context;
       8: aload_1
       9: invokespecial #22                 // Method android/support/constraint/d$a."<init>":(Landroid/content/Context;Landroid/util/AttributeSet;)V
      12: areturn

  protected android.view.ViewGroup$LayoutParams generateDefaultLayoutParams();
    Code:
       0: aload_0
       1: invokevirtual #26                 // Method a:()Landroid/support/constraint/d$a;
       4: areturn

  public android.view.ViewGroup$LayoutParams generateLayoutParams(android.util.AttributeSet);
    Code:
       0: aload_0
       1: aload_1
       2: invokevirtual #30                 // Method a:(Landroid/util/AttributeSet;)Landroid/support/constraint/d$a;
       5: areturn

  protected android.view.ViewGroup$LayoutParams generateLayoutParams(android.view.ViewGroup$LayoutParams);
    Code:
       0: new           #33                 // class android/support/constraint/ConstraintLayout$a
       3: dup
       4: aload_1
       5: invokespecial #36                 // Method android/support/constraint/ConstraintLayout$a."<init>":(Landroid/view/ViewGroup$LayoutParams;)V
       8: areturn

  public android.support.constraint.c getConstraintSet();
    Code:
       0: aload_0
       1: getfield      #40                 // Field a:Landroid/support/constraint/c;
       4: ifnonnull     18
       7: aload_0
       8: new           #42                 // class android/support/constraint/c
      11: dup
      12: invokespecial #45                 // Method android/support/constraint/c."<init>":()V
      15: putfield      #40                 // Field a:Landroid/support/constraint/c;
      18: aload_0
      19: getfield      #40                 // Field a:Landroid/support/constraint/c;
      22: aload_0
      23: invokevirtual #48                 // Method android/support/constraint/c.a:(Landroid/support/constraint/d;)V
      26: aload_0
      27: getfield      #40                 // Field a:Landroid/support/constraint/c;
      30: areturn

  protected void onLayout(boolean, int, int, int, int);
    Code:
       0: return
}
