public class android.support.constraint.e extends android.view.View {
  public void a(android.support.constraint.ConstraintLayout);
    Code:
       0: aload_0
       1: getfield      #12                 // Field a:I
       4: iconst_m1
       5: if_icmpne     23
       8: aload_0
       9: invokevirtual #16                 // Method isInEditMode:()Z
      12: ifne          23
      15: aload_0
      16: aload_0
      17: getfield      #18                 // Field c:I
      20: invokevirtual #22                 // Method setVisibility:(I)V
      23: aload_0
      24: aload_1
      25: aload_0
      26: getfield      #12                 // Field a:I
      29: invokevirtual #28                 // Method android/support/constraint/ConstraintLayout.findViewById:(I)Landroid/view/View;
      32: putfield      #30                 // Field b:Landroid/view/View;
      35: aload_0
      36: getfield      #30                 // Field b:Landroid/view/View;
      39: ifnull        69
      42: aload_0
      43: getfield      #30                 // Field b:Landroid/view/View;
      46: invokevirtual #34                 // Method android/view/View.getLayoutParams:()Landroid/view/ViewGroup$LayoutParams;
      49: checkcast     #36                 // class android/support/constraint/ConstraintLayout$a
      52: iconst_1
      53: putfield      #40                 // Field android/support/constraint/ConstraintLayout$a.aa:Z
      56: aload_0
      57: getfield      #30                 // Field b:Landroid/view/View;
      60: iconst_0
      61: invokevirtual #41                 // Method android/view/View.setVisibility:(I)V
      64: aload_0
      65: iconst_0
      66: invokevirtual #22                 // Method setVisibility:(I)V
      69: return

  public void b(android.support.constraint.ConstraintLayout);
    Code:
       0: aload_0
       1: getfield      #30                 // Field b:Landroid/view/View;
       4: ifnonnull     8
       7: return
       8: aload_0
       9: invokevirtual #43                 // Method getLayoutParams:()Landroid/view/ViewGroup$LayoutParams;
      12: checkcast     #36                 // class android/support/constraint/ConstraintLayout$a
      15: astore_1
      16: aload_0
      17: getfield      #30                 // Field b:Landroid/view/View;
      20: invokevirtual #34                 // Method android/view/View.getLayoutParams:()Landroid/view/ViewGroup$LayoutParams;
      23: checkcast     #36                 // class android/support/constraint/ConstraintLayout$a
      26: astore_2
      27: aload_2
      28: getfield      #47                 // Field android/support/constraint/ConstraintLayout$a.al:Landroid/support/constraint/a/a/d;
      31: iconst_0
      32: invokevirtual #52                 // Method android/support/constraint/a/a/d.e:(I)V
      35: aload_1
      36: getfield      #47                 // Field android/support/constraint/ConstraintLayout$a.al:Landroid/support/constraint/a/a/d;
      39: aload_2
      40: getfield      #47                 // Field android/support/constraint/ConstraintLayout$a.al:Landroid/support/constraint/a/a/d;
      43: invokevirtual #56                 // Method android/support/constraint/a/a/d.o:()I
      46: invokevirtual #59                 // Method android/support/constraint/a/a/d.h:(I)V
      49: aload_1
      50: getfield      #47                 // Field android/support/constraint/ConstraintLayout$a.al:Landroid/support/constraint/a/a/d;
      53: aload_2
      54: getfield      #47                 // Field android/support/constraint/ConstraintLayout$a.al:Landroid/support/constraint/a/a/d;
      57: invokevirtual #62                 // Method android/support/constraint/a/a/d.q:()I
      60: invokevirtual #65                 // Method android/support/constraint/a/a/d.i:(I)V
      63: aload_2
      64: getfield      #47                 // Field android/support/constraint/ConstraintLayout$a.al:Landroid/support/constraint/a/a/d;
      67: bipush        8
      69: invokevirtual #52                 // Method android/support/constraint/a/a/d.e:(I)V
      72: return

  public android.view.View getContent();
    Code:
       0: aload_0
       1: getfield      #30                 // Field b:Landroid/view/View;
       4: areturn

  public int getEmptyVisibility();
    Code:
       0: aload_0
       1: getfield      #18                 // Field c:I
       4: ireturn

  public void onDraw(android.graphics.Canvas);
    Code:
       0: aload_0
       1: invokevirtual #16                 // Method isInEditMode:()Z
       4: ifeq          177
       7: aload_1
       8: sipush        223
      11: sipush        223
      14: sipush        223
      17: invokevirtual #76                 // Method android/graphics/Canvas.drawRGB:(III)V
      20: new           #78                 // class android/graphics/Paint
      23: dup
      24: invokespecial #82                 // Method android/graphics/Paint."<init>":()V
      27: astore        4
      29: aload         4
      31: sipush        255
      34: sipush        210
      37: sipush        210
      40: sipush        210
      43: invokevirtual #86                 // Method android/graphics/Paint.setARGB:(IIII)V
      46: aload         4
      48: getstatic     #92                 // Field android/graphics/Paint$Align.CENTER:Landroid/graphics/Paint$Align;
      51: invokevirtual #96                 // Method android/graphics/Paint.setTextAlign:(Landroid/graphics/Paint$Align;)V
      54: aload         4
      56: getstatic     #102                // Field android/graphics/Typeface.DEFAULT:Landroid/graphics/Typeface;
      59: iconst_0
      60: invokestatic  #106                // Method android/graphics/Typeface.create:(Landroid/graphics/Typeface;I)Landroid/graphics/Typeface;
      63: invokevirtual #110                // Method android/graphics/Paint.setTypeface:(Landroid/graphics/Typeface;)Landroid/graphics/Typeface;
      66: pop
      67: new           #112                // class android/graphics/Rect
      70: dup
      71: invokespecial #113                // Method android/graphics/Rect."<init>":()V
      74: astore        5
      76: aload_1
      77: aload         5
      79: invokevirtual #117                // Method android/graphics/Canvas.getClipBounds:(Landroid/graphics/Rect;)Z
      82: pop
      83: aload         4
      85: aload         5
      87: invokevirtual #120                // Method android/graphics/Rect.height:()I
      90: i2f
      91: invokevirtual #124                // Method android/graphics/Paint.setTextSize:(F)V
      94: aload         5
      96: invokevirtual #120                // Method android/graphics/Rect.height:()I
      99: istore_2
     100: aload         5
     102: invokevirtual #127                // Method android/graphics/Rect.width:()I
     105: istore_3
     106: aload         4
     108: getstatic     #130                // Field android/graphics/Paint$Align.LEFT:Landroid/graphics/Paint$Align;
     111: invokevirtual #96                 // Method android/graphics/Paint.setTextAlign:(Landroid/graphics/Paint$Align;)V
     114: aload         4
     116: ldc           #132                // String ?
     118: iconst_0
     119: ldc           #132                // String ?
     121: invokevirtual #137                // Method java/lang/String.length:()I
     124: aload         5
     126: invokevirtual #141                // Method android/graphics/Paint.getTextBounds:(Ljava/lang/String;IILandroid/graphics/Rect;)V
     129: aload_1
     130: ldc           #132                // String ?
     132: iload_3
     133: i2f
     134: fconst_2
     135: fdiv
     136: aload         5
     138: invokevirtual #127                // Method android/graphics/Rect.width:()I
     141: i2f
     142: fconst_2
     143: fdiv
     144: fsub
     145: aload         5
     147: getfield      #144                // Field android/graphics/Rect.left:I
     150: i2f
     151: fsub
     152: iload_2
     153: i2f
     154: fconst_2
     155: fdiv
     156: aload         5
     158: invokevirtual #120                // Method android/graphics/Rect.height:()I
     161: i2f
     162: fconst_2
     163: fdiv
     164: fadd
     165: aload         5
     167: getfield      #147                // Field android/graphics/Rect.bottom:I
     170: i2f
     171: fsub
     172: aload         4
     174: invokevirtual #151                // Method android/graphics/Canvas.drawText:(Ljava/lang/String;FFLandroid/graphics/Paint;)V
     177: return

  public void setContentId(int);
    Code:
       0: aload_0
       1: getfield      #12                 // Field a:I
       4: iload_1
       5: if_icmpne     9
       8: return
       9: aload_0
      10: getfield      #30                 // Field b:Landroid/view/View;
      13: ifnull        43
      16: aload_0
      17: getfield      #30                 // Field b:Landroid/view/View;
      20: iconst_0
      21: invokevirtual #41                 // Method android/view/View.setVisibility:(I)V
      24: aload_0
      25: getfield      #30                 // Field b:Landroid/view/View;
      28: invokevirtual #34                 // Method android/view/View.getLayoutParams:()Landroid/view/ViewGroup$LayoutParams;
      31: checkcast     #36                 // class android/support/constraint/ConstraintLayout$a
      34: iconst_0
      35: putfield      #40                 // Field android/support/constraint/ConstraintLayout$a.aa:Z
      38: aload_0
      39: aconst_null
      40: putfield      #30                 // Field b:Landroid/view/View;
      43: aload_0
      44: iload_1
      45: putfield      #12                 // Field a:I
      48: iload_1
      49: iconst_m1
      50: if_icmpeq     75
      53: aload_0
      54: invokevirtual #156                // Method getParent:()Landroid/view/ViewParent;
      57: checkcast     #4                  // class android/view/View
      60: iload_1
      61: invokevirtual #157                // Method android/view/View.findViewById:(I)Landroid/view/View;
      64: astore_2
      65: aload_2
      66: ifnull        75
      69: aload_2
      70: bipush        8
      72: invokevirtual #41                 // Method android/view/View.setVisibility:(I)V
      75: return

  public void setEmptyVisibility(int);
    Code:
       0: aload_0
       1: iload_1
       2: putfield      #18                 // Field c:I
       5: return
}
