class android.arch.a.b.b$b<K, V> extends android.arch.a.b.b$e<K, V> {
  android.arch.a.b.b$b(android.arch.a.b.b$c<K, V>, android.arch.a.b.b$c<K, V>);
    Code:
       0: aload_0
       1: aload_1
       2: aload_2
       3: invokespecial #12                 // Method android/arch/a/b/b$e."<init>":(Landroid/arch/a/b/b$c;Landroid/arch/a/b/b$c;)V
       6: return

  android.arch.a.b.b$c<K, V> a(android.arch.a.b.b$c<K, V>);
    Code:
       0: aload_1
       1: getfield      #23                 // Field android/arch/a/b/b$c.d:Landroid/arch/a/b/b$c;
       4: areturn

  android.arch.a.b.b$c<K, V> b(android.arch.a.b.b$c<K, V>);
    Code:
       0: aload_1
       1: getfield      #27                 // Field android/arch/a/b/b$c.c:Landroid/arch/a/b/b$c;
       4: areturn
}
