class android.support.v7.c.a.b$a {
  final android.content.res.ColorStateList a;

  final android.content.res.Configuration b;

  android.support.v7.c.a.b$a(android.content.res.ColorStateList, android.content.res.Configuration);
    Code:
       0: aload_0
       1: invokespecial #15                 // Method java/lang/Object."<init>":()V
       4: aload_0
       5: aload_1
       6: putfield      #17                 // Field a:Landroid/content/res/ColorStateList;
       9: aload_0
      10: aload_2
      11: putfield      #19                 // Field b:Landroid/content/res/Configuration;
      14: return
}
