public final class android.support.v7.c.a.b {
  static {};
    Code:
       0: new           #18                 // class java/lang/ThreadLocal
       3: dup
       4: invokespecial #21                 // Method java/lang/ThreadLocal."<init>":()V
       7: putstatic     #23                 // Field a:Ljava/lang/ThreadLocal;
      10: new           #25                 // class java/util/WeakHashMap
      13: dup
      14: iconst_0
      15: invokespecial #28                 // Method java/util/WeakHashMap."<init>":(I)V
      18: putstatic     #30                 // Field b:Ljava/util/WeakHashMap;
      21: new           #4                  // class java/lang/Object
      24: dup
      25: invokespecial #31                 // Method java/lang/Object."<init>":()V
      28: putstatic     #33                 // Field c:Ljava/lang/Object;
      31: return

  public static android.content.res.ColorStateList a(android.content.Context, int);
    Code:
       0: getstatic     #41                 // Field android/os/Build$VERSION.SDK_INT:I
       3: bipush        23
       5: if_icmplt     14
       8: aload_0
       9: iload_1
      10: invokevirtual #47                 // Method android/content/Context.getColorStateList:(I)Landroid/content/res/ColorStateList;
      13: areturn
      14: aload_0
      15: iload_1
      16: invokestatic  #50                 // Method d:(Landroid/content/Context;I)Landroid/content/res/ColorStateList;
      19: astore_2
      20: aload_2
      21: ifnull        26
      24: aload_2
      25: areturn
      26: aload_0
      27: iload_1
      28: invokestatic  #52                 // Method c:(Landroid/content/Context;I)Landroid/content/res/ColorStateList;
      31: astore_2
      32: aload_2
      33: ifnull        44
      36: aload_0
      37: iload_1
      38: aload_2
      39: invokestatic  #55                 // Method a:(Landroid/content/Context;ILandroid/content/res/ColorStateList;)V
      42: aload_2
      43: areturn
      44: aload_0
      45: iload_1
      46: invokestatic  #59                 // Method android/support/v4/a/a.b:(Landroid/content/Context;I)Landroid/content/res/ColorStateList;
      49: areturn

  public static android.graphics.drawable.Drawable b(android.content.Context, int);
    Code:
       0: invokestatic  #104                // Method android/support/v7/widget/m.a:()Landroid/support/v7/widget/m;
       3: aload_0
       4: iload_1
       5: invokevirtual #106                // Method android/support/v7/widget/m.a:(Landroid/content/Context;I)Landroid/graphics/drawable/Drawable;
       8: areturn
}
