public class ryey.easer.plugins.operation.brightness.a extends ryey.easer.plugins.operation.c<ryey.easer.plugins.operation.brightness.b> {
  public ryey.easer.plugins.operation.brightness.a(android.content.Context);
    Code:
       0: aload_0
       1: aload_1
       2: invokespecial #9                  // Method ryey/easer/plugins/operation/c."<init>":(Landroid/content/Context;)V
       5: return

  public boolean a(ryey.easer.commons.local_plugin.c.b);
    Code:
       0: aload_0
       1: aload_1
       2: checkcast     #14                 // class ryey/easer/plugins/operation/brightness/b
       5: invokevirtual #57                 // Method a:(Lryey/easer/plugins/operation/brightness/b;)Z
       8: ireturn

  public boolean a(ryey.easer.plugins.operation.brightness.b);
    Code:
       0: aload_0
       1: aload_1
       2: invokespecial #59                 // Method b:(Lryey/easer/plugins/operation/brightness/b;)Z
       5: ireturn
}
