public class ryey.easer.plugins.a.l.d extends ryey.easer.plugins.c<ryey.easer.plugins.a.l.a> {
  android.widget.RadioButton a;

  android.widget.RadioButton b;

  public ryey.easer.plugins.a.l.d();
    Code:
       0: aload_0
       1: invokespecial #12                 // Method ryey/easer/plugins/c."<init>":()V
       4: return

  public ryey.easer.commons.local_plugin.f a();
    Code:
       0: aload_0
       1: invokevirtual #17                 // Method b:()Lryey/easer/plugins/a/l/a;
       4: areturn

  protected void a(ryey.easer.plugins.a.l.a);
    Code:
       0: aload_1
       1: getfield      #23                 // Field ryey/easer/plugins/a/l/a.a:Z
       4: ifeq          18
       7: aload_0
       8: getfield      #25                 // Field a:Landroid/widget/RadioButton;
      11: astore_1
      12: aload_1
      13: iconst_1
      14: invokevirtual #31                 // Method android/widget/RadioButton.setChecked:(Z)V
      17: return
      18: aload_0
      19: getfield      #33                 // Field b:Landroid/widget/RadioButton;
      22: astore_1
      23: goto          12

  public ryey.easer.plugins.a.l.a b();
    Code:
       0: new           #20                 // class ryey/easer/plugins/a/l/a
       3: dup
       4: aload_0
       5: getfield      #25                 // Field a:Landroid/widget/RadioButton;
       8: invokevirtual #37                 // Method android/widget/RadioButton.isChecked:()Z
      11: invokespecial #39                 // Method ryey/easer/plugins/a/l/a."<init>":(Z)V
      14: areturn

  protected void b(ryey.easer.commons.local_plugin.f);
    Code:
       0: aload_0
       1: aload_1
       2: checkcast     #20                 // class ryey/easer/plugins/a/l/a
       5: invokevirtual #42                 // Method a:(Lryey/easer/plugins/a/l/a;)V
       8: return

  public android.view.View onCreateView(android.view.LayoutInflater, android.view.ViewGroup, android.os.Bundle);
    Code:
       0: aload_1
       1: ldc           #45                 // int 2131427429
       3: aload_2
       4: iconst_0
       5: invokevirtual #51                 // Method android/view/LayoutInflater.inflate:(ILandroid/view/ViewGroup;Z)Landroid/view/View;
       8: astore_1
       9: aload_0
      10: aload_1
      11: ldc           #52                 // int 2131296558
      13: invokevirtual #58                 // Method android/view/View.findViewById:(I)Landroid/view/View;
      16: checkcast     #27                 // class android/widget/RadioButton
      19: putfield      #25                 // Field a:Landroid/widget/RadioButton;
      22: aload_0
      23: aload_1
      24: ldc           #59                 // int 2131296537
      26: invokevirtual #58                 // Method android/view/View.findViewById:(I)Landroid/view/View;
      29: checkcast     #27                 // class android/widget/RadioButton
      32: putfield      #33                 // Field b:Landroid/widget/RadioButton;
      35: aload_1
      36: areturn
}
