class ryey.easer.commons.a.a$1 implements android.widget.AdapterView$OnItemSelectedListener {
  final ryey.easer.commons.a.a a;

  ryey.easer.commons.a.a$1(ryey.easer.commons.a.a);
    Code:
       0: aload_0
       1: aload_1
       2: putfield      #17                 // Field a:Lryey/easer/commons/a/a;
       5: aload_0
       6: invokespecial #19                 // Method java/lang/Object."<init>":()V
       9: return

  public void onItemSelected(android.widget.AdapterView<?>, android.view.View, int, long);
    Code:
       0: aload_1
       1: iload_3
       2: invokevirtual #28                 // Method android/widget/AdapterView.setSelection:(I)V
       5: return

  public void onNothingSelected(android.widget.AdapterView<?>);
    Code:
       0: return
}
