public class ryey.easer.plugins.a.f.d extends ryey.easer.plugins.c<ryey.easer.plugins.a.f.a> {
  public ryey.easer.plugins.a.f.d();
    Code:
       0: aload_0
       1: invokespecial #11                 // Method ryey/easer/plugins/c."<init>":()V
       4: return

  public ryey.easer.commons.local_plugin.f a();
    Code:
       0: aload_0
       1: invokevirtual #49                 // Method b:()Lryey/easer/plugins/a/f/a;
       4: areturn

  protected void a(ryey.easer.plugins.a.f.a);
    Code:
       0: aload_0
       1: getfield      #52                 // Field a:Landroid/widget/DatePicker;
       4: aload_1
       5: getfield      #57                 // Field ryey/easer/plugins/a/f/a.a:Ljava/util/Calendar;
       8: invokestatic  #59                 // Method a:(Landroid/widget/DatePicker;Ljava/util/Calendar;)V
      11: return

  public ryey.easer.plugins.a.f.a b();
    Code:
       0: new           #54                 // class ryey/easer/plugins/a/f/a
       3: dup
       4: aload_0
       5: getfield      #52                 // Field a:Landroid/widget/DatePicker;
       8: invokestatic  #61                 // Method a:(Landroid/widget/DatePicker;)Ljava/util/Calendar;
      11: getstatic     #66                 // Field ryey/easer/plugins/a/f/a$a.a:Lryey/easer/plugins/a/f/a$a;
      14: invokespecial #69                 // Method ryey/easer/plugins/a/f/a."<init>":(Ljava/util/Calendar;Lryey/easer/plugins/a/f/a$a;)V
      17: areturn

  protected void b(ryey.easer.commons.local_plugin.f);
    Code:
       0: aload_0
       1: aload_1
       2: checkcast     #54                 // class ryey/easer/plugins/a/f/a
       5: invokevirtual #72                 // Method a:(Lryey/easer/plugins/a/f/a;)V
       8: return

  public android.view.View onCreateView(android.view.LayoutInflater, android.view.ViewGroup, android.os.Bundle);
    Code:
       0: aload_1
       1: ldc           #75                 // int 2131427426
       3: aload_2
       4: iconst_0
       5: invokevirtual #81                 // Method android/view/LayoutInflater.inflate:(ILandroid/view/ViewGroup;Z)Landroid/view/View;
       8: astore_1
       9: aload_0
      10: aload_1
      11: ldc           #82                 // int 2131296360
      13: invokevirtual #88                 // Method android/view/View.findViewById:(I)Landroid/view/View;
      16: checkcast     #21                 // class android/widget/DatePicker
      19: putfield      #52                 // Field a:Landroid/widget/DatePicker;
      22: aload_1
      23: areturn
}
