class android.support.v7.view.menu.e$3 implements android.support.v7.widget.ax {
  final android.support.v7.view.menu.e a;

  android.support.v7.view.menu.e$3(android.support.v7.view.menu.e);
    Code:
       0: aload_0
       1: aload_1
       2: putfield      #16                 // Field a:Landroid/support/v7/view/menu/e;
       5: aload_0
       6: invokespecial #19                 // Method java/lang/Object."<init>":()V
       9: return

  public void a(android.support.v7.view.menu.h, android.view.MenuItem);
    Code:
       0: aload_0
       1: getfield      #16                 // Field a:Landroid/support/v7/view/menu/e;
       4: getfield      #24                 // Field android/support/v7/view/menu/e.a:Landroid/os/Handler;
       7: aload_1
       8: invokevirtual #30                 // Method android/os/Handler.removeCallbacksAndMessages:(Ljava/lang/Object;)V
      11: return

  public void b(android.support.v7.view.menu.h, android.view.MenuItem);
    Code:
       0: aload_0
       1: getfield      #16                 // Field a:Landroid/support/v7/view/menu/e;
       4: getfield      #24                 // Field android/support/v7/view/menu/e.a:Landroid/os/Handler;
       7: astore        8
       9: aconst_null
      10: astore        7
      12: aload         8
      14: aconst_null
      15: invokevirtual #30                 // Method android/os/Handler.removeCallbacksAndMessages:(Ljava/lang/Object;)V
      18: aload_0
      19: getfield      #16                 // Field a:Landroid/support/v7/view/menu/e;
      22: getfield      #34                 // Field android/support/v7/view/menu/e.b:Ljava/util/List;
      25: invokeinterface #40,  1           // InterfaceMethod java/util/List.size:()I
      30: istore        4
      32: iconst_0
      33: istore_3
      34: iload_3
      35: iload         4
      37: if_icmpge     73
      40: aload_1
      41: aload_0
      42: getfield      #16                 // Field a:Landroid/support/v7/view/menu/e;
      45: getfield      #34                 // Field android/support/v7/view/menu/e.b:Ljava/util/List;
      48: iload_3
      49: invokeinterface #44,  2           // InterfaceMethod java/util/List.get:(I)Ljava/lang/Object;
      54: checkcast     #46                 // class android/support/v7/view/menu/e$a
      57: getfield      #49                 // Field android/support/v7/view/menu/e$a.b:Landroid/support/v7/view/menu/h;
      60: if_acmpne     66
      63: goto          75
      66: iload_3
      67: iconst_1
      68: iadd
      69: istore_3
      70: goto          34
      73: iconst_m1
      74: istore_3
      75: iload_3
      76: iconst_m1
      77: if_icmpne     81
      80: return
      81: iload_3
      82: iconst_1
      83: iadd
      84: istore_3
      85: iload_3
      86: aload_0
      87: getfield      #16                 // Field a:Landroid/support/v7/view/menu/e;
      90: getfield      #34                 // Field android/support/v7/view/menu/e.b:Ljava/util/List;
      93: invokeinterface #40,  1           // InterfaceMethod java/util/List.size:()I
      98: if_icmpge     119
     101: aload_0
     102: getfield      #16                 // Field a:Landroid/support/v7/view/menu/e;
     105: getfield      #34                 // Field android/support/v7/view/menu/e.b:Ljava/util/List;
     108: iload_3
     109: invokeinterface #44,  2           // InterfaceMethod java/util/List.get:(I)Ljava/lang/Object;
     114: checkcast     #46                 // class android/support/v7/view/menu/e$a
     117: astore        7
     119: new           #10                 // class android/support/v7/view/menu/e$3$1
     122: dup
     123: aload_0
     124: aload         7
     126: aload_2
     127: aload_1
     128: invokespecial #52                 // Method android/support/v7/view/menu/e$3$1."<init>":(Landroid/support/v7/view/menu/e$3;Landroid/support/v7/view/menu/e$a;Landroid/view/MenuItem;Landroid/support/v7/view/menu/h;)V
     131: astore_2
     132: invokestatic  #58                 // Method android/os/SystemClock.uptimeMillis:()J
     135: lstore        5
     137: aload_0
     138: getfield      #16                 // Field a:Landroid/support/v7/view/menu/e;
     141: getfield      #24                 // Field android/support/v7/view/menu/e.a:Landroid/os/Handler;
     144: aload_2
     145: aload_1
     146: lload         5
     148: ldc2_w        #59                 // long 200l
     151: ladd
     152: invokevirtual #64                 // Method android/os/Handler.postAtTime:(Ljava/lang/Runnable;Ljava/lang/Object;J)Z
     155: pop
     156: return
}
