class android.support.v7.view.menu.e$a {
  public final android.support.v7.widget.ay a;

  public final android.support.v7.view.menu.h b;

  public final int c;

  public android.support.v7.view.menu.e$a(android.support.v7.widget.ay, android.support.v7.view.menu.h, int);
    Code:
       0: aload_0
       1: invokespecial #17                 // Method java/lang/Object."<init>":()V
       4: aload_0
       5: aload_1
       6: putfield      #19                 // Field a:Landroid/support/v7/widget/ay;
       9: aload_0
      10: aload_2
      11: putfield      #21                 // Field b:Landroid/support/v7/view/menu/h;
      14: aload_0
      15: iload_3
      16: putfield      #23                 // Field c:I
      19: return

  public android.widget.ListView a();
    Code:
       0: aload_0
       1: getfield      #19                 // Field a:Landroid/support/v7/widget/ay;
       4: invokevirtual #30                 // Method android/support/v7/widget/ay.g:()Landroid/widget/ListView;
       7: areturn
}
