public final class android.support.v7.view.menu.ExpandedMenuView extends android.widget.ListView implements android.support.v7.view.menu.h$b,android.support.v7.view.menu.p,android.widget.AdapterView$OnItemClickListener {
  static {};
    Code:
       0: iconst_2
       1: newarray       int
       3: dup
       4: iconst_0
       5: ldc           #19                 // int 16842964
       7: iastore
       8: dup
       9: iconst_1
      10: ldc           #20                 // int 16843049
      12: iastore
      13: putstatic     #22                 // Field a:[I
      16: return

  public android.support.v7.view.menu.ExpandedMenuView(android.content.Context, android.util.AttributeSet);
    Code:
       0: aload_0
       1: aload_1
       2: aload_2
       3: ldc           #26                 // int 16842868
       5: invokespecial #29                 // Method "<init>":(Landroid/content/Context;Landroid/util/AttributeSet;I)V
       8: return

  public android.support.v7.view.menu.ExpandedMenuView(android.content.Context, android.util.AttributeSet, int);
    Code:
       0: aload_0
       1: aload_1
       2: aload_2
       3: invokespecial #31                 // Method android/widget/ListView."<init>":(Landroid/content/Context;Landroid/util/AttributeSet;)V
       6: aload_0
       7: aload_0
       8: invokevirtual #35                 // Method setOnItemClickListener:(Landroid/widget/AdapterView$OnItemClickListener;)V
      11: aload_1
      12: aload_2
      13: getstatic     #22                 // Field a:[I
      16: iload_3
      17: iconst_0
      18: invokestatic  #40                 // Method android/support/v7/widget/bp.a:(Landroid/content/Context;Landroid/util/AttributeSet;[III)Landroid/support/v7/widget/bp;
      21: astore_1
      22: aload_1
      23: iconst_0
      24: invokevirtual #44                 // Method android/support/v7/widget/bp.g:(I)Z
      27: ifeq          39
      30: aload_0
      31: aload_1
      32: iconst_0
      33: invokevirtual #47                 // Method android/support/v7/widget/bp.a:(I)Landroid/graphics/drawable/Drawable;
      36: invokevirtual #51                 // Method setBackgroundDrawable:(Landroid/graphics/drawable/Drawable;)V
      39: aload_1
      40: iconst_1
      41: invokevirtual #44                 // Method android/support/v7/widget/bp.g:(I)Z
      44: ifeq          56
      47: aload_0
      48: aload_1
      49: iconst_1
      50: invokevirtual #47                 // Method android/support/v7/widget/bp.a:(I)Landroid/graphics/drawable/Drawable;
      53: invokevirtual #54                 // Method setDivider:(Landroid/graphics/drawable/Drawable;)V
      56: aload_1
      57: invokevirtual #56                 // Method android/support/v7/widget/bp.a:()V
      60: return

  public void a(android.support.v7.view.menu.h);
    Code:
       0: aload_0
       1: aload_1
       2: putfield      #59                 // Field b:Landroid/support/v7/view/menu/h;
       5: return

  public boolean a(android.support.v7.view.menu.j);
    Code:
       0: aload_0
       1: getfield      #59                 // Field b:Landroid/support/v7/view/menu/h;
       4: aload_1
       5: iconst_0
       6: invokevirtual #65                 // Method android/support/v7/view/menu/h.a:(Landroid/view/MenuItem;I)Z
       9: ireturn

  public int getWindowAnimations();
    Code:
       0: aload_0
       1: getfield      #69                 // Field c:I
       4: ireturn

  protected void onDetachedFromWindow();
    Code:
       0: aload_0
       1: invokespecial #72                 // Method android/widget/ListView.onDetachedFromWindow:()V
       4: aload_0
       5: iconst_0
       6: invokevirtual #76                 // Method setChildrenDrawingCacheEnabled:(Z)V
       9: return

  public void onItemClick(android.widget.AdapterView, android.view.View, int, long);
    Code:
       0: aload_0
       1: aload_0
       2: invokevirtual #82                 // Method getAdapter:()Landroid/widget/ListAdapter;
       5: iload_3
       6: invokeinterface #88,  2           // InterfaceMethod android/widget/ListAdapter.getItem:(I)Ljava/lang/Object;
      11: checkcast     #90                 // class android/support/v7/view/menu/j
      14: invokevirtual #92                 // Method a:(Landroid/support/v7/view/menu/j;)Z
      17: pop
      18: return
}
