class android.support.v7.view.menu.i implements android.content.DialogInterface$OnClickListener,android.content.DialogInterface$OnDismissListener,android.content.DialogInterface$OnKeyListener,android.support.v7.view.menu.o$a {
  android.support.v7.view.menu.f a;

  public android.support.v7.view.menu.i(android.support.v7.view.menu.h);
    Code:
       0: aload_0
       1: invokespecial #25                 // Method java/lang/Object."<init>":()V
       4: aload_0
       5: aload_1
       6: putfield      #27                 // Field b:Landroid/support/v7/view/menu/h;
       9: return

  public void a();
    Code:
       0: aload_0
       1: getfield      #30                 // Field c:Landroid/support/v7/app/d;
       4: ifnull        14
       7: aload_0
       8: getfield      #30                 // Field c:Landroid/support/v7/app/d;
      11: invokevirtual #35                 // Method android/support/v7/app/d.dismiss:()V
      14: return

  public void a(android.os.IBinder);
    Code:
       0: aload_0
       1: getfield      #27                 // Field b:Landroid/support/v7/view/menu/h;
       4: astore_2
       5: new           #38                 // class android/support/v7/app/d$a
       8: dup
       9: aload_2
      10: invokevirtual #44                 // Method android/support/v7/view/menu/h.e:()Landroid/content/Context;
      13: invokespecial #47                 // Method android/support/v7/app/d$a."<init>":(Landroid/content/Context;)V
      16: astore_3
      17: aload_0
      18: new           #49                 // class android/support/v7/view/menu/f
      21: dup
      22: aload_3
      23: invokevirtual #51                 // Method android/support/v7/app/d$a.a:()Landroid/content/Context;
      26: getstatic     #57                 // Field android/support/v7/a/a$g.abc_list_menu_item_layout:I
      29: invokespecial #60                 // Method android/support/v7/view/menu/f."<init>":(Landroid/content/Context;I)V
      32: putfield      #62                 // Field a:Landroid/support/v7/view/menu/f;
      35: aload_0
      36: getfield      #62                 // Field a:Landroid/support/v7/view/menu/f;
      39: aload_0
      40: invokevirtual #65                 // Method android/support/v7/view/menu/f.a:(Landroid/support/v7/view/menu/o$a;)V
      43: aload_0
      44: getfield      #27                 // Field b:Landroid/support/v7/view/menu/h;
      47: aload_0
      48: getfield      #62                 // Field a:Landroid/support/v7/view/menu/f;
      51: invokevirtual #68                 // Method android/support/v7/view/menu/h.a:(Landroid/support/v7/view/menu/o;)V
      54: aload_3
      55: aload_0
      56: getfield      #62                 // Field a:Landroid/support/v7/view/menu/f;
      59: invokevirtual #71                 // Method android/support/v7/view/menu/f.d:()Landroid/widget/ListAdapter;
      62: aload_0
      63: invokevirtual #74                 // Method android/support/v7/app/d$a.a:(Landroid/widget/ListAdapter;Landroid/content/DialogInterface$OnClickListener;)Landroid/support/v7/app/d$a;
      66: pop
      67: aload_2
      68: invokevirtual #78                 // Method android/support/v7/view/menu/h.o:()Landroid/view/View;
      71: astore        4
      73: aload         4
      75: ifnull        88
      78: aload_3
      79: aload         4
      81: invokevirtual #81                 // Method android/support/v7/app/d$a.a:(Landroid/view/View;)Landroid/support/v7/app/d$a;
      84: pop
      85: goto          104
      88: aload_3
      89: aload_2
      90: invokevirtual #85                 // Method android/support/v7/view/menu/h.n:()Landroid/graphics/drawable/Drawable;
      93: invokevirtual #88                 // Method android/support/v7/app/d$a.a:(Landroid/graphics/drawable/Drawable;)Landroid/support/v7/app/d$a;
      96: aload_2
      97: invokevirtual #92                 // Method android/support/v7/view/menu/h.m:()Ljava/lang/CharSequence;
     100: invokevirtual #95                 // Method android/support/v7/app/d$a.a:(Ljava/lang/CharSequence;)Landroid/support/v7/app/d$a;
     103: pop
     104: aload_3
     105: aload_0
     106: invokevirtual #98                 // Method android/support/v7/app/d$a.a:(Landroid/content/DialogInterface$OnKeyListener;)Landroid/support/v7/app/d$a;
     109: pop
     110: aload_0
     111: aload_3
     112: invokevirtual #101                // Method android/support/v7/app/d$a.b:()Landroid/support/v7/app/d;
     115: putfield      #30                 // Field c:Landroid/support/v7/app/d;
     118: aload_0
     119: getfield      #30                 // Field c:Landroid/support/v7/app/d;
     122: aload_0
     123: invokevirtual #105                // Method android/support/v7/app/d.setOnDismissListener:(Landroid/content/DialogInterface$OnDismissListener;)V
     126: aload_0
     127: getfield      #30                 // Field c:Landroid/support/v7/app/d;
     130: invokevirtual #109                // Method android/support/v7/app/d.getWindow:()Landroid/view/Window;
     133: invokevirtual #115                // Method android/view/Window.getAttributes:()Landroid/view/WindowManager$LayoutParams;
     136: astore_2
     137: aload_2
     138: sipush        1003
     141: putfield      #120                // Field android/view/WindowManager$LayoutParams.type:I
     144: aload_1
     145: ifnull        153
     148: aload_2
     149: aload_1
     150: putfield      #124                // Field android/view/WindowManager$LayoutParams.token:Landroid/os/IBinder;
     153: aload_2
     154: aload_2
     155: getfield      #127                // Field android/view/WindowManager$LayoutParams.flags:I
     158: ldc           #128                // int 131072
     160: ior
     161: putfield      #127                // Field android/view/WindowManager$LayoutParams.flags:I
     164: aload_0
     165: getfield      #30                 // Field c:Landroid/support/v7/app/d;
     168: invokevirtual #131                // Method android/support/v7/app/d.show:()V
     171: return

  public void a(android.support.v7.view.menu.h, boolean);
    Code:
       0: iload_2
       1: ifne          12
       4: aload_1
       5: aload_0
       6: getfield      #27                 // Field b:Landroid/support/v7/view/menu/h;
       9: if_acmpne     16
      12: aload_0
      13: invokevirtual #134                // Method a:()V
      16: aload_0
      17: getfield      #136                // Field d:Landroid/support/v7/view/menu/o$a;
      20: ifnull        34
      23: aload_0
      24: getfield      #136                // Field d:Landroid/support/v7/view/menu/o$a;
      27: aload_1
      28: iload_2
      29: invokeinterface #138,  3          // InterfaceMethod android/support/v7/view/menu/o$a.a:(Landroid/support/v7/view/menu/h;Z)V
      34: return

  public boolean a(android.support.v7.view.menu.h);
    Code:
       0: aload_0
       1: getfield      #136                // Field d:Landroid/support/v7/view/menu/o$a;
       4: ifnull        18
       7: aload_0
       8: getfield      #136                // Field d:Landroid/support/v7/view/menu/o$a;
      11: aload_1
      12: invokeinterface #141,  2          // InterfaceMethod android/support/v7/view/menu/o$a.a:(Landroid/support/v7/view/menu/h;)Z
      17: ireturn
      18: iconst_0
      19: ireturn

  public void onClick(android.content.DialogInterface, int);
    Code:
       0: aload_0
       1: getfield      #27                 // Field b:Landroid/support/v7/view/menu/h;
       4: aload_0
       5: getfield      #62                 // Field a:Landroid/support/v7/view/menu/f;
       8: invokevirtual #71                 // Method android/support/v7/view/menu/f.d:()Landroid/widget/ListAdapter;
      11: iload_2
      12: invokeinterface #149,  2          // InterfaceMethod android/widget/ListAdapter.getItem:(I)Ljava/lang/Object;
      17: checkcast     #151                // class android/support/v7/view/menu/j
      20: iconst_0
      21: invokevirtual #154                // Method android/support/v7/view/menu/h.a:(Landroid/view/MenuItem;I)Z
      24: pop
      25: return

  public void onDismiss(android.content.DialogInterface);
    Code:
       0: aload_0
       1: getfield      #62                 // Field a:Landroid/support/v7/view/menu/f;
       4: aload_0
       5: getfield      #27                 // Field b:Landroid/support/v7/view/menu/h;
       8: iconst_1
       9: invokevirtual #157                // Method android/support/v7/view/menu/f.a:(Landroid/support/v7/view/menu/h;Z)V
      12: return

  public boolean onKey(android.content.DialogInterface, int, android.view.KeyEvent);
    Code:
       0: iload_2
       1: bipush        82
       3: if_icmpeq     11
       6: iload_2
       7: iconst_4
       8: if_icmpne     141
      11: aload_3
      12: invokevirtual #165                // Method android/view/KeyEvent.getAction:()I
      15: ifne          63
      18: aload_3
      19: invokevirtual #168                // Method android/view/KeyEvent.getRepeatCount:()I
      22: ifne          63
      25: aload_0
      26: getfield      #30                 // Field c:Landroid/support/v7/app/d;
      29: invokevirtual #109                // Method android/support/v7/app/d.getWindow:()Landroid/view/Window;
      32: astore_1
      33: aload_1
      34: ifnull        141
      37: aload_1
      38: invokevirtual #171                // Method android/view/Window.getDecorView:()Landroid/view/View;
      41: astore_1
      42: aload_1
      43: ifnull        141
      46: aload_1
      47: invokevirtual #177                // Method android/view/View.getKeyDispatcherState:()Landroid/view/KeyEvent$DispatcherState;
      50: astore_1
      51: aload_1
      52: ifnull        141
      55: aload_1
      56: aload_3
      57: aload_0
      58: invokevirtual #183                // Method android/view/KeyEvent$DispatcherState.startTracking:(Landroid/view/KeyEvent;Ljava/lang/Object;)V
      61: iconst_1
      62: ireturn
      63: aload_3
      64: invokevirtual #165                // Method android/view/KeyEvent.getAction:()I
      67: iconst_1
      68: if_icmpne     141
      71: aload_3
      72: invokevirtual #187                // Method android/view/KeyEvent.isCanceled:()Z
      75: ifne          141
      78: aload_0
      79: getfield      #30                 // Field c:Landroid/support/v7/app/d;
      82: invokevirtual #109                // Method android/support/v7/app/d.getWindow:()Landroid/view/Window;
      85: astore        4
      87: aload         4
      89: ifnull        141
      92: aload         4
      94: invokevirtual #171                // Method android/view/Window.getDecorView:()Landroid/view/View;
      97: astore        4
      99: aload         4
     101: ifnull        141
     104: aload         4
     106: invokevirtual #177                // Method android/view/View.getKeyDispatcherState:()Landroid/view/KeyEvent$DispatcherState;
     109: astore        4
     111: aload         4
     113: ifnull        141
     116: aload         4
     118: aload_3
     119: invokevirtual #191                // Method android/view/KeyEvent$DispatcherState.isTracking:(Landroid/view/KeyEvent;)Z
     122: ifeq          141
     125: aload_0
     126: getfield      #27                 // Field b:Landroid/support/v7/view/menu/h;
     129: iconst_1
     130: invokevirtual #194                // Method android/support/v7/view/menu/h.b:(Z)V
     133: aload_1
     134: invokeinterface #197,  1          // InterfaceMethod android/content/DialogInterface.dismiss:()V
     139: iconst_1
     140: ireturn
     141: aload_0
     142: getfield      #27                 // Field b:Landroid/support/v7/view/menu/h;
     145: iload_2
     146: aload_3
     147: iconst_0
     148: invokevirtual #201                // Method android/support/v7/view/menu/h.performShortcut:(ILandroid/view/KeyEvent;I)Z
     151: ireturn
}
