class android.support.v7.view.menu.j$1 implements android.support.v4.view.c$b {
  final android.support.v7.view.menu.j a;

  android.support.v7.view.menu.j$1(android.support.v7.view.menu.j);
    Code:
       0: aload_0
       1: aload_1
       2: putfield      #16                 // Field a:Landroid/support/v7/view/menu/j;
       5: aload_0
       6: invokespecial #19                 // Method java/lang/Object."<init>":()V
       9: return

  public void a(boolean);
    Code:
       0: aload_0
       1: getfield      #16                 // Field a:Landroid/support/v7/view/menu/j;
       4: getfield      #24                 // Field android/support/v7/view/menu/j.a:Landroid/support/v7/view/menu/h;
       7: aload_0
       8: getfield      #16                 // Field a:Landroid/support/v7/view/menu/j;
      11: invokevirtual #28                 // Method android/support/v7/view/menu/h.a:(Landroid/support/v7/view/menu/j;)V
      14: return
}
