class android.support.v7.view.menu.l extends android.support.v7.view.menu.k {
  android.support.v7.view.menu.l(android.content.Context, android.support.v4.c.a.b);
    Code:
       0: aload_0
       1: aload_1
       2: aload_2
       3: invokespecial #11                 // Method android/support/v7/view/menu/k."<init>":(Landroid/content/Context;Landroid/support/v4/c/a/b;)V
       6: return

  android.support.v7.view.menu.k$a a(android.view.ActionProvider);
    Code:
       0: new           #6                  // class android/support/v7/view/menu/l$a
       3: dup
       4: aload_0
       5: aload_0
       6: getfield      #16                 // Field a:Landroid/content/Context;
       9: aload_1
      10: invokespecial #19                 // Method android/support/v7/view/menu/l$a."<init>":(Landroid/support/v7/view/menu/l;Landroid/content/Context;Landroid/view/ActionProvider;)V
      13: areturn
}
