public class android.support.v7.view.menu.ListMenuItemView extends android.widget.LinearLayout implements android.support.v7.view.menu.p$a {
  public android.support.v7.view.menu.ListMenuItemView(android.content.Context, android.util.AttributeSet);
    Code:
       0: aload_0
       1: aload_1
       2: aload_2
       3: getstatic     #38                 // Field android/support/v7/a/a$a.listMenuViewStyle:I
       6: invokespecial #41                 // Method "<init>":(Landroid/content/Context;Landroid/util/AttributeSet;I)V
       9: return

  public android.support.v7.view.menu.ListMenuItemView(android.content.Context, android.util.AttributeSet, int);
    Code:
       0: aload_0
       1: aload_1
       2: aload_2
       3: invokespecial #44                 // Method android/widget/LinearLayout."<init>":(Landroid/content/Context;Landroid/util/AttributeSet;)V
       6: aload_0
       7: invokevirtual #48                 // Method getContext:()Landroid/content/Context;
      10: aload_2
      11: getstatic     #54                 // Field android/support/v7/a/a$j.MenuView:[I
      14: iload_3
      15: iconst_0
      16: invokestatic  #59                 // Method android/support/v7/widget/bp.a:(Landroid/content/Context;Landroid/util/AttributeSet;[III)Landroid/support/v7/widget/bp;
      19: astore_2
      20: aload_0
      21: aload_2
      22: getstatic     #62                 // Field android/support/v7/a/a$j.MenuView_android_itemBackground:I
      25: invokevirtual #65                 // Method android/support/v7/widget/bp.a:(I)Landroid/graphics/drawable/Drawable;
      28: putfield      #67                 // Field h:Landroid/graphics/drawable/Drawable;
      31: aload_0
      32: aload_2
      33: getstatic     #70                 // Field android/support/v7/a/a$j.MenuView_android_itemTextAppearance:I
      36: iconst_m1
      37: invokevirtual #73                 // Method android/support/v7/widget/bp.g:(II)I
      40: putfield      #75                 // Field i:I
      43: aload_0
      44: aload_2
      45: getstatic     #78                 // Field android/support/v7/a/a$j.MenuView_preserveIconSpacing:I
      48: iconst_0
      49: invokevirtual #81                 // Method android/support/v7/widget/bp.a:(IZ)Z
      52: putfield      #83                 // Field k:Z
      55: aload_0
      56: aload_1
      57: putfield      #85                 // Field j:Landroid/content/Context;
      60: aload_0
      61: aload_2
      62: getstatic     #88                 // Field android/support/v7/a/a$j.MenuView_subMenuArrow:I
      65: invokevirtual #65                 // Method android/support/v7/widget/bp.a:(I)Landroid/graphics/drawable/Drawable;
      68: putfield      #90                 // Field l:Landroid/graphics/drawable/Drawable;
      71: aload_2
      72: invokevirtual #93                 // Method android/support/v7/widget/bp.a:()V
      75: return

  public void a(android.support.v7.view.menu.j, int);
    Code:
       0: aload_0
       1: aload_1
       2: putfield      #150                // Field a:Landroid/support/v7/view/menu/j;
       5: aload_0
       6: iload_2
       7: putfield      #152                // Field m:I
      10: aload_1
      11: invokevirtual #158                // Method android/support/v7/view/menu/j.isVisible:()Z
      14: ifeq          22
      17: iconst_0
      18: istore_2
      19: goto          25
      22: bipush        8
      24: istore_2
      25: aload_0
      26: iload_2
      27: invokevirtual #159                // Method setVisibility:(I)V
      30: aload_0
      31: aload_1
      32: aload_0
      33: invokevirtual #162                // Method android/support/v7/view/menu/j.a:(Landroid/support/v7/view/menu/p$a;)Ljava/lang/CharSequence;
      36: invokevirtual #166                // Method setTitle:(Ljava/lang/CharSequence;)V
      39: aload_0
      40: aload_1
      41: invokevirtual #169                // Method android/support/v7/view/menu/j.isCheckable:()Z
      44: invokevirtual #172                // Method setCheckable:(Z)V
      47: aload_0
      48: aload_1
      49: invokevirtual #174                // Method android/support/v7/view/menu/j.f:()Z
      52: aload_1
      53: invokevirtual #177                // Method android/support/v7/view/menu/j.d:()C
      56: invokevirtual #180                // Method a:(ZC)V
      59: aload_0
      60: aload_1
      61: invokevirtual #184                // Method android/support/v7/view/menu/j.getIcon:()Landroid/graphics/drawable/Drawable;
      64: invokevirtual #188                // Method setIcon:(Landroid/graphics/drawable/Drawable;)V
      67: aload_0
      68: aload_1
      69: invokevirtual #191                // Method android/support/v7/view/menu/j.isEnabled:()Z
      72: invokevirtual #194                // Method setEnabled:(Z)V
      75: aload_0
      76: aload_1
      77: invokevirtual #197                // Method android/support/v7/view/menu/j.hasSubMenu:()Z
      80: invokespecial #199                // Method setSubMenuArrowVisible:(Z)V
      83: aload_0
      84: aload_1
      85: invokevirtual #203                // Method android/support/v7/view/menu/j.getContentDescription:()Ljava/lang/CharSequence;
      88: invokevirtual #206                // Method setContentDescription:(Ljava/lang/CharSequence;)V
      91: return

  public void a(boolean, char);
    Code:
       0: iload_1
       1: ifeq          19
       4: aload_0
       5: getfield      #150                // Field a:Landroid/support/v7/view/menu/j;
       8: invokevirtual #174                // Method android/support/v7/view/menu/j.f:()Z
      11: ifeq          19
      14: iconst_0
      15: istore_2
      16: goto          22
      19: bipush        8
      21: istore_2
      22: iload_2
      23: ifne          40
      26: aload_0
      27: getfield      #208                // Field f:Landroid/widget/TextView;
      30: aload_0
      31: getfield      #150                // Field a:Landroid/support/v7/view/menu/j;
      34: invokevirtual #211                // Method android/support/v7/view/menu/j.e:()Ljava/lang/String;
      37: invokevirtual #216                // Method android/widget/TextView.setText:(Ljava/lang/CharSequence;)V
      40: aload_0
      41: getfield      #208                // Field f:Landroid/widget/TextView;
      44: invokevirtual #220                // Method android/widget/TextView.getVisibility:()I
      47: iload_2
      48: if_icmpeq     59
      51: aload_0
      52: getfield      #208                // Field f:Landroid/widget/TextView;
      55: iload_2
      56: invokevirtual #221                // Method android/widget/TextView.setVisibility:(I)V
      59: return

  public boolean b();
    Code:
       0: iconst_0
       1: ireturn

  public android.support.v7.view.menu.j getItemData();
    Code:
       0: aload_0
       1: getfield      #150                // Field a:Landroid/support/v7/view/menu/j;
       4: areturn

  protected void onFinishInflate();
    Code:
       0: aload_0
       1: invokespecial #226                // Method android/widget/LinearLayout.onFinishInflate:()V
       4: aload_0
       5: aload_0
       6: getfield      #67                 // Field h:Landroid/graphics/drawable/Drawable;
       9: invokestatic  #231                // Method android/support/v4/view/s.a:(Landroid/view/View;Landroid/graphics/drawable/Drawable;)V
      12: aload_0
      13: aload_0
      14: getstatic     #236                // Field android/support/v7/a/a$f.title:I
      17: invokevirtual #240                // Method findViewById:(I)Landroid/view/View;
      20: checkcast     #213                // class android/widget/TextView
      23: putfield      #242                // Field d:Landroid/widget/TextView;
      26: aload_0
      27: getfield      #75                 // Field i:I
      30: iconst_m1
      31: if_icmpeq     49
      34: aload_0
      35: getfield      #242                // Field d:Landroid/widget/TextView;
      38: aload_0
      39: getfield      #85                 // Field j:Landroid/content/Context;
      42: aload_0
      43: getfield      #75                 // Field i:I
      46: invokevirtual #246                // Method android/widget/TextView.setTextAppearance:(Landroid/content/Context;I)V
      49: aload_0
      50: aload_0
      51: getstatic     #249                // Field android/support/v7/a/a$f.shortcut:I
      54: invokevirtual #240                // Method findViewById:(I)Landroid/view/View;
      57: checkcast     #213                // class android/widget/TextView
      60: putfield      #208                // Field f:Landroid/widget/TextView;
      63: aload_0
      64: aload_0
      65: getstatic     #252                // Field android/support/v7/a/a$f.submenuarrow:I
      68: invokevirtual #240                // Method findViewById:(I)Landroid/view/View;
      71: checkcast     #110                // class android/widget/ImageView
      74: putfield      #143                // Field g:Landroid/widget/ImageView;
      77: aload_0
      78: getfield      #143                // Field g:Landroid/widget/ImageView;
      81: ifnull        95
      84: aload_0
      85: getfield      #143                // Field g:Landroid/widget/ImageView;
      88: aload_0
      89: getfield      #90                 // Field l:Landroid/graphics/drawable/Drawable;
      92: invokevirtual #255                // Method android/widget/ImageView.setImageDrawable:(Landroid/graphics/drawable/Drawable;)V
      95: return

  protected void onMeasure(int, int);
    Code:
       0: aload_0
       1: getfield      #112                // Field b:Landroid/widget/ImageView;
       4: ifnull        55
       7: aload_0
       8: getfield      #83                 // Field k:Z
      11: ifeq          55
      14: aload_0
      15: invokevirtual #261                // Method getLayoutParams:()Landroid/view/ViewGroup$LayoutParams;
      18: astore_3
      19: aload_0
      20: getfield      #112                // Field b:Landroid/widget/ImageView;
      23: invokevirtual #262                // Method android/widget/ImageView.getLayoutParams:()Landroid/view/ViewGroup$LayoutParams;
      26: checkcast     #264                // class android/widget/LinearLayout$LayoutParams
      29: astore        4
      31: aload_3
      32: getfield      #269                // Field android/view/ViewGroup$LayoutParams.height:I
      35: ifle          55
      38: aload         4
      40: getfield      #272                // Field android/widget/LinearLayout$LayoutParams.width:I
      43: ifgt          55
      46: aload         4
      48: aload_3
      49: getfield      #269                // Field android/view/ViewGroup$LayoutParams.height:I
      52: putfield      #272                // Field android/widget/LinearLayout$LayoutParams.width:I
      55: aload_0
      56: iload_1
      57: iload_2
      58: invokespecial #274                // Method android/widget/LinearLayout.onMeasure:(II)V
      61: return

  public void setCheckable(boolean);
    Code:
       0: iload_1
       1: ifne          19
       4: aload_0
       5: getfield      #123                // Field c:Landroid/widget/RadioButton;
       8: ifnonnull     19
      11: aload_0
      12: getfield      #133                // Field e:Landroid/widget/CheckBox;
      15: ifnonnull     19
      18: return
      19: aload_0
      20: getfield      #150                // Field a:Landroid/support/v7/view/menu/j;
      23: invokevirtual #276                // Method android/support/v7/view/menu/j.g:()Z
      26: ifeq          54
      29: aload_0
      30: getfield      #123                // Field c:Landroid/widget/RadioButton;
      33: ifnonnull     40
      36: aload_0
      37: invokespecial #278                // Method c:()V
      40: aload_0
      41: getfield      #123                // Field c:Landroid/widget/RadioButton;
      44: astore_3
      45: aload_0
      46: getfield      #133                // Field e:Landroid/widget/CheckBox;
      49: astore        4
      51: goto          76
      54: aload_0
      55: getfield      #133                // Field e:Landroid/widget/CheckBox;
      58: ifnonnull     65
      61: aload_0
      62: invokespecial #280                // Method d:()V
      65: aload_0
      66: getfield      #133                // Field e:Landroid/widget/CheckBox;
      69: astore_3
      70: aload_0
      71: getfield      #123                // Field c:Landroid/widget/RadioButton;
      74: astore        4
      76: iload_1
      77: ifeq          139
      80: aload_3
      81: aload_0
      82: getfield      #150                // Field a:Landroid/support/v7/view/menu/j;
      85: invokevirtual #283                // Method android/support/v7/view/menu/j.isChecked:()Z
      88: invokevirtual #288                // Method android/widget/CompoundButton.setChecked:(Z)V
      91: iload_1
      92: ifeq          100
      95: iconst_0
      96: istore_2
      97: goto          103
     100: bipush        8
     102: istore_2
     103: aload_3
     104: invokevirtual #289                // Method android/widget/CompoundButton.getVisibility:()I
     107: iload_2
     108: if_icmpeq     116
     111: aload_3
     112: iload_2
     113: invokevirtual #290                // Method android/widget/CompoundButton.setVisibility:(I)V
     116: aload         4
     118: ifnull        171
     121: aload         4
     123: invokevirtual #289                // Method android/widget/CompoundButton.getVisibility:()I
     126: bipush        8
     128: if_icmpeq     171
     131: aload         4
     133: bipush        8
     135: invokevirtual #290                // Method android/widget/CompoundButton.setVisibility:(I)V
     138: return
     139: aload_0
     140: getfield      #133                // Field e:Landroid/widget/CheckBox;
     143: ifnull        155
     146: aload_0
     147: getfield      #133                // Field e:Landroid/widget/CheckBox;
     150: bipush        8
     152: invokevirtual #291                // Method android/widget/CheckBox.setVisibility:(I)V
     155: aload_0
     156: getfield      #123                // Field c:Landroid/widget/RadioButton;
     159: ifnull        171
     162: aload_0
     163: getfield      #123                // Field c:Landroid/widget/RadioButton;
     166: bipush        8
     168: invokevirtual #292                // Method android/widget/RadioButton.setVisibility:(I)V
     171: return

  public void setChecked(boolean);
    Code:
       0: aload_0
       1: getfield      #150                // Field a:Landroid/support/v7/view/menu/j;
       4: invokevirtual #276                // Method android/support/v7/view/menu/j.g:()Z
       7: ifeq          29
      10: aload_0
      11: getfield      #123                // Field c:Landroid/widget/RadioButton;
      14: ifnonnull     21
      17: aload_0
      18: invokespecial #278                // Method c:()V
      21: aload_0
      22: getfield      #123                // Field c:Landroid/widget/RadioButton;
      25: astore_2
      26: goto          45
      29: aload_0
      30: getfield      #133                // Field e:Landroid/widget/CheckBox;
      33: ifnonnull     40
      36: aload_0
      37: invokespecial #280                // Method d:()V
      40: aload_0
      41: getfield      #133                // Field e:Landroid/widget/CheckBox;
      44: astore_2
      45: aload_2
      46: iload_1
      47: invokevirtual #288                // Method android/widget/CompoundButton.setChecked:(Z)V
      50: return

  public void setForceShowIcon(boolean);
    Code:
       0: aload_0
       1: iload_1
       2: putfield      #295                // Field o:Z
       5: aload_0
       6: iload_1
       7: putfield      #83                 // Field k:Z
      10: return

  public void setIcon(android.graphics.drawable.Drawable);
    Code:
       0: aload_0
       1: getfield      #150                // Field a:Landroid/support/v7/view/menu/j;
       4: invokevirtual #297                // Method android/support/v7/view/menu/j.i:()Z
       7: ifne          25
      10: aload_0
      11: getfield      #295                // Field o:Z
      14: ifeq          20
      17: goto          25
      20: iconst_0
      21: istore_2
      22: goto          27
      25: iconst_1
      26: istore_2
      27: iload_2
      28: ifne          39
      31: aload_0
      32: getfield      #83                 // Field k:Z
      35: ifne          39
      38: return
      39: aload_0
      40: getfield      #112                // Field b:Landroid/widget/ImageView;
      43: ifnonnull     58
      46: aload_1
      47: ifnonnull     58
      50: aload_0
      51: getfield      #83                 // Field k:Z
      54: ifne          58
      57: return
      58: aload_0
      59: getfield      #112                // Field b:Landroid/widget/ImageView;
      62: ifnonnull     69
      65: aload_0
      66: invokespecial #298                // Method a:()V
      69: aload_1
      70: ifnonnull     93
      73: aload_0
      74: getfield      #83                 // Field k:Z
      77: ifeq          83
      80: goto          93
      83: aload_0
      84: getfield      #112                // Field b:Landroid/widget/ImageView;
      87: bipush        8
      89: invokevirtual #147                // Method android/widget/ImageView.setVisibility:(I)V
      92: return
      93: aload_0
      94: getfield      #112                // Field b:Landroid/widget/ImageView;
      97: astore_3
      98: iload_2
      99: ifeq          105
     102: goto          107
     105: aconst_null
     106: astore_1
     107: aload_3
     108: aload_1
     109: invokevirtual #255                // Method android/widget/ImageView.setImageDrawable:(Landroid/graphics/drawable/Drawable;)V
     112: aload_0
     113: getfield      #112                // Field b:Landroid/widget/ImageView;
     116: invokevirtual #299                // Method android/widget/ImageView.getVisibility:()I
     119: ifeq          130
     122: aload_0
     123: getfield      #112                // Field b:Landroid/widget/ImageView;
     126: iconst_0
     127: invokevirtual #147                // Method android/widget/ImageView.setVisibility:(I)V
     130: return

  public void setTitle(java.lang.CharSequence);
    Code:
       0: aload_1
       1: ifnull        35
       4: aload_0
       5: getfield      #242                // Field d:Landroid/widget/TextView;
       8: aload_1
       9: invokevirtual #216                // Method android/widget/TextView.setText:(Ljava/lang/CharSequence;)V
      12: aload_0
      13: getfield      #242                // Field d:Landroid/widget/TextView;
      16: invokevirtual #220                // Method android/widget/TextView.getVisibility:()I
      19: ifeq          60
      22: aload_0
      23: getfield      #242                // Field d:Landroid/widget/TextView;
      26: astore_1
      27: iconst_0
      28: istore_2
      29: aload_1
      30: iload_2
      31: invokevirtual #221                // Method android/widget/TextView.setVisibility:(I)V
      34: return
      35: aload_0
      36: getfield      #242                // Field d:Landroid/widget/TextView;
      39: invokevirtual #220                // Method android/widget/TextView.getVisibility:()I
      42: istore_3
      43: bipush        8
      45: istore_2
      46: iload_3
      47: bipush        8
      49: if_icmpeq     60
      52: aload_0
      53: getfield      #242                // Field d:Landroid/widget/TextView;
      56: astore_1
      57: goto          29
      60: return
}
