class android.support.v7.view.menu.n$1 implements android.widget.PopupWindow$OnDismissListener {
  final android.support.v7.view.menu.n a;

  android.support.v7.view.menu.n$1(android.support.v7.view.menu.n);
    Code:
       0: aload_0
       1: aload_1
       2: putfield      #14                 // Field a:Landroid/support/v7/view/menu/n;
       5: aload_0
       6: invokespecial #17                 // Method java/lang/Object."<init>":()V
       9: return

  public void onDismiss();
    Code:
       0: aload_0
       1: getfield      #14                 // Field a:Landroid/support/v7/view/menu/n;
       4: invokevirtual #22                 // Method android/support/v7/view/menu/n.e:()V
       7: return
}
