class android.support.v4.widget.c$a extends android.support.v4.widget.c$c {
  android.support.v4.widget.c$a();
    Code:
       0: aload_0
       1: invokespecial #11                 // Method android/support/v4/widget/c$c."<init>":()V
       4: return

  public void a(android.widget.CompoundButton, android.content.res.ColorStateList);
    Code:
       0: aload_1
       1: aload_2
       2: invokevirtual #19                 // Method android/widget/CompoundButton.setButtonTintList:(Landroid/content/res/ColorStateList;)V
       5: return

  public void a(android.widget.CompoundButton, android.graphics.PorterDuff$Mode);
    Code:
       0: aload_1
       1: aload_2
       2: invokevirtual #24                 // Method android/widget/CompoundButton.setButtonTintMode:(Landroid/graphics/PorterDuff$Mode;)V
       5: return
}
