class android.support.v4.widget.c$c {
  android.support.v4.widget.c$c();
    Code:
       0: aload_0
       1: invokespecial #15                 // Method java/lang/Object."<init>":()V
       4: return

  public android.graphics.drawable.Drawable a(android.widget.CompoundButton);
    Code:
       0: getstatic     #23                 // Field b:Z
       3: ifne          40
       6: ldc           #25                 // class android/widget/CompoundButton
       8: ldc           #27                 // String mButtonDrawable
      10: invokevirtual #33                 // Method java/lang/Class.getDeclaredField:(Ljava/lang/String;)Ljava/lang/reflect/Field;
      13: putstatic     #35                 // Field a:Ljava/lang/reflect/Field;
      16: getstatic     #35                 // Field a:Ljava/lang/reflect/Field;
      19: iconst_1
      20: invokevirtual #41                 // Method java/lang/reflect/Field.setAccessible:(Z)V
      23: goto          36
      26: astore_2
      27: ldc           #43                 // String CompoundButtonCompat
      29: ldc           #45                 // String Failed to retrieve mButtonDrawable field
      31: aload_2
      32: invokestatic  #51                 // Method android/util/Log.i:(Ljava/lang/String;Ljava/lang/String;Ljava/lang/Throwable;)I
      35: pop
      36: iconst_1
      37: putstatic     #23                 // Field b:Z
      40: getstatic     #35                 // Field a:Ljava/lang/reflect/Field;
      43: ifnull        73
      46: getstatic     #35                 // Field a:Ljava/lang/reflect/Field;
      49: aload_1
      50: invokevirtual #55                 // Method java/lang/reflect/Field.get:(Ljava/lang/Object;)Ljava/lang/Object;
      53: checkcast     #57                 // class android/graphics/drawable/Drawable
      56: astore_1
      57: aload_1
      58: areturn
      59: astore_1
      60: ldc           #43                 // String CompoundButtonCompat
      62: ldc           #59                 // String Failed to get button drawable via reflection
      64: aload_1
      65: invokestatic  #51                 // Method android/util/Log.i:(Ljava/lang/String;Ljava/lang/String;Ljava/lang/Throwable;)I
      68: pop
      69: aconst_null
      70: putstatic     #35                 // Field a:Ljava/lang/reflect/Field;
      73: aconst_null
      74: areturn
    Exception table:
       from    to  target type
           6    23    26   Class java/lang/NoSuchFieldException
          46    57    59   Class java/lang/IllegalAccessException

  public void a(android.widget.CompoundButton, android.content.res.ColorStateList);
    Code:
       0: aload_1
       1: instanceof    #62                 // class android/support/v4/widget/n
       4: ifeq          17
       7: aload_1
       8: checkcast     #62                 // class android/support/v4/widget/n
      11: aload_2
      12: invokeinterface #66,  2           // InterfaceMethod android/support/v4/widget/n.setSupportButtonTintList:(Landroid/content/res/ColorStateList;)V
      17: return

  public void a(android.widget.CompoundButton, android.graphics.PorterDuff$Mode);
    Code:
       0: aload_1
       1: instanceof    #62                 // class android/support/v4/widget/n
       4: ifeq          17
       7: aload_1
       8: checkcast     #62                 // class android/support/v4/widget/n
      11: aload_2
      12: invokeinterface #71,  2           // InterfaceMethod android/support/v4/widget/n.setSupportButtonTintMode:(Landroid/graphics/PorterDuff$Mode;)V
      17: return
}
