public class android.support.v4.widget.DrawerLayout$e extends android.support.v4.view.a {
  public static final android.os.Parcelable$Creator<android.support.v4.widget.DrawerLayout$e> CREATOR;

  int a;

  int b;

  int c;

  int e;

  int f;

  static {};
    Code:
       0: new           #9                  // class android/support/v4/widget/DrawerLayout$e$1
       3: dup
       4: invokespecial #22                 // Method android/support/v4/widget/DrawerLayout$e$1."<init>":()V
       7: putstatic     #24                 // Field CREATOR:Landroid/os/Parcelable$Creator;
      10: return

  public android.support.v4.widget.DrawerLayout$e(android.os.Parcel, java.lang.ClassLoader);
    Code:
       0: aload_0
       1: aload_1
       2: aload_2
       3: invokespecial #28                 // Method android/support/v4/view/a."<init>":(Landroid/os/Parcel;Ljava/lang/ClassLoader;)V
       6: aload_0
       7: iconst_0
       8: putfield      #30                 // Field a:I
      11: aload_0
      12: aload_1
      13: invokevirtual #36                 // Method android/os/Parcel.readInt:()I
      16: putfield      #30                 // Field a:I
      19: aload_0
      20: aload_1
      21: invokevirtual #36                 // Method android/os/Parcel.readInt:()I
      24: putfield      #38                 // Field b:I
      27: aload_0
      28: aload_1
      29: invokevirtual #36                 // Method android/os/Parcel.readInt:()I
      32: putfield      #40                 // Field c:I
      35: aload_0
      36: aload_1
      37: invokevirtual #36                 // Method android/os/Parcel.readInt:()I
      40: putfield      #42                 // Field e:I
      43: aload_0
      44: aload_1
      45: invokevirtual #36                 // Method android/os/Parcel.readInt:()I
      48: putfield      #44                 // Field f:I
      51: return

  public android.support.v4.widget.DrawerLayout$e(android.os.Parcelable);
    Code:
       0: aload_0
       1: aload_1
       2: invokespecial #47                 // Method android/support/v4/view/a."<init>":(Landroid/os/Parcelable;)V
       5: aload_0
       6: iconst_0
       7: putfield      #30                 // Field a:I
      10: return

  public void writeToParcel(android.os.Parcel, int);
    Code:
       0: aload_0
       1: aload_1
       2: iload_2
       3: invokespecial #51                 // Method android/support/v4/view/a.writeToParcel:(Landroid/os/Parcel;I)V
       6: aload_1
       7: aload_0
       8: getfield      #30                 // Field a:I
      11: invokevirtual #55                 // Method android/os/Parcel.writeInt:(I)V
      14: aload_1
      15: aload_0
      16: getfield      #38                 // Field b:I
      19: invokevirtual #55                 // Method android/os/Parcel.writeInt:(I)V
      22: aload_1
      23: aload_0
      24: getfield      #40                 // Field c:I
      27: invokevirtual #55                 // Method android/os/Parcel.writeInt:(I)V
      30: aload_1
      31: aload_0
      32: getfield      #42                 // Field e:I
      35: invokevirtual #55                 // Method android/os/Parcel.writeInt:(I)V
      38: aload_1
      39: aload_0
      40: getfield      #44                 // Field f:I
      43: invokevirtual #55                 // Method android/os/Parcel.writeInt:(I)V
      46: return
}
