class android.support.v4.widget.DrawerLayout$f$1 implements java.lang.Runnable {
  final android.support.v4.widget.DrawerLayout$f a;

  android.support.v4.widget.DrawerLayout$f$1(android.support.v4.widget.DrawerLayout$f);
    Code:
       0: aload_0
       1: aload_1
       2: putfield      #17                 // Field a:Landroid/support/v4/widget/DrawerLayout$f;
       5: aload_0
       6: invokespecial #20                 // Method java/lang/Object."<init>":()V
       9: return

  public void run();
    Code:
       0: aload_0
       1: getfield      #17                 // Field a:Landroid/support/v4/widget/DrawerLayout$f;
       4: invokevirtual #25                 // Method android/support/v4/widget/DrawerLayout$f.b:()V
       7: return
}
