class android.support.v4.widget.k$a extends android.support.v4.widget.k$d {
  android.support.v4.widget.k$a();
    Code:
       0: aload_0
       1: invokespecial #11                 // Method android/support/v4/widget/k$d."<init>":()V
       4: return

  public void a(android.widget.PopupWindow, android.view.View, int, int, int);
    Code:
       0: aload_1
       1: aload_2
       2: iload_3
       3: iload         4
       5: iload         5
       7: invokevirtual #19                 // Method android/widget/PopupWindow.showAsDropDown:(Landroid/view/View;III)V
      10: return
}
