class android.support.v4.widget.k$c extends android.support.v4.widget.k$b {
  android.support.v4.widget.k$c();
    Code:
       0: aload_0
       1: invokespecial #11                 // Method android/support/v4/widget/k$b."<init>":()V
       4: return

  public void a(android.widget.PopupWindow, int);
    Code:
       0: aload_1
       1: iload_2
       2: invokevirtual #20                 // Method android/widget/PopupWindow.setWindowLayoutType:(I)V
       5: return

  public void a(android.widget.PopupWindow, boolean);
    Code:
       0: aload_1
       1: iload_2
       2: invokevirtual #25                 // Method android/widget/PopupWindow.setOverlapAnchor:(Z)V
       5: return
}
