class android.support.v4.widget.m$c extends android.support.v4.widget.m$b {
  android.support.v4.widget.m$c();
    Code:
       0: aload_0
       1: invokespecial #11                 // Method android/support/v4/widget/m$b."<init>":()V
       4: return

  public void a(android.widget.TextView, android.graphics.drawable.Drawable, android.graphics.drawable.Drawable, android.graphics.drawable.Drawable, android.graphics.drawable.Drawable);
    Code:
       0: aload_1
       1: aload_2
       2: aload_3
       3: aload         4
       5: aload         5
       7: invokevirtual #20                 // Method android/widget/TextView.setCompoundDrawablesRelative:(Landroid/graphics/drawable/Drawable;Landroid/graphics/drawable/Drawable;Landroid/graphics/drawable/Drawable;Landroid/graphics/drawable/Drawable;)V
      10: return
}
