public abstract class android.support.v4.widget.p$a {
  public android.support.v4.widget.p$a();
    Code:
       0: aload_0
       1: invokespecial #11                 // Method java/lang/Object."<init>":()V
       4: return

  public int a(android.view.View);
    Code:
       0: iconst_0
       1: ireturn

  public int a(android.view.View, int, int);
    Code:
       0: iconst_0
       1: ireturn

  public void a(int);
    Code:
       0: return

  public void a(int, int);
    Code:
       0: return

  public void a(android.view.View, float, float);
    Code:
       0: return

  public void a(android.view.View, int, int, int, int);
    Code:
       0: return

  public abstract boolean a(android.view.View, int);

  public int b(android.view.View);
    Code:
       0: iconst_0
       1: ireturn

  public int b(android.view.View, int, int);
    Code:
       0: iconst_0
       1: ireturn

  public void b(int, int);
    Code:
       0: return

  public void b(android.view.View, int);
    Code:
       0: return

  public boolean b(int);
    Code:
       0: iconst_0
       1: ireturn

  public int c(int);
    Code:
       0: iload_1
       1: ireturn
}
