final class com.google.a.a.a.a.a.a$b extends com.google.a.a.a.a.a.a$a {
  com.google.a.a.a.a.a.a$b();
    Code:
       0: aload_0
       1: invokespecial #11                 // Method com/google/a/a/a/a/a/a$a."<init>":()V
       4: return

  public void a(java.lang.Throwable);
    Code:
       0: aload_1
       1: invokevirtual #19                 // Method java/lang/Throwable.printStackTrace:()V
       4: return

  public void a(java.lang.Throwable, java.io.PrintWriter);
    Code:
       0: aload_1
       1: aload_2
       2: invokevirtual #23                 // Method java/lang/Throwable.printStackTrace:(Ljava/io/PrintWriter;)V
       5: return

  public void a(java.lang.Throwable, java.lang.Throwable);
    Code:
       0: return
}
