public class ryey.easer.plugins.operation.media_control.e extends ryey.easer.plugins.c<ryey.easer.plugins.operation.media_control.b> {
  public ryey.easer.plugins.operation.media_control.e();
    Code:
       0: aload_0
       1: invokespecial #17                 // Method ryey/easer/plugins/c."<init>":()V
       4: return

  public ryey.easer.commons.local_plugin.f a();
    Code:
       0: aload_0
       1: invokevirtual #22                 // Method b:()Lryey/easer/plugins/operation/media_control/b;
       4: areturn

  protected void a(ryey.easer.plugins.operation.media_control.b);
    Code:
       0: aload_1
       1: getfield      #28                 // Field ryey/easer/plugins/operation/media_control/b.a:Lryey/easer/plugins/operation/media_control/b$a;
       4: astore_1
       5: getstatic     #31                 // Field ryey/easer/plugins/operation/media_control/e$1.a:[I
       8: aload_1
       9: invokevirtual #37                 // Method ryey/easer/plugins/operation/media_control/b$a.ordinal:()I
      12: iaload
      13: tableswitch   { // 1 to 5
                     1: 81
                     2: 73
                     3: 65
                     4: 57
                     5: 49
               default: 48
          }
      48: return
      49: aload_0
      50: getfield      #39                 // Field e:Landroid/widget/RadioButton;
      53: astore_1
      54: goto          86
      57: aload_0
      58: getfield      #41                 // Field d:Landroid/widget/RadioButton;
      61: astore_1
      62: goto          86
      65: aload_0
      66: getfield      #43                 // Field c:Landroid/widget/RadioButton;
      69: astore_1
      70: goto          86
      73: aload_0
      74: getfield      #45                 // Field b:Landroid/widget/RadioButton;
      77: astore_1
      78: goto          86
      81: aload_0
      82: getfield      #47                 // Field a:Landroid/widget/RadioButton;
      85: astore_1
      86: aload_1
      87: iconst_1
      88: invokevirtual #53                 // Method android/widget/RadioButton.setChecked:(Z)V
      91: return

  public ryey.easer.plugins.operation.media_control.b b();
    Code:
       0: aload_0
       1: getfield      #47                 // Field a:Landroid/widget/RadioButton;
       4: invokevirtual #57                 // Method android/widget/RadioButton.isChecked:()Z
       7: ifeq          17
      10: getstatic     #58                 // Field ryey/easer/plugins/operation/media_control/b$a.a:Lryey/easer/plugins/operation/media_control/b$a;
      13: astore_1
      14: goto          87
      17: aload_0
      18: getfield      #45                 // Field b:Landroid/widget/RadioButton;
      21: invokevirtual #57                 // Method android/widget/RadioButton.isChecked:()Z
      24: ifeq          34
      27: getstatic     #60                 // Field ryey/easer/plugins/operation/media_control/b$a.b:Lryey/easer/plugins/operation/media_control/b$a;
      30: astore_1
      31: goto          87
      34: aload_0
      35: getfield      #43                 // Field c:Landroid/widget/RadioButton;
      38: invokevirtual #57                 // Method android/widget/RadioButton.isChecked:()Z
      41: ifeq          51
      44: getstatic     #62                 // Field ryey/easer/plugins/operation/media_control/b$a.c:Lryey/easer/plugins/operation/media_control/b$a;
      47: astore_1
      48: goto          87
      51: aload_0
      52: getfield      #41                 // Field d:Landroid/widget/RadioButton;
      55: invokevirtual #57                 // Method android/widget/RadioButton.isChecked:()Z
      58: ifeq          68
      61: getstatic     #64                 // Field ryey/easer/plugins/operation/media_control/b$a.d:Lryey/easer/plugins/operation/media_control/b$a;
      64: astore_1
      65: goto          87
      68: aload_0
      69: getfield      #39                 // Field e:Landroid/widget/RadioButton;
      72: invokevirtual #57                 // Method android/widget/RadioButton.isChecked:()Z
      75: ifeq          85
      78: getstatic     #66                 // Field ryey/easer/plugins/operation/media_control/b$a.e:Lryey/easer/plugins/operation/media_control/b$a;
      81: astore_1
      82: goto          87
      85: aconst_null
      86: astore_1
      87: aload_1
      88: ifnonnull     99
      91: new           #68                 // class ryey/easer/commons/local_plugin/c
      94: dup
      95: invokespecial #69                 // Method ryey/easer/commons/local_plugin/c."<init>":()V
      98: athrow
      99: new           #25                 // class ryey/easer/plugins/operation/media_control/b
     102: dup
     103: aload_1
     104: invokespecial #72                 // Method ryey/easer/plugins/operation/media_control/b."<init>":(Lryey/easer/plugins/operation/media_control/b$a;)V
     107: areturn

  protected void b(ryey.easer.commons.local_plugin.f);
    Code:
       0: aload_0
       1: aload_1
       2: checkcast     #25                 // class ryey/easer/plugins/operation/media_control/b
       5: invokevirtual #75                 // Method a:(Lryey/easer/plugins/operation/media_control/b;)V
       8: return

  public android.view.View onCreateView(android.view.LayoutInflater, android.view.ViewGroup, android.os.Bundle);
    Code:
       0: aload_1
       1: ldc           #78                 // int 2131427449
       3: aload_2
       4: iconst_0
       5: invokevirtual #84                 // Method android/view/LayoutInflater.inflate:(ILandroid/view/ViewGroup;Z)Landroid/view/View;
       8: astore_1
       9: aload_0
      10: aload_1
      11: ldc           #85                 // int 2131296542
      13: invokevirtual #91                 // Method android/view/View.findViewById:(I)Landroid/view/View;
      16: checkcast     #49                 // class android/widget/RadioButton
      19: putfield      #47                 // Field a:Landroid/widget/RadioButton;
      22: aload_0
      23: aload_1
      24: ldc           #92                 // int 2131296541
      26: invokevirtual #91                 // Method android/view/View.findViewById:(I)Landroid/view/View;
      29: checkcast     #49                 // class android/widget/RadioButton
      32: putfield      #45                 // Field b:Landroid/widget/RadioButton;
      35: aload_0
      36: aload_1
      37: ldc           #93                 // int 2131296540
      39: invokevirtual #91                 // Method android/view/View.findViewById:(I)Landroid/view/View;
      42: checkcast     #49                 // class android/widget/RadioButton
      45: putfield      #43                 // Field c:Landroid/widget/RadioButton;
      48: aload_0
      49: aload_1
      50: ldc           #94                 // int 2131296546
      52: invokevirtual #91                 // Method android/view/View.findViewById:(I)Landroid/view/View;
      55: checkcast     #49                 // class android/widget/RadioButton
      58: putfield      #41                 // Field d:Landroid/widget/RadioButton;
      61: aload_0
      62: aload_1
      63: ldc           #95                 // int 2131296536
      65: invokevirtual #91                 // Method android/view/View.findViewById:(I)Landroid/view/View;
      68: checkcast     #49                 // class android/widget/RadioButton
      71: putfield      #39                 // Field e:Landroid/widget/RadioButton;
      74: aload_1
      75: areturn
}
