public class de.blox.graphview.b.a implements de.blox.graphview.a {
  public de.blox.graphview.b.a();
    Code:
       0: aload_0
       1: new           #26                 // class de/blox/graphview/b/b$a
       4: dup
       5: invokespecial #28                 // Method de/blox/graphview/b/b$a."<init>":()V
       8: invokevirtual #31                 // Method de/blox/graphview/b/b$a.a:()Lde/blox/graphview/b/b;
      11: invokespecial #34                 // Method "<init>":(Lde/blox/graphview/b/b;)V
      14: return

  public de.blox.graphview.b.a(de.blox.graphview.b.b);
    Code:
       0: aload_0
       1: invokespecial #36                 // Method java/lang/Object."<init>":()V
       4: aload_0
       5: new           #38                 // class java/util/HashMap
       8: dup
       9: invokespecial #39                 // Method java/util/HashMap."<init>":()V
      12: putfield      #41                 // Field b:Ljava/util/Map;
      15: aload_0
      16: ldc           #42                 // int 2147483647
      18: putfield      #44                 // Field d:I
      21: aload_0
      22: ldc           #42                 // int 2147483647
      24: putfield      #46                 // Field e:I
      27: aload_0
      28: ldc           #47                 // int -2147483648
      30: putfield      #49                 // Field f:I
      33: aload_0
      34: ldc           #47                 // int -2147483648
      36: putfield      #51                 // Field g:I
      39: aload_0
      40: new           #53                 // class de/blox/graphview/k
      43: dup
      44: iconst_0
      45: iconst_0
      46: invokespecial #56                 // Method de/blox/graphview/k."<init>":(II)V
      49: putfield      #58                 // Field h:Lde/blox/graphview/k;
      52: aload_0
      53: aload_1
      54: putfield      #60                 // Field a:Lde/blox/graphview/b/b;
      57: aload_0
      58: new           #62                 // class de/blox/graphview/b/d
      61: dup
      62: aload_1
      63: invokespecial #63                 // Method de/blox/graphview/b/d."<init>":(Lde/blox/graphview/b/b;)V
      66: putfield      #65                 // Field c:Lde/blox/graphview/a/a;
      69: return

  static int a(int, int);
    Code:
       0: iload_0
       1: iload_1
       2: invokestatic  #68                 // Method b:(II)I
       5: ireturn

  static de.blox.graphview.b.c a(de.blox.graphview.b.a, de.blox.graphview.h);
    Code:
       0: aload_0
       1: aload_1
       2: invokespecial #72                 // Method b:(Lde/blox/graphview/h;)Lde/blox/graphview/b/c;
       5: areturn

  public de.blox.graphview.k a();
    Code:
       0: aload_0
       1: getfield      #58                 // Field h:Lde/blox/graphview/k;
       4: areturn

  public void a(android.graphics.Canvas, de.blox.graphview.e, android.graphics.Paint);
    Code:
       0: aload_0
       1: getfield      #65                 // Field c:Lde/blox/graphview/a/a;
       4: aload_1
       5: aload_2
       6: aload_3
       7: invokeinterface #334,  4          // InterfaceMethod de/blox/graphview/a/a.a:(Landroid/graphics/Canvas;Lde/blox/graphview/e;Landroid/graphics/Paint;)V
      12: return

  public void a(de.blox.graphview.e);
    Code:
       0: aload_0
       1: getfield      #41                 // Field b:Ljava/util/Map;
       4: invokeinterface #337,  1          // InterfaceMethod java/util/Map.clear:()V
       9: aload_1
      10: iconst_0
      11: invokevirtual #340                // Method de/blox/graphview/e.a:(I)Lde/blox/graphview/h;
      14: astore_2
      15: aload_0
      16: aload_1
      17: aload_2
      18: iconst_0
      19: iconst_0
      20: invokespecial #255                // Method a:(Lde/blox/graphview/e;Lde/blox/graphview/h;II)V
      23: aload_0
      24: aload_1
      25: aload_2
      26: dconst_0
      27: invokespecial #240                // Method a:(Lde/blox/graphview/e;Lde/blox/graphview/h;D)V
      30: aload_0
      31: aload_1
      32: invokespecial #342                // Method c:(Lde/blox/graphview/e;)V
      35: aload_0
      36: aload_1
      37: invokespecial #344                // Method b:(Lde/blox/graphview/e;)V
      40: return
}
