public class de.blox.graphview.b.b {
  de.blox.graphview.b.b(de.blox.graphview.b.b$a, de.blox.graphview.b.b$1);
    Code:
       0: aload_0
       1: aload_1
       2: invokespecial #39                 // Method "<init>":(Lde/blox/graphview/b/b$a;)V
       5: return

  public int a();
    Code:
       0: aload_0
       1: getfield      #23                 // Field a:I
       4: ireturn

  public int b();
    Code:
       0: aload_0
       1: getfield      #27                 // Field b:I
       4: ireturn

  public int c();
    Code:
       0: aload_0
       1: getfield      #31                 // Field c:I
       4: ireturn

  public int d();
    Code:
       0: aload_0
       1: getfield      #35                 // Field d:I
       4: ireturn
}
