class de.blox.graphview.b.c {
  de.blox.graphview.b.c();
    Code:
       0: aload_0
       1: invokespecial #19                 // Method java/lang/Object."<init>":()V
       4: return

  de.blox.graphview.h a();
    Code:
       0: aload_0
       1: getfield      #23                 // Field a:Lde/blox/graphview/h;
       4: areturn

  void a(double);
    Code:
       0: aload_0
       1: dload_1
       2: putfield      #26                 // Field e:D
       5: return

  void a(int);
    Code:
       0: aload_0
       1: iload_1
       2: putfield      #29                 // Field c:I
       5: return

  void a(de.blox.graphview.h);
    Code:
       0: aload_0
       1: aload_1
       2: putfield      #23                 // Field a:Lde/blox/graphview/h;
       5: return

  de.blox.graphview.h b();
    Code:
       0: aload_0
       1: getfield      #32                 // Field b:Lde/blox/graphview/h;
       4: areturn

  void b(double);
    Code:
       0: aload_0
       1: dload_1
       2: putfield      #34                 // Field f:D
       5: return

  void b(int);
    Code:
       0: aload_0
       1: iload_1
       2: putfield      #36                 // Field d:I
       5: return

  void b(de.blox.graphview.h);
    Code:
       0: aload_0
       1: aload_1
       2: putfield      #32                 // Field b:Lde/blox/graphview/h;
       5: return

  int c();
    Code:
       0: aload_0
       1: getfield      #29                 // Field c:I
       4: ireturn

  void c(double);
    Code:
       0: aload_0
       1: dload_1
       2: putfield      #39                 // Field g:D
       5: return

  int d();
    Code:
       0: aload_0
       1: getfield      #36                 // Field d:I
       4: ireturn

  void d(double);
    Code:
       0: aload_0
       1: dload_1
       2: putfield      #41                 // Field h:D
       5: return

  double e();
    Code:
       0: aload_0
       1: getfield      #26                 // Field e:D
       4: dreturn

  double f();
    Code:
       0: aload_0
       1: getfield      #34                 // Field f:D
       4: dreturn

  double g();
    Code:
       0: aload_0
       1: getfield      #39                 // Field g:D
       4: dreturn

  double h();
    Code:
       0: aload_0
       1: getfield      #41                 // Field h:D
       4: dreturn
}
