class de.blox.graphview.b.d implements de.blox.graphview.a.a {
  de.blox.graphview.b.d(de.blox.graphview.b.b);
    Code:
       0: aload_0
       1: invokespecial #15                 // Method java/lang/Object."<init>":()V
       4: aload_0
       5: new           #17                 // class android/graphics/Path
       8: dup
       9: invokespecial #18                 // Method android/graphics/Path."<init>":()V
      12: putfield      #20                 // Field b:Landroid/graphics/Path;
      15: aload_0
      16: aload_1
      17: putfield      #22                 // Field a:Lde/blox/graphview/b/b;
      20: return

  public void a(android.graphics.Canvas, de.blox.graphview.e, android.graphics.Paint);
    Code:
       0: aload_2
       1: invokevirtual #29                 // Method de/blox/graphview/e.b:()Ljava/util/List;
       4: invokeinterface #35,  1           // InterfaceMethod java/util/List.iterator:()Ljava/util/Iterator;
       9: astore        8
      11: aload         8
      13: invokeinterface #41,  1           // InterfaceMethod java/util/Iterator.hasNext:()Z
      18: ifeq          825
      21: aload         8
      23: invokeinterface #45,  1           // InterfaceMethod java/util/Iterator.next:()Ljava/lang/Object;
      28: checkcast     #47                 // class de/blox/graphview/h
      31: astore        9
      33: aload_2
      34: aload         9
      36: invokevirtual #51                 // Method de/blox/graphview/e.c:(Lde/blox/graphview/h;)Ljava/util/List;
      39: invokeinterface #35,  1           // InterfaceMethod java/util/List.iterator:()Ljava/util/Iterator;
      44: astore        10
      46: aload         10
      48: invokeinterface #41,  1           // InterfaceMethod java/util/Iterator.hasNext:()Z
      53: ifeq          11
      56: aload         10
      58: invokeinterface #45,  1           // InterfaceMethod java/util/Iterator.next:()Ljava/lang/Object;
      63: checkcast     #47                 // class de/blox/graphview/h
      66: astore        7
      68: aload_0
      69: getfield      #20                 // Field b:Landroid/graphics/Path;
      72: invokevirtual #54                 // Method android/graphics/Path.reset:()V
      75: aload_0
      76: getfield      #22                 // Field a:Lde/blox/graphview/b/b;
      79: invokevirtual #60                 // Method de/blox/graphview/b/b.d:()I
      82: tableswitch   { // 1 to 4
                     1: 627
                     2: 459
                     3: 283
                     4: 115
               default: 112
          }
     112: goto          813
     115: aload_0
     116: getfield      #20                 // Field b:Landroid/graphics/Path;
     119: aload         7
     121: invokevirtual #63                 // Method de/blox/graphview/h.b:()F
     124: aload         7
     126: invokevirtual #66                 // Method de/blox/graphview/h.e:()I
     129: i2f
     130: fadd
     131: aload         7
     133: invokevirtual #68                 // Method de/blox/graphview/h.c:()F
     136: aload         7
     138: invokevirtual #71                 // Method de/blox/graphview/h.f:()I
     141: iconst_2
     142: idiv
     143: i2f
     144: fadd
     145: invokevirtual #75                 // Method android/graphics/Path.moveTo:(FF)V
     148: aload_0
     149: getfield      #20                 // Field b:Landroid/graphics/Path;
     152: aload         7
     154: invokevirtual #63                 // Method de/blox/graphview/h.b:()F
     157: aload         7
     159: invokevirtual #66                 // Method de/blox/graphview/h.e:()I
     162: i2f
     163: fadd
     164: aload_0
     165: getfield      #22                 // Field a:Lde/blox/graphview/b/b;
     168: invokevirtual #77                 // Method de/blox/graphview/b/b.b:()I
     171: iconst_2
     172: idiv
     173: i2f
     174: fadd
     175: aload         7
     177: invokevirtual #68                 // Method de/blox/graphview/h.c:()F
     180: aload         7
     182: invokevirtual #71                 // Method de/blox/graphview/h.f:()I
     185: iconst_2
     186: idiv
     187: i2f
     188: fadd
     189: invokevirtual #80                 // Method android/graphics/Path.lineTo:(FF)V
     192: aload_0
     193: getfield      #20                 // Field b:Landroid/graphics/Path;
     196: aload         7
     198: invokevirtual #63                 // Method de/blox/graphview/h.b:()F
     201: aload         7
     203: invokevirtual #66                 // Method de/blox/graphview/h.e:()I
     206: i2f
     207: fadd
     208: aload_0
     209: getfield      #22                 // Field a:Lde/blox/graphview/b/b;
     212: invokevirtual #77                 // Method de/blox/graphview/b/b.b:()I
     215: iconst_2
     216: idiv
     217: i2f
     218: fadd
     219: aload         9
     221: invokevirtual #68                 // Method de/blox/graphview/h.c:()F
     224: aload         9
     226: invokevirtual #71                 // Method de/blox/graphview/h.f:()I
     229: iconst_2
     230: idiv
     231: i2f
     232: fadd
     233: invokevirtual #80                 // Method android/graphics/Path.lineTo:(FF)V
     236: aload_0
     237: getfield      #20                 // Field b:Landroid/graphics/Path;
     240: aload         7
     242: invokevirtual #63                 // Method de/blox/graphview/h.b:()F
     245: aload         7
     247: invokevirtual #66                 // Method de/blox/graphview/h.e:()I
     250: i2f
     251: fadd
     252: aload_0
     253: getfield      #22                 // Field a:Lde/blox/graphview/b/b;
     256: invokevirtual #77                 // Method de/blox/graphview/b/b.b:()I
     259: iconst_2
     260: idiv
     261: i2f
     262: fadd
     263: aload         9
     265: invokevirtual #68                 // Method de/blox/graphview/h.c:()F
     268: aload         9
     270: invokevirtual #71                 // Method de/blox/graphview/h.f:()I
     273: iconst_2
     274: idiv
     275: i2f
     276: fadd
     277: invokevirtual #75                 // Method android/graphics/Path.moveTo:(FF)V
     280: goto          420
     283: aload_0
     284: getfield      #20                 // Field b:Landroid/graphics/Path;
     287: aload         7
     289: invokevirtual #63                 // Method de/blox/graphview/h.b:()F
     292: aload         7
     294: invokevirtual #68                 // Method de/blox/graphview/h.c:()F
     297: aload         7
     299: invokevirtual #71                 // Method de/blox/graphview/h.f:()I
     302: iconst_2
     303: idiv
     304: i2f
     305: fadd
     306: invokevirtual #75                 // Method android/graphics/Path.moveTo:(FF)V
     309: aload_0
     310: getfield      #20                 // Field b:Landroid/graphics/Path;
     313: aload         7
     315: invokevirtual #63                 // Method de/blox/graphview/h.b:()F
     318: aload_0
     319: getfield      #22                 // Field a:Lde/blox/graphview/b/b;
     322: invokevirtual #77                 // Method de/blox/graphview/b/b.b:()I
     325: iconst_2
     326: idiv
     327: i2f
     328: fsub
     329: aload         7
     331: invokevirtual #68                 // Method de/blox/graphview/h.c:()F
     334: aload         7
     336: invokevirtual #71                 // Method de/blox/graphview/h.f:()I
     339: iconst_2
     340: idiv
     341: i2f
     342: fadd
     343: invokevirtual #80                 // Method android/graphics/Path.lineTo:(FF)V
     346: aload_0
     347: getfield      #20                 // Field b:Landroid/graphics/Path;
     350: aload         7
     352: invokevirtual #63                 // Method de/blox/graphview/h.b:()F
     355: aload_0
     356: getfield      #22                 // Field a:Lde/blox/graphview/b/b;
     359: invokevirtual #77                 // Method de/blox/graphview/b/b.b:()I
     362: iconst_2
     363: idiv
     364: i2f
     365: fsub
     366: aload         9
     368: invokevirtual #68                 // Method de/blox/graphview/h.c:()F
     371: aload         9
     373: invokevirtual #71                 // Method de/blox/graphview/h.f:()I
     376: iconst_2
     377: idiv
     378: i2f
     379: fadd
     380: invokevirtual #80                 // Method android/graphics/Path.lineTo:(FF)V
     383: aload_0
     384: getfield      #20                 // Field b:Landroid/graphics/Path;
     387: aload         7
     389: invokevirtual #63                 // Method de/blox/graphview/h.b:()F
     392: aload_0
     393: getfield      #22                 // Field a:Lde/blox/graphview/b/b;
     396: invokevirtual #77                 // Method de/blox/graphview/b/b.b:()I
     399: iconst_2
     400: idiv
     401: i2f
     402: fsub
     403: aload         9
     405: invokevirtual #68                 // Method de/blox/graphview/h.c:()F
     408: aload         9
     410: invokevirtual #71                 // Method de/blox/graphview/h.f:()I
     413: iconst_2
     414: idiv
     415: i2f
     416: fadd
     417: invokevirtual #75                 // Method android/graphics/Path.moveTo:(FF)V
     420: aload_0
     421: getfield      #20                 // Field b:Landroid/graphics/Path;
     424: astore        7
     426: aload         9
     428: invokevirtual #63                 // Method de/blox/graphview/h.b:()F
     431: aload         9
     433: invokevirtual #66                 // Method de/blox/graphview/h.e:()I
     436: i2f
     437: fadd
     438: fstore        4
     440: aload         9
     442: invokevirtual #68                 // Method de/blox/graphview/h.c:()F
     445: fstore        5
     447: aload         9
     449: invokevirtual #71                 // Method de/blox/graphview/h.f:()I
     452: iconst_2
     453: idiv
     454: istore        6
     456: goto          800
     459: aload_0
     460: getfield      #20                 // Field b:Landroid/graphics/Path;
     463: aload         7
     465: invokevirtual #63                 // Method de/blox/graphview/h.b:()F
     468: aload         7
     470: invokevirtual #66                 // Method de/blox/graphview/h.e:()I
     473: iconst_2
     474: idiv
     475: i2f
     476: fadd
     477: aload         7
     479: invokevirtual #68                 // Method de/blox/graphview/h.c:()F
     482: aload         7
     484: invokevirtual #71                 // Method de/blox/graphview/h.f:()I
     487: i2f
     488: fadd
     489: invokevirtual #75                 // Method android/graphics/Path.moveTo:(FF)V
     492: aload_0
     493: getfield      #20                 // Field b:Landroid/graphics/Path;
     496: aload         7
     498: invokevirtual #63                 // Method de/blox/graphview/h.b:()F
     501: aload         7
     503: invokevirtual #66                 // Method de/blox/graphview/h.e:()I
     506: iconst_2
     507: idiv
     508: i2f
     509: fadd
     510: aload         7
     512: invokevirtual #68                 // Method de/blox/graphview/h.c:()F
     515: aload         7
     517: invokevirtual #71                 // Method de/blox/graphview/h.f:()I
     520: i2f
     521: fadd
     522: aload_0
     523: getfield      #22                 // Field a:Lde/blox/graphview/b/b;
     526: invokevirtual #77                 // Method de/blox/graphview/b/b.b:()I
     529: iconst_2
     530: idiv
     531: i2f
     532: fadd
     533: invokevirtual #80                 // Method android/graphics/Path.lineTo:(FF)V
     536: aload_0
     537: getfield      #20                 // Field b:Landroid/graphics/Path;
     540: aload         9
     542: invokevirtual #63                 // Method de/blox/graphview/h.b:()F
     545: aload         9
     547: invokevirtual #66                 // Method de/blox/graphview/h.e:()I
     550: iconst_2
     551: idiv
     552: i2f
     553: fadd
     554: aload         7
     556: invokevirtual #68                 // Method de/blox/graphview/h.c:()F
     559: aload         7
     561: invokevirtual #71                 // Method de/blox/graphview/h.f:()I
     564: i2f
     565: fadd
     566: aload_0
     567: getfield      #22                 // Field a:Lde/blox/graphview/b/b;
     570: invokevirtual #77                 // Method de/blox/graphview/b/b.b:()I
     573: iconst_2
     574: idiv
     575: i2f
     576: fadd
     577: invokevirtual #80                 // Method android/graphics/Path.lineTo:(FF)V
     580: aload_0
     581: getfield      #20                 // Field b:Landroid/graphics/Path;
     584: aload         9
     586: invokevirtual #63                 // Method de/blox/graphview/h.b:()F
     589: aload         9
     591: invokevirtual #66                 // Method de/blox/graphview/h.e:()I
     594: iconst_2
     595: idiv
     596: i2f
     597: fadd
     598: aload         7
     600: invokevirtual #68                 // Method de/blox/graphview/h.c:()F
     603: aload         7
     605: invokevirtual #71                 // Method de/blox/graphview/h.f:()I
     608: i2f
     609: fadd
     610: aload_0
     611: getfield      #22                 // Field a:Lde/blox/graphview/b/b;
     614: invokevirtual #77                 // Method de/blox/graphview/b/b.b:()I
     617: iconst_2
     618: idiv
     619: i2f
     620: fadd
     621: invokevirtual #75                 // Method android/graphics/Path.moveTo:(FF)V
     624: goto          764
     627: aload_0
     628: getfield      #20                 // Field b:Landroid/graphics/Path;
     631: aload         7
     633: invokevirtual #63                 // Method de/blox/graphview/h.b:()F
     636: aload         7
     638: invokevirtual #66                 // Method de/blox/graphview/h.e:()I
     641: iconst_2
     642: idiv
     643: i2f
     644: fadd
     645: aload         7
     647: invokevirtual #68                 // Method de/blox/graphview/h.c:()F
     650: invokevirtual #75                 // Method android/graphics/Path.moveTo:(FF)V
     653: aload_0
     654: getfield      #20                 // Field b:Landroid/graphics/Path;
     657: aload         7
     659: invokevirtual #63                 // Method de/blox/graphview/h.b:()F
     662: aload         7
     664: invokevirtual #66                 // Method de/blox/graphview/h.e:()I
     667: iconst_2
     668: idiv
     669: i2f
     670: fadd
     671: aload         7
     673: invokevirtual #68                 // Method de/blox/graphview/h.c:()F
     676: aload_0
     677: getfield      #22                 // Field a:Lde/blox/graphview/b/b;
     680: invokevirtual #77                 // Method de/blox/graphview/b/b.b:()I
     683: iconst_2
     684: idiv
     685: i2f
     686: fsub
     687: invokevirtual #80                 // Method android/graphics/Path.lineTo:(FF)V
     690: aload_0
     691: getfield      #20                 // Field b:Landroid/graphics/Path;
     694: aload         9
     696: invokevirtual #63                 // Method de/blox/graphview/h.b:()F
     699: aload         9
     701: invokevirtual #66                 // Method de/blox/graphview/h.e:()I
     704: iconst_2
     705: idiv
     706: i2f
     707: fadd
     708: aload         7
     710: invokevirtual #68                 // Method de/blox/graphview/h.c:()F
     713: aload_0
     714: getfield      #22                 // Field a:Lde/blox/graphview/b/b;
     717: invokevirtual #77                 // Method de/blox/graphview/b/b.b:()I
     720: iconst_2
     721: idiv
     722: i2f
     723: fsub
     724: invokevirtual #80                 // Method android/graphics/Path.lineTo:(FF)V
     727: aload_0
     728: getfield      #20                 // Field b:Landroid/graphics/Path;
     731: aload         9
     733: invokevirtual #63                 // Method de/blox/graphview/h.b:()F
     736: aload         9
     738: invokevirtual #66                 // Method de/blox/graphview/h.e:()I
     741: iconst_2
     742: idiv
     743: i2f
     744: fadd
     745: aload         7
     747: invokevirtual #68                 // Method de/blox/graphview/h.c:()F
     750: aload_0
     751: getfield      #22                 // Field a:Lde/blox/graphview/b/b;
     754: invokevirtual #77                 // Method de/blox/graphview/b/b.b:()I
     757: iconst_2
     758: idiv
     759: i2f
     760: fsub
     761: invokevirtual #75                 // Method android/graphics/Path.moveTo:(FF)V
     764: aload_0
     765: getfield      #20                 // Field b:Landroid/graphics/Path;
     768: astore        7
     770: aload         9
     772: invokevirtual #63                 // Method de/blox/graphview/h.b:()F
     775: aload         9
     777: invokevirtual #66                 // Method de/blox/graphview/h.e:()I
     780: iconst_2
     781: idiv
     782: i2f
     783: fadd
     784: fstore        4
     786: aload         9
     788: invokevirtual #68                 // Method de/blox/graphview/h.c:()F
     791: fstore        5
     793: aload         9
     795: invokevirtual #71                 // Method de/blox/graphview/h.f:()I
     798: istore        6
     800: aload         7
     802: fload         4
     804: fload         5
     806: iload         6
     808: i2f
     809: fadd
     810: invokevirtual #80                 // Method android/graphics/Path.lineTo:(FF)V
     813: aload_1
     814: aload_0
     815: getfield      #20                 // Field b:Landroid/graphics/Path;
     818: aload_3
     819: invokevirtual #86                 // Method android/graphics/Canvas.drawPath:(Landroid/graphics/Path;Landroid/graphics/Paint;)V
     822: goto          46
     825: return
}
