public class ryey.easer.plugins.operation.b.e extends ryey.easer.plugins.c<ryey.easer.plugins.operation.b.b> {
  public ryey.easer.plugins.operation.b.e();
    Code:
       0: aload_0
       1: invokespecial #15                 // Method ryey/easer/plugins/c."<init>":()V
       4: return

  public ryey.easer.commons.local_plugin.f a();
    Code:
       0: aload_0
       1: invokevirtual #20                 // Method b:()Lryey/easer/plugins/operation/b/b;
       4: areturn

  protected void a(ryey.easer.plugins.operation.b.b);
    Code:
       0: aload_0
       1: getfield      #23                 // Field a:Landroid/widget/EditText;
       4: aload_1
       5: getfield      #28                 // Field ryey/easer/plugins/operation/b/b.a:Ljava/util/Calendar;
       8: invokestatic  #31                 // Method ryey/easer/plugins/operation/b/b.a:(Ljava/util/Calendar;)Ljava/lang/String;
      11: invokevirtual #37                 // Method android/widget/EditText.setText:(Ljava/lang/CharSequence;)V
      14: aload_0
      15: getfield      #39                 // Field b:Landroid/widget/EditText;
      18: aload_1
      19: getfield      #42                 // Field ryey/easer/plugins/operation/b/b.b:Ljava/lang/String;
      22: invokevirtual #37                 // Method android/widget/EditText.setText:(Ljava/lang/CharSequence;)V
      25: aload_1
      26: getfield      #45                 // Field ryey/easer/plugins/operation/b/b.c:Z
      29: ifeq          43
      32: aload_0
      33: getfield      #47                 // Field c:Landroid/widget/RadioButton;
      36: astore_1
      37: aload_1
      38: iconst_1
      39: invokevirtual #53                 // Method android/widget/RadioButton.setChecked:(Z)V
      42: return
      43: aload_0
      44: getfield      #55                 // Field d:Landroid/widget/RadioButton;
      47: astore_1
      48: goto          37

  public ryey.easer.plugins.operation.b.b b();
    Code:
       0: aload_0
       1: getfield      #23                 // Field a:Landroid/widget/EditText;
       4: invokevirtual #61                 // Method android/widget/EditText.getText:()Landroid/text/Editable;
       7: invokevirtual #67                 // Method java/lang/Object.toString:()Ljava/lang/String;
      10: invokestatic  #70                 // Method ryey/easer/plugins/operation/b/b.a:(Ljava/lang/String;)Ljava/util/Calendar;
      13: astore_1
      14: new           #25                 // class ryey/easer/plugins/operation/b/b
      17: dup
      18: aload_1
      19: aload_0
      20: getfield      #39                 // Field b:Landroid/widget/EditText;
      23: invokevirtual #61                 // Method android/widget/EditText.getText:()Landroid/text/Editable;
      26: invokevirtual #67                 // Method java/lang/Object.toString:()Ljava/lang/String;
      29: aload_0
      30: getfield      #47                 // Field c:Landroid/widget/RadioButton;
      33: invokevirtual #74                 // Method android/widget/RadioButton.isChecked:()Z
      36: invokespecial #77                 // Method ryey/easer/plugins/operation/b/b."<init>":(Ljava/util/Calendar;Ljava/lang/String;Z)V
      39: areturn
      40: astore_1
      41: aload_1
      42: invokestatic  #82                 // Method com/google/a/a/a/a/a/a.a:(Ljava/lang/Throwable;)V
      45: new           #84                 // class ryey/easer/commons/local_plugin/c
      48: dup
      49: aload_1
      50: invokevirtual #87                 // Method java/text/ParseException.getMessage:()Ljava/lang/String;
      53: invokespecial #90                 // Method ryey/easer/commons/local_plugin/c."<init>":(Ljava/lang/String;)V
      56: athrow
    Exception table:
       from    to  target type
           0    14    40   Class java/text/ParseException

  protected void b(ryey.easer.commons.local_plugin.f);
    Code:
       0: aload_0
       1: aload_1
       2: checkcast     #25                 // class ryey/easer/plugins/operation/b/b
       5: invokevirtual #93                 // Method a:(Lryey/easer/plugins/operation/b/b;)V
       8: return

  public android.view.View onCreateView(android.view.LayoutInflater, android.view.ViewGroup, android.os.Bundle);
    Code:
       0: aload_1
       1: ldc           #96                 // int 2131427455
       3: aload_2
       4: iconst_0
       5: invokevirtual #102                // Method android/view/LayoutInflater.inflate:(ILandroid/view/ViewGroup;Z)Landroid/view/View;
       8: astore_1
       9: aload_0
      10: aload_1
      11: ldc           #103                // int 2131296400
      13: invokevirtual #109                // Method android/view/View.findViewById:(I)Landroid/view/View;
      16: checkcast     #33                 // class android/widget/EditText
      19: putfield      #23                 // Field a:Landroid/widget/EditText;
      22: aload_0
      23: aload_1
      24: ldc           #110                // int 2131296386
      26: invokevirtual #109                // Method android/view/View.findViewById:(I)Landroid/view/View;
      29: checkcast     #33                 // class android/widget/EditText
      32: putfield      #39                 // Field b:Landroid/widget/EditText;
      35: aload_0
      36: aload_1
      37: ldc           #111                // int 2131296522
      39: invokevirtual #109                // Method android/view/View.findViewById:(I)Landroid/view/View;
      42: checkcast     #49                 // class android/widget/RadioButton
      45: putfield      #47                 // Field c:Landroid/widget/RadioButton;
      48: aload_0
      49: aload_1
      50: ldc           #112                // int 2131296547
      52: invokevirtual #109                // Method android/view/View.findViewById:(I)Landroid/view/View;
      55: checkcast     #49                 // class android/widget/RadioButton
      58: putfield      #55                 // Field d:Landroid/widget/RadioButton;
      61: aload_1
      62: areturn
}
