public final class ryey.easer.plugins.b {
  static {};
    Code:
       0: new           #2                  // class ryey/easer/plugins/b
       3: dup
       4: invokespecial #28                 // Method "<init>":()V
       7: putstatic     #30                 // Field e:Lryey/easer/plugins/b;
      10: return

  public static ryey.easer.plugins.b a();
    Code:
       0: getstatic     #30                 // Field e:Lryey/easer/plugins/b;
       3: areturn

  public ryey.easer.plugins.b$c<ryey.easer.commons.local_plugin.eventplugin.b, ryey.easer.commons.local_plugin.eventplugin.EventData> b();
    Code:
       0: aload_0
       1: getfield      #37                 // Field a:Lryey/easer/plugins/b$c;
       4: areturn

  public ryey.easer.plugins.b$c<ryey.easer.commons.local_plugin.c.d, ryey.easer.commons.local_plugin.c.b> c();
    Code:
       0: aload_0
       1: getfield      #50                 // Field b:Lryey/easer/plugins/b$c;
       4: areturn

  public ryey.easer.plugins.b$c<ryey.easer.commons.local_plugin.a.c, ryey.easer.commons.local_plugin.a.a> d();
    Code:
       0: aload_0
       1: getfield      #52                 // Field c:Lryey/easer/plugins/b$c;
       4: areturn

  public ryey.easer.plugins.b$b<ryey.easer.commons.local_plugin.d, ryey.easer.commons.local_plugin.f> e();
    Code:
       0: aload_0
       1: getfield      #57                 // Field d:Lryey/easer/plugins/b$a;
       4: areturn
}
