public abstract class ryey.easer.plugins.c<T extends ryey.easer.commons.local_plugin.f> extends ryey.easer.commons.local_plugin.e<T> {
  public ryey.easer.plugins.c();
    Code:
       0: aload_0
       1: invokespecial #19                 // Method ryey/easer/commons/local_plugin/e."<init>":()V
       4: aload_0
       5: new           #7                  // class ryey/easer/plugins/c$a
       8: dup
       9: aload_0
      10: ldc           #21                 // String FillDataJob
      12: invokespecial #24                 // Method ryey/easer/plugins/c$a."<init>":(Lryey/easer/plugins/c;Ljava/lang/String;)V
      15: putfield      #26                 // Field a:Lryey/easer/plugins/c$a;
      18: aload_0
      19: new           #10                 // class ryey/easer/plugins/c$b
      22: dup
      23: aload_0
      24: ldc           #21                 // String FillDataJob
      26: invokespecial #27                 // Method ryey/easer/plugins/c$b."<init>":(Lryey/easer/plugins/c;Ljava/lang/String;)V
      29: putfield      #29                 // Field b:Lryey/easer/plugins/c$b;
      32: return

  protected static void a(android.view.View, boolean);
    Code:
       0: aload_0
       1: iload_1
       2: invokevirtual #37                 // Method android/view/View.setEnabled:(Z)V
       5: aload_0
       6: instanceof    #39                 // class android/view/ViewGroup
       9: ifeq          43
      12: iconst_0
      13: istore_2
      14: aload_0
      15: checkcast     #39                 // class android/view/ViewGroup
      18: astore_3
      19: iload_2
      20: aload_3
      21: invokevirtual #43                 // Method android/view/ViewGroup.getChildCount:()I
      24: if_icmpge     43
      27: aload_3
      28: iload_2
      29: invokevirtual #47                 // Method android/view/ViewGroup.getChildAt:(I)Landroid/view/View;
      32: iload_1
      33: invokestatic  #49                 // Method a:(Landroid/view/View;Z)V
      36: iload_2
      37: iconst_1
      38: iadd
      39: istore_2
      40: goto          14
      43: return

  public java.lang.String a(android.content.res.Resources);
    Code:
       0: aload_1
       1: invokestatic  #56                 // Method ryey/easer/plugins/b.a:()Lryey/easer/plugins/b;
       4: invokevirtual #60                 // Method ryey/easer/plugins/b.e:()Lryey/easer/plugins/b$b;
       7: aload_0
       8: invokeinterface #65,  2           // InterfaceMethod ryey/easer/plugins/b$b.a:(Lryey/easer/commons/local_plugin/e;)Lryey/easer/commons/local_plugin/d;
      13: invokeinterface #94,  1           // InterfaceMethod ryey/easer/commons/local_plugin/d.b:()I
      18: invokevirtual #100                // Method android/content/res/Resources.getString:(I)Ljava/lang/String;
      21: areturn

  public void a(T);
    Code:
       0: aload_0
       1: aload_1
       2: invokespecial #102                // Method c:(Lryey/easer/commons/local_plugin/f;)V
       5: aload_0
       6: getfield      #26                 // Field a:Lryey/easer/plugins/c$a;
       9: aload_1
      10: invokestatic  #105                // Method ryey/easer/plugins/c$a.a:(Lryey/easer/plugins/c$a;Lryey/easer/commons/local_plugin/f;)Lryey/easer/commons/local_plugin/f;
      13: pop
      14: aload_0
      15: getfield      #26                 // Field a:Lryey/easer/plugins/c$a;
      18: iconst_1
      19: invokevirtual #108                // Method ryey/easer/plugins/c$a.a:(I)V
      22: return
      23: astore_1
      24: aload_1
      25: ldc           #110                // String filling with illegal data type
      27: iconst_0
      28: anewarray     #77                 // class java/lang/Object
      31: invokestatic  #115                // Method com/b/a/i.a:(Ljava/lang/Throwable;Ljava/lang/String;[Ljava/lang/Object;)V
      34: aload_1
      35: athrow
    Exception table:
       from    to  target type
           0    22    23   Class ryey/easer/plugins/a

  public void a(boolean);
    Code:
       0: aload_0
       1: getfield      #29                 // Field b:Lryey/easer/plugins/c$b;
       4: iload_1
       5: invokestatic  #118                // Method ryey/easer/plugins/c$b.a:(Lryey/easer/plugins/c$b;Z)Z
       8: pop
       9: aload_0
      10: getfield      #29                 // Field b:Lryey/easer/plugins/c$b;
      13: iconst_1
      14: invokevirtual #119                // Method ryey/easer/plugins/c$b.a:(I)V
      17: return

  protected abstract void b(T);

  public void onViewCreated(android.view.View, android.os.Bundle);
    Code:
       0: aload_0
       1: getfield      #26                 // Field a:Lryey/easer/plugins/c$a;
       4: iconst_0
       5: invokevirtual #108                // Method ryey/easer/plugins/c$a.a:(I)V
       8: aload_0
       9: getfield      #29                 // Field b:Lryey/easer/plugins/c$b;
      12: iconst_0
      13: invokevirtual #119                // Method ryey/easer/plugins/c$b.a:(I)V
      16: return
}
