class se.emilsjolander.stickylistheaders.StickyListHeadersListView$b implements se.emilsjolander.stickylistheaders.a$a {
  final se.emilsjolander.stickylistheaders.StickyListHeadersListView a;

  se.emilsjolander.stickylistheaders.StickyListHeadersListView$b(se.emilsjolander.stickylistheaders.StickyListHeadersListView, se.emilsjolander.stickylistheaders.StickyListHeadersListView$1);
    Code:
       0: aload_0
       1: aload_1
       2: invokespecial #22                 // Method "<init>":(Lse/emilsjolander/stickylistheaders/StickyListHeadersListView;)V
       5: return

  public void a(android.view.View, int, long);
    Code:
       0: aload_0
       1: getfield      #15                 // Field a:Lse/emilsjolander/stickylistheaders/StickyListHeadersListView;
       4: invokestatic  #27                 // Method se/emilsjolander/stickylistheaders/StickyListHeadersListView.d:(Lse/emilsjolander/stickylistheaders/StickyListHeadersListView;)Lse/emilsjolander/stickylistheaders/StickyListHeadersListView$c;
       7: aload_0
       8: getfield      #15                 // Field a:Lse/emilsjolander/stickylistheaders/StickyListHeadersListView;
      11: aload_1
      12: iload_2
      13: lload_3
      14: iconst_0
      15: invokeinterface #32,  7           // InterfaceMethod se/emilsjolander/stickylistheaders/StickyListHeadersListView$c.a:(Lse/emilsjolander/stickylistheaders/StickyListHeadersListView;Landroid/view/View;IJZ)V
      20: return
}
