class se.emilsjolander.stickylistheaders.StickyListHeadersListView$a extends android.database.DataSetObserver {
  final se.emilsjolander.stickylistheaders.StickyListHeadersListView a;

  se.emilsjolander.stickylistheaders.StickyListHeadersListView$a(se.emilsjolander.stickylistheaders.StickyListHeadersListView, se.emilsjolander.stickylistheaders.StickyListHeadersListView$1);
    Code:
       0: aload_0
       1: aload_1
       2: invokespecial #19                 // Method "<init>":(Lse/emilsjolander/stickylistheaders/StickyListHeadersListView;)V
       5: return

  public void onChanged();
    Code:
       0: aload_0
       1: getfield      #12                 // Field a:Lse/emilsjolander/stickylistheaders/StickyListHeadersListView;
       4: invokestatic  #23                 // Method se/emilsjolander/stickylistheaders/StickyListHeadersListView.e:(Lse/emilsjolander/stickylistheaders/StickyListHeadersListView;)V
       7: return

  public void onInvalidated();
    Code:
       0: aload_0
       1: getfield      #12                 // Field a:Lse/emilsjolander/stickylistheaders/StickyListHeadersListView;
       4: invokestatic  #23                 // Method se/emilsjolander/stickylistheaders/StickyListHeadersListView.e:(Lse/emilsjolander/stickylistheaders/StickyListHeadersListView;)V
       7: return
}
