public class ryey.easer.core.a.a.b extends ryey.easer.core.a.a.a<ryey.easer.core.a.b, ryey.easer.core.a.a.a.a> {
  public ryey.easer.core.a.a.b(android.content.Context);
    Code:
       0: aload_0
       1: aload_1
       2: iconst_1
       3: anewarray     #9                  // class ryey/easer/core/a/a/a/a
       6: dup
       7: iconst_0
       8: new           #11                 // class ryey/easer/core/a/a/a/a/a/c
      11: dup
      12: aload_1
      13: invokespecial #13                 // Method ryey/easer/core/a/a/a/a/a/c."<init>":(Landroid/content/Context;)V
      16: aastore
      17: invokespecial #16                 // Method ryey/easer/core/a/a/a."<init>":(Landroid/content/Context;[Lryey/easer/core/a/a/a/b;)V
      20: return

  protected void a(java.lang.String, ryey.easer.core.a.b);
    Code:
       0: new           #73                 // class ryey/easer/core/a/a/e
       3: dup
       4: aload_0
       5: getfield      #109                // Field a:Landroid/content/Context;
       8: invokespecial #110                // Method ryey/easer/core/a/a/e."<init>":(Landroid/content/Context;)V
      11: astore_3
      12: aload_3
      13: aload_1
      14: aload_2
      15: invokestatic  #112                // Method a:(Lryey/easer/core/a/a/e;Ljava/lang/String;Lryey/easer/core/a/b;)V
      18: new           #21                 // class ryey/easer/core/a/a/c
      21: dup
      22: aload_0
      23: getfield      #109                // Field a:Landroid/content/Context;
      26: invokespecial #113                // Method ryey/easer/core/a/a/c."<init>":(Landroid/content/Context;)V
      29: aload_1
      30: aload_2
      31: invokevirtual #102                // Method ryey/easer/core/a/b.a:()Ljava/lang/String;
      34: invokestatic  #115                // Method a:(Lryey/easer/core/a/a/c;Ljava/lang/String;Ljava/lang/String;)V
      37: aload_3
      38: aload_1
      39: aload_2
      40: invokevirtual #102                // Method ryey/easer/core/a/b.a:()Ljava/lang/String;
      43: invokestatic  #117                // Method a:(Lryey/easer/core/a/a/e;Ljava/lang/String;Ljava/lang/String;)V
      46: return

  protected void b(java.lang.String, ryey.easer.core.a.f);
    Code:
       0: aload_0
       1: aload_1
       2: aload_2
       3: checkcast     #99                 // class ryey/easer/core/a/b
       6: invokevirtual #120                // Method a:(Ljava/lang/String;Lryey/easer/core/a/b;)V
       9: return

  boolean b(java.lang.String);
    Code:
       0: new           #73                 // class ryey/easer/core/a/a/e
       3: dup
       4: aload_0
       5: getfield      #109                // Field a:Landroid/content/Context;
       8: invokespecial #110                // Method ryey/easer/core/a/a/e."<init>":(Landroid/content/Context;)V
      11: astore_2
      12: aload_2
      13: invokevirtual #74                 // Method ryey/easer/core/a/a/e.a:()Ljava/util/List;
      16: invokeinterface #30,  1           // InterfaceMethod java/util/List.iterator:()Ljava/util/Iterator;
      21: astore_3
      22: aload_3
      23: invokeinterface #36,  1           // InterfaceMethod java/util/Iterator.hasNext:()Z
      28: ifeq          74
      31: aload_2
      32: aload_3
      33: invokeinterface #40,  1           // InterfaceMethod java/util/Iterator.next:()Ljava/lang/Object;
      38: checkcast     #42                 // class java/lang/String
      41: invokevirtual #75                 // Method ryey/easer/core/a/a/e.a:(Ljava/lang/String;)Lryey/easer/core/a/f;
      44: checkcast     #77                 // class ryey/easer/core/a/j
      47: astore        4
      49: aload         4
      51: invokevirtual #93                 // Method ryey/easer/core/a/j.f:()Z
      54: ifeq          22
      57: aload         4
      59: invokevirtual #97                 // Method ryey/easer/core/a/j.g:()Lryey/easer/core/a/b;
      62: invokevirtual #102                // Method ryey/easer/core/a/b.a:()Ljava/lang/String;
      65: aload_1
      66: invokevirtual #60                 // Method java/lang/String.equals:(Ljava/lang/Object;)Z
      69: ifeq          22
      72: iconst_0
      73: ireturn
      74: new           #21                 // class ryey/easer/core/a/a/c
      77: dup
      78: aload_0
      79: getfield      #109                // Field a:Landroid/content/Context;
      82: invokespecial #113                // Method ryey/easer/core/a/a/c."<init>":(Landroid/content/Context;)V
      85: astore_2
      86: aload_2
      87: invokevirtual #24                 // Method ryey/easer/core/a/a/c.a:()Ljava/util/List;
      90: invokeinterface #30,  1           // InterfaceMethod java/util/List.iterator:()Ljava/util/Iterator;
      95: astore_3
      96: aload_3
      97: invokeinterface #36,  1           // InterfaceMethod java/util/Iterator.hasNext:()Z
     102: ifeq          151
     105: aload_2
     106: aload_3
     107: invokeinterface #40,  1           // InterfaceMethod java/util/Iterator.next:()Ljava/lang/Object;
     112: checkcast     #42                 // class java/lang/String
     115: invokevirtual #45                 // Method ryey/easer/core/a/a/c.a:(Ljava/lang/String;)Lryey/easer/core/a/f;
     118: checkcast     #47                 // class ryey/easer/core/a/c
     121: invokevirtual #51                 // Method ryey/easer/core/a/c.c:()Lryey/easer/commons/local_plugin/eventplugin/EventData;
     124: astore        4
     126: aload         4
     128: instanceof    #53                 // class ryey/easer/plugins/event/f/a
     131: ifeq          96
     134: aload_1
     135: aload         4
     137: checkcast     #53                 // class ryey/easer/plugins/event/f/a
     140: getfield      #56                 // Field ryey/easer/plugins/event/f/a.a:Ljava/lang/String;
     143: invokevirtual #60                 // Method java/lang/String.equals:(Ljava/lang/Object;)Z
     146: ifeq          96
     149: iconst_0
     150: ireturn
     151: iconst_1
     152: ireturn
}
