public class ryey.easer.core.a.a.c extends ryey.easer.core.a.a.a<ryey.easer.core.a.c, ryey.easer.core.a.a.a.c> {
  public ryey.easer.core.a.a.c(android.content.Context);
    Code:
       0: aload_0
       1: aload_1
       2: iconst_1
       3: anewarray     #9                  // class ryey/easer/core/a/a/a/c
       6: dup
       7: iconst_0
       8: new           #11                 // class ryey/easer/core/a/a/a/a/b/c
      11: dup
      12: aload_1
      13: invokespecial #13                 // Method ryey/easer/core/a/a/a/a/b/c."<init>":(Landroid/content/Context;)V
      16: aastore
      17: invokespecial #16                 // Method ryey/easer/core/a/a/a."<init>":(Landroid/content/Context;[Lryey/easer/core/a/a/a/b;)V
      20: return

  protected void a(java.lang.String, ryey.easer.core.a.c);
    Code:
       0: new           #21                 // class ryey/easer/core/a/a/e
       3: dup
       4: aload_0
       5: getfield      #24                 // Field a:Landroid/content/Context;
       8: invokespecial #25                 // Method ryey/easer/core/a/a/e."<init>":(Landroid/content/Context;)V
      11: astore_3
      12: aload_3
      13: invokevirtual #29                 // Method ryey/easer/core/a/a/e.c:()Ljava/util/List;
      16: invokeinterface #35,  1           // InterfaceMethod java/util/List.iterator:()Ljava/util/Iterator;
      21: astore        4
      23: aload         4
      25: invokeinterface #41,  1           // InterfaceMethod java/util/Iterator.hasNext:()Z
      30: ifeq          94
      33: aload         4
      35: invokeinterface #45,  1           // InterfaceMethod java/util/Iterator.next:()Ljava/lang/Object;
      40: checkcast     #47                 // class ryey/easer/core/a/j
      43: astore        5
      45: aload         5
      47: invokevirtual #49                 // Method ryey/easer/core/a/j.c:()Z
      50: ifeq          23
      53: aload         5
      55: invokevirtual #53                 // Method ryey/easer/core/a/j.e:()Lryey/easer/core/a/c;
      58: invokevirtual #57                 // Method ryey/easer/core/a/c.e:()Z
      61: ifne          23
      64: aload_1
      65: aload         5
      67: invokevirtual #53                 // Method ryey/easer/core/a/j.e:()Lryey/easer/core/a/c;
      70: invokevirtual #60                 // Method ryey/easer/core/a/c.a:()Ljava/lang/String;
      73: invokevirtual #66                 // Method java/lang/String.equals:(Ljava/lang/Object;)Z
      76: ifeq          23
      79: aload         5
      81: aload_2
      82: invokevirtual #69                 // Method ryey/easer/core/a/j.a:(Lryey/easer/core/a/c;)V
      85: aload_3
      86: aload         5
      88: invokevirtual #73                 // Method ryey/easer/core/a/a/e.b:(Lryey/easer/core/a/f;)V
      91: goto          23
      94: return

  protected void b(java.lang.String, ryey.easer.core.a.f);
    Code:
       0: aload_0
       1: aload_1
       2: aload_2
       3: checkcast     #55                 // class ryey/easer/core/a/c
       6: invokevirtual #76                 // Method a:(Ljava/lang/String;Lryey/easer/core/a/c;)V
       9: return

  boolean b(java.lang.String);
    Code:
       0: new           #21                 // class ryey/easer/core/a/a/e
       3: dup
       4: aload_0
       5: getfield      #24                 // Field a:Landroid/content/Context;
       8: invokespecial #25                 // Method ryey/easer/core/a/a/e."<init>":(Landroid/content/Context;)V
      11: invokevirtual #29                 // Method ryey/easer/core/a/a/e.c:()Ljava/util/List;
      14: invokeinterface #35,  1           // InterfaceMethod java/util/List.iterator:()Ljava/util/Iterator;
      19: astore_2
      20: aload_2
      21: invokeinterface #41,  1           // InterfaceMethod java/util/Iterator.hasNext:()Z
      26: ifeq          62
      29: aload_2
      30: invokeinterface #45,  1           // InterfaceMethod java/util/Iterator.next:()Ljava/lang/Object;
      35: checkcast     #47                 // class ryey/easer/core/a/j
      38: astore_3
      39: aload_3
      40: invokevirtual #49                 // Method ryey/easer/core/a/j.c:()Z
      43: ifeq          20
      46: aload_1
      47: aload_3
      48: invokevirtual #53                 // Method ryey/easer/core/a/j.e:()Lryey/easer/core/a/c;
      51: invokevirtual #60                 // Method ryey/easer/core/a/c.a:()Ljava/lang/String;
      54: invokevirtual #66                 // Method java/lang/String.equals:(Ljava/lang/Object;)Z
      57: ifeq          20
      60: iconst_0
      61: ireturn
      62: iconst_1
      63: ireturn
}
