public class ryey.easer.core.a.a.e extends ryey.easer.core.a.a.a<ryey.easer.core.a.j, ryey.easer.core.a.a.a.h> {
  static final boolean c;

  static {};
    Code:
       0: return

  public ryey.easer.core.a.a.e(android.content.Context);
    Code:
       0: aload_0
       1: aload_1
       2: iconst_1
       3: anewarray     #15                 // class ryey/easer/core/a/a/a/h
       6: dup
       7: iconst_0
       8: new           #17                 // class ryey/easer/core/a/a/a/a/d/a
      11: dup
      12: aload_1
      13: invokespecial #19                 // Method ryey/easer/core/a/a/a/a/d/a."<init>":(Landroid/content/Context;)V
      16: aastore
      17: invokespecial #22                 // Method ryey/easer/core/a/a/a."<init>":(Landroid/content/Context;[Lryey/easer/core/a/a/a/b;)V
      20: return

  protected void a(java.lang.String, ryey.easer.core.a.j);
    Code:
       0: aload_2
       1: invokevirtual #29                 // Method ryey/easer/core/a/j.a:()Ljava/lang/String;
       4: astore_2
       5: aload_0
       6: invokevirtual #32                 // Method c:()Ljava/util/List;
       9: invokestatic  #38                 // Method ryey/easer/core/a/a/f.b:(Ljava/util/List;)Ljava/util/Map;
      12: aload_1
      13: invokeinterface #44,  2           // InterfaceMethod java/util/Map.get:(Ljava/lang/Object;)Ljava/lang/Object;
      18: checkcast     #46                 // class java/util/List
      21: astore_3
      22: aload_3
      23: ifnull        68
      26: aload_3
      27: invokeinterface #50,  1           // InterfaceMethod java/util/List.iterator:()Ljava/util/Iterator;
      32: astore_3
      33: aload_3
      34: invokeinterface #56,  1           // InterfaceMethod java/util/Iterator.hasNext:()Z
      39: ifeq          68
      42: aload_3
      43: invokeinterface #60,  1           // InterfaceMethod java/util/Iterator.next:()Ljava/lang/Object;
      48: checkcast     #26                 // class ryey/easer/core/a/j
      51: astore        4
      53: aload         4
      55: aload_2
      56: invokevirtual #63                 // Method ryey/easer/core/a/j.c:(Ljava/lang/String;)V
      59: aload_0
      60: aload         4
      62: invokevirtual #66                 // Method b:(Lryey/easer/core/a/f;)V
      65: goto          33
      68: new           #68                 // class ryey/easer/core/a/a/d
      71: dup
      72: aload_0
      73: getfield      #71                 // Field a:Landroid/content/Context;
      76: invokespecial #72                 // Method ryey/easer/core/a/a/d."<init>":(Landroid/content/Context;)V
      79: astore_3
      80: new           #74                 // class ryey/easer/plugins/operation/n/d
      83: dup
      84: invokespecial #76                 // Method ryey/easer/plugins/operation/n/d."<init>":()V
      87: invokevirtual #77                 // Method ryey/easer/plugins/operation/n/d.a:()Ljava/lang/String;
      90: astore        4
      92: aload_3
      93: invokevirtual #79                 // Method ryey/easer/core/a/a/d.a:()Ljava/util/List;
      96: invokeinterface #50,  1           // InterfaceMethod java/util/List.iterator:()Ljava/util/Iterator;
     101: astore        5
     103: aload         5
     105: invokeinterface #56,  1           // InterfaceMethod java/util/Iterator.hasNext:()Z
     110: ifeq          418
     113: aload         5
     115: invokeinterface #60,  1           // InterfaceMethod java/util/Iterator.next:()Ljava/lang/Object;
     120: checkcast     #81                 // class java/lang/String
     123: astore        6
     125: aload_3
     126: aload         6
     128: invokevirtual #84                 // Method ryey/easer/core/a/a/d.a:(Ljava/lang/String;)Lryey/easer/core/a/f;
     131: checkcast     #86                 // class ryey/easer/core/a/g
     134: astore        7
     136: aload         7
     138: aload         4
     140: invokevirtual #89                 // Method ryey/easer/core/a/g.b:(Ljava/lang/String;)Ljava/util/Collection;
     143: astore        9
     145: aload         9
     147: ifnull        103
     150: new           #91                 // class java/util/ArrayList
     153: dup
     154: invokespecial #92                 // Method java/util/ArrayList."<init>":()V
     157: astore        8
     159: aload         9
     161: invokeinterface #95,  1           // InterfaceMethod java/util/Collection.iterator:()Ljava/util/Iterator;
     166: astore        10
     168: aload         10
     170: invokeinterface #56,  1           // InterfaceMethod java/util/Iterator.hasNext:()Z
     175: ifeq          266
     178: aload         10
     180: invokeinterface #60,  1           // InterfaceMethod java/util/Iterator.next:()Ljava/lang/Object;
     185: checkcast     #97                 // class ryey/easer/core/a/h
     188: astore        11
     190: aload         11
     192: invokevirtual #99                 // Method ryey/easer/core/a/h.a:()Z
     195: ifeq          208
     198: new           #101                // class java/lang/IllegalStateException
     201: dup
     202: ldc           #103                // String StateControlOperationData should not be remote
     204: invokespecial #105                // Method java/lang/IllegalStateException."<init>":(Ljava/lang/String;)V
     207: athrow
     208: aload         11
     210: getfield      #108                // Field ryey/easer/core/a/h.a:Lryey/easer/commons/local_plugin/c/b;
     213: astore        11
     215: getstatic     #110                // Field c:Z
     218: ifne          234
     221: aload         11
     223: ifnonnull     234
     226: new           #112                // class java/lang/AssertionError
     229: dup
     230: invokespecial #113                // Method java/lang/AssertionError."<init>":()V
     233: athrow
     234: aload         11
     236: checkcast     #115                // class ryey/easer/plugins/operation/n/c
     239: astore        11
     241: aload_1
     242: aload         11
     244: getfield      #118                // Field ryey/easer/plugins/operation/n/c.a:Ljava/lang/String;
     247: invokevirtual #122                // Method java/lang/String.equals:(Ljava/lang/Object;)Z
     250: ifeq          168
     253: aload         8
     255: aload         11
     257: invokeinterface #125,  2          // InterfaceMethod java/util/List.add:(Ljava/lang/Object;)Z
     262: pop
     263: goto          168
     266: aload         8
     268: invokeinterface #129,  1          // InterfaceMethod java/util/List.size:()I
     273: ifle          103
     276: new           #91                 // class java/util/ArrayList
     279: dup
     280: aload         9
     282: invokeinterface #130,  1          // InterfaceMethod java/util/Collection.size:()I
     287: invokespecial #133                // Method java/util/ArrayList."<init>":(I)V
     290: astore        10
     292: aload         9
     294: invokeinterface #95,  1           // InterfaceMethod java/util/Collection.iterator:()Ljava/util/Iterator;
     299: astore        9
     301: aload         9
     303: invokeinterface #56,  1           // InterfaceMethod java/util/Iterator.hasNext:()Z
     308: ifeq          335
     311: aload         10
     313: aload         9
     315: invokeinterface #60,  1           // InterfaceMethod java/util/Iterator.next:()Ljava/lang/Object;
     320: checkcast     #97                 // class ryey/easer/core/a/h
     323: getfield      #108                // Field ryey/easer/core/a/h.a:Lryey/easer/commons/local_plugin/c/b;
     326: invokeinterface #134,  2          // InterfaceMethod java/util/Collection.add:(Ljava/lang/Object;)Z
     331: pop
     332: goto          301
     335: aload         8
     337: invokeinterface #50,  1           // InterfaceMethod java/util/List.iterator:()Ljava/util/Iterator;
     342: astore        8
     344: aload         8
     346: invokeinterface #56,  1           // InterfaceMethod java/util/Iterator.hasNext:()Z
     351: ifeq          397
     354: aload         8
     356: invokeinterface #60,  1           // InterfaceMethod java/util/Iterator.next:()Ljava/lang/Object;
     361: checkcast     #115                // class ryey/easer/plugins/operation/n/c
     364: astore        9
     366: aload         10
     368: aload         9
     370: invokeinterface #137,  2          // InterfaceMethod java/util/Collection.remove:(Ljava/lang/Object;)Z
     375: pop
     376: aload         10
     378: new           #115                // class ryey/easer/plugins/operation/n/c
     381: dup
     382: aload         9
     384: aload_2
     385: invokespecial #140                // Method ryey/easer/plugins/operation/n/c."<init>":(Lryey/easer/plugins/operation/n/c;Ljava/lang/String;)V
     388: invokeinterface #134,  2          // InterfaceMethod java/util/Collection.add:(Ljava/lang/Object;)Z
     393: pop
     394: goto          344
     397: aload         7
     399: aload         4
     401: aload         10
     403: invokevirtual #143                // Method ryey/easer/core/a/g.a:(Ljava/lang/String;Ljava/util/Collection;)V
     406: aload_3
     407: aload         6
     409: aload         7
     411: invokevirtual #146                // Method ryey/easer/core/a/a/d.a:(Ljava/lang/String;Lryey/easer/core/a/f;)Z
     414: pop
     415: goto          103
     418: return

  public java.util.List<ryey.easer.core.a.k> b();
    Code:
       0: aload_0
       1: invokevirtual #32                 // Method c:()Ljava/util/List;
       4: invokestatic  #149                // Method ryey/easer/core/a/a/f.a:(Ljava/util/List;)Ljava/util/List;
       7: areturn

  protected void b(java.lang.String, ryey.easer.core.a.f);
    Code:
       0: aload_0
       1: aload_1
       2: aload_2
       3: checkcast     #26                 // class ryey/easer/core/a/j
       6: invokevirtual #154                // Method a:(Ljava/lang/String;Lryey/easer/core/a/j;)V
       9: return

  boolean b(java.lang.String);
    Code:
       0: aload_0
       1: invokevirtual #32                 // Method c:()Ljava/util/List;
       4: invokeinterface #50,  1           // InterfaceMethod java/util/List.iterator:()Ljava/util/Iterator;
       9: astore_2
      10: aload_2
      11: invokeinterface #56,  1           // InterfaceMethod java/util/Iterator.hasNext:()Z
      16: ifeq          40
      19: aload_1
      20: aload_2
      21: invokeinterface #60,  1           // InterfaceMethod java/util/Iterator.next:()Ljava/lang/Object;
      26: checkcast     #26                 // class ryey/easer/core/a/j
      29: invokevirtual #158                // Method ryey/easer/core/a/j.j:()Ljava/lang/String;
      32: invokevirtual #122                // Method java/lang/String.equals:(Ljava/lang/Object;)Z
      35: ifeq          10
      38: iconst_0
      39: ireturn
      40: new           #68                 // class ryey/easer/core/a/a/d
      43: dup
      44: aload_0
      45: getfield      #71                 // Field a:Landroid/content/Context;
      48: invokespecial #72                 // Method ryey/easer/core/a/a/d."<init>":(Landroid/content/Context;)V
      51: astore_2
      52: new           #74                 // class ryey/easer/plugins/operation/n/d
      55: dup
      56: invokespecial #76                 // Method ryey/easer/plugins/operation/n/d."<init>":()V
      59: invokevirtual #77                 // Method ryey/easer/plugins/operation/n/d.a:()Ljava/lang/String;
      62: astore_3
      63: aload_2
      64: invokevirtual #79                 // Method ryey/easer/core/a/a/d.a:()Ljava/util/List;
      67: invokeinterface #50,  1           // InterfaceMethod java/util/List.iterator:()Ljava/util/Iterator;
      72: astore        4
      74: aload         4
      76: invokeinterface #56,  1           // InterfaceMethod java/util/Iterator.hasNext:()Z
      81: ifeq          204
      84: aload_2
      85: aload         4
      87: invokeinterface #60,  1           // InterfaceMethod java/util/Iterator.next:()Ljava/lang/Object;
      92: checkcast     #81                 // class java/lang/String
      95: invokevirtual #84                 // Method ryey/easer/core/a/a/d.a:(Ljava/lang/String;)Lryey/easer/core/a/f;
      98: checkcast     #86                 // class ryey/easer/core/a/g
     101: aload_3
     102: invokevirtual #89                 // Method ryey/easer/core/a/g.b:(Ljava/lang/String;)Ljava/util/Collection;
     105: astore        5
     107: aload         5
     109: ifnull        74
     112: aload         5
     114: invokeinterface #95,  1           // InterfaceMethod java/util/Collection.iterator:()Ljava/util/Iterator;
     119: astore        5
     121: aload         5
     123: invokeinterface #56,  1           // InterfaceMethod java/util/Iterator.hasNext:()Z
     128: ifeq          74
     131: aload         5
     133: invokeinterface #60,  1           // InterfaceMethod java/util/Iterator.next:()Ljava/lang/Object;
     138: checkcast     #97                 // class ryey/easer/core/a/h
     141: astore        6
     143: aload         6
     145: invokevirtual #99                 // Method ryey/easer/core/a/h.a:()Z
     148: ifeq          161
     151: new           #101                // class java/lang/IllegalStateException
     154: dup
     155: ldc           #103                // String StateControlOperationData should not be remote
     157: invokespecial #105                // Method java/lang/IllegalStateException."<init>":(Ljava/lang/String;)V
     160: athrow
     161: aload         6
     163: getfield      #108                // Field ryey/easer/core/a/h.a:Lryey/easer/commons/local_plugin/c/b;
     166: checkcast     #115                // class ryey/easer/plugins/operation/n/c
     169: astore        6
     171: getstatic     #110                // Field c:Z
     174: ifne          190
     177: aload         6
     179: ifnonnull     190
     182: new           #112                // class java/lang/AssertionError
     185: dup
     186: invokespecial #113                // Method java/lang/AssertionError."<init>":()V
     189: athrow
     190: aload_1
     191: aload         6
     193: getfield      #118                // Field ryey/easer/plugins/operation/n/c.a:Ljava/lang/String;
     196: invokevirtual #122                // Method java/lang/String.equals:(Ljava/lang/Object;)Z
     199: ifeq          121
     202: iconst_0
     203: ireturn
     204: iconst_1
     205: ireturn

  java.util.List<ryey.easer.core.a.j> c();
    Code:
       0: aload_0
       1: getfield      #161                // Field b:[Lryey/easer/core/a/a/a/b;
       4: checkcast     #163                // class "[Lryey/easer/core/a/a/a/h;"
       7: astore        4
       9: aload         4
      11: arraylength
      12: istore_2
      13: aconst_null
      14: astore_3
      15: iconst_0
      16: istore_1
      17: iload_1
      18: iload_2
      19: if_icmpge     64
      22: aload         4
      24: iload_1
      25: aaload
      26: astore        5
      28: aload_3
      29: ifnonnull     43
      32: aload         5
      34: invokeinterface #165,  1          // InterfaceMethod ryey/easer/core/a/a/a/h.b:()Ljava/util/List;
      39: astore_3
      40: goto          57
      43: aload_3
      44: aload         5
      46: invokeinterface #165,  1          // InterfaceMethod ryey/easer/core/a/a/a/h.b:()Ljava/util/List;
      51: invokeinterface #169,  2          // InterfaceMethod java/util/List.addAll:(Ljava/util/Collection;)Z
      56: pop
      57: iload_1
      58: iconst_1
      59: iadd
      60: istore_1
      61: goto          17
      64: aload_3
      65: areturn
}
