class ryey.easer.core.a.a.f$a extends java.io.IOException {
  ryey.easer.core.a.a.f$a(java.io.IOException, java.lang.String, ryey.easer.core.a.a.f$1);
    Code:
       0: aload_0
       1: aload_1
       2: aload_2
       3: invokespecial #19                 // Method "<init>":(Ljava/io/IOException;Ljava/lang/String;)V
       6: return

  static java.lang.String a(ryey.easer.core.a.a.f$a);
    Code:
       0: aload_0
       1: getfield      #15                 // Field a:Ljava/lang/String;
       4: areturn
}
