public class ryey.easer.core.a.a.f {
  static java.util.List<ryey.easer.core.a.k> a(java.util.List<ryey.easer.core.a.j>);
    Code:
       0: aload_0
       1: invokestatic  #14                 // Method b:(Ljava/util/List;)Ljava/util/Map;
       4: aconst_null
       5: invokestatic  #17                 // Method a:(Ljava/util/Map;Ljava/lang/String;)Ljava/util/List;
       8: areturn

  public static boolean a(android.content.Context);
    Code:
       0: iconst_4
       1: anewarray     #70                 // class ryey/easer/core/a/a/a
       4: astore_3
       5: aload_3
       6: iconst_0
       7: new           #88                 // class ryey/easer/core/a/a/d
      10: dup
      11: aload_0
      12: invokespecial #91                 // Method ryey/easer/core/a/a/d."<init>":(Landroid/content/Context;)V
      15: aastore
      16: aload_3
      17: iconst_1
      18: new           #93                 // class ryey/easer/core/a/a/e
      21: dup
      22: aload_0
      23: invokespecial #94                 // Method ryey/easer/core/a/a/e."<init>":(Landroid/content/Context;)V
      26: aastore
      27: aload_3
      28: iconst_2
      29: new           #96                 // class ryey/easer/core/a/a/c
      32: dup
      33: aload_0
      34: invokespecial #97                 // Method ryey/easer/core/a/a/c."<init>":(Landroid/content/Context;)V
      37: aastore
      38: aload_3
      39: iconst_3
      40: new           #99                 // class ryey/easer/core/a/a/b
      43: dup
      44: aload_0
      45: invokespecial #100                // Method ryey/easer/core/a/a/b."<init>":(Landroid/content/Context;)V
      48: aastore
      49: aload_3
      50: arraylength
      51: istore_2
      52: iconst_0
      53: istore_1
      54: iload_1
      55: iload_2
      56: if_icmpge     123
      59: aload_3
      60: iload_1
      61: aaload
      62: astore        4
      64: aload         4
      66: invokevirtual #73                 // Method ryey/easer/core/a/a/a.a:()Ljava/util/List;
      69: invokeinterface #38,  1           // InterfaceMethod java/util/List.iterator:()Ljava/util/Iterator;
      74: astore        5
      76: aload         5
      78: invokeinterface #44,  1           // InterfaceMethod java/util/Iterator.hasNext:()Z
      83: ifeq          116
      86: aload         4
      88: aload         5
      90: invokeinterface #48,  1           // InterfaceMethod java/util/Iterator.next:()Ljava/lang/Object;
      95: checkcast     #75                 // class java/lang/String
      98: invokevirtual #78                 // Method ryey/easer/core/a/a/a.a:(Ljava/lang/String;)Lryey/easer/core/a/f;
     101: checkcast     #102                // class ryey/easer/core/a/m
     104: invokeinterface #106,  1          // InterfaceMethod ryey/easer/core/a/m.d:()I
     109: bipush        11
     111: if_icmpge     76
     114: iconst_1
     115: ireturn
     116: iload_1
     117: iconst_1
     118: iadd
     119: istore_1
     120: goto          54
     123: new           #108                // class java/io/File
     126: dup
     127: aload_0
     128: invokevirtual #114                // Method android/content/Context.getFilesDir:()Ljava/io/File;
     131: ldc           #116                // String event
     133: invokespecial #119                // Method java/io/File."<init>":(Ljava/io/File;Ljava/lang/String;)V
     136: astore_3
     137: new           #108                // class java/io/File
     140: dup
     141: aload_0
     142: invokevirtual #114                // Method android/content/Context.getFilesDir:()Ljava/io/File;
     145: ldc           #121                // String scenario
     147: invokespecial #119                // Method java/io/File."<init>":(Ljava/io/File;Ljava/lang/String;)V
     150: astore        4
     152: new           #108                // class java/io/File
     155: dup
     156: aload_0
     157: invokevirtual #114                // Method android/content/Context.getFilesDir:()Ljava/io/File;
     160: ldc           #123                // String script
     162: invokespecial #119                // Method java/io/File."<init>":(Ljava/io/File;Ljava/lang/String;)V
     165: astore_0
     166: aload_3
     167: invokevirtual #126                // Method java/io/File.exists:()Z
     170: ifeq          183
     173: aload         4
     175: invokevirtual #126                // Method java/io/File.exists:()Z
     178: ifeq          183
     181: iconst_1
     182: ireturn
     183: aload         4
     185: invokevirtual #126                // Method java/io/File.exists:()Z
     188: ifeq          200
     191: aload_0
     192: invokevirtual #126                // Method java/io/File.exists:()Z
     195: ifeq          200
     198: iconst_1
     199: ireturn
     200: iconst_0
     201: ireturn

  static java.util.Map<java.lang.String, java.util.List<ryey.easer.core.a.j>> b(java.util.List<ryey.easer.core.a.j>);
    Code:
       0: new           #136                // class java/util/HashMap
       3: dup
       4: invokespecial #137                // Method java/util/HashMap."<init>":()V
       7: astore_1
       8: aload_0
       9: invokeinterface #38,  1           // InterfaceMethod java/util/List.iterator:()Ljava/util/Iterator;
      14: astore_0
      15: aload_0
      16: invokeinterface #44,  1           // InterfaceMethod java/util/Iterator.hasNext:()Z
      21: ifeq          88
      24: aload_0
      25: invokeinterface #48,  1           // InterfaceMethod java/util/Iterator.next:()Ljava/lang/Object;
      30: checkcast     #50                 // class ryey/easer/core/a/j
      33: astore_2
      34: aload_1
      35: aload_2
      36: invokevirtual #140                // Method ryey/easer/core/a/j.j:()Ljava/lang/String;
      39: invokeinterface #143,  2          // InterfaceMethod java/util/Map.containsKey:(Ljava/lang/Object;)Z
      44: ifne          65
      47: aload_1
      48: aload_2
      49: invokevirtual #140                // Method ryey/easer/core/a/j.j:()Ljava/lang/String;
      52: new           #145                // class java/util/ArrayList
      55: dup
      56: invokespecial #146                // Method java/util/ArrayList."<init>":()V
      59: invokeinterface #150,  3          // InterfaceMethod java/util/Map.put:(Ljava/lang/Object;Ljava/lang/Object;)Ljava/lang/Object;
      64: pop
      65: aload_1
      66: aload_2
      67: invokevirtual #140                // Method ryey/easer/core/a/j.j:()Ljava/lang/String;
      70: invokeinterface #32,  2           // InterfaceMethod java/util/Map.get:(Ljava/lang/Object;)Ljava/lang/Object;
      75: checkcast     #34                 // class java/util/List
      78: aload_2
      79: invokeinterface #64,  2           // InterfaceMethod java/util/List.add:(Ljava/lang/Object;)Z
      84: pop
      85: goto          15
      88: aload_1
      89: areturn

  public static boolean b(android.content.Context);
    Code:
       0: aload_0
       1: ldc           #152                // int 2131624144
       3: iconst_0
       4: invokestatic  #158                // Method android/widget/Toast.makeText:(Landroid/content/Context;II)Landroid/widget/Toast;
       7: invokevirtual #161                // Method android/widget/Toast.show:()V
      10: new           #108                // class java/io/File
      13: dup
      14: aload_0
      15: invokevirtual #114                // Method android/content/Context.getFilesDir:()Ljava/io/File;
      18: ldc           #116                // String event
      20: invokespecial #119                // Method java/io/File."<init>":(Ljava/io/File;Ljava/lang/String;)V
      23: astore_2
      24: new           #108                // class java/io/File
      27: dup
      28: aload_0
      29: invokevirtual #114                // Method android/content/Context.getFilesDir:()Ljava/io/File;
      32: ldc           #121                // String scenario
      34: invokespecial #119                // Method java/io/File."<init>":(Ljava/io/File;Ljava/lang/String;)V
      37: astore_3
      38: new           #108                // class java/io/File
      41: dup
      42: aload_0
      43: invokevirtual #114                // Method android/content/Context.getFilesDir:()Ljava/io/File;
      46: ldc           #123                // String script
      48: invokespecial #119                // Method java/io/File."<init>":(Ljava/io/File;Ljava/lang/String;)V
      51: astore        4
      53: aload_2
      54: invokestatic  #163                // Method a:(Ljava/io/File;)Z
      57: ifeq          99
      60: aload_3
      61: invokestatic  #163                // Method a:(Ljava/io/File;)Z
      64: ifeq          99
      67: aload_2
      68: aload         4
      70: invokevirtual #166                // Method java/io/File.renameTo:(Ljava/io/File;)Z
      73: ifne          99
      76: ldc           #168                // String Failed to rename \"event\" directory to \"script\".
      78: astore_2
      79: aload_2
      80: iconst_0
      81: anewarray     #4                  // class java/lang/Object
      84: invokestatic  #173                // Method com/b/a/i.b:(Ljava/lang/String;[Ljava/lang/Object;)V
      87: aload_0
      88: ldc           #174                // int 2131624141
      90: iconst_1
      91: invokestatic  #158                // Method android/widget/Toast.makeText:(Landroid/content/Context;II)Landroid/widget/Toast;
      94: invokevirtual #161                // Method android/widget/Toast.show:()V
      97: iconst_0
      98: ireturn
      99: aload_3
     100: invokestatic  #163                // Method a:(Ljava/io/File;)Z
     103: ifeq          155
     106: aload         4
     108: invokestatic  #163                // Method a:(Ljava/io/File;)Z
     111: ifeq          155
     114: aload_2
     115: invokevirtual #126                // Method java/io/File.exists:()Z
     118: ifeq          141
     121: aload_2
     122: invokestatic  #163                // Method a:(Ljava/io/File;)Z
     125: ifne          141
     128: aload_2
     129: invokevirtual #177                // Method java/io/File.delete:()Z
     132: ifne          141
     135: ldc           #179                // String Failed to delete empty directory \"event\".
     137: astore_2
     138: goto          79
     141: aload_3
     142: aload_2
     143: invokevirtual #166                // Method java/io/File.renameTo:(Ljava/io/File;)Z
     146: ifne          155
     149: ldc           #181                // String Failed to rename \"scenario\" directory to \"event\".
     151: astore_2
     152: goto          79
     155: iconst_4
     156: anewarray     #70                 // class ryey/easer/core/a/a/a
     159: astore_3
     160: aload_3
     161: iconst_0
     162: new           #88                 // class ryey/easer/core/a/a/d
     165: dup
     166: aload_0
     167: invokespecial #91                 // Method ryey/easer/core/a/a/d."<init>":(Landroid/content/Context;)V
     170: aastore
     171: aload_3
     172: iconst_1
     173: new           #93                 // class ryey/easer/core/a/a/e
     176: dup
     177: aload_0
     178: invokespecial #94                 // Method ryey/easer/core/a/a/e."<init>":(Landroid/content/Context;)V
     181: aastore
     182: aload_3
     183: iconst_2
     184: new           #96                 // class ryey/easer/core/a/a/c
     187: dup
     188: aload_0
     189: invokespecial #97                 // Method ryey/easer/core/a/a/c."<init>":(Landroid/content/Context;)V
     192: aastore
     193: aload_3
     194: iconst_3
     195: new           #99                 // class ryey/easer/core/a/a/b
     198: dup
     199: aload_0
     200: invokespecial #100                // Method ryey/easer/core/a/a/b."<init>":(Landroid/content/Context;)V
     203: aastore
     204: iconst_0
     205: istore_1
     206: iload_1
     207: aload_3
     208: arraylength
     209: if_icmpge     280
     212: aload_3
     213: iload_1
     214: aaload
     215: astore        4
     217: iconst_4
     218: anewarray     #75                 // class java/lang/String
     221: dup
     222: iconst_0
     223: ldc           #183                // String Profile
     225: aastore
     226: dup
     227: iconst_1
     228: ldc           #185                // String Script
     230: aastore
     231: dup
     232: iconst_2
     233: ldc           #187                // String Scenario
     235: aastore
     236: dup
     237: iconst_3
     238: ldc           #189                // String Condition
     240: aastore
     241: iload_1
     242: aaload
     243: astore_2
     244: aload         4
     246: invokestatic  #191                // Method a:(Lryey/easer/core/a/a/a;)V
     249: iload_1
     250: iconst_1
     251: iadd
     252: istore_1
     253: goto          206
     256: astore_3
     257: ldc           #193                // String Failed to convert <%s> <%s> to new format.
     259: iconst_2
     260: anewarray     #4                  // class java/lang/Object
     263: dup
     264: iconst_0
     265: aload_2
     266: aastore
     267: dup
     268: iconst_1
     269: aload_3
     270: invokestatic  #196                // Method ryey/easer/core/a/a/f$a.a:(Lryey/easer/core/a/a/f$a;)Ljava/lang/String;
     273: aastore
     274: invokestatic  #173                // Method com/b/a/i.b:(Ljava/lang/String;[Ljava/lang/Object;)V
     277: goto          87
     280: aload_0
     281: ldc           #197                // int 2131624143
     283: iconst_1
     284: invokestatic  #158                // Method android/widget/Toast.makeText:(Landroid/content/Context;II)Landroid/widget/Toast;
     287: invokevirtual #161                // Method android/widget/Toast.show:()V
     290: iconst_1
     291: ireturn
    Exception table:
       from    to  target type
         244   249   256   Class ryey/easer/core/a/a/f$a
}
