public class android.arch.lifecycle.SingleGeneratedAdapterObserver implements android.arch.lifecycle.GenericLifecycleObserver {
  android.arch.lifecycle.SingleGeneratedAdapterObserver(android.arch.lifecycle.b);
    Code:
       0: aload_0
       1: invokespecial #13                 // Method java/lang/Object."<init>":()V
       4: aload_0
       5: aload_1
       6: putfield      #15                 // Field a:Landroid/arch/lifecycle/b;
       9: return

  public void a(android.arch.lifecycle.e, android.arch.lifecycle.c$a);
    Code:
       0: aload_0
       1: getfield      #15                 // Field a:Landroid/arch/lifecycle/b;
       4: aload_1
       5: aload_2
       6: iconst_0
       7: aconst_null
       8: invokeinterface #22,  5           // InterfaceMethod android/arch/lifecycle/b.a:(Landroid/arch/lifecycle/e;Landroid/arch/lifecycle/c$a;ZLandroid/arch/lifecycle/i;)V
      13: aload_0
      14: getfield      #15                 // Field a:Landroid/arch/lifecycle/b;
      17: aload_1
      18: aload_2
      19: iconst_1
      20: aconst_null
      21: invokeinterface #22,  5           // InterfaceMethod android/arch/lifecycle/b.a:(Landroid/arch/lifecycle/e;Landroid/arch/lifecycle/c$a;ZLandroid/arch/lifecycle/i;)V
      26: return
}
