public class android.support.v4.view.a.b$a {
  public static final android.support.v4.view.a.b$a A;

  public static final android.support.v4.view.a.b$a B;

  public static final android.support.v4.view.a.b$a C;

  public static final android.support.v4.view.a.b$a D;

  public static final android.support.v4.view.a.b$a a;

  public static final android.support.v4.view.a.b$a b;

  public static final android.support.v4.view.a.b$a c;

  public static final android.support.v4.view.a.b$a d;

  public static final android.support.v4.view.a.b$a e;

  public static final android.support.v4.view.a.b$a f;

  public static final android.support.v4.view.a.b$a g;

  public static final android.support.v4.view.a.b$a h;

  public static final android.support.v4.view.a.b$a i;

  public static final android.support.v4.view.a.b$a j;

  public static final android.support.v4.view.a.b$a k;

  public static final android.support.v4.view.a.b$a l;

  public static final android.support.v4.view.a.b$a m;

  public static final android.support.v4.view.a.b$a n;

  public static final android.support.v4.view.a.b$a o;

  public static final android.support.v4.view.a.b$a p;

  public static final android.support.v4.view.a.b$a q;

  public static final android.support.v4.view.a.b$a r;

  public static final android.support.v4.view.a.b$a s;

  public static final android.support.v4.view.a.b$a t;

  public static final android.support.v4.view.a.b$a u;

  public static final android.support.v4.view.a.b$a v;

  public static final android.support.v4.view.a.b$a w;

  public static final android.support.v4.view.a.b$a x;

  public static final android.support.v4.view.a.b$a y;

  public static final android.support.v4.view.a.b$a z;

  final java.lang.Object E;

  static {};
    Code:
       0: aconst_null
       1: astore_1
       2: new           #2                  // class android/support/v4/view/a/b$a
       5: dup
       6: iconst_1
       7: aconst_null
       8: invokespecial #45                 // Method "<init>":(ILjava/lang/CharSequence;)V
      11: putstatic     #47                 // Field a:Landroid/support/v4/view/a/b$a;
      14: new           #2                  // class android/support/v4/view/a/b$a
      17: dup
      18: iconst_2
      19: aconst_null
      20: invokespecial #45                 // Method "<init>":(ILjava/lang/CharSequence;)V
      23: putstatic     #49                 // Field b:Landroid/support/v4/view/a/b$a;
      26: new           #2                  // class android/support/v4/view/a/b$a
      29: dup
      30: iconst_4
      31: aconst_null
      32: invokespecial #45                 // Method "<init>":(ILjava/lang/CharSequence;)V
      35: putstatic     #51                 // Field c:Landroid/support/v4/view/a/b$a;
      38: new           #2                  // class android/support/v4/view/a/b$a
      41: dup
      42: bipush        8
      44: aconst_null
      45: invokespecial #45                 // Method "<init>":(ILjava/lang/CharSequence;)V
      48: putstatic     #53                 // Field d:Landroid/support/v4/view/a/b$a;
      51: new           #2                  // class android/support/v4/view/a/b$a
      54: dup
      55: bipush        16
      57: aconst_null
      58: invokespecial #45                 // Method "<init>":(ILjava/lang/CharSequence;)V
      61: putstatic     #55                 // Field e:Landroid/support/v4/view/a/b$a;
      64: new           #2                  // class android/support/v4/view/a/b$a
      67: dup
      68: bipush        32
      70: aconst_null
      71: invokespecial #45                 // Method "<init>":(ILjava/lang/CharSequence;)V
      74: putstatic     #57                 // Field f:Landroid/support/v4/view/a/b$a;
      77: new           #2                  // class android/support/v4/view/a/b$a
      80: dup
      81: bipush        64
      83: aconst_null
      84: invokespecial #45                 // Method "<init>":(ILjava/lang/CharSequence;)V
      87: putstatic     #59                 // Field g:Landroid/support/v4/view/a/b$a;
      90: new           #2                  // class android/support/v4/view/a/b$a
      93: dup
      94: sipush        128
      97: aconst_null
      98: invokespecial #45                 // Method "<init>":(ILjava/lang/CharSequence;)V
     101: putstatic     #61                 // Field h:Landroid/support/v4/view/a/b$a;
     104: new           #2                  // class android/support/v4/view/a/b$a
     107: dup
     108: sipush        256
     111: aconst_null
     112: invokespecial #45                 // Method "<init>":(ILjava/lang/CharSequence;)V
     115: putstatic     #63                 // Field i:Landroid/support/v4/view/a/b$a;
     118: new           #2                  // class android/support/v4/view/a/b$a
     121: dup
     122: sipush        512
     125: aconst_null
     126: invokespecial #45                 // Method "<init>":(ILjava/lang/CharSequence;)V
     129: putstatic     #65                 // Field j:Landroid/support/v4/view/a/b$a;
     132: new           #2                  // class android/support/v4/view/a/b$a
     135: dup
     136: sipush        1024
     139: aconst_null
     140: invokespecial #45                 // Method "<init>":(ILjava/lang/CharSequence;)V
     143: putstatic     #67                 // Field k:Landroid/support/v4/view/a/b$a;
     146: new           #2                  // class android/support/v4/view/a/b$a
     149: dup
     150: sipush        2048
     153: aconst_null
     154: invokespecial #45                 // Method "<init>":(ILjava/lang/CharSequence;)V
     157: putstatic     #69                 // Field l:Landroid/support/v4/view/a/b$a;
     160: new           #2                  // class android/support/v4/view/a/b$a
     163: dup
     164: sipush        4096
     167: aconst_null
     168: invokespecial #45                 // Method "<init>":(ILjava/lang/CharSequence;)V
     171: putstatic     #71                 // Field m:Landroid/support/v4/view/a/b$a;
     174: new           #2                  // class android/support/v4/view/a/b$a
     177: dup
     178: sipush        8192
     181: aconst_null
     182: invokespecial #45                 // Method "<init>":(ILjava/lang/CharSequence;)V
     185: putstatic     #73                 // Field n:Landroid/support/v4/view/a/b$a;
     188: new           #2                  // class android/support/v4/view/a/b$a
     191: dup
     192: sipush        16384
     195: aconst_null
     196: invokespecial #45                 // Method "<init>":(ILjava/lang/CharSequence;)V
     199: putstatic     #75                 // Field o:Landroid/support/v4/view/a/b$a;
     202: new           #2                  // class android/support/v4/view/a/b$a
     205: dup
     206: ldc           #76                 // int 32768
     208: aconst_null
     209: invokespecial #45                 // Method "<init>":(ILjava/lang/CharSequence;)V
     212: putstatic     #78                 // Field p:Landroid/support/v4/view/a/b$a;
     215: new           #2                  // class android/support/v4/view/a/b$a
     218: dup
     219: ldc           #79                 // int 65536
     221: aconst_null
     222: invokespecial #45                 // Method "<init>":(ILjava/lang/CharSequence;)V
     225: putstatic     #81                 // Field q:Landroid/support/v4/view/a/b$a;
     228: new           #2                  // class android/support/v4/view/a/b$a
     231: dup
     232: ldc           #82                 // int 131072
     234: aconst_null
     235: invokespecial #45                 // Method "<init>":(ILjava/lang/CharSequence;)V
     238: putstatic     #84                 // Field r:Landroid/support/v4/view/a/b$a;
     241: new           #2                  // class android/support/v4/view/a/b$a
     244: dup
     245: ldc           #85                 // int 262144
     247: aconst_null
     248: invokespecial #45                 // Method "<init>":(ILjava/lang/CharSequence;)V
     251: putstatic     #87                 // Field s:Landroid/support/v4/view/a/b$a;
     254: new           #2                  // class android/support/v4/view/a/b$a
     257: dup
     258: ldc           #88                 // int 524288
     260: aconst_null
     261: invokespecial #45                 // Method "<init>":(ILjava/lang/CharSequence;)V
     264: putstatic     #90                 // Field t:Landroid/support/v4/view/a/b$a;
     267: new           #2                  // class android/support/v4/view/a/b$a
     270: dup
     271: ldc           #91                 // int 1048576
     273: aconst_null
     274: invokespecial #45                 // Method "<init>":(ILjava/lang/CharSequence;)V
     277: putstatic     #93                 // Field u:Landroid/support/v4/view/a/b$a;
     280: new           #2                  // class android/support/v4/view/a/b$a
     283: dup
     284: ldc           #94                 // int 2097152
     286: aconst_null
     287: invokespecial #45                 // Method "<init>":(ILjava/lang/CharSequence;)V
     290: putstatic     #96                 // Field v:Landroid/support/v4/view/a/b$a;
     293: getstatic     #102                // Field android/os/Build$VERSION.SDK_INT:I
     296: bipush        23
     298: if_icmplt     308
     301: getstatic     #108                // Field android/view/accessibility/AccessibilityNodeInfo$AccessibilityAction.ACTION_SHOW_ON_SCREEN:Landroid/view/accessibility/AccessibilityNodeInfo$AccessibilityAction;
     304: astore_0
     305: goto          310
     308: aconst_null
     309: astore_0
     310: new           #2                  // class android/support/v4/view/a/b$a
     313: dup
     314: aload_0
     315: invokespecial #111                // Method "<init>":(Ljava/lang/Object;)V
     318: putstatic     #113                // Field w:Landroid/support/v4/view/a/b$a;
     321: getstatic     #102                // Field android/os/Build$VERSION.SDK_INT:I
     324: bipush        23
     326: if_icmplt     336
     329: getstatic     #116                // Field android/view/accessibility/AccessibilityNodeInfo$AccessibilityAction.ACTION_SCROLL_TO_POSITION:Landroid/view/accessibility/AccessibilityNodeInfo$AccessibilityAction;
     332: astore_0
     333: goto          338
     336: aconst_null
     337: astore_0
     338: new           #2                  // class android/support/v4/view/a/b$a
     341: dup
     342: aload_0
     343: invokespecial #111                // Method "<init>":(Ljava/lang/Object;)V
     346: putstatic     #118                // Field x:Landroid/support/v4/view/a/b$a;
     349: getstatic     #102                // Field android/os/Build$VERSION.SDK_INT:I
     352: bipush        23
     354: if_icmplt     364
     357: getstatic     #121                // Field android/view/accessibility/AccessibilityNodeInfo$AccessibilityAction.ACTION_SCROLL_UP:Landroid/view/accessibility/AccessibilityNodeInfo$AccessibilityAction;
     360: astore_0
     361: goto          366
     364: aconst_null
     365: astore_0
     366: new           #2                  // class android/support/v4/view/a/b$a
     369: dup
     370: aload_0
     371: invokespecial #111                // Method "<init>":(Ljava/lang/Object;)V
     374: putstatic     #123                // Field y:Landroid/support/v4/view/a/b$a;
     377: getstatic     #102                // Field android/os/Build$VERSION.SDK_INT:I
     380: bipush        23
     382: if_icmplt     392
     385: getstatic     #126                // Field android/view/accessibility/AccessibilityNodeInfo$AccessibilityAction.ACTION_SCROLL_LEFT:Landroid/view/accessibility/AccessibilityNodeInfo$AccessibilityAction;
     388: astore_0
     389: goto          394
     392: aconst_null
     393: astore_0
     394: new           #2                  // class android/support/v4/view/a/b$a
     397: dup
     398: aload_0
     399: invokespecial #111                // Method "<init>":(Ljava/lang/Object;)V
     402: putstatic     #128                // Field z:Landroid/support/v4/view/a/b$a;
     405: getstatic     #102                // Field android/os/Build$VERSION.SDK_INT:I
     408: bipush        23
     410: if_icmplt     420
     413: getstatic     #131                // Field android/view/accessibility/AccessibilityNodeInfo$AccessibilityAction.ACTION_SCROLL_DOWN:Landroid/view/accessibility/AccessibilityNodeInfo$AccessibilityAction;
     416: astore_0
     417: goto          422
     420: aconst_null
     421: astore_0
     422: new           #2                  // class android/support/v4/view/a/b$a
     425: dup
     426: aload_0
     427: invokespecial #111                // Method "<init>":(Ljava/lang/Object;)V
     430: putstatic     #133                // Field A:Landroid/support/v4/view/a/b$a;
     433: getstatic     #102                // Field android/os/Build$VERSION.SDK_INT:I
     436: bipush        23
     438: if_icmplt     448
     441: getstatic     #136                // Field android/view/accessibility/AccessibilityNodeInfo$AccessibilityAction.ACTION_SCROLL_RIGHT:Landroid/view/accessibility/AccessibilityNodeInfo$AccessibilityAction;
     444: astore_0
     445: goto          450
     448: aconst_null
     449: astore_0
     450: new           #2                  // class android/support/v4/view/a/b$a
     453: dup
     454: aload_0
     455: invokespecial #111                // Method "<init>":(Ljava/lang/Object;)V
     458: putstatic     #138                // Field B:Landroid/support/v4/view/a/b$a;
     461: getstatic     #102                // Field android/os/Build$VERSION.SDK_INT:I
     464: bipush        23
     466: if_icmplt     476
     469: getstatic     #141                // Field android/view/accessibility/AccessibilityNodeInfo$AccessibilityAction.ACTION_CONTEXT_CLICK:Landroid/view/accessibility/AccessibilityNodeInfo$AccessibilityAction;
     472: astore_0
     473: goto          478
     476: aconst_null
     477: astore_0
     478: new           #2                  // class android/support/v4/view/a/b$a
     481: dup
     482: aload_0
     483: invokespecial #111                // Method "<init>":(Ljava/lang/Object;)V
     486: putstatic     #143                // Field C:Landroid/support/v4/view/a/b$a;
     489: aload_1
     490: astore_0
     491: getstatic     #102                // Field android/os/Build$VERSION.SDK_INT:I
     494: bipush        24
     496: if_icmplt     503
     499: getstatic     #146                // Field android/view/accessibility/AccessibilityNodeInfo$AccessibilityAction.ACTION_SET_PROGRESS:Landroid/view/accessibility/AccessibilityNodeInfo$AccessibilityAction;
     502: astore_0
     503: new           #2                  // class android/support/v4/view/a/b$a
     506: dup
     507: aload_0
     508: invokespecial #111                // Method "<init>":(Ljava/lang/Object;)V
     511: putstatic     #148                // Field D:Landroid/support/v4/view/a/b$a;
     514: return

  public android.support.v4.view.a.b$a(int, java.lang.CharSequence);
    Code:
       0: getstatic     #102                // Field android/os/Build$VERSION.SDK_INT:I
       3: bipush        21
       5: if_icmplt     21
       8: new           #104                // class android/view/accessibility/AccessibilityNodeInfo$AccessibilityAction
      11: dup
      12: iload_1
      13: aload_2
      14: invokespecial #150                // Method android/view/accessibility/AccessibilityNodeInfo$AccessibilityAction."<init>":(ILjava/lang/CharSequence;)V
      17: astore_2
      18: goto          23
      21: aconst_null
      22: astore_2
      23: aload_0
      24: aload_2
      25: invokespecial #111                // Method "<init>":(Ljava/lang/Object;)V
      28: return

  android.support.v4.view.a.b$a(java.lang.Object);
    Code:
       0: aload_0
       1: invokespecial #152                // Method java/lang/Object."<init>":()V
       4: aload_0
       5: aload_1
       6: putfield      #154                // Field E:Ljava/lang/Object;
       9: return
}
