public class android.support.v4.view.a.b {
  public int a;

  public static android.support.v4.view.a.b a(android.support.v4.view.a.b);
    Code:
       0: aload_0
       1: getfield      #24                 // Field b:Landroid/view/accessibility/AccessibilityNodeInfo;
       4: invokestatic  #32                 // Method android/view/accessibility/AccessibilityNodeInfo.obtain:(Landroid/view/accessibility/AccessibilityNodeInfo;)Landroid/view/accessibility/AccessibilityNodeInfo;
       7: invokestatic  #35                 // Method a:(Landroid/view/accessibility/AccessibilityNodeInfo;)Landroid/support/v4/view/a/b;
      10: areturn

  public static android.support.v4.view.a.b a(android.view.accessibility.AccessibilityNodeInfo);
    Code:
       0: new           #2                  // class android/support/v4/view/a/b
       3: dup
       4: aload_0
       5: invokespecial #37                 // Method "<init>":(Landroid/view/accessibility/AccessibilityNodeInfo;)V
       8: areturn

  public android.view.accessibility.AccessibilityNodeInfo a();
    Code:
       0: aload_0
       1: getfield      #24                 // Field b:Landroid/view/accessibility/AccessibilityNodeInfo;
       4: areturn

  public void a(int);
    Code:
       0: aload_0
       1: getfield      #24                 // Field b:Landroid/view/accessibility/AccessibilityNodeInfo;
       4: iload_1
       5: invokevirtual #81                 // Method android/view/accessibility/AccessibilityNodeInfo.addAction:(I)V
       8: return

  public void a(android.graphics.Rect);
    Code:
       0: aload_0
       1: getfield      #24                 // Field b:Landroid/view/accessibility/AccessibilityNodeInfo;
       4: aload_1
       5: invokevirtual #85                 // Method android/view/accessibility/AccessibilityNodeInfo.getBoundsInParent:(Landroid/graphics/Rect;)V
       8: return

  public void a(android.view.View);
    Code:
       0: aload_0
       1: getfield      #24                 // Field b:Landroid/view/accessibility/AccessibilityNodeInfo;
       4: aload_1
       5: invokevirtual #89                 // Method android/view/accessibility/AccessibilityNodeInfo.setSource:(Landroid/view/View;)V
       8: return

  public void a(java.lang.CharSequence);
    Code:
       0: aload_0
       1: getfield      #24                 // Field b:Landroid/view/accessibility/AccessibilityNodeInfo;
       4: aload_1
       5: invokevirtual #93                 // Method android/view/accessibility/AccessibilityNodeInfo.setPackageName:(Ljava/lang/CharSequence;)V
       8: return

  public void a(java.lang.Object);
    Code:
       0: getstatic     #99                 // Field android/os/Build$VERSION.SDK_INT:I
       3: bipush        19
       5: if_icmplt     25
       8: aload_0
       9: getfield      #24                 // Field b:Landroid/view/accessibility/AccessibilityNodeInfo;
      12: aload_1
      13: checkcast     #9                  // class android/support/v4/view/a/b$b
      16: getfield      #102                // Field android/support/v4/view/a/b$b.a:Ljava/lang/Object;
      19: checkcast     #104                // class android/view/accessibility/AccessibilityNodeInfo$CollectionInfo
      22: invokevirtual #108                // Method android/view/accessibility/AccessibilityNodeInfo.setCollectionInfo:(Landroid/view/accessibility/AccessibilityNodeInfo$CollectionInfo;)V
      25: return

  public void a(boolean);
    Code:
       0: aload_0
       1: getfield      #24                 // Field b:Landroid/view/accessibility/AccessibilityNodeInfo;
       4: iload_1
       5: invokevirtual #112                // Method android/view/accessibility/AccessibilityNodeInfo.setCheckable:(Z)V
       8: return

  public boolean a(android.support.v4.view.a.b$a);
    Code:
       0: getstatic     #99                 // Field android/os/Build$VERSION.SDK_INT:I
       3: bipush        21
       5: if_icmplt     23
       8: aload_0
       9: getfield      #24                 // Field b:Landroid/view/accessibility/AccessibilityNodeInfo;
      12: aload_1
      13: getfield      #116                // Field android/support/v4/view/a/b$a.E:Ljava/lang/Object;
      16: checkcast     #118                // class android/view/accessibility/AccessibilityNodeInfo$AccessibilityAction
      19: invokevirtual #122                // Method android/view/accessibility/AccessibilityNodeInfo.removeAction:(Landroid/view/accessibility/AccessibilityNodeInfo$AccessibilityAction;)Z
      22: ireturn
      23: iconst_0
      24: ireturn

  public int b();
    Code:
       0: aload_0
       1: getfield      #24                 // Field b:Landroid/view/accessibility/AccessibilityNodeInfo;
       4: invokevirtual #126                // Method android/view/accessibility/AccessibilityNodeInfo.getActions:()I
       7: ireturn

  public void b(android.graphics.Rect);
    Code:
       0: aload_0
       1: getfield      #24                 // Field b:Landroid/view/accessibility/AccessibilityNodeInfo;
       4: aload_1
       5: invokevirtual #129                // Method android/view/accessibility/AccessibilityNodeInfo.setBoundsInParent:(Landroid/graphics/Rect;)V
       8: return

  public void b(android.view.View);
    Code:
       0: aload_0
       1: getfield      #24                 // Field b:Landroid/view/accessibility/AccessibilityNodeInfo;
       4: aload_1
       5: invokevirtual #132                // Method android/view/accessibility/AccessibilityNodeInfo.addChild:(Landroid/view/View;)V
       8: return

  public void b(java.lang.CharSequence);
    Code:
       0: aload_0
       1: getfield      #24                 // Field b:Landroid/view/accessibility/AccessibilityNodeInfo;
       4: aload_1
       5: invokevirtual #135                // Method android/view/accessibility/AccessibilityNodeInfo.setClassName:(Ljava/lang/CharSequence;)V
       8: return

  public void b(java.lang.Object);
    Code:
       0: getstatic     #99                 // Field android/os/Build$VERSION.SDK_INT:I
       3: bipush        19
       5: if_icmplt     25
       8: aload_0
       9: getfield      #24                 // Field b:Landroid/view/accessibility/AccessibilityNodeInfo;
      12: aload_1
      13: checkcast     #12                 // class android/support/v4/view/a/b$c
      16: getfield      #136                // Field android/support/v4/view/a/b$c.a:Ljava/lang/Object;
      19: checkcast     #138                // class android/view/accessibility/AccessibilityNodeInfo$CollectionItemInfo
      22: invokevirtual #142                // Method android/view/accessibility/AccessibilityNodeInfo.setCollectionItemInfo:(Landroid/view/accessibility/AccessibilityNodeInfo$CollectionItemInfo;)V
      25: return

  public void b(boolean);
    Code:
       0: aload_0
       1: getfield      #24                 // Field b:Landroid/view/accessibility/AccessibilityNodeInfo;
       4: iload_1
       5: invokevirtual #145                // Method android/view/accessibility/AccessibilityNodeInfo.setChecked:(Z)V
       8: return

  public void c(android.graphics.Rect);
    Code:
       0: aload_0
       1: getfield      #24                 // Field b:Landroid/view/accessibility/AccessibilityNodeInfo;
       4: aload_1
       5: invokevirtual #148                // Method android/view/accessibility/AccessibilityNodeInfo.getBoundsInScreen:(Landroid/graphics/Rect;)V
       8: return

  public void c(android.view.View);
    Code:
       0: aload_0
       1: getfield      #24                 // Field b:Landroid/view/accessibility/AccessibilityNodeInfo;
       4: aload_1
       5: invokevirtual #151                // Method android/view/accessibility/AccessibilityNodeInfo.setParent:(Landroid/view/View;)V
       8: return

  public void c(java.lang.CharSequence);
    Code:
       0: aload_0
       1: getfield      #24                 // Field b:Landroid/view/accessibility/AccessibilityNodeInfo;
       4: aload_1
       5: invokevirtual #154                // Method android/view/accessibility/AccessibilityNodeInfo.setContentDescription:(Ljava/lang/CharSequence;)V
       8: return

  public void c(boolean);
    Code:
       0: aload_0
       1: getfield      #24                 // Field b:Landroid/view/accessibility/AccessibilityNodeInfo;
       4: iload_1
       5: invokevirtual #157                // Method android/view/accessibility/AccessibilityNodeInfo.setFocusable:(Z)V
       8: return

  public boolean c();
    Code:
       0: aload_0
       1: getfield      #24                 // Field b:Landroid/view/accessibility/AccessibilityNodeInfo;
       4: invokevirtual #161                // Method android/view/accessibility/AccessibilityNodeInfo.isCheckable:()Z
       7: ireturn

  public void d(android.graphics.Rect);
    Code:
       0: aload_0
       1: getfield      #24                 // Field b:Landroid/view/accessibility/AccessibilityNodeInfo;
       4: aload_1
       5: invokevirtual #165                // Method android/view/accessibility/AccessibilityNodeInfo.setBoundsInScreen:(Landroid/graphics/Rect;)V
       8: return

  public void d(boolean);
    Code:
       0: aload_0
       1: getfield      #24                 // Field b:Landroid/view/accessibility/AccessibilityNodeInfo;
       4: iload_1
       5: invokevirtual #168                // Method android/view/accessibility/AccessibilityNodeInfo.setFocused:(Z)V
       8: return

  public boolean d();
    Code:
       0: aload_0
       1: getfield      #24                 // Field b:Landroid/view/accessibility/AccessibilityNodeInfo;
       4: invokevirtual #171                // Method android/view/accessibility/AccessibilityNodeInfo.isChecked:()Z
       7: ireturn

  public void e(boolean);
    Code:
       0: getstatic     #99                 // Field android/os/Build$VERSION.SDK_INT:I
       3: bipush        16
       5: if_icmplt     16
       8: aload_0
       9: getfield      #24                 // Field b:Landroid/view/accessibility/AccessibilityNodeInfo;
      12: iload_1
      13: invokevirtual #175                // Method android/view/accessibility/AccessibilityNodeInfo.setVisibleToUser:(Z)V
      16: return

  public boolean e();
    Code:
       0: aload_0
       1: getfield      #24                 // Field b:Landroid/view/accessibility/AccessibilityNodeInfo;
       4: invokevirtual #178                // Method android/view/accessibility/AccessibilityNodeInfo.isFocusable:()Z
       7: ireturn

  public boolean equals(java.lang.Object);
    Code:
       0: aload_0
       1: aload_1
       2: if_acmpne     7
       5: iconst_1
       6: ireturn
       7: aload_1
       8: ifnonnull     13
      11: iconst_0
      12: ireturn
      13: aload_0
      14: invokevirtual #184                // Method java/lang/Object.getClass:()Ljava/lang/Class;
      17: aload_1
      18: invokevirtual #184                // Method java/lang/Object.getClass:()Ljava/lang/Class;
      21: if_acmpeq     26
      24: iconst_0
      25: ireturn
      26: aload_1
      27: checkcast     #2                  // class android/support/v4/view/a/b
      30: astore_1
      31: aload_0
      32: getfield      #24                 // Field b:Landroid/view/accessibility/AccessibilityNodeInfo;
      35: ifnonnull     47
      38: aload_1
      39: getfield      #24                 // Field b:Landroid/view/accessibility/AccessibilityNodeInfo;
      42: ifnull        63
      45: iconst_0
      46: ireturn
      47: aload_0
      48: getfield      #24                 // Field b:Landroid/view/accessibility/AccessibilityNodeInfo;
      51: aload_1
      52: getfield      #24                 // Field b:Landroid/view/accessibility/AccessibilityNodeInfo;
      55: invokevirtual #186                // Method android/view/accessibility/AccessibilityNodeInfo.equals:(Ljava/lang/Object;)Z
      58: ifne          63
      61: iconst_0
      62: ireturn
      63: iconst_1
      64: ireturn

  public void f(boolean);
    Code:
       0: getstatic     #99                 // Field android/os/Build$VERSION.SDK_INT:I
       3: bipush        16
       5: if_icmplt     16
       8: aload_0
       9: getfield      #24                 // Field b:Landroid/view/accessibility/AccessibilityNodeInfo;
      12: iload_1
      13: invokevirtual #190                // Method android/view/accessibility/AccessibilityNodeInfo.setAccessibilityFocused:(Z)V
      16: return

  public boolean f();
    Code:
       0: aload_0
       1: getfield      #24                 // Field b:Landroid/view/accessibility/AccessibilityNodeInfo;
       4: invokevirtual #193                // Method android/view/accessibility/AccessibilityNodeInfo.isFocused:()Z
       7: ireturn

  public void g(boolean);
    Code:
       0: aload_0
       1: getfield      #24                 // Field b:Landroid/view/accessibility/AccessibilityNodeInfo;
       4: iload_1
       5: invokevirtual #197                // Method android/view/accessibility/AccessibilityNodeInfo.setSelected:(Z)V
       8: return

  public boolean g();
    Code:
       0: getstatic     #99                 // Field android/os/Build$VERSION.SDK_INT:I
       3: bipush        16
       5: if_icmplt     16
       8: aload_0
       9: getfield      #24                 // Field b:Landroid/view/accessibility/AccessibilityNodeInfo;
      12: invokevirtual #200                // Method android/view/accessibility/AccessibilityNodeInfo.isVisibleToUser:()Z
      15: ireturn
      16: iconst_0
      17: ireturn

  public void h(boolean);
    Code:
       0: aload_0
       1: getfield      #24                 // Field b:Landroid/view/accessibility/AccessibilityNodeInfo;
       4: iload_1
       5: invokevirtual #204                // Method android/view/accessibility/AccessibilityNodeInfo.setClickable:(Z)V
       8: return

  public boolean h();
    Code:
       0: getstatic     #99                 // Field android/os/Build$VERSION.SDK_INT:I
       3: bipush        16
       5: if_icmplt     16
       8: aload_0
       9: getfield      #24                 // Field b:Landroid/view/accessibility/AccessibilityNodeInfo;
      12: invokevirtual #207                // Method android/view/accessibility/AccessibilityNodeInfo.isAccessibilityFocused:()Z
      15: ireturn
      16: iconst_0
      17: ireturn

  public int hashCode();
    Code:
       0: aload_0
       1: getfield      #24                 // Field b:Landroid/view/accessibility/AccessibilityNodeInfo;
       4: ifnonnull     9
       7: iconst_0
       8: ireturn
       9: aload_0
      10: getfield      #24                 // Field b:Landroid/view/accessibility/AccessibilityNodeInfo;
      13: invokevirtual #210                // Method android/view/accessibility/AccessibilityNodeInfo.hashCode:()I
      16: ireturn

  public void i(boolean);
    Code:
       0: aload_0
       1: getfield      #24                 // Field b:Landroid/view/accessibility/AccessibilityNodeInfo;
       4: iload_1
       5: invokevirtual #214                // Method android/view/accessibility/AccessibilityNodeInfo.setLongClickable:(Z)V
       8: return

  public boolean i();
    Code:
       0: aload_0
       1: getfield      #24                 // Field b:Landroid/view/accessibility/AccessibilityNodeInfo;
       4: invokevirtual #217                // Method android/view/accessibility/AccessibilityNodeInfo.isSelected:()Z
       7: ireturn

  public void j(boolean);
    Code:
       0: aload_0
       1: getfield      #24                 // Field b:Landroid/view/accessibility/AccessibilityNodeInfo;
       4: iload_1
       5: invokevirtual #221                // Method android/view/accessibility/AccessibilityNodeInfo.setEnabled:(Z)V
       8: return

  public boolean j();
    Code:
       0: aload_0
       1: getfield      #24                 // Field b:Landroid/view/accessibility/AccessibilityNodeInfo;
       4: invokevirtual #224                // Method android/view/accessibility/AccessibilityNodeInfo.isClickable:()Z
       7: ireturn

  public void k(boolean);
    Code:
       0: aload_0
       1: getfield      #24                 // Field b:Landroid/view/accessibility/AccessibilityNodeInfo;
       4: iload_1
       5: invokevirtual #228                // Method android/view/accessibility/AccessibilityNodeInfo.setScrollable:(Z)V
       8: return

  public boolean k();
    Code:
       0: aload_0
       1: getfield      #24                 // Field b:Landroid/view/accessibility/AccessibilityNodeInfo;
       4: invokevirtual #231                // Method android/view/accessibility/AccessibilityNodeInfo.isLongClickable:()Z
       7: ireturn

  public boolean l();
    Code:
       0: aload_0
       1: getfield      #24                 // Field b:Landroid/view/accessibility/AccessibilityNodeInfo;
       4: invokevirtual #235                // Method android/view/accessibility/AccessibilityNodeInfo.isEnabled:()Z
       7: ireturn

  public boolean m();
    Code:
       0: aload_0
       1: getfield      #24                 // Field b:Landroid/view/accessibility/AccessibilityNodeInfo;
       4: invokevirtual #239                // Method android/view/accessibility/AccessibilityNodeInfo.isPassword:()Z
       7: ireturn

  public boolean n();
    Code:
       0: aload_0
       1: getfield      #24                 // Field b:Landroid/view/accessibility/AccessibilityNodeInfo;
       4: invokevirtual #243                // Method android/view/accessibility/AccessibilityNodeInfo.isScrollable:()Z
       7: ireturn

  public java.lang.CharSequence o();
    Code:
       0: aload_0
       1: getfield      #24                 // Field b:Landroid/view/accessibility/AccessibilityNodeInfo;
       4: invokevirtual #248                // Method android/view/accessibility/AccessibilityNodeInfo.getPackageName:()Ljava/lang/CharSequence;
       7: areturn

  public java.lang.CharSequence p();
    Code:
       0: aload_0
       1: getfield      #24                 // Field b:Landroid/view/accessibility/AccessibilityNodeInfo;
       4: invokevirtual #252                // Method android/view/accessibility/AccessibilityNodeInfo.getClassName:()Ljava/lang/CharSequence;
       7: areturn

  public java.lang.CharSequence q();
    Code:
       0: aload_0
       1: getfield      #24                 // Field b:Landroid/view/accessibility/AccessibilityNodeInfo;
       4: invokevirtual #256                // Method android/view/accessibility/AccessibilityNodeInfo.getText:()Ljava/lang/CharSequence;
       7: areturn

  public java.lang.CharSequence r();
    Code:
       0: aload_0
       1: getfield      #24                 // Field b:Landroid/view/accessibility/AccessibilityNodeInfo;
       4: invokevirtual #260                // Method android/view/accessibility/AccessibilityNodeInfo.getContentDescription:()Ljava/lang/CharSequence;
       7: areturn

  public void s();
    Code:
       0: aload_0
       1: getfield      #24                 // Field b:Landroid/view/accessibility/AccessibilityNodeInfo;
       4: invokevirtual #264                // Method android/view/accessibility/AccessibilityNodeInfo.recycle:()V
       7: return

  public java.lang.String t();
    Code:
       0: getstatic     #99                 // Field android/os/Build$VERSION.SDK_INT:I
       3: bipush        18
       5: if_icmplt     16
       8: aload_0
       9: getfield      #24                 // Field b:Landroid/view/accessibility/AccessibilityNodeInfo;
      12: invokevirtual #269                // Method android/view/accessibility/AccessibilityNodeInfo.getViewIdResourceName:()Ljava/lang/String;
      15: areturn
      16: aconst_null
      17: areturn

  public java.lang.String toString();
    Code:
       0: new           #272                // class java/lang/StringBuilder
       3: dup
       4: invokespecial #273                // Method java/lang/StringBuilder."<init>":()V
       7: astore        4
       9: aload         4
      11: aload_0
      12: invokespecial #275                // Method java/lang/Object.toString:()Ljava/lang/String;
      15: invokevirtual #279                // Method java/lang/StringBuilder.append:(Ljava/lang/String;)Ljava/lang/StringBuilder;
      18: pop
      19: new           #281                // class android/graphics/Rect
      22: dup
      23: invokespecial #282                // Method android/graphics/Rect."<init>":()V
      26: astore        5
      28: aload_0
      29: aload         5
      31: invokevirtual #284                // Method a:(Landroid/graphics/Rect;)V
      34: new           #272                // class java/lang/StringBuilder
      37: dup
      38: invokespecial #273                // Method java/lang/StringBuilder."<init>":()V
      41: astore        6
      43: aload         6
      45: ldc_w         #286                // String ; boundsInParent:
      48: invokevirtual #279                // Method java/lang/StringBuilder.append:(Ljava/lang/String;)Ljava/lang/StringBuilder;
      51: pop
      52: aload         6
      54: aload         5
      56: invokevirtual #289                // Method java/lang/StringBuilder.append:(Ljava/lang/Object;)Ljava/lang/StringBuilder;
      59: pop
      60: aload         4
      62: aload         6
      64: invokevirtual #290                // Method java/lang/StringBuilder.toString:()Ljava/lang/String;
      67: invokevirtual #279                // Method java/lang/StringBuilder.append:(Ljava/lang/String;)Ljava/lang/StringBuilder;
      70: pop
      71: aload_0
      72: aload         5
      74: invokevirtual #292                // Method c:(Landroid/graphics/Rect;)V
      77: new           #272                // class java/lang/StringBuilder
      80: dup
      81: invokespecial #273                // Method java/lang/StringBuilder."<init>":()V
      84: astore        6
      86: aload         6
      88: ldc_w         #294                // String ; boundsInScreen:
      91: invokevirtual #279                // Method java/lang/StringBuilder.append:(Ljava/lang/String;)Ljava/lang/StringBuilder;
      94: pop
      95: aload         6
      97: aload         5
      99: invokevirtual #289                // Method java/lang/StringBuilder.append:(Ljava/lang/Object;)Ljava/lang/StringBuilder;
     102: pop
     103: aload         4
     105: aload         6
     107: invokevirtual #290                // Method java/lang/StringBuilder.toString:()Ljava/lang/String;
     110: invokevirtual #279                // Method java/lang/StringBuilder.append:(Ljava/lang/String;)Ljava/lang/StringBuilder;
     113: pop
     114: aload         4
     116: ldc_w         #296                // String ; packageName:
     119: invokevirtual #279                // Method java/lang/StringBuilder.append:(Ljava/lang/String;)Ljava/lang/StringBuilder;
     122: pop
     123: aload         4
     125: aload_0
     126: invokevirtual #298                // Method o:()Ljava/lang/CharSequence;
     129: invokevirtual #301                // Method java/lang/StringBuilder.append:(Ljava/lang/CharSequence;)Ljava/lang/StringBuilder;
     132: pop
     133: aload         4
     135: ldc_w         #303                // String ; className:
     138: invokevirtual #279                // Method java/lang/StringBuilder.append:(Ljava/lang/String;)Ljava/lang/StringBuilder;
     141: pop
     142: aload         4
     144: aload_0
     145: invokevirtual #305                // Method p:()Ljava/lang/CharSequence;
     148: invokevirtual #301                // Method java/lang/StringBuilder.append:(Ljava/lang/CharSequence;)Ljava/lang/StringBuilder;
     151: pop
     152: aload         4
     154: ldc_w         #307                // String ; text:
     157: invokevirtual #279                // Method java/lang/StringBuilder.append:(Ljava/lang/String;)Ljava/lang/StringBuilder;
     160: pop
     161: aload         4
     163: aload_0
     164: invokevirtual #309                // Method q:()Ljava/lang/CharSequence;
     167: invokevirtual #301                // Method java/lang/StringBuilder.append:(Ljava/lang/CharSequence;)Ljava/lang/StringBuilder;
     170: pop
     171: aload         4
     173: ldc_w         #311                // String ; contentDescription:
     176: invokevirtual #279                // Method java/lang/StringBuilder.append:(Ljava/lang/String;)Ljava/lang/StringBuilder;
     179: pop
     180: aload         4
     182: aload_0
     183: invokevirtual #313                // Method r:()Ljava/lang/CharSequence;
     186: invokevirtual #301                // Method java/lang/StringBuilder.append:(Ljava/lang/CharSequence;)Ljava/lang/StringBuilder;
     189: pop
     190: aload         4
     192: ldc_w         #315                // String ; viewId:
     195: invokevirtual #279                // Method java/lang/StringBuilder.append:(Ljava/lang/String;)Ljava/lang/StringBuilder;
     198: pop
     199: aload         4
     201: aload_0
     202: invokevirtual #317                // Method t:()Ljava/lang/String;
     205: invokevirtual #279                // Method java/lang/StringBuilder.append:(Ljava/lang/String;)Ljava/lang/StringBuilder;
     208: pop
     209: aload         4
     211: ldc_w         #319                // String ; checkable:
     214: invokevirtual #279                // Method java/lang/StringBuilder.append:(Ljava/lang/String;)Ljava/lang/StringBuilder;
     217: pop
     218: aload         4
     220: aload_0
     221: invokevirtual #321                // Method c:()Z
     224: invokevirtual #324                // Method java/lang/StringBuilder.append:(Z)Ljava/lang/StringBuilder;
     227: pop
     228: aload         4
     230: ldc_w         #326                // String ; checked:
     233: invokevirtual #279                // Method java/lang/StringBuilder.append:(Ljava/lang/String;)Ljava/lang/StringBuilder;
     236: pop
     237: aload         4
     239: aload_0
     240: invokevirtual #328                // Method d:()Z
     243: invokevirtual #324                // Method java/lang/StringBuilder.append:(Z)Ljava/lang/StringBuilder;
     246: pop
     247: aload         4
     249: ldc_w         #330                // String ; focusable:
     252: invokevirtual #279                // Method java/lang/StringBuilder.append:(Ljava/lang/String;)Ljava/lang/StringBuilder;
     255: pop
     256: aload         4
     258: aload_0
     259: invokevirtual #332                // Method e:()Z
     262: invokevirtual #324                // Method java/lang/StringBuilder.append:(Z)Ljava/lang/StringBuilder;
     265: pop
     266: aload         4
     268: ldc_w         #334                // String ; focused:
     271: invokevirtual #279                // Method java/lang/StringBuilder.append:(Ljava/lang/String;)Ljava/lang/StringBuilder;
     274: pop
     275: aload         4
     277: aload_0
     278: invokevirtual #336                // Method f:()Z
     281: invokevirtual #324                // Method java/lang/StringBuilder.append:(Z)Ljava/lang/StringBuilder;
     284: pop
     285: aload         4
     287: ldc_w         #338                // String ; selected:
     290: invokevirtual #279                // Method java/lang/StringBuilder.append:(Ljava/lang/String;)Ljava/lang/StringBuilder;
     293: pop
     294: aload         4
     296: aload_0
     297: invokevirtual #340                // Method i:()Z
     300: invokevirtual #324                // Method java/lang/StringBuilder.append:(Z)Ljava/lang/StringBuilder;
     303: pop
     304: aload         4
     306: ldc_w         #342                // String ; clickable:
     309: invokevirtual #279                // Method java/lang/StringBuilder.append:(Ljava/lang/String;)Ljava/lang/StringBuilder;
     312: pop
     313: aload         4
     315: aload_0
     316: invokevirtual #344                // Method j:()Z
     319: invokevirtual #324                // Method java/lang/StringBuilder.append:(Z)Ljava/lang/StringBuilder;
     322: pop
     323: aload         4
     325: ldc_w         #346                // String ; longClickable:
     328: invokevirtual #279                // Method java/lang/StringBuilder.append:(Ljava/lang/String;)Ljava/lang/StringBuilder;
     331: pop
     332: aload         4
     334: aload_0
     335: invokevirtual #348                // Method k:()Z
     338: invokevirtual #324                // Method java/lang/StringBuilder.append:(Z)Ljava/lang/StringBuilder;
     341: pop
     342: aload         4
     344: ldc_w         #350                // String ; enabled:
     347: invokevirtual #279                // Method java/lang/StringBuilder.append:(Ljava/lang/String;)Ljava/lang/StringBuilder;
     350: pop
     351: aload         4
     353: aload_0
     354: invokevirtual #352                // Method l:()Z
     357: invokevirtual #324                // Method java/lang/StringBuilder.append:(Z)Ljava/lang/StringBuilder;
     360: pop
     361: aload         4
     363: ldc_w         #354                // String ; password:
     366: invokevirtual #279                // Method java/lang/StringBuilder.append:(Ljava/lang/String;)Ljava/lang/StringBuilder;
     369: pop
     370: aload         4
     372: aload_0
     373: invokevirtual #356                // Method m:()Z
     376: invokevirtual #324                // Method java/lang/StringBuilder.append:(Z)Ljava/lang/StringBuilder;
     379: pop
     380: new           #272                // class java/lang/StringBuilder
     383: dup
     384: invokespecial #273                // Method java/lang/StringBuilder."<init>":()V
     387: astore        5
     389: aload         5
     391: ldc_w         #358                // String ; scrollable:
     394: invokevirtual #279                // Method java/lang/StringBuilder.append:(Ljava/lang/String;)Ljava/lang/StringBuilder;
     397: pop
     398: aload         5
     400: aload_0
     401: invokevirtual #360                // Method n:()Z
     404: invokevirtual #324                // Method java/lang/StringBuilder.append:(Z)Ljava/lang/StringBuilder;
     407: pop
     408: aload         4
     410: aload         5
     412: invokevirtual #290                // Method java/lang/StringBuilder.toString:()Ljava/lang/String;
     415: invokevirtual #279                // Method java/lang/StringBuilder.append:(Ljava/lang/String;)Ljava/lang/StringBuilder;
     418: pop
     419: aload         4
     421: ldc_w         #362                // String ; [
     424: invokevirtual #279                // Method java/lang/StringBuilder.append:(Ljava/lang/String;)Ljava/lang/StringBuilder;
     427: pop
     428: aload_0
     429: invokevirtual #364                // Method b:()I
     432: istore_1
     433: iload_1
     434: ifeq          480
     437: iconst_1
     438: iload_1
     439: invokestatic  #370                // Method java/lang/Integer.numberOfTrailingZeros:(I)I
     442: ishl
     443: istore_3
     444: iload_1
     445: iload_3
     446: iconst_m1
     447: ixor
     448: iand
     449: istore_2
     450: aload         4
     452: iload_3
     453: invokestatic  #372                // Method b:(I)Ljava/lang/String;
     456: invokevirtual #279                // Method java/lang/StringBuilder.append:(Ljava/lang/String;)Ljava/lang/StringBuilder;
     459: pop
     460: iload_2
     461: istore_1
     462: iload_2
     463: ifeq          433
     466: aload         4
     468: ldc_w         #374                // String ,
     471: invokevirtual #279                // Method java/lang/StringBuilder.append:(Ljava/lang/String;)Ljava/lang/StringBuilder;
     474: pop
     475: iload_2
     476: istore_1
     477: goto          433
     480: aload         4
     482: ldc_w         #376                // String ]
     485: invokevirtual #279                // Method java/lang/StringBuilder.append:(Ljava/lang/String;)Ljava/lang/StringBuilder;
     488: pop
     489: aload         4
     491: invokevirtual #290                // Method java/lang/StringBuilder.toString:()Ljava/lang/String;
     494: areturn
}
