class ryey.easer.plugins.operation.i.a$a extends android.os.AsyncTask<ryey.easer.plugins.operation.i.b, java.lang.Void, java.lang.Boolean> {
  ryey.easer.plugins.operation.i.a$a(ryey.easer.plugins.operation.i.a$1);
    Code:
       0: aload_0
       1: invokespecial #15                 // Method "<init>":()V
       4: return

  protected java.lang.Boolean a(ryey.easer.plugins.operation.i.b...);
    Code:
       0: aload_1
       1: iconst_0
       2: aaload
       3: astore_3
       4: aload_3
       5: getfield      #26                 // Field ryey/easer/plugins/operation/i/b.b:Ljava/lang/String;
       8: invokestatic  #32                 // Method java/net/InetAddress.getByName:(Ljava/lang/String;)Ljava/net/InetAddress;
      11: astore_1
      12: getstatic     #37                 // Field ryey/easer/plugins/operation/i/a$1.a:[I
      15: aload_3
      16: getfield      #40                 // Field ryey/easer/plugins/operation/i/b.a:Lryey/easer/plugins/operation/i/b$a;
      19: invokevirtual #46                 // Method ryey/easer/plugins/operation/i/b$a.ordinal:()I
      22: iaload
      23: tableswitch   { // 1 to 2
                     1: 104
                     2: 47
               default: 229
          }
      44: goto          209
      47: new           #48                 // class java/net/DatagramPacket
      50: dup
      51: aload_3
      52: getfield      #51                 // Field ryey/easer/plugins/operation/i/b.d:Ljava/lang/String;
      55: invokevirtual #57                 // Method java/lang/String.getBytes:()[B
      58: aload_3
      59: getfield      #51                 // Field ryey/easer/plugins/operation/i/b.d:Ljava/lang/String;
      62: invokevirtual #60                 // Method java/lang/String.length:()I
      65: aload_1
      66: aload_3
      67: getfield      #64                 // Field ryey/easer/plugins/operation/i/b.c:I
      70: invokespecial #67                 // Method java/net/DatagramPacket."<init>":([BILjava/net/InetAddress;I)V
      73: astore_1
      74: new           #69                 // class java/net/DatagramSocket
      77: dup
      78: invokespecial #70                 // Method java/net/DatagramSocket."<init>":()V
      81: astore_2
      82: aload_2
      83: aload_1
      84: invokevirtual #74                 // Method java/net/DatagramSocket.send:(Ljava/net/DatagramPacket;)V
      87: aload_2
      88: invokevirtual #77                 // Method java/net/DatagramSocket.close:()V
      91: goto          163
      94: astore_1
      95: aload_1
      96: invokestatic  #82                 // Method com/google/a/a/a/a/a/a.a:(Ljava/lang/Throwable;)V
      99: iconst_0
     100: invokestatic  #88                 // Method java/lang/Boolean.valueOf:(Z)Ljava/lang/Boolean;
     103: areturn
     104: new           #90                 // class java/net/Socket
     107: dup
     108: aload_1
     109: aload_3
     110: getfield      #64                 // Field ryey/easer/plugins/operation/i/b.c:I
     113: invokespecial #93                 // Method java/net/Socket."<init>":(Ljava/net/InetAddress;I)V
     116: astore_1
     117: aload_1
     118: invokevirtual #97                 // Method java/net/Socket.getOutputStream:()Ljava/io/OutputStream;
     121: astore_2
     122: new           #99                 // class java/io/DataOutputStream
     125: dup
     126: aload_2
     127: invokespecial #102                // Method java/io/DataOutputStream."<init>":(Ljava/io/OutputStream;)V
     130: astore        4
     132: aload         4
     134: aload_3
     135: getfield      #51                 // Field ryey/easer/plugins/operation/i/b.d:Ljava/lang/String;
     138: invokevirtual #106                // Method java/io/DataOutputStream.writeBytes:(Ljava/lang/String;)V
     141: aload         4
     143: invokevirtual #109                // Method java/io/DataOutputStream.flush:()V
     146: aload         4
     148: invokevirtual #110                // Method java/io/DataOutputStream.close:()V
     151: aload_2
     152: invokevirtual #113                // Method java/io/OutputStream.flush:()V
     155: aload_2
     156: invokevirtual #114                // Method java/io/OutputStream.close:()V
     159: aload_1
     160: invokevirtual #115                // Method java/net/Socket.close:()V
     163: iconst_1
     164: invokestatic  #88                 // Method java/lang/Boolean.valueOf:(Z)Ljava/lang/Boolean;
     167: areturn
     168: astore_3
     169: aload         4
     171: invokevirtual #109                // Method java/io/DataOutputStream.flush:()V
     174: aload         4
     176: invokevirtual #110                // Method java/io/DataOutputStream.close:()V
     179: aload_3
     180: athrow
     181: astore_3
     182: aload_2
     183: invokevirtual #113                // Method java/io/OutputStream.flush:()V
     186: aload_2
     187: invokevirtual #114                // Method java/io/OutputStream.close:()V
     190: aload_3
     191: athrow
     192: astore_2
     193: aload_1
     194: invokevirtual #115                // Method java/net/Socket.close:()V
     197: aload_2
     198: athrow
     199: astore_1
     200: aload_1
     201: invokestatic  #82                 // Method com/google/a/a/a/a/a/a.a:(Ljava/lang/Throwable;)V
     204: iconst_0
     205: invokestatic  #88                 // Method java/lang/Boolean.valueOf:(Z)Ljava/lang/Boolean;
     208: areturn
     209: new           #117                // class java/lang/IllegalAccessError
     212: dup
     213: ldc           #119                // String data should be valid when calling this method
     215: invokespecial #121                // Method java/lang/IllegalAccessError."<init>":(Ljava/lang/String;)V
     218: athrow
     219: astore_1
     220: aload_1
     221: invokestatic  #82                 // Method com/google/a/a/a/a/a/a.a:(Ljava/lang/Throwable;)V
     224: iconst_0
     225: invokestatic  #88                 // Method java/lang/Boolean.valueOf:(Z)Ljava/lang/Boolean;
     228: areturn
     229: goto          44
    Exception table:
       from    to  target type
           4    44   219   Class java/net/UnknownHostException
          47    74   219   Class java/net/UnknownHostException
          74    91    94   Class java/io/IOException
          74    91   219   Class java/net/UnknownHostException
          95    99   219   Class java/net/UnknownHostException
         104   117   199   Class java/io/IOException
         104   117   219   Class java/net/UnknownHostException
         117   122   192   any
         122   132   181   any
         132   141   168   any
         141   151   181   any
         151   159   192   any
         159   163   199   Class java/io/IOException
         159   163   219   Class java/net/UnknownHostException
         169   181   181   any
         182   192   192   any
         193   199   199   Class java/io/IOException
         193   199   219   Class java/net/UnknownHostException
         200   209   219   Class java/net/UnknownHostException
         209   219   219   Class java/net/UnknownHostException

  protected java.lang.Object doInBackground(java.lang.Object[]);
    Code:
       0: aload_0
       1: aload_1
       2: checkcast     #125                // class "[Lryey/easer/plugins/operation/i/b;"
       5: invokevirtual #127                // Method a:([Lryey/easer/plugins/operation/i/b;)Ljava/lang/Boolean;
       8: areturn
}
