final class ryey.easer.core.ui.a$a$1 extends android.support.v7.g.c$c<ryey.easer.core.log.a> {
  ryey.easer.core.ui.a$a$1();
    Code:
       0: aload_0
       1: invokespecial #14                 // Method android/support/v7/g/c$c."<init>":()V
       4: return

  public boolean a(java.lang.Object, java.lang.Object);
    Code:
       0: aload_0
       1: aload_1
       2: checkcast     #18                 // class ryey/easer/core/log/a
       5: aload_2
       6: checkcast     #18                 // class ryey/easer/core/log/a
       9: invokevirtual #21                 // Method a:(Lryey/easer/core/log/a;Lryey/easer/core/log/a;)Z
      12: ireturn

  public boolean a(ryey.easer.core.log.a, ryey.easer.core.log.a);
    Code:
       0: aload_1
       1: aload_2
       2: invokeinterface #25,  2           // InterfaceMethod ryey/easer/core/log/a.equals:(Ljava/lang/Object;)Z
       7: ireturn

  public boolean b(java.lang.Object, java.lang.Object);
    Code:
       0: aload_0
       1: aload_1
       2: checkcast     #18                 // class ryey/easer/core/log/a
       5: aload_2
       6: checkcast     #18                 // class ryey/easer/core/log/a
       9: invokevirtual #28                 // Method b:(Lryey/easer/core/log/a;Lryey/easer/core/log/a;)Z
      12: ireturn

  public boolean b(ryey.easer.core.log.a, ryey.easer.core.log.a);
    Code:
       0: aload_1
       1: aload_2
       2: invokeinterface #25,  2           // InterfaceMethod ryey/easer/core/log/a.equals:(Ljava/lang/Object;)Z
       7: ireturn
}
