public final class ryey.easer.core.ui.c$a {
  public ryey.easer.core.ui.c$a(a.b.b.a);
    Code:
       0: aload_0
       1: invokespecial #14                 // Method "<init>":()V
       4: return

  public final void a(ryey.easer.core.a.k, de.blox.graphview.e, de.blox.graphview.h);
    Code:
       0: aload_1
       1: ldc           #17                 // String scriptTree
       3: invokestatic  #23                 // Method a/b/b/c.b:(Ljava/lang/Object;Ljava/lang/String;)V
       6: aload_2
       7: ldc           #25                 // String graph
       9: invokestatic  #23                 // Method a/b/b/c.b:(Ljava/lang/Object;Ljava/lang/String;)V
      12: aload_3
      13: ldc           #27                 // String parent
      15: invokestatic  #23                 // Method a/b/b/c.b:(Ljava/lang/Object;Ljava/lang/String;)V
      18: new           #29                 // class de/blox/graphview/h
      21: dup
      22: aload_1
      23: invokevirtual #35                 // Method ryey/easer/core/a/k.k:()Lryey/easer/core/a/j;
      26: invokestatic  #40                 // Method ryey/easer/core/a/a.a:(Lryey/easer/core/a/j;)Lryey/easer/core/a/a;
      29: invokespecial #43                 // Method de/blox/graphview/h."<init>":(Ljava/lang/Object;)V
      32: astore        4
      34: aload_2
      35: aload         4
      37: invokevirtual #48                 // Method de/blox/graphview/e.a:(Lde/blox/graphview/h;)V
      40: aload_2
      41: aload_3
      42: aload         4
      44: invokevirtual #51                 // Method de/blox/graphview/e.a:(Lde/blox/graphview/h;Lde/blox/graphview/h;)Lde/blox/graphview/d;
      47: pop
      48: aload_1
      49: invokevirtual #55                 // Method ryey/easer/core/a/k.i:()Ljava/lang/String;
      52: ifnull        95
      55: aload_1
      56: invokevirtual #55                 // Method ryey/easer/core/a/k.i:()Ljava/lang/String;
      59: astore_3
      60: aload_3
      61: ldc           #57                 // String scriptTree.profile
      63: invokestatic  #59                 // Method a/b/b/c.a:(Ljava/lang/Object;Ljava/lang/String;)V
      66: new           #29                 // class de/blox/graphview/h
      69: dup
      70: new           #61                 // class ryey/easer/core/ui/c$b
      73: dup
      74: aload_3
      75: invokespecial #64                 // Method ryey/easer/core/ui/c$b."<init>":(Ljava/lang/String;)V
      78: invokespecial #43                 // Method de/blox/graphview/h."<init>":(Ljava/lang/Object;)V
      81: astore_3
      82: aload_2
      83: aload_3
      84: invokevirtual #48                 // Method de/blox/graphview/e.a:(Lde/blox/graphview/h;)V
      87: aload_2
      88: aload         4
      90: aload_3
      91: invokevirtual #51                 // Method de/blox/graphview/e.a:(Lde/blox/graphview/h;Lde/blox/graphview/h;)Lde/blox/graphview/d;
      94: pop
      95: aload_1
      96: invokevirtual #68                 // Method ryey/easer/core/a/k.h:()Ljava/util/List;
      99: invokeinterface #74,  1           // InterfaceMethod java/util/List.iterator:()Ljava/util/Iterator;
     104: astore_1
     105: aload_1
     106: invokeinterface #80,  1           // InterfaceMethod java/util/Iterator.hasNext:()Z
     111: ifeq          148
     114: aload_1
     115: invokeinterface #84,  1           // InterfaceMethod java/util/Iterator.next:()Ljava/lang/Object;
     120: checkcast     #31                 // class ryey/easer/core/a/k
     123: astore_3
     124: aload_0
     125: checkcast     #2                  // class ryey/easer/core/ui/c$a
     128: astore        5
     130: aload_3
     131: ldc           #86                 // String subTree
     133: invokestatic  #59                 // Method a/b/b/c.a:(Ljava/lang/Object;Ljava/lang/String;)V
     136: aload         5
     138: aload_3
     139: aload_2
     140: aload         4
     142: invokevirtual #88                 // Method a:(Lryey/easer/core/a/k;Lde/blox/graphview/e;Lde/blox/graphview/h;)V
     145: goto          105
     148: return
}
