public final class ryey.easer.core.ui.c$b {
  public ryey.easer.core.ui.c$b(java.lang.String);
    Code:
       0: aload_1
       1: ldc           #13                 // String name
       3: invokestatic  #18                 // Method a/b/b/c.b:(Ljava/lang/Object;Ljava/lang/String;)V
       6: aload_0
       7: invokespecial #21                 // Method java/lang/Object."<init>":()V
      10: aload_0
      11: aload_1
      12: putfield      #23                 // Field a:Ljava/lang/String;
      15: return

  public final java.lang.String a();
    Code:
       0: aload_0
       1: getfield      #23                 // Field a:Ljava/lang/String;
       4: areturn
}
