class ryey.easer.core.ui.MainActivity$a {
  static {};
    Code:
       0: bipush        7
       2: newarray       int
       4: dup
       5: iconst_0
       6: ldc           #15                 // int 2131296486
       8: iastore
       9: dup
      10: iconst_1
      11: ldc           #16                 // int 2131296487
      13: iastore
      14: dup
      15: iconst_2
      16: ldc           #17                 // int 2131296490
      18: iastore
      19: dup
      20: iconst_3
      21: ldc           #18                 // int 2131296488
      23: iastore
      24: dup
      25: iconst_4
      26: ldc           #19                 // int 2131296489
      28: iastore
      29: dup
      30: iconst_5
      31: ldc           #20                 // int 2131296484
      33: iastore
      34: dup
      35: bipush        6
      37: ldc           #21                 // int 2131296485
      39: iastore
      40: putstatic     #23                 // Field a:[I
      43: bipush        7
      45: anewarray     #25                 // class java/lang/String
      48: dup
      49: iconst_0
      50: ldc           #27                 // String ryey.easer.FRAGMENT.OUTLINE
      52: aastore
      53: dup
      54: iconst_1
      55: ldc           #29                 // String ryey.easer.FRAGMENT.PIVOT
      57: aastore
      58: dup
      59: iconst_2
      60: ldc           #31                 // String ryey.easer.FRAGMENT.SCRIPT
      62: aastore
      63: dup
      64: iconst_3
      65: ldc           #33                 // String ryey.easer.FRAGMENT.PROFILE
      67: aastore
      68: dup
      69: iconst_4
      70: ldc           #35                 // String ryey.easer.FRAGMENT.SCENARIO
      72: aastore
      73: dup
      74: iconst_5
      75: ldc           #37                 // String ryey.easer.FRAGMENT.CONDITION
      77: aastore
      78: dup
      79: bipush        6
      81: ldc           #39                 // String ryey.easer.FRAGMENT.LOG
      83: aastore
      84: putstatic     #41                 // Field b:[Ljava/lang/String;
      87: bipush        7
      89: anewarray     #43                 // class ryey/easer/core/ui/data/e$a
      92: dup
      93: iconst_0
      94: aconst_null
      95: aastore
      96: dup
      97: iconst_1
      98: aconst_null
      99: aastore
     100: dup
     101: iconst_2
     102: getstatic     #46                 // Field ryey/easer/core/ui/data/e$a.a:Lryey/easer/core/ui/data/e$a;
     105: aastore
     106: dup
     107: iconst_3
     108: getstatic     #49                 // Field ryey/easer/core/ui/data/e$a.e:Lryey/easer/core/ui/data/e$a;
     111: aastore
     112: dup
     113: iconst_4
     114: getstatic     #51                 // Field ryey/easer/core/ui/data/e$a.c:Lryey/easer/core/ui/data/e$a;
     117: aastore
     118: dup
     119: iconst_5
     120: getstatic     #54                 // Field ryey/easer/core/ui/data/e$a.d:Lryey/easer/core/ui/data/e$a;
     123: aastore
     124: dup
     125: bipush        6
     127: aconst_null
     128: aastore
     129: putstatic     #56                 // Field c:[Lryey/easer/core/ui/data/e$a;
     132: return

  ryey.easer.core.ui.MainActivity$a(ryey.easer.core.ui.MainActivity$1);
    Code:
       0: aload_0
       1: invokespecial #62                 // Method "<init>":()V
       4: return

  static java.lang.String a(ryey.easer.core.ui.MainActivity$a, int);
    Code:
       0: aload_0
       1: iload_1
       2: invokespecial #66                 // Method a:(I)Ljava/lang/String;
       5: areturn

  static ryey.easer.core.ui.data.e$a b(ryey.easer.core.ui.MainActivity$a, int);
    Code:
       0: aload_0
       1: iload_1
       2: invokespecial #70                 // Method b:(I)Lryey/easer/core/ui/data/e$a;
       5: areturn
}
