class ryey.easer.core.ui.PermissionOutlineFragment$1 implements android.view.View$OnClickListener {
  final ryey.easer.core.ui.PermissionOutlineFragment a;

  ryey.easer.core.ui.PermissionOutlineFragment$1(ryey.easer.core.ui.PermissionOutlineFragment);
    Code:
       0: aload_0
       1: aload_1
       2: putfield      #17                 // Field a:Lryey/easer/core/ui/PermissionOutlineFragment;
       5: aload_0
       6: invokespecial #20                 // Method java/lang/Object."<init>":()V
       9: return

  public void onClick(android.view.View);
    Code:
       0: aload_0
       1: getfield      #17                 // Field a:Lryey/easer/core/ui/PermissionOutlineFragment;
       4: invokevirtual #26                 // Method ryey/easer/core/ui/PermissionOutlineFragment.b:()V
       7: return
}
