class b.a.a.c$1 implements android.view.View$OnClickListener {
  final android.support.v7.widget.RecyclerView$x a;

  final b.a.a.c b;

  b.a.a.c$1(b.a.a.c, android.support.v7.widget.RecyclerView$x);
    Code:
       0: aload_0
       1: aload_1
       2: putfield      #18                 // Field b:Lb/a/a/c;
       5: aload_0
       6: aload_2
       7: putfield      #20                 // Field a:Landroid/support/v7/widget/RecyclerView$x;
      10: aload_0
      11: invokespecial #23                 // Method java/lang/Object."<init>":()V
      14: return

  public void onClick(android.view.View);
    Code:
       0: aload_0
       1: getfield      #18                 // Field b:Lb/a/a/c;
       4: invokestatic  #31                 // Method b/a/a/c.a:(Lb/a/a/c;)Ljava/util/List;
       7: aload_0
       8: getfield      #20                 // Field a:Landroid/support/v7/widget/RecyclerView$x;
      11: invokevirtual #37                 // Method android/support/v7/widget/RecyclerView$x.d:()I
      14: invokeinterface #43,  2           // InterfaceMethod java/util/List.get:(I)Ljava/lang/Object;
      19: checkcast     #45                 // class b/a/a/b
      22: astore_1
      23: aload_0
      24: getfield      #20                 // Field a:Landroid/support/v7/widget/RecyclerView$x;
      27: getfield      #48                 // Field android/support/v7/widget/RecyclerView$x.a:Landroid/view/View;
      30: invokevirtual #54                 // Method android/view/View.getTag:()Ljava/lang/Object;
      33: checkcast     #56                 // class java/lang/Long
      36: invokevirtual #60                 // Method java/lang/Long.longValue:()J
      39: lstore_3
      40: invokestatic  #65                 // Method java/lang/System.currentTimeMillis:()J
      43: lstore        5
      45: lload         5
      47: lload_3
      48: lsub
      49: ldc2_w        #66                 // long 500l
      52: lcmp
      53: ifge          73
      56: return
      57: aload_0
      58: getfield      #20                 // Field a:Landroid/support/v7/widget/RecyclerView$x;
      61: getfield      #48                 // Field android/support/v7/widget/RecyclerView$x.a:Landroid/view/View;
      64: invokestatic  #65                 // Method java/lang/System.currentTimeMillis:()J
      67: invokestatic  #71                 // Method java/lang/Long.valueOf:(J)Ljava/lang/Long;
      70: invokevirtual #75                 // Method android/view/View.setTag:(Ljava/lang/Object;)V
      73: aload_0
      74: getfield      #20                 // Field a:Landroid/support/v7/widget/RecyclerView$x;
      77: getfield      #48                 // Field android/support/v7/widget/RecyclerView$x.a:Landroid/view/View;
      80: invokestatic  #65                 // Method java/lang/System.currentTimeMillis:()J
      83: invokestatic  #71                 // Method java/lang/Long.valueOf:(J)Ljava/lang/Long;
      86: invokevirtual #75                 // Method android/view/View.setTag:(Ljava/lang/Object;)V
      89: aload_0
      90: getfield      #18                 // Field b:Lb/a/a/c;
      93: invokestatic  #78                 // Method b/a/a/c.b:(Lb/a/a/c;)Lb/a/a/c$a;
      96: ifnull        120
      99: aload_0
     100: getfield      #18                 // Field b:Lb/a/a/c;
     103: invokestatic  #78                 // Method b/a/a/c.b:(Lb/a/a/c;)Lb/a/a/c$a;
     106: aload_1
     107: aload_0
     108: getfield      #20                 // Field a:Landroid/support/v7/widget/RecyclerView$x;
     111: invokeinterface #83,  3           // InterfaceMethod b/a/a/c$a.a:(Lb/a/a/b;Landroid/support/v7/widget/RecyclerView$x;)Z
     116: ifeq          120
     119: return
     120: aload_1
     121: invokevirtual #87                 // Method b/a/a/b.c:()Z
     124: ifeq          128
     127: return
     128: aload_1
     129: invokevirtual #90                 // Method b/a/a/b.g:()Z
     132: istore        7
     134: aload_0
     135: getfield      #18                 // Field b:Lb/a/a/c;
     138: invokestatic  #31                 // Method b/a/a/c.a:(Lb/a/a/c;)Ljava/util/List;
     141: aload_1
     142: invokeinterface #94,  2           // InterfaceMethod java/util/List.indexOf:(Ljava/lang/Object;)I
     147: iconst_1
     148: iadd
     149: istore_2
     150: iload         7
     152: ifne          173
     155: aload_0
     156: getfield      #18                 // Field b:Lb/a/a/c;
     159: iload_2
     160: aload_0
     161: getfield      #18                 // Field b:Lb/a/a/c;
     164: aload_1
     165: iload_2
     166: invokestatic  #97                 // Method b/a/a/c.a:(Lb/a/a/c;Lb/a/a/b;I)I
     169: invokevirtual #100                // Method b/a/a/c.b:(II)V
     172: return
     173: aload_0
     174: getfield      #18                 // Field b:Lb/a/a/c;
     177: iload_2
     178: aload_0
     179: getfield      #18                 // Field b:Lb/a/a/c;
     182: aload_1
     183: iconst_1
     184: invokestatic  #103                // Method b/a/a/c.a:(Lb/a/a/c;Lb/a/a/b;Z)I
     187: invokevirtual #105                // Method b/a/a/c.c:(II)V
     190: return
     191: astore        8
     193: goto          57
    Exception table:
       from    to  target type
          23    45   191   Class java/lang/Exception
}
