public class ryey.easer.plugins.a.i.d extends ryey.easer.plugins.c<ryey.easer.plugins.a.i.a> {
  public ryey.easer.plugins.a.i.d();
    Code:
       0: aload_0
       1: invokespecial #13                 // Method ryey/easer/plugins/c."<init>":()V
       4: return

  public ryey.easer.commons.local_plugin.f a();
    Code:
       0: aload_0
       1: invokevirtual #18                 // Method b:()Lryey/easer/plugins/a/i/a;
       4: areturn

  protected void a(ryey.easer.plugins.a.i.a);
    Code:
       0: aload_1
       1: getfield      #24                 // Field ryey/easer/plugins/a/i/a.a:Lryey/easer/plugins/a/i/a$a;
       4: getstatic     #27                 // Field ryey/easer/plugins/a/i/a$a.a:Lryey/easer/plugins/a/i/a$a;
       7: if_acmpne     21
      10: aload_0
      11: getfield      #29                 // Field a:Landroid/widget/RadioButton;
      14: astore_1
      15: aload_1
      16: iconst_1
      17: invokevirtual #35                 // Method android/widget/RadioButton.setChecked:(Z)V
      20: return
      21: aload_1
      22: getfield      #24                 // Field ryey/easer/plugins/a/i/a.a:Lryey/easer/plugins/a/i/a$a;
      25: getstatic     #37                 // Field ryey/easer/plugins/a/i/a$a.b:Lryey/easer/plugins/a/i/a$a;
      28: if_acmpne     39
      31: aload_0
      32: getfield      #39                 // Field b:Landroid/widget/RadioButton;
      35: astore_1
      36: goto          15
      39: aload_1
      40: getfield      #24                 // Field ryey/easer/plugins/a/i/a.a:Lryey/easer/plugins/a/i/a$a;
      43: getstatic     #41                 // Field ryey/easer/plugins/a/i/a$a.c:Lryey/easer/plugins/a/i/a$a;
      46: if_acmpne     57
      49: aload_0
      50: getfield      #43                 // Field c:Landroid/widget/RadioButton;
      53: astore_1
      54: goto          15
      57: return

  public ryey.easer.plugins.a.i.a b();
    Code:
       0: aload_0
       1: getfield      #29                 // Field a:Landroid/widget/RadioButton;
       4: invokevirtual #47                 // Method android/widget/RadioButton.isChecked:()Z
       7: ifeq          21
      10: new           #21                 // class ryey/easer/plugins/a/i/a
      13: dup
      14: getstatic     #27                 // Field ryey/easer/plugins/a/i/a$a.a:Lryey/easer/plugins/a/i/a$a;
      17: invokespecial #50                 // Method ryey/easer/plugins/a/i/a."<init>":(Lryey/easer/plugins/a/i/a$a;)V
      20: areturn
      21: aload_0
      22: getfield      #39                 // Field b:Landroid/widget/RadioButton;
      25: invokevirtual #47                 // Method android/widget/RadioButton.isChecked:()Z
      28: ifeq          42
      31: new           #21                 // class ryey/easer/plugins/a/i/a
      34: dup
      35: getstatic     #37                 // Field ryey/easer/plugins/a/i/a$a.b:Lryey/easer/plugins/a/i/a$a;
      38: invokespecial #50                 // Method ryey/easer/plugins/a/i/a."<init>":(Lryey/easer/plugins/a/i/a$a;)V
      41: areturn
      42: new           #21                 // class ryey/easer/plugins/a/i/a
      45: dup
      46: getstatic     #41                 // Field ryey/easer/plugins/a/i/a$a.c:Lryey/easer/plugins/a/i/a$a;
      49: invokespecial #50                 // Method ryey/easer/plugins/a/i/a."<init>":(Lryey/easer/plugins/a/i/a$a;)V
      52: areturn

  protected void b(ryey.easer.commons.local_plugin.f);
    Code:
       0: aload_0
       1: aload_1
       2: checkcast     #21                 // class ryey/easer/plugins/a/i/a
       5: invokevirtual #53                 // Method a:(Lryey/easer/plugins/a/i/a;)V
       8: return

  public android.view.View onCreateView(android.view.LayoutInflater, android.view.ViewGroup, android.os.Bundle);
    Code:
       0: aload_1
       1: ldc           #56                 // int 2131427439
       3: aload_2
       4: iconst_0
       5: invokevirtual #62                 // Method android/view/LayoutInflater.inflate:(ILandroid/view/ViewGroup;Z)Landroid/view/View;
       8: astore_1
       9: aload_0
      10: aload_1
      11: ldc           #63                 // int 2131296551
      13: invokevirtual #69                 // Method android/view/View.findViewById:(I)Landroid/view/View;
      16: checkcast     #31                 // class android/widget/RadioButton
      19: putfield      #29                 // Field a:Landroid/widget/RadioButton;
      22: aload_0
      23: aload_1
      24: ldc           #70                 // int 2131296550
      26: invokevirtual #69                 // Method android/view/View.findViewById:(I)Landroid/view/View;
      29: checkcast     #31                 // class android/widget/RadioButton
      32: putfield      #39                 // Field b:Landroid/widget/RadioButton;
      35: aload_0
      36: aload_1
      37: ldc           #71                 // int 2131296552
      39: invokevirtual #69                 // Method android/view/View.findViewById:(I)Landroid/view/View;
      42: checkcast     #31                 // class android/widget/RadioButton
      45: putfield      #43                 // Field c:Landroid/widget/RadioButton;
      48: aload_1
      49: areturn
}
