public class ryey.easer.core.ui.setting.c extends android.preference.Preference {
  public ryey.easer.core.ui.setting.c(android.content.Context, ryey.easer.core.g);
    Code:
       0: aload_0
       1: aload_1
       2: invokespecial #9                  // Method android/preference/Preference."<init>":(Landroid/content/Context;)V
       5: aload_0
       6: aload_2
       7: invokevirtual #15                 // Method ryey/easer/core/g.e:()Ljava/lang/String;
      10: invokevirtual #19                 // Method setTitle:(Ljava/lang/CharSequence;)V
      13: return
}
