class android.support.v4.app.a$d extends android.app.SharedElementCallback {
  protected android.support.v4.app.ah a;

  android.support.v4.app.a$d(android.support.v4.app.ah);
    Code:
       0: aload_0
       1: invokespecial #14                 // Method android/app/SharedElementCallback."<init>":()V
       4: aload_0
       5: aload_1
       6: putfield      #16                 // Field a:Landroid/support/v4/app/ah;
       9: return

  public android.os.Parcelable onCaptureSharedElementSnapshot(android.view.View, android.graphics.Matrix, android.graphics.RectF);
    Code:
       0: aload_0
       1: getfield      #16                 // Field a:Landroid/support/v4/app/ah;
       4: aload_1
       5: aload_2
       6: aload_3
       7: invokevirtual #23                 // Method android/support/v4/app/ah.a:(Landroid/view/View;Landroid/graphics/Matrix;Landroid/graphics/RectF;)Landroid/os/Parcelable;
      10: areturn

  public android.view.View onCreateSnapshotView(android.content.Context, android.os.Parcelable);
    Code:
       0: aload_0
       1: getfield      #16                 // Field a:Landroid/support/v4/app/ah;
       4: aload_1
       5: aload_2
       6: invokevirtual #27                 // Method android/support/v4/app/ah.a:(Landroid/content/Context;Landroid/os/Parcelable;)Landroid/view/View;
       9: areturn

  public void onMapSharedElements(java.util.List<java.lang.String>, java.util.Map<java.lang.String, android.view.View>);
    Code:
       0: aload_0
       1: getfield      #16                 // Field a:Landroid/support/v4/app/ah;
       4: aload_1
       5: aload_2
       6: invokevirtual #31                 // Method android/support/v4/app/ah.a:(Ljava/util/List;Ljava/util/Map;)V
       9: return

  public void onRejectSharedElements(java.util.List<android.view.View>);
    Code:
       0: aload_0
       1: getfield      #16                 // Field a:Landroid/support/v4/app/ah;
       4: aload_1
       5: invokevirtual #37                 // Method android/support/v4/app/ah.a:(Ljava/util/List;)V
       8: return

  public void onSharedElementEnd(java.util.List<java.lang.String>, java.util.List<android.view.View>, java.util.List<android.view.View>);
    Code:
       0: aload_0
       1: getfield      #16                 // Field a:Landroid/support/v4/app/ah;
       4: aload_1
       5: aload_2
       6: aload_3
       7: invokevirtual #43                 // Method android/support/v4/app/ah.b:(Ljava/util/List;Ljava/util/List;Ljava/util/List;)V
      10: return

  public void onSharedElementStart(java.util.List<java.lang.String>, java.util.List<android.view.View>, java.util.List<android.view.View>);
    Code:
       0: aload_0
       1: getfield      #16                 // Field a:Landroid/support/v4/app/ah;
       4: aload_1
       5: aload_2
       6: aload_3
       7: invokevirtual #47                 // Method android/support/v4/app/ah.a:(Ljava/util/List;Ljava/util/List;Ljava/util/List;)V
      10: return
}
