class android.support.v4.app.a$e extends android.support.v4.app.a$d {
  android.support.v4.app.a$e(android.support.v4.app.ah);
    Code:
       0: aload_0
       1: aload_1
       2: invokespecial #13                 // Method android/support/v4/app/a$d."<init>":(Landroid/support/v4/app/ah;)V
       5: return

  public void onSharedElementsArrived(java.util.List<java.lang.String>, java.util.List<android.view.View>, android.app.SharedElementCallback$OnSharedElementsReadyListener);
    Code:
       0: aload_0
       1: getfield      #20                 // Field a:Landroid/support/v4/app/ah;
       4: aload_1
       5: aload_2
       6: new           #9                  // class android/support/v4/app/a$e$1
       9: dup
      10: aload_0
      11: aload_3
      12: invokespecial #23                 // Method android/support/v4/app/a$e$1."<init>":(Landroid/support/v4/app/a$e;Landroid/app/SharedElementCallback$OnSharedElementsReadyListener;)V
      15: invokevirtual #28                 // Method android/support/v4/app/ah.a:(Ljava/util/List;Ljava/util/List;Landroid/support/v4/app/ah$a;)V
      18: return
}
