public class android.support.v4.app.ac$a {
  final android.os.Bundle a;

  public int b;

  public java.lang.CharSequence c;

  public android.app.PendingIntent d;

  public int a();
    Code:
       0: aload_0
       1: getfield      #22                 // Field b:I
       4: ireturn

  public java.lang.CharSequence b();
    Code:
       0: aload_0
       1: getfield      #26                 // Field c:Ljava/lang/CharSequence;
       4: areturn

  public android.app.PendingIntent c();
    Code:
       0: aload_0
       1: getfield      #29                 // Field d:Landroid/app/PendingIntent;
       4: areturn

  public android.os.Bundle d();
    Code:
       0: aload_0
       1: getfield      #32                 // Field a:Landroid/os/Bundle;
       4: areturn

  public boolean e();
    Code:
       0: aload_0
       1: getfield      #35                 // Field g:Z
       4: ireturn

  public android.support.v4.app.ag[] f();
    Code:
       0: aload_0
       1: getfield      #38                 // Field e:[Landroid/support/v4/app/ag;
       4: areturn

  public android.support.v4.app.ag[] g();
    Code:
       0: aload_0
       1: getfield      #40                 // Field f:[Landroid/support/v4/app/ag;
       4: areturn
}
