final class android.support.v4.app.c$a {
  int a;

  android.support.v4.app.i b;

  int c;

  int d;

  int e;

  int f;

  android.support.v4.app.c$a();
    Code:
       0: aload_0
       1: invokespecial #18                 // Method java/lang/Object."<init>":()V
       4: return

  android.support.v4.app.c$a(int, android.support.v4.app.i);
    Code:
       0: aload_0
       1: invokespecial #18                 // Method java/lang/Object."<init>":()V
       4: aload_0
       5: iload_1
       6: putfield      #22                 // Field a:I
       9: aload_0
      10: aload_2
      11: putfield      #24                 // Field b:Landroid/support/v4/app/i;
      14: return
}
