class android.support.v4.app.i$a {
  android.view.View a;

  android.animation.Animator b;

  int c;

  int d;

  int e;

  int f;

  android.support.v4.app.ah g;

  android.support.v4.app.ah h;

  boolean i;

  android.support.v4.app.i$c j;

  boolean k;

  android.support.v4.app.i$a();
    Code:
       0: aload_0
       1: invokespecial #37                 // Method java/lang/Object."<init>":()V
       4: aload_0
       5: aconst_null
       6: putfield      #39                 // Field l:Ljava/lang/Object;
       9: aload_0
      10: getstatic     #42                 // Field android/support/v4/app/i.USE_DEFAULT_TRANSITION:Ljava/lang/Object;
      13: putfield      #44                 // Field m:Ljava/lang/Object;
      16: aload_0
      17: aconst_null
      18: putfield      #46                 // Field n:Ljava/lang/Object;
      21: aload_0
      22: getstatic     #42                 // Field android/support/v4/app/i.USE_DEFAULT_TRANSITION:Ljava/lang/Object;
      25: putfield      #48                 // Field o:Ljava/lang/Object;
      28: aload_0
      29: aconst_null
      30: putfield      #50                 // Field p:Ljava/lang/Object;
      33: aload_0
      34: getstatic     #42                 // Field android/support/v4/app/i.USE_DEFAULT_TRANSITION:Ljava/lang/Object;
      37: putfield      #52                 // Field q:Ljava/lang/Object;
      40: aload_0
      41: aconst_null
      42: putfield      #54                 // Field g:Landroid/support/v4/app/ah;
      45: aload_0
      46: aconst_null
      47: putfield      #56                 // Field h:Landroid/support/v4/app/ah;
      50: return

  static java.lang.Boolean a(android.support.v4.app.i$a, java.lang.Boolean);
    Code:
       0: aload_0
       1: aload_1
       2: putfield      #60                 // Field s:Ljava/lang/Boolean;
       5: aload_1
       6: areturn

  static java.lang.Object a(android.support.v4.app.i$a);
    Code:
       0: aload_0
       1: getfield      #39                 // Field l:Ljava/lang/Object;
       4: areturn

  static java.lang.Object a(android.support.v4.app.i$a, java.lang.Object);
    Code:
       0: aload_0
       1: aload_1
       2: putfield      #39                 // Field l:Ljava/lang/Object;
       5: aload_1
       6: areturn

  static java.lang.Boolean b(android.support.v4.app.i$a, java.lang.Boolean);
    Code:
       0: aload_0
       1: aload_1
       2: putfield      #64                 // Field r:Ljava/lang/Boolean;
       5: aload_1
       6: areturn

  static java.lang.Object b(android.support.v4.app.i$a);
    Code:
       0: aload_0
       1: getfield      #44                 // Field m:Ljava/lang/Object;
       4: areturn

  static java.lang.Object b(android.support.v4.app.i$a, java.lang.Object);
    Code:
       0: aload_0
       1: aload_1
       2: putfield      #44                 // Field m:Ljava/lang/Object;
       5: aload_1
       6: areturn

  static java.lang.Object c(android.support.v4.app.i$a);
    Code:
       0: aload_0
       1: getfield      #46                 // Field n:Ljava/lang/Object;
       4: areturn

  static java.lang.Object c(android.support.v4.app.i$a, java.lang.Object);
    Code:
       0: aload_0
       1: aload_1
       2: putfield      #46                 // Field n:Ljava/lang/Object;
       5: aload_1
       6: areturn

  static java.lang.Object d(android.support.v4.app.i$a);
    Code:
       0: aload_0
       1: getfield      #48                 // Field o:Ljava/lang/Object;
       4: areturn

  static java.lang.Object d(android.support.v4.app.i$a, java.lang.Object);
    Code:
       0: aload_0
       1: aload_1
       2: putfield      #48                 // Field o:Ljava/lang/Object;
       5: aload_1
       6: areturn

  static java.lang.Object e(android.support.v4.app.i$a);
    Code:
       0: aload_0
       1: getfield      #50                 // Field p:Ljava/lang/Object;
       4: areturn

  static java.lang.Object e(android.support.v4.app.i$a, java.lang.Object);
    Code:
       0: aload_0
       1: aload_1
       2: putfield      #50                 // Field p:Ljava/lang/Object;
       5: aload_1
       6: areturn

  static java.lang.Object f(android.support.v4.app.i$a);
    Code:
       0: aload_0
       1: getfield      #52                 // Field q:Ljava/lang/Object;
       4: areturn

  static java.lang.Object f(android.support.v4.app.i$a, java.lang.Object);
    Code:
       0: aload_0
       1: aload_1
       2: putfield      #52                 // Field q:Ljava/lang/Object;
       5: aload_1
       6: areturn

  static java.lang.Boolean g(android.support.v4.app.i$a);
    Code:
       0: aload_0
       1: getfield      #60                 // Field s:Ljava/lang/Boolean;
       4: areturn

  static java.lang.Boolean h(android.support.v4.app.i$a);
    Code:
       0: aload_0
       1: getfield      #64                 // Field r:Ljava/lang/Boolean;
       4: areturn
}
