public abstract class android.support.v4.app.k {
  public android.support.v4.app.k();
    Code:
       0: aload_0
       1: invokespecial #8                  // Method java/lang/Object."<init>":()V
       4: return

  public android.support.v4.app.i a(android.content.Context, java.lang.String, android.os.Bundle);
    Code:
       0: aload_1
       1: aload_2
       2: aload_3
       3: invokestatic  #16                 // Method android/support/v4/app/i.instantiate:(Landroid/content/Context;Ljava/lang/String;Landroid/os/Bundle;)Landroid/support/v4/app/i;
       6: areturn

  public abstract android.view.View a(int);

  public abstract boolean a();
}
