public class android.support.v4.app.l {
  public static android.support.v4.app.l a(android.support.v4.app.m<?>);
    Code:
       0: new           #2                  // class android/support/v4/app/l
       3: dup
       4: aload_0
       5: invokespecial #20                 // Method "<init>":(Landroid/support/v4/app/m;)V
       8: areturn

  public android.support.v4.app.i a(java.lang.String);
    Code:
       0: aload_0
       1: getfield      #14                 // Field a:Landroid/support/v4/app/m;
       4: getfield      #28                 // Field android/support/v4/app/m.d:Landroid/support/v4/app/o;
       7: aload_1
       8: invokevirtual #33                 // Method android/support/v4/app/o.b:(Ljava/lang/String;)Landroid/support/v4/app/i;
      11: areturn

  public android.support.v4.app.n a();
    Code:
       0: aload_0
       1: getfield      #14                 // Field a:Landroid/support/v4/app/m;
       4: invokevirtual #38                 // Method android/support/v4/app/m.k:()Landroid/support/v4/app/o;
       7: areturn

  public android.view.View a(android.view.View, java.lang.String, android.content.Context, android.util.AttributeSet);
    Code:
       0: aload_0
       1: getfield      #14                 // Field a:Landroid/support/v4/app/m;
       4: getfield      #28                 // Field android/support/v4/app/m.d:Landroid/support/v4/app/o;
       7: aload_1
       8: aload_2
       9: aload_3
      10: aload         4
      12: invokevirtual #42                 // Method android/support/v4/app/o.onCreateView:(Landroid/view/View;Ljava/lang/String;Landroid/content/Context;Landroid/util/AttributeSet;)Landroid/view/View;
      15: areturn

  public void a(android.content.res.Configuration);
    Code:
       0: aload_0
       1: getfield      #14                 // Field a:Landroid/support/v4/app/m;
       4: getfield      #28                 // Field android/support/v4/app/m.d:Landroid/support/v4/app/o;
       7: aload_1
       8: invokevirtual #45                 // Method android/support/v4/app/o.a:(Landroid/content/res/Configuration;)V
      11: return

  public void a(android.os.Parcelable, android.support.v4.app.p);
    Code:
       0: aload_0
       1: getfield      #14                 // Field a:Landroid/support/v4/app/m;
       4: getfield      #28                 // Field android/support/v4/app/m.d:Landroid/support/v4/app/o;
       7: aload_1
       8: aload_2
       9: invokevirtual #48                 // Method android/support/v4/app/o.a:(Landroid/os/Parcelable;Landroid/support/v4/app/p;)V
      12: return

  public void a(android.support.v4.app.i);
    Code:
       0: aload_0
       1: getfield      #14                 // Field a:Landroid/support/v4/app/m;
       4: getfield      #28                 // Field android/support/v4/app/m.d:Landroid/support/v4/app/o;
       7: aload_0
       8: getfield      #14                 // Field a:Landroid/support/v4/app/m;
      11: aload_0
      12: getfield      #14                 // Field a:Landroid/support/v4/app/m;
      15: aload_1
      16: invokevirtual #52                 // Method android/support/v4/app/o.a:(Landroid/support/v4/app/m;Landroid/support/v4/app/k;Landroid/support/v4/app/i;)V
      19: return

  public void a(boolean);
    Code:
       0: aload_0
       1: getfield      #14                 // Field a:Landroid/support/v4/app/m;
       4: getfield      #28                 // Field android/support/v4/app/m.d:Landroid/support/v4/app/o;
       7: iload_1
       8: invokevirtual #55                 // Method android/support/v4/app/o.a:(Z)V
      11: return

  public boolean a(android.view.Menu);
    Code:
       0: aload_0
       1: getfield      #14                 // Field a:Landroid/support/v4/app/m;
       4: getfield      #28                 // Field android/support/v4/app/m.d:Landroid/support/v4/app/o;
       7: aload_1
       8: invokevirtual #58                 // Method android/support/v4/app/o.a:(Landroid/view/Menu;)Z
      11: ireturn

  public boolean a(android.view.Menu, android.view.MenuInflater);
    Code:
       0: aload_0
       1: getfield      #14                 // Field a:Landroid/support/v4/app/m;
       4: getfield      #28                 // Field android/support/v4/app/m.d:Landroid/support/v4/app/o;
       7: aload_1
       8: aload_2
       9: invokevirtual #61                 // Method android/support/v4/app/o.a:(Landroid/view/Menu;Landroid/view/MenuInflater;)Z
      12: ireturn

  public boolean a(android.view.MenuItem);
    Code:
       0: aload_0
       1: getfield      #14                 // Field a:Landroid/support/v4/app/m;
       4: getfield      #28                 // Field android/support/v4/app/m.d:Landroid/support/v4/app/o;
       7: aload_1
       8: invokevirtual #64                 // Method android/support/v4/app/o.a:(Landroid/view/MenuItem;)Z
      11: ireturn

  public void b();
    Code:
       0: aload_0
       1: getfield      #14                 // Field a:Landroid/support/v4/app/m;
       4: getfield      #28                 // Field android/support/v4/app/m.d:Landroid/support/v4/app/o;
       7: invokevirtual #67                 // Method android/support/v4/app/o.m:()V
      10: return

  public void b(android.view.Menu);
    Code:
       0: aload_0
       1: getfield      #14                 // Field a:Landroid/support/v4/app/m;
       4: getfield      #28                 // Field android/support/v4/app/m.d:Landroid/support/v4/app/o;
       7: aload_1
       8: invokevirtual #70                 // Method android/support/v4/app/o.b:(Landroid/view/Menu;)V
      11: return

  public void b(boolean);
    Code:
       0: aload_0
       1: getfield      #14                 // Field a:Landroid/support/v4/app/m;
       4: getfield      #28                 // Field android/support/v4/app/m.d:Landroid/support/v4/app/o;
       7: iload_1
       8: invokevirtual #72                 // Method android/support/v4/app/o.b:(Z)V
      11: return

  public boolean b(android.view.MenuItem);
    Code:
       0: aload_0
       1: getfield      #14                 // Field a:Landroid/support/v4/app/m;
       4: getfield      #28                 // Field android/support/v4/app/m.d:Landroid/support/v4/app/o;
       7: aload_1
       8: invokevirtual #74                 // Method android/support/v4/app/o.b:(Landroid/view/MenuItem;)Z
      11: ireturn

  public android.os.Parcelable c();
    Code:
       0: aload_0
       1: getfield      #14                 // Field a:Landroid/support/v4/app/m;
       4: getfield      #28                 // Field android/support/v4/app/m.d:Landroid/support/v4/app/o;
       7: invokevirtual #79                 // Method android/support/v4/app/o.l:()Landroid/os/Parcelable;
      10: areturn

  public android.support.v4.app.p d();
    Code:
       0: aload_0
       1: getfield      #14                 // Field a:Landroid/support/v4/app/m;
       4: getfield      #28                 // Field android/support/v4/app/m.d:Landroid/support/v4/app/o;
       7: invokevirtual #83                 // Method android/support/v4/app/o.j:()Landroid/support/v4/app/p;
      10: areturn

  public void e();
    Code:
       0: aload_0
       1: getfield      #14                 // Field a:Landroid/support/v4/app/m;
       4: getfield      #28                 // Field android/support/v4/app/m.d:Landroid/support/v4/app/o;
       7: invokevirtual #87                 // Method android/support/v4/app/o.n:()V
      10: return

  public void f();
    Code:
       0: aload_0
       1: getfield      #14                 // Field a:Landroid/support/v4/app/m;
       4: getfield      #28                 // Field android/support/v4/app/m.d:Landroid/support/v4/app/o;
       7: invokevirtual #91                 // Method android/support/v4/app/o.o:()V
      10: return

  public void g();
    Code:
       0: aload_0
       1: getfield      #14                 // Field a:Landroid/support/v4/app/m;
       4: getfield      #28                 // Field android/support/v4/app/m.d:Landroid/support/v4/app/o;
       7: invokevirtual #95                 // Method android/support/v4/app/o.p:()V
      10: return

  public void h();
    Code:
       0: aload_0
       1: getfield      #14                 // Field a:Landroid/support/v4/app/m;
       4: getfield      #28                 // Field android/support/v4/app/m.d:Landroid/support/v4/app/o;
       7: invokevirtual #99                 // Method android/support/v4/app/o.q:()V
      10: return

  public void i();
    Code:
       0: aload_0
       1: getfield      #14                 // Field a:Landroid/support/v4/app/m;
       4: getfield      #28                 // Field android/support/v4/app/m.d:Landroid/support/v4/app/o;
       7: invokevirtual #103                // Method android/support/v4/app/o.r:()V
      10: return

  public void j();
    Code:
       0: aload_0
       1: getfield      #14                 // Field a:Landroid/support/v4/app/m;
       4: getfield      #28                 // Field android/support/v4/app/m.d:Landroid/support/v4/app/o;
       7: invokevirtual #106                // Method android/support/v4/app/o.s:()V
      10: return

  public void k();
    Code:
       0: aload_0
       1: getfield      #14                 // Field a:Landroid/support/v4/app/m;
       4: getfield      #28                 // Field android/support/v4/app/m.d:Landroid/support/v4/app/o;
       7: invokevirtual #109                // Method android/support/v4/app/o.t:()V
      10: return

  public void l();
    Code:
       0: aload_0
       1: getfield      #14                 // Field a:Landroid/support/v4/app/m;
       4: getfield      #28                 // Field android/support/v4/app/m.d:Landroid/support/v4/app/o;
       7: invokevirtual #112                // Method android/support/v4/app/o.v:()V
      10: return

  public void m();
    Code:
       0: aload_0
       1: getfield      #14                 // Field a:Landroid/support/v4/app/m;
       4: getfield      #28                 // Field android/support/v4/app/m.d:Landroid/support/v4/app/o;
       7: invokevirtual #115                // Method android/support/v4/app/o.w:()V
      10: return

  public boolean n();
    Code:
       0: aload_0
       1: getfield      #14                 // Field a:Landroid/support/v4/app/m;
       4: getfield      #28                 // Field android/support/v4/app/m.d:Landroid/support/v4/app/o;
       7: invokevirtual #118                // Method android/support/v4/app/o.g:()Z
      10: ireturn
}
