public abstract class android.support.v4.app.n$a {
  public android.support.v4.app.n$a();
    Code:
       0: aload_0
       1: invokespecial #11                 // Method java/lang/Object."<init>":()V
       4: return

  public void a(android.support.v4.app.n, android.support.v4.app.i);
    Code:
       0: return

  public void a(android.support.v4.app.n, android.support.v4.app.i, android.content.Context);
    Code:
       0: return

  public void a(android.support.v4.app.n, android.support.v4.app.i, android.os.Bundle);
    Code:
       0: return

  public void a(android.support.v4.app.n, android.support.v4.app.i, android.view.View, android.os.Bundle);
    Code:
       0: return

  public void b(android.support.v4.app.n, android.support.v4.app.i);
    Code:
       0: return

  public void b(android.support.v4.app.n, android.support.v4.app.i, android.content.Context);
    Code:
       0: return

  public void b(android.support.v4.app.n, android.support.v4.app.i, android.os.Bundle);
    Code:
       0: return

  public void c(android.support.v4.app.n, android.support.v4.app.i);
    Code:
       0: return

  public void c(android.support.v4.app.n, android.support.v4.app.i, android.os.Bundle);
    Code:
       0: return

  public void d(android.support.v4.app.n, android.support.v4.app.i);
    Code:
       0: return

  public void d(android.support.v4.app.n, android.support.v4.app.i, android.os.Bundle);
    Code:
       0: return

  public void e(android.support.v4.app.n, android.support.v4.app.i);
    Code:
       0: return

  public void f(android.support.v4.app.n, android.support.v4.app.i);
    Code:
       0: return

  public void g(android.support.v4.app.n, android.support.v4.app.i);
    Code:
       0: return
}
