class android.support.v4.app.o$c {
  public final android.view.animation.Animation a;

  public final android.animation.Animator b;

  android.support.v4.app.o$c(android.animation.Animator, android.support.v4.app.o$1);
    Code:
       0: aload_0
       1: aload_1
       2: invokespecial #31                 // Method "<init>":(Landroid/animation/Animator;)V
       5: return

  android.support.v4.app.o$c(android.view.animation.Animation, android.support.v4.app.o$1);
    Code:
       0: aload_0
       1: aload_1
       2: invokespecial #37                 // Method "<init>":(Landroid/view/animation/Animation;)V
       5: return
}
