public class android.support.v4.app.p {
  android.support.v4.app.p(java.util.List<android.support.v4.app.i>, java.util.List<android.support.v4.app.p>, java.util.List<android.arch.lifecycle.p>);
    Code:
       0: aload_0
       1: invokespecial #16                 // Method java/lang/Object."<init>":()V
       4: aload_0
       5: aload_1
       6: putfield      #18                 // Field a:Ljava/util/List;
       9: aload_0
      10: aload_2
      11: putfield      #20                 // Field b:Ljava/util/List;
      14: aload_0
      15: aload_3
      16: putfield      #22                 // Field c:Ljava/util/List;
      19: return

  java.util.List<android.support.v4.app.i> a();
    Code:
       0: aload_0
       1: getfield      #18                 // Field a:Ljava/util/List;
       4: areturn

  java.util.List<android.support.v4.app.p> b();
    Code:
       0: aload_0
       1: getfield      #20                 // Field b:Ljava/util/List;
       4: areturn

  java.util.List<android.arch.lifecycle.p> c();
    Code:
       0: aload_0
       1: getfield      #22                 // Field c:Ljava/util/List;
       4: areturn
}
