final class android.support.v4.app.v$2 implements java.lang.Runnable {
  final java.lang.Object a;

  final android.support.v4.app.x b;

  final android.view.View c;

  final android.support.v4.app.i d;

  final java.util.ArrayList e;

  final java.util.ArrayList f;

  final java.util.ArrayList g;

  final java.lang.Object h;

  android.support.v4.app.v$2(java.lang.Object, android.support.v4.app.x, android.view.View, android.support.v4.app.i, java.util.ArrayList, java.util.ArrayList, java.util.ArrayList, java.lang.Object);
    Code:
       0: aload_0
       1: aload_1
       2: putfield      #27                 // Field a:Ljava/lang/Object;
       5: aload_0
       6: aload_2
       7: putfield      #29                 // Field b:Landroid/support/v4/app/x;
      10: aload_0
      11: aload_3
      12: putfield      #31                 // Field c:Landroid/view/View;
      15: aload_0
      16: aload         4
      18: putfield      #33                 // Field d:Landroid/support/v4/app/i;
      21: aload_0
      22: aload         5
      24: putfield      #35                 // Field e:Ljava/util/ArrayList;
      27: aload_0
      28: aload         6
      30: putfield      #37                 // Field f:Ljava/util/ArrayList;
      33: aload_0
      34: aload         7
      36: putfield      #39                 // Field g:Ljava/util/ArrayList;
      39: aload_0
      40: aload         8
      42: putfield      #41                 // Field h:Ljava/lang/Object;
      45: aload_0
      46: invokespecial #44                 // Method java/lang/Object."<init>":()V
      49: return

  public void run();
    Code:
       0: aload_0
       1: getfield      #27                 // Field a:Ljava/lang/Object;
       4: ifnull        55
       7: aload_0
       8: getfield      #29                 // Field b:Landroid/support/v4/app/x;
      11: aload_0
      12: getfield      #27                 // Field a:Ljava/lang/Object;
      15: aload_0
      16: getfield      #31                 // Field c:Landroid/view/View;
      19: invokevirtual #51                 // Method android/support/v4/app/x.c:(Ljava/lang/Object;Landroid/view/View;)V
      22: aload_0
      23: getfield      #29                 // Field b:Landroid/support/v4/app/x;
      26: aload_0
      27: getfield      #27                 // Field a:Ljava/lang/Object;
      30: aload_0
      31: getfield      #33                 // Field d:Landroid/support/v4/app/i;
      34: aload_0
      35: getfield      #35                 // Field e:Ljava/util/ArrayList;
      38: aload_0
      39: getfield      #31                 // Field c:Landroid/view/View;
      42: invokestatic  #54                 // Method android/support/v4/app/v.a:(Landroid/support/v4/app/x;Ljava/lang/Object;Landroid/support/v4/app/i;Ljava/util/ArrayList;Landroid/view/View;)Ljava/util/ArrayList;
      45: astore_1
      46: aload_0
      47: getfield      #37                 // Field f:Ljava/util/ArrayList;
      50: aload_1
      51: invokevirtual #60                 // Method java/util/ArrayList.addAll:(Ljava/util/Collection;)Z
      54: pop
      55: aload_0
      56: getfield      #39                 // Field g:Ljava/util/ArrayList;
      59: ifnull        121
      62: aload_0
      63: getfield      #41                 // Field h:Ljava/lang/Object;
      66: ifnull        102
      69: new           #56                 // class java/util/ArrayList
      72: dup
      73: invokespecial #61                 // Method java/util/ArrayList."<init>":()V
      76: astore_1
      77: aload_1
      78: aload_0
      79: getfield      #31                 // Field c:Landroid/view/View;
      82: invokevirtual #65                 // Method java/util/ArrayList.add:(Ljava/lang/Object;)Z
      85: pop
      86: aload_0
      87: getfield      #29                 // Field b:Landroid/support/v4/app/x;
      90: aload_0
      91: getfield      #41                 // Field h:Ljava/lang/Object;
      94: aload_0
      95: getfield      #39                 // Field g:Ljava/util/ArrayList;
      98: aload_1
      99: invokevirtual #68                 // Method android/support/v4/app/x.b:(Ljava/lang/Object;Ljava/util/ArrayList;Ljava/util/ArrayList;)V
     102: aload_0
     103: getfield      #39                 // Field g:Ljava/util/ArrayList;
     106: invokevirtual #71                 // Method java/util/ArrayList.clear:()V
     109: aload_0
     110: getfield      #39                 // Field g:Ljava/util/ArrayList;
     113: aload_0
     114: getfield      #31                 // Field c:Landroid/view/View;
     117: invokevirtual #65                 // Method java/util/ArrayList.add:(Ljava/lang/Object;)Z
     120: pop
     121: return
}
