class android.support.v4.app.v {
  static {};
    Code:
       0: bipush        10
       2: newarray       int
       4: dup
       5: iconst_0
       6: iconst_0
       7: iastore
       8: dup
       9: iconst_1
      10: iconst_3
      11: iastore
      12: dup
      13: iconst_2
      14: iconst_0
      15: iastore
      16: dup
      17: iconst_3
      18: iconst_1
      19: iastore
      20: dup
      21: iconst_4
      22: iconst_5
      23: iastore
      24: dup
      25: iconst_5
      26: iconst_4
      27: iastore
      28: dup
      29: bipush        6
      31: bipush        7
      33: iastore
      34: dup
      35: bipush        7
      37: bipush        6
      39: iastore
      40: dup
      41: bipush        8
      43: bipush        9
      45: iastore
      46: dup
      47: bipush        9
      49: bipush        8
      51: iastore
      52: putstatic     #23                 // Field a:[I
      55: getstatic     #29                 // Field android/os/Build$VERSION.SDK_INT:I
      58: bipush        21
      60: if_icmplt     74
      63: new           #31                 // class android/support/v4/app/w
      66: dup
      67: invokespecial #34                 // Method android/support/v4/app/w."<init>":()V
      70: astore_0
      71: goto          76
      74: aconst_null
      75: astore_0
      76: aload_0
      77: putstatic     #36                 // Field b:Landroid/support/v4/app/x;
      80: invokestatic  #39                 // Method a:()Landroid/support/v4/app/x;
      83: putstatic     #41                 // Field c:Landroid/support/v4/app/x;
      86: return

  static android.support.v4.g.a a(android.support.v4.app.x, android.support.v4.g.a, java.lang.Object, android.support.v4.app.v$a);
    Code:
       0: aload_0
       1: aload_1
       2: aload_2
       3: aload_3
       4: invokestatic  #159                // Method c:(Landroid/support/v4/app/x;Landroid/support/v4/g/a;Ljava/lang/Object;Landroid/support/v4/app/v$a;)Landroid/support/v4/g/a;
       7: areturn

  static android.view.View a(android.support.v4.g.a, android.support.v4.app.v$a, java.lang.Object, boolean);
    Code:
       0: aload_0
       1: aload_1
       2: aload_2
       3: iload_3
       4: invokestatic  #162                // Method b:(Landroid/support/v4/g/a;Landroid/support/v4/app/v$a;Ljava/lang/Object;Z)Landroid/view/View;
       7: areturn

  static java.util.ArrayList a(android.support.v4.app.x, java.lang.Object, android.support.v4.app.i, java.util.ArrayList, android.view.View);
    Code:
       0: aload_0
       1: aload_1
       2: aload_2
       3: aload_3
       4: aload         4
       6: invokestatic  #263                // Method b:(Landroid/support/v4/app/x;Ljava/lang/Object;Landroid/support/v4/app/i;Ljava/util/ArrayList;Landroid/view/View;)Ljava/util/ArrayList;
       9: areturn

  public static void a(android.support.v4.app.c, android.util.SparseArray<android.support.v4.app.v$a>, boolean);
    Code:
       0: aload_0
       1: getfield      #326                // Field android/support/v4/app/c.b:Ljava/util/ArrayList;
       4: invokevirtual #143                // Method java/util/ArrayList.size:()I
       7: istore        4
       9: iconst_0
      10: istore_3
      11: iload_3
      12: iload         4
      14: if_icmpge     42
      17: aload_0
      18: aload_0
      19: getfield      #326                // Field android/support/v4/app/c.b:Ljava/util/ArrayList;
      22: iload_3
      23: invokevirtual #125                // Method java/util/ArrayList.get:(I)Ljava/lang/Object;
      26: checkcast     #266                // class android/support/v4/app/c$a
      29: aload_1
      30: iconst_0
      31: iload_2
      32: invokestatic  #328                // Method a:(Landroid/support/v4/app/c;Landroid/support/v4/app/c$a;Landroid/util/SparseArray;ZZ)V
      35: iload_3
      36: iconst_1
      37: iadd
      38: istore_3
      39: goto          11
      42: return

  static void a(android.support.v4.app.i, android.support.v4.app.i, boolean, android.support.v4.g.a, boolean);
    Code:
       0: aload_0
       1: aload_1
       2: iload_2
       3: aload_3
       4: iload         4
       6: invokestatic  #210                // Method b:(Landroid/support/v4/app/i;Landroid/support/v4/app/i;ZLandroid/support/v4/g/a;Z)V
       9: return

  static void a(android.support.v4.app.o, java.util.ArrayList<android.support.v4.app.c>, java.util.ArrayList<java.lang.Boolean>, int, int, boolean);
    Code:
       0: aload_0
       1: getfield      #312                // Field android/support/v4/app/o.l:I
       4: iconst_1
       5: if_icmpge     9
       8: return
       9: new           #46                 // class android/util/SparseArray
      12: dup
      13: invokespecial #377                // Method android/util/SparseArray."<init>":()V
      16: astore        9
      18: iload_3
      19: istore        6
      21: iload         6
      23: iload         4
      25: if_icmpge     84
      28: aload_1
      29: iload         6
      31: invokevirtual #125                // Method java/util/ArrayList.get:(I)Ljava/lang/Object;
      34: checkcast     #127                // class android/support/v4/app/c
      37: astore        10
      39: aload_2
      40: iload         6
      42: invokevirtual #125                // Method java/util/ArrayList.get:(I)Ljava/lang/Object;
      45: checkcast     #132                // class java/lang/Boolean
      48: invokevirtual #135                // Method java/lang/Boolean.booleanValue:()Z
      51: ifeq          66
      54: aload         10
      56: aload         9
      58: iload         5
      60: invokestatic  #379                // Method b:(Landroid/support/v4/app/c;Landroid/util/SparseArray;Z)V
      63: goto          75
      66: aload         10
      68: aload         9
      70: iload         5
      72: invokestatic  #381                // Method a:(Landroid/support/v4/app/c;Landroid/util/SparseArray;Z)V
      75: iload         6
      77: iconst_1
      78: iadd
      79: istore        6
      81: goto          21
      84: aload         9
      86: invokevirtual #382                // Method android/util/SparseArray.size:()I
      89: ifeq          199
      92: new           #181                // class android/view/View
      95: dup
      96: aload_0
      97: getfield      #386                // Field android/support/v4/app/o.m:Landroid/support/v4/app/m;
     100: invokevirtual #392                // Method android/support/v4/app/m.i:()Landroid/content/Context;
     103: invokespecial #395                // Method android/view/View."<init>":(Landroid/content/Context;)V
     106: astore        10
     108: aload         9
     110: invokevirtual #382                // Method android/util/SparseArray.size:()I
     113: istore        7
     115: iconst_0
     116: istore        6
     118: iload         6
     120: iload         7
     122: if_icmpge     199
     125: aload         9
     127: iload         6
     129: invokevirtual #399                // Method android/util/SparseArray.keyAt:(I)I
     132: istore        8
     134: iload         8
     136: aload_1
     137: aload_2
     138: iload_3
     139: iload         4
     141: invokestatic  #401                // Method a:(ILjava/util/ArrayList;Ljava/util/ArrayList;II)Landroid/support/v4/g/a;
     144: astore        11
     146: aload         9
     148: iload         6
     150: invokevirtual #404                // Method android/util/SparseArray.valueAt:(I)Ljava/lang/Object;
     153: checkcast     #14                 // class android/support/v4/app/v$a
     156: astore        12
     158: iload         5
     160: ifeq          178
     163: aload_0
     164: iload         8
     166: aload         12
     168: aload         10
     170: aload         11
     172: invokestatic  #406                // Method a:(Landroid/support/v4/app/o;ILandroid/support/v4/app/v$a;Landroid/view/View;Landroid/support/v4/g/a;)V
     175: goto          190
     178: aload_0
     179: iload         8
     181: aload         12
     183: aload         10
     185: aload         11
     187: invokestatic  #408                // Method b:(Landroid/support/v4/app/o;ILandroid/support/v4/app/v$a;Landroid/view/View;Landroid/support/v4/g/a;)V
     190: iload         6
     192: iconst_1
     193: iadd
     194: istore        6
     196: goto          118
     199: return

  static void a(java.util.ArrayList, int);
    Code:
       0: aload_0
       1: iload_1
       2: invokestatic  #354                // Method b:(Ljava/util/ArrayList;I)V
       5: return

  public static void b(android.support.v4.app.c, android.util.SparseArray<android.support.v4.app.v$a>, boolean);
    Code:
       0: aload_0
       1: getfield      #304                // Field android/support/v4/app/c.a:Landroid/support/v4/app/o;
       4: getfield      #334                // Field android/support/v4/app/o.n:Landroid/support/v4/app/k;
       7: invokevirtual #338                // Method android/support/v4/app/k.a:()Z
      10: ifne          14
      13: return
      14: aload_0
      15: getfield      #326                // Field android/support/v4/app/c.b:Ljava/util/ArrayList;
      18: invokevirtual #143                // Method java/util/ArrayList.size:()I
      21: iconst_1
      22: isub
      23: istore_3
      24: iload_3
      25: iflt          53
      28: aload_0
      29: aload_0
      30: getfield      #326                // Field android/support/v4/app/c.b:Ljava/util/ArrayList;
      33: iload_3
      34: invokevirtual #125                // Method java/util/ArrayList.get:(I)Ljava/lang/Object;
      37: checkcast     #266                // class android/support/v4/app/c$a
      40: aload_1
      41: iconst_1
      42: iload_2
      43: invokestatic  #328                // Method a:(Landroid/support/v4/app/c;Landroid/support/v4/app/c$a;Landroid/util/SparseArray;ZZ)V
      46: iload_3
      47: iconst_1
      48: isub
      49: istore_3
      50: goto          24
      53: return
}
