class android.support.v4.app.x$1 implements java.lang.Runnable {
  final int a;

  final java.util.ArrayList b;

  final java.util.ArrayList c;

  final java.util.ArrayList d;

  final java.util.ArrayList e;

  final android.support.v4.app.x f;

  android.support.v4.app.x$1(android.support.v4.app.x, int, java.util.ArrayList, java.util.ArrayList, java.util.ArrayList, java.util.ArrayList);
    Code:
       0: aload_0
       1: aload_1
       2: putfield      #23                 // Field f:Landroid/support/v4/app/x;
       5: aload_0
       6: iload_2
       7: putfield      #25                 // Field a:I
      10: aload_0
      11: aload_3
      12: putfield      #27                 // Field b:Ljava/util/ArrayList;
      15: aload_0
      16: aload         4
      18: putfield      #29                 // Field c:Ljava/util/ArrayList;
      21: aload_0
      22: aload         5
      24: putfield      #31                 // Field d:Ljava/util/ArrayList;
      27: aload_0
      28: aload         6
      30: putfield      #33                 // Field e:Ljava/util/ArrayList;
      33: aload_0
      34: invokespecial #36                 // Method java/lang/Object."<init>":()V
      37: return

  public void run();
    Code:
       0: iconst_0
       1: istore_1
       2: iload_1
       3: aload_0
       4: getfield      #25                 // Field a:I
       7: if_icmpge     67
      10: aload_0
      11: getfield      #27                 // Field b:Ljava/util/ArrayList;
      14: iload_1
      15: invokevirtual #44                 // Method java/util/ArrayList.get:(I)Ljava/lang/Object;
      18: checkcast     #46                 // class android/view/View
      21: aload_0
      22: getfield      #29                 // Field c:Ljava/util/ArrayList;
      25: iload_1
      26: invokevirtual #44                 // Method java/util/ArrayList.get:(I)Ljava/lang/Object;
      29: checkcast     #48                 // class java/lang/String
      32: invokestatic  #53                 // Method android/support/v4/view/s.a:(Landroid/view/View;Ljava/lang/String;)V
      35: aload_0
      36: getfield      #31                 // Field d:Ljava/util/ArrayList;
      39: iload_1
      40: invokevirtual #44                 // Method java/util/ArrayList.get:(I)Ljava/lang/Object;
      43: checkcast     #46                 // class android/view/View
      46: aload_0
      47: getfield      #33                 // Field e:Ljava/util/ArrayList;
      50: iload_1
      51: invokevirtual #44                 // Method java/util/ArrayList.get:(I)Ljava/lang/Object;
      54: checkcast     #48                 // class java/lang/String
      57: invokestatic  #53                 // Method android/support/v4/view/s.a:(Landroid/view/View;Ljava/lang/String;)V
      60: iload_1
      61: iconst_1
      62: iadd
      63: istore_1
      64: goto          2
      67: return
}
