public abstract class android.support.v4.app.x {
  public android.support.v4.app.x();
    Code:
       0: aload_0
       1: invokespecial #14                 // Method java/lang/Object."<init>":()V
       4: return

  static java.lang.String a(java.util.Map<java.lang.String, java.lang.String>, java.lang.String);
    Code:
       0: aload_0
       1: invokeinterface #23,  1           // InterfaceMethod java/util/Map.entrySet:()Ljava/util/Set;
       6: invokeinterface #29,  1           // InterfaceMethod java/util/Set.iterator:()Ljava/util/Iterator;
      11: astore_0
      12: aload_0
      13: invokeinterface #35,  1           // InterfaceMethod java/util/Iterator.hasNext:()Z
      18: ifeq          54
      21: aload_0
      22: invokeinterface #39,  1           // InterfaceMethod java/util/Iterator.next:()Ljava/lang/Object;
      27: checkcast     #41                 // class java/util/Map$Entry
      30: astore_2
      31: aload_1
      32: aload_2
      33: invokeinterface #44,  1           // InterfaceMethod java/util/Map$Entry.getValue:()Ljava/lang/Object;
      38: invokevirtual #50                 // Method java/lang/String.equals:(Ljava/lang/Object;)Z
      41: ifeq          12
      44: aload_2
      45: invokeinterface #53,  1           // InterfaceMethod java/util/Map$Entry.getKey:()Ljava/lang/Object;
      50: checkcast     #46                 // class java/lang/String
      53: areturn
      54: aconst_null
      55: areturn

  protected static void a(java.util.List<android.view.View>, android.view.View);
    Code:
       0: aload_0
       1: invokeinterface #62,  1           // InterfaceMethod java/util/List.size:()I
       6: istore        4
       8: aload_0
       9: aload_1
      10: iload         4
      12: invokestatic  #65                 // Method a:(Ljava/util/List;Landroid/view/View;I)Z
      15: ifeq          19
      18: return
      19: aload_0
      20: aload_1
      21: invokeinterface #68,  2           // InterfaceMethod java/util/List.add:(Ljava/lang/Object;)Z
      26: pop
      27: iload         4
      29: istore_2
      30: iload_2
      31: aload_0
      32: invokeinterface #62,  1           // InterfaceMethod java/util/List.size:()I
      37: if_icmpge     118
      40: aload_0
      41: iload_2
      42: invokeinterface #72,  2           // InterfaceMethod java/util/List.get:(I)Ljava/lang/Object;
      47: checkcast     #74                 // class android/view/View
      50: astore_1
      51: aload_1
      52: instanceof    #76                 // class android/view/ViewGroup
      55: ifeq          111
      58: aload_1
      59: checkcast     #76                 // class android/view/ViewGroup
      62: astore_1
      63: aload_1
      64: invokevirtual #79                 // Method android/view/ViewGroup.getChildCount:()I
      67: istore        5
      69: iconst_0
      70: istore_3
      71: iload_3
      72: iload         5
      74: if_icmpge     111
      77: aload_1
      78: iload_3
      79: invokevirtual #83                 // Method android/view/ViewGroup.getChildAt:(I)Landroid/view/View;
      82: astore        6
      84: aload_0
      85: aload         6
      87: iload         4
      89: invokestatic  #65                 // Method a:(Ljava/util/List;Landroid/view/View;I)Z
      92: ifne          104
      95: aload_0
      96: aload         6
      98: invokeinterface #68,  2           // InterfaceMethod java/util/List.add:(Ljava/lang/Object;)Z
     103: pop
     104: iload_3
     105: iconst_1
     106: iadd
     107: istore_3
     108: goto          71
     111: iload_2
     112: iconst_1
     113: iadd
     114: istore_2
     115: goto          30
     118: return

  protected static boolean a(java.util.List);
    Code:
       0: aload_0
       1: ifnull        18
       4: aload_0
       5: invokeinterface #88,  1           // InterfaceMethod java/util/List.isEmpty:()Z
      10: ifeq          16
      13: goto          18
      16: iconst_0
      17: ireturn
      18: iconst_1
      19: ireturn

  public abstract java.lang.Object a(java.lang.Object, java.lang.Object, java.lang.Object);

  java.util.ArrayList<java.lang.String> a(java.util.ArrayList<android.view.View>);
    Code:
       0: new           #93                 // class java/util/ArrayList
       3: dup
       4: invokespecial #94                 // Method java/util/ArrayList."<init>":()V
       7: astore        4
       9: aload_1
      10: invokevirtual #95                 // Method java/util/ArrayList.size:()I
      13: istore_3
      14: iconst_0
      15: istore_2
      16: iload_2
      17: iload_3
      18: if_icmpge     55
      21: aload_1
      22: iload_2
      23: invokevirtual #96                 // Method java/util/ArrayList.get:(I)Ljava/lang/Object;
      26: checkcast     #74                 // class android/view/View
      29: astore        5
      31: aload         4
      33: aload         5
      35: invokestatic  #102                // Method android/support/v4/view/s.m:(Landroid/view/View;)Ljava/lang/String;
      38: invokevirtual #103                // Method java/util/ArrayList.add:(Ljava/lang/Object;)Z
      41: pop
      42: aload         5
      44: aconst_null
      45: invokestatic  #106                // Method android/support/v4/view/s.a:(Landroid/view/View;Ljava/lang/String;)V
      48: iload_2
      49: iconst_1
      50: iadd
      51: istore_2
      52: goto          16
      55: aload         4
      57: areturn

  protected void a(android.view.View, android.graphics.Rect);
    Code:
       0: iconst_2
       1: newarray       int
       3: astore_3
       4: aload_1
       5: aload_3
       6: invokevirtual #112                // Method android/view/View.getLocationOnScreen:([I)V
       9: aload_2
      10: aload_3
      11: iconst_0
      12: iaload
      13: aload_3
      14: iconst_1
      15: iaload
      16: aload_3
      17: iconst_0
      18: iaload
      19: aload_1
      20: invokevirtual #115                // Method android/view/View.getWidth:()I
      23: iadd
      24: aload_3
      25: iconst_1
      26: iaload
      27: aload_1
      28: invokevirtual #118                // Method android/view/View.getHeight:()I
      31: iadd
      32: invokevirtual #124                // Method android/graphics/Rect.set:(IIII)V
      35: return

  void a(android.view.View, java.util.ArrayList<android.view.View>, java.util.ArrayList<android.view.View>, java.util.ArrayList<java.lang.String>, java.util.Map<java.lang.String, java.lang.String>);
    Code:
       0: aload_3
       1: invokevirtual #95                 // Method java/util/ArrayList.size:()I
       4: istore        8
       6: new           #93                 // class java/util/ArrayList
       9: dup
      10: invokespecial #94                 // Method java/util/ArrayList."<init>":()V
      13: astore        9
      15: iconst_0
      16: istore        6
      18: iload         6
      20: iload         8
      22: if_icmpge     139
      25: aload_2
      26: iload         6
      28: invokevirtual #96                 // Method java/util/ArrayList.get:(I)Ljava/lang/Object;
      31: checkcast     #74                 // class android/view/View
      34: astore        11
      36: aload         11
      38: invokestatic  #102                // Method android/support/v4/view/s.m:(Landroid/view/View;)Ljava/lang/String;
      41: astore        10
      43: aload         9
      45: aload         10
      47: invokevirtual #103                // Method java/util/ArrayList.add:(Ljava/lang/Object;)Z
      50: pop
      51: aload         10
      53: ifnonnull     59
      56: goto          130
      59: aload         11
      61: aconst_null
      62: invokestatic  #106                // Method android/support/v4/view/s.a:(Landroid/view/View;Ljava/lang/String;)V
      65: aload         5
      67: aload         10
      69: invokeinterface #128,  2          // InterfaceMethod java/util/Map.get:(Ljava/lang/Object;)Ljava/lang/Object;
      74: checkcast     #46                 // class java/lang/String
      77: astore        11
      79: iconst_0
      80: istore        7
      82: iload         7
      84: iload         8
      86: if_icmpge     130
      89: aload         11
      91: aload         4
      93: iload         7
      95: invokevirtual #96                 // Method java/util/ArrayList.get:(I)Ljava/lang/Object;
      98: invokevirtual #50                 // Method java/lang/String.equals:(Ljava/lang/Object;)Z
     101: ifeq          121
     104: aload_3
     105: iload         7
     107: invokevirtual #96                 // Method java/util/ArrayList.get:(I)Ljava/lang/Object;
     110: checkcast     #74                 // class android/view/View
     113: aload         10
     115: invokestatic  #106                // Method android/support/v4/view/s.a:(Landroid/view/View;Ljava/lang/String;)V
     118: goto          130
     121: iload         7
     123: iconst_1
     124: iadd
     125: istore        7
     127: goto          82
     130: iload         6
     132: iconst_1
     133: iadd
     134: istore        6
     136: goto          18
     139: aload_1
     140: new           #6                  // class android/support/v4/app/x$1
     143: dup
     144: aload_0
     145: iload         8
     147: aload_3
     148: aload         4
     150: aload_2
     151: aload         9
     153: invokespecial #131                // Method android/support/v4/app/x$1."<init>":(Landroid/support/v4/app/x;ILjava/util/ArrayList;Ljava/util/ArrayList;Ljava/util/ArrayList;Ljava/util/ArrayList;)V
     156: invokestatic  #136                // Method android/support/v4/app/af.a:(Landroid/view/View;Ljava/lang/Runnable;)Landroid/support/v4/app/af;
     159: pop
     160: return

  void a(android.view.View, java.util.ArrayList<android.view.View>, java.util.Map<java.lang.String, java.lang.String>);
    Code:
       0: aload_1
       1: new           #8                  // class android/support/v4/app/x$2
       4: dup
       5: aload_0
       6: aload_2
       7: aload_3
       8: invokespecial #141                // Method android/support/v4/app/x$2."<init>":(Landroid/support/v4/app/x;Ljava/util/ArrayList;Ljava/util/Map;)V
      11: invokestatic  #136                // Method android/support/v4/app/af.a:(Landroid/view/View;Ljava/lang/Runnable;)Landroid/support/v4/app/af;
      14: pop
      15: return

  public abstract void a(android.view.ViewGroup, java.lang.Object);

  void a(android.view.ViewGroup, java.util.ArrayList<android.view.View>, java.util.Map<java.lang.String, java.lang.String>);
    Code:
       0: aload_1
       1: new           #10                 // class android/support/v4/app/x$3
       4: dup
       5: aload_0
       6: aload_2
       7: aload_3
       8: invokespecial #145                // Method android/support/v4/app/x$3."<init>":(Landroid/support/v4/app/x;Ljava/util/ArrayList;Ljava/util/Map;)V
      11: invokestatic  #136                // Method android/support/v4/app/af.a:(Landroid/view/View;Ljava/lang/Runnable;)Landroid/support/v4/app/af;
      14: pop
      15: return

  public abstract void a(java.lang.Object, android.graphics.Rect);

  public abstract void a(java.lang.Object, android.view.View);

  public abstract void a(java.lang.Object, android.view.View, java.util.ArrayList<android.view.View>);

  public abstract void a(java.lang.Object, java.lang.Object, java.util.ArrayList<android.view.View>, java.lang.Object, java.util.ArrayList<android.view.View>, java.lang.Object, java.util.ArrayList<android.view.View>);

  public abstract void a(java.lang.Object, java.util.ArrayList<android.view.View>);

  public abstract void a(java.lang.Object, java.util.ArrayList<android.view.View>, java.util.ArrayList<android.view.View>);

  void a(java.util.ArrayList<android.view.View>, android.view.View);
    Code:
       0: aload_2
       1: invokevirtual #156                // Method android/view/View.getVisibility:()I
       4: ifne          74
       7: aload_2
       8: astore        5
      10: aload_2
      11: instanceof    #76                 // class android/view/ViewGroup
      14: ifeq          67
      17: aload_2
      18: checkcast     #76                 // class android/view/ViewGroup
      21: astore        5
      23: aload         5
      25: invokestatic  #161                // Method android/support/v4/view/u.a:(Landroid/view/ViewGroup;)Z
      28: ifeq          34
      31: goto          67
      34: aload         5
      36: invokevirtual #79                 // Method android/view/ViewGroup.getChildCount:()I
      39: istore        4
      41: iconst_0
      42: istore_3
      43: iload_3
      44: iload         4
      46: if_icmpge     74
      49: aload_0
      50: aload_1
      51: aload         5
      53: iload_3
      54: invokevirtual #83                 // Method android/view/ViewGroup.getChildAt:(I)Landroid/view/View;
      57: invokevirtual #163                // Method a:(Ljava/util/ArrayList;Landroid/view/View;)V
      60: iload_3
      61: iconst_1
      62: iadd
      63: istore_3
      64: goto          43
      67: aload_1
      68: aload         5
      70: invokevirtual #103                // Method java/util/ArrayList.add:(Ljava/lang/Object;)Z
      73: pop
      74: return

  void a(java.util.Map<java.lang.String, android.view.View>, android.view.View);
    Code:
       0: aload_2
       1: invokevirtual #156                // Method android/view/View.getVisibility:()I
       4: ifne          71
       7: aload_2
       8: invokestatic  #102                // Method android/support/v4/view/s.m:(Landroid/view/View;)Ljava/lang/String;
      11: astore        5
      13: aload         5
      15: ifnull        28
      18: aload_1
      19: aload         5
      21: aload_2
      22: invokeinterface #169,  3          // InterfaceMethod java/util/Map.put:(Ljava/lang/Object;Ljava/lang/Object;)Ljava/lang/Object;
      27: pop
      28: aload_2
      29: instanceof    #76                 // class android/view/ViewGroup
      32: ifeq          71
      35: aload_2
      36: checkcast     #76                 // class android/view/ViewGroup
      39: astore_2
      40: aload_2
      41: invokevirtual #79                 // Method android/view/ViewGroup.getChildCount:()I
      44: istore        4
      46: iconst_0
      47: istore_3
      48: iload_3
      49: iload         4
      51: if_icmpge     71
      54: aload_0
      55: aload_1
      56: aload_2
      57: iload_3
      58: invokevirtual #83                 // Method android/view/ViewGroup.getChildAt:(I)Landroid/view/View;
      61: invokevirtual #171                // Method a:(Ljava/util/Map;Landroid/view/View;)V
      64: iload_3
      65: iconst_1
      66: iadd
      67: istore_3
      68: goto          48
      71: return

  public abstract boolean a(java.lang.Object);

  public abstract java.lang.Object b(java.lang.Object);

  public abstract java.lang.Object b(java.lang.Object, java.lang.Object, java.lang.Object);

  public abstract void b(java.lang.Object, android.view.View);

  public abstract void b(java.lang.Object, android.view.View, java.util.ArrayList<android.view.View>);

  public abstract void b(java.lang.Object, java.util.ArrayList<android.view.View>, java.util.ArrayList<android.view.View>);

  public abstract java.lang.Object c(java.lang.Object);

  public abstract void c(java.lang.Object, android.view.View);
}
