public class ryey.easer.plugins.event.f.d extends ryey.easer.plugins.c<ryey.easer.plugins.event.f.a> {
  public ryey.easer.plugins.event.f.d();
    Code:
       0: aload_0
       1: invokespecial #13                 // Method ryey/easer/plugins/c."<init>":()V
       4: return

  public ryey.easer.commons.local_plugin.f a();
    Code:
       0: aload_0
       1: invokevirtual #18                 // Method b:()Lryey/easer/plugins/event/f/a;
       4: areturn

  protected void a(ryey.easer.plugins.event.f.a);
    Code:
       0: aload_0
       1: getfield      #21                 // Field a:Lryey/easer/commons/a/a;
       4: aload_1
       5: getfield      #26                 // Field ryey/easer/plugins/event/f/a.a:Ljava/lang/String;
       8: invokevirtual #31                 // Method ryey/easer/commons/a/a.a:(Ljava/lang/String;)V
      11: aload_1
      12: getfield      #34                 // Field ryey/easer/plugins/event/f/a.b:Lryey/easer/plugins/event/f/a$a;
      15: getstatic     #38                 // Field ryey/easer/plugins/event/f/a$a.a:Lryey/easer/plugins/event/f/a$a;
      18: if_acmpne     35
      21: aload_0
      22: getfield      #40                 // Field b:Landroid/widget/RadioGroup;
      25: astore_1
      26: ldc           #41                 // int 2131296570
      28: istore_2
      29: aload_1
      30: iload_2
      31: invokevirtual #47                 // Method android/widget/RadioGroup.check:(I)V
      34: return
      35: aload_0
      36: getfield      #40                 // Field b:Landroid/widget/RadioGroup;
      39: astore_1
      40: ldc           #48                 // int 2131296571
      42: istore_2
      43: goto          29

  public ryey.easer.plugins.event.f.a b();
    Code:
       0: aload_0
       1: getfield      #21                 // Field a:Lryey/easer/commons/a/a;
       4: invokevirtual #52                 // Method ryey/easer/commons/a/a.c:()Ljava/lang/String;
       7: astore_2
       8: aload_0
       9: getfield      #40                 // Field b:Landroid/widget/RadioGroup;
      12: invokevirtual #56                 // Method android/widget/RadioGroup.getCheckedRadioButtonId:()I
      15: ldc           #41                 // int 2131296570
      17: if_icmpne     27
      20: getstatic     #38                 // Field ryey/easer/plugins/event/f/a$a.a:Lryey/easer/plugins/event/f/a$a;
      23: astore_1
      24: goto          31
      27: getstatic     #57                 // Field ryey/easer/plugins/event/f/a$a.b:Lryey/easer/plugins/event/f/a$a;
      30: astore_1
      31: new           #23                 // class ryey/easer/plugins/event/f/a
      34: dup
      35: aload_2
      36: aload_1
      37: invokespecial #60                 // Method ryey/easer/plugins/event/f/a."<init>":(Ljava/lang/String;Lryey/easer/plugins/event/f/a$a;)V
      40: areturn

  protected void b(ryey.easer.commons.local_plugin.f);
    Code:
       0: aload_0
       1: aload_1
       2: checkcast     #23                 // class ryey/easer/plugins/event/f/a
       5: invokevirtual #63                 // Method a:(Lryey/easer/plugins/event/f/a;)V
       8: return

  public android.view.View onCreateView(android.view.LayoutInflater, android.view.ViewGroup, android.os.Bundle);
    Code:
       0: aload_1
       1: ldc           #66                 // int 2131427434
       3: aload_2
       4: iconst_0
       5: invokevirtual #72                 // Method android/view/LayoutInflater.inflate:(ILandroid/view/ViewGroup;Z)Landroid/view/View;
       8: astore_1
       9: aload_0
      10: new           #28                 // class ryey/easer/commons/a/a
      13: dup
      14: aload_0
      15: invokevirtual #76                 // Method getContext:()Landroid/content/Context;
      18: aload_1
      19: ldc           #77                 // int 2131296624
      21: invokevirtual #83                 // Method android/view/View.findViewById:(I)Landroid/view/View;
      24: checkcast     #85                 // class android/widget/Spinner
      27: invokespecial #88                 // Method ryey/easer/commons/a/a."<init>":(Landroid/content/Context;Landroid/widget/Spinner;)V
      30: putfield      #21                 // Field a:Lryey/easer/commons/a/a;
      33: aload_0
      34: getfield      #21                 // Field a:Lryey/easer/commons/a/a;
      37: invokevirtual #91                 // Method ryey/easer/commons/a/a.a:()Lryey/easer/commons/a/a;
      40: iconst_0
      41: invokevirtual #94                 // Method ryey/easer/commons/a/a.a:(Z)Lryey/easer/commons/a/a;
      44: new           #96                 // class ryey/easer/core/a/a/b
      47: dup
      48: aload_0
      49: invokevirtual #76                 // Method getContext:()Landroid/content/Context;
      52: invokespecial #99                 // Method ryey/easer/core/a/a/b."<init>":(Landroid/content/Context;)V
      55: invokevirtual #102                // Method ryey/easer/core/a/a/b.a:()Ljava/util/List;
      58: invokevirtual #105                // Method ryey/easer/commons/a/a.a:(Ljava/util/List;)Lryey/easer/commons/a/a;
      61: invokevirtual #107                // Method ryey/easer/commons/a/a.b:()V
      64: aload_0
      65: aload_1
      66: ldc           #108                // int 2131296579
      68: invokevirtual #83                 // Method android/view/View.findViewById:(I)Landroid/view/View;
      71: checkcast     #43                 // class android/widget/RadioGroup
      74: putfield      #40                 // Field b:Landroid/widget/RadioGroup;
      77: aload_1
      78: areturn
}
