public class ryey.easer.plugins.event.m.d extends ryey.easer.plugins.c<ryey.easer.plugins.event.m.a> {
  public ryey.easer.plugins.event.m.d();
    Code:
       0: aload_0
       1: invokespecial #18                 // Method ryey/easer/plugins/c."<init>":()V
       4: return

  static android.widget.EditText a(ryey.easer.plugins.event.m.d);
    Code:
       0: aload_0
       1: getfield      #22                 // Field d:Landroid/widget/EditText;
       4: areturn

  public ryey.easer.commons.local_plugin.f a();
    Code:
       0: aload_0
       1: invokevirtual #26                 // Method b:()Lryey/easer/plugins/event/m/a;
       4: areturn

  protected void a(ryey.easer.plugins.event.m.a);
    Code:
       0: aload_0
       1: getfield      #29                 // Field a:Landroid/widget/EditText;
       4: aload_1
       5: getfield      #34                 // Field ryey/easer/plugins/event/m/a.a:Ljava/lang/String;
       8: invokevirtual #40                 // Method android/widget/EditText.setText:(Ljava/lang/CharSequence;)V
      11: aload_0
      12: getfield      #42                 // Field b:Landroid/widget/EditText;
      15: aload_1
      16: getfield      #45                 // Field ryey/easer/plugins/event/m/a.b:I
      19: invokestatic  #51                 // Method java/lang/String.valueOf:(I)Ljava/lang/String;
      22: invokevirtual #40                 // Method android/widget/EditText.setText:(Ljava/lang/CharSequence;)V
      25: aload_0
      26: getfield      #53                 // Field c:Landroid/widget/EditText;
      29: aload_1
      30: getfield      #55                 // Field ryey/easer/plugins/event/m/a.c:Ljava/lang/String;
      33: invokevirtual #40                 // Method android/widget/EditText.setText:(Ljava/lang/CharSequence;)V
      36: aload_0
      37: getfield      #57                 // Field e:Landroid/widget/CompoundButton;
      40: aload_1
      41: getfield      #60                 // Field ryey/easer/plugins/event/m/a.d:Z
      44: invokevirtual #66                 // Method android/widget/CompoundButton.setChecked:(Z)V
      47: aload_1
      48: getfield      #60                 // Field ryey/easer/plugins/event/m/a.d:Z
      51: ifeq          65
      54: aload_0
      55: getfield      #22                 // Field d:Landroid/widget/EditText;
      58: aload_1
      59: getfield      #68                 // Field ryey/easer/plugins/event/m/a.e:Ljava/lang/String;
      62: invokevirtual #40                 // Method android/widget/EditText.setText:(Ljava/lang/CharSequence;)V
      65: return

  public ryey.easer.plugins.event.m.a b();
    Code:
       0: aload_0
       1: getfield      #29                 // Field a:Landroid/widget/EditText;
       4: invokevirtual #72                 // Method android/widget/EditText.getText:()Landroid/text/Editable;
       7: invokevirtual #78                 // Method java/lang/Object.toString:()Ljava/lang/String;
      10: astore        4
      12: aload_0
      13: getfield      #42                 // Field b:Landroid/widget/EditText;
      16: invokevirtual #72                 // Method android/widget/EditText.getText:()Landroid/text/Editable;
      19: invokevirtual #78                 // Method java/lang/Object.toString:()Ljava/lang/String;
      22: invokestatic  #84                 // Method java/lang/Integer.parseInt:(Ljava/lang/String;)I
      25: istore_1
      26: aload_0
      27: getfield      #53                 // Field c:Landroid/widget/EditText;
      30: invokevirtual #72                 // Method android/widget/EditText.getText:()Landroid/text/Editable;
      33: invokevirtual #78                 // Method java/lang/Object.toString:()Ljava/lang/String;
      36: astore        5
      38: aload_0
      39: getfield      #57                 // Field e:Landroid/widget/CompoundButton;
      42: invokevirtual #88                 // Method android/widget/CompoundButton.isChecked:()Z
      45: istore_2
      46: iload_2
      47: ifeq          64
      50: aload_0
      51: getfield      #22                 // Field d:Landroid/widget/EditText;
      54: invokevirtual #72                 // Method android/widget/EditText.getText:()Landroid/text/Editable;
      57: invokevirtual #78                 // Method java/lang/Object.toString:()Ljava/lang/String;
      60: astore_3
      61: goto          69
      64: aconst_null
      65: astore_3
      66: goto          61
      69: new           #31                 // class ryey/easer/plugins/event/m/a
      72: dup
      73: aload         4
      75: iload_1
      76: aload         5
      78: iload_2
      79: aload_3
      80: invokespecial #91                 // Method ryey/easer/plugins/event/m/a."<init>":(Ljava/lang/String;ILjava/lang/String;ZLjava/lang/String;)V
      83: areturn

  protected void b(ryey.easer.commons.local_plugin.f);
    Code:
       0: aload_0
       1: aload_1
       2: checkcast     #31                 // class ryey/easer/plugins/event/m/a
       5: invokevirtual #94                 // Method a:(Lryey/easer/plugins/event/m/a;)V
       8: return

  public android.view.View onCreateView(android.view.LayoutInflater, android.view.ViewGroup, android.os.Bundle);
    Code:
       0: aload_1
       1: ldc           #97                 // int 2131427441
       3: aload_2
       4: iconst_0
       5: invokevirtual #103                // Method android/view/LayoutInflater.inflate:(ILandroid/view/ViewGroup;Z)Landroid/view/View;
       8: astore_1
       9: aload_0
      10: aload_1
      11: ldc           #104                // int 2131296391
      13: invokevirtual #110                // Method android/view/View.findViewById:(I)Landroid/view/View;
      16: checkcast     #36                 // class android/widget/EditText
      19: putfield      #29                 // Field a:Landroid/widget/EditText;
      22: aload_0
      23: aload_1
      24: ldc           #111                // int 2131296392
      26: invokevirtual #110                // Method android/view/View.findViewById:(I)Landroid/view/View;
      29: checkcast     #36                 // class android/widget/EditText
      32: putfield      #42                 // Field b:Landroid/widget/EditText;
      35: aload_0
      36: aload_1
      37: ldc           #112                // int 2131296397
      39: invokevirtual #110                // Method android/view/View.findViewById:(I)Landroid/view/View;
      42: checkcast     #36                 // class android/widget/EditText
      45: putfield      #53                 // Field c:Landroid/widget/EditText;
      48: aload_0
      49: aload_1
      50: ldc           #113                // int 2131296334
      52: invokevirtual #110                // Method android/view/View.findViewById:(I)Landroid/view/View;
      55: checkcast     #62                 // class android/widget/CompoundButton
      58: putfield      #57                 // Field e:Landroid/widget/CompoundButton;
      61: aload_0
      62: aload_1
      63: ldc           #114                // int 2131296394
      65: invokevirtual #110                // Method android/view/View.findViewById:(I)Landroid/view/View;
      68: checkcast     #36                 // class android/widget/EditText
      71: putfield      #22                 // Field d:Landroid/widget/EditText;
      74: aload_0
      75: getfield      #57                 // Field e:Landroid/widget/CompoundButton;
      78: new           #7                  // class ryey/easer/plugins/event/m/d$1
      81: dup
      82: aload_0
      83: invokespecial #117                // Method ryey/easer/plugins/event/m/d$1."<init>":(Lryey/easer/plugins/event/m/d;)V
      86: invokevirtual #121                // Method android/widget/CompoundButton.setOnCheckedChangeListener:(Landroid/widget/CompoundButton$OnCheckedChangeListener;)V
      89: aload_0
      90: getfield      #57                 // Field e:Landroid/widget/CompoundButton;
      93: iconst_1
      94: invokevirtual #66                 // Method android/widget/CompoundButton.setChecked:(Z)V
      97: aload_0
      98: getfield      #57                 // Field e:Landroid/widget/CompoundButton;
     101: iconst_0
     102: invokevirtual #66                 // Method android/widget/CompoundButton.setChecked:(Z)V
     105: aload_1
     106: areturn
}
