class ryey.easer.plugins.event.m.e$a extends java.lang.Thread {
  final java.net.Socket a;

  final ryey.easer.plugins.event.m.e b;

  ryey.easer.plugins.event.m.e$a(ryey.easer.plugins.event.m.e, java.net.Socket);
    Code:
       0: aload_0
       1: aload_1
       2: putfield      #14                 // Field b:Lryey/easer/plugins/event/m/e;
       5: aload_0
       6: invokespecial #17                 // Method java/lang/Thread."<init>":()V
       9: aload_0
      10: aload_2
      11: putfield      #19                 // Field a:Ljava/net/Socket;
      14: return

  public void run();
    Code:
       0: aload_0
       1: getfield      #14                 // Field b:Lryey/easer/plugins/event/m/e;
       4: invokestatic  #28                 // Method ryey/easer/plugins/event/m/e.a:(Lryey/easer/plugins/event/m/e;)Lryey/easer/commons/local_plugin/eventplugin/EventData;
       7: checkcast     #30                 // class ryey/easer/plugins/event/m/a
      10: getfield      #34                 // Field ryey/easer/plugins/event/m/a.d:Z
      13: ifne          25
      16: aload_0
      17: getfield      #14                 // Field b:Lryey/easer/plugins/event/m/e;
      20: iconst_1
      21: invokestatic  #37                 // Method ryey/easer/plugins/event/m/e.a:(Lryey/easer/plugins/event/m/e;Z)V
      24: return
      25: ldc           #39                 // String waiting for TCP response
      27: iconst_0
      28: anewarray     #41                 // class java/lang/Object
      31: invokestatic  #46                 // Method com/b/a/i.d:(Ljava/lang/String;[Ljava/lang/Object;)V
      34: new           #48                 // class java/io/BufferedReader
      37: dup
      38: new           #50                 // class java/io/InputStreamReader
      41: dup
      42: aload_0
      43: getfield      #19                 // Field a:Ljava/net/Socket;
      46: invokevirtual #56                 // Method java/net/Socket.getInputStream:()Ljava/io/InputStream;
      49: invokespecial #59                 // Method java/io/InputStreamReader."<init>":(Ljava/io/InputStream;)V
      52: invokespecial #62                 // Method java/io/BufferedReader."<init>":(Ljava/io/Reader;)V
      55: astore        5
      57: ldc           #64                 // String Reader for TCP response got
      59: iconst_0
      60: anewarray     #41                 // class java/lang/Object
      63: invokestatic  #46                 // Method com/b/a/i.d:(Ljava/lang/String;[Ljava/lang/Object;)V
      66: iconst_0
      67: istore_1
      68: iconst_0
      69: istore_2
      70: ldc           #66                 // String closed? %s :: inputShutdown? %s
      72: iconst_2
      73: anewarray     #41                 // class java/lang/Object
      76: dup
      77: iconst_0
      78: aload_0
      79: getfield      #19                 // Field a:Ljava/net/Socket;
      82: invokevirtual #70                 // Method java/net/Socket.isClosed:()Z
      85: invokestatic  #76                 // Method java/lang/Boolean.valueOf:(Z)Ljava/lang/Boolean;
      88: aastore
      89: dup
      90: iconst_1
      91: aload_0
      92: getfield      #19                 // Field a:Ljava/net/Socket;
      95: invokevirtual #79                 // Method java/net/Socket.isInputShutdown:()Z
      98: invokestatic  #76                 // Method java/lang/Boolean.valueOf:(Z)Ljava/lang/Boolean;
     101: aastore
     102: invokestatic  #46                 // Method com/b/a/i.d:(Ljava/lang/String;[Ljava/lang/Object;)V
     105: aload         5
     107: invokevirtual #82                 // Method java/io/BufferedReader.ready:()Z
     110: ifeq          286
     113: aload         5
     115: invokevirtual #86                 // Method java/io/BufferedReader.readLine:()Ljava/lang/String;
     118: astore        6
     120: ldc           #88                 // String got message <%s>
     122: iconst_1
     123: anewarray     #41                 // class java/lang/Object
     126: dup
     127: iconst_0
     128: aload         6
     130: aastore
     131: invokestatic  #46                 // Method com/b/a/i.d:(Ljava/lang/String;[Ljava/lang/Object;)V
     134: aload         6
     136: aload_0
     137: getfield      #14                 // Field b:Lryey/easer/plugins/event/m/e;
     140: invokestatic  #91                 // Method ryey/easer/plugins/event/m/e.c:(Lryey/easer/plugins/event/m/e;)Lryey/easer/commons/local_plugin/eventplugin/EventData;
     143: checkcast     #30                 // class ryey/easer/plugins/event/m/a
     146: getfield      #95                 // Field ryey/easer/plugins/event/m/a.e:Ljava/lang/String;
     149: iload_1
     150: aload         6
     152: invokevirtual #101                // Method java/lang/String.length:()I
     155: iload_1
     156: iadd
     157: invokevirtual #105                // Method java/lang/String.substring:(II)Ljava/lang/String;
     160: invokevirtual #109                // Method java/lang/String.equals:(Ljava/lang/Object;)Z
     163: ifne          193
     166: ldc           #111                // String message is NOT correct on line %d
     168: iconst_1
     169: anewarray     #41                 // class java/lang/Object
     172: dup
     173: iconst_0
     174: iload_2
     175: invokestatic  #116                // Method java/lang/Integer.valueOf:(I)Ljava/lang/Integer;
     178: aastore
     179: invokestatic  #118                // Method com/b/a/i.a:(Ljava/lang/String;[Ljava/lang/Object;)V
     182: aload_0
     183: getfield      #14                 // Field b:Lryey/easer/plugins/event/m/e;
     186: iconst_0
     187: invokestatic  #120                // Method ryey/easer/plugins/event/m/e.c:(Lryey/easer/plugins/event/m/e;Z)V
     190: goto          322
     193: iload_2
     194: iconst_1
     195: iadd
     196: istore        4
     198: iload_1
     199: istore_3
     200: ldc           #122                // String message is correct on line %d
     202: iconst_1
     203: anewarray     #41                 // class java/lang/Object
     206: dup
     207: iconst_0
     208: iload_2
     209: invokestatic  #116                // Method java/lang/Integer.valueOf:(I)Ljava/lang/Integer;
     212: aastore
     213: invokestatic  #118                // Method com/b/a/i.a:(Ljava/lang/String;[Ljava/lang/Object;)V
     216: iload_1
     217: istore_3
     218: iload_1
     219: aload         6
     221: invokevirtual #101                // Method java/lang/String.length:()I
     224: iadd
     225: istore_1
     226: iload_1
     227: istore_3
     228: iload_1
     229: aload_0
     230: getfield      #14                 // Field b:Lryey/easer/plugins/event/m/e;
     233: invokestatic  #124                // Method ryey/easer/plugins/event/m/e.d:(Lryey/easer/plugins/event/m/e;)Lryey/easer/commons/local_plugin/eventplugin/EventData;
     236: checkcast     #30                 // class ryey/easer/plugins/event/m/a
     239: getfield      #95                 // Field ryey/easer/plugins/event/m/a.e:Ljava/lang/String;
     242: invokevirtual #101                // Method java/lang/String.length:()I
     245: if_icmpne     272
     248: iload_1
     249: istore_3
     250: ldc           #126                // String got whole match for response
     252: iconst_0
     253: anewarray     #41                 // class java/lang/Object
     256: invokestatic  #128                // Method com/b/a/i.c:(Ljava/lang/String;[Ljava/lang/Object;)V
     259: iload_1
     260: istore_3
     261: aload_0
     262: getfield      #14                 // Field b:Lryey/easer/plugins/event/m/e;
     265: iconst_1
     266: invokestatic  #130                // Method ryey/easer/plugins/event/m/e.d:(Lryey/easer/plugins/event/m/e;Z)V
     269: goto          322
     272: iload         4
     274: istore_2
     275: goto          312
     278: iload         4
     280: istore_2
     281: iload_3
     282: istore_1
     283: goto          295
     286: ldc2_w        #131                // long 2000l
     289: invokestatic  #136                // Method sleep:(J)V
     292: goto          312
     295: ldc           #138                // String Socket unexpectedly closed while waiting for (more) response
     297: iconst_0
     298: anewarray     #41                 // class java/lang/Object
     301: invokestatic  #128                // Method com/b/a/i.c:(Ljava/lang/String;[Ljava/lang/Object;)V
     304: aload_0
     305: getfield      #14                 // Field b:Lryey/easer/plugins/event/m/e;
     308: iconst_0
     309: invokestatic  #140                // Method ryey/easer/plugins/event/m/e.e:(Lryey/easer/plugins/event/m/e;Z)V
     312: aload_0
     313: getfield      #19                 // Field a:Ljava/net/Socket;
     316: invokevirtual #70                 // Method java/net/Socket.isClosed:()Z
     319: ifeq          70
     322: aload_0
     323: getfield      #19                 // Field a:Ljava/net/Socket;
     326: invokevirtual #143                // Method java/net/Socket.close:()V
     329: ldc           #145                // String Done listening for reply
     331: iconst_0
     332: anewarray     #41                 // class java/lang/Object
     335: invokestatic  #46                 // Method com/b/a/i.d:(Ljava/lang/String;[Ljava/lang/Object;)V
     338: return
     339: ldc           #147                // String no valid InputStream
     341: iconst_0
     342: anewarray     #41                 // class java/lang/Object
     345: invokestatic  #46                 // Method com/b/a/i.d:(Ljava/lang/String;[Ljava/lang/Object;)V
     348: aload_0
     349: getfield      #14                 // Field b:Lryey/easer/plugins/event/m/e;
     352: invokestatic  #149                // Method ryey/easer/plugins/event/m/e.b:(Lryey/easer/plugins/event/m/e;)Lryey/easer/commons/local_plugin/eventplugin/EventData;
     355: checkcast     #30                 // class ryey/easer/plugins/event/m/a
     358: getfield      #34                 // Field ryey/easer/plugins/event/m/a.d:Z
     361: ifeq          372
     364: aload_0
     365: getfield      #14                 // Field b:Lryey/easer/plugins/event/m/e;
     368: iconst_0
     369: invokestatic  #151                // Method ryey/easer/plugins/event/m/e.b:(Lryey/easer/plugins/event/m/e;Z)V
     372: return
     373: astore        5
     375: goto          339
     378: astore        6
     380: goto          295
     383: astore        5
     385: goto          322
     388: astore        6
     390: goto          278
     393: astore        5
     395: goto          329
    Exception table:
       from    to  target type
          34    66   373   Class java/io/IOException
         105   190   378   Class java/io/IOException
         105   190   383   Class java/lang/InterruptedException
         200   216   388   Class java/io/IOException
         200   216   383   Class java/lang/InterruptedException
         218   226   388   Class java/io/IOException
         218   226   383   Class java/lang/InterruptedException
         228   248   388   Class java/io/IOException
         228   248   383   Class java/lang/InterruptedException
         250   259   388   Class java/io/IOException
         250   259   383   Class java/lang/InterruptedException
         261   269   388   Class java/io/IOException
         261   269   383   Class java/lang/InterruptedException
         286   292   378   Class java/io/IOException
         286   292   383   Class java/lang/InterruptedException
         322   329   393   Class java/io/IOException
}
