public class ryey.easer.plugins.event.m.e extends ryey.easer.plugins.event.b<ryey.easer.plugins.event.m.a> {
  ryey.easer.plugins.event.m.e(android.content.Context, ryey.easer.plugins.event.m.a);
    Code:
       0: aload_0
       1: aload_1
       2: aload_2
       3: iconst_1
       4: iconst_0
       5: invokespecial #15                 // Method "<init>":(Landroid/content/Context;Lryey/easer/plugins/event/m/a;ZZ)V
       8: return

  ryey.easer.plugins.event.m.e(android.content.Context, ryey.easer.plugins.event.m.a, boolean, boolean);
    Code:
       0: aload_0
       1: aload_1
       2: aload_2
       3: iload_3
       4: iload         4
       6: invokespecial #19                 // Method ryey/easer/plugins/event/b."<init>":(Landroid/content/Context;Lryey/easer/commons/local_plugin/eventplugin/EventData;ZZ)V
       9: return

  static ryey.easer.commons.local_plugin.eventplugin.EventData a(ryey.easer.plugins.event.m.e);
    Code:
       0: aload_0
       1: getfield      #24                 // Field b:Lryey/easer/commons/local_plugin/eventplugin/EventData;
       4: areturn

  static void a(ryey.easer.plugins.event.m.e, boolean);
    Code:
       0: aload_0
       1: iload_1
       2: invokevirtual #28                 // Method a:(Z)V
       5: return

  static ryey.easer.commons.local_plugin.eventplugin.EventData b(ryey.easer.plugins.event.m.e);
    Code:
       0: aload_0
       1: getfield      #24                 // Field b:Lryey/easer/commons/local_plugin/eventplugin/EventData;
       4: areturn

  static void b(ryey.easer.plugins.event.m.e, boolean);
    Code:
       0: aload_0
       1: iload_1
       2: invokevirtual #28                 // Method a:(Z)V
       5: return

  static ryey.easer.commons.local_plugin.eventplugin.EventData c(ryey.easer.plugins.event.m.e);
    Code:
       0: aload_0
       1: getfield      #24                 // Field b:Lryey/easer/commons/local_plugin/eventplugin/EventData;
       4: areturn

  static void c(ryey.easer.plugins.event.m.e, boolean);
    Code:
       0: aload_0
       1: iload_1
       2: invokevirtual #28                 // Method a:(Z)V
       5: return

  static ryey.easer.commons.local_plugin.eventplugin.EventData d(ryey.easer.plugins.event.m.e);
    Code:
       0: aload_0
       1: getfield      #24                 // Field b:Lryey/easer/commons/local_plugin/eventplugin/EventData;
       4: areturn

  static void d(ryey.easer.plugins.event.m.e, boolean);
    Code:
       0: aload_0
       1: iload_1
       2: invokevirtual #28                 // Method a:(Z)V
       5: return

  static void e(ryey.easer.plugins.event.m.e, boolean);
    Code:
       0: aload_0
       1: iload_1
       2: invokevirtual #28                 // Method a:(Z)V
       5: return

  public void a();
    Code:
       0: ldc           #38                 // String sending TCP packet
       2: iconst_0
       3: anewarray     #40                 // class java/lang/Object
       6: invokestatic  #45                 // Method com/b/a/i.d:(Ljava/lang/String;[Ljava/lang/Object;)V
       9: new           #47                 // class java/net/Socket
      12: dup
      13: aload_0
      14: getfield      #24                 // Field b:Lryey/easer/commons/local_plugin/eventplugin/EventData;
      17: checkcast     #49                 // class ryey/easer/plugins/event/m/a
      20: getfield      #52                 // Field ryey/easer/plugins/event/m/a.a:Ljava/lang/String;
      23: invokestatic  #58                 // Method java/net/InetAddress.getByName:(Ljava/lang/String;)Ljava/net/InetAddress;
      26: aload_0
      27: getfield      #24                 // Field b:Lryey/easer/commons/local_plugin/eventplugin/EventData;
      30: checkcast     #49                 // class ryey/easer/plugins/event/m/a
      33: getfield      #61                 // Field ryey/easer/plugins/event/m/a.b:I
      36: invokespecial #64                 // Method java/net/Socket."<init>":(Ljava/net/InetAddress;I)V
      39: astore_1
      40: aload_0
      41: getfield      #24                 // Field b:Lryey/easer/commons/local_plugin/eventplugin/EventData;
      44: checkcast     #49                 // class ryey/easer/plugins/event/m/a
      47: getfield      #66                 // Field ryey/easer/plugins/event/m/a.c:Ljava/lang/String;
      50: invokestatic  #71                 // Method ryey/easer/b.a:(Ljava/lang/String;)Z
      53: ifne          80
      56: new           #73                 // class java/io/DataOutputStream
      59: dup
      60: aload_1
      61: invokevirtual #77                 // Method java/net/Socket.getOutputStream:()Ljava/io/OutputStream;
      64: invokespecial #80                 // Method java/io/DataOutputStream."<init>":(Ljava/io/OutputStream;)V
      67: aload_0
      68: getfield      #24                 // Field b:Lryey/easer/commons/local_plugin/eventplugin/EventData;
      71: checkcast     #49                 // class ryey/easer/plugins/event/m/a
      74: getfield      #66                 // Field ryey/easer/plugins/event/m/a.c:Ljava/lang/String;
      77: invokevirtual #84                 // Method java/io/DataOutputStream.writeBytes:(Ljava/lang/String;)V
      80: aload_1
      81: invokevirtual #87                 // Method java/net/Socket.shutdownOutput:()V
      84: ldc           #89                 // String TCP packet sent and has told output to close
      86: iconst_0
      87: anewarray     #40                 // class java/lang/Object
      90: invokestatic  #45                 // Method com/b/a/i.d:(Ljava/lang/String;[Ljava/lang/Object;)V
      93: aload_0
      94: new           #7                  // class ryey/easer/plugins/event/m/e$a
      97: dup
      98: aload_0
      99: aload_1
     100: invokespecial #92                 // Method ryey/easer/plugins/event/m/e$a."<init>":(Lryey/easer/plugins/event/m/e;Ljava/net/Socket;)V
     103: putfield      #94                 // Field g:Ljava/lang/Thread;
     106: aload_0
     107: getfield      #94                 // Field g:Ljava/lang/Thread;
     110: invokevirtual #99                 // Method java/lang/Thread.start:()V
     113: return
     114: astore_1
     115: aload_1
     116: invokestatic  #104                // Method com/google/a/a/a/a/a/a.a:(Ljava/lang/Throwable;)V
     119: return
    Exception table:
       from    to  target type
           0    80   114   Class java/net/UnknownHostException
           0    80   114   Class java/io/IOException
          80   113   114   Class java/net/UnknownHostException
          80   113   114   Class java/io/IOException

  public void b();
    Code:
       0: aload_0
       1: getfield      #94                 // Field g:Ljava/lang/Thread;
       4: ifnull        14
       7: aload_0
       8: getfield      #94                 // Field g:Ljava/lang/Thread;
      11: invokevirtual #107                // Method java/lang/Thread.interrupt:()V
      14: return
}
