public class com.b.a.b implements com.b.a.e {
  static {};
    Code:
       0: ldc           #23                 // String line.separator
       2: invokestatic  #29                 // Method java/lang/System.getProperty:(Ljava/lang/String;)Ljava/lang/String;
       5: putstatic     #31                 // Field a:Ljava/lang/String;
       8: return

  com.b.a.b(com.b.a.b$a, com.b.a.b$1);
    Code:
       0: aload_0
       1: aload_1
       2: invokespecial #55                 // Method "<init>":(Lcom/b/a/b$a;)V
       5: return

  public static com.b.a.b$a a();
    Code:
       0: new           #10                 // class com/b/a/b$a
       3: dup
       4: aconst_null
       5: invokespecial #59                 // Method com/b/a/b$a."<init>":(Lcom/b/a/b$1;)V
       8: areturn

  public void a(int, java.lang.String, java.lang.String);
    Code:
       0: aload_0
       1: aload_2
       2: invokespecial #83                 // Method a:(Ljava/lang/String;)Ljava/lang/String;
       5: astore        4
       7: aload_0
       8: getfield      #40                 // Field b:Ljava/util/Date;
      11: invokestatic  #87                 // Method java/lang/System.currentTimeMillis:()J
      14: invokevirtual #93                 // Method java/util/Date.setTime:(J)V
      17: new           #69                 // class java/lang/StringBuilder
      20: dup
      21: invokespecial #70                 // Method java/lang/StringBuilder."<init>":()V
      24: astore        5
      26: aload         5
      28: aload_0
      29: getfield      #40                 // Field b:Ljava/util/Date;
      32: invokevirtual #96                 // Method java/util/Date.getTime:()J
      35: invokestatic  #101                // Method java/lang/Long.toString:(J)Ljava/lang/String;
      38: invokevirtual #74                 // Method java/lang/StringBuilder.append:(Ljava/lang/String;)Ljava/lang/StringBuilder;
      41: pop
      42: aload         5
      44: ldc           #103                // String ,
      46: invokevirtual #74                 // Method java/lang/StringBuilder.append:(Ljava/lang/String;)Ljava/lang/StringBuilder;
      49: pop
      50: aload         5
      52: aload_0
      53: getfield      #44                 // Field c:Ljava/text/SimpleDateFormat;
      56: aload_0
      57: getfield      #40                 // Field b:Ljava/util/Date;
      60: invokevirtual #109                // Method java/text/SimpleDateFormat.format:(Ljava/util/Date;)Ljava/lang/String;
      63: invokevirtual #74                 // Method java/lang/StringBuilder.append:(Ljava/lang/String;)Ljava/lang/StringBuilder;
      66: pop
      67: aload         5
      69: ldc           #103                // String ,
      71: invokevirtual #74                 // Method java/lang/StringBuilder.append:(Ljava/lang/String;)Ljava/lang/StringBuilder;
      74: pop
      75: aload         5
      77: iload_1
      78: invokestatic  #112                // Method com/b/a/m.a:(I)Ljava/lang/String;
      81: invokevirtual #74                 // Method java/lang/StringBuilder.append:(Ljava/lang/String;)Ljava/lang/StringBuilder;
      84: pop
      85: aload         5
      87: ldc           #103                // String ,
      89: invokevirtual #74                 // Method java/lang/StringBuilder.append:(Ljava/lang/String;)Ljava/lang/StringBuilder;
      92: pop
      93: aload         5
      95: aload         4
      97: invokevirtual #74                 // Method java/lang/StringBuilder.append:(Ljava/lang/String;)Ljava/lang/StringBuilder;
     100: pop
     101: aload_3
     102: astore_2
     103: aload_3
     104: getstatic     #31                 // Field a:Ljava/lang/String;
     107: invokevirtual #117                // Method java/lang/String.contains:(Ljava/lang/CharSequence;)Z
     110: ifeq          123
     113: aload_3
     114: getstatic     #31                 // Field a:Ljava/lang/String;
     117: ldc           #119                // String  <br>
     119: invokevirtual #123                // Method java/lang/String.replaceAll:(Ljava/lang/String;Ljava/lang/String;)Ljava/lang/String;
     122: astore_2
     123: aload         5
     125: ldc           #103                // String ,
     127: invokevirtual #74                 // Method java/lang/StringBuilder.append:(Ljava/lang/String;)Ljava/lang/StringBuilder;
     130: pop
     131: aload         5
     133: aload_2
     134: invokevirtual #74                 // Method java/lang/StringBuilder.append:(Ljava/lang/String;)Ljava/lang/StringBuilder;
     137: pop
     138: aload         5
     140: getstatic     #31                 // Field a:Ljava/lang/String;
     143: invokevirtual #74                 // Method java/lang/StringBuilder.append:(Ljava/lang/String;)Ljava/lang/StringBuilder;
     146: pop
     147: aload_0
     148: getfield      #48                 // Field d:Lcom/b/a/g;
     151: iload_1
     152: aload         4
     154: aload         5
     156: invokevirtual #80                 // Method java/lang/StringBuilder.toString:()Ljava/lang/String;
     159: invokeinterface #127,  4          // InterfaceMethod com/b/a/g.a:(ILjava/lang/String;Ljava/lang/String;)V
     164: return
}
