class android.support.v4.b.a.d$b extends android.support.v4.b.a.d$a {
  android.support.v4.b.a.d$b(android.support.v4.b.a.d$a, android.content.res.Resources);
    Code:
       0: aload_0
       1: aload_1
       2: aload_2
       3: invokespecial #11                 // Method android/support/v4/b/a/d$a."<init>":(Landroid/support/v4/b/a/d$a;Landroid/content/res/Resources;)V
       6: return

  public android.graphics.drawable.Drawable newDrawable(android.content.res.Resources);
    Code:
       0: new           #6                  // class android/support/v4/b/a/d
       3: dup
       4: aload_0
       5: aload_1
       6: invokespecial #15                 // Method android/support/v4/b/a/d."<init>":(Landroid/support/v4/b/a/d$a;Landroid/content/res/Resources;)V
       9: areturn
}
