public class ryey.easer.core.a.d {
  public static void a(android.content.Context, android.net.Uri);
    Code:
       0: aload_0
       1: aload_0
       2: invokevirtual #12                 // Method android/content/Context.getContentResolver:()Landroid/content/ContentResolver;
       5: aload_1
       6: invokevirtual #18                 // Method android/content/ContentResolver.openOutputStream:(Landroid/net/Uri;)Ljava/io/OutputStream;
       9: invokestatic  #21                 // Method a:(Landroid/content/Context;Ljava/io/OutputStream;)V
      12: return

  public static void a(android.content.Context, java.io.File);
    Code:
       0: aload_0
       1: new           #25                 // class java/io/FileOutputStream
       4: dup
       5: aload_1
       6: invokespecial #29                 // Method java/io/FileOutputStream."<init>":(Ljava/io/File;)V
       9: invokestatic  #21                 // Method a:(Landroid/content/Context;Ljava/io/OutputStream;)V
      12: return

  public static void a(android.content.Context, java.io.OutputStream);
    Code:
       0: new           #31                 // class java/util/zip/ZipOutputStream
       3: dup
       4: aload_1
       5: invokespecial #34                 // Method java/util/zip/ZipOutputStream."<init>":(Ljava/io/OutputStream;)V
       8: astore_1
       9: aload_0
      10: invokevirtual #38                 // Method android/content/Context.getFilesDir:()Ljava/io/File;
      13: astore_0
      14: aload_0
      15: invokevirtual #44                 // Method java/io/File.listFiles:()[Ljava/io/File;
      18: astore        4
      20: aload         4
      22: arraylength
      23: istore_3
      24: iconst_0
      25: istore_2
      26: iload_2
      27: iload_3
      28: if_icmpge     62
      31: aload         4
      33: iload_2
      34: aaload
      35: astore        5
      37: aload         5
      39: invokevirtual #48                 // Method java/io/File.isDirectory:()Z
      42: ifeq          55
      45: aload_1
      46: aload_0
      47: aload         5
      49: invokevirtual #52                 // Method java/io/File.getName:()Ljava/lang/String;
      52: invokestatic  #55                 // Method a:(Ljava/util/zip/ZipOutputStream;Ljava/io/File;Ljava/lang/String;)V
      55: iload_2
      56: iconst_1
      57: iadd
      58: istore_2
      59: goto          26
      62: aload_1
      63: invokevirtual #59                 // Method java/util/zip/ZipOutputStream.close:()V
      66: return

  public static void b(android.content.Context, android.net.Uri);
    Code:
       0: aload_0
       1: aload_1
       2: invokestatic  #105                // Method c:(Landroid/content/Context;Landroid/net/Uri;)Z
       5: ifne          18
       8: new           #107                // class ryey/easer/core/a/e
      11: dup
      12: ldc           #109                // String exported data is not valid
      14: invokespecial #110                // Method ryey/easer/core/a/e."<init>":(Ljava/lang/String;)V
      17: athrow
      18: aload_0
      19: invokevirtual #38                 // Method android/content/Context.getFilesDir:()Ljava/io/File;
      22: astore_3
      23: new           #112                // class java/util/zip/ZipInputStream
      26: dup
      27: aload_0
      28: invokevirtual #12                 // Method android/content/Context.getContentResolver:()Landroid/content/ContentResolver;
      31: aload_1
      32: invokevirtual #116                // Method android/content/ContentResolver.openInputStream:(Landroid/net/Uri;)Ljava/io/InputStream;
      35: invokespecial #119                // Method java/util/zip/ZipInputStream."<init>":(Ljava/io/InputStream;)V
      38: astore_0
      39: sipush        1024
      42: newarray       byte
      44: astore_1
      45: aload_0
      46: invokevirtual #123                // Method java/util/zip/ZipInputStream.getNextEntry:()Ljava/util/zip/ZipEntry;
      49: astore        4
      51: aload         4
      53: ifnull        264
      56: aload         4
      58: invokevirtual #124                // Method java/util/zip/ZipEntry.isDirectory:()Z
      61: ifeq          213
      64: new           #40                 // class java/io/File
      67: dup
      68: aload_3
      69: aload         4
      71: invokevirtual #125                // Method java/util/zip/ZipEntry.getName:()Ljava/lang/String;
      74: invokespecial #62                 // Method java/io/File."<init>":(Ljava/io/File;Ljava/lang/String;)V
      77: astore        4
      79: aload         4
      81: invokevirtual #128                // Method java/io/File.exists:()Z
      84: ifne          150
      87: aload         4
      89: invokevirtual #131                // Method java/io/File.mkdir:()Z
      92: ifne          130
      95: ldc           #133                // String failed to create dir <%s>
      97: iconst_1
      98: anewarray     #4                  // class java/lang/Object
     101: dup
     102: iconst_0
     103: aload         4
     105: invokevirtual #134                // Method java/io/File.toString:()Ljava/lang/String;
     108: aastore
     109: invokestatic  #140                // Method java/lang/String.format:(Ljava/lang/String;[Ljava/lang/Object;)Ljava/lang/String;
     112: astore_0
     113: aload_0
     114: iconst_0
     115: anewarray     #4                  // class java/lang/Object
     118: invokestatic  #145                // Method com/b/a/i.b:(Ljava/lang/String;[Ljava/lang/Object;)V
     121: new           #147                // class java/io/IOException
     124: dup
     125: aload_0
     126: invokespecial #148                // Method java/io/IOException."<init>":(Ljava/lang/String;)V
     129: athrow
     130: ldc           #150                // String successfully created dir <%s>
     132: iconst_1
     133: anewarray     #4                  // class java/lang/Object
     136: dup
     137: iconst_0
     138: aload         4
     140: invokevirtual #134                // Method java/io/File.toString:()Ljava/lang/String;
     143: aastore
     144: invokestatic  #152                // Method com/b/a/i.a:(Ljava/lang/String;[Ljava/lang/Object;)V
     147: goto          45
     150: aload         4
     152: invokevirtual #48                 // Method java/io/File.isDirectory:()Z
     155: ifne          193
     158: ldc           #154                // String <%s> exists but is not a directory
     160: iconst_1
     161: anewarray     #4                  // class java/lang/Object
     164: dup
     165: iconst_0
     166: aload         4
     168: invokevirtual #134                // Method java/io/File.toString:()Ljava/lang/String;
     171: aastore
     172: invokestatic  #140                // Method java/lang/String.format:(Ljava/lang/String;[Ljava/lang/Object;)Ljava/lang/String;
     175: astore_0
     176: aload_0
     177: iconst_0
     178: anewarray     #4                  // class java/lang/Object
     181: invokestatic  #145                // Method com/b/a/i.b:(Ljava/lang/String;[Ljava/lang/Object;)V
     184: new           #147                // class java/io/IOException
     187: dup
     188: aload_0
     189: invokespecial #148                // Method java/io/IOException."<init>":(Ljava/lang/String;)V
     192: athrow
     193: ldc           #156                // String dir <%s> exists
     195: iconst_1
     196: anewarray     #4                  // class java/lang/Object
     199: dup
     200: iconst_0
     201: aload         4
     203: invokevirtual #134                // Method java/io/File.toString:()Ljava/lang/String;
     206: aastore
     207: invokestatic  #159                // Method com/b/a/i.d:(Ljava/lang/String;[Ljava/lang/Object;)V
     210: goto          45
     213: new           #25                 // class java/io/FileOutputStream
     216: dup
     217: new           #40                 // class java/io/File
     220: dup
     221: aload_3
     222: aload         4
     224: invokevirtual #125                // Method java/util/zip/ZipEntry.getName:()Ljava/lang/String;
     227: invokespecial #62                 // Method java/io/File."<init>":(Ljava/io/File;Ljava/lang/String;)V
     230: invokespecial #29                 // Method java/io/FileOutputStream."<init>":(Ljava/io/File;)V
     233: astore        4
     235: aload_0
     236: aload_1
     237: invokevirtual #160                // Method java/util/zip/ZipInputStream.read:([B)I
     240: istore_2
     241: iload_2
     242: ifle          256
     245: aload         4
     247: aload_1
     248: iconst_0
     249: iload_2
     250: invokevirtual #161                // Method java/io/FileOutputStream.write:([BII)V
     253: goto          235
     256: aload         4
     258: invokevirtual #162                // Method java/io/FileOutputStream.close:()V
     261: goto          45
     264: aload_0
     265: invokevirtual #165                // Method java/util/zip/ZipInputStream.closeEntry:()V
     268: aload_0
     269: invokevirtual #166                // Method java/util/zip/ZipInputStream.close:()V
     272: return
}
