public final class ryey.easer.core.a.k {
  final ryey.easer.core.a.j a;

  final java.util.List<ryey.easer.core.a.k> b;

  public ryey.easer.core.a.k(ryey.easer.core.a.j, java.util.List<ryey.easer.core.a.k>);
    Code:
       0: aload_0
       1: invokespecial #14                 // Method java/lang/Object."<init>":()V
       4: aload_0
       5: aload_1
       6: putfield      #16                 // Field a:Lryey/easer/core/a/j;
       9: aload_0
      10: aload_2
      11: putfield      #18                 // Field b:Ljava/util/List;
      14: return

  public java.lang.String a();
    Code:
       0: aload_0
       1: getfield      #16                 // Field a:Lryey/easer/core/a/j;
       4: getfield      #27                 // Field ryey/easer/core/a/j.a:Ljava/lang/String;
       7: areturn

  public boolean b();
    Code:
       0: aload_0
       1: getfield      #16                 // Field a:Lryey/easer/core/a/j;
       4: invokevirtual #32                 // Method ryey/easer/core/a/j.e:()Lryey/easer/core/a/c;
       7: ifnull        12
      10: iconst_1
      11: ireturn
      12: iconst_0
      13: ireturn

  public ryey.easer.core.a.c c();
    Code:
       0: aload_0
       1: getfield      #16                 // Field a:Lryey/easer/core/a/j;
       4: invokevirtual #32                 // Method ryey/easer/core/a/j.e:()Lryey/easer/core/a/c;
       7: areturn

  public ryey.easer.core.a.b d();
    Code:
       0: aload_0
       1: getfield      #16                 // Field a:Lryey/easer/core/a/j;
       4: invokevirtual #38                 // Method ryey/easer/core/a/j.g:()Lryey/easer/core/a/b;
       7: areturn

  public boolean e();
    Code:
       0: aload_0
       1: getfield      #16                 // Field a:Lryey/easer/core/a/j;
       4: invokevirtual #41                 // Method ryey/easer/core/a/j.m:()Z
       7: ireturn

  public boolean f();
    Code:
       0: aload_0
       1: getfield      #16                 // Field a:Lryey/easer/core/a/j;
       4: invokevirtual #45                 // Method ryey/easer/core/a/j.k:()Z
       7: ireturn

  public boolean g();
    Code:
       0: aload_0
       1: getfield      #16                 // Field a:Lryey/easer/core/a/j;
       4: invokevirtual #48                 // Method ryey/easer/core/a/j.l:()Z
       7: ireturn

  public java.util.List<ryey.easer.core.a.k> h();
    Code:
       0: aload_0
       1: getfield      #18                 // Field b:Ljava/util/List;
       4: areturn

  public java.lang.String i();
    Code:
       0: aload_0
       1: getfield      #16                 // Field a:Lryey/easer/core/a/j;
       4: getfield      #54                 // Field ryey/easer/core/a/j.c:Ljava/lang/String;
       7: areturn

  public boolean j();
    Code:
       0: aload_0
       1: getfield      #16                 // Field a:Lryey/easer/core/a/j;
       4: invokevirtual #57                 // Method ryey/easer/core/a/j.h:()Z
       7: ireturn

  public ryey.easer.core.a.j k();
    Code:
       0: aload_0
       1: getfield      #16                 // Field a:Lryey/easer/core/a/j;
       4: areturn
}
