final class ryey.easer.core.ui.version_n_info.c$a implements android.content.DialogInterface$OnClickListener {
  public static final ryey.easer.core.ui.version_n_info.c$a a;

  static {};
    Code:
       0: new           #2                  // class ryey/easer/core/ui/version_n_info/c$a
       3: dup
       4: invokespecial #17                 // Method "<init>":()V
       7: putstatic     #19                 // Field a:Lryey/easer/core/ui/version_n_info/c$a;
      10: return

  ryey.easer.core.ui.version_n_info.c$a();
    Code:
       0: aload_0
       1: invokespecial #21                 // Method java/lang/Object."<init>":()V
       4: return

  public final void onClick(android.content.DialogInterface, int);
    Code:
       0: aload_1
       1: invokeinterface #28,  1           // InterfaceMethod android/content/DialogInterface.dismiss:()V
       6: return
}
