public final class ryey.easer.core.ui.version_n_info.c {
  public static final ryey.easer.core.ui.version_n_info.c a;

  static {};
    Code:
       0: new           #2                  // class ryey/easer/core/ui/version_n_info/c
       3: dup
       4: invokespecial #13                 // Method "<init>":()V
       7: putstatic     #15                 // Field a:Lryey/easer/core/ui/version_n_info/c;
      10: return

  public final void a(android.content.Context);
    Code:
       0: aload_1
       1: ldc           #123                // String context
       3: invokestatic  #126                // Method a/b/b/c.b:(Ljava/lang/Object;Ljava/lang/String;)V
       6: aload_1
       7: invokestatic  #131                // Method ryey/easer/core/a/a/f.a:(Landroid/content/Context;)Z
      10: ifeq          25
      13: aload_0
      14: aload_1
      15: ldc           #132                // int 2131623977
      17: ldc           #133                // int 2131623976
      19: iconst_0
      20: newarray       int
      22: invokespecial #135                // Method a:(Landroid/content/Context;II[I)V
      25: return

  public final void b(android.content.Context);
    Code:
       0: aload_1
       1: ldc           #123                // String context
       3: invokestatic  #126                // Method a/b/b/c.b:(Ljava/lang/Object;Ljava/lang/String;)V
       6: return
}
