class android.support.design.internal.c$e implements android.support.design.internal.c$d {
  public android.support.design.internal.c$e(int, int);
    Code:
       0: aload_0
       1: invokespecial #17                 // Method java/lang/Object."<init>":()V
       4: aload_0
       5: iload_1
       6: putfield      #19                 // Field a:I
       9: aload_0
      10: iload_2
      11: putfield      #21                 // Field b:I
      14: return

  public int a();
    Code:
       0: aload_0
       1: getfield      #19                 // Field a:I
       4: ireturn

  public int b();
    Code:
       0: aload_0
       1: getfield      #21                 // Field b:I
       4: ireturn
}
