class android.support.design.internal.c$f implements android.support.design.internal.c$d {
  boolean a;

  android.support.design.internal.c$f(android.support.v7.view.menu.j);
    Code:
       0: aload_0
       1: invokespecial #18                 // Method java/lang/Object."<init>":()V
       4: aload_0
       5: aload_1
       6: putfield      #20                 // Field b:Landroid/support/v7/view/menu/j;
       9: return

  public android.support.v7.view.menu.j a();
    Code:
       0: aload_0
       1: getfield      #20                 // Field b:Landroid/support/v7/view/menu/j;
       4: areturn
}
