public class android.support.design.internal.d extends android.support.v7.view.menu.u {
  public android.support.design.internal.d(android.content.Context, android.support.design.internal.b, android.support.v7.view.menu.j);
    Code:
       0: aload_0
       1: aload_1
       2: aload_2
       3: aload_3
       4: invokespecial #9                  // Method android/support/v7/view/menu/u."<init>":(Landroid/content/Context;Landroid/support/v7/view/menu/h;Landroid/support/v7/view/menu/j;)V
       7: return

  public void a(boolean);
    Code:
       0: aload_0
       1: iload_1
       2: invokespecial #14                 // Method android/support/v7/view/menu/u.a:(Z)V
       5: aload_0
       6: invokevirtual #18                 // Method s:()Landroid/view/Menu;
       9: checkcast     #20                 // class android/support/v7/view/menu/h
      12: iload_1
      13: invokevirtual #21                 // Method android/support/v7/view/menu/h.a:(Z)V
      16: return
}
