class android.support.design.internal.NavigationMenuItemView$1 extends android.support.v4.view.b {
  final android.support.design.internal.NavigationMenuItemView a;

  android.support.design.internal.NavigationMenuItemView$1(android.support.design.internal.NavigationMenuItemView);
    Code:
       0: aload_0
       1: aload_1
       2: putfield      #12                 // Field a:Landroid/support/design/internal/NavigationMenuItemView;
       5: aload_0
       6: invokespecial #15                 // Method android/support/v4/view/b."<init>":()V
       9: return

  public void a(android.view.View, android.support.v4.view.a.b);
    Code:
       0: aload_0
       1: aload_1
       2: aload_2
       3: invokespecial #19                 // Method android/support/v4/view/b.a:(Landroid/view/View;Landroid/support/v4/view/a/b;)V
       6: aload_2
       7: aload_0
       8: getfield      #12                 // Field a:Landroid/support/design/internal/NavigationMenuItemView;
      11: getfield      #23                 // Field android/support/design/internal/NavigationMenuItemView.c:Z
      14: invokevirtual #28                 // Method android/support/v4/view/a/b.a:(Z)V
      17: return
}
