class ryey.easer.plugins.b.e$a extends android.telephony.PhoneStateListener {
  final ryey.easer.plugins.b.e a;

  ryey.easer.plugins.b.e$a(ryey.easer.plugins.b.e, ryey.easer.plugins.b.e$1);
    Code:
       0: aload_0
       1: aload_1
       2: invokespecial #19                 // Method "<init>":(Lryey/easer/plugins/b/e;)V
       5: return

  public void onCellLocationChanged(android.telephony.CellLocation);
    Code:
       0: aload_0
       1: monitorenter
       2: aload_0
       3: getfield      #12                 // Field a:Lryey/easer/plugins/b/e;
       6: aload_1
       7: invokestatic  #26                 // Method ryey/easer/plugins/b/b.a:(Landroid/telephony/CellLocation;)Lryey/easer/plugins/b/b;
      10: invokestatic  #29                 // Method ryey/easer/plugins/b/e.a:(Lryey/easer/plugins/b/e;Lryey/easer/plugins/b/b;)V
      13: aload_0
      14: monitorexit
      15: return
      16: astore_1
      17: aload_0
      18: monitorexit
      19: aload_1
      20: athrow
    Exception table:
       from    to  target type
           2    13    16   any
}
