class ryey.easer.plugins.b.e$b extends android.os.AsyncTask<java.lang.Void, ryey.easer.plugins.b.b, java.lang.Void> {
  ryey.easer.plugins.b.e$b(android.telephony.TelephonyManager, java.util.List, android.widget.ArrayAdapter, ryey.easer.plugins.b.e$1);
    Code:
       0: aload_0
       1: aload_1
       2: aload_2
       3: aload_3
       4: invokespecial #35                 // Method "<init>":(Landroid/telephony/TelephonyManager;Ljava/util/List;Landroid/widget/ArrayAdapter;)V
       7: return

  protected java.lang.Void a(java.lang.Void...);
    Code:
       0: getstatic     #42                 // Field android/os/Build$VERSION.SDK_INT:I
       3: bipush        17
       5: if_icmplt     65
       8: aload_0
       9: getfield      #25                 // Field a:Landroid/telephony/TelephonyManager;
      12: invokevirtual #48                 // Method android/telephony/TelephonyManager.getAllCellInfo:()Ljava/util/List;
      15: invokeinterface #54,  1           // InterfaceMethod java/util/List.iterator:()Ljava/util/Iterator;
      20: astore_1
      21: aload_1
      22: invokeinterface #60,  1           // InterfaceMethod java/util/Iterator.hasNext:()Z
      27: ifeq          86
      30: aload_1
      31: invokeinterface #64,  1           // InterfaceMethod java/util/Iterator.next:()Ljava/lang/Object;
      36: checkcast     #66                 // class android/telephony/CellInfo
      39: astore_2
      40: aload_2
      41: invokevirtual #69                 // Method android/telephony/CellInfo.isRegistered:()Z
      44: ifeq          21
      47: aload_0
      48: iconst_1
      49: anewarray     #71                 // class ryey/easer/plugins/b/b
      52: dup
      53: iconst_0
      54: aload_2
      55: invokestatic  #74                 // Method ryey/easer/plugins/b/b.a:(Landroid/telephony/CellInfo;)Lryey/easer/plugins/b/b;
      58: aastore
      59: invokevirtual #78                 // Method publishProgress:([Ljava/lang/Object;)V
      62: goto          21
      65: aload_0
      66: iconst_1
      67: anewarray     #71                 // class ryey/easer/plugins/b/b
      70: dup
      71: iconst_0
      72: aload_0
      73: getfield      #25                 // Field a:Landroid/telephony/TelephonyManager;
      76: invokevirtual #82                 // Method android/telephony/TelephonyManager.getCellLocation:()Landroid/telephony/CellLocation;
      79: invokestatic  #85                 // Method ryey/easer/plugins/b/b.a:(Landroid/telephony/CellLocation;)Lryey/easer/plugins/b/b;
      82: aastore
      83: invokevirtual #78                 // Method publishProgress:([Ljava/lang/Object;)V
      86: aconst_null
      87: areturn

  protected void a(ryey.easer.plugins.b.b...);
    Code:
       0: aload_0
       1: getfield      #27                 // Field b:Ljava/util/List;
       4: aload_0
       5: getfield      #29                 // Field c:Landroid/widget/ArrayAdapter;
       8: aload_1
       9: iconst_0
      10: aaload
      11: invokestatic  #89                 // Method ryey/easer/plugins/b/e.a:(Ljava/util/List;Landroid/widget/ArrayAdapter;Lryey/easer/plugins/b/b;)V
      14: return

  protected java.lang.Object doInBackground(java.lang.Object[]);
    Code:
       0: aload_0
       1: aload_1
       2: checkcast     #93                 // class "[Ljava/lang/Void;"
       5: invokevirtual #95                 // Method a:([Ljava/lang/Void;)Ljava/lang/Void;
       8: areturn

  protected void onProgressUpdate(java.lang.Object[]);
    Code:
       0: aload_0
       1: aload_1
       2: checkcast     #98                 // class "[Lryey/easer/plugins/b/b;"
       5: invokevirtual #100                // Method a:([Lryey/easer/plugins/b/b;)V
       8: return
}
