public class ryey.easer.plugins.operation.g.f extends ryey.easer.plugins.operation.e<ryey.easer.plugins.operation.g.c> {
  public ryey.easer.plugins.operation.g.f();
    Code:
       0: aload_0
       1: invokespecial #9                  // Method ryey/easer/plugins/operation/e."<init>":()V
       4: return

  public ryey.easer.commons.local_plugin.f a();
    Code:
       0: aload_0
       1: invokevirtual #16                 // Method c:()Lryey/easer/plugins/operation/g/c;
       4: areturn

  public ryey.easer.plugins.operation.g.c c();
    Code:
       0: new           #18                 // class ryey/easer/plugins/operation/g/c
       3: dup
       4: aload_0
       5: invokevirtual #22                 // Method b:()Ljava/lang/Boolean;
       8: invokespecial #25                 // Method ryey/easer/plugins/operation/g/c."<init>":(Ljava/lang/Boolean;)V
      11: areturn
}
