public class android.support.constraint.a.a.a extends android.support.constraint.a.a.g {
  public android.support.constraint.a.a.a();
    Code:
       0: aload_0
       1: invokespecial #15                 // Method android/support/constraint/a/a/g."<init>":()V
       4: aload_0
       5: iconst_0
       6: putfield      #17                 // Field ad:I
       9: aload_0
      10: new           #19                 // class java/util/ArrayList
      13: dup
      14: iconst_4
      15: invokespecial #22                 // Method java/util/ArrayList."<init>":(I)V
      18: putfield      #24                 // Field ae:Ljava/util/ArrayList;
      21: aload_0
      22: iconst_1
      23: putfield      #26                 // Field af:Z
      26: return

  public void a(int);
    Code:
       0: aload_0
       1: iload_1
       2: putfield      #17                 // Field ad:I
       5: return

  public void a(android.support.constraint.a.e);
    Code:
       0: aload_0
       1: getfield      #33                 // Field y:[Landroid/support/constraint/a/a/c;
       4: iconst_0
       5: aload_0
       6: getfield      #37                 // Field q:Landroid/support/constraint/a/a/c;
       9: aastore
      10: aload_0
      11: getfield      #33                 // Field y:[Landroid/support/constraint/a/a/c;
      14: iconst_2
      15: aload_0
      16: getfield      #40                 // Field r:Landroid/support/constraint/a/a/c;
      19: aastore
      20: aload_0
      21: getfield      #33                 // Field y:[Landroid/support/constraint/a/a/c;
      24: iconst_1
      25: aload_0
      26: getfield      #43                 // Field s:Landroid/support/constraint/a/a/c;
      29: aastore
      30: aload_0
      31: getfield      #33                 // Field y:[Landroid/support/constraint/a/a/c;
      34: iconst_3
      35: aload_0
      36: getfield      #46                 // Field t:Landroid/support/constraint/a/a/c;
      39: aastore
      40: iconst_0
      41: istore_2
      42: iload_2
      43: aload_0
      44: getfield      #33                 // Field y:[Landroid/support/constraint/a/a/c;
      47: arraylength
      48: if_icmpge     77
      51: aload_0
      52: getfield      #33                 // Field y:[Landroid/support/constraint/a/a/c;
      55: iload_2
      56: aaload
      57: aload_1
      58: aload_0
      59: getfield      #33                 // Field y:[Landroid/support/constraint/a/a/c;
      62: iload_2
      63: aaload
      64: invokevirtual #51                 // Method android/support/constraint/a/e.a:(Ljava/lang/Object;)Landroid/support/constraint/a/h;
      67: putfield      #57                 // Field android/support/constraint/a/a/c.f:Landroid/support/constraint/a/h;
      70: iload_2
      71: iconst_1
      72: iadd
      73: istore_2
      74: goto          42
      77: aload_0
      78: getfield      #17                 // Field ad:I
      81: iflt          608
      84: aload_0
      85: getfield      #17                 // Field ad:I
      88: iconst_4
      89: if_icmpge     608
      92: aload_0
      93: getfield      #33                 // Field y:[Landroid/support/constraint/a/a/c;
      96: aload_0
      97: getfield      #17                 // Field ad:I
     100: aaload
     101: astore        4
     103: iconst_0
     104: istore_2
     105: iload_2
     106: aload_0
     107: getfield      #60                 // Field ac:I
     110: if_icmpge     207
     113: aload_0
     114: getfield      #64                 // Field ab:[Landroid/support/constraint/a/a/d;
     117: iload_2
     118: aaload
     119: astore        5
     121: aload_0
     122: getfield      #26                 // Field af:Z
     125: ifne          139
     128: aload         5
     130: invokevirtual #69                 // Method android/support/constraint/a/a/d.a:()Z
     133: ifne          139
     136: goto          200
     139: aload_0
     140: getfield      #17                 // Field ad:I
     143: ifeq          154
     146: aload_0
     147: getfield      #17                 // Field ad:I
     150: iconst_1
     151: if_icmpne     170
     154: aload         5
     156: invokevirtual #73                 // Method android/support/constraint/a/a/d.F:()Landroid/support/constraint/a/a/d$a;
     159: getstatic     #79                 // Field android/support/constraint/a/a/d$a.c:Landroid/support/constraint/a/a/d$a;
     162: if_acmpne     170
     165: iconst_1
     166: istore_3
     167: goto          209
     170: aload_0
     171: getfield      #17                 // Field ad:I
     174: iconst_2
     175: if_icmpeq     186
     178: aload_0
     179: getfield      #17                 // Field ad:I
     182: iconst_3
     183: if_icmpne     200
     186: aload         5
     188: invokevirtual #82                 // Method android/support/constraint/a/a/d.G:()Landroid/support/constraint/a/a/d$a;
     191: getstatic     #79                 // Field android/support/constraint/a/a/d$a.c:Landroid/support/constraint/a/a/d$a;
     194: if_acmpne     200
     197: goto          165
     200: iload_2
     201: iconst_1
     202: iadd
     203: istore_2
     204: goto          105
     207: iconst_0
     208: istore_3
     209: aload_0
     210: getfield      #17                 // Field ad:I
     213: ifeq          243
     216: aload_0
     217: getfield      #17                 // Field ad:I
     220: iconst_1
     221: if_icmpne     227
     224: goto          243
     227: aload_0
     228: invokevirtual #86                 // Method j:()Landroid/support/constraint/a/a/d;
     231: invokevirtual #82                 // Method android/support/constraint/a/a/d.G:()Landroid/support/constraint/a/a/d$a;
     234: getstatic     #89                 // Field android/support/constraint/a/a/d$a.b:Landroid/support/constraint/a/a/d$a;
     237: if_acmpne     258
     240: goto          256
     243: aload_0
     244: invokevirtual #86                 // Method j:()Landroid/support/constraint/a/a/d;
     247: invokevirtual #73                 // Method android/support/constraint/a/a/d.F:()Landroid/support/constraint/a/a/d$a;
     250: getstatic     #89                 // Field android/support/constraint/a/a/d$a.b:Landroid/support/constraint/a/a/d$a;
     253: if_acmpne     258
     256: iconst_0
     257: istore_3
     258: iconst_0
     259: istore_2
     260: iload_2
     261: aload_0
     262: getfield      #60                 // Field ac:I
     265: if_icmpge     377
     268: aload_0
     269: getfield      #64                 // Field ab:[Landroid/support/constraint/a/a/d;
     272: iload_2
     273: aaload
     274: astore        5
     276: aload_0
     277: getfield      #26                 // Field af:Z
     280: ifne          294
     283: aload         5
     285: invokevirtual #69                 // Method android/support/constraint/a/a/d.a:()Z
     288: ifne          294
     291: goto          370
     294: aload_1
     295: aload         5
     297: getfield      #90                 // Field android/support/constraint/a/a/d.y:[Landroid/support/constraint/a/a/c;
     300: aload_0
     301: getfield      #17                 // Field ad:I
     304: aaload
     305: invokevirtual #51                 // Method android/support/constraint/a/e.a:(Ljava/lang/Object;)Landroid/support/constraint/a/h;
     308: astore        6
     310: aload         5
     312: getfield      #90                 // Field android/support/constraint/a/a/d.y:[Landroid/support/constraint/a/a/c;
     315: aload_0
     316: getfield      #17                 // Field ad:I
     319: aaload
     320: aload         6
     322: putfield      #57                 // Field android/support/constraint/a/a/c.f:Landroid/support/constraint/a/h;
     325: aload_0
     326: getfield      #17                 // Field ad:I
     329: ifeq          358
     332: aload_0
     333: getfield      #17                 // Field ad:I
     336: iconst_2
     337: if_icmpne     343
     340: goto          358
     343: aload_1
     344: aload         4
     346: getfield      #57                 // Field android/support/constraint/a/a/c.f:Landroid/support/constraint/a/h;
     349: aload         6
     351: iload_3
     352: invokevirtual #93                 // Method android/support/constraint/a/e.a:(Landroid/support/constraint/a/h;Landroid/support/constraint/a/h;Z)V
     355: goto          370
     358: aload_1
     359: aload         4
     361: getfield      #57                 // Field android/support/constraint/a/a/c.f:Landroid/support/constraint/a/h;
     364: aload         6
     366: iload_3
     367: invokevirtual #95                 // Method android/support/constraint/a/e.b:(Landroid/support/constraint/a/h;Landroid/support/constraint/a/h;Z)V
     370: iload_2
     371: iconst_1
     372: iadd
     373: istore_2
     374: goto          260
     377: aload_0
     378: getfield      #17                 // Field ad:I
     381: ifne          443
     384: aload_1
     385: aload_0
     386: getfield      #43                 // Field s:Landroid/support/constraint/a/a/c;
     389: getfield      #57                 // Field android/support/constraint/a/a/c.f:Landroid/support/constraint/a/h;
     392: aload_0
     393: getfield      #37                 // Field q:Landroid/support/constraint/a/a/c;
     396: getfield      #57                 // Field android/support/constraint/a/a/c.f:Landroid/support/constraint/a/h;
     399: iconst_0
     400: bipush        6
     402: invokevirtual #98                 // Method android/support/constraint/a/e.c:(Landroid/support/constraint/a/h;Landroid/support/constraint/a/h;II)Landroid/support/constraint/a/b;
     405: pop
     406: iload_3
     407: ifne          608
     410: aload_0
     411: getfield      #37                 // Field q:Landroid/support/constraint/a/a/c;
     414: getfield      #57                 // Field android/support/constraint/a/a/c.f:Landroid/support/constraint/a/h;
     417: astore        4
     419: aload_0
     420: getfield      #102                // Field B:Landroid/support/constraint/a/a/d;
     423: getfield      #103                // Field android/support/constraint/a/a/d.s:Landroid/support/constraint/a/a/c;
     426: astore        5
     428: aload_1
     429: aload         4
     431: aload         5
     433: getfield      #57                 // Field android/support/constraint/a/a/c.f:Landroid/support/constraint/a/h;
     436: iconst_0
     437: iconst_5
     438: invokevirtual #98                 // Method android/support/constraint/a/e.c:(Landroid/support/constraint/a/h;Landroid/support/constraint/a/h;II)Landroid/support/constraint/a/b;
     441: pop
     442: return
     443: aload_0
     444: getfield      #17                 // Field ad:I
     447: iconst_1
     448: if_icmpne     498
     451: aload_1
     452: aload_0
     453: getfield      #37                 // Field q:Landroid/support/constraint/a/a/c;
     456: getfield      #57                 // Field android/support/constraint/a/a/c.f:Landroid/support/constraint/a/h;
     459: aload_0
     460: getfield      #43                 // Field s:Landroid/support/constraint/a/a/c;
     463: getfield      #57                 // Field android/support/constraint/a/a/c.f:Landroid/support/constraint/a/h;
     466: iconst_0
     467: bipush        6
     469: invokevirtual #98                 // Method android/support/constraint/a/e.c:(Landroid/support/constraint/a/h;Landroid/support/constraint/a/h;II)Landroid/support/constraint/a/b;
     472: pop
     473: iload_3
     474: ifne          608
     477: aload_0
     478: getfield      #37                 // Field q:Landroid/support/constraint/a/a/c;
     481: getfield      #57                 // Field android/support/constraint/a/a/c.f:Landroid/support/constraint/a/h;
     484: astore        4
     486: aload_0
     487: getfield      #102                // Field B:Landroid/support/constraint/a/a/d;
     490: getfield      #104                // Field android/support/constraint/a/a/d.q:Landroid/support/constraint/a/a/c;
     493: astore        5
     495: goto          428
     498: aload_0
     499: getfield      #17                 // Field ad:I
     502: iconst_2
     503: if_icmpne     553
     506: aload_1
     507: aload_0
     508: getfield      #46                 // Field t:Landroid/support/constraint/a/a/c;
     511: getfield      #57                 // Field android/support/constraint/a/a/c.f:Landroid/support/constraint/a/h;
     514: aload_0
     515: getfield      #40                 // Field r:Landroid/support/constraint/a/a/c;
     518: getfield      #57                 // Field android/support/constraint/a/a/c.f:Landroid/support/constraint/a/h;
     521: iconst_0
     522: bipush        6
     524: invokevirtual #98                 // Method android/support/constraint/a/e.c:(Landroid/support/constraint/a/h;Landroid/support/constraint/a/h;II)Landroid/support/constraint/a/b;
     527: pop
     528: iload_3
     529: ifne          608
     532: aload_0
     533: getfield      #40                 // Field r:Landroid/support/constraint/a/a/c;
     536: getfield      #57                 // Field android/support/constraint/a/a/c.f:Landroid/support/constraint/a/h;
     539: astore        4
     541: aload_0
     542: getfield      #102                // Field B:Landroid/support/constraint/a/a/d;
     545: getfield      #105                // Field android/support/constraint/a/a/d.t:Landroid/support/constraint/a/a/c;
     548: astore        5
     550: goto          428
     553: aload_0
     554: getfield      #17                 // Field ad:I
     557: iconst_3
     558: if_icmpne     608
     561: aload_1
     562: aload_0
     563: getfield      #40                 // Field r:Landroid/support/constraint/a/a/c;
     566: getfield      #57                 // Field android/support/constraint/a/a/c.f:Landroid/support/constraint/a/h;
     569: aload_0
     570: getfield      #46                 // Field t:Landroid/support/constraint/a/a/c;
     573: getfield      #57                 // Field android/support/constraint/a/a/c.f:Landroid/support/constraint/a/h;
     576: iconst_0
     577: bipush        6
     579: invokevirtual #98                 // Method android/support/constraint/a/e.c:(Landroid/support/constraint/a/h;Landroid/support/constraint/a/h;II)Landroid/support/constraint/a/b;
     582: pop
     583: iload_3
     584: ifne          608
     587: aload_0
     588: getfield      #40                 // Field r:Landroid/support/constraint/a/a/c;
     591: getfield      #57                 // Field android/support/constraint/a/a/c.f:Landroid/support/constraint/a/h;
     594: astore        4
     596: aload_0
     597: getfield      #102                // Field B:Landroid/support/constraint/a/a/d;
     600: getfield      #106                // Field android/support/constraint/a/a/d.r:Landroid/support/constraint/a/a/c;
     603: astore        5
     605: goto          428
     608: return

  public void a(boolean);
    Code:
       0: aload_0
       1: iload_1
       2: putfield      #26                 // Field af:Z
       5: return

  public boolean a();
    Code:
       0: iconst_1
       1: ireturn

  public void b();
    Code:
       0: aload_0
       1: invokespecial #109                // Method android/support/constraint/a/a/g.b:()V
       4: aload_0
       5: getfield      #24                 // Field ae:Ljava/util/ArrayList;
       8: invokevirtual #112                // Method java/util/ArrayList.clear:()V
      11: return

  public void b(int);
    Code:
       0: aload_0
       1: getfield      #102                // Field B:Landroid/support/constraint/a/a/d;
       4: ifnonnull     8
       7: return
       8: aload_0
       9: getfield      #102                // Field B:Landroid/support/constraint/a/a/d;
      12: checkcast     #114                // class android/support/constraint/a/a/e
      15: iconst_2
      16: invokevirtual #117                // Method android/support/constraint/a/a/e.q:(I)Z
      19: ifne          23
      22: return
      23: aload_0
      24: getfield      #17                 // Field ad:I
      27: tableswitch   { // 0 to 3
                     0: 81
                     1: 73
                     2: 65
                     3: 57
               default: 56
          }
      56: return
      57: aload_0
      58: getfield      #46                 // Field t:Landroid/support/constraint/a/a/c;
      61: astore_2
      62: goto          86
      65: aload_0
      66: getfield      #40                 // Field r:Landroid/support/constraint/a/a/c;
      69: astore_2
      70: goto          86
      73: aload_0
      74: getfield      #43                 // Field s:Landroid/support/constraint/a/a/c;
      77: astore_2
      78: goto          86
      81: aload_0
      82: getfield      #37                 // Field q:Landroid/support/constraint/a/a/c;
      85: astore_2
      86: aload_2
      87: invokevirtual #120                // Method android/support/constraint/a/a/c.a:()Landroid/support/constraint/a/a/j;
      90: astore_3
      91: aload_3
      92: iconst_5
      93: invokevirtual #124                // Method android/support/constraint/a/a/j.b:(I)V
      96: aload_0
      97: getfield      #17                 // Field ad:I
     100: ifeq          134
     103: aload_0
     104: getfield      #17                 // Field ad:I
     107: iconst_1
     108: if_icmpne     114
     111: goto          134
     114: aload_0
     115: getfield      #37                 // Field q:Landroid/support/constraint/a/a/c;
     118: invokevirtual #120                // Method android/support/constraint/a/a/c.a:()Landroid/support/constraint/a/a/j;
     121: aconst_null
     122: fconst_0
     123: invokevirtual #127                // Method android/support/constraint/a/a/j.a:(Landroid/support/constraint/a/a/j;F)V
     126: aload_0
     127: getfield      #43                 // Field s:Landroid/support/constraint/a/a/c;
     130: astore_2
     131: goto          151
     134: aload_0
     135: getfield      #40                 // Field r:Landroid/support/constraint/a/a/c;
     138: invokevirtual #120                // Method android/support/constraint/a/a/c.a:()Landroid/support/constraint/a/a/j;
     141: aconst_null
     142: fconst_0
     143: invokevirtual #127                // Method android/support/constraint/a/a/j.a:(Landroid/support/constraint/a/a/j;F)V
     146: aload_0
     147: getfield      #46                 // Field t:Landroid/support/constraint/a/a/c;
     150: astore_2
     151: aload_2
     152: invokevirtual #120                // Method android/support/constraint/a/a/c.a:()Landroid/support/constraint/a/a/j;
     155: aconst_null
     156: fconst_0
     157: invokevirtual #127                // Method android/support/constraint/a/a/j.a:(Landroid/support/constraint/a/a/j;F)V
     160: aload_0
     161: getfield      #24                 // Field ae:Ljava/util/ArrayList;
     164: invokevirtual #112                // Method java/util/ArrayList.clear:()V
     167: iconst_0
     168: istore_1
     169: iload_1
     170: aload_0
     171: getfield      #60                 // Field ac:I
     174: if_icmpge     300
     177: aload_0
     178: getfield      #64                 // Field ab:[Landroid/support/constraint/a/a/d;
     181: iload_1
     182: aaload
     183: astore_2
     184: aload_0
     185: getfield      #26                 // Field af:Z
     188: ifne          201
     191: aload_2
     192: invokevirtual #69                 // Method android/support/constraint/a/a/d.a:()Z
     195: ifne          201
     198: goto          293
     201: aload_0
     202: getfield      #17                 // Field ad:I
     205: tableswitch   { // 0 to 3
                     0: 265
                     1: 257
                     2: 249
                     3: 241
               default: 236
          }
     236: aconst_null
     237: astore_2
     238: goto          275
     241: aload_2
     242: getfield      #105                // Field android/support/constraint/a/a/d.t:Landroid/support/constraint/a/a/c;
     245: astore_2
     246: goto          270
     249: aload_2
     250: getfield      #106                // Field android/support/constraint/a/a/d.r:Landroid/support/constraint/a/a/c;
     253: astore_2
     254: goto          270
     257: aload_2
     258: getfield      #103                // Field android/support/constraint/a/a/d.s:Landroid/support/constraint/a/a/c;
     261: astore_2
     262: goto          270
     265: aload_2
     266: getfield      #104                // Field android/support/constraint/a/a/d.q:Landroid/support/constraint/a/a/c;
     269: astore_2
     270: aload_2
     271: invokevirtual #120                // Method android/support/constraint/a/a/c.a:()Landroid/support/constraint/a/a/j;
     274: astore_2
     275: aload_2
     276: ifnull        293
     279: aload_0
     280: getfield      #24                 // Field ae:Ljava/util/ArrayList;
     283: aload_2
     284: invokevirtual #131                // Method java/util/ArrayList.add:(Ljava/lang/Object;)Z
     287: pop
     288: aload_2
     289: aload_3
     290: invokevirtual #134                // Method android/support/constraint/a/a/j.a:(Landroid/support/constraint/a/a/l;)V
     293: iload_1
     294: iconst_1
     295: iadd
     296: istore_1
     297: goto          169
     300: return

  public void c();
    Code:
       0: aload_0
       1: getfield      #17                 // Field ad:I
       4: istore_3
       5: ldc           #135                // float 3.4028235E38f
       7: fstore_1
       8: iload_3
       9: tableswitch   { // 0 to 3
                     0: 77
                     1: 59
                     2: 50
                     3: 41
               default: 40
          }
      40: return
      41: aload_0
      42: getfield      #46                 // Field t:Landroid/support/constraint/a/a/c;
      45: astore        5
      47: goto          65
      50: aload_0
      51: getfield      #40                 // Field r:Landroid/support/constraint/a/a/c;
      54: astore        5
      56: goto          83
      59: aload_0
      60: getfield      #43                 // Field s:Landroid/support/constraint/a/a/c;
      63: astore        5
      65: aload         5
      67: invokevirtual #120                // Method android/support/constraint/a/a/c.a:()Landroid/support/constraint/a/a/j;
      70: astore        5
      72: fconst_0
      73: fstore_1
      74: goto          90
      77: aload_0
      78: getfield      #37                 // Field q:Landroid/support/constraint/a/a/c;
      81: astore        5
      83: aload         5
      85: invokevirtual #120                // Method android/support/constraint/a/a/c.a:()Landroid/support/constraint/a/a/j;
      88: astore        5
      90: aload_0
      91: getfield      #24                 // Field ae:Ljava/util/ArrayList;
      94: invokevirtual #139                // Method java/util/ArrayList.size:()I
      97: istore        4
      99: aconst_null
     100: astore        6
     102: iconst_0
     103: istore_3
     104: iload_3
     105: iload         4
     107: if_icmpge     200
     110: aload_0
     111: getfield      #24                 // Field ae:Ljava/util/ArrayList;
     114: iload_3
     115: invokevirtual #143                // Method java/util/ArrayList.get:(I)Ljava/lang/Object;
     118: checkcast     #122                // class android/support/constraint/a/a/j
     121: astore        7
     123: aload         7
     125: getfield      #146                // Field android/support/constraint/a/a/j.i:I
     128: iconst_1
     129: if_icmpeq     133
     132: return
     133: aload_0
     134: getfield      #17                 // Field ad:I
     137: ifeq          166
     140: aload_0
     141: getfield      #17                 // Field ad:I
     144: iconst_2
     145: if_icmpne     151
     148: goto          166
     151: fload_1
     152: fstore_2
     153: aload         7
     155: getfield      #148                // Field android/support/constraint/a/a/j.f:F
     158: fload_1
     159: fcmpl
     160: ifle          191
     163: goto          178
     166: fload_1
     167: fstore_2
     168: aload         7
     170: getfield      #148                // Field android/support/constraint/a/a/j.f:F
     173: fload_1
     174: fcmpg
     175: ifge          191
     178: aload         7
     180: getfield      #148                // Field android/support/constraint/a/a/j.f:F
     183: fstore_2
     184: aload         7
     186: getfield      #152                // Field android/support/constraint/a/a/j.e:Landroid/support/constraint/a/a/j;
     189: astore        6
     191: iload_3
     192: iconst_1
     193: iadd
     194: istore_3
     195: fload_2
     196: fstore_1
     197: goto          104
     200: invokestatic  #155                // Method android/support/constraint/a/e.a:()Landroid/support/constraint/a/f;
     203: ifnull        223
     206: invokestatic  #155                // Method android/support/constraint/a/e.a:()Landroid/support/constraint/a/f;
     209: astore        7
     211: aload         7
     213: aload         7
     215: getfield      #161                // Field android/support/constraint/a/f.z:J
     218: lconst_1
     219: ladd
     220: putfield      #161                // Field android/support/constraint/a/f.z:J
     223: aload         5
     225: aload         6
     227: putfield      #152                // Field android/support/constraint/a/a/j.e:Landroid/support/constraint/a/a/j;
     230: aload         5
     232: fload_1
     233: putfield      #148                // Field android/support/constraint/a/a/j.f:F
     236: aload         5
     238: invokevirtual #163                // Method android/support/constraint/a/a/j.f:()V
     241: aload_0
     242: getfield      #17                 // Field ad:I
     245: tableswitch   { // 0 to 3
                     0: 304
                     1: 295
                     2: 286
                     3: 277
               default: 276
          }
     276: return
     277: aload_0
     278: getfield      #40                 // Field r:Landroid/support/constraint/a/a/c;
     281: astore        5
     283: goto          310
     286: aload_0
     287: getfield      #46                 // Field t:Landroid/support/constraint/a/a/c;
     290: astore        5
     292: goto          310
     295: aload_0
     296: getfield      #37                 // Field q:Landroid/support/constraint/a/a/c;
     299: astore        5
     301: goto          310
     304: aload_0
     305: getfield      #43                 // Field s:Landroid/support/constraint/a/a/c;
     308: astore        5
     310: aload         5
     312: invokevirtual #120                // Method android/support/constraint/a/a/c.a:()Landroid/support/constraint/a/a/j;
     315: aload         6
     317: fload_1
     318: invokevirtual #127                // Method android/support/constraint/a/a/j.a:(Landroid/support/constraint/a/a/j;F)V
     321: return
}
