class android.support.constraint.a.a.b {
  static void a(android.support.constraint.a.a.e, android.support.constraint.a.e, int);
    Code:
       0: iconst_0
       1: istore        5
       3: iload_2
       4: ifne          24
       7: aload_0
       8: getfield      #12                 // Field android/support/constraint/a/a/e.ag:I
      11: istore        4
      13: aload_0
      14: getfield      #16                 // Field android/support/constraint/a/a/e.aj:[Landroid/support/constraint/a/a/d;
      17: astore        6
      19: iconst_0
      20: istore_3
      21: goto          38
      24: iconst_2
      25: istore_3
      26: aload_0
      27: getfield      #19                 // Field android/support/constraint/a/a/e.ah:I
      30: istore        4
      32: aload_0
      33: getfield      #22                 // Field android/support/constraint/a/a/e.ai:[Landroid/support/constraint/a/a/d;
      36: astore        6
      38: iload         5
      40: iload         4
      42: if_icmpge     90
      45: aload         6
      47: iload         5
      49: aaload
      50: astore        7
      52: aload_0
      53: iconst_4
      54: invokevirtual #26                 // Method android/support/constraint/a/a/e.q:(I)Z
      57: ifeq          72
      60: aload_0
      61: aload_1
      62: iload_2
      63: iload_3
      64: aload         7
      66: invokestatic  #31                 // Method android/support/constraint/a/a/h.a:(Landroid/support/constraint/a/a/e;Landroid/support/constraint/a/e;IILandroid/support/constraint/a/a/d;)Z
      69: ifne          81
      72: aload_0
      73: aload_1
      74: iload_2
      75: iload_3
      76: aload         7
      78: invokestatic  #34                 // Method a:(Landroid/support/constraint/a/a/e;Landroid/support/constraint/a/e;IILandroid/support/constraint/a/a/d;)V
      81: iload         5
      83: iconst_1
      84: iadd
      85: istore        5
      87: goto          38
      90: return

  static void a(android.support.constraint.a.a.e, android.support.constraint.a.e, int, int, android.support.constraint.a.a.d);
    Code:
       0: aload_0
       1: getfield      #39                 // Field android/support/constraint/a/a/e.A:[Landroid/support/constraint/a/a/d$a;
       4: iload_2
       5: aaload
       6: getstatic     #45                 // Field android/support/constraint/a/a/d$a.b:Landroid/support/constraint/a/a/d$a;
       9: if_acmpne     18
      12: iconst_1
      13: istore        12
      15: goto          21
      18: iconst_0
      19: istore        12
      21: iload_2
      22: ifne          130
      25: aload_0
      26: invokevirtual #49                 // Method android/support/constraint/a/a/e.K:()Z
      29: ifeq          130
      32: aload         4
      34: astore        17
      36: iconst_0
      37: istore        8
      39: aload         17
      41: astore        16
      43: iload         8
      45: ifne          134
      48: aload         17
      50: getfield      #55                 // Field android/support/constraint/a/a/d.y:[Landroid/support/constraint/a/a/c;
      53: iload_3
      54: iconst_1
      55: iadd
      56: aaload
      57: getfield      #61                 // Field android/support/constraint/a/a/c.c:Landroid/support/constraint/a/a/c;
      60: astore        16
      62: aload         16
      64: ifnull        109
      67: aload         16
      69: getfield      #64                 // Field android/support/constraint/a/a/c.a:Landroid/support/constraint/a/a/d;
      72: astore        18
      74: aload         18
      76: getfield      #55                 // Field android/support/constraint/a/a/d.y:[Landroid/support/constraint/a/a/c;
      79: iload_3
      80: aaload
      81: getfield      #61                 // Field android/support/constraint/a/a/c.c:Landroid/support/constraint/a/a/c;
      84: ifnull        109
      87: aload         18
      89: astore        16
      91: aload         18
      93: getfield      #55                 // Field android/support/constraint/a/a/d.y:[Landroid/support/constraint/a/a/c;
      96: iload_3
      97: aaload
      98: getfield      #61                 // Field android/support/constraint/a/a/c.c:Landroid/support/constraint/a/a/c;
     101: getfield      #64                 // Field android/support/constraint/a/a/c.a:Landroid/support/constraint/a/a/d;
     104: aload         17
     106: if_acmpeq     112
     109: aconst_null
     110: astore        16
     112: aload         16
     114: ifnull        124
     117: aload         16
     119: astore        17
     121: goto          39
     124: iconst_1
     125: istore        8
     127: goto          39
     130: aload         4
     132: astore        16
     134: iload_2
     135: ifne          246
     138: aload         16
     140: getfield      #67                 // Field android/support/constraint/a/a/d.S:I
     143: ifne          152
     146: iconst_1
     147: istore        8
     149: goto          155
     152: iconst_0
     153: istore        8
     155: aload         16
     157: getfield      #67                 // Field android/support/constraint/a/a/d.S:I
     160: iconst_1
     161: if_icmpne     170
     164: iconst_1
     165: istore        9
     167: goto          173
     170: iconst_0
     171: istore        9
     173: iload         8
     175: istore        10
     177: iload         9
     179: istore        11
     181: aload         16
     183: getfield      #67                 // Field android/support/constraint/a/a/d.S:I
     186: iconst_2
     187: if_icmpne     204
     190: iconst_1
     191: istore        13
     193: iload         8
     195: istore        10
     197: iload         9
     199: istore        11
     201: goto          207
     204: iconst_0
     205: istore        13
     207: aload         4
     209: astore        20
     211: aconst_null
     212: astore        23
     214: aload         23
     216: astore        19
     218: aload         19
     220: astore        17
     222: aload         17
     224: astore        18
     226: iconst_0
     227: istore        8
     229: iconst_0
     230: istore        9
     232: fconst_0
     233: fstore        5
     235: aload         16
     237: astore        22
     239: aload         20
     241: astore        16
     243: goto          301
     246: aload         16
     248: getfield      #70                 // Field android/support/constraint/a/a/d.T:I
     251: ifne          260
     254: iconst_1
     255: istore        8
     257: goto          263
     260: iconst_0
     261: istore        8
     263: aload         16
     265: getfield      #70                 // Field android/support/constraint/a/a/d.T:I
     268: iconst_1
     269: if_icmpne     278
     272: iconst_1
     273: istore        9
     275: goto          281
     278: iconst_0
     279: istore        9
     281: iload         8
     283: istore        10
     285: iload         9
     287: istore        11
     289: aload         16
     291: getfield      #70                 // Field android/support/constraint/a/a/d.T:I
     294: iconst_2
     295: if_icmpne     204
     298: goto          190
     301: iload         8
     303: ifne          814
     306: aload         16
     308: getfield      #73                 // Field android/support/constraint/a/a/d.Y:[Landroid/support/constraint/a/a/d;
     311: iload_2
     312: aconst_null
     313: aastore
     314: aload         17
     316: astore        21
     318: aload         18
     320: astore        20
     322: aload         16
     324: invokevirtual #77                 // Method android/support/constraint/a/a/d.k:()I
     327: bipush        8
     329: if_icmpeq     363
     332: aload         18
     334: ifnull        346
     337: aload         18
     339: getfield      #73                 // Field android/support/constraint/a/a/d.Y:[Landroid/support/constraint/a/a/d;
     342: iload_2
     343: aload         16
     345: aastore
     346: aload         17
     348: astore        21
     350: aload         17
     352: ifnonnull     359
     355: aload         16
     357: astore        21
     359: aload         16
     361: astore        20
     363: aload         16
     365: getfield      #55                 // Field android/support/constraint/a/a/d.y:[Landroid/support/constraint/a/a/c;
     368: iload_3
     369: aaload
     370: astore        17
     372: aload         17
     374: invokevirtual #80                 // Method android/support/constraint/a/a/c.e:()I
     377: istore        15
     379: aload         17
     381: getfield      #61                 // Field android/support/constraint/a/a/c.c:Landroid/support/constraint/a/a/c;
     384: ifnull        424
     387: aload         16
     389: aload         4
     391: if_acmpeq     424
     394: iload         15
     396: istore        14
     398: aload         16
     400: invokevirtual #77                 // Method android/support/constraint/a/a/d.k:()I
     403: bipush        8
     405: if_icmpeq     428
     408: iload         15
     410: aload         17
     412: getfield      #61                 // Field android/support/constraint/a/a/c.c:Landroid/support/constraint/a/a/c;
     415: invokevirtual #80                 // Method android/support/constraint/a/a/c.e:()I
     418: iadd
     419: istore        14
     421: goto          428
     424: iload         15
     426: istore        14
     428: iload         13
     430: ifeq          454
     433: aload         16
     435: aload         4
     437: if_acmpeq     454
     440: aload         16
     442: aload         21
     444: if_acmpeq     454
     447: bipush        6
     449: istore        15
     451: goto          457
     454: iconst_1
     455: istore        15
     457: aload         16
     459: aload         21
     461: if_acmpne     487
     464: aload_1
     465: aload         17
     467: getfield      #84                 // Field android/support/constraint/a/a/c.f:Landroid/support/constraint/a/h;
     470: aload         17
     472: getfield      #61                 // Field android/support/constraint/a/a/c.c:Landroid/support/constraint/a/a/c;
     475: getfield      #84                 // Field android/support/constraint/a/a/c.f:Landroid/support/constraint/a/h;
     478: iload         14
     480: iconst_5
     481: invokevirtual #89                 // Method android/support/constraint/a/e.a:(Landroid/support/constraint/a/h;Landroid/support/constraint/a/h;II)V
     484: goto          508
     487: aload_1
     488: aload         17
     490: getfield      #84                 // Field android/support/constraint/a/a/c.f:Landroid/support/constraint/a/h;
     493: aload         17
     495: getfield      #61                 // Field android/support/constraint/a/a/c.c:Landroid/support/constraint/a/a/c;
     498: getfield      #84                 // Field android/support/constraint/a/a/c.f:Landroid/support/constraint/a/h;
     501: iload         14
     503: bipush        6
     505: invokevirtual #89                 // Method android/support/constraint/a/e.a:(Landroid/support/constraint/a/h;Landroid/support/constraint/a/h;II)V
     508: aload_1
     509: aload         17
     511: getfield      #84                 // Field android/support/constraint/a/a/c.f:Landroid/support/constraint/a/h;
     514: aload         17
     516: getfield      #61                 // Field android/support/constraint/a/a/c.c:Landroid/support/constraint/a/a/c;
     519: getfield      #84                 // Field android/support/constraint/a/a/c.f:Landroid/support/constraint/a/h;
     522: iload         14
     524: iload         15
     526: invokevirtual #92                 // Method android/support/constraint/a/e.c:(Landroid/support/constraint/a/h;Landroid/support/constraint/a/h;II)Landroid/support/constraint/a/b;
     529: pop
     530: aload         16
     532: getfield      #95                 // Field android/support/constraint/a/a/d.X:[Landroid/support/constraint/a/a/d;
     535: iload_2
     536: aconst_null
     537: aastore
     538: aload         23
     540: astore        24
     542: iload         9
     544: istore        14
     546: aload         19
     548: astore        18
     550: fload         5
     552: fstore        6
     554: aload         16
     556: invokevirtual #77                 // Method android/support/constraint/a/a/d.k:()I
     559: bipush        8
     561: if_icmpeq     674
     564: aload         23
     566: astore        24
     568: iload         9
     570: istore        14
     572: aload         19
     574: astore        18
     576: fload         5
     578: fstore        6
     580: aload         16
     582: getfield      #96                 // Field android/support/constraint/a/a/d.A:[Landroid/support/constraint/a/a/d$a;
     585: iload_2
     586: aaload
     587: getstatic     #98                 // Field android/support/constraint/a/a/d$a.c:Landroid/support/constraint/a/a/d$a;
     590: if_acmpne     674
     593: iload         9
     595: iconst_1
     596: iadd
     597: istore        14
     599: fload         5
     601: aload         16
     603: getfield      #102                // Field android/support/constraint/a/a/d.W:[F
     606: iload_2
     607: faload
     608: fadd
     609: fstore        6
     611: aload         19
     613: ifnonnull     623
     616: aload         16
     618: astore        19
     620: goto          632
     623: aload         23
     625: getfield      #95                 // Field android/support/constraint/a/a/d.X:[Landroid/support/constraint/a/a/d;
     628: iload_2
     629: aload         16
     631: aastore
     632: iload         12
     634: ifeq          666
     637: aload_1
     638: aload         16
     640: getfield      #55                 // Field android/support/constraint/a/a/d.y:[Landroid/support/constraint/a/a/c;
     643: iload_3
     644: iconst_1
     645: iadd
     646: aaload
     647: getfield      #84                 // Field android/support/constraint/a/a/c.f:Landroid/support/constraint/a/h;
     650: aload         16
     652: getfield      #55                 // Field android/support/constraint/a/a/d.y:[Landroid/support/constraint/a/a/c;
     655: iload_3
     656: aaload
     657: getfield      #84                 // Field android/support/constraint/a/a/c.f:Landroid/support/constraint/a/h;
     660: iconst_0
     661: bipush        6
     663: invokevirtual #89                 // Method android/support/constraint/a/e.a:(Landroid/support/constraint/a/h;Landroid/support/constraint/a/h;II)V
     666: aload         16
     668: astore        24
     670: aload         19
     672: astore        18
     674: iload         12
     676: ifeq          708
     679: aload_1
     680: aload         16
     682: getfield      #55                 // Field android/support/constraint/a/a/d.y:[Landroid/support/constraint/a/a/c;
     685: iload_3
     686: aaload
     687: getfield      #84                 // Field android/support/constraint/a/a/c.f:Landroid/support/constraint/a/h;
     690: aload_0
     691: getfield      #103                // Field android/support/constraint/a/a/e.y:[Landroid/support/constraint/a/a/c;
     694: iload_3
     695: aaload
     696: getfield      #84                 // Field android/support/constraint/a/a/c.f:Landroid/support/constraint/a/h;
     699: iconst_0
     700: bipush        6
     702: invokevirtual #89                 // Method android/support/constraint/a/e.a:(Landroid/support/constraint/a/h;Landroid/support/constraint/a/h;II)V
     705: goto          708
     708: aload         16
     710: getfield      #55                 // Field android/support/constraint/a/a/d.y:[Landroid/support/constraint/a/a/c;
     713: iload_3
     714: iconst_1
     715: iadd
     716: aaload
     717: getfield      #61                 // Field android/support/constraint/a/a/c.c:Landroid/support/constraint/a/a/c;
     720: astore        17
     722: aload         17
     724: ifnull        769
     727: aload         17
     729: getfield      #64                 // Field android/support/constraint/a/a/c.a:Landroid/support/constraint/a/a/d;
     732: astore        19
     734: aload         19
     736: getfield      #55                 // Field android/support/constraint/a/a/d.y:[Landroid/support/constraint/a/a/c;
     739: iload_3
     740: aaload
     741: getfield      #61                 // Field android/support/constraint/a/a/c.c:Landroid/support/constraint/a/a/c;
     744: ifnull        769
     747: aload         19
     749: astore        17
     751: aload         19
     753: getfield      #55                 // Field android/support/constraint/a/a/d.y:[Landroid/support/constraint/a/a/c;
     756: iload_3
     757: aaload
     758: getfield      #61                 // Field android/support/constraint/a/a/c.c:Landroid/support/constraint/a/a/c;
     761: getfield      #64                 // Field android/support/constraint/a/a/c.a:Landroid/support/constraint/a/a/d;
     764: aload         16
     766: if_acmpeq     772
     769: aconst_null
     770: astore        17
     772: aload         17
     774: ifnull        784
     777: aload         17
     779: astore        16
     781: goto          787
     784: iconst_1
     785: istore        8
     787: aload         21
     789: astore        17
     791: aload         24
     793: astore        23
     795: iload         14
     797: istore        9
     799: aload         18
     801: astore        19
     803: aload         20
     805: astore        18
     807: fload         6
     809: fstore        5
     811: goto          301
     814: aload         18
     816: ifnull        885
     819: aload         16
     821: getfield      #55                 // Field android/support/constraint/a/a/d.y:[Landroid/support/constraint/a/a/c;
     824: astore        20
     826: iload_3
     827: iconst_1
     828: iadd
     829: istore        8
     831: aload         20
     833: iload         8
     835: aaload
     836: getfield      #61                 // Field android/support/constraint/a/a/c.c:Landroid/support/constraint/a/a/c;
     839: ifnull        885
     842: aload         18
     844: getfield      #55                 // Field android/support/constraint/a/a/d.y:[Landroid/support/constraint/a/a/c;
     847: iload         8
     849: aaload
     850: astore        20
     852: aload_1
     853: aload         20
     855: getfield      #84                 // Field android/support/constraint/a/a/c.f:Landroid/support/constraint/a/h;
     858: aload         16
     860: getfield      #55                 // Field android/support/constraint/a/a/d.y:[Landroid/support/constraint/a/a/c;
     863: iload         8
     865: aaload
     866: getfield      #61                 // Field android/support/constraint/a/a/c.c:Landroid/support/constraint/a/a/c;
     869: getfield      #84                 // Field android/support/constraint/a/a/c.f:Landroid/support/constraint/a/h;
     872: aload         20
     874: invokevirtual #80                 // Method android/support/constraint/a/a/c.e:()I
     877: ineg
     878: iconst_5
     879: invokevirtual #105                // Method android/support/constraint/a/e.b:(Landroid/support/constraint/a/h;Landroid/support/constraint/a/h;II)V
     882: goto          885
     885: iload         12
     887: ifeq          935
     890: aload_0
     891: getfield      #103                // Field android/support/constraint/a/a/e.y:[Landroid/support/constraint/a/a/c;
     894: astore_0
     895: iload_3
     896: iconst_1
     897: iadd
     898: istore        8
     900: aload_1
     901: aload_0
     902: iload         8
     904: aaload
     905: getfield      #84                 // Field android/support/constraint/a/a/c.f:Landroid/support/constraint/a/h;
     908: aload         16
     910: getfield      #55                 // Field android/support/constraint/a/a/d.y:[Landroid/support/constraint/a/a/c;
     913: iload         8
     915: aaload
     916: getfield      #84                 // Field android/support/constraint/a/a/c.f:Landroid/support/constraint/a/h;
     919: aload         16
     921: getfield      #55                 // Field android/support/constraint/a/a/d.y:[Landroid/support/constraint/a/a/c;
     924: iload         8
     926: aaload
     927: invokevirtual #80                 // Method android/support/constraint/a/a/c.e:()I
     930: bipush        6
     932: invokevirtual #89                 // Method android/support/constraint/a/e.a:(Landroid/support/constraint/a/h;Landroid/support/constraint/a/h;II)V
     935: iload         9
     937: ifle          1141
     940: aload         19
     942: ifnull        1141
     945: aload         19
     947: getfield      #95                 // Field android/support/constraint/a/a/d.X:[Landroid/support/constraint/a/a/d;
     950: iload_2
     951: aaload
     952: astore_0
     953: aload_0
     954: ifnull        1135
     957: aload         19
     959: getfield      #102                // Field android/support/constraint/a/a/d.W:[F
     962: iload_2
     963: faload
     964: fstore        6
     966: aload_0
     967: getfield      #102                // Field android/support/constraint/a/a/d.W:[F
     970: iload_2
     971: faload
     972: fstore        7
     974: aload         19
     976: getfield      #55                 // Field android/support/constraint/a/a/d.y:[Landroid/support/constraint/a/a/c;
     979: iload_3
     980: aaload
     981: getfield      #84                 // Field android/support/constraint/a/a/c.f:Landroid/support/constraint/a/h;
     984: astore        20
     986: aload         19
     988: getfield      #55                 // Field android/support/constraint/a/a/d.y:[Landroid/support/constraint/a/a/c;
     991: astore        21
     993: iload_3
     994: iconst_1
     995: iadd
     996: istore        8
     998: aload         21
    1000: iload         8
    1002: aaload
    1003: getfield      #84                 // Field android/support/constraint/a/a/c.f:Landroid/support/constraint/a/h;
    1006: astore        21
    1008: aload_0
    1009: getfield      #55                 // Field android/support/constraint/a/a/d.y:[Landroid/support/constraint/a/a/c;
    1012: iload_3
    1013: aaload
    1014: getfield      #84                 // Field android/support/constraint/a/a/c.f:Landroid/support/constraint/a/h;
    1017: astore        23
    1019: aload_0
    1020: getfield      #55                 // Field android/support/constraint/a/a/d.y:[Landroid/support/constraint/a/a/c;
    1023: iload         8
    1025: aaload
    1026: getfield      #84                 // Field android/support/constraint/a/a/c.f:Landroid/support/constraint/a/h;
    1029: astore        24
    1031: iload_2
    1032: ifne          1051
    1035: aload         19
    1037: getfield      #107                // Field android/support/constraint/a/a/d.e:I
    1040: istore        8
    1042: aload_0
    1043: getfield      #107                // Field android/support/constraint/a/a/d.e:I
    1046: istore        9
    1048: goto          1064
    1051: aload         19
    1053: getfield      #109                // Field android/support/constraint/a/a/d.f:I
    1056: istore        8
    1058: aload_0
    1059: getfield      #109                // Field android/support/constraint/a/a/d.f:I
    1062: istore        9
    1064: iload         8
    1066: ifeq          1075
    1069: iload         8
    1071: iconst_3
    1072: if_icmpne     1089
    1075: iload         9
    1077: ifeq          1095
    1080: iload         9
    1082: iconst_3
    1083: if_icmpne     1089
    1086: goto          1095
    1089: iconst_0
    1090: istore        8
    1092: goto          1098
    1095: iconst_1
    1096: istore        8
    1098: iload         8
    1100: ifeq          1135
    1103: aload_1
    1104: invokevirtual #112                // Method android/support/constraint/a/e.c:()Landroid/support/constraint/a/b;
    1107: astore        19
    1109: aload         19
    1111: fload         6
    1113: fload         5
    1115: fload         7
    1117: aload         20
    1119: aload         21
    1121: aload         23
    1123: aload         24
    1125: invokevirtual #117                // Method android/support/constraint/a/b.a:(FFFLandroid/support/constraint/a/h;Landroid/support/constraint/a/h;Landroid/support/constraint/a/h;Landroid/support/constraint/a/h;)Landroid/support/constraint/a/b;
    1128: pop
    1129: aload_1
    1130: aload         19
    1132: invokevirtual #120                // Method android/support/constraint/a/e.a:(Landroid/support/constraint/a/b;)V
    1135: aload_0
    1136: astore        19
    1138: goto          940
    1141: aload         17
    1143: ifnull        1379
    1146: aload         17
    1148: aload         18
    1150: if_acmpeq     1158
    1153: iload         13
    1155: ifeq          1379
    1158: aload         4
    1160: getfield      #55                 // Field android/support/constraint/a/a/d.y:[Landroid/support/constraint/a/a/c;
    1163: iload_3
    1164: aaload
    1165: astore        20
    1167: aload         16
    1169: getfield      #55                 // Field android/support/constraint/a/a/d.y:[Landroid/support/constraint/a/a/c;
    1172: astore_0
    1173: iload_3
    1174: iconst_1
    1175: iadd
    1176: istore        8
    1178: aload_0
    1179: iload         8
    1181: aaload
    1182: astore        21
    1184: aload         4
    1186: getfield      #55                 // Field android/support/constraint/a/a/d.y:[Landroid/support/constraint/a/a/c;
    1189: iload_3
    1190: aaload
    1191: getfield      #61                 // Field android/support/constraint/a/a/c.c:Landroid/support/constraint/a/a/c;
    1194: ifnull        1215
    1197: aload         4
    1199: getfield      #55                 // Field android/support/constraint/a/a/d.y:[Landroid/support/constraint/a/a/c;
    1202: iload_3
    1203: aaload
    1204: getfield      #61                 // Field android/support/constraint/a/a/c.c:Landroid/support/constraint/a/a/c;
    1207: getfield      #84                 // Field android/support/constraint/a/a/c.f:Landroid/support/constraint/a/h;
    1210: astore        4
    1212: goto          1218
    1215: aconst_null
    1216: astore        4
    1218: aload         16
    1220: getfield      #55                 // Field android/support/constraint/a/a/d.y:[Landroid/support/constraint/a/a/c;
    1223: iload         8
    1225: aaload
    1226: getfield      #61                 // Field android/support/constraint/a/a/c.c:Landroid/support/constraint/a/a/c;
    1229: ifnull        1251
    1232: aload         16
    1234: getfield      #55                 // Field android/support/constraint/a/a/d.y:[Landroid/support/constraint/a/a/c;
    1237: iload         8
    1239: aaload
    1240: getfield      #61                 // Field android/support/constraint/a/a/c.c:Landroid/support/constraint/a/a/c;
    1243: getfield      #84                 // Field android/support/constraint/a/a/c.f:Landroid/support/constraint/a/h;
    1246: astore        19
    1248: goto          1254
    1251: aconst_null
    1252: astore        19
    1254: aload         17
    1256: aload         18
    1258: if_acmpne     1280
    1261: aload         17
    1263: getfield      #55                 // Field android/support/constraint/a/a/d.y:[Landroid/support/constraint/a/a/c;
    1266: iload_3
    1267: aaload
    1268: astore        20
    1270: aload         17
    1272: getfield      #55                 // Field android/support/constraint/a/a/d.y:[Landroid/support/constraint/a/a/c;
    1275: iload         8
    1277: aaload
    1278: astore        21
    1280: aload         4
    1282: ifnull        1367
    1285: aload         19
    1287: ifnull        1367
    1290: iload_2
    1291: ifne          1304
    1294: aload         22
    1296: getfield      #124                // Field android/support/constraint/a/a/d.O:F
    1299: fstore        5
    1301: goto          1311
    1304: aload         22
    1306: getfield      #127                // Field android/support/constraint/a/a/d.P:F
    1309: fstore        5
    1311: aload         20
    1313: invokevirtual #80                 // Method android/support/constraint/a/a/c.e:()I
    1316: istore_2
    1317: aload         18
    1319: astore_0
    1320: aload         18
    1322: ifnonnull     1328
    1325: aload         16
    1327: astore_0
    1328: aload_0
    1329: getfield      #55                 // Field android/support/constraint/a/a/d.y:[Landroid/support/constraint/a/a/c;
    1332: iload         8
    1334: aaload
    1335: invokevirtual #80                 // Method android/support/constraint/a/a/c.e:()I
    1338: istore        8
    1340: aload_1
    1341: aload         20
    1343: getfield      #84                 // Field android/support/constraint/a/a/c.f:Landroid/support/constraint/a/h;
    1346: aload         4
    1348: iload_2
    1349: fload         5
    1351: aload         19
    1353: aload         21
    1355: getfield      #84                 // Field android/support/constraint/a/a/c.f:Landroid/support/constraint/a/h;
    1358: iload         8
    1360: iconst_5
    1361: invokevirtual #130                // Method android/support/constraint/a/e.a:(Landroid/support/constraint/a/h;Landroid/support/constraint/a/h;IFLandroid/support/constraint/a/h;Landroid/support/constraint/a/h;II)V
    1364: goto          1370
    1367: aload         18
    1369: astore_0
    1370: aload_0
    1371: astore        19
    1373: aload         17
    1375: astore_0
    1376: goto          2376
    1379: iload         10
    1381: ifeq          1839
    1384: aload         17
    1386: ifnull        1839
    1389: aload         17
    1391: astore_0
    1392: aload_0
    1393: astore        20
    1395: aload         17
    1397: astore        19
    1399: aload         20
    1401: astore        17
    1403: aload_0
    1404: astore        22
    1406: aload         17
    1408: ifnull        1829
    1411: aload         17
    1413: getfield      #73                 // Field android/support/constraint/a/a/d.Y:[Landroid/support/constraint/a/a/d;
    1416: iload_2
    1417: aaload
    1418: astore        21
    1420: aload         21
    1422: ifnonnull     1441
    1425: aload         17
    1427: aload         18
    1429: if_acmpne     1435
    1432: goto          1441
    1435: aload         21
    1437: astore_0
    1438: goto          1819
    1441: aload         17
    1443: getfield      #55                 // Field android/support/constraint/a/a/d.y:[Landroid/support/constraint/a/a/c;
    1446: iload_3
    1447: aaload
    1448: astore        23
    1450: aload         23
    1452: getfield      #84                 // Field android/support/constraint/a/a/c.f:Landroid/support/constraint/a/h;
    1455: astore        26
    1457: aload         23
    1459: getfield      #61                 // Field android/support/constraint/a/a/c.c:Landroid/support/constraint/a/a/c;
    1462: ifnull        1478
    1465: aload         23
    1467: getfield      #61                 // Field android/support/constraint/a/a/c.c:Landroid/support/constraint/a/a/c;
    1470: getfield      #84                 // Field android/support/constraint/a/a/c.f:Landroid/support/constraint/a/h;
    1473: astore        20
    1475: goto          1481
    1478: aconst_null
    1479: astore        20
    1481: aload         22
    1483: aload         17
    1485: if_acmpeq     1506
    1488: aload         22
    1490: getfield      #55                 // Field android/support/constraint/a/a/d.y:[Landroid/support/constraint/a/a/c;
    1493: iload_3
    1494: iconst_1
    1495: iadd
    1496: aaload
    1497: astore_0
    1498: aload_0
    1499: getfield      #84                 // Field android/support/constraint/a/a/c.f:Landroid/support/constraint/a/h;
    1502: astore_0
    1503: goto          1555
    1506: aload         20
    1508: astore_0
    1509: aload         17
    1511: aload         19
    1513: if_acmpne     1555
    1516: aload         20
    1518: astore_0
    1519: aload         22
    1521: aload         17
    1523: if_acmpne     1555
    1526: aload         4
    1528: getfield      #55                 // Field android/support/constraint/a/a/d.y:[Landroid/support/constraint/a/a/c;
    1531: iload_3
    1532: aaload
    1533: getfield      #61                 // Field android/support/constraint/a/a/c.c:Landroid/support/constraint/a/a/c;
    1536: ifnull        1553
    1539: aload         4
    1541: getfield      #55                 // Field android/support/constraint/a/a/d.y:[Landroid/support/constraint/a/a/c;
    1544: iload_3
    1545: aaload
    1546: getfield      #61                 // Field android/support/constraint/a/a/c.c:Landroid/support/constraint/a/a/c;
    1549: astore_0
    1550: goto          1498
    1553: aconst_null
    1554: astore_0
    1555: aload         23
    1557: invokevirtual #80                 // Method android/support/constraint/a/a/c.e:()I
    1560: istore        12
    1562: aload         17
    1564: getfield      #55                 // Field android/support/constraint/a/a/d.y:[Landroid/support/constraint/a/a/c;
    1567: astore        20
    1569: iload_3
    1570: iconst_1
    1571: iadd
    1572: istore        13
    1574: aload         20
    1576: iload         13
    1578: aaload
    1579: invokevirtual #80                 // Method android/support/constraint/a/a/c.e:()I
    1582: istore        9
    1584: aload         21
    1586: ifnull        1632
    1589: aload         21
    1591: getfield      #55                 // Field android/support/constraint/a/a/d.y:[Landroid/support/constraint/a/a/c;
    1594: iload_3
    1595: aaload
    1596: astore        24
    1598: aload         24
    1600: getfield      #84                 // Field android/support/constraint/a/a/c.f:Landroid/support/constraint/a/h;
    1603: astore        23
    1605: aload         24
    1607: getfield      #61                 // Field android/support/constraint/a/a/c.c:Landroid/support/constraint/a/a/c;
    1610: ifnull        1626
    1613: aload         24
    1615: getfield      #61                 // Field android/support/constraint/a/a/c.c:Landroid/support/constraint/a/a/c;
    1618: getfield      #84                 // Field android/support/constraint/a/a/c.f:Landroid/support/constraint/a/h;
    1621: astore        20
    1623: goto          1684
    1626: aconst_null
    1627: astore        20
    1629: goto          1684
    1632: aload         16
    1634: getfield      #55                 // Field android/support/constraint/a/a/d.y:[Landroid/support/constraint/a/a/c;
    1637: iload         13
    1639: aaload
    1640: getfield      #61                 // Field android/support/constraint/a/a/c.c:Landroid/support/constraint/a/a/c;
    1643: astore        24
    1645: aload         24
    1647: ifnull        1660
    1650: aload         24
    1652: getfield      #84                 // Field android/support/constraint/a/a/c.f:Landroid/support/constraint/a/h;
    1655: astore        20
    1657: goto          1663
    1660: aconst_null
    1661: astore        20
    1663: aload         17
    1665: getfield      #55                 // Field android/support/constraint/a/a/d.y:[Landroid/support/constraint/a/a/c;
    1668: iload         13
    1670: aaload
    1671: getfield      #84                 // Field android/support/constraint/a/a/c.f:Landroid/support/constraint/a/h;
    1674: astore        25
    1676: aload         20
    1678: astore        23
    1680: aload         25
    1682: astore        20
    1684: iload         9
    1686: istore        8
    1688: aload         24
    1690: ifnull        1703
    1693: iload         9
    1695: aload         24
    1697: invokevirtual #80                 // Method android/support/constraint/a/a/c.e:()I
    1700: iadd
    1701: istore        8
    1703: iload         12
    1705: istore        9
    1707: aload         22
    1709: ifnull        1728
    1712: iload         12
    1714: aload         22
    1716: getfield      #55                 // Field android/support/constraint/a/a/d.y:[Landroid/support/constraint/a/a/c;
    1719: iload         13
    1721: aaload
    1722: invokevirtual #80                 // Method android/support/constraint/a/a/c.e:()I
    1725: iadd
    1726: istore        9
    1728: aload         26
    1730: ifnull        1816
    1733: aload_0
    1734: ifnull        1816
    1737: aload         23
    1739: ifnull        1816
    1742: aload         20
    1744: ifnull        1816
    1747: aload         17
    1749: aload         19
    1751: if_acmpne     1769
    1754: aload         19
    1756: getfield      #55                 // Field android/support/constraint/a/a/d.y:[Landroid/support/constraint/a/a/c;
    1759: iload_3
    1760: aaload
    1761: invokevirtual #80                 // Method android/support/constraint/a/a/c.e:()I
    1764: istore        9
    1766: goto          1769
    1769: aload         17
    1771: aload         18
    1773: if_acmpne     1792
    1776: aload         18
    1778: getfield      #55                 // Field android/support/constraint/a/a/d.y:[Landroid/support/constraint/a/a/c;
    1781: iload         13
    1783: aaload
    1784: invokevirtual #80                 // Method android/support/constraint/a/a/c.e:()I
    1787: istore        8
    1789: goto          1792
    1792: aload_1
    1793: aload         26
    1795: aload_0
    1796: iload         9
    1798: ldc           #131                // float 0.5f
    1800: aload         23
    1802: aload         20
    1804: iload         8
    1806: iconst_4
    1807: invokevirtual #130                // Method android/support/constraint/a/e.a:(Landroid/support/constraint/a/h;Landroid/support/constraint/a/h;IFLandroid/support/constraint/a/h;Landroid/support/constraint/a/h;II)V
    1810: aload         21
    1812: astore_0
    1813: goto          1819
    1816: aload         21
    1818: astore_0
    1819: aload         17
    1821: astore        22
    1823: aload_0
    1824: astore        17
    1826: goto          1406
    1829: aload         19
    1831: astore_0
    1832: aload         18
    1834: astore        19
    1836: goto          1376
    1839: aload         17
    1841: astore_0
    1842: aload         18
    1844: astore        19
    1846: iload         11
    1848: ifeq          1376
    1851: aload         17
    1853: astore_0
    1854: aload         18
    1856: astore        19
    1858: aload         17
    1860: ifnull        1376
    1863: aload         17
    1865: astore_0
    1866: aload_0
    1867: astore        19
    1869: aload_0
    1870: astore        21
    1872: aload         19
    1874: astore        20
    1876: aload         20
    1878: ifnull        2195
    1881: aload         20
    1883: getfield      #73                 // Field android/support/constraint/a/a/d.Y:[Landroid/support/constraint/a/a/d;
    1886: iload_2
    1887: aaload
    1888: astore_0
    1889: aload         20
    1891: aload         17
    1893: if_acmpeq     2185
    1896: aload         20
    1898: aload         18
    1900: if_acmpeq     2185
    1903: aload_0
    1904: ifnull        2185
    1907: aload_0
    1908: aload         18
    1910: if_acmpne     1918
    1913: aconst_null
    1914: astore_0
    1915: goto          1918
    1918: aload         20
    1920: getfield      #55                 // Field android/support/constraint/a/a/d.y:[Landroid/support/constraint/a/a/c;
    1923: iload_3
    1924: aaload
    1925: astore        19
    1927: aload         19
    1929: getfield      #84                 // Field android/support/constraint/a/a/c.f:Landroid/support/constraint/a/h;
    1932: astore        25
    1934: aload         19
    1936: getfield      #61                 // Field android/support/constraint/a/a/c.c:Landroid/support/constraint/a/a/c;
    1939: ifnull        1952
    1942: aload         19
    1944: getfield      #61                 // Field android/support/constraint/a/a/c.c:Landroid/support/constraint/a/a/c;
    1947: getfield      #84                 // Field android/support/constraint/a/a/c.f:Landroid/support/constraint/a/h;
    1950: astore        22
    1952: aload         21
    1954: getfield      #55                 // Field android/support/constraint/a/a/d.y:[Landroid/support/constraint/a/a/c;
    1957: astore        22
    1959: iload_3
    1960: iconst_1
    1961: iadd
    1962: istore        13
    1964: aload         22
    1966: iload         13
    1968: aaload
    1969: getfield      #84                 // Field android/support/constraint/a/a/c.f:Landroid/support/constraint/a/h;
    1972: astore        26
    1974: aload         19
    1976: invokevirtual #80                 // Method android/support/constraint/a/a/c.e:()I
    1979: istore        12
    1981: aload         20
    1983: getfield      #55                 // Field android/support/constraint/a/a/d.y:[Landroid/support/constraint/a/a/c;
    1986: iload         13
    1988: aaload
    1989: invokevirtual #80                 // Method android/support/constraint/a/a/c.e:()I
    1992: istore        9
    1994: aload_0
    1995: ifnull        2040
    1998: aload_0
    1999: getfield      #55                 // Field android/support/constraint/a/a/d.y:[Landroid/support/constraint/a/a/c;
    2002: iload_3
    2003: aaload
    2004: astore        22
    2006: aload         22
    2008: getfield      #84                 // Field android/support/constraint/a/a/c.f:Landroid/support/constraint/a/h;
    2011: astore        23
    2013: aload         22
    2015: getfield      #61                 // Field android/support/constraint/a/a/c.c:Landroid/support/constraint/a/a/c;
    2018: ifnull        2034
    2021: aload         22
    2023: getfield      #61                 // Field android/support/constraint/a/a/c.c:Landroid/support/constraint/a/a/c;
    2026: getfield      #84                 // Field android/support/constraint/a/a/c.f:Landroid/support/constraint/a/h;
    2029: astore        19
    2031: goto          2096
    2034: aconst_null
    2035: astore        19
    2037: goto          2096
    2040: aload         20
    2042: getfield      #55                 // Field android/support/constraint/a/a/d.y:[Landroid/support/constraint/a/a/c;
    2045: iload         13
    2047: aaload
    2048: getfield      #61                 // Field android/support/constraint/a/a/c.c:Landroid/support/constraint/a/a/c;
    2051: astore        24
    2053: aload         24
    2055: ifnull        2068
    2058: aload         24
    2060: getfield      #84                 // Field android/support/constraint/a/a/c.f:Landroid/support/constraint/a/h;
    2063: astore        19
    2065: goto          2071
    2068: aconst_null
    2069: astore        19
    2071: aload         20
    2073: getfield      #55                 // Field android/support/constraint/a/a/d.y:[Landroid/support/constraint/a/a/c;
    2076: iload         13
    2078: aaload
    2079: getfield      #84                 // Field android/support/constraint/a/a/c.f:Landroid/support/constraint/a/h;
    2082: astore        22
    2084: aload         19
    2086: astore        23
    2088: aload         22
    2090: astore        19
    2092: aload         24
    2094: astore        22
    2096: iload         9
    2098: istore        8
    2100: aload         22
    2102: ifnull        2115
    2105: iload         9
    2107: aload         22
    2109: invokevirtual #80                 // Method android/support/constraint/a/a/c.e:()I
    2112: iadd
    2113: istore        8
    2115: iload         12
    2117: istore        9
    2119: aload         21
    2121: ifnull        2140
    2124: iload         12
    2126: aload         21
    2128: getfield      #55                 // Field android/support/constraint/a/a/d.y:[Landroid/support/constraint/a/a/c;
    2131: iload         13
    2133: aaload
    2134: invokevirtual #80                 // Method android/support/constraint/a/a/c.e:()I
    2137: iadd
    2138: istore        9
    2140: aload         25
    2142: ifnull        2182
    2145: aload         26
    2147: ifnull        2182
    2150: aload         23
    2152: ifnull        2182
    2155: aload         19
    2157: ifnull        2182
    2160: aload_1
    2161: aload         25
    2163: aload         26
    2165: iload         9
    2167: ldc           #131                // float 0.5f
    2169: aload         23
    2171: aload         19
    2173: iload         8
    2175: iconst_4
    2176: invokevirtual #130                // Method android/support/constraint/a/e.a:(Landroid/support/constraint/a/h;Landroid/support/constraint/a/h;IFLandroid/support/constraint/a/h;Landroid/support/constraint/a/h;II)V
    2179: goto          2182
    2182: goto          2185
    2185: aload         20
    2187: astore        21
    2189: aload_0
    2190: astore        19
    2192: goto          1872
    2195: aload         17
    2197: getfield      #55                 // Field android/support/constraint/a/a/d.y:[Landroid/support/constraint/a/a/c;
    2200: iload_3
    2201: aaload
    2202: astore_0
    2203: aload         4
    2205: getfield      #55                 // Field android/support/constraint/a/a/d.y:[Landroid/support/constraint/a/a/c;
    2208: iload_3
    2209: aaload
    2210: getfield      #61                 // Field android/support/constraint/a/a/c.c:Landroid/support/constraint/a/a/c;
    2213: astore        19
    2215: aload         18
    2217: getfield      #55                 // Field android/support/constraint/a/a/d.y:[Landroid/support/constraint/a/a/c;
    2220: astore        4
    2222: iload_3
    2223: iconst_1
    2224: iadd
    2225: istore_2
    2226: aload         4
    2228: iload_2
    2229: aaload
    2230: astore        4
    2232: aload         16
    2234: getfield      #55                 // Field android/support/constraint/a/a/d.y:[Landroid/support/constraint/a/a/c;
    2237: iload_2
    2238: aaload
    2239: getfield      #61                 // Field android/support/constraint/a/a/c.c:Landroid/support/constraint/a/a/c;
    2242: astore        20
    2244: aload         19
    2246: ifnull        2321
    2249: aload         17
    2251: aload         18
    2253: if_acmpeq     2278
    2256: aload_1
    2257: aload_0
    2258: getfield      #84                 // Field android/support/constraint/a/a/c.f:Landroid/support/constraint/a/h;
    2261: aload         19
    2263: getfield      #84                 // Field android/support/constraint/a/a/c.f:Landroid/support/constraint/a/h;
    2266: aload_0
    2267: invokevirtual #80                 // Method android/support/constraint/a/a/c.e:()I
    2270: iconst_5
    2271: invokevirtual #92                 // Method android/support/constraint/a/e.c:(Landroid/support/constraint/a/h;Landroid/support/constraint/a/h;II)Landroid/support/constraint/a/b;
    2274: pop
    2275: goto          2321
    2278: aload         20
    2280: ifnull        2321
    2283: aload_1
    2284: aload_0
    2285: getfield      #84                 // Field android/support/constraint/a/a/c.f:Landroid/support/constraint/a/h;
    2288: aload         19
    2290: getfield      #84                 // Field android/support/constraint/a/a/c.f:Landroid/support/constraint/a/h;
    2293: aload_0
    2294: invokevirtual #80                 // Method android/support/constraint/a/a/c.e:()I
    2297: ldc           #131                // float 0.5f
    2299: aload         4
    2301: getfield      #84                 // Field android/support/constraint/a/a/c.f:Landroid/support/constraint/a/h;
    2304: aload         20
    2306: getfield      #84                 // Field android/support/constraint/a/a/c.f:Landroid/support/constraint/a/h;
    2309: aload         4
    2311: invokevirtual #80                 // Method android/support/constraint/a/a/c.e:()I
    2314: iconst_5
    2315: invokevirtual #130                // Method android/support/constraint/a/e.a:(Landroid/support/constraint/a/h;Landroid/support/constraint/a/h;IFLandroid/support/constraint/a/h;Landroid/support/constraint/a/h;II)V
    2318: goto          2321
    2321: aload         17
    2323: astore_0
    2324: aload         18
    2326: astore        19
    2328: aload         20
    2330: ifnull        2376
    2333: aload         17
    2335: astore_0
    2336: aload         18
    2338: astore        19
    2340: aload         17
    2342: aload         18
    2344: if_acmpeq     2376
    2347: aload_1
    2348: aload         4
    2350: getfield      #84                 // Field android/support/constraint/a/a/c.f:Landroid/support/constraint/a/h;
    2353: aload         20
    2355: getfield      #84                 // Field android/support/constraint/a/a/c.f:Landroid/support/constraint/a/h;
    2358: aload         4
    2360: invokevirtual #80                 // Method android/support/constraint/a/a/c.e:()I
    2363: ineg
    2364: iconst_5
    2365: invokevirtual #92                 // Method android/support/constraint/a/e.c:(Landroid/support/constraint/a/h;Landroid/support/constraint/a/h;II)Landroid/support/constraint/a/b;
    2368: pop
    2369: aload         18
    2371: astore        19
    2373: aload         17
    2375: astore_0
    2376: iload         10
    2378: ifne          2386
    2381: iload         11
    2383: ifeq          2545
    2386: aload_0
    2387: ifnull        2545
    2390: aload_0
    2391: getfield      #55                 // Field android/support/constraint/a/a/d.y:[Landroid/support/constraint/a/a/c;
    2394: iload_3
    2395: aaload
    2396: astore        18
    2398: aload         19
    2400: getfield      #55                 // Field android/support/constraint/a/a/d.y:[Landroid/support/constraint/a/a/c;
    2403: astore        4
    2405: iload_3
    2406: iconst_1
    2407: iadd
    2408: istore_2
    2409: aload         4
    2411: iload_2
    2412: aaload
    2413: astore        20
    2415: aload         18
    2417: getfield      #61                 // Field android/support/constraint/a/a/c.c:Landroid/support/constraint/a/a/c;
    2420: ifnull        2436
    2423: aload         18
    2425: getfield      #61                 // Field android/support/constraint/a/a/c.c:Landroid/support/constraint/a/a/c;
    2428: getfield      #84                 // Field android/support/constraint/a/a/c.f:Landroid/support/constraint/a/h;
    2431: astore        4
    2433: goto          2439
    2436: aconst_null
    2437: astore        4
    2439: aload         20
    2441: getfield      #61                 // Field android/support/constraint/a/a/c.c:Landroid/support/constraint/a/a/c;
    2444: ifnull        2460
    2447: aload         20
    2449: getfield      #61                 // Field android/support/constraint/a/a/c.c:Landroid/support/constraint/a/a/c;
    2452: getfield      #84                 // Field android/support/constraint/a/a/c.f:Landroid/support/constraint/a/h;
    2455: astore        17
    2457: goto          2463
    2460: aconst_null
    2461: astore        17
    2463: aload_0
    2464: aload         19
    2466: if_acmpne     2485
    2469: aload_0
    2470: getfield      #55                 // Field android/support/constraint/a/a/d.y:[Landroid/support/constraint/a/a/c;
    2473: iload_3
    2474: aaload
    2475: astore        18
    2477: aload_0
    2478: getfield      #55                 // Field android/support/constraint/a/a/d.y:[Landroid/support/constraint/a/a/c;
    2481: iload_2
    2482: aaload
    2483: astore        20
    2485: aload         4
    2487: ifnull        2545
    2490: aload         17
    2492: ifnull        2545
    2495: aload         18
    2497: invokevirtual #80                 // Method android/support/constraint/a/a/c.e:()I
    2500: istore_3
    2501: aload         19
    2503: astore_0
    2504: aload         19
    2506: ifnonnull     2512
    2509: aload         16
    2511: astore_0
    2512: aload_0
    2513: getfield      #55                 // Field android/support/constraint/a/a/d.y:[Landroid/support/constraint/a/a/c;
    2516: iload_2
    2517: aaload
    2518: invokevirtual #80                 // Method android/support/constraint/a/a/c.e:()I
    2521: istore_2
    2522: aload_1
    2523: aload         18
    2525: getfield      #84                 // Field android/support/constraint/a/a/c.f:Landroid/support/constraint/a/h;
    2528: aload         4
    2530: iload_3
    2531: ldc           #131                // float 0.5f
    2533: aload         17
    2535: aload         20
    2537: getfield      #84                 // Field android/support/constraint/a/a/c.f:Landroid/support/constraint/a/h;
    2540: iload_2
    2541: iconst_5
    2542: invokevirtual #130                // Method android/support/constraint/a/e.a:(Landroid/support/constraint/a/h;Landroid/support/constraint/a/h;IFLandroid/support/constraint/a/h;Landroid/support/constraint/a/h;II)V
    2545: return
}
