public final class android.support.constraint.a.a.c$c extends java.lang.Enum<android.support.constraint.a.a.c$c> {
  public static final android.support.constraint.a.a.c$c a;

  public static final android.support.constraint.a.a.c$c b;

  public static final android.support.constraint.a.a.c$c c;

  public static final android.support.constraint.a.a.c$c d;

  public static final android.support.constraint.a.a.c$c e;

  public static final android.support.constraint.a.a.c$c f;

  public static final android.support.constraint.a.a.c$c g;

  public static final android.support.constraint.a.a.c$c h;

  public static final android.support.constraint.a.a.c$c i;

  static {};
    Code:
       0: new           #2                  // class android/support/constraint/a/a/c$c
       3: dup
       4: ldc           #23                 // String NONE
       6: iconst_0
       7: invokespecial #27                 // Method "<init>":(Ljava/lang/String;I)V
      10: putstatic     #29                 // Field a:Landroid/support/constraint/a/a/c$c;
      13: new           #2                  // class android/support/constraint/a/a/c$c
      16: dup
      17: ldc           #31                 // String LEFT
      19: iconst_1
      20: invokespecial #27                 // Method "<init>":(Ljava/lang/String;I)V
      23: putstatic     #33                 // Field b:Landroid/support/constraint/a/a/c$c;
      26: new           #2                  // class android/support/constraint/a/a/c$c
      29: dup
      30: ldc           #35                 // String TOP
      32: iconst_2
      33: invokespecial #27                 // Method "<init>":(Ljava/lang/String;I)V
      36: putstatic     #37                 // Field c:Landroid/support/constraint/a/a/c$c;
      39: new           #2                  // class android/support/constraint/a/a/c$c
      42: dup
      43: ldc           #39                 // String RIGHT
      45: iconst_3
      46: invokespecial #27                 // Method "<init>":(Ljava/lang/String;I)V
      49: putstatic     #41                 // Field d:Landroid/support/constraint/a/a/c$c;
      52: new           #2                  // class android/support/constraint/a/a/c$c
      55: dup
      56: ldc           #43                 // String BOTTOM
      58: iconst_4
      59: invokespecial #27                 // Method "<init>":(Ljava/lang/String;I)V
      62: putstatic     #45                 // Field e:Landroid/support/constraint/a/a/c$c;
      65: new           #2                  // class android/support/constraint/a/a/c$c
      68: dup
      69: ldc           #47                 // String BASELINE
      71: iconst_5
      72: invokespecial #27                 // Method "<init>":(Ljava/lang/String;I)V
      75: putstatic     #49                 // Field f:Landroid/support/constraint/a/a/c$c;
      78: new           #2                  // class android/support/constraint/a/a/c$c
      81: dup
      82: ldc           #51                 // String CENTER
      84: bipush        6
      86: invokespecial #27                 // Method "<init>":(Ljava/lang/String;I)V
      89: putstatic     #53                 // Field g:Landroid/support/constraint/a/a/c$c;
      92: new           #2                  // class android/support/constraint/a/a/c$c
      95: dup
      96: ldc           #55                 // String CENTER_X
      98: bipush        7
     100: invokespecial #27                 // Method "<init>":(Ljava/lang/String;I)V
     103: putstatic     #57                 // Field h:Landroid/support/constraint/a/a/c$c;
     106: new           #2                  // class android/support/constraint/a/a/c$c
     109: dup
     110: ldc           #59                 // String CENTER_Y
     112: bipush        8
     114: invokespecial #27                 // Method "<init>":(Ljava/lang/String;I)V
     117: putstatic     #61                 // Field i:Landroid/support/constraint/a/a/c$c;
     120: bipush        9
     122: anewarray     #2                  // class android/support/constraint/a/a/c$c
     125: dup
     126: iconst_0
     127: getstatic     #29                 // Field a:Landroid/support/constraint/a/a/c$c;
     130: aastore
     131: dup
     132: iconst_1
     133: getstatic     #33                 // Field b:Landroid/support/constraint/a/a/c$c;
     136: aastore
     137: dup
     138: iconst_2
     139: getstatic     #37                 // Field c:Landroid/support/constraint/a/a/c$c;
     142: aastore
     143: dup
     144: iconst_3
     145: getstatic     #41                 // Field d:Landroid/support/constraint/a/a/c$c;
     148: aastore
     149: dup
     150: iconst_4
     151: getstatic     #45                 // Field e:Landroid/support/constraint/a/a/c$c;
     154: aastore
     155: dup
     156: iconst_5
     157: getstatic     #49                 // Field f:Landroid/support/constraint/a/a/c$c;
     160: aastore
     161: dup
     162: bipush        6
     164: getstatic     #53                 // Field g:Landroid/support/constraint/a/a/c$c;
     167: aastore
     168: dup
     169: bipush        7
     171: getstatic     #57                 // Field h:Landroid/support/constraint/a/a/c$c;
     174: aastore
     175: dup
     176: bipush        8
     178: getstatic     #61                 // Field i:Landroid/support/constraint/a/a/c$c;
     181: aastore
     182: putstatic     #63                 // Field j:[Landroid/support/constraint/a/a/c$c;
     185: return

  public static android.support.constraint.a.a.c$c valueOf(java.lang.String);
    Code:
       0: ldc           #2                  // class android/support/constraint/a/a/c$c
       2: aload_0
       3: invokestatic  #71                 // Method java/lang/Enum.valueOf:(Ljava/lang/Class;Ljava/lang/String;)Ljava/lang/Enum;
       6: checkcast     #2                  // class android/support/constraint/a/a/c$c
       9: areturn

  public static android.support.constraint.a.a.c$c[] values();
    Code:
       0: getstatic     #63                 // Field j:[Landroid/support/constraint/a/a/c$c;
       3: invokevirtual #78                 // Method "[Landroid/support/constraint/a/a/c$c;".clone:()Ljava/lang/Object;
       6: checkcast     #74                 // class "[Landroid/support/constraint/a/a/c$c;"
       9: areturn
}
