public class android.support.constraint.a.a.c {
  final android.support.constraint.a.a.d a;

  final android.support.constraint.a.a.c$c b;

  android.support.constraint.a.a.c c;

  public int d;

  int e;

  android.support.constraint.a.h f;

  public android.support.constraint.a.a.c(android.support.constraint.a.a.d, android.support.constraint.a.a.c$c);
    Code:
       0: aload_0
       1: invokespecial #35                 // Method java/lang/Object."<init>":()V
       4: aload_0
       5: new           #37                 // class android/support/constraint/a/a/j
       8: dup
       9: aload_0
      10: invokespecial #40                 // Method android/support/constraint/a/a/j."<init>":(Landroid/support/constraint/a/a/c;)V
      13: putfield      #42                 // Field g:Landroid/support/constraint/a/a/j;
      16: aload_0
      17: iconst_0
      18: putfield      #44                 // Field d:I
      21: aload_0
      22: iconst_m1
      23: putfield      #46                 // Field e:I
      26: aload_0
      27: getstatic     #48                 // Field android/support/constraint/a/a/c$b.a:Landroid/support/constraint/a/a/c$b;
      30: putfield      #50                 // Field h:Landroid/support/constraint/a/a/c$b;
      33: aload_0
      34: getstatic     #52                 // Field android/support/constraint/a/a/c$a.a:Landroid/support/constraint/a/a/c$a;
      37: putfield      #54                 // Field i:Landroid/support/constraint/a/a/c$a;
      40: aload_0
      41: iconst_0
      42: putfield      #56                 // Field j:I
      45: aload_0
      46: aload_1
      47: putfield      #58                 // Field a:Landroid/support/constraint/a/a/d;
      50: aload_0
      51: aload_2
      52: putfield      #60                 // Field b:Landroid/support/constraint/a/a/c$c;
      55: return

  public android.support.constraint.a.a.j a();
    Code:
       0: aload_0
       1: getfield      #42                 // Field g:Landroid/support/constraint/a/a/j;
       4: areturn

  public void a(android.support.constraint.a.c);
    Code:
       0: aload_0
       1: getfield      #65                 // Field f:Landroid/support/constraint/a/h;
       4: ifnonnull     23
       7: aload_0
       8: new           #67                 // class android/support/constraint/a/h
      11: dup
      12: getstatic     #72                 // Field android/support/constraint/a/h$a.a:Landroid/support/constraint/a/h$a;
      15: aconst_null
      16: invokespecial #75                 // Method android/support/constraint/a/h."<init>":(Landroid/support/constraint/a/h$a;Ljava/lang/String;)V
      19: putfield      #65                 // Field f:Landroid/support/constraint/a/h;
      22: return
      23: aload_0
      24: getfield      #65                 // Field f:Landroid/support/constraint/a/h;
      27: invokevirtual #77                 // Method android/support/constraint/a/h.b:()V
      30: return

  public boolean a(android.support.constraint.a.a.c);
    Code:
       0: iconst_0
       1: istore_3
       2: aload_1
       3: ifnonnull     8
       6: iconst_0
       7: ireturn
       8: aload_1
       9: invokevirtual #81                 // Method d:()Landroid/support/constraint/a/a/c$c;
      12: astore        4
      14: aload         4
      16: aload_0
      17: getfield      #60                 // Field b:Landroid/support/constraint/a/a/c$c;
      20: if_acmpne     57
      23: aload_0
      24: getfield      #60                 // Field b:Landroid/support/constraint/a/a/c$c;
      27: getstatic     #83                 // Field android/support/constraint/a/a/c$c.f:Landroid/support/constraint/a/a/c$c;
      30: if_acmpne     55
      33: aload_1
      34: invokevirtual #86                 // Method c:()Landroid/support/constraint/a/a/d;
      37: invokevirtual #92                 // Method android/support/constraint/a/a/d.z:()Z
      40: ifeq          53
      43: aload_0
      44: invokevirtual #86                 // Method c:()Landroid/support/constraint/a/a/d;
      47: invokevirtual #92                 // Method android/support/constraint/a/a/d.z:()Z
      50: ifne          55
      53: iconst_0
      54: ireturn
      55: iconst_1
      56: ireturn
      57: getstatic     #95                 // Field android/support/constraint/a/a/c$1.a:[I
      60: aload_0
      61: getfield      #60                 // Field b:Landroid/support/constraint/a/a/c$c;
      64: invokevirtual #99                 // Method android/support/constraint/a/a/c$c.ordinal:()I
      67: iaload
      68: tableswitch   { // 1 to 9
                     1: 255
                     2: 196
                     3: 196
                     4: 137
                     5: 137
                     6: 135
                     7: 135
                     8: 135
                     9: 135
               default: 120
          }
     120: new           #101                // class java/lang/AssertionError
     123: dup
     124: aload_0
     125: getfield      #60                 // Field b:Landroid/support/constraint/a/a/c$c;
     128: invokevirtual #105                // Method android/support/constraint/a/a/c$c.name:()Ljava/lang/String;
     131: invokespecial #108                // Method java/lang/AssertionError."<init>":(Ljava/lang/Object;)V
     134: athrow
     135: iconst_0
     136: ireturn
     137: aload         4
     139: getstatic     #110                // Field android/support/constraint/a/a/c$c.c:Landroid/support/constraint/a/a/c$c;
     142: if_acmpeq     161
     145: aload         4
     147: getstatic     #112                // Field android/support/constraint/a/a/c$c.e:Landroid/support/constraint/a/a/c$c;
     150: if_acmpne     156
     153: goto          161
     156: iconst_0
     157: istore_2
     158: goto          163
     161: iconst_1
     162: istore_2
     163: iload_2
     164: istore_3
     165: aload_1
     166: invokevirtual #86                 // Method c:()Landroid/support/constraint/a/a/d;
     169: instanceof    #114                // class android/support/constraint/a/a/f
     172: ifeq          194
     175: iload_2
     176: ifne          192
     179: aload         4
     181: getstatic     #116                // Field android/support/constraint/a/a/c$c.i:Landroid/support/constraint/a/a/c$c;
     184: if_acmpne     190
     187: goto          192
     190: iconst_0
     191: ireturn
     192: iconst_1
     193: istore_3
     194: iload_3
     195: ireturn
     196: aload         4
     198: getstatic     #117                // Field android/support/constraint/a/a/c$c.b:Landroid/support/constraint/a/a/c$c;
     201: if_acmpeq     220
     204: aload         4
     206: getstatic     #119                // Field android/support/constraint/a/a/c$c.d:Landroid/support/constraint/a/a/c$c;
     209: if_acmpne     215
     212: goto          220
     215: iconst_0
     216: istore_2
     217: goto          222
     220: iconst_1
     221: istore_2
     222: iload_2
     223: istore_3
     224: aload_1
     225: invokevirtual #86                 // Method c:()Landroid/support/constraint/a/a/d;
     228: instanceof    #114                // class android/support/constraint/a/a/f
     231: ifeq          253
     234: iload_2
     235: ifne          251
     238: aload         4
     240: getstatic     #121                // Field android/support/constraint/a/a/c$c.h:Landroid/support/constraint/a/a/c$c;
     243: if_acmpne     249
     246: goto          251
     249: iconst_0
     250: ireturn
     251: iconst_1
     252: istore_3
     253: iload_3
     254: ireturn
     255: iload_3
     256: istore_2
     257: aload         4
     259: getstatic     #83                 // Field android/support/constraint/a/a/c$c.f:Landroid/support/constraint/a/a/c$c;
     262: if_acmpeq     287
     265: iload_3
     266: istore_2
     267: aload         4
     269: getstatic     #121                // Field android/support/constraint/a/a/c$c.h:Landroid/support/constraint/a/a/c$c;
     272: if_acmpeq     287
     275: iload_3
     276: istore_2
     277: aload         4
     279: getstatic     #116                // Field android/support/constraint/a/a/c$c.i:Landroid/support/constraint/a/a/c$c;
     282: if_acmpeq     287
     285: iconst_1
     286: istore_2
     287: iload_2
     288: ireturn

  public boolean a(android.support.constraint.a.a.c, int, int, android.support.constraint.a.a.c$b, int, boolean);
    Code:
       0: aload_1
       1: ifnonnull     33
       4: aload_0
       5: aconst_null
       6: putfield      #124                // Field c:Landroid/support/constraint/a/a/c;
       9: aload_0
      10: iconst_0
      11: putfield      #44                 // Field d:I
      14: aload_0
      15: iconst_m1
      16: putfield      #46                 // Field e:I
      19: aload_0
      20: getstatic     #48                 // Field android/support/constraint/a/a/c$b.a:Landroid/support/constraint/a/a/c$b;
      23: putfield      #50                 // Field h:Landroid/support/constraint/a/a/c$b;
      26: aload_0
      27: iconst_2
      28: putfield      #56                 // Field j:I
      31: iconst_1
      32: ireturn
      33: iload         6
      35: ifne          48
      38: aload_0
      39: aload_1
      40: invokevirtual #126                // Method a:(Landroid/support/constraint/a/a/c;)Z
      43: ifne          48
      46: iconst_0
      47: ireturn
      48: aload_0
      49: aload_1
      50: putfield      #124                // Field c:Landroid/support/constraint/a/a/c;
      53: iload_2
      54: ifle          65
      57: aload_0
      58: iload_2
      59: putfield      #44                 // Field d:I
      62: goto          70
      65: aload_0
      66: iconst_0
      67: putfield      #44                 // Field d:I
      70: aload_0
      71: iload_3
      72: putfield      #46                 // Field e:I
      75: aload_0
      76: aload         4
      78: putfield      #50                 // Field h:Landroid/support/constraint/a/a/c$b;
      81: aload_0
      82: iload         5
      84: putfield      #56                 // Field j:I
      87: iconst_1
      88: ireturn

  public boolean a(android.support.constraint.a.a.c, int, android.support.constraint.a.a.c$b, int);
    Code:
       0: aload_0
       1: aload_1
       2: iload_2
       3: iconst_m1
       4: aload_3
       5: iload         4
       7: iconst_0
       8: invokevirtual #129                // Method a:(Landroid/support/constraint/a/a/c;IILandroid/support/constraint/a/a/c$b;IZ)Z
      11: ireturn

  public android.support.constraint.a.h b();
    Code:
       0: aload_0
       1: getfield      #65                 // Field f:Landroid/support/constraint/a/h;
       4: areturn

  public android.support.constraint.a.a.d c();
    Code:
       0: aload_0
       1: getfield      #58                 // Field a:Landroid/support/constraint/a/a/d;
       4: areturn

  public android.support.constraint.a.a.c$c d();
    Code:
       0: aload_0
       1: getfield      #60                 // Field b:Landroid/support/constraint/a/a/c$c;
       4: areturn

  public int e();
    Code:
       0: aload_0
       1: getfield      #58                 // Field a:Landroid/support/constraint/a/a/d;
       4: invokevirtual #133                // Method android/support/constraint/a/a/d.k:()I
       7: bipush        8
       9: if_icmpne     14
      12: iconst_0
      13: ireturn
      14: aload_0
      15: getfield      #46                 // Field e:I
      18: iconst_m1
      19: if_icmple     49
      22: aload_0
      23: getfield      #124                // Field c:Landroid/support/constraint/a/a/c;
      26: ifnull        49
      29: aload_0
      30: getfield      #124                // Field c:Landroid/support/constraint/a/a/c;
      33: getfield      #58                 // Field a:Landroid/support/constraint/a/a/d;
      36: invokevirtual #133                // Method android/support/constraint/a/a/d.k:()I
      39: bipush        8
      41: if_icmpne     49
      44: aload_0
      45: getfield      #46                 // Field e:I
      48: ireturn
      49: aload_0
      50: getfield      #44                 // Field d:I
      53: ireturn

  public android.support.constraint.a.a.c$b f();
    Code:
       0: aload_0
       1: getfield      #50                 // Field h:Landroid/support/constraint/a/a/c$b;
       4: areturn

  public android.support.constraint.a.a.c g();
    Code:
       0: aload_0
       1: getfield      #124                // Field c:Landroid/support/constraint/a/a/c;
       4: areturn

  public int h();
    Code:
       0: aload_0
       1: getfield      #56                 // Field j:I
       4: ireturn

  public void i();
    Code:
       0: aload_0
       1: aconst_null
       2: putfield      #124                // Field c:Landroid/support/constraint/a/a/c;
       5: aload_0
       6: iconst_0
       7: putfield      #44                 // Field d:I
      10: aload_0
      11: iconst_m1
      12: putfield      #46                 // Field e:I
      15: aload_0
      16: getstatic     #137                // Field android/support/constraint/a/a/c$b.b:Landroid/support/constraint/a/a/c$b;
      19: putfield      #50                 // Field h:Landroid/support/constraint/a/a/c$b;
      22: aload_0
      23: iconst_0
      24: putfield      #56                 // Field j:I
      27: aload_0
      28: getstatic     #52                 // Field android/support/constraint/a/a/c$a.a:Landroid/support/constraint/a/a/c$a;
      31: putfield      #54                 // Field i:Landroid/support/constraint/a/a/c$a;
      34: aload_0
      35: getfield      #42                 // Field g:Landroid/support/constraint/a/a/j;
      38: invokevirtual #138                // Method android/support/constraint/a/a/j.b:()V
      41: return

  public boolean j();
    Code:
       0: aload_0
       1: getfield      #124                // Field c:Landroid/support/constraint/a/a/c;
       4: ifnull        9
       7: iconst_1
       8: ireturn
       9: iconst_0
      10: ireturn

  public java.lang.String toString();
    Code:
       0: new           #141                // class java/lang/StringBuilder
       3: dup
       4: invokespecial #142                // Method java/lang/StringBuilder."<init>":()V
       7: astore_1
       8: aload_1
       9: aload_0
      10: getfield      #58                 // Field a:Landroid/support/constraint/a/a/d;
      13: invokevirtual #145                // Method android/support/constraint/a/a/d.l:()Ljava/lang/String;
      16: invokevirtual #149                // Method java/lang/StringBuilder.append:(Ljava/lang/String;)Ljava/lang/StringBuilder;
      19: pop
      20: aload_1
      21: ldc           #151                // String :
      23: invokevirtual #149                // Method java/lang/StringBuilder.append:(Ljava/lang/String;)Ljava/lang/StringBuilder;
      26: pop
      27: aload_1
      28: aload_0
      29: getfield      #60                 // Field b:Landroid/support/constraint/a/a/c$c;
      32: invokevirtual #153                // Method android/support/constraint/a/a/c$c.toString:()Ljava/lang/String;
      35: invokevirtual #149                // Method java/lang/StringBuilder.append:(Ljava/lang/String;)Ljava/lang/StringBuilder;
      38: pop
      39: aload_1
      40: invokevirtual #154                // Method java/lang/StringBuilder.toString:()Ljava/lang/String;
      43: areturn
}
