class android.support.constraint.a.a.d$1 {
  static final int[] a;

  static final int[] b;

  static {};
    Code:
       0: invokestatic  #19                 // Method android/support/constraint/a/a/d$a.values:()[Landroid/support/constraint/a/a/d$a;
       3: arraylength
       4: newarray       int
       6: putstatic     #21                 // Field b:[I
       9: getstatic     #21                 // Field b:[I
      12: getstatic     #24                 // Field android/support/constraint/a/a/d$a.a:Landroid/support/constraint/a/a/d$a;
      15: invokevirtual #28                 // Method android/support/constraint/a/a/d$a.ordinal:()I
      18: iconst_1
      19: iastore
      20: getstatic     #21                 // Field b:[I
      23: getstatic     #30                 // Field android/support/constraint/a/a/d$a.b:Landroid/support/constraint/a/a/d$a;
      26: invokevirtual #28                 // Method android/support/constraint/a/a/d$a.ordinal:()I
      29: iconst_2
      30: iastore
      31: getstatic     #21                 // Field b:[I
      34: getstatic     #33                 // Field android/support/constraint/a/a/d$a.d:Landroid/support/constraint/a/a/d$a;
      37: invokevirtual #28                 // Method android/support/constraint/a/a/d$a.ordinal:()I
      40: iconst_3
      41: iastore
      42: getstatic     #21                 // Field b:[I
      45: getstatic     #36                 // Field android/support/constraint/a/a/d$a.c:Landroid/support/constraint/a/a/d$a;
      48: invokevirtual #28                 // Method android/support/constraint/a/a/d$a.ordinal:()I
      51: iconst_4
      52: iastore
      53: invokestatic  #41                 // Method android/support/constraint/a/a/c$c.values:()[Landroid/support/constraint/a/a/c$c;
      56: arraylength
      57: newarray       int
      59: putstatic     #43                 // Field a:[I
      62: getstatic     #43                 // Field a:[I
      65: getstatic     #46                 // Field android/support/constraint/a/a/c$c.b:Landroid/support/constraint/a/a/c$c;
      68: invokevirtual #47                 // Method android/support/constraint/a/a/c$c.ordinal:()I
      71: iconst_1
      72: iastore
      73: getstatic     #43                 // Field a:[I
      76: getstatic     #49                 // Field android/support/constraint/a/a/c$c.c:Landroid/support/constraint/a/a/c$c;
      79: invokevirtual #47                 // Method android/support/constraint/a/a/c$c.ordinal:()I
      82: iconst_2
      83: iastore
      84: getstatic     #43                 // Field a:[I
      87: getstatic     #51                 // Field android/support/constraint/a/a/c$c.d:Landroid/support/constraint/a/a/c$c;
      90: invokevirtual #47                 // Method android/support/constraint/a/a/c$c.ordinal:()I
      93: iconst_3
      94: iastore
      95: getstatic     #43                 // Field a:[I
      98: getstatic     #54                 // Field android/support/constraint/a/a/c$c.e:Landroid/support/constraint/a/a/c$c;
     101: invokevirtual #47                 // Method android/support/constraint/a/a/c$c.ordinal:()I
     104: iconst_4
     105: iastore
     106: getstatic     #43                 // Field a:[I
     109: getstatic     #57                 // Field android/support/constraint/a/a/c$c.f:Landroid/support/constraint/a/a/c$c;
     112: invokevirtual #47                 // Method android/support/constraint/a/a/c$c.ordinal:()I
     115: iconst_5
     116: iastore
     117: getstatic     #43                 // Field a:[I
     120: getstatic     #60                 // Field android/support/constraint/a/a/c$c.g:Landroid/support/constraint/a/a/c$c;
     123: invokevirtual #47                 // Method android/support/constraint/a/a/c$c.ordinal:()I
     126: bipush        6
     128: iastore
     129: getstatic     #43                 // Field a:[I
     132: getstatic     #63                 // Field android/support/constraint/a/a/c$c.h:Landroid/support/constraint/a/a/c$c;
     135: invokevirtual #47                 // Method android/support/constraint/a/a/c$c.ordinal:()I
     138: bipush        7
     140: iastore
     141: getstatic     #43                 // Field a:[I
     144: getstatic     #66                 // Field android/support/constraint/a/a/c$c.i:Landroid/support/constraint/a/a/c$c;
     147: invokevirtual #47                 // Method android/support/constraint/a/a/c$c.ordinal:()I
     150: bipush        8
     152: iastore
     153: getstatic     #43                 // Field a:[I
     156: getstatic     #68                 // Field android/support/constraint/a/a/c$c.a:Landroid/support/constraint/a/a/c$c;
     159: invokevirtual #47                 // Method android/support/constraint/a/a/c$c.ordinal:()I
     162: bipush        9
     164: iastore
     165: return
     166: astore_0
     167: goto          20
     170: astore_0
     171: goto          31
     174: astore_0
     175: goto          42
     178: astore_0
     179: goto          53
     182: astore_0
     183: goto          73
     186: astore_0
     187: goto          84
     190: astore_0
     191: goto          95
     194: astore_0
     195: goto          106
     198: astore_0
     199: goto          117
     202: astore_0
     203: goto          129
     206: astore_0
     207: goto          141
     210: astore_0
     211: goto          153
     214: astore_0
     215: return
    Exception table:
       from    to  target type
           9    20   166   Class java/lang/NoSuchFieldError
          20    31   170   Class java/lang/NoSuchFieldError
          31    42   174   Class java/lang/NoSuchFieldError
          42    53   178   Class java/lang/NoSuchFieldError
          62    73   182   Class java/lang/NoSuchFieldError
          73    84   186   Class java/lang/NoSuchFieldError
          84    95   190   Class java/lang/NoSuchFieldError
          95   106   194   Class java/lang/NoSuchFieldError
         106   117   198   Class java/lang/NoSuchFieldError
         117   129   202   Class java/lang/NoSuchFieldError
         129   141   206   Class java/lang/NoSuchFieldError
         141   153   210   Class java/lang/NoSuchFieldError
         153   165   214   Class java/lang/NoSuchFieldError
}
