public final class android.support.constraint.a.a.d$a extends java.lang.Enum<android.support.constraint.a.a.d$a> {
  public static final android.support.constraint.a.a.d$a a;

  public static final android.support.constraint.a.a.d$a b;

  public static final android.support.constraint.a.a.d$a c;

  public static final android.support.constraint.a.a.d$a d;

  static {};
    Code:
       0: new           #2                  // class android/support/constraint/a/a/d$a
       3: dup
       4: ldc           #18                 // String FIXED
       6: iconst_0
       7: invokespecial #22                 // Method "<init>":(Ljava/lang/String;I)V
      10: putstatic     #24                 // Field a:Landroid/support/constraint/a/a/d$a;
      13: new           #2                  // class android/support/constraint/a/a/d$a
      16: dup
      17: ldc           #26                 // String WRAP_CONTENT
      19: iconst_1
      20: invokespecial #22                 // Method "<init>":(Ljava/lang/String;I)V
      23: putstatic     #28                 // Field b:Landroid/support/constraint/a/a/d$a;
      26: new           #2                  // class android/support/constraint/a/a/d$a
      29: dup
      30: ldc           #30                 // String MATCH_CONSTRAINT
      32: iconst_2
      33: invokespecial #22                 // Method "<init>":(Ljava/lang/String;I)V
      36: putstatic     #32                 // Field c:Landroid/support/constraint/a/a/d$a;
      39: new           #2                  // class android/support/constraint/a/a/d$a
      42: dup
      43: ldc           #34                 // String MATCH_PARENT
      45: iconst_3
      46: invokespecial #22                 // Method "<init>":(Ljava/lang/String;I)V
      49: putstatic     #36                 // Field d:Landroid/support/constraint/a/a/d$a;
      52: iconst_4
      53: anewarray     #2                  // class android/support/constraint/a/a/d$a
      56: dup
      57: iconst_0
      58: getstatic     #24                 // Field a:Landroid/support/constraint/a/a/d$a;
      61: aastore
      62: dup
      63: iconst_1
      64: getstatic     #28                 // Field b:Landroid/support/constraint/a/a/d$a;
      67: aastore
      68: dup
      69: iconst_2
      70: getstatic     #32                 // Field c:Landroid/support/constraint/a/a/d$a;
      73: aastore
      74: dup
      75: iconst_3
      76: getstatic     #36                 // Field d:Landroid/support/constraint/a/a/d$a;
      79: aastore
      80: putstatic     #38                 // Field e:[Landroid/support/constraint/a/a/d$a;
      83: return

  public static android.support.constraint.a.a.d$a valueOf(java.lang.String);
    Code:
       0: ldc           #2                  // class android/support/constraint/a/a/d$a
       2: aload_0
       3: invokestatic  #46                 // Method java/lang/Enum.valueOf:(Ljava/lang/Class;Ljava/lang/String;)Ljava/lang/Enum;
       6: checkcast     #2                  // class android/support/constraint/a/a/d$a
       9: areturn

  public static android.support.constraint.a.a.d$a[] values();
    Code:
       0: getstatic     #38                 // Field e:[Landroid/support/constraint/a/a/d$a;
       3: invokevirtual #53                 // Method "[Landroid/support/constraint/a/a/d$a;".clone:()Ljava/lang/Object;
       6: checkcast     #49                 // class "[Landroid/support/constraint/a/a/d$a;"
       9: areturn
}
