public class android.support.constraint.a.a.d {
  public static float N;

  protected android.support.constraint.a.a.d$a[] A;

  android.support.constraint.a.a.d B;

  int C;

  int D;

  protected float E;

  protected int F;

  protected int G;

  protected int H;

  protected int I;

  protected int J;

  int K;

  protected int L;

  protected int M;

  float O;

  float P;

  boolean Q;

  boolean R;

  int S;

  int T;

  boolean U;

  boolean V;

  float[] W;

  protected android.support.constraint.a.a.d[] X;

  protected android.support.constraint.a.a.d[] Y;

  android.support.constraint.a.a.d Z;

  public int a;

  android.support.constraint.a.a.d aa;

  public int b;

  android.support.constraint.a.a.k c;

  android.support.constraint.a.a.k d;

  int e;

  int f;

  int g;

  int h;

  float i;

  int j;

  int k;

  float l;

  boolean m;

  boolean n;

  int o;

  float p;

  android.support.constraint.a.a.c q;

  android.support.constraint.a.a.c r;

  android.support.constraint.a.a.c s;

  android.support.constraint.a.a.c t;

  android.support.constraint.a.a.c u;

  android.support.constraint.a.a.c v;

  android.support.constraint.a.a.c w;

  android.support.constraint.a.a.c x;

  protected android.support.constraint.a.a.c[] y;

  protected java.util.ArrayList<android.support.constraint.a.a.c> z;

  static {};
    Code:
       0: return

  public android.support.constraint.a.a.d();
    Code:
       0: aload_0
       1: invokespecial #93                 // Method java/lang/Object."<init>":()V
       4: aload_0
       5: iconst_m1
       6: putfield      #95                 // Field a:I
       9: aload_0
      10: iconst_m1
      11: putfield      #97                 // Field b:I
      14: aload_0
      15: iconst_0
      16: putfield      #99                 // Field e:I
      19: aload_0
      20: iconst_0
      21: putfield      #101                // Field f:I
      24: aload_0
      25: iconst_0
      26: putfield      #103                // Field g:I
      29: aload_0
      30: iconst_0
      31: putfield      #105                // Field h:I
      34: aload_0
      35: fconst_1
      36: putfield      #107                // Field i:F
      39: aload_0
      40: iconst_0
      41: putfield      #109                // Field j:I
      44: aload_0
      45: iconst_0
      46: putfield      #111                // Field k:I
      49: aload_0
      50: fconst_1
      51: putfield      #113                // Field l:F
      54: aload_0
      55: iconst_m1
      56: putfield      #115                // Field o:I
      59: aload_0
      60: fconst_1
      61: putfield      #117                // Field p:F
      64: aload_0
      65: iconst_2
      66: newarray       int
      68: dup
      69: iconst_0
      70: ldc           #118                // int 2147483647
      72: iastore
      73: dup
      74: iconst_1
      75: ldc           #118                // int 2147483647
      77: iastore
      78: putfield      #120                // Field ab:[I
      81: aload_0
      82: fconst_0
      83: putfield      #122                // Field ac:F
      86: aload_0
      87: new           #124                // class android/support/constraint/a/a/c
      90: dup
      91: aload_0
      92: getstatic     #129                // Field android/support/constraint/a/a/c$c.b:Landroid/support/constraint/a/a/c$c;
      95: invokespecial #132                // Method android/support/constraint/a/a/c."<init>":(Landroid/support/constraint/a/a/d;Landroid/support/constraint/a/a/c$c;)V
      98: putfield      #134                // Field q:Landroid/support/constraint/a/a/c;
     101: aload_0
     102: new           #124                // class android/support/constraint/a/a/c
     105: dup
     106: aload_0
     107: getstatic     #136                // Field android/support/constraint/a/a/c$c.c:Landroid/support/constraint/a/a/c$c;
     110: invokespecial #132                // Method android/support/constraint/a/a/c."<init>":(Landroid/support/constraint/a/a/d;Landroid/support/constraint/a/a/c$c;)V
     113: putfield      #138                // Field r:Landroid/support/constraint/a/a/c;
     116: aload_0
     117: new           #124                // class android/support/constraint/a/a/c
     120: dup
     121: aload_0
     122: getstatic     #140                // Field android/support/constraint/a/a/c$c.d:Landroid/support/constraint/a/a/c$c;
     125: invokespecial #132                // Method android/support/constraint/a/a/c."<init>":(Landroid/support/constraint/a/a/d;Landroid/support/constraint/a/a/c$c;)V
     128: putfield      #142                // Field s:Landroid/support/constraint/a/a/c;
     131: aload_0
     132: new           #124                // class android/support/constraint/a/a/c
     135: dup
     136: aload_0
     137: getstatic     #144                // Field android/support/constraint/a/a/c$c.e:Landroid/support/constraint/a/a/c$c;
     140: invokespecial #132                // Method android/support/constraint/a/a/c."<init>":(Landroid/support/constraint/a/a/d;Landroid/support/constraint/a/a/c$c;)V
     143: putfield      #146                // Field t:Landroid/support/constraint/a/a/c;
     146: aload_0
     147: new           #124                // class android/support/constraint/a/a/c
     150: dup
     151: aload_0
     152: getstatic     #148                // Field android/support/constraint/a/a/c$c.f:Landroid/support/constraint/a/a/c$c;
     155: invokespecial #132                // Method android/support/constraint/a/a/c."<init>":(Landroid/support/constraint/a/a/d;Landroid/support/constraint/a/a/c$c;)V
     158: putfield      #150                // Field u:Landroid/support/constraint/a/a/c;
     161: aload_0
     162: new           #124                // class android/support/constraint/a/a/c
     165: dup
     166: aload_0
     167: getstatic     #152                // Field android/support/constraint/a/a/c$c.h:Landroid/support/constraint/a/a/c$c;
     170: invokespecial #132                // Method android/support/constraint/a/a/c."<init>":(Landroid/support/constraint/a/a/d;Landroid/support/constraint/a/a/c$c;)V
     173: putfield      #154                // Field v:Landroid/support/constraint/a/a/c;
     176: aload_0
     177: new           #124                // class android/support/constraint/a/a/c
     180: dup
     181: aload_0
     182: getstatic     #156                // Field android/support/constraint/a/a/c$c.i:Landroid/support/constraint/a/a/c$c;
     185: invokespecial #132                // Method android/support/constraint/a/a/c."<init>":(Landroid/support/constraint/a/a/d;Landroid/support/constraint/a/a/c$c;)V
     188: putfield      #158                // Field w:Landroid/support/constraint/a/a/c;
     191: aload_0
     192: new           #124                // class android/support/constraint/a/a/c
     195: dup
     196: aload_0
     197: getstatic     #160                // Field android/support/constraint/a/a/c$c.g:Landroid/support/constraint/a/a/c$c;
     200: invokespecial #132                // Method android/support/constraint/a/a/c."<init>":(Landroid/support/constraint/a/a/d;Landroid/support/constraint/a/a/c$c;)V
     203: putfield      #162                // Field x:Landroid/support/constraint/a/a/c;
     206: aload_0
     207: bipush        6
     209: anewarray     #124                // class android/support/constraint/a/a/c
     212: dup
     213: iconst_0
     214: aload_0
     215: getfield      #134                // Field q:Landroid/support/constraint/a/a/c;
     218: aastore
     219: dup
     220: iconst_1
     221: aload_0
     222: getfield      #142                // Field s:Landroid/support/constraint/a/a/c;
     225: aastore
     226: dup
     227: iconst_2
     228: aload_0
     229: getfield      #138                // Field r:Landroid/support/constraint/a/a/c;
     232: aastore
     233: dup
     234: iconst_3
     235: aload_0
     236: getfield      #146                // Field t:Landroid/support/constraint/a/a/c;
     239: aastore
     240: dup
     241: iconst_4
     242: aload_0
     243: getfield      #150                // Field u:Landroid/support/constraint/a/a/c;
     246: aastore
     247: dup
     248: iconst_5
     249: aload_0
     250: getfield      #162                // Field x:Landroid/support/constraint/a/a/c;
     253: aastore
     254: putfield      #164                // Field y:[Landroid/support/constraint/a/a/c;
     257: aload_0
     258: new           #166                // class java/util/ArrayList
     261: dup
     262: invokespecial #167                // Method java/util/ArrayList."<init>":()V
     265: putfield      #169                // Field z:Ljava/util/ArrayList;
     268: aload_0
     269: iconst_2
     270: anewarray     #8                  // class android/support/constraint/a/a/d$a
     273: dup
     274: iconst_0
     275: getstatic     #172                // Field android/support/constraint/a/a/d$a.a:Landroid/support/constraint/a/a/d$a;
     278: aastore
     279: dup
     280: iconst_1
     281: getstatic     #172                // Field android/support/constraint/a/a/d$a.a:Landroid/support/constraint/a/a/d$a;
     284: aastore
     285: putfield      #174                // Field A:[Landroid/support/constraint/a/a/d$a;
     288: aload_0
     289: aconst_null
     290: putfield      #176                // Field B:Landroid/support/constraint/a/a/d;
     293: aload_0
     294: iconst_0
     295: putfield      #178                // Field C:I
     298: aload_0
     299: iconst_0
     300: putfield      #180                // Field D:I
     303: aload_0
     304: fconst_0
     305: putfield      #182                // Field E:F
     308: aload_0
     309: iconst_m1
     310: putfield      #184                // Field F:I
     313: aload_0
     314: iconst_0
     315: putfield      #186                // Field G:I
     318: aload_0
     319: iconst_0
     320: putfield      #188                // Field H:I
     323: aload_0
     324: iconst_0
     325: putfield      #190                // Field ad:I
     328: aload_0
     329: iconst_0
     330: putfield      #192                // Field ae:I
     333: aload_0
     334: iconst_0
     335: putfield      #194                // Field af:I
     338: aload_0
     339: iconst_0
     340: putfield      #196                // Field ag:I
     343: aload_0
     344: iconst_0
     345: putfield      #198                // Field I:I
     348: aload_0
     349: iconst_0
     350: putfield      #200                // Field J:I
     353: aload_0
     354: iconst_0
     355: putfield      #202                // Field K:I
     358: aload_0
     359: getstatic     #204                // Field N:F
     362: putfield      #206                // Field O:F
     365: aload_0
     366: getstatic     #204                // Field N:F
     369: putfield      #208                // Field P:F
     372: aload_0
     373: iconst_0
     374: putfield      #210                // Field ak:I
     377: aload_0
     378: iconst_0
     379: putfield      #212                // Field al:I
     382: aload_0
     383: aconst_null
     384: putfield      #214                // Field am:Ljava/lang/String;
     387: aload_0
     388: aconst_null
     389: putfield      #216                // Field an:Ljava/lang/String;
     392: aload_0
     393: iconst_0
     394: putfield      #218                // Field S:I
     397: aload_0
     398: iconst_0
     399: putfield      #220                // Field T:I
     402: aload_0
     403: iconst_2
     404: newarray       float
     406: dup
     407: iconst_0
     408: fconst_0
     409: fastore
     410: dup
     411: iconst_1
     412: fconst_0
     413: fastore
     414: putfield      #222                // Field W:[F
     417: aload_0
     418: iconst_2
     419: anewarray     #2                  // class android/support/constraint/a/a/d
     422: dup
     423: iconst_0
     424: aconst_null
     425: aastore
     426: dup
     427: iconst_1
     428: aconst_null
     429: aastore
     430: putfield      #224                // Field X:[Landroid/support/constraint/a/a/d;
     433: aload_0
     434: iconst_2
     435: anewarray     #2                  // class android/support/constraint/a/a/d
     438: dup
     439: iconst_0
     440: aconst_null
     441: aastore
     442: dup
     443: iconst_1
     444: aconst_null
     445: aastore
     446: putfield      #226                // Field Y:[Landroid/support/constraint/a/a/d;
     449: aload_0
     450: aconst_null
     451: putfield      #228                // Field Z:Landroid/support/constraint/a/a/d;
     454: aload_0
     455: aconst_null
     456: putfield      #230                // Field aa:Landroid/support/constraint/a/a/d;
     459: aload_0
     460: invokespecial #232                // Method H:()V
     463: return

  public int A();
    Code:
       0: aload_0
       1: getfield      #202                // Field K:I
       4: ireturn

  public java.lang.Object B();
    Code:
       0: aload_0
       1: getfield      #320                // Field aj:Ljava/lang/Object;
       4: areturn

  public java.util.ArrayList<android.support.constraint.a.a.c> C();
    Code:
       0: aload_0
       1: getfield      #169                // Field z:Ljava/util/ArrayList;
       4: areturn

  public void D();
    Code:
       0: aload_0
       1: getfield      #186                // Field G:I
       4: istore_1
       5: aload_0
       6: getfield      #188                // Field H:I
       9: istore_2
      10: aload_0
      11: getfield      #186                // Field G:I
      14: istore_3
      15: aload_0
      16: getfield      #178                // Field C:I
      19: istore        4
      21: aload_0
      22: getfield      #188                // Field H:I
      25: istore        5
      27: aload_0
      28: getfield      #180                // Field D:I
      31: istore        6
      33: aload_0
      34: iload_1
      35: putfield      #190                // Field ad:I
      38: aload_0
      39: iload_2
      40: putfield      #192                // Field ae:I
      43: aload_0
      44: iload_3
      45: iload         4
      47: iadd
      48: iload_1
      49: isub
      50: putfield      #194                // Field af:I
      53: aload_0
      54: iload         5
      56: iload         6
      58: iadd
      59: iload_2
      60: isub
      61: putfield      #196                // Field ag:I
      64: return

  public void E();
    Code:
       0: aload_0
       1: invokevirtual #326                // Method j:()Landroid/support/constraint/a/a/d;
       4: astore_3
       5: aload_3
       6: ifnull        30
       9: aload_3
      10: instanceof    #328                // class android/support/constraint/a/a/e
      13: ifeq          30
      16: aload_0
      17: invokevirtual #326                // Method j:()Landroid/support/constraint/a/a/d;
      20: checkcast     #328                // class android/support/constraint/a/a/e
      23: invokevirtual #330                // Method android/support/constraint/a/a/e.Q:()Z
      26: ifeq          30
      29: return
      30: iconst_0
      31: istore_1
      32: aload_0
      33: getfield      #169                // Field z:Ljava/util/ArrayList;
      36: invokevirtual #333                // Method java/util/ArrayList.size:()I
      39: istore_2
      40: iload_1
      41: iload_2
      42: if_icmpge     66
      45: aload_0
      46: getfield      #169                // Field z:Ljava/util/ArrayList;
      49: iload_1
      50: invokevirtual #337                // Method java/util/ArrayList.get:(I)Ljava/lang/Object;
      53: checkcast     #124                // class android/support/constraint/a/a/c
      56: invokevirtual #339                // Method android/support/constraint/a/a/c.i:()V
      59: iload_1
      60: iconst_1
      61: iadd
      62: istore_1
      63: goto          40
      66: return

  public android.support.constraint.a.a.d$a F();
    Code:
       0: aload_0
       1: getfield      #174                // Field A:[Landroid/support/constraint/a/a/d$a;
       4: iconst_0
       5: aaload
       6: areturn

  public android.support.constraint.a.a.d$a G();
    Code:
       0: aload_0
       1: getfield      #174                // Field A:[Landroid/support/constraint/a/a/d$a;
       4: iconst_1
       5: aaload
       6: areturn

  public android.support.constraint.a.a.c a(android.support.constraint.a.a.c$c);
    Code:
       0: getstatic     #342                // Field android/support/constraint/a/a/d$1.a:[I
       3: aload_1
       4: invokevirtual #343                // Method android/support/constraint/a/a/c$c.ordinal:()I
       7: iaload
       8: tableswitch   { // 1 to 9
                     1: 109
                     2: 104
                     3: 99
                     4: 94
                     5: 89
                     6: 84
                     7: 79
                     8: 74
                     9: 72
               default: 60
          }
      60: new           #345                // class java/lang/AssertionError
      63: dup
      64: aload_1
      65: invokevirtual #349                // Method android/support/constraint/a/a/c$c.name:()Ljava/lang/String;
      68: invokespecial #352                // Method java/lang/AssertionError."<init>":(Ljava/lang/Object;)V
      71: athrow
      72: aconst_null
      73: areturn
      74: aload_0
      75: getfield      #158                // Field w:Landroid/support/constraint/a/a/c;
      78: areturn
      79: aload_0
      80: getfield      #154                // Field v:Landroid/support/constraint/a/a/c;
      83: areturn
      84: aload_0
      85: getfield      #162                // Field x:Landroid/support/constraint/a/a/c;
      88: areturn
      89: aload_0
      90: getfield      #150                // Field u:Landroid/support/constraint/a/a/c;
      93: areturn
      94: aload_0
      95: getfield      #146                // Field t:Landroid/support/constraint/a/a/c;
      98: areturn
      99: aload_0
     100: getfield      #142                // Field s:Landroid/support/constraint/a/a/c;
     103: areturn
     104: aload_0
     105: getfield      #138                // Field r:Landroid/support/constraint/a/a/c;
     108: areturn
     109: aload_0
     110: getfield      #134                // Field q:Landroid/support/constraint/a/a/c;
     113: areturn

  public void a(float);
    Code:
       0: aload_0
       1: fload_1
       2: putfield      #206                // Field O:F
       5: return

  public void a(int, int);
    Code:
       0: aload_0
       1: iload_1
       2: putfield      #186                // Field G:I
       5: aload_0
       6: iload_2
       7: putfield      #188                // Field H:I
      10: return

  public void a(int, int, int, float);
    Code:
       0: aload_0
       1: iload_1
       2: putfield      #99                 // Field e:I
       5: aload_0
       6: iload_2
       7: putfield      #103                // Field g:I
      10: aload_0
      11: iload_3
      12: putfield      #105                // Field h:I
      15: aload_0
      16: fload         4
      18: putfield      #107                // Field i:F
      21: fload         4
      23: fconst_1
      24: fcmpg
      25: ifge          40
      28: aload_0
      29: getfield      #99                 // Field e:I
      32: ifne          40
      35: aload_0
      36: iconst_2
      37: putfield      #99                 // Field e:I
      40: return

  public void a(int, int, int, int);
    Code:
       0: iload_3
       1: iload_1
       2: isub
       3: istore        5
       5: iload         4
       7: iload_2
       8: isub
       9: istore_3
      10: aload_0
      11: iload_1
      12: putfield      #186                // Field G:I
      15: aload_0
      16: iload_2
      17: putfield      #188                // Field H:I
      20: aload_0
      21: getfield      #212                // Field al:I
      24: bipush        8
      26: if_icmpne     40
      29: aload_0
      30: iconst_0
      31: putfield      #178                // Field C:I
      34: aload_0
      35: iconst_0
      36: putfield      #180                // Field D:I
      39: return
      40: iload         5
      42: istore_1
      43: aload_0
      44: getfield      #174                // Field A:[Landroid/support/constraint/a/a/d$a;
      47: iconst_0
      48: aaload
      49: getstatic     #172                // Field android/support/constraint/a/a/d$a.a:Landroid/support/constraint/a/a/d$a;
      52: if_acmpne     72
      55: iload         5
      57: istore_1
      58: iload         5
      60: aload_0
      61: getfield      #178                // Field C:I
      64: if_icmpge     72
      67: aload_0
      68: getfield      #178                // Field C:I
      71: istore_1
      72: iload_3
      73: istore_2
      74: aload_0
      75: getfield      #174                // Field A:[Landroid/support/constraint/a/a/d$a;
      78: iconst_1
      79: aaload
      80: getstatic     #172                // Field android/support/constraint/a/a/d$a.a:Landroid/support/constraint/a/a/d$a;
      83: if_acmpne     101
      86: iload_3
      87: istore_2
      88: iload_3
      89: aload_0
      90: getfield      #180                // Field D:I
      93: if_icmpge     101
      96: aload_0
      97: getfield      #180                // Field D:I
     100: istore_2
     101: aload_0
     102: iload_1
     103: putfield      #178                // Field C:I
     106: aload_0
     107: iload_2
     108: putfield      #180                // Field D:I
     111: aload_0
     112: getfield      #180                // Field D:I
     115: aload_0
     116: getfield      #358                // Field M:I
     119: if_icmpge     130
     122: aload_0
     123: aload_0
     124: getfield      #358                // Field M:I
     127: putfield      #180                // Field D:I
     130: aload_0
     131: getfield      #178                // Field C:I
     134: aload_0
     135: getfield      #360                // Field L:I
     138: if_icmpge     149
     141: aload_0
     142: aload_0
     143: getfield      #360                // Field L:I
     146: putfield      #178                // Field C:I
     149: return

  public void a(android.support.constraint.a.a.c$c, android.support.constraint.a.a.d, android.support.constraint.a.a.c$c, int, int);
    Code:
       0: aload_0
       1: aload_1
       2: invokevirtual #303                // Method a:(Landroid/support/constraint/a/a/c$c;)Landroid/support/constraint/a/a/c;
       5: aload_2
       6: aload_3
       7: invokevirtual #303                // Method a:(Landroid/support/constraint/a/a/c$c;)Landroid/support/constraint/a/a/c;
      10: iload         4
      12: iload         5
      14: getstatic     #366                // Field android/support/constraint/a/a/c$b.b:Landroid/support/constraint/a/a/c$b;
      17: iconst_0
      18: iconst_1
      19: invokevirtual #369                // Method android/support/constraint/a/a/c.a:(Landroid/support/constraint/a/a/c;IILandroid/support/constraint/a/a/c$b;IZ)Z
      22: pop
      23: return

  public void a(android.support.constraint.a.a.d$a);
    Code:
       0: aload_0
       1: getfield      #174                // Field A:[Landroid/support/constraint/a/a/d$a;
       4: iconst_0
       5: aload_1
       6: aastore
       7: aload_1
       8: getstatic     #372                // Field android/support/constraint/a/a/d$a.b:Landroid/support/constraint/a/a/d$a;
      11: if_acmpne     22
      14: aload_0
      15: aload_0
      16: getfield      #374                // Field ah:I
      19: invokevirtual #377                // Method h:(I)V
      22: return

  public void a(android.support.constraint.a.a.d);
    Code:
       0: aload_0
       1: aload_1
       2: putfield      #176                // Field B:Landroid/support/constraint/a/a/d;
       5: return

  public void a(android.support.constraint.a.a.d, float, int);
    Code:
       0: aload_0
       1: getstatic     #160                // Field android/support/constraint/a/a/c$c.g:Landroid/support/constraint/a/a/c$c;
       4: aload_1
       5: getstatic     #160                // Field android/support/constraint/a/a/c$c.g:Landroid/support/constraint/a/a/c$c;
       8: iload_3
       9: iconst_0
      10: invokevirtual #381                // Method a:(Landroid/support/constraint/a/a/c$c;Landroid/support/constraint/a/a/d;Landroid/support/constraint/a/a/c$c;II)V
      13: aload_0
      14: fload_2
      15: putfield      #122                // Field ac:F
      18: return

  public void a(android.support.constraint.a.c);
    Code:
       0: aload_0
       1: getfield      #134                // Field q:Landroid/support/constraint/a/a/c;
       4: aload_1
       5: invokevirtual #384                // Method android/support/constraint/a/a/c.a:(Landroid/support/constraint/a/c;)V
       8: aload_0
       9: getfield      #138                // Field r:Landroid/support/constraint/a/a/c;
      12: aload_1
      13: invokevirtual #384                // Method android/support/constraint/a/a/c.a:(Landroid/support/constraint/a/c;)V
      16: aload_0
      17: getfield      #142                // Field s:Landroid/support/constraint/a/a/c;
      20: aload_1
      21: invokevirtual #384                // Method android/support/constraint/a/a/c.a:(Landroid/support/constraint/a/c;)V
      24: aload_0
      25: getfield      #146                // Field t:Landroid/support/constraint/a/a/c;
      28: aload_1
      29: invokevirtual #384                // Method android/support/constraint/a/a/c.a:(Landroid/support/constraint/a/c;)V
      32: aload_0
      33: getfield      #150                // Field u:Landroid/support/constraint/a/a/c;
      36: aload_1
      37: invokevirtual #384                // Method android/support/constraint/a/a/c.a:(Landroid/support/constraint/a/c;)V
      40: aload_0
      41: getfield      #162                // Field x:Landroid/support/constraint/a/a/c;
      44: aload_1
      45: invokevirtual #384                // Method android/support/constraint/a/a/c.a:(Landroid/support/constraint/a/c;)V
      48: aload_0
      49: getfield      #154                // Field v:Landroid/support/constraint/a/a/c;
      52: aload_1
      53: invokevirtual #384                // Method android/support/constraint/a/a/c.a:(Landroid/support/constraint/a/c;)V
      56: aload_0
      57: getfield      #158                // Field w:Landroid/support/constraint/a/a/c;
      60: aload_1
      61: invokevirtual #384                // Method android/support/constraint/a/a/c.a:(Landroid/support/constraint/a/c;)V
      64: return

  public void a(android.support.constraint.a.e);
    Code:
       0: aload_0
       1: astore        16
       3: aload_1
       4: aload         16
       6: getfield      #134                // Field q:Landroid/support/constraint/a/a/c;
       9: invokevirtual #242                // Method android/support/constraint/a/e.a:(Ljava/lang/Object;)Landroid/support/constraint/a/h;
      12: astore        17
      14: aload_1
      15: aload         16
      17: getfield      #142                // Field s:Landroid/support/constraint/a/a/c;
      20: invokevirtual #242                // Method android/support/constraint/a/e.a:(Ljava/lang/Object;)Landroid/support/constraint/a/h;
      23: astore        19
      25: aload_1
      26: aload         16
      28: getfield      #138                // Field r:Landroid/support/constraint/a/a/c;
      31: invokevirtual #242                // Method android/support/constraint/a/e.a:(Ljava/lang/Object;)Landroid/support/constraint/a/h;
      34: astore        21
      36: aload_1
      37: aload         16
      39: getfield      #146                // Field t:Landroid/support/constraint/a/a/c;
      42: invokevirtual #242                // Method android/support/constraint/a/e.a:(Ljava/lang/Object;)Landroid/support/constraint/a/h;
      45: astore        18
      47: aload_1
      48: aload         16
      50: getfield      #150                // Field u:Landroid/support/constraint/a/a/c;
      53: invokevirtual #242                // Method android/support/constraint/a/e.a:(Ljava/lang/Object;)Landroid/support/constraint/a/h;
      56: astore        20
      58: aload         16
      60: getfield      #176                // Field B:Landroid/support/constraint/a/a/d;
      63: ifnull        447
      66: aload         16
      68: getfield      #176                // Field B:Landroid/support/constraint/a/a/d;
      71: ifnull        96
      74: aload         16
      76: getfield      #176                // Field B:Landroid/support/constraint/a/a/d;
      79: getfield      #174                // Field A:[Landroid/support/constraint/a/a/d$a;
      82: iconst_0
      83: aaload
      84: getstatic     #372                // Field android/support/constraint/a/a/d$a.b:Landroid/support/constraint/a/a/d$a;
      87: if_acmpne     96
      90: iconst_1
      91: istore        7
      93: goto          99
      96: iconst_0
      97: istore        7
      99: aload         16
     101: getfield      #176                // Field B:Landroid/support/constraint/a/a/d;
     104: ifnull        129
     107: aload         16
     109: getfield      #176                // Field B:Landroid/support/constraint/a/a/d;
     112: getfield      #174                // Field A:[Landroid/support/constraint/a/a/d$a;
     115: iconst_1
     116: aaload
     117: getstatic     #372                // Field android/support/constraint/a/a/d$a.b:Landroid/support/constraint/a/a/d$a;
     120: if_acmpne     129
     123: iconst_1
     124: istore        8
     126: goto          132
     129: iconst_0
     130: istore        8
     132: aload         16
     134: getfield      #134                // Field q:Landroid/support/constraint/a/a/c;
     137: getfield      #386                // Field android/support/constraint/a/a/c.c:Landroid/support/constraint/a/a/c;
     140: ifnull        162
     143: aload         16
     145: getfield      #134                // Field q:Landroid/support/constraint/a/a/c;
     148: getfield      #386                // Field android/support/constraint/a/a/c.c:Landroid/support/constraint/a/a/c;
     151: getfield      #386                // Field android/support/constraint/a/a/c.c:Landroid/support/constraint/a/a/c;
     154: aload         16
     156: getfield      #134                // Field q:Landroid/support/constraint/a/a/c;
     159: if_acmpeq     192
     162: aload         16
     164: getfield      #142                // Field s:Landroid/support/constraint/a/a/c;
     167: getfield      #386                // Field android/support/constraint/a/a/c.c:Landroid/support/constraint/a/a/c;
     170: ifnull        212
     173: aload         16
     175: getfield      #142                // Field s:Landroid/support/constraint/a/a/c;
     178: getfield      #386                // Field android/support/constraint/a/a/c.c:Landroid/support/constraint/a/a/c;
     181: getfield      #386                // Field android/support/constraint/a/a/c.c:Landroid/support/constraint/a/a/c;
     184: aload         16
     186: getfield      #142                // Field s:Landroid/support/constraint/a/a/c;
     189: if_acmpne     212
     192: aload         16
     194: getfield      #176                // Field B:Landroid/support/constraint/a/a/d;
     197: checkcast     #328                // class android/support/constraint/a/a/e
     200: aload         16
     202: iconst_0
     203: invokevirtual #389                // Method android/support/constraint/a/a/e.a:(Landroid/support/constraint/a/a/d;I)V
     206: iconst_1
     207: istore        9
     209: goto          215
     212: iconst_0
     213: istore        9
     215: aload         16
     217: getfield      #138                // Field r:Landroid/support/constraint/a/a/c;
     220: getfield      #386                // Field android/support/constraint/a/a/c.c:Landroid/support/constraint/a/a/c;
     223: ifnull        245
     226: aload         16
     228: getfield      #138                // Field r:Landroid/support/constraint/a/a/c;
     231: getfield      #386                // Field android/support/constraint/a/a/c.c:Landroid/support/constraint/a/a/c;
     234: getfield      #386                // Field android/support/constraint/a/a/c.c:Landroid/support/constraint/a/a/c;
     237: aload         16
     239: getfield      #138                // Field r:Landroid/support/constraint/a/a/c;
     242: if_acmpeq     275
     245: aload         16
     247: getfield      #146                // Field t:Landroid/support/constraint/a/a/c;
     250: getfield      #386                // Field android/support/constraint/a/a/c.c:Landroid/support/constraint/a/a/c;
     253: ifnull        295
     256: aload         16
     258: getfield      #146                // Field t:Landroid/support/constraint/a/a/c;
     261: getfield      #386                // Field android/support/constraint/a/a/c.c:Landroid/support/constraint/a/a/c;
     264: getfield      #386                // Field android/support/constraint/a/a/c.c:Landroid/support/constraint/a/a/c;
     267: aload         16
     269: getfield      #146                // Field t:Landroid/support/constraint/a/a/c;
     272: if_acmpne     295
     275: aload         16
     277: getfield      #176                // Field B:Landroid/support/constraint/a/a/d;
     280: checkcast     #328                // class android/support/constraint/a/a/e
     283: aload         16
     285: iconst_1
     286: invokevirtual #389                // Method android/support/constraint/a/a/e.a:(Landroid/support/constraint/a/a/d;I)V
     289: iconst_1
     290: istore        10
     292: goto          298
     295: iconst_0
     296: istore        10
     298: iload         7
     300: ifeq          355
     303: aload         16
     305: getfield      #212                // Field al:I
     308: bipush        8
     310: if_icmpeq     355
     313: aload         16
     315: getfield      #134                // Field q:Landroid/support/constraint/a/a/c;
     318: getfield      #386                // Field android/support/constraint/a/a/c.c:Landroid/support/constraint/a/a/c;
     321: ifnonnull     355
     324: aload         16
     326: getfield      #142                // Field s:Landroid/support/constraint/a/a/c;
     329: getfield      #386                // Field android/support/constraint/a/a/c.c:Landroid/support/constraint/a/a/c;
     332: ifnonnull     355
     335: aload_1
     336: aload_1
     337: aload         16
     339: getfield      #176                // Field B:Landroid/support/constraint/a/a/d;
     342: getfield      #142                // Field s:Landroid/support/constraint/a/a/c;
     345: invokevirtual #242                // Method android/support/constraint/a/e.a:(Ljava/lang/Object;)Landroid/support/constraint/a/h;
     348: aload         19
     350: iconst_0
     351: iconst_1
     352: invokevirtual #267                // Method android/support/constraint/a/e.a:(Landroid/support/constraint/a/h;Landroid/support/constraint/a/h;II)V
     355: iload         8
     357: ifeq          420
     360: aload         16
     362: getfield      #212                // Field al:I
     365: bipush        8
     367: if_icmpeq     420
     370: aload         16
     372: getfield      #138                // Field r:Landroid/support/constraint/a/a/c;
     375: getfield      #386                // Field android/support/constraint/a/a/c.c:Landroid/support/constraint/a/a/c;
     378: ifnonnull     420
     381: aload         16
     383: getfield      #146                // Field t:Landroid/support/constraint/a/a/c;
     386: getfield      #386                // Field android/support/constraint/a/a/c.c:Landroid/support/constraint/a/a/c;
     389: ifnonnull     420
     392: aload         16
     394: getfield      #150                // Field u:Landroid/support/constraint/a/a/c;
     397: ifnonnull     420
     400: aload_1
     401: aload_1
     402: aload         16
     404: getfield      #176                // Field B:Landroid/support/constraint/a/a/d;
     407: getfield      #146                // Field t:Landroid/support/constraint/a/a/c;
     410: invokevirtual #242                // Method android/support/constraint/a/e.a:(Ljava/lang/Object;)Landroid/support/constraint/a/h;
     413: aload         18
     415: iconst_0
     416: iconst_1
     417: invokevirtual #267                // Method android/support/constraint/a/e.a:(Landroid/support/constraint/a/h;Landroid/support/constraint/a/h;II)V
     420: iload         9
     422: istore        11
     424: iload         10
     426: istore        12
     428: iload         7
     430: istore        9
     432: iload         8
     434: istore        7
     436: iload         11
     438: istore        10
     440: iload         12
     442: istore        8
     444: goto          459
     447: iconst_0
     448: istore        9
     450: iconst_0
     451: istore        7
     453: iconst_0
     454: istore        10
     456: iconst_0
     457: istore        8
     459: aload         16
     461: getfield      #178                // Field C:I
     464: istore        4
     466: iload         4
     468: istore_3
     469: iload         4
     471: aload         16
     473: getfield      #360                // Field L:I
     476: if_icmpge     485
     479: aload         16
     481: getfield      #360                // Field L:I
     484: istore_3
     485: aload         16
     487: getfield      #180                // Field D:I
     490: istore        5
     492: iload         5
     494: istore        4
     496: iload         5
     498: aload         16
     500: getfield      #358                // Field M:I
     503: if_icmpge     513
     506: aload         16
     508: getfield      #358                // Field M:I
     511: istore        4
     513: aload         16
     515: getfield      #174                // Field A:[Landroid/support/constraint/a/a/d$a;
     518: iconst_0
     519: aaload
     520: getstatic     #391                // Field android/support/constraint/a/a/d$a.c:Landroid/support/constraint/a/a/d$a;
     523: if_acmpeq     532
     526: iconst_1
     527: istore        11
     529: goto          535
     532: iconst_0
     533: istore        11
     535: aload         16
     537: getfield      #174                // Field A:[Landroid/support/constraint/a/a/d$a;
     540: iconst_1
     541: aaload
     542: getstatic     #391                // Field android/support/constraint/a/a/d$a.c:Landroid/support/constraint/a/a/d$a;
     545: if_acmpeq     554
     548: iconst_1
     549: istore        12
     551: goto          557
     554: iconst_0
     555: istore        12
     557: aload         16
     559: aload         16
     561: getfield      #184                // Field F:I
     564: putfield      #115                // Field o:I
     567: aload         16
     569: aload         16
     571: getfield      #182                // Field E:F
     574: putfield      #117                // Field p:F
     577: aload         16
     579: getfield      #182                // Field E:F
     582: fconst_0
     583: fcmpl
     584: ifle          762
     587: aload         16
     589: getfield      #212                // Field al:I
     592: bipush        8
     594: if_icmpeq     762
     597: aload         16
     599: getfield      #174                // Field A:[Landroid/support/constraint/a/a/d$a;
     602: iconst_0
     603: aaload
     604: getstatic     #391                // Field android/support/constraint/a/a/d$a.c:Landroid/support/constraint/a/a/d$a;
     607: if_acmpne     642
     610: aload         16
     612: getfield      #174                // Field A:[Landroid/support/constraint/a/a/d$a;
     615: iconst_1
     616: aaload
     617: getstatic     #391                // Field android/support/constraint/a/a/d$a.c:Landroid/support/constraint/a/a/d$a;
     620: if_acmpne     642
     623: aload         16
     625: iload         9
     627: iload         7
     629: iload         11
     631: iload         12
     633: invokevirtual #394                // Method a:(ZZZZ)V
     636: iload_3
     637: istore        5
     639: goto          746
     642: aload         16
     644: getfield      #174                // Field A:[Landroid/support/constraint/a/a/d$a;
     647: iconst_0
     648: aaload
     649: getstatic     #391                // Field android/support/constraint/a/a/d$a.c:Landroid/support/constraint/a/a/d$a;
     652: if_acmpne     679
     655: aload         16
     657: iconst_0
     658: putfield      #115                // Field o:I
     661: aload         16
     663: getfield      #117                // Field p:F
     666: aload         16
     668: getfield      #180                // Field D:I
     671: i2f
     672: fmul
     673: f2i
     674: istore        5
     676: goto          746
     679: iload_3
     680: istore        5
     682: aload         16
     684: getfield      #174                // Field A:[Landroid/support/constraint/a/a/d$a;
     687: iconst_1
     688: aaload
     689: getstatic     #391                // Field android/support/constraint/a/a/d$a.c:Landroid/support/constraint/a/a/d$a;
     692: if_acmpne     746
     695: aload         16
     697: iconst_1
     698: putfield      #115                // Field o:I
     701: aload         16
     703: getfield      #184                // Field F:I
     706: iconst_m1
     707: if_icmpne     722
     710: aload         16
     712: fconst_1
     713: aload         16
     715: getfield      #117                // Field p:F
     718: fdiv
     719: putfield      #117                // Field p:F
     722: aload         16
     724: getfield      #117                // Field p:F
     727: aload         16
     729: getfield      #178                // Field C:I
     732: i2f
     733: fmul
     734: f2i
     735: istore        5
     737: iload_3
     738: istore        4
     740: iload         5
     742: istore_3
     743: goto          753
     746: iload         4
     748: istore_3
     749: iload         5
     751: istore        4
     753: iconst_1
     754: istore        5
     756: iload_3
     757: istore        6
     759: goto          772
     762: iconst_0
     763: istore        5
     765: iload         4
     767: istore        6
     769: iload_3
     770: istore        4
     772: iload         5
     774: ifeq          800
     777: aload         16
     779: getfield      #115                // Field o:I
     782: ifeq          794
     785: aload         16
     787: getfield      #115                // Field o:I
     790: iconst_m1
     791: if_icmpne     800
     794: iconst_1
     795: istore        11
     797: goto          803
     800: iconst_0
     801: istore        11
     803: aload         16
     805: getfield      #174                // Field A:[Landroid/support/constraint/a/a/d$a;
     808: iconst_0
     809: aaload
     810: getstatic     #372                // Field android/support/constraint/a/a/d$a.b:Landroid/support/constraint/a/a/d$a;
     813: if_acmpne     830
     816: aload         16
     818: instanceof    #328                // class android/support/constraint/a/a/e
     821: ifeq          830
     824: iconst_1
     825: istore        12
     827: goto          833
     830: iconst_0
     831: istore        12
     833: aload         16
     835: getfield      #162                // Field x:Landroid/support/constraint/a/a/c;
     838: invokevirtual #272                // Method android/support/constraint/a/a/c.j:()Z
     841: iconst_1
     842: ixor
     843: istore        13
     845: aload         16
     847: getfield      #95                 // Field a:I
     850: iconst_2
     851: if_icmpeq     994
     854: aload         16
     856: getfield      #176                // Field B:Landroid/support/constraint/a/a/d;
     859: ifnull        879
     862: aload_1
     863: aload         16
     865: getfield      #176                // Field B:Landroid/support/constraint/a/a/d;
     868: getfield      #142                // Field s:Landroid/support/constraint/a/a/c;
     871: invokevirtual #242                // Method android/support/constraint/a/e.a:(Ljava/lang/Object;)Landroid/support/constraint/a/h;
     874: astore        14
     876: goto          882
     879: aconst_null
     880: astore        14
     882: aload         16
     884: getfield      #176                // Field B:Landroid/support/constraint/a/a/d;
     887: ifnull        907
     890: aload_1
     891: aload         16
     893: getfield      #176                // Field B:Landroid/support/constraint/a/a/d;
     896: getfield      #134                // Field q:Landroid/support/constraint/a/a/c;
     899: invokevirtual #242                // Method android/support/constraint/a/e.a:(Ljava/lang/Object;)Landroid/support/constraint/a/h;
     902: astore        15
     904: goto          910
     907: aconst_null
     908: astore        15
     910: aload         16
     912: aload_1
     913: iload         9
     915: aload         15
     917: aload         14
     919: aload         16
     921: getfield      #174                // Field A:[Landroid/support/constraint/a/a/d$a;
     924: iconst_0
     925: aaload
     926: iload         12
     928: aload         16
     930: getfield      #134                // Field q:Landroid/support/constraint/a/a/c;
     933: aload         16
     935: getfield      #142                // Field s:Landroid/support/constraint/a/a/c;
     938: aload         16
     940: getfield      #186                // Field G:I
     943: iload         4
     945: aload         16
     947: getfield      #360                // Field L:I
     950: aload         16
     952: getfield      #120                // Field ab:[I
     955: iconst_0
     956: iaload
     957: aload         16
     959: getfield      #206                // Field O:F
     962: iload         11
     964: iload         10
     966: aload         16
     968: getfield      #99                 // Field e:I
     971: aload         16
     973: getfield      #103                // Field g:I
     976: aload         16
     978: getfield      #105                // Field h:I
     981: aload         16
     983: getfield      #107                // Field i:F
     986: iload         13
     988: invokespecial #396                // Method a:(Landroid/support/constraint/a/e;ZLandroid/support/constraint/a/h;Landroid/support/constraint/a/h;Landroid/support/constraint/a/a/d$a;ZLandroid/support/constraint/a/a/c;Landroid/support/constraint/a/a/c;IIIIFZZIIIFZ)V
     991: goto          994
     994: aload         21
     996: astore        16
     998: aload         20
    1000: astore        21
    1002: aload         19
    1004: astore        14
    1006: aload         18
    1008: astore        15
    1010: aload_0
    1011: astore        20
    1013: aload         20
    1015: getfield      #97                 // Field b:I
    1018: iconst_2
    1019: if_icmpne     1023
    1022: return
    1023: aload         20
    1025: getfield      #174                // Field A:[Landroid/support/constraint/a/a/d$a;
    1028: iconst_1
    1029: aaload
    1030: getstatic     #372                // Field android/support/constraint/a/a/d$a.b:Landroid/support/constraint/a/a/d$a;
    1033: if_acmpne     1050
    1036: aload         20
    1038: instanceof    #328                // class android/support/constraint/a/a/e
    1041: ifeq          1050
    1044: iconst_1
    1045: istore        9
    1047: goto          1053
    1050: iconst_0
    1051: istore        9
    1053: iload         5
    1055: ifeq          1082
    1058: aload         20
    1060: getfield      #115                // Field o:I
    1063: iconst_1
    1064: if_icmpeq     1076
    1067: aload         20
    1069: getfield      #115                // Field o:I
    1072: iconst_m1
    1073: if_icmpne     1082
    1076: iconst_1
    1077: istore        10
    1079: goto          1085
    1082: iconst_0
    1083: istore        10
    1085: aload         20
    1087: getfield      #202                // Field K:I
    1090: ifle          1183
    1093: aload         20
    1095: getfield      #150                // Field u:Landroid/support/constraint/a/a/c;
    1098: invokevirtual #250                // Method android/support/constraint/a/a/c.a:()Landroid/support/constraint/a/a/j;
    1101: getfield      #254                // Field android/support/constraint/a/a/j.i:I
    1104: iconst_1
    1105: if_icmpne     1123
    1108: aload         20
    1110: getfield      #150                // Field u:Landroid/support/constraint/a/a/c;
    1113: invokevirtual #250                // Method android/support/constraint/a/a/c.a:()Landroid/support/constraint/a/a/j;
    1116: aload_1
    1117: invokevirtual #264                // Method android/support/constraint/a/a/j.a:(Landroid/support/constraint/a/e;)V
    1120: goto          1183
    1123: aload_1
    1124: astore        18
    1126: aload         18
    1128: aload         21
    1130: aload         16
    1132: aload_0
    1133: invokevirtual #398                // Method A:()I
    1136: bipush        6
    1138: invokevirtual #286                // Method android/support/constraint/a/e.c:(Landroid/support/constraint/a/h;Landroid/support/constraint/a/h;II)Landroid/support/constraint/a/b;
    1141: pop
    1142: aload         20
    1144: getfield      #150                // Field u:Landroid/support/constraint/a/a/c;
    1147: getfield      #386                // Field android/support/constraint/a/a/c.c:Landroid/support/constraint/a/a/c;
    1150: ifnull        1183
    1153: aload         18
    1155: aload         21
    1157: aload         18
    1159: aload         20
    1161: getfield      #150                // Field u:Landroid/support/constraint/a/a/c;
    1164: getfield      #386                // Field android/support/constraint/a/a/c.c:Landroid/support/constraint/a/a/c;
    1167: invokevirtual #242                // Method android/support/constraint/a/e.a:(Ljava/lang/Object;)Landroid/support/constraint/a/h;
    1170: iconst_0
    1171: bipush        6
    1173: invokevirtual #286                // Method android/support/constraint/a/e.c:(Landroid/support/constraint/a/h;Landroid/support/constraint/a/h;II)Landroid/support/constraint/a/b;
    1176: pop
    1177: iconst_0
    1178: istore        11
    1180: goto          1187
    1183: iload         13
    1185: istore        11
    1187: aload_1
    1188: astore        21
    1190: aload         20
    1192: getfield      #176                // Field B:Landroid/support/constraint/a/a/d;
    1195: ifnull        1216
    1198: aload         21
    1200: aload         20
    1202: getfield      #176                // Field B:Landroid/support/constraint/a/a/d;
    1205: getfield      #146                // Field t:Landroid/support/constraint/a/a/c;
    1208: invokevirtual #242                // Method android/support/constraint/a/e.a:(Ljava/lang/Object;)Landroid/support/constraint/a/h;
    1211: astore        18
    1213: goto          1219
    1216: aconst_null
    1217: astore        18
    1219: aload         20
    1221: getfield      #176                // Field B:Landroid/support/constraint/a/a/d;
    1224: ifnull        1245
    1227: aload         21
    1229: aload         20
    1231: getfield      #176                // Field B:Landroid/support/constraint/a/a/d;
    1234: getfield      #138                // Field r:Landroid/support/constraint/a/a/c;
    1237: invokevirtual #242                // Method android/support/constraint/a/e.a:(Ljava/lang/Object;)Landroid/support/constraint/a/h;
    1240: astore        19
    1242: goto          1248
    1245: aconst_null
    1246: astore        19
    1248: aload         20
    1250: aload         21
    1252: iload         7
    1254: aload         19
    1256: aload         18
    1258: aload         20
    1260: getfield      #174                // Field A:[Landroid/support/constraint/a/a/d$a;
    1263: iconst_1
    1264: aaload
    1265: iload         9
    1267: aload         20
    1269: getfield      #138                // Field r:Landroid/support/constraint/a/a/c;
    1272: aload         20
    1274: getfield      #146                // Field t:Landroid/support/constraint/a/a/c;
    1277: aload         20
    1279: getfield      #188                // Field H:I
    1282: iload         6
    1284: aload         20
    1286: getfield      #358                // Field M:I
    1289: aload         20
    1291: getfield      #120                // Field ab:[I
    1294: iconst_1
    1295: iaload
    1296: aload         20
    1298: getfield      #208                // Field P:F
    1301: iload         10
    1303: iload         8
    1305: aload         20
    1307: getfield      #101                // Field f:I
    1310: aload         20
    1312: getfield      #109                // Field j:I
    1315: aload         20
    1317: getfield      #111                // Field k:I
    1320: aload         20
    1322: getfield      #113                // Field l:F
    1325: iload         11
    1327: invokespecial #396                // Method a:(Landroid/support/constraint/a/e;ZLandroid/support/constraint/a/h;Landroid/support/constraint/a/h;Landroid/support/constraint/a/a/d$a;ZLandroid/support/constraint/a/a/c;Landroid/support/constraint/a/a/c;IIIIFZZIIIFZ)V
    1330: iload         5
    1332: ifeq          1404
    1335: aload_0
    1336: astore        18
    1338: aload         18
    1340: getfield      #115                // Field o:I
    1343: iconst_1
    1344: if_icmpne     1371
    1347: aload         18
    1349: getfield      #117                // Field p:F
    1352: fstore_2
    1353: aload_1
    1354: aload         15
    1356: aload         16
    1358: aload         14
    1360: aload         17
    1362: fload_2
    1363: bipush        6
    1365: invokevirtual #401                // Method android/support/constraint/a/e.a:(Landroid/support/constraint/a/h;Landroid/support/constraint/a/h;Landroid/support/constraint/a/h;Landroid/support/constraint/a/h;FI)V
    1368: goto          1404
    1371: aload         18
    1373: getfield      #117                // Field p:F
    1376: fstore_2
    1377: aload         15
    1379: astore        18
    1381: aload         16
    1383: astore        19
    1385: aload         14
    1387: astore        15
    1389: aload         17
    1391: astore        16
    1393: aload         18
    1395: astore        14
    1397: aload         19
    1399: astore        17
    1401: goto          1353
    1404: aload_0
    1405: astore        14
    1407: aload         14
    1409: getfield      #162                // Field x:Landroid/support/constraint/a/a/c;
    1412: invokevirtual #272                // Method android/support/constraint/a/a/c.j:()Z
    1415: ifeq          1457
    1418: aload_1
    1419: aload         14
    1421: aload         14
    1423: getfield      #162                // Field x:Landroid/support/constraint/a/a/c;
    1426: invokevirtual #245                // Method android/support/constraint/a/a/c.g:()Landroid/support/constraint/a/a/c;
    1429: invokevirtual #403                // Method android/support/constraint/a/a/c.c:()Landroid/support/constraint/a/a/d;
    1432: aload         14
    1434: getfield      #122                // Field ac:F
    1437: ldc_w         #404                // float 90.0f
    1440: fadd
    1441: f2d
    1442: invokestatic  #408                // Method java/lang/Math.toRadians:(D)D
    1445: d2f
    1446: aload         14
    1448: getfield      #162                // Field x:Landroid/support/constraint/a/a/c;
    1451: invokevirtual #283                // Method android/support/constraint/a/a/c.e:()I
    1454: invokevirtual #411                // Method android/support/constraint/a/e.a:(Landroid/support/constraint/a/a/d;Landroid/support/constraint/a/a/d;FI)V
    1457: return

  public void a(java.lang.Object);
    Code:
       0: aload_0
       1: aload_1
       2: putfield      #320                // Field aj:Ljava/lang/Object;
       5: return

  public void a(java.lang.String);
    Code:
       0: aload_0
       1: aload_1
       2: putfield      #214                // Field am:Ljava/lang/String;
       5: return

  public void a(boolean, boolean, boolean, boolean);
    Code:
       0: aload_0
       1: getfield      #99                 // Field e:I
       4: ifne          12
       7: aload_0
       8: iconst_3
       9: putfield      #99                 // Field e:I
      12: aload_0
      13: getfield      #101                // Field f:I
      16: ifne          24
      19: aload_0
      20: iconst_3
      21: putfield      #101                // Field f:I
      24: aload_0
      25: getfield      #115                // Field o:I
      28: iconst_m1
      29: if_icmpne     81
      32: iload_3
      33: ifeq          49
      36: iload         4
      38: ifne          49
      41: aload_0
      42: iconst_0
      43: putfield      #115                // Field o:I
      46: goto          81
      49: iload_3
      50: ifne          81
      53: iload         4
      55: ifeq          81
      58: aload_0
      59: iconst_1
      60: putfield      #115                // Field o:I
      63: aload_0
      64: getfield      #184                // Field F:I
      67: iconst_m1
      68: if_icmpne     81
      71: aload_0
      72: fconst_1
      73: aload_0
      74: getfield      #117                // Field p:F
      77: fdiv
      78: putfield      #117                // Field p:F
      81: aload_0
      82: getfield      #115                // Field o:I
      85: ifne          116
      88: aload_0
      89: getfield      #138                // Field r:Landroid/support/constraint/a/a/c;
      92: invokevirtual #272                // Method android/support/constraint/a/a/c.j:()Z
      95: ifeq          108
      98: aload_0
      99: getfield      #146                // Field t:Landroid/support/constraint/a/a/c;
     102: invokevirtual #272                // Method android/support/constraint/a/a/c.j:()Z
     105: ifne          116
     108: aload_0
     109: iconst_1
     110: putfield      #115                // Field o:I
     113: goto          149
     116: aload_0
     117: getfield      #115                // Field o:I
     120: iconst_1
     121: if_icmpne     149
     124: aload_0
     125: getfield      #134                // Field q:Landroid/support/constraint/a/a/c;
     128: invokevirtual #272                // Method android/support/constraint/a/a/c.j:()Z
     131: ifeq          144
     134: aload_0
     135: getfield      #142                // Field s:Landroid/support/constraint/a/a/c;
     138: invokevirtual #272                // Method android/support/constraint/a/a/c.j:()Z
     141: ifne          149
     144: aload_0
     145: iconst_0
     146: putfield      #115                // Field o:I
     149: aload_0
     150: getfield      #115                // Field o:I
     153: iconst_m1
     154: if_icmpne     260
     157: aload_0
     158: getfield      #138                // Field r:Landroid/support/constraint/a/a/c;
     161: invokevirtual #272                // Method android/support/constraint/a/a/c.j:()Z
     164: ifeq          197
     167: aload_0
     168: getfield      #146                // Field t:Landroid/support/constraint/a/a/c;
     171: invokevirtual #272                // Method android/support/constraint/a/a/c.j:()Z
     174: ifeq          197
     177: aload_0
     178: getfield      #134                // Field q:Landroid/support/constraint/a/a/c;
     181: invokevirtual #272                // Method android/support/constraint/a/a/c.j:()Z
     184: ifeq          197
     187: aload_0
     188: getfield      #142                // Field s:Landroid/support/constraint/a/a/c;
     191: invokevirtual #272                // Method android/support/constraint/a/a/c.j:()Z
     194: ifne          260
     197: aload_0
     198: getfield      #138                // Field r:Landroid/support/constraint/a/a/c;
     201: invokevirtual #272                // Method android/support/constraint/a/a/c.j:()Z
     204: ifeq          225
     207: aload_0
     208: getfield      #146                // Field t:Landroid/support/constraint/a/a/c;
     211: invokevirtual #272                // Method android/support/constraint/a/a/c.j:()Z
     214: ifeq          225
     217: aload_0
     218: iconst_0
     219: putfield      #115                // Field o:I
     222: goto          260
     225: aload_0
     226: getfield      #134                // Field q:Landroid/support/constraint/a/a/c;
     229: invokevirtual #272                // Method android/support/constraint/a/a/c.j:()Z
     232: ifeq          260
     235: aload_0
     236: getfield      #142                // Field s:Landroid/support/constraint/a/a/c;
     239: invokevirtual #272                // Method android/support/constraint/a/a/c.j:()Z
     242: ifeq          260
     245: aload_0
     246: fconst_1
     247: aload_0
     248: getfield      #117                // Field p:F
     251: fdiv
     252: putfield      #117                // Field p:F
     255: aload_0
     256: iconst_1
     257: putfield      #115                // Field o:I
     260: aload_0
     261: getfield      #115                // Field o:I
     264: iconst_m1
     265: if_icmpne     307
     268: iload_1
     269: ifeq          284
     272: iload_2
     273: ifne          284
     276: aload_0
     277: iconst_0
     278: putfield      #115                // Field o:I
     281: goto          307
     284: iload_1
     285: ifne          307
     288: iload_2
     289: ifeq          307
     292: aload_0
     293: fconst_1
     294: aload_0
     295: getfield      #117                // Field p:F
     298: fdiv
     299: putfield      #117                // Field p:F
     302: aload_0
     303: iconst_1
     304: putfield      #115                // Field o:I
     307: aload_0
     308: getfield      #115                // Field o:I
     311: iconst_m1
     312: if_icmpne     363
     315: aload_0
     316: getfield      #103                // Field g:I
     319: ifle          335
     322: aload_0
     323: getfield      #109                // Field j:I
     326: ifne          335
     329: aload_0
     330: iconst_0
     331: putfield      #115                // Field o:I
     334: return
     335: aload_0
     336: getfield      #103                // Field g:I
     339: ifne          348
     342: aload_0
     343: getfield      #109                // Field j:I
     346: istore        5
     348: aload_0
     349: fconst_1
     350: aload_0
     351: getfield      #117                // Field p:F
     354: fdiv
     355: putfield      #117                // Field p:F
     358: aload_0
     359: iconst_1
     360: putfield      #115                // Field o:I
     363: return

  public boolean a();
    Code:
       0: aload_0
       1: getfield      #212                // Field al:I
       4: bipush        8
       6: if_icmpeq     11
       9: iconst_1
      10: ireturn
      11: iconst_0
      12: ireturn

  public void b();
    Code:
       0: iconst_0
       1: istore_1
       2: iload_1
       3: bipush        6
       5: if_icmpge     27
       8: aload_0
       9: getfield      #164                // Field y:[Landroid/support/constraint/a/a/c;
      12: iload_1
      13: aaload
      14: invokevirtual #250                // Method android/support/constraint/a/a/c.a:()Landroid/support/constraint/a/a/j;
      17: invokevirtual #414                // Method android/support/constraint/a/a/j.b:()V
      20: iload_1
      21: iconst_1
      22: iadd
      23: istore_1
      24: goto          2
      27: return

  public void b(float);
    Code:
       0: aload_0
       1: fload_1
       2: putfield      #208                // Field P:F
       5: return

  public void b(int);
    Code:
       0: iload_1
       1: aload_0
       2: invokestatic  #419                // Method android/support/constraint/a/a/h.a:(ILandroid/support/constraint/a/a/d;)V
       5: return

  public void b(int, int);
    Code:
       0: aload_0
       1: iload_1
       2: putfield      #198                // Field I:I
       5: aload_0
       6: iload_2
       7: putfield      #200                // Field J:I
      10: return

  public void b(int, int, int, float);
    Code:
       0: aload_0
       1: iload_1
       2: putfield      #101                // Field f:I
       5: aload_0
       6: iload_2
       7: putfield      #109                // Field j:I
      10: aload_0
      11: iload_3
      12: putfield      #111                // Field k:I
      15: aload_0
      16: fload         4
      18: putfield      #113                // Field l:F
      21: fload         4
      23: fconst_1
      24: fcmpg
      25: ifge          40
      28: aload_0
      29: getfield      #101                // Field f:I
      32: ifne          40
      35: aload_0
      36: iconst_2
      37: putfield      #101                // Field f:I
      40: return

  public void b(android.support.constraint.a.a.d$a);
    Code:
       0: aload_0
       1: getfield      #174                // Field A:[Landroid/support/constraint/a/a/d$a;
       4: iconst_1
       5: aload_1
       6: aastore
       7: aload_1
       8: getstatic     #372                // Field android/support/constraint/a/a/d$a.b:Landroid/support/constraint/a/a/d$a;
      11: if_acmpne     22
      14: aload_0
      15: aload_0
      16: getfield      #421                // Field ai:I
      19: invokevirtual #423                // Method i:(I)V
      22: return

  public void b(android.support.constraint.a.e);
    Code:
       0: aload_0
       1: aload_1
       2: aload_0
       3: getfield      #134                // Field q:Landroid/support/constraint/a/a/c;
       6: invokevirtual #426                // Method android/support/constraint/a/e.b:(Ljava/lang/Object;)I
       9: aload_1
      10: aload_0
      11: getfield      #138                // Field r:Landroid/support/constraint/a/a/c;
      14: invokevirtual #426                // Method android/support/constraint/a/e.b:(Ljava/lang/Object;)I
      17: aload_1
      18: aload_0
      19: getfield      #142                // Field s:Landroid/support/constraint/a/a/c;
      22: invokevirtual #426                // Method android/support/constraint/a/e.b:(Ljava/lang/Object;)I
      25: aload_1
      26: aload_0
      27: getfield      #146                // Field t:Landroid/support/constraint/a/a/c;
      30: invokevirtual #426                // Method android/support/constraint/a/e.b:(Ljava/lang/Object;)I
      33: invokevirtual #428                // Method a:(IIII)V
      36: return

  public void b(java.lang.String);
    Code:
       0: aload_1
       1: ifnull        261
       4: aload_1
       5: invokevirtual #435                // Method java/lang/String.length:()I
       8: ifne          14
      11: goto          261
      14: iconst_m1
      15: istore        6
      17: aload_1
      18: invokevirtual #435                // Method java/lang/String.length:()I
      21: istore        8
      23: aload_1
      24: bipush        44
      26: invokevirtual #439                // Method java/lang/String.indexOf:(I)I
      29: istore        9
      31: iconst_0
      32: istore        7
      34: iload         6
      36: istore        4
      38: iload         7
      40: istore        5
      42: iload         9
      44: ifle          114
      47: iload         6
      49: istore        4
      51: iload         7
      53: istore        5
      55: iload         9
      57: iload         8
      59: iconst_1
      60: isub
      61: if_icmpge     114
      64: aload_1
      65: iconst_0
      66: iload         9
      68: invokevirtual #443                // Method java/lang/String.substring:(II)Ljava/lang/String;
      71: astore        10
      73: aload         10
      75: ldc_w         #444                // String W
      78: invokevirtual #448                // Method java/lang/String.equalsIgnoreCase:(Ljava/lang/String;)Z
      81: ifeq          90
      84: iconst_0
      85: istore        4
      87: goto          108
      90: iload         6
      92: istore        4
      94: aload         10
      96: ldc_w         #449                // String H
      99: invokevirtual #448                // Method java/lang/String.equalsIgnoreCase:(Ljava/lang/String;)Z
     102: ifeq          108
     105: iconst_1
     106: istore        4
     108: iload         9
     110: iconst_1
     111: iadd
     112: istore        5
     114: aload_1
     115: bipush        58
     117: invokevirtual #439                // Method java/lang/String.indexOf:(I)I
     120: istore        6
     122: iload         6
     124: iflt          219
     127: iload         6
     129: iload         8
     131: iconst_1
     132: isub
     133: if_icmpge     219
     136: aload_1
     137: iload         5
     139: iload         6
     141: invokevirtual #443                // Method java/lang/String.substring:(II)Ljava/lang/String;
     144: astore        10
     146: aload_1
     147: iload         6
     149: iconst_1
     150: iadd
     151: invokevirtual #452                // Method java/lang/String.substring:(I)Ljava/lang/String;
     154: astore_1
     155: aload         10
     157: invokevirtual #435                // Method java/lang/String.length:()I
     160: ifle          241
     163: aload_1
     164: invokevirtual #435                // Method java/lang/String.length:()I
     167: ifle          241
     170: aload         10
     172: invokestatic  #458                // Method java/lang/Float.parseFloat:(Ljava/lang/String;)F
     175: fstore_2
     176: aload_1
     177: invokestatic  #458                // Method java/lang/Float.parseFloat:(Ljava/lang/String;)F
     180: fstore_3
     181: fload_2
     182: fconst_0
     183: fcmpl
     184: ifle          241
     187: fload_3
     188: fconst_0
     189: fcmpl
     190: ifle          241
     193: iload         4
     195: iconst_1
     196: if_icmpne     209
     199: fload_3
     200: fload_2
     201: fdiv
     202: invokestatic  #462                // Method java/lang/Math.abs:(F)F
     205: fstore_2
     206: goto          243
     209: fload_2
     210: fload_3
     211: fdiv
     212: invokestatic  #462                // Method java/lang/Math.abs:(F)F
     215: fstore_2
     216: goto          243
     219: aload_1
     220: iload         5
     222: invokevirtual #452                // Method java/lang/String.substring:(I)Ljava/lang/String;
     225: astore_1
     226: aload_1
     227: invokevirtual #435                // Method java/lang/String.length:()I
     230: ifle          241
     233: aload_1
     234: invokestatic  #458                // Method java/lang/Float.parseFloat:(Ljava/lang/String;)F
     237: fstore_2
     238: goto          243
     241: fconst_0
     242: fstore_2
     243: fload_2
     244: fconst_0
     245: fcmpl
     246: ifle          260
     249: aload_0
     250: fload_2
     251: putfield      #182                // Field E:F
     254: aload_0
     255: iload         4
     257: putfield      #184                // Field F:I
     260: return
     261: aload_0
     262: fconst_0
     263: putfield      #182                // Field E:F
     266: return
     267: astore_1
     268: goto          241
    Exception table:
       from    to  target type
         170   181   267   Class java/lang/NumberFormatException
         199   206   267   Class java/lang/NumberFormatException
         209   216   267   Class java/lang/NumberFormatException
         233   238   267   Class java/lang/NumberFormatException

  public void b(boolean);
    Code:
       0: aload_0
       1: iload_1
       2: putfield      #465                // Field m:Z
       5: return

  public void c();
    Code:
       0: return

  public void c(float);
    Code:
       0: aload_0
       1: getfield      #222                // Field W:[F
       4: iconst_0
       5: fload_1
       6: fastore
       7: return

  public void c(int);
    Code:
       0: aload_0
       1: getfield      #120                // Field ab:[I
       4: iconst_0
       5: iload_1
       6: iastore
       7: return

  public void c(int, int);
    Code:
       0: aload_0
       1: iload_1
       2: putfield      #186                // Field G:I
       5: aload_0
       6: iload_2
       7: iload_1
       8: isub
       9: putfield      #178                // Field C:I
      12: aload_0
      13: getfield      #178                // Field C:I
      16: aload_0
      17: getfield      #360                // Field L:I
      20: if_icmpge     31
      23: aload_0
      24: aload_0
      25: getfield      #360                // Field L:I
      28: putfield      #178                // Field C:I
      31: return

  public void c(boolean);
    Code:
       0: aload_0
       1: iload_1
       2: putfield      #467                // Field n:Z
       5: return

  public void d(float);
    Code:
       0: aload_0
       1: getfield      #222                // Field W:[F
       4: iconst_1
       5: fload_1
       6: fastore
       7: return

  public void d(int);
    Code:
       0: aload_0
       1: getfield      #120                // Field ab:[I
       4: iconst_1
       5: iload_1
       6: iastore
       7: return

  public void d(int, int);
    Code:
       0: aload_0
       1: iload_1
       2: putfield      #188                // Field H:I
       5: aload_0
       6: iload_2
       7: iload_1
       8: isub
       9: putfield      #180                // Field D:I
      12: aload_0
      13: getfield      #180                // Field D:I
      16: aload_0
      17: getfield      #358                // Field M:I
      20: if_icmpge     31
      23: aload_0
      24: aload_0
      25: getfield      #358                // Field M:I
      28: putfield      #180                // Field D:I
      31: return

  public boolean d();
    Code:
       0: aload_0
       1: getfield      #99                 // Field e:I
       4: istore_1
       5: iconst_0
       6: istore_3
       7: iload_3
       8: istore_2
       9: iload_1
      10: ifne          58
      13: iload_3
      14: istore_2
      15: aload_0
      16: getfield      #182                // Field E:F
      19: fconst_0
      20: fcmpl
      21: ifne          58
      24: iload_3
      25: istore_2
      26: aload_0
      27: getfield      #103                // Field g:I
      30: ifne          58
      33: iload_3
      34: istore_2
      35: aload_0
      36: getfield      #105                // Field h:I
      39: ifne          58
      42: iload_3
      43: istore_2
      44: aload_0
      45: getfield      #174                // Field A:[Landroid/support/constraint/a/a/d$a;
      48: iconst_0
      49: aaload
      50: getstatic     #391                // Field android/support/constraint/a/a/d$a.c:Landroid/support/constraint/a/a/d$a;
      53: if_acmpne     58
      56: iconst_1
      57: istore_2
      58: iload_2
      59: ireturn

  public void e(int);
    Code:
       0: aload_0
       1: iload_1
       2: putfield      #212                // Field al:I
       5: return

  public boolean e();
    Code:
       0: aload_0
       1: getfield      #101                // Field f:I
       4: ifne          44
       7: aload_0
       8: getfield      #182                // Field E:F
      11: fconst_0
      12: fcmpl
      13: ifne          44
      16: aload_0
      17: getfield      #109                // Field j:I
      20: ifne          44
      23: aload_0
      24: getfield      #111                // Field k:I
      27: ifne          44
      30: aload_0
      31: getfield      #174                // Field A:[Landroid/support/constraint/a/a/d$a;
      34: iconst_1
      35: aaload
      36: getstatic     #391                // Field android/support/constraint/a/a/d$a.c:Landroid/support/constraint/a/a/d$a;
      39: if_acmpne     44
      42: iconst_1
      43: ireturn
      44: iconst_0
      45: ireturn

  public void f();
    Code:
       0: aload_0
       1: getfield      #134                // Field q:Landroid/support/constraint/a/a/c;
       4: invokevirtual #339                // Method android/support/constraint/a/a/c.i:()V
       7: aload_0
       8: getfield      #138                // Field r:Landroid/support/constraint/a/a/c;
      11: invokevirtual #339                // Method android/support/constraint/a/a/c.i:()V
      14: aload_0
      15: getfield      #142                // Field s:Landroid/support/constraint/a/a/c;
      18: invokevirtual #339                // Method android/support/constraint/a/a/c.i:()V
      21: aload_0
      22: getfield      #146                // Field t:Landroid/support/constraint/a/a/c;
      25: invokevirtual #339                // Method android/support/constraint/a/a/c.i:()V
      28: aload_0
      29: getfield      #150                // Field u:Landroid/support/constraint/a/a/c;
      32: invokevirtual #339                // Method android/support/constraint/a/a/c.i:()V
      35: aload_0
      36: getfield      #154                // Field v:Landroid/support/constraint/a/a/c;
      39: invokevirtual #339                // Method android/support/constraint/a/a/c.i:()V
      42: aload_0
      43: getfield      #158                // Field w:Landroid/support/constraint/a/a/c;
      46: invokevirtual #339                // Method android/support/constraint/a/a/c.i:()V
      49: aload_0
      50: getfield      #162                // Field x:Landroid/support/constraint/a/a/c;
      53: invokevirtual #339                // Method android/support/constraint/a/a/c.i:()V
      56: aload_0
      57: aconst_null
      58: putfield      #176                // Field B:Landroid/support/constraint/a/a/d;
      61: aload_0
      62: fconst_0
      63: putfield      #122                // Field ac:F
      66: aload_0
      67: iconst_0
      68: putfield      #178                // Field C:I
      71: aload_0
      72: iconst_0
      73: putfield      #180                // Field D:I
      76: aload_0
      77: fconst_0
      78: putfield      #182                // Field E:F
      81: aload_0
      82: iconst_m1
      83: putfield      #184                // Field F:I
      86: aload_0
      87: iconst_0
      88: putfield      #186                // Field G:I
      91: aload_0
      92: iconst_0
      93: putfield      #188                // Field H:I
      96: aload_0
      97: iconst_0
      98: putfield      #190                // Field ad:I
     101: aload_0
     102: iconst_0
     103: putfield      #192                // Field ae:I
     106: aload_0
     107: iconst_0
     108: putfield      #194                // Field af:I
     111: aload_0
     112: iconst_0
     113: putfield      #196                // Field ag:I
     116: aload_0
     117: iconst_0
     118: putfield      #198                // Field I:I
     121: aload_0
     122: iconst_0
     123: putfield      #200                // Field J:I
     126: aload_0
     127: iconst_0
     128: putfield      #202                // Field K:I
     131: aload_0
     132: iconst_0
     133: putfield      #360                // Field L:I
     136: aload_0
     137: iconst_0
     138: putfield      #358                // Field M:I
     141: aload_0
     142: iconst_0
     143: putfield      #374                // Field ah:I
     146: aload_0
     147: iconst_0
     148: putfield      #421                // Field ai:I
     151: aload_0
     152: getstatic     #204                // Field N:F
     155: putfield      #206                // Field O:F
     158: aload_0
     159: getstatic     #204                // Field N:F
     162: putfield      #208                // Field P:F
     165: aload_0
     166: getfield      #174                // Field A:[Landroid/support/constraint/a/a/d$a;
     169: iconst_0
     170: getstatic     #172                // Field android/support/constraint/a/a/d$a.a:Landroid/support/constraint/a/a/d$a;
     173: aastore
     174: aload_0
     175: getfield      #174                // Field A:[Landroid/support/constraint/a/a/d$a;
     178: iconst_1
     179: getstatic     #172                // Field android/support/constraint/a/a/d$a.a:Landroid/support/constraint/a/a/d$a;
     182: aastore
     183: aload_0
     184: aconst_null
     185: putfield      #320                // Field aj:Ljava/lang/Object;
     188: aload_0
     189: iconst_0
     190: putfield      #210                // Field ak:I
     193: aload_0
     194: iconst_0
     195: putfield      #212                // Field al:I
     198: aload_0
     199: aconst_null
     200: putfield      #216                // Field an:Ljava/lang/String;
     203: aload_0
     204: iconst_0
     205: putfield      #469                // Field Q:Z
     208: aload_0
     209: iconst_0
     210: putfield      #471                // Field R:Z
     213: aload_0
     214: iconst_0
     215: putfield      #218                // Field S:I
     218: aload_0
     219: iconst_0
     220: putfield      #220                // Field T:I
     223: aload_0
     224: iconst_0
     225: putfield      #473                // Field U:Z
     228: aload_0
     229: iconst_0
     230: putfield      #475                // Field V:Z
     233: aload_0
     234: getfield      #222                // Field W:[F
     237: iconst_0
     238: fconst_0
     239: fastore
     240: aload_0
     241: getfield      #222                // Field W:[F
     244: iconst_1
     245: fconst_0
     246: fastore
     247: aload_0
     248: iconst_m1
     249: putfield      #95                 // Field a:I
     252: aload_0
     253: iconst_m1
     254: putfield      #97                 // Field b:I
     257: aload_0
     258: getfield      #120                // Field ab:[I
     261: iconst_0
     262: ldc           #118                // int 2147483647
     264: iastore
     265: aload_0
     266: getfield      #120                // Field ab:[I
     269: iconst_1
     270: ldc           #118                // int 2147483647
     272: iastore
     273: aload_0
     274: iconst_0
     275: putfield      #99                 // Field e:I
     278: aload_0
     279: iconst_0
     280: putfield      #101                // Field f:I
     283: aload_0
     284: fconst_1
     285: putfield      #107                // Field i:F
     288: aload_0
     289: fconst_1
     290: putfield      #113                // Field l:F
     293: aload_0
     294: ldc           #118                // int 2147483647
     296: putfield      #105                // Field h:I
     299: aload_0
     300: ldc           #118                // int 2147483647
     302: putfield      #111                // Field k:I
     305: aload_0
     306: iconst_0
     307: putfield      #103                // Field g:I
     310: aload_0
     311: iconst_0
     312: putfield      #109                // Field j:I
     315: aload_0
     316: iconst_m1
     317: putfield      #115                // Field o:I
     320: aload_0
     321: fconst_1
     322: putfield      #117                // Field p:F
     325: aload_0
     326: getfield      #477                // Field c:Landroid/support/constraint/a/a/k;
     329: ifnull        339
     332: aload_0
     333: getfield      #477                // Field c:Landroid/support/constraint/a/a/k;
     336: invokevirtual #480                // Method android/support/constraint/a/a/k.b:()V
     339: aload_0
     340: getfield      #482                // Field d:Landroid/support/constraint/a/a/k;
     343: ifnull        353
     346: aload_0
     347: getfield      #482                // Field d:Landroid/support/constraint/a/a/k;
     350: invokevirtual #480                // Method android/support/constraint/a/a/k.b:()V
     353: return

  public void f(int);
    Code:
       0: aload_0
       1: iload_1
       2: putfield      #186                // Field G:I
       5: return

  public void g();
    Code:
       0: iconst_0
       1: istore_1
       2: iload_1
       3: bipush        6
       5: if_icmpge     27
       8: aload_0
       9: getfield      #164                // Field y:[Landroid/support/constraint/a/a/c;
      12: iload_1
      13: aaload
      14: invokevirtual #250                // Method android/support/constraint/a/a/c.a:()Landroid/support/constraint/a/a/j;
      17: invokevirtual #484                // Method android/support/constraint/a/a/j.c:()V
      20: iload_1
      21: iconst_1
      22: iadd
      23: istore_1
      24: goto          2
      27: return

  public void g(int);
    Code:
       0: aload_0
       1: iload_1
       2: putfield      #188                // Field H:I
       5: return

  public android.support.constraint.a.a.k h();
    Code:
       0: aload_0
       1: getfield      #477                // Field c:Landroid/support/constraint/a/a/k;
       4: ifnonnull     18
       7: aload_0
       8: new           #479                // class android/support/constraint/a/a/k
      11: dup
      12: invokespecial #486                // Method android/support/constraint/a/a/k."<init>":()V
      15: putfield      #477                // Field c:Landroid/support/constraint/a/a/k;
      18: aload_0
      19: getfield      #477                // Field c:Landroid/support/constraint/a/a/k;
      22: areturn

  public void h(int);
    Code:
       0: aload_0
       1: iload_1
       2: putfield      #178                // Field C:I
       5: aload_0
       6: getfield      #178                // Field C:I
       9: aload_0
      10: getfield      #360                // Field L:I
      13: if_icmpge     24
      16: aload_0
      17: aload_0
      18: getfield      #360                // Field L:I
      21: putfield      #178                // Field C:I
      24: return

  public android.support.constraint.a.a.k i();
    Code:
       0: aload_0
       1: getfield      #482                // Field d:Landroid/support/constraint/a/a/k;
       4: ifnonnull     18
       7: aload_0
       8: new           #479                // class android/support/constraint/a/a/k
      11: dup
      12: invokespecial #486                // Method android/support/constraint/a/a/k."<init>":()V
      15: putfield      #482                // Field d:Landroid/support/constraint/a/a/k;
      18: aload_0
      19: getfield      #482                // Field d:Landroid/support/constraint/a/a/k;
      22: areturn

  public void i(int);
    Code:
       0: aload_0
       1: iload_1
       2: putfield      #180                // Field D:I
       5: aload_0
       6: getfield      #180                // Field D:I
       9: aload_0
      10: getfield      #358                // Field M:I
      13: if_icmpge     24
      16: aload_0
      17: aload_0
      18: getfield      #358                // Field M:I
      21: putfield      #180                // Field D:I
      24: return

  public android.support.constraint.a.a.d j();
    Code:
       0: aload_0
       1: getfield      #176                // Field B:Landroid/support/constraint/a/a/d;
       4: areturn

  public void j(int);
    Code:
       0: iload_1
       1: istore_2
       2: iload_1
       3: ifge          8
       6: iconst_0
       7: istore_2
       8: aload_0
       9: iload_2
      10: putfield      #360                // Field L:I
      13: return

  public int k();
    Code:
       0: aload_0
       1: getfield      #212                // Field al:I
       4: ireturn

  public void k(int);
    Code:
       0: iload_1
       1: istore_2
       2: iload_1
       3: ifge          8
       6: iconst_0
       7: istore_2
       8: aload_0
       9: iload_2
      10: putfield      #358                // Field M:I
      13: return

  public java.lang.String l();
    Code:
       0: aload_0
       1: getfield      #214                // Field am:Ljava/lang/String;
       4: areturn

  public void l(int);
    Code:
       0: aload_0
       1: iload_1
       2: putfield      #374                // Field ah:I
       5: return

  public int m();
    Code:
       0: aload_0
       1: getfield      #186                // Field G:I
       4: ireturn

  public void m(int);
    Code:
       0: aload_0
       1: iload_1
       2: putfield      #421                // Field ai:I
       5: return

  public int n();
    Code:
       0: aload_0
       1: getfield      #188                // Field H:I
       4: ireturn

  public void n(int);
    Code:
       0: aload_0
       1: iload_1
       2: putfield      #202                // Field K:I
       5: return

  public int o();
    Code:
       0: aload_0
       1: getfield      #212                // Field al:I
       4: bipush        8
       6: if_icmpne     11
       9: iconst_0
      10: ireturn
      11: aload_0
      12: getfield      #178                // Field C:I
      15: ireturn

  public void o(int);
    Code:
       0: aload_0
       1: iload_1
       2: putfield      #218                // Field S:I
       5: return

  public int p();
    Code:
       0: aload_0
       1: getfield      #374                // Field ah:I
       4: ireturn

  public void p(int);
    Code:
       0: aload_0
       1: iload_1
       2: putfield      #220                // Field T:I
       5: return

  public int q();
    Code:
       0: aload_0
       1: getfield      #212                // Field al:I
       4: bipush        8
       6: if_icmpne     11
       9: iconst_0
      10: ireturn
      11: aload_0
      12: getfield      #180                // Field D:I
      15: ireturn

  public int r();
    Code:
       0: aload_0
       1: getfield      #421                // Field ai:I
       4: ireturn

  public int s();
    Code:
       0: aload_0
       1: getfield      #190                // Field ad:I
       4: aload_0
       5: getfield      #198                // Field I:I
       8: iadd
       9: ireturn

  public int t();
    Code:
       0: aload_0
       1: getfield      #192                // Field ae:I
       4: aload_0
       5: getfield      #200                // Field J:I
       8: iadd
       9: ireturn

  public java.lang.String toString();
    Code:
       0: new           #489                // class java/lang/StringBuilder
       3: dup
       4: invokespecial #490                // Method java/lang/StringBuilder."<init>":()V
       7: astore_2
       8: aload_0
       9: getfield      #216                // Field an:Ljava/lang/String;
      12: ifnull        56
      15: new           #489                // class java/lang/StringBuilder
      18: dup
      19: invokespecial #490                // Method java/lang/StringBuilder."<init>":()V
      22: astore_1
      23: aload_1
      24: ldc_w         #492                // String type:
      27: invokevirtual #496                // Method java/lang/StringBuilder.append:(Ljava/lang/String;)Ljava/lang/StringBuilder;
      30: pop
      31: aload_1
      32: aload_0
      33: getfield      #216                // Field an:Ljava/lang/String;
      36: invokevirtual #496                // Method java/lang/StringBuilder.append:(Ljava/lang/String;)Ljava/lang/StringBuilder;
      39: pop
      40: aload_1
      41: ldc_w         #498                // String
      44: invokevirtual #496                // Method java/lang/StringBuilder.append:(Ljava/lang/String;)Ljava/lang/StringBuilder;
      47: pop
      48: aload_1
      49: invokevirtual #500                // Method java/lang/StringBuilder.toString:()Ljava/lang/String;
      52: astore_1
      53: goto          60
      56: ldc_w         #502                // String
      59: astore_1
      60: aload_2
      61: aload_1
      62: invokevirtual #496                // Method java/lang/StringBuilder.append:(Ljava/lang/String;)Ljava/lang/StringBuilder;
      65: pop
      66: aload_0
      67: getfield      #214                // Field am:Ljava/lang/String;
      70: ifnull        114
      73: new           #489                // class java/lang/StringBuilder
      76: dup
      77: invokespecial #490                // Method java/lang/StringBuilder."<init>":()V
      80: astore_1
      81: aload_1
      82: ldc_w         #504                // String id:
      85: invokevirtual #496                // Method java/lang/StringBuilder.append:(Ljava/lang/String;)Ljava/lang/StringBuilder;
      88: pop
      89: aload_1
      90: aload_0
      91: getfield      #214                // Field am:Ljava/lang/String;
      94: invokevirtual #496                // Method java/lang/StringBuilder.append:(Ljava/lang/String;)Ljava/lang/StringBuilder;
      97: pop
      98: aload_1
      99: ldc_w         #498                // String
     102: invokevirtual #496                // Method java/lang/StringBuilder.append:(Ljava/lang/String;)Ljava/lang/StringBuilder;
     105: pop
     106: aload_1
     107: invokevirtual #500                // Method java/lang/StringBuilder.toString:()Ljava/lang/String;
     110: astore_1
     111: goto          118
     114: ldc_w         #502                // String
     117: astore_1
     118: aload_2
     119: aload_1
     120: invokevirtual #496                // Method java/lang/StringBuilder.append:(Ljava/lang/String;)Ljava/lang/StringBuilder;
     123: pop
     124: aload_2
     125: ldc_w         #506                // String (
     128: invokevirtual #496                // Method java/lang/StringBuilder.append:(Ljava/lang/String;)Ljava/lang/StringBuilder;
     131: pop
     132: aload_2
     133: aload_0
     134: getfield      #186                // Field G:I
     137: invokevirtual #509                // Method java/lang/StringBuilder.append:(I)Ljava/lang/StringBuilder;
     140: pop
     141: aload_2
     142: ldc_w         #511                // String ,
     145: invokevirtual #496                // Method java/lang/StringBuilder.append:(Ljava/lang/String;)Ljava/lang/StringBuilder;
     148: pop
     149: aload_2
     150: aload_0
     151: getfield      #188                // Field H:I
     154: invokevirtual #509                // Method java/lang/StringBuilder.append:(I)Ljava/lang/StringBuilder;
     157: pop
     158: aload_2
     159: ldc_w         #513                // String ) - (
     162: invokevirtual #496                // Method java/lang/StringBuilder.append:(Ljava/lang/String;)Ljava/lang/StringBuilder;
     165: pop
     166: aload_2
     167: aload_0
     168: getfield      #178                // Field C:I
     171: invokevirtual #509                // Method java/lang/StringBuilder.append:(I)Ljava/lang/StringBuilder;
     174: pop
     175: aload_2
     176: ldc_w         #515                // String  x
     179: invokevirtual #496                // Method java/lang/StringBuilder.append:(Ljava/lang/String;)Ljava/lang/StringBuilder;
     182: pop
     183: aload_2
     184: aload_0
     185: getfield      #180                // Field D:I
     188: invokevirtual #509                // Method java/lang/StringBuilder.append:(I)Ljava/lang/StringBuilder;
     191: pop
     192: aload_2
     193: ldc_w         #517                // String ) wrap: (
     196: invokevirtual #496                // Method java/lang/StringBuilder.append:(Ljava/lang/String;)Ljava/lang/StringBuilder;
     199: pop
     200: aload_2
     201: aload_0
     202: getfield      #374                // Field ah:I
     205: invokevirtual #509                // Method java/lang/StringBuilder.append:(I)Ljava/lang/StringBuilder;
     208: pop
     209: aload_2
     210: ldc_w         #515                // String  x
     213: invokevirtual #496                // Method java/lang/StringBuilder.append:(Ljava/lang/String;)Ljava/lang/StringBuilder;
     216: pop
     217: aload_2
     218: aload_0
     219: getfield      #421                // Field ai:I
     222: invokevirtual #509                // Method java/lang/StringBuilder.append:(I)Ljava/lang/StringBuilder;
     225: pop
     226: aload_2
     227: ldc_w         #519                // String )
     230: invokevirtual #496                // Method java/lang/StringBuilder.append:(Ljava/lang/String;)Ljava/lang/StringBuilder;
     233: pop
     234: aload_2
     235: invokevirtual #500                // Method java/lang/StringBuilder.toString:()Ljava/lang/String;
     238: areturn

  protected int u();
    Code:
       0: aload_0
       1: getfield      #186                // Field G:I
       4: aload_0
       5: getfield      #198                // Field I:I
       8: iadd
       9: ireturn

  protected int v();
    Code:
       0: aload_0
       1: getfield      #188                // Field H:I
       4: aload_0
       5: getfield      #200                // Field J:I
       8: iadd
       9: ireturn

  public int w();
    Code:
       0: aload_0
       1: invokevirtual #521                // Method m:()I
       4: aload_0
       5: getfield      #178                // Field C:I
       8: iadd
       9: ireturn

  public int x();
    Code:
       0: aload_0
       1: invokevirtual #523                // Method n:()I
       4: aload_0
       5: getfield      #180                // Field D:I
       8: iadd
       9: ireturn

  public float y();
    Code:
       0: aload_0
       1: getfield      #206                // Field O:F
       4: freturn

  public boolean z();
    Code:
       0: aload_0
       1: getfield      #202                // Field K:I
       4: ifle          9
       7: iconst_1
       8: ireturn
       9: iconst_0
      10: ireturn
}
