public class android.support.constraint.a.a.e extends android.support.constraint.a.a.n {
  protected android.support.constraint.a.e ab;

  int ac;

  int ad;

  int ae;

  int af;

  int ag;

  int ah;

  android.support.constraint.a.a.d[] ai;

  android.support.constraint.a.a.d[] aj;

  int ak;

  public android.support.constraint.a.a.e();
    Code:
       0: aload_0
       1: invokespecial #28                 // Method android/support/constraint/a/a/n."<init>":()V
       4: aload_0
       5: iconst_0
       6: putfield      #30                 // Field am:Z
       9: aload_0
      10: new           #32                 // class android/support/constraint/a/e
      13: dup
      14: invokespecial #33                 // Method android/support/constraint/a/e."<init>":()V
      17: putfield      #35                 // Field ab:Landroid/support/constraint/a/e;
      20: aload_0
      21: iconst_0
      22: putfield      #37                 // Field ag:I
      25: aload_0
      26: iconst_0
      27: putfield      #39                 // Field ah:I
      30: aload_0
      31: iconst_4
      32: anewarray     #41                 // class android/support/constraint/a/a/d
      35: putfield      #43                 // Field ai:[Landroid/support/constraint/a/a/d;
      38: aload_0
      39: iconst_4
      40: anewarray     #41                 // class android/support/constraint/a/a/d
      43: putfield      #45                 // Field aj:[Landroid/support/constraint/a/a/d;
      46: aload_0
      47: iconst_3
      48: putfield      #47                 // Field ao:I
      51: aload_0
      52: iconst_0
      53: putfield      #49                 // Field ap:Z
      56: aload_0
      57: iconst_0
      58: putfield      #51                 // Field aq:Z
      61: aload_0
      62: iconst_0
      63: putfield      #53                 // Field ak:I
      66: return

  public int H();
    Code:
       0: aload_0
       1: getfield      #47                 // Field ao:I
       4: ireturn

  public boolean I();
    Code:
       0: aload_0
       1: getfield      #49                 // Field ap:Z
       4: ireturn

  public boolean J();
    Code:
       0: aload_0
       1: getfield      #51                 // Field aq:Z
       4: ireturn

  public boolean K();
    Code:
       0: aload_0
       1: getfield      #30                 // Field am:Z
       4: ireturn

  public void L();
    Code:
       0: aload_0
       1: getfield      #76                 // Field G:I
       4: istore        6
       6: aload_0
       7: getfield      #78                 // Field H:I
      10: istore        7
      12: iconst_0
      13: aload_0
      14: invokevirtual #81                 // Method o:()I
      17: invokestatic  #87                 // Method java/lang/Math.max:(II)I
      20: istore        8
      22: iconst_0
      23: aload_0
      24: invokevirtual #90                 // Method q:()I
      27: invokestatic  #87                 // Method java/lang/Math.max:(II)I
      30: istore        9
      32: aload_0
      33: iconst_0
      34: putfield      #49                 // Field ap:Z
      37: aload_0
      38: iconst_0
      39: putfield      #51                 // Field aq:Z
      42: aload_0
      43: getfield      #94                 // Field B:Landroid/support/constraint/a/a/d;
      46: ifnull        110
      49: aload_0
      50: getfield      #96                 // Field an:Landroid/support/constraint/a/a/m;
      53: ifnonnull     68
      56: aload_0
      57: new           #98                 // class android/support/constraint/a/a/m
      60: dup
      61: aload_0
      62: invokespecial #100                // Method android/support/constraint/a/a/m."<init>":(Landroid/support/constraint/a/a/d;)V
      65: putfield      #96                 // Field an:Landroid/support/constraint/a/a/m;
      68: aload_0
      69: getfield      #96                 // Field an:Landroid/support/constraint/a/a/m;
      72: aload_0
      73: invokevirtual #103                // Method android/support/constraint/a/a/m.a:(Landroid/support/constraint/a/a/d;)V
      76: aload_0
      77: aload_0
      78: getfield      #105                // Field ac:I
      81: invokevirtual #109                // Method f:(I)V
      84: aload_0
      85: aload_0
      86: getfield      #111                // Field ad:I
      89: invokevirtual #114                // Method g:(I)V
      92: aload_0
      93: invokevirtual #117                // Method E:()V
      96: aload_0
      97: aload_0
      98: getfield      #35                 // Field ab:Landroid/support/constraint/a/e;
     101: invokevirtual #120                // Method android/support/constraint/a/e.g:()Landroid/support/constraint/a/c;
     104: invokevirtual #123                // Method a:(Landroid/support/constraint/a/c;)V
     107: goto          120
     110: aload_0
     111: iconst_0
     112: putfield      #76                 // Field G:I
     115: aload_0
     116: iconst_0
     117: putfield      #78                 // Field H:I
     120: aload_0
     121: getfield      #47                 // Field ao:I
     124: ifeq          155
     127: aload_0
     128: bipush        8
     130: invokevirtual #126                // Method q:(I)Z
     133: ifne          140
     136: aload_0
     137: invokevirtual #129                // Method O:()V
     140: aload_0
     141: invokevirtual #132                // Method P:()V
     144: aload_0
     145: getfield      #35                 // Field ab:Landroid/support/constraint/a/e;
     148: iconst_1
     149: putfield      #135                // Field android/support/constraint/a/e.c:Z
     152: goto          163
     155: aload_0
     156: getfield      #35                 // Field ab:Landroid/support/constraint/a/e;
     159: iconst_0
     160: putfield      #135                // Field android/support/constraint/a/e.c:Z
     163: aload_0
     164: getfield      #139                // Field A:[Landroid/support/constraint/a/a/d$a;
     167: iconst_1
     168: aaload
     169: astore        15
     171: aload_0
     172: getfield      #139                // Field A:[Landroid/support/constraint/a/a/d$a;
     175: iconst_0
     176: aaload
     177: astore        16
     179: aload_0
     180: invokespecial #141                // Method T:()V
     183: aload_0
     184: getfield      #145                // Field al:Ljava/util/ArrayList;
     187: invokevirtual #150                // Method java/util/ArrayList.size:()I
     190: istore        10
     192: iconst_0
     193: istore_1
     194: iload_1
     195: iload         10
     197: if_icmpge     236
     200: aload_0
     201: getfield      #145                // Field al:Ljava/util/ArrayList;
     204: iload_1
     205: invokevirtual #154                // Method java/util/ArrayList.get:(I)Ljava/lang/Object;
     208: checkcast     #41                 // class android/support/constraint/a/a/d
     211: astore        14
     213: aload         14
     215: instanceof    #4                  // class android/support/constraint/a/a/n
     218: ifeq          229
     221: aload         14
     223: checkcast     #4                  // class android/support/constraint/a/a/n
     226: invokevirtual #156                // Method android/support/constraint/a/a/n.L:()V
     229: iload_1
     230: iconst_1
     231: iadd
     232: istore_1
     233: goto          194
     236: iconst_1
     237: istore        11
     239: iconst_0
     240: istore_2
     241: iconst_0
     242: istore_1
     243: iload         11
     245: ifeq          918
     248: iload_2
     249: iconst_1
     250: iadd
     251: istore        5
     253: aload_0
     254: getfield      #35                 // Field ab:Landroid/support/constraint/a/e;
     257: invokevirtual #159                // Method android/support/constraint/a/e.b:()V
     260: aload_0
     261: aload_0
     262: getfield      #35                 // Field ab:Landroid/support/constraint/a/e;
     265: invokevirtual #162                // Method c:(Landroid/support/constraint/a/e;)Z
     268: istore        12
     270: iload         12
     272: istore        11
     274: iload         12
     276: ifeq          349
     279: aload_0
     280: getfield      #35                 // Field ab:Landroid/support/constraint/a/e;
     283: invokevirtual #164                // Method android/support/constraint/a/e.f:()V
     286: iload         12
     288: istore        11
     290: goto          349
     293: astore        14
     295: iload         12
     297: istore        11
     299: goto          304
     302: astore        14
     304: aload         14
     306: invokestatic  #169                // Method com/google/a/a/a/a/a/a.a:(Ljava/lang/Throwable;)V
     309: getstatic     #175                // Field java/lang/System.out:Ljava/io/PrintStream;
     312: astore        17
     314: new           #177                // class java/lang/StringBuilder
     317: dup
     318: invokespecial #178                // Method java/lang/StringBuilder."<init>":()V
     321: astore        18
     323: aload         18
     325: ldc           #180                // String EXCEPTION :
     327: invokevirtual #184                // Method java/lang/StringBuilder.append:(Ljava/lang/String;)Ljava/lang/StringBuilder;
     330: pop
     331: aload         18
     333: aload         14
     335: invokevirtual #187                // Method java/lang/StringBuilder.append:(Ljava/lang/Object;)Ljava/lang/StringBuilder;
     338: pop
     339: aload         17
     341: aload         18
     343: invokevirtual #191                // Method java/lang/StringBuilder.toString:()Ljava/lang/String;
     346: invokevirtual #197                // Method java/io/PrintStream.println:(Ljava/lang/String;)V
     349: iload         11
     351: ifeq          368
     354: aload_0
     355: aload_0
     356: getfield      #35                 // Field ab:Landroid/support/constraint/a/e;
     359: getstatic     #202                // Field android/support/constraint/a/a/h.a:[Z
     362: invokevirtual #205                // Method a:(Landroid/support/constraint/a/e;[Z)V
     365: goto          474
     368: aload_0
     369: aload_0
     370: getfield      #35                 // Field ab:Landroid/support/constraint/a/e;
     373: invokevirtual #208                // Method b:(Landroid/support/constraint/a/e;)V
     376: iconst_0
     377: istore_2
     378: iload_2
     379: iload         10
     381: if_icmpge     474
     384: aload_0
     385: getfield      #145                // Field al:Ljava/util/ArrayList;
     388: iload_2
     389: invokevirtual #154                // Method java/util/ArrayList.get:(I)Ljava/lang/Object;
     392: checkcast     #41                 // class android/support/constraint/a/a/d
     395: astore        14
     397: aload         14
     399: getfield      #209                // Field android/support/constraint/a/a/d.A:[Landroid/support/constraint/a/a/d$a;
     402: iconst_0
     403: aaload
     404: getstatic     #214                // Field android/support/constraint/a/a/d$a.c:Landroid/support/constraint/a/a/d$a;
     407: if_acmpne     432
     410: aload         14
     412: invokevirtual #215                // Method android/support/constraint/a/a/d.o:()I
     415: aload         14
     417: invokevirtual #218                // Method android/support/constraint/a/a/d.p:()I
     420: if_icmpge     432
     423: getstatic     #202                // Field android/support/constraint/a/a/h.a:[Z
     426: iconst_2
     427: iconst_1
     428: bastore
     429: goto          365
     432: aload         14
     434: getfield      #209                // Field android/support/constraint/a/a/d.A:[Landroid/support/constraint/a/a/d$a;
     437: iconst_1
     438: aaload
     439: getstatic     #214                // Field android/support/constraint/a/a/d$a.c:Landroid/support/constraint/a/a/d$a;
     442: if_acmpne     467
     445: aload         14
     447: invokevirtual #219                // Method android/support/constraint/a/a/d.q:()I
     450: aload         14
     452: invokevirtual #222                // Method android/support/constraint/a/a/d.r:()I
     455: if_icmpge     467
     458: getstatic     #202                // Field android/support/constraint/a/a/h.a:[Z
     461: iconst_2
     462: iconst_1
     463: bastore
     464: goto          474
     467: iload_2
     468: iconst_1
     469: iadd
     470: istore_2
     471: goto          378
     474: iload         5
     476: bipush        8
     478: if_icmpge     671
     481: getstatic     #202                // Field android/support/constraint/a/a/h.a:[Z
     484: iconst_2
     485: baload
     486: ifeq          671
     489: iconst_0
     490: istore_3
     491: iconst_0
     492: istore        4
     494: iconst_0
     495: istore_2
     496: iload_3
     497: iload         10
     499: if_icmpge     556
     502: aload_0
     503: getfield      #145                // Field al:Ljava/util/ArrayList;
     506: iload_3
     507: invokevirtual #154                // Method java/util/ArrayList.get:(I)Ljava/lang/Object;
     510: checkcast     #41                 // class android/support/constraint/a/a/d
     513: astore        14
     515: iload         4
     517: aload         14
     519: getfield      #223                // Field android/support/constraint/a/a/d.G:I
     522: aload         14
     524: invokevirtual #215                // Method android/support/constraint/a/a/d.o:()I
     527: iadd
     528: invokestatic  #87                 // Method java/lang/Math.max:(II)I
     531: istore        4
     533: iload_2
     534: aload         14
     536: getfield      #224                // Field android/support/constraint/a/a/d.H:I
     539: aload         14
     541: invokevirtual #219                // Method android/support/constraint/a/a/d.q:()I
     544: iadd
     545: invokestatic  #87                 // Method java/lang/Math.max:(II)I
     548: istore_2
     549: iload_3
     550: iconst_1
     551: iadd
     552: istore_3
     553: goto          496
     556: aload_0
     557: getfield      #226                // Field L:I
     560: iload         4
     562: invokestatic  #87                 // Method java/lang/Math.max:(II)I
     565: istore        4
     567: aload_0
     568: getfield      #229                // Field M:I
     571: iload_2
     572: invokestatic  #87                 // Method java/lang/Math.max:(II)I
     575: istore_3
     576: aload         16
     578: getstatic     #231                // Field android/support/constraint/a/a/d$a.b:Landroid/support/constraint/a/a/d$a;
     581: if_acmpne     616
     584: aload_0
     585: invokevirtual #81                 // Method o:()I
     588: iload         4
     590: if_icmpge     616
     593: aload_0
     594: iload         4
     596: invokevirtual #234                // Method h:(I)V
     599: aload_0
     600: getfield      #139                // Field A:[Landroid/support/constraint/a/a/d$a;
     603: iconst_0
     604: getstatic     #231                // Field android/support/constraint/a/a/d$a.b:Landroid/support/constraint/a/a/d$a;
     607: aastore
     608: iconst_1
     609: istore        12
     611: iconst_1
     612: istore_2
     613: goto          621
     616: iconst_0
     617: istore        12
     619: iload_1
     620: istore_2
     621: iload         12
     623: istore        11
     625: iload_2
     626: istore_1
     627: aload         15
     629: getstatic     #231                // Field android/support/constraint/a/a/d$a.b:Landroid/support/constraint/a/a/d$a;
     632: if_acmpne     674
     635: iload         12
     637: istore        11
     639: iload_2
     640: istore_1
     641: aload_0
     642: invokevirtual #90                 // Method q:()I
     645: iload_3
     646: if_icmpge     674
     649: aload_0
     650: iload_3
     651: invokevirtual #237                // Method i:(I)V
     654: aload_0
     655: getfield      #139                // Field A:[Landroid/support/constraint/a/a/d$a;
     658: iconst_1
     659: getstatic     #231                // Field android/support/constraint/a/a/d$a.b:Landroid/support/constraint/a/a/d$a;
     662: aastore
     663: iconst_1
     664: istore        11
     666: iconst_1
     667: istore_1
     668: goto          674
     671: iconst_0
     672: istore        11
     674: aload_0
     675: getfield      #226                // Field L:I
     678: aload_0
     679: invokevirtual #81                 // Method o:()I
     682: invokestatic  #87                 // Method java/lang/Math.max:(II)I
     685: istore_2
     686: iload_2
     687: aload_0
     688: invokevirtual #81                 // Method o:()I
     691: if_icmple     713
     694: aload_0
     695: iload_2
     696: invokevirtual #234                // Method h:(I)V
     699: aload_0
     700: getfield      #139                // Field A:[Landroid/support/constraint/a/a/d$a;
     703: iconst_0
     704: getstatic     #239                // Field android/support/constraint/a/a/d$a.a:Landroid/support/constraint/a/a/d$a;
     707: aastore
     708: iconst_1
     709: istore        11
     711: iconst_1
     712: istore_1
     713: aload_0
     714: getfield      #229                // Field M:I
     717: aload_0
     718: invokevirtual #90                 // Method q:()I
     721: invokestatic  #87                 // Method java/lang/Math.max:(II)I
     724: istore_2
     725: iload_2
     726: aload_0
     727: invokevirtual #90                 // Method q:()I
     730: if_icmple     755
     733: aload_0
     734: iload_2
     735: invokevirtual #237                // Method i:(I)V
     738: aload_0
     739: getfield      #139                // Field A:[Landroid/support/constraint/a/a/d$a;
     742: iconst_1
     743: getstatic     #239                // Field android/support/constraint/a/a/d$a.a:Landroid/support/constraint/a/a/d$a;
     746: aastore
     747: iconst_1
     748: istore        11
     750: iconst_1
     751: istore_1
     752: goto          755
     755: iload         11
     757: istore        13
     759: iload_1
     760: istore_3
     761: iload_1
     762: ifne          906
     765: iload         11
     767: istore        12
     769: iload_1
     770: istore_2
     771: aload_0
     772: getfield      #139                // Field A:[Landroid/support/constraint/a/a/d$a;
     775: iconst_0
     776: aaload
     777: getstatic     #231                // Field android/support/constraint/a/a/d$a.b:Landroid/support/constraint/a/a/d$a;
     780: if_acmpne     834
     783: iload         11
     785: istore        12
     787: iload_1
     788: istore_2
     789: iload         8
     791: ifle          834
     794: iload         11
     796: istore        12
     798: iload_1
     799: istore_2
     800: aload_0
     801: invokevirtual #81                 // Method o:()I
     804: iload         8
     806: if_icmple     834
     809: aload_0
     810: iconst_1
     811: putfield      #49                 // Field ap:Z
     814: aload_0
     815: getfield      #139                // Field A:[Landroid/support/constraint/a/a/d$a;
     818: iconst_0
     819: getstatic     #239                // Field android/support/constraint/a/a/d$a.a:Landroid/support/constraint/a/a/d$a;
     822: aastore
     823: aload_0
     824: iload         8
     826: invokevirtual #234                // Method h:(I)V
     829: iconst_1
     830: istore        12
     832: iconst_1
     833: istore_2
     834: iload         12
     836: istore        13
     838: iload_2
     839: istore_3
     840: aload_0
     841: getfield      #139                // Field A:[Landroid/support/constraint/a/a/d$a;
     844: iconst_1
     845: aaload
     846: getstatic     #231                // Field android/support/constraint/a/a/d$a.b:Landroid/support/constraint/a/a/d$a;
     849: if_acmpne     906
     852: iload         12
     854: istore        13
     856: iload_2
     857: istore_3
     858: iload         9
     860: ifle          906
     863: iload         12
     865: istore        13
     867: iload_2
     868: istore_3
     869: aload_0
     870: invokevirtual #90                 // Method q:()I
     873: iload         9
     875: if_icmple     906
     878: aload_0
     879: iconst_1
     880: putfield      #51                 // Field aq:Z
     883: aload_0
     884: getfield      #139                // Field A:[Landroid/support/constraint/a/a/d$a;
     887: iconst_1
     888: getstatic     #239                // Field android/support/constraint/a/a/d$a.a:Landroid/support/constraint/a/a/d$a;
     891: aastore
     892: aload_0
     893: iload         9
     895: invokevirtual #237                // Method i:(I)V
     898: iconst_1
     899: istore        11
     901: iconst_1
     902: istore_1
     903: goto          912
     906: iload         13
     908: istore        11
     910: iload_3
     911: istore_1
     912: iload         5
     914: istore_2
     915: goto          243
     918: aload_0
     919: getfield      #94                 // Field B:Landroid/support/constraint/a/a/d;
     922: ifnull        990
     925: aload_0
     926: getfield      #226                // Field L:I
     929: aload_0
     930: invokevirtual #81                 // Method o:()I
     933: invokestatic  #87                 // Method java/lang/Math.max:(II)I
     936: istore_2
     937: aload_0
     938: getfield      #229                // Field M:I
     941: aload_0
     942: invokevirtual #90                 // Method q:()I
     945: invokestatic  #87                 // Method java/lang/Math.max:(II)I
     948: istore_3
     949: aload_0
     950: getfield      #96                 // Field an:Landroid/support/constraint/a/a/m;
     953: aload_0
     954: invokevirtual #241                // Method android/support/constraint/a/a/m.b:(Landroid/support/constraint/a/a/d;)V
     957: aload_0
     958: iload_2
     959: aload_0
     960: getfield      #105                // Field ac:I
     963: iadd
     964: aload_0
     965: getfield      #243                // Field ae:I
     968: iadd
     969: invokevirtual #234                // Method h:(I)V
     972: aload_0
     973: iload_3
     974: aload_0
     975: getfield      #111                // Field ad:I
     978: iadd
     979: aload_0
     980: getfield      #245                // Field af:I
     983: iadd
     984: invokevirtual #237                // Method i:(I)V
     987: goto          1002
     990: aload_0
     991: iload         6
     993: putfield      #76                 // Field G:I
     996: aload_0
     997: iload         7
     999: putfield      #78                 // Field H:I
    1002: iload_1
    1003: ifeq          1022
    1006: aload_0
    1007: getfield      #139                // Field A:[Landroid/support/constraint/a/a/d$a;
    1010: iconst_0
    1011: aload         16
    1013: aastore
    1014: aload_0
    1015: getfield      #139                // Field A:[Landroid/support/constraint/a/a/d$a;
    1018: iconst_1
    1019: aload         15
    1021: aastore
    1022: aload_0
    1023: aload_0
    1024: getfield      #35                 // Field ab:Landroid/support/constraint/a/e;
    1027: invokevirtual #120                // Method android/support/constraint/a/e.g:()Landroid/support/constraint/a/c;
    1030: invokevirtual #123                // Method a:(Landroid/support/constraint/a/c;)V
    1033: aload_0
    1034: aload_0
    1035: invokevirtual #249                // Method R:()Landroid/support/constraint/a/a/e;
    1038: if_acmpne     1045
    1041: aload_0
    1042: invokevirtual #252                // Method D:()V
    1045: return
    Exception table:
       from    to  target type
         253   270   302   Class java/lang/Exception
         279   286   293   Class java/lang/Exception

  public void M();
    Code:
       0: aload_0
       1: invokevirtual #129                // Method O:()V
       4: aload_0
       5: aload_0
       6: getfield      #47                 // Field ao:I
       9: invokevirtual #254                // Method b:(I)V
      12: return

  public void N();
    Code:
       0: aload_0
       1: getstatic     #260                // Field android/support/constraint/a/a/c$c.b:Landroid/support/constraint/a/a/c$c;
       4: invokevirtual #263                // Method a:(Landroid/support/constraint/a/a/c$c;)Landroid/support/constraint/a/a/c;
       7: invokevirtual #268                // Method android/support/constraint/a/a/c.a:()Landroid/support/constraint/a/a/j;
      10: astore_1
      11: aload_0
      12: getstatic     #270                // Field android/support/constraint/a/a/c$c.c:Landroid/support/constraint/a/a/c$c;
      15: invokevirtual #263                // Method a:(Landroid/support/constraint/a/a/c$c;)Landroid/support/constraint/a/a/c;
      18: invokevirtual #268                // Method android/support/constraint/a/a/c.a:()Landroid/support/constraint/a/a/j;
      21: astore_2
      22: aload_1
      23: aconst_null
      24: fconst_0
      25: invokevirtual #275                // Method android/support/constraint/a/a/j.a:(Landroid/support/constraint/a/a/j;F)V
      28: aload_2
      29: aconst_null
      30: fconst_0
      31: invokevirtual #275                // Method android/support/constraint/a/a/j.a:(Landroid/support/constraint/a/a/j;F)V
      34: return

  public void O();
    Code:
       0: aload_0
       1: getfield      #145                // Field al:Ljava/util/ArrayList;
       4: invokevirtual #150                // Method java/util/ArrayList.size:()I
       7: istore_2
       8: aload_0
       9: invokevirtual #276                // Method b:()V
      12: iconst_0
      13: istore_1
      14: iload_1
      15: iload_2
      16: if_icmpge     40
      19: aload_0
      20: getfield      #145                // Field al:Ljava/util/ArrayList;
      23: iload_1
      24: invokevirtual #154                // Method java/util/ArrayList.get:(I)Ljava/lang/Object;
      27: checkcast     #41                 // class android/support/constraint/a/a/d
      30: invokevirtual #277                // Method android/support/constraint/a/a/d.b:()V
      33: iload_1
      34: iconst_1
      35: iadd
      36: istore_1
      37: goto          14
      40: return

  public void P();
    Code:
       0: aload_0
       1: bipush        8
       3: invokevirtual #126                // Method q:(I)Z
       6: ifne          17
       9: aload_0
      10: aload_0
      11: getfield      #47                 // Field ao:I
      14: invokevirtual #254                // Method b:(I)V
      17: aload_0
      18: invokevirtual #279                // Method N:()V
      21: return

  public boolean Q();
    Code:
       0: iconst_0
       1: ireturn

  public void a(int);
    Code:
       0: aload_0
       1: iload_1
       2: putfield      #47                 // Field ao:I
       5: return

  void a(android.support.constraint.a.a.d, int);
    Code:
       0: iload_2
       1: ifne          90
       4: aload_1
       5: getfield      #284                // Field android/support/constraint/a/a/d.q:Landroid/support/constraint/a/a/c;
       8: getfield      #286                // Field android/support/constraint/a/a/c.c:Landroid/support/constraint/a/a/c;
      11: ifnull        84
      14: aload_1
      15: getfield      #284                // Field android/support/constraint/a/a/d.q:Landroid/support/constraint/a/a/c;
      18: getfield      #286                // Field android/support/constraint/a/a/c.c:Landroid/support/constraint/a/a/c;
      21: getfield      #288                // Field android/support/constraint/a/a/c.a:Landroid/support/constraint/a/a/d;
      24: getfield      #291                // Field android/support/constraint/a/a/d.s:Landroid/support/constraint/a/a/c;
      27: getfield      #286                // Field android/support/constraint/a/a/c.c:Landroid/support/constraint/a/a/c;
      30: ifnull        84
      33: aload_1
      34: getfield      #284                // Field android/support/constraint/a/a/d.q:Landroid/support/constraint/a/a/c;
      37: getfield      #286                // Field android/support/constraint/a/a/c.c:Landroid/support/constraint/a/a/c;
      40: getfield      #288                // Field android/support/constraint/a/a/c.a:Landroid/support/constraint/a/a/d;
      43: getfield      #291                // Field android/support/constraint/a/a/d.s:Landroid/support/constraint/a/a/c;
      46: getfield      #286                // Field android/support/constraint/a/a/c.c:Landroid/support/constraint/a/a/c;
      49: aload_1
      50: getfield      #284                // Field android/support/constraint/a/a/d.q:Landroid/support/constraint/a/a/c;
      53: if_acmpne     84
      56: aload_1
      57: getfield      #284                // Field android/support/constraint/a/a/d.q:Landroid/support/constraint/a/a/c;
      60: getfield      #286                // Field android/support/constraint/a/a/c.c:Landroid/support/constraint/a/a/c;
      63: getfield      #288                // Field android/support/constraint/a/a/c.a:Landroid/support/constraint/a/a/d;
      66: aload_1
      67: if_acmpeq     84
      70: aload_1
      71: getfield      #284                // Field android/support/constraint/a/a/d.q:Landroid/support/constraint/a/a/c;
      74: getfield      #286                // Field android/support/constraint/a/a/c.c:Landroid/support/constraint/a/a/c;
      77: getfield      #288                // Field android/support/constraint/a/a/c.a:Landroid/support/constraint/a/a/d;
      80: astore_1
      81: goto          4
      84: aload_0
      85: aload_1
      86: invokespecial #293                // Method d:(Landroid/support/constraint/a/a/d;)V
      89: return
      90: iload_2
      91: iconst_1
      92: if_icmpne     180
      95: aload_1
      96: getfield      #295                // Field android/support/constraint/a/a/d.r:Landroid/support/constraint/a/a/c;
      99: getfield      #286                // Field android/support/constraint/a/a/c.c:Landroid/support/constraint/a/a/c;
     102: ifnull        175
     105: aload_1
     106: getfield      #295                // Field android/support/constraint/a/a/d.r:Landroid/support/constraint/a/a/c;
     109: getfield      #286                // Field android/support/constraint/a/a/c.c:Landroid/support/constraint/a/a/c;
     112: getfield      #288                // Field android/support/constraint/a/a/c.a:Landroid/support/constraint/a/a/d;
     115: getfield      #298                // Field android/support/constraint/a/a/d.t:Landroid/support/constraint/a/a/c;
     118: getfield      #286                // Field android/support/constraint/a/a/c.c:Landroid/support/constraint/a/a/c;
     121: ifnull        175
     124: aload_1
     125: getfield      #295                // Field android/support/constraint/a/a/d.r:Landroid/support/constraint/a/a/c;
     128: getfield      #286                // Field android/support/constraint/a/a/c.c:Landroid/support/constraint/a/a/c;
     131: getfield      #288                // Field android/support/constraint/a/a/c.a:Landroid/support/constraint/a/a/d;
     134: getfield      #298                // Field android/support/constraint/a/a/d.t:Landroid/support/constraint/a/a/c;
     137: getfield      #286                // Field android/support/constraint/a/a/c.c:Landroid/support/constraint/a/a/c;
     140: aload_1
     141: getfield      #295                // Field android/support/constraint/a/a/d.r:Landroid/support/constraint/a/a/c;
     144: if_acmpne     175
     147: aload_1
     148: getfield      #295                // Field android/support/constraint/a/a/d.r:Landroid/support/constraint/a/a/c;
     151: getfield      #286                // Field android/support/constraint/a/a/c.c:Landroid/support/constraint/a/a/c;
     154: getfield      #288                // Field android/support/constraint/a/a/c.a:Landroid/support/constraint/a/a/d;
     157: aload_1
     158: if_acmpeq     175
     161: aload_1
     162: getfield      #295                // Field android/support/constraint/a/a/d.r:Landroid/support/constraint/a/a/c;
     165: getfield      #286                // Field android/support/constraint/a/a/c.c:Landroid/support/constraint/a/a/c;
     168: getfield      #288                // Field android/support/constraint/a/a/c.a:Landroid/support/constraint/a/a/d;
     171: astore_1
     172: goto          95
     175: aload_0
     176: aload_1
     177: invokespecial #300                // Method e:(Landroid/support/constraint/a/a/d;)V
     180: return

  public void a(android.support.constraint.a.e, boolean[]);
    Code:
       0: aload_2
       1: iconst_2
       2: iconst_0
       3: bastore
       4: aload_0
       5: aload_1
       6: invokevirtual #208                // Method b:(Landroid/support/constraint/a/e;)V
       9: aload_0
      10: getfield      #145                // Field al:Ljava/util/ArrayList;
      13: invokevirtual #150                // Method java/util/ArrayList.size:()I
      16: istore        4
      18: iconst_0
      19: istore_3
      20: iload_3
      21: iload         4
      23: if_icmpge     112
      26: aload_0
      27: getfield      #145                // Field al:Ljava/util/ArrayList;
      30: iload_3
      31: invokevirtual #154                // Method java/util/ArrayList.get:(I)Ljava/lang/Object;
      34: checkcast     #41                 // class android/support/constraint/a/a/d
      37: astore        5
      39: aload         5
      41: aload_1
      42: invokevirtual #301                // Method android/support/constraint/a/a/d.b:(Landroid/support/constraint/a/e;)V
      45: aload         5
      47: getfield      #209                // Field android/support/constraint/a/a/d.A:[Landroid/support/constraint/a/a/d$a;
      50: iconst_0
      51: aaload
      52: getstatic     #214                // Field android/support/constraint/a/a/d$a.c:Landroid/support/constraint/a/a/d$a;
      55: if_acmpne     75
      58: aload         5
      60: invokevirtual #215                // Method android/support/constraint/a/a/d.o:()I
      63: aload         5
      65: invokevirtual #218                // Method android/support/constraint/a/a/d.p:()I
      68: if_icmpge     75
      71: aload_2
      72: iconst_2
      73: iconst_1
      74: bastore
      75: aload         5
      77: getfield      #209                // Field android/support/constraint/a/a/d.A:[Landroid/support/constraint/a/a/d$a;
      80: iconst_1
      81: aaload
      82: getstatic     #214                // Field android/support/constraint/a/a/d$a.c:Landroid/support/constraint/a/a/d$a;
      85: if_acmpne     105
      88: aload         5
      90: invokevirtual #219                // Method android/support/constraint/a/a/d.q:()I
      93: aload         5
      95: invokevirtual #222                // Method android/support/constraint/a/a/d.r:()I
      98: if_icmpge     105
     101: aload_2
     102: iconst_2
     103: iconst_1
     104: bastore
     105: iload_3
     106: iconst_1
     107: iadd
     108: istore_3
     109: goto          20
     112: return

  public void a(boolean);
    Code:
       0: aload_0
       1: iload_1
       2: putfield      #30                 // Field am:Z
       5: return

  public void b(int);
    Code:
       0: aload_0
       1: iload_1
       2: invokespecial #303                // Method android/support/constraint/a/a/n.b:(I)V
       5: aload_0
       6: getfield      #145                // Field al:Ljava/util/ArrayList;
       9: invokevirtual #150                // Method java/util/ArrayList.size:()I
      12: istore_3
      13: iconst_0
      14: istore_2
      15: iload_2
      16: iload_3
      17: if_icmpge     42
      20: aload_0
      21: getfield      #145                // Field al:Ljava/util/ArrayList;
      24: iload_2
      25: invokevirtual #154                // Method java/util/ArrayList.get:(I)Ljava/lang/Object;
      28: checkcast     #41                 // class android/support/constraint/a/a/d
      31: iload_1
      32: invokevirtual #304                // Method android/support/constraint/a/a/d.b:(I)V
      35: iload_2
      36: iconst_1
      37: iadd
      38: istore_2
      39: goto          15
      42: return

  public boolean c(android.support.constraint.a.e);
    Code:
       0: aload_0
       1: aload_1
       2: invokevirtual #306                // Method a:(Landroid/support/constraint/a/e;)V
       5: aload_0
       6: getfield      #145                // Field al:Ljava/util/ArrayList;
       9: invokevirtual #150                // Method java/util/ArrayList.size:()I
      12: istore_3
      13: iconst_0
      14: istore_2
      15: iload_2
      16: iload_3
      17: if_icmpge     150
      20: aload_0
      21: getfield      #145                // Field al:Ljava/util/ArrayList;
      24: iload_2
      25: invokevirtual #154                // Method java/util/ArrayList.get:(I)Ljava/lang/Object;
      28: checkcast     #41                 // class android/support/constraint/a/a/d
      31: astore        4
      33: aload         4
      35: instanceof    #2                  // class android/support/constraint/a/a/e
      38: ifeq          130
      41: aload         4
      43: getfield      #209                // Field android/support/constraint/a/a/d.A:[Landroid/support/constraint/a/a/d$a;
      46: iconst_0
      47: aaload
      48: astore        5
      50: aload         4
      52: getfield      #209                // Field android/support/constraint/a/a/d.A:[Landroid/support/constraint/a/a/d$a;
      55: iconst_1
      56: aaload
      57: astore        6
      59: aload         5
      61: getstatic     #231                // Field android/support/constraint/a/a/d$a.b:Landroid/support/constraint/a/a/d$a;
      64: if_acmpne     75
      67: aload         4
      69: getstatic     #239                // Field android/support/constraint/a/a/d$a.a:Landroid/support/constraint/a/a/d$a;
      72: invokevirtual #309                // Method android/support/constraint/a/a/d.a:(Landroid/support/constraint/a/a/d$a;)V
      75: aload         6
      77: getstatic     #231                // Field android/support/constraint/a/a/d$a.b:Landroid/support/constraint/a/a/d$a;
      80: if_acmpne     91
      83: aload         4
      85: getstatic     #239                // Field android/support/constraint/a/a/d$a.a:Landroid/support/constraint/a/a/d$a;
      88: invokevirtual #311                // Method android/support/constraint/a/a/d.b:(Landroid/support/constraint/a/a/d$a;)V
      91: aload         4
      93: aload_1
      94: invokevirtual #312                // Method android/support/constraint/a/a/d.a:(Landroid/support/constraint/a/e;)V
      97: aload         5
      99: getstatic     #231                // Field android/support/constraint/a/a/d$a.b:Landroid/support/constraint/a/a/d$a;
     102: if_acmpne     112
     105: aload         4
     107: aload         5
     109: invokevirtual #309                // Method android/support/constraint/a/a/d.a:(Landroid/support/constraint/a/a/d$a;)V
     112: aload         6
     114: getstatic     #231                // Field android/support/constraint/a/a/d$a.b:Landroid/support/constraint/a/a/d$a;
     117: if_acmpne     143
     120: aload         4
     122: aload         6
     124: invokevirtual #311                // Method android/support/constraint/a/a/d.b:(Landroid/support/constraint/a/a/d$a;)V
     127: goto          143
     130: aload_0
     131: aload_1
     132: aload         4
     134: invokestatic  #315                // Method android/support/constraint/a/a/h.a:(Landroid/support/constraint/a/a/e;Landroid/support/constraint/a/e;Landroid/support/constraint/a/a/d;)V
     137: aload         4
     139: aload_1
     140: invokevirtual #312                // Method android/support/constraint/a/a/d.a:(Landroid/support/constraint/a/e;)V
     143: iload_2
     144: iconst_1
     145: iadd
     146: istore_2
     147: goto          15
     150: aload_0
     151: getfield      #37                 // Field ag:I
     154: ifle          163
     157: aload_0
     158: aload_1
     159: iconst_0
     160: invokestatic  #320                // Method android/support/constraint/a/a/b.a:(Landroid/support/constraint/a/a/e;Landroid/support/constraint/a/e;I)V
     163: aload_0
     164: getfield      #39                 // Field ah:I
     167: ifle          176
     170: aload_0
     171: aload_1
     172: iconst_1
     173: invokestatic  #320                // Method android/support/constraint/a/a/b.a:(Landroid/support/constraint/a/a/e;Landroid/support/constraint/a/e;I)V
     176: iconst_1
     177: ireturn

  public void e(int, int);
    Code:
       0: aload_0
       1: getfield      #139                // Field A:[Landroid/support/constraint/a/a/d$a;
       4: iconst_0
       5: aaload
       6: getstatic     #231                // Field android/support/constraint/a/a/d$a.b:Landroid/support/constraint/a/a/d$a;
       9: if_acmpeq     27
      12: aload_0
      13: getfield      #324                // Field c:Landroid/support/constraint/a/a/k;
      16: ifnull        27
      19: aload_0
      20: getfield      #324                // Field c:Landroid/support/constraint/a/a/k;
      23: iload_1
      24: invokevirtual #328                // Method android/support/constraint/a/a/k.a:(I)V
      27: aload_0
      28: getfield      #139                // Field A:[Landroid/support/constraint/a/a/d$a;
      31: iconst_1
      32: aaload
      33: getstatic     #231                // Field android/support/constraint/a/a/d$a.b:Landroid/support/constraint/a/a/d$a;
      36: if_acmpeq     54
      39: aload_0
      40: getfield      #330                // Field d:Landroid/support/constraint/a/a/k;
      43: ifnull        54
      46: aload_0
      47: getfield      #330                // Field d:Landroid/support/constraint/a/a/k;
      50: iload_2
      51: invokevirtual #328                // Method android/support/constraint/a/a/k.a:(I)V
      54: return

  public void f();
    Code:
       0: aload_0
       1: getfield      #35                 // Field ab:Landroid/support/constraint/a/e;
       4: invokevirtual #159                // Method android/support/constraint/a/e.b:()V
       7: aload_0
       8: iconst_0
       9: putfield      #105                // Field ac:I
      12: aload_0
      13: iconst_0
      14: putfield      #243                // Field ae:I
      17: aload_0
      18: iconst_0
      19: putfield      #111                // Field ad:I
      22: aload_0
      23: iconst_0
      24: putfield      #245                // Field af:I
      27: aload_0
      28: invokespecial #331                // Method android/support/constraint/a/a/n.f:()V
      31: return

  public boolean q(int);
    Code:
       0: aload_0
       1: getfield      #47                 // Field ao:I
       4: iload_1
       5: iand
       6: iload_1
       7: if_icmpne     12
      10: iconst_1
      11: ireturn
      12: iconst_0
      13: ireturn
}
