public class android.support.constraint.a.a.f extends android.support.constraint.a.a.d {
  protected float ab;

  protected int ac;

  protected int ad;

  public android.support.constraint.a.a.f();
    Code:
       0: aload_0
       1: invokespecial #24                 // Method android/support/constraint/a/a/d."<init>":()V
       4: aload_0
       5: ldc           #25                 // float -1.0f
       7: putfield      #27                 // Field ab:F
      10: aload_0
      11: iconst_m1
      12: putfield      #29                 // Field ac:I
      15: aload_0
      16: iconst_m1
      17: putfield      #31                 // Field ad:I
      20: aload_0
      21: aload_0
      22: getfield      #34                 // Field r:Landroid/support/constraint/a/a/c;
      25: putfield      #36                 // Field ae:Landroid/support/constraint/a/a/c;
      28: iconst_0
      29: istore_1
      30: aload_0
      31: iconst_0
      32: putfield      #38                 // Field af:I
      35: aload_0
      36: iconst_0
      37: putfield      #40                 // Field ag:Z
      40: aload_0
      41: iconst_0
      42: putfield      #42                 // Field ah:I
      45: aload_0
      46: new           #44                 // class android/support/constraint/a/a/i
      49: dup
      50: invokespecial #45                 // Method android/support/constraint/a/a/i."<init>":()V
      53: putfield      #47                 // Field ai:Landroid/support/constraint/a/a/i;
      56: aload_0
      57: bipush        8
      59: putfield      #49                 // Field aj:I
      62: aload_0
      63: getfield      #53                 // Field z:Ljava/util/ArrayList;
      66: invokevirtual #58                 // Method java/util/ArrayList.clear:()V
      69: aload_0
      70: getfield      #53                 // Field z:Ljava/util/ArrayList;
      73: aload_0
      74: getfield      #36                 // Field ae:Landroid/support/constraint/a/a/c;
      77: invokevirtual #62                 // Method java/util/ArrayList.add:(Ljava/lang/Object;)Z
      80: pop
      81: aload_0
      82: getfield      #66                 // Field y:[Landroid/support/constraint/a/a/c;
      85: arraylength
      86: istore_2
      87: iload_1
      88: iload_2
      89: if_icmpge     109
      92: aload_0
      93: getfield      #66                 // Field y:[Landroid/support/constraint/a/a/c;
      96: iload_1
      97: aload_0
      98: getfield      #36                 // Field ae:Landroid/support/constraint/a/a/c;
     101: aastore
     102: iload_1
     103: iconst_1
     104: iadd
     105: istore_1
     106: goto          87
     109: return

  public java.util.ArrayList<android.support.constraint.a.a.c> C();
    Code:
       0: aload_0
       1: getfield      #53                 // Field z:Ljava/util/ArrayList;
       4: areturn

  public int H();
    Code:
       0: aload_0
       1: getfield      #38                 // Field af:I
       4: ireturn

  public android.support.constraint.a.a.c a(android.support.constraint.a.a.c$c);
    Code:
       0: getstatic     #78                 // Field android/support/constraint/a/a/f$1.a:[I
       3: aload_1
       4: invokevirtual #83                 // Method android/support/constraint/a/a/c$c.ordinal:()I
       7: iaload
       8: tableswitch   { // 1 to 9
                     1: 77
                     2: 77
                     3: 65
                     4: 65
                     5: 63
                     6: 63
                     7: 63
                     8: 63
                     9: 63
               default: 60
          }
      60: goto          90
      63: aconst_null
      64: areturn
      65: aload_0
      66: getfield      #38                 // Field af:I
      69: ifne          90
      72: aload_0
      73: getfield      #36                 // Field ae:Landroid/support/constraint/a/a/c;
      76: areturn
      77: aload_0
      78: getfield      #38                 // Field af:I
      81: iconst_1
      82: if_icmpne     90
      85: aload_0
      86: getfield      #36                 // Field ae:Landroid/support/constraint/a/a/c;
      89: areturn
      90: new           #85                 // class java/lang/AssertionError
      93: dup
      94: aload_1
      95: invokevirtual #89                 // Method android/support/constraint/a/a/c$c.name:()Ljava/lang/String;
      98: invokespecial #92                 // Method java/lang/AssertionError."<init>":(Ljava/lang/Object;)V
     101: athrow

  public void a(int);
    Code:
       0: aload_0
       1: getfield      #38                 // Field af:I
       4: iload_1
       5: if_icmpne     9
       8: return
       9: aload_0
      10: iload_1
      11: putfield      #38                 // Field af:I
      14: aload_0
      15: getfield      #53                 // Field z:Ljava/util/ArrayList;
      18: invokevirtual #58                 // Method java/util/ArrayList.clear:()V
      21: aload_0
      22: getfield      #38                 // Field af:I
      25: iconst_1
      26: if_icmpne     42
      29: aload_0
      30: getfield      #96                 // Field q:Landroid/support/constraint/a/a/c;
      33: astore_3
      34: aload_0
      35: aload_3
      36: putfield      #36                 // Field ae:Landroid/support/constraint/a/a/c;
      39: goto          50
      42: aload_0
      43: getfield      #34                 // Field r:Landroid/support/constraint/a/a/c;
      46: astore_3
      47: goto          34
      50: aload_0
      51: getfield      #53                 // Field z:Ljava/util/ArrayList;
      54: aload_0
      55: getfield      #36                 // Field ae:Landroid/support/constraint/a/a/c;
      58: invokevirtual #62                 // Method java/util/ArrayList.add:(Ljava/lang/Object;)Z
      61: pop
      62: aload_0
      63: getfield      #66                 // Field y:[Landroid/support/constraint/a/a/c;
      66: arraylength
      67: istore_2
      68: iconst_0
      69: istore_1
      70: iload_1
      71: iload_2
      72: if_icmpge     92
      75: aload_0
      76: getfield      #66                 // Field y:[Landroid/support/constraint/a/a/c;
      79: iload_1
      80: aload_0
      81: getfield      #36                 // Field ae:Landroid/support/constraint/a/a/c;
      84: aastore
      85: iload_1
      86: iconst_1
      87: iadd
      88: istore_1
      89: goto          70
      92: return

  public void a(android.support.constraint.a.e);
    Code:
       0: aload_0
       1: invokevirtual #101                // Method j:()Landroid/support/constraint/a/a/d;
       4: checkcast     #103                // class android/support/constraint/a/a/e
       7: astore        5
       9: aload         5
      11: ifnonnull     15
      14: return
      15: aload         5
      17: getstatic     #107                // Field android/support/constraint/a/a/c$c.b:Landroid/support/constraint/a/a/c$c;
      20: invokevirtual #109                // Method android/support/constraint/a/a/e.a:(Landroid/support/constraint/a/a/c$c;)Landroid/support/constraint/a/a/c;
      23: astore_3
      24: aload         5
      26: getstatic     #112                // Field android/support/constraint/a/a/c$c.d:Landroid/support/constraint/a/a/c$c;
      29: invokevirtual #109                // Method android/support/constraint/a/a/e.a:(Landroid/support/constraint/a/a/c$c;)Landroid/support/constraint/a/a/c;
      32: astore        4
      34: aload_0
      35: getfield      #116                // Field B:Landroid/support/constraint/a/a/d;
      38: ifnull        61
      41: aload_0
      42: getfield      #116                // Field B:Landroid/support/constraint/a/a/d;
      45: getfield      #120                // Field android/support/constraint/a/a/d.A:[Landroid/support/constraint/a/a/d$a;
      48: iconst_0
      49: aaload
      50: getstatic     #125                // Field android/support/constraint/a/a/d$a.b:Landroid/support/constraint/a/a/d$a;
      53: if_acmpne     61
      56: iconst_1
      57: istore_2
      58: goto          63
      61: iconst_0
      62: istore_2
      63: aload_0
      64: getfield      #38                 // Field af:I
      67: ifne          118
      70: aload         5
      72: getstatic     #128                // Field android/support/constraint/a/a/c$c.c:Landroid/support/constraint/a/a/c$c;
      75: invokevirtual #109                // Method android/support/constraint/a/a/e.a:(Landroid/support/constraint/a/a/c$c;)Landroid/support/constraint/a/a/c;
      78: astore_3
      79: aload         5
      81: getstatic     #131                // Field android/support/constraint/a/a/c$c.e:Landroid/support/constraint/a/a/c$c;
      84: invokevirtual #109                // Method android/support/constraint/a/a/e.a:(Landroid/support/constraint/a/a/c$c;)Landroid/support/constraint/a/a/c;
      87: astore        4
      89: aload_0
      90: getfield      #116                // Field B:Landroid/support/constraint/a/a/d;
      93: ifnull        116
      96: aload_0
      97: getfield      #116                // Field B:Landroid/support/constraint/a/a/d;
     100: getfield      #120                // Field android/support/constraint/a/a/d.A:[Landroid/support/constraint/a/a/d$a;
     103: iconst_1
     104: aaload
     105: getstatic     #125                // Field android/support/constraint/a/a/d$a.b:Landroid/support/constraint/a/a/d$a;
     108: if_acmpne     116
     111: iconst_1
     112: istore_2
     113: goto          118
     116: iconst_0
     117: istore_2
     118: aload_0
     119: getfield      #29                 // Field ac:I
     122: iconst_m1
     123: if_icmpeq     173
     126: aload_1
     127: aload_0
     128: getfield      #36                 // Field ae:Landroid/support/constraint/a/a/c;
     131: invokevirtual #136                // Method android/support/constraint/a/e.a:(Ljava/lang/Object;)Landroid/support/constraint/a/h;
     134: astore        5
     136: aload_1
     137: aload         5
     139: aload_1
     140: aload_3
     141: invokevirtual #136                // Method android/support/constraint/a/e.a:(Ljava/lang/Object;)Landroid/support/constraint/a/h;
     144: aload_0
     145: getfield      #29                 // Field ac:I
     148: bipush        6
     150: invokevirtual #139                // Method android/support/constraint/a/e.c:(Landroid/support/constraint/a/h;Landroid/support/constraint/a/h;II)Landroid/support/constraint/a/b;
     153: pop
     154: iload_2
     155: ifeq          288
     158: aload_1
     159: aload_1
     160: aload         4
     162: invokevirtual #136                // Method android/support/constraint/a/e.a:(Ljava/lang/Object;)Landroid/support/constraint/a/h;
     165: aload         5
     167: iconst_0
     168: iconst_5
     169: invokevirtual #142                // Method android/support/constraint/a/e.a:(Landroid/support/constraint/a/h;Landroid/support/constraint/a/h;II)V
     172: return
     173: aload_0
     174: getfield      #31                 // Field ad:I
     177: iconst_m1
     178: if_icmpeq     243
     181: aload_1
     182: aload_0
     183: getfield      #36                 // Field ae:Landroid/support/constraint/a/a/c;
     186: invokevirtual #136                // Method android/support/constraint/a/e.a:(Ljava/lang/Object;)Landroid/support/constraint/a/h;
     189: astore        5
     191: aload_1
     192: aload         4
     194: invokevirtual #136                // Method android/support/constraint/a/e.a:(Ljava/lang/Object;)Landroid/support/constraint/a/h;
     197: astore        4
     199: aload_1
     200: aload         5
     202: aload         4
     204: aload_0
     205: getfield      #31                 // Field ad:I
     208: ineg
     209: bipush        6
     211: invokevirtual #139                // Method android/support/constraint/a/e.c:(Landroid/support/constraint/a/h;Landroid/support/constraint/a/h;II)Landroid/support/constraint/a/b;
     214: pop
     215: iload_2
     216: ifeq          288
     219: aload_1
     220: aload         5
     222: aload_1
     223: aload_3
     224: invokevirtual #136                // Method android/support/constraint/a/e.a:(Ljava/lang/Object;)Landroid/support/constraint/a/h;
     227: iconst_0
     228: iconst_5
     229: invokevirtual #142                // Method android/support/constraint/a/e.a:(Landroid/support/constraint/a/h;Landroid/support/constraint/a/h;II)V
     232: aload_1
     233: aload         4
     235: aload         5
     237: iconst_0
     238: iconst_5
     239: invokevirtual #142                // Method android/support/constraint/a/e.a:(Landroid/support/constraint/a/h;Landroid/support/constraint/a/h;II)V
     242: return
     243: aload_0
     244: getfield      #27                 // Field ab:F
     247: ldc           #25                 // float -1.0f
     249: fcmpl
     250: ifeq          288
     253: aload_1
     254: aload_1
     255: aload_1
     256: aload_0
     257: getfield      #36                 // Field ae:Landroid/support/constraint/a/a/c;
     260: invokevirtual #136                // Method android/support/constraint/a/e.a:(Ljava/lang/Object;)Landroid/support/constraint/a/h;
     263: aload_1
     264: aload_3
     265: invokevirtual #136                // Method android/support/constraint/a/e.a:(Ljava/lang/Object;)Landroid/support/constraint/a/h;
     268: aload_1
     269: aload         4
     271: invokevirtual #136                // Method android/support/constraint/a/e.a:(Ljava/lang/Object;)Landroid/support/constraint/a/h;
     274: aload_0
     275: getfield      #27                 // Field ab:F
     278: aload_0
     279: getfield      #40                 // Field ag:Z
     282: invokestatic  #145                // Method android/support/constraint/a/e.a:(Landroid/support/constraint/a/e;Landroid/support/constraint/a/h;Landroid/support/constraint/a/h;Landroid/support/constraint/a/h;FZ)Landroid/support/constraint/a/b;
     285: invokevirtual #148                // Method android/support/constraint/a/e.a:(Landroid/support/constraint/a/b;)V
     288: return

  public boolean a();
    Code:
       0: iconst_1
       1: ireturn

  public void b(int);
    Code:
       0: aload_0
       1: invokevirtual #101                // Method j:()Landroid/support/constraint/a/a/d;
       4: astore_3
       5: aload_3
       6: ifnonnull     10
       9: return
      10: aload_0
      11: invokevirtual #151                // Method H:()I
      14: iconst_1
      15: if_icmpne     250
      18: aload_0
      19: getfield      #34                 // Field r:Landroid/support/constraint/a/a/c;
      22: invokevirtual #156                // Method android/support/constraint/a/a/c.a:()Landroid/support/constraint/a/a/j;
      25: iconst_1
      26: aload_3
      27: getfield      #157                // Field android/support/constraint/a/a/d.r:Landroid/support/constraint/a/a/c;
      30: invokevirtual #156                // Method android/support/constraint/a/a/c.a:()Landroid/support/constraint/a/a/j;
      33: iconst_0
      34: invokevirtual #162                // Method android/support/constraint/a/a/j.a:(ILandroid/support/constraint/a/a/j;I)V
      37: aload_0
      38: getfield      #165                // Field t:Landroid/support/constraint/a/a/c;
      41: invokevirtual #156                // Method android/support/constraint/a/a/c.a:()Landroid/support/constraint/a/a/j;
      44: iconst_1
      45: aload_3
      46: getfield      #157                // Field android/support/constraint/a/a/d.r:Landroid/support/constraint/a/a/c;
      49: invokevirtual #156                // Method android/support/constraint/a/a/c.a:()Landroid/support/constraint/a/a/j;
      52: iconst_0
      53: invokevirtual #162                // Method android/support/constraint/a/a/j.a:(ILandroid/support/constraint/a/a/j;I)V
      56: aload_0
      57: getfield      #29                 // Field ac:I
      60: iconst_m1
      61: if_icmpeq     117
      64: aload_0
      65: getfield      #96                 // Field q:Landroid/support/constraint/a/a/c;
      68: invokevirtual #156                // Method android/support/constraint/a/a/c.a:()Landroid/support/constraint/a/a/j;
      71: iconst_1
      72: aload_3
      73: getfield      #166                // Field android/support/constraint/a/a/d.q:Landroid/support/constraint/a/a/c;
      76: invokevirtual #156                // Method android/support/constraint/a/a/c.a:()Landroid/support/constraint/a/a/j;
      79: aload_0
      80: getfield      #29                 // Field ac:I
      83: invokevirtual #162                // Method android/support/constraint/a/a/j.a:(ILandroid/support/constraint/a/a/j;I)V
      86: aload_0
      87: getfield      #169                // Field s:Landroid/support/constraint/a/a/c;
      90: invokevirtual #156                // Method android/support/constraint/a/a/c.a:()Landroid/support/constraint/a/a/j;
      93: astore_2
      94: aload_3
      95: getfield      #166                // Field android/support/constraint/a/a/d.q:Landroid/support/constraint/a/a/c;
      98: astore_3
      99: aload_3
     100: invokevirtual #156                // Method android/support/constraint/a/a/c.a:()Landroid/support/constraint/a/a/j;
     103: astore_3
     104: aload_0
     105: getfield      #29                 // Field ac:I
     108: istore_1
     109: aload_2
     110: iconst_1
     111: aload_3
     112: iload_1
     113: invokevirtual #162                // Method android/support/constraint/a/a/j.a:(ILandroid/support/constraint/a/a/j;I)V
     116: return
     117: aload_0
     118: getfield      #31                 // Field ad:I
     121: iconst_m1
     122: if_icmpeq     175
     125: aload_0
     126: getfield      #96                 // Field q:Landroid/support/constraint/a/a/c;
     129: invokevirtual #156                // Method android/support/constraint/a/a/c.a:()Landroid/support/constraint/a/a/j;
     132: iconst_1
     133: aload_3
     134: getfield      #170                // Field android/support/constraint/a/a/d.s:Landroid/support/constraint/a/a/c;
     137: invokevirtual #156                // Method android/support/constraint/a/a/c.a:()Landroid/support/constraint/a/a/j;
     140: aload_0
     141: getfield      #31                 // Field ad:I
     144: ineg
     145: invokevirtual #162                // Method android/support/constraint/a/a/j.a:(ILandroid/support/constraint/a/a/j;I)V
     148: aload_0
     149: getfield      #169                // Field s:Landroid/support/constraint/a/a/c;
     152: invokevirtual #156                // Method android/support/constraint/a/a/c.a:()Landroid/support/constraint/a/a/j;
     155: astore_2
     156: aload_3
     157: getfield      #170                // Field android/support/constraint/a/a/d.s:Landroid/support/constraint/a/a/c;
     160: astore_3
     161: aload_3
     162: invokevirtual #156                // Method android/support/constraint/a/a/c.a:()Landroid/support/constraint/a/a/j;
     165: astore_3
     166: aload_0
     167: getfield      #31                 // Field ad:I
     170: ineg
     171: istore_1
     172: goto          109
     175: aload_0
     176: getfield      #27                 // Field ab:F
     179: ldc           #25                 // float -1.0f
     181: fcmpl
     182: ifeq          448
     185: aload_3
     186: invokevirtual #173                // Method android/support/constraint/a/a/d.F:()Landroid/support/constraint/a/a/d$a;
     189: getstatic     #175                // Field android/support/constraint/a/a/d$a.a:Landroid/support/constraint/a/a/d$a;
     192: if_acmpne     448
     195: aload_3
     196: getfield      #177                // Field android/support/constraint/a/a/d.C:I
     199: i2f
     200: aload_0
     201: getfield      #27                 // Field ab:F
     204: fmul
     205: f2i
     206: istore_1
     207: aload_0
     208: getfield      #96                 // Field q:Landroid/support/constraint/a/a/c;
     211: invokevirtual #156                // Method android/support/constraint/a/a/c.a:()Landroid/support/constraint/a/a/j;
     214: iconst_1
     215: aload_3
     216: getfield      #166                // Field android/support/constraint/a/a/d.q:Landroid/support/constraint/a/a/c;
     219: invokevirtual #156                // Method android/support/constraint/a/a/c.a:()Landroid/support/constraint/a/a/j;
     222: iload_1
     223: invokevirtual #162                // Method android/support/constraint/a/a/j.a:(ILandroid/support/constraint/a/a/j;I)V
     226: aload_0
     227: getfield      #169                // Field s:Landroid/support/constraint/a/a/c;
     230: invokevirtual #156                // Method android/support/constraint/a/a/c.a:()Landroid/support/constraint/a/a/j;
     233: astore_2
     234: aload_3
     235: getfield      #166                // Field android/support/constraint/a/a/d.q:Landroid/support/constraint/a/a/c;
     238: astore_3
     239: aload_2
     240: iconst_1
     241: aload_3
     242: invokevirtual #156                // Method android/support/constraint/a/a/c.a:()Landroid/support/constraint/a/a/j;
     245: iload_1
     246: invokevirtual #162                // Method android/support/constraint/a/a/j.a:(ILandroid/support/constraint/a/a/j;I)V
     249: return
     250: aload_0
     251: getfield      #96                 // Field q:Landroid/support/constraint/a/a/c;
     254: invokevirtual #156                // Method android/support/constraint/a/a/c.a:()Landroid/support/constraint/a/a/j;
     257: iconst_1
     258: aload_3
     259: getfield      #166                // Field android/support/constraint/a/a/d.q:Landroid/support/constraint/a/a/c;
     262: invokevirtual #156                // Method android/support/constraint/a/a/c.a:()Landroid/support/constraint/a/a/j;
     265: iconst_0
     266: invokevirtual #162                // Method android/support/constraint/a/a/j.a:(ILandroid/support/constraint/a/a/j;I)V
     269: aload_0
     270: getfield      #169                // Field s:Landroid/support/constraint/a/a/c;
     273: invokevirtual #156                // Method android/support/constraint/a/a/c.a:()Landroid/support/constraint/a/a/j;
     276: iconst_1
     277: aload_3
     278: getfield      #166                // Field android/support/constraint/a/a/d.q:Landroid/support/constraint/a/a/c;
     281: invokevirtual #156                // Method android/support/constraint/a/a/c.a:()Landroid/support/constraint/a/a/j;
     284: iconst_0
     285: invokevirtual #162                // Method android/support/constraint/a/a/j.a:(ILandroid/support/constraint/a/a/j;I)V
     288: aload_0
     289: getfield      #29                 // Field ac:I
     292: iconst_m1
     293: if_icmpeq     334
     296: aload_0
     297: getfield      #34                 // Field r:Landroid/support/constraint/a/a/c;
     300: invokevirtual #156                // Method android/support/constraint/a/a/c.a:()Landroid/support/constraint/a/a/j;
     303: iconst_1
     304: aload_3
     305: getfield      #157                // Field android/support/constraint/a/a/d.r:Landroid/support/constraint/a/a/c;
     308: invokevirtual #156                // Method android/support/constraint/a/a/c.a:()Landroid/support/constraint/a/a/j;
     311: aload_0
     312: getfield      #29                 // Field ac:I
     315: invokevirtual #162                // Method android/support/constraint/a/a/j.a:(ILandroid/support/constraint/a/a/j;I)V
     318: aload_0
     319: getfield      #165                // Field t:Landroid/support/constraint/a/a/c;
     322: invokevirtual #156                // Method android/support/constraint/a/a/c.a:()Landroid/support/constraint/a/a/j;
     325: astore_2
     326: aload_3
     327: getfield      #157                // Field android/support/constraint/a/a/d.r:Landroid/support/constraint/a/a/c;
     330: astore_3
     331: goto          99
     334: aload_0
     335: getfield      #31                 // Field ad:I
     338: iconst_m1
     339: if_icmpeq     381
     342: aload_0
     343: getfield      #34                 // Field r:Landroid/support/constraint/a/a/c;
     346: invokevirtual #156                // Method android/support/constraint/a/a/c.a:()Landroid/support/constraint/a/a/j;
     349: iconst_1
     350: aload_3
     351: getfield      #178                // Field android/support/constraint/a/a/d.t:Landroid/support/constraint/a/a/c;
     354: invokevirtual #156                // Method android/support/constraint/a/a/c.a:()Landroid/support/constraint/a/a/j;
     357: aload_0
     358: getfield      #31                 // Field ad:I
     361: ineg
     362: invokevirtual #162                // Method android/support/constraint/a/a/j.a:(ILandroid/support/constraint/a/a/j;I)V
     365: aload_0
     366: getfield      #165                // Field t:Landroid/support/constraint/a/a/c;
     369: invokevirtual #156                // Method android/support/constraint/a/a/c.a:()Landroid/support/constraint/a/a/j;
     372: astore_2
     373: aload_3
     374: getfield      #178                // Field android/support/constraint/a/a/d.t:Landroid/support/constraint/a/a/c;
     377: astore_3
     378: goto          161
     381: aload_0
     382: getfield      #27                 // Field ab:F
     385: ldc           #25                 // float -1.0f
     387: fcmpl
     388: ifeq          448
     391: aload_3
     392: invokevirtual #181                // Method android/support/constraint/a/a/d.G:()Landroid/support/constraint/a/a/d$a;
     395: getstatic     #175                // Field android/support/constraint/a/a/d$a.a:Landroid/support/constraint/a/a/d$a;
     398: if_acmpne     448
     401: aload_3
     402: getfield      #184                // Field android/support/constraint/a/a/d.D:I
     405: i2f
     406: aload_0
     407: getfield      #27                 // Field ab:F
     410: fmul
     411: f2i
     412: istore_1
     413: aload_0
     414: getfield      #34                 // Field r:Landroid/support/constraint/a/a/c;
     417: invokevirtual #156                // Method android/support/constraint/a/a/c.a:()Landroid/support/constraint/a/a/j;
     420: iconst_1
     421: aload_3
     422: getfield      #157                // Field android/support/constraint/a/a/d.r:Landroid/support/constraint/a/a/c;
     425: invokevirtual #156                // Method android/support/constraint/a/a/c.a:()Landroid/support/constraint/a/a/j;
     428: iload_1
     429: invokevirtual #162                // Method android/support/constraint/a/a/j.a:(ILandroid/support/constraint/a/a/j;I)V
     432: aload_0
     433: getfield      #165                // Field t:Landroid/support/constraint/a/a/c;
     436: invokevirtual #156                // Method android/support/constraint/a/a/c.a:()Landroid/support/constraint/a/a/j;
     439: astore_2
     440: aload_3
     441: getfield      #157                // Field android/support/constraint/a/a/d.r:Landroid/support/constraint/a/a/c;
     444: astore_3
     445: goto          239
     448: return

  public void b(android.support.constraint.a.e);
    Code:
       0: aload_0
       1: invokevirtual #101                // Method j:()Landroid/support/constraint/a/a/d;
       4: ifnonnull     8
       7: return
       8: aload_1
       9: aload_0
      10: getfield      #36                 // Field ae:Landroid/support/constraint/a/a/c;
      13: invokevirtual #187                // Method android/support/constraint/a/e.b:(Ljava/lang/Object;)I
      16: istore_2
      17: aload_0
      18: getfield      #38                 // Field af:I
      21: iconst_1
      22: if_icmpne     52
      25: aload_0
      26: iload_2
      27: invokevirtual #190                // Method f:(I)V
      30: aload_0
      31: iconst_0
      32: invokevirtual #193                // Method g:(I)V
      35: aload_0
      36: aload_0
      37: invokevirtual #101                // Method j:()Landroid/support/constraint/a/a/d;
      40: invokevirtual #195                // Method android/support/constraint/a/a/d.q:()I
      43: invokevirtual #198                // Method i:(I)V
      46: aload_0
      47: iconst_0
      48: invokevirtual #201                // Method h:(I)V
      51: return
      52: aload_0
      53: iconst_0
      54: invokevirtual #190                // Method f:(I)V
      57: aload_0
      58: iload_2
      59: invokevirtual #193                // Method g:(I)V
      62: aload_0
      63: aload_0
      64: invokevirtual #101                // Method j:()Landroid/support/constraint/a/a/d;
      67: invokevirtual #204                // Method android/support/constraint/a/a/d.o:()I
      70: invokevirtual #201                // Method h:(I)V
      73: aload_0
      74: iconst_0
      75: invokevirtual #198                // Method i:(I)V
      78: return

  public void e(float);
    Code:
       0: fload_1
       1: ldc           #25                 // float -1.0f
       3: fcmpl
       4: ifle          22
       7: aload_0
       8: fload_1
       9: putfield      #27                 // Field ab:F
      12: aload_0
      13: iconst_m1
      14: putfield      #29                 // Field ac:I
      17: aload_0
      18: iconst_m1
      19: putfield      #31                 // Field ad:I
      22: return

  public void q(int);
    Code:
       0: iload_1
       1: iconst_m1
       2: if_icmple     21
       5: aload_0
       6: ldc           #25                 // float -1.0f
       8: putfield      #27                 // Field ab:F
      11: aload_0
      12: iload_1
      13: putfield      #29                 // Field ac:I
      16: aload_0
      17: iconst_m1
      18: putfield      #31                 // Field ad:I
      21: return

  public void r(int);
    Code:
       0: iload_1
       1: iconst_m1
       2: if_icmple     21
       5: aload_0
       6: ldc           #25                 // float -1.0f
       8: putfield      #27                 // Field ab:F
      11: aload_0
      12: iconst_m1
      13: putfield      #29                 // Field ac:I
      16: aload_0
      17: iload_1
      18: putfield      #31                 // Field ad:I
      21: return
}
