public class android.support.constraint.a.a.h {
  static boolean[] a;

  static {};
    Code:
       0: iconst_3
       1: newarray       boolean
       3: putstatic     #10                 // Field a:[Z
       6: return

  static void a(int, android.support.constraint.a.a.d);
    Code:
       0: aload_1
       1: invokevirtual #17                 // Method android/support/constraint/a/a/d.g:()V
       4: aload_1
       5: getfield      #21                 // Field android/support/constraint/a/a/d.q:Landroid/support/constraint/a/a/c;
       8: invokevirtual #26                 // Method android/support/constraint/a/a/c.a:()Landroid/support/constraint/a/a/j;
      11: astore_3
      12: aload_1
      13: getfield      #29                 // Field android/support/constraint/a/a/d.r:Landroid/support/constraint/a/a/c;
      16: invokevirtual #26                 // Method android/support/constraint/a/a/c.a:()Landroid/support/constraint/a/a/j;
      19: astore        4
      21: aload_1
      22: getfield      #32                 // Field android/support/constraint/a/a/d.s:Landroid/support/constraint/a/a/c;
      25: invokevirtual #26                 // Method android/support/constraint/a/a/c.a:()Landroid/support/constraint/a/a/j;
      28: astore        5
      30: aload_1
      31: getfield      #35                 // Field android/support/constraint/a/a/d.t:Landroid/support/constraint/a/a/c;
      34: invokevirtual #26                 // Method android/support/constraint/a/a/c.a:()Landroid/support/constraint/a/a/j;
      37: astore        6
      39: iload_0
      40: bipush        8
      42: iand
      43: bipush        8
      45: if_icmpne     53
      48: iconst_1
      49: istore_0
      50: goto          55
      53: iconst_0
      54: istore_0
      55: aload_3
      56: getfield      #40                 // Field android/support/constraint/a/a/j.g:I
      59: iconst_4
      60: if_icmpeq     593
      63: aload         5
      65: getfield      #40                 // Field android/support/constraint/a/a/j.g:I
      68: iconst_4
      69: if_icmpeq     593
      72: aload_1
      73: getfield      #44                 // Field android/support/constraint/a/a/d.A:[Landroid/support/constraint/a/a/d$a;
      76: iconst_0
      77: aaload
      78: getstatic     #49                 // Field android/support/constraint/a/a/d$a.a:Landroid/support/constraint/a/a/d$a;
      81: if_acmpne     365
      84: aload_1
      85: getfield      #21                 // Field android/support/constraint/a/a/d.q:Landroid/support/constraint/a/a/c;
      88: getfield      #52                 // Field android/support/constraint/a/a/c.c:Landroid/support/constraint/a/a/c;
      91: ifnonnull     148
      94: aload_1
      95: getfield      #32                 // Field android/support/constraint/a/a/d.s:Landroid/support/constraint/a/a/c;
      98: getfield      #52                 // Field android/support/constraint/a/a/c.c:Landroid/support/constraint/a/a/c;
     101: ifnonnull     148
     104: aload_3
     105: iconst_1
     106: invokevirtual #56                 // Method android/support/constraint/a/a/j.b:(I)V
     109: aload         5
     111: iconst_1
     112: invokevirtual #56                 // Method android/support/constraint/a/a/j.b:(I)V
     115: iload_0
     116: ifeq          133
     119: aload         5
     121: aload_3
     122: iconst_1
     123: aload_1
     124: invokevirtual #60                 // Method android/support/constraint/a/a/d.h:()Landroid/support/constraint/a/a/k;
     127: invokevirtual #63                 // Method android/support/constraint/a/a/j.a:(Landroid/support/constraint/a/a/j;ILandroid/support/constraint/a/a/k;)V
     130: goto          593
     133: aload_1
     134: invokevirtual #67                 // Method android/support/constraint/a/a/d.o:()I
     137: istore_2
     138: aload         5
     140: aload_3
     141: iload_2
     142: invokevirtual #70                 // Method android/support/constraint/a/a/j.a:(Landroid/support/constraint/a/a/j;I)V
     145: goto          593
     148: aload_1
     149: getfield      #21                 // Field android/support/constraint/a/a/d.q:Landroid/support/constraint/a/a/c;
     152: getfield      #52                 // Field android/support/constraint/a/a/c.c:Landroid/support/constraint/a/a/c;
     155: ifnull        186
     158: aload_1
     159: getfield      #32                 // Field android/support/constraint/a/a/d.s:Landroid/support/constraint/a/a/c;
     162: getfield      #52                 // Field android/support/constraint/a/a/c.c:Landroid/support/constraint/a/a/c;
     165: ifnonnull     186
     168: aload_3
     169: iconst_1
     170: invokevirtual #56                 // Method android/support/constraint/a/a/j.b:(I)V
     173: aload         5
     175: iconst_1
     176: invokevirtual #56                 // Method android/support/constraint/a/a/j.b:(I)V
     179: iload_0
     180: ifeq          133
     183: goto          119
     186: aload_1
     187: getfield      #21                 // Field android/support/constraint/a/a/d.q:Landroid/support/constraint/a/a/c;
     190: getfield      #52                 // Field android/support/constraint/a/a/c.c:Landroid/support/constraint/a/a/c;
     193: ifnonnull     262
     196: aload_1
     197: getfield      #32                 // Field android/support/constraint/a/a/d.s:Landroid/support/constraint/a/a/c;
     200: getfield      #52                 // Field android/support/constraint/a/a/c.c:Landroid/support/constraint/a/a/c;
     203: ifnull        262
     206: aload_3
     207: iconst_1
     208: invokevirtual #56                 // Method android/support/constraint/a/a/j.b:(I)V
     211: aload         5
     213: iconst_1
     214: invokevirtual #56                 // Method android/support/constraint/a/a/j.b:(I)V
     217: aload_3
     218: aload         5
     220: aload_1
     221: invokevirtual #67                 // Method android/support/constraint/a/a/d.o:()I
     224: ineg
     225: invokevirtual #70                 // Method android/support/constraint/a/a/j.a:(Landroid/support/constraint/a/a/j;I)V
     228: iload_0
     229: ifeq          246
     232: aload_3
     233: aload         5
     235: iconst_m1
     236: aload_1
     237: invokevirtual #60                 // Method android/support/constraint/a/a/d.h:()Landroid/support/constraint/a/a/k;
     240: invokevirtual #63                 // Method android/support/constraint/a/a/j.a:(Landroid/support/constraint/a/a/j;ILandroid/support/constraint/a/a/k;)V
     243: goto          593
     246: aload_1
     247: invokevirtual #67                 // Method android/support/constraint/a/a/d.o:()I
     250: istore_2
     251: aload_3
     252: aload         5
     254: iload_2
     255: ineg
     256: invokevirtual #70                 // Method android/support/constraint/a/a/j.a:(Landroid/support/constraint/a/a/j;I)V
     259: goto          593
     262: aload_1
     263: getfield      #21                 // Field android/support/constraint/a/a/d.q:Landroid/support/constraint/a/a/c;
     266: getfield      #52                 // Field android/support/constraint/a/a/c.c:Landroid/support/constraint/a/a/c;
     269: ifnull        593
     272: aload_1
     273: getfield      #32                 // Field android/support/constraint/a/a/d.s:Landroid/support/constraint/a/a/c;
     276: getfield      #52                 // Field android/support/constraint/a/a/c.c:Landroid/support/constraint/a/a/c;
     279: ifnull        593
     282: aload_3
     283: iconst_2
     284: invokevirtual #56                 // Method android/support/constraint/a/a/j.b:(I)V
     287: aload         5
     289: iconst_2
     290: invokevirtual #56                 // Method android/support/constraint/a/a/j.b:(I)V
     293: iload_0
     294: ifeq          339
     297: aload_1
     298: invokevirtual #60                 // Method android/support/constraint/a/a/d.h:()Landroid/support/constraint/a/a/k;
     301: aload_3
     302: invokevirtual #75                 // Method android/support/constraint/a/a/k.a:(Landroid/support/constraint/a/a/l;)V
     305: aload_1
     306: invokevirtual #60                 // Method android/support/constraint/a/a/d.h:()Landroid/support/constraint/a/a/k;
     309: aload         5
     311: invokevirtual #75                 // Method android/support/constraint/a/a/k.a:(Landroid/support/constraint/a/a/l;)V
     314: aload_3
     315: aload         5
     317: iconst_m1
     318: aload_1
     319: invokevirtual #60                 // Method android/support/constraint/a/a/d.h:()Landroid/support/constraint/a/a/k;
     322: invokevirtual #77                 // Method android/support/constraint/a/a/j.b:(Landroid/support/constraint/a/a/j;ILandroid/support/constraint/a/a/k;)V
     325: aload         5
     327: aload_3
     328: iconst_1
     329: aload_1
     330: invokevirtual #60                 // Method android/support/constraint/a/a/d.h:()Landroid/support/constraint/a/a/k;
     333: invokevirtual #77                 // Method android/support/constraint/a/a/j.b:(Landroid/support/constraint/a/a/j;ILandroid/support/constraint/a/a/k;)V
     336: goto          593
     339: aload_3
     340: aload         5
     342: aload_1
     343: invokevirtual #67                 // Method android/support/constraint/a/a/d.o:()I
     346: ineg
     347: i2f
     348: invokevirtual #80                 // Method android/support/constraint/a/a/j.b:(Landroid/support/constraint/a/a/j;F)V
     351: aload         5
     353: aload_3
     354: aload_1
     355: invokevirtual #67                 // Method android/support/constraint/a/a/d.o:()I
     358: i2f
     359: invokevirtual #80                 // Method android/support/constraint/a/a/j.b:(Landroid/support/constraint/a/a/j;F)V
     362: goto          593
     365: aload_1
     366: getfield      #44                 // Field android/support/constraint/a/a/d.A:[Landroid/support/constraint/a/a/d$a;
     369: iconst_0
     370: aaload
     371: getstatic     #82                 // Field android/support/constraint/a/a/d$a.c:Landroid/support/constraint/a/a/d$a;
     374: if_acmpne     593
     377: aload_1
     378: iconst_0
     379: invokestatic  #85                 // Method a:(Landroid/support/constraint/a/a/d;I)Z
     382: ifeq          593
     385: aload_1
     386: invokevirtual #67                 // Method android/support/constraint/a/a/d.o:()I
     389: istore_2
     390: aload_3
     391: iconst_1
     392: invokevirtual #56                 // Method android/support/constraint/a/a/j.b:(I)V
     395: aload         5
     397: iconst_1
     398: invokevirtual #56                 // Method android/support/constraint/a/a/j.b:(I)V
     401: aload_1
     402: getfield      #21                 // Field android/support/constraint/a/a/d.q:Landroid/support/constraint/a/a/c;
     405: getfield      #52                 // Field android/support/constraint/a/a/c.c:Landroid/support/constraint/a/a/c;
     408: ifnonnull     428
     411: aload_1
     412: getfield      #32                 // Field android/support/constraint/a/a/d.s:Landroid/support/constraint/a/a/c;
     415: getfield      #52                 // Field android/support/constraint/a/a/c.c:Landroid/support/constraint/a/a/c;
     418: ifnonnull     428
     421: iload_0
     422: ifeq          138
     425: goto          119
     428: aload_1
     429: getfield      #21                 // Field android/support/constraint/a/a/d.q:Landroid/support/constraint/a/a/c;
     432: getfield      #52                 // Field android/support/constraint/a/a/c.c:Landroid/support/constraint/a/a/c;
     435: ifnull        455
     438: aload_1
     439: getfield      #32                 // Field android/support/constraint/a/a/d.s:Landroid/support/constraint/a/a/c;
     442: getfield      #52                 // Field android/support/constraint/a/a/c.c:Landroid/support/constraint/a/a/c;
     445: ifnonnull     455
     448: iload_0
     449: ifeq          138
     452: goto          119
     455: aload_1
     456: getfield      #21                 // Field android/support/constraint/a/a/d.q:Landroid/support/constraint/a/a/c;
     459: getfield      #52                 // Field android/support/constraint/a/a/c.c:Landroid/support/constraint/a/a/c;
     462: ifnonnull     482
     465: aload_1
     466: getfield      #32                 // Field android/support/constraint/a/a/d.s:Landroid/support/constraint/a/a/c;
     469: getfield      #52                 // Field android/support/constraint/a/a/c.c:Landroid/support/constraint/a/a/c;
     472: ifnull        482
     475: iload_0
     476: ifeq          251
     479: goto          232
     482: aload_1
     483: getfield      #21                 // Field android/support/constraint/a/a/d.q:Landroid/support/constraint/a/a/c;
     486: getfield      #52                 // Field android/support/constraint/a/a/c.c:Landroid/support/constraint/a/a/c;
     489: ifnull        593
     492: aload_1
     493: getfield      #32                 // Field android/support/constraint/a/a/d.s:Landroid/support/constraint/a/a/c;
     496: getfield      #52                 // Field android/support/constraint/a/a/c.c:Landroid/support/constraint/a/a/c;
     499: ifnull        593
     502: iload_0
     503: ifeq          523
     506: aload_1
     507: invokevirtual #60                 // Method android/support/constraint/a/a/d.h:()Landroid/support/constraint/a/a/k;
     510: aload_3
     511: invokevirtual #75                 // Method android/support/constraint/a/a/k.a:(Landroid/support/constraint/a/a/l;)V
     514: aload_1
     515: invokevirtual #60                 // Method android/support/constraint/a/a/d.h:()Landroid/support/constraint/a/a/k;
     518: aload         5
     520: invokevirtual #75                 // Method android/support/constraint/a/a/k.a:(Landroid/support/constraint/a/a/l;)V
     523: aload_1
     524: getfield      #89                 // Field android/support/constraint/a/a/d.E:F
     527: fconst_0
     528: fcmpl
     529: ifne          560
     532: aload_3
     533: iconst_3
     534: invokevirtual #56                 // Method android/support/constraint/a/a/j.b:(I)V
     537: aload         5
     539: iconst_3
     540: invokevirtual #56                 // Method android/support/constraint/a/a/j.b:(I)V
     543: aload_3
     544: aload         5
     546: fconst_0
     547: invokevirtual #80                 // Method android/support/constraint/a/a/j.b:(Landroid/support/constraint/a/a/j;F)V
     550: aload         5
     552: aload_3
     553: fconst_0
     554: invokevirtual #80                 // Method android/support/constraint/a/a/j.b:(Landroid/support/constraint/a/a/j;F)V
     557: goto          593
     560: aload_3
     561: iconst_2
     562: invokevirtual #56                 // Method android/support/constraint/a/a/j.b:(I)V
     565: aload         5
     567: iconst_2
     568: invokevirtual #56                 // Method android/support/constraint/a/a/j.b:(I)V
     571: aload_3
     572: aload         5
     574: iload_2
     575: ineg
     576: i2f
     577: invokevirtual #80                 // Method android/support/constraint/a/a/j.b:(Landroid/support/constraint/a/a/j;F)V
     580: aload         5
     582: aload_3
     583: iload_2
     584: i2f
     585: invokevirtual #80                 // Method android/support/constraint/a/a/j.b:(Landroid/support/constraint/a/a/j;F)V
     588: aload_1
     589: iload_2
     590: invokevirtual #91                 // Method android/support/constraint/a/a/d.h:(I)V
     593: aload         4
     595: getfield      #40                 // Field android/support/constraint/a/a/j.g:I
     598: iconst_4
     599: if_icmpeq     1284
     602: aload         6
     604: getfield      #40                 // Field android/support/constraint/a/a/j.g:I
     607: iconst_4
     608: if_icmpeq     1284
     611: aload_1
     612: getfield      #44                 // Field android/support/constraint/a/a/d.A:[Landroid/support/constraint/a/a/d$a;
     615: iconst_1
     616: aaload
     617: getstatic     #49                 // Field android/support/constraint/a/a/d$a.a:Landroid/support/constraint/a/a/d$a;
     620: if_acmpne     1001
     623: aload_1
     624: getfield      #29                 // Field android/support/constraint/a/a/d.r:Landroid/support/constraint/a/a/c;
     627: getfield      #52                 // Field android/support/constraint/a/a/c.c:Landroid/support/constraint/a/a/c;
     630: ifnonnull     725
     633: aload_1
     634: getfield      #35                 // Field android/support/constraint/a/a/d.t:Landroid/support/constraint/a/a/c;
     637: getfield      #52                 // Field android/support/constraint/a/a/c.c:Landroid/support/constraint/a/a/c;
     640: ifnonnull     725
     643: aload         4
     645: iconst_1
     646: invokevirtual #56                 // Method android/support/constraint/a/a/j.b:(I)V
     649: aload         6
     651: iconst_1
     652: invokevirtual #56                 // Method android/support/constraint/a/a/j.b:(I)V
     655: iload_0
     656: ifeq          674
     659: aload         6
     661: aload         4
     663: iconst_1
     664: aload_1
     665: invokevirtual #94                 // Method android/support/constraint/a/a/d.i:()Landroid/support/constraint/a/a/k;
     668: invokevirtual #63                 // Method android/support/constraint/a/a/j.a:(Landroid/support/constraint/a/a/j;ILandroid/support/constraint/a/a/k;)V
     671: goto          685
     674: aload         6
     676: aload         4
     678: aload_1
     679: invokevirtual #96                 // Method android/support/constraint/a/a/d.q:()I
     682: invokevirtual #70                 // Method android/support/constraint/a/a/j.a:(Landroid/support/constraint/a/a/j;I)V
     685: aload_1
     686: getfield      #99                 // Field android/support/constraint/a/a/d.u:Landroid/support/constraint/a/a/c;
     689: getfield      #52                 // Field android/support/constraint/a/a/c.c:Landroid/support/constraint/a/a/c;
     692: ifnull        1284
     695: aload_1
     696: getfield      #99                 // Field android/support/constraint/a/a/d.u:Landroid/support/constraint/a/a/c;
     699: invokevirtual #26                 // Method android/support/constraint/a/a/c.a:()Landroid/support/constraint/a/a/j;
     702: iconst_1
     703: invokevirtual #56                 // Method android/support/constraint/a/a/j.b:(I)V
     706: aload         4
     708: iconst_1
     709: aload_1
     710: getfield      #99                 // Field android/support/constraint/a/a/d.u:Landroid/support/constraint/a/a/c;
     713: invokevirtual #26                 // Method android/support/constraint/a/a/c.a:()Landroid/support/constraint/a/a/j;
     716: aload_1
     717: getfield      #102                // Field android/support/constraint/a/a/d.K:I
     720: ineg
     721: invokevirtual #105                // Method android/support/constraint/a/a/j.a:(ILandroid/support/constraint/a/a/j;I)V
     724: return
     725: aload_1
     726: getfield      #29                 // Field android/support/constraint/a/a/d.r:Landroid/support/constraint/a/a/c;
     729: getfield      #52                 // Field android/support/constraint/a/a/c.c:Landroid/support/constraint/a/a/c;
     732: ifnull        812
     735: aload_1
     736: getfield      #35                 // Field android/support/constraint/a/a/d.t:Landroid/support/constraint/a/a/c;
     739: getfield      #52                 // Field android/support/constraint/a/a/c.c:Landroid/support/constraint/a/a/c;
     742: ifnonnull     812
     745: aload         4
     747: iconst_1
     748: invokevirtual #56                 // Method android/support/constraint/a/a/j.b:(I)V
     751: aload         6
     753: iconst_1
     754: invokevirtual #56                 // Method android/support/constraint/a/a/j.b:(I)V
     757: iload_0
     758: ifeq          776
     761: aload         6
     763: aload         4
     765: iconst_1
     766: aload_1
     767: invokevirtual #94                 // Method android/support/constraint/a/a/d.i:()Landroid/support/constraint/a/a/k;
     770: invokevirtual #63                 // Method android/support/constraint/a/a/j.a:(Landroid/support/constraint/a/a/j;ILandroid/support/constraint/a/a/k;)V
     773: goto          787
     776: aload         6
     778: aload         4
     780: aload_1
     781: invokevirtual #96                 // Method android/support/constraint/a/a/d.q:()I
     784: invokevirtual #70                 // Method android/support/constraint/a/a/j.a:(Landroid/support/constraint/a/a/j;I)V
     787: aload_1
     788: getfield      #102                // Field android/support/constraint/a/a/d.K:I
     791: ifle          1284
     794: aload_1
     795: getfield      #99                 // Field android/support/constraint/a/a/d.u:Landroid/support/constraint/a/a/c;
     798: invokevirtual #26                 // Method android/support/constraint/a/a/c.a:()Landroid/support/constraint/a/a/j;
     801: iconst_1
     802: aload         4
     804: aload_1
     805: getfield      #102                // Field android/support/constraint/a/a/d.K:I
     808: invokevirtual #105                // Method android/support/constraint/a/a/j.a:(ILandroid/support/constraint/a/a/j;I)V
     811: return
     812: aload_1
     813: getfield      #29                 // Field android/support/constraint/a/a/d.r:Landroid/support/constraint/a/a/c;
     816: getfield      #52                 // Field android/support/constraint/a/a/c.c:Landroid/support/constraint/a/a/c;
     819: ifnonnull     885
     822: aload_1
     823: getfield      #35                 // Field android/support/constraint/a/a/d.t:Landroid/support/constraint/a/a/c;
     826: getfield      #52                 // Field android/support/constraint/a/a/c.c:Landroid/support/constraint/a/a/c;
     829: ifnull        885
     832: aload         4
     834: iconst_1
     835: invokevirtual #56                 // Method android/support/constraint/a/a/j.b:(I)V
     838: aload         6
     840: iconst_1
     841: invokevirtual #56                 // Method android/support/constraint/a/a/j.b:(I)V
     844: iload_0
     845: ifeq          863
     848: aload         4
     850: aload         6
     852: iconst_m1
     853: aload_1
     854: invokevirtual #94                 // Method android/support/constraint/a/a/d.i:()Landroid/support/constraint/a/a/k;
     857: invokevirtual #63                 // Method android/support/constraint/a/a/j.a:(Landroid/support/constraint/a/a/j;ILandroid/support/constraint/a/a/k;)V
     860: goto          875
     863: aload         4
     865: aload         6
     867: aload_1
     868: invokevirtual #96                 // Method android/support/constraint/a/a/d.q:()I
     871: ineg
     872: invokevirtual #70                 // Method android/support/constraint/a/a/j.a:(Landroid/support/constraint/a/a/j;I)V
     875: aload_1
     876: getfield      #102                // Field android/support/constraint/a/a/d.K:I
     879: ifle          1284
     882: goto          794
     885: aload_1
     886: getfield      #29                 // Field android/support/constraint/a/a/d.r:Landroid/support/constraint/a/a/c;
     889: getfield      #52                 // Field android/support/constraint/a/a/c.c:Landroid/support/constraint/a/a/c;
     892: ifnull        1284
     895: aload_1
     896: getfield      #35                 // Field android/support/constraint/a/a/d.t:Landroid/support/constraint/a/a/c;
     899: getfield      #52                 // Field android/support/constraint/a/a/c.c:Landroid/support/constraint/a/a/c;
     902: ifnull        1284
     905: aload         4
     907: iconst_2
     908: invokevirtual #56                 // Method android/support/constraint/a/a/j.b:(I)V
     911: aload         6
     913: iconst_2
     914: invokevirtual #56                 // Method android/support/constraint/a/a/j.b:(I)V
     917: iload_0
     918: ifeq          966
     921: aload         4
     923: aload         6
     925: iconst_m1
     926: aload_1
     927: invokevirtual #94                 // Method android/support/constraint/a/a/d.i:()Landroid/support/constraint/a/a/k;
     930: invokevirtual #77                 // Method android/support/constraint/a/a/j.b:(Landroid/support/constraint/a/a/j;ILandroid/support/constraint/a/a/k;)V
     933: aload         6
     935: aload         4
     937: iconst_1
     938: aload_1
     939: invokevirtual #94                 // Method android/support/constraint/a/a/d.i:()Landroid/support/constraint/a/a/k;
     942: invokevirtual #77                 // Method android/support/constraint/a/a/j.b:(Landroid/support/constraint/a/a/j;ILandroid/support/constraint/a/a/k;)V
     945: aload_1
     946: invokevirtual #94                 // Method android/support/constraint/a/a/d.i:()Landroid/support/constraint/a/a/k;
     949: aload         4
     951: invokevirtual #75                 // Method android/support/constraint/a/a/k.a:(Landroid/support/constraint/a/a/l;)V
     954: aload_1
     955: invokevirtual #60                 // Method android/support/constraint/a/a/d.h:()Landroid/support/constraint/a/a/k;
     958: aload         6
     960: invokevirtual #75                 // Method android/support/constraint/a/a/k.a:(Landroid/support/constraint/a/a/l;)V
     963: goto          991
     966: aload         4
     968: aload         6
     970: aload_1
     971: invokevirtual #96                 // Method android/support/constraint/a/a/d.q:()I
     974: ineg
     975: i2f
     976: invokevirtual #80                 // Method android/support/constraint/a/a/j.b:(Landroid/support/constraint/a/a/j;F)V
     979: aload         6
     981: aload         4
     983: aload_1
     984: invokevirtual #96                 // Method android/support/constraint/a/a/d.q:()I
     987: i2f
     988: invokevirtual #80                 // Method android/support/constraint/a/a/j.b:(Landroid/support/constraint/a/a/j;F)V
     991: aload_1
     992: getfield      #102                // Field android/support/constraint/a/a/d.K:I
     995: ifle          1284
     998: goto          794
    1001: aload_1
    1002: getfield      #44                 // Field android/support/constraint/a/a/d.A:[Landroid/support/constraint/a/a/d$a;
    1005: iconst_1
    1006: aaload
    1007: getstatic     #82                 // Field android/support/constraint/a/a/d$a.c:Landroid/support/constraint/a/a/d$a;
    1010: if_acmpne     1284
    1013: aload_1
    1014: iconst_1
    1015: invokestatic  #85                 // Method a:(Landroid/support/constraint/a/a/d;I)Z
    1018: ifeq          1284
    1021: aload_1
    1022: invokevirtual #96                 // Method android/support/constraint/a/a/d.q:()I
    1025: istore_2
    1026: aload         4
    1028: iconst_1
    1029: invokevirtual #56                 // Method android/support/constraint/a/a/j.b:(I)V
    1032: aload         6
    1034: iconst_1
    1035: invokevirtual #56                 // Method android/support/constraint/a/a/j.b:(I)V
    1038: aload_1
    1039: getfield      #29                 // Field android/support/constraint/a/a/d.r:Landroid/support/constraint/a/a/c;
    1042: getfield      #52                 // Field android/support/constraint/a/a/c.c:Landroid/support/constraint/a/a/c;
    1045: ifnonnull     1084
    1048: aload_1
    1049: getfield      #35                 // Field android/support/constraint/a/a/d.t:Landroid/support/constraint/a/a/c;
    1052: getfield      #52                 // Field android/support/constraint/a/a/c.c:Landroid/support/constraint/a/a/c;
    1055: ifnonnull     1084
    1058: iload_0
    1059: ifeq          1075
    1062: aload         6
    1064: aload         4
    1066: iconst_1
    1067: aload_1
    1068: invokevirtual #94                 // Method android/support/constraint/a/a/d.i:()Landroid/support/constraint/a/a/k;
    1071: invokevirtual #63                 // Method android/support/constraint/a/a/j.a:(Landroid/support/constraint/a/a/j;ILandroid/support/constraint/a/a/k;)V
    1074: return
    1075: aload         6
    1077: aload         4
    1079: iload_2
    1080: invokevirtual #70                 // Method android/support/constraint/a/a/j.a:(Landroid/support/constraint/a/a/j;I)V
    1083: return
    1084: aload_1
    1085: getfield      #29                 // Field android/support/constraint/a/a/d.r:Landroid/support/constraint/a/a/c;
    1088: getfield      #52                 // Field android/support/constraint/a/a/c.c:Landroid/support/constraint/a/a/c;
    1091: ifnull        1111
    1094: aload_1
    1095: getfield      #35                 // Field android/support/constraint/a/a/d.t:Landroid/support/constraint/a/a/c;
    1098: getfield      #52                 // Field android/support/constraint/a/a/c.c:Landroid/support/constraint/a/a/c;
    1101: ifnonnull     1111
    1104: iload_0
    1105: ifeq          1075
    1108: goto          1062
    1111: aload_1
    1112: getfield      #29                 // Field android/support/constraint/a/a/d.r:Landroid/support/constraint/a/a/c;
    1115: getfield      #52                 // Field android/support/constraint/a/a/c.c:Landroid/support/constraint/a/a/c;
    1118: ifnonnull     1158
    1121: aload_1
    1122: getfield      #35                 // Field android/support/constraint/a/a/d.t:Landroid/support/constraint/a/a/c;
    1125: getfield      #52                 // Field android/support/constraint/a/a/c.c:Landroid/support/constraint/a/a/c;
    1128: ifnull        1158
    1131: iload_0
    1132: ifeq          1148
    1135: aload         4
    1137: aload         6
    1139: iconst_m1
    1140: aload_1
    1141: invokevirtual #94                 // Method android/support/constraint/a/a/d.i:()Landroid/support/constraint/a/a/k;
    1144: invokevirtual #63                 // Method android/support/constraint/a/a/j.a:(Landroid/support/constraint/a/a/j;ILandroid/support/constraint/a/a/k;)V
    1147: return
    1148: aload         4
    1150: aload         6
    1152: iload_2
    1153: ineg
    1154: invokevirtual #70                 // Method android/support/constraint/a/a/j.a:(Landroid/support/constraint/a/a/j;I)V
    1157: return
    1158: aload_1
    1159: getfield      #29                 // Field android/support/constraint/a/a/d.r:Landroid/support/constraint/a/a/c;
    1162: getfield      #52                 // Field android/support/constraint/a/a/c.c:Landroid/support/constraint/a/a/c;
    1165: ifnull        1284
    1168: aload_1
    1169: getfield      #35                 // Field android/support/constraint/a/a/d.t:Landroid/support/constraint/a/a/c;
    1172: getfield      #52                 // Field android/support/constraint/a/a/c.c:Landroid/support/constraint/a/a/c;
    1175: ifnull        1284
    1178: iload_0
    1179: ifeq          1200
    1182: aload_1
    1183: invokevirtual #94                 // Method android/support/constraint/a/a/d.i:()Landroid/support/constraint/a/a/k;
    1186: aload         4
    1188: invokevirtual #75                 // Method android/support/constraint/a/a/k.a:(Landroid/support/constraint/a/a/l;)V
    1191: aload_1
    1192: invokevirtual #60                 // Method android/support/constraint/a/a/d.h:()Landroid/support/constraint/a/a/k;
    1195: aload         6
    1197: invokevirtual #75                 // Method android/support/constraint/a/a/k.a:(Landroid/support/constraint/a/a/l;)V
    1200: aload_1
    1201: getfield      #89                 // Field android/support/constraint/a/a/d.E:F
    1204: fconst_0
    1205: fcmpl
    1206: ifne          1238
    1209: aload         4
    1211: iconst_3
    1212: invokevirtual #56                 // Method android/support/constraint/a/a/j.b:(I)V
    1215: aload         6
    1217: iconst_3
    1218: invokevirtual #56                 // Method android/support/constraint/a/a/j.b:(I)V
    1221: aload         4
    1223: aload         6
    1225: fconst_0
    1226: invokevirtual #80                 // Method android/support/constraint/a/a/j.b:(Landroid/support/constraint/a/a/j;F)V
    1229: aload         6
    1231: aload         4
    1233: fconst_0
    1234: invokevirtual #80                 // Method android/support/constraint/a/a/j.b:(Landroid/support/constraint/a/a/j;F)V
    1237: return
    1238: aload         4
    1240: iconst_2
    1241: invokevirtual #56                 // Method android/support/constraint/a/a/j.b:(I)V
    1244: aload         6
    1246: iconst_2
    1247: invokevirtual #56                 // Method android/support/constraint/a/a/j.b:(I)V
    1250: aload         4
    1252: aload         6
    1254: iload_2
    1255: ineg
    1256: i2f
    1257: invokevirtual #80                 // Method android/support/constraint/a/a/j.b:(Landroid/support/constraint/a/a/j;F)V
    1260: aload         6
    1262: aload         4
    1264: iload_2
    1265: i2f
    1266: invokevirtual #80                 // Method android/support/constraint/a/a/j.b:(Landroid/support/constraint/a/a/j;F)V
    1269: aload_1
    1270: iload_2
    1271: invokevirtual #107                // Method android/support/constraint/a/a/d.i:(I)V
    1274: aload_1
    1275: getfield      #102                // Field android/support/constraint/a/a/d.K:I
    1278: ifle          1284
    1281: goto          794
    1284: return

  static void a(android.support.constraint.a.a.e, android.support.constraint.a.e, android.support.constraint.a.a.d);
    Code:
       0: aload_0
       1: getfield      #111                // Field android/support/constraint/a/a/e.A:[Landroid/support/constraint/a/a/d$a;
       4: iconst_0
       5: aaload
       6: getstatic     #113                // Field android/support/constraint/a/a/d$a.b:Landroid/support/constraint/a/a/d$a;
       9: if_acmpeq     113
      12: aload_2
      13: getfield      #44                 // Field android/support/constraint/a/a/d.A:[Landroid/support/constraint/a/a/d$a;
      16: iconst_0
      17: aaload
      18: getstatic     #116                // Field android/support/constraint/a/a/d$a.d:Landroid/support/constraint/a/a/d$a;
      21: if_acmpne     113
      24: aload_2
      25: getfield      #21                 // Field android/support/constraint/a/a/d.q:Landroid/support/constraint/a/a/c;
      28: getfield      #118                // Field android/support/constraint/a/a/c.d:I
      31: istore_3
      32: aload_0
      33: invokevirtual #119                // Method android/support/constraint/a/a/e.o:()I
      36: aload_2
      37: getfield      #32                 // Field android/support/constraint/a/a/d.s:Landroid/support/constraint/a/a/c;
      40: getfield      #118                // Field android/support/constraint/a/a/c.d:I
      43: isub
      44: istore        4
      46: aload_2
      47: getfield      #21                 // Field android/support/constraint/a/a/d.q:Landroid/support/constraint/a/a/c;
      50: aload_1
      51: aload_2
      52: getfield      #21                 // Field android/support/constraint/a/a/d.q:Landroid/support/constraint/a/a/c;
      55: invokevirtual #124                // Method android/support/constraint/a/e.a:(Ljava/lang/Object;)Landroid/support/constraint/a/h;
      58: putfield      #128                // Field android/support/constraint/a/a/c.f:Landroid/support/constraint/a/h;
      61: aload_2
      62: getfield      #32                 // Field android/support/constraint/a/a/d.s:Landroid/support/constraint/a/a/c;
      65: aload_1
      66: aload_2
      67: getfield      #32                 // Field android/support/constraint/a/a/d.s:Landroid/support/constraint/a/a/c;
      70: invokevirtual #124                // Method android/support/constraint/a/e.a:(Ljava/lang/Object;)Landroid/support/constraint/a/h;
      73: putfield      #128                // Field android/support/constraint/a/a/c.f:Landroid/support/constraint/a/h;
      76: aload_1
      77: aload_2
      78: getfield      #21                 // Field android/support/constraint/a/a/d.q:Landroid/support/constraint/a/a/c;
      81: getfield      #128                // Field android/support/constraint/a/a/c.f:Landroid/support/constraint/a/h;
      84: iload_3
      85: invokevirtual #131                // Method android/support/constraint/a/e.a:(Landroid/support/constraint/a/h;I)V
      88: aload_1
      89: aload_2
      90: getfield      #32                 // Field android/support/constraint/a/a/d.s:Landroid/support/constraint/a/a/c;
      93: getfield      #128                // Field android/support/constraint/a/a/c.f:Landroid/support/constraint/a/h;
      96: iload         4
      98: invokevirtual #131                // Method android/support/constraint/a/e.a:(Landroid/support/constraint/a/h;I)V
     101: aload_2
     102: iconst_2
     103: putfield      #133                // Field android/support/constraint/a/a/d.a:I
     106: aload_2
     107: iload_3
     108: iload         4
     110: invokevirtual #136                // Method android/support/constraint/a/a/d.c:(II)V
     113: aload_0
     114: getfield      #111                // Field android/support/constraint/a/a/e.A:[Landroid/support/constraint/a/a/d$a;
     117: iconst_1
     118: aaload
     119: getstatic     #113                // Field android/support/constraint/a/a/d$a.b:Landroid/support/constraint/a/a/d$a;
     122: if_acmpeq     274
     125: aload_2
     126: getfield      #44                 // Field android/support/constraint/a/a/d.A:[Landroid/support/constraint/a/a/d$a;
     129: iconst_1
     130: aaload
     131: getstatic     #116                // Field android/support/constraint/a/a/d$a.d:Landroid/support/constraint/a/a/d$a;
     134: if_acmpne     274
     137: aload_2
     138: getfield      #29                 // Field android/support/constraint/a/a/d.r:Landroid/support/constraint/a/a/c;
     141: getfield      #118                // Field android/support/constraint/a/a/c.d:I
     144: istore_3
     145: aload_0
     146: invokevirtual #137                // Method android/support/constraint/a/a/e.q:()I
     149: aload_2
     150: getfield      #35                 // Field android/support/constraint/a/a/d.t:Landroid/support/constraint/a/a/c;
     153: getfield      #118                // Field android/support/constraint/a/a/c.d:I
     156: isub
     157: istore        4
     159: aload_2
     160: getfield      #29                 // Field android/support/constraint/a/a/d.r:Landroid/support/constraint/a/a/c;
     163: aload_1
     164: aload_2
     165: getfield      #29                 // Field android/support/constraint/a/a/d.r:Landroid/support/constraint/a/a/c;
     168: invokevirtual #124                // Method android/support/constraint/a/e.a:(Ljava/lang/Object;)Landroid/support/constraint/a/h;
     171: putfield      #128                // Field android/support/constraint/a/a/c.f:Landroid/support/constraint/a/h;
     174: aload_2
     175: getfield      #35                 // Field android/support/constraint/a/a/d.t:Landroid/support/constraint/a/a/c;
     178: aload_1
     179: aload_2
     180: getfield      #35                 // Field android/support/constraint/a/a/d.t:Landroid/support/constraint/a/a/c;
     183: invokevirtual #124                // Method android/support/constraint/a/e.a:(Ljava/lang/Object;)Landroid/support/constraint/a/h;
     186: putfield      #128                // Field android/support/constraint/a/a/c.f:Landroid/support/constraint/a/h;
     189: aload_1
     190: aload_2
     191: getfield      #29                 // Field android/support/constraint/a/a/d.r:Landroid/support/constraint/a/a/c;
     194: getfield      #128                // Field android/support/constraint/a/a/c.f:Landroid/support/constraint/a/h;
     197: iload_3
     198: invokevirtual #131                // Method android/support/constraint/a/e.a:(Landroid/support/constraint/a/h;I)V
     201: aload_1
     202: aload_2
     203: getfield      #35                 // Field android/support/constraint/a/a/d.t:Landroid/support/constraint/a/a/c;
     206: getfield      #128                // Field android/support/constraint/a/a/c.f:Landroid/support/constraint/a/h;
     209: iload         4
     211: invokevirtual #131                // Method android/support/constraint/a/e.a:(Landroid/support/constraint/a/h;I)V
     214: aload_2
     215: getfield      #102                // Field android/support/constraint/a/a/d.K:I
     218: ifgt          230
     221: aload_2
     222: invokevirtual #140                // Method android/support/constraint/a/a/d.k:()I
     225: bipush        8
     227: if_icmpne     262
     230: aload_2
     231: getfield      #99                 // Field android/support/constraint/a/a/d.u:Landroid/support/constraint/a/a/c;
     234: aload_1
     235: aload_2
     236: getfield      #99                 // Field android/support/constraint/a/a/d.u:Landroid/support/constraint/a/a/c;
     239: invokevirtual #124                // Method android/support/constraint/a/e.a:(Ljava/lang/Object;)Landroid/support/constraint/a/h;
     242: putfield      #128                // Field android/support/constraint/a/a/c.f:Landroid/support/constraint/a/h;
     245: aload_1
     246: aload_2
     247: getfield      #99                 // Field android/support/constraint/a/a/d.u:Landroid/support/constraint/a/a/c;
     250: getfield      #128                // Field android/support/constraint/a/a/c.f:Landroid/support/constraint/a/h;
     253: aload_2
     254: getfield      #102                // Field android/support/constraint/a/a/d.K:I
     257: iload_3
     258: iadd
     259: invokevirtual #131                // Method android/support/constraint/a/e.a:(Landroid/support/constraint/a/h;I)V
     262: aload_2
     263: iconst_2
     264: putfield      #142                // Field android/support/constraint/a/a/d.b:I
     267: aload_2
     268: iload_3
     269: iload         4
     271: invokevirtual #144                // Method android/support/constraint/a/a/d.d:(II)V
     274: return

  static boolean a(android.support.constraint.a.a.e, android.support.constraint.a.e, int, int, android.support.constraint.a.a.d);
    Code:
       0: aload_0
       1: getfield      #111                // Field android/support/constraint/a/a/e.A:[Landroid/support/constraint/a/a/d$a;
       4: iload_2
       5: aaload
       6: astore        20
       8: getstatic     #113                // Field android/support/constraint/a/a/d$a.b:Landroid/support/constraint/a/a/d$a;
      11: astore        20
      13: iload_2
      14: ifne          117
      17: aload_0
      18: invokevirtual #161                // Method android/support/constraint/a/a/e.K:()Z
      21: ifeq          117
      24: aload         4
      26: astore_0
      27: iconst_0
      28: istore        12
      30: aload_0
      31: astore        20
      33: iload         12
      35: ifne          121
      38: aload_0
      39: getfield      #165                // Field android/support/constraint/a/a/d.y:[Landroid/support/constraint/a/a/c;
      42: iload_3
      43: iconst_1
      44: iadd
      45: aaload
      46: getfield      #52                 // Field android/support/constraint/a/a/c.c:Landroid/support/constraint/a/a/c;
      49: astore        20
      51: aload         20
      53: ifnull        97
      56: aload         20
      58: getfield      #168                // Field android/support/constraint/a/a/c.a:Landroid/support/constraint/a/a/d;
      61: astore        21
      63: aload         21
      65: getfield      #165                // Field android/support/constraint/a/a/d.y:[Landroid/support/constraint/a/a/c;
      68: iload_3
      69: aaload
      70: getfield      #52                 // Field android/support/constraint/a/a/c.c:Landroid/support/constraint/a/a/c;
      73: ifnull        97
      76: aload         21
      78: astore        20
      80: aload         21
      82: getfield      #165                // Field android/support/constraint/a/a/d.y:[Landroid/support/constraint/a/a/c;
      85: iload_3
      86: aaload
      87: getfield      #52                 // Field android/support/constraint/a/a/c.c:Landroid/support/constraint/a/a/c;
      90: getfield      #168                // Field android/support/constraint/a/a/c.a:Landroid/support/constraint/a/a/d;
      93: aload_0
      94: if_acmpeq     100
      97: aconst_null
      98: astore        20
     100: aload         20
     102: ifnull        111
     105: aload         20
     107: astore_0
     108: goto          30
     111: iconst_1
     112: istore        12
     114: goto          30
     117: aload         4
     119: astore        20
     121: iload_2
     122: ifne          197
     125: aload         20
     127: getfield      #171                // Field android/support/constraint/a/a/d.S:I
     130: ifne          139
     133: iconst_1
     134: istore        12
     136: goto          142
     139: iconst_0
     140: istore        12
     142: aload         20
     144: getfield      #171                // Field android/support/constraint/a/a/d.S:I
     147: iconst_1
     148: if_icmpne     157
     151: iconst_1
     152: istore        13
     154: goto          160
     157: iconst_0
     158: istore        13
     160: iload         12
     162: istore        15
     164: iload         13
     166: istore        14
     168: aload         20
     170: getfield      #171                // Field android/support/constraint/a/a/d.S:I
     173: iconst_2
     174: if_icmpne     183
     177: iconst_1
     178: istore        16
     180: goto          252
     183: iconst_0
     184: istore        16
     186: iload         15
     188: istore        12
     190: iload         14
     192: istore        13
     194: goto          252
     197: aload         20
     199: getfield      #174                // Field android/support/constraint/a/a/d.T:I
     202: ifne          211
     205: iconst_1
     206: istore        12
     208: goto          214
     211: iconst_0
     212: istore        12
     214: aload         20
     216: getfield      #174                // Field android/support/constraint/a/a/d.T:I
     219: iconst_1
     220: if_icmpne     229
     223: iconst_1
     224: istore        13
     226: goto          232
     229: iconst_0
     230: istore        13
     232: iload         12
     234: istore        15
     236: iload         13
     238: istore        14
     240: aload         20
     242: getfield      #174                // Field android/support/constraint/a/a/d.T:I
     245: iconst_2
     246: if_icmpne     183
     249: goto          177
     252: aload         4
     254: astore        23
     256: aconst_null
     257: astore        26
     259: aload         26
     261: astore_0
     262: aload_0
     263: astore        20
     265: aload         20
     267: astore        21
     269: iconst_0
     270: istore        15
     272: iconst_0
     273: istore        18
     275: iconst_0
     276: istore        14
     278: fconst_0
     279: fstore        9
     281: fconst_0
     282: fstore        8
     284: fconst_0
     285: fstore        7
     287: aload_0
     288: astore        22
     290: aload         23
     292: astore_0
     293: iload         15
     295: ifne          745
     298: aload_0
     299: getfield      #178                // Field android/support/constraint/a/a/d.Y:[Landroid/support/constraint/a/a/d;
     302: iload_2
     303: aconst_null
     304: aastore
     305: aload         22
     307: astore        24
     309: aload         20
     311: astore        23
     313: iload         18
     315: istore        17
     317: fload         9
     319: fstore        5
     321: fload         8
     323: fstore        6
     325: aload_0
     326: invokevirtual #140                // Method android/support/constraint/a/a/d.k:()I
     329: bipush        8
     331: if_icmpeq     459
     334: aload         22
     336: ifnull        347
     339: aload         22
     341: getfield      #178                // Field android/support/constraint/a/a/d.Y:[Landroid/support/constraint/a/a/d;
     344: iload_2
     345: aload_0
     346: aastore
     347: aload         20
     349: astore        22
     351: aload         20
     353: ifnonnull     359
     356: aload_0
     357: astore        22
     359: iload         18
     361: iconst_1
     362: iadd
     363: istore        18
     365: iload_2
     366: ifne          386
     369: aload_0
     370: invokevirtual #67                 // Method android/support/constraint/a/a/d.o:()I
     373: istore        17
     375: fload         9
     377: iload         17
     379: i2f
     380: fadd
     381: fstore        6
     383: goto          395
     386: aload_0
     387: invokevirtual #96                 // Method android/support/constraint/a/a/d.q:()I
     390: istore        17
     392: goto          375
     395: fload         6
     397: fstore        5
     399: aload_0
     400: aload         22
     402: if_acmpeq     420
     405: fload         6
     407: aload_0
     408: getfield      #165                // Field android/support/constraint/a/a/d.y:[Landroid/support/constraint/a/a/c;
     411: iload_3
     412: aaload
     413: invokevirtual #180                // Method android/support/constraint/a/a/c.e:()I
     416: i2f
     417: fadd
     418: fstore        5
     420: fload         8
     422: aload_0
     423: getfield      #165                // Field android/support/constraint/a/a/d.y:[Landroid/support/constraint/a/a/c;
     426: iload_3
     427: aaload
     428: invokevirtual #180                // Method android/support/constraint/a/a/c.e:()I
     431: i2f
     432: fadd
     433: aload_0
     434: getfield      #165                // Field android/support/constraint/a/a/d.y:[Landroid/support/constraint/a/a/c;
     437: iload_3
     438: iconst_1
     439: iadd
     440: aaload
     441: invokevirtual #180                // Method android/support/constraint/a/a/c.e:()I
     444: i2f
     445: fadd
     446: fstore        6
     448: aload_0
     449: astore        24
     451: iload         18
     453: istore        17
     455: aload         22
     457: astore        23
     459: aload_0
     460: getfield      #165                // Field android/support/constraint/a/a/d.y:[Landroid/support/constraint/a/a/c;
     463: iload_3
     464: aaload
     465: astore        20
     467: aload_0
     468: getfield      #183                // Field android/support/constraint/a/a/d.X:[Landroid/support/constraint/a/a/d;
     471: iload_2
     472: aconst_null
     473: aastore
     474: aload         26
     476: astore        22
     478: iload         14
     480: istore        19
     482: fload         7
     484: fstore        10
     486: aload         21
     488: astore        25
     490: aload_0
     491: invokevirtual #140                // Method android/support/constraint/a/a/d.k:()I
     494: bipush        8
     496: if_icmpeq     630
     499: aload         26
     501: astore        22
     503: iload         14
     505: istore        19
     507: fload         7
     509: fstore        10
     511: aload         21
     513: astore        25
     515: aload_0
     516: getfield      #44                 // Field android/support/constraint/a/a/d.A:[Landroid/support/constraint/a/a/d$a;
     519: iload_2
     520: aaload
     521: getstatic     #82                 // Field android/support/constraint/a/a/d$a.c:Landroid/support/constraint/a/a/d$a;
     524: if_acmpne     630
     527: iload         14
     529: iconst_1
     530: iadd
     531: istore        19
     533: iload_2
     534: ifne          562
     537: aload_0
     538: getfield      #147                // Field android/support/constraint/a/a/d.e:I
     541: ifeq          546
     544: iconst_0
     545: ireturn
     546: aload_0
     547: getfield      #148                // Field android/support/constraint/a/a/d.g:I
     550: ifne          560
     553: aload_0
     554: getfield      #150                // Field android/support/constraint/a/a/d.h:I
     557: ifeq          588
     560: iconst_0
     561: ireturn
     562: aload_0
     563: getfield      #152                // Field android/support/constraint/a/a/d.f:I
     566: ifeq          571
     569: iconst_0
     570: ireturn
     571: aload_0
     572: getfield      #155                // Field android/support/constraint/a/a/d.j:I
     575: ifne          628
     578: aload_0
     579: getfield      #157                // Field android/support/constraint/a/a/d.k:I
     582: ifeq          588
     585: goto          628
     588: fload         7
     590: aload_0
     591: getfield      #187                // Field android/support/constraint/a/a/d.W:[F
     594: iload_2
     595: faload
     596: fadd
     597: fstore        10
     599: aload         21
     601: ifnonnull     610
     604: aload_0
     605: astore        21
     607: goto          618
     610: aload         26
     612: getfield      #183                // Field android/support/constraint/a/a/d.X:[Landroid/support/constraint/a/a/d;
     615: iload_2
     616: aload_0
     617: aastore
     618: aload_0
     619: astore        22
     621: aload         21
     623: astore        25
     625: goto          630
     628: iconst_0
     629: ireturn
     630: aload_0
     631: getfield      #165                // Field android/support/constraint/a/a/d.y:[Landroid/support/constraint/a/a/c;
     634: iload_3
     635: iconst_1
     636: iadd
     637: aaload
     638: getfield      #52                 // Field android/support/constraint/a/a/c.c:Landroid/support/constraint/a/a/c;
     641: astore        20
     643: aload         20
     645: ifnull        689
     648: aload         20
     650: getfield      #168                // Field android/support/constraint/a/a/c.a:Landroid/support/constraint/a/a/d;
     653: astore        21
     655: aload         21
     657: getfield      #165                // Field android/support/constraint/a/a/d.y:[Landroid/support/constraint/a/a/c;
     660: iload_3
     661: aaload
     662: getfield      #52                 // Field android/support/constraint/a/a/c.c:Landroid/support/constraint/a/a/c;
     665: ifnull        689
     668: aload         21
     670: astore        20
     672: aload         21
     674: getfield      #165                // Field android/support/constraint/a/a/d.y:[Landroid/support/constraint/a/a/c;
     677: iload_3
     678: aaload
     679: getfield      #52                 // Field android/support/constraint/a/a/c.c:Landroid/support/constraint/a/a/c;
     682: getfield      #168                // Field android/support/constraint/a/a/c.a:Landroid/support/constraint/a/a/d;
     685: aload_0
     686: if_acmpeq     692
     689: aconst_null
     690: astore        20
     692: aload         20
     694: ifnull        703
     697: aload         20
     699: astore_0
     700: goto          706
     703: iconst_1
     704: istore        15
     706: aload         22
     708: astore        26
     710: aload         24
     712: astore        22
     714: aload         23
     716: astore        20
     718: iload         17
     720: istore        18
     722: iload         19
     724: istore        14
     726: fload         5
     728: fstore        9
     730: fload         6
     732: fstore        8
     734: fload         10
     736: fstore        7
     738: aload         25
     740: astore        21
     742: goto          293
     745: aload         4
     747: getfield      #165                // Field android/support/constraint/a/a/d.y:[Landroid/support/constraint/a/a/c;
     750: iload_3
     751: aaload
     752: invokevirtual #26                 // Method android/support/constraint/a/a/c.a:()Landroid/support/constraint/a/a/j;
     755: astore        21
     757: aload_0
     758: getfield      #165                // Field android/support/constraint/a/a/d.y:[Landroid/support/constraint/a/a/c;
     761: astore        23
     763: iload_3
     764: iconst_1
     765: iadd
     766: istore        15
     768: aload         23
     770: iload         15
     772: aaload
     773: invokevirtual #26                 // Method android/support/constraint/a/a/c.a:()Landroid/support/constraint/a/a/j;
     776: astore        23
     778: aload         21
     780: getfield      #190                // Field android/support/constraint/a/a/j.c:Landroid/support/constraint/a/a/j;
     783: ifnull        2000
     786: aload         23
     788: getfield      #190                // Field android/support/constraint/a/a/j.c:Landroid/support/constraint/a/a/j;
     791: ifnonnull     797
     794: goto          2000
     797: aload         21
     799: getfield      #190                // Field android/support/constraint/a/a/j.c:Landroid/support/constraint/a/a/j;
     802: getfield      #192                // Field android/support/constraint/a/a/j.i:I
     805: iconst_1
     806: if_icmpeq     823
     809: aload         23
     811: getfield      #190                // Field android/support/constraint/a/a/j.c:Landroid/support/constraint/a/a/j;
     814: getfield      #192                // Field android/support/constraint/a/a/j.i:I
     817: iconst_1
     818: if_icmpeq     823
     821: iconst_0
     822: ireturn
     823: iload         14
     825: ifle          837
     828: iload         14
     830: iload         18
     832: if_icmpeq     837
     835: iconst_0
     836: ireturn
     837: iload         16
     839: ifne          861
     842: iload         12
     844: ifne          861
     847: iload         13
     849: ifeq          855
     852: goto          861
     855: fconst_0
     856: fstore        5
     858: goto          911
     861: aload         20
     863: ifnull        882
     866: aload         20
     868: getfield      #165                // Field android/support/constraint/a/a/d.y:[Landroid/support/constraint/a/a/c;
     871: iload_3
     872: aaload
     873: invokevirtual #180                // Method android/support/constraint/a/a/c.e:()I
     876: i2f
     877: fstore        6
     879: goto          885
     882: fconst_0
     883: fstore        6
     885: fload         6
     887: fstore        5
     889: aload         22
     891: ifnull        911
     894: fload         6
     896: aload         22
     898: getfield      #165                // Field android/support/constraint/a/a/d.y:[Landroid/support/constraint/a/a/c;
     901: iload         15
     903: aaload
     904: invokevirtual #180                // Method android/support/constraint/a/a/c.e:()I
     907: i2f
     908: fadd
     909: fstore        5
     911: aload         21
     913: getfield      #190                // Field android/support/constraint/a/a/j.c:Landroid/support/constraint/a/a/j;
     916: getfield      #194                // Field android/support/constraint/a/a/j.f:F
     919: fstore        10
     921: aload         23
     923: getfield      #190                // Field android/support/constraint/a/a/j.c:Landroid/support/constraint/a/a/j;
     926: getfield      #194                // Field android/support/constraint/a/a/j.f:F
     929: fstore        6
     931: fload         10
     933: fload         6
     935: fcmpg
     936: ifge          956
     939: fload         6
     941: fload         10
     943: fsub
     944: fstore        6
     946: fload         6
     948: fload         9
     950: fsub
     951: fstore        11
     953: goto          966
     956: fload         10
     958: fload         6
     960: fsub
     961: fstore        6
     963: goto          946
     966: iload         14
     968: ifle          1368
     971: iload         14
     973: iload         18
     975: if_icmpne     1368
     978: aload_0
     979: invokevirtual #197                // Method android/support/constraint/a/a/d.j:()Landroid/support/constraint/a/a/d;
     982: ifnull        1002
     985: aload_0
     986: invokevirtual #197                // Method android/support/constraint/a/a/d.j:()Landroid/support/constraint/a/a/d;
     989: getfield      #44                 // Field android/support/constraint/a/a/d.A:[Landroid/support/constraint/a/a/d$a;
     992: iload_2
     993: aaload
     994: getstatic     #113                // Field android/support/constraint/a/a/d$a.b:Landroid/support/constraint/a/a/d$a;
     997: if_acmpne     1002
    1000: iconst_0
    1001: ireturn
    1002: fload         11
    1004: fload         9
    1006: fadd
    1007: fload         8
    1009: fsub
    1010: fstore        9
    1012: fload         9
    1014: fstore        6
    1016: iload         12
    1018: ifeq          1031
    1021: fload         9
    1023: fload         8
    1025: fload         5
    1027: fsub
    1028: fsub
    1029: fstore        6
    1031: aload         21
    1033: astore_0
    1034: fload         10
    1036: fstore        5
    1038: aload         20
    1040: astore        4
    1042: iload         12
    1044: ifeq          1112
    1047: fload         10
    1049: aload         20
    1051: getfield      #165                // Field android/support/constraint/a/a/d.y:[Landroid/support/constraint/a/a/c;
    1054: iload         15
    1056: aaload
    1057: invokevirtual #180                // Method android/support/constraint/a/a/c.e:()I
    1060: i2f
    1061: fadd
    1062: fstore        8
    1064: aload         20
    1066: getfield      #178                // Field android/support/constraint/a/a/d.Y:[Landroid/support/constraint/a/a/d;
    1069: iload_2
    1070: aaload
    1071: astore        23
    1073: aload         21
    1075: astore_0
    1076: fload         8
    1078: fstore        5
    1080: aload         20
    1082: astore        4
    1084: aload         23
    1086: ifnull        1112
    1089: fload         8
    1091: aload         23
    1093: getfield      #165                // Field android/support/constraint/a/a/d.y:[Landroid/support/constraint/a/a/c;
    1096: iload_3
    1097: aaload
    1098: invokevirtual #180                // Method android/support/constraint/a/a/c.e:()I
    1101: i2f
    1102: fadd
    1103: fstore        5
    1105: aload         20
    1107: astore        4
    1109: aload         21
    1111: astore_0
    1112: aload         4
    1114: ifnull        1366
    1117: getstatic     #200                // Field android/support/constraint/a/e.g:Landroid/support/constraint/a/f;
    1120: ifnull        1177
    1123: getstatic     #200                // Field android/support/constraint/a/e.g:Landroid/support/constraint/a/f;
    1126: astore        20
    1128: aload         20
    1130: aload         20
    1132: getfield      #206                // Field android/support/constraint/a/f.B:J
    1135: lconst_1
    1136: lsub
    1137: putfield      #206                // Field android/support/constraint/a/f.B:J
    1140: getstatic     #200                // Field android/support/constraint/a/e.g:Landroid/support/constraint/a/f;
    1143: astore        20
    1145: aload         20
    1147: aload         20
    1149: getfield      #208                // Field android/support/constraint/a/f.s:J
    1152: lconst_1
    1153: ladd
    1154: putfield      #208                // Field android/support/constraint/a/f.s:J
    1157: getstatic     #200                // Field android/support/constraint/a/e.g:Landroid/support/constraint/a/f;
    1160: astore        20
    1162: aload         20
    1164: aload         20
    1166: getfield      #210                // Field android/support/constraint/a/f.y:J
    1169: lconst_1
    1170: ladd
    1171: putfield      #210                // Field android/support/constraint/a/f.y:J
    1174: goto          1177
    1177: aload         4
    1179: getfield      #178                // Field android/support/constraint/a/a/d.Y:[Landroid/support/constraint/a/a/d;
    1182: iload_2
    1183: aaload
    1184: astore        20
    1186: aload         20
    1188: ifnonnull     1204
    1191: aload         4
    1193: aload         22
    1195: if_acmpne     1201
    1198: goto          1204
    1201: goto          1359
    1204: fload         6
    1206: iload         14
    1208: i2f
    1209: fdiv
    1210: fstore        8
    1212: fload         7
    1214: fconst_0
    1215: fcmpl
    1216: ifle          1234
    1219: aload         4
    1221: getfield      #187                // Field android/support/constraint/a/a/d.W:[F
    1224: iload_2
    1225: faload
    1226: fload         6
    1228: fmul
    1229: fload         7
    1231: fdiv
    1232: fstore        8
    1234: fload         5
    1236: aload         4
    1238: getfield      #165                // Field android/support/constraint/a/a/d.y:[Landroid/support/constraint/a/a/c;
    1241: iload_3
    1242: aaload
    1243: invokevirtual #180                // Method android/support/constraint/a/a/c.e:()I
    1246: i2f
    1247: fadd
    1248: fstore        5
    1250: aload         4
    1252: getfield      #165                // Field android/support/constraint/a/a/d.y:[Landroid/support/constraint/a/a/c;
    1255: iload_3
    1256: aaload
    1257: invokevirtual #26                 // Method android/support/constraint/a/a/c.a:()Landroid/support/constraint/a/a/j;
    1260: astore        23
    1262: aload_0
    1263: astore        21
    1265: aload         23
    1267: aload         21
    1269: getfield      #212                // Field android/support/constraint/a/a/j.e:Landroid/support/constraint/a/a/j;
    1272: fload         5
    1274: invokevirtual #214                // Method android/support/constraint/a/a/j.a:(Landroid/support/constraint/a/a/j;F)V
    1277: aload         4
    1279: getfield      #165                // Field android/support/constraint/a/a/d.y:[Landroid/support/constraint/a/a/c;
    1282: iload         15
    1284: aaload
    1285: invokevirtual #26                 // Method android/support/constraint/a/a/c.a:()Landroid/support/constraint/a/a/j;
    1288: astore        23
    1290: aload         21
    1292: getfield      #212                // Field android/support/constraint/a/a/j.e:Landroid/support/constraint/a/a/j;
    1295: astore        21
    1297: fload         5
    1299: fload         8
    1301: fadd
    1302: fstore        5
    1304: aload         23
    1306: aload         21
    1308: fload         5
    1310: invokevirtual #214                // Method android/support/constraint/a/a/j.a:(Landroid/support/constraint/a/a/j;F)V
    1313: aload         4
    1315: getfield      #165                // Field android/support/constraint/a/a/d.y:[Landroid/support/constraint/a/a/c;
    1318: iload_3
    1319: aaload
    1320: invokevirtual #26                 // Method android/support/constraint/a/a/c.a:()Landroid/support/constraint/a/a/j;
    1323: aload_1
    1324: invokevirtual #217                // Method android/support/constraint/a/a/j.a:(Landroid/support/constraint/a/e;)V
    1327: aload         4
    1329: getfield      #165                // Field android/support/constraint/a/a/d.y:[Landroid/support/constraint/a/a/c;
    1332: iload         15
    1334: aaload
    1335: invokevirtual #26                 // Method android/support/constraint/a/a/c.a:()Landroid/support/constraint/a/a/j;
    1338: aload_1
    1339: invokevirtual #217                // Method android/support/constraint/a/a/j.a:(Landroid/support/constraint/a/e;)V
    1342: fload         5
    1344: aload         4
    1346: getfield      #165                // Field android/support/constraint/a/a/d.y:[Landroid/support/constraint/a/a/c;
    1349: iload         15
    1351: aaload
    1352: invokevirtual #180                // Method android/support/constraint/a/a/c.e:()I
    1355: i2f
    1356: fadd
    1357: fstore        5
    1359: aload         20
    1361: astore        4
    1363: goto          1112
    1366: iconst_1
    1367: ireturn
    1368: fload         11
    1370: fload         9
    1372: fcmpg
    1373: ifge          1378
    1376: iconst_0
    1377: ireturn
    1378: iload         16
    1380: ifeq          1634
    1383: fload         10
    1385: fload         11
    1387: fload         5
    1389: fsub
    1390: aload         4
    1392: invokevirtual #220                // Method android/support/constraint/a/a/d.y:()F
    1395: fmul
    1396: fadd
    1397: fstore        5
    1399: aload         20
    1401: ifnull        1632
    1404: getstatic     #200                // Field android/support/constraint/a/e.g:Landroid/support/constraint/a/f;
    1407: ifnull        1452
    1410: getstatic     #200                // Field android/support/constraint/a/e.g:Landroid/support/constraint/a/f;
    1413: astore_0
    1414: aload_0
    1415: aload_0
    1416: getfield      #206                // Field android/support/constraint/a/f.B:J
    1419: lconst_1
    1420: lsub
    1421: putfield      #206                // Field android/support/constraint/a/f.B:J
    1424: getstatic     #200                // Field android/support/constraint/a/e.g:Landroid/support/constraint/a/f;
    1427: astore_0
    1428: aload_0
    1429: aload_0
    1430: getfield      #208                // Field android/support/constraint/a/f.s:J
    1433: lconst_1
    1434: ladd
    1435: putfield      #208                // Field android/support/constraint/a/f.s:J
    1438: getstatic     #200                // Field android/support/constraint/a/e.g:Landroid/support/constraint/a/f;
    1441: astore_0
    1442: aload_0
    1443: aload_0
    1444: getfield      #210                // Field android/support/constraint/a/f.y:J
    1447: lconst_1
    1448: ladd
    1449: putfield      #210                // Field android/support/constraint/a/f.y:J
    1452: aload         20
    1454: getfield      #178                // Field android/support/constraint/a/a/d.Y:[Landroid/support/constraint/a/a/d;
    1457: iload_2
    1458: aaload
    1459: astore_0
    1460: aload_0
    1461: ifnonnull     1475
    1464: fload         5
    1466: fstore        6
    1468: aload         20
    1470: aload         22
    1472: if_acmpne     1622
    1475: iload_2
    1476: ifne          1494
    1479: aload         20
    1481: invokevirtual #67                 // Method android/support/constraint/a/a/d.o:()I
    1484: istore        12
    1486: iload         12
    1488: i2f
    1489: fstore        6
    1491: goto          1504
    1494: aload         20
    1496: invokevirtual #96                 // Method android/support/constraint/a/a/d.q:()I
    1499: istore        12
    1501: goto          1486
    1504: fload         5
    1506: aload         20
    1508: getfield      #165                // Field android/support/constraint/a/a/d.y:[Landroid/support/constraint/a/a/c;
    1511: iload_3
    1512: aaload
    1513: invokevirtual #180                // Method android/support/constraint/a/a/c.e:()I
    1516: i2f
    1517: fadd
    1518: fstore        5
    1520: aload         20
    1522: getfield      #165                // Field android/support/constraint/a/a/d.y:[Landroid/support/constraint/a/a/c;
    1525: iload_3
    1526: aaload
    1527: invokevirtual #26                 // Method android/support/constraint/a/a/c.a:()Landroid/support/constraint/a/a/j;
    1530: aload         21
    1532: getfield      #212                // Field android/support/constraint/a/a/j.e:Landroid/support/constraint/a/a/j;
    1535: fload         5
    1537: invokevirtual #214                // Method android/support/constraint/a/a/j.a:(Landroid/support/constraint/a/a/j;F)V
    1540: aload         20
    1542: getfield      #165                // Field android/support/constraint/a/a/d.y:[Landroid/support/constraint/a/a/c;
    1545: iload         15
    1547: aaload
    1548: invokevirtual #26                 // Method android/support/constraint/a/a/c.a:()Landroid/support/constraint/a/a/j;
    1551: astore        4
    1553: aload         21
    1555: getfield      #212                // Field android/support/constraint/a/a/j.e:Landroid/support/constraint/a/a/j;
    1558: astore        23
    1560: fload         5
    1562: fload         6
    1564: fadd
    1565: fstore        5
    1567: aload         4
    1569: aload         23
    1571: fload         5
    1573: invokevirtual #214                // Method android/support/constraint/a/a/j.a:(Landroid/support/constraint/a/a/j;F)V
    1576: aload         20
    1578: getfield      #165                // Field android/support/constraint/a/a/d.y:[Landroid/support/constraint/a/a/c;
    1581: iload_3
    1582: aaload
    1583: invokevirtual #26                 // Method android/support/constraint/a/a/c.a:()Landroid/support/constraint/a/a/j;
    1586: aload_1
    1587: invokevirtual #217                // Method android/support/constraint/a/a/j.a:(Landroid/support/constraint/a/e;)V
    1590: aload         20
    1592: getfield      #165                // Field android/support/constraint/a/a/d.y:[Landroid/support/constraint/a/a/c;
    1595: iload         15
    1597: aaload
    1598: invokevirtual #26                 // Method android/support/constraint/a/a/c.a:()Landroid/support/constraint/a/a/j;
    1601: aload_1
    1602: invokevirtual #217                // Method android/support/constraint/a/a/j.a:(Landroid/support/constraint/a/e;)V
    1605: fload         5
    1607: aload         20
    1609: getfield      #165                // Field android/support/constraint/a/a/d.y:[Landroid/support/constraint/a/a/c;
    1612: iload         15
    1614: aaload
    1615: invokevirtual #180                // Method android/support/constraint/a/a/c.e:()I
    1618: i2f
    1619: fadd
    1620: fstore        6
    1622: aload_0
    1623: astore        20
    1625: fload         6
    1627: fstore        5
    1629: goto          1399
    1632: iconst_1
    1633: ireturn
    1634: iload         12
    1636: ifne          1644
    1639: iload         13
    1641: ifeq          1632
    1644: iload         12
    1646: ifeq          1659
    1649: fload         11
    1651: fload         5
    1653: fsub
    1654: fstore        6
    1656: goto          1671
    1659: fload         11
    1661: fstore        6
    1663: iload         13
    1665: ifeq          1671
    1668: goto          1649
    1671: fload         6
    1673: iload         18
    1675: iconst_1
    1676: iadd
    1677: i2f
    1678: fdiv
    1679: fstore        7
    1681: iload         13
    1683: ifeq          1715
    1686: iload         18
    1688: iconst_1
    1689: if_icmple     1709
    1692: iload         18
    1694: iconst_1
    1695: isub
    1696: i2f
    1697: fstore        5
    1699: fload         6
    1701: fload         5
    1703: fdiv
    1704: fstore        7
    1706: goto          1715
    1709: fconst_2
    1710: fstore        5
    1712: goto          1699
    1715: fload         10
    1717: fload         7
    1719: fadd
    1720: fstore        6
    1722: fload         6
    1724: fstore        5
    1726: iload         13
    1728: ifeq          1757
    1731: fload         6
    1733: fstore        5
    1735: iload         18
    1737: iconst_1
    1738: if_icmple     1757
    1741: aload         20
    1743: getfield      #165                // Field android/support/constraint/a/a/d.y:[Landroid/support/constraint/a/a/c;
    1746: iload_3
    1747: aaload
    1748: invokevirtual #180                // Method android/support/constraint/a/a/c.e:()I
    1751: i2f
    1752: fload         10
    1754: fadd
    1755: fstore        5
    1757: fload         5
    1759: fstore        6
    1761: aload         20
    1763: astore_0
    1764: iload         12
    1766: ifeq          1800
    1769: fload         5
    1771: fstore        6
    1773: aload         20
    1775: astore_0
    1776: aload         20
    1778: ifnull        1800
    1781: fload         5
    1783: aload         20
    1785: getfield      #165                // Field android/support/constraint/a/a/d.y:[Landroid/support/constraint/a/a/c;
    1788: iload_3
    1789: aaload
    1790: invokevirtual #180                // Method android/support/constraint/a/a/c.e:()I
    1793: i2f
    1794: fadd
    1795: fstore        6
    1797: aload         20
    1799: astore_0
    1800: aload_0
    1801: ifnull        1632
    1804: getstatic     #200                // Field android/support/constraint/a/e.g:Landroid/support/constraint/a/f;
    1807: ifnull        1861
    1810: getstatic     #200                // Field android/support/constraint/a/e.g:Landroid/support/constraint/a/f;
    1813: astore        4
    1815: aload         4
    1817: aload         4
    1819: getfield      #206                // Field android/support/constraint/a/f.B:J
    1822: lconst_1
    1823: lsub
    1824: putfield      #206                // Field android/support/constraint/a/f.B:J
    1827: getstatic     #200                // Field android/support/constraint/a/e.g:Landroid/support/constraint/a/f;
    1830: astore        4
    1832: aload         4
    1834: aload         4
    1836: getfield      #208                // Field android/support/constraint/a/f.s:J
    1839: lconst_1
    1840: ladd
    1841: putfield      #208                // Field android/support/constraint/a/f.s:J
    1844: getstatic     #200                // Field android/support/constraint/a/e.g:Landroid/support/constraint/a/f;
    1847: astore        4
    1849: aload         4
    1851: aload         4
    1853: getfield      #210                // Field android/support/constraint/a/f.y:J
    1856: lconst_1
    1857: ladd
    1858: putfield      #210                // Field android/support/constraint/a/f.y:J
    1861: aload_0
    1862: getfield      #178                // Field android/support/constraint/a/a/d.Y:[Landroid/support/constraint/a/a/d;
    1865: iload_2
    1866: aaload
    1867: astore        4
    1869: aload         4
    1871: ifnonnull     1884
    1874: fload         6
    1876: fstore        5
    1878: aload_0
    1879: aload         22
    1881: if_acmpne     1990
    1884: iload_2
    1885: ifne          1902
    1888: aload_0
    1889: invokevirtual #67                 // Method android/support/constraint/a/a/d.o:()I
    1892: istore        12
    1894: iload         12
    1896: i2f
    1897: fstore        5
    1899: goto          1911
    1902: aload_0
    1903: invokevirtual #96                 // Method android/support/constraint/a/a/d.q:()I
    1906: istore        12
    1908: goto          1894
    1911: aload_0
    1912: getfield      #165                // Field android/support/constraint/a/a/d.y:[Landroid/support/constraint/a/a/c;
    1915: iload_3
    1916: aaload
    1917: invokevirtual #26                 // Method android/support/constraint/a/a/c.a:()Landroid/support/constraint/a/a/j;
    1920: aload         21
    1922: getfield      #212                // Field android/support/constraint/a/a/j.e:Landroid/support/constraint/a/a/j;
    1925: fload         6
    1927: invokevirtual #214                // Method android/support/constraint/a/a/j.a:(Landroid/support/constraint/a/a/j;F)V
    1930: aload_0
    1931: getfield      #165                // Field android/support/constraint/a/a/d.y:[Landroid/support/constraint/a/a/c;
    1934: iload         15
    1936: aaload
    1937: invokevirtual #26                 // Method android/support/constraint/a/a/c.a:()Landroid/support/constraint/a/a/j;
    1940: aload         21
    1942: getfield      #212                // Field android/support/constraint/a/a/j.e:Landroid/support/constraint/a/a/j;
    1945: fload         6
    1947: fload         5
    1949: fadd
    1950: invokevirtual #214                // Method android/support/constraint/a/a/j.a:(Landroid/support/constraint/a/a/j;F)V
    1953: aload_0
    1954: getfield      #165                // Field android/support/constraint/a/a/d.y:[Landroid/support/constraint/a/a/c;
    1957: iload_3
    1958: aaload
    1959: invokevirtual #26                 // Method android/support/constraint/a/a/c.a:()Landroid/support/constraint/a/a/j;
    1962: aload_1
    1963: invokevirtual #217                // Method android/support/constraint/a/a/j.a:(Landroid/support/constraint/a/e;)V
    1966: aload_0
    1967: getfield      #165                // Field android/support/constraint/a/a/d.y:[Landroid/support/constraint/a/a/c;
    1970: iload         15
    1972: aaload
    1973: invokevirtual #26                 // Method android/support/constraint/a/a/c.a:()Landroid/support/constraint/a/a/j;
    1976: aload_1
    1977: invokevirtual #217                // Method android/support/constraint/a/a/j.a:(Landroid/support/constraint/a/e;)V
    1980: fload         6
    1982: fload         5
    1984: fload         7
    1986: fadd
    1987: fadd
    1988: fstore        5
    1990: aload         4
    1992: astore_0
    1993: fload         5
    1995: fstore        6
    1997: goto          1800
    2000: iconst_0
    2001: ireturn
}
