public class android.support.constraint.a.a.j extends android.support.constraint.a.a.l {
  android.support.constraint.a.a.c a;

  float b;

  android.support.constraint.a.a.j c;

  float d;

  android.support.constraint.a.a.j e;

  float f;

  int g;

  public android.support.constraint.a.a.j(android.support.constraint.a.a.c);
    Code:
       0: aload_0
       1: invokespecial #27                 // Method android/support/constraint/a/a/l."<init>":()V
       4: aload_0
       5: iconst_0
       6: putfield      #29                 // Field g:I
       9: aload_0
      10: aconst_null
      11: putfield      #31                 // Field l:Landroid/support/constraint/a/a/k;
      14: aload_0
      15: iconst_1
      16: putfield      #33                 // Field m:I
      19: aload_0
      20: aconst_null
      21: putfield      #35                 // Field n:Landroid/support/constraint/a/a/k;
      24: aload_0
      25: iconst_1
      26: putfield      #37                 // Field o:I
      29: aload_0
      30: aload_1
      31: putfield      #39                 // Field a:Landroid/support/constraint/a/a/c;
      34: return

  java.lang.String a(int);
    Code:
       0: iload_1
       1: iconst_1
       2: if_icmpne     8
       5: ldc           #43                 // String DIRECT
       7: areturn
       8: iload_1
       9: iconst_2
      10: if_icmpne     16
      13: ldc           #45                 // String CENTER
      15: areturn
      16: iload_1
      17: iconst_3
      18: if_icmpne     24
      21: ldc           #47                 // String MATCH
      23: areturn
      24: iload_1
      25: iconst_4
      26: if_icmpne     32
      29: ldc           #49                 // String CHAIN
      31: areturn
      32: iload_1
      33: iconst_5
      34: if_icmpne     40
      37: ldc           #51                 // String BARRIER
      39: areturn
      40: ldc           #53                 // String UNCONNECTED
      42: areturn

  public void a();
    Code:
       0: aload_0
       1: getfield      #56                 // Field i:I
       4: iconst_1
       5: if_icmpne     9
       8: return
       9: aload_0
      10: getfield      #29                 // Field g:I
      13: iconst_4
      14: if_icmpne     18
      17: return
      18: aload_0
      19: getfield      #31                 // Field l:Landroid/support/constraint/a/a/k;
      22: ifnull        54
      25: aload_0
      26: getfield      #31                 // Field l:Landroid/support/constraint/a/a/k;
      29: getfield      #59                 // Field android/support/constraint/a/a/k.i:I
      32: iconst_1
      33: if_icmpeq     37
      36: return
      37: aload_0
      38: aload_0
      39: getfield      #33                 // Field m:I
      42: i2f
      43: aload_0
      44: getfield      #31                 // Field l:Landroid/support/constraint/a/a/k;
      47: getfield      #61                 // Field android/support/constraint/a/a/k.a:F
      50: fmul
      51: putfield      #63                 // Field d:F
      54: aload_0
      55: getfield      #35                 // Field n:Landroid/support/constraint/a/a/k;
      58: ifnull        90
      61: aload_0
      62: getfield      #35                 // Field n:Landroid/support/constraint/a/a/k;
      65: getfield      #59                 // Field android/support/constraint/a/a/k.i:I
      68: iconst_1
      69: if_icmpeq     73
      72: return
      73: aload_0
      74: aload_0
      75: getfield      #37                 // Field o:I
      78: i2f
      79: aload_0
      80: getfield      #35                 // Field n:Landroid/support/constraint/a/a/k;
      83: getfield      #61                 // Field android/support/constraint/a/a/k.a:F
      86: fmul
      87: putfield      #65                 // Field k:F
      90: aload_0
      91: getfield      #29                 // Field g:I
      94: iconst_1
      95: if_icmpne     173
      98: aload_0
      99: getfield      #67                 // Field c:Landroid/support/constraint/a/a/j;
     102: ifnull        116
     105: aload_0
     106: getfield      #67                 // Field c:Landroid/support/constraint/a/a/j;
     109: getfield      #56                 // Field i:I
     112: iconst_1
     113: if_icmpne     173
     116: aload_0
     117: getfield      #67                 // Field c:Landroid/support/constraint/a/a/j;
     120: ifnonnull     141
     123: aload_0
     124: aload_0
     125: putfield      #69                 // Field e:Landroid/support/constraint/a/a/j;
     128: aload_0
     129: getfield      #63                 // Field d:F
     132: fstore_1
     133: aload_0
     134: fload_1
     135: putfield      #71                 // Field f:F
     138: goto          168
     141: aload_0
     142: aload_0
     143: getfield      #67                 // Field c:Landroid/support/constraint/a/a/j;
     146: getfield      #69                 // Field e:Landroid/support/constraint/a/a/j;
     149: putfield      #69                 // Field e:Landroid/support/constraint/a/a/j;
     152: aload_0
     153: getfield      #67                 // Field c:Landroid/support/constraint/a/a/j;
     156: getfield      #71                 // Field f:F
     159: aload_0
     160: getfield      #63                 // Field d:F
     163: fadd
     164: fstore_1
     165: goto          133
     168: aload_0
     169: invokevirtual #73                 // Method f:()V
     172: return
     173: aload_0
     174: getfield      #29                 // Field g:I
     177: iconst_2
     178: if_icmpne     587
     181: aload_0
     182: getfield      #67                 // Field c:Landroid/support/constraint/a/a/j;
     185: ifnull        587
     188: aload_0
     189: getfield      #67                 // Field c:Landroid/support/constraint/a/a/j;
     192: getfield      #56                 // Field i:I
     195: iconst_1
     196: if_icmpne     587
     199: aload_0
     200: getfield      #75                 // Field j:Landroid/support/constraint/a/a/j;
     203: ifnull        587
     206: aload_0
     207: getfield      #75                 // Field j:Landroid/support/constraint/a/a/j;
     210: getfield      #67                 // Field c:Landroid/support/constraint/a/a/j;
     213: ifnull        587
     216: aload_0
     217: getfield      #75                 // Field j:Landroid/support/constraint/a/a/j;
     220: getfield      #67                 // Field c:Landroid/support/constraint/a/a/j;
     223: getfield      #56                 // Field i:I
     226: iconst_1
     227: if_icmpne     587
     230: invokestatic  #80                 // Method android/support/constraint/a/e.a:()Landroid/support/constraint/a/f;
     233: ifnull        253
     236: invokestatic  #80                 // Method android/support/constraint/a/e.a:()Landroid/support/constraint/a/f;
     239: astore        7
     241: aload         7
     243: aload         7
     245: getfield      #86                 // Field android/support/constraint/a/f.w:J
     248: lconst_1
     249: ladd
     250: putfield      #86                 // Field android/support/constraint/a/f.w:J
     253: aload_0
     254: aload_0
     255: getfield      #67                 // Field c:Landroid/support/constraint/a/a/j;
     258: getfield      #69                 // Field e:Landroid/support/constraint/a/a/j;
     261: putfield      #69                 // Field e:Landroid/support/constraint/a/a/j;
     264: aload_0
     265: getfield      #75                 // Field j:Landroid/support/constraint/a/a/j;
     268: aload_0
     269: getfield      #75                 // Field j:Landroid/support/constraint/a/a/j;
     272: getfield      #67                 // Field c:Landroid/support/constraint/a/a/j;
     275: getfield      #69                 // Field e:Landroid/support/constraint/a/a/j;
     278: putfield      #69                 // Field e:Landroid/support/constraint/a/a/j;
     281: aload_0
     282: getfield      #65                 // Field k:F
     285: fconst_0
     286: fcmpl
     287: ifle          318
     290: aload_0
     291: getfield      #67                 // Field c:Landroid/support/constraint/a/a/j;
     294: getfield      #71                 // Field f:F
     297: fstore_1
     298: aload_0
     299: getfield      #75                 // Field j:Landroid/support/constraint/a/a/j;
     302: getfield      #67                 // Field c:Landroid/support/constraint/a/a/j;
     305: astore        7
     307: fload_1
     308: aload         7
     310: getfield      #71                 // Field f:F
     313: fsub
     314: fstore_1
     315: goto          338
     318: aload_0
     319: getfield      #75                 // Field j:Landroid/support/constraint/a/a/j;
     322: getfield      #67                 // Field c:Landroid/support/constraint/a/a/j;
     325: getfield      #71                 // Field f:F
     328: fstore_1
     329: aload_0
     330: getfield      #67                 // Field c:Landroid/support/constraint/a/a/j;
     333: astore        7
     335: goto          307
     338: aload_0
     339: getfield      #39                 // Field a:Landroid/support/constraint/a/a/c;
     342: getfield      #91                 // Field android/support/constraint/a/a/c.b:Landroid/support/constraint/a/a/c$c;
     345: getstatic     #94                 // Field android/support/constraint/a/a/c$c.b:Landroid/support/constraint/a/a/c$c;
     348: if_acmpeq     395
     351: aload_0
     352: getfield      #39                 // Field a:Landroid/support/constraint/a/a/c;
     355: getfield      #91                 // Field android/support/constraint/a/a/c.b:Landroid/support/constraint/a/a/c$c;
     358: getstatic     #96                 // Field android/support/constraint/a/a/c$c.d:Landroid/support/constraint/a/a/c$c;
     361: if_acmpne     367
     364: goto          395
     367: fload_1
     368: aload_0
     369: getfield      #39                 // Field a:Landroid/support/constraint/a/a/c;
     372: getfield      #99                 // Field android/support/constraint/a/a/c.a:Landroid/support/constraint/a/a/d;
     375: invokevirtual #105                // Method android/support/constraint/a/a/d.q:()I
     378: i2f
     379: fsub
     380: fstore_2
     381: aload_0
     382: getfield      #39                 // Field a:Landroid/support/constraint/a/a/c;
     385: getfield      #99                 // Field android/support/constraint/a/a/c.a:Landroid/support/constraint/a/a/d;
     388: getfield      #108                // Field android/support/constraint/a/a/d.P:F
     391: fstore_1
     392: goto          420
     395: fload_1
     396: aload_0
     397: getfield      #39                 // Field a:Landroid/support/constraint/a/a/c;
     400: getfield      #99                 // Field android/support/constraint/a/a/c.a:Landroid/support/constraint/a/a/d;
     403: invokevirtual #110                // Method android/support/constraint/a/a/d.o:()I
     406: i2f
     407: fsub
     408: fstore_2
     409: aload_0
     410: getfield      #39                 // Field a:Landroid/support/constraint/a/a/c;
     413: getfield      #99                 // Field android/support/constraint/a/a/c.a:Landroid/support/constraint/a/a/d;
     416: getfield      #113                // Field android/support/constraint/a/a/d.O:F
     419: fstore_1
     420: aload_0
     421: getfield      #39                 // Field a:Landroid/support/constraint/a/a/c;
     424: invokevirtual #115                // Method android/support/constraint/a/a/c.e:()I
     427: istore        5
     429: aload_0
     430: getfield      #75                 // Field j:Landroid/support/constraint/a/a/j;
     433: getfield      #39                 // Field a:Landroid/support/constraint/a/a/c;
     436: invokevirtual #115                // Method android/support/constraint/a/a/c.e:()I
     439: istore        6
     441: aload_0
     442: getfield      #39                 // Field a:Landroid/support/constraint/a/a/c;
     445: invokevirtual #118                // Method android/support/constraint/a/a/c.g:()Landroid/support/constraint/a/a/c;
     448: aload_0
     449: getfield      #75                 // Field j:Landroid/support/constraint/a/a/j;
     452: getfield      #39                 // Field a:Landroid/support/constraint/a/a/c;
     455: invokevirtual #118                // Method android/support/constraint/a/a/c.g:()Landroid/support/constraint/a/a/c;
     458: if_acmpne     470
     461: ldc           #119                // float 0.5f
     463: fstore_1
     464: iconst_0
     465: istore        5
     467: iconst_0
     468: istore        6
     470: iload         5
     472: i2f
     473: fstore_3
     474: iload         6
     476: i2f
     477: fstore        4
     479: fload_2
     480: fload_3
     481: fsub
     482: fload         4
     484: fsub
     485: fstore_2
     486: aload_0
     487: getfield      #65                 // Field k:F
     490: fconst_0
     491: fcmpl
     492: ifle          541
     495: aload_0
     496: getfield      #75                 // Field j:Landroid/support/constraint/a/a/j;
     499: aload_0
     500: getfield      #75                 // Field j:Landroid/support/constraint/a/a/j;
     503: getfield      #67                 // Field c:Landroid/support/constraint/a/a/j;
     506: getfield      #71                 // Field f:F
     509: fload         4
     511: fadd
     512: fload_2
     513: fload_1
     514: fmul
     515: fadd
     516: putfield      #71                 // Field f:F
     519: aload_0
     520: aload_0
     521: getfield      #67                 // Field c:Landroid/support/constraint/a/a/j;
     524: getfield      #71                 // Field f:F
     527: fload_3
     528: fsub
     529: fload_2
     530: fconst_1
     531: fload_1
     532: fsub
     533: fmul
     534: fsub
     535: putfield      #71                 // Field f:F
     538: goto          736
     541: aload_0
     542: aload_0
     543: getfield      #67                 // Field c:Landroid/support/constraint/a/a/j;
     546: getfield      #71                 // Field f:F
     549: fload_3
     550: fadd
     551: fload_2
     552: fload_1
     553: fmul
     554: fadd
     555: putfield      #71                 // Field f:F
     558: aload_0
     559: getfield      #75                 // Field j:Landroid/support/constraint/a/a/j;
     562: aload_0
     563: getfield      #75                 // Field j:Landroid/support/constraint/a/a/j;
     566: getfield      #67                 // Field c:Landroid/support/constraint/a/a/j;
     569: getfield      #71                 // Field f:F
     572: fload         4
     574: fsub
     575: fload_2
     576: fconst_1
     577: fload_1
     578: fsub
     579: fmul
     580: fsub
     581: putfield      #71                 // Field f:F
     584: goto          736
     587: aload_0
     588: getfield      #29                 // Field g:I
     591: iconst_3
     592: if_icmpne     748
     595: aload_0
     596: getfield      #67                 // Field c:Landroid/support/constraint/a/a/j;
     599: ifnull        748
     602: aload_0
     603: getfield      #67                 // Field c:Landroid/support/constraint/a/a/j;
     606: getfield      #56                 // Field i:I
     609: iconst_1
     610: if_icmpne     748
     613: aload_0
     614: getfield      #75                 // Field j:Landroid/support/constraint/a/a/j;
     617: ifnull        748
     620: aload_0
     621: getfield      #75                 // Field j:Landroid/support/constraint/a/a/j;
     624: getfield      #67                 // Field c:Landroid/support/constraint/a/a/j;
     627: ifnull        748
     630: aload_0
     631: getfield      #75                 // Field j:Landroid/support/constraint/a/a/j;
     634: getfield      #67                 // Field c:Landroid/support/constraint/a/a/j;
     637: getfield      #56                 // Field i:I
     640: iconst_1
     641: if_icmpne     748
     644: invokestatic  #80                 // Method android/support/constraint/a/e.a:()Landroid/support/constraint/a/f;
     647: ifnull        667
     650: invokestatic  #80                 // Method android/support/constraint/a/e.a:()Landroid/support/constraint/a/f;
     653: astore        7
     655: aload         7
     657: aload         7
     659: getfield      #122                // Field android/support/constraint/a/f.x:J
     662: lconst_1
     663: ladd
     664: putfield      #122                // Field android/support/constraint/a/f.x:J
     667: aload_0
     668: aload_0
     669: getfield      #67                 // Field c:Landroid/support/constraint/a/a/j;
     672: getfield      #69                 // Field e:Landroid/support/constraint/a/a/j;
     675: putfield      #69                 // Field e:Landroid/support/constraint/a/a/j;
     678: aload_0
     679: getfield      #75                 // Field j:Landroid/support/constraint/a/a/j;
     682: aload_0
     683: getfield      #75                 // Field j:Landroid/support/constraint/a/a/j;
     686: getfield      #67                 // Field c:Landroid/support/constraint/a/a/j;
     689: getfield      #69                 // Field e:Landroid/support/constraint/a/a/j;
     692: putfield      #69                 // Field e:Landroid/support/constraint/a/a/j;
     695: aload_0
     696: aload_0
     697: getfield      #67                 // Field c:Landroid/support/constraint/a/a/j;
     700: getfield      #71                 // Field f:F
     703: aload_0
     704: getfield      #63                 // Field d:F
     707: fadd
     708: putfield      #71                 // Field f:F
     711: aload_0
     712: getfield      #75                 // Field j:Landroid/support/constraint/a/a/j;
     715: aload_0
     716: getfield      #75                 // Field j:Landroid/support/constraint/a/a/j;
     719: getfield      #67                 // Field c:Landroid/support/constraint/a/a/j;
     722: getfield      #71                 // Field f:F
     725: aload_0
     726: getfield      #75                 // Field j:Landroid/support/constraint/a/a/j;
     729: getfield      #63                 // Field d:F
     732: fadd
     733: putfield      #71                 // Field f:F
     736: aload_0
     737: invokevirtual #73                 // Method f:()V
     740: aload_0
     741: getfield      #75                 // Field j:Landroid/support/constraint/a/a/j;
     744: invokevirtual #73                 // Method f:()V
     747: return
     748: aload_0
     749: getfield      #29                 // Field g:I
     752: iconst_5
     753: if_icmpne     766
     756: aload_0
     757: getfield      #39                 // Field a:Landroid/support/constraint/a/a/c;
     760: getfield      #99                 // Field android/support/constraint/a/a/c.a:Landroid/support/constraint/a/a/d;
     763: invokevirtual #124                // Method android/support/constraint/a/a/d.c:()V
     766: return

  public void a(int, android.support.constraint.a.a.j, int);
    Code:
       0: aload_0
       1: iload_1
       2: putfield      #29                 // Field g:I
       5: aload_0
       6: aload_2
       7: putfield      #67                 // Field c:Landroid/support/constraint/a/a/j;
      10: aload_0
      11: iload_3
      12: i2f
      13: putfield      #63                 // Field d:F
      16: aload_0
      17: getfield      #67                 // Field c:Landroid/support/constraint/a/a/j;
      20: aload_0
      21: invokevirtual #128                // Method a:(Landroid/support/constraint/a/a/l;)V
      24: return

  public void a(android.support.constraint.a.a.j, float);
    Code:
       0: aload_0
       1: getfield      #56                 // Field i:I
       4: ifeq          24
       7: aload_0
       8: getfield      #69                 // Field e:Landroid/support/constraint/a/a/j;
      11: aload_1
      12: if_acmpeq     50
      15: aload_0
      16: getfield      #71                 // Field f:F
      19: fload_2
      20: fcmpl
      21: ifeq          50
      24: aload_0
      25: aload_1
      26: putfield      #69                 // Field e:Landroid/support/constraint/a/a/j;
      29: aload_0
      30: fload_2
      31: putfield      #71                 // Field f:F
      34: aload_0
      35: getfield      #56                 // Field i:I
      38: iconst_1
      39: if_icmpne     46
      42: aload_0
      43: invokevirtual #131                // Method e:()V
      46: aload_0
      47: invokevirtual #73                 // Method f:()V
      50: return

  public void a(android.support.constraint.a.a.j, int);
    Code:
       0: aload_0
       1: aload_1
       2: putfield      #67                 // Field c:Landroid/support/constraint/a/a/j;
       5: aload_0
       6: iload_2
       7: i2f
       8: putfield      #63                 // Field d:F
      11: aload_0
      12: getfield      #67                 // Field c:Landroid/support/constraint/a/a/j;
      15: aload_0
      16: invokevirtual #128                // Method a:(Landroid/support/constraint/a/a/l;)V
      19: return

  public void a(android.support.constraint.a.a.j, int, android.support.constraint.a.a.k);
    Code:
       0: aload_0
       1: aload_1
       2: putfield      #67                 // Field c:Landroid/support/constraint/a/a/j;
       5: aload_0
       6: getfield      #67                 // Field c:Landroid/support/constraint/a/a/j;
       9: aload_0
      10: invokevirtual #128                // Method a:(Landroid/support/constraint/a/a/l;)V
      13: aload_0
      14: aload_3
      15: putfield      #31                 // Field l:Landroid/support/constraint/a/a/k;
      18: aload_0
      19: iload_2
      20: putfield      #33                 // Field m:I
      23: aload_0
      24: getfield      #31                 // Field l:Landroid/support/constraint/a/a/k;
      27: aload_0
      28: invokevirtual #134                // Method android/support/constraint/a/a/k.a:(Landroid/support/constraint/a/a/l;)V
      31: return

  void a(android.support.constraint.a.e);
    Code:
       0: aload_0
       1: getfield      #39                 // Field a:Landroid/support/constraint/a/a/c;
       4: invokevirtual #138                // Method android/support/constraint/a/a/c.b:()Landroid/support/constraint/a/h;
       7: astore_2
       8: aload_0
       9: getfield      #69                 // Field e:Landroid/support/constraint/a/a/j;
      12: ifnonnull     26
      15: aload_1
      16: aload_2
      17: aload_0
      18: getfield      #71                 // Field f:F
      21: f2i
      22: invokevirtual #141                // Method android/support/constraint/a/e.a:(Landroid/support/constraint/a/h;I)V
      25: return
      26: aload_1
      27: aload_2
      28: aload_1
      29: aload_0
      30: getfield      #69                 // Field e:Landroid/support/constraint/a/a/j;
      33: getfield      #39                 // Field a:Landroid/support/constraint/a/a/c;
      36: invokevirtual #144                // Method android/support/constraint/a/e.a:(Ljava/lang/Object;)Landroid/support/constraint/a/h;
      39: aload_0
      40: getfield      #71                 // Field f:F
      43: f2i
      44: bipush        6
      46: invokevirtual #147                // Method android/support/constraint/a/e.c:(Landroid/support/constraint/a/h;Landroid/support/constraint/a/h;II)Landroid/support/constraint/a/b;
      49: pop
      50: return

  public void b();
    Code:
       0: aload_0
       1: invokespecial #149                // Method android/support/constraint/a/a/l.b:()V
       4: aload_0
       5: aconst_null
       6: putfield      #67                 // Field c:Landroid/support/constraint/a/a/j;
       9: aload_0
      10: fconst_0
      11: putfield      #63                 // Field d:F
      14: aload_0
      15: aconst_null
      16: putfield      #31                 // Field l:Landroid/support/constraint/a/a/k;
      19: aload_0
      20: iconst_1
      21: putfield      #33                 // Field m:I
      24: aload_0
      25: aconst_null
      26: putfield      #35                 // Field n:Landroid/support/constraint/a/a/k;
      29: aload_0
      30: iconst_1
      31: putfield      #37                 // Field o:I
      34: aload_0
      35: aconst_null
      36: putfield      #69                 // Field e:Landroid/support/constraint/a/a/j;
      39: aload_0
      40: fconst_0
      41: putfield      #71                 // Field f:F
      44: aload_0
      45: fconst_0
      46: putfield      #151                // Field b:F
      49: aload_0
      50: aconst_null
      51: putfield      #75                 // Field j:Landroid/support/constraint/a/a/j;
      54: aload_0
      55: fconst_0
      56: putfield      #65                 // Field k:F
      59: aload_0
      60: iconst_0
      61: putfield      #29                 // Field g:I
      64: return

  public void b(int);
    Code:
       0: aload_0
       1: iload_1
       2: putfield      #29                 // Field g:I
       5: return

  public void b(android.support.constraint.a.a.j, float);
    Code:
       0: aload_0
       1: aload_1
       2: putfield      #75                 // Field j:Landroid/support/constraint/a/a/j;
       5: aload_0
       6: fload_2
       7: putfield      #65                 // Field k:F
      10: return

  public void b(android.support.constraint.a.a.j, int, android.support.constraint.a.a.k);
    Code:
       0: aload_0
       1: aload_1
       2: putfield      #75                 // Field j:Landroid/support/constraint/a/a/j;
       5: aload_0
       6: aload_3
       7: putfield      #35                 // Field n:Landroid/support/constraint/a/a/k;
      10: aload_0
      11: iload_2
      12: putfield      #37                 // Field o:I
      15: return

  public void c();
    Code:
       0: aload_0
       1: getfield      #39                 // Field a:Landroid/support/constraint/a/a/c;
       4: invokevirtual #118                // Method android/support/constraint/a/a/c.g:()Landroid/support/constraint/a/a/c;
       7: astore_3
       8: aload_3
       9: ifnonnull     13
      12: return
      13: aload_3
      14: invokevirtual #118                // Method android/support/constraint/a/a/c.g:()Landroid/support/constraint/a/a/c;
      17: aload_0
      18: getfield      #39                 // Field a:Landroid/support/constraint/a/a/c;
      21: if_acmpne     37
      24: aload_0
      25: iconst_4
      26: putfield      #29                 // Field g:I
      29: aload_3
      30: invokevirtual #155                // Method android/support/constraint/a/a/c.a:()Landroid/support/constraint/a/a/j;
      33: iconst_4
      34: putfield      #29                 // Field g:I
      37: aload_0
      38: getfield      #39                 // Field a:Landroid/support/constraint/a/a/c;
      41: invokevirtual #115                // Method android/support/constraint/a/a/c.e:()I
      44: istore_2
      45: aload_0
      46: getfield      #39                 // Field a:Landroid/support/constraint/a/a/c;
      49: getfield      #91                 // Field android/support/constraint/a/a/c.b:Landroid/support/constraint/a/a/c$c;
      52: getstatic     #96                 // Field android/support/constraint/a/a/c$c.d:Landroid/support/constraint/a/a/c$c;
      55: if_acmpeq     73
      58: iload_2
      59: istore_1
      60: aload_0
      61: getfield      #39                 // Field a:Landroid/support/constraint/a/a/c;
      64: getfield      #91                 // Field android/support/constraint/a/a/c.b:Landroid/support/constraint/a/a/c$c;
      67: getstatic     #157                // Field android/support/constraint/a/a/c$c.e:Landroid/support/constraint/a/a/c$c;
      70: if_acmpne     76
      73: iload_2
      74: ineg
      75: istore_1
      76: aload_0
      77: aload_3
      78: invokevirtual #155                // Method android/support/constraint/a/a/c.a:()Landroid/support/constraint/a/a/j;
      81: iload_1
      82: invokevirtual #159                // Method a:(Landroid/support/constraint/a/a/j;I)V
      85: return

  public float d();
    Code:
       0: aload_0
       1: getfield      #71                 // Field f:F
       4: freturn

  public java.lang.String toString();
    Code:
       0: aload_0
       1: getfield      #56                 // Field i:I
       4: iconst_1
       5: if_icmpne     145
       8: aload_0
       9: getfield      #69                 // Field e:Landroid/support/constraint/a/a/j;
      12: aload_0
      13: if_acmpne     83
      16: new           #164                // class java/lang/StringBuilder
      19: dup
      20: invokespecial #165                // Method java/lang/StringBuilder."<init>":()V
      23: astore_1
      24: aload_1
      25: ldc           #167                // String [
      27: invokevirtual #171                // Method java/lang/StringBuilder.append:(Ljava/lang/String;)Ljava/lang/StringBuilder;
      30: pop
      31: aload_1
      32: aload_0
      33: getfield      #39                 // Field a:Landroid/support/constraint/a/a/c;
      36: invokevirtual #174                // Method java/lang/StringBuilder.append:(Ljava/lang/Object;)Ljava/lang/StringBuilder;
      39: pop
      40: aload_1
      41: ldc           #176                // String , RESOLVED:
      43: invokevirtual #171                // Method java/lang/StringBuilder.append:(Ljava/lang/String;)Ljava/lang/StringBuilder;
      46: pop
      47: aload_1
      48: aload_0
      49: getfield      #71                 // Field f:F
      52: invokevirtual #179                // Method java/lang/StringBuilder.append:(F)Ljava/lang/StringBuilder;
      55: pop
      56: ldc           #181                // String ]  type:
      58: astore_2
      59: aload_1
      60: aload_2
      61: invokevirtual #171                // Method java/lang/StringBuilder.append:(Ljava/lang/String;)Ljava/lang/StringBuilder;
      64: pop
      65: aload_1
      66: aload_0
      67: aload_0
      68: getfield      #29                 // Field g:I
      71: invokevirtual #183                // Method a:(I)Ljava/lang/String;
      74: invokevirtual #171                // Method java/lang/StringBuilder.append:(Ljava/lang/String;)Ljava/lang/StringBuilder;
      77: pop
      78: aload_1
      79: invokevirtual #185                // Method java/lang/StringBuilder.toString:()Ljava/lang/String;
      82: areturn
      83: new           #164                // class java/lang/StringBuilder
      86: dup
      87: invokespecial #165                // Method java/lang/StringBuilder."<init>":()V
      90: astore_1
      91: aload_1
      92: ldc           #167                // String [
      94: invokevirtual #171                // Method java/lang/StringBuilder.append:(Ljava/lang/String;)Ljava/lang/StringBuilder;
      97: pop
      98: aload_1
      99: aload_0
     100: getfield      #39                 // Field a:Landroid/support/constraint/a/a/c;
     103: invokevirtual #174                // Method java/lang/StringBuilder.append:(Ljava/lang/Object;)Ljava/lang/StringBuilder;
     106: pop
     107: aload_1
     108: ldc           #176                // String , RESOLVED:
     110: invokevirtual #171                // Method java/lang/StringBuilder.append:(Ljava/lang/String;)Ljava/lang/StringBuilder;
     113: pop
     114: aload_1
     115: aload_0
     116: getfield      #69                 // Field e:Landroid/support/constraint/a/a/j;
     119: invokevirtual #174                // Method java/lang/StringBuilder.append:(Ljava/lang/Object;)Ljava/lang/StringBuilder;
     122: pop
     123: aload_1
     124: ldc           #187                // String :
     126: invokevirtual #171                // Method java/lang/StringBuilder.append:(Ljava/lang/String;)Ljava/lang/StringBuilder;
     129: pop
     130: aload_1
     131: aload_0
     132: getfield      #71                 // Field f:F
     135: invokevirtual #179                // Method java/lang/StringBuilder.append:(F)Ljava/lang/StringBuilder;
     138: pop
     139: ldc           #189                // String ] type:
     141: astore_2
     142: goto          59
     145: new           #164                // class java/lang/StringBuilder
     148: dup
     149: invokespecial #165                // Method java/lang/StringBuilder."<init>":()V
     152: astore_1
     153: aload_1
     154: ldc           #191                // String {
     156: invokevirtual #171                // Method java/lang/StringBuilder.append:(Ljava/lang/String;)Ljava/lang/StringBuilder;
     159: pop
     160: aload_1
     161: aload_0
     162: getfield      #39                 // Field a:Landroid/support/constraint/a/a/c;
     165: invokevirtual #174                // Method java/lang/StringBuilder.append:(Ljava/lang/Object;)Ljava/lang/StringBuilder;
     168: pop
     169: ldc           #193                // String  UNRESOLVED} type:
     171: astore_2
     172: goto          59
}
