class android.support.constraint.a.a.m$a {
  public android.support.constraint.a.a.m$a(android.support.constraint.a.a.c);
    Code:
       0: aload_0
       1: invokespecial #19                 // Method java/lang/Object."<init>":()V
       4: aload_0
       5: aload_1
       6: putfield      #21                 // Field a:Landroid/support/constraint/a/a/c;
       9: aload_0
      10: aload_1
      11: invokevirtual #27                 // Method android/support/constraint/a/a/c.g:()Landroid/support/constraint/a/a/c;
      14: putfield      #29                 // Field b:Landroid/support/constraint/a/a/c;
      17: aload_0
      18: aload_1
      19: invokevirtual #32                 // Method android/support/constraint/a/a/c.e:()I
      22: putfield      #34                 // Field c:I
      25: aload_0
      26: aload_1
      27: invokevirtual #38                 // Method android/support/constraint/a/a/c.f:()Landroid/support/constraint/a/a/c$b;
      30: putfield      #40                 // Field d:Landroid/support/constraint/a/a/c$b;
      33: aload_0
      34: aload_1
      35: invokevirtual #43                 // Method android/support/constraint/a/a/c.h:()I
      38: putfield      #45                 // Field e:I
      41: return

  public void a(android.support.constraint.a.a.d);
    Code:
       0: aload_0
       1: aload_1
       2: aload_0
       3: getfield      #21                 // Field a:Landroid/support/constraint/a/a/c;
       6: invokevirtual #50                 // Method android/support/constraint/a/a/c.d:()Landroid/support/constraint/a/a/c$c;
       9: invokevirtual #55                 // Method android/support/constraint/a/a/d.a:(Landroid/support/constraint/a/a/c$c;)Landroid/support/constraint/a/a/c;
      12: putfield      #21                 // Field a:Landroid/support/constraint/a/a/c;
      15: aload_0
      16: getfield      #21                 // Field a:Landroid/support/constraint/a/a/c;
      19: ifnull        69
      22: aload_0
      23: aload_0
      24: getfield      #21                 // Field a:Landroid/support/constraint/a/a/c;
      27: invokevirtual #27                 // Method android/support/constraint/a/a/c.g:()Landroid/support/constraint/a/a/c;
      30: putfield      #29                 // Field b:Landroid/support/constraint/a/a/c;
      33: aload_0
      34: aload_0
      35: getfield      #21                 // Field a:Landroid/support/constraint/a/a/c;
      38: invokevirtual #32                 // Method android/support/constraint/a/a/c.e:()I
      41: putfield      #34                 // Field c:I
      44: aload_0
      45: aload_0
      46: getfield      #21                 // Field a:Landroid/support/constraint/a/a/c;
      49: invokevirtual #38                 // Method android/support/constraint/a/a/c.f:()Landroid/support/constraint/a/a/c$b;
      52: putfield      #40                 // Field d:Landroid/support/constraint/a/a/c$b;
      55: aload_0
      56: getfield      #21                 // Field a:Landroid/support/constraint/a/a/c;
      59: invokevirtual #43                 // Method android/support/constraint/a/a/c.h:()I
      62: istore_2
      63: aload_0
      64: iload_2
      65: putfield      #45                 // Field e:I
      68: return
      69: aload_0
      70: aconst_null
      71: putfield      #29                 // Field b:Landroid/support/constraint/a/a/c;
      74: iconst_0
      75: istore_2
      76: aload_0
      77: iconst_0
      78: putfield      #34                 // Field c:I
      81: aload_0
      82: getstatic     #59                 // Field android/support/constraint/a/a/c$b.b:Landroid/support/constraint/a/a/c$b;
      85: putfield      #40                 // Field d:Landroid/support/constraint/a/a/c$b;
      88: goto          63

  public void b(android.support.constraint.a.a.d);
    Code:
       0: aload_1
       1: aload_0
       2: getfield      #21                 // Field a:Landroid/support/constraint/a/a/c;
       5: invokevirtual #50                 // Method android/support/constraint/a/a/c.d:()Landroid/support/constraint/a/a/c$c;
       8: invokevirtual #55                 // Method android/support/constraint/a/a/d.a:(Landroid/support/constraint/a/a/c$c;)Landroid/support/constraint/a/a/c;
      11: aload_0
      12: getfield      #29                 // Field b:Landroid/support/constraint/a/a/c;
      15: aload_0
      16: getfield      #34                 // Field c:I
      19: aload_0
      20: getfield      #40                 // Field d:Landroid/support/constraint/a/a/c$b;
      23: aload_0
      24: getfield      #45                 // Field e:I
      27: invokevirtual #62                 // Method android/support/constraint/a/a/c.a:(Landroid/support/constraint/a/a/c;ILandroid/support/constraint/a/a/c$b;I)Z
      30: pop
      31: return
}
