public class android.support.constraint.a.a.m {
  public android.support.constraint.a.a.m(android.support.constraint.a.a.d);
    Code:
       0: aload_0
       1: invokespecial #19                 // Method java/lang/Object."<init>":()V
       4: aload_0
       5: new           #21                 // class java/util/ArrayList
       8: dup
       9: invokespecial #22                 // Method java/util/ArrayList."<init>":()V
      12: putfield      #24                 // Field e:Ljava/util/ArrayList;
      15: aload_0
      16: aload_1
      17: invokevirtual #30                 // Method android/support/constraint/a/a/d.m:()I
      20: putfield      #32                 // Field a:I
      23: aload_0
      24: aload_1
      25: invokevirtual #35                 // Method android/support/constraint/a/a/d.n:()I
      28: putfield      #37                 // Field b:I
      31: aload_0
      32: aload_1
      33: invokevirtual #40                 // Method android/support/constraint/a/a/d.o:()I
      36: putfield      #42                 // Field c:I
      39: aload_0
      40: aload_1
      41: invokevirtual #45                 // Method android/support/constraint/a/a/d.q:()I
      44: putfield      #47                 // Field d:I
      47: aload_1
      48: invokevirtual #51                 // Method android/support/constraint/a/a/d.C:()Ljava/util/ArrayList;
      51: astore_1
      52: aload_1
      53: invokevirtual #54                 // Method java/util/ArrayList.size:()I
      56: istore_3
      57: iconst_0
      58: istore_2
      59: iload_2
      60: iload_3
      61: if_icmpge     98
      64: aload_1
      65: iload_2
      66: invokevirtual #58                 // Method java/util/ArrayList.get:(I)Ljava/lang/Object;
      69: checkcast     #60                 // class android/support/constraint/a/a/c
      72: astore        4
      74: aload_0
      75: getfield      #24                 // Field e:Ljava/util/ArrayList;
      78: new           #6                  // class android/support/constraint/a/a/m$a
      81: dup
      82: aload         4
      84: invokespecial #63                 // Method android/support/constraint/a/a/m$a."<init>":(Landroid/support/constraint/a/a/c;)V
      87: invokevirtual #67                 // Method java/util/ArrayList.add:(Ljava/lang/Object;)Z
      90: pop
      91: iload_2
      92: iconst_1
      93: iadd
      94: istore_2
      95: goto          59
      98: return

  public void a(android.support.constraint.a.a.d);
    Code:
       0: aload_0
       1: aload_1
       2: invokevirtual #30                 // Method android/support/constraint/a/a/d.m:()I
       5: putfield      #32                 // Field a:I
       8: aload_0
       9: aload_1
      10: invokevirtual #35                 // Method android/support/constraint/a/a/d.n:()I
      13: putfield      #37                 // Field b:I
      16: aload_0
      17: aload_1
      18: invokevirtual #40                 // Method android/support/constraint/a/a/d.o:()I
      21: putfield      #42                 // Field c:I
      24: aload_0
      25: aload_1
      26: invokevirtual #45                 // Method android/support/constraint/a/a/d.q:()I
      29: putfield      #47                 // Field d:I
      32: aload_0
      33: getfield      #24                 // Field e:Ljava/util/ArrayList;
      36: invokevirtual #54                 // Method java/util/ArrayList.size:()I
      39: istore_3
      40: iconst_0
      41: istore_2
      42: iload_2
      43: iload_3
      44: if_icmpge     69
      47: aload_0
      48: getfield      #24                 // Field e:Ljava/util/ArrayList;
      51: iload_2
      52: invokevirtual #58                 // Method java/util/ArrayList.get:(I)Ljava/lang/Object;
      55: checkcast     #6                  // class android/support/constraint/a/a/m$a
      58: aload_1
      59: invokevirtual #70                 // Method android/support/constraint/a/a/m$a.a:(Landroid/support/constraint/a/a/d;)V
      62: iload_2
      63: iconst_1
      64: iadd
      65: istore_2
      66: goto          42
      69: return

  public void b(android.support.constraint.a.a.d);
    Code:
       0: aload_1
       1: aload_0
       2: getfield      #32                 // Field a:I
       5: invokevirtual #74                 // Method android/support/constraint/a/a/d.f:(I)V
       8: aload_1
       9: aload_0
      10: getfield      #37                 // Field b:I
      13: invokevirtual #77                 // Method android/support/constraint/a/a/d.g:(I)V
      16: aload_1
      17: aload_0
      18: getfield      #42                 // Field c:I
      21: invokevirtual #80                 // Method android/support/constraint/a/a/d.h:(I)V
      24: aload_1
      25: aload_0
      26: getfield      #47                 // Field d:I
      29: invokevirtual #83                 // Method android/support/constraint/a/a/d.i:(I)V
      32: aload_0
      33: getfield      #24                 // Field e:Ljava/util/ArrayList;
      36: invokevirtual #54                 // Method java/util/ArrayList.size:()I
      39: istore_3
      40: iconst_0
      41: istore_2
      42: iload_2
      43: iload_3
      44: if_icmpge     69
      47: aload_0
      48: getfield      #24                 // Field e:Ljava/util/ArrayList;
      51: iload_2
      52: invokevirtual #58                 // Method java/util/ArrayList.get:(I)Ljava/lang/Object;
      55: checkcast     #6                  // class android/support/constraint/a/a/m$a
      58: aload_1
      59: invokevirtual #85                 // Method android/support/constraint/a/a/m$a.b:(Landroid/support/constraint/a/a/d;)V
      62: iload_2
      63: iconst_1
      64: iadd
      65: istore_2
      66: goto          42
      69: return
}
