public class android.support.constraint.a.a.n extends android.support.constraint.a.a.d {
  protected java.util.ArrayList<android.support.constraint.a.a.d> al;

  public android.support.constraint.a.a.n();
    Code:
       0: aload_0
       1: invokespecial #11                 // Method android/support/constraint/a/a/d."<init>":()V
       4: aload_0
       5: new           #13                 // class java/util/ArrayList
       8: dup
       9: invokespecial #14                 // Method java/util/ArrayList."<init>":()V
      12: putfield      #16                 // Field al:Ljava/util/ArrayList;
      15: return

  public void D();
    Code:
       0: aload_0
       1: invokespecial #20                 // Method android/support/constraint/a/a/d.D:()V
       4: aload_0
       5: getfield      #16                 // Field al:Ljava/util/ArrayList;
       8: ifnonnull     12
      11: return
      12: aload_0
      13: getfield      #16                 // Field al:Ljava/util/ArrayList;
      16: invokevirtual #24                 // Method java/util/ArrayList.size:()I
      19: istore_2
      20: iconst_0
      21: istore_1
      22: iload_1
      23: iload_2
      24: if_icmpge     69
      27: aload_0
      28: getfield      #16                 // Field al:Ljava/util/ArrayList;
      31: iload_1
      32: invokevirtual #28                 // Method java/util/ArrayList.get:(I)Ljava/lang/Object;
      35: checkcast     #4                  // class android/support/constraint/a/a/d
      38: astore_3
      39: aload_3
      40: aload_0
      41: invokevirtual #31                 // Method s:()I
      44: aload_0
      45: invokevirtual #34                 // Method t:()I
      48: invokevirtual #38                 // Method android/support/constraint/a/a/d.b:(II)V
      51: aload_3
      52: instanceof    #40                 // class android/support/constraint/a/a/e
      55: ifne          62
      58: aload_3
      59: invokevirtual #20                 // Method android/support/constraint/a/a/d.D:()V
      62: iload_1
      63: iconst_1
      64: iadd
      65: istore_1
      66: goto          22
      69: return

  public void L();
    Code:
       0: aload_0
       1: invokevirtual #42                 // Method D:()V
       4: aload_0
       5: getfield      #16                 // Field al:Ljava/util/ArrayList;
       8: ifnonnull     12
      11: return
      12: aload_0
      13: getfield      #16                 // Field al:Ljava/util/ArrayList;
      16: invokevirtual #24                 // Method java/util/ArrayList.size:()I
      19: istore_2
      20: iconst_0
      21: istore_1
      22: iload_1
      23: iload_2
      24: if_icmpge     60
      27: aload_0
      28: getfield      #16                 // Field al:Ljava/util/ArrayList;
      31: iload_1
      32: invokevirtual #28                 // Method java/util/ArrayList.get:(I)Ljava/lang/Object;
      35: checkcast     #4                  // class android/support/constraint/a/a/d
      38: astore_3
      39: aload_3
      40: instanceof    #2                  // class android/support/constraint/a/a/n
      43: ifeq          53
      46: aload_3
      47: checkcast     #2                  // class android/support/constraint/a/a/n
      50: invokevirtual #44                 // Method L:()V
      53: iload_1
      54: iconst_1
      55: iadd
      56: istore_1
      57: goto          22
      60: return

  public android.support.constraint.a.a.e R();
    Code:
       0: aload_0
       1: invokevirtual #50                 // Method android/support/constraint/a/a/d.j:()Landroid/support/constraint/a/a/d;
       4: astore_2
       5: aload_0
       6: instanceof    #40                 // class android/support/constraint/a/a/e
       9: ifeq          20
      12: aload_0
      13: checkcast     #40                 // class android/support/constraint/a/a/e
      16: astore_1
      17: goto          22
      20: aconst_null
      21: astore_1
      22: aload_2
      23: ifnull        48
      26: aload_2
      27: invokevirtual #50                 // Method android/support/constraint/a/a/d.j:()Landroid/support/constraint/a/a/d;
      30: astore_3
      31: aload_2
      32: instanceof    #40                 // class android/support/constraint/a/a/e
      35: ifeq          43
      38: aload_2
      39: checkcast     #40                 // class android/support/constraint/a/a/e
      42: astore_1
      43: aload_3
      44: astore_2
      45: goto          22
      48: aload_1
      49: areturn

  public void S();
    Code:
       0: aload_0
       1: getfield      #16                 // Field al:Ljava/util/ArrayList;
       4: invokevirtual #54                 // Method java/util/ArrayList.clear:()V
       7: return

  public void a(android.support.constraint.a.c);
    Code:
       0: aload_0
       1: aload_1
       2: invokespecial #58                 // Method android/support/constraint/a/a/d.a:(Landroid/support/constraint/a/c;)V
       5: aload_0
       6: getfield      #16                 // Field al:Ljava/util/ArrayList;
       9: invokevirtual #24                 // Method java/util/ArrayList.size:()I
      12: istore_3
      13: iconst_0
      14: istore_2
      15: iload_2
      16: iload_3
      17: if_icmpge     42
      20: aload_0
      21: getfield      #16                 // Field al:Ljava/util/ArrayList;
      24: iload_2
      25: invokevirtual #28                 // Method java/util/ArrayList.get:(I)Ljava/lang/Object;
      28: checkcast     #4                  // class android/support/constraint/a/a/d
      31: aload_1
      32: invokevirtual #58                 // Method android/support/constraint/a/a/d.a:(Landroid/support/constraint/a/c;)V
      35: iload_2
      36: iconst_1
      37: iadd
      38: istore_2
      39: goto          15
      42: return

  public void b(int, int);
    Code:
       0: aload_0
       1: iload_1
       2: iload_2
       3: invokespecial #38                 // Method android/support/constraint/a/a/d.b:(II)V
       6: aload_0
       7: getfield      #16                 // Field al:Ljava/util/ArrayList;
      10: invokevirtual #24                 // Method java/util/ArrayList.size:()I
      13: istore_2
      14: iconst_0
      15: istore_1
      16: iload_1
      17: iload_2
      18: if_icmpge     50
      21: aload_0
      22: getfield      #16                 // Field al:Ljava/util/ArrayList;
      25: iload_1
      26: invokevirtual #28                 // Method java/util/ArrayList.get:(I)Ljava/lang/Object;
      29: checkcast     #4                  // class android/support/constraint/a/a/d
      32: aload_0
      33: invokevirtual #61                 // Method u:()I
      36: aload_0
      37: invokevirtual #64                 // Method v:()I
      40: invokevirtual #38                 // Method android/support/constraint/a/a/d.b:(II)V
      43: iload_1
      44: iconst_1
      45: iadd
      46: istore_1
      47: goto          16
      50: return

  public void b(android.support.constraint.a.a.d);
    Code:
       0: aload_0
       1: getfield      #16                 // Field al:Ljava/util/ArrayList;
       4: aload_1
       5: invokevirtual #69                 // Method java/util/ArrayList.add:(Ljava/lang/Object;)Z
       8: pop
       9: aload_1
      10: invokevirtual #50                 // Method android/support/constraint/a/a/d.j:()Landroid/support/constraint/a/a/d;
      13: ifnull        27
      16: aload_1
      17: invokevirtual #50                 // Method android/support/constraint/a/a/d.j:()Landroid/support/constraint/a/a/d;
      20: checkcast     #2                  // class android/support/constraint/a/a/n
      23: aload_1
      24: invokevirtual #72                 // Method c:(Landroid/support/constraint/a/a/d;)V
      27: aload_1
      28: aload_0
      29: invokevirtual #74                 // Method android/support/constraint/a/a/d.a:(Landroid/support/constraint/a/a/d;)V
      32: return

  public void c(android.support.constraint.a.a.d);
    Code:
       0: aload_0
       1: getfield      #16                 // Field al:Ljava/util/ArrayList;
       4: aload_1
       5: invokevirtual #77                 // Method java/util/ArrayList.remove:(Ljava/lang/Object;)Z
       8: pop
       9: aload_1
      10: aconst_null
      11: invokevirtual #74                 // Method android/support/constraint/a/a/d.a:(Landroid/support/constraint/a/a/d;)V
      14: return

  public void f();
    Code:
       0: aload_0
       1: getfield      #16                 // Field al:Ljava/util/ArrayList;
       4: invokevirtual #54                 // Method java/util/ArrayList.clear:()V
       7: aload_0
       8: invokespecial #80                 // Method android/support/constraint/a/a/d.f:()V
      11: return
}
