class ryey.easer.plugins.event.c$1 extends android.content.BroadcastReceiver {
  final ryey.easer.plugins.event.c a;

  ryey.easer.plugins.event.c$1(ryey.easer.plugins.event.c);
    Code:
       0: aload_0
       1: aload_1
       2: putfield      #12                 // Field a:Lryey/easer/plugins/event/c;
       5: aload_0
       6: invokespecial #15                 // Method android/content/BroadcastReceiver."<init>":()V
       9: return

  public void onReceive(android.content.Context, android.content.Intent);
    Code:
       0: ldc           #20                 // String self notifying Intent received. action: %s
       2: iconst_1
       3: anewarray     #22                 // class java/lang/Object
       6: dup
       7: iconst_0
       8: aload_2
       9: invokevirtual #28                 // Method android/content/Intent.getAction:()Ljava/lang/String;
      12: aastore
      13: invokestatic  #33                 // Method com/b/a/i.a:(Ljava/lang/String;[Ljava/lang/Object;)V
      16: aload_2
      17: invokevirtual #28                 // Method android/content/Intent.getAction:()Ljava/lang/String;
      20: ldc           #35                 // String ryey.easer.triggerlotus.abstractslot.SATISFIED
      22: invokevirtual #41                 // Method java/lang/String.equals:(Ljava/lang/Object;)Z
      25: ifeq          37
      28: aload_0
      29: getfield      #12                 // Field a:Lryey/easer/plugins/event/c;
      32: aload_2
      33: invokevirtual #44                 // Method ryey/easer/plugins/event/c.a:(Landroid/content/Intent;)V
      36: return
      37: aload_2
      38: invokevirtual #28                 // Method android/content/Intent.getAction:()Ljava/lang/String;
      41: ldc           #46                 // String ryey.easer.triggerlotus.abstractslot.UNSATISFIED
      43: invokevirtual #41                 // Method java/lang/String.equals:(Ljava/lang/Object;)Z
      46: ifeq          57
      49: aload_0
      50: getfield      #12                 // Field a:Lryey/easer/plugins/event/c;
      53: aload_2
      54: invokevirtual #49                 // Method ryey/easer/plugins/event/c.b:(Landroid/content/Intent;)V
      57: return
}
