public final class android.support.v4.media.MediaDescriptionCompat$a {
  public android.support.v4.media.MediaDescriptionCompat$a();
    Code:
       0: aload_0
       1: invokespecial #23                 // Method java/lang/Object."<init>":()V
       4: return

  public android.support.v4.media.MediaDescriptionCompat$a a(android.graphics.Bitmap);
    Code:
       0: aload_0
       1: aload_1
       2: putfield      #27                 // Field e:Landroid/graphics/Bitmap;
       5: aload_0
       6: areturn

  public android.support.v4.media.MediaDescriptionCompat$a a(android.net.Uri);
    Code:
       0: aload_0
       1: aload_1
       2: putfield      #30                 // Field f:Landroid/net/Uri;
       5: aload_0
       6: areturn

  public android.support.v4.media.MediaDescriptionCompat$a a(android.os.Bundle);
    Code:
       0: aload_0
       1: aload_1
       2: putfield      #33                 // Field g:Landroid/os/Bundle;
       5: aload_0
       6: areturn

  public android.support.v4.media.MediaDescriptionCompat$a a(java.lang.CharSequence);
    Code:
       0: aload_0
       1: aload_1
       2: putfield      #36                 // Field b:Ljava/lang/CharSequence;
       5: aload_0
       6: areturn

  public android.support.v4.media.MediaDescriptionCompat$a a(java.lang.String);
    Code:
       0: aload_0
       1: aload_1
       2: putfield      #39                 // Field a:Ljava/lang/String;
       5: aload_0
       6: areturn

  public android.support.v4.media.MediaDescriptionCompat a();
    Code:
       0: new           #6                  // class android/support/v4/media/MediaDescriptionCompat
       3: dup
       4: aload_0
       5: getfield      #39                 // Field a:Ljava/lang/String;
       8: aload_0
       9: getfield      #36                 // Field b:Ljava/lang/CharSequence;
      12: aload_0
      13: getfield      #42                 // Field c:Ljava/lang/CharSequence;
      16: aload_0
      17: getfield      #44                 // Field d:Ljava/lang/CharSequence;
      20: aload_0
      21: getfield      #27                 // Field e:Landroid/graphics/Bitmap;
      24: aload_0
      25: getfield      #30                 // Field f:Landroid/net/Uri;
      28: aload_0
      29: getfield      #33                 // Field g:Landroid/os/Bundle;
      32: aload_0
      33: getfield      #46                 // Field h:Landroid/net/Uri;
      36: invokespecial #49                 // Method android/support/v4/media/MediaDescriptionCompat."<init>":(Ljava/lang/String;Ljava/lang/CharSequence;Ljava/lang/CharSequence;Ljava/lang/CharSequence;Landroid/graphics/Bitmap;Landroid/net/Uri;Landroid/os/Bundle;Landroid/net/Uri;)V
      39: areturn

  public android.support.v4.media.MediaDescriptionCompat$a b(android.net.Uri);
    Code:
       0: aload_0
       1: aload_1
       2: putfield      #46                 // Field h:Landroid/net/Uri;
       5: aload_0
       6: areturn

  public android.support.v4.media.MediaDescriptionCompat$a b(java.lang.CharSequence);
    Code:
       0: aload_0
       1: aload_1
       2: putfield      #42                 // Field c:Ljava/lang/CharSequence;
       5: aload_0
       6: areturn

  public android.support.v4.media.MediaDescriptionCompat$a c(java.lang.CharSequence);
    Code:
       0: aload_0
       1: aload_1
       2: putfield      #44                 // Field d:Ljava/lang/CharSequence;
       5: aload_0
       6: areturn
}
