public class ryey.easer.commons.local_plugin.b extends java.lang.Exception {
  public ryey.easer.commons.local_plugin.b(java.lang.Exception);
    Code:
       0: aload_0
       1: aload_1
       2: invokevirtual #10                 // Method java/lang/Exception.getMessage:()Ljava/lang/String;
       5: invokespecial #13                 // Method "<init>":(Ljava/lang/String;)V
       8: return

  public ryey.easer.commons.local_plugin.b(java.lang.String);
    Code:
       0: aload_0
       1: aload_1
       2: invokespecial #15                 // Method java/lang/Exception."<init>":(Ljava/lang/String;)V
       5: return
}
