public final class ryey.easer.core.log.ActivityLogService$a extends android.os.Binder {
  public ryey.easer.core.log.ActivityLogService$a(ryey.easer.core.log.ActivityLogService);
    Code:
       0: aload_1
       1: ldc           #12                 // String service
       3: invokestatic  #18                 // Method a/b/b/c.b:(Ljava/lang/Object;Ljava/lang/String;)V
       6: aload_0
       7: invokespecial #21                 // Method android/os/Binder."<init>":()V
      10: aload_0
      11: aload_1
      12: putfield      #23                 // Field a:Lryey/easer/core/log/ActivityLogService;
      15: return

  public final void a();
    Code:
       0: invokestatic  #27                 // Method ryey/easer/core/log/ActivityLogService.a:()Ljava/util/LinkedList;
       3: invokevirtual #32                 // Method java/util/LinkedList.clear:()V
       6: return
}
