class ryey.easer.core.ui.data.script.EditScriptActivity$2 implements android.view.View$OnClickListener {
  final ryey.easer.core.ui.data.script.EditScriptActivity a;

  ryey.easer.core.ui.data.script.EditScriptActivity$2(ryey.easer.core.ui.data.script.EditScriptActivity);
    Code:
       0: aload_0
       1: aload_1
       2: putfield      #17                 // Field a:Lryey/easer/core/ui/data/script/EditScriptActivity;
       5: aload_0
       6: invokespecial #19                 // Method java/lang/Object."<init>":()V
       9: return

  public void onClick(android.view.View);
    Code:
       0: new           #26                 // class android/content/Intent
       3: dup
       4: aload_0
       5: getfield      #17                 // Field a:Lryey/easer/core/ui/data/script/EditScriptActivity;
       8: ldc           #28                 // class ryey/easer/core/ui/data/script/ListDynamicsActivity
      10: invokespecial #31                 // Method android/content/Intent."<init>":(Landroid/content/Context;Ljava/lang/Class;)V
      13: astore_2
      14: aload_2
      15: ldc           #33                 // String ryey.easer.core.ui.data.extra.DYNAMICS_LINK
      17: aload_0
      18: getfield      #17                 // Field a:Lryey/easer/core/ui/data/script/EditScriptActivity;
      21: getfield      #37                 // Field ryey/easer/core/ui/data/script/EditScriptActivity.s:Lryey/easer/commons/local_plugin/b/b;
      24: invokevirtual #41                 // Method android/content/Intent.putExtra:(Ljava/lang/String;Landroid/os/Parcelable;)Landroid/content/Intent;
      27: pop
      28: new           #43                 // class java/util/ArrayList
      31: dup
      32: invokespecial #44                 // Method java/util/ArrayList."<init>":()V
      35: astore_1
      36: aload_0
      37: getfield      #17                 // Field a:Lryey/easer/core/ui/data/script/EditScriptActivity;
      40: getfield      #48                 // Field ryey/easer/core/ui/data/script/EditScriptActivity.h:Lryey/easer/commons/a/a;
      43: invokevirtual #54                 // Method ryey/easer/commons/a/a.c:()Ljava/lang/String;
      46: astore_3
      47: aload_3
      48: ifnull        77
      51: aload_1
      52: new           #56                 // class ryey/easer/core/a/a/d
      55: dup
      56: aload_0
      57: getfield      #17                 // Field a:Lryey/easer/core/ui/data/script/EditScriptActivity;
      60: invokespecial #59                 // Method ryey/easer/core/a/a/d."<init>":(Landroid/content/Context;)V
      63: aload_3
      64: invokevirtual #62                 // Method ryey/easer/core/a/a/d.a:(Ljava/lang/String;)Lryey/easer/core/a/f;
      67: checkcast     #64                 // class ryey/easer/core/a/g
      70: invokevirtual #68                 // Method ryey/easer/core/a/g.e:()Ljava/util/Set;
      73: invokevirtual #72                 // Method java/util/ArrayList.addAll:(Ljava/util/Collection;)Z
      76: pop
      77: aload_2
      78: ldc           #74                 // String ryey.easer.core.ui.data.extras.PLACEHOLDERS
      80: aload_1
      81: invokevirtual #78                 // Method android/content/Intent.putStringArrayListExtra:(Ljava/lang/String;Ljava/util/ArrayList;)Landroid/content/Intent;
      84: pop
      85: aload_0
      86: getfield      #17                 // Field a:Lryey/easer/core/ui/data/script/EditScriptActivity;
      89: getfield      #82                 // Field ryey/easer/core/ui/data/script/EditScriptActivity.j:Landroid/widget/RadioGroup;
      92: invokevirtual #88                 // Method android/widget/RadioGroup.getCheckedRadioButtonId:()I
      95: ldc           #89                 // int 2131296531
      97: if_icmpne     131
     100: aload_0
     101: getfield      #17                 // Field a:Lryey/easer/core/ui/data/script/EditScriptActivity;
     104: getfield      #92                 // Field ryey/easer/core/ui/data/script/EditScriptActivity.e:Lryey/easer/core/ui/data/event/EventPluginViewPager;
     107: invokevirtual #98                 // Method ryey/easer/core/ui/data/event/EventPluginViewPager.getEventData:()Lryey/easer/commons/local_plugin/eventplugin/EventData;
     110: astore_1
     111: aload_2
     112: ldc           #100                // String ryey.easer.core.ui.data.extra.PLUGIN_TYPE
     114: ldc           #102                // String event
     116: invokevirtual #105                // Method android/content/Intent.putExtra:(Ljava/lang/String;Ljava/lang/String;)Landroid/content/Intent;
     119: pop
     120: aload_2
     121: ldc           #107                // String ryey.easer.core.ui.data.extra.PLUGIN_DATA
     123: aload_1
     124: invokevirtual #41                 // Method android/content/Intent.putExtra:(Ljava/lang/String;Landroid/os/Parcelable;)Landroid/content/Intent;
     127: pop
     128: goto          226
     131: aload_0
     132: getfield      #17                 // Field a:Lryey/easer/core/ui/data/script/EditScriptActivity;
     135: getfield      #82                 // Field ryey/easer/core/ui/data/script/EditScriptActivity.j:Landroid/widget/RadioGroup;
     138: invokevirtual #88                 // Method android/widget/RadioGroup.getCheckedRadioButtonId:()I
     141: ldc           #108                // int 2131296549
     143: if_icmpne     205
     146: new           #110                // class ryey/easer/core/a/a/c
     149: dup
     150: aload_0
     151: getfield      #17                 // Field a:Lryey/easer/core/ui/data/script/EditScriptActivity;
     154: invokespecial #111                // Method ryey/easer/core/a/a/c."<init>":(Landroid/content/Context;)V
     157: astore_1
     158: aload_0
     159: getfield      #17                 // Field a:Lryey/easer/core/ui/data/script/EditScriptActivity;
     162: getfield      #114                // Field ryey/easer/core/ui/data/script/EditScriptActivity.m:Lryey/easer/commons/a/a;
     165: invokevirtual #54                 // Method ryey/easer/commons/a/a.c:()Ljava/lang/String;
     168: astore_3
     169: aload_3
     170: ifnull        254
     173: aload_2
     174: ldc           #107                // String ryey.easer.core.ui.data.extra.PLUGIN_DATA
     176: aload_1
     177: aload_3
     178: invokevirtual #115                // Method ryey/easer/core/a/a/c.a:(Ljava/lang/String;)Lryey/easer/core/a/f;
     181: checkcast     #117                // class ryey/easer/core/a/c
     184: invokevirtual #119                // Method ryey/easer/core/a/c.c:()Lryey/easer/commons/local_plugin/eventplugin/EventData;
     187: invokevirtual #41                 // Method android/content/Intent.putExtra:(Ljava/lang/String;Landroid/os/Parcelable;)Landroid/content/Intent;
     190: pop
     191: goto          254
     194: aload_2
     195: ldc           #100                // String ryey.easer.core.ui.data.extra.PLUGIN_TYPE
     197: aload_1
     198: invokevirtual #105                // Method android/content/Intent.putExtra:(Ljava/lang/String;Ljava/lang/String;)Landroid/content/Intent;
     201: pop
     202: goto          226
     205: aload_0
     206: getfield      #17                 // Field a:Lryey/easer/core/ui/data/script/EditScriptActivity;
     209: getfield      #82                 // Field ryey/easer/core/ui/data/script/EditScriptActivity.j:Landroid/widget/RadioGroup;
     212: invokevirtual #88                 // Method android/widget/RadioGroup.getCheckedRadioButtonId:()I
     215: ldc           #120                // int 2131296524
     217: if_icmpne     226
     220: ldc           #122                // String condition
     222: astore_1
     223: goto          194
     226: aload_0
     227: getfield      #17                 // Field a:Lryey/easer/core/ui/data/script/EditScriptActivity;
     230: aload_2
     231: iconst_1
     232: invokevirtual #126                // Method ryey/easer/core/ui/data/script/EditScriptActivity.startActivityForResult:(Landroid/content/Intent;I)V
     235: return
     236: aload_0
     237: getfield      #17                 // Field a:Lryey/easer/core/ui/data/script/EditScriptActivity;
     240: ldc           #127                // int 2131624239
     242: iconst_1
     243: invokestatic  #133                // Method android/widget/Toast.makeText:(Landroid/content/Context;II)Landroid/widget/Toast;
     246: invokevirtual #136                // Method android/widget/Toast.show:()V
     249: return
     250: astore_1
     251: goto          236
     254: ldc           #102                // String event
     256: astore_1
     257: goto          194
    Exception table:
       from    to  target type
          85   128   250   Class ryey/easer/commons/local_plugin/c
         131   169   250   Class ryey/easer/commons/local_plugin/c
         173   191   250   Class ryey/easer/commons/local_plugin/c
         194   202   250   Class ryey/easer/commons/local_plugin/c
         205   220   250   Class ryey/easer/commons/local_plugin/c
         226   235   250   Class ryey/easer/commons/local_plugin/c
}
