class ryey.easer.core.ui.data.script.EditScriptActivity$1 implements android.widget.RadioGroup$OnCheckedChangeListener {
  final ryey.easer.core.ui.data.script.EditScriptActivity a;

  ryey.easer.core.ui.data.script.EditScriptActivity$1(ryey.easer.core.ui.data.script.EditScriptActivity);
    Code:
       0: aload_0
       1: aload_1
       2: putfield      #17                 // Field a:Lryey/easer/core/ui/data/script/EditScriptActivity;
       5: aload_0
       6: invokespecial #19                 // Method java/lang/Object."<init>":()V
       9: return

  public void onCheckedChanged(android.widget.RadioGroup, int);
    Code:
       0: iconst_0
       1: istore_3
       2: bipush        8
       4: istore        4
       6: iload_2
       7: ldc           #23                 // int 2131296531
       9: if_icmpne     24
      12: bipush        8
      14: istore_2
      15: bipush        8
      17: istore_3
      18: iconst_0
      19: istore        4
      21: goto          53
      24: iload_2
      25: ldc           #24                 // int 2131296549
      27: if_icmpne     42
      30: bipush        8
      32: istore        5
      34: iload_3
      35: istore_2
      36: iload         5
      38: istore_3
      39: goto          53
      42: iload_2
      43: ldc           #25                 // int 2131296524
      45: if_icmpne     88
      48: bipush        8
      50: istore_2
      51: iconst_0
      52: istore_3
      53: aload_0
      54: getfield      #17                 // Field a:Lryey/easer/core/ui/data/script/EditScriptActivity;
      57: getfield      #29                 // Field ryey/easer/core/ui/data/script/EditScriptActivity.e:Lryey/easer/core/ui/data/event/EventPluginViewPager;
      60: iload         4
      62: invokevirtual #35                 // Method ryey/easer/core/ui/data/event/EventPluginViewPager.setVisibility:(I)V
      65: aload_0
      66: getfield      #17                 // Field a:Lryey/easer/core/ui/data/script/EditScriptActivity;
      69: getfield      #39                 // Field ryey/easer/core/ui/data/script/EditScriptActivity.l:Landroid/support/constraint/ConstraintLayout;
      72: iload_2
      73: invokevirtual #42                 // Method android/support/constraint/ConstraintLayout.setVisibility:(I)V
      76: aload_0
      77: getfield      #17                 // Field a:Lryey/easer/core/ui/data/script/EditScriptActivity;
      80: getfield      #45                 // Field ryey/easer/core/ui/data/script/EditScriptActivity.p:Landroid/support/constraint/ConstraintLayout;
      83: iload_3
      84: invokevirtual #42                 // Method android/support/constraint/ConstraintLayout.setVisibility:(I)V
      87: return
      88: new           #47                 // class java/lang/IllegalAccessError
      91: dup
      92: invokespecial #48                 // Method java/lang/IllegalAccessError."<init>":()V
      95: athrow
}
