public class ryey.easer.core.ui.data.script.EditScriptActivity extends ryey.easer.core.ui.data.b<ryey.easer.core.a.j, ryey.easer.core.a.a.e> {
  ryey.easer.core.ui.data.event.EventPluginViewPager e;

  android.widget.EditText f;

  ryey.easer.commons.a.a g;

  ryey.easer.commons.a.a h;

  boolean i;

  android.widget.RadioGroup j;

  android.widget.CompoundButton k;

  android.support.constraint.ConstraintLayout l;

  ryey.easer.commons.a.a m;

  android.widget.CompoundButton n;

  android.widget.CompoundButton o;

  android.support.constraint.ConstraintLayout p;

  ryey.easer.commons.a.a q;

  android.widget.ImageButton r;

  ryey.easer.commons.local_plugin.b.b s;

  static {};
    Code:
       0: ldc           #37                 // String script
       2: putstatic     #41                 // Field a:Ljava/lang/String;
       5: return

  public ryey.easer.core.ui.data.script.EditScriptActivity();
    Code:
       0: aload_0
       1: invokespecial #45                 // Method ryey/easer/core/ui/data/b."<init>":()V
       4: aload_0
       5: aconst_null
       6: putfield      #47                 // Field f:Landroid/widget/EditText;
       9: aload_0
      10: iconst_1
      11: putfield      #49                 // Field i:Z
      14: return

  protected ryey.easer.core.a.a.a a();
    Code:
       0: aload_0
       1: invokevirtual #53                 // Method g:()Lryey/easer/core/a/a/e;
       4: areturn

  protected void a(ryey.easer.core.a.f);
    Code:
       0: aload_0
       1: aload_1
       2: checkcast     #56                 // class ryey/easer/core/a/j
       5: invokevirtual #59                 // Method a:(Lryey/easer/core/a/j;)V
       8: return

  protected void a(ryey.easer.core.a.j);
    Code:
       0: aload_0
       1: aload_1
       2: invokevirtual #62                 // Method ryey/easer/core/a/j.a:()Ljava/lang/String;
       5: putfield      #65                 // Field d:Ljava/lang/String;
       8: aload_0
       9: getfield      #47                 // Field f:Landroid/widget/EditText;
      12: aload_0
      13: getfield      #65                 // Field d:Ljava/lang/String;
      16: invokevirtual #71                 // Method android/widget/EditText.setText:(Ljava/lang/CharSequence;)V
      19: aload_1
      20: invokevirtual #73                 // Method ryey/easer/core/a/j.i:()Ljava/lang/String;
      23: astore_2
      24: aload_0
      25: getfield      #75                 // Field h:Lryey/easer/commons/a/a;
      28: aload_2
      29: invokevirtual #80                 // Method ryey/easer/commons/a/a.a:(Ljava/lang/String;)V
      32: aload_1
      33: invokevirtual #82                 // Method ryey/easer/core/a/j.j:()Ljava/lang/String;
      36: astore_2
      37: aload_0
      38: getfield      #84                 // Field g:Lryey/easer/commons/a/a;
      41: aload_2
      42: invokevirtual #80                 // Method ryey/easer/commons/a/a.a:(Ljava/lang/String;)V
      45: aload_0
      46: getfield      #86                 // Field k:Landroid/widget/CompoundButton;
      49: aload_1
      50: invokevirtual #89                 // Method ryey/easer/core/a/j.m:()Z
      53: invokevirtual #95                 // Method android/widget/CompoundButton.setChecked:(Z)V
      56: aload_1
      57: invokevirtual #98                 // Method ryey/easer/core/a/j.c:()Z
      60: ifeq          145
      63: aload_1
      64: invokevirtual #101                // Method ryey/easer/core/a/j.e:()Lryey/easer/core/a/c;
      67: astore_2
      68: aload_2
      69: invokevirtual #105                // Method ryey/easer/core/a/c.e:()Z
      72: ifeq          100
      75: aload_0
      76: getfield      #107                // Field j:Landroid/widget/RadioGroup;
      79: ldc           #108                // int 2131296531
      81: invokevirtual #114                // Method android/widget/RadioGroup.check:(I)V
      84: aload_2
      85: invokevirtual #117                // Method ryey/easer/core/a/c.c:()Lryey/easer/commons/local_plugin/eventplugin/EventData;
      88: astore_2
      89: aload_0
      90: getfield      #119                // Field e:Lryey/easer/core/ui/data/event/EventPluginViewPager;
      93: aload_2
      94: invokevirtual #125                // Method ryey/easer/core/ui/data/event/EventPluginViewPager.setEventData:(Lryey/easer/commons/local_plugin/eventplugin/EventData;)V
      97: goto          170
     100: aload_0
     101: getfield      #107                // Field j:Landroid/widget/RadioGroup;
     104: ldc           #126                // int 2131296549
     106: invokevirtual #114                // Method android/widget/RadioGroup.check:(I)V
     109: aload_0
     110: getfield      #128                // Field m:Lryey/easer/commons/a/a;
     113: aload_2
     114: invokevirtual #129                // Method ryey/easer/core/a/c.a:()Ljava/lang/String;
     117: invokevirtual #80                 // Method ryey/easer/commons/a/a.a:(Ljava/lang/String;)V
     120: aload_0
     121: getfield      #131                // Field n:Landroid/widget/CompoundButton;
     124: aload_1
     125: invokevirtual #133                // Method ryey/easer/core/a/j.k:()Z
     128: invokevirtual #95                 // Method android/widget/CompoundButton.setChecked:(Z)V
     131: aload_0
     132: getfield      #135                // Field o:Landroid/widget/CompoundButton;
     135: aload_1
     136: invokevirtual #137                // Method ryey/easer/core/a/j.l:()Z
     139: invokevirtual #95                 // Method android/widget/CompoundButton.setChecked:(Z)V
     142: goto          170
     145: aload_0
     146: getfield      #107                // Field j:Landroid/widget/RadioGroup;
     149: ldc           #138                // int 2131296524
     151: invokevirtual #114                // Method android/widget/RadioGroup.check:(I)V
     154: aload_1
     155: invokevirtual #141                // Method ryey/easer/core/a/j.g:()Lryey/easer/core/a/b;
     158: astore_2
     159: aload_0
     160: getfield      #143                // Field q:Lryey/easer/commons/a/a;
     163: aload_2
     164: invokevirtual #146                // Method ryey/easer/core/a/b.a:()Ljava/lang/String;
     167: invokevirtual #80                 // Method ryey/easer/commons/a/a.a:(Ljava/lang/String;)V
     170: aload_0
     171: aload_1
     172: invokevirtual #148                // Method ryey/easer/core/a/j.h:()Z
     175: putfield      #49                 // Field i:Z
     178: aload_0
     179: aload_1
     180: invokevirtual #151                // Method ryey/easer/core/a/j.n:()Lryey/easer/commons/local_plugin/b/b;
     183: putfield      #153                // Field s:Lryey/easer/commons/local_plugin/b/b;
     186: return

  protected java.lang.String b();
    Code:
       0: aload_0
       1: ldc           #155                // int 2131624312
       3: invokevirtual #159                // Method getString:(I)Ljava/lang/String;
       6: areturn

  protected int c();
    Code:
       0: ldc           #161                // int 2131427361
       2: ireturn

  protected void d();
    Code:
       0: aload_0
       1: aload_0
       2: ldc           #162                // int 2131296395
       4: invokevirtual #166                // Method findViewById:(I)Landroid/view/View;
       7: checkcast     #67                 // class android/widget/EditText
      10: putfield      #47                 // Field f:Landroid/widget/EditText;
      13: aload_0
      14: new           #77                 // class ryey/easer/commons/a/a
      17: dup
      18: aload_0
      19: aload_0
      20: ldc           #167                // int 2131296627
      22: invokevirtual #166                // Method findViewById:(I)Landroid/view/View;
      25: checkcast     #169                // class android/widget/Spinner
      28: invokespecial #172                // Method ryey/easer/commons/a/a."<init>":(Landroid/content/Context;Landroid/widget/Spinner;)V
      31: putfield      #84                 // Field g:Lryey/easer/commons/a/a;
      34: aload_0
      35: getfield      #84                 // Field g:Lryey/easer/commons/a/a;
      38: invokevirtual #175                // Method ryey/easer/commons/a/a.a:()Lryey/easer/commons/a/a;
      41: iconst_1
      42: invokevirtual #178                // Method ryey/easer/commons/a/a.a:(Z)Lryey/easer/commons/a/a;
      45: new           #180                // class ryey/easer/core/a/a/e
      48: dup
      49: aload_0
      50: invokespecial #183                // Method ryey/easer/core/a/a/e."<init>":(Landroid/content/Context;)V
      53: invokevirtual #186                // Method ryey/easer/core/a/a/e.a:()Ljava/util/List;
      56: invokevirtual #189                // Method ryey/easer/commons/a/a.a:(Ljava/util/List;)Lryey/easer/commons/a/a;
      59: invokevirtual #191                // Method ryey/easer/commons/a/a.b:()V
      62: aload_0
      63: new           #77                 // class ryey/easer/commons/a/a
      66: dup
      67: aload_0
      68: aload_0
      69: ldc           #192                // int 2131296629
      71: invokevirtual #166                // Method findViewById:(I)Landroid/view/View;
      74: checkcast     #169                // class android/widget/Spinner
      77: invokespecial #172                // Method ryey/easer/commons/a/a."<init>":(Landroid/content/Context;Landroid/widget/Spinner;)V
      80: putfield      #75                 // Field h:Lryey/easer/commons/a/a;
      83: aload_0
      84: getfield      #75                 // Field h:Lryey/easer/commons/a/a;
      87: invokevirtual #175                // Method ryey/easer/commons/a/a.a:()Lryey/easer/commons/a/a;
      90: iconst_1
      91: invokevirtual #178                // Method ryey/easer/commons/a/a.a:(Z)Lryey/easer/commons/a/a;
      94: new           #194                // class ryey/easer/core/a/a/d
      97: dup
      98: aload_0
      99: invokespecial #195                // Method ryey/easer/core/a/a/d."<init>":(Landroid/content/Context;)V
     102: invokevirtual #196                // Method ryey/easer/core/a/a/d.a:()Ljava/util/List;
     105: invokevirtual #189                // Method ryey/easer/commons/a/a.a:(Ljava/util/List;)Lryey/easer/commons/a/a;
     108: invokevirtual #191                // Method ryey/easer/commons/a/a.b:()V
     111: aload_0
     112: aload_0
     113: ldc           #197                // int 2131296645
     115: invokevirtual #166                // Method findViewById:(I)Landroid/view/View;
     118: checkcast     #91                 // class android/widget/CompoundButton
     121: putfield      #86                 // Field k:Landroid/widget/CompoundButton;
     124: aload_0
     125: aload_0
     126: ldc           #198                // int 2131296506
     128: invokevirtual #166                // Method findViewById:(I)Landroid/view/View;
     131: checkcast     #121                // class ryey/easer/core/ui/data/event/EventPluginViewPager
     134: putfield      #119                // Field e:Lryey/easer/core/ui/data/event/EventPluginViewPager;
     137: aload_0
     138: getfield      #119                // Field e:Lryey/easer/core/ui/data/event/EventPluginViewPager;
     141: aload_0
     142: invokevirtual #201                // Method ryey/easer/core/ui/data/event/EventPluginViewPager.a:(Landroid/support/v7/app/e;)V
     145: aload_0
     146: aload_0
     147: ldc           #202                // int 2131296463
     149: invokevirtual #166                // Method findViewById:(I)Landroid/view/View;
     152: checkcast     #204                // class android/support/constraint/ConstraintLayout
     155: putfield      #206                // Field l:Landroid/support/constraint/ConstraintLayout;
     158: aload_0
     159: new           #77                 // class ryey/easer/commons/a/a
     162: dup
     163: aload_0
     164: aload_0
     165: ldc           #207                // int 2131296630
     167: invokevirtual #166                // Method findViewById:(I)Landroid/view/View;
     170: checkcast     #169                // class android/widget/Spinner
     173: invokespecial #172                // Method ryey/easer/commons/a/a."<init>":(Landroid/content/Context;Landroid/widget/Spinner;)V
     176: putfield      #128                // Field m:Lryey/easer/commons/a/a;
     179: aload_0
     180: getfield      #128                // Field m:Lryey/easer/commons/a/a;
     183: invokevirtual #175                // Method ryey/easer/commons/a/a.a:()Lryey/easer/commons/a/a;
     186: iconst_0
     187: invokevirtual #178                // Method ryey/easer/commons/a/a.a:(Z)Lryey/easer/commons/a/a;
     190: new           #209                // class ryey/easer/core/a/a/c
     193: dup
     194: aload_0
     195: invokespecial #210                // Method ryey/easer/core/a/a/c."<init>":(Landroid/content/Context;)V
     198: invokevirtual #211                // Method ryey/easer/core/a/a/c.a:()Ljava/util/List;
     201: invokevirtual #189                // Method ryey/easer/commons/a/a.a:(Ljava/util/List;)Lryey/easer/commons/a/a;
     204: invokevirtual #191                // Method ryey/easer/commons/a/a.b:()V
     207: aload_0
     208: aload_0
     209: ldc           #212                // int 2131296644
     211: invokevirtual #166                // Method findViewById:(I)Landroid/view/View;
     214: checkcast     #91                 // class android/widget/CompoundButton
     217: putfield      #131                // Field n:Landroid/widget/CompoundButton;
     220: aload_0
     221: aload_0
     222: ldc           #213                // int 2131296643
     224: invokevirtual #166                // Method findViewById:(I)Landroid/view/View;
     227: checkcast     #91                 // class android/widget/CompoundButton
     230: putfield      #135                // Field o:Landroid/widget/CompoundButton;
     233: aload_0
     234: aload_0
     235: ldc           #214                // int 2131296462
     237: invokevirtual #166                // Method findViewById:(I)Landroid/view/View;
     240: checkcast     #204                // class android/support/constraint/ConstraintLayout
     243: putfield      #216                // Field p:Landroid/support/constraint/ConstraintLayout;
     246: aload_0
     247: new           #77                 // class ryey/easer/commons/a/a
     250: dup
     251: aload_0
     252: aload_0
     253: ldc           #217                // int 2131296624
     255: invokevirtual #166                // Method findViewById:(I)Landroid/view/View;
     258: checkcast     #169                // class android/widget/Spinner
     261: invokespecial #172                // Method ryey/easer/commons/a/a."<init>":(Landroid/content/Context;Landroid/widget/Spinner;)V
     264: putfield      #143                // Field q:Lryey/easer/commons/a/a;
     267: aload_0
     268: getfield      #143                // Field q:Lryey/easer/commons/a/a;
     271: invokevirtual #175                // Method ryey/easer/commons/a/a.a:()Lryey/easer/commons/a/a;
     274: iconst_0
     275: invokevirtual #178                // Method ryey/easer/commons/a/a.a:(Z)Lryey/easer/commons/a/a;
     278: new           #219                // class ryey/easer/core/a/a/b
     281: dup
     282: aload_0
     283: invokespecial #220                // Method ryey/easer/core/a/a/b."<init>":(Landroid/content/Context;)V
     286: invokevirtual #221                // Method ryey/easer/core/a/a/b.a:()Ljava/util/List;
     289: invokevirtual #189                // Method ryey/easer/commons/a/a.a:(Ljava/util/List;)Lryey/easer/commons/a/a;
     292: invokevirtual #191                // Method ryey/easer/commons/a/a.b:()V
     295: aload_0
     296: aload_0
     297: ldc           #222                // int 2131296581
     299: invokevirtual #166                // Method findViewById:(I)Landroid/view/View;
     302: checkcast     #110                // class android/widget/RadioGroup
     305: putfield      #107                // Field j:Landroid/widget/RadioGroup;
     308: aload_0
     309: getfield      #107                // Field j:Landroid/widget/RadioGroup;
     312: new           #7                  // class ryey/easer/core/ui/data/script/EditScriptActivity$1
     315: dup
     316: aload_0
     317: invokespecial #225                // Method ryey/easer/core/ui/data/script/EditScriptActivity$1."<init>":(Lryey/easer/core/ui/data/script/EditScriptActivity;)V
     320: invokevirtual #229                // Method android/widget/RadioGroup.setOnCheckedChangeListener:(Landroid/widget/RadioGroup$OnCheckedChangeListener;)V
     323: aload_0
     324: getfield      #107                // Field j:Landroid/widget/RadioGroup;
     327: ldc           #138                // int 2131296524
     329: invokevirtual #114                // Method android/widget/RadioGroup.check:(I)V
     332: aload_0
     333: getfield      #107                // Field j:Landroid/widget/RadioGroup;
     336: ldc           #126                // int 2131296549
     338: invokevirtual #114                // Method android/widget/RadioGroup.check:(I)V
     341: aload_0
     342: aload_0
     343: ldc           #230                // int 2131296308
     345: invokevirtual #166                // Method findViewById:(I)Landroid/view/View;
     348: checkcast     #232                // class android/widget/ImageButton
     351: putfield      #234                // Field r:Landroid/widget/ImageButton;
     354: aload_0
     355: getfield      #234                // Field r:Landroid/widget/ImageButton;
     358: new           #9                  // class ryey/easer/core/ui/data/script/EditScriptActivity$2
     361: dup
     362: aload_0
     363: invokespecial #235                // Method ryey/easer/core/ui/data/script/EditScriptActivity$2."<init>":(Lryey/easer/core/ui/data/script/EditScriptActivity;)V
     366: invokevirtual #239                // Method android/widget/ImageButton.setOnClickListener:(Landroid/view/View$OnClickListener;)V
     369: return

  protected ryey.easer.core.a.f e();
    Code:
       0: aload_0
       1: invokevirtual #243                // Method h:()Lryey/easer/core/a/j;
       4: areturn

  protected ryey.easer.core.a.a.e g();
    Code:
       0: new           #180                // class ryey/easer/core/a/a/e
       3: dup
       4: aload_0
       5: invokespecial #183                // Method ryey/easer/core/a/a/e."<init>":(Landroid/content/Context;)V
       8: areturn

  protected ryey.easer.core.a.j h();
    Code:
       0: new           #56                 // class ryey/easer/core/a/j
       3: dup
       4: iconst_m1
       5: invokespecial #245                // Method ryey/easer/core/a/j."<init>":(I)V
       8: astore_1
       9: aload_1
      10: aload_0
      11: getfield      #47                 // Field f:Landroid/widget/EditText;
      14: invokevirtual #249                // Method android/widget/EditText.getText:()Landroid/text/Editable;
      17: invokevirtual #254                // Method java/lang/Object.toString:()Ljava/lang/String;
      20: invokevirtual #255                // Method ryey/easer/core/a/j.a:(Ljava/lang/String;)V
      23: aload_1
      24: aload_0
      25: getfield      #75                 // Field h:Lryey/easer/commons/a/a;
      28: invokevirtual #257                // Method ryey/easer/commons/a/a.c:()Ljava/lang/String;
      31: invokevirtual #259                // Method ryey/easer/core/a/j.b:(Ljava/lang/String;)V
      34: aload_1
      35: aload_0
      36: getfield      #49                 // Field i:Z
      39: invokevirtual #261                // Method ryey/easer/core/a/j.a:(Z)V
      42: aload_1
      43: aload_0
      44: getfield      #84                 // Field g:Lryey/easer/commons/a/a;
      47: invokevirtual #257                // Method ryey/easer/commons/a/a.c:()Ljava/lang/String;
      50: invokevirtual #263                // Method ryey/easer/core/a/j.c:(Ljava/lang/String;)V
      53: aload_1
      54: aload_0
      55: getfield      #86                 // Field k:Landroid/widget/CompoundButton;
      58: invokevirtual #266                // Method android/widget/CompoundButton.isChecked:()Z
      61: invokevirtual #268                // Method ryey/easer/core/a/j.d:(Z)V
      64: aload_0
      65: getfield      #107                // Field j:Landroid/widget/RadioGroup;
      68: invokevirtual #271                // Method android/widget/RadioGroup.getCheckedRadioButtonId:()I
      71: ldc           #108                // int 2131296531
      73: if_icmpne     99
      76: new           #209                // class ryey/easer/core/a/a/c
      79: dup
      80: aload_0
      81: invokespecial #210                // Method ryey/easer/core/a/a/c."<init>":(Landroid/content/Context;)V
      84: pop
      85: aload_1
      86: aload_0
      87: getfield      #119                // Field e:Lryey/easer/core/ui/data/event/EventPluginViewPager;
      90: invokevirtual #274                // Method ryey/easer/core/ui/data/event/EventPluginViewPager.getEventData:()Lryey/easer/commons/local_plugin/eventplugin/EventData;
      93: invokevirtual #276                // Method ryey/easer/core/a/j.a:(Lryey/easer/commons/local_plugin/eventplugin/EventData;)V
      96: goto          198
      99: aload_0
     100: getfield      #107                // Field j:Landroid/widget/RadioGroup;
     103: invokevirtual #271                // Method android/widget/RadioGroup.getCheckedRadioButtonId:()I
     106: ldc           #126                // int 2131296549
     108: if_icmpne     161
     111: aload_1
     112: new           #209                // class ryey/easer/core/a/a/c
     115: dup
     116: aload_0
     117: invokespecial #210                // Method ryey/easer/core/a/a/c."<init>":(Landroid/content/Context;)V
     120: aload_0
     121: getfield      #128                // Field m:Lryey/easer/commons/a/a;
     124: invokevirtual #257                // Method ryey/easer/commons/a/a.c:()Ljava/lang/String;
     127: invokevirtual #279                // Method ryey/easer/core/a/a/c.a:(Ljava/lang/String;)Lryey/easer/core/a/f;
     130: checkcast     #103                // class ryey/easer/core/a/c
     133: invokevirtual #282                // Method ryey/easer/core/a/j.a:(Lryey/easer/core/a/c;)V
     136: aload_1
     137: aload_0
     138: getfield      #131                // Field n:Landroid/widget/CompoundButton;
     141: invokevirtual #266                // Method android/widget/CompoundButton.isChecked:()Z
     144: invokevirtual #284                // Method ryey/easer/core/a/j.b:(Z)V
     147: aload_1
     148: aload_0
     149: getfield      #135                // Field o:Landroid/widget/CompoundButton;
     152: invokevirtual #266                // Method android/widget/CompoundButton.isChecked:()Z
     155: invokevirtual #286                // Method ryey/easer/core/a/j.c:(Z)V
     158: goto          198
     161: aload_0
     162: getfield      #107                // Field j:Landroid/widget/RadioGroup;
     165: invokevirtual #271                // Method android/widget/RadioGroup.getCheckedRadioButtonId:()I
     168: ldc           #138                // int 2131296524
     170: if_icmpne     198
     173: aload_1
     174: new           #219                // class ryey/easer/core/a/a/b
     177: dup
     178: aload_0
     179: invokespecial #220                // Method ryey/easer/core/a/a/b."<init>":(Landroid/content/Context;)V
     182: aload_0
     183: getfield      #143                // Field q:Lryey/easer/commons/a/a;
     186: invokevirtual #257                // Method ryey/easer/commons/a/a.c:()Ljava/lang/String;
     189: invokevirtual #287                // Method ryey/easer/core/a/a/b.a:(Ljava/lang/String;)Lryey/easer/core/a/f;
     192: checkcast     #145                // class ryey/easer/core/a/b
     195: invokevirtual #290                // Method ryey/easer/core/a/j.a:(Lryey/easer/core/a/b;)V
     198: aload_1
     199: aload_0
     200: getfield      #153                // Field s:Lryey/easer/commons/local_plugin/b/b;
     203: invokevirtual #293                // Method ryey/easer/core/a/j.a:(Lryey/easer/commons/local_plugin/b/b;)V
     206: aload_1
     207: areturn

  protected void onActivityResult(int, int, android.content.Intent);
    Code:
       0: iload_1
       1: iconst_1
       2: if_icmpne     25
       5: iload_2
       6: iconst_m1
       7: if_icmpne     32
      10: aload_0
      11: aload_3
      12: ldc_w         #297                // String ryey.easer.core.ui.data.extra.DYNAMICS_LINK
      15: invokevirtual #303                // Method android/content/Intent.getParcelableExtra:(Ljava/lang/String;)Landroid/os/Parcelable;
      18: checkcast     #305                // class ryey/easer/commons/local_plugin/b/b
      21: putfield      #153                // Field s:Lryey/easer/commons/local_plugin/b/b;
      24: return
      25: aload_0
      26: iload_1
      27: iload_2
      28: aload_3
      29: invokespecial #307                // Method ryey/easer/core/ui/data/b.onActivityResult:(IILandroid/content/Intent;)V
      32: return

  public boolean onCreateOptionsMenu(android.view.Menu);
    Code:
       0: aload_0
       1: invokevirtual #313                // Method getMenuInflater:()Landroid/view/MenuInflater;
       4: ldc_w         #314                // int 2131492867
       7: aload_1
       8: invokevirtual #320                // Method android/view/MenuInflater.inflate:(ILandroid/view/Menu;)V
      11: aload_1
      12: ldc_w         #321                // int 2131296288
      15: invokeinterface #327,  2          // InterfaceMethod android/view/Menu.findItem:(I)Landroid/view/MenuItem;
      20: aload_0
      21: getfield      #49                 // Field i:Z
      24: invokeinterface #332,  2          // InterfaceMethod android/view/MenuItem.setChecked:(Z)Landroid/view/MenuItem;
      29: pop
      30: iconst_1
      31: ireturn

  public boolean onOptionsItemSelected(android.view.MenuItem);
    Code:
       0: aload_1
       1: invokeinterface #337,  1          // InterfaceMethod android/view/MenuItem.getItemId:()I
       6: ldc_w         #321                // int 2131296288
       9: if_icmpeq     18
      12: aload_0
      13: aload_1
      14: invokespecial #339                // Method ryey/easer/core/ui/data/b.onOptionsItemSelected:(Landroid/view/MenuItem;)Z
      17: ireturn
      18: aload_0
      19: aload_1
      20: invokeinterface #340,  1          // InterfaceMethod android/view/MenuItem.isChecked:()Z
      25: iconst_1
      26: ixor
      27: putfield      #49                 // Field i:Z
      30: aload_1
      31: aload_0
      32: getfield      #49                 // Field i:Z
      35: invokeinterface #332,  2          // InterfaceMethod android/view/MenuItem.setChecked:(Z)Landroid/view/MenuItem;
      40: pop
      41: iconst_1
      42: ireturn
}
