class ryey.easer.core.ui.data.script.ListDynamicsActivity$EditDynamicsActivity$1 implements android.view.View$OnClickListener {
  final ryey.easer.core.ui.data.script.ListDynamicsActivity$EditDynamicsActivity a;

  ryey.easer.core.ui.data.script.ListDynamicsActivity$EditDynamicsActivity$1(ryey.easer.core.ui.data.script.ListDynamicsActivity$EditDynamicsActivity);
    Code:
       0: aload_0
       1: aload_1
       2: putfield      #20                 // Field a:Lryey/easer/core/ui/data/script/ListDynamicsActivity$EditDynamicsActivity;
       5: aload_0
       6: invokespecial #23                 // Method java/lang/Object."<init>":()V
       9: return

  public void onClick(android.view.View);
    Code:
       0: aload_0
       1: getfield      #20                 // Field a:Lryey/easer/core/ui/data/script/ListDynamicsActivity$EditDynamicsActivity;
       4: getfield      #39                 // Field ryey/easer/core/ui/data/script/ListDynamicsActivity$EditDynamicsActivity.a:Landroid/widget/Spinner;
       7: invokevirtual #45                 // Method android/widget/Spinner.getSelectedItem:()Ljava/lang/Object;
      10: checkcast     #47                 // class java/lang/String
      13: astore_1
      14: aload_1
      15: ifnonnull     23
      18: aload_0
      19: invokespecial #49                 // Method a:()V
      22: return
      23: aload_0
      24: getfield      #20                 // Field a:Lryey/easer/core/ui/data/script/ListDynamicsActivity$EditDynamicsActivity;
      27: getfield      #52                 // Field ryey/easer/core/ui/data/script/ListDynamicsActivity$EditDynamicsActivity.b:Landroid/widget/Spinner;
      30: invokevirtual #45                 // Method android/widget/Spinner.getSelectedItem:()Ljava/lang/Object;
      33: checkcast     #54                 // class ryey/easer/core/ui/data/script/ListDynamicsActivity$EditDynamicsActivity$a
      36: astore_2
      37: aload_2
      38: ifnonnull     46
      41: aload_0
      42: invokespecial #49                 // Method a:()V
      45: return
      46: new           #56                 // class android/content/Intent
      49: dup
      50: invokespecial #57                 // Method android/content/Intent."<init>":()V
      53: astore_3
      54: aload_3
      55: ldc           #59                 // String ryey.easer.core.ui.data.extras.LINK_ITEM
      57: new           #61                 // class ryey/easer/core/ui/data/script/ListDynamicsActivity$b
      60: dup
      61: aload_1
      62: aload_2
      63: getfield      #64                 // Field ryey/easer/core/ui/data/script/ListDynamicsActivity$EditDynamicsActivity$a.a:Ljava/lang/String;
      66: aload_2
      67: getfield      #66                 // Field ryey/easer/core/ui/data/script/ListDynamicsActivity$EditDynamicsActivity$a.b:Ljava/lang/String;
      70: invokespecial #69                 // Method ryey/easer/core/ui/data/script/ListDynamicsActivity$b."<init>":(Ljava/lang/String;Ljava/lang/String;Ljava/lang/String;)V
      73: invokevirtual #73                 // Method android/content/Intent.putExtra:(Ljava/lang/String;Landroid/os/Parcelable;)Landroid/content/Intent;
      76: pop
      77: aload_0
      78: getfield      #20                 // Field a:Lryey/easer/core/ui/data/script/ListDynamicsActivity$EditDynamicsActivity;
      81: iconst_m1
      82: aload_3
      83: invokevirtual #77                 // Method ryey/easer/core/ui/data/script/ListDynamicsActivity$EditDynamicsActivity.setResult:(ILandroid/content/Intent;)V
      86: aload_0
      87: getfield      #20                 // Field a:Lryey/easer/core/ui/data/script/ListDynamicsActivity$EditDynamicsActivity;
      90: invokevirtual #80                 // Method ryey/easer/core/ui/data/script/ListDynamicsActivity$EditDynamicsActivity.finish:()V
      93: return
}
