public class ryey.easer.core.ui.data.script.ListDynamicsActivity$EditDynamicsActivity extends android.support.v7.app.e {
  android.widget.Spinner a;

  android.widget.Spinner b;

  android.widget.ArrayAdapter<java.lang.String> c;

  android.widget.ArrayAdapter<ryey.easer.core.ui.data.script.ListDynamicsActivity$EditDynamicsActivity$a> d;

  public ryey.easer.core.ui.data.script.ListDynamicsActivity$EditDynamicsActivity();
    Code:
       0: aload_0
       1: invokespecial #23                 // Method android/support/v7/app/e."<init>":()V
       4: return

  protected void onCreate(android.os.Bundle);
    Code:
       0: aload_0
       1: aload_1
       2: invokespecial #28                 // Method android/support/v7/app/e.onCreate:(Landroid/os/Bundle;)V
       5: aload_0
       6: ldc           #29                 // int 2131427358
       8: invokevirtual #33                 // Method setContentView:(I)V
      11: aload_0
      12: aload_0
      13: ldc           #34                 // int 2131296628
      15: invokevirtual #38                 // Method findViewById:(I)Landroid/view/View;
      18: checkcast     #40                 // class android/widget/Spinner
      21: putfield      #42                 // Field a:Landroid/widget/Spinner;
      24: aload_0
      25: aload_0
      26: ldc           #43                 // int 2131296625
      28: invokevirtual #38                 // Method findViewById:(I)Landroid/view/View;
      31: checkcast     #40                 // class android/widget/Spinner
      34: putfield      #45                 // Field b:Landroid/widget/Spinner;
      37: aload_0
      38: new           #47                 // class android/widget/ArrayAdapter
      41: dup
      42: aload_0
      43: ldc           #48                 // int 2131427465
      45: aload_0
      46: invokevirtual #52                 // Method getIntent:()Landroid/content/Intent;
      49: ldc           #54                 // String ryey.easer.core.ui.data.extras.PLACEHOLDERS
      51: invokevirtual #60                 // Method android/content/Intent.getStringArrayListExtra:(Ljava/lang/String;)Ljava/util/ArrayList;
      54: invokespecial #63                 // Method android/widget/ArrayAdapter."<init>":(Landroid/content/Context;ILjava/util/List;)V
      57: putfield      #65                 // Field c:Landroid/widget/ArrayAdapter;
      60: aload_0
      61: getfield      #42                 // Field a:Landroid/widget/Spinner;
      64: aload_0
      65: getfield      #65                 // Field c:Landroid/widget/ArrayAdapter;
      68: invokevirtual #69                 // Method android/widget/Spinner.setAdapter:(Landroid/widget/SpinnerAdapter;)V
      71: new           #71                 // class java/util/ArrayList
      74: dup
      75: invokespecial #72                 // Method java/util/ArrayList."<init>":()V
      78: astore_2
      79: aload_2
      80: invokestatic  #77                 // Method ryey/easer/core/b/a.a:()[Lryey/easer/core/b/b;
      83: invokestatic  #83                 // Method java/util/Arrays.asList:([Ljava/lang/Object;)Ljava/util/List;
      86: invokeinterface #89,  2           // InterfaceMethod java/util/List.addAll:(Ljava/util/Collection;)Z
      91: pop
      92: ldc           #91                 // String event
      94: aload_0
      95: invokevirtual #52                 // Method getIntent:()Landroid/content/Intent;
      98: ldc           #93                 // String ryey.easer.core.ui.data.extra.PLUGIN_TYPE
     100: invokevirtual #97                 // Method android/content/Intent.getStringExtra:(Ljava/lang/String;)Ljava/lang/String;
     103: invokevirtual #103                // Method java/lang/String.equals:(Ljava/lang/Object;)Z
     106: ifeq          142
     109: aload_0
     110: invokevirtual #52                 // Method getIntent:()Landroid/content/Intent;
     113: ldc           #105                // String ryey.easer.core.ui.data.extra.PLUGIN_DATA
     115: invokevirtual #109                // Method android/content/Intent.getParcelableExtra:(Ljava/lang/String;)Landroid/os/Parcelable;
     118: checkcast     #111                // class ryey/easer/commons/local_plugin/eventplugin/EventData
     121: invokeinterface #115,  1          // InterfaceMethod ryey/easer/commons/local_plugin/eventplugin/EventData.dynamics:()[Lryey/easer/commons/local_plugin/b/a;
     126: astore_1
     127: aload_1
     128: ifnull        142
     131: aload_2
     132: aload_1
     133: invokestatic  #83                 // Method java/util/Arrays.asList:([Ljava/lang/Object;)Ljava/util/List;
     136: invokeinterface #89,  2           // InterfaceMethod java/util/List.addAll:(Ljava/util/Collection;)Z
     141: pop
     142: new           #71                 // class java/util/ArrayList
     145: dup
     146: invokespecial #72                 // Method java/util/ArrayList."<init>":()V
     149: astore_1
     150: aload_2
     151: invokeinterface #119,  1          // InterfaceMethod java/util/List.iterator:()Ljava/util/Iterator;
     156: astore_2
     157: aload_2
     158: invokeinterface #125,  1          // InterfaceMethod java/util/Iterator.hasNext:()Z
     163: ifeq          209
     166: aload_2
     167: invokeinterface #129,  1          // InterfaceMethod java/util/Iterator.next:()Ljava/lang/Object;
     172: checkcast     #131                // class ryey/easer/commons/local_plugin/b/a
     175: astore_3
     176: aload_1
     177: new           #11                 // class ryey/easer/core/ui/data/script/ListDynamicsActivity$EditDynamicsActivity$a
     180: dup
     181: aload_3
     182: invokeinterface #134,  1          // InterfaceMethod ryey/easer/commons/local_plugin/b/a.a:()Ljava/lang/String;
     187: aload_0
     188: aload_3
     189: invokeinterface #137,  1          // InterfaceMethod ryey/easer/commons/local_plugin/b/a.b:()I
     194: invokevirtual #141                // Method getString:(I)Ljava/lang/String;
     197: invokespecial #144                // Method ryey/easer/core/ui/data/script/ListDynamicsActivity$EditDynamicsActivity$a."<init>":(Ljava/lang/String;Ljava/lang/String;)V
     200: invokeinterface #147,  2          // InterfaceMethod java/util/List.add:(Ljava/lang/Object;)Z
     205: pop
     206: goto          157
     209: aload_0
     210: new           #47                 // class android/widget/ArrayAdapter
     213: dup
     214: aload_0
     215: ldc           #48                 // int 2131427465
     217: aload_1
     218: invokespecial #63                 // Method android/widget/ArrayAdapter."<init>":(Landroid/content/Context;ILjava/util/List;)V
     221: putfield      #149                // Field d:Landroid/widget/ArrayAdapter;
     224: aload_0
     225: getfield      #45                 // Field b:Landroid/widget/Spinner;
     228: aload_0
     229: getfield      #149                // Field d:Landroid/widget/ArrayAdapter;
     232: invokevirtual #69                 // Method android/widget/Spinner.setAdapter:(Landroid/widget/SpinnerAdapter;)V
     235: aload_0
     236: ldc           #150                // int 2131296309
     238: invokevirtual #38                 // Method findViewById:(I)Landroid/view/View;
     241: checkcast     #152                // class android/widget/Button
     244: new           #9                  // class ryey/easer/core/ui/data/script/ListDynamicsActivity$EditDynamicsActivity$1
     247: dup
     248: aload_0
     249: invokespecial #155                // Method ryey/easer/core/ui/data/script/ListDynamicsActivity$EditDynamicsActivity$1."<init>":(Lryey/easer/core/ui/data/script/ListDynamicsActivity$EditDynamicsActivity;)V
     252: invokevirtual #159                // Method android/widget/Button.setOnClickListener:(Landroid/view/View$OnClickListener;)V
     255: return
}
