final class com.c.a.f$e {
  public com.c.a.f$e();
    Code:
       0: aload_0
       1: invokespecial #17                 // Method java/lang/Object."<init>":()V
       4: return

  public final int a();
    Code:
       0: aload_0
       1: getfield      #21                 // Field a:I
       4: ireturn

  public final void a(int);
    Code:
       0: aload_0
       1: iload_1
       2: putfield      #21                 // Field a:I
       5: return

  public final void a(boolean);
    Code:
       0: aload_0
       1: iload_1
       2: putfield      #25                 // Field d:Z
       5: return

  public final int b();
    Code:
       0: aload_0
       1: getfield      #27                 // Field b:I
       4: ireturn

  public final void b(int);
    Code:
       0: aload_0
       1: iload_1
       2: putfield      #27                 // Field b:I
       5: return

  public final int c();
    Code:
       0: aload_0
       1: getfield      #29                 // Field c:I
       4: ireturn

  public final void c(int);
    Code:
       0: aload_0
       1: iload_1
       2: putfield      #29                 // Field c:I
       5: return

  public final boolean d();
    Code:
       0: aload_0
       1: getfield      #25                 // Field d:Z
       4: ireturn
}
