public final class com.c.a.f$k extends android.animation.AnimatorListenerAdapter {
  final com.c.a.f a;

  com.c.a.f$k();
    Code:
       0: aload_0
       1: aload_1
       2: putfield      #14                 // Field a:Lcom/c/a/f;
       5: aload_0
       6: invokespecial #17                 // Method android/animation/AnimatorListenerAdapter."<init>":()V
       9: return

  public void onAnimationCancel(android.animation.Animator);
    Code:
       0: aload_0
       1: getfield      #14                 // Field a:Lcom/c/a/f;
       4: iconst_0
       5: invokestatic  #24                 // Method com/c/a/f.a:(Lcom/c/a/f;I)Z
       8: pop
       9: return

  public void onAnimationEnd(android.animation.Animator);
    Code:
       0: aload_0
       1: getfield      #14                 // Field a:Lcom/c/a/f;
       4: iconst_0
       5: invokestatic  #24                 // Method com/c/a/f.a:(Lcom/c/a/f;I)Z
       8: pop
       9: return
}
