public final class com.c.a.h$a {
  public com.c.a.h$a(a.b.b.a);
    Code:
       0: aload_0
       1: invokespecial #14                 // Method "<init>":()V
       4: return

  public final com.c.a.h a(java.lang.String);
    Code:
       0: aload_1
       1: ldc           #17                 // String tag
       3: invokestatic  #23                 // Method a/b/b/c.b:(Ljava/lang/Object;Ljava/lang/String;)V
       6: new           #6                  // class com/c/a/h
       9: dup
      10: aload_1
      11: aconst_null
      12: invokespecial #26                 // Method com/c/a/h."<init>":(Ljava/lang/String;La/b/b/a;)V
      15: areturn
}
