public class ryey.easer.plugins.event.e.a extends ryey.easer.plugins.event.a {
  public static final android.os.Parcelable$Creator<ryey.easer.plugins.event.e.a> CREATOR;

  static {};
    Code:
       0: new           #6                  // class ryey/easer/plugins/event/e/a$1
       3: dup
       4: invokespecial #21                 // Method ryey/easer/plugins/event/e/a$1."<init>":()V
       7: putstatic     #23                 // Field CREATOR:Landroid/os/Parcelable$Creator;
      10: return

  public ryey.easer.plugins.event.e.a();
    Code:
       0: aload_0
       1: invokespecial #25                 // Method ryey/easer/plugins/event/a."<init>":()V
       4: aload_0
       5: new           #27                 // class java/util/ArrayList
       8: dup
       9: invokespecial #28                 // Method java/util/ArrayList."<init>":()V
      12: putfield      #30                 // Field a:Ljava/util/List;
      15: return

  ryey.easer.plugins.event.e.a(android.os.Parcel, ryey.easer.plugins.event.e.a$1);
    Code:
       0: aload_0
       1: aload_1
       2: invokespecial #48                 // Method "<init>":(Landroid/os/Parcel;)V
       5: return

  ryey.easer.plugins.event.e.a(java.lang.String, ryey.easer.b.a, int);
    Code:
       0: aload_0
       1: invokespecial #25                 // Method ryey/easer/plugins/event/a."<init>":()V
       4: aload_0
       5: new           #27                 // class java/util/ArrayList
       8: dup
       9: invokespecial #28                 // Method java/util/ArrayList."<init>":()V
      12: putfield      #30                 // Field a:Ljava/util/List;
      15: aload_0
      16: aload_1
      17: aload_2
      18: iload_3
      19: invokevirtual #51                 // Method a:(Ljava/lang/String;Lryey/easer/b/a;I)V
      22: return

  ryey.easer.plugins.event.e.a(java.lang.String[]);
    Code:
       0: aload_0
       1: invokespecial #25                 // Method ryey/easer/plugins/event/a."<init>":()V
       4: aload_0
       5: new           #27                 // class java/util/ArrayList
       8: dup
       9: invokespecial #28                 // Method java/util/ArrayList."<init>":()V
      12: putfield      #30                 // Field a:Ljava/util/List;
      15: aload_0
      16: aload_1
      17: invokespecial #54                 // Method a:([Ljava/lang/String;)V
      20: return

  public static ryey.easer.plugins.event.e.a a(java.lang.String);
    Code:
       0: new           #2                  // class ryey/easer/plugins/event/e/a
       3: dup
       4: aload_0
       5: ldc           #57                 // String \n
       7: invokevirtual #63                 // Method java/lang/String.split:(Ljava/lang/String;)[Ljava/lang/String;
      10: invokespecial #65                 // Method "<init>":([Ljava/lang/String;)V
      13: astore_0
      14: aload_0
      15: invokevirtual #68                 // Method a:()Z
      18: ifeq          23
      21: aload_0
      22: areturn
      23: aconst_null
      24: areturn

  public java.lang.String a(ryey.easer.b.a);
    Code:
       0: getstatic     #86                 // Field ryey/easer/plugins/event/e/a$2.a:[I
       3: aload_1
       4: invokevirtual #92                 // Method ryey/easer/b/a.ordinal:()I
       7: iaload
       8: istore_2
       9: new           #94                 // class org/json/JSONArray
      12: dup
      13: invokespecial #95                 // Method org/json/JSONArray."<init>":()V
      16: astore_1
      17: aload_0
      18: getfield      #30                 // Field a:Ljava/util/List;
      21: invokeinterface #99,  1           // InterfaceMethod java/util/List.iterator:()Ljava/util/Iterator;
      26: astore_3
      27: aload_3
      28: invokeinterface #104,  1          // InterfaceMethod java/util/Iterator.hasNext:()Z
      33: ifeq          56
      36: aload_1
      37: aload_3
      38: invokeinterface #108,  1          // InterfaceMethod java/util/Iterator.next:()Ljava/lang/Object;
      43: checkcast     #33                 // class ryey/easer/plugins/b/b
      46: invokevirtual #112                // Method ryey/easer/plugins/b/b.toString:()Ljava/lang/String;
      49: invokevirtual #116                // Method org/json/JSONArray.put:(Ljava/lang/Object;)Lorg/json/JSONArray;
      52: pop
      53: goto          27
      56: aload_1
      57: invokevirtual #117                // Method org/json/JSONArray.toString:()Ljava/lang/String;
      60: areturn

  public void a(java.lang.String, ryey.easer.b.a, int);
    Code:
       0: new           #94                 // class org/json/JSONArray
       3: dup
       4: aload_1
       5: invokespecial #122                // Method org/json/JSONArray."<init>":(Ljava/lang/String;)V
       8: astore_1
       9: aload_1
      10: invokevirtual #125                // Method org/json/JSONArray.length:()I
      13: anewarray     #59                 // class java/lang/String
      16: astore_2
      17: iconst_0
      18: istore_3
      19: iload_3
      20: aload_1
      21: invokevirtual #125                // Method org/json/JSONArray.length:()I
      24: if_icmpge     42
      27: aload_2
      28: iload_3
      29: aload_1
      30: iload_3
      31: invokevirtual #129                // Method org/json/JSONArray.getString:(I)Ljava/lang/String;
      34: aastore
      35: iload_3
      36: iconst_1
      37: iadd
      38: istore_3
      39: goto          19
      42: aload_0
      43: aload_2
      44: invokespecial #54                 // Method a:([Ljava/lang/String;)V
      47: return
      48: astore_1
      49: aload_1
      50: invokestatic  #134                // Method com/google/a/a/a/a/a/a.a:(Ljava/lang/Throwable;)V
      53: new           #136                // class ryey/easer/commons/local_plugin/b
      56: dup
      57: aload_1
      58: invokespecial #139                // Method ryey/easer/commons/local_plugin/b."<init>":(Ljava/lang/Exception;)V
      61: athrow
    Exception table:
       from    to  target type
           0    17    48   Class org/json/JSONException
          19    35    48   Class org/json/JSONException
          42    47    48   Class org/json/JSONException

  public boolean a();
    Code:
       0: aload_0
       1: getfield      #30                 // Field a:Ljava/util/List;
       4: invokeinterface #142,  1          // InterfaceMethod java/util/List.size:()I
       9: ifne          14
      12: iconst_0
      13: ireturn
      14: iconst_1
      15: ireturn

  boolean a(ryey.easer.plugins.b.b);
    Code:
       0: aload_0
       1: getfield      #30                 // Field a:Ljava/util/List;
       4: invokeinterface #99,  1           // InterfaceMethod java/util/List.iterator:()Ljava/util/Iterator;
       9: astore_2
      10: aload_2
      11: invokeinterface #104,  1          // InterfaceMethod java/util/Iterator.hasNext:()Z
      16: ifeq          37
      19: aload_1
      20: aload_2
      21: invokeinterface #108,  1          // InterfaceMethod java/util/Iterator.next:()Ljava/lang/Object;
      26: checkcast     #33                 // class ryey/easer/plugins/b/b
      29: invokevirtual #146                // Method ryey/easer/plugins/b/b.equals:(Ljava/lang/Object;)Z
      32: ifeq          10
      35: iconst_1
      36: ireturn
      37: iconst_0
      38: ireturn

  public int describeContents();
    Code:
       0: iconst_0
       1: ireturn

  public ryey.easer.commons.local_plugin.b.a[] dynamics();
    Code:
       0: iconst_1
       1: anewarray     #151                // class ryey/easer/commons/local_plugin/b/a
       4: dup
       5: iconst_0
       6: new           #10                 // class ryey/easer/plugins/event/e/a$a
       9: dup
      10: invokespecial #152                // Method ryey/easer/plugins/event/e/a$a."<init>":()V
      13: aastore
      14: areturn

  public boolean equals(java.lang.Object);
    Code:
       0: aload_1
       1: ifnull        36
       4: aload_1
       5: instanceof    #2                  // class ryey/easer/plugins/event/e/a
       8: ifne          13
      11: iconst_0
      12: ireturn
      13: aload_0
      14: getfield      #30                 // Field a:Ljava/util/List;
      17: aload_1
      18: checkcast     #2                  // class ryey/easer/plugins/event/e/a
      21: getfield      #30                 // Field a:Ljava/util/List;
      24: invokeinterface #153,  2          // InterfaceMethod java/util/List.equals:(Ljava/lang/Object;)Z
      29: ifne          34
      32: iconst_0
      33: ireturn
      34: iconst_1
      35: ireturn
      36: iconst_0
      37: ireturn

  public java.lang.String toString();
    Code:
       0: new           #155                // class java/lang/StringBuilder
       3: dup
       4: invokespecial #156                // Method java/lang/StringBuilder."<init>":()V
       7: astore_2
       8: aload_0
       9: getfield      #30                 // Field a:Ljava/util/List;
      12: invokeinterface #142,  1          // InterfaceMethod java/util/List.size:()I
      17: ifle          93
      20: aload_2
      21: aload_0
      22: getfield      #30                 // Field a:Ljava/util/List;
      25: iconst_0
      26: invokeinterface #160,  2          // InterfaceMethod java/util/List.get:(I)Ljava/lang/Object;
      31: checkcast     #33                 // class ryey/easer/plugins/b/b
      34: invokevirtual #112                // Method ryey/easer/plugins/b/b.toString:()Ljava/lang/String;
      37: invokevirtual #164                // Method java/lang/StringBuilder.append:(Ljava/lang/String;)Ljava/lang/StringBuilder;
      40: pop
      41: iconst_1
      42: istore_1
      43: iload_1
      44: aload_0
      45: getfield      #30                 // Field a:Ljava/util/List;
      48: invokeinterface #142,  1          // InterfaceMethod java/util/List.size:()I
      53: if_icmpge     93
      56: aload_0
      57: getfield      #30                 // Field a:Ljava/util/List;
      60: iload_1
      61: invokeinterface #160,  2          // InterfaceMethod java/util/List.get:(I)Ljava/lang/Object;
      66: checkcast     #33                 // class ryey/easer/plugins/b/b
      69: astore_3
      70: aload_2
      71: ldc           #57                 // String \n
      73: invokevirtual #164                // Method java/lang/StringBuilder.append:(Ljava/lang/String;)Ljava/lang/StringBuilder;
      76: pop
      77: aload_2
      78: aload_3
      79: invokevirtual #112                // Method ryey/easer/plugins/b/b.toString:()Ljava/lang/String;
      82: invokevirtual #164                // Method java/lang/StringBuilder.append:(Ljava/lang/String;)Ljava/lang/StringBuilder;
      85: pop
      86: iload_1
      87: iconst_1
      88: iadd
      89: istore_1
      90: goto          43
      93: aload_2
      94: invokevirtual #165                // Method java/lang/StringBuilder.toString:()Ljava/lang/String;
      97: areturn

  public void writeToParcel(android.os.Parcel, int);
    Code:
       0: aload_1
       1: aload_0
       2: getfield      #30                 // Field a:Ljava/util/List;
       5: invokevirtual #171                // Method android/os/Parcel.writeList:(Ljava/util/List;)V
       8: return
}
