class ryey.easer.plugins.event.e.e$a extends android.telephony.PhoneStateListener {
  final ryey.easer.plugins.event.e.e a;

  ryey.easer.plugins.event.e.e$a(ryey.easer.plugins.event.e.e);
    Code:
       0: aload_0
       1: aload_1
       2: putfield      #12                 // Field a:Lryey/easer/plugins/event/e/e;
       5: aload_0
       6: invokespecial #15                 // Method android/telephony/PhoneStateListener."<init>":()V
       9: return

  public void onCellLocationChanged(android.telephony.CellLocation);
    Code:
       0: aload_0
       1: monitorenter
       2: aload_0
       3: aload_1
       4: invokespecial #20                 // Method android/telephony/PhoneStateListener.onCellLocationChanged:(Landroid/telephony/CellLocation;)V
       7: aload_0
       8: getfield      #12                 // Field a:Lryey/easer/plugins/event/e/e;
      11: aload_1
      12: invokestatic  #25                 // Method ryey/easer/plugins/b/b.a:(Landroid/telephony/CellLocation;)Lryey/easer/plugins/b/b;
      15: invokestatic  #28                 // Method ryey/easer/plugins/event/e/e.a:(Lryey/easer/plugins/event/e/e;Lryey/easer/plugins/b/b;)Lryey/easer/plugins/b/b;
      18: pop
      19: aload_0
      20: getfield      #12                 // Field a:Lryey/easer/plugins/event/e/e;
      23: invokestatic  #31                 // Method ryey/easer/plugins/event/e/e.a:(Lryey/easer/plugins/event/e/e;)Lryey/easer/plugins/b/b;
      26: ifnull        60
      29: aload_0
      30: getfield      #12                 // Field a:Lryey/easer/plugins/event/e/e;
      33: aload_0
      34: getfield      #12                 // Field a:Lryey/easer/plugins/event/e/e;
      37: invokestatic  #35                 // Method ryey/easer/plugins/event/e/e.b:(Lryey/easer/plugins/event/e/e;)Lryey/easer/commons/local_plugin/eventplugin/EventData;
      40: checkcast     #37                 // class ryey/easer/plugins/event/e/a
      43: aload_0
      44: getfield      #12                 // Field a:Lryey/easer/plugins/event/e/e;
      47: invokestatic  #31                 // Method ryey/easer/plugins/event/e/e.a:(Lryey/easer/plugins/event/e/e;)Lryey/easer/plugins/b/b;
      50: invokevirtual #40                 // Method ryey/easer/plugins/event/e/a.a:(Lryey/easer/plugins/b/b;)Z
      53: aload_1
      54: invokestatic  #43                 // Method ryey/easer/plugins/event/e/e.a:(Landroid/telephony/CellLocation;)Landroid/os/Bundle;
      57: invokestatic  #46                 // Method ryey/easer/plugins/event/e/e.a:(Lryey/easer/plugins/event/e/e;ZLandroid/os/Bundle;)V
      60: aload_0
      61: monitorexit
      62: return
      63: astore_1
      64: aload_0
      65: monitorexit
      66: aload_1
      67: athrow
    Exception table:
       from    to  target type
           2    60    63   any
}
