class ryey.easer.plugins.event.l.a$1 extends android.content.BroadcastReceiver {
  final ryey.easer.plugins.event.l.a a;

  ryey.easer.plugins.event.l.a$1(ryey.easer.plugins.event.l.a);
    Code:
       0: aload_0
       1: aload_1
       2: putfield      #12                 // Field a:Lryey/easer/plugins/event/l/a;
       5: aload_0
       6: invokespecial #15                 // Method android/content/BroadcastReceiver."<init>":()V
       9: return

  public void onReceive(android.content.Context, android.content.Intent);
    Code:
       0: aload_2
       1: invokevirtual #26                 // Method android/content/Intent.getAction:()Ljava/lang/String;
       4: ldc           #28                 // String android.provider.Telephony.SMS_RECEIVED
       6: invokevirtual #34                 // Method java/lang/String.equals:(Ljava/lang/Object;)Z
       9: ifeq          207
      12: aload_2
      13: invokevirtual #38                 // Method android/content/Intent.getExtras:()Landroid/os/Bundle;
      16: ldc           #40                 // String pdus
      18: invokevirtual #46                 // Method android/os/Bundle.get:(Ljava/lang/String;)Ljava/lang/Object;
      21: checkcast     #48                 // class "[Ljava/lang/Object;"
      24: astore        5
      26: aload         5
      28: arraylength
      29: anewarray     #50                 // class android/telephony/SmsMessage
      32: astore        6
      34: iconst_0
      35: istore_3
      36: iload_3
      37: aload         6
      39: arraylength
      40: if_icmpge     181
      43: aload         6
      45: iload_3
      46: aload         5
      48: iload_3
      49: aaload
      50: checkcast     #52                 // class "[B"
      53: invokestatic  #56                 // Method android/telephony/SmsMessage.createFromPdu:([B)Landroid/telephony/SmsMessage;
      56: aastore
      57: aload         6
      59: iload_3
      60: aaload
      61: invokevirtual #59                 // Method android/telephony/SmsMessage.getOriginatingAddress:()Ljava/lang/String;
      64: astore_2
      65: aload         6
      67: iload_3
      68: aaload
      69: invokevirtual #62                 // Method android/telephony/SmsMessage.getMessageBody:()Ljava/lang/String;
      72: astore        4
      74: aload_0
      75: getfield      #12                 // Field a:Lryey/easer/plugins/event/l/a;
      78: invokestatic  #65                 // Method ryey/easer/plugins/event/l/a.a:(Lryey/easer/plugins/event/l/a;)Lryey/easer/plugins/event/l/e;
      81: getfield      #70                 // Field ryey/easer/plugins/event/l/e.a:Ljava/lang/String;
      84: invokestatic  #75                 // Method ryey/easer/b.a:(Ljava/lang/String;)Z
      87: ifne          111
      90: aload_1
      91: aload_2
      92: aload_0
      93: getfield      #12                 // Field a:Lryey/easer/plugins/event/l/a;
      96: invokestatic  #65                 // Method ryey/easer/plugins/event/l/a.a:(Lryey/easer/plugins/event/l/a;)Lryey/easer/plugins/event/l/e;
      99: getfield      #70                 // Field ryey/easer/plugins/event/l/e.a:Ljava/lang/String;
     102: invokestatic  #81                 // Method android/telephony/PhoneNumberUtils.compare:(Landroid/content/Context;Ljava/lang/String;Ljava/lang/String;)Z
     105: ifne          111
     108: goto          208
     111: aload_0
     112: getfield      #12                 // Field a:Lryey/easer/plugins/event/l/a;
     115: invokestatic  #65                 // Method ryey/easer/plugins/event/l/a.a:(Lryey/easer/plugins/event/l/a;)Lryey/easer/plugins/event/l/e;
     118: getfield      #84                 // Field ryey/easer/plugins/event/l/e.b:Ljava/lang/String;
     121: invokestatic  #75                 // Method ryey/easer/b.a:(Ljava/lang/String;)Z
     124: ifne          148
     127: aload         4
     129: aload_0
     130: getfield      #12                 // Field a:Lryey/easer/plugins/event/l/a;
     133: invokestatic  #65                 // Method ryey/easer/plugins/event/l/a.a:(Lryey/easer/plugins/event/l/a;)Lryey/easer/plugins/event/l/e;
     136: getfield      #84                 // Field ryey/easer/plugins/event/l/e.b:Ljava/lang/String;
     139: invokevirtual #88                 // Method java/lang/String.contains:(Ljava/lang/CharSequence;)Z
     142: ifne          148
     145: goto          208
     148: new           #42                 // class android/os/Bundle
     151: dup
     152: invokespecial #89                 // Method android/os/Bundle."<init>":()V
     155: astore_1
     156: aload_1
     157: ldc           #91                 // String ryey.easer.plugins.event.sms.dynamics.sender
     159: aload_2
     160: invokevirtual #95                 // Method android/os/Bundle.putString:(Ljava/lang/String;Ljava/lang/String;)V
     163: aload_1
     164: ldc           #97                 // String ryey.easer.plugins.event.sms.dynamics.content
     166: aload         4
     168: invokevirtual #95                 // Method android/os/Bundle.putString:(Ljava/lang/String;Ljava/lang/String;)V
     171: aload_0
     172: getfield      #12                 // Field a:Lryey/easer/plugins/event/l/a;
     175: iconst_1
     176: aload_1
     177: invokestatic  #100                // Method ryey/easer/plugins/event/l/a.a:(Lryey/easer/plugins/event/l/a;ZLandroid/os/Bundle;)V
     180: return
     181: aload_0
     182: getfield      #12                 // Field a:Lryey/easer/plugins/event/l/a;
     185: iconst_0
     186: invokestatic  #103                // Method ryey/easer/plugins/event/l/a.a:(Lryey/easer/plugins/event/l/a;Z)V
     189: return
     190: astore_1
     191: ldc           #105                // String Exception caught
     193: iconst_1
     194: anewarray     #107                // class java/lang/Object
     197: dup
     198: iconst_0
     199: aload_1
     200: invokevirtual #110                // Method java/lang/Exception.getMessage:()Ljava/lang/String;
     203: aastore
     204: invokestatic  #115                // Method com/b/a/i.a:(Ljava/lang/String;[Ljava/lang/Object;)V
     207: return
     208: iload_3
     209: iconst_1
     210: iadd
     211: istore_3
     212: goto          36
    Exception table:
       from    to  target type
          12    34   190   Class java/lang/Exception
          36   108   190   Class java/lang/Exception
         111   145   190   Class java/lang/Exception
         148   180   190   Class java/lang/Exception
         181   189   190   Class java/lang/Exception
}
