public class ryey.easer.core.b.a {
  static {};
    Code:
       0: iconst_4
       1: anewarray     #10                 // class ryey/easer/core/b/b
       4: dup
       5: iconst_0
       6: new           #12                 // class ryey/easer/core/b/c
       9: dup
      10: invokespecial #15                 // Method ryey/easer/core/b/c."<init>":()V
      13: aastore
      14: dup
      15: iconst_1
      16: new           #17                 // class ryey/easer/core/b/f
      19: dup
      20: invokespecial #18                 // Method ryey/easer/core/b/f."<init>":()V
      23: aastore
      24: dup
      25: iconst_2
      26: new           #20                 // class ryey/easer/core/b/e
      29: dup
      30: invokespecial #21                 // Method ryey/easer/core/b/e."<init>":()V
      33: aastore
      34: dup
      35: iconst_3
      36: new           #23                 // class ryey/easer/core/b/d
      39: dup
      40: invokespecial #24                 // Method ryey/easer/core/b/d."<init>":()V
      43: aastore
      44: putstatic     #26                 // Field a:[Lryey/easer/core/b/b;
      47: return

  public static ryey.easer.core.b.b[] a();
    Code:
       0: getstatic     #26                 // Field a:[Lryey/easer/core/b/b;
       3: areturn
}
