public class ryey.easer.core.b.e implements ryey.easer.core.b.b {
  public ryey.easer.core.b.e();
    Code:
       0: aload_0
       1: invokespecial #10                 // Method java/lang/Object."<init>":()V
       4: return

  public java.lang.String a();
    Code:
       0: ldc           #15                 // String ryey.easer.core.dynamics.script_name
       2: areturn

  public java.lang.String a(android.content.Context, android.os.Bundle);
    Code:
       0: aload_2
       1: ldc           #18                 // String ryey.easer.extra.EVENT_NAME
       3: invokevirtual #24                 // Method android/os/Bundle.getString:(Ljava/lang/String;)Ljava/lang/String;
       6: areturn

  public int b();
    Code:
       0: ldc           #27                 // int 2131624035
       2: ireturn
}
