public final class com.github.paolorotolo.appintro.R$styleable {
  public static final int[] ActionBar;

  public static final int[] ActionBarLayout;

  public static final int ActionBarLayout_android_layout_gravity;

  public static final int ActionBar_background;

  public static final int ActionBar_backgroundSplit;

  public static final int ActionBar_backgroundStacked;

  public static final int ActionBar_contentInsetEnd;

  public static final int ActionBar_contentInsetEndWithActions;

  public static final int ActionBar_contentInsetLeft;

  public static final int ActionBar_contentInsetRight;

  public static final int ActionBar_contentInsetStart;

  public static final int ActionBar_contentInsetStartWithNavigation;

  public static final int ActionBar_customNavigationLayout;

  public static final int ActionBar_displayOptions;

  public static final int ActionBar_divider;

  public static final int ActionBar_elevation;

  public static final int ActionBar_height;

  public static final int ActionBar_hideOnContentScroll;

  public static final int ActionBar_homeAsUpIndicator;

  public static final int ActionBar_homeLayout;

  public static final int ActionBar_icon;

  public static final int ActionBar_indeterminateProgressStyle;

  public static final int ActionBar_itemPadding;

  public static final int ActionBar_logo;

  public static final int ActionBar_navigationMode;

  public static final int ActionBar_popupTheme;

  public static final int ActionBar_progressBarPadding;

  public static final int ActionBar_progressBarStyle;

  public static final int ActionBar_subtitle;

  public static final int ActionBar_subtitleTextStyle;

  public static final int ActionBar_title;

  public static final int ActionBar_titleTextStyle;

  public static final int[] ActionMenuItemView;

  public static final int ActionMenuItemView_android_minWidth;

  public static final int[] ActionMode;

  public static final int ActionMode_background;

  public static final int ActionMode_backgroundSplit;

  public static final int ActionMode_closeItemLayout;

  public static final int ActionMode_height;

  public static final int ActionMode_subtitleTextStyle;

  public static final int ActionMode_titleTextStyle;

  public static final int[] ActivityChooserView;

  public static final int ActivityChooserView_expandActivityOverflowButtonDrawable;

  public static final int ActivityChooserView_initialActivityCount;

  public static final int[] AlertDialog;

  public static final int AlertDialog_android_layout;

  public static final int AlertDialog_buttonIconDimen;

  public static final int AlertDialog_buttonPanelSideLayout;

  public static final int AlertDialog_listItemLayout;

  public static final int AlertDialog_listLayout;

  public static final int AlertDialog_multiChoiceItemLayout;

  public static final int AlertDialog_showTitle;

  public static final int AlertDialog_singleChoiceItemLayout;

  public static final int[] AppCompatImageView;

  public static final int AppCompatImageView_android_src;

  public static final int AppCompatImageView_srcCompat;

  public static final int AppCompatImageView_tint;

  public static final int AppCompatImageView_tintMode;

  public static final int[] AppCompatSeekBar;

  public static final int AppCompatSeekBar_android_thumb;

  public static final int AppCompatSeekBar_tickMark;

  public static final int AppCompatSeekBar_tickMarkTint;

  public static final int AppCompatSeekBar_tickMarkTintMode;

  public static final int[] AppCompatTextHelper;

  public static final int AppCompatTextHelper_android_drawableBottom;

  public static final int AppCompatTextHelper_android_drawableEnd;

  public static final int AppCompatTextHelper_android_drawableLeft;

  public static final int AppCompatTextHelper_android_drawableRight;

  public static final int AppCompatTextHelper_android_drawableStart;

  public static final int AppCompatTextHelper_android_drawableTop;

  public static final int AppCompatTextHelper_android_textAppearance;

  public static final int[] AppCompatTextView;

  public static final int AppCompatTextView_android_textAppearance;

  public static final int AppCompatTextView_autoSizeMaxTextSize;

  public static final int AppCompatTextView_autoSizeMinTextSize;

  public static final int AppCompatTextView_autoSizePresetSizes;

  public static final int AppCompatTextView_autoSizeStepGranularity;

  public static final int AppCompatTextView_autoSizeTextType;

  public static final int AppCompatTextView_fontFamily;

  public static final int AppCompatTextView_textAllCaps;

  public static final int[] AppCompatTheme;

  public static final int AppCompatTheme_actionBarDivider;

  public static final int AppCompatTheme_actionBarItemBackground;

  public static final int AppCompatTheme_actionBarPopupTheme;

  public static final int AppCompatTheme_actionBarSize;

  public static final int AppCompatTheme_actionBarSplitStyle;

  public static final int AppCompatTheme_actionBarStyle;

  public static final int AppCompatTheme_actionBarTabBarStyle;

  public static final int AppCompatTheme_actionBarTabStyle;

  public static final int AppCompatTheme_actionBarTabTextStyle;

  public static final int AppCompatTheme_actionBarTheme;

  public static final int AppCompatTheme_actionBarWidgetTheme;

  public static final int AppCompatTheme_actionButtonStyle;

  public static final int AppCompatTheme_actionDropDownStyle;

  public static final int AppCompatTheme_actionMenuTextAppearance;

  public static final int AppCompatTheme_actionMenuTextColor;

  public static final int AppCompatTheme_actionModeBackground;

  public static final int AppCompatTheme_actionModeCloseButtonStyle;

  public static final int AppCompatTheme_actionModeCloseDrawable;

  public static final int AppCompatTheme_actionModeCopyDrawable;

  public static final int AppCompatTheme_actionModeCutDrawable;

  public static final int AppCompatTheme_actionModeFindDrawable;

  public static final int AppCompatTheme_actionModePasteDrawable;

  public static final int AppCompatTheme_actionModePopupWindowStyle;

  public static final int AppCompatTheme_actionModeSelectAllDrawable;

  public static final int AppCompatTheme_actionModeShareDrawable;

  public static final int AppCompatTheme_actionModeSplitBackground;

  public static final int AppCompatTheme_actionModeStyle;

  public static final int AppCompatTheme_actionModeWebSearchDrawable;

  public static final int AppCompatTheme_actionOverflowButtonStyle;

  public static final int AppCompatTheme_actionOverflowMenuStyle;

  public static final int AppCompatTheme_activityChooserViewStyle;

  public static final int AppCompatTheme_alertDialogButtonGroupStyle;

  public static final int AppCompatTheme_alertDialogCenterButtons;

  public static final int AppCompatTheme_alertDialogStyle;

  public static final int AppCompatTheme_alertDialogTheme;

  public static final int AppCompatTheme_android_windowAnimationStyle;

  public static final int AppCompatTheme_android_windowIsFloating;

  public static final int AppCompatTheme_autoCompleteTextViewStyle;

  public static final int AppCompatTheme_borderlessButtonStyle;

  public static final int AppCompatTheme_buttonBarButtonStyle;

  public static final int AppCompatTheme_buttonBarNegativeButtonStyle;

  public static final int AppCompatTheme_buttonBarNeutralButtonStyle;

  public static final int AppCompatTheme_buttonBarPositiveButtonStyle;

  public static final int AppCompatTheme_buttonBarStyle;

  public static final int AppCompatTheme_buttonStyle;

  public static final int AppCompatTheme_buttonStyleSmall;

  public static final int AppCompatTheme_checkboxStyle;

  public static final int AppCompatTheme_checkedTextViewStyle;

  public static final int AppCompatTheme_colorAccent;

  public static final int AppCompatTheme_colorBackgroundFloating;

  public static final int AppCompatTheme_colorButtonNormal;

  public static final int AppCompatTheme_colorControlActivated;

  public static final int AppCompatTheme_colorControlHighlight;

  public static final int AppCompatTheme_colorControlNormal;

  public static final int AppCompatTheme_colorError;

  public static final int AppCompatTheme_colorPrimary;

  public static final int AppCompatTheme_colorPrimaryDark;

  public static final int AppCompatTheme_colorSwitchThumbNormal;

  public static final int AppCompatTheme_controlBackground;

  public static final int AppCompatTheme_dialogPreferredPadding;

  public static final int AppCompatTheme_dialogTheme;

  public static final int AppCompatTheme_dividerHorizontal;

  public static final int AppCompatTheme_dividerVertical;

  public static final int AppCompatTheme_dropDownListViewStyle;

  public static final int AppCompatTheme_dropdownListPreferredItemHeight;

  public static final int AppCompatTheme_editTextBackground;

  public static final int AppCompatTheme_editTextColor;

  public static final int AppCompatTheme_editTextStyle;

  public static final int AppCompatTheme_homeAsUpIndicator;

  public static final int AppCompatTheme_imageButtonStyle;

  public static final int AppCompatTheme_listChoiceBackgroundIndicator;

  public static final int AppCompatTheme_listDividerAlertDialog;

  public static final int AppCompatTheme_listMenuViewStyle;

  public static final int AppCompatTheme_listPopupWindowStyle;

  public static final int AppCompatTheme_listPreferredItemHeight;

  public static final int AppCompatTheme_listPreferredItemHeightLarge;

  public static final int AppCompatTheme_listPreferredItemHeightSmall;

  public static final int AppCompatTheme_listPreferredItemPaddingLeft;

  public static final int AppCompatTheme_listPreferredItemPaddingRight;

  public static final int AppCompatTheme_panelBackground;

  public static final int AppCompatTheme_panelMenuListTheme;

  public static final int AppCompatTheme_panelMenuListWidth;

  public static final int AppCompatTheme_popupMenuStyle;

  public static final int AppCompatTheme_popupWindowStyle;

  public static final int AppCompatTheme_radioButtonStyle;

  public static final int AppCompatTheme_ratingBarStyle;

  public static final int AppCompatTheme_ratingBarStyleIndicator;

  public static final int AppCompatTheme_ratingBarStyleSmall;

  public static final int AppCompatTheme_searchViewStyle;

  public static final int AppCompatTheme_seekBarStyle;

  public static final int AppCompatTheme_selectableItemBackground;

  public static final int AppCompatTheme_selectableItemBackgroundBorderless;

  public static final int AppCompatTheme_spinnerDropDownItemStyle;

  public static final int AppCompatTheme_spinnerStyle;

  public static final int AppCompatTheme_switchStyle;

  public static final int AppCompatTheme_textAppearanceLargePopupMenu;

  public static final int AppCompatTheme_textAppearanceListItem;

  public static final int AppCompatTheme_textAppearanceListItemSecondary;

  public static final int AppCompatTheme_textAppearanceListItemSmall;

  public static final int AppCompatTheme_textAppearancePopupMenuHeader;

  public static final int AppCompatTheme_textAppearanceSearchResultSubtitle;

  public static final int AppCompatTheme_textAppearanceSearchResultTitle;

  public static final int AppCompatTheme_textAppearanceSmallPopupMenu;

  public static final int AppCompatTheme_textColorAlertDialogListItem;

  public static final int AppCompatTheme_textColorSearchUrl;

  public static final int AppCompatTheme_toolbarNavigationButtonStyle;

  public static final int AppCompatTheme_toolbarStyle;

  public static final int AppCompatTheme_tooltipForegroundColor;

  public static final int AppCompatTheme_tooltipFrameBackground;

  public static final int AppCompatTheme_viewInflaterClass;

  public static final int AppCompatTheme_windowActionBar;

  public static final int AppCompatTheme_windowActionBarOverlay;

  public static final int AppCompatTheme_windowActionModeOverlay;

  public static final int AppCompatTheme_windowFixedHeightMajor;

  public static final int AppCompatTheme_windowFixedHeightMinor;

  public static final int AppCompatTheme_windowFixedWidthMajor;

  public static final int AppCompatTheme_windowFixedWidthMinor;

  public static final int AppCompatTheme_windowMinWidthMajor;

  public static final int AppCompatTheme_windowMinWidthMinor;

  public static final int AppCompatTheme_windowNoTitle;

  public static final int[] ButtonBarLayout;

  public static final int ButtonBarLayout_allowStacking;

  public static final int[] ColorStateListItem;

  public static final int ColorStateListItem_alpha;

  public static final int ColorStateListItem_android_alpha;

  public static final int ColorStateListItem_android_color;

  public static final int[] CompoundButton;

  public static final int CompoundButton_android_button;

  public static final int CompoundButton_buttonTint;

  public static final int CompoundButton_buttonTintMode;

  public static final int[] DrawerArrowToggle;

  public static final int DrawerArrowToggle_arrowHeadLength;

  public static final int DrawerArrowToggle_arrowShaftLength;

  public static final int DrawerArrowToggle_barLength;

  public static final int DrawerArrowToggle_color;

  public static final int DrawerArrowToggle_drawableSize;

  public static final int DrawerArrowToggle_gapBetweenBars;

  public static final int DrawerArrowToggle_spinBars;

  public static final int DrawerArrowToggle_thickness;

  public static final int[] FontFamily;

  public static final int[] FontFamilyFont;

  public static final int FontFamilyFont_android_font;

  public static final int FontFamilyFont_android_fontStyle;

  public static final int FontFamilyFont_android_fontWeight;

  public static final int FontFamilyFont_font;

  public static final int FontFamilyFont_fontStyle;

  public static final int FontFamilyFont_fontWeight;

  public static final int FontFamily_fontProviderAuthority;

  public static final int FontFamily_fontProviderCerts;

  public static final int FontFamily_fontProviderFetchStrategy;

  public static final int FontFamily_fontProviderFetchTimeout;

  public static final int FontFamily_fontProviderPackage;

  public static final int FontFamily_fontProviderQuery;

  public static final int[] LinearLayoutCompat;

  public static final int[] LinearLayoutCompat_Layout;

  public static final int LinearLayoutCompat_Layout_android_layout_gravity;

  public static final int LinearLayoutCompat_Layout_android_layout_height;

  public static final int LinearLayoutCompat_Layout_android_layout_weight;

  public static final int LinearLayoutCompat_Layout_android_layout_width;

  public static final int LinearLayoutCompat_android_baselineAligned;

  public static final int LinearLayoutCompat_android_baselineAlignedChildIndex;

  public static final int LinearLayoutCompat_android_gravity;

  public static final int LinearLayoutCompat_android_orientation;

  public static final int LinearLayoutCompat_android_weightSum;

  public static final int LinearLayoutCompat_divider;

  public static final int LinearLayoutCompat_dividerPadding;

  public static final int LinearLayoutCompat_measureWithLargestChild;

  public static final int LinearLayoutCompat_showDividers;

  public static final int[] ListPopupWindow;

  public static final int ListPopupWindow_android_dropDownHorizontalOffset;

  public static final int ListPopupWindow_android_dropDownVerticalOffset;

  public static final int[] MenuGroup;

  public static final int MenuGroup_android_checkableBehavior;

  public static final int MenuGroup_android_enabled;

  public static final int MenuGroup_android_id;

  public static final int MenuGroup_android_menuCategory;

  public static final int MenuGroup_android_orderInCategory;

  public static final int MenuGroup_android_visible;

  public static final int[] MenuItem;

  public static final int MenuItem_actionLayout;

  public static final int MenuItem_actionProviderClass;

  public static final int MenuItem_actionViewClass;

  public static final int MenuItem_alphabeticModifiers;

  public static final int MenuItem_android_alphabeticShortcut;

  public static final int MenuItem_android_checkable;

  public static final int MenuItem_android_checked;

  public static final int MenuItem_android_enabled;

  public static final int MenuItem_android_icon;

  public static final int MenuItem_android_id;

  public static final int MenuItem_android_menuCategory;

  public static final int MenuItem_android_numericShortcut;

  public static final int MenuItem_android_onClick;

  public static final int MenuItem_android_orderInCategory;

  public static final int MenuItem_android_title;

  public static final int MenuItem_android_titleCondensed;

  public static final int MenuItem_android_visible;

  public static final int MenuItem_contentDescription;

  public static final int MenuItem_iconTint;

  public static final int MenuItem_iconTintMode;

  public static final int MenuItem_numericModifiers;

  public static final int MenuItem_showAsAction;

  public static final int MenuItem_tooltipText;

  public static final int[] MenuView;

  public static final int MenuView_android_headerBackground;

  public static final int MenuView_android_horizontalDivider;

  public static final int MenuView_android_itemBackground;

  public static final int MenuView_android_itemIconDisabledAlpha;

  public static final int MenuView_android_itemTextAppearance;

  public static final int MenuView_android_verticalDivider;

  public static final int MenuView_android_windowAnimationStyle;

  public static final int MenuView_preserveIconSpacing;

  public static final int MenuView_subMenuArrow;

  public static final int[] PopupWindow;

  public static final int[] PopupWindowBackgroundState;

  public static final int PopupWindowBackgroundState_state_above_anchor;

  public static final int PopupWindow_android_popupAnimationStyle;

  public static final int PopupWindow_android_popupBackground;

  public static final int PopupWindow_overlapAnchor;

  public static final int[] RecycleListView;

  public static final int RecycleListView_paddingBottomNoButtons;

  public static final int RecycleListView_paddingTopNoTitle;

  public static final int[] SearchView;

  public static final int SearchView_android_focusable;

  public static final int SearchView_android_imeOptions;

  public static final int SearchView_android_inputType;

  public static final int SearchView_android_maxWidth;

  public static final int SearchView_closeIcon;

  public static final int SearchView_commitIcon;

  public static final int SearchView_defaultQueryHint;

  public static final int SearchView_goIcon;

  public static final int SearchView_iconifiedByDefault;

  public static final int SearchView_layout;

  public static final int SearchView_queryBackground;

  public static final int SearchView_queryHint;

  public static final int SearchView_searchHintIcon;

  public static final int SearchView_searchIcon;

  public static final int SearchView_submitBackground;

  public static final int SearchView_suggestionRowLayout;

  public static final int SearchView_voiceIcon;

  public static final int[] Spinner;

  public static final int Spinner_android_dropDownWidth;

  public static final int Spinner_android_entries;

  public static final int Spinner_android_popupBackground;

  public static final int Spinner_android_prompt;

  public static final int Spinner_popupTheme;

  public static final int[] SwitchCompat;

  public static final int SwitchCompat_android_textOff;

  public static final int SwitchCompat_android_textOn;

  public static final int SwitchCompat_android_thumb;

  public static final int SwitchCompat_showText;

  public static final int SwitchCompat_splitTrack;

  public static final int SwitchCompat_switchMinWidth;

  public static final int SwitchCompat_switchPadding;

  public static final int SwitchCompat_switchTextAppearance;

  public static final int SwitchCompat_thumbTextPadding;

  public static final int SwitchCompat_thumbTint;

  public static final int SwitchCompat_thumbTintMode;

  public static final int SwitchCompat_track;

  public static final int SwitchCompat_trackTint;

  public static final int SwitchCompat_trackTintMode;

  public static final int[] TextAppearance;

  public static final int TextAppearance_android_fontFamily;

  public static final int TextAppearance_android_shadowColor;

  public static final int TextAppearance_android_shadowDx;

  public static final int TextAppearance_android_shadowDy;

  public static final int TextAppearance_android_shadowRadius;

  public static final int TextAppearance_android_textColor;

  public static final int TextAppearance_android_textColorHint;

  public static final int TextAppearance_android_textColorLink;

  public static final int TextAppearance_android_textSize;

  public static final int TextAppearance_android_textStyle;

  public static final int TextAppearance_android_typeface;

  public static final int TextAppearance_fontFamily;

  public static final int TextAppearance_textAllCaps;

  public static final int[] Toolbar;

  public static final int Toolbar_android_gravity;

  public static final int Toolbar_android_minHeight;

  public static final int Toolbar_buttonGravity;

  public static final int Toolbar_collapseContentDescription;

  public static final int Toolbar_collapseIcon;

  public static final int Toolbar_contentInsetEnd;

  public static final int Toolbar_contentInsetEndWithActions;

  public static final int Toolbar_contentInsetLeft;

  public static final int Toolbar_contentInsetRight;

  public static final int Toolbar_contentInsetStart;

  public static final int Toolbar_contentInsetStartWithNavigation;

  public static final int Toolbar_logo;

  public static final int Toolbar_logoDescription;

  public static final int Toolbar_maxButtonHeight;

  public static final int Toolbar_navigationContentDescription;

  public static final int Toolbar_navigationIcon;

  public static final int Toolbar_popupTheme;

  public static final int Toolbar_subtitle;

  public static final int Toolbar_subtitleTextAppearance;

  public static final int Toolbar_subtitleTextColor;

  public static final int Toolbar_title;

  public static final int Toolbar_titleMargin;

  public static final int Toolbar_titleMarginBottom;

  public static final int Toolbar_titleMarginEnd;

  public static final int Toolbar_titleMarginStart;

  public static final int Toolbar_titleMarginTop;

  public static final int Toolbar_titleMargins;

  public static final int Toolbar_titleTextAppearance;

  public static final int Toolbar_titleTextColor;

  public static final int[] View;

  public static final int[] ViewBackgroundHelper;

  public static final int ViewBackgroundHelper_android_background;

  public static final int ViewBackgroundHelper_backgroundTint;

  public static final int ViewBackgroundHelper_backgroundTintMode;

  public static final int[] ViewStubCompat;

  public static final int ViewStubCompat_android_id;

  public static final int ViewStubCompat_android_inflatedId;

  public static final int ViewStubCompat_android_layout;

  public static final int View_android_focusable;

  public static final int View_android_theme;

  public static final int View_paddingEnd;

  public static final int View_paddingStart;

  public static final int View_theme;

  static {};
    Code:
       0: bipush        29
       2: newarray       int
       4: dup
       5: iconst_0
       6: ldc_w         #531                // int 2130968628
       9: iastore
      10: dup
      11: iconst_1
      12: ldc_w         #532                // int 2130968629
      15: iastore
      16: dup
      17: iconst_2
      18: ldc_w         #533                // int 2130968630
      21: iastore
      22: dup
      23: iconst_3
      24: ldc_w         #534                // int 2130968689
      27: iastore
      28: dup
      29: iconst_4
      30: ldc_w         #535                // int 2130968690
      33: iastore
      34: dup
      35: iconst_5
      36: ldc_w         #536                // int 2130968691
      39: iastore
      40: dup
      41: bipush        6
      43: ldc_w         #537                // int 2130968692
      46: iastore
      47: dup
      48: bipush        7
      50: ldc_w         #538                // int 2130968693
      53: iastore
      54: dup
      55: bipush        8
      57: ldc_w         #539                // int 2130968694
      60: iastore
      61: dup
      62: bipush        9
      64: ldc_w         #540                // int 2130968707
      67: iastore
      68: dup
      69: bipush        10
      71: ldc_w         #541                // int 2130968712
      74: iastore
      75: dup
      76: bipush        11
      78: ldc_w         #542                // int 2130968713
      81: iastore
      82: dup
      83: bipush        12
      85: ldc_w         #543                // int 2130968724
      88: iastore
      89: dup
      90: bipush        13
      92: ldc_w         #544                // int 2130968761
      95: iastore
      96: dup
      97: bipush        14
      99: ldc_w         #545                // int 2130968762
     102: iastore
     103: dup
     104: bipush        15
     106: ldc_w         #546                // int 2130968766
     109: iastore
     110: dup
     111: bipush        16
     113: ldc_w         #547                // int 2130968767
     116: iastore
     117: dup
     118: bipush        17
     120: ldc_w         #548                // int 2130968769
     123: iastore
     124: dup
     125: bipush        18
     127: ldc_w         #549                // int 2130968774
     130: iastore
     131: dup
     132: bipush        19
     134: ldc_w         #550                // int 2130968781
     137: iastore
     138: dup
     139: bipush        20
     141: ldc_w         #551                // int 2130968863
     144: iastore
     145: dup
     146: bipush        21
     148: ldc_w         #552                // int 2130968876
     151: iastore
     152: dup
     153: bipush        22
     155: ldc_w         #553                // int 2130968895
     158: iastore
     159: dup
     160: bipush        23
     162: ldc_w         #554                // int 2130968899
     165: iastore
     166: dup
     167: bipush        24
     169: ldc_w         #555                // int 2130968900
     172: iastore
     173: dup
     174: bipush        25
     176: ldc_w         #556                // int 2130968937
     179: iastore
     180: dup
     181: bipush        26
     183: ldc_w         #557                // int 2130968940
     186: iastore
     187: dup
     188: bipush        27
     190: ldc_w         #558                // int 2130968984
     193: iastore
     194: dup
     195: bipush        28
     197: ldc_w         #559                // int 2130968994
     200: iastore
     201: putstatic     #561                // Field ActionBar:[I
     204: iconst_1
     205: newarray       int
     207: dup
     208: iconst_0
     209: ldc_w         #562                // int 16842931
     212: iastore
     213: putstatic     #564                // Field ActionBarLayout:[I
     216: iconst_1
     217: newarray       int
     219: dup
     220: iconst_0
     221: ldc_w         #565                // int 16843071
     224: iastore
     225: putstatic     #567                // Field ActionMenuItemView:[I
     228: bipush        6
     230: newarray       int
     232: dup
     233: iconst_0
     234: ldc_w         #531                // int 2130968628
     237: iastore
     238: dup
     239: iconst_1
     240: ldc_w         #532                // int 2130968629
     243: iastore
     244: dup
     245: iconst_2
     246: ldc_w         #568                // int 2130968668
     249: iastore
     250: dup
     251: iconst_3
     252: ldc_w         #544                // int 2130968761
     255: iastore
     256: dup
     257: iconst_4
     258: ldc_w         #557                // int 2130968940
     261: iastore
     262: dup
     263: iconst_5
     264: ldc_w         #559                // int 2130968994
     267: iastore
     268: putstatic     #570                // Field ActionMode:[I
     271: iconst_2
     272: newarray       int
     274: dup
     275: iconst_0
     276: ldc_w         #571                // int 2130968728
     279: iastore
     280: dup
     281: iconst_1
     282: ldc_w         #572                // int 2130968775
     285: iastore
     286: putstatic     #574                // Field ActivityChooserView:[I
     289: bipush        8
     291: newarray       int
     293: dup
     294: iconst_0
     295: ldc_w         #575                // int 16842994
     298: iastore
     299: dup
     300: iconst_1
     301: ldc_w         #576                // int 2130968651
     304: iastore
     305: dup
     306: iconst_2
     307: ldc_w         #577                // int 2130968652
     310: iastore
     311: dup
     312: iconst_3
     313: ldc_w         #578                // int 2130968854
     316: iastore
     317: dup
     318: iconst_4
     319: ldc_w         #579                // int 2130968855
     322: iastore
     323: dup
     324: iconst_5
     325: ldc_w         #580                // int 2130968873
     328: iastore
     329: dup
     330: bipush        6
     332: ldc_w         #581                // int 2130968920
     335: iastore
     336: dup
     337: bipush        7
     339: ldc_w         #582                // int 2130968921
     342: iastore
     343: putstatic     #584                // Field AlertDialog:[I
     346: iconst_4
     347: newarray       int
     349: dup
     350: iconst_0
     351: ldc_w         #585                // int 16843033
     354: iastore
     355: dup
     356: iconst_1
     357: ldc_w         #586                // int 2130968927
     360: iastore
     361: dup
     362: iconst_2
     363: ldc_w         #587                // int 2130968982
     366: iastore
     367: dup
     368: iconst_3
     369: ldc_w         #588                // int 2130968983
     372: iastore
     373: putstatic     #590                // Field AppCompatImageView:[I
     376: iconst_4
     377: newarray       int
     379: dup
     380: iconst_0
     381: ldc_w         #591                // int 16843074
     384: iastore
     385: dup
     386: iconst_1
     387: ldc_w         #592                // int 2130968979
     390: iastore
     391: dup
     392: iconst_2
     393: ldc_w         #593                // int 2130968980
     396: iastore
     397: dup
     398: iconst_3
     399: ldc_w         #594                // int 2130968981
     402: iastore
     403: putstatic     #596                // Field AppCompatSeekBar:[I
     406: bipush        7
     408: newarray       int
     410: dup
     411: iconst_0
     412: ldc_w         #597                // int 16842804
     415: iastore
     416: dup
     417: iconst_1
     418: ldc_w         #598                // int 16843117
     421: iastore
     422: dup
     423: iconst_2
     424: ldc_w         #599                // int 16843118
     427: iastore
     428: dup
     429: iconst_3
     430: ldc_w         #600                // int 16843119
     433: iastore
     434: dup
     435: iconst_4
     436: ldc_w         #601                // int 16843120
     439: iastore
     440: dup
     441: iconst_5
     442: ldc_w         #602                // int 16843666
     445: iastore
     446: dup
     447: bipush        6
     449: ldc_w         #603                // int 16843667
     452: iastore
     453: putstatic     #605                // Field AppCompatTextHelper:[I
     456: bipush        8
     458: newarray       int
     460: dup
     461: iconst_0
     462: ldc_w         #597                // int 16842804
     465: iastore
     466: dup
     467: iconst_1
     468: ldc_w         #606                // int 2130968623
     471: iastore
     472: dup
     473: iconst_2
     474: ldc_w         #607                // int 2130968624
     477: iastore
     478: dup
     479: iconst_3
     480: ldc_w         #608                // int 2130968625
     483: iastore
     484: dup
     485: iconst_4
     486: ldc_w         #609                // int 2130968626
     489: iastore
     490: dup
     491: iconst_5
     492: ldc_w         #610                // int 2130968627
     495: iastore
     496: dup
     497: bipush        6
     499: ldc_w         #611                // int 2130968746
     502: iastore
     503: dup
     504: bipush        7
     506: ldc_w         #612                // int 2130968962
     509: iastore
     510: putstatic     #614                // Field AppCompatTextView:[I
     513: bipush        120
     515: newarray       int
     517: dup
     518: iconst_0
     519: ldc_w         #615                // int 16842839
     522: iastore
     523: dup
     524: iconst_1
     525: ldc_w         #616                // int 16842926
     528: iastore
     529: dup
     530: iconst_2
     531: ldc_w         #617                // int 2130968576
     534: iastore
     535: dup
     536: iconst_3
     537: ldc_w         #618                // int 2130968577
     540: iastore
     541: dup
     542: iconst_4
     543: ldc_w         #619                // int 2130968578
     546: iastore
     547: dup
     548: iconst_5
     549: ldc_w         #620                // int 2130968579
     552: iastore
     553: dup
     554: bipush        6
     556: ldc_w         #621                // int 2130968580
     559: iastore
     560: dup
     561: bipush        7
     563: ldc_w         #622                // int 2130968581
     566: iastore
     567: dup
     568: bipush        8
     570: ldc_w         #623                // int 2130968582
     573: iastore
     574: dup
     575: bipush        9
     577: ldc_w         #624                // int 2130968583
     580: iastore
     581: dup
     582: bipush        10
     584: ldc_w         #625                // int 2130968584
     587: iastore
     588: dup
     589: bipush        11
     591: ldc_w         #626                // int 2130968585
     594: iastore
     595: dup
     596: bipush        12
     598: ldc_w         #627                // int 2130968586
     601: iastore
     602: dup
     603: bipush        13
     605: ldc_w         #628                // int 2130968587
     608: iastore
     609: dup
     610: bipush        14
     612: ldc_w         #629                // int 2130968588
     615: iastore
     616: dup
     617: bipush        15
     619: ldc_w         #630                // int 2130968590
     622: iastore
     623: dup
     624: bipush        16
     626: ldc_w         #631                // int 2130968591
     629: iastore
     630: dup
     631: bipush        17
     633: ldc_w         #632                // int 2130968592
     636: iastore
     637: dup
     638: bipush        18
     640: ldc_w         #633                // int 2130968593
     643: iastore
     644: dup
     645: bipush        19
     647: ldc_w         #634                // int 2130968594
     650: iastore
     651: dup
     652: bipush        20
     654: ldc_w         #635                // int 2130968595
     657: iastore
     658: dup
     659: bipush        21
     661: ldc_w         #636                // int 2130968596
     664: iastore
     665: dup
     666: bipush        22
     668: ldc_w         #637                // int 2130968597
     671: iastore
     672: dup
     673: bipush        23
     675: ldc_w         #638                // int 2130968598
     678: iastore
     679: dup
     680: bipush        24
     682: ldc_w         #639                // int 2130968599
     685: iastore
     686: dup
     687: bipush        25
     689: ldc_w         #640                // int 2130968600
     692: iastore
     693: dup
     694: bipush        26
     696: ldc_w         #641                // int 2130968601
     699: iastore
     700: dup
     701: bipush        27
     703: ldc_w         #642                // int 2130968602
     706: iastore
     707: dup
     708: bipush        28
     710: ldc_w         #643                // int 2130968603
     713: iastore
     714: dup
     715: bipush        29
     717: ldc_w         #644                // int 2130968604
     720: iastore
     721: dup
     722: bipush        30
     724: ldc_w         #645                // int 2130968605
     727: iastore
     728: dup
     729: bipush        31
     731: ldc_w         #646                // int 2130968606
     734: iastore
     735: dup
     736: bipush        32
     738: ldc_w         #647                // int 2130968609
     741: iastore
     742: dup
     743: bipush        33
     745: ldc_w         #648                // int 2130968610
     748: iastore
     749: dup
     750: bipush        34
     752: ldc_w         #649                // int 2130968611
     755: iastore
     756: dup
     757: bipush        35
     759: ldc_w         #650                // int 2130968612
     762: iastore
     763: dup
     764: bipush        36
     766: ldc_w         #651                // int 2130968613
     769: iastore
     770: dup
     771: bipush        37
     773: ldc_w         #652                // int 2130968622
     776: iastore
     777: dup
     778: bipush        38
     780: ldc_w         #653                // int 2130968642
     783: iastore
     784: dup
     785: bipush        39
     787: ldc_w         #654                // int 2130968645
     790: iastore
     791: dup
     792: bipush        40
     794: ldc_w         #655                // int 2130968646
     797: iastore
     798: dup
     799: bipush        41
     801: ldc_w         #656                // int 2130968647
     804: iastore
     805: dup
     806: bipush        42
     808: ldc_w         #657                // int 2130968648
     811: iastore
     812: dup
     813: bipush        43
     815: ldc_w         #658                // int 2130968649
     818: iastore
     819: dup
     820: bipush        44
     822: ldc_w         #659                // int 2130968653
     825: iastore
     826: dup
     827: bipush        45
     829: ldc_w         #660                // int 2130968654
     832: iastore
     833: dup
     834: bipush        46
     836: ldc_w         #661                // int 2130968665
     839: iastore
     840: dup
     841: bipush        47
     843: ldc_w         #662                // int 2130968666
     846: iastore
     847: dup
     848: bipush        48
     850: ldc_w         #663                // int 2130968674
     853: iastore
     854: dup
     855: bipush        49
     857: ldc_w         #664                // int 2130968675
     860: iastore
     861: dup
     862: bipush        50
     864: ldc_w         #665                // int 2130968676
     867: iastore
     868: dup
     869: bipush        51
     871: ldc_w         #666                // int 2130968677
     874: iastore
     875: dup
     876: bipush        52
     878: ldc_w         #667                // int 2130968678
     881: iastore
     882: dup
     883: bipush        53
     885: ldc_w         #668                // int 2130968679
     888: iastore
     889: dup
     890: bipush        54
     892: ldc_w         #669                // int 2130968680
     895: iastore
     896: dup
     897: bipush        55
     899: ldc_w         #670                // int 2130968681
     902: iastore
     903: dup
     904: bipush        56
     906: ldc_w         #671                // int 2130968682
     909: iastore
     910: dup
     911: bipush        57
     913: ldc_w         #672                // int 2130968683
     916: iastore
     917: dup
     918: bipush        58
     920: ldc_w         #673                // int 2130968701
     923: iastore
     924: dup
     925: bipush        59
     927: ldc_w         #674                // int 2130968710
     930: iastore
     931: dup
     932: bipush        60
     934: ldc_w         #675                // int 2130968711
     937: iastore
     938: dup
     939: bipush        61
     941: ldc_w         #676                // int 2130968714
     944: iastore
     945: dup
     946: bipush        62
     948: ldc_w         #677                // int 2130968716
     951: iastore
     952: dup
     953: bipush        63
     955: ldc_w         #678                // int 2130968719
     958: iastore
     959: dup
     960: bipush        64
     962: ldc_w         #679                // int 2130968720
     965: iastore
     966: dup
     967: bipush        65
     969: ldc_w         #680                // int 2130968721
     972: iastore
     973: dup
     974: bipush        66
     976: ldc_w         #681                // int 2130968722
     979: iastore
     980: dup
     981: bipush        67
     983: ldc_w         #682                // int 2130968723
     986: iastore
     987: dup
     988: bipush        68
     990: ldc_w         #546                // int 2130968766
     993: iastore
     994: dup
     995: bipush        69
     997: ldc_w         #683                // int 2130968773
    1000: iastore
    1001: dup
    1002: bipush        70
    1004: ldc_w         #684                // int 2130968852
    1007: iastore
    1008: dup
    1009: bipush        71
    1011: ldc_w         #685                // int 2130968853
    1014: iastore
    1015: dup
    1016: bipush        72
    1018: ldc_w         #686                // int 2130968856
    1021: iastore
    1022: dup
    1023: bipush        73
    1025: ldc_w         #687                // int 2130968857
    1028: iastore
    1029: dup
    1030: bipush        74
    1032: ldc_w         #688                // int 2130968858
    1035: iastore
    1036: dup
    1037: bipush        75
    1039: ldc_w         #689                // int 2130968859
    1042: iastore
    1043: dup
    1044: bipush        76
    1046: ldc_w         #690                // int 2130968860
    1049: iastore
    1050: dup
    1051: bipush        77
    1053: ldc_w         #691                // int 2130968861
    1056: iastore
    1057: dup
    1058: bipush        78
    1060: ldc_w         #692                // int 2130968862
    1063: iastore
    1064: dup
    1065: bipush        79
    1067: ldc_w         #693                // int 2130968886
    1070: iastore
    1071: dup
    1072: bipush        80
    1074: ldc_w         #694                // int 2130968887
    1077: iastore
    1078: dup
    1079: bipush        81
    1081: ldc_w         #695                // int 2130968888
    1084: iastore
    1085: dup
    1086: bipush        82
    1088: ldc_w         #696                // int 2130968894
    1091: iastore
    1092: dup
    1093: bipush        83
    1095: ldc_w         #697                // int 2130968896
    1098: iastore
    1099: dup
    1100: bipush        84
    1102: ldc_w         #698                // int 2130968903
    1105: iastore
    1106: dup
    1107: bipush        85
    1109: ldc_w         #699                // int 2130968904
    1112: iastore
    1113: dup
    1114: bipush        86
    1116: ldc_w         #700                // int 2130968905
    1119: iastore
    1120: dup
    1121: bipush        87
    1123: ldc_w         #701                // int 2130968906
    1126: iastore
    1127: dup
    1128: bipush        88
    1130: ldc_w         #702                // int 2130968913
    1133: iastore
    1134: dup
    1135: bipush        89
    1137: ldc_w         #703                // int 2130968914
    1140: iastore
    1141: dup
    1142: bipush        90
    1144: ldc_w         #704                // int 2130968915
    1147: iastore
    1148: dup
    1149: bipush        91
    1151: ldc_w         #705                // int 2130968916
    1154: iastore
    1155: dup
    1156: bipush        92
    1158: ldc_w         #706                // int 2130968924
    1161: iastore
    1162: dup
    1163: bipush        93
    1165: ldc_w         #707                // int 2130968925
    1168: iastore
    1169: dup
    1170: bipush        94
    1172: ldc_w         #708                // int 2130968944
    1175: iastore
    1176: dup
    1177: bipush        95
    1179: ldc_w         #709                // int 2130968963
    1182: iastore
    1183: dup
    1184: bipush        96
    1186: ldc_w         #710                // int 2130968964
    1189: iastore
    1190: dup
    1191: bipush        97
    1193: ldc_w         #711                // int 2130968965
    1196: iastore
    1197: dup
    1198: bipush        98
    1200: ldc_w         #712                // int 2130968966
    1203: iastore
    1204: dup
    1205: bipush        99
    1207: ldc_w         #713                // int 2130968967
    1210: iastore
    1211: dup
    1212: bipush        100
    1214: ldc_w         #714                // int 2130968968
    1217: iastore
    1218: dup
    1219: bipush        101
    1221: ldc_w         #715                // int 2130968969
    1224: iastore
    1225: dup
    1226: bipush        102
    1228: ldc_w         #716                // int 2130968970
    1231: iastore
    1232: dup
    1233: bipush        103
    1235: ldc_w         #717                // int 2130968971
    1238: iastore
    1239: dup
    1240: bipush        104
    1242: ldc_w         #718                // int 2130968973
    1245: iastore
    1246: dup
    1247: bipush        105
    1249: ldc_w         #719                // int 2130968996
    1252: iastore
    1253: dup
    1254: bipush        106
    1256: ldc_w         #720                // int 2130968997
    1259: iastore
    1260: dup
    1261: bipush        107
    1263: ldc_w         #721                // int 2130968998
    1266: iastore
    1267: dup
    1268: bipush        108
    1270: ldc_w         #722                // int 2130968999
    1273: iastore
    1274: dup
    1275: bipush        109
    1277: ldc_w         #723                // int 2130969009
    1280: iastore
    1281: dup
    1282: bipush        110
    1284: ldc_w         #724                // int 2130969012
    1287: iastore
    1288: dup
    1289: bipush        111
    1291: ldc_w         #725                // int 2130969013
    1294: iastore
    1295: dup
    1296: bipush        112
    1298: ldc_w         #726                // int 2130969014
    1301: iastore
    1302: dup
    1303: bipush        113
    1305: ldc_w         #727                // int 2130969015
    1308: iastore
    1309: dup
    1310: bipush        114
    1312: ldc_w         #728                // int 2130969016
    1315: iastore
    1316: dup
    1317: bipush        115
    1319: ldc_w         #729                // int 2130969017
    1322: iastore
    1323: dup
    1324: bipush        116
    1326: ldc_w         #730                // int 2130969018
    1329: iastore
    1330: dup
    1331: bipush        117
    1333: ldc_w         #731                // int 2130969019
    1336: iastore
    1337: dup
    1338: bipush        118
    1340: ldc_w         #732                // int 2130969020
    1343: iastore
    1344: dup
    1345: bipush        119
    1347: ldc_w         #733                // int 2130969021
    1350: iastore
    1351: putstatic     #735                // Field AppCompatTheme:[I
    1354: iconst_1
    1355: newarray       int
    1357: dup
    1358: iconst_0
    1359: ldc_w         #736                // int 2130968616
    1362: iastore
    1363: putstatic     #738                // Field ButtonBarLayout:[I
    1366: iconst_3
    1367: newarray       int
    1369: dup
    1370: iconst_0
    1371: ldc_w         #739                // int 16843173
    1374: iastore
    1375: dup
    1376: iconst_1
    1377: ldc_w         #740                // int 16843551
    1380: iastore
    1381: dup
    1382: iconst_2
    1383: ldc_w         #741                // int 2130968617
    1386: iastore
    1387: putstatic     #743                // Field ColorStateListItem:[I
    1390: iconst_3
    1391: newarray       int
    1393: dup
    1394: iconst_0
    1395: ldc_w         #744                // int 16843015
    1398: iastore
    1399: dup
    1400: iconst_1
    1401: ldc_w         #745                // int 2130968655
    1404: iastore
    1405: dup
    1406: iconst_2
    1407: ldc_w         #746                // int 2130968656
    1410: iastore
    1411: putstatic     #748                // Field CompoundButton:[I
    1414: bipush        8
    1416: newarray       int
    1418: dup
    1419: iconst_0
    1420: ldc_w         #749                // int 2130968620
    1423: iastore
    1424: dup
    1425: iconst_1
    1426: ldc_w         #750                // int 2130968621
    1429: iastore
    1430: dup
    1431: iconst_2
    1432: ldc_w         #751                // int 2130968633
    1435: iastore
    1436: dup
    1437: iconst_3
    1438: ldc_w         #752                // int 2130968673
    1441: iastore
    1442: dup
    1443: iconst_4
    1444: ldc_w         #753                // int 2130968717
    1447: iastore
    1448: dup
    1449: iconst_5
    1450: ldc_w         #754                // int 2130968756
    1453: iastore
    1454: dup
    1455: bipush        6
    1457: ldc_w         #755                // int 2130968923
    1460: iastore
    1461: dup
    1462: bipush        7
    1464: ldc_w         #756                // int 2130968975
    1467: iastore
    1468: putstatic     #758                // Field DrawerArrowToggle:[I
    1471: bipush        6
    1473: newarray       int
    1475: dup
    1476: iconst_0
    1477: ldc_w         #759                // int 2130968747
    1480: iastore
    1481: dup
    1482: iconst_1
    1483: ldc_w         #760                // int 2130968748
    1486: iastore
    1487: dup
    1488: iconst_2
    1489: ldc_w         #761                // int 2130968749
    1492: iastore
    1493: dup
    1494: iconst_3
    1495: ldc_w         #762                // int 2130968750
    1498: iastore
    1499: dup
    1500: iconst_4
    1501: ldc_w         #763                // int 2130968751
    1504: iastore
    1505: dup
    1506: iconst_5
    1507: ldc_w         #764                // int 2130968752
    1510: iastore
    1511: putstatic     #766                // Field FontFamily:[I
    1514: bipush        6
    1516: newarray       int
    1518: dup
    1519: iconst_0
    1520: ldc_w         #767                // int 16844082
    1523: iastore
    1524: dup
    1525: iconst_1
    1526: ldc_w         #768                // int 16844083
    1529: iastore
    1530: dup
    1531: iconst_2
    1532: ldc_w         #769                // int 16844095
    1535: iastore
    1536: dup
    1537: iconst_3
    1538: ldc_w         #770                // int 2130968745
    1541: iastore
    1542: dup
    1543: iconst_4
    1544: ldc_w         #771                // int 2130968753
    1547: iastore
    1548: dup
    1549: iconst_5
    1550: ldc_w         #772                // int 2130968754
    1553: iastore
    1554: putstatic     #774                // Field FontFamilyFont:[I
    1557: bipush        9
    1559: newarray       int
    1561: dup
    1562: iconst_0
    1563: ldc_w         #775                // int 16842927
    1566: iastore
    1567: dup
    1568: iconst_1
    1569: ldc_w         #776                // int 16842948
    1572: iastore
    1573: dup
    1574: iconst_2
    1575: ldc_w         #777                // int 16843046
    1578: iastore
    1579: dup
    1580: iconst_3
    1581: ldc_w         #778                // int 16843047
    1584: iastore
    1585: dup
    1586: iconst_4
    1587: ldc_w         #779                // int 16843048
    1590: iastore
    1591: dup
    1592: iconst_5
    1593: ldc_w         #542                // int 2130968713
    1596: iastore
    1597: dup
    1598: bipush        6
    1600: ldc_w         #780                // int 2130968715
    1603: iastore
    1604: dup
    1605: bipush        7
    1607: ldc_w         #781                // int 2130968869
    1610: iastore
    1611: dup
    1612: bipush        8
    1614: ldc_w         #782                // int 2130968918
    1617: iastore
    1618: putstatic     #784                // Field LinearLayoutCompat:[I
    1621: iconst_4
    1622: newarray       int
    1624: dup
    1625: iconst_0
    1626: ldc_w         #562                // int 16842931
    1629: iastore
    1630: dup
    1631: iconst_1
    1632: ldc_w         #785                // int 16842996
    1635: iastore
    1636: dup
    1637: iconst_2
    1638: ldc_w         #786                // int 16842997
    1641: iastore
    1642: dup
    1643: iconst_3
    1644: ldc_w         #787                // int 16843137
    1647: iastore
    1648: putstatic     #789                // Field LinearLayoutCompat_Layout:[I
    1651: iconst_2
    1652: newarray       int
    1654: dup
    1655: iconst_0
    1656: ldc_w         #790                // int 16843436
    1659: iastore
    1660: dup
    1661: iconst_1
    1662: ldc_w         #791                // int 16843437
    1665: iastore
    1666: putstatic     #793                // Field ListPopupWindow:[I
    1669: bipush        6
    1671: newarray       int
    1673: dup
    1674: iconst_0
    1675: ldc_w         #794                // int 16842766
    1678: iastore
    1679: dup
    1680: iconst_1
    1681: ldc_w         #795                // int 16842960
    1684: iastore
    1685: dup
    1686: iconst_2
    1687: ldc_w         #796                // int 16843156
    1690: iastore
    1691: dup
    1692: iconst_3
    1693: ldc_w         #797                // int 16843230
    1696: iastore
    1697: dup
    1698: iconst_4
    1699: ldc_w         #798                // int 16843231
    1702: iastore
    1703: dup
    1704: iconst_5
    1705: ldc_w         #799                // int 16843232
    1708: iastore
    1709: putstatic     #801                // Field MenuGroup:[I
    1712: bipush        23
    1714: newarray       int
    1716: dup
    1717: iconst_0
    1718: ldc_w         #802                // int 16842754
    1721: iastore
    1722: dup
    1723: iconst_1
    1724: ldc_w         #794                // int 16842766
    1727: iastore
    1728: dup
    1729: iconst_2
    1730: ldc_w         #795                // int 16842960
    1733: iastore
    1734: dup
    1735: iconst_3
    1736: ldc_w         #803                // int 16843014
    1739: iastore
    1740: dup
    1741: iconst_4
    1742: ldc_w         #796                // int 16843156
    1745: iastore
    1746: dup
    1747: iconst_5
    1748: ldc_w         #797                // int 16843230
    1751: iastore
    1752: dup
    1753: bipush        6
    1755: ldc_w         #798                // int 16843231
    1758: iastore
    1759: dup
    1760: bipush        7
    1762: ldc_w         #804                // int 16843233
    1765: iastore
    1766: dup
    1767: bipush        8
    1769: ldc_w         #805                // int 16843234
    1772: iastore
    1773: dup
    1774: bipush        9
    1776: ldc_w         #806                // int 16843235
    1779: iastore
    1780: dup
    1781: bipush        10
    1783: ldc_w         #807                // int 16843236
    1786: iastore
    1787: dup
    1788: bipush        11
    1790: ldc_w         #808                // int 16843237
    1793: iastore
    1794: dup
    1795: bipush        12
    1797: ldc_w         #809                // int 16843375
    1800: iastore
    1801: dup
    1802: bipush        13
    1804: ldc_w         #810                // int 2130968589
    1807: iastore
    1808: dup
    1809: bipush        14
    1811: ldc_w         #811                // int 2130968607
    1814: iastore
    1815: dup
    1816: bipush        15
    1818: ldc_w         #812                // int 2130968608
    1821: iastore
    1822: dup
    1823: bipush        16
    1825: ldc_w         #813                // int 2130968618
    1828: iastore
    1829: dup
    1830: bipush        17
    1832: ldc_w         #814                // int 2130968688
    1835: iastore
    1836: dup
    1837: bipush        18
    1839: ldc_w         #815                // int 2130968770
    1842: iastore
    1843: dup
    1844: bipush        19
    1846: ldc_w         #816                // int 2130968771
    1849: iastore
    1850: dup
    1851: bipush        20
    1853: ldc_w         #817                // int 2130968877
    1856: iastore
    1857: dup
    1858: bipush        21
    1860: ldc_w         #818                // int 2130968917
    1863: iastore
    1864: dup
    1865: bipush        22
    1867: ldc_w         #819                // int 2130969000
    1870: iastore
    1871: putstatic     #821                // Field MenuItem:[I
    1874: bipush        9
    1876: newarray       int
    1878: dup
    1879: iconst_0
    1880: ldc_w         #616                // int 16842926
    1883: iastore
    1884: dup
    1885: iconst_1
    1886: ldc_w         #822                // int 16843052
    1889: iastore
    1890: dup
    1891: iconst_2
    1892: ldc_w         #823                // int 16843053
    1895: iastore
    1896: dup
    1897: iconst_3
    1898: ldc_w         #824                // int 16843054
    1901: iastore
    1902: dup
    1903: iconst_4
    1904: ldc_w         #825                // int 16843055
    1907: iastore
    1908: dup
    1909: iconst_5
    1910: ldc_w         #826                // int 16843056
    1913: iastore
    1914: dup
    1915: bipush        6
    1917: ldc_w         #827                // int 16843057
    1920: iastore
    1921: dup
    1922: bipush        7
    1924: ldc_w         #828                // int 2130968897
    1927: iastore
    1928: dup
    1929: bipush        8
    1931: ldc_w         #829                // int 2130968935
    1934: iastore
    1935: putstatic     #831                // Field MenuView:[I
    1938: iconst_3
    1939: newarray       int
    1941: dup
    1942: iconst_0
    1943: ldc_w         #832                // int 16843126
    1946: iastore
    1947: dup
    1948: iconst_1
    1949: ldc_w         #833                // int 16843465
    1952: iastore
    1953: dup
    1954: iconst_2
    1955: ldc_w         #834                // int 2130968881
    1958: iastore
    1959: putstatic     #836                // Field PopupWindow:[I
    1962: iconst_1
    1963: newarray       int
    1965: dup
    1966: iconst_0
    1967: ldc_w         #837                // int 2130968929
    1970: iastore
    1971: putstatic     #839                // Field PopupWindowBackgroundState:[I
    1974: iconst_2
    1975: newarray       int
    1977: dup
    1978: iconst_0
    1979: ldc_w         #840                // int 2130968882
    1982: iastore
    1983: dup
    1984: iconst_1
    1985: ldc_w         #841                // int 2130968885
    1988: iastore
    1989: putstatic     #843                // Field RecycleListView:[I
    1992: bipush        17
    1994: newarray       int
    1996: dup
    1997: iconst_0
    1998: ldc_w         #844                // int 16842970
    2001: iastore
    2002: dup
    2003: iconst_1
    2004: ldc_w         #845                // int 16843039
    2007: iastore
    2008: dup
    2009: iconst_2
    2010: ldc_w         #846                // int 16843296
    2013: iastore
    2014: dup
    2015: iconst_3
    2016: ldc_w         #847                // int 16843364
    2019: iastore
    2020: dup
    2021: iconst_4
    2022: ldc_w         #848                // int 2130968667
    2025: iastore
    2026: dup
    2027: iconst_5
    2028: ldc_w         #849                // int 2130968684
    2031: iastore
    2032: dup
    2033: bipush        6
    2035: ldc_w         #850                // int 2130968709
    2038: iastore
    2039: dup
    2040: bipush        7
    2042: ldc_w         #851                // int 2130968757
    2045: iastore
    2046: dup
    2047: bipush        8
    2049: ldc_w         #852                // int 2130968772
    2052: iastore
    2053: dup
    2054: bipush        9
    2056: ldc_w         #853                // int 2130968785
    2059: iastore
    2060: dup
    2061: bipush        10
    2063: ldc_w         #854                // int 2130968901
    2066: iastore
    2067: dup
    2068: bipush        11
    2070: ldc_w         #855                // int 2130968902
    2073: iastore
    2074: dup
    2075: bipush        12
    2077: ldc_w         #856                // int 2130968911
    2080: iastore
    2081: dup
    2082: bipush        13
    2084: ldc_w         #857                // int 2130968912
    2087: iastore
    2088: dup
    2089: bipush        14
    2091: ldc_w         #858                // int 2130968936
    2094: iastore
    2095: dup
    2096: bipush        15
    2098: ldc_w         #859                // int 2130968941
    2101: iastore
    2102: dup
    2103: bipush        16
    2105: ldc_w         #860                // int 2130969010
    2108: iastore
    2109: putstatic     #862                // Field SearchView:[I
    2112: iconst_5
    2113: newarray       int
    2115: dup
    2116: iconst_0
    2117: ldc_w         #863                // int 16842930
    2120: iastore
    2121: dup
    2122: iconst_1
    2123: ldc_w         #832                // int 16843126
    2126: iastore
    2127: dup
    2128: iconst_2
    2129: ldc_w         #864                // int 16843131
    2132: iastore
    2133: dup
    2134: iconst_3
    2135: ldc_w         #865                // int 16843362
    2138: iastore
    2139: dup
    2140: iconst_4
    2141: ldc_w         #553                // int 2130968895
    2144: iastore
    2145: putstatic     #867                // Field Spinner:[I
    2148: bipush        14
    2150: newarray       int
    2152: dup
    2153: iconst_0
    2154: ldc_w         #868                // int 16843044
    2157: iastore
    2158: dup
    2159: iconst_1
    2160: ldc_w         #869                // int 16843045
    2163: iastore
    2164: dup
    2165: iconst_2
    2166: ldc_w         #591                // int 16843074
    2169: iastore
    2170: dup
    2171: iconst_3
    2172: ldc_w         #870                // int 2130968919
    2175: iastore
    2176: dup
    2177: iconst_4
    2178: ldc_w         #871                // int 2130968926
    2181: iastore
    2182: dup
    2183: iconst_5
    2184: ldc_w         #872                // int 2130968942
    2187: iastore
    2188: dup
    2189: bipush        6
    2191: ldc_w         #873                // int 2130968943
    2194: iastore
    2195: dup
    2196: bipush        7
    2198: ldc_w         #874                // int 2130968945
    2201: iastore
    2202: dup
    2203: bipush        8
    2205: ldc_w         #875                // int 2130968976
    2208: iastore
    2209: dup
    2210: bipush        9
    2212: ldc_w         #876                // int 2130968977
    2215: iastore
    2216: dup
    2217: bipush        10
    2219: ldc_w         #877                // int 2130968978
    2222: iastore
    2223: dup
    2224: bipush        11
    2226: ldc_w         #878                // int 2130969001
    2229: iastore
    2230: dup
    2231: bipush        12
    2233: ldc_w         #879                // int 2130969002
    2236: iastore
    2237: dup
    2238: bipush        13
    2240: ldc_w         #880                // int 2130969003
    2243: iastore
    2244: putstatic     #882                // Field SwitchCompat:[I
    2247: bipush        13
    2249: newarray       int
    2251: dup
    2252: iconst_0
    2253: ldc_w         #883                // int 16842901
    2256: iastore
    2257: dup
    2258: iconst_1
    2259: ldc_w         #884                // int 16842902
    2262: iastore
    2263: dup
    2264: iconst_2
    2265: ldc_w         #885                // int 16842903
    2268: iastore
    2269: dup
    2270: iconst_3
    2271: ldc_w         #886                // int 16842904
    2274: iastore
    2275: dup
    2276: iconst_4
    2277: ldc_w         #887                // int 16842906
    2280: iastore
    2281: dup
    2282: iconst_5
    2283: ldc_w         #888                // int 16842907
    2286: iastore
    2287: dup
    2288: bipush        6
    2290: ldc_w         #889                // int 16843105
    2293: iastore
    2294: dup
    2295: bipush        7
    2297: ldc_w         #890                // int 16843106
    2300: iastore
    2301: dup
    2302: bipush        8
    2304: ldc_w         #891                // int 16843107
    2307: iastore
    2308: dup
    2309: bipush        9
    2311: ldc_w         #892                // int 16843108
    2314: iastore
    2315: dup
    2316: bipush        10
    2318: ldc_w         #893                // int 16843692
    2321: iastore
    2322: dup
    2323: bipush        11
    2325: ldc_w         #611                // int 2130968746
    2328: iastore
    2329: dup
    2330: bipush        12
    2332: ldc_w         #612                // int 2130968962
    2335: iastore
    2336: putstatic     #895                // Field TextAppearance:[I
    2339: bipush        29
    2341: newarray       int
    2343: dup
    2344: iconst_0
    2345: ldc_w         #775                // int 16842927
    2348: iastore
    2349: dup
    2350: iconst_1
    2351: ldc_w         #896                // int 16843072
    2354: iastore
    2355: dup
    2356: iconst_2
    2357: ldc_w         #897                // int 2130968650
    2360: iastore
    2361: dup
    2362: iconst_3
    2363: ldc_w         #898                // int 2130968669
    2366: iastore
    2367: dup
    2368: iconst_4
    2369: ldc_w         #899                // int 2130968670
    2372: iastore
    2373: dup
    2374: iconst_5
    2375: ldc_w         #534                // int 2130968689
    2378: iastore
    2379: dup
    2380: bipush        6
    2382: ldc_w         #535                // int 2130968690
    2385: iastore
    2386: dup
    2387: bipush        7
    2389: ldc_w         #536                // int 2130968691
    2392: iastore
    2393: dup
    2394: bipush        8
    2396: ldc_w         #537                // int 2130968692
    2399: iastore
    2400: dup
    2401: bipush        9
    2403: ldc_w         #538                // int 2130968693
    2406: iastore
    2407: dup
    2408: bipush        10
    2410: ldc_w         #539                // int 2130968694
    2413: iastore
    2414: dup
    2415: bipush        11
    2417: ldc_w         #551                // int 2130968863
    2420: iastore
    2421: dup
    2422: bipush        12
    2424: ldc_w         #900                // int 2130968864
    2427: iastore
    2428: dup
    2429: bipush        13
    2431: ldc_w         #901                // int 2130968866
    2434: iastore
    2435: dup
    2436: bipush        14
    2438: ldc_w         #902                // int 2130968874
    2441: iastore
    2442: dup
    2443: bipush        15
    2445: ldc_w         #903                // int 2130968875
    2448: iastore
    2449: dup
    2450: bipush        16
    2452: ldc_w         #553                // int 2130968895
    2455: iastore
    2456: dup
    2457: bipush        17
    2459: ldc_w         #556                // int 2130968937
    2462: iastore
    2463: dup
    2464: bipush        18
    2466: ldc_w         #904                // int 2130968938
    2469: iastore
    2470: dup
    2471: bipush        19
    2473: ldc_w         #905                // int 2130968939
    2476: iastore
    2477: dup
    2478: bipush        20
    2480: ldc_w         #558                // int 2130968984
    2483: iastore
    2484: dup
    2485: bipush        21
    2487: ldc_w         #906                // int 2130968986
    2490: iastore
    2491: dup
    2492: bipush        22
    2494: ldc_w         #907                // int 2130968987
    2497: iastore
    2498: dup
    2499: bipush        23
    2501: ldc_w         #908                // int 2130968988
    2504: iastore
    2505: dup
    2506: bipush        24
    2508: ldc_w         #909                // int 2130968989
    2511: iastore
    2512: dup
    2513: bipush        25
    2515: ldc_w         #910                // int 2130968990
    2518: iastore
    2519: dup
    2520: bipush        26
    2522: ldc_w         #911                // int 2130968991
    2525: iastore
    2526: dup
    2527: bipush        27
    2529: ldc_w         #912                // int 2130968992
    2532: iastore
    2533: dup
    2534: bipush        28
    2536: ldc_w         #913                // int 2130968993
    2539: iastore
    2540: putstatic     #915                // Field Toolbar:[I
    2543: iconst_5
    2544: newarray       int
    2546: dup
    2547: iconst_0
    2548: ldc_w         #916                // int 16842752
    2551: iastore
    2552: dup
    2553: iconst_1
    2554: ldc_w         #844                // int 16842970
    2557: iastore
    2558: dup
    2559: iconst_2
    2560: ldc_w         #917                // int 2130968883
    2563: iastore
    2564: dup
    2565: iconst_3
    2566: ldc_w         #918                // int 2130968884
    2569: iastore
    2570: dup
    2571: iconst_4
    2572: ldc_w         #919                // int 2130968974
    2575: iastore
    2576: putstatic     #921                // Field View:[I
    2579: iconst_3
    2580: newarray       int
    2582: dup
    2583: iconst_0
    2584: ldc_w         #922                // int 16842964
    2587: iastore
    2588: dup
    2589: iconst_1
    2590: ldc_w         #923                // int 2130968631
    2593: iastore
    2594: dup
    2595: iconst_2
    2596: ldc_w         #924                // int 2130968632
    2599: iastore
    2600: putstatic     #926                // Field ViewBackgroundHelper:[I
    2603: iconst_3
    2604: newarray       int
    2606: dup
    2607: iconst_0
    2608: ldc_w         #795                // int 16842960
    2611: iastore
    2612: dup
    2613: iconst_1
    2614: ldc_w         #575                // int 16842994
    2617: iastore
    2618: dup
    2619: iconst_2
    2620: ldc_w         #927                // int 16842995
    2623: iastore
    2624: putstatic     #929                // Field ViewStubCompat:[I
    2627: return

  public com.github.paolorotolo.appintro.R$styleable();
    Code:
       0: aload_0
       1: invokespecial #933                // Method java/lang/Object."<init>":()V
       4: return
}
