class com.github.paolorotolo.appintro.ViewPageTransformer$1 {
  static final int[] $SwitchMap$com$github$paolorotolo$appintro$ViewPageTransformer$TransformType;

  static {};
    Code:
       0: invokestatic  #18                 // Method com/github/paolorotolo/appintro/ViewPageTransformer$TransformType.values:()[Lcom/github/paolorotolo/appintro/ViewPageTransformer$TransformType;
       3: arraylength
       4: newarray       int
       6: putstatic     #20                 // Field $SwitchMap$com$github$paolorotolo$appintro$ViewPageTransformer$TransformType:[I
       9: getstatic     #20                 // Field $SwitchMap$com$github$paolorotolo$appintro$ViewPageTransformer$TransformType:[I
      12: getstatic     #24                 // Field com/github/paolorotolo/appintro/ViewPageTransformer$TransformType.FLOW:Lcom/github/paolorotolo/appintro/ViewPageTransformer$TransformType;
      15: invokevirtual #28                 // Method com/github/paolorotolo/appintro/ViewPageTransformer$TransformType.ordinal:()I
      18: iconst_1
      19: iastore
      20: getstatic     #20                 // Field $SwitchMap$com$github$paolorotolo$appintro$ViewPageTransformer$TransformType:[I
      23: getstatic     #31                 // Field com/github/paolorotolo/appintro/ViewPageTransformer$TransformType.SLIDE_OVER:Lcom/github/paolorotolo/appintro/ViewPageTransformer$TransformType;
      26: invokevirtual #28                 // Method com/github/paolorotolo/appintro/ViewPageTransformer$TransformType.ordinal:()I
      29: iconst_2
      30: iastore
      31: getstatic     #20                 // Field $SwitchMap$com$github$paolorotolo$appintro$ViewPageTransformer$TransformType:[I
      34: getstatic     #34                 // Field com/github/paolorotolo/appintro/ViewPageTransformer$TransformType.DEPTH:Lcom/github/paolorotolo/appintro/ViewPageTransformer$TransformType;
      37: invokevirtual #28                 // Method com/github/paolorotolo/appintro/ViewPageTransformer$TransformType.ordinal:()I
      40: iconst_3
      41: iastore
      42: getstatic     #20                 // Field $SwitchMap$com$github$paolorotolo$appintro$ViewPageTransformer$TransformType:[I
      45: getstatic     #37                 // Field com/github/paolorotolo/appintro/ViewPageTransformer$TransformType.ZOOM:Lcom/github/paolorotolo/appintro/ViewPageTransformer$TransformType;
      48: invokevirtual #28                 // Method com/github/paolorotolo/appintro/ViewPageTransformer$TransformType.ordinal:()I
      51: iconst_4
      52: iastore
      53: getstatic     #20                 // Field $SwitchMap$com$github$paolorotolo$appintro$ViewPageTransformer$TransformType:[I
      56: getstatic     #40                 // Field com/github/paolorotolo/appintro/ViewPageTransformer$TransformType.FADE:Lcom/github/paolorotolo/appintro/ViewPageTransformer$TransformType;
      59: invokevirtual #28                 // Method com/github/paolorotolo/appintro/ViewPageTransformer$TransformType.ordinal:()I
      62: iconst_5
      63: iastore
      64: return
      65: astore_0
      66: goto          20
      69: astore_0
      70: goto          31
      73: astore_0
      74: goto          42
      77: astore_0
      78: goto          53
      81: astore_0
      82: return
    Exception table:
       from    to  target type
           9    20    65   Class java/lang/NoSuchFieldError
          20    31    69   Class java/lang/NoSuchFieldError
          31    42    73   Class java/lang/NoSuchFieldError
          42    53    77   Class java/lang/NoSuchFieldError
          53    64    81   Class java/lang/NoSuchFieldError
}
