public class ryey.easer.plugins.event.j.d extends ryey.easer.plugins.c<ryey.easer.plugins.event.j.a> {
  static {};
    Code:
       0: iconst_3
       1: newarray       int
       3: dup
       4: iconst_0
       5: ldc           #14                 // int 2131296544
       7: iastore
       8: dup
       9: iconst_1
      10: ldc           #15                 // int 2131296545
      12: iastore
      13: dup
      14: iconst_2
      15: ldc           #16                 // int 2131296543
      17: iastore
      18: putstatic     #18                 // Field a:[I
      21: iconst_3
      22: newarray       int
      24: dup
      25: iconst_0
      26: ldc           #19                 // int 2131296535
      28: iastore
      29: dup
      30: iconst_1
      31: ldc           #20                 // int 2131296534
      33: iastore
      34: dup
      35: iconst_2
      36: ldc           #21                 // int 2131296533
      38: iastore
      39: putstatic     #23                 // Field b:[I
      42: return

  public ryey.easer.plugins.event.j.d();
    Code:
       0: aload_0
       1: invokespecial #27                 // Method ryey/easer/plugins/c."<init>":()V
       4: aload_0
       5: getstatic     #18                 // Field a:[I
       8: arraylength
       9: anewarray     #29                 // class android/widget/RadioButton
      12: putfield      #31                 // Field c:[Landroid/widget/RadioButton;
      15: aload_0
      16: getstatic     #23                 // Field b:[I
      19: arraylength
      20: anewarray     #29                 // class android/widget/RadioButton
      23: putfield      #33                 // Field d:[Landroid/widget/RadioButton;
      26: return

  public ryey.easer.commons.local_plugin.f a();
    Code:
       0: aload_0
       1: invokevirtual #37                 // Method b:()Lryey/easer/plugins/event/j/a;
       4: areturn

  protected void a(ryey.easer.plugins.event.j.a);
    Code:
       0: aload_0
       1: getfield      #31                 // Field c:[Landroid/widget/RadioButton;
       4: aload_1
       5: getfield      #43                 // Field ryey/easer/plugins/event/j/a.a:Lryey/easer/plugins/event/j/a$a;
       8: invokevirtual #49                 // Method ryey/easer/plugins/event/j/a$a.ordinal:()I
      11: aaload
      12: iconst_1
      13: invokevirtual #53                 // Method android/widget/RadioButton.setChecked:(Z)V
      16: aload_0
      17: getfield      #33                 // Field d:[Landroid/widget/RadioButton;
      20: aload_1
      21: getfield      #56                 // Field ryey/easer/plugins/event/j/a.b:Lryey/easer/plugins/event/j/a$b;
      24: invokevirtual #59                 // Method ryey/easer/plugins/event/j/a$b.ordinal:()I
      27: aaload
      28: iconst_1
      29: invokevirtual #53                 // Method android/widget/RadioButton.setChecked:(Z)V
      32: return

  public ryey.easer.plugins.event.j.a b();
    Code:
       0: new           #40                 // class ryey/easer/plugins/event/j/a
       3: dup
       4: invokestatic  #63                 // Method ryey/easer/plugins/event/j/a$a.values:()[Lryey/easer/plugins/event/j/a$a;
       7: aload_0
       8: getfield      #31                 // Field c:[Landroid/widget/RadioButton;
      11: invokestatic  #68                 // Method ryey/easer/b.a:([Landroid/widget/CompoundButton;)I
      14: aaload
      15: invokestatic  #71                 // Method ryey/easer/plugins/event/j/a$b.values:()[Lryey/easer/plugins/event/j/a$b;
      18: aload_0
      19: getfield      #33                 // Field d:[Landroid/widget/RadioButton;
      22: invokestatic  #68                 // Method ryey/easer/b.a:([Landroid/widget/CompoundButton;)I
      25: aaload
      26: invokespecial #74                 // Method ryey/easer/plugins/event/j/a."<init>":(Lryey/easer/plugins/event/j/a$a;Lryey/easer/plugins/event/j/a$b;)V
      29: areturn

  protected void b(ryey.easer.commons.local_plugin.f);
    Code:
       0: aload_0
       1: aload_1
       2: checkcast     #40                 // class ryey/easer/plugins/event/j/a
       5: invokevirtual #77                 // Method a:(Lryey/easer/plugins/event/j/a;)V
       8: return

  public android.view.View onCreateView(android.view.LayoutInflater, android.view.ViewGroup, android.os.Bundle);
    Code:
       0: iconst_0
       1: istore        6
       3: aload_1
       4: ldc           #80                 // int 2131427436
       6: aload_2
       7: iconst_0
       8: invokevirtual #86                 // Method android/view/LayoutInflater.inflate:(ILandroid/view/ViewGroup;Z)Landroid/view/View;
      11: astore_1
      12: iconst_0
      13: istore        4
      15: iload         6
      17: istore        5
      19: iload         4
      21: getstatic     #18                 // Field a:[I
      24: arraylength
      25: if_icmpge     57
      28: aload_0
      29: getfield      #31                 // Field c:[Landroid/widget/RadioButton;
      32: iload         4
      34: aload_1
      35: getstatic     #18                 // Field a:[I
      38: iload         4
      40: iaload
      41: invokevirtual #92                 // Method android/view/View.findViewById:(I)Landroid/view/View;
      44: checkcast     #29                 // class android/widget/RadioButton
      47: aastore
      48: iload         4
      50: iconst_1
      51: iadd
      52: istore        4
      54: goto          15
      57: iload         5
      59: getstatic     #23                 // Field b:[I
      62: arraylength
      63: if_icmpge     95
      66: aload_0
      67: getfield      #33                 // Field d:[Landroid/widget/RadioButton;
      70: iload         5
      72: aload_1
      73: getstatic     #23                 // Field b:[I
      76: iload         5
      78: iaload
      79: invokevirtual #92                 // Method android/view/View.findViewById:(I)Landroid/view/View;
      82: checkcast     #29                 // class android/widget/RadioButton
      85: aastore
      86: iload         5
      88: iconst_1
      89: iadd
      90: istore        5
      92: goto          57
      95: aload_1
      96: areturn
}
