class ryey.easer.plugins.event.j.e$1 extends android.content.BroadcastReceiver {
  final ryey.easer.plugins.event.j.e a;

  ryey.easer.plugins.event.j.e$1(ryey.easer.plugins.event.j.e);
    Code:
       0: aload_0
       1: aload_1
       2: putfield      #12                 // Field a:Lryey/easer/plugins/event/j/e;
       5: aload_0
       6: invokespecial #15                 // Method android/content/BroadcastReceiver."<init>":()V
       9: return

  public void onReceive(android.content.Context, android.content.Intent);
    Code:
       0: aload_2
       1: invokevirtual #24                 // Method android/content/Intent.getExtras:()Landroid/os/Bundle;
       4: astore_1
       5: invokestatic  #28                 // Method ryey/easer/plugins/event/j/e.c:()Ljava/lang/String;
       8: aload_2
       9: invokevirtual #31                 // Method android/content/Intent.getAction:()Ljava/lang/String;
      12: invokevirtual #37                 // Method java/lang/String.equals:(Ljava/lang/Object;)Z
      15: ifeq          93
      18: aload_1
      19: ifnull        93
      22: aload_1
      23: ldc           #39                 // String state
      25: invokevirtual #45                 // Method android/os/Bundle.getInt:(Ljava/lang/String;)I
      28: istore_3
      29: aload_1
      30: ldc           #47                 // String microphone
      32: invokevirtual #45                 // Method android/os/Bundle.getInt:(Ljava/lang/String;)I
      35: istore        4
      37: aload_0
      38: getfield      #12                 // Field a:Lryey/easer/plugins/event/j/e;
      41: invokestatic  #50                 // Method ryey/easer/plugins/event/j/e.a:(Lryey/easer/plugins/event/j/e;)Lryey/easer/commons/local_plugin/eventplugin/EventData;
      44: checkcast     #52                 // class ryey/easer/plugins/event/j/a
      47: astore_1
      48: iconst_0
      49: istore        6
      51: iload_3
      52: iconst_1
      53: if_icmpne     62
      56: iconst_1
      57: istore        5
      59: goto          65
      62: iconst_0
      63: istore        5
      65: iload         4
      67: iconst_1
      68: if_icmpne     74
      71: iconst_1
      72: istore        6
      74: aload_1
      75: iload         5
      77: iload         6
      79: invokestatic  #55                 // Method ryey/easer/plugins/event/j/e.a:(Lryey/easer/plugins/event/j/a;ZZ)Z
      82: istore        5
      84: aload_0
      85: getfield      #12                 // Field a:Lryey/easer/plugins/event/j/e;
      88: iload         5
      90: invokestatic  #58                 // Method ryey/easer/plugins/event/j/e.a:(Lryey/easer/plugins/event/j/e;Z)V
      93: return
}
