public final class android.support.v7.g.a implements android.support.v7.g.d {
  public android.support.v7.g.a(android.support.v7.widget.RecyclerView$a);
    Code:
       0: aload_0
       1: invokespecial #13                 // Method java/lang/Object."<init>":()V
       4: aload_0
       5: aload_1
       6: putfield      #15                 // Field a:Landroid/support/v7/widget/RecyclerView$a;
       9: return

  public void a(int, int);
    Code:
       0: aload_0
       1: getfield      #15                 // Field a:Landroid/support/v7/widget/RecyclerView$a;
       4: iload_1
       5: iload_2
       6: invokevirtual #22                 // Method android/support/v7/widget/RecyclerView$a.b:(II)V
       9: return

  public void a(int, int, java.lang.Object);
    Code:
       0: aload_0
       1: getfield      #15                 // Field a:Landroid/support/v7/widget/RecyclerView$a;
       4: iload_1
       5: iload_2
       6: aload_3
       7: invokevirtual #25                 // Method android/support/v7/widget/RecyclerView$a.a:(IILjava/lang/Object;)V
      10: return

  public void b(int, int);
    Code:
       0: aload_0
       1: getfield      #15                 // Field a:Landroid/support/v7/widget/RecyclerView$a;
       4: iload_1
       5: iload_2
       6: invokevirtual #28                 // Method android/support/v7/widget/RecyclerView$a.c:(II)V
       9: return

  public void c(int, int);
    Code:
       0: aload_0
       1: getfield      #15                 // Field a:Landroid/support/v7/widget/RecyclerView$a;
       4: iload_1
       5: iload_2
       6: invokevirtual #30                 // Method android/support/v7/widget/RecyclerView$a.a:(II)V
       9: return
}
