class android.support.v7.g.c$d {
  int a;

  int b;

  boolean c;

  public android.support.v7.g.c$d(int, int, boolean);
    Code:
       0: aload_0
       1: invokespecial #17                 // Method java/lang/Object."<init>":()V
       4: aload_0
       5: iload_1
       6: putfield      #19                 // Field a:I
       9: aload_0
      10: iload_2
      11: putfield      #21                 // Field b:I
      14: aload_0
      15: iload_3
      16: putfield      #23                 // Field c:Z
      19: return
}
