class android.support.v7.g.c$e {
  int a;

  int b;

  int c;

  int d;

  public android.support.v7.g.c$e();
    Code:
       0: aload_0
       1: invokespecial #16                 // Method java/lang/Object."<init>":()V
       4: return

  public android.support.v7.g.c$e(int, int, int, int);
    Code:
       0: aload_0
       1: invokespecial #16                 // Method java/lang/Object."<init>":()V
       4: aload_0
       5: iload_1
       6: putfield      #20                 // Field a:I
       9: aload_0
      10: iload_2
      11: putfield      #22                 // Field b:I
      14: aload_0
      15: iload_3
      16: putfield      #24                 // Field c:I
      19: aload_0
      20: iload         4
      22: putfield      #26                 // Field d:I
      25: return
}
