class android.support.v4.media.session.MediaControllerCompat$MediaControllerImplApi21 {
  static android.support.v4.media.session.b a(android.support.v4.media.session.MediaControllerCompat$MediaControllerImplApi21, android.support.v4.media.session.b);
    Code:
       0: aload_0
       1: aload_1
       2: putfield      #23                 // Field b:Landroid/support/v4/media/session/b;
       5: aload_1
       6: areturn

  static void a(android.support.v4.media.session.MediaControllerCompat$MediaControllerImplApi21);
    Code:
       0: aload_0
       1: invokespecial #84                 // Method a:()V
       4: return
}
