public final class android.support.v4.media.session.MediaControllerCompat$b {
  android.support.v4.media.session.MediaControllerCompat$b(int, int, int, int, int);
    Code:
       0: aload_0
       1: invokespecial #17                 // Method java/lang/Object."<init>":()V
       4: aload_0
       5: iload_1
       6: putfield      #19                 // Field a:I
       9: aload_0
      10: iload_2
      11: putfield      #21                 // Field b:I
      14: aload_0
      15: iload_3
      16: putfield      #23                 // Field c:I
      19: aload_0
      20: iload         4
      22: putfield      #25                 // Field d:I
      25: aload_0
      26: iload         5
      28: putfield      #27                 // Field e:I
      31: return
}
