class android.support.v4.media.session.MediaControllerCompat$MediaControllerImplApi21$a extends android.support.v4.media.session.MediaControllerCompat$a$c {
  android.support.v4.media.session.MediaControllerCompat$MediaControllerImplApi21$a(android.support.v4.media.session.MediaControllerCompat$a);
    Code:
       0: aload_0
       1: aload_1
       2: invokespecial #14                 // Method android/support/v4/media/session/MediaControllerCompat$a$c."<init>":(Landroid/support/v4/media/session/MediaControllerCompat$a;)V
       5: return

  public void a();
    Code:
       0: new           #18                 // class java/lang/AssertionError
       3: dup
       4: invokespecial #20                 // Method java/lang/AssertionError."<init>":()V
       7: athrow

  public void a(android.os.Bundle);
    Code:
       0: new           #18                 // class java/lang/AssertionError
       3: dup
       4: invokespecial #20                 // Method java/lang/AssertionError."<init>":()V
       7: athrow

  public void a(android.support.v4.media.MediaMetadataCompat);
    Code:
       0: new           #18                 // class java/lang/AssertionError
       3: dup
       4: invokespecial #20                 // Method java/lang/AssertionError."<init>":()V
       7: athrow

  public void a(android.support.v4.media.session.ParcelableVolumeInfo);
    Code:
       0: new           #18                 // class java/lang/AssertionError
       3: dup
       4: invokespecial #20                 // Method java/lang/AssertionError."<init>":()V
       7: athrow

  public void a(java.lang.CharSequence);
    Code:
       0: new           #18                 // class java/lang/AssertionError
       3: dup
       4: invokespecial #20                 // Method java/lang/AssertionError."<init>":()V
       7: athrow

  public void a(java.util.List<android.support.v4.media.session.MediaSessionCompat$QueueItem>);
    Code:
       0: new           #18                 // class java/lang/AssertionError
       3: dup
       4: invokespecial #20                 // Method java/lang/AssertionError."<init>":()V
       7: athrow
}
