public final class com.google.common.base.Preconditions {
  public static void checkArgument(boolean);
    Code:
       0: iload_0
       1: ifne          12
       4: new           #37                 // class java/lang/IllegalArgumentException
       7: dup
       8: invokespecial #62                 // Method java/lang/IllegalArgumentException."<init>":()V
      11: athrow
      12: return

  public static void checkArgument(boolean, java.lang.Object);
    Code:
       0: iload_0
       1: ifne          16
       4: new           #37                 // class java/lang/IllegalArgumentException
       7: dup
       8: aload_1
       9: invokestatic  #68                 // Method java/lang/String.valueOf:(Ljava/lang/Object;)Ljava/lang/String;
      12: invokespecial #44                 // Method java/lang/IllegalArgumentException."<init>":(Ljava/lang/String;)V
      15: athrow
      16: return

  public static void checkArgument(boolean, java.lang.String, char);
    Code:
       0: iload_0
       1: ifne          27
       4: new           #37                 // class java/lang/IllegalArgumentException
       7: dup
       8: aload_1
       9: iconst_1
      10: anewarray     #4                  // class java/lang/Object
      13: dup
      14: iconst_0
      15: iload_2
      16: invokestatic  #74                 // Method java/lang/Character.valueOf:(C)Ljava/lang/Character;
      19: aastore
      20: invokestatic  #23                 // Method format:(Ljava/lang/String;[Ljava/lang/Object;)Ljava/lang/String;
      23: invokespecial #44                 // Method java/lang/IllegalArgumentException."<init>":(Ljava/lang/String;)V
      26: athrow
      27: return

  public static void checkArgument(boolean, java.lang.String, char, char);
    Code:
       0: iload_0
       1: ifne          34
       4: new           #37                 // class java/lang/IllegalArgumentException
       7: dup
       8: aload_1
       9: iconst_2
      10: anewarray     #4                  // class java/lang/Object
      13: dup
      14: iconst_0
      15: iload_2
      16: invokestatic  #74                 // Method java/lang/Character.valueOf:(C)Ljava/lang/Character;
      19: aastore
      20: dup
      21: iconst_1
      22: iload_3
      23: invokestatic  #74                 // Method java/lang/Character.valueOf:(C)Ljava/lang/Character;
      26: aastore
      27: invokestatic  #23                 // Method format:(Ljava/lang/String;[Ljava/lang/Object;)Ljava/lang/String;
      30: invokespecial #44                 // Method java/lang/IllegalArgumentException."<init>":(Ljava/lang/String;)V
      33: athrow
      34: return

  public static void checkArgument(boolean, java.lang.String, char, int);
    Code:
       0: iload_0
       1: ifne          34
       4: new           #37                 // class java/lang/IllegalArgumentException
       7: dup
       8: aload_1
       9: iconst_2
      10: anewarray     #4                  // class java/lang/Object
      13: dup
      14: iconst_0
      15: iload_2
      16: invokestatic  #74                 // Method java/lang/Character.valueOf:(C)Ljava/lang/Character;
      19: aastore
      20: dup
      21: iconst_1
      22: iload_3
      23: invokestatic  #19                 // Method java/lang/Integer.valueOf:(I)Ljava/lang/Integer;
      26: aastore
      27: invokestatic  #23                 // Method format:(Ljava/lang/String;[Ljava/lang/Object;)Ljava/lang/String;
      30: invokespecial #44                 // Method java/lang/IllegalArgumentException."<init>":(Ljava/lang/String;)V
      33: athrow
      34: return

  public static void checkArgument(boolean, java.lang.String, char, long);
    Code:
       0: iload_0
       1: ifne          34
       4: new           #37                 // class java/lang/IllegalArgumentException
       7: dup
       8: aload_1
       9: iconst_2
      10: anewarray     #4                  // class java/lang/Object
      13: dup
      14: iconst_0
      15: iload_2
      16: invokestatic  #74                 // Method java/lang/Character.valueOf:(C)Ljava/lang/Character;
      19: aastore
      20: dup
      21: iconst_1
      22: lload_3
      23: invokestatic  #82                 // Method java/lang/Long.valueOf:(J)Ljava/lang/Long;
      26: aastore
      27: invokestatic  #23                 // Method format:(Ljava/lang/String;[Ljava/lang/Object;)Ljava/lang/String;
      30: invokespecial #44                 // Method java/lang/IllegalArgumentException."<init>":(Ljava/lang/String;)V
      33: athrow
      34: return

  public static void checkArgument(boolean, java.lang.String, char, java.lang.Object);
    Code:
       0: iload_0
       1: ifne          31
       4: new           #37                 // class java/lang/IllegalArgumentException
       7: dup
       8: aload_1
       9: iconst_2
      10: anewarray     #4                  // class java/lang/Object
      13: dup
      14: iconst_0
      15: iload_2
      16: invokestatic  #74                 // Method java/lang/Character.valueOf:(C)Ljava/lang/Character;
      19: aastore
      20: dup
      21: iconst_1
      22: aload_3
      23: aastore
      24: invokestatic  #23                 // Method format:(Ljava/lang/String;[Ljava/lang/Object;)Ljava/lang/String;
      27: invokespecial #44                 // Method java/lang/IllegalArgumentException."<init>":(Ljava/lang/String;)V
      30: athrow
      31: return

  public static void checkArgument(boolean, java.lang.String, int);
    Code:
       0: iload_0
       1: ifne          27
       4: new           #37                 // class java/lang/IllegalArgumentException
       7: dup
       8: aload_1
       9: iconst_1
      10: anewarray     #4                  // class java/lang/Object
      13: dup
      14: iconst_0
      15: iload_2
      16: invokestatic  #19                 // Method java/lang/Integer.valueOf:(I)Ljava/lang/Integer;
      19: aastore
      20: invokestatic  #23                 // Method format:(Ljava/lang/String;[Ljava/lang/Object;)Ljava/lang/String;
      23: invokespecial #44                 // Method java/lang/IllegalArgumentException."<init>":(Ljava/lang/String;)V
      26: athrow
      27: return

  public static void checkArgument(boolean, java.lang.String, int, char);
    Code:
       0: iload_0
       1: ifne          34
       4: new           #37                 // class java/lang/IllegalArgumentException
       7: dup
       8: aload_1
       9: iconst_2
      10: anewarray     #4                  // class java/lang/Object
      13: dup
      14: iconst_0
      15: iload_2
      16: invokestatic  #19                 // Method java/lang/Integer.valueOf:(I)Ljava/lang/Integer;
      19: aastore
      20: dup
      21: iconst_1
      22: iload_3
      23: invokestatic  #74                 // Method java/lang/Character.valueOf:(C)Ljava/lang/Character;
      26: aastore
      27: invokestatic  #23                 // Method format:(Ljava/lang/String;[Ljava/lang/Object;)Ljava/lang/String;
      30: invokespecial #44                 // Method java/lang/IllegalArgumentException."<init>":(Ljava/lang/String;)V
      33: athrow
      34: return

  public static void checkArgument(boolean, java.lang.String, int, int);
    Code:
       0: iload_0
       1: ifne          34
       4: new           #37                 // class java/lang/IllegalArgumentException
       7: dup
       8: aload_1
       9: iconst_2
      10: anewarray     #4                  // class java/lang/Object
      13: dup
      14: iconst_0
      15: iload_2
      16: invokestatic  #19                 // Method java/lang/Integer.valueOf:(I)Ljava/lang/Integer;
      19: aastore
      20: dup
      21: iconst_1
      22: iload_3
      23: invokestatic  #19                 // Method java/lang/Integer.valueOf:(I)Ljava/lang/Integer;
      26: aastore
      27: invokestatic  #23                 // Method format:(Ljava/lang/String;[Ljava/lang/Object;)Ljava/lang/String;
      30: invokespecial #44                 // Method java/lang/IllegalArgumentException."<init>":(Ljava/lang/String;)V
      33: athrow
      34: return

  public static void checkArgument(boolean, java.lang.String, int, long);
    Code:
       0: iload_0
       1: ifne          34
       4: new           #37                 // class java/lang/IllegalArgumentException
       7: dup
       8: aload_1
       9: iconst_2
      10: anewarray     #4                  // class java/lang/Object
      13: dup
      14: iconst_0
      15: iload_2
      16: invokestatic  #19                 // Method java/lang/Integer.valueOf:(I)Ljava/lang/Integer;
      19: aastore
      20: dup
      21: iconst_1
      22: lload_3
      23: invokestatic  #82                 // Method java/lang/Long.valueOf:(J)Ljava/lang/Long;
      26: aastore
      27: invokestatic  #23                 // Method format:(Ljava/lang/String;[Ljava/lang/Object;)Ljava/lang/String;
      30: invokespecial #44                 // Method java/lang/IllegalArgumentException."<init>":(Ljava/lang/String;)V
      33: athrow
      34: return

  public static void checkArgument(boolean, java.lang.String, int, java.lang.Object);
    Code:
       0: iload_0
       1: ifne          31
       4: new           #37                 // class java/lang/IllegalArgumentException
       7: dup
       8: aload_1
       9: iconst_2
      10: anewarray     #4                  // class java/lang/Object
      13: dup
      14: iconst_0
      15: iload_2
      16: invokestatic  #19                 // Method java/lang/Integer.valueOf:(I)Ljava/lang/Integer;
      19: aastore
      20: dup
      21: iconst_1
      22: aload_3
      23: aastore
      24: invokestatic  #23                 // Method format:(Ljava/lang/String;[Ljava/lang/Object;)Ljava/lang/String;
      27: invokespecial #44                 // Method java/lang/IllegalArgumentException."<init>":(Ljava/lang/String;)V
      30: athrow
      31: return

  public static void checkArgument(boolean, java.lang.String, long);
    Code:
       0: iload_0
       1: ifne          27
       4: new           #37                 // class java/lang/IllegalArgumentException
       7: dup
       8: aload_1
       9: iconst_1
      10: anewarray     #4                  // class java/lang/Object
      13: dup
      14: iconst_0
      15: lload_2
      16: invokestatic  #82                 // Method java/lang/Long.valueOf:(J)Ljava/lang/Long;
      19: aastore
      20: invokestatic  #23                 // Method format:(Ljava/lang/String;[Ljava/lang/Object;)Ljava/lang/String;
      23: invokespecial #44                 // Method java/lang/IllegalArgumentException."<init>":(Ljava/lang/String;)V
      26: athrow
      27: return

  public static void checkArgument(boolean, java.lang.String, long, char);
    Code:
       0: iload_0
       1: ifne          35
       4: new           #37                 // class java/lang/IllegalArgumentException
       7: dup
       8: aload_1
       9: iconst_2
      10: anewarray     #4                  // class java/lang/Object
      13: dup
      14: iconst_0
      15: lload_2
      16: invokestatic  #82                 // Method java/lang/Long.valueOf:(J)Ljava/lang/Long;
      19: aastore
      20: dup
      21: iconst_1
      22: iload         4
      24: invokestatic  #74                 // Method java/lang/Character.valueOf:(C)Ljava/lang/Character;
      27: aastore
      28: invokestatic  #23                 // Method format:(Ljava/lang/String;[Ljava/lang/Object;)Ljava/lang/String;
      31: invokespecial #44                 // Method java/lang/IllegalArgumentException."<init>":(Ljava/lang/String;)V
      34: athrow
      35: return

  public static void checkArgument(boolean, java.lang.String, long, int);
    Code:
       0: iload_0
       1: ifne          35
       4: new           #37                 // class java/lang/IllegalArgumentException
       7: dup
       8: aload_1
       9: iconst_2
      10: anewarray     #4                  // class java/lang/Object
      13: dup
      14: iconst_0
      15: lload_2
      16: invokestatic  #82                 // Method java/lang/Long.valueOf:(J)Ljava/lang/Long;
      19: aastore
      20: dup
      21: iconst_1
      22: iload         4
      24: invokestatic  #19                 // Method java/lang/Integer.valueOf:(I)Ljava/lang/Integer;
      27: aastore
      28: invokestatic  #23                 // Method format:(Ljava/lang/String;[Ljava/lang/Object;)Ljava/lang/String;
      31: invokespecial #44                 // Method java/lang/IllegalArgumentException."<init>":(Ljava/lang/String;)V
      34: athrow
      35: return

  public static void checkArgument(boolean, java.lang.String, long, long);
    Code:
       0: iload_0
       1: ifne          35
       4: new           #37                 // class java/lang/IllegalArgumentException
       7: dup
       8: aload_1
       9: iconst_2
      10: anewarray     #4                  // class java/lang/Object
      13: dup
      14: iconst_0
      15: lload_2
      16: invokestatic  #82                 // Method java/lang/Long.valueOf:(J)Ljava/lang/Long;
      19: aastore
      20: dup
      21: iconst_1
      22: lload         4
      24: invokestatic  #82                 // Method java/lang/Long.valueOf:(J)Ljava/lang/Long;
      27: aastore
      28: invokestatic  #23                 // Method format:(Ljava/lang/String;[Ljava/lang/Object;)Ljava/lang/String;
      31: invokespecial #44                 // Method java/lang/IllegalArgumentException."<init>":(Ljava/lang/String;)V
      34: athrow
      35: return

  public static void checkArgument(boolean, java.lang.String, long, java.lang.Object);
    Code:
       0: iload_0
       1: ifne          32
       4: new           #37                 // class java/lang/IllegalArgumentException
       7: dup
       8: aload_1
       9: iconst_2
      10: anewarray     #4                  // class java/lang/Object
      13: dup
      14: iconst_0
      15: lload_2
      16: invokestatic  #82                 // Method java/lang/Long.valueOf:(J)Ljava/lang/Long;
      19: aastore
      20: dup
      21: iconst_1
      22: aload         4
      24: aastore
      25: invokestatic  #23                 // Method format:(Ljava/lang/String;[Ljava/lang/Object;)Ljava/lang/String;
      28: invokespecial #44                 // Method java/lang/IllegalArgumentException."<init>":(Ljava/lang/String;)V
      31: athrow
      32: return

  public static void checkArgument(boolean, java.lang.String, java.lang.Object);
    Code:
       0: iload_0
       1: ifne          24
       4: new           #37                 // class java/lang/IllegalArgumentException
       7: dup
       8: aload_1
       9: iconst_1
      10: anewarray     #4                  // class java/lang/Object
      13: dup
      14: iconst_0
      15: aload_2
      16: aastore
      17: invokestatic  #23                 // Method format:(Ljava/lang/String;[Ljava/lang/Object;)Ljava/lang/String;
      20: invokespecial #44                 // Method java/lang/IllegalArgumentException."<init>":(Ljava/lang/String;)V
      23: athrow
      24: return

  public static void checkArgument(boolean, java.lang.String, java.lang.Object, char);
    Code:
       0: iload_0
       1: ifne          31
       4: new           #37                 // class java/lang/IllegalArgumentException
       7: dup
       8: aload_1
       9: iconst_2
      10: anewarray     #4                  // class java/lang/Object
      13: dup
      14: iconst_0
      15: aload_2
      16: aastore
      17: dup
      18: iconst_1
      19: iload_3
      20: invokestatic  #74                 // Method java/lang/Character.valueOf:(C)Ljava/lang/Character;
      23: aastore
      24: invokestatic  #23                 // Method format:(Ljava/lang/String;[Ljava/lang/Object;)Ljava/lang/String;
      27: invokespecial #44                 // Method java/lang/IllegalArgumentException."<init>":(Ljava/lang/String;)V
      30: athrow
      31: return

  public static void checkArgument(boolean, java.lang.String, java.lang.Object, int);
    Code:
       0: iload_0
       1: ifne          31
       4: new           #37                 // class java/lang/IllegalArgumentException
       7: dup
       8: aload_1
       9: iconst_2
      10: anewarray     #4                  // class java/lang/Object
      13: dup
      14: iconst_0
      15: aload_2
      16: aastore
      17: dup
      18: iconst_1
      19: iload_3
      20: invokestatic  #19                 // Method java/lang/Integer.valueOf:(I)Ljava/lang/Integer;
      23: aastore
      24: invokestatic  #23                 // Method format:(Ljava/lang/String;[Ljava/lang/Object;)Ljava/lang/String;
      27: invokespecial #44                 // Method java/lang/IllegalArgumentException."<init>":(Ljava/lang/String;)V
      30: athrow
      31: return

  public static void checkArgument(boolean, java.lang.String, java.lang.Object, long);
    Code:
       0: iload_0
       1: ifne          31
       4: new           #37                 // class java/lang/IllegalArgumentException
       7: dup
       8: aload_1
       9: iconst_2
      10: anewarray     #4                  // class java/lang/Object
      13: dup
      14: iconst_0
      15: aload_2
      16: aastore
      17: dup
      18: iconst_1
      19: lload_3
      20: invokestatic  #82                 // Method java/lang/Long.valueOf:(J)Ljava/lang/Long;
      23: aastore
      24: invokestatic  #23                 // Method format:(Ljava/lang/String;[Ljava/lang/Object;)Ljava/lang/String;
      27: invokespecial #44                 // Method java/lang/IllegalArgumentException."<init>":(Ljava/lang/String;)V
      30: athrow
      31: return

  public static void checkArgument(boolean, java.lang.String, java.lang.Object, java.lang.Object);
    Code:
       0: iload_0
       1: ifne          28
       4: new           #37                 // class java/lang/IllegalArgumentException
       7: dup
       8: aload_1
       9: iconst_2
      10: anewarray     #4                  // class java/lang/Object
      13: dup
      14: iconst_0
      15: aload_2
      16: aastore
      17: dup
      18: iconst_1
      19: aload_3
      20: aastore
      21: invokestatic  #23                 // Method format:(Ljava/lang/String;[Ljava/lang/Object;)Ljava/lang/String;
      24: invokespecial #44                 // Method java/lang/IllegalArgumentException."<init>":(Ljava/lang/String;)V
      27: athrow
      28: return

  public static void checkArgument(boolean, java.lang.String, java.lang.Object, java.lang.Object, java.lang.Object);
    Code:
       0: iload_0
       1: ifne          33
       4: new           #37                 // class java/lang/IllegalArgumentException
       7: dup
       8: aload_1
       9: iconst_3
      10: anewarray     #4                  // class java/lang/Object
      13: dup
      14: iconst_0
      15: aload_2
      16: aastore
      17: dup
      18: iconst_1
      19: aload_3
      20: aastore
      21: dup
      22: iconst_2
      23: aload         4
      25: aastore
      26: invokestatic  #23                 // Method format:(Ljava/lang/String;[Ljava/lang/Object;)Ljava/lang/String;
      29: invokespecial #44                 // Method java/lang/IllegalArgumentException."<init>":(Ljava/lang/String;)V
      32: athrow
      33: return

  public static void checkArgument(boolean, java.lang.String, java.lang.Object, java.lang.Object, java.lang.Object, java.lang.Object);
    Code:
       0: iload_0
       1: ifne          38
       4: new           #37                 // class java/lang/IllegalArgumentException
       7: dup
       8: aload_1
       9: iconst_4
      10: anewarray     #4                  // class java/lang/Object
      13: dup
      14: iconst_0
      15: aload_2
      16: aastore
      17: dup
      18: iconst_1
      19: aload_3
      20: aastore
      21: dup
      22: iconst_2
      23: aload         4
      25: aastore
      26: dup
      27: iconst_3
      28: aload         5
      30: aastore
      31: invokestatic  #23                 // Method format:(Ljava/lang/String;[Ljava/lang/Object;)Ljava/lang/String;
      34: invokespecial #44                 // Method java/lang/IllegalArgumentException."<init>":(Ljava/lang/String;)V
      37: athrow
      38: return

  public static void checkArgument(boolean, java.lang.String, java.lang.Object...);
    Code:
       0: iload_0
       1: ifne          17
       4: new           #37                 // class java/lang/IllegalArgumentException
       7: dup
       8: aload_1
       9: aload_2
      10: invokestatic  #23                 // Method format:(Ljava/lang/String;[Ljava/lang/Object;)Ljava/lang/String;
      13: invokespecial #44                 // Method java/lang/IllegalArgumentException."<init>":(Ljava/lang/String;)V
      16: athrow
      17: return

  public static int checkElementIndex(int, int);
    Code:
       0: iload_0
       1: iload_1
       2: ldc           #106                // String index
       4: invokestatic  #109                // Method checkElementIndex:(IILjava/lang/String;)I
       7: ireturn

  public static int checkElementIndex(int, int, java.lang.String);
    Code:
       0: iload_0
       1: iflt          14
       4: iload_0
       5: iload_1
       6: if_icmplt     12
       9: goto          14
      12: iload_0
      13: ireturn
      14: new           #112                // class java/lang/IndexOutOfBoundsException
      17: dup
      18: iload_0
      19: iload_1
      20: aload_2
      21: invokestatic  #114                // Method badElementIndex:(IILjava/lang/String;)Ljava/lang/String;
      24: invokespecial #115                // Method java/lang/IndexOutOfBoundsException."<init>":(Ljava/lang/String;)V
      27: athrow

  public static <T> T checkNotNull(T);
    Code:
       0: aload_0
       1: ifnonnull     12
       4: new           #119                // class java/lang/NullPointerException
       7: dup
       8: invokespecial #120                // Method java/lang/NullPointerException."<init>":()V
      11: athrow
      12: aload_0
      13: areturn

  public static <T> T checkNotNull(T, java.lang.Object);
    Code:
       0: aload_0
       1: ifnonnull     16
       4: new           #119                // class java/lang/NullPointerException
       7: dup
       8: aload_1
       9: invokestatic  #68                 // Method java/lang/String.valueOf:(Ljava/lang/Object;)Ljava/lang/String;
      12: invokespecial #124                // Method java/lang/NullPointerException."<init>":(Ljava/lang/String;)V
      15: athrow
      16: aload_0
      17: areturn

  public static <T> T checkNotNull(T, java.lang.String, char);
    Code:
       0: aload_0
       1: ifnonnull     27
       4: new           #119                // class java/lang/NullPointerException
       7: dup
       8: aload_1
       9: iconst_1
      10: anewarray     #4                  // class java/lang/Object
      13: dup
      14: iconst_0
      15: iload_2
      16: invokestatic  #74                 // Method java/lang/Character.valueOf:(C)Ljava/lang/Character;
      19: aastore
      20: invokestatic  #23                 // Method format:(Ljava/lang/String;[Ljava/lang/Object;)Ljava/lang/String;
      23: invokespecial #124                // Method java/lang/NullPointerException."<init>":(Ljava/lang/String;)V
      26: athrow
      27: aload_0
      28: areturn

  public static <T> T checkNotNull(T, java.lang.String, char, char);
    Code:
       0: aload_0
       1: ifnonnull     34
       4: new           #119                // class java/lang/NullPointerException
       7: dup
       8: aload_1
       9: iconst_2
      10: anewarray     #4                  // class java/lang/Object
      13: dup
      14: iconst_0
      15: iload_2
      16: invokestatic  #74                 // Method java/lang/Character.valueOf:(C)Ljava/lang/Character;
      19: aastore
      20: dup
      21: iconst_1
      22: iload_3
      23: invokestatic  #74                 // Method java/lang/Character.valueOf:(C)Ljava/lang/Character;
      26: aastore
      27: invokestatic  #23                 // Method format:(Ljava/lang/String;[Ljava/lang/Object;)Ljava/lang/String;
      30: invokespecial #124                // Method java/lang/NullPointerException."<init>":(Ljava/lang/String;)V
      33: athrow
      34: aload_0
      35: areturn

  public static <T> T checkNotNull(T, java.lang.String, char, int);
    Code:
       0: aload_0
       1: ifnonnull     34
       4: new           #119                // class java/lang/NullPointerException
       7: dup
       8: aload_1
       9: iconst_2
      10: anewarray     #4                  // class java/lang/Object
      13: dup
      14: iconst_0
      15: iload_2
      16: invokestatic  #74                 // Method java/lang/Character.valueOf:(C)Ljava/lang/Character;
      19: aastore
      20: dup
      21: iconst_1
      22: iload_3
      23: invokestatic  #19                 // Method java/lang/Integer.valueOf:(I)Ljava/lang/Integer;
      26: aastore
      27: invokestatic  #23                 // Method format:(Ljava/lang/String;[Ljava/lang/Object;)Ljava/lang/String;
      30: invokespecial #124                // Method java/lang/NullPointerException."<init>":(Ljava/lang/String;)V
      33: athrow
      34: aload_0
      35: areturn

  public static <T> T checkNotNull(T, java.lang.String, char, long);
    Code:
       0: aload_0
       1: ifnonnull     34
       4: new           #119                // class java/lang/NullPointerException
       7: dup
       8: aload_1
       9: iconst_2
      10: anewarray     #4                  // class java/lang/Object
      13: dup
      14: iconst_0
      15: iload_2
      16: invokestatic  #74                 // Method java/lang/Character.valueOf:(C)Ljava/lang/Character;
      19: aastore
      20: dup
      21: iconst_1
      22: lload_3
      23: invokestatic  #82                 // Method java/lang/Long.valueOf:(J)Ljava/lang/Long;
      26: aastore
      27: invokestatic  #23                 // Method format:(Ljava/lang/String;[Ljava/lang/Object;)Ljava/lang/String;
      30: invokespecial #124                // Method java/lang/NullPointerException."<init>":(Ljava/lang/String;)V
      33: athrow
      34: aload_0
      35: areturn

  public static <T> T checkNotNull(T, java.lang.String, char, java.lang.Object);
    Code:
       0: aload_0
       1: ifnonnull     31
       4: new           #119                // class java/lang/NullPointerException
       7: dup
       8: aload_1
       9: iconst_2
      10: anewarray     #4                  // class java/lang/Object
      13: dup
      14: iconst_0
      15: iload_2
      16: invokestatic  #74                 // Method java/lang/Character.valueOf:(C)Ljava/lang/Character;
      19: aastore
      20: dup
      21: iconst_1
      22: aload_3
      23: aastore
      24: invokestatic  #23                 // Method format:(Ljava/lang/String;[Ljava/lang/Object;)Ljava/lang/String;
      27: invokespecial #124                // Method java/lang/NullPointerException."<init>":(Ljava/lang/String;)V
      30: athrow
      31: aload_0
      32: areturn

  public static <T> T checkNotNull(T, java.lang.String, int);
    Code:
       0: aload_0
       1: ifnonnull     27
       4: new           #119                // class java/lang/NullPointerException
       7: dup
       8: aload_1
       9: iconst_1
      10: anewarray     #4                  // class java/lang/Object
      13: dup
      14: iconst_0
      15: iload_2
      16: invokestatic  #19                 // Method java/lang/Integer.valueOf:(I)Ljava/lang/Integer;
      19: aastore
      20: invokestatic  #23                 // Method format:(Ljava/lang/String;[Ljava/lang/Object;)Ljava/lang/String;
      23: invokespecial #124                // Method java/lang/NullPointerException."<init>":(Ljava/lang/String;)V
      26: athrow
      27: aload_0
      28: areturn

  public static <T> T checkNotNull(T, java.lang.String, int, char);
    Code:
       0: aload_0
       1: ifnonnull     34
       4: new           #119                // class java/lang/NullPointerException
       7: dup
       8: aload_1
       9: iconst_2
      10: anewarray     #4                  // class java/lang/Object
      13: dup
      14: iconst_0
      15: iload_2
      16: invokestatic  #19                 // Method java/lang/Integer.valueOf:(I)Ljava/lang/Integer;
      19: aastore
      20: dup
      21: iconst_1
      22: iload_3
      23: invokestatic  #74                 // Method java/lang/Character.valueOf:(C)Ljava/lang/Character;
      26: aastore
      27: invokestatic  #23                 // Method format:(Ljava/lang/String;[Ljava/lang/Object;)Ljava/lang/String;
      30: invokespecial #124                // Method java/lang/NullPointerException."<init>":(Ljava/lang/String;)V
      33: athrow
      34: aload_0
      35: areturn

  public static <T> T checkNotNull(T, java.lang.String, int, int);
    Code:
       0: aload_0
       1: ifnonnull     34
       4: new           #119                // class java/lang/NullPointerException
       7: dup
       8: aload_1
       9: iconst_2
      10: anewarray     #4                  // class java/lang/Object
      13: dup
      14: iconst_0
      15: iload_2
      16: invokestatic  #19                 // Method java/lang/Integer.valueOf:(I)Ljava/lang/Integer;
      19: aastore
      20: dup
      21: iconst_1
      22: iload_3
      23: invokestatic  #19                 // Method java/lang/Integer.valueOf:(I)Ljava/lang/Integer;
      26: aastore
      27: invokestatic  #23                 // Method format:(Ljava/lang/String;[Ljava/lang/Object;)Ljava/lang/String;
      30: invokespecial #124                // Method java/lang/NullPointerException."<init>":(Ljava/lang/String;)V
      33: athrow
      34: aload_0
      35: areturn

  public static <T> T checkNotNull(T, java.lang.String, int, long);
    Code:
       0: aload_0
       1: ifnonnull     34
       4: new           #119                // class java/lang/NullPointerException
       7: dup
       8: aload_1
       9: iconst_2
      10: anewarray     #4                  // class java/lang/Object
      13: dup
      14: iconst_0
      15: iload_2
      16: invokestatic  #19                 // Method java/lang/Integer.valueOf:(I)Ljava/lang/Integer;
      19: aastore
      20: dup
      21: iconst_1
      22: lload_3
      23: invokestatic  #82                 // Method java/lang/Long.valueOf:(J)Ljava/lang/Long;
      26: aastore
      27: invokestatic  #23                 // Method format:(Ljava/lang/String;[Ljava/lang/Object;)Ljava/lang/String;
      30: invokespecial #124                // Method java/lang/NullPointerException."<init>":(Ljava/lang/String;)V
      33: athrow
      34: aload_0
      35: areturn

  public static <T> T checkNotNull(T, java.lang.String, int, java.lang.Object);
    Code:
       0: aload_0
       1: ifnonnull     31
       4: new           #119                // class java/lang/NullPointerException
       7: dup
       8: aload_1
       9: iconst_2
      10: anewarray     #4                  // class java/lang/Object
      13: dup
      14: iconst_0
      15: iload_2
      16: invokestatic  #19                 // Method java/lang/Integer.valueOf:(I)Ljava/lang/Integer;
      19: aastore
      20: dup
      21: iconst_1
      22: aload_3
      23: aastore
      24: invokestatic  #23                 // Method format:(Ljava/lang/String;[Ljava/lang/Object;)Ljava/lang/String;
      27: invokespecial #124                // Method java/lang/NullPointerException."<init>":(Ljava/lang/String;)V
      30: athrow
      31: aload_0
      32: areturn

  public static <T> T checkNotNull(T, java.lang.String, long);
    Code:
       0: aload_0
       1: ifnonnull     27
       4: new           #119                // class java/lang/NullPointerException
       7: dup
       8: aload_1
       9: iconst_1
      10: anewarray     #4                  // class java/lang/Object
      13: dup
      14: iconst_0
      15: lload_2
      16: invokestatic  #82                 // Method java/lang/Long.valueOf:(J)Ljava/lang/Long;
      19: aastore
      20: invokestatic  #23                 // Method format:(Ljava/lang/String;[Ljava/lang/Object;)Ljava/lang/String;
      23: invokespecial #124                // Method java/lang/NullPointerException."<init>":(Ljava/lang/String;)V
      26: athrow
      27: aload_0
      28: areturn

  public static <T> T checkNotNull(T, java.lang.String, long, char);
    Code:
       0: aload_0
       1: ifnonnull     35
       4: new           #119                // class java/lang/NullPointerException
       7: dup
       8: aload_1
       9: iconst_2
      10: anewarray     #4                  // class java/lang/Object
      13: dup
      14: iconst_0
      15: lload_2
      16: invokestatic  #82                 // Method java/lang/Long.valueOf:(J)Ljava/lang/Long;
      19: aastore
      20: dup
      21: iconst_1
      22: iload         4
      24: invokestatic  #74                 // Method java/lang/Character.valueOf:(C)Ljava/lang/Character;
      27: aastore
      28: invokestatic  #23                 // Method format:(Ljava/lang/String;[Ljava/lang/Object;)Ljava/lang/String;
      31: invokespecial #124                // Method java/lang/NullPointerException."<init>":(Ljava/lang/String;)V
      34: athrow
      35: aload_0
      36: areturn

  public static <T> T checkNotNull(T, java.lang.String, long, int);
    Code:
       0: aload_0
       1: ifnonnull     35
       4: new           #119                // class java/lang/NullPointerException
       7: dup
       8: aload_1
       9: iconst_2
      10: anewarray     #4                  // class java/lang/Object
      13: dup
      14: iconst_0
      15: lload_2
      16: invokestatic  #82                 // Method java/lang/Long.valueOf:(J)Ljava/lang/Long;
      19: aastore
      20: dup
      21: iconst_1
      22: iload         4
      24: invokestatic  #19                 // Method java/lang/Integer.valueOf:(I)Ljava/lang/Integer;
      27: aastore
      28: invokestatic  #23                 // Method format:(Ljava/lang/String;[Ljava/lang/Object;)Ljava/lang/String;
      31: invokespecial #124                // Method java/lang/NullPointerException."<init>":(Ljava/lang/String;)V
      34: athrow
      35: aload_0
      36: areturn

  public static <T> T checkNotNull(T, java.lang.String, long, long);
    Code:
       0: aload_0
       1: ifnonnull     35
       4: new           #119                // class java/lang/NullPointerException
       7: dup
       8: aload_1
       9: iconst_2
      10: anewarray     #4                  // class java/lang/Object
      13: dup
      14: iconst_0
      15: lload_2
      16: invokestatic  #82                 // Method java/lang/Long.valueOf:(J)Ljava/lang/Long;
      19: aastore
      20: dup
      21: iconst_1
      22: lload         4
      24: invokestatic  #82                 // Method java/lang/Long.valueOf:(J)Ljava/lang/Long;
      27: aastore
      28: invokestatic  #23                 // Method format:(Ljava/lang/String;[Ljava/lang/Object;)Ljava/lang/String;
      31: invokespecial #124                // Method java/lang/NullPointerException."<init>":(Ljava/lang/String;)V
      34: athrow
      35: aload_0
      36: areturn

  public static <T> T checkNotNull(T, java.lang.String, long, java.lang.Object);
    Code:
       0: aload_0
       1: ifnonnull     32
       4: new           #119                // class java/lang/NullPointerException
       7: dup
       8: aload_1
       9: iconst_2
      10: anewarray     #4                  // class java/lang/Object
      13: dup
      14: iconst_0
      15: lload_2
      16: invokestatic  #82                 // Method java/lang/Long.valueOf:(J)Ljava/lang/Long;
      19: aastore
      20: dup
      21: iconst_1
      22: aload         4
      24: aastore
      25: invokestatic  #23                 // Method format:(Ljava/lang/String;[Ljava/lang/Object;)Ljava/lang/String;
      28: invokespecial #124                // Method java/lang/NullPointerException."<init>":(Ljava/lang/String;)V
      31: athrow
      32: aload_0
      33: areturn

  public static <T> T checkNotNull(T, java.lang.String, java.lang.Object);
    Code:
       0: aload_0
       1: ifnonnull     24
       4: new           #119                // class java/lang/NullPointerException
       7: dup
       8: aload_1
       9: iconst_1
      10: anewarray     #4                  // class java/lang/Object
      13: dup
      14: iconst_0
      15: aload_2
      16: aastore
      17: invokestatic  #23                 // Method format:(Ljava/lang/String;[Ljava/lang/Object;)Ljava/lang/String;
      20: invokespecial #124                // Method java/lang/NullPointerException."<init>":(Ljava/lang/String;)V
      23: athrow
      24: aload_0
      25: areturn

  public static <T> T checkNotNull(T, java.lang.String, java.lang.Object, char);
    Code:
       0: aload_0
       1: ifnonnull     31
       4: new           #119                // class java/lang/NullPointerException
       7: dup
       8: aload_1
       9: iconst_2
      10: anewarray     #4                  // class java/lang/Object
      13: dup
      14: iconst_0
      15: aload_2
      16: aastore
      17: dup
      18: iconst_1
      19: iload_3
      20: invokestatic  #74                 // Method java/lang/Character.valueOf:(C)Ljava/lang/Character;
      23: aastore
      24: invokestatic  #23                 // Method format:(Ljava/lang/String;[Ljava/lang/Object;)Ljava/lang/String;
      27: invokespecial #124                // Method java/lang/NullPointerException."<init>":(Ljava/lang/String;)V
      30: athrow
      31: aload_0
      32: areturn

  public static <T> T checkNotNull(T, java.lang.String, java.lang.Object, int);
    Code:
       0: aload_0
       1: ifnonnull     31
       4: new           #119                // class java/lang/NullPointerException
       7: dup
       8: aload_1
       9: iconst_2
      10: anewarray     #4                  // class java/lang/Object
      13: dup
      14: iconst_0
      15: aload_2
      16: aastore
      17: dup
      18: iconst_1
      19: iload_3
      20: invokestatic  #19                 // Method java/lang/Integer.valueOf:(I)Ljava/lang/Integer;
      23: aastore
      24: invokestatic  #23                 // Method format:(Ljava/lang/String;[Ljava/lang/Object;)Ljava/lang/String;
      27: invokespecial #124                // Method java/lang/NullPointerException."<init>":(Ljava/lang/String;)V
      30: athrow
      31: aload_0
      32: areturn

  public static <T> T checkNotNull(T, java.lang.String, java.lang.Object, long);
    Code:
       0: aload_0
       1: ifnonnull     31
       4: new           #119                // class java/lang/NullPointerException
       7: dup
       8: aload_1
       9: iconst_2
      10: anewarray     #4                  // class java/lang/Object
      13: dup
      14: iconst_0
      15: aload_2
      16: aastore
      17: dup
      18: iconst_1
      19: lload_3
      20: invokestatic  #82                 // Method java/lang/Long.valueOf:(J)Ljava/lang/Long;
      23: aastore
      24: invokestatic  #23                 // Method format:(Ljava/lang/String;[Ljava/lang/Object;)Ljava/lang/String;
      27: invokespecial #124                // Method java/lang/NullPointerException."<init>":(Ljava/lang/String;)V
      30: athrow
      31: aload_0
      32: areturn

  public static <T> T checkNotNull(T, java.lang.String, java.lang.Object, java.lang.Object);
    Code:
       0: aload_0
       1: ifnonnull     28
       4: new           #119                // class java/lang/NullPointerException
       7: dup
       8: aload_1
       9: iconst_2
      10: anewarray     #4                  // class java/lang/Object
      13: dup
      14: iconst_0
      15: aload_2
      16: aastore
      17: dup
      18: iconst_1
      19: aload_3
      20: aastore
      21: invokestatic  #23                 // Method format:(Ljava/lang/String;[Ljava/lang/Object;)Ljava/lang/String;
      24: invokespecial #124                // Method java/lang/NullPointerException."<init>":(Ljava/lang/String;)V
      27: athrow
      28: aload_0
      29: areturn

  public static <T> T checkNotNull(T, java.lang.String, java.lang.Object, java.lang.Object, java.lang.Object);
    Code:
       0: aload_0
       1: ifnonnull     33
       4: new           #119                // class java/lang/NullPointerException
       7: dup
       8: aload_1
       9: iconst_3
      10: anewarray     #4                  // class java/lang/Object
      13: dup
      14: iconst_0
      15: aload_2
      16: aastore
      17: dup
      18: iconst_1
      19: aload_3
      20: aastore
      21: dup
      22: iconst_2
      23: aload         4
      25: aastore
      26: invokestatic  #23                 // Method format:(Ljava/lang/String;[Ljava/lang/Object;)Ljava/lang/String;
      29: invokespecial #124                // Method java/lang/NullPointerException."<init>":(Ljava/lang/String;)V
      32: athrow
      33: aload_0
      34: areturn

  public static <T> T checkNotNull(T, java.lang.String, java.lang.Object, java.lang.Object, java.lang.Object, java.lang.Object);
    Code:
       0: aload_0
       1: ifnonnull     38
       4: new           #119                // class java/lang/NullPointerException
       7: dup
       8: aload_1
       9: iconst_4
      10: anewarray     #4                  // class java/lang/Object
      13: dup
      14: iconst_0
      15: aload_2
      16: aastore
      17: dup
      18: iconst_1
      19: aload_3
      20: aastore
      21: dup
      22: iconst_2
      23: aload         4
      25: aastore
      26: dup
      27: iconst_3
      28: aload         5
      30: aastore
      31: invokestatic  #23                 // Method format:(Ljava/lang/String;[Ljava/lang/Object;)Ljava/lang/String;
      34: invokespecial #124                // Method java/lang/NullPointerException."<init>":(Ljava/lang/String;)V
      37: athrow
      38: aload_0
      39: areturn

  public static <T> T checkNotNull(T, java.lang.String, java.lang.Object...);
    Code:
       0: aload_0
       1: ifnonnull     17
       4: new           #119                // class java/lang/NullPointerException
       7: dup
       8: aload_1
       9: aload_2
      10: invokestatic  #23                 // Method format:(Ljava/lang/String;[Ljava/lang/Object;)Ljava/lang/String;
      13: invokespecial #124                // Method java/lang/NullPointerException."<init>":(Ljava/lang/String;)V
      16: athrow
      17: aload_0
      18: areturn

  public static int checkPositionIndex(int, int);
    Code:
       0: iload_0
       1: iload_1
       2: ldc           #106                // String index
       4: invokestatic  #174                // Method checkPositionIndex:(IILjava/lang/String;)I
       7: ireturn

  public static int checkPositionIndex(int, int, java.lang.String);
    Code:
       0: iload_0
       1: iflt          14
       4: iload_0
       5: iload_1
       6: if_icmple     12
       9: goto          14
      12: iload_0
      13: ireturn
      14: new           #112                // class java/lang/IndexOutOfBoundsException
      17: dup
      18: iload_0
      19: iload_1
      20: aload_2
      21: invokestatic  #57                 // Method badPositionIndex:(IILjava/lang/String;)Ljava/lang/String;
      24: invokespecial #115                // Method java/lang/IndexOutOfBoundsException."<init>":(Ljava/lang/String;)V
      27: athrow

  public static void checkPositionIndexes(int, int, int);
    Code:
       0: iload_0
       1: iflt          18
       4: iload_1
       5: iload_0
       6: if_icmplt     18
       9: iload_1
      10: iload_2
      11: if_icmple     17
      14: goto          18
      17: return
      18: new           #112                // class java/lang/IndexOutOfBoundsException
      21: dup
      22: iload_0
      23: iload_1
      24: iload_2
      25: invokestatic  #178                // Method badPositionIndexes:(III)Ljava/lang/String;
      28: invokespecial #115                // Method java/lang/IndexOutOfBoundsException."<init>":(Ljava/lang/String;)V
      31: athrow

  public static void checkState(boolean);
    Code:
       0: iload_0
       1: ifne          12
       4: new           #181                // class java/lang/IllegalStateException
       7: dup
       8: invokespecial #182                // Method java/lang/IllegalStateException."<init>":()V
      11: athrow
      12: return

  public static void checkState(boolean, java.lang.Object);
    Code:
       0: iload_0
       1: ifne          16
       4: new           #181                // class java/lang/IllegalStateException
       7: dup
       8: aload_1
       9: invokestatic  #68                 // Method java/lang/String.valueOf:(Ljava/lang/Object;)Ljava/lang/String;
      12: invokespecial #183                // Method java/lang/IllegalStateException."<init>":(Ljava/lang/String;)V
      15: athrow
      16: return

  public static void checkState(boolean, java.lang.String, char);
    Code:
       0: iload_0
       1: ifne          27
       4: new           #181                // class java/lang/IllegalStateException
       7: dup
       8: aload_1
       9: iconst_1
      10: anewarray     #4                  // class java/lang/Object
      13: dup
      14: iconst_0
      15: iload_2
      16: invokestatic  #74                 // Method java/lang/Character.valueOf:(C)Ljava/lang/Character;
      19: aastore
      20: invokestatic  #23                 // Method format:(Ljava/lang/String;[Ljava/lang/Object;)Ljava/lang/String;
      23: invokespecial #183                // Method java/lang/IllegalStateException."<init>":(Ljava/lang/String;)V
      26: athrow
      27: return

  public static void checkState(boolean, java.lang.String, char, char);
    Code:
       0: iload_0
       1: ifne          34
       4: new           #181                // class java/lang/IllegalStateException
       7: dup
       8: aload_1
       9: iconst_2
      10: anewarray     #4                  // class java/lang/Object
      13: dup
      14: iconst_0
      15: iload_2
      16: invokestatic  #74                 // Method java/lang/Character.valueOf:(C)Ljava/lang/Character;
      19: aastore
      20: dup
      21: iconst_1
      22: iload_3
      23: invokestatic  #74                 // Method java/lang/Character.valueOf:(C)Ljava/lang/Character;
      26: aastore
      27: invokestatic  #23                 // Method format:(Ljava/lang/String;[Ljava/lang/Object;)Ljava/lang/String;
      30: invokespecial #183                // Method java/lang/IllegalStateException."<init>":(Ljava/lang/String;)V
      33: athrow
      34: return

  public static void checkState(boolean, java.lang.String, char, int);
    Code:
       0: iload_0
       1: ifne          34
       4: new           #181                // class java/lang/IllegalStateException
       7: dup
       8: aload_1
       9: iconst_2
      10: anewarray     #4                  // class java/lang/Object
      13: dup
      14: iconst_0
      15: iload_2
      16: invokestatic  #74                 // Method java/lang/Character.valueOf:(C)Ljava/lang/Character;
      19: aastore
      20: dup
      21: iconst_1
      22: iload_3
      23: invokestatic  #19                 // Method java/lang/Integer.valueOf:(I)Ljava/lang/Integer;
      26: aastore
      27: invokestatic  #23                 // Method format:(Ljava/lang/String;[Ljava/lang/Object;)Ljava/lang/String;
      30: invokespecial #183                // Method java/lang/IllegalStateException."<init>":(Ljava/lang/String;)V
      33: athrow
      34: return

  public static void checkState(boolean, java.lang.String, char, long);
    Code:
       0: iload_0
       1: ifne          34
       4: new           #181                // class java/lang/IllegalStateException
       7: dup
       8: aload_1
       9: iconst_2
      10: anewarray     #4                  // class java/lang/Object
      13: dup
      14: iconst_0
      15: iload_2
      16: invokestatic  #74                 // Method java/lang/Character.valueOf:(C)Ljava/lang/Character;
      19: aastore
      20: dup
      21: iconst_1
      22: lload_3
      23: invokestatic  #82                 // Method java/lang/Long.valueOf:(J)Ljava/lang/Long;
      26: aastore
      27: invokestatic  #23                 // Method format:(Ljava/lang/String;[Ljava/lang/Object;)Ljava/lang/String;
      30: invokespecial #183                // Method java/lang/IllegalStateException."<init>":(Ljava/lang/String;)V
      33: athrow
      34: return

  public static void checkState(boolean, java.lang.String, char, java.lang.Object);
    Code:
       0: iload_0
       1: ifne          31
       4: new           #181                // class java/lang/IllegalStateException
       7: dup
       8: aload_1
       9: iconst_2
      10: anewarray     #4                  // class java/lang/Object
      13: dup
      14: iconst_0
      15: iload_2
      16: invokestatic  #74                 // Method java/lang/Character.valueOf:(C)Ljava/lang/Character;
      19: aastore
      20: dup
      21: iconst_1
      22: aload_3
      23: aastore
      24: invokestatic  #23                 // Method format:(Ljava/lang/String;[Ljava/lang/Object;)Ljava/lang/String;
      27: invokespecial #183                // Method java/lang/IllegalStateException."<init>":(Ljava/lang/String;)V
      30: athrow
      31: return

  public static void checkState(boolean, java.lang.String, int);
    Code:
       0: iload_0
       1: ifne          27
       4: new           #181                // class java/lang/IllegalStateException
       7: dup
       8: aload_1
       9: iconst_1
      10: anewarray     #4                  // class java/lang/Object
      13: dup
      14: iconst_0
      15: iload_2
      16: invokestatic  #19                 // Method java/lang/Integer.valueOf:(I)Ljava/lang/Integer;
      19: aastore
      20: invokestatic  #23                 // Method format:(Ljava/lang/String;[Ljava/lang/Object;)Ljava/lang/String;
      23: invokespecial #183                // Method java/lang/IllegalStateException."<init>":(Ljava/lang/String;)V
      26: athrow
      27: return

  public static void checkState(boolean, java.lang.String, int, char);
    Code:
       0: iload_0
       1: ifne          34
       4: new           #181                // class java/lang/IllegalStateException
       7: dup
       8: aload_1
       9: iconst_2
      10: anewarray     #4                  // class java/lang/Object
      13: dup
      14: iconst_0
      15: iload_2
      16: invokestatic  #19                 // Method java/lang/Integer.valueOf:(I)Ljava/lang/Integer;
      19: aastore
      20: dup
      21: iconst_1
      22: iload_3
      23: invokestatic  #74                 // Method java/lang/Character.valueOf:(C)Ljava/lang/Character;
      26: aastore
      27: invokestatic  #23                 // Method format:(Ljava/lang/String;[Ljava/lang/Object;)Ljava/lang/String;
      30: invokespecial #183                // Method java/lang/IllegalStateException."<init>":(Ljava/lang/String;)V
      33: athrow
      34: return

  public static void checkState(boolean, java.lang.String, int, int);
    Code:
       0: iload_0
       1: ifne          34
       4: new           #181                // class java/lang/IllegalStateException
       7: dup
       8: aload_1
       9: iconst_2
      10: anewarray     #4                  // class java/lang/Object
      13: dup
      14: iconst_0
      15: iload_2
      16: invokestatic  #19                 // Method java/lang/Integer.valueOf:(I)Ljava/lang/Integer;
      19: aastore
      20: dup
      21: iconst_1
      22: iload_3
      23: invokestatic  #19                 // Method java/lang/Integer.valueOf:(I)Ljava/lang/Integer;
      26: aastore
      27: invokestatic  #23                 // Method format:(Ljava/lang/String;[Ljava/lang/Object;)Ljava/lang/String;
      30: invokespecial #183                // Method java/lang/IllegalStateException."<init>":(Ljava/lang/String;)V
      33: athrow
      34: return

  public static void checkState(boolean, java.lang.String, int, long);
    Code:
       0: iload_0
       1: ifne          34
       4: new           #181                // class java/lang/IllegalStateException
       7: dup
       8: aload_1
       9: iconst_2
      10: anewarray     #4                  // class java/lang/Object
      13: dup
      14: iconst_0
      15: iload_2
      16: invokestatic  #19                 // Method java/lang/Integer.valueOf:(I)Ljava/lang/Integer;
      19: aastore
      20: dup
      21: iconst_1
      22: lload_3
      23: invokestatic  #82                 // Method java/lang/Long.valueOf:(J)Ljava/lang/Long;
      26: aastore
      27: invokestatic  #23                 // Method format:(Ljava/lang/String;[Ljava/lang/Object;)Ljava/lang/String;
      30: invokespecial #183                // Method java/lang/IllegalStateException."<init>":(Ljava/lang/String;)V
      33: athrow
      34: return

  public static void checkState(boolean, java.lang.String, int, java.lang.Object);
    Code:
       0: iload_0
       1: ifne          31
       4: new           #181                // class java/lang/IllegalStateException
       7: dup
       8: aload_1
       9: iconst_2
      10: anewarray     #4                  // class java/lang/Object
      13: dup
      14: iconst_0
      15: iload_2
      16: invokestatic  #19                 // Method java/lang/Integer.valueOf:(I)Ljava/lang/Integer;
      19: aastore
      20: dup
      21: iconst_1
      22: aload_3
      23: aastore
      24: invokestatic  #23                 // Method format:(Ljava/lang/String;[Ljava/lang/Object;)Ljava/lang/String;
      27: invokespecial #183                // Method java/lang/IllegalStateException."<init>":(Ljava/lang/String;)V
      30: athrow
      31: return

  public static void checkState(boolean, java.lang.String, long);
    Code:
       0: iload_0
       1: ifne          27
       4: new           #181                // class java/lang/IllegalStateException
       7: dup
       8: aload_1
       9: iconst_1
      10: anewarray     #4                  // class java/lang/Object
      13: dup
      14: iconst_0
      15: lload_2
      16: invokestatic  #82                 // Method java/lang/Long.valueOf:(J)Ljava/lang/Long;
      19: aastore
      20: invokestatic  #23                 // Method format:(Ljava/lang/String;[Ljava/lang/Object;)Ljava/lang/String;
      23: invokespecial #183                // Method java/lang/IllegalStateException."<init>":(Ljava/lang/String;)V
      26: athrow
      27: return

  public static void checkState(boolean, java.lang.String, long, char);
    Code:
       0: iload_0
       1: ifne          35
       4: new           #181                // class java/lang/IllegalStateException
       7: dup
       8: aload_1
       9: iconst_2
      10: anewarray     #4                  // class java/lang/Object
      13: dup
      14: iconst_0
      15: lload_2
      16: invokestatic  #82                 // Method java/lang/Long.valueOf:(J)Ljava/lang/Long;
      19: aastore
      20: dup
      21: iconst_1
      22: iload         4
      24: invokestatic  #74                 // Method java/lang/Character.valueOf:(C)Ljava/lang/Character;
      27: aastore
      28: invokestatic  #23                 // Method format:(Ljava/lang/String;[Ljava/lang/Object;)Ljava/lang/String;
      31: invokespecial #183                // Method java/lang/IllegalStateException."<init>":(Ljava/lang/String;)V
      34: athrow
      35: return

  public static void checkState(boolean, java.lang.String, long, int);
    Code:
       0: iload_0
       1: ifne          35
       4: new           #181                // class java/lang/IllegalStateException
       7: dup
       8: aload_1
       9: iconst_2
      10: anewarray     #4                  // class java/lang/Object
      13: dup
      14: iconst_0
      15: lload_2
      16: invokestatic  #82                 // Method java/lang/Long.valueOf:(J)Ljava/lang/Long;
      19: aastore
      20: dup
      21: iconst_1
      22: iload         4
      24: invokestatic  #19                 // Method java/lang/Integer.valueOf:(I)Ljava/lang/Integer;
      27: aastore
      28: invokestatic  #23                 // Method format:(Ljava/lang/String;[Ljava/lang/Object;)Ljava/lang/String;
      31: invokespecial #183                // Method java/lang/IllegalStateException."<init>":(Ljava/lang/String;)V
      34: athrow
      35: return

  public static void checkState(boolean, java.lang.String, long, long);
    Code:
       0: iload_0
       1: ifne          35
       4: new           #181                // class java/lang/IllegalStateException
       7: dup
       8: aload_1
       9: iconst_2
      10: anewarray     #4                  // class java/lang/Object
      13: dup
      14: iconst_0
      15: lload_2
      16: invokestatic  #82                 // Method java/lang/Long.valueOf:(J)Ljava/lang/Long;
      19: aastore
      20: dup
      21: iconst_1
      22: lload         4
      24: invokestatic  #82                 // Method java/lang/Long.valueOf:(J)Ljava/lang/Long;
      27: aastore
      28: invokestatic  #23                 // Method format:(Ljava/lang/String;[Ljava/lang/Object;)Ljava/lang/String;
      31: invokespecial #183                // Method java/lang/IllegalStateException."<init>":(Ljava/lang/String;)V
      34: athrow
      35: return

  public static void checkState(boolean, java.lang.String, long, java.lang.Object);
    Code:
       0: iload_0
       1: ifne          32
       4: new           #181                // class java/lang/IllegalStateException
       7: dup
       8: aload_1
       9: iconst_2
      10: anewarray     #4                  // class java/lang/Object
      13: dup
      14: iconst_0
      15: lload_2
      16: invokestatic  #82                 // Method java/lang/Long.valueOf:(J)Ljava/lang/Long;
      19: aastore
      20: dup
      21: iconst_1
      22: aload         4
      24: aastore
      25: invokestatic  #23                 // Method format:(Ljava/lang/String;[Ljava/lang/Object;)Ljava/lang/String;
      28: invokespecial #183                // Method java/lang/IllegalStateException."<init>":(Ljava/lang/String;)V
      31: athrow
      32: return

  public static void checkState(boolean, java.lang.String, java.lang.Object);
    Code:
       0: iload_0
       1: ifne          24
       4: new           #181                // class java/lang/IllegalStateException
       7: dup
       8: aload_1
       9: iconst_1
      10: anewarray     #4                  // class java/lang/Object
      13: dup
      14: iconst_0
      15: aload_2
      16: aastore
      17: invokestatic  #23                 // Method format:(Ljava/lang/String;[Ljava/lang/Object;)Ljava/lang/String;
      20: invokespecial #183                // Method java/lang/IllegalStateException."<init>":(Ljava/lang/String;)V
      23: athrow
      24: return

  public static void checkState(boolean, java.lang.String, java.lang.Object, char);
    Code:
       0: iload_0
       1: ifne          31
       4: new           #181                // class java/lang/IllegalStateException
       7: dup
       8: aload_1
       9: iconst_2
      10: anewarray     #4                  // class java/lang/Object
      13: dup
      14: iconst_0
      15: aload_2
      16: aastore
      17: dup
      18: iconst_1
      19: iload_3
      20: invokestatic  #74                 // Method java/lang/Character.valueOf:(C)Ljava/lang/Character;
      23: aastore
      24: invokestatic  #23                 // Method format:(Ljava/lang/String;[Ljava/lang/Object;)Ljava/lang/String;
      27: invokespecial #183                // Method java/lang/IllegalStateException."<init>":(Ljava/lang/String;)V
      30: athrow
      31: return

  public static void checkState(boolean, java.lang.String, java.lang.Object, int);
    Code:
       0: iload_0
       1: ifne          31
       4: new           #181                // class java/lang/IllegalStateException
       7: dup
       8: aload_1
       9: iconst_2
      10: anewarray     #4                  // class java/lang/Object
      13: dup
      14: iconst_0
      15: aload_2
      16: aastore
      17: dup
      18: iconst_1
      19: iload_3
      20: invokestatic  #19                 // Method java/lang/Integer.valueOf:(I)Ljava/lang/Integer;
      23: aastore
      24: invokestatic  #23                 // Method format:(Ljava/lang/String;[Ljava/lang/Object;)Ljava/lang/String;
      27: invokespecial #183                // Method java/lang/IllegalStateException."<init>":(Ljava/lang/String;)V
      30: athrow
      31: return

  public static void checkState(boolean, java.lang.String, java.lang.Object, long);
    Code:
       0: iload_0
       1: ifne          31
       4: new           #181                // class java/lang/IllegalStateException
       7: dup
       8: aload_1
       9: iconst_2
      10: anewarray     #4                  // class java/lang/Object
      13: dup
      14: iconst_0
      15: aload_2
      16: aastore
      17: dup
      18: iconst_1
      19: lload_3
      20: invokestatic  #82                 // Method java/lang/Long.valueOf:(J)Ljava/lang/Long;
      23: aastore
      24: invokestatic  #23                 // Method format:(Ljava/lang/String;[Ljava/lang/Object;)Ljava/lang/String;
      27: invokespecial #183                // Method java/lang/IllegalStateException."<init>":(Ljava/lang/String;)V
      30: athrow
      31: return

  public static void checkState(boolean, java.lang.String, java.lang.Object, java.lang.Object);
    Code:
       0: iload_0
       1: ifne          28
       4: new           #181                // class java/lang/IllegalStateException
       7: dup
       8: aload_1
       9: iconst_2
      10: anewarray     #4                  // class java/lang/Object
      13: dup
      14: iconst_0
      15: aload_2
      16: aastore
      17: dup
      18: iconst_1
      19: aload_3
      20: aastore
      21: invokestatic  #23                 // Method format:(Ljava/lang/String;[Ljava/lang/Object;)Ljava/lang/String;
      24: invokespecial #183                // Method java/lang/IllegalStateException."<init>":(Ljava/lang/String;)V
      27: athrow
      28: return

  public static void checkState(boolean, java.lang.String, java.lang.Object, java.lang.Object, java.lang.Object);
    Code:
       0: iload_0
       1: ifne          33
       4: new           #181                // class java/lang/IllegalStateException
       7: dup
       8: aload_1
       9: iconst_3
      10: anewarray     #4                  // class java/lang/Object
      13: dup
      14: iconst_0
      15: aload_2
      16: aastore
      17: dup
      18: iconst_1
      19: aload_3
      20: aastore
      21: dup
      22: iconst_2
      23: aload         4
      25: aastore
      26: invokestatic  #23                 // Method format:(Ljava/lang/String;[Ljava/lang/Object;)Ljava/lang/String;
      29: invokespecial #183                // Method java/lang/IllegalStateException."<init>":(Ljava/lang/String;)V
      32: athrow
      33: return

  public static void checkState(boolean, java.lang.String, java.lang.Object, java.lang.Object, java.lang.Object, java.lang.Object);
    Code:
       0: iload_0
       1: ifne          38
       4: new           #181                // class java/lang/IllegalStateException
       7: dup
       8: aload_1
       9: iconst_4
      10: anewarray     #4                  // class java/lang/Object
      13: dup
      14: iconst_0
      15: aload_2
      16: aastore
      17: dup
      18: iconst_1
      19: aload_3
      20: aastore
      21: dup
      22: iconst_2
      23: aload         4
      25: aastore
      26: dup
      27: iconst_3
      28: aload         5
      30: aastore
      31: invokestatic  #23                 // Method format:(Ljava/lang/String;[Ljava/lang/Object;)Ljava/lang/String;
      34: invokespecial #183                // Method java/lang/IllegalStateException."<init>":(Ljava/lang/String;)V
      37: athrow
      38: return

  public static void checkState(boolean, java.lang.String, java.lang.Object...);
    Code:
       0: iload_0
       1: ifne          17
       4: new           #181                // class java/lang/IllegalStateException
       7: dup
       8: aload_1
       9: aload_2
      10: invokestatic  #23                 // Method format:(Ljava/lang/String;[Ljava/lang/Object;)Ljava/lang/String;
      13: invokespecial #183                // Method java/lang/IllegalStateException."<init>":(Ljava/lang/String;)V
      16: athrow
      17: return

  static java.lang.String format(java.lang.String, java.lang.Object...);
    Code:
       0: aload_0
       1: invokestatic  #68                 // Method java/lang/String.valueOf:(Ljava/lang/Object;)Ljava/lang/String;
       4: astore        5
       6: iconst_0
       7: istore_2
       8: aload_1
       9: astore_0
      10: aload_1
      11: ifnonnull     24
      14: iconst_1
      15: anewarray     #4                  // class java/lang/Object
      18: astore_0
      19: aload_0
      20: iconst_0
      21: ldc           #185                // String (Object[])null
      23: aastore
      24: new           #25                 // class java/lang/StringBuilder
      27: dup
      28: aload         5
      30: invokevirtual #189                // Method java/lang/String.length:()I
      33: aload_0
      34: arraylength
      35: bipush        16
      37: imul
      38: iadd
      39: invokespecial #192                // Method java/lang/StringBuilder."<init>":(I)V
      42: astore_1
      43: iconst_0
      44: istore_3
      45: iload_2
      46: aload_0
      47: arraylength
      48: if_icmpge     100
      51: aload         5
      53: ldc           #194                // String %s
      55: iload_3
      56: invokevirtual #198                // Method java/lang/String.indexOf:(Ljava/lang/String;I)I
      59: istore        4
      61: iload         4
      63: iconst_m1
      64: if_icmpne     70
      67: goto          100
      70: aload_1
      71: aload         5
      73: iload_3
      74: iload         4
      76: invokevirtual #201                // Method java/lang/StringBuilder.append:(Ljava/lang/CharSequence;II)Ljava/lang/StringBuilder;
      79: pop
      80: aload_1
      81: aload_0
      82: iload_2
      83: aaload
      84: invokevirtual #204                // Method java/lang/StringBuilder.append:(Ljava/lang/Object;)Ljava/lang/StringBuilder;
      87: pop
      88: iload         4
      90: iconst_2
      91: iadd
      92: istore_3
      93: iload_2
      94: iconst_1
      95: iadd
      96: istore_2
      97: goto          45
     100: aload_1
     101: aload         5
     103: iload_3
     104: aload         5
     106: invokevirtual #189                // Method java/lang/String.length:()I
     109: invokevirtual #201                // Method java/lang/StringBuilder.append:(Ljava/lang/CharSequence;II)Ljava/lang/StringBuilder;
     112: pop
     113: iload_2
     114: aload_0
     115: arraylength
     116: if_icmpge     175
     119: aload_1
     120: ldc           #206                // String  [
     122: invokevirtual #32                 // Method java/lang/StringBuilder.append:(Ljava/lang/String;)Ljava/lang/StringBuilder;
     125: pop
     126: iload_2
     127: iconst_1
     128: iadd
     129: istore_3
     130: aload_1
     131: aload_0
     132: iload_2
     133: aaload
     134: invokevirtual #204                // Method java/lang/StringBuilder.append:(Ljava/lang/Object;)Ljava/lang/StringBuilder;
     137: pop
     138: iload_3
     139: istore_2
     140: iload_2
     141: aload_0
     142: arraylength
     143: if_icmpge     168
     146: aload_1
     147: ldc           #208                // String ,
     149: invokevirtual #32                 // Method java/lang/StringBuilder.append:(Ljava/lang/String;)Ljava/lang/StringBuilder;
     152: pop
     153: aload_1
     154: aload_0
     155: iload_2
     156: aaload
     157: invokevirtual #204                // Method java/lang/StringBuilder.append:(Ljava/lang/Object;)Ljava/lang/StringBuilder;
     160: pop
     161: iload_2
     162: iconst_1
     163: iadd
     164: istore_2
     165: goto          140
     168: aload_1
     169: bipush        93
     171: invokevirtual #211                // Method java/lang/StringBuilder.append:(C)Ljava/lang/StringBuilder;
     174: pop
     175: aload_1
     176: invokevirtual #41                 // Method java/lang/StringBuilder.toString:()Ljava/lang/String;
     179: areturn
}
