public class ryey.easer.plugins.a.j.d extends ryey.easer.plugins.c<ryey.easer.plugins.a.j.a> {
  public ryey.easer.plugins.a.j.d();
    Code:
       0: aload_0
       1: invokespecial #11                 // Method ryey/easer/plugins/c."<init>":()V
       4: return

  public ryey.easer.commons.local_plugin.f a();
    Code:
       0: aload_0
       1: invokevirtual #78                 // Method b:()Lryey/easer/plugins/a/j/a;
       4: areturn

  protected void a(ryey.easer.plugins.a.j.a);
    Code:
       0: aload_0
       1: getfield      #81                 // Field a:Landroid/widget/TimePicker;
       4: aload_1
       5: getfield      #86                 // Field ryey/easer/plugins/a/j/a.a:Ljava/util/Calendar;
       8: invokestatic  #88                 // Method a:(Landroid/widget/TimePicker;Ljava/util/Calendar;)V
      11: return

  public ryey.easer.plugins.a.j.a b();
    Code:
       0: new           #83                 // class ryey/easer/plugins/a/j/a
       3: dup
       4: aload_0
       5: getfield      #81                 // Field a:Landroid/widget/TimePicker;
       8: invokestatic  #90                 // Method a:(Landroid/widget/TimePicker;)Ljava/util/Calendar;
      11: getstatic     #95                 // Field ryey/easer/plugins/a/j/a$a.a:Lryey/easer/plugins/a/j/a$a;
      14: invokespecial #98                 // Method ryey/easer/plugins/a/j/a."<init>":(Ljava/util/Calendar;Lryey/easer/plugins/a/j/a$a;)V
      17: areturn

  protected void b(ryey.easer.commons.local_plugin.f);
    Code:
       0: aload_0
       1: aload_1
       2: checkcast     #83                 // class ryey/easer/plugins/a/j/a
       5: invokevirtual #101                // Method a:(Lryey/easer/plugins/a/j/a;)V
       8: return

  public android.view.View onCreateView(android.view.LayoutInflater, android.view.ViewGroup, android.os.Bundle);
    Code:
       0: aload_1
       1: ldc           #104                // int 2131427428
       3: aload_2
       4: iconst_0
       5: invokevirtual #110                // Method android/view/LayoutInflater.inflate:(ILandroid/view/ViewGroup;Z)Landroid/view/View;
       8: astore_1
       9: aload_0
      10: aload_1
      11: ldc           #111                // int 2131296720
      13: invokevirtual #117                // Method android/view/View.findViewById:(I)Landroid/view/View;
      16: checkcast     #27                 // class android/widget/TimePicker
      19: putfield      #81                 // Field a:Landroid/widget/TimePicker;
      22: aload_0
      23: getfield      #81                 // Field a:Landroid/widget/TimePicker;
      26: aload_0
      27: invokevirtual #121                // Method getContext:()Landroid/content/Context;
      30: invokestatic  #127                // Method ryey/easer/a.c:(Landroid/content/Context;)Z
      33: iconst_1
      34: ixor
      35: invokestatic  #132                // Method java/lang/Boolean.valueOf:(Z)Ljava/lang/Boolean;
      38: invokevirtual #136                // Method android/widget/TimePicker.setIs24HourView:(Ljava/lang/Boolean;)V
      41: aload_1
      42: areturn
}
