class com.google.common.a.b$b extends com.google.common.a.b<K, V>.a implements java.util.Set<java.util.Map$Entry<K, V>> {
  final com.google.common.a.b b;

  com.google.common.a.b$b(com.google.common.a.b, com.google.common.a.b$1);
    Code:
       0: aload_0
       1: aload_1
       2: invokespecial #21                 // Method "<init>":(Lcom/google/common/a/b;)V
       5: return

  public boolean equals(java.lang.Object);
    Code:
       0: aload_0
       1: aload_1
       2: invokestatic  #29                 // Method com/google/common/a/p.a:(Ljava/util/Set;Ljava/lang/Object;)Z
       5: ireturn

  public int hashCode();
    Code:
       0: aload_0
       1: invokestatic  #34                 // Method com/google/common/a/p.a:(Ljava/util/Set;)I
       4: ireturn
}
