class com.google.common.a.c$a extends com.google.common.a.n$b<E> {
  final com.google.common.a.c a;

  com.google.common.a.c$a(com.google.common.a.c);
    Code:
       0: aload_0
       1: aload_1
       2: putfield      #13                 // Field a:Lcom/google/common/a/c;
       5: aload_0
       6: invokespecial #16                 // Method com/google/common/a/n$b."<init>":()V
       9: return

  com.google.common.a.m<E> a();
    Code:
       0: aload_0
       1: getfield      #13                 // Field a:Lcom/google/common/a/c;
       4: areturn
}
