class com.google.common.a.g$d<K, V> {
  com.google.common.a.g$e<K, V> a;

  com.google.common.a.g$e<K, V> b;

  int c;

  com.google.common.a.g$d(com.google.common.a.g$e<K, V>);
    Code:
       0: aload_0
       1: invokespecial #19                 // Method java/lang/Object."<init>":()V
       4: aload_0
       5: aload_1
       6: putfield      #21                 // Field a:Lcom/google/common/a/g$e;
       9: aload_0
      10: aload_1
      11: putfield      #23                 // Field b:Lcom/google/common/a/g$e;
      14: aload_1
      15: aconst_null
      16: putfield      #28                 // Field com/google/common/a/g$e.f:Lcom/google/common/a/g$e;
      19: aload_1
      20: aconst_null
      21: putfield      #31                 // Field com/google/common/a/g$e.e:Lcom/google/common/a/g$e;
      24: aload_0
      25: iconst_1
      26: putfield      #33                 // Field c:I
      29: return
}
