class android.support.design.widget.a {
  static final android.view.animation.Interpolator a;

  static final android.view.animation.Interpolator b;

  static final android.view.animation.Interpolator c;

  static final android.view.animation.Interpolator d;

  static final android.view.animation.Interpolator e;

  static {};
    Code:
       0: new           #14                 // class android/view/animation/LinearInterpolator
       3: dup
       4: invokespecial #17                 // Method android/view/animation/LinearInterpolator."<init>":()V
       7: putstatic     #19                 // Field a:Landroid/view/animation/Interpolator;
      10: new           #21                 // class android/support/v4/view/b/b
      13: dup
      14: invokespecial #22                 // Method android/support/v4/view/b/b."<init>":()V
      17: putstatic     #24                 // Field b:Landroid/view/animation/Interpolator;
      20: new           #26                 // class android/support/v4/view/b/a
      23: dup
      24: invokespecial #27                 // Method android/support/v4/view/b/a."<init>":()V
      27: putstatic     #29                 // Field c:Landroid/view/animation/Interpolator;
      30: new           #31                 // class android/support/v4/view/b/c
      33: dup
      34: invokespecial #32                 // Method android/support/v4/view/b/c."<init>":()V
      37: putstatic     #34                 // Field d:Landroid/view/animation/Interpolator;
      40: new           #36                 // class android/view/animation/DecelerateInterpolator
      43: dup
      44: invokespecial #37                 // Method android/view/animation/DecelerateInterpolator."<init>":()V
      47: putstatic     #39                 // Field e:Landroid/view/animation/Interpolator;
      50: return
}
