class android.support.design.widget.b$6$1 implements java.lang.Runnable {
  final android.support.design.widget.b$6 a;

  android.support.design.widget.b$6$1(android.support.design.widget.b$6);
    Code:
       0: aload_0
       1: aload_1
       2: putfield      #17                 // Field a:Landroid/support/design/widget/b$6;
       5: aload_0
       6: invokespecial #20                 // Method java/lang/Object."<init>":()V
       9: return

  public void run();
    Code:
       0: aload_0
       1: getfield      #17                 // Field a:Landroid/support/design/widget/b$6;
       4: getfield      #25                 // Field android/support/design/widget/b$6.a:Landroid/support/design/widget/b;
       7: iconst_3
       8: invokevirtual #31                 // Method android/support/design/widget/b.c:(I)V
      11: return
}
