public abstract class android.support.design.widget.CoordinatorLayout$b<V extends android.view.View> {
  public android.support.design.widget.CoordinatorLayout$b();
    Code:
       0: aload_0
       1: invokespecial #12                 // Method java/lang/Object."<init>":()V
       4: return

  public android.support.design.widget.CoordinatorLayout$b(android.content.Context, android.util.AttributeSet);
    Code:
       0: aload_0
       1: invokespecial #12                 // Method java/lang/Object."<init>":()V
       4: return

  public android.support.v4.view.ab a(android.support.design.widget.CoordinatorLayout, V, android.support.v4.view.ab);
    Code:
       0: aload_3
       1: areturn

  public void a(android.support.design.widget.CoordinatorLayout$e);
    Code:
       0: return

  public void a(android.support.design.widget.CoordinatorLayout, V, android.os.Parcelable);
    Code:
       0: return

  public void a(android.support.design.widget.CoordinatorLayout, V, android.view.View, int);
    Code:
       0: iload         4
       2: ifne          12
       5: aload_0
       6: aload_1
       7: aload_2
       8: aload_3
       9: invokevirtual #26                 // Method c:(Landroid/support/design/widget/CoordinatorLayout;Landroid/view/View;Landroid/view/View;)V
      12: return

  public void a(android.support.design.widget.CoordinatorLayout, V, android.view.View, int, int, int, int);
    Code:
       0: return

  public void a(android.support.design.widget.CoordinatorLayout, V, android.view.View, int, int, int, int, int);
    Code:
       0: iload         8
       2: ifne          20
       5: aload_0
       6: aload_1
       7: aload_2
       8: aload_3
       9: iload         4
      11: iload         5
      13: iload         6
      15: iload         7
      17: invokevirtual #34                 // Method a:(Landroid/support/design/widget/CoordinatorLayout;Landroid/view/View;Landroid/view/View;IIII)V
      20: return

  public void a(android.support.design.widget.CoordinatorLayout, V, android.view.View, int, int, int[]);
    Code:
       0: return

  public void a(android.support.design.widget.CoordinatorLayout, V, android.view.View, int, int, int[], int);
    Code:
       0: iload         7
       2: ifne          18
       5: aload_0
       6: aload_1
       7: aload_2
       8: aload_3
       9: iload         4
      11: iload         5
      13: aload         6
      15: invokevirtual #40                 // Method a:(Landroid/support/design/widget/CoordinatorLayout;Landroid/view/View;Landroid/view/View;II[I)V
      18: return

  public boolean a(android.support.design.widget.CoordinatorLayout, V, int);
    Code:
       0: iconst_0
       1: ireturn

  public boolean a(android.support.design.widget.CoordinatorLayout, V, int, int, int, int);
    Code:
       0: iconst_0
       1: ireturn

  public boolean a(android.support.design.widget.CoordinatorLayout, V, android.graphics.Rect);
    Code:
       0: iconst_0
       1: ireturn

  public boolean a(android.support.design.widget.CoordinatorLayout, V, android.graphics.Rect, boolean);
    Code:
       0: iconst_0
       1: ireturn

  public boolean a(android.support.design.widget.CoordinatorLayout, V, android.view.MotionEvent);
    Code:
       0: iconst_0
       1: ireturn

  public boolean a(android.support.design.widget.CoordinatorLayout, V, android.view.View);
    Code:
       0: iconst_0
       1: ireturn

  public boolean a(android.support.design.widget.CoordinatorLayout, V, android.view.View, float, float);
    Code:
       0: iconst_0
       1: ireturn

  public boolean a(android.support.design.widget.CoordinatorLayout, V, android.view.View, float, float, boolean);
    Code:
       0: iconst_0
       1: ireturn

  public boolean a(android.support.design.widget.CoordinatorLayout, V, android.view.View, android.view.View, int);
    Code:
       0: iconst_0
       1: ireturn

  public boolean a(android.support.design.widget.CoordinatorLayout, V, android.view.View, android.view.View, int, int);
    Code:
       0: iload         6
       2: ifne          17
       5: aload_0
       6: aload_1
       7: aload_2
       8: aload_3
       9: aload         4
      11: iload         5
      13: invokevirtual #62                 // Method a:(Landroid/support/design/widget/CoordinatorLayout;Landroid/view/View;Landroid/view/View;Landroid/view/View;I)Z
      16: ireturn
      17: iconst_0
      18: ireturn

  public android.os.Parcelable b(android.support.design.widget.CoordinatorLayout, V);
    Code:
       0: getstatic     #70                 // Field android/view/View$BaseSavedState.EMPTY_STATE:Landroid/view/AbsSavedState;
       3: areturn

  public void b(android.support.design.widget.CoordinatorLayout, V, android.view.View, android.view.View, int);
    Code:
       0: return

  public void b(android.support.design.widget.CoordinatorLayout, V, android.view.View, android.view.View, int, int);
    Code:
       0: iload         6
       2: ifne          16
       5: aload_0
       6: aload_1
       7: aload_2
       8: aload_3
       9: aload         4
      11: iload         5
      13: invokevirtual #76                 // Method b:(Landroid/support/design/widget/CoordinatorLayout;Landroid/view/View;Landroid/view/View;Landroid/view/View;I)V
      16: return

  public boolean b(android.support.design.widget.CoordinatorLayout, V, android.view.MotionEvent);
    Code:
       0: iconst_0
       1: ireturn

  public boolean b(android.support.design.widget.CoordinatorLayout, V, android.view.View);
    Code:
       0: iconst_0
       1: ireturn

  public int c(android.support.design.widget.CoordinatorLayout, V);
    Code:
       0: ldc           #79                 // int -16777216
       2: ireturn

  public void c();
    Code:
       0: return

  public void c(android.support.design.widget.CoordinatorLayout, V, android.view.View);
    Code:
       0: return

  public float d(android.support.design.widget.CoordinatorLayout, V);
    Code:
       0: fconst_0
       1: freturn

  public void d(android.support.design.widget.CoordinatorLayout, V, android.view.View);
    Code:
       0: return

  public boolean e(android.support.design.widget.CoordinatorLayout, V);
    Code:
       0: aload_0
       1: aload_1
       2: aload_2
       3: invokevirtual #88                 // Method d:(Landroid/support/design/widget/CoordinatorLayout;Landroid/view/View;)F
       6: fconst_0
       7: fcmpl
       8: ifle          13
      11: iconst_1
      12: ireturn
      13: iconst_0
      14: ireturn
}
