class android.support.design.widget.CoordinatorLayout$1 implements android.support.v4.view.p {
  final android.support.design.widget.CoordinatorLayout a;

  android.support.design.widget.CoordinatorLayout$1(android.support.design.widget.CoordinatorLayout);
    Code:
       0: aload_0
       1: aload_1
       2: putfield      #17                 // Field a:Landroid/support/design/widget/CoordinatorLayout;
       5: aload_0
       6: invokespecial #19                 // Method java/lang/Object."<init>":()V
       9: return

  public android.support.v4.view.ab a(android.view.View, android.support.v4.view.ab);
    Code:
       0: aload_0
       1: getfield      #17                 // Field a:Landroid/support/design/widget/CoordinatorLayout;
       4: aload_2
       5: invokevirtual #24                 // Method android/support/design/widget/CoordinatorLayout.a:(Landroid/support/v4/view/ab;)Landroid/support/v4/view/ab;
       8: areturn
}
