class android.support.design.widget.e$3 implements android.view.ViewTreeObserver$OnPreDrawListener {
  final android.support.design.widget.e a;

  android.support.design.widget.e$3(android.support.design.widget.e);
    Code:
       0: aload_0
       1: aload_1
       2: putfield      #17                 // Field a:Landroid/support/design/widget/e;
       5: aload_0
       6: invokespecial #19                 // Method java/lang/Object."<init>":()V
       9: return

  public boolean onPreDraw();
    Code:
       0: aload_0
       1: getfield      #17                 // Field a:Landroid/support/design/widget/e;
       4: invokevirtual #25                 // Method android/support/design/widget/e.j:()V
       7: iconst_1
       8: ireturn
}
