class android.support.design.widget.e$b extends android.support.design.widget.e$e {
  final android.support.design.widget.e a;

  android.support.design.widget.e$b(android.support.design.widget.e);
    Code:
       0: aload_0
       1: aload_1
       2: putfield      #13                 // Field a:Landroid/support/design/widget/e;
       5: aload_0
       6: aload_1
       7: aconst_null
       8: invokespecial #16                 // Method android/support/design/widget/e$e."<init>":(Landroid/support/design/widget/e;Landroid/support/design/widget/e$1;)V
      11: return

  protected float a();
    Code:
       0: aload_0
       1: getfield      #13                 // Field a:Landroid/support/design/widget/e;
       4: getfield      #22                 // Field android/support/design/widget/e.h:F
       7: aload_0
       8: getfield      #13                 // Field a:Landroid/support/design/widget/e;
      11: getfield      #25                 // Field android/support/design/widget/e.i:F
      14: fadd
      15: freturn
}
