class android.support.design.widget.f extends android.support.design.widget.e {
  android.support.design.widget.f(android.support.design.widget.r, android.support.design.widget.j);
    Code:
       0: aload_0
       1: aload_1
       2: aload_2
       3: invokespecial #13                 // Method android/support/design/widget/e."<init>":(Landroid/support/design/widget/r;Landroid/support/design/widget/j;)V
       6: return

  public float a();
    Code:
       0: aload_0
       1: getfield      #19                 // Field n:Landroid/support/design/widget/r;
       4: invokevirtual #24                 // Method android/support/design/widget/r.getElevation:()F
       7: freturn

  void a(float, float);
    Code:
       0: getstatic     #31                 // Field android/os/Build$VERSION.SDK_INT:I
       3: bipush        21
       5: if_icmpne     76
       8: aload_0
       9: getfield      #19                 // Field n:Landroid/support/design/widget/r;
      12: invokevirtual #35                 // Method android/support/design/widget/r.isEnabled:()Z
      15: ifeq          57
      18: aload_0
      19: getfield      #19                 // Field n:Landroid/support/design/widget/r;
      22: fload_1
      23: invokevirtual #39                 // Method android/support/design/widget/r.setElevation:(F)V
      26: aload_0
      27: getfield      #19                 // Field n:Landroid/support/design/widget/r;
      30: invokevirtual #42                 // Method android/support/design/widget/r.isFocused:()Z
      33: ifne          46
      36: aload_0
      37: getfield      #19                 // Field n:Landroid/support/design/widget/r;
      40: invokevirtual #45                 // Method android/support/design/widget/r.isPressed:()Z
      43: ifeq          65
      46: aload_0
      47: getfield      #19                 // Field n:Landroid/support/design/widget/r;
      50: fload_2
      51: invokevirtual #48                 // Method android/support/design/widget/r.setTranslationZ:(F)V
      54: goto          490
      57: aload_0
      58: getfield      #19                 // Field n:Landroid/support/design/widget/r;
      61: fconst_0
      62: invokevirtual #39                 // Method android/support/design/widget/r.setElevation:(F)V
      65: aload_0
      66: getfield      #19                 // Field n:Landroid/support/design/widget/r;
      69: fconst_0
      70: invokevirtual #48                 // Method android/support/design/widget/r.setTranslationZ:(F)V
      73: goto          490
      76: new           #50                 // class android/animation/StateListAnimator
      79: dup
      80: invokespecial #53                 // Method android/animation/StateListAnimator."<init>":()V
      83: astore_3
      84: new           #55                 // class android/animation/AnimatorSet
      87: dup
      88: invokespecial #56                 // Method android/animation/AnimatorSet."<init>":()V
      91: astore        4
      93: aload         4
      95: aload_0
      96: getfield      #19                 // Field n:Landroid/support/design/widget/r;
      99: ldc           #58                 // String elevation
     101: iconst_1
     102: newarray       float
     104: dup
     105: iconst_0
     106: fload_1
     107: fastore
     108: invokestatic  #64                 // Method android/animation/ObjectAnimator.ofFloat:(Ljava/lang/Object;Ljava/lang/String;[F)Landroid/animation/ObjectAnimator;
     111: lconst_0
     112: invokevirtual #68                 // Method android/animation/ObjectAnimator.setDuration:(J)Landroid/animation/ObjectAnimator;
     115: invokevirtual #72                 // Method android/animation/AnimatorSet.play:(Landroid/animation/Animator;)Landroid/animation/AnimatorSet$Builder;
     118: aload_0
     119: getfield      #19                 // Field n:Landroid/support/design/widget/r;
     122: getstatic     #78                 // Field android/view/View.TRANSLATION_Z:Landroid/util/Property;
     125: iconst_1
     126: newarray       float
     128: dup
     129: iconst_0
     130: fload_2
     131: fastore
     132: invokestatic  #81                 // Method android/animation/ObjectAnimator.ofFloat:(Ljava/lang/Object;Landroid/util/Property;[F)Landroid/animation/ObjectAnimator;
     135: ldc2_w        #82                 // long 100l
     138: invokevirtual #68                 // Method android/animation/ObjectAnimator.setDuration:(J)Landroid/animation/ObjectAnimator;
     141: invokevirtual #88                 // Method android/animation/AnimatorSet$Builder.with:(Landroid/animation/Animator;)Landroid/animation/AnimatorSet$Builder;
     144: pop
     145: aload         4
     147: getstatic     #91                 // Field a:Landroid/view/animation/Interpolator;
     150: invokevirtual #95                 // Method android/animation/AnimatorSet.setInterpolator:(Landroid/animation/TimeInterpolator;)V
     153: aload_3
     154: getstatic     #99                 // Field j:[I
     157: aload         4
     159: invokevirtual #103                // Method android/animation/StateListAnimator.addState:([ILandroid/animation/Animator;)V
     162: new           #55                 // class android/animation/AnimatorSet
     165: dup
     166: invokespecial #56                 // Method android/animation/AnimatorSet."<init>":()V
     169: astore        4
     171: aload         4
     173: aload_0
     174: getfield      #19                 // Field n:Landroid/support/design/widget/r;
     177: ldc           #58                 // String elevation
     179: iconst_1
     180: newarray       float
     182: dup
     183: iconst_0
     184: fload_1
     185: fastore
     186: invokestatic  #64                 // Method android/animation/ObjectAnimator.ofFloat:(Ljava/lang/Object;Ljava/lang/String;[F)Landroid/animation/ObjectAnimator;
     189: lconst_0
     190: invokevirtual #68                 // Method android/animation/ObjectAnimator.setDuration:(J)Landroid/animation/ObjectAnimator;
     193: invokevirtual #72                 // Method android/animation/AnimatorSet.play:(Landroid/animation/Animator;)Landroid/animation/AnimatorSet$Builder;
     196: aload_0
     197: getfield      #19                 // Field n:Landroid/support/design/widget/r;
     200: getstatic     #78                 // Field android/view/View.TRANSLATION_Z:Landroid/util/Property;
     203: iconst_1
     204: newarray       float
     206: dup
     207: iconst_0
     208: fload_2
     209: fastore
     210: invokestatic  #81                 // Method android/animation/ObjectAnimator.ofFloat:(Ljava/lang/Object;Landroid/util/Property;[F)Landroid/animation/ObjectAnimator;
     213: ldc2_w        #82                 // long 100l
     216: invokevirtual #68                 // Method android/animation/ObjectAnimator.setDuration:(J)Landroid/animation/ObjectAnimator;
     219: invokevirtual #88                 // Method android/animation/AnimatorSet$Builder.with:(Landroid/animation/Animator;)Landroid/animation/AnimatorSet$Builder;
     222: pop
     223: aload         4
     225: getstatic     #91                 // Field a:Landroid/view/animation/Interpolator;
     228: invokevirtual #95                 // Method android/animation/AnimatorSet.setInterpolator:(Landroid/animation/TimeInterpolator;)V
     231: aload_3
     232: getstatic     #106                // Field k:[I
     235: aload         4
     237: invokevirtual #103                // Method android/animation/StateListAnimator.addState:([ILandroid/animation/Animator;)V
     240: new           #55                 // class android/animation/AnimatorSet
     243: dup
     244: invokespecial #56                 // Method android/animation/AnimatorSet."<init>":()V
     247: astore        4
     249: new           #108                // class java/util/ArrayList
     252: dup
     253: invokespecial #109                // Method java/util/ArrayList."<init>":()V
     256: astore        5
     258: aload         5
     260: aload_0
     261: getfield      #19                 // Field n:Landroid/support/design/widget/r;
     264: ldc           #58                 // String elevation
     266: iconst_1
     267: newarray       float
     269: dup
     270: iconst_0
     271: fload_1
     272: fastore
     273: invokestatic  #64                 // Method android/animation/ObjectAnimator.ofFloat:(Ljava/lang/Object;Ljava/lang/String;[F)Landroid/animation/ObjectAnimator;
     276: lconst_0
     277: invokevirtual #68                 // Method android/animation/ObjectAnimator.setDuration:(J)Landroid/animation/ObjectAnimator;
     280: invokeinterface #115,  2          // InterfaceMethod java/util/List.add:(Ljava/lang/Object;)Z
     285: pop
     286: getstatic     #31                 // Field android/os/Build$VERSION.SDK_INT:I
     289: bipush        22
     291: if_icmplt     339
     294: getstatic     #31                 // Field android/os/Build$VERSION.SDK_INT:I
     297: bipush        24
     299: if_icmpgt     339
     302: aload         5
     304: aload_0
     305: getfield      #19                 // Field n:Landroid/support/design/widget/r;
     308: getstatic     #78                 // Field android/view/View.TRANSLATION_Z:Landroid/util/Property;
     311: iconst_1
     312: newarray       float
     314: dup
     315: iconst_0
     316: aload_0
     317: getfield      #19                 // Field n:Landroid/support/design/widget/r;
     320: invokevirtual #118                // Method android/support/design/widget/r.getTranslationZ:()F
     323: fastore
     324: invokestatic  #81                 // Method android/animation/ObjectAnimator.ofFloat:(Ljava/lang/Object;Landroid/util/Property;[F)Landroid/animation/ObjectAnimator;
     327: ldc2_w        #82                 // long 100l
     330: invokevirtual #68                 // Method android/animation/ObjectAnimator.setDuration:(J)Landroid/animation/ObjectAnimator;
     333: invokeinterface #115,  2          // InterfaceMethod java/util/List.add:(Ljava/lang/Object;)Z
     338: pop
     339: aload         5
     341: aload_0
     342: getfield      #19                 // Field n:Landroid/support/design/widget/r;
     345: getstatic     #78                 // Field android/view/View.TRANSLATION_Z:Landroid/util/Property;
     348: iconst_1
     349: newarray       float
     351: dup
     352: iconst_0
     353: fconst_0
     354: fastore
     355: invokestatic  #81                 // Method android/animation/ObjectAnimator.ofFloat:(Ljava/lang/Object;Landroid/util/Property;[F)Landroid/animation/ObjectAnimator;
     358: ldc2_w        #82                 // long 100l
     361: invokevirtual #68                 // Method android/animation/ObjectAnimator.setDuration:(J)Landroid/animation/ObjectAnimator;
     364: invokeinterface #115,  2          // InterfaceMethod java/util/List.add:(Ljava/lang/Object;)Z
     369: pop
     370: aload         4
     372: aload         5
     374: iconst_0
     375: anewarray     #60                 // class android/animation/ObjectAnimator
     378: invokeinterface #122,  2          // InterfaceMethod java/util/List.toArray:([Ljava/lang/Object;)[Ljava/lang/Object;
     383: checkcast     #124                // class "[Landroid/animation/Animator;"
     386: invokevirtual #128                // Method android/animation/AnimatorSet.playSequentially:([Landroid/animation/Animator;)V
     389: aload         4
     391: getstatic     #91                 // Field a:Landroid/view/animation/Interpolator;
     394: invokevirtual #95                 // Method android/animation/AnimatorSet.setInterpolator:(Landroid/animation/TimeInterpolator;)V
     397: aload_3
     398: getstatic     #131                // Field l:[I
     401: aload         4
     403: invokevirtual #103                // Method android/animation/StateListAnimator.addState:([ILandroid/animation/Animator;)V
     406: new           #55                 // class android/animation/AnimatorSet
     409: dup
     410: invokespecial #56                 // Method android/animation/AnimatorSet."<init>":()V
     413: astore        4
     415: aload         4
     417: aload_0
     418: getfield      #19                 // Field n:Landroid/support/design/widget/r;
     421: ldc           #58                 // String elevation
     423: iconst_1
     424: newarray       float
     426: dup
     427: iconst_0
     428: fconst_0
     429: fastore
     430: invokestatic  #64                 // Method android/animation/ObjectAnimator.ofFloat:(Ljava/lang/Object;Ljava/lang/String;[F)Landroid/animation/ObjectAnimator;
     433: lconst_0
     434: invokevirtual #68                 // Method android/animation/ObjectAnimator.setDuration:(J)Landroid/animation/ObjectAnimator;
     437: invokevirtual #72                 // Method android/animation/AnimatorSet.play:(Landroid/animation/Animator;)Landroid/animation/AnimatorSet$Builder;
     440: aload_0
     441: getfield      #19                 // Field n:Landroid/support/design/widget/r;
     444: getstatic     #78                 // Field android/view/View.TRANSLATION_Z:Landroid/util/Property;
     447: iconst_1
     448: newarray       float
     450: dup
     451: iconst_0
     452: fconst_0
     453: fastore
     454: invokestatic  #81                 // Method android/animation/ObjectAnimator.ofFloat:(Ljava/lang/Object;Landroid/util/Property;[F)Landroid/animation/ObjectAnimator;
     457: lconst_0
     458: invokevirtual #68                 // Method android/animation/ObjectAnimator.setDuration:(J)Landroid/animation/ObjectAnimator;
     461: invokevirtual #88                 // Method android/animation/AnimatorSet$Builder.with:(Landroid/animation/Animator;)Landroid/animation/AnimatorSet$Builder;
     464: pop
     465: aload         4
     467: getstatic     #91                 // Field a:Landroid/view/animation/Interpolator;
     470: invokevirtual #95                 // Method android/animation/AnimatorSet.setInterpolator:(Landroid/animation/TimeInterpolator;)V
     473: aload_3
     474: getstatic     #134                // Field m:[I
     477: aload         4
     479: invokevirtual #103                // Method android/animation/StateListAnimator.addState:([ILandroid/animation/Animator;)V
     482: aload_0
     483: getfield      #19                 // Field n:Landroid/support/design/widget/r;
     486: aload_3
     487: invokevirtual #138                // Method android/support/design/widget/r.setStateListAnimator:(Landroid/animation/StateListAnimator;)V
     490: aload_0
     491: getfield      #142                // Field o:Landroid/support/design/widget/j;
     494: invokeinterface #147,  1          // InterfaceMethod android/support/design/widget/j.b:()Z
     499: ifeq          506
     502: aload_0
     503: invokevirtual #150                // Method e:()V
     506: return

  void a(int);
    Code:
       0: aload_0
       1: getfield      #154                // Field e:Landroid/graphics/drawable/Drawable;
       4: instanceof    #156                // class android/graphics/drawable/RippleDrawable
       7: ifeq          25
      10: aload_0
      11: getfield      #154                // Field e:Landroid/graphics/drawable/Drawable;
      14: checkcast     #156                // class android/graphics/drawable/RippleDrawable
      17: iload_1
      18: invokestatic  #162                // Method android/content/res/ColorStateList.valueOf:(I)Landroid/content/res/ColorStateList;
      21: invokevirtual #166                // Method android/graphics/drawable/RippleDrawable.setColor:(Landroid/content/res/ColorStateList;)V
      24: return
      25: aload_0
      26: iload_1
      27: invokespecial #168                // Method android/support/design/widget/e.a:(I)V
      30: return

  void a(android.content.res.ColorStateList, android.graphics.PorterDuff$Mode, int, int);
    Code:
       0: aload_0
       1: aload_0
       2: invokevirtual #172                // Method k:()Landroid/graphics/drawable/GradientDrawable;
       5: invokestatic  #178                // Method android/support/v4/b/a/a.f:(Landroid/graphics/drawable/Drawable;)Landroid/graphics/drawable/Drawable;
       8: putfield      #181                // Field d:Landroid/graphics/drawable/Drawable;
      11: aload_0
      12: getfield      #181                // Field d:Landroid/graphics/drawable/Drawable;
      15: aload_1
      16: invokestatic  #184                // Method android/support/v4/b/a/a.a:(Landroid/graphics/drawable/Drawable;Landroid/content/res/ColorStateList;)V
      19: aload_2
      20: ifnull        31
      23: aload_0
      24: getfield      #181                // Field d:Landroid/graphics/drawable/Drawable;
      27: aload_2
      28: invokestatic  #187                // Method android/support/v4/b/a/a.a:(Landroid/graphics/drawable/Drawable;Landroid/graphics/PorterDuff$Mode;)V
      31: iload         4
      33: ifle          76
      36: aload_0
      37: aload_0
      38: iload         4
      40: aload_1
      41: invokevirtual #190                // Method a:(ILandroid/content/res/ColorStateList;)Landroid/support/design/widget/c;
      44: putfield      #193                // Field f:Landroid/support/design/widget/c;
      47: new           #195                // class android/graphics/drawable/LayerDrawable
      50: dup
      51: iconst_2
      52: anewarray     #197                // class android/graphics/drawable/Drawable
      55: dup
      56: iconst_0
      57: aload_0
      58: getfield      #193                // Field f:Landroid/support/design/widget/c;
      61: aastore
      62: dup
      63: iconst_1
      64: aload_0
      65: getfield      #181                // Field d:Landroid/graphics/drawable/Drawable;
      68: aastore
      69: invokespecial #200                // Method android/graphics/drawable/LayerDrawable."<init>":([Landroid/graphics/drawable/Drawable;)V
      72: astore_1
      73: goto          86
      76: aload_0
      77: aconst_null
      78: putfield      #193                // Field f:Landroid/support/design/widget/c;
      81: aload_0
      82: getfield      #181                // Field d:Landroid/graphics/drawable/Drawable;
      85: astore_1
      86: aload_0
      87: new           #156                // class android/graphics/drawable/RippleDrawable
      90: dup
      91: iload_3
      92: invokestatic  #162                // Method android/content/res/ColorStateList.valueOf:(I)Landroid/content/res/ColorStateList;
      95: aload_1
      96: aconst_null
      97: invokespecial #203                // Method android/graphics/drawable/RippleDrawable."<init>":(Landroid/content/res/ColorStateList;Landroid/graphics/drawable/Drawable;Landroid/graphics/drawable/Drawable;)V
     100: putfield      #154                // Field e:Landroid/graphics/drawable/Drawable;
     103: aload_0
     104: aload_0
     105: getfield      #154                // Field e:Landroid/graphics/drawable/Drawable;
     108: putfield      #206                // Field g:Landroid/graphics/drawable/Drawable;
     111: aload_0
     112: getfield      #142                // Field o:Landroid/support/design/widget/j;
     115: aload_0
     116: getfield      #154                // Field e:Landroid/graphics/drawable/Drawable;
     119: invokeinterface #209,  2          // InterfaceMethod android/support/design/widget/j.a:(Landroid/graphics/drawable/Drawable;)V
     124: return

  void a(android.graphics.Rect);
    Code:
       0: aload_0
       1: getfield      #142                // Field o:Landroid/support/design/widget/j;
       4: invokeinterface #147,  1          // InterfaceMethod android/support/design/widget/j.b:()Z
       9: ifeq          71
      12: aload_0
      13: getfield      #142                // Field o:Landroid/support/design/widget/j;
      16: invokeinterface #212,  1          // InterfaceMethod android/support/design/widget/j.a:()F
      21: fstore_2
      22: aload_0
      23: invokevirtual #213                // Method a:()F
      26: aload_0
      27: getfield      #217                // Field i:F
      30: fadd
      31: fstore_3
      32: fload_3
      33: fload_2
      34: iconst_0
      35: invokestatic  #222                // Method android/support/design/widget/i.b:(FFZ)F
      38: f2d
      39: invokestatic  #228                // Method java/lang/Math.ceil:(D)D
      42: d2i
      43: istore        4
      45: fload_3
      46: fload_2
      47: iconst_0
      48: invokestatic  #230                // Method android/support/design/widget/i.a:(FFZ)F
      51: f2d
      52: invokestatic  #228                // Method java/lang/Math.ceil:(D)D
      55: d2i
      56: istore        5
      58: aload_1
      59: iload         4
      61: iload         5
      63: iload         4
      65: iload         5
      67: invokevirtual #236                // Method android/graphics/Rect.set:(IIII)V
      70: return
      71: aload_1
      72: iconst_0
      73: iconst_0
      74: iconst_0
      75: iconst_0
      76: invokevirtual #236                // Method android/graphics/Rect.set:(IIII)V
      79: return

  void a(int[]);
    Code:
       0: return

  void b();
    Code:
       0: return

  void b(android.graphics.Rect);
    Code:
       0: aload_0
       1: getfield      #142                // Field o:Landroid/support/design/widget/j;
       4: invokeinterface #147,  1          // InterfaceMethod android/support/design/widget/j.b:()Z
       9: ifeq          61
      12: aload_0
      13: new           #239                // class android/graphics/drawable/InsetDrawable
      16: dup
      17: aload_0
      18: getfield      #154                // Field e:Landroid/graphics/drawable/Drawable;
      21: aload_1
      22: getfield      #242                // Field android/graphics/Rect.left:I
      25: aload_1
      26: getfield      #245                // Field android/graphics/Rect.top:I
      29: aload_1
      30: getfield      #248                // Field android/graphics/Rect.right:I
      33: aload_1
      34: getfield      #251                // Field android/graphics/Rect.bottom:I
      37: invokespecial #254                // Method android/graphics/drawable/InsetDrawable."<init>":(Landroid/graphics/drawable/Drawable;IIII)V
      40: putfield      #256                // Field p:Landroid/graphics/drawable/InsetDrawable;
      43: aload_0
      44: getfield      #142                // Field o:Landroid/support/design/widget/j;
      47: astore_2
      48: aload_0
      49: getfield      #256                // Field p:Landroid/graphics/drawable/InsetDrawable;
      52: astore_1
      53: aload_2
      54: aload_1
      55: invokeinterface #209,  2          // InterfaceMethod android/support/design/widget/j.a:(Landroid/graphics/drawable/Drawable;)V
      60: return
      61: aload_0
      62: getfield      #142                // Field o:Landroid/support/design/widget/j;
      65: astore_2
      66: aload_0
      67: getfield      #154                // Field e:Landroid/graphics/drawable/Drawable;
      70: astore_1
      71: goto          53

  void d();
    Code:
       0: aload_0
       1: invokevirtual #150                // Method e:()V
       4: return

  boolean h();
    Code:
       0: iconst_0
       1: ireturn

  android.support.design.widget.c i();
    Code:
       0: new           #260                // class android/support/design/widget/d
       3: dup
       4: invokespecial #261                // Method android/support/design/widget/d."<init>":()V
       7: areturn

  android.graphics.drawable.GradientDrawable l();
    Code:
       0: new           #6                  // class android/support/design/widget/f$a
       3: dup
       4: invokespecial #262                // Method android/support/design/widget/f$a."<init>":()V
       7: areturn
}
