class android.support.design.widget.l$a {
  final int[] a;

  final android.animation.ValueAnimator b;

  android.support.design.widget.l$a(int[], android.animation.ValueAnimator);
    Code:
       0: aload_0
       1: invokespecial #15                 // Method java/lang/Object."<init>":()V
       4: aload_0
       5: aload_1
       6: putfield      #17                 // Field a:[I
       9: aload_0
      10: aload_2
      11: putfield      #19                 // Field b:Landroid/animation/ValueAnimator;
      14: return
}
