public class android.support.v4.view.b.b extends android.support.v4.view.b.d {
  static {};
    Code:
       0: sipush        201
       3: newarray       float
       5: dup
       6: iconst_0
       7: fconst_0
       8: fastore
       9: dup
      10: iconst_1
      11: ldc           #9                  // float 1.0E-4f
      13: fastore
      14: dup
      15: iconst_2
      16: ldc           #10                 // float 2.0E-4f
      18: fastore
      19: dup
      20: iconst_3
      21: ldc           #11                 // float 5.0E-4f
      23: fastore
      24: dup
      25: iconst_4
      26: ldc           #12                 // float 9.0E-4f
      28: fastore
      29: dup
      30: iconst_5
      31: ldc           #13                 // float 0.0014f
      33: fastore
      34: dup
      35: bipush        6
      37: ldc           #14                 // float 0.002f
      39: fastore
      40: dup
      41: bipush        7
      43: ldc           #15                 // float 0.0027f
      45: fastore
      46: dup
      47: bipush        8
      49: ldc           #16                 // float 0.0036f
      51: fastore
      52: dup
      53: bipush        9
      55: ldc           #17                 // float 0.0046f
      57: fastore
      58: dup
      59: bipush        10
      61: ldc           #18                 // float 0.0058f
      63: fastore
      64: dup
      65: bipush        11
      67: ldc           #19                 // float 0.0071f
      69: fastore
      70: dup
      71: bipush        12
      73: ldc           #20                 // float 0.0085f
      75: fastore
      76: dup
      77: bipush        13
      79: ldc           #21                 // float 0.0101f
      81: fastore
      82: dup
      83: bipush        14
      85: ldc           #22                 // float 0.0118f
      87: fastore
      88: dup
      89: bipush        15
      91: ldc           #23                 // float 0.0137f
      93: fastore
      94: dup
      95: bipush        16
      97: ldc           #24                 // float 0.0158f
      99: fastore
     100: dup
     101: bipush        17
     103: ldc           #25                 // float 0.018f
     105: fastore
     106: dup
     107: bipush        18
     109: ldc           #26                 // float 0.0205f
     111: fastore
     112: dup
     113: bipush        19
     115: ldc           #27                 // float 0.0231f
     117: fastore
     118: dup
     119: bipush        20
     121: ldc           #28                 // float 0.0259f
     123: fastore
     124: dup
     125: bipush        21
     127: ldc           #29                 // float 0.0289f
     129: fastore
     130: dup
     131: bipush        22
     133: ldc           #30                 // float 0.0321f
     135: fastore
     136: dup
     137: bipush        23
     139: ldc           #31                 // float 0.0355f
     141: fastore
     142: dup
     143: bipush        24
     145: ldc           #32                 // float 0.0391f
     147: fastore
     148: dup
     149: bipush        25
     151: ldc           #33                 // float 0.043f
     153: fastore
     154: dup
     155: bipush        26
     157: ldc           #34                 // float 0.0471f
     159: fastore
     160: dup
     161: bipush        27
     163: ldc           #35                 // float 0.0514f
     165: fastore
     166: dup
     167: bipush        28
     169: ldc           #36                 // float 0.056f
     171: fastore
     172: dup
     173: bipush        29
     175: ldc           #37                 // float 0.0608f
     177: fastore
     178: dup
     179: bipush        30
     181: ldc           #38                 // float 0.066f
     183: fastore
     184: dup
     185: bipush        31
     187: ldc           #39                 // float 0.0714f
     189: fastore
     190: dup
     191: bipush        32
     193: ldc           #40                 // float 0.0771f
     195: fastore
     196: dup
     197: bipush        33
     199: ldc           #41                 // float 0.083f
     201: fastore
     202: dup
     203: bipush        34
     205: ldc           #42                 // float 0.0893f
     207: fastore
     208: dup
     209: bipush        35
     211: ldc           #43                 // float 0.0959f
     213: fastore
     214: dup
     215: bipush        36
     217: ldc           #44                 // float 0.1029f
     219: fastore
     220: dup
     221: bipush        37
     223: ldc           #45                 // float 0.1101f
     225: fastore
     226: dup
     227: bipush        38
     229: ldc           #46                 // float 0.1177f
     231: fastore
     232: dup
     233: bipush        39
     235: ldc           #47                 // float 0.1257f
     237: fastore
     238: dup
     239: bipush        40
     241: ldc           #48                 // float 0.1339f
     243: fastore
     244: dup
     245: bipush        41
     247: ldc           #49                 // float 0.1426f
     249: fastore
     250: dup
     251: bipush        42
     253: ldc           #50                 // float 0.1516f
     255: fastore
     256: dup
     257: bipush        43
     259: ldc           #51                 // float 0.161f
     261: fastore
     262: dup
     263: bipush        44
     265: ldc           #52                 // float 0.1707f
     267: fastore
     268: dup
     269: bipush        45
     271: ldc           #53                 // float 0.1808f
     273: fastore
     274: dup
     275: bipush        46
     277: ldc           #54                 // float 0.1913f
     279: fastore
     280: dup
     281: bipush        47
     283: ldc           #55                 // float 0.2021f
     285: fastore
     286: dup
     287: bipush        48
     289: ldc           #56                 // float 0.2133f
     291: fastore
     292: dup
     293: bipush        49
     295: ldc           #57                 // float 0.2248f
     297: fastore
     298: dup
     299: bipush        50
     301: ldc           #58                 // float 0.2366f
     303: fastore
     304: dup
     305: bipush        51
     307: ldc           #59                 // float 0.2487f
     309: fastore
     310: dup
     311: bipush        52
     313: ldc           #60                 // float 0.2611f
     315: fastore
     316: dup
     317: bipush        53
     319: ldc           #61                 // float 0.2738f
     321: fastore
     322: dup
     323: bipush        54
     325: ldc           #62                 // float 0.2867f
     327: fastore
     328: dup
     329: bipush        55
     331: ldc           #63                 // float 0.2998f
     333: fastore
     334: dup
     335: bipush        56
     337: ldc           #64                 // float 0.3131f
     339: fastore
     340: dup
     341: bipush        57
     343: ldc           #65                 // float 0.3265f
     345: fastore
     346: dup
     347: bipush        58
     349: ldc           #66                 // float 0.34f
     351: fastore
     352: dup
     353: bipush        59
     355: ldc           #67                 // float 0.3536f
     357: fastore
     358: dup
     359: bipush        60
     361: ldc           #68                 // float 0.3673f
     363: fastore
     364: dup
     365: bipush        61
     367: ldc           #69                 // float 0.381f
     369: fastore
     370: dup
     371: bipush        62
     373: ldc           #70                 // float 0.3946f
     375: fastore
     376: dup
     377: bipush        63
     379: ldc           #71                 // float 0.4082f
     381: fastore
     382: dup
     383: bipush        64
     385: ldc           #72                 // float 0.4217f
     387: fastore
     388: dup
     389: bipush        65
     391: ldc           #73                 // float 0.4352f
     393: fastore
     394: dup
     395: bipush        66
     397: ldc           #74                 // float 0.4485f
     399: fastore
     400: dup
     401: bipush        67
     403: ldc           #75                 // float 0.4616f
     405: fastore
     406: dup
     407: bipush        68
     409: ldc           #76                 // float 0.4746f
     411: fastore
     412: dup
     413: bipush        69
     415: ldc           #77                 // float 0.4874f
     417: fastore
     418: dup
     419: bipush        70
     421: ldc           #78                 // float 0.5f
     423: fastore
     424: dup
     425: bipush        71
     427: ldc           #79                 // float 0.5124f
     429: fastore
     430: dup
     431: bipush        72
     433: ldc           #80                 // float 0.5246f
     435: fastore
     436: dup
     437: bipush        73
     439: ldc           #81                 // float 0.5365f
     441: fastore
     442: dup
     443: bipush        74
     445: ldc           #82                 // float 0.5482f
     447: fastore
     448: dup
     449: bipush        75
     451: ldc           #83                 // float 0.5597f
     453: fastore
     454: dup
     455: bipush        76
     457: ldc           #84                 // float 0.571f
     459: fastore
     460: dup
     461: bipush        77
     463: ldc           #85                 // float 0.582f
     465: fastore
     466: dup
     467: bipush        78
     469: ldc           #86                 // float 0.5928f
     471: fastore
     472: dup
     473: bipush        79
     475: ldc           #87                 // float 0.6033f
     477: fastore
     478: dup
     479: bipush        80
     481: ldc           #88                 // float 0.6136f
     483: fastore
     484: dup
     485: bipush        81
     487: ldc           #89                 // float 0.6237f
     489: fastore
     490: dup
     491: bipush        82
     493: ldc           #90                 // float 0.6335f
     495: fastore
     496: dup
     497: bipush        83
     499: ldc           #91                 // float 0.6431f
     501: fastore
     502: dup
     503: bipush        84
     505: ldc           #92                 // float 0.6525f
     507: fastore
     508: dup
     509: bipush        85
     511: ldc           #93                 // float 0.6616f
     513: fastore
     514: dup
     515: bipush        86
     517: ldc           #94                 // float 0.6706f
     519: fastore
     520: dup
     521: bipush        87
     523: ldc           #95                 // float 0.6793f
     525: fastore
     526: dup
     527: bipush        88
     529: ldc           #96                 // float 0.6878f
     531: fastore
     532: dup
     533: bipush        89
     535: ldc           #97                 // float 0.6961f
     537: fastore
     538: dup
     539: bipush        90
     541: ldc           #98                 // float 0.7043f
     543: fastore
     544: dup
     545: bipush        91
     547: ldc           #99                 // float 0.7122f
     549: fastore
     550: dup
     551: bipush        92
     553: ldc           #100                // float 0.7199f
     555: fastore
     556: dup
     557: bipush        93
     559: ldc           #101                // float 0.7275f
     561: fastore
     562: dup
     563: bipush        94
     565: ldc           #102                // float 0.7349f
     567: fastore
     568: dup
     569: bipush        95
     571: ldc           #103                // float 0.7421f
     573: fastore
     574: dup
     575: bipush        96
     577: ldc           #104                // float 0.7491f
     579: fastore
     580: dup
     581: bipush        97
     583: ldc           #105                // float 0.7559f
     585: fastore
     586: dup
     587: bipush        98
     589: ldc           #106                // float 0.7626f
     591: fastore
     592: dup
     593: bipush        99
     595: ldc           #107                // float 0.7692f
     597: fastore
     598: dup
     599: bipush        100
     601: ldc           #108                // float 0.7756f
     603: fastore
     604: dup
     605: bipush        101
     607: ldc           #109                // float 0.7818f
     609: fastore
     610: dup
     611: bipush        102
     613: ldc           #110                // float 0.7879f
     615: fastore
     616: dup
     617: bipush        103
     619: ldc           #111                // float 0.7938f
     621: fastore
     622: dup
     623: bipush        104
     625: ldc           #112                // float 0.7996f
     627: fastore
     628: dup
     629: bipush        105
     631: ldc           #113                // float 0.8053f
     633: fastore
     634: dup
     635: bipush        106
     637: ldc           #114                // float 0.8108f
     639: fastore
     640: dup
     641: bipush        107
     643: ldc           #115                // float 0.8162f
     645: fastore
     646: dup
     647: bipush        108
     649: ldc           #116                // float 0.8215f
     651: fastore
     652: dup
     653: bipush        109
     655: ldc           #117                // float 0.8266f
     657: fastore
     658: dup
     659: bipush        110
     661: ldc           #118                // float 0.8317f
     663: fastore
     664: dup
     665: bipush        111
     667: ldc           #119                // float 0.8366f
     669: fastore
     670: dup
     671: bipush        112
     673: ldc           #120                // float 0.8414f
     675: fastore
     676: dup
     677: bipush        113
     679: ldc           #121                // float 0.8461f
     681: fastore
     682: dup
     683: bipush        114
     685: ldc           #122                // float 0.8507f
     687: fastore
     688: dup
     689: bipush        115
     691: ldc           #123                // float 0.8551f
     693: fastore
     694: dup
     695: bipush        116
     697: ldc           #124                // float 0.8595f
     699: fastore
     700: dup
     701: bipush        117
     703: ldc           #125                // float 0.8638f
     705: fastore
     706: dup
     707: bipush        118
     709: ldc           #126                // float 0.8679f
     711: fastore
     712: dup
     713: bipush        119
     715: ldc           #127                // float 0.872f
     717: fastore
     718: dup
     719: bipush        120
     721: ldc           #128                // float 0.876f
     723: fastore
     724: dup
     725: bipush        121
     727: ldc           #129                // float 0.8798f
     729: fastore
     730: dup
     731: bipush        122
     733: ldc           #130                // float 0.8836f
     735: fastore
     736: dup
     737: bipush        123
     739: ldc           #131                // float 0.8873f
     741: fastore
     742: dup
     743: bipush        124
     745: ldc           #132                // float 0.8909f
     747: fastore
     748: dup
     749: bipush        125
     751: ldc           #133                // float 0.8945f
     753: fastore
     754: dup
     755: bipush        126
     757: ldc           #134                // float 0.8979f
     759: fastore
     760: dup
     761: bipush        127
     763: ldc           #135                // float 0.9013f
     765: fastore
     766: dup
     767: sipush        128
     770: ldc           #136                // float 0.9046f
     772: fastore
     773: dup
     774: sipush        129
     777: ldc           #137                // float 0.9078f
     779: fastore
     780: dup
     781: sipush        130
     784: ldc           #138                // float 0.9109f
     786: fastore
     787: dup
     788: sipush        131
     791: ldc           #139                // float 0.9139f
     793: fastore
     794: dup
     795: sipush        132
     798: ldc           #140                // float 0.9169f
     800: fastore
     801: dup
     802: sipush        133
     805: ldc           #141                // float 0.9198f
     807: fastore
     808: dup
     809: sipush        134
     812: ldc           #142                // float 0.9227f
     814: fastore
     815: dup
     816: sipush        135
     819: ldc           #143                // float 0.9254f
     821: fastore
     822: dup
     823: sipush        136
     826: ldc           #144                // float 0.9281f
     828: fastore
     829: dup
     830: sipush        137
     833: ldc           #145                // float 0.9307f
     835: fastore
     836: dup
     837: sipush        138
     840: ldc           #146                // float 0.9333f
     842: fastore
     843: dup
     844: sipush        139
     847: ldc           #147                // float 0.9358f
     849: fastore
     850: dup
     851: sipush        140
     854: ldc           #148                // float 0.9382f
     856: fastore
     857: dup
     858: sipush        141
     861: ldc           #149                // float 0.9406f
     863: fastore
     864: dup
     865: sipush        142
     868: ldc           #150                // float 0.9429f
     870: fastore
     871: dup
     872: sipush        143
     875: ldc           #151                // float 0.9452f
     877: fastore
     878: dup
     879: sipush        144
     882: ldc           #152                // float 0.9474f
     884: fastore
     885: dup
     886: sipush        145
     889: ldc           #153                // float 0.9495f
     891: fastore
     892: dup
     893: sipush        146
     896: ldc           #154                // float 0.9516f
     898: fastore
     899: dup
     900: sipush        147
     903: ldc           #155                // float 0.9536f
     905: fastore
     906: dup
     907: sipush        148
     910: ldc           #156                // float 0.9556f
     912: fastore
     913: dup
     914: sipush        149
     917: ldc           #157                // float 0.9575f
     919: fastore
     920: dup
     921: sipush        150
     924: ldc           #158                // float 0.9594f
     926: fastore
     927: dup
     928: sipush        151
     931: ldc           #159                // float 0.9612f
     933: fastore
     934: dup
     935: sipush        152
     938: ldc           #160                // float 0.9629f
     940: fastore
     941: dup
     942: sipush        153
     945: ldc           #161                // float 0.9646f
     947: fastore
     948: dup
     949: sipush        154
     952: ldc           #162                // float 0.9663f
     954: fastore
     955: dup
     956: sipush        155
     959: ldc           #163                // float 0.9679f
     961: fastore
     962: dup
     963: sipush        156
     966: ldc           #164                // float 0.9695f
     968: fastore
     969: dup
     970: sipush        157
     973: ldc           #165                // float 0.971f
     975: fastore
     976: dup
     977: sipush        158
     980: ldc           #166                // float 0.9725f
     982: fastore
     983: dup
     984: sipush        159
     987: ldc           #167                // float 0.9739f
     989: fastore
     990: dup
     991: sipush        160
     994: ldc           #168                // float 0.9753f
     996: fastore
     997: dup
     998: sipush        161
    1001: ldc           #169                // float 0.9766f
    1003: fastore
    1004: dup
    1005: sipush        162
    1008: ldc           #170                // float 0.9779f
    1010: fastore
    1011: dup
    1012: sipush        163
    1015: ldc           #171                // float 0.9791f
    1017: fastore
    1018: dup
    1019: sipush        164
    1022: ldc           #172                // float 0.9803f
    1024: fastore
    1025: dup
    1026: sipush        165
    1029: ldc           #173                // float 0.9815f
    1031: fastore
    1032: dup
    1033: sipush        166
    1036: ldc           #174                // float 0.9826f
    1038: fastore
    1039: dup
    1040: sipush        167
    1043: ldc           #175                // float 0.9837f
    1045: fastore
    1046: dup
    1047: sipush        168
    1050: ldc           #176                // float 0.9848f
    1052: fastore
    1053: dup
    1054: sipush        169
    1057: ldc           #177                // float 0.9858f
    1059: fastore
    1060: dup
    1061: sipush        170
    1064: ldc           #178                // float 0.9867f
    1066: fastore
    1067: dup
    1068: sipush        171
    1071: ldc           #179                // float 0.9877f
    1073: fastore
    1074: dup
    1075: sipush        172
    1078: ldc           #180                // float 0.9885f
    1080: fastore
    1081: dup
    1082: sipush        173
    1085: ldc           #181                // float 0.9894f
    1087: fastore
    1088: dup
    1089: sipush        174
    1092: ldc           #182                // float 0.9902f
    1094: fastore
    1095: dup
    1096: sipush        175
    1099: ldc           #183                // float 0.991f
    1101: fastore
    1102: dup
    1103: sipush        176
    1106: ldc           #184                // float 0.9917f
    1108: fastore
    1109: dup
    1110: sipush        177
    1113: ldc           #185                // float 0.9924f
    1115: fastore
    1116: dup
    1117: sipush        178
    1120: ldc           #186                // float 0.9931f
    1122: fastore
    1123: dup
    1124: sipush        179
    1127: ldc           #187                // float 0.9937f
    1129: fastore
    1130: dup
    1131: sipush        180
    1134: ldc           #188                // float 0.9944f
    1136: fastore
    1137: dup
    1138: sipush        181
    1141: ldc           #189                // float 0.9949f
    1143: fastore
    1144: dup
    1145: sipush        182
    1148: ldc           #190                // float 0.9955f
    1150: fastore
    1151: dup
    1152: sipush        183
    1155: ldc           #191                // float 0.996f
    1157: fastore
    1158: dup
    1159: sipush        184
    1162: ldc           #192                // float 0.9964f
    1164: fastore
    1165: dup
    1166: sipush        185
    1169: ldc           #193                // float 0.9969f
    1171: fastore
    1172: dup
    1173: sipush        186
    1176: ldc           #194                // float 0.9973f
    1178: fastore
    1179: dup
    1180: sipush        187
    1183: ldc           #195                // float 0.9977f
    1185: fastore
    1186: dup
    1187: sipush        188
    1190: ldc           #196                // float 0.998f
    1192: fastore
    1193: dup
    1194: sipush        189
    1197: ldc           #197                // float 0.9984f
    1199: fastore
    1200: dup
    1201: sipush        190
    1204: ldc           #198                // float 0.9986f
    1206: fastore
    1207: dup
    1208: sipush        191
    1211: ldc           #199                // float 0.9989f
    1213: fastore
    1214: dup
    1215: sipush        192
    1218: ldc           #200                // float 0.9991f
    1220: fastore
    1221: dup
    1222: sipush        193
    1225: ldc           #201                // float 0.9993f
    1227: fastore
    1228: dup
    1229: sipush        194
    1232: ldc           #202                // float 0.9995f
    1234: fastore
    1235: dup
    1236: sipush        195
    1239: ldc           #203                // float 0.9997f
    1241: fastore
    1242: dup
    1243: sipush        196
    1246: ldc           #204                // float 0.9998f
    1248: fastore
    1249: dup
    1250: sipush        197
    1253: ldc           #205                // float 0.9999f
    1255: fastore
    1256: dup
    1257: sipush        198
    1260: ldc           #205                // float 0.9999f
    1262: fastore
    1263: dup
    1264: sipush        199
    1267: fconst_1
    1268: fastore
    1269: dup
    1270: sipush        200
    1273: fconst_1
    1274: fastore
    1275: putstatic     #207                // Field a:[F
    1278: return

  public android.support.v4.view.b.b();
    Code:
       0: aload_0
       1: getstatic     #207                // Field a:[F
       4: invokespecial #212                // Method android/support/v4/view/b/d."<init>":([F)V
       7: return

  public float getInterpolation(float);
    Code:
       0: aload_0
       1: fload_1
       2: invokespecial #216                // Method android/support/v4/view/b/d.getInterpolation:(F)F
       5: freturn
}
