class android.support.v7.e.a.a$a$a implements java.util.concurrent.Executor {
  final android.os.Handler a;

  android.support.v7.e.a.a$a$a(android.support.v7.e.a.a$1);
    Code:
       0: aload_0
       1: invokespecial #32                 // Method "<init>":()V
       4: return

  public void execute(java.lang.Runnable);
    Code:
       0: aload_0
       1: getfield      #29                 // Field a:Landroid/os/Handler;
       4: aload_1
       5: invokevirtual #38                 // Method android/os/Handler.post:(Ljava/lang/Runnable;)Z
       8: pop
       9: return
}
