public final class android.support.v7.e.a.a<T> {
  android.support.v7.e.a.a(java.util.concurrent.Executor, java.util.concurrent.Executor, android.support.v7.g.c$c, android.support.v7.e.a.a$1);
    Code:
       0: aload_0
       1: aload_1
       2: aload_2
       3: aload_3
       4: invokespecial #34                 // Method "<init>":(Ljava/util/concurrent/Executor;Ljava/util/concurrent/Executor;Landroid/support/v7/g/c$c;)V
       7: return

  public java.util.concurrent.Executor a();
    Code:
       0: aload_0
       1: getfield      #24                 // Field a:Ljava/util/concurrent/Executor;
       4: areturn

  public java.util.concurrent.Executor b();
    Code:
       0: aload_0
       1: getfield      #26                 // Field b:Ljava/util/concurrent/Executor;
       4: areturn

  public android.support.v7.g.c$c<T> c();
    Code:
       0: aload_0
       1: getfield      #28                 // Field c:Landroid/support/v7/g/c$c;
       4: areturn
}
