class android.support.v7.e.a.b$1$1 extends android.support.v7.g.c$a {
  final android.support.v7.e.a.b$1 a;

  android.support.v7.e.a.b$1$1(android.support.v7.e.a.b$1);
    Code:
       0: aload_0
       1: aload_1
       2: putfield      #15                 // Field a:Landroid/support/v7/e/a/b$1;
       5: aload_0
       6: invokespecial #17                 // Method android/support/v7/g/c$a."<init>":()V
       9: return

  public int a();
    Code:
       0: aload_0
       1: getfield      #15                 // Field a:Landroid/support/v7/e/a/b$1;
       4: getfield      #22                 // Field android/support/v7/e/a/b$1.a:Ljava/util/List;
       7: invokeinterface #27,  1           // InterfaceMethod java/util/List.size:()I
      12: ireturn

  public boolean a(int, int);
    Code:
       0: aload_0
       1: getfield      #15                 // Field a:Landroid/support/v7/e/a/b$1;
       4: getfield      #32                 // Field android/support/v7/e/a/b$1.d:Landroid/support/v7/e/a/b;
       7: invokestatic  #37                 // Method android/support/v7/e/a/b.a:(Landroid/support/v7/e/a/b;)Landroid/support/v7/e/a/a;
      10: invokevirtual #43                 // Method android/support/v7/e/a/a.c:()Landroid/support/v7/g/c$c;
      13: aload_0
      14: getfield      #15                 // Field a:Landroid/support/v7/e/a/b$1;
      17: getfield      #22                 // Field android/support/v7/e/a/b$1.a:Ljava/util/List;
      20: iload_1
      21: invokeinterface #47,  2           // InterfaceMethod java/util/List.get:(I)Ljava/lang/Object;
      26: aload_0
      27: getfield      #15                 // Field a:Landroid/support/v7/e/a/b$1;
      30: getfield      #50                 // Field android/support/v7/e/a/b$1.b:Ljava/util/List;
      33: iload_2
      34: invokeinterface #47,  2           // InterfaceMethod java/util/List.get:(I)Ljava/lang/Object;
      39: invokevirtual #55                 // Method android/support/v7/g/c$c.a:(Ljava/lang/Object;Ljava/lang/Object;)Z
      42: ireturn

  public int b();
    Code:
       0: aload_0
       1: getfield      #15                 // Field a:Landroid/support/v7/e/a/b$1;
       4: getfield      #50                 // Field android/support/v7/e/a/b$1.b:Ljava/util/List;
       7: invokeinterface #27,  1           // InterfaceMethod java/util/List.size:()I
      12: ireturn

  public boolean b(int, int);
    Code:
       0: aload_0
       1: getfield      #15                 // Field a:Landroid/support/v7/e/a/b$1;
       4: getfield      #32                 // Field android/support/v7/e/a/b$1.d:Landroid/support/v7/e/a/b;
       7: invokestatic  #37                 // Method android/support/v7/e/a/b.a:(Landroid/support/v7/e/a/b;)Landroid/support/v7/e/a/a;
      10: invokevirtual #43                 // Method android/support/v7/e/a/a.c:()Landroid/support/v7/g/c$c;
      13: aload_0
      14: getfield      #15                 // Field a:Landroid/support/v7/e/a/b$1;
      17: getfield      #22                 // Field android/support/v7/e/a/b$1.a:Ljava/util/List;
      20: iload_1
      21: invokeinterface #47,  2           // InterfaceMethod java/util/List.get:(I)Ljava/lang/Object;
      26: aload_0
      27: getfield      #15                 // Field a:Landroid/support/v7/e/a/b$1;
      30: getfield      #50                 // Field android/support/v7/e/a/b$1.b:Ljava/util/List;
      33: iload_2
      34: invokeinterface #47,  2           // InterfaceMethod java/util/List.get:(I)Ljava/lang/Object;
      39: invokevirtual #57                 // Method android/support/v7/g/c$c.b:(Ljava/lang/Object;Ljava/lang/Object;)Z
      42: ireturn

  public java.lang.Object c(int, int);
    Code:
       0: aload_0
       1: getfield      #15                 // Field a:Landroid/support/v7/e/a/b$1;
       4: getfield      #32                 // Field android/support/v7/e/a/b$1.d:Landroid/support/v7/e/a/b;
       7: invokestatic  #37                 // Method android/support/v7/e/a/b.a:(Landroid/support/v7/e/a/b;)Landroid/support/v7/e/a/a;
      10: invokevirtual #43                 // Method android/support/v7/e/a/a.c:()Landroid/support/v7/g/c$c;
      13: aload_0
      14: getfield      #15                 // Field a:Landroid/support/v7/e/a/b$1;
      17: getfield      #22                 // Field android/support/v7/e/a/b$1.a:Ljava/util/List;
      20: iload_1
      21: invokeinterface #47,  2           // InterfaceMethod java/util/List.get:(I)Ljava/lang/Object;
      26: aload_0
      27: getfield      #15                 // Field a:Landroid/support/v7/e/a/b$1;
      30: getfield      #50                 // Field android/support/v7/e/a/b$1.b:Ljava/util/List;
      33: iload_2
      34: invokeinterface #47,  2           // InterfaceMethod java/util/List.get:(I)Ljava/lang/Object;
      39: invokevirtual #61                 // Method android/support/v7/g/c$c.c:(Ljava/lang/Object;Ljava/lang/Object;)Ljava/lang/Object;
      42: areturn
}
