class android.support.v7.e.a.b$1 implements java.lang.Runnable {
  final java.util.List a;

  final java.util.List b;

  final int c;

  final android.support.v7.e.a.b d;

  android.support.v7.e.a.b$1(android.support.v7.e.a.b, java.util.List, java.util.List, int);
    Code:
       0: aload_0
       1: aload_1
       2: putfield      #25                 // Field d:Landroid/support/v7/e/a/b;
       5: aload_0
       6: aload_2
       7: putfield      #27                 // Field a:Ljava/util/List;
      10: aload_0
      11: aload_3
      12: putfield      #29                 // Field b:Ljava/util/List;
      15: aload_0
      16: iload         4
      18: putfield      #31                 // Field c:I
      21: aload_0
      22: invokespecial #34                 // Method java/lang/Object."<init>":()V
      25: return

  public void run();
    Code:
       0: new           #13                 // class android/support/v7/e/a/b$1$1
       3: dup
       4: aload_0
       5: invokespecial #39                 // Method android/support/v7/e/a/b$1$1."<init>":(Landroid/support/v7/e/a/b$1;)V
       8: invokestatic  #44                 // Method android/support/v7/g/c.a:(Landroid/support/v7/g/c$a;)Landroid/support/v7/g/c$b;
      11: astore_1
      12: aload_0
      13: getfield      #25                 // Field d:Landroid/support/v7/e/a/b;
      16: invokestatic  #47                 // Method android/support/v7/e/a/b.a:(Landroid/support/v7/e/a/b;)Landroid/support/v7/e/a/a;
      19: invokevirtual #52                 // Method android/support/v7/e/a/a.a:()Ljava/util/concurrent/Executor;
      22: new           #15                 // class android/support/v7/e/a/b$1$2
      25: dup
      26: aload_0
      27: aload_1
      28: invokespecial #55                 // Method android/support/v7/e/a/b$1$2."<init>":(Landroid/support/v7/e/a/b$1;Landroid/support/v7/g/c$b;)V
      31: invokeinterface #61,  2           // InterfaceMethod java/util/concurrent/Executor.execute:(Ljava/lang/Runnable;)V
      36: return
}
