class android.support.v4.b.g$2 implements android.support.v4.b.g$a<android.support.v4.a.a.a$c> {
  final android.support.v4.b.g a;

  android.support.v4.b.g$2(android.support.v4.b.g);
    Code:
       0: aload_0
       1: aload_1
       2: putfield      #17                 // Field a:Landroid/support/v4/b/g;
       5: aload_0
       6: invokespecial #20                 // Method java/lang/Object."<init>":()V
       9: return

  public int a(android.support.v4.a.a.a$c);
    Code:
       0: aload_1
       1: invokevirtual #28                 // Method android/support/v4/a/a/a$c.b:()I
       4: ireturn

  public boolean a(java.lang.Object);
    Code:
       0: aload_0
       1: aload_1
       2: checkcast     #24                 // class android/support/v4/a/a/a$c
       5: invokevirtual #32                 // Method b:(Landroid/support/v4/a/a/a$c;)Z
       8: ireturn

  public int b(java.lang.Object);
    Code:
       0: aload_0
       1: aload_1
       2: checkcast     #24                 // class android/support/v4/a/a/a$c
       5: invokevirtual #35                 // Method a:(Landroid/support/v4/a/a/a$c;)I
       8: ireturn

  public boolean b(android.support.v4.a.a.a$c);
    Code:
       0: aload_1
       1: invokevirtual #39                 // Method android/support/v4/a/a/a$c.c:()Z
       4: ireturn
}
