class android.support.v4.view.b$b {
  android.support.v4.view.b$b();
    Code:
       0: aload_0
       1: invokespecial #13                 // Method java/lang/Object."<init>":()V
       4: return

  public android.support.v4.view.a.c a(android.view.View$AccessibilityDelegate, android.view.View);
    Code:
       0: aconst_null
       1: areturn

  public android.view.View$AccessibilityDelegate a(android.support.v4.view.b);
    Code:
       0: new           #9                  // class android/support/v4/view/b$b$1
       3: dup
       4: aload_0
       5: aload_1
       6: invokespecial #20                 // Method android/support/v4/view/b$b$1."<init>":(Landroid/support/v4/view/b$b;Landroid/support/v4/view/b;)V
       9: areturn

  public boolean a(android.view.View$AccessibilityDelegate, android.view.View, int, android.os.Bundle);
    Code:
       0: iconst_0
       1: ireturn
}
