class android.support.v4.view.h$b implements android.support.v4.view.h$c {
  android.support.v4.view.h$b();
    Code:
       0: aload_0
       1: invokespecial #13                 // Method java/lang/Object."<init>":()V
       4: return

  public void a(android.view.MenuItem, char, int);
    Code:
       0: return

  public void a(android.view.MenuItem, android.content.res.ColorStateList);
    Code:
       0: return

  public void a(android.view.MenuItem, android.graphics.PorterDuff$Mode);
    Code:
       0: return

  public void a(android.view.MenuItem, java.lang.CharSequence);
    Code:
       0: return

  public void b(android.view.MenuItem, char, int);
    Code:
       0: return

  public void b(android.view.MenuItem, java.lang.CharSequence);
    Code:
       0: return
}
