class android.support.v4.view.s$g extends android.support.v4.view.s$f {
  android.support.v4.view.s$g();
    Code:
       0: aload_0
       1: invokespecial #11                 // Method android/support/v4/view/s$f."<init>":()V
       4: return

  public void a(android.view.View, int, int);
    Code:
       0: aload_1
       1: iload_2
       2: iload_3
       3: invokevirtual #20                 // Method android/view/View.setScrollIndicators:(II)V
       6: return

  public void b(android.view.View, int);
    Code:
       0: aload_1
       1: iload_2
       2: invokevirtual #26                 // Method android/view/View.offsetLeftAndRight:(I)V
       5: return

  public void c(android.view.View, int);
    Code:
       0: aload_1
       1: iload_2
       2: invokevirtual #30                 // Method android/view/View.offsetTopAndBottom:(I)V
       5: return
}
