public class android.support.v4.view.s {
  static final android.support.v4.view.s$j a;

  static {};
    Code:
       0: getstatic     #45                 // Field android/os/Build$VERSION.SDK_INT:I
       3: bipush        26
       5: if_icmplt     21
       8: new           #32                 // class android/support/v4/view/s$i
      11: dup
      12: invokespecial #48                 // Method android/support/v4/view/s$i."<init>":()V
      15: astore_0
      16: aload_0
      17: putstatic     #50                 // Field a:Landroid/support/v4/view/s$j;
      20: return
      21: getstatic     #45                 // Field android/os/Build$VERSION.SDK_INT:I
      24: bipush        24
      26: if_icmplt     40
      29: new           #29                 // class android/support/v4/view/s$h
      32: dup
      33: invokespecial #51                 // Method android/support/v4/view/s$h."<init>":()V
      36: astore_0
      37: goto          16
      40: getstatic     #45                 // Field android/os/Build$VERSION.SDK_INT:I
      43: bipush        23
      45: if_icmplt     59
      48: new           #26                 // class android/support/v4/view/s$g
      51: dup
      52: invokespecial #52                 // Method android/support/v4/view/s$g."<init>":()V
      55: astore_0
      56: goto          16
      59: getstatic     #45                 // Field android/os/Build$VERSION.SDK_INT:I
      62: bipush        21
      64: if_icmplt     78
      67: new           #21                 // class android/support/v4/view/s$f
      70: dup
      71: invokespecial #53                 // Method android/support/v4/view/s$f."<init>":()V
      74: astore_0
      75: goto          16
      78: getstatic     #45                 // Field android/os/Build$VERSION.SDK_INT:I
      81: bipush        19
      83: if_icmplt     97
      86: new           #18                 // class android/support/v4/view/s$e
      89: dup
      90: invokespecial #54                 // Method android/support/v4/view/s$e."<init>":()V
      93: astore_0
      94: goto          16
      97: getstatic     #45                 // Field android/os/Build$VERSION.SDK_INT:I
     100: bipush        18
     102: if_icmplt     116
     105: new           #15                 // class android/support/v4/view/s$d
     108: dup
     109: invokespecial #55                 // Method android/support/v4/view/s$d."<init>":()V
     112: astore_0
     113: goto          16
     116: getstatic     #45                 // Field android/os/Build$VERSION.SDK_INT:I
     119: bipush        17
     121: if_icmplt     135
     124: new           #12                 // class android/support/v4/view/s$c
     127: dup
     128: invokespecial #56                 // Method android/support/v4/view/s$c."<init>":()V
     131: astore_0
     132: goto          16
     135: getstatic     #45                 // Field android/os/Build$VERSION.SDK_INT:I
     138: bipush        16
     140: if_icmplt     154
     143: new           #9                  // class android/support/v4/view/s$b
     146: dup
     147: invokespecial #57                 // Method android/support/v4/view/s$b."<init>":()V
     150: astore_0
     151: goto          16
     154: getstatic     #45                 // Field android/os/Build$VERSION.SDK_INT:I
     157: bipush        15
     159: if_icmplt     173
     162: new           #6                  // class android/support/v4/view/s$a
     165: dup
     166: invokespecial #58                 // Method android/support/v4/view/s$a."<init>":()V
     169: astore_0
     170: goto          16
     173: new           #35                 // class android/support/v4/view/s$j
     176: dup
     177: invokespecial #59                 // Method android/support/v4/view/s$j."<init>":()V
     180: astore_0
     181: goto          16

  public static boolean A(android.view.View);
    Code:
       0: getstatic     #50                 // Field a:Landroid/support/v4/view/s$j;
       3: aload_0
       4: invokevirtual #64                 // Method android/support/v4/view/s$j.a:(Landroid/view/View;)Z
       7: ireturn

  public static android.view.Display B(android.view.View);
    Code:
       0: getstatic     #50                 // Field a:Landroid/support/v4/view/s$j;
       3: aload_0
       4: invokevirtual #69                 // Method android/support/v4/view/s$j.p:(Landroid/view/View;)Landroid/view/Display;
       7: areturn

  public static android.support.v4.view.ab a(android.view.View, android.support.v4.view.ab);
    Code:
       0: getstatic     #50                 // Field a:Landroid/support/v4/view/s$j;
       3: aload_0
       4: aload_1
       5: invokevirtual #72                 // Method android/support/v4/view/s$j.a:(Landroid/view/View;Landroid/support/v4/view/ab;)Landroid/support/v4/view/ab;
       8: areturn

  public static void a(android.view.View, float);
    Code:
       0: getstatic     #50                 // Field a:Landroid/support/v4/view/s$j;
       3: aload_0
       4: fload_1
       5: invokevirtual #75                 // Method android/support/v4/view/s$j.a:(Landroid/view/View;F)V
       8: return

  public static void a(android.view.View, int);
    Code:
       0: getstatic     #50                 // Field a:Landroid/support/v4/view/s$j;
       3: aload_0
       4: iload_1
       5: invokevirtual #78                 // Method android/support/v4/view/s$j.a:(Landroid/view/View;I)V
       8: return

  public static void a(android.view.View, int, int);
    Code:
       0: getstatic     #50                 // Field a:Landroid/support/v4/view/s$j;
       3: aload_0
       4: iload_1
       5: iload_2
       6: invokevirtual #81                 // Method android/support/v4/view/s$j.a:(Landroid/view/View;II)V
       9: return

  public static void a(android.view.View, int, int, int, int);
    Code:
       0: getstatic     #50                 // Field a:Landroid/support/v4/view/s$j;
       3: aload_0
       4: iload_1
       5: iload_2
       6: iload_3
       7: iload         4
       9: invokevirtual #84                 // Method android/support/v4/view/s$j.a:(Landroid/view/View;IIII)V
      12: return

  public static void a(android.view.View, android.content.res.ColorStateList);
    Code:
       0: getstatic     #50                 // Field a:Landroid/support/v4/view/s$j;
       3: aload_0
       4: aload_1
       5: invokevirtual #87                 // Method android/support/v4/view/s$j.a:(Landroid/view/View;Landroid/content/res/ColorStateList;)V
       8: return

  public static void a(android.view.View, android.graphics.PorterDuff$Mode);
    Code:
       0: getstatic     #50                 // Field a:Landroid/support/v4/view/s$j;
       3: aload_0
       4: aload_1
       5: invokevirtual #90                 // Method android/support/v4/view/s$j.a:(Landroid/view/View;Landroid/graphics/PorterDuff$Mode;)V
       8: return

  public static void a(android.view.View, android.graphics.Rect);
    Code:
       0: getstatic     #50                 // Field a:Landroid/support/v4/view/s$j;
       3: aload_0
       4: aload_1
       5: invokevirtual #93                 // Method android/support/v4/view/s$j.a:(Landroid/view/View;Landroid/graphics/Rect;)V
       8: return

  public static void a(android.view.View, android.graphics.drawable.Drawable);
    Code:
       0: getstatic     #50                 // Field a:Landroid/support/v4/view/s$j;
       3: aload_0
       4: aload_1
       5: invokevirtual #96                 // Method android/support/v4/view/s$j.a:(Landroid/view/View;Landroid/graphics/drawable/Drawable;)V
       8: return

  public static void a(android.view.View, android.support.v4.view.b);
    Code:
       0: getstatic     #50                 // Field a:Landroid/support/v4/view/s$j;
       3: aload_0
       4: aload_1
       5: invokevirtual #99                 // Method android/support/v4/view/s$j.a:(Landroid/view/View;Landroid/support/v4/view/b;)V
       8: return

  public static void a(android.view.View, android.support.v4.view.p);
    Code:
       0: getstatic     #50                 // Field a:Landroid/support/v4/view/s$j;
       3: aload_0
       4: aload_1
       5: invokevirtual #102                // Method android/support/v4/view/s$j.a:(Landroid/view/View;Landroid/support/v4/view/p;)V
       8: return

  public static void a(android.view.View, java.lang.Runnable);
    Code:
       0: getstatic     #50                 // Field a:Landroid/support/v4/view/s$j;
       3: aload_0
       4: aload_1
       5: invokevirtual #105                // Method android/support/v4/view/s$j.a:(Landroid/view/View;Ljava/lang/Runnable;)V
       8: return

  public static void a(android.view.View, java.lang.Runnable, long);
    Code:
       0: getstatic     #50                 // Field a:Landroid/support/v4/view/s$j;
       3: aload_0
       4: aload_1
       5: lload_2
       6: invokevirtual #108                // Method android/support/v4/view/s$j.a:(Landroid/view/View;Ljava/lang/Runnable;J)V
       9: return

  public static void a(android.view.View, java.lang.String);
    Code:
       0: getstatic     #50                 // Field a:Landroid/support/v4/view/s$j;
       3: aload_0
       4: aload_1
       5: invokevirtual #111                // Method android/support/v4/view/s$j.a:(Landroid/view/View;Ljava/lang/String;)V
       8: return

  public static void a(android.view.View, boolean);
    Code:
       0: getstatic     #50                 // Field a:Landroid/support/v4/view/s$j;
       3: aload_0
       4: iload_1
       5: invokevirtual #114                // Method android/support/v4/view/s$j.a:(Landroid/view/View;Z)V
       8: return

  public static boolean a(android.view.View);
    Code:
       0: getstatic     #50                 // Field a:Landroid/support/v4/view/s$j;
       3: aload_0
       4: invokevirtual #116                // Method android/support/v4/view/s$j.B:(Landroid/view/View;)Z
       7: ireturn

  public static android.support.v4.view.ab b(android.view.View, android.support.v4.view.ab);
    Code:
       0: getstatic     #50                 // Field a:Landroid/support/v4/view/s$j;
       3: aload_0
       4: aload_1
       5: invokevirtual #118                // Method android/support/v4/view/s$j.b:(Landroid/view/View;Landroid/support/v4/view/ab;)Landroid/support/v4/view/ab;
       8: areturn

  public static void b(android.view.View, int);
    Code:
       0: getstatic     #50                 // Field a:Landroid/support/v4/view/s$j;
       3: aload_0
       4: iload_1
       5: invokevirtual #120                // Method android/support/v4/view/s$j.c:(Landroid/view/View;I)V
       8: return

  public static void b(android.view.View, boolean);
    Code:
       0: aload_0
       1: iload_1
       2: invokevirtual #127                // Method android/view/View.setFitsSystemWindows:(Z)V
       5: return

  public static boolean b(android.view.View);
    Code:
       0: getstatic     #50                 // Field a:Landroid/support/v4/view/s$j;
       3: aload_0
       4: invokevirtual #130                // Method android/support/v4/view/s$j.b:(Landroid/view/View;)Z
       7: ireturn

  public static void c(android.view.View);
    Code:
       0: getstatic     #50                 // Field a:Landroid/support/v4/view/s$j;
       3: aload_0
       4: invokevirtual #133                // Method android/support/v4/view/s$j.c:(Landroid/view/View;)V
       7: return

  public static void c(android.view.View, int);
    Code:
       0: getstatic     #50                 // Field a:Landroid/support/v4/view/s$j;
       3: aload_0
       4: iload_1
       5: invokevirtual #135                // Method android/support/v4/view/s$j.b:(Landroid/view/View;I)V
       8: return

  public static int d(android.view.View);
    Code:
       0: getstatic     #50                 // Field a:Landroid/support/v4/view/s$j;
       3: aload_0
       4: invokevirtual #138                // Method android/support/v4/view/s$j.d:(Landroid/view/View;)I
       7: ireturn

  public static int e(android.view.View);
    Code:
       0: getstatic     #50                 // Field a:Landroid/support/v4/view/s$j;
       3: aload_0
       4: invokevirtual #141                // Method android/support/v4/view/s$j.k:(Landroid/view/View;)I
       7: ireturn

  public static android.view.ViewParent f(android.view.View);
    Code:
       0: getstatic     #50                 // Field a:Landroid/support/v4/view/s$j;
       3: aload_0
       4: invokevirtual #144                // Method android/support/v4/view/s$j.e:(Landroid/view/View;)Landroid/view/ViewParent;
       7: areturn

  public static int g(android.view.View);
    Code:
       0: getstatic     #50                 // Field a:Landroid/support/v4/view/s$j;
       3: aload_0
       4: invokevirtual #147                // Method android/support/v4/view/s$j.l:(Landroid/view/View;)I
       7: ireturn

  public static int h(android.view.View);
    Code:
       0: getstatic     #50                 // Field a:Landroid/support/v4/view/s$j;
       3: aload_0
       4: invokevirtual #150                // Method android/support/v4/view/s$j.m:(Landroid/view/View;)I
       7: ireturn

  public static int i(android.view.View);
    Code:
       0: getstatic     #50                 // Field a:Landroid/support/v4/view/s$j;
       3: aload_0
       4: invokevirtual #152                // Method android/support/v4/view/s$j.f:(Landroid/view/View;)I
       7: ireturn

  public static int j(android.view.View);
    Code:
       0: getstatic     #50                 // Field a:Landroid/support/v4/view/s$j;
       3: aload_0
       4: invokevirtual #154                // Method android/support/v4/view/s$j.g:(Landroid/view/View;)I
       7: ireturn

  public static android.support.v4.view.x k(android.view.View);
    Code:
       0: getstatic     #50                 // Field a:Landroid/support/v4/view/s$j;
       3: aload_0
       4: invokevirtual #158                // Method android/support/v4/view/s$j.C:(Landroid/view/View;)Landroid/support/v4/view/x;
       7: areturn

  public static float l(android.view.View);
    Code:
       0: getstatic     #50                 // Field a:Landroid/support/v4/view/s$j;
       3: aload_0
       4: invokevirtual #162                // Method android/support/v4/view/s$j.u:(Landroid/view/View;)F
       7: freturn

  public static java.lang.String m(android.view.View);
    Code:
       0: getstatic     #50                 // Field a:Landroid/support/v4/view/s$j;
       3: aload_0
       4: invokevirtual #166                // Method android/support/v4/view/s$j.t:(Landroid/view/View;)Ljava/lang/String;
       7: areturn

  public static int n(android.view.View);
    Code:
       0: getstatic     #50                 // Field a:Landroid/support/v4/view/s$j;
       3: aload_0
       4: invokevirtual #169                // Method android/support/v4/view/s$j.n:(Landroid/view/View;)I
       7: ireturn

  public static void o(android.view.View);
    Code:
       0: getstatic     #50                 // Field a:Landroid/support/v4/view/s$j;
       3: aload_0
       4: invokevirtual #172                // Method android/support/v4/view/s$j.h:(Landroid/view/View;)V
       7: return

  public static boolean p(android.view.View);
    Code:
       0: getstatic     #50                 // Field a:Landroid/support/v4/view/s$j;
       3: aload_0
       4: invokevirtual #174                // Method android/support/v4/view/s$j.i:(Landroid/view/View;)Z
       7: ireturn

  public static boolean q(android.view.View);
    Code:
       0: getstatic     #50                 // Field a:Landroid/support/v4/view/s$j;
       3: aload_0
       4: invokevirtual #177                // Method android/support/v4/view/s$j.j:(Landroid/view/View;)Z
       7: ireturn

  public static boolean r(android.view.View);
    Code:
       0: getstatic     #50                 // Field a:Landroid/support/v4/view/s$j;
       3: aload_0
       4: invokevirtual #180                // Method android/support/v4/view/s$j.o:(Landroid/view/View;)Z
       7: ireturn

  public static android.content.res.ColorStateList s(android.view.View);
    Code:
       0: getstatic     #50                 // Field a:Landroid/support/v4/view/s$j;
       3: aload_0
       4: invokevirtual #185                // Method android/support/v4/view/s$j.y:(Landroid/view/View;)Landroid/content/res/ColorStateList;
       7: areturn

  public static android.graphics.PorterDuff$Mode t(android.view.View);
    Code:
       0: getstatic     #50                 // Field a:Landroid/support/v4/view/s$j;
       3: aload_0
       4: invokevirtual #189                // Method android/support/v4/view/s$j.z:(Landroid/view/View;)Landroid/graphics/PorterDuff$Mode;
       7: areturn

  public static boolean u(android.view.View);
    Code:
       0: getstatic     #50                 // Field a:Landroid/support/v4/view/s$j;
       3: aload_0
       4: invokevirtual #192                // Method android/support/v4/view/s$j.w:(Landroid/view/View;)Z
       7: ireturn

  public static void v(android.view.View);
    Code:
       0: getstatic     #50                 // Field a:Landroid/support/v4/view/s$j;
       3: aload_0
       4: invokevirtual #196                // Method android/support/v4/view/s$j.x:(Landroid/view/View;)V
       7: return

  public static boolean w(android.view.View);
    Code:
       0: getstatic     #50                 // Field a:Landroid/support/v4/view/s$j;
       3: aload_0
       4: invokevirtual #198                // Method android/support/v4/view/s$j.r:(Landroid/view/View;)Z
       7: ireturn

  public static float x(android.view.View);
    Code:
       0: getstatic     #50                 // Field a:Landroid/support/v4/view/s$j;
       3: aload_0
       4: invokevirtual #200                // Method android/support/v4/view/s$j.A:(Landroid/view/View;)F
       7: freturn

  public static android.graphics.Rect y(android.view.View);
    Code:
       0: getstatic     #50                 // Field a:Landroid/support/v4/view/s$j;
       3: aload_0
       4: invokevirtual #203                // Method android/support/v4/view/s$j.q:(Landroid/view/View;)Landroid/graphics/Rect;
       7: areturn

  public static boolean z(android.view.View);
    Code:
       0: getstatic     #50                 // Field a:Landroid/support/v4/view/s$j;
       3: aload_0
       4: invokevirtual #205                // Method android/support/v4/view/s$j.s:(Landroid/view/View;)Z
       7: ireturn
}
