class android.support.v4.view.w$b extends android.support.v4.view.w$a {
  android.support.v4.view.w$b();
    Code:
       0: aload_0
       1: invokespecial #11                 // Method android/support/v4/view/w$a."<init>":()V
       4: return

  public void a(android.view.ViewParent, android.view.View);
    Code:
       0: aload_1
       1: aload_2
       2: invokeinterface #22,  2           // InterfaceMethod android/view/ViewParent.onStopNestedScroll:(Landroid/view/View;)V
       7: return
       8: astore_2
       9: new           #24                 // class java/lang/StringBuilder
      12: dup
      13: invokespecial #25                 // Method java/lang/StringBuilder."<init>":()V
      16: astore_3
      17: aload_3
      18: ldc           #27                 // String ViewParent
      20: invokevirtual #31                 // Method java/lang/StringBuilder.append:(Ljava/lang/String;)Ljava/lang/StringBuilder;
      23: pop
      24: aload_3
      25: aload_1
      26: invokevirtual #34                 // Method java/lang/StringBuilder.append:(Ljava/lang/Object;)Ljava/lang/StringBuilder;
      29: pop
      30: aload_3
      31: ldc           #36                 // String  does not implement interface
      33: invokevirtual #31                 // Method java/lang/StringBuilder.append:(Ljava/lang/String;)Ljava/lang/StringBuilder;
      36: pop
      37: aload_3
      38: ldc           #38                 // String method onStopNestedScroll
      40: invokevirtual #31                 // Method java/lang/StringBuilder.append:(Ljava/lang/String;)Ljava/lang/StringBuilder;
      43: pop
      44: ldc           #40                 // String ViewParentCompat
      46: aload_3
      47: invokevirtual #44                 // Method java/lang/StringBuilder.toString:()Ljava/lang/String;
      50: aload_2
      51: invokestatic  #50                 // Method android/util/Log.e:(Ljava/lang/String;Ljava/lang/String;Ljava/lang/Throwable;)I
      54: pop
      55: return
    Exception table:
       from    to  target type
           0     7     8   Class java/lang/AbstractMethodError

  public void a(android.view.ViewParent, android.view.View, int, int, int, int);
    Code:
       0: aload_1
       1: aload_2
       2: iload_3
       3: iload         4
       5: iload         5
       7: iload         6
       9: invokeinterface #55,  6           // InterfaceMethod android/view/ViewParent.onNestedScroll:(Landroid/view/View;IIII)V
      14: return
      15: astore_2
      16: new           #24                 // class java/lang/StringBuilder
      19: dup
      20: invokespecial #25                 // Method java/lang/StringBuilder."<init>":()V
      23: astore        7
      25: aload         7
      27: ldc           #27                 // String ViewParent
      29: invokevirtual #31                 // Method java/lang/StringBuilder.append:(Ljava/lang/String;)Ljava/lang/StringBuilder;
      32: pop
      33: aload         7
      35: aload_1
      36: invokevirtual #34                 // Method java/lang/StringBuilder.append:(Ljava/lang/Object;)Ljava/lang/StringBuilder;
      39: pop
      40: aload         7
      42: ldc           #36                 // String  does not implement interface
      44: invokevirtual #31                 // Method java/lang/StringBuilder.append:(Ljava/lang/String;)Ljava/lang/StringBuilder;
      47: pop
      48: aload         7
      50: ldc           #57                 // String method onNestedScroll
      52: invokevirtual #31                 // Method java/lang/StringBuilder.append:(Ljava/lang/String;)Ljava/lang/StringBuilder;
      55: pop
      56: ldc           #40                 // String ViewParentCompat
      58: aload         7
      60: invokevirtual #44                 // Method java/lang/StringBuilder.toString:()Ljava/lang/String;
      63: aload_2
      64: invokestatic  #50                 // Method android/util/Log.e:(Ljava/lang/String;Ljava/lang/String;Ljava/lang/Throwable;)I
      67: pop
      68: return
    Exception table:
       from    to  target type
           0    14    15   Class java/lang/AbstractMethodError

  public void a(android.view.ViewParent, android.view.View, int, int, int[]);
    Code:
       0: aload_1
       1: aload_2
       2: iload_3
       3: iload         4
       5: aload         5
       7: invokeinterface #62,  5           // InterfaceMethod android/view/ViewParent.onNestedPreScroll:(Landroid/view/View;II[I)V
      12: return
      13: astore_2
      14: new           #24                 // class java/lang/StringBuilder
      17: dup
      18: invokespecial #25                 // Method java/lang/StringBuilder."<init>":()V
      21: astore        5
      23: aload         5
      25: ldc           #27                 // String ViewParent
      27: invokevirtual #31                 // Method java/lang/StringBuilder.append:(Ljava/lang/String;)Ljava/lang/StringBuilder;
      30: pop
      31: aload         5
      33: aload_1
      34: invokevirtual #34                 // Method java/lang/StringBuilder.append:(Ljava/lang/Object;)Ljava/lang/StringBuilder;
      37: pop
      38: aload         5
      40: ldc           #36                 // String  does not implement interface
      42: invokevirtual #31                 // Method java/lang/StringBuilder.append:(Ljava/lang/String;)Ljava/lang/StringBuilder;
      45: pop
      46: aload         5
      48: ldc           #64                 // String method onNestedPreScroll
      50: invokevirtual #31                 // Method java/lang/StringBuilder.append:(Ljava/lang/String;)Ljava/lang/StringBuilder;
      53: pop
      54: ldc           #40                 // String ViewParentCompat
      56: aload         5
      58: invokevirtual #44                 // Method java/lang/StringBuilder.toString:()Ljava/lang/String;
      61: aload_2
      62: invokestatic  #50                 // Method android/util/Log.e:(Ljava/lang/String;Ljava/lang/String;Ljava/lang/Throwable;)I
      65: pop
      66: return
    Exception table:
       from    to  target type
           0    12    13   Class java/lang/AbstractMethodError

  public boolean a(android.view.ViewParent, android.view.View, float, float);
    Code:
       0: aload_1
       1: aload_2
       2: fload_3
       3: fload         4
       5: invokeinterface #69,  4           // InterfaceMethod android/view/ViewParent.onNestedPreFling:(Landroid/view/View;FF)Z
      10: istore        5
      12: iload         5
      14: ireturn
      15: astore_2
      16: new           #24                 // class java/lang/StringBuilder
      19: dup
      20: invokespecial #25                 // Method java/lang/StringBuilder."<init>":()V
      23: astore        6
      25: aload         6
      27: ldc           #27                 // String ViewParent
      29: invokevirtual #31                 // Method java/lang/StringBuilder.append:(Ljava/lang/String;)Ljava/lang/StringBuilder;
      32: pop
      33: aload         6
      35: aload_1
      36: invokevirtual #34                 // Method java/lang/StringBuilder.append:(Ljava/lang/Object;)Ljava/lang/StringBuilder;
      39: pop
      40: aload         6
      42: ldc           #36                 // String  does not implement interface
      44: invokevirtual #31                 // Method java/lang/StringBuilder.append:(Ljava/lang/String;)Ljava/lang/StringBuilder;
      47: pop
      48: aload         6
      50: ldc           #71                 // String method onNestedPreFling
      52: invokevirtual #31                 // Method java/lang/StringBuilder.append:(Ljava/lang/String;)Ljava/lang/StringBuilder;
      55: pop
      56: ldc           #40                 // String ViewParentCompat
      58: aload         6
      60: invokevirtual #44                 // Method java/lang/StringBuilder.toString:()Ljava/lang/String;
      63: aload_2
      64: invokestatic  #50                 // Method android/util/Log.e:(Ljava/lang/String;Ljava/lang/String;Ljava/lang/Throwable;)I
      67: pop
      68: iconst_0
      69: ireturn
    Exception table:
       from    to  target type
           0    12    15   Class java/lang/AbstractMethodError

  public boolean a(android.view.ViewParent, android.view.View, float, float, boolean);
    Code:
       0: aload_1
       1: aload_2
       2: fload_3
       3: fload         4
       5: iload         5
       7: invokeinterface #76,  5           // InterfaceMethod android/view/ViewParent.onNestedFling:(Landroid/view/View;FFZ)Z
      12: istore        5
      14: iload         5
      16: ireturn
      17: astore_2
      18: new           #24                 // class java/lang/StringBuilder
      21: dup
      22: invokespecial #25                 // Method java/lang/StringBuilder."<init>":()V
      25: astore        6
      27: aload         6
      29: ldc           #27                 // String ViewParent
      31: invokevirtual #31                 // Method java/lang/StringBuilder.append:(Ljava/lang/String;)Ljava/lang/StringBuilder;
      34: pop
      35: aload         6
      37: aload_1
      38: invokevirtual #34                 // Method java/lang/StringBuilder.append:(Ljava/lang/Object;)Ljava/lang/StringBuilder;
      41: pop
      42: aload         6
      44: ldc           #36                 // String  does not implement interface
      46: invokevirtual #31                 // Method java/lang/StringBuilder.append:(Ljava/lang/String;)Ljava/lang/StringBuilder;
      49: pop
      50: aload         6
      52: ldc           #78                 // String method onNestedFling
      54: invokevirtual #31                 // Method java/lang/StringBuilder.append:(Ljava/lang/String;)Ljava/lang/StringBuilder;
      57: pop
      58: ldc           #40                 // String ViewParentCompat
      60: aload         6
      62: invokevirtual #44                 // Method java/lang/StringBuilder.toString:()Ljava/lang/String;
      65: aload_2
      66: invokestatic  #50                 // Method android/util/Log.e:(Ljava/lang/String;Ljava/lang/String;Ljava/lang/Throwable;)I
      69: pop
      70: iconst_0
      71: ireturn
    Exception table:
       from    to  target type
           0    14    17   Class java/lang/AbstractMethodError

  public boolean a(android.view.ViewParent, android.view.View, android.view.View, int);
    Code:
       0: aload_1
       1: aload_2
       2: aload_3
       3: iload         4
       5: invokeinterface #83,  4           // InterfaceMethod android/view/ViewParent.onStartNestedScroll:(Landroid/view/View;Landroid/view/View;I)Z
      10: istore        5
      12: iload         5
      14: ireturn
      15: astore_2
      16: new           #24                 // class java/lang/StringBuilder
      19: dup
      20: invokespecial #25                 // Method java/lang/StringBuilder."<init>":()V
      23: astore_3
      24: aload_3
      25: ldc           #27                 // String ViewParent
      27: invokevirtual #31                 // Method java/lang/StringBuilder.append:(Ljava/lang/String;)Ljava/lang/StringBuilder;
      30: pop
      31: aload_3
      32: aload_1
      33: invokevirtual #34                 // Method java/lang/StringBuilder.append:(Ljava/lang/Object;)Ljava/lang/StringBuilder;
      36: pop
      37: aload_3
      38: ldc           #36                 // String  does not implement interface
      40: invokevirtual #31                 // Method java/lang/StringBuilder.append:(Ljava/lang/String;)Ljava/lang/StringBuilder;
      43: pop
      44: aload_3
      45: ldc           #85                 // String method onStartNestedScroll
      47: invokevirtual #31                 // Method java/lang/StringBuilder.append:(Ljava/lang/String;)Ljava/lang/StringBuilder;
      50: pop
      51: ldc           #40                 // String ViewParentCompat
      53: aload_3
      54: invokevirtual #44                 // Method java/lang/StringBuilder.toString:()Ljava/lang/String;
      57: aload_2
      58: invokestatic  #50                 // Method android/util/Log.e:(Ljava/lang/String;Ljava/lang/String;Ljava/lang/Throwable;)I
      61: pop
      62: iconst_0
      63: ireturn
    Exception table:
       from    to  target type
           0    12    15   Class java/lang/AbstractMethodError

  public void b(android.view.ViewParent, android.view.View, android.view.View, int);
    Code:
       0: aload_1
       1: aload_2
       2: aload_3
       3: iload         4
       5: invokeinterface #90,  4           // InterfaceMethod android/view/ViewParent.onNestedScrollAccepted:(Landroid/view/View;Landroid/view/View;I)V
      10: return
      11: astore_2
      12: new           #24                 // class java/lang/StringBuilder
      15: dup
      16: invokespecial #25                 // Method java/lang/StringBuilder."<init>":()V
      19: astore_3
      20: aload_3
      21: ldc           #27                 // String ViewParent
      23: invokevirtual #31                 // Method java/lang/StringBuilder.append:(Ljava/lang/String;)Ljava/lang/StringBuilder;
      26: pop
      27: aload_3
      28: aload_1
      29: invokevirtual #34                 // Method java/lang/StringBuilder.append:(Ljava/lang/Object;)Ljava/lang/StringBuilder;
      32: pop
      33: aload_3
      34: ldc           #36                 // String  does not implement interface
      36: invokevirtual #31                 // Method java/lang/StringBuilder.append:(Ljava/lang/String;)Ljava/lang/StringBuilder;
      39: pop
      40: aload_3
      41: ldc           #92                 // String method onNestedScrollAccepted
      43: invokevirtual #31                 // Method java/lang/StringBuilder.append:(Ljava/lang/String;)Ljava/lang/StringBuilder;
      46: pop
      47: ldc           #40                 // String ViewParentCompat
      49: aload_3
      50: invokevirtual #44                 // Method java/lang/StringBuilder.toString:()Ljava/lang/String;
      53: aload_2
      54: invokestatic  #50                 // Method android/util/Log.e:(Ljava/lang/String;Ljava/lang/String;Ljava/lang/Throwable;)I
      57: pop
      58: return
    Exception table:
       from    to  target type
           0    10    11   Class java/lang/AbstractMethodError
}
