final class android.support.v4.a.c$a {
  final android.content.Intent a;

  final java.util.ArrayList<android.support.v4.a.c$b> b;

  android.support.v4.a.c$a(android.content.Intent, java.util.ArrayList<android.support.v4.a.c$b>);
    Code:
       0: aload_0
       1: invokespecial #16                 // Method java/lang/Object."<init>":()V
       4: aload_0
       5: aload_1
       6: putfield      #18                 // Field a:Landroid/content/Intent;
       9: aload_0
      10: aload_2
      11: putfield      #20                 // Field b:Ljava/util/ArrayList;
      14: return
}
