class ryey.easer.core.a.a.a.a.d.b implements ryey.easer.core.a.a.a.f<ryey.easer.core.a.j> {
  final android.content.Context a;

  ryey.easer.core.a.a.a.a.d.b(android.content.Context);
    Code:
       0: aload_0
       1: invokespecial #16                 // Method java/lang/Object."<init>":()V
       4: aload_0
       5: aload_1
       6: putfield      #18                 // Field a:Landroid/content/Context;
       9: return

  public java.lang.Object a(java.io.InputStream);
    Code:
       0: aload_0
       1: aload_1
       2: invokevirtual #103                // Method b:(Ljava/io/InputStream;)Lryey/easer/core/a/j;
       5: areturn

  ryey.easer.commons.local_plugin.eventplugin.EventData a(org.json.JSONObject, int);
    Code:
       0: aload_1
       1: ldc           #24                 // String type
       3: invokevirtual #30                 // Method org/json/JSONObject.getString:(Ljava/lang/String;)Ljava/lang/String;
       6: pop
       7: aload_1
       8: ldc           #105                // String situation
      10: invokevirtual #109                // Method org/json/JSONObject.getJSONObject:(Ljava/lang/String;)Lorg/json/JSONObject;
      13: astore_1
      14: aload_1
      15: ldc           #111                // String spec
      17: invokevirtual #30                 // Method org/json/JSONObject.getString:(Ljava/lang/String;)Ljava/lang/String;
      20: astore_3
      21: invokestatic  #116                // Method ryey/easer/plugins/b.a:()Lryey/easer/plugins/b;
      24: invokevirtual #119                // Method ryey/easer/plugins/b.b:()Lryey/easer/plugins/b$c;
      27: aload_3
      28: invokevirtual #124                // Method ryey/easer/plugins/b$c.b:(Ljava/lang/String;)Lryey/easer/commons/local_plugin/d;
      31: checkcast     #126                // class ryey/easer/commons/local_plugin/eventplugin/b
      34: invokeinterface #130,  1          // InterfaceMethod ryey/easer/commons/local_plugin/eventplugin/b.e:()Lryey/easer/commons/local_plugin/eventplugin/a;
      39: aload_1
      40: ldc           #132                // String data
      42: invokevirtual #30                 // Method org/json/JSONObject.getString:(Ljava/lang/String;)Ljava/lang/String;
      45: getstatic     #137                // Field ryey/easer/b/a.a:Lryey/easer/b/a;
      48: iload_2
      49: invokeinterface #142,  4          // InterfaceMethod ryey/easer/commons/local_plugin/eventplugin/a.a:(Ljava/lang/String;Lryey/easer/b/a;I)Lryey/easer/commons/local_plugin/eventplugin/EventData;
      54: astore_1
      55: aload_1
      56: areturn
      57: astore_1
      58: new           #82                 // class ryey/easer/commons/local_plugin/b
      61: dup
      62: aload_1
      63: invokespecial #95                 // Method ryey/easer/commons/local_plugin/b."<init>":(Ljava/lang/Exception;)V
      66: athrow
    Exception table:
       from    to  target type
           0    55    57   Class org/json/JSONException

  public ryey.easer.core.a.j b(java.io.InputStream);
    Code:
       0: new           #26                 // class org/json/JSONObject
       3: dup
       4: aload_1
       5: invokestatic  #147                // Method ryey/easer/core/a/a/a/e.a:(Ljava/io/InputStream;)Ljava/lang/String;
       8: invokespecial #148                // Method org/json/JSONObject."<init>":(Ljava/lang/String;)V
      11: astore_1
      12: aload_1
      13: ldc           #150                // String version
      15: iconst_2
      16: invokevirtual #154                // Method org/json/JSONObject.optInt:(Ljava/lang/String;I)I
      19: istore_2
      20: aload_0
      21: new           #62                 // class ryey/easer/core/a/j
      24: dup
      25: iload_2
      26: invokespecial #157                // Method ryey/easer/core/a/j."<init>":(I)V
      29: putfield      #60                 // Field b:Lryey/easer/core/a/j;
      32: aload_0
      33: getfield      #60                 // Field b:Lryey/easer/core/a/j;
      36: aload_1
      37: ldc           #159                // String name
      39: invokevirtual #30                 // Method org/json/JSONObject.getString:(Ljava/lang/String;)Ljava/lang/String;
      42: invokevirtual #161                // Method ryey/easer/core/a/j.a:(Ljava/lang/String;)V
      45: aload_0
      46: getfield      #60                 // Field b:Lryey/easer/core/a/j;
      49: aload_1
      50: ldc           #163                // String active
      52: iconst_1
      53: invokevirtual #167                // Method org/json/JSONObject.optBoolean:(Ljava/lang/String;Z)Z
      56: invokevirtual #170                // Method ryey/easer/core/a/j.a:(Z)V
      59: aload_0
      60: getfield      #60                 // Field b:Lryey/easer/core/a/j;
      63: aload_1
      64: ldc           #172                // String profile
      66: aconst_null
      67: invokevirtual #176                // Method org/json/JSONObject.optString:(Ljava/lang/String;Ljava/lang/String;)Ljava/lang/String;
      70: invokevirtual #178                // Method ryey/easer/core/a/j.b:(Ljava/lang/String;)V
      73: aload_0
      74: getfield      #60                 // Field b:Lryey/easer/core/a/j;
      77: aload_1
      78: ldc           #180                // String after
      80: aconst_null
      81: invokevirtual #176                // Method org/json/JSONObject.optString:(Ljava/lang/String;Ljava/lang/String;)Ljava/lang/String;
      84: invokevirtual #183                // Method ryey/easer/core/a/j.c:(Ljava/lang/String;)V
      87: iload_2
      88: iconst_4
      89: if_icmpge     115
      92: aload_0
      93: aload_1
      94: ldc           #185                // String trigger
      96: invokevirtual #109                // Method org/json/JSONObject.getJSONObject:(Ljava/lang/String;)Lorg/json/JSONObject;
      99: iload_2
     100: invokevirtual #77                 // Method a:(Lorg/json/JSONObject;I)Lryey/easer/commons/local_plugin/eventplugin/EventData;
     103: astore_3
     104: aload_0
     105: getfield      #60                 // Field b:Lryey/easer/core/a/j;
     108: aload_3
     109: invokevirtual #80                 // Method ryey/easer/core/a/j.a:(Lryey/easer/commons/local_plugin/eventplugin/EventData;)V
     112: goto          204
     115: aload_0
     116: aload_1
     117: ldc           #185                // String trigger
     119: invokevirtual #109                // Method org/json/JSONObject.getJSONObject:(Ljava/lang/String;)Lorg/json/JSONObject;
     122: iload_2
     123: invokespecial #187                // Method b:(Lorg/json/JSONObject;I)V
     126: aload_0
     127: getfield      #60                 // Field b:Lryey/easer/core/a/j;
     130: invokevirtual #190                // Method ryey/easer/core/a/j.c:()Z
     133: ifeq          191
     136: aload_0
     137: getfield      #60                 // Field b:Lryey/easer/core/a/j;
     140: invokevirtual #193                // Method ryey/easer/core/a/j.e:()Lryey/easer/core/a/c;
     143: invokevirtual #195                // Method ryey/easer/core/a/c.e:()Z
     146: ifne          204
     149: aload_0
     150: getfield      #60                 // Field b:Lryey/easer/core/a/j;
     153: aload_1
     154: ldc           #197                // String reverse
     156: invokevirtual #201                // Method org/json/JSONObject.getBoolean:(Ljava/lang/String;)Z
     159: invokevirtual #204                // Method ryey/easer/core/a/j.d:(Z)V
     162: aload_0
     163: getfield      #60                 // Field b:Lryey/easer/core/a/j;
     166: aload_1
     167: ldc           #206                // String repeatable
     169: invokevirtual #201                // Method org/json/JSONObject.getBoolean:(Ljava/lang/String;)Z
     172: invokevirtual #208                // Method ryey/easer/core/a/j.b:(Z)V
     175: aload_0
     176: getfield      #60                 // Field b:Lryey/easer/core/a/j;
     179: aload_1
     180: ldc           #210                // String persistent
     182: invokevirtual #201                // Method org/json/JSONObject.getBoolean:(Ljava/lang/String;)Z
     185: invokevirtual #212                // Method ryey/easer/core/a/j.c:(Z)V
     188: goto          204
     191: aload_0
     192: getfield      #60                 // Field b:Lryey/easer/core/a/j;
     195: aload_1
     196: ldc           #197                // String reverse
     198: invokevirtual #201                // Method org/json/JSONObject.getBoolean:(Ljava/lang/String;)Z
     201: invokevirtual #204                // Method ryey/easer/core/a/j.d:(Z)V
     204: iload_2
     205: bipush        11
     207: if_icmplt     280
     210: aload_1
     211: ldc           #214                // String dynamics
     213: invokevirtual #217                // Method org/json/JSONObject.optJSONObject:(Ljava/lang/String;)Lorg/json/JSONObject;
     216: astore_1
     217: aload_1
     218: ifnull        280
     221: new           #219                // class ryey/easer/commons/local_plugin/b/b
     224: dup
     225: invokespecial #220                // Method ryey/easer/commons/local_plugin/b/b."<init>":()V
     228: astore_3
     229: aload_1
     230: invokevirtual #224                // Method org/json/JSONObject.keys:()Ljava/util/Iterator;
     233: astore        4
     235: aload         4
     237: invokeinterface #229,  1          // InterfaceMethod java/util/Iterator.hasNext:()Z
     242: ifeq          272
     245: aload         4
     247: invokeinterface #233,  1          // InterfaceMethod java/util/Iterator.next:()Ljava/lang/Object;
     252: checkcast     #32                 // class java/lang/String
     255: astore        5
     257: aload_3
     258: aload         5
     260: aload_1
     261: aload         5
     263: invokevirtual #30                 // Method org/json/JSONObject.getString:(Ljava/lang/String;)Ljava/lang/String;
     266: invokevirtual #236                // Method ryey/easer/commons/local_plugin/b/b.a:(Ljava/lang/String;Ljava/lang/String;)V
     269: goto          235
     272: aload_0
     273: getfield      #60                 // Field b:Lryey/easer/core/a/j;
     276: aload_3
     277: invokevirtual #239                // Method ryey/easer/core/a/j.a:(Lryey/easer/commons/local_plugin/b/b;)V
     280: aload_0
     281: getfield      #60                 // Field b:Lryey/easer/core/a/j;
     284: astore_1
     285: aload_1
     286: areturn
     287: astore_1
     288: new           #82                 // class ryey/easer/commons/local_plugin/b
     291: dup
     292: aload_1
     293: invokespecial #95                 // Method ryey/easer/commons/local_plugin/b."<init>":(Ljava/lang/Exception;)V
     296: athrow
    Exception table:
       from    to  target type
           0    87   287   Class org/json/JSONException
          92   112   287   Class org/json/JSONException
         115   188   287   Class org/json/JSONException
         191   204   287   Class org/json/JSONException
         210   217   287   Class org/json/JSONException
         221   235   287   Class org/json/JSONException
         235   269   287   Class org/json/JSONException
         272   280   287   Class org/json/JSONException
         280   285   287   Class org/json/JSONException
}
