class ryey.easer.core.a.a.a.a.d.c implements ryey.easer.core.a.a.a.i<ryey.easer.core.a.j> {
  ryey.easer.core.a.a.a.a.d.c();
    Code:
       0: aload_0
       1: invokespecial #11                 // Method java/lang/Object."<init>":()V
       4: return

  public java.lang.String a(java.lang.Object);
    Code:
       0: aload_0
       1: aload_1
       2: checkcast     #33                 // class ryey/easer/core/a/j
       5: invokevirtual #36                 // Method a:(Lryey/easer/core/a/j;)Ljava/lang/String;
       8: areturn

  public java.lang.String a(ryey.easer.core.a.j);
    Code:
       0: new           #16                 // class org/json/JSONObject
       3: dup
       4: invokespecial #17                 // Method org/json/JSONObject."<init>":()V
       7: astore        4
       9: aload         4
      11: ldc           #40                 // String name
      13: aload_1
      14: invokevirtual #41                 // Method ryey/easer/core/a/j.a:()Ljava/lang/String;
      17: invokevirtual #25                 // Method org/json/JSONObject.put:(Ljava/lang/String;Ljava/lang/Object;)Lorg/json/JSONObject;
      20: pop
      21: aload         4
      23: ldc           #43                 // String version
      25: bipush        11
      27: invokevirtual #46                 // Method org/json/JSONObject.put:(Ljava/lang/String;I)Lorg/json/JSONObject;
      30: pop
      31: aload         4
      33: ldc           #48                 // String active
      35: aload_1
      36: invokevirtual #52                 // Method ryey/easer/core/a/j.h:()Z
      39: invokevirtual #55                 // Method org/json/JSONObject.put:(Ljava/lang/String;Z)Lorg/json/JSONObject;
      42: pop
      43: aload         4
      45: ldc           #57                 // String profile
      47: aload_1
      48: invokevirtual #60                 // Method ryey/easer/core/a/j.i:()Ljava/lang/String;
      51: invokevirtual #25                 // Method org/json/JSONObject.put:(Ljava/lang/String;Ljava/lang/Object;)Lorg/json/JSONObject;
      54: pop
      55: aload         4
      57: ldc           #62                 // String after
      59: aload_1
      60: invokevirtual #65                 // Method ryey/easer/core/a/j.j:()Ljava/lang/String;
      63: invokevirtual #25                 // Method org/json/JSONObject.put:(Ljava/lang/String;Ljava/lang/Object;)Lorg/json/JSONObject;
      66: pop
      67: aload_1
      68: invokevirtual #69                 // Method ryey/easer/core/a/j.e:()Lryey/easer/core/a/c;
      71: ifnull        143
      74: aload         4
      76: ldc           #71                 // String trigger
      78: aload_0
      79: aload_1
      80: invokevirtual #69                 // Method ryey/easer/core/a/j.e:()Lryey/easer/core/a/c;
      83: invokevirtual #74                 // Method a:(Lryey/easer/core/a/c;)Lorg/json/JSONObject;
      86: invokevirtual #25                 // Method org/json/JSONObject.put:(Ljava/lang/String;Ljava/lang/Object;)Lorg/json/JSONObject;
      89: pop
      90: aload_1
      91: invokevirtual #69                 // Method ryey/easer/core/a/j.e:()Lryey/easer/core/a/c;
      94: invokevirtual #78                 // Method ryey/easer/core/a/c.e:()Z
      97: ifne          170
     100: aload         4
     102: ldc           #80                 // String reverse
     104: aload_1
     105: invokevirtual #83                 // Method ryey/easer/core/a/j.m:()Z
     108: invokevirtual #55                 // Method org/json/JSONObject.put:(Ljava/lang/String;Z)Lorg/json/JSONObject;
     111: pop
     112: aload         4
     114: ldc           #85                 // String repeatable
     116: aload_1
     117: invokevirtual #88                 // Method ryey/easer/core/a/j.k:()Z
     120: invokevirtual #55                 // Method org/json/JSONObject.put:(Ljava/lang/String;Z)Lorg/json/JSONObject;
     123: pop
     124: ldc           #90                 // String persistent
     126: astore_3
     127: aload_1
     128: invokevirtual #93                 // Method ryey/easer/core/a/j.l:()Z
     131: istore_2
     132: aload         4
     134: aload_3
     135: iload_2
     136: invokevirtual #55                 // Method org/json/JSONObject.put:(Ljava/lang/String;Z)Lorg/json/JSONObject;
     139: pop
     140: goto          170
     143: aload         4
     145: ldc           #71                 // String trigger
     147: aload_0
     148: aload_1
     149: invokevirtual #97                 // Method ryey/easer/core/a/j.g:()Lryey/easer/core/a/b;
     152: invokespecial #99                 // Method a:(Lryey/easer/core/a/b;)Lorg/json/JSONObject;
     155: invokevirtual #25                 // Method org/json/JSONObject.put:(Ljava/lang/String;Ljava/lang/Object;)Lorg/json/JSONObject;
     158: pop
     159: ldc           #80                 // String reverse
     161: astore_3
     162: aload_1
     163: invokevirtual #83                 // Method ryey/easer/core/a/j.m:()Z
     166: istore_2
     167: goto          132
     170: aload_1
     171: invokevirtual #103                // Method ryey/easer/core/a/j.n:()Lryey/easer/commons/local_plugin/b/b;
     174: astore_3
     175: aload_3
     176: ifnull        257
     179: new           #16                 // class org/json/JSONObject
     182: dup
     183: invokespecial #17                 // Method org/json/JSONObject."<init>":()V
     186: astore_1
     187: aload_3
     188: invokevirtual #108                // Method ryey/easer/commons/local_plugin/b/b.a:()Ljava/util/Map;
     191: astore_3
     192: aload_3
     193: invokeinterface #114,  1          // InterfaceMethod java/util/Map.keySet:()Ljava/util/Set;
     198: invokeinterface #120,  1          // InterfaceMethod java/util/Set.iterator:()Ljava/util/Iterator;
     203: astore        5
     205: aload         5
     207: invokeinterface #125,  1          // InterfaceMethod java/util/Iterator.hasNext:()Z
     212: ifeq          248
     215: aload         5
     217: invokeinterface #129,  1          // InterfaceMethod java/util/Iterator.next:()Ljava/lang/Object;
     222: checkcast     #131                // class java/lang/String
     225: astore        6
     227: aload_1
     228: aload         6
     230: aload_3
     231: aload         6
     233: invokeinterface #135,  2          // InterfaceMethod java/util/Map.get:(Ljava/lang/Object;)Ljava/lang/Object;
     238: checkcast     #131                // class java/lang/String
     241: invokevirtual #25                 // Method org/json/JSONObject.put:(Ljava/lang/String;Ljava/lang/Object;)Lorg/json/JSONObject;
     244: pop
     245: goto          205
     248: aload         4
     250: ldc           #137                // String dynamics
     252: aload_1
     253: invokevirtual #25                 // Method org/json/JSONObject.put:(Ljava/lang/String;Ljava/lang/Object;)Lorg/json/JSONObject;
     256: pop
     257: aload         4
     259: invokevirtual #140                // Method org/json/JSONObject.toString:()Ljava/lang/String;
     262: astore_1
     263: aload_1
     264: areturn
     265: astore_1
     266: new           #142                // class ryey/easer/core/a/a/a/j
     269: dup
     270: aload_1
     271: invokevirtual #145                // Method org/json/JSONException.getMessage:()Ljava/lang/String;
     274: invokespecial #148                // Method ryey/easer/core/a/a/a/j."<init>":(Ljava/lang/String;)V
     277: athrow
    Exception table:
       from    to  target type
           0   124   265   Class org/json/JSONException
         127   132   265   Class org/json/JSONException
         132   140   265   Class org/json/JSONException
         143   159   265   Class org/json/JSONException
         162   167   265   Class org/json/JSONException
         170   175   265   Class org/json/JSONException
         179   205   265   Class org/json/JSONException
         205   245   265   Class org/json/JSONException
         248   257   265   Class org/json/JSONException
         257   263   265   Class org/json/JSONException

  org.json.JSONObject a(ryey.easer.commons.local_plugin.eventplugin.EventData);
    Code:
       0: new           #16                 // class org/json/JSONObject
       3: dup
       4: invokespecial #17                 // Method org/json/JSONObject."<init>":()V
       7: astore_2
       8: aload_2
       9: ldc           #19                 // String type
      11: ldc           #151                // String raw_event
      13: invokevirtual #25                 // Method org/json/JSONObject.put:(Ljava/lang/String;Ljava/lang/Object;)Lorg/json/JSONObject;
      16: pop
      17: aload_2
      18: ldc           #153                // String situation
      20: aload_0
      21: aload_1
      22: invokevirtual #156                // Method b:(Lryey/easer/commons/local_plugin/eventplugin/EventData;)Lorg/json/JSONObject;
      25: invokevirtual #25                 // Method org/json/JSONObject.put:(Ljava/lang/String;Ljava/lang/Object;)Lorg/json/JSONObject;
      28: pop
      29: aload_2
      30: areturn

  org.json.JSONObject a(ryey.easer.core.a.c);
    Code:
       0: aload_1
       1: invokevirtual #78                 // Method ryey/easer/core/a/c.e:()Z
       4: ifeq          16
       7: aload_0
       8: aload_1
       9: invokevirtual #160                // Method ryey/easer/core/a/c.c:()Lryey/easer/commons/local_plugin/eventplugin/EventData;
      12: invokevirtual #162                // Method a:(Lryey/easer/commons/local_plugin/eventplugin/EventData;)Lorg/json/JSONObject;
      15: areturn
      16: new           #16                 // class org/json/JSONObject
      19: dup
      20: invokespecial #17                 // Method org/json/JSONObject."<init>":()V
      23: astore_2
      24: aload_2
      25: ldc           #19                 // String type
      27: ldc           #164                // String pre_defined
      29: invokevirtual #25                 // Method org/json/JSONObject.put:(Ljava/lang/String;Ljava/lang/Object;)Lorg/json/JSONObject;
      32: pop
      33: aload_2
      34: ldc           #166                // String event
      36: aload_1
      37: invokevirtual #167                // Method ryey/easer/core/a/c.a:()Ljava/lang/String;
      40: invokevirtual #25                 // Method org/json/JSONObject.put:(Ljava/lang/String;Ljava/lang/Object;)Lorg/json/JSONObject;
      43: pop
      44: aload_2
      45: areturn

  org.json.JSONObject b(ryey.easer.commons.local_plugin.eventplugin.EventData);
    Code:
       0: new           #16                 // class org/json/JSONObject
       3: dup
       4: invokespecial #17                 // Method org/json/JSONObject."<init>":()V
       7: astore_2
       8: aload_2
       9: ldc           #169                // String spec
      11: invokestatic  #174                // Method ryey/easer/plugins/b.a:()Lryey/easer/plugins/b;
      14: invokevirtual #177                // Method ryey/easer/plugins/b.b:()Lryey/easer/plugins/b$c;
      17: aload_1
      18: invokevirtual #182                // Method ryey/easer/plugins/b$c.a:(Lryey/easer/commons/local_plugin/f;)Lryey/easer/commons/local_plugin/d;
      21: checkcast     #184                // class ryey/easer/commons/local_plugin/eventplugin/b
      24: invokeinterface #185,  1          // InterfaceMethod ryey/easer/commons/local_plugin/eventplugin/b.a:()Ljava/lang/String;
      29: invokevirtual #25                 // Method org/json/JSONObject.put:(Ljava/lang/String;Ljava/lang/Object;)Lorg/json/JSONObject;
      32: pop
      33: aload_2
      34: ldc           #187                // String data
      36: aload_1
      37: getstatic     #192                // Field ryey/easer/b/a.a:Lryey/easer/b/a;
      40: invokeinterface #197,  2          // InterfaceMethod ryey/easer/commons/local_plugin/eventplugin/EventData.a:(Lryey/easer/b/a;)Ljava/lang/String;
      45: invokevirtual #25                 // Method org/json/JSONObject.put:(Ljava/lang/String;Ljava/lang/Object;)Lorg/json/JSONObject;
      48: pop
      49: aload_2
      50: areturn
}
