public final class ryey.easer.core.ui.data.script.script_tree_list.a implements b.a.a.a {
  final java.lang.String a;

  final boolean b;

  final boolean c;

  public ryey.easer.core.ui.data.script.script_tree_list.a(java.lang.String, boolean, boolean);
    Code:
       0: aload_0
       1: invokespecial #16                 // Method java/lang/Object."<init>":()V
       4: aload_0
       5: aload_1
       6: putfield      #18                 // Field a:Ljava/lang/String;
       9: aload_0
      10: iload_2
      11: putfield      #20                 // Field b:Z
      14: aload_0
      15: iload_3
      16: putfield      #22                 // Field c:Z
      19: return

  public int a();
    Code:
       0: ldc           #25                 // int 2131427407
       2: ireturn
}
