class ryey.easer.core.ui.data.script.script_tree_list.b$2 implements ryey.easer.core.ui.data.script.script_tree_list.c$c {
  final ryey.easer.core.ui.data.script.script_tree_list.b a;

  ryey.easer.core.ui.data.script.script_tree_list.b$2(ryey.easer.core.ui.data.script.script_tree_list.b);
    Code:
       0: aload_0
       1: aload_1
       2: putfield      #17                 // Field a:Lryey/easer/core/ui/data/script/script_tree_list/b;
       5: aload_0
       6: invokespecial #20                 // Method java/lang/Object."<init>":()V
       9: return

  public void a(android.view.View, ryey.easer.core.ui.data.script.script_tree_list.a);
    Code:
       0: aload_0
       1: getfield      #17                 // Field a:Lryey/easer/core/ui/data/script/script_tree_list/b;
       4: aload_2
       5: invokestatic  #25                 // Method ryey/easer/core/ui/data/script/script_tree_list/b.a:(Lryey/easer/core/ui/data/script/script_tree_list/b;Lryey/easer/core/ui/data/script/script_tree_list/a;)Lryey/easer/core/ui/data/script/script_tree_list/a;
       8: pop
       9: aload_1
      10: invokevirtual #31                 // Method android/view/View.showContextMenu:()Z
      13: pop
      14: return
}
