class ryey.easer.core.ui.data.script.script_tree_list.c$a extends b.a.a.d<ryey.easer.core.ui.data.script.script_tree_list.c$b> {
  java.lang.ref.WeakReference<ryey.easer.core.ui.data.script.script_tree_list.c> a;

  ryey.easer.core.ui.data.script.script_tree_list.c$a(ryey.easer.core.ui.data.script.script_tree_list.c$1);
    Code:
       0: aload_0
       1: invokespecial #19                 // Method "<init>":()V
       4: return

  public int a();
    Code:
       0: ldc           #21                 // int 2131427407
       2: ireturn

  public ryey.easer.core.ui.data.script.script_tree_list.c$b a(android.view.View);
    Code:
       0: new           #24                 // class ryey/easer/core/ui/data/script/script_tree_list/c$b
       3: dup
       4: aload_1
       5: invokespecial #27                 // Method ryey/easer/core/ui/data/script/script_tree_list/c$b."<init>":(Landroid/view/View;)V
       8: areturn

  public void a(android.support.v7.widget.RecyclerView$x, int, b.a.a.b);
    Code:
       0: aload_0
       1: aload_1
       2: checkcast     #24                 // class ryey/easer/core/ui/data/script/script_tree_list/c$b
       5: iload_2
       6: aload_3
       7: invokevirtual #31                 // Method a:(Lryey/easer/core/ui/data/script/script_tree_list/c$b;ILb/a/a/b;)V
      10: return

  public void a(ryey.easer.core.ui.data.script.script_tree_list.c$b, int, b.a.a.b);
    Code:
       0: aload_3
       1: invokevirtual #37                 // Method b/a/a/b.d:()Lb/a/a/a;
       4: checkcast     #39                 // class ryey/easer/core/ui/data/script/script_tree_list/a
       7: astore        4
       9: aload_1
      10: getfield      #42                 // Field ryey/easer/core/ui/data/script/script_tree_list/c$b.a:Landroid/view/View;
      13: new           #10                 // class ryey/easer/core/ui/data/script/script_tree_list/c$a$1
      16: dup
      17: aload_0
      18: aload         4
      20: invokespecial #45                 // Method ryey/easer/core/ui/data/script/script_tree_list/c$a$1."<init>":(Lryey/easer/core/ui/data/script/script_tree_list/c$a;Lryey/easer/core/ui/data/script/script_tree_list/a;)V
      23: invokevirtual #51                 // Method android/view/View.setOnLongClickListener:(Landroid/view/View$OnLongClickListener;)V
      26: aload_1
      27: getfield      #55                 // Field ryey/easer/core/ui/data/script/script_tree_list/c$b.n:Landroid/widget/TextView;
      30: aload         4
      32: getfield      #58                 // Field ryey/easer/core/ui/data/script/script_tree_list/a.a:Ljava/lang/String;
      35: invokevirtual #64                 // Method android/widget/TextView.setText:(Ljava/lang/CharSequence;)V
      38: aload         4
      40: getfield      #68                 // Field ryey/easer/core/ui/data/script/script_tree_list/a.c:Z
      43: ifne          52
      46: ldc           #69                 // int 2131099699
      48: istore_2
      49: goto          69
      52: aload         4
      54: getfield      #72                 // Field ryey/easer/core/ui/data/script/script_tree_list/a.b:Z
      57: ifne          66
      60: ldc           #73                 // int 2131099700
      62: istore_2
      63: goto          69
      66: ldc           #74                 // int 2131099697
      68: istore_2
      69: aload_1
      70: getfield      #55                 // Field ryey/easer/core/ui/data/script/script_tree_list/c$b.n:Landroid/widget/TextView;
      73: aload_0
      74: getfield      #76                 // Field a:Ljava/lang/ref/WeakReference;
      77: invokevirtual #82                 // Method java/lang/ref/WeakReference.get:()Ljava/lang/Object;
      80: checkcast     #7                  // class ryey/easer/core/ui/data/script/script_tree_list/c
      83: invokestatic  #85                 // Method ryey/easer/core/ui/data/script/script_tree_list/c.a:(Lryey/easer/core/ui/data/script/script_tree_list/c;)Ljava/lang/ref/WeakReference;
      86: invokevirtual #82                 // Method java/lang/ref/WeakReference.get:()Ljava/lang/Object;
      89: checkcast     #87                 // class android/content/Context
      92: iload_2
      93: invokestatic  #92                 // Method android/support/v4/a/a.c:(Landroid/content/Context;I)I
      96: invokevirtual #96                 // Method android/widget/TextView.setTextColor:(I)V
      99: aload_1
     100: getfield      #100                // Field ryey/easer/core/ui/data/script/script_tree_list/c$b.o:Landroid/widget/ImageView;
     103: ldc           #101                // int 2131230829
     105: invokevirtual #106                // Method android/widget/ImageView.setImageResource:(I)V
     108: aload_3
     109: invokevirtual #110                // Method b/a/a/b.g:()Z
     112: ifeq          121
     115: bipush        90
     117: istore_2
     118: goto          123
     121: iconst_0
     122: istore_2
     123: aload_1
     124: getfield      #100                // Field ryey/easer/core/ui/data/script/script_tree_list/c$b.o:Landroid/widget/ImageView;
     127: iload_2
     128: i2f
     129: invokevirtual #114                // Method android/widget/ImageView.setRotation:(F)V
     132: aload_1
     133: getfield      #55                 // Field ryey/easer/core/ui/data/script/script_tree_list/c$b.n:Landroid/widget/TextView;
     136: aload         4
     138: getfield      #58                 // Field ryey/easer/core/ui/data/script/script_tree_list/a.a:Ljava/lang/String;
     141: invokevirtual #64                 // Method android/widget/TextView.setText:(Ljava/lang/CharSequence;)V
     144: aload_3
     145: invokevirtual #116                // Method b/a/a/b.c:()Z
     148: ifeq          160
     151: aload_1
     152: getfield      #100                // Field ryey/easer/core/ui/data/script/script_tree_list/c$b.o:Landroid/widget/ImageView;
     155: iconst_4
     156: invokevirtual #119                // Method android/widget/ImageView.setVisibility:(I)V
     159: return
     160: aload_1
     161: getfield      #100                // Field ryey/easer/core/ui/data/script/script_tree_list/c$b.o:Landroid/widget/ImageView;
     164: iconst_0
     165: invokevirtual #119                // Method android/widget/ImageView.setVisibility:(I)V
     168: return

  public void a(ryey.easer.core.ui.data.script.script_tree_list.c);
    Code:
       0: aload_0
       1: new           #78                 // class java/lang/ref/WeakReference
       4: dup
       5: aload_1
       6: invokespecial #123                // Method java/lang/ref/WeakReference."<init>":(Ljava/lang/Object;)V
       9: putfield      #76                 // Field a:Ljava/lang/ref/WeakReference;
      12: return

  public android.support.v7.widget.RecyclerView$x b(android.view.View);
    Code:
       0: aload_0
       1: aload_1
       2: invokevirtual #126                // Method a:(Landroid/view/View;)Lryey/easer/core/ui/data/script/script_tree_list/c$b;
       5: areturn
}
