final class ryey.easer.core.ui.data.script.script_tree_list.c$b extends b.a.a.d$a {
  final android.widget.TextView n;

  final android.widget.ImageView o;

  ryey.easer.core.ui.data.script.script_tree_list.c$b(android.view.View);
    Code:
       0: aload_0
       1: aload_1
       2: invokespecial #15                 // Method b/a/a/d$a."<init>":(Landroid/view/View;)V
       5: aload_0
       6: aload_1
       7: ldc           #16                 // int 2131296737
       9: invokevirtual #22                 // Method android/view/View.findViewById:(I)Landroid/view/View;
      12: checkcast     #24                 // class android/widget/TextView
      15: putfield      #26                 // Field n:Landroid/widget/TextView;
      18: aload_0
      19: aload_1
      20: ldc           #27                 // int 2131296456
      22: invokevirtual #22                 // Method android/view/View.findViewById:(I)Landroid/view/View;
      25: checkcast     #29                 // class android/widget/ImageView
      28: putfield      #31                 // Field o:Landroid/widget/ImageView;
      31: return
}
