public class ryey.easer.core.ui.data.script.script_tree_list.c extends b.a.a.c {
  ryey.easer.core.ui.data.script.script_tree_list.c$c a;

  ryey.easer.core.ui.data.script.script_tree_list.c(java.util.List<b.a.a.b>, android.content.Context);
    Code:
       0: aload_0
       1: aload_1
       2: new           #8                  // class ryey/easer/core/ui/data/script/script_tree_list/c$a
       5: dup
       6: aconst_null
       7: invokespecial #25                 // Method ryey/easer/core/ui/data/script/script_tree_list/c$a."<init>":(Lryey/easer/core/ui/data/script/script_tree_list/c$1;)V
      10: aload_2
      11: invokespecial #28                 // Method "<init>":(Ljava/util/List;Lryey/easer/core/ui/data/script/script_tree_list/c$a;Landroid/content/Context;)V
      14: return

  static java.lang.ref.WeakReference a(ryey.easer.core.ui.data.script.script_tree_list.c);
    Code:
       0: aload_0
       1: getfield      #50                 // Field b:Ljava/lang/ref/WeakReference;
       4: areturn

  public void a(ryey.easer.core.ui.data.script.script_tree_list.c$c);
    Code:
       0: aload_0
       1: aload_1
       2: putfield      #55                 // Field a:Lryey/easer/core/ui/data/script/script_tree_list/c$c;
       5: return
}
