public class ryey.easer.core.ui.data.script.script_tree_list.RecyclerViewWithContext extends android.support.v7.widget.RecyclerView {
  public ryey.easer.core.ui.data.script.script_tree_list.RecyclerViewWithContext(android.content.Context);
    Code:
       0: aload_0
       1: aload_1
       2: invokespecial #10                 // Method android/support/v7/widget/RecyclerView."<init>":(Landroid/content/Context;)V
       5: return

  public ryey.easer.core.ui.data.script.script_tree_list.RecyclerViewWithContext(android.content.Context, android.util.AttributeSet);
    Code:
       0: aload_0
       1: aload_1
       2: aload_2
       3: invokespecial #14                 // Method android/support/v7/widget/RecyclerView."<init>":(Landroid/content/Context;Landroid/util/AttributeSet;)V
       6: return

  public ryey.easer.core.ui.data.script.script_tree_list.RecyclerViewWithContext(android.content.Context, android.util.AttributeSet, int);
    Code:
       0: aload_0
       1: aload_1
       2: aload_2
       3: iload_3
       4: invokespecial #17                 // Method android/support/v7/widget/RecyclerView."<init>":(Landroid/content/Context;Landroid/util/AttributeSet;I)V
       7: return

  public android.view.ContextMenu$ContextMenuInfo getContextMenuInfo();
    Code:
       0: aload_0
       1: invokevirtual #22                 // Method getContextMenuInfo:()Landroid/widget/AdapterView$AdapterContextMenuInfo;
       4: areturn

  public android.widget.AdapterView$AdapterContextMenuInfo getContextMenuInfo();
    Code:
       0: aload_0
       1: getfield      #24                 // Field J:Landroid/widget/AdapterView$AdapterContextMenuInfo;
       4: areturn

  public boolean showContextMenuForChild(android.view.View);
    Code:
       0: aload_0
       1: new           #28                 // class android/widget/AdapterView$AdapterContextMenuInfo
       4: dup
       5: aload_1
       6: aload_0
       7: aload_1
       8: invokevirtual #32                 // Method f:(Landroid/view/View;)I
      11: aload_0
      12: aload_1
      13: invokevirtual #36                 // Method h:(Landroid/view/View;)J
      16: invokespecial #39                 // Method android/widget/AdapterView$AdapterContextMenuInfo."<init>":(Landroid/view/View;IJ)V
      19: putfield      #24                 // Field J:Landroid/widget/AdapterView$AdapterContextMenuInfo;
      22: aload_0
      23: aload_1
      24: invokespecial #41                 // Method android/support/v7/widget/RecyclerView.showContextMenuForChild:(Landroid/view/View;)Z
      27: ireturn
}
