class ryey.easer.core.ui.data.profile.a$1 implements android.widget.CompoundButton$OnCheckedChangeListener {
  final ryey.easer.core.ui.data.profile.a a;

  ryey.easer.core.ui.data.profile.a$1(ryey.easer.core.ui.data.profile.a);
    Code:
       0: aload_0
       1: aload_1
       2: putfield      #17                 // Field a:Lryey/easer/core/ui/data/profile/a;
       5: aload_0
       6: invokespecial #20                 // Method java/lang/Object."<init>":()V
       9: return

  public void onCheckedChanged(android.widget.CompoundButton, boolean);
    Code:
       0: aload_0
       1: getfield      #17                 // Field a:Lryey/easer/core/ui/data/profile/a;
       4: invokestatic  #26                 // Method ryey/easer/core/ui/data/profile/a.a:(Lryey/easer/core/ui/data/profile/a;)Lryey/easer/commons/local_plugin/e;
       7: iload_2
       8: invokevirtual #31                 // Method ryey/easer/commons/local_plugin/e.a:(Z)V
      11: return
}
