class ryey.easer.core.ui.data.profile.d$2 implements ryey.easer.core.f$g {
  final android.widget.TextView a;

  final ryey.easer.core.ui.data.profile.d b;

  ryey.easer.core.ui.data.profile.d$2(ryey.easer.core.ui.data.profile.d, android.widget.TextView);
    Code:
       0: aload_0
       1: aload_1
       2: putfield      #19                 // Field b:Lryey/easer/core/ui/data/profile/d;
       5: aload_0
       6: aload_2
       7: putfield      #21                 // Field a:Landroid/widget/TextView;
      10: aload_0
      11: invokespecial #24                 // Method java/lang/Object."<init>":()V
      14: return

  public void a(ryey.easer.core.g);
    Code:
       0: aload_0
       1: getfield      #21                 // Field a:Landroid/widget/TextView;
       4: aload_1
       5: invokevirtual #32                 // Method ryey/easer/core/g.e:()Ljava/lang/String;
       8: invokevirtual #38                 // Method android/widget/TextView.setText:(Ljava/lang/CharSequence;)V
      11: return
}
