class ryey.easer.core.ui.data.profile.EditProfileActivity$1 implements android.view.View$OnClickListener {
  final ryey.easer.core.ui.data.profile.EditProfileActivity a;

  ryey.easer.core.ui.data.profile.EditProfileActivity$1(ryey.easer.core.ui.data.profile.EditProfileActivity);
    Code:
       0: aload_0
       1: aload_1
       2: putfield      #17                 // Field a:Lryey/easer/core/ui/data/profile/EditProfileActivity;
       5: aload_0
       6: invokespecial #19                 // Method java/lang/Object."<init>":()V
       9: return

  public void onClick(android.view.View);
    Code:
       0: aload_0
       1: getfield      #17                 // Field a:Lryey/easer/core/ui/data/profile/EditProfileActivity;
       4: getfield      #26                 // Field ryey/easer/core/ui/data/profile/EditProfileActivity.g:Lryey/easer/core/ui/data/profile/b;
       7: aload_0
       8: getfield      #17                 // Field a:Lryey/easer/core/ui/data/profile/EditProfileActivity;
      11: invokevirtual #30                 // Method ryey/easer/core/ui/data/profile/EditProfileActivity.getSupportFragmentManager:()Landroid/support/v4/app/n;
      14: ldc           #32                 // String add_op
      16: invokevirtual #37                 // Method ryey/easer/core/ui/data/profile/b.a:(Landroid/support/v4/app/n;Ljava/lang/String;)V
      19: return
}
