public class ryey.easer.plugins.event.c.b extends ryey.easer.plugins.event.a {
  public static final android.os.Parcelable$Creator<ryey.easer.plugins.event.c.b> CREATOR;

  ryey.easer.plugins.event.c.f a;

  static {};
    Code:
       0: new           #6                  // class ryey/easer/plugins/event/c/b$1
       3: dup
       4: invokespecial #29                 // Method ryey/easer/plugins/event/c/b$1."<init>":()V
       7: putstatic     #31                 // Field CREATOR:Landroid/os/Parcelable$Creator;
      10: return

  ryey.easer.plugins.event.c.b(android.os.Parcel, ryey.easer.plugins.event.c.b$1);
    Code:
       0: aload_0
       1: aload_1
       2: invokespecial #53                 // Method "<init>":(Landroid/os/Parcel;)V
       5: return

  ryey.easer.plugins.event.c.b(java.lang.String, ryey.easer.b.a, int);
    Code:
       0: aload_0
       1: invokespecial #34                 // Method ryey/easer/plugins/event/a."<init>":()V
       4: aload_0
       5: aload_1
       6: aload_2
       7: iload_3
       8: invokevirtual #56                 // Method a:(Ljava/lang/String;Lryey/easer/b/a;I)V
      11: return

  ryey.easer.plugins.event.c.b(ryey.easer.plugins.event.c.f);
    Code:
       0: aload_0
       1: invokespecial #34                 // Method ryey/easer/plugins/event/a."<init>":()V
       4: aload_0
       5: aload_1
       6: putfield      #39                 // Field a:Lryey/easer/plugins/event/c/f;
       9: return

  public java.lang.String a(ryey.easer.b.a);
    Code:
       0: getstatic     #63                 // Field ryey/easer/plugins/event/c/b$2.a:[I
       3: aload_1
       4: invokevirtual #69                 // Method ryey/easer/b/a.ordinal:()I
       7: iaload
       8: istore_2
       9: new           #71                 // class org/json/JSONObject
      12: dup
      13: invokespecial #72                 // Method org/json/JSONObject."<init>":()V
      16: astore_1
      17: new           #74                 // class org/json/JSONArray
      20: dup
      21: invokespecial #75                 // Method org/json/JSONArray."<init>":()V
      24: astore_3
      25: aload_0
      26: getfield      #39                 // Field a:Lryey/easer/plugins/event/c/f;
      29: getfield      #42                 // Field ryey/easer/plugins/event/c/f.a:Ljava/util/List;
      32: ifnull        77
      35: aload_0
      36: getfield      #39                 // Field a:Lryey/easer/plugins/event/c/f;
      39: getfield      #42                 // Field ryey/easer/plugins/event/c/f.a:Ljava/util/List;
      42: invokeinterface #81,  1           // InterfaceMethod java/util/List.iterator:()Ljava/util/Iterator;
      47: astore        4
      49: aload         4
      51: invokeinterface #87,  1           // InterfaceMethod java/util/Iterator.hasNext:()Z
      56: ifeq          77
      59: aload_3
      60: aload         4
      62: invokeinterface #91,  1           // InterfaceMethod java/util/Iterator.next:()Ljava/lang/Object;
      67: checkcast     #93                 // class java/lang/String
      70: invokevirtual #97                 // Method org/json/JSONArray.put:(Ljava/lang/Object;)Lorg/json/JSONArray;
      73: pop
      74: goto          49
      77: aload_1
      78: ldc           #99                 // String action
      80: aload_3
      81: invokevirtual #102                // Method org/json/JSONObject.put:(Ljava/lang/String;Ljava/lang/Object;)Lorg/json/JSONObject;
      84: pop
      85: new           #74                 // class org/json/JSONArray
      88: dup
      89: invokespecial #75                 // Method org/json/JSONArray."<init>":()V
      92: astore_3
      93: aload_0
      94: getfield      #39                 // Field a:Lryey/easer/plugins/event/c/f;
      97: getfield      #50                 // Field ryey/easer/plugins/event/c/f.b:Ljava/util/List;
     100: ifnull        145
     103: aload_0
     104: getfield      #39                 // Field a:Lryey/easer/plugins/event/c/f;
     107: getfield      #50                 // Field ryey/easer/plugins/event/c/f.b:Ljava/util/List;
     110: invokeinterface #81,  1           // InterfaceMethod java/util/List.iterator:()Ljava/util/Iterator;
     115: astore        4
     117: aload         4
     119: invokeinterface #87,  1           // InterfaceMethod java/util/Iterator.hasNext:()Z
     124: ifeq          145
     127: aload_3
     128: aload         4
     130: invokeinterface #91,  1           // InterfaceMethod java/util/Iterator.next:()Ljava/lang/Object;
     135: checkcast     #93                 // class java/lang/String
     138: invokevirtual #97                 // Method org/json/JSONArray.put:(Ljava/lang/Object;)Lorg/json/JSONArray;
     141: pop
     142: goto          117
     145: aload_1
     146: ldc           #104                // String category
     148: aload_3
     149: invokevirtual #102                // Method org/json/JSONObject.put:(Ljava/lang/String;Ljava/lang/Object;)Lorg/json/JSONObject;
     152: pop
     153: aload_1
     154: invokevirtual #108                // Method org/json/JSONObject.toString:()Ljava/lang/String;
     157: astore_1
     158: aload_1
     159: areturn
     160: astore_1
     161: aload_1
     162: invokestatic  #113                // Method com/google/a/a/a/a/a/a.a:(Ljava/lang/Throwable;)V
     165: new           #115                // class java/lang/IllegalStateException
     168: dup
     169: aload_1
     170: invokevirtual #118                // Method org/json/JSONException.getMessage:()Ljava/lang/String;
     173: invokespecial #121                // Method java/lang/IllegalStateException."<init>":(Ljava/lang/String;)V
     176: athrow
    Exception table:
       from    to  target type
           9    49   160   Class org/json/JSONException
          49    74   160   Class org/json/JSONException
          77   117   160   Class org/json/JSONException
         117   142   160   Class org/json/JSONException
         145   158   160   Class org/json/JSONException

  public void a(java.lang.String, ryey.easer.b.a, int);
    Code:
       0: aload_0
       1: new           #36                 // class ryey/easer/plugins/event/c/f
       4: dup
       5: invokespecial #37                 // Method ryey/easer/plugins/event/c/f."<init>":()V
       8: putfield      #39                 // Field a:Lryey/easer/plugins/event/c/f;
      11: getstatic     #63                 // Field ryey/easer/plugins/event/c/b$2.a:[I
      14: aload_2
      15: invokevirtual #69                 // Method ryey/easer/b/a.ordinal:()I
      18: iaload
      19: istore_3
      20: new           #71                 // class org/json/JSONObject
      23: dup
      24: aload_1
      25: invokespecial #122                // Method org/json/JSONObject."<init>":(Ljava/lang/String;)V
      28: astore_1
      29: aload_1
      30: ldc           #99                 // String action
      32: invokevirtual #126                // Method org/json/JSONObject.getJSONArray:(Ljava/lang/String;)Lorg/json/JSONArray;
      35: astore_2
      36: iconst_0
      37: istore        4
      39: iconst_0
      40: istore_3
      41: iload_3
      42: aload_2
      43: invokevirtual #129                // Method org/json/JSONArray.length:()I
      46: if_icmpge     74
      49: aload_0
      50: getfield      #39                 // Field a:Lryey/easer/plugins/event/c/f;
      53: getfield      #42                 // Field ryey/easer/plugins/event/c/f.a:Ljava/util/List;
      56: aload_2
      57: iload_3
      58: invokevirtual #133                // Method org/json/JSONArray.getString:(I)Ljava/lang/String;
      61: invokeinterface #137,  2          // InterfaceMethod java/util/List.add:(Ljava/lang/Object;)Z
      66: pop
      67: iload_3
      68: iconst_1
      69: iadd
      70: istore_3
      71: goto          41
      74: aload_1
      75: ldc           #104                // String category
      77: invokevirtual #126                // Method org/json/JSONObject.getJSONArray:(Ljava/lang/String;)Lorg/json/JSONArray;
      80: astore_1
      81: iload         4
      83: istore_3
      84: iload_3
      85: aload_1
      86: invokevirtual #129                // Method org/json/JSONArray.length:()I
      89: if_icmpge     117
      92: aload_0
      93: getfield      #39                 // Field a:Lryey/easer/plugins/event/c/f;
      96: getfield      #50                 // Field ryey/easer/plugins/event/c/f.b:Ljava/util/List;
      99: aload_1
     100: iload_3
     101: invokevirtual #133                // Method org/json/JSONArray.getString:(I)Ljava/lang/String;
     104: invokeinterface #137,  2          // InterfaceMethod java/util/List.add:(Ljava/lang/Object;)Z
     109: pop
     110: iload_3
     111: iconst_1
     112: iadd
     113: istore_3
     114: goto          84
     117: return
     118: astore_1
     119: aload_1
     120: invokestatic  #113                // Method com/google/a/a/a/a/a/a.a:(Ljava/lang/Throwable;)V
     123: new           #139                // class ryey/easer/commons/local_plugin/b
     126: dup
     127: aload_1
     128: invokespecial #142                // Method ryey/easer/commons/local_plugin/b."<init>":(Ljava/lang/Exception;)V
     131: athrow
    Exception table:
       from    to  target type
          20    36   118   Class org/json/JSONException
          41    67   118   Class org/json/JSONException
          74    81   118   Class org/json/JSONException
          84   110   118   Class org/json/JSONException

  public boolean a();
    Code:
       0: aload_0
       1: getfield      #39                 // Field a:Lryey/easer/plugins/event/c/f;
       4: getfield      #42                 // Field ryey/easer/plugins/event/c/f.a:Ljava/util/List;
       7: ifnull        25
      10: aload_0
      11: getfield      #39                 // Field a:Lryey/easer/plugins/event/c/f;
      14: getfield      #42                 // Field ryey/easer/plugins/event/c/f.a:Ljava/util/List;
      17: invokeinterface #145,  1          // InterfaceMethod java/util/List.size:()I
      22: ifne          53
      25: aload_0
      26: getfield      #39                 // Field a:Lryey/easer/plugins/event/c/f;
      29: getfield      #50                 // Field ryey/easer/plugins/event/c/f.b:Ljava/util/List;
      32: ifnull        55
      35: aload_0
      36: getfield      #39                 // Field a:Lryey/easer/plugins/event/c/f;
      39: getfield      #50                 // Field ryey/easer/plugins/event/c/f.b:Ljava/util/List;
      42: invokeinterface #145,  1          // InterfaceMethod java/util/List.size:()I
      47: ifne          53
      50: goto          55
      53: iconst_1
      54: ireturn
      55: iconst_0
      56: ireturn

  public int describeContents();
    Code:
       0: iconst_0
       1: ireturn

  public ryey.easer.commons.local_plugin.b.a[] dynamics();
    Code:
       0: iconst_4
       1: anewarray     #150                // class ryey/easer/commons/local_plugin/b/a
       4: dup
       5: iconst_0
       6: new           #10                 // class ryey/easer/plugins/event/c/b$a
       9: dup
      10: invokespecial #151                // Method ryey/easer/plugins/event/c/b$a."<init>":()V
      13: aastore
      14: dup
      15: iconst_1
      16: new           #13                 // class ryey/easer/plugins/event/c/b$b
      19: dup
      20: invokespecial #152                // Method ryey/easer/plugins/event/c/b$b."<init>":()V
      23: aastore
      24: dup
      25: iconst_2
      26: new           #19                 // class ryey/easer/plugins/event/c/b$d
      29: dup
      30: invokespecial #153                // Method ryey/easer/plugins/event/c/b$d."<init>":()V
      33: aastore
      34: dup
      35: iconst_3
      36: new           #16                 // class ryey/easer/plugins/event/c/b$c
      39: dup
      40: invokespecial #154                // Method ryey/easer/plugins/event/c/b$c."<init>":()V
      43: aastore
      44: areturn

  public boolean equals(java.lang.Object);
    Code:
       0: aload_1
       1: aload_0
       2: if_acmpne     7
       5: iconst_1
       6: ireturn
       7: aload_1
       8: instanceof    #2                  // class ryey/easer/plugins/event/c/b
      11: ifne          16
      14: iconst_0
      15: ireturn
      16: aload_0
      17: getfield      #39                 // Field a:Lryey/easer/plugins/event/c/f;
      20: getfield      #42                 // Field ryey/easer/plugins/event/c/f.a:Ljava/util/List;
      23: astore_2
      24: aload_1
      25: checkcast     #2                  // class ryey/easer/plugins/event/c/b
      28: astore_1
      29: aload_2
      30: aload_1
      31: getfield      #39                 // Field a:Lryey/easer/plugins/event/c/f;
      34: getfield      #42                 // Field ryey/easer/plugins/event/c/f.a:Ljava/util/List;
      37: invokestatic  #160                // Method ryey/easer/b.a:(Ljava/lang/Object;Ljava/lang/Object;)Z
      40: ifne          45
      43: iconst_0
      44: ireturn
      45: aload_0
      46: getfield      #39                 // Field a:Lryey/easer/plugins/event/c/f;
      49: getfield      #50                 // Field ryey/easer/plugins/event/c/f.b:Ljava/util/List;
      52: aload_1
      53: getfield      #39                 // Field a:Lryey/easer/plugins/event/c/f;
      56: getfield      #50                 // Field ryey/easer/plugins/event/c/f.b:Ljava/util/List;
      59: invokestatic  #160                // Method ryey/easer/b.a:(Ljava/lang/Object;Ljava/lang/Object;)Z
      62: ifne          67
      65: iconst_0
      66: ireturn
      67: iconst_1
      68: ireturn

  public void writeToParcel(android.os.Parcel, int);
    Code:
       0: aload_1
       1: aload_0
       2: getfield      #39                 // Field a:Lryey/easer/plugins/event/c/f;
       5: getfield      #42                 // Field ryey/easer/plugins/event/c/f.a:Ljava/util/List;
       8: invokevirtual #165                // Method android/os/Parcel.writeStringList:(Ljava/util/List;)V
      11: aload_1
      12: aload_0
      13: getfield      #39                 // Field a:Lryey/easer/plugins/event/c/f;
      16: getfield      #50                 // Field ryey/easer/plugins/event/c/f.b:Ljava/util/List;
      19: invokevirtual #165                // Method android/os/Parcel.writeStringList:(Ljava/util/List;)V
      22: return
}
