class ryey.easer.plugins.event.c.f {
  java.util.List<java.lang.String> a;

  java.util.List<java.lang.String> b;

  ryey.easer.plugins.event.c.f();
    Code:
       0: aload_0
       1: invokespecial #12                 // Method java/lang/Object."<init>":()V
       4: aload_0
       5: new           #14                 // class java/util/ArrayList
       8: dup
       9: invokespecial #15                 // Method java/util/ArrayList."<init>":()V
      12: putfield      #17                 // Field a:Ljava/util/List;
      15: aload_0
      16: new           #14                 // class java/util/ArrayList
      19: dup
      20: invokespecial #15                 // Method java/util/ArrayList."<init>":()V
      23: putfield      #19                 // Field b:Ljava/util/List;
      26: return
}
