class android.support.transition.ab {
  final android.support.v4.g.a<android.view.View, android.support.transition.aa> a;

  final android.util.SparseArray<android.view.View> b;

  final android.support.v4.g.f<android.view.View> c;

  final android.support.v4.g.a<java.lang.String, android.view.View> d;

  android.support.transition.ab();
    Code:
       0: aload_0
       1: invokespecial #19                 // Method java/lang/Object."<init>":()V
       4: aload_0
       5: new           #21                 // class android/support/v4/g/a
       8: dup
       9: invokespecial #22                 // Method android/support/v4/g/a."<init>":()V
      12: putfield      #24                 // Field a:Landroid/support/v4/g/a;
      15: aload_0
      16: new           #26                 // class android/util/SparseArray
      19: dup
      20: invokespecial #27                 // Method android/util/SparseArray."<init>":()V
      23: putfield      #29                 // Field b:Landroid/util/SparseArray;
      26: aload_0
      27: new           #31                 // class android/support/v4/g/f
      30: dup
      31: invokespecial #32                 // Method android/support/v4/g/f."<init>":()V
      34: putfield      #34                 // Field c:Landroid/support/v4/g/f;
      37: aload_0
      38: new           #21                 // class android/support/v4/g/a
      41: dup
      42: invokespecial #22                 // Method android/support/v4/g/a."<init>":()V
      45: putfield      #36                 // Field d:Landroid/support/v4/g/a;
      48: return
}
