class android.support.transition.ac extends android.support.transition.aj implements android.support.transition.ae {
  android.support.transition.ac(android.content.Context, android.view.ViewGroup, android.view.View);
    Code:
       0: aload_0
       1: aload_1
       2: aload_2
       3: aload_3
       4: invokespecial #10                 // Method android/support/transition/aj."<init>":(Landroid/content/Context;Landroid/view/ViewGroup;Landroid/view/View;)V
       7: return

  static android.support.transition.ac a(android.view.ViewGroup);
    Code:
       0: aload_0
       1: invokestatic  #17                 // Method android/support/transition/aj.d:(Landroid/view/View;)Landroid/support/transition/aj;
       4: checkcast     #2                  // class android/support/transition/ac
       7: areturn

  public void a(android.view.View);
    Code:
       0: aload_0
       1: getfield      #21                 // Field a:Landroid/support/transition/aj$a;
       4: aload_1
       5: invokevirtual #25                 // Method android/support/transition/aj$a.a:(Landroid/view/View;)V
       8: return

  public void b(android.view.View);
    Code:
       0: aload_0
       1: getfield      #21                 // Field a:Landroid/support/transition/aj$a;
       4: aload_1
       5: invokevirtual #28                 // Method android/support/transition/aj$a.b:(Landroid/view/View;)V
       8: return
}
