class android.support.transition.ad implements android.support.transition.ae {
  android.support.transition.ad(android.view.ViewGroup);
    Code:
       0: aload_0
       1: invokespecial #13                 // Method java/lang/Object."<init>":()V
       4: aload_0
       5: aload_1
       6: invokevirtual #19                 // Method android/view/ViewGroup.getOverlay:()Landroid/view/ViewGroupOverlay;
       9: putfield      #21                 // Field a:Landroid/view/ViewGroupOverlay;
      12: return

  public void a(android.graphics.drawable.Drawable);
    Code:
       0: aload_0
       1: getfield      #21                 // Field a:Landroid/view/ViewGroupOverlay;
       4: aload_1
       5: invokevirtual #28                 // Method android/view/ViewGroupOverlay.add:(Landroid/graphics/drawable/Drawable;)V
       8: return

  public void a(android.view.View);
    Code:
       0: aload_0
       1: getfield      #21                 // Field a:Landroid/view/ViewGroupOverlay;
       4: aload_1
       5: invokevirtual #31                 // Method android/view/ViewGroupOverlay.add:(Landroid/view/View;)V
       8: return

  public void b(android.graphics.drawable.Drawable);
    Code:
       0: aload_0
       1: getfield      #21                 // Field a:Landroid/view/ViewGroupOverlay;
       4: aload_1
       5: invokevirtual #35                 // Method android/view/ViewGroupOverlay.remove:(Landroid/graphics/drawable/Drawable;)V
       8: return

  public void b(android.view.View);
    Code:
       0: aload_0
       1: getfield      #21                 // Field a:Landroid/view/ViewGroupOverlay;
       4: aload_1
       5: invokevirtual #37                 // Method android/view/ViewGroupOverlay.remove:(Landroid/view/View;)V
       8: return
}
