class android.support.transition.ag$1 extends android.animation.LayoutTransition {
  final android.support.transition.ag a;

  android.support.transition.ag$1(android.support.transition.ag);
    Code:
       0: aload_0
       1: aload_1
       2: putfield      #14                 // Field a:Landroid/support/transition/ag;
       5: aload_0
       6: invokespecial #17                 // Method android/animation/LayoutTransition."<init>":()V
       9: return

  public boolean isChangingLayout();
    Code:
       0: iconst_1
       1: ireturn
}
