class android.support.transition.aj implements android.support.transition.al {
  protected android.support.transition.aj$a a;

  android.support.transition.aj(android.content.Context, android.view.ViewGroup, android.view.View);
    Code:
       0: aload_0
       1: invokespecial #15                 // Method java/lang/Object."<init>":()V
       4: aload_0
       5: new           #8                  // class android/support/transition/aj$a
       8: dup
       9: aload_1
      10: aload_2
      11: aload_3
      12: aload_0
      13: invokespecial #18                 // Method android/support/transition/aj$a."<init>":(Landroid/content/Context;Landroid/view/ViewGroup;Landroid/view/View;Landroid/support/transition/aj;)V
      16: putfield      #20                 // Field a:Landroid/support/transition/aj$a;
      19: return

  static android.view.ViewGroup c(android.view.View);
    Code:
       0: aload_0
       1: ifnull        46
       4: aload_0
       5: invokevirtual #29                 // Method android/view/View.getId:()I
       8: ldc           #30                 // int 16908290
      10: if_icmpne     25
      13: aload_0
      14: instanceof    #32                 // class android/view/ViewGroup
      17: ifeq          25
      20: aload_0
      21: checkcast     #32                 // class android/view/ViewGroup
      24: areturn
      25: aload_0
      26: invokevirtual #36                 // Method android/view/View.getParent:()Landroid/view/ViewParent;
      29: instanceof    #32                 // class android/view/ViewGroup
      32: ifeq          0
      35: aload_0
      36: invokevirtual #36                 // Method android/view/View.getParent:()Landroid/view/ViewParent;
      39: checkcast     #32                 // class android/view/ViewGroup
      42: astore_0
      43: goto          0
      46: aconst_null
      47: areturn

  static android.support.transition.aj d(android.view.View);
    Code:
       0: aload_0
       1: invokestatic  #40                 // Method c:(Landroid/view/View;)Landroid/view/ViewGroup;
       4: astore_3
       5: aload_3
       6: ifnull        66
       9: aload_3
      10: invokevirtual #43                 // Method android/view/ViewGroup.getChildCount:()I
      13: istore_2
      14: iconst_0
      15: istore_1
      16: iload_1
      17: iload_2
      18: if_icmpge     52
      21: aload_3
      22: iload_1
      23: invokevirtual #47                 // Method android/view/ViewGroup.getChildAt:(I)Landroid/view/View;
      26: astore        4
      28: aload         4
      30: instanceof    #8                  // class android/support/transition/aj$a
      33: ifeq          45
      36: aload         4
      38: checkcast     #8                  // class android/support/transition/aj$a
      41: getfield      #51                 // Field android/support/transition/aj$a.e:Landroid/support/transition/aj;
      44: areturn
      45: iload_1
      46: iconst_1
      47: iadd
      48: istore_1
      49: goto          16
      52: new           #53                 // class android/support/transition/ac
      55: dup
      56: aload_3
      57: invokevirtual #57                 // Method android/view/ViewGroup.getContext:()Landroid/content/Context;
      60: aload_3
      61: aload_0
      62: invokespecial #59                 // Method android/support/transition/ac."<init>":(Landroid/content/Context;Landroid/view/ViewGroup;Landroid/view/View;)V
      65: areturn
      66: aconst_null
      67: areturn

  public void a(android.graphics.drawable.Drawable);
    Code:
       0: aload_0
       1: getfield      #20                 // Field a:Landroid/support/transition/aj$a;
       4: aload_1
       5: invokevirtual #62                 // Method android/support/transition/aj$a.a:(Landroid/graphics/drawable/Drawable;)V
       8: return

  public void b(android.graphics.drawable.Drawable);
    Code:
       0: aload_0
       1: getfield      #20                 // Field a:Landroid/support/transition/aj$a;
       4: aload_1
       5: invokevirtual #65                 // Method android/support/transition/aj$a.b:(Landroid/graphics/drawable/Drawable;)V
       8: return
}
