class android.support.transition.ao extends android.support.transition.an {
  android.support.transition.ao();
    Code:
       0: aload_0
       1: invokespecial #8                  // Method android/support/transition/an."<init>":()V
       4: return

  public android.support.transition.al a(android.view.View);
    Code:
       0: new           #13                 // class android/support/transition/ak
       3: dup
       4: aload_1
       5: invokespecial #16                 // Method android/support/transition/ak."<init>":(Landroid/view/View;)V
       8: areturn

  public android.support.transition.aw b(android.view.View);
    Code:
       0: new           #20                 // class android/support/transition/av
       3: dup
       4: aload_1
       5: invokespecial #21                 // Method android/support/transition/av."<init>":(Landroid/view/View;)V
       8: areturn
}
