class android.support.transition.at$1 extends android.animation.AnimatorListenerAdapter {
  final android.support.transition.ae a;

  final android.view.View b;

  final android.support.transition.at c;

  android.support.transition.at$1(android.support.transition.at, android.support.transition.ae, android.view.View);
    Code:
       0: aload_0
       1: aload_1
       2: putfield      #18                 // Field c:Landroid/support/transition/at;
       5: aload_0
       6: aload_2
       7: putfield      #20                 // Field a:Landroid/support/transition/ae;
      10: aload_0
      11: aload_3
      12: putfield      #22                 // Field b:Landroid/view/View;
      15: aload_0
      16: invokespecial #25                 // Method android/animation/AnimatorListenerAdapter."<init>":()V
      19: return

  public void onAnimationEnd(android.animation.Animator);
    Code:
       0: aload_0
       1: getfield      #20                 // Field a:Landroid/support/transition/ae;
       4: aload_0
       5: getfield      #22                 // Field b:Landroid/view/View;
       8: invokeinterface #33,  2           // InterfaceMethod android/support/transition/ae.b:(Landroid/view/View;)V
      13: return
}
