public abstract class android.support.transition.at extends android.support.transition.u {
  static {};
    Code:
       0: iconst_2
       1: anewarray     #20                 // class java/lang/String
       4: dup
       5: iconst_0
       6: ldc           #22                 // String android:visibility:visibility
       8: aastore
       9: dup
      10: iconst_1
      11: ldc           #24                 // String android:visibility:parent
      13: aastore
      14: putstatic     #26                 // Field g:[Ljava/lang/String;
      17: return

  public android.support.transition.at();
    Code:
       0: aload_0
       1: invokespecial #30                 // Method android/support/transition/u."<init>":()V
       4: aload_0
       5: iconst_3
       6: putfield      #32                 // Field h:I
       9: return

  public android.animation.Animator a(android.view.ViewGroup, android.support.transition.aa, int, android.support.transition.aa, int);
    Code:
       0: aload_0
       1: getfield      #32                 // Field h:I
       4: iconst_1
       5: iand
       6: iconst_1
       7: if_icmpne     74
      10: aload         4
      12: ifnonnull     17
      15: aconst_null
      16: areturn
      17: aload_2
      18: ifnonnull     60
      21: aload         4
      23: getfield      #81                 // Field android/support/transition/aa.b:Landroid/view/View;
      26: invokevirtual #98                 // Method android/view/View.getParent:()Landroid/view/ViewParent;
      29: checkcast     #83                 // class android/view/View
      32: astore        6
      34: aload_0
      35: aload_0
      36: aload         6
      38: iconst_0
      39: invokevirtual #108                // Method b:(Landroid/view/View;Z)Landroid/support/transition/aa;
      42: aload_0
      43: aload         6
      45: iconst_0
      46: invokevirtual #110                // Method a:(Landroid/view/View;Z)Landroid/support/transition/aa;
      49: invokespecial #112                // Method b:(Landroid/support/transition/aa;Landroid/support/transition/aa;)Landroid/support/transition/at$b;
      52: getfield      #39                 // Field android/support/transition/at$b.a:Z
      55: ifeq          60
      58: aconst_null
      59: areturn
      60: aload_0
      61: aload_1
      62: aload         4
      64: getfield      #81                 // Field android/support/transition/aa.b:Landroid/view/View;
      67: aload_2
      68: aload         4
      70: invokevirtual #115                // Method a:(Landroid/view/ViewGroup;Landroid/view/View;Landroid/support/transition/aa;Landroid/support/transition/aa;)Landroid/animation/Animator;
      73: areturn
      74: aconst_null
      75: areturn

  public android.animation.Animator a(android.view.ViewGroup, android.support.transition.aa, android.support.transition.aa);
    Code:
       0: aload_0
       1: aload_2
       2: aload_3
       3: invokespecial #112                // Method b:(Landroid/support/transition/aa;Landroid/support/transition/aa;)Landroid/support/transition/at$b;
       6: astore        4
       8: aload         4
      10: getfield      #39                 // Field android/support/transition/at$b.a:Z
      13: ifeq          76
      16: aload         4
      18: getfield      #71                 // Field android/support/transition/at$b.e:Landroid/view/ViewGroup;
      21: ifnonnull     32
      24: aload         4
      26: getfield      #77                 // Field android/support/transition/at$b.f:Landroid/view/ViewGroup;
      29: ifnull        76
      32: aload         4
      34: getfield      #41                 // Field android/support/transition/at$b.b:Z
      37: ifeq          58
      40: aload_0
      41: aload_1
      42: aload_2
      43: aload         4
      45: getfield      #65                 // Field android/support/transition/at$b.c:I
      48: aload_3
      49: aload         4
      51: getfield      #74                 // Field android/support/transition/at$b.d:I
      54: invokevirtual #118                // Method a:(Landroid/view/ViewGroup;Landroid/support/transition/aa;ILandroid/support/transition/aa;I)Landroid/animation/Animator;
      57: areturn
      58: aload_0
      59: aload_1
      60: aload_2
      61: aload         4
      63: getfield      #65                 // Field android/support/transition/at$b.c:I
      66: aload_3
      67: aload         4
      69: getfield      #74                 // Field android/support/transition/at$b.d:I
      72: invokevirtual #120                // Method b:(Landroid/view/ViewGroup;Landroid/support/transition/aa;ILandroid/support/transition/aa;I)Landroid/animation/Animator;
      75: areturn
      76: aconst_null
      77: areturn

  public android.animation.Animator a(android.view.ViewGroup, android.view.View, android.support.transition.aa, android.support.transition.aa);
    Code:
       0: aconst_null
       1: areturn

  public void a(int);
    Code:
       0: iload_1
       1: bipush        -4
       3: iand
       4: ifeq          17
       7: new           #123                // class java/lang/IllegalArgumentException
      10: dup
      11: ldc           #125                // String Only MODE_IN and MODE_OUT flags are allowed
      13: invokespecial #128                // Method java/lang/IllegalArgumentException."<init>":(Ljava/lang/String;)V
      16: athrow
      17: aload_0
      18: iload_1
      19: putfield      #32                 // Field h:I
      22: return

  public void a(android.support.transition.aa);
    Code:
       0: aload_0
       1: aload_1
       2: invokespecial #130                // Method d:(Landroid/support/transition/aa;)V
       5: return

  public boolean a(android.support.transition.aa, android.support.transition.aa);
    Code:
       0: iconst_0
       1: istore        4
       3: aload_1
       4: ifnonnull     13
       7: aload_2
       8: ifnonnull     13
      11: iconst_0
      12: ireturn
      13: aload_1
      14: ifnull        48
      17: aload_2
      18: ifnull        48
      21: aload_2
      22: getfield      #46                 // Field android/support/transition/aa.a:Ljava/util/Map;
      25: ldc           #22                 // String android:visibility:visibility
      27: invokeinterface #52,  2           // InterfaceMethod java/util/Map.containsKey:(Ljava/lang/Object;)Z
      32: aload_1
      33: getfield      #46                 // Field android/support/transition/aa.a:Ljava/util/Map;
      36: ldc           #22                 // String android:visibility:visibility
      38: invokeinterface #52,  2           // InterfaceMethod java/util/Map.containsKey:(Ljava/lang/Object;)Z
      43: if_icmpeq     48
      46: iconst_0
      47: ireturn
      48: aload_0
      49: aload_1
      50: aload_2
      51: invokespecial #112                // Method b:(Landroid/support/transition/aa;Landroid/support/transition/aa;)Landroid/support/transition/at$b;
      54: astore_1
      55: iload         4
      57: istore_3
      58: aload_1
      59: getfield      #39                 // Field android/support/transition/at$b.a:Z
      62: ifeq          84
      65: aload_1
      66: getfield      #65                 // Field android/support/transition/at$b.c:I
      69: ifeq          82
      72: iload         4
      74: istore_3
      75: aload_1
      76: getfield      #74                 // Field android/support/transition/at$b.d:I
      79: ifne          84
      82: iconst_1
      83: istore_3
      84: iload_3
      85: ireturn

  public java.lang.String[] a();
    Code:
       0: getstatic     #26                 // Field g:[Ljava/lang/String;
       3: areturn

  public android.animation.Animator b(android.view.ViewGroup, android.support.transition.aa, int, android.support.transition.aa, int);
    Code:
       0: aload_0
       1: getfield      #32                 // Field h:I
       4: iconst_2
       5: iand
       6: iconst_2
       7: if_icmpeq     12
      10: aconst_null
      11: areturn
      12: aload_2
      13: ifnull        25
      16: aload_2
      17: getfield      #81                 // Field android/support/transition/aa.b:Landroid/view/View;
      20: astore        8
      22: goto          28
      25: aconst_null
      26: astore        8
      28: aload         4
      30: ifnull        43
      33: aload         4
      35: getfield      #81                 // Field android/support/transition/aa.b:Landroid/view/View;
      38: astore        7
      40: goto          46
      43: aconst_null
      44: astore        7
      46: aload         7
      48: ifnull        88
      51: aload         7
      53: invokevirtual #98                 // Method android/view/View.getParent:()Landroid/view/ViewParent;
      56: ifnonnull     62
      59: goto          88
      62: iload         5
      64: iconst_4
      65: if_icmpne     71
      68: goto          82
      71: aload         8
      73: astore        6
      75: aload         8
      77: aload         7
      79: if_acmpne     97
      82: aconst_null
      83: astore        6
      85: goto          235
      88: aload         7
      90: ifnull        103
      93: aload         7
      95: astore        6
      97: aconst_null
      98: astore        7
     100: goto          235
     103: aload         8
     105: ifnull        228
     108: aload         8
     110: invokevirtual #98                 // Method android/view/View.getParent:()Landroid/view/ViewParent;
     113: ifnonnull     123
     116: aload         8
     118: astore        6
     120: goto          97
     123: aload         8
     125: invokevirtual #98                 // Method android/view/View.getParent:()Landroid/view/ViewParent;
     128: instanceof    #83                 // class android/view/View
     131: ifeq          228
     134: aload         8
     136: invokevirtual #98                 // Method android/view/View.getParent:()Landroid/view/ViewParent;
     139: checkcast     #83                 // class android/view/View
     142: astore        6
     144: aload_0
     145: aload_0
     146: aload         6
     148: iconst_1
     149: invokevirtual #110                // Method a:(Landroid/view/View;Z)Landroid/support/transition/aa;
     152: aload_0
     153: aload         6
     155: iconst_1
     156: invokevirtual #108                // Method b:(Landroid/view/View;Z)Landroid/support/transition/aa;
     159: invokespecial #112                // Method b:(Landroid/support/transition/aa;Landroid/support/transition/aa;)Landroid/support/transition/at$b;
     162: getfield      #39                 // Field android/support/transition/at$b.a:Z
     165: ifne          181
     168: aload_1
     169: aload         8
     171: aload         6
     173: invokestatic  #137                // Method android/support/transition/z.a:(Landroid/view/ViewGroup;Landroid/view/View;Landroid/view/View;)Landroid/view/View;
     176: astore        6
     178: goto          97
     181: aload         6
     183: invokevirtual #98                 // Method android/view/View.getParent:()Landroid/view/ViewParent;
     186: ifnonnull     222
     189: aload         6
     191: invokevirtual #140                // Method android/view/View.getId:()I
     194: istore_3
     195: iload_3
     196: iconst_m1
     197: if_icmpeq     222
     200: aload_1
     201: iload_3
     202: invokevirtual #144                // Method android/view/ViewGroup.findViewById:(I)Landroid/view/View;
     205: ifnull        222
     208: aload_0
     209: getfield      #146                // Field e:Z
     212: ifeq          222
     215: aload         8
     217: astore        6
     219: goto          97
     222: aconst_null
     223: astore        6
     225: goto          97
     228: aconst_null
     229: astore        6
     231: aload         6
     233: astore        7
     235: aload         6
     237: ifnull        376
     240: aload_2
     241: ifnull        376
     244: aload_2
     245: getfield      #46                 // Field android/support/transition/aa.a:Ljava/util/Map;
     248: ldc           #104                // String android:visibility:screenLocation
     250: invokeinterface #56,  2           // InterfaceMethod java/util/Map.get:(Ljava/lang/Object;)Ljava/lang/Object;
     255: checkcast     #148                // class "[I"
     258: astore        7
     260: aload         7
     262: iconst_0
     263: iaload
     264: istore_3
     265: aload         7
     267: iconst_1
     268: iaload
     269: istore        5
     271: iconst_2
     272: newarray       int
     274: astore        7
     276: aload_1
     277: aload         7
     279: invokevirtual #149                // Method android/view/ViewGroup.getLocationOnScreen:([I)V
     282: aload         6
     284: iload_3
     285: aload         7
     287: iconst_0
     288: iaload
     289: isub
     290: aload         6
     292: invokevirtual #152                // Method android/view/View.getLeft:()I
     295: isub
     296: invokevirtual #155                // Method android/view/View.offsetLeftAndRight:(I)V
     299: aload         6
     301: iload         5
     303: aload         7
     305: iconst_1
     306: iaload
     307: isub
     308: aload         6
     310: invokevirtual #158                // Method android/view/View.getTop:()I
     313: isub
     314: invokevirtual #161                // Method android/view/View.offsetTopAndBottom:(I)V
     317: aload_1
     318: invokestatic  #166                // Method android/support/transition/af.a:(Landroid/view/ViewGroup;)Landroid/support/transition/ae;
     321: astore        7
     323: aload         7
     325: aload         6
     327: invokeinterface #171,  2          // InterfaceMethod android/support/transition/ae.a:(Landroid/view/View;)V
     332: aload_0
     333: aload_1
     334: aload         6
     336: aload_2
     337: aload         4
     339: invokevirtual #173                // Method b:(Landroid/view/ViewGroup;Landroid/view/View;Landroid/support/transition/aa;Landroid/support/transition/aa;)Landroid/animation/Animator;
     342: astore_1
     343: aload_1
     344: ifnonnull     358
     347: aload         7
     349: aload         6
     351: invokeinterface #175,  2          // InterfaceMethod android/support/transition/ae.b:(Landroid/view/View;)V
     356: aload_1
     357: areturn
     358: aload_1
     359: new           #6                  // class android/support/transition/at$1
     362: dup
     363: aload_0
     364: aload         7
     366: aload         6
     368: invokespecial #178                // Method android/support/transition/at$1."<init>":(Landroid/support/transition/at;Landroid/support/transition/ae;Landroid/view/View;)V
     371: invokevirtual #184                // Method android/animation/Animator.addListener:(Landroid/animation/Animator$AnimatorListener;)V
     374: aload_1
     375: areturn
     376: aload         7
     378: ifnull        447
     381: aload         7
     383: invokevirtual #86                 // Method android/view/View.getVisibility:()I
     386: istore_3
     387: aload         7
     389: iconst_0
     390: invokestatic  #189                // Method android/support/transition/am.a:(Landroid/view/View;I)V
     393: aload_0
     394: aload_1
     395: aload         7
     397: aload_2
     398: aload         4
     400: invokevirtual #173                // Method b:(Landroid/view/ViewGroup;Landroid/view/View;Landroid/support/transition/aa;Landroid/support/transition/aa;)Landroid/animation/Animator;
     403: astore_1
     404: aload_1
     405: ifnull        439
     408: new           #8                  // class android/support/transition/at$a
     411: dup
     412: aload         7
     414: iload         5
     416: iconst_1
     417: invokespecial #192                // Method android/support/transition/at$a."<init>":(Landroid/view/View;IZ)V
     420: astore_2
     421: aload_1
     422: aload_2
     423: invokevirtual #184                // Method android/animation/Animator.addListener:(Landroid/animation/Animator$AnimatorListener;)V
     426: aload_1
     427: aload_2
     428: invokestatic  #197                // Method android/support/transition/a.a:(Landroid/animation/Animator;Landroid/animation/AnimatorListenerAdapter;)V
     431: aload_0
     432: aload_2
     433: invokevirtual #200                // Method a:(Landroid/support/transition/u$c;)Landroid/support/transition/u;
     436: pop
     437: aload_1
     438: areturn
     439: aload         7
     441: iload_3
     442: invokestatic  #189                // Method android/support/transition/am.a:(Landroid/view/View;I)V
     445: aload_1
     446: areturn
     447: aconst_null
     448: areturn

  public android.animation.Animator b(android.view.ViewGroup, android.view.View, android.support.transition.aa, android.support.transition.aa);
    Code:
       0: aconst_null
       1: areturn

  public void b(android.support.transition.aa);
    Code:
       0: aload_0
       1: aload_1
       2: invokespecial #130                // Method d:(Landroid/support/transition/aa;)V
       5: return
}
