class android.support.transition.f$8 extends android.animation.AnimatorListenerAdapter {
  final android.support.transition.f$a a;

  final android.support.transition.f b;

  android.support.transition.f$8(android.support.transition.f, android.support.transition.f$a);
    Code:
       0: aload_0
       1: aload_1
       2: putfield      #17                 // Field b:Landroid/support/transition/f;
       5: aload_0
       6: aload_2
       7: putfield      #19                 // Field a:Landroid/support/transition/f$a;
      10: aload_0
      11: invokespecial #22                 // Method android/animation/AnimatorListenerAdapter."<init>":()V
      14: aload_0
      15: aload_0
      16: getfield      #19                 // Field a:Landroid/support/transition/f$a;
      19: putfield      #24                 // Field mViewBounds:Landroid/support/transition/f$a;
      22: return
}
