public class android.support.transition.f extends android.support.transition.u {
  static {};
    Code:
       0: iconst_5
       1: anewarray     #50                 // class java/lang/String
       4: dup
       5: iconst_0
       6: ldc           #52                 // String android:changeBounds:bounds
       8: aastore
       9: dup
      10: iconst_1
      11: ldc           #54                 // String android:changeBounds:clip
      13: aastore
      14: dup
      15: iconst_2
      16: ldc           #56                 // String android:changeBounds:parent
      18: aastore
      19: dup
      20: iconst_3
      21: ldc           #58                 // String android:changeBounds:windowX
      23: aastore
      24: dup
      25: iconst_4
      26: ldc           #60                 // String android:changeBounds:windowY
      28: aastore
      29: putstatic     #62                 // Field g:[Ljava/lang/String;
      32: new           #6                  // class android/support/transition/f$1
      35: dup
      36: ldc           #64                 // class android/graphics/PointF
      38: ldc           #66                 // String boundsOrigin
      40: invokespecial #70                 // Method android/support/transition/f$1."<init>":(Ljava/lang/Class;Ljava/lang/String;)V
      43: putstatic     #72                 // Field h:Landroid/util/Property;
      46: new           #12                 // class android/support/transition/f$3
      49: dup
      50: ldc           #64                 // class android/graphics/PointF
      52: ldc           #74                 // String topLeft
      54: invokespecial #75                 // Method android/support/transition/f$3."<init>":(Ljava/lang/Class;Ljava/lang/String;)V
      57: putstatic     #77                 // Field i:Landroid/util/Property;
      60: new           #14                 // class android/support/transition/f$4
      63: dup
      64: ldc           #64                 // class android/graphics/PointF
      66: ldc           #79                 // String bottomRight
      68: invokespecial #80                 // Method android/support/transition/f$4."<init>":(Ljava/lang/Class;Ljava/lang/String;)V
      71: putstatic     #82                 // Field j:Landroid/util/Property;
      74: new           #16                 // class android/support/transition/f$5
      77: dup
      78: ldc           #64                 // class android/graphics/PointF
      80: ldc           #79                 // String bottomRight
      82: invokespecial #83                 // Method android/support/transition/f$5."<init>":(Ljava/lang/Class;Ljava/lang/String;)V
      85: putstatic     #85                 // Field k:Landroid/util/Property;
      88: new           #18                 // class android/support/transition/f$6
      91: dup
      92: ldc           #64                 // class android/graphics/PointF
      94: ldc           #74                 // String topLeft
      96: invokespecial #86                 // Method android/support/transition/f$6."<init>":(Ljava/lang/Class;Ljava/lang/String;)V
      99: putstatic     #88                 // Field l:Landroid/util/Property;
     102: new           #20                 // class android/support/transition/f$7
     105: dup
     106: ldc           #64                 // class android/graphics/PointF
     108: ldc           #90                 // String position
     110: invokespecial #91                 // Method android/support/transition/f$7."<init>":(Ljava/lang/Class;Ljava/lang/String;)V
     113: putstatic     #93                 // Field m:Landroid/util/Property;
     116: new           #95                 // class android/support/transition/s
     119: dup
     120: invokespecial #97                 // Method android/support/transition/s."<init>":()V
     123: putstatic     #99                 // Field q:Landroid/support/transition/s;
     126: return

  public android.support.transition.f();
    Code:
       0: aload_0
       1: invokespecial #101                // Method android/support/transition/u."<init>":()V
       4: aload_0
       5: iconst_2
       6: newarray       int
       8: putfield      #103                // Field n:[I
      11: aload_0
      12: iconst_0
      13: putfield      #105                // Field o:Z
      16: aload_0
      17: iconst_0
      18: putfield      #107                // Field p:Z
      21: return

  public android.animation.Animator a(android.view.ViewGroup, android.support.transition.aa, android.support.transition.aa);
    Code:
       0: aload_2
       1: ifnull        1094
       4: aload_3
       5: ifnonnull     11
       8: goto          1094
      11: aload_2
      12: getfield      #137                // Field android/support/transition/aa.a:Ljava/util/Map;
      15: astore        20
      17: aload_3
      18: getfield      #137                // Field android/support/transition/aa.a:Ljava/util/Map;
      21: astore        19
      23: aload         20
      25: ldc           #56                 // String android:changeBounds:parent
      27: invokeinterface #183,  2          // InterfaceMethod java/util/Map.get:(Ljava/lang/Object;)Ljava/lang/Object;
      32: checkcast     #185                // class android/view/ViewGroup
      35: astore        20
      37: aload         19
      39: ldc           #56                 // String android:changeBounds:parent
      41: invokeinterface #183,  2          // InterfaceMethod java/util/Map.get:(Ljava/lang/Object;)Ljava/lang/Object;
      46: checkcast     #185                // class android/view/ViewGroup
      49: astore        21
      51: aload         20
      53: ifnull        1092
      56: aload         21
      58: ifnonnull     64
      61: goto          1092
      64: aload_3
      65: getfield      #117                // Field android/support/transition/aa.b:Landroid/view/View;
      68: astore        19
      70: aload_0
      71: aload         20
      73: aload         21
      75: invokespecial #187                // Method a:(Landroid/view/View;Landroid/view/View;)Z
      78: ifeq          840
      81: aload_2
      82: getfield      #137                // Field android/support/transition/aa.a:Ljava/util/Map;
      85: ldc           #52                 // String android:changeBounds:bounds
      87: invokeinterface #183,  2          // InterfaceMethod java/util/Map.get:(Ljava/lang/Object;)Ljava/lang/Object;
      92: checkcast     #139                // class android/graphics/Rect
      95: astore_1
      96: aload_3
      97: getfield      #137                // Field android/support/transition/aa.a:Ljava/util/Map;
     100: ldc           #52                 // String android:changeBounds:bounds
     102: invokeinterface #183,  2          // InterfaceMethod java/util/Map.get:(Ljava/lang/Object;)Ljava/lang/Object;
     107: checkcast     #139                // class android/graphics/Rect
     110: astore        20
     112: aload_1
     113: getfield      #191                // Field android/graphics/Rect.left:I
     116: istore        7
     118: aload         20
     120: getfield      #191                // Field android/graphics/Rect.left:I
     123: istore        8
     125: aload_1
     126: getfield      #194                // Field android/graphics/Rect.top:I
     129: istore        9
     131: aload         20
     133: getfield      #194                // Field android/graphics/Rect.top:I
     136: istore        10
     138: aload_1
     139: getfield      #197                // Field android/graphics/Rect.right:I
     142: istore        11
     144: aload         20
     146: getfield      #197                // Field android/graphics/Rect.right:I
     149: istore        12
     151: aload_1
     152: getfield      #200                // Field android/graphics/Rect.bottom:I
     155: istore        13
     157: aload         20
     159: getfield      #200                // Field android/graphics/Rect.bottom:I
     162: istore        14
     164: iload         11
     166: iload         7
     168: isub
     169: istore        15
     171: iload         13
     173: iload         9
     175: isub
     176: istore        16
     178: iload         12
     180: iload         8
     182: isub
     183: istore        17
     185: iload         14
     187: iload         10
     189: isub
     190: istore        18
     192: aload_2
     193: getfield      #137                // Field android/support/transition/aa.a:Ljava/util/Map;
     196: ldc           #54                 // String android:changeBounds:clip
     198: invokeinterface #183,  2          // InterfaceMethod java/util/Map.get:(Ljava/lang/Object;)Ljava/lang/Object;
     203: checkcast     #139                // class android/graphics/Rect
     206: astore_2
     207: aload_3
     208: getfield      #137                // Field android/support/transition/aa.a:Ljava/util/Map;
     211: ldc           #54                 // String android:changeBounds:clip
     213: invokeinterface #183,  2          // InterfaceMethod java/util/Map.get:(Ljava/lang/Object;)Ljava/lang/Object;
     218: checkcast     #139                // class android/graphics/Rect
     221: astore        20
     223: iload         15
     225: ifeq          233
     228: iload         16
     230: ifne          243
     233: iload         17
     235: ifeq          296
     238: iload         18
     240: ifeq          296
     243: iload         7
     245: iload         8
     247: if_icmpne     266
     250: iload         9
     252: iload         10
     254: if_icmpeq     260
     257: goto          266
     260: iconst_0
     261: istore        6
     263: goto          269
     266: iconst_1
     267: istore        6
     269: iload         11
     271: iload         12
     273: if_icmpne     287
     276: iload         6
     278: istore        5
     280: iload         13
     282: iload         14
     284: if_icmpeq     299
     287: iload         6
     289: iconst_1
     290: iadd
     291: istore        5
     293: goto          299
     296: iconst_0
     297: istore        5
     299: aload_2
     300: ifnull        312
     303: aload_2
     304: aload         20
     306: invokevirtual #204                // Method android/graphics/Rect.equals:(Ljava/lang/Object;)Z
     309: ifeq          329
     312: iload         5
     314: istore        6
     316: aload_2
     317: ifnonnull     335
     320: iload         5
     322: istore        6
     324: aload         20
     326: ifnull        335
     329: iload         5
     331: iconst_1
     332: iadd
     333: istore        6
     335: iload         6
     337: ifle          933
     340: aload_0
     341: getfield      #105                // Field o:Z
     344: ifne          596
     347: aload         19
     349: astore_3
     350: aload_3
     351: iload         7
     353: iload         9
     355: iload         11
     357: iload         13
     359: invokestatic  #209                // Method android/support/transition/am.a:(Landroid/view/View;IIII)V
     362: iload         6
     364: iconst_2
     365: if_icmpne     518
     368: iload         15
     370: iload         17
     372: if_icmpne     409
     375: iload         16
     377: iload         18
     379: if_icmpne     409
     382: aload_0
     383: invokevirtual #212                // Method l:()Landroid/support/transition/l;
     386: iload         7
     388: i2f
     389: iload         9
     391: i2f
     392: iload         8
     394: i2f
     395: iload         10
     397: i2f
     398: invokevirtual #217                // Method android/support/transition/l.a:(FFFF)Landroid/graphics/Path;
     401: astore_1
     402: getstatic     #93                 // Field m:Landroid/util/Property;
     405: astore_2
     406: goto          586
     409: new           #26                 // class android/support/transition/f$a
     412: dup
     413: aload_3
     414: invokespecial #220                // Method android/support/transition/f$a."<init>":(Landroid/view/View;)V
     417: astore_2
     418: aload_0
     419: invokevirtual #212                // Method l:()Landroid/support/transition/l;
     422: iload         7
     424: i2f
     425: iload         9
     427: i2f
     428: iload         8
     430: i2f
     431: iload         10
     433: i2f
     434: invokevirtual #217                // Method android/support/transition/l.a:(FFFF)Landroid/graphics/Path;
     437: astore_1
     438: aload_2
     439: getstatic     #77                 // Field i:Landroid/util/Property;
     442: aload_1
     443: invokestatic  #225                // Method android/support/transition/h.a:(Ljava/lang/Object;Landroid/util/Property;Landroid/graphics/Path;)Landroid/animation/ObjectAnimator;
     446: astore_3
     447: aload_0
     448: invokevirtual #212                // Method l:()Landroid/support/transition/l;
     451: iload         11
     453: i2f
     454: iload         13
     456: i2f
     457: iload         12
     459: i2f
     460: iload         14
     462: i2f
     463: invokevirtual #217                // Method android/support/transition/l.a:(FFFF)Landroid/graphics/Path;
     466: astore_1
     467: aload_2
     468: getstatic     #82                 // Field j:Landroid/util/Property;
     471: aload_1
     472: invokestatic  #225                // Method android/support/transition/h.a:(Ljava/lang/Object;Landroid/util/Property;Landroid/graphics/Path;)Landroid/animation/ObjectAnimator;
     475: astore        20
     477: new           #227                // class android/animation/AnimatorSet
     480: dup
     481: invokespecial #228                // Method android/animation/AnimatorSet."<init>":()V
     484: astore_1
     485: aload_1
     486: iconst_2
     487: anewarray     #230                // class android/animation/Animator
     490: dup
     491: iconst_0
     492: aload_3
     493: aastore
     494: dup
     495: iconst_1
     496: aload         20
     498: aastore
     499: invokevirtual #234                // Method android/animation/AnimatorSet.playTogether:([Landroid/animation/Animator;)V
     502: aload_1
     503: new           #22                 // class android/support/transition/f$8
     506: dup
     507: aload_0
     508: aload_2
     509: invokespecial #237                // Method android/support/transition/f$8."<init>":(Landroid/support/transition/f;Landroid/support/transition/f$a;)V
     512: invokevirtual #241                // Method android/animation/AnimatorSet.addListener:(Landroid/animation/Animator$AnimatorListener;)V
     515: goto          799
     518: iload         7
     520: iload         8
     522: if_icmpne     562
     525: iload         9
     527: iload         10
     529: if_icmpeq     535
     532: goto          562
     535: aload_0
     536: invokevirtual #212                // Method l:()Landroid/support/transition/l;
     539: iload         11
     541: i2f
     542: iload         13
     544: i2f
     545: iload         12
     547: i2f
     548: iload         14
     550: i2f
     551: invokevirtual #217                // Method android/support/transition/l.a:(FFFF)Landroid/graphics/Path;
     554: astore_1
     555: getstatic     #85                 // Field k:Landroid/util/Property;
     558: astore_2
     559: goto          586
     562: aload_0
     563: invokevirtual #212                // Method l:()Landroid/support/transition/l;
     566: iload         7
     568: i2f
     569: iload         9
     571: i2f
     572: iload         8
     574: i2f
     575: iload         10
     577: i2f
     578: invokevirtual #217                // Method android/support/transition/l.a:(FFFF)Landroid/graphics/Path;
     581: astore_1
     582: getstatic     #88                 // Field l:Landroid/util/Property;
     585: astore_2
     586: aload_3
     587: aload_2
     588: aload_1
     589: invokestatic  #225                // Method android/support/transition/h.a:(Ljava/lang/Object;Landroid/util/Property;Landroid/graphics/Path;)Landroid/animation/ObjectAnimator;
     592: astore_1
     593: goto          799
     596: aload         19
     598: astore        21
     600: aload         21
     602: iload         7
     604: iload         9
     606: iload         15
     608: iload         17
     610: invokestatic  #247                // Method java/lang/Math.max:(II)I
     613: iload         7
     615: iadd
     616: iload         16
     618: iload         18
     620: invokestatic  #247                // Method java/lang/Math.max:(II)I
     623: iload         9
     625: iadd
     626: invokestatic  #209                // Method android/support/transition/am.a:(Landroid/view/View;IIII)V
     629: iload         7
     631: iload         8
     633: if_icmpne     651
     636: iload         9
     638: iload         10
     640: if_icmpeq     646
     643: goto          651
     646: aconst_null
     647: astore_1
     648: goto          681
     651: aload_0
     652: invokevirtual #212                // Method l:()Landroid/support/transition/l;
     655: iload         7
     657: i2f
     658: iload         9
     660: i2f
     661: iload         8
     663: i2f
     664: iload         10
     666: i2f
     667: invokevirtual #217                // Method android/support/transition/l.a:(FFFF)Landroid/graphics/Path;
     670: astore_1
     671: aload         21
     673: getstatic     #93                 // Field m:Landroid/util/Property;
     676: aload_1
     677: invokestatic  #225                // Method android/support/transition/h.a:(Ljava/lang/Object;Landroid/util/Property;Landroid/graphics/Path;)Landroid/animation/ObjectAnimator;
     680: astore_1
     681: aload_2
     682: ifnonnull     702
     685: new           #139                // class android/graphics/Rect
     688: dup
     689: iconst_0
     690: iconst_0
     691: iload         15
     693: iload         16
     695: invokespecial #154                // Method android/graphics/Rect."<init>":(IIII)V
     698: astore_2
     699: goto          702
     702: aload         20
     704: ifnonnull     724
     707: new           #139                // class android/graphics/Rect
     710: dup
     711: iconst_0
     712: iconst_0
     713: iload         17
     715: iload         18
     717: invokespecial #154                // Method android/graphics/Rect."<init>":(IIII)V
     720: astore_3
     721: goto          727
     724: aload         20
     726: astore_3
     727: aload_2
     728: aload_3
     729: invokevirtual #204                // Method android/graphics/Rect.equals:(Ljava/lang/Object;)Z
     732: ifne          791
     735: aload         21
     737: aload_2
     738: invokestatic  #250                // Method android/support/v4/view/s.a:(Landroid/view/View;Landroid/graphics/Rect;)V
     741: aload         21
     743: ldc           #252                // String clipBounds
     745: getstatic     #99                 // Field q:Landroid/support/transition/s;
     748: iconst_2
     749: anewarray     #254                // class java/lang/Object
     752: dup
     753: iconst_0
     754: aload_2
     755: aastore
     756: dup
     757: iconst_1
     758: aload_3
     759: aastore
     760: invokestatic  #260                // Method android/animation/ObjectAnimator.ofObject:(Ljava/lang/Object;Ljava/lang/String;Landroid/animation/TypeEvaluator;[Ljava/lang/Object;)Landroid/animation/ObjectAnimator;
     763: astore_2
     764: aload_2
     765: new           #24                 // class android/support/transition/f$9
     768: dup
     769: aload_0
     770: aload         21
     772: aload         20
     774: iload         8
     776: iload         10
     778: iload         12
     780: iload         14
     782: invokespecial #263                // Method android/support/transition/f$9."<init>":(Landroid/support/transition/f;Landroid/view/View;Landroid/graphics/Rect;IIII)V
     785: invokevirtual #264                // Method android/animation/ObjectAnimator.addListener:(Landroid/animation/Animator$AnimatorListener;)V
     788: goto          793
     791: aconst_null
     792: astore_2
     793: aload_1
     794: aload_2
     795: invokestatic  #269                // Method android/support/transition/z.a:(Landroid/animation/Animator;Landroid/animation/Animator;)Landroid/animation/Animator;
     798: astore_1
     799: aload         19
     801: invokevirtual #164                // Method android/view/View.getParent:()Landroid/view/ViewParent;
     804: instanceof    #185                // class android/view/ViewGroup
     807: ifeq          838
     810: aload         19
     812: invokevirtual #164                // Method android/view/View.getParent:()Landroid/view/ViewParent;
     815: checkcast     #185                // class android/view/ViewGroup
     818: astore_2
     819: aload_2
     820: iconst_1
     821: invokestatic  #274                // Method android/support/transition/af.a:(Landroid/view/ViewGroup;Z)V
     824: aload_0
     825: new           #8                  // class android/support/transition/f$10
     828: dup
     829: aload_0
     830: aload_2
     831: invokespecial #277                // Method android/support/transition/f$10."<init>":(Landroid/support/transition/f;Landroid/view/ViewGroup;)V
     834: invokevirtual #280                // Method a:(Landroid/support/transition/u$c;)Landroid/support/transition/u;
     837: pop
     838: aload_1
     839: areturn
     840: aload_2
     841: getfield      #137                // Field android/support/transition/aa.a:Ljava/util/Map;
     844: ldc           #58                 // String android:changeBounds:windowX
     846: invokeinterface #183,  2          // InterfaceMethod java/util/Map.get:(Ljava/lang/Object;)Ljava/lang/Object;
     851: checkcast     #170                // class java/lang/Integer
     854: invokevirtual #283                // Method java/lang/Integer.intValue:()I
     857: istore        5
     859: aload_2
     860: getfield      #137                // Field android/support/transition/aa.a:Ljava/util/Map;
     863: ldc           #60                 // String android:changeBounds:windowY
     865: invokeinterface #183,  2          // InterfaceMethod java/util/Map.get:(Ljava/lang/Object;)Ljava/lang/Object;
     870: checkcast     #170                // class java/lang/Integer
     873: invokevirtual #283                // Method java/lang/Integer.intValue:()I
     876: istore        6
     878: aload_3
     879: getfield      #137                // Field android/support/transition/aa.a:Ljava/util/Map;
     882: ldc           #58                 // String android:changeBounds:windowX
     884: invokeinterface #183,  2          // InterfaceMethod java/util/Map.get:(Ljava/lang/Object;)Ljava/lang/Object;
     889: checkcast     #170                // class java/lang/Integer
     892: invokevirtual #283                // Method java/lang/Integer.intValue:()I
     895: istore        7
     897: aload_3
     898: getfield      #137                // Field android/support/transition/aa.a:Ljava/util/Map;
     901: ldc           #60                 // String android:changeBounds:windowY
     903: invokeinterface #183,  2          // InterfaceMethod java/util/Map.get:(Ljava/lang/Object;)Ljava/lang/Object;
     908: checkcast     #170                // class java/lang/Integer
     911: invokevirtual #283                // Method java/lang/Integer.intValue:()I
     914: istore        8
     916: iload         5
     918: iload         7
     920: if_icmpne     935
     923: iload         6
     925: iload         8
     927: if_icmpeq     933
     930: goto          935
     933: aconst_null
     934: areturn
     935: aload_1
     936: aload_0
     937: getfield      #103                // Field n:[I
     940: invokevirtual #284                // Method android/view/ViewGroup.getLocationInWindow:([I)V
     943: aload         19
     945: invokevirtual #131                // Method android/view/View.getWidth:()I
     948: aload         19
     950: invokevirtual #134                // Method android/view/View.getHeight:()I
     953: getstatic     #290                // Field android/graphics/Bitmap$Config.ARGB_8888:Landroid/graphics/Bitmap$Config;
     956: invokestatic  #296                // Method android/graphics/Bitmap.createBitmap:(IILandroid/graphics/Bitmap$Config;)Landroid/graphics/Bitmap;
     959: astore_2
     960: aload         19
     962: new           #298                // class android/graphics/Canvas
     965: dup
     966: aload_2
     967: invokespecial #301                // Method android/graphics/Canvas."<init>":(Landroid/graphics/Bitmap;)V
     970: invokevirtual #305                // Method android/view/View.draw:(Landroid/graphics/Canvas;)V
     973: new           #307                // class android/graphics/drawable/BitmapDrawable
     976: dup
     977: aload_2
     978: invokespecial #308                // Method android/graphics/drawable/BitmapDrawable."<init>":(Landroid/graphics/Bitmap;)V
     981: astore_2
     982: aload         19
     984: invokestatic  #312                // Method android/support/transition/am.c:(Landroid/view/View;)F
     987: fstore        4
     989: aload         19
     991: fconst_0
     992: invokestatic  #315                // Method android/support/transition/am.a:(Landroid/view/View;F)V
     995: aload_1
     996: invokestatic  #318                // Method android/support/transition/am.a:(Landroid/view/View;)Landroid/support/transition/al;
     999: aload_2
    1000: invokeinterface #323,  2          // InterfaceMethod android/support/transition/al.a:(Landroid/graphics/drawable/Drawable;)V
    1005: aload_0
    1006: invokevirtual #212                // Method l:()Landroid/support/transition/l;
    1009: iload         5
    1011: aload_0
    1012: getfield      #103                // Field n:[I
    1015: iconst_0
    1016: iaload
    1017: isub
    1018: i2f
    1019: iload         6
    1021: aload_0
    1022: getfield      #103                // Field n:[I
    1025: iconst_1
    1026: iaload
    1027: isub
    1028: i2f
    1029: iload         7
    1031: aload_0
    1032: getfield      #103                // Field n:[I
    1035: iconst_0
    1036: iaload
    1037: isub
    1038: i2f
    1039: iload         8
    1041: aload_0
    1042: getfield      #103                // Field n:[I
    1045: iconst_1
    1046: iaload
    1047: isub
    1048: i2f
    1049: invokevirtual #217                // Method android/support/transition/l.a:(FFFF)Landroid/graphics/Path;
    1052: astore_3
    1053: aload_2
    1054: iconst_1
    1055: anewarray     #325                // class android/animation/PropertyValuesHolder
    1058: dup
    1059: iconst_0
    1060: getstatic     #72                 // Field h:Landroid/util/Property;
    1063: aload_3
    1064: invokestatic  #330                // Method android/support/transition/n.a:(Landroid/util/Property;Landroid/graphics/Path;)Landroid/animation/PropertyValuesHolder;
    1067: aastore
    1068: invokestatic  #334                // Method android/animation/ObjectAnimator.ofPropertyValuesHolder:(Ljava/lang/Object;[Landroid/animation/PropertyValuesHolder;)Landroid/animation/ObjectAnimator;
    1071: astore_3
    1072: aload_3
    1073: new           #10                 // class android/support/transition/f$2
    1076: dup
    1077: aload_0
    1078: aload_1
    1079: aload_2
    1080: aload         19
    1082: fload         4
    1084: invokespecial #337                // Method android/support/transition/f$2."<init>":(Landroid/support/transition/f;Landroid/view/ViewGroup;Landroid/graphics/drawable/BitmapDrawable;Landroid/view/View;F)V
    1087: invokevirtual #264                // Method android/animation/ObjectAnimator.addListener:(Landroid/animation/Animator$AnimatorListener;)V
    1090: aload_3
    1091: areturn
    1092: aconst_null
    1093: areturn
    1094: aconst_null
    1095: areturn

  public void a(android.support.transition.aa);
    Code:
       0: aload_0
       1: aload_1
       2: invokespecial #339                // Method d:(Landroid/support/transition/aa;)V
       5: return

  public java.lang.String[] a();
    Code:
       0: getstatic     #62                 // Field g:[Ljava/lang/String;
       3: areturn

  public void b(android.support.transition.aa);
    Code:
       0: aload_0
       1: aload_1
       2: invokespecial #339                // Method d:(Landroid/support/transition/aa;)V
       5: return
}
