class android.support.transition.FragmentTransitionSupport$1 extends android.support.transition.u$b {
  final android.graphics.Rect a;

  final android.support.transition.FragmentTransitionSupport b;

  android.support.transition.FragmentTransitionSupport$1(android.support.transition.FragmentTransitionSupport, android.graphics.Rect);
    Code:
       0: aload_0
       1: aload_1
       2: putfield      #16                 // Field b:Landroid/support/transition/FragmentTransitionSupport;
       5: aload_0
       6: aload_2
       7: putfield      #18                 // Field a:Landroid/graphics/Rect;
      10: aload_0
      11: invokespecial #21                 // Method android/support/transition/u$b."<init>":()V
      14: return
}
