class android.support.transition.j implements android.support.transition.k {
  android.support.transition.j();
    Code:
       0: aload_0
       1: invokespecial #10                 // Method java/lang/Object."<init>":()V
       4: return

  public <T> android.animation.ObjectAnimator a(T, android.util.Property<T, android.graphics.PointF>, android.graphics.Path);
    Code:
       0: aload_1
       1: aload_2
       2: aconst_null
       3: aload_3
       4: invokestatic  #19                 // Method android/animation/ObjectAnimator.ofObject:(Ljava/lang/Object;Landroid/util/Property;Landroid/animation/TypeConverter;Landroid/graphics/Path;)Landroid/animation/ObjectAnimator;
       7: areturn
}
