class android.support.transition.p implements android.support.transition.q {
  android.support.transition.p();
    Code:
       0: aload_0
       1: invokespecial #10                 // Method java/lang/Object."<init>":()V
       4: return

  public android.animation.PropertyValuesHolder a(android.util.Property<?, android.graphics.PointF>, android.graphics.Path);
    Code:
       0: aload_1
       1: aconst_null
       2: aload_2
       3: invokestatic  #19                 // Method android/animation/PropertyValuesHolder.ofObject:(Landroid/util/Property;Landroid/animation/TypeConverter;Landroid/graphics/Path;)Landroid/animation/PropertyValuesHolder;
       6: areturn
}
