class android.support.transition.u$a {
  android.view.View a;

  java.lang.String b;

  android.support.transition.aa c;

  android.support.transition.aw d;

  android.support.transition.u e;

  android.support.transition.u$a(android.view.View, java.lang.String, android.support.transition.u, android.support.transition.aw, android.support.transition.aa);
    Code:
       0: aload_0
       1: invokespecial #21                 // Method java/lang/Object."<init>":()V
       4: aload_0
       5: aload_1
       6: putfield      #23                 // Field a:Landroid/view/View;
       9: aload_0
      10: aload_2
      11: putfield      #25                 // Field b:Ljava/lang/String;
      14: aload_0
      15: aload         5
      17: putfield      #27                 // Field c:Landroid/support/transition/aa;
      20: aload_0
      21: aload         4
      23: putfield      #29                 // Field d:Landroid/support/transition/aw;
      26: aload_0
      27: aload_3
      28: putfield      #31                 // Field e:Landroid/support/transition/u;
      31: return
}
