class android.support.transition.y$1 extends android.support.transition.v {
  final android.support.transition.u a;

  final android.support.transition.y b;

  android.support.transition.y$1(android.support.transition.y, android.support.transition.u);
    Code:
       0: aload_0
       1: aload_1
       2: putfield      #17                 // Field b:Landroid/support/transition/y;
       5: aload_0
       6: aload_2
       7: putfield      #19                 // Field a:Landroid/support/transition/u;
      10: aload_0
      11: invokespecial #21                 // Method android/support/transition/v."<init>":()V
      14: return

  public void a(android.support.transition.u);
    Code:
       0: aload_0
       1: getfield      #19                 // Field a:Landroid/support/transition/u;
       4: invokevirtual #26                 // Method android/support/transition/u.e:()V
       7: aload_1
       8: aload_0
       9: invokevirtual #29                 // Method android/support/transition/u.b:(Landroid/support/transition/u$c;)Landroid/support/transition/u;
      12: pop
      13: return
}
