class ryey.easer.plugins.event.p.e$2 implements android.view.View$OnClickListener {
  final ryey.easer.plugins.event.p.e a;

  ryey.easer.plugins.event.p.e$2(ryey.easer.plugins.event.p.e);
    Code:
       0: aload_0
       1: aload_1
       2: putfield      #17                 // Field a:Lryey/easer/plugins/event/p/e;
       5: aload_0
       6: invokespecial #20                 // Method java/lang/Object."<init>":()V
       9: return

  public void onClick(android.view.View);
    Code:
       0: aload_0
       1: getfield      #17                 // Field a:Lryey/easer/plugins/event/p/e;
       4: invokevirtual #27                 // Method ryey/easer/plugins/event/p/e.getContext:()Landroid/content/Context;
       7: ldc           #29                 // String android.permission.ACCESS_WIFI_STATE
       9: invokestatic  #34                 // Method ryey/easer/b.a:(Landroid/content/Context;Ljava/lang/String;)Z
      12: ifne          16
      15: return
      16: aload_0
      17: getfield      #17                 // Field a:Lryey/easer/plugins/event/p/e;
      20: invokestatic  #38                 // Method ryey/easer/plugins/event/p/e.b:(Lryey/easer/plugins/event/p/e;)Ljava/util/concurrent/locks/ReentrantLock;
      23: invokevirtual #43                 // Method java/util/concurrent/locks/ReentrantLock.lock:()V
      26: aload_0
      27: getfield      #17                 // Field a:Lryey/easer/plugins/event/p/e;
      30: iconst_1
      31: invokestatic  #46                 // Method ryey/easer/plugins/event/p/e.a:(Lryey/easer/plugins/event/p/e;Z)Z
      34: pop
      35: aload_0
      36: getfield      #17                 // Field a:Lryey/easer/plugins/event/p/e;
      39: invokestatic  #38                 // Method ryey/easer/plugins/event/p/e.b:(Lryey/easer/plugins/event/p/e;)Ljava/util/concurrent/locks/ReentrantLock;
      42: invokevirtual #49                 // Method java/util/concurrent/locks/ReentrantLock.unlock:()V
      45: aload_0
      46: getfield      #17                 // Field a:Lryey/easer/plugins/event/p/e;
      49: invokestatic  #53                 // Method ryey/easer/plugins/event/p/e.c:(Lryey/easer/plugins/event/p/e;)Landroid/net/wifi/WifiManager;
      52: invokevirtual #59                 // Method android/net/wifi/WifiManager.startScan:()Z
      55: pop
      56: aload_0
      57: getfield      #17                 // Field a:Lryey/easer/plugins/event/p/e;
      60: new           #61                 // class android/app/ProgressDialog
      63: dup
      64: aload_0
      65: getfield      #17                 // Field a:Lryey/easer/plugins/event/p/e;
      68: invokevirtual #27                 // Method ryey/easer/plugins/event/p/e.getContext:()Landroid/content/Context;
      71: invokespecial #64                 // Method android/app/ProgressDialog."<init>":(Landroid/content/Context;)V
      74: putfield      #67                 // Field ryey/easer/plugins/event/p/e.a:Landroid/app/ProgressDialog;
      77: aload_0
      78: getfield      #17                 // Field a:Lryey/easer/plugins/event/p/e;
      81: getfield      #67                 // Field ryey/easer/plugins/event/p/e.a:Landroid/app/ProgressDialog;
      84: ldc           #68                 // int 2131624328
      86: invokevirtual #72                 // Method android/app/ProgressDialog.setTitle:(I)V
      89: aload_0
      90: getfield      #17                 // Field a:Lryey/easer/plugins/event/p/e;
      93: getfield      #67                 // Field ryey/easer/plugins/event/p/e.a:Landroid/app/ProgressDialog;
      96: iconst_1
      97: invokevirtual #76                 // Method android/app/ProgressDialog.setIndeterminate:(Z)V
     100: aload_0
     101: getfield      #17                 // Field a:Lryey/easer/plugins/event/p/e;
     104: getfield      #67                 // Field ryey/easer/plugins/event/p/e.a:Landroid/app/ProgressDialog;
     107: invokevirtual #79                 // Method android/app/ProgressDialog.show:()V
     110: return
     111: astore_1
     112: aload_0
     113: getfield      #17                 // Field a:Lryey/easer/plugins/event/p/e;
     116: invokestatic  #38                 // Method ryey/easer/plugins/event/p/e.b:(Lryey/easer/plugins/event/p/e;)Ljava/util/concurrent/locks/ReentrantLock;
     119: invokevirtual #49                 // Method java/util/concurrent/locks/ReentrantLock.unlock:()V
     122: aload_1
     123: athrow
    Exception table:
       from    to  target type
          26    35   111   any
}
