class ryey.easer.plugins.event.b.d$1 extends android.content.BroadcastReceiver {
  final ryey.easer.plugins.event.b.d a;

  ryey.easer.plugins.event.b.d$1(ryey.easer.plugins.event.b.d);
    Code:
       0: aload_0
       1: aload_1
       2: putfield      #12                 // Field a:Lryey/easer/plugins/event/b/d;
       5: aload_0
       6: invokespecial #15                 // Method android/content/BroadcastReceiver."<init>":()V
       9: return

  public void onReceive(android.content.Context, android.content.Intent);
    Code:
       0: aload_2
       1: invokevirtual #24                 // Method android/content/Intent.getAction:()Ljava/lang/String;
       4: ldc           #26                 // String ryey.easer.plugins.event.bluetooth_device.return_from_dialog
       6: invokevirtual #32                 // Method java/lang/String.equals:(Ljava/lang/Object;)Z
       9: ifeq          36
      12: aload_0
      13: getfield      #12                 // Field a:Lryey/easer/plugins/event/b/d;
      16: aload_2
      17: ldc           #34                 // String ryey.easer.plugins.event.bluetooth_device.extra.hardware_address
      19: invokevirtual #38                 // Method android/content/Intent.getStringExtra:(Ljava/lang/String;)Ljava/lang/String;
      22: invokestatic  #41                 // Method ryey/easer/plugins/event/b/d.a:(Lryey/easer/plugins/event/b/d;Ljava/lang/String;)V
      25: aload_1
      26: aload_0
      27: getfield      #12                 // Field a:Lryey/easer/plugins/event/b/d;
      30: invokestatic  #44                 // Method ryey/easer/plugins/event/b/d.a:(Lryey/easer/plugins/event/b/d;)Landroid/content/BroadcastReceiver;
      33: invokevirtual #50                 // Method android/content/Context.unregisterReceiver:(Landroid/content/BroadcastReceiver;)V
      36: return
}
