class ryey.easer.plugins.event.b.e$1 extends android.content.BroadcastReceiver {
  final ryey.easer.plugins.event.b.e a;

  ryey.easer.plugins.event.b.e$1(ryey.easer.plugins.event.b.e);
    Code:
       0: aload_0
       1: aload_1
       2: putfield      #12                 // Field a:Lryey/easer/plugins/event/b/e;
       5: aload_0
       6: invokespecial #15                 // Method android/content/BroadcastReceiver."<init>":()V
       9: return

  public void onReceive(android.content.Context, android.content.Intent);
    Code:
       0: aload_2
       1: invokevirtual #24                 // Method android/content/Intent.getAction:()Ljava/lang/String;
       4: astore_1
       5: aload_1
       6: ldc           #26                 // String android.bluetooth.device.action.ACL_CONNECTED
       8: invokevirtual #32                 // Method java/lang/String.equals:(Ljava/lang/Object;)Z
      11: ifeq          46
      14: aload_2
      15: ldc           #34                 // String android.bluetooth.device.extra.DEVICE
      17: invokevirtual #38                 // Method android/content/Intent.getParcelableExtra:(Ljava/lang/String;)Landroid/os/Parcelable;
      20: checkcast     #40                 // class android/bluetooth/BluetoothDevice
      23: astore_1
      24: aload_0
      25: getfield      #12                 // Field a:Lryey/easer/plugins/event/b/e;
      28: aload_1
      29: invokestatic  #43                 // Method ryey/easer/plugins/event/b/e.a:(Lryey/easer/plugins/event/b/e;Landroid/bluetooth/BluetoothDevice;)Z
      32: ifeq          95
      35: aload_0
      36: getfield      #12                 // Field a:Lryey/easer/plugins/event/b/e;
      39: invokestatic  #46                 // Method ryey/easer/plugins/event/b/e.a:(Lryey/easer/plugins/event/b/e;)I
      42: pop
      43: goto          84
      46: aload_1
      47: ldc           #48                 // String android.bluetooth.device.action.ACL_DISCONNECTED
      49: invokevirtual #32                 // Method java/lang/String.equals:(Ljava/lang/Object;)Z
      52: ifeq          95
      55: aload_2
      56: ldc           #34                 // String android.bluetooth.device.extra.DEVICE
      58: invokevirtual #38                 // Method android/content/Intent.getParcelableExtra:(Ljava/lang/String;)Landroid/os/Parcelable;
      61: checkcast     #40                 // class android/bluetooth/BluetoothDevice
      64: astore_1
      65: aload_0
      66: getfield      #12                 // Field a:Lryey/easer/plugins/event/b/e;
      69: aload_1
      70: invokestatic  #43                 // Method ryey/easer/plugins/event/b/e.a:(Lryey/easer/plugins/event/b/e;Landroid/bluetooth/BluetoothDevice;)Z
      73: ifeq          95
      76: aload_0
      77: getfield      #12                 // Field a:Lryey/easer/plugins/event/b/e;
      80: invokestatic  #51                 // Method ryey/easer/plugins/event/b/e.b:(Lryey/easer/plugins/event/b/e;)I
      83: pop
      84: aload_0
      85: getfield      #12                 // Field a:Lryey/easer/plugins/event/b/e;
      88: aload_1
      89: invokestatic  #54                 // Method ryey/easer/plugins/event/b/e.a:(Landroid/bluetooth/BluetoothDevice;)Landroid/os/Bundle;
      92: invokestatic  #57                 // Method ryey/easer/plugins/event/b/e.a:(Lryey/easer/plugins/event/b/e;Landroid/os/Bundle;)V
      95: return
}
