public class org.apmem.tools.layouts.FlowLayout extends android.view.ViewGroup {
  java.util.List<org.apmem.tools.layouts.b> a;

  public org.apmem.tools.layouts.FlowLayout(android.content.Context);
    Code:
       0: aload_0
       1: aload_1
       2: invokespecial #15                 // Method android/view/ViewGroup."<init>":(Landroid/content/Context;)V
       5: aload_0
       6: new           #17                 // class java/util/ArrayList
       9: dup
      10: invokespecial #20                 // Method java/util/ArrayList."<init>":()V
      13: putfield      #22                 // Field a:Ljava/util/List;
      16: aload_0
      17: new           #24                 // class org/apmem/tools/layouts/a
      20: dup
      21: aload_1
      22: aconst_null
      23: invokespecial #27                 // Method org/apmem/tools/layouts/a."<init>":(Landroid/content/Context;Landroid/util/AttributeSet;)V
      26: putfield      #29                 // Field b:Lorg/apmem/tools/layouts/a;
      29: return

  public org.apmem.tools.layouts.FlowLayout(android.content.Context, android.util.AttributeSet);
    Code:
       0: aload_0
       1: aload_1
       2: aload_2
       3: invokespecial #31                 // Method android/view/ViewGroup."<init>":(Landroid/content/Context;Landroid/util/AttributeSet;)V
       6: aload_0
       7: new           #17                 // class java/util/ArrayList
      10: dup
      11: invokespecial #20                 // Method java/util/ArrayList."<init>":()V
      14: putfield      #22                 // Field a:Ljava/util/List;
      17: aload_0
      18: new           #24                 // class org/apmem/tools/layouts/a
      21: dup
      22: aload_1
      23: aload_2
      24: invokespecial #27                 // Method org/apmem/tools/layouts/a."<init>":(Landroid/content/Context;Landroid/util/AttributeSet;)V
      27: putfield      #29                 // Field b:Lorg/apmem/tools/layouts/a;
      30: return

  public org.apmem.tools.layouts.FlowLayout(android.content.Context, android.util.AttributeSet, int);
    Code:
       0: aload_0
       1: aload_1
       2: aload_2
       3: iload_3
       4: invokespecial #34                 // Method android/view/ViewGroup."<init>":(Landroid/content/Context;Landroid/util/AttributeSet;I)V
       7: aload_0
       8: new           #17                 // class java/util/ArrayList
      11: dup
      12: invokespecial #20                 // Method java/util/ArrayList."<init>":()V
      15: putfield      #22                 // Field a:Ljava/util/List;
      18: aload_0
      19: new           #24                 // class org/apmem/tools/layouts/a
      22: dup
      23: aload_1
      24: aload_2
      25: invokespecial #27                 // Method org/apmem/tools/layouts/a."<init>":(Landroid/content/Context;Landroid/util/AttributeSet;)V
      28: putfield      #29                 // Field b:Lorg/apmem/tools/layouts/a;
      31: return

  protected org.apmem.tools.layouts.FlowLayout$a a();
    Code:
       0: new           #6                  // class org/apmem/tools/layouts/FlowLayout$a
       3: dup
       4: bipush        -2
       6: bipush        -2
       8: invokespecial #275                // Method org/apmem/tools/layouts/FlowLayout$a."<init>":(II)V
      11: areturn

  public org.apmem.tools.layouts.FlowLayout$a a(android.util.AttributeSet);
    Code:
       0: new           #6                  // class org/apmem/tools/layouts/FlowLayout$a
       3: dup
       4: aload_0
       5: invokevirtual #280                // Method getContext:()Landroid/content/Context;
       8: aload_1
       9: invokespecial #281                // Method org/apmem/tools/layouts/FlowLayout$a."<init>":(Landroid/content/Context;Landroid/util/AttributeSet;)V
      12: areturn

  protected org.apmem.tools.layouts.FlowLayout$a a(android.view.ViewGroup$LayoutParams);
    Code:
       0: new           #6                  // class org/apmem/tools/layouts/FlowLayout$a
       3: dup
       4: aload_1
       5: invokespecial #285                // Method org/apmem/tools/layouts/FlowLayout$a."<init>":(Landroid/view/ViewGroup$LayoutParams;)V
       8: areturn

  public boolean b();
    Code:
       0: aload_0
       1: getfield      #29                 // Field b:Lorg/apmem/tools/layouts/a;
       4: invokevirtual #286                // Method org/apmem/tools/layouts/a.b:()Z
       7: ifne          22
      10: aload_0
      11: invokespecial #288                // Method c:()Z
      14: ifeq          20
      17: goto          22
      20: iconst_0
      21: ireturn
      22: iconst_1
      23: ireturn

  protected boolean checkLayoutParams(android.view.ViewGroup$LayoutParams);
    Code:
       0: aload_1
       1: instanceof    #6                  // class org/apmem/tools/layouts/FlowLayout$a
       4: ireturn

  protected boolean drawChild(android.graphics.Canvas, android.view.View, long);
    Code:
       0: aload_0
       1: aload_1
       2: aload_2
       3: lload_3
       4: invokespecial #294                // Method android/view/ViewGroup.drawChild:(Landroid/graphics/Canvas;Landroid/view/View;J)Z
       7: istore        5
       9: aload_0
      10: aload_1
      11: aload_2
      12: invokespecial #296                // Method a:(Landroid/graphics/Canvas;Landroid/view/View;)V
      15: iload         5
      17: ireturn

  protected android.view.ViewGroup$LayoutParams generateDefaultLayoutParams();
    Code:
       0: aload_0
       1: invokevirtual #299                // Method a:()Lorg/apmem/tools/layouts/FlowLayout$a;
       4: areturn

  public android.view.ViewGroup$LayoutParams generateLayoutParams(android.util.AttributeSet);
    Code:
       0: aload_0
       1: aload_1
       2: invokevirtual #303                // Method a:(Landroid/util/AttributeSet;)Lorg/apmem/tools/layouts/FlowLayout$a;
       5: areturn

  protected android.view.ViewGroup$LayoutParams generateLayoutParams(android.view.ViewGroup$LayoutParams);
    Code:
       0: aload_0
       1: aload_1
       2: invokevirtual #306                // Method a:(Landroid/view/ViewGroup$LayoutParams;)Lorg/apmem/tools/layouts/FlowLayout$a;
       5: areturn

  public int getGravity();
    Code:
       0: aload_0
       1: getfield      #29                 // Field b:Lorg/apmem/tools/layouts/a;
       4: invokevirtual #55                 // Method org/apmem/tools/layouts/a.d:()I
       7: ireturn

  public int getLayoutDirection();
    Code:
       0: aload_0
       1: getfield      #29                 // Field b:Lorg/apmem/tools/layouts/a;
       4: ifnonnull     9
       7: iconst_0
       8: ireturn
       9: aload_0
      10: getfield      #29                 // Field b:Lorg/apmem/tools/layouts/a;
      13: invokevirtual #42                 // Method org/apmem/tools/layouts/a.e:()I
      16: ireturn

  public int getOrientation();
    Code:
       0: aload_0
       1: getfield      #29                 // Field b:Lorg/apmem/tools/layouts/a;
       4: invokevirtual #38                 // Method org/apmem/tools/layouts/a.a:()I
       7: ireturn

  public float getWeightDefault();
    Code:
       0: aload_0
       1: getfield      #29                 // Field b:Lorg/apmem/tools/layouts/a;
       4: invokevirtual #222                // Method org/apmem/tools/layouts/a.c:()F
       7: freturn

  protected void onLayout(boolean, int, int, int, int);
    Code:
       0: aload_0
       1: invokevirtual #315                // Method getChildCount:()I
       4: istore_3
       5: iconst_0
       6: istore_2
       7: iload_2
       8: iload_3
       9: if_icmpge     97
      12: aload_0
      13: iload_2
      14: invokevirtual #319                // Method getChildAt:(I)Landroid/view/View;
      17: astore        6
      19: aload         6
      21: invokevirtual #76                 // Method android/view/View.getLayoutParams:()Landroid/view/ViewGroup$LayoutParams;
      24: checkcast     #6                  // class org/apmem/tools/layouts/FlowLayout$a
      27: astore        7
      29: aload         6
      31: aload         7
      33: invokestatic  #320                // Method org/apmem/tools/layouts/FlowLayout$a.a:(Lorg/apmem/tools/layouts/FlowLayout$a;)I
      36: aload         7
      38: getfield      #99                 // Field org/apmem/tools/layouts/FlowLayout$a.leftMargin:I
      41: iadd
      42: aload         7
      44: invokestatic  #322                // Method org/apmem/tools/layouts/FlowLayout$a.b:(Lorg/apmem/tools/layouts/FlowLayout$a;)I
      47: aload         7
      49: getfield      #114                // Field org/apmem/tools/layouts/FlowLayout$a.topMargin:I
      52: iadd
      53: aload         7
      55: invokestatic  #320                // Method org/apmem/tools/layouts/FlowLayout$a.a:(Lorg/apmem/tools/layouts/FlowLayout$a;)I
      58: aload         7
      60: getfield      #99                 // Field org/apmem/tools/layouts/FlowLayout$a.leftMargin:I
      63: iadd
      64: aload         6
      66: invokevirtual #325                // Method android/view/View.getMeasuredWidth:()I
      69: iadd
      70: aload         7
      72: invokestatic  #322                // Method org/apmem/tools/layouts/FlowLayout$a.b:(Lorg/apmem/tools/layouts/FlowLayout$a;)I
      75: aload         7
      77: getfield      #114                // Field org/apmem/tools/layouts/FlowLayout$a.topMargin:I
      80: iadd
      81: aload         6
      83: invokevirtual #328                // Method android/view/View.getMeasuredHeight:()I
      86: iadd
      87: invokevirtual #332                // Method android/view/View.layout:(IIII)V
      90: iload_2
      91: iconst_1
      92: iadd
      93: istore_2
      94: goto          7
      97: return

  protected void onMeasure(int, int);
    Code:
       0: iload_1
       1: invokestatic  #336                // Method android/view/View$MeasureSpec.getSize:(I)I
       4: aload_0
       5: invokevirtual #339                // Method getPaddingRight:()I
       8: isub
       9: aload_0
      10: invokevirtual #195                // Method getPaddingLeft:()I
      13: isub
      14: istore        4
      16: iload_2
      17: invokestatic  #336                // Method android/view/View$MeasureSpec.getSize:(I)I
      20: aload_0
      21: invokevirtual #199                // Method getPaddingTop:()I
      24: isub
      25: aload_0
      26: invokevirtual #342                // Method getPaddingBottom:()I
      29: isub
      30: istore        5
      32: iload_1
      33: invokestatic  #345                // Method android/view/View$MeasureSpec.getMode:(I)I
      36: istore        6
      38: iload_2
      39: invokestatic  #345                // Method android/view/View$MeasureSpec.getMode:(I)I
      42: istore        8
      44: aload_0
      45: getfield      #29                 // Field b:Lorg/apmem/tools/layouts/a;
      48: invokevirtual #38                 // Method org/apmem/tools/layouts/a.a:()I
      51: ifne          60
      54: iload         4
      56: istore_3
      57: goto          63
      60: iload         5
      62: istore_3
      63: aload_0
      64: getfield      #29                 // Field b:Lorg/apmem/tools/layouts/a;
      67: invokevirtual #38                 // Method org/apmem/tools/layouts/a.a:()I
      70: ifne          77
      73: iload         5
      75: istore        4
      77: aload_0
      78: getfield      #29                 // Field b:Lorg/apmem/tools/layouts/a;
      81: invokevirtual #38                 // Method org/apmem/tools/layouts/a.a:()I
      84: ifne          94
      87: iload         6
      89: istore        5
      91: goto          98
      94: iload         8
      96: istore        5
      98: aload_0
      99: getfield      #29                 // Field b:Lorg/apmem/tools/layouts/a;
     102: invokevirtual #38                 // Method org/apmem/tools/layouts/a.a:()I
     105: pop
     106: aload_0
     107: getfield      #22                 // Field a:Ljava/util/List;
     110: invokeinterface #348,  1          // InterfaceMethod java/util/List.clear:()V
     115: new           #130                // class org/apmem/tools/layouts/b
     118: dup
     119: iload_3
     120: invokespecial #350                // Method org/apmem/tools/layouts/b."<init>":(I)V
     123: astore        11
     125: aload_0
     126: getfield      #22                 // Field a:Ljava/util/List;
     129: aload         11
     131: invokeinterface #354,  2          // InterfaceMethod java/util/List.add:(Ljava/lang/Object;)Z
     136: pop
     137: aload_0
     138: invokevirtual #315                // Method getChildCount:()I
     141: istore        10
     143: iconst_0
     144: istore        9
     146: iconst_0
     147: istore        6
     149: iload         6
     151: iload         10
     153: if_icmpge     445
     156: aload_0
     157: iload         6
     159: invokevirtual #319                // Method getChildAt:(I)Landroid/view/View;
     162: astore        12
     164: aload         12
     166: invokevirtual #357                // Method android/view/View.getVisibility:()I
     169: bipush        8
     171: if_icmpne     177
     174: goto          436
     177: aload         12
     179: invokevirtual #76                 // Method android/view/View.getLayoutParams:()Landroid/view/ViewGroup$LayoutParams;
     182: checkcast     #6                  // class org/apmem/tools/layouts/FlowLayout$a
     185: astore        13
     187: aload         12
     189: iload_1
     190: aload_0
     191: invokevirtual #195                // Method getPaddingLeft:()I
     194: aload_0
     195: invokevirtual #339                // Method getPaddingRight:()I
     198: iadd
     199: aload         13
     201: getfield      #359                // Field org/apmem/tools/layouts/FlowLayout$a.width:I
     204: invokestatic  #362                // Method getChildMeasureSpec:(III)I
     207: iload_2
     208: aload_0
     209: invokevirtual #199                // Method getPaddingTop:()I
     212: aload_0
     213: invokevirtual #342                // Method getPaddingBottom:()I
     216: iadd
     217: aload         13
     219: getfield      #364                // Field org/apmem/tools/layouts/FlowLayout$a.height:I
     222: invokestatic  #362                // Method getChildMeasureSpec:(III)I
     225: invokevirtual #214                // Method android/view/View.measure:(II)V
     228: aload         13
     230: aload_0
     231: getfield      #29                 // Field b:Lorg/apmem/tools/layouts/a;
     234: invokevirtual #38                 // Method org/apmem/tools/layouts/a.a:()I
     237: invokestatic  #367                // Method org/apmem/tools/layouts/FlowLayout$a.a:(Lorg/apmem/tools/layouts/FlowLayout$a;I)I
     240: pop
     241: aload_0
     242: getfield      #29                 // Field b:Lorg/apmem/tools/layouts/a;
     245: invokevirtual #38                 // Method org/apmem/tools/layouts/a.a:()I
     248: ifne          278
     251: aload         13
     253: aload         12
     255: invokevirtual #325                // Method android/view/View.getMeasuredWidth:()I
     258: invokevirtual #243                // Method org/apmem/tools/layouts/FlowLayout$a.b:(I)V
     261: aload         12
     263: invokevirtual #328                // Method android/view/View.getMeasuredHeight:()I
     266: istore        7
     268: aload         13
     270: iload         7
     272: invokevirtual #244                // Method org/apmem/tools/layouts/FlowLayout$a.c:(I)V
     275: goto          298
     278: aload         13
     280: aload         12
     282: invokevirtual #328                // Method android/view/View.getMeasuredHeight:()I
     285: invokevirtual #243                // Method org/apmem/tools/layouts/FlowLayout$a.b:(I)V
     288: aload         12
     290: invokevirtual #325                // Method android/view/View.getMeasuredWidth:()I
     293: istore        7
     295: goto          268
     298: aload         13
     300: invokevirtual #117                // Method org/apmem/tools/layouts/FlowLayout$a.k:()Z
     303: ifne          330
     306: iload         5
     308: ifeq          324
     311: aload         11
     313: aload         12
     315: invokevirtual #370                // Method org/apmem/tools/layouts/b.b:(Landroid/view/View;)Z
     318: ifne          324
     321: goto          330
     324: iconst_0
     325: istore        7
     327: goto          333
     330: iconst_1
     331: istore        7
     333: iload         7
     335: ifeq          397
     338: new           #130                // class org/apmem/tools/layouts/b
     341: dup
     342: iload_3
     343: invokespecial #350                // Method org/apmem/tools/layouts/b."<init>":(I)V
     346: astore        11
     348: aload_0
     349: getfield      #29                 // Field b:Lorg/apmem/tools/layouts/a;
     352: invokevirtual #38                 // Method org/apmem/tools/layouts/a.a:()I
     355: iconst_1
     356: if_icmpne     385
     359: aload_0
     360: getfield      #29                 // Field b:Lorg/apmem/tools/layouts/a;
     363: invokevirtual #42                 // Method org/apmem/tools/layouts/a.e:()I
     366: iconst_1
     367: if_icmpne     385
     370: aload_0
     371: getfield      #22                 // Field a:Ljava/util/List;
     374: iconst_0
     375: aload         11
     377: invokeinterface #373,  3          // InterfaceMethod java/util/List.add:(ILjava/lang/Object;)V
     382: goto          397
     385: aload_0
     386: getfield      #22                 // Field a:Ljava/util/List;
     389: aload         11
     391: invokeinterface #354,  2          // InterfaceMethod java/util/List.add:(Ljava/lang/Object;)Z
     396: pop
     397: aload_0
     398: getfield      #29                 // Field b:Lorg/apmem/tools/layouts/a;
     401: invokevirtual #38                 // Method org/apmem/tools/layouts/a.a:()I
     404: ifne          429
     407: aload_0
     408: getfield      #29                 // Field b:Lorg/apmem/tools/layouts/a;
     411: invokevirtual #42                 // Method org/apmem/tools/layouts/a.e:()I
     414: iconst_1
     415: if_icmpne     429
     418: aload         11
     420: iconst_0
     421: aload         12
     423: invokevirtual #376                // Method org/apmem/tools/layouts/b.a:(ILandroid/view/View;)V
     426: goto          436
     429: aload         11
     431: aload         12
     433: invokevirtual #379                // Method org/apmem/tools/layouts/b.a:(Landroid/view/View;)V
     436: iload         6
     438: iconst_1
     439: iadd
     440: istore        6
     442: goto          149
     445: aload_0
     446: aload_0
     447: getfield      #22                 // Field a:Ljava/util/List;
     450: invokespecial #381                // Method a:(Ljava/util/List;)V
     453: aload_0
     454: getfield      #22                 // Field a:Ljava/util/List;
     457: invokeinterface #124,  1          // InterfaceMethod java/util/List.size:()I
     462: istore        10
     464: iconst_0
     465: istore        7
     467: iconst_0
     468: istore        6
     470: iload         7
     472: iload         10
     474: if_icmpge     510
     477: iload         6
     479: aload_0
     480: getfield      #22                 // Field a:Ljava/util/List;
     483: iload         7
     485: invokeinterface #128,  2          // InterfaceMethod java/util/List.get:(I)Ljava/lang/Object;
     490: checkcast     #130                // class org/apmem/tools/layouts/b
     493: invokevirtual #156                // Method org/apmem/tools/layouts/b.c:()I
     496: invokestatic  #384                // Method java/lang/Math.max:(II)I
     499: istore        6
     501: iload         7
     503: iconst_1
     504: iadd
     505: istore        7
     507: goto          470
     510: aload         11
     512: invokevirtual #147                // Method org/apmem/tools/layouts/b.a:()I
     515: aload         11
     517: invokevirtual #135                // Method org/apmem/tools/layouts/b.b:()I
     520: iadd
     521: istore        7
     523: aload_0
     524: iload         5
     526: iload_3
     527: iload         6
     529: invokespecial #386                // Method a:(III)I
     532: istore_3
     533: aload_0
     534: iload         8
     536: iload         4
     538: iload         7
     540: invokespecial #386                // Method a:(III)I
     543: istore        4
     545: aload_0
     546: aload_0
     547: getfield      #22                 // Field a:Ljava/util/List;
     550: iload_3
     551: iload         4
     553: invokespecial #388                // Method a:(Ljava/util/List;II)V
     556: iload         9
     558: istore_3
     559: iload_3
     560: iload         10
     562: if_icmpge     599
     565: aload_0
     566: getfield      #22                 // Field a:Ljava/util/List;
     569: iload_3
     570: invokeinterface #128,  2          // InterfaceMethod java/util/List.get:(I)Ljava/lang/Object;
     575: checkcast     #130                // class org/apmem/tools/layouts/b
     578: astore        11
     580: aload_0
     581: aload         11
     583: invokespecial #390                // Method b:(Lorg/apmem/tools/layouts/b;)V
     586: aload_0
     587: aload         11
     589: invokespecial #392                // Method a:(Lorg/apmem/tools/layouts/b;)V
     592: iload_3
     593: iconst_1
     594: iadd
     595: istore_3
     596: goto          559
     599: aload_0
     600: invokevirtual #195                // Method getPaddingLeft:()I
     603: aload_0
     604: invokevirtual #339                // Method getPaddingRight:()I
     607: iadd
     608: istore_3
     609: aload_0
     610: invokevirtual #342                // Method getPaddingBottom:()I
     613: aload_0
     614: invokevirtual #199                // Method getPaddingTop:()I
     617: iadd
     618: istore        4
     620: aload_0
     621: getfield      #29                 // Field b:Lorg/apmem/tools/layouts/a;
     624: invokevirtual #38                 // Method org/apmem/tools/layouts/a.a:()I
     627: ifne          645
     630: iload_3
     631: iload         6
     633: iadd
     634: istore_3
     635: iload         4
     637: iload         7
     639: iadd
     640: istore        4
     642: goto          657
     645: iload_3
     646: iload         7
     648: iadd
     649: istore_3
     650: iload         4
     652: iload         6
     654: iadd
     655: istore        4
     657: aload_0
     658: iload_3
     659: iload_1
     660: invokestatic  #395                // Method resolveSize:(II)I
     663: iload         4
     665: iload_2
     666: invokestatic  #395                // Method resolveSize:(II)I
     669: invokevirtual #398                // Method setMeasuredDimension:(II)V
     672: return

  public void setDebugDraw(boolean);
    Code:
       0: aload_0
       1: getfield      #29                 // Field b:Lorg/apmem/tools/layouts/a;
       4: iload_1
       5: invokevirtual #401                // Method org/apmem/tools/layouts/a.a:(Z)V
       8: aload_0
       9: invokevirtual #404                // Method invalidate:()V
      12: return

  public void setGravity(int);
    Code:
       0: aload_0
       1: getfield      #29                 // Field b:Lorg/apmem/tools/layouts/a;
       4: iload_1
       5: invokevirtual #406                // Method org/apmem/tools/layouts/a.b:(I)V
       8: aload_0
       9: invokevirtual #409                // Method requestLayout:()V
      12: return

  public void setLayoutDirection(int);
    Code:
       0: aload_0
       1: getfield      #29                 // Field b:Lorg/apmem/tools/layouts/a;
       4: iload_1
       5: invokevirtual #411                // Method org/apmem/tools/layouts/a.c:(I)V
       8: aload_0
       9: invokevirtual #409                // Method requestLayout:()V
      12: return

  public void setOrientation(int);
    Code:
       0: aload_0
       1: getfield      #29                 // Field b:Lorg/apmem/tools/layouts/a;
       4: iload_1
       5: invokevirtual #413                // Method org/apmem/tools/layouts/a.a:(I)V
       8: aload_0
       9: invokevirtual #409                // Method requestLayout:()V
      12: return

  public void setWeightDefault(float);
    Code:
       0: aload_0
       1: getfield      #29                 // Field b:Lorg/apmem/tools/layouts/a;
       4: fload_1
       5: invokevirtual #416                // Method org/apmem/tools/layouts/a.a:(F)V
       8: aload_0
       9: invokevirtual #409                // Method requestLayout:()V
      12: return
}
