public class ryey.easer.plugins.operation.f.b extends ryey.easer.plugins.operation.d {
  public static final android.os.Parcelable$Creator<ryey.easer.plugins.operation.f.b> CREATOR;

  static {};
    Code:
       0: new           #6                  // class ryey/easer/plugins/operation/f/b$1
       3: dup
       4: invokespecial #14                 // Method ryey/easer/plugins/operation/f/b$1."<init>":()V
       7: putstatic     #16                 // Field CREATOR:Landroid/os/Parcelable$Creator;
      10: return

  ryey.easer.plugins.operation.f.b(android.os.Parcel, ryey.easer.plugins.operation.f.b$1);
    Code:
       0: aload_0
       1: aload_1
       2: invokespecial #22                 // Method "<init>":(Landroid/os/Parcel;)V
       5: return

  ryey.easer.plugins.operation.f.b(java.lang.String);
    Code:
       0: aload_0
       1: aload_1
       2: invokespecial #25                 // Method ryey/easer/plugins/operation/d."<init>":(Ljava/lang/String;)V
       5: return

  ryey.easer.plugins.operation.f.b(java.lang.String, ryey.easer.b.a, int);
    Code:
       0: aload_0
       1: aload_1
       2: aload_2
       3: iload_3
       4: invokespecial #28                 // Method ryey/easer/plugins/operation/d."<init>":(Ljava/lang/String;Lryey/easer/b/a;I)V
       7: return

  public ryey.easer.commons.local_plugin.c.b a(ryey.easer.commons.local_plugin.b.c);
    Code:
       0: new           #2                  // class ryey/easer/plugins/operation/f/b
       3: dup
       4: aload_0
       5: getfield      #33                 // Field a:Ljava/lang/String;
       8: aload_1
       9: invokestatic  #38                 // Method ryey/easer/b.a:(Ljava/lang/String;Lryey/easer/commons/local_plugin/b/c;)Ljava/lang/String;
      12: invokespecial #39                 // Method "<init>":(Ljava/lang/String;)V
      15: areturn
}
