class ryey.easer.plugins.a.c.e$1 extends android.content.BroadcastReceiver {
  final ryey.easer.plugins.a.c.e a;

  ryey.easer.plugins.a.c.e$1(ryey.easer.plugins.a.c.e);
    Code:
       0: aload_0
       1: aload_1
       2: putfield      #12                 // Field a:Lryey/easer/plugins/a/c/e;
       5: aload_0
       6: invokespecial #15                 // Method android/content/BroadcastReceiver."<init>":()V
       9: return

  public void onReceive(android.content.Context, android.content.Intent);
    Code:
       0: ldc           #20                 // String android.bluetooth.adapter.action.STATE_CHANGED
       2: aload_2
       3: invokevirtual #26                 // Method android/content/Intent.getAction:()Ljava/lang/String;
       6: invokevirtual #32                 // Method java/lang/String.equals:(Ljava/lang/Object;)Z
       9: ifeq          90
      12: aload_2
      13: ldc           #34                 // String android.bluetooth.adapter.extra.STATE
      15: iconst_m1
      16: invokevirtual #38                 // Method android/content/Intent.getIntExtra:(Ljava/lang/String;I)I
      19: istore_3
      20: iload_3
      21: bipush        10
      23: if_icmpeq     65
      26: iload_3
      27: bipush        12
      29: if_icmpeq     41
      32: aload_0
      33: getfield      #12                 // Field a:Lryey/easer/plugins/a/c/e;
      36: aconst_null
      37: invokestatic  #42                 // Method ryey/easer/plugins/a/c/e.c:(Lryey/easer/plugins/a/c/e;Ljava/lang/Boolean;)V
      40: return
      41: aload_0
      42: getfield      #12                 // Field a:Lryey/easer/plugins/a/c/e;
      45: aload_0
      46: getfield      #12                 // Field a:Lryey/easer/plugins/a/c/e;
      49: invokestatic  #45                 // Method ryey/easer/plugins/a/c/e.a:(Lryey/easer/plugins/a/c/e;)Lryey/easer/commons/local_plugin/a/a;
      52: checkcast     #47                 // class ryey/easer/plugins/a/c/a
      55: getfield      #50                 // Field ryey/easer/plugins/a/c/a.a:Z
      58: invokestatic  #56                 // Method java/lang/Boolean.valueOf:(Z)Ljava/lang/Boolean;
      61: invokestatic  #58                 // Method ryey/easer/plugins/a/c/e.a:(Lryey/easer/plugins/a/c/e;Ljava/lang/Boolean;)V
      64: return
      65: aload_0
      66: getfield      #12                 // Field a:Lryey/easer/plugins/a/c/e;
      69: aload_0
      70: getfield      #12                 // Field a:Lryey/easer/plugins/a/c/e;
      73: invokestatic  #61                 // Method ryey/easer/plugins/a/c/e.b:(Lryey/easer/plugins/a/c/e;)Lryey/easer/commons/local_plugin/a/a;
      76: checkcast     #47                 // class ryey/easer/plugins/a/c/a
      79: getfield      #50                 // Field ryey/easer/plugins/a/c/a.a:Z
      82: iconst_1
      83: ixor
      84: invokestatic  #56                 // Method java/lang/Boolean.valueOf:(Z)Ljava/lang/Boolean;
      87: invokestatic  #63                 // Method ryey/easer/plugins/a/c/e.b:(Lryey/easer/plugins/a/c/e;Ljava/lang/Boolean;)V
      90: return
}
