public class ryey.easer.plugins.operation.e.a extends ryey.easer.plugins.operation.c<ryey.easer.plugins.operation.e.b> {
  public ryey.easer.plugins.operation.e.a(android.content.Context);
    Code:
       0: aload_0
       1: aload_1
       2: invokespecial #9                  // Method ryey/easer/plugins/operation/c."<init>":(Landroid/content/Context;)V
       5: return

  public boolean a(ryey.easer.commons.local_plugin.c.b);
    Code:
       0: aload_0
       1: aload_1
       2: checkcast     #14                 // class ryey/easer/plugins/operation/e/b
       5: invokevirtual #17                 // Method a:(Lryey/easer/plugins/operation/e/b;)Z
       8: ireturn

  public boolean a(ryey.easer.plugins.operation.e.b);
    Code:
       0: aload_1
       1: invokevirtual #31                 // Method ryey/easer/plugins/operation/e/b.c:()Ljava/lang/Boolean;
       4: astore_1
       5: aload_0
       6: getfield      #34                 // Field a:Landroid/content/Context;
       9: ldc           #36                 // String phone
      11: invokevirtual #42                 // Method android/content/Context.getSystemService:(Ljava/lang/String;)Ljava/lang/Object;
      14: checkcast     #44                 // class android/telephony/TelephonyManager
      17: astore        4
      19: aload_1
      20: invokevirtual #50                 // Method java/lang/Boolean.booleanValue:()Z
      23: istore_3
      24: aload         4
      26: invokevirtual #54                 // Method android/telephony/TelephonyManager.getDataState:()I
      29: iconst_2
      30: if_icmpne     38
      33: iconst_1
      34: istore_2
      35: goto          40
      38: iconst_0
      39: istore_2
      40: iload_3
      41: iload_2
      42: if_icmpne     47
      45: iconst_1
      46: ireturn
      47: aload_0
      48: getfield      #34                 // Field a:Landroid/content/Context;
      51: invokestatic  #59                 // Method ryey/easer/plugins/b/d.a:(Landroid/content/Context;)Z
      54: ifeq          118
      57: new           #61                 // class java/lang/StringBuilder
      60: dup
      61: invokespecial #64                 // Method java/lang/StringBuilder."<init>":()V
      64: astore        4
      66: aload         4
      68: ldc           #66                 // String svc data
      70: invokevirtual #70                 // Method java/lang/StringBuilder.append:(Ljava/lang/String;)Ljava/lang/StringBuilder;
      73: pop
      74: aload_1
      75: invokevirtual #50                 // Method java/lang/Boolean.booleanValue:()Z
      78: ifeq          246
      81: ldc           #72                 // String enable
      83: astore_1
      84: goto          87
      87: aload         4
      89: aload_1
      90: invokevirtual #70                 // Method java/lang/StringBuilder.append:(Ljava/lang/String;)Ljava/lang/StringBuilder;
      93: pop
      94: aload         4
      96: invokevirtual #76                 // Method java/lang/StringBuilder.toString:()Ljava/lang/String;
      99: astore_1
     100: aload_0
     101: getfield      #34                 // Field a:Landroid/content/Context;
     104: aload_1
     105: invokestatic  #79                 // Method ryey/easer/plugins/b/d.a:(Landroid/content/Context;Ljava/lang/String;)Ljava/lang/Process;
     108: pop
     109: iconst_1
     110: ireturn
     111: astore_1
     112: aload_1
     113: invokestatic  #84                 // Method com/google/a/a/a/a/a/a.a:(Ljava/lang/Throwable;)V
     116: iconst_0
     117: ireturn
     118: aload         4
     120: invokevirtual #90                 // Method java/lang/Object.getClass:()Ljava/lang/Class;
     123: invokevirtual #95                 // Method java/lang/Class.getName:()Ljava/lang/String;
     126: invokestatic  #99                 // Method java/lang/Class.forName:(Ljava/lang/String;)Ljava/lang/Class;
     129: ldc           #101                // String getITelephony
     131: iconst_0
     132: anewarray     #92                 // class java/lang/Class
     135: invokevirtual #105                // Method java/lang/Class.getDeclaredMethod:(Ljava/lang/String;[Ljava/lang/Class;)Ljava/lang/reflect/Method;
     138: astore        5
     140: aload         5
     142: iconst_1
     143: invokevirtual #111                // Method java/lang/reflect/Method.setAccessible:(Z)V
     146: aload         5
     148: aload         4
     150: iconst_0
     151: anewarray     #86                 // class java/lang/Object
     154: invokevirtual #115                // Method java/lang/reflect/Method.invoke:(Ljava/lang/Object;[Ljava/lang/Object;)Ljava/lang/Object;
     157: astore        5
     159: aload         5
     161: invokevirtual #90                 // Method java/lang/Object.getClass:()Ljava/lang/Class;
     164: invokevirtual #95                 // Method java/lang/Class.getName:()Ljava/lang/String;
     167: invokestatic  #99                 // Method java/lang/Class.forName:(Ljava/lang/String;)Ljava/lang/Class;
     170: astore        6
     172: aload_1
     173: invokevirtual #50                 // Method java/lang/Boolean.booleanValue:()Z
     176: ifeq          200
     179: ldc           #117                // String enableDataConnectivity
     181: astore        4
     183: iconst_0
     184: anewarray     #92                 // class java/lang/Class
     187: astore_1
     188: aload         6
     190: aload         4
     192: aload_1
     193: invokevirtual #105                // Method java/lang/Class.getDeclaredMethod:(Ljava/lang/String;[Ljava/lang/Class;)Ljava/lang/reflect/Method;
     196: astore_1
     197: goto          212
     200: ldc           #119                // String disableDataConnectivity
     202: astore        4
     204: iconst_0
     205: anewarray     #92                 // class java/lang/Class
     208: astore_1
     209: goto          188
     212: aload_1
     213: iconst_1
     214: invokevirtual #111                // Method java/lang/reflect/Method.setAccessible:(Z)V
     217: aload_1
     218: aload         5
     220: iconst_0
     221: anewarray     #86                 // class java/lang/Object
     224: invokevirtual #115                // Method java/lang/reflect/Method.invoke:(Ljava/lang/Object;[Ljava/lang/Object;)Ljava/lang/Object;
     227: pop
     228: iconst_1
     229: ireturn
     230: astore_1
     231: aload_1
     232: aconst_null
     233: iconst_0
     234: anewarray     #86                 // class java/lang/Object
     237: invokestatic  #124                // Method com/b/a/i.a:(Ljava/lang/Throwable;Ljava/lang/String;[Ljava/lang/Object;)V
     240: aload_1
     241: invokestatic  #84                 // Method com/google/a/a/a/a/a/a.a:(Ljava/lang/Throwable;)V
     244: iconst_0
     245: ireturn
     246: ldc           #126                // String disable
     248: astore_1
     249: goto          87
    Exception table:
       from    to  target type
          57    81   111   Class java/io/IOException
          87   109   111   Class java/io/IOException
         118   179   230   Class java/lang/ClassNotFoundException
         118   179   230   Class java/lang/reflect/InvocationTargetException
         118   179   230   Class java/lang/NoSuchMethodException
         118   179   230   Class java/lang/IllegalAccessException
         183   188   230   Class java/lang/ClassNotFoundException
         183   188   230   Class java/lang/reflect/InvocationTargetException
         183   188   230   Class java/lang/NoSuchMethodException
         183   188   230   Class java/lang/IllegalAccessException
         188   197   230   Class java/lang/ClassNotFoundException
         188   197   230   Class java/lang/reflect/InvocationTargetException
         188   197   230   Class java/lang/NoSuchMethodException
         188   197   230   Class java/lang/IllegalAccessException
         204   209   230   Class java/lang/ClassNotFoundException
         204   209   230   Class java/lang/reflect/InvocationTargetException
         204   209   230   Class java/lang/NoSuchMethodException
         204   209   230   Class java/lang/IllegalAccessException
         212   228   230   Class java/lang/ClassNotFoundException
         212   228   230   Class java/lang/reflect/InvocationTargetException
         212   228   230   Class java/lang/NoSuchMethodException
         212   228   230   Class java/lang/IllegalAccessException
}
