class ryey.easer.core.a$a$a {
  public final java.lang.String a;

  public final java.lang.String b;

  public final android.os.Bundle c;

  public final ryey.easer.commons.local_plugin.b.b d;

  public ryey.easer.core.a$a$a(java.lang.String, java.lang.String, android.os.Bundle, ryey.easer.commons.local_plugin.b.b);
    Code:
       0: aload_0
       1: invokespecial #20                 // Method java/lang/Object."<init>":()V
       4: aload_0
       5: aload_1
       6: putfield      #22                 // Field a:Ljava/lang/String;
       9: aload_0
      10: aload_2
      11: putfield      #24                 // Field b:Ljava/lang/String;
      14: aload_0
      15: aload_3
      16: putfield      #26                 // Field c:Landroid/os/Bundle;
      19: aload_0
      20: aload         4
      22: putfield      #28                 // Field d:Lryey/easer/commons/local_plugin/b/b;
      25: return
}
