public class ryey.easer.core.a$a {
  public ryey.easer.core.a$a();
    Code:
       0: aload_0
       1: invokespecial #19                 // Method java/lang/Object."<init>":()V
       4: aload_0
       5: new           #21                 // class java/util/concurrent/locks/ReentrantLock
       8: dup
       9: invokespecial #22                 // Method java/util/concurrent/locks/ReentrantLock."<init>":()V
      12: putfield      #24                 // Field a:Ljava/util/concurrent/locks/Lock;
      15: aload_0
      16: new           #26                 // class java/util/ArrayList
      19: dup
      20: invokespecial #27                 // Method java/util/ArrayList."<init>":()V
      23: putfield      #29                 // Field c:Ljava/util/List;
      26: return

  public void a();
    Code:
       0: aload_0
       1: getfield      #24                 // Field a:Ljava/util/concurrent/locks/Lock;
       4: invokeinterface #57,  1           // InterfaceMethod java/util/concurrent/locks/Lock.lock:()V
       9: aload_0
      10: aconst_null
      11: putfield      #59                 // Field b:Lryey/easer/core/ProfileLoaderService$a;
      14: aload_0
      15: getfield      #24                 // Field a:Ljava/util/concurrent/locks/Lock;
      18: invokeinterface #70,  1           // InterfaceMethod java/util/concurrent/locks/Lock.unlock:()V
      23: return
      24: astore_1
      25: aload_0
      26: getfield      #24                 // Field a:Ljava/util/concurrent/locks/Lock;
      29: invokeinterface #70,  1           // InterfaceMethod java/util/concurrent/locks/Lock.unlock:()V
      34: aload_1
      35: athrow
    Exception table:
       from    to  target type
           9    14    24   any

  public void a(java.lang.String);
    Code:
       0: aload_0
       1: new           #9                  // class ryey/easer/core/a$a$a
       4: dup
       5: aload_1
       6: aconst_null
       7: aconst_null
       8: aconst_null
       9: invokespecial #72                 // Method ryey/easer/core/a$a$a."<init>":(Ljava/lang/String;Ljava/lang/String;Landroid/os/Bundle;Lryey/easer/commons/local_plugin/b/b;)V
      12: invokespecial #74                 // Method a:(Lryey/easer/core/a$a$a;)V
      15: return

  public void a(java.lang.String, java.lang.String, android.os.Bundle, ryey.easer.commons.local_plugin.b.b);
    Code:
       0: aload_0
       1: new           #9                  // class ryey/easer/core/a$a$a
       4: dup
       5: aload_1
       6: aload_2
       7: aload_3
       8: aload         4
      10: invokespecial #72                 // Method ryey/easer/core/a$a$a."<init>":(Ljava/lang/String;Ljava/lang/String;Landroid/os/Bundle;Lryey/easer/commons/local_plugin/b/b;)V
      13: invokespecial #74                 // Method a:(Lryey/easer/core/a$a$a;)V
      16: return

  public void a(ryey.easer.core.ProfileLoaderService$a);
    Code:
       0: aload_0
       1: getfield      #24                 // Field a:Ljava/util/concurrent/locks/Lock;
       4: invokeinterface #57,  1           // InterfaceMethod java/util/concurrent/locks/Lock.lock:()V
       9: aload_0
      10: aload_1
      11: putfield      #59                 // Field b:Lryey/easer/core/ProfileLoaderService$a;
      14: aload_0
      15: getfield      #29                 // Field c:Ljava/util/List;
      18: invokeinterface #79,  1           // InterfaceMethod java/util/List.size:()I
      23: iconst_1
      24: isub
      25: istore_2
      26: iload_2
      27: iflt          65
      30: aload_1
      31: aload_0
      32: getfield      #29                 // Field c:Ljava/util/List;
      35: iload_2
      36: invokeinterface #83,  2           // InterfaceMethod java/util/List.get:(I)Ljava/lang/Object;
      41: checkcast     #9                  // class ryey/easer/core/a$a$a
      44: invokestatic  #61                 // Method a:(Lryey/easer/core/ProfileLoaderService$a;Lryey/easer/core/a$a$a;)V
      47: aload_0
      48: getfield      #29                 // Field c:Ljava/util/List;
      51: iload_2
      52: invokeinterface #86,  2           // InterfaceMethod java/util/List.remove:(I)Ljava/lang/Object;
      57: pop
      58: iload_2
      59: iconst_1
      60: isub
      61: istore_2
      62: goto          26
      65: aload_0
      66: getfield      #24                 // Field a:Ljava/util/concurrent/locks/Lock;
      69: invokeinterface #70,  1           // InterfaceMethod java/util/concurrent/locks/Lock.unlock:()V
      74: return
      75: astore_1
      76: aload_0
      77: getfield      #24                 // Field a:Ljava/util/concurrent/locks/Lock;
      80: invokeinterface #70,  1           // InterfaceMethod java/util/concurrent/locks/Lock.unlock:()V
      85: aload_1
      86: athrow
    Exception table:
       from    to  target type
           9    26    75   any
          30    58    75   any
}
