class ryey.easer.core.c extends ryey.easer.core.d {
  ryey.easer.core.c(android.content.Context, ryey.easer.core.a.k, java.util.concurrent.ExecutorService, ryey.easer.core.ConditionHolderService$a, ryey.easer.core.a$a);
    Code:
       0: aload_0
       1: aload_1
       2: aload_2
       3: aload_3
       4: aload         4
       6: aload         5
       8: invokespecial #21                 // Method ryey/easer/core/d."<init>":(Landroid/content/Context;Lryey/easer/core/a/k;Ljava/util/concurrent/ExecutorService;Lryey/easer/core/ConditionHolderService$a;Lryey/easer/core/a$a;)V
      11: aload_0
      12: aload_2
      13: invokevirtual #27                 // Method ryey/easer/core/a/k.f:()Z
      16: putfield      #29                 // Field l:Z
      19: aload_0
      20: aload_2
      21: invokevirtual #32                 // Method ryey/easer/core/a/k.g:()Z
      24: putfield      #34                 // Field m:Z
      27: aload_0
      28: aload_0
      29: aload_2
      30: invokespecial #38                 // Method a:(Lryey/easer/core/a/k;)Lryey/easer/commons/local_plugin/eventplugin/c;
      33: putfield      #40                 // Field i:Lryey/easer/commons/local_plugin/eventplugin/c;
      36: aload_0
      37: getfield      #40                 // Field i:Lryey/easer/commons/local_plugin/eventplugin/c;
      40: aload_0
      41: getfield      #44                 // Field h:Landroid/net/Uri;
      44: invokeinterface #49,  2           // InterfaceMethod ryey/easer/commons/local_plugin/eventplugin/c.a:(Landroid/net/Uri;)V
      49: aload_0
      50: aload_1
      51: invokestatic  #54                 // Method ryey/easer/a.a:(Landroid/content/Context;)I
      54: sipush        1000
      57: imul
      58: i2l
      59: putfield      #56                 // Field j:J
      62: return

  static ryey.easer.commons.local_plugin.eventplugin.c a(ryey.easer.core.c);
    Code:
       0: aload_0
       1: getfield      #40                 // Field i:Lryey/easer/commons/local_plugin/eventplugin/c;
       4: areturn

  protected void a();
    Code:
       0: aload_0
       1: monitorenter
       2: aload_0
       3: getfield      #125                // Field c:Ljava/util/concurrent/ExecutorService;
       6: new           #6                  // class ryey/easer/core/c$1
       9: dup
      10: aload_0
      11: invokespecial #128                // Method ryey/easer/core/c$1."<init>":(Lryey/easer/core/c;)V
      14: invokeinterface #134,  2          // InterfaceMethod java/util/concurrent/ExecutorService.submit:(Ljava/lang/Runnable;)Ljava/util/concurrent/Future;
      19: pop
      20: aload_0
      21: monitorexit
      22: return
      23: astore_1
      24: aload_0
      25: monitorexit
      26: aload_1
      27: athrow
    Exception table:
       from    to  target type
           2    20    23   any

  protected void a(android.os.Bundle);
    Code:
       0: aload_0
       1: monitorenter
       2: aload_0
       3: getfield      #29                 // Field l:Z
       6: ifne          21
       9: aload_0
      10: getfield      #137                // Field g:Z
      13: istore_2
      14: iload_2
      15: ifeq          21
      18: aload_0
      19: monitorexit
      20: return
      21: aload_0
      22: aload_0
      23: getfield      #140                // Field b:Lryey/easer/core/a/k;
      26: invokevirtual #143                // Method ryey/easer/core/a/k.a:()Ljava/lang/String;
      29: invokespecial #145                // Method a:(Ljava/lang/String;)Z
      32: ifeq          40
      35: aload_0
      36: aload_1
      37: invokespecial #147                // Method ryey/easer/core/d.a:(Landroid/os/Bundle;)V
      40: aload_0
      41: monitorexit
      42: return
      43: astore_1
      44: aload_0
      45: monitorexit
      46: aload_1
      47: athrow
    Exception table:
       from    to  target type
           2    14    43   any
          21    40    43   any

  protected void b();
    Code:
       0: aload_0
       1: monitorenter
       2: aload_0
       3: getfield      #125                // Field c:Ljava/util/concurrent/ExecutorService;
       6: new           #8                  // class ryey/easer/core/c$2
       9: dup
      10: aload_0
      11: invokespecial #148                // Method ryey/easer/core/c$2."<init>":(Lryey/easer/core/c;)V
      14: invokeinterface #134,  2          // InterfaceMethod java/util/concurrent/ExecutorService.submit:(Ljava/lang/Runnable;)Ljava/util/concurrent/Future;
      19: pop
      20: aload_0
      21: monitorexit
      22: return
      23: astore_1
      24: aload_0
      25: monitorexit
      26: aload_1
      27: athrow
    Exception table:
       from    to  target type
           2    20    23   any

  protected void c();
    Code:
       0: aload_0
       1: monitorenter
       2: aload_0
       3: getfield      #34                 // Field m:Z
       6: ifeq          21
       9: aload_0
      10: getfield      #137                // Field g:Z
      13: istore_1
      14: iload_1
      15: ifeq          21
      18: aload_0
      19: monitorexit
      20: return
      21: aload_0
      22: aload_0
      23: getfield      #140                // Field b:Lryey/easer/core/a/k;
      26: invokevirtual #143                // Method ryey/easer/core/a/k.a:()Ljava/lang/String;
      29: invokespecial #145                // Method a:(Ljava/lang/String;)Z
      32: ifeq          39
      35: aload_0
      36: invokespecial #150                // Method ryey/easer/core/d.c:()V
      39: aload_0
      40: monitorexit
      41: return
      42: astore_2
      43: aload_0
      44: monitorexit
      45: aload_2
      46: athrow
    Exception table:
       from    to  target type
           2    14    42   any
          21    39    42   any
}
