public class ryey.easer.core.ConditionHolderService extends android.app.Service {
  public ryey.easer.core.ConditionHolderService();
    Code:
       0: aload_0
       1: invokespecial #23                 // Method android/app/Service."<init>":()V
       4: aload_0
       5: new           #25                 // class java/util/HashMap
       8: dup
       9: invokespecial #26                 // Method java/util/HashMap."<init>":()V
      12: putfield      #28                 // Field a:Ljava/util/Map;
      15: aload_0
      16: new           #25                 // class java/util/HashMap
      19: dup
      20: invokespecial #26                 // Method java/util/HashMap."<init>":()V
      23: putfield      #30                 // Field b:Ljava/util/Map;
      26: aload_0
      27: getstatic     #36                 // Field java/util/Locale.US:Ljava/util/Locale;
      30: ldc           #38                 // String conditionholder://%d/
      32: iconst_1
      33: anewarray     #40                 // class java/lang/Object
      36: dup
      37: iconst_0
      38: aload_0
      39: invokevirtual #44                 // Method java/lang/Object.hashCode:()I
      42: invokestatic  #50                 // Method java/lang/Integer.valueOf:(I)Ljava/lang/Integer;
      45: aastore
      46: invokestatic  #56                 // Method java/lang/String.format:(Ljava/util/Locale;Ljava/lang/String;[Ljava/lang/Object;)Ljava/lang/String;
      49: invokestatic  #62                 // Method android/net/Uri.parse:(Ljava/lang/String;)Landroid/net/Uri;
      52: putfield      #64                 // Field c:Landroid/net/Uri;
      55: aload_0
      56: new           #6                  // class ryey/easer/core/ConditionHolderService$1
      59: dup
      60: aload_0
      61: invokespecial #67                 // Method ryey/easer/core/ConditionHolderService$1."<init>":(Lryey/easer/core/ConditionHolderService;)V
      64: putfield      #69                 // Field d:Landroid/content/BroadcastReceiver;
      67: aload_0
      68: new           #71                 // class android/content/IntentFilter
      71: dup
      72: invokespecial #72                 // Method android/content/IntentFilter."<init>":()V
      75: putfield      #74                 // Field e:Landroid/content/IntentFilter;
      78: aload_0
      79: getfield      #74                 // Field e:Landroid/content/IntentFilter;
      82: ldc           #76                 // String ryey.easer.triggerlotus.action.TRACKER_SATISFIED
      84: invokevirtual #80                 // Method android/content/IntentFilter.addAction:(Ljava/lang/String;)V
      87: aload_0
      88: getfield      #74                 // Field e:Landroid/content/IntentFilter;
      91: ldc           #82                 // String ryey.easer.triggerlotus.action.TRACKER_UNSATISFIED
      93: invokevirtual #80                 // Method android/content/IntentFilter.addAction:(Ljava/lang/String;)V
      96: aload_0
      97: getfield      #74                 // Field e:Landroid/content/IntentFilter;
     100: ldc           #84                 // String ryey.easer.triggerlotus.category.NOTIFY_HOLDER
     102: invokevirtual #87                 // Method android/content/IntentFilter.addCategory:(Ljava/lang/String;)V
     105: aload_0
     106: getfield      #74                 // Field e:Landroid/content/IntentFilter;
     109: aload_0
     110: getfield      #64                 // Field c:Landroid/net/Uri;
     113: invokevirtual #91                 // Method android/net/Uri.getScheme:()Ljava/lang/String;
     116: invokevirtual #94                 // Method android/content/IntentFilter.addDataScheme:(Ljava/lang/String;)V
     119: aload_0
     120: getfield      #74                 // Field e:Landroid/content/IntentFilter;
     123: aload_0
     124: getfield      #64                 // Field c:Landroid/net/Uri;
     127: invokevirtual #97                 // Method android/net/Uri.getAuthority:()Ljava/lang/String;
     130: aconst_null
     131: invokevirtual #101                // Method android/content/IntentFilter.addDataAuthority:(Ljava/lang/String;Ljava/lang/String;)V
     134: aload_0
     135: getfield      #74                 // Field e:Landroid/content/IntentFilter;
     138: aload_0
     139: getfield      #64                 // Field c:Landroid/net/Uri;
     142: invokevirtual #104                // Method android/net/Uri.getPath:()Ljava/lang/String;
     145: iconst_1
     146: invokevirtual #108                // Method android/content/IntentFilter.addDataPath:(Ljava/lang/String;I)V
     149: return

  static android.os.Bundle a(java.lang.String);
    Code:
       0: aload_0
       1: invokestatic  #112                // Method b:(Ljava/lang/String;)Landroid/os/Bundle;
       4: areturn

  static java.util.Map a(ryey.easer.core.ConditionHolderService);
    Code:
       0: aload_0
       1: getfield      #30                 // Field b:Ljava/util/Map;
       4: areturn

  static java.util.Map b(ryey.easer.core.ConditionHolderService);
    Code:
       0: aload_0
       1: getfield      #28                 // Field a:Ljava/util/Map;
       4: areturn

  static void c(ryey.easer.core.ConditionHolderService);
    Code:
       0: aload_0
       1: invokespecial #231                // Method b:()V
       4: return

  static void d(ryey.easer.core.ConditionHolderService);
    Code:
       0: aload_0
       1: invokespecial #232                // Method a:()V
       4: return

  public android.os.IBinder onBind(android.content.Intent);
    Code:
       0: new           #8                  // class ryey/easer/core/ConditionHolderService$a
       3: dup
       4: aload_0
       5: invokespecial #235                // Method ryey/easer/core/ConditionHolderService$a."<init>":(Lryey/easer/core/ConditionHolderService;)V
       8: areturn

  public void onCreate();
    Code:
       0: aload_0
       1: invokespecial #238                // Method android/app/Service.onCreate:()V
       4: getstatic     #243                // Field ryey/easer/core/h.a:Lryey/easer/core/h$a;
       7: aload_0
       8: invokevirtual #248                // Method ryey/easer/core/h$a.a:(Landroid/app/Service;)V
      11: aload_0
      12: aload_0
      13: getfield      #69                 // Field d:Landroid/content/BroadcastReceiver;
      16: aload_0
      17: getfield      #74                 // Field e:Landroid/content/IntentFilter;
      20: invokevirtual #252                // Method registerReceiver:(Landroid/content/BroadcastReceiver;Landroid/content/IntentFilter;)Landroid/content/Intent;
      23: pop
      24: aload_0
      25: invokespecial #232                // Method a:()V
      28: return

  public void onDestroy();
    Code:
       0: aload_0
       1: invokespecial #255                // Method android/app/Service.onDestroy:()V
       4: getstatic     #243                // Field ryey/easer/core/h.a:Lryey/easer/core/h$a;
       7: aload_0
       8: invokevirtual #257                // Method ryey/easer/core/h$a.b:(Landroid/app/Service;)V
      11: aload_0
      12: aload_0
      13: getfield      #69                 // Field d:Landroid/content/BroadcastReceiver;
      16: invokevirtual #261                // Method unregisterReceiver:(Landroid/content/BroadcastReceiver;)V
      19: aload_0
      20: invokespecial #231                // Method b:()V
      23: return
}
