class ryey.easer.core.ConditionHolderService$1 extends android.content.BroadcastReceiver {
  final ryey.easer.core.ConditionHolderService a;

  ryey.easer.core.ConditionHolderService$1(ryey.easer.core.ConditionHolderService);
    Code:
       0: aload_0
       1: aload_1
       2: putfield      #12                 // Field a:Lryey/easer/core/ConditionHolderService;
       5: aload_0
       6: invokespecial #15                 // Method android/content/BroadcastReceiver."<init>":()V
       9: return

  public void onReceive(android.content.Context, android.content.Intent);
    Code:
       0: ldc           #22                 // String ryey.easer.triggerlotus.action.TRACKER_SATISFIED
       2: aload_2
       3: invokevirtual #28                 // Method android/content/Intent.getAction:()Ljava/lang/String;
       6: invokevirtual #34                 // Method java/lang/String.equals:(Ljava/lang/Object;)Z
       9: ifne          24
      12: ldc           #36                 // String ryey.easer.triggerlotus.action.TRACKER_UNSATISFIED
      14: aload_2
      15: invokevirtual #28                 // Method android/content/Intent.getAction:()Ljava/lang/String;
      18: invokevirtual #34                 // Method java/lang/String.equals:(Ljava/lang/Object;)Z
      21: ifeq          175
      24: aload_2
      25: invokevirtual #40                 // Method android/content/Intent.getData:()Landroid/net/Uri;
      28: invokevirtual #45                 // Method android/net/Uri.getLastPathSegment:()Ljava/lang/String;
      31: astore_3
      32: aload_2
      33: invokevirtual #28                 // Method android/content/Intent.getAction:()Ljava/lang/String;
      36: ldc           #22                 // String ryey.easer.triggerlotus.action.TRACKER_SATISFIED
      38: invokevirtual #34                 // Method java/lang/String.equals:(Ljava/lang/Object;)Z
      41: ifeq          98
      44: aload_0
      45: getfield      #12                 // Field a:Lryey/easer/core/ConditionHolderService;
      48: invokestatic  #48                 // Method ryey/easer/core/ConditionHolderService.a:(Lryey/easer/core/ConditionHolderService;)Ljava/util/Map;
      51: aload_3
      52: invokeinterface #54,  2           // InterfaceMethod java/util/Map.get:(Ljava/lang/Object;)Ljava/lang/Object;
      57: checkcast     #56                 // class java/util/Set
      60: invokeinterface #60,  1           // InterfaceMethod java/util/Set.iterator:()Ljava/util/Iterator;
      65: astore_2
      66: aload_2
      67: invokeinterface #66,  1           // InterfaceMethod java/util/Iterator.hasNext:()Z
      72: ifeq          175
      75: aload_1
      76: aload_2
      77: invokeinterface #70,  1           // InterfaceMethod java/util/Iterator.next:()Ljava/lang/Object;
      82: checkcast     #42                 // class android/net/Uri
      85: aload_3
      86: invokestatic  #73                 // Method ryey/easer/core/ConditionHolderService.a:(Ljava/lang/String;)Landroid/os/Bundle;
      89: invokestatic  #78                 // Method ryey/easer/core/d$a.a:(Landroid/net/Uri;Landroid/os/Bundle;)Landroid/content/Intent;
      92: invokevirtual #84                 // Method android/content/Context.sendBroadcast:(Landroid/content/Intent;)V
      95: goto          66
      98: aload_2
      99: invokevirtual #28                 // Method android/content/Intent.getAction:()Ljava/lang/String;
     102: ldc           #36                 // String ryey.easer.triggerlotus.action.TRACKER_UNSATISFIED
     104: invokevirtual #34                 // Method java/lang/String.equals:(Ljava/lang/Object;)Z
     107: ifeq          175
     110: aload_0
     111: getfield      #12                 // Field a:Lryey/easer/core/ConditionHolderService;
     114: invokestatic  #48                 // Method ryey/easer/core/ConditionHolderService.a:(Lryey/easer/core/ConditionHolderService;)Ljava/util/Map;
     117: aload_3
     118: invokeinterface #54,  2           // InterfaceMethod java/util/Map.get:(Ljava/lang/Object;)Ljava/lang/Object;
     123: checkcast     #56                 // class java/util/Set
     126: invokeinterface #60,  1           // InterfaceMethod java/util/Set.iterator:()Ljava/util/Iterator;
     131: astore_2
     132: aload_2
     133: invokeinterface #66,  1           // InterfaceMethod java/util/Iterator.hasNext:()Z
     138: ifeq          175
     141: aload_1
     142: aload_2
     143: invokeinterface #70,  1           // InterfaceMethod java/util/Iterator.next:()Ljava/lang/Object;
     148: checkcast     #42                 // class android/net/Uri
     151: aload_3
     152: invokestatic  #73                 // Method ryey/easer/core/ConditionHolderService.a:(Ljava/lang/String;)Landroid/os/Bundle;
     155: invokestatic  #87                 // Method ryey/easer/core/d$a.b:(Landroid/net/Uri;Landroid/os/Bundle;)Landroid/content/Intent;
     158: invokevirtual #84                 // Method android/content/Context.sendBroadcast:(Landroid/content/Intent;)V
     161: goto          132
     164: astore_1
     165: aload_1
     166: ldc           #89                 // String ConditionHolder's BroadcastListener shouldn't hear invalid Intent
     168: iconst_0
     169: anewarray     #91                 // class java/lang/Object
     172: invokestatic  #96                 // Method com/b/a/i.a:(Ljava/lang/Throwable;Ljava/lang/String;[Ljava/lang/Object;)V
     175: return
    Exception table:
       from    to  target type
           0    24   164   Class java/lang/NullPointerException
          24    66   164   Class java/lang/NullPointerException
          66    95   164   Class java/lang/NullPointerException
          98   132   164   Class java/lang/NullPointerException
         132   161   164   Class java/lang/NullPointerException
}
