class ryey.easer.core.d$1 extends android.content.BroadcastReceiver {
  final ryey.easer.core.d a;

  ryey.easer.core.d$1(ryey.easer.core.d);
    Code:
       0: aload_0
       1: aload_1
       2: putfield      #12                 // Field a:Lryey/easer/core/d;
       5: aload_0
       6: invokespecial #15                 // Method android/content/BroadcastReceiver."<init>":()V
       9: return

  public void onReceive(android.content.Context, android.content.Intent);
    Code:
       0: aload_2
       1: invokevirtual #24                 // Method android/content/Intent.getAction:()Ljava/lang/String;
       4: astore_1
       5: ldc           #26                 // String ryey.easer.triggerlotus.action.SLOT_SATISFIED
       7: aload_1
       8: invokevirtual #32                 // Method java/lang/String.equals:(Ljava/lang/Object;)Z
      11: ifne          23
      14: ldc           #34                 // String ryey.easer.triggerlotus.action.SLOT_UNSATISFIED
      16: aload_1
      17: invokevirtual #32                 // Method java/lang/String.equals:(Ljava/lang/Object;)Z
      20: ifeq          40
      23: aload_0
      24: getfield      #12                 // Field a:Lryey/easer/core/d;
      27: ldc           #26                 // String ryey.easer.triggerlotus.action.SLOT_SATISFIED
      29: aload_1
      30: invokevirtual #32                 // Method java/lang/String.equals:(Ljava/lang/Object;)Z
      33: aload_2
      34: invokevirtual #38                 // Method android/content/Intent.getExtras:()Landroid/os/Bundle;
      37: invokevirtual #41                 // Method ryey/easer/core/d.a:(ZLandroid/os/Bundle;)V
      40: return
}
