class ryey.easer.core.EHService$2 extends android.content.BroadcastReceiver {
  final ryey.easer.core.EHService a;

  ryey.easer.core.EHService$2(ryey.easer.core.EHService);
    Code:
       0: aload_0
       1: aload_1
       2: putfield      #12                 // Field a:Lryey/easer/core/EHService;
       5: aload_0
       6: invokespecial #15                 // Method android/content/BroadcastReceiver."<init>":()V
       9: return

  public void onReceive(android.content.Context, android.content.Intent);
    Code:
       0: aload_2
       1: invokevirtual #24                 // Method android/content/Intent.getAction:()Ljava/lang/String;
       4: astore_1
       5: ldc           #26                 // String Broadcast received :: action: <%s>
       7: iconst_1
       8: anewarray     #28                 // class java/lang/Object
      11: dup
      12: iconst_0
      13: aload_1
      14: aastore
      15: invokestatic  #33                 // Method com/b/a/i.a:(Ljava/lang/String;[Ljava/lang/Object;)V
      18: ldc           #35                 // String ryey.easer.action.RELOAD
      20: aload_1
      21: invokevirtual #41                 // Method java/lang/String.equals:(Ljava/lang/Object;)Z
      24: ifeq          35
      27: aload_0
      28: getfield      #12                 // Field a:Lryey/easer/core/EHService;
      31: invokestatic  #44                 // Method ryey/easer/core/EHService.d:(Lryey/easer/core/EHService;)V
      34: return
      35: ldc           #46                 // String ryey.easer.service.action.REGISTER_CONDITION_EVENT
      37: aload_2
      38: invokevirtual #24                 // Method android/content/Intent.getAction:()Ljava/lang/String;
      41: invokevirtual #41                 // Method java/lang/String.equals:(Ljava/lang/Object;)Z
      44: ifne          59
      47: ldc           #48                 // String ryey.easer.service.action.UNREGISTER_CONDITION_EVENT
      49: aload_2
      50: invokevirtual #24                 // Method android/content/Intent.getAction:()Ljava/lang/String;
      53: invokevirtual #41                 // Method java/lang/String.equals:(Ljava/lang/Object;)Z
      56: ifeq          122
      59: aload_2
      60: ldc           #50                 // String ryey.easer.service.extra.CONDITION_NAME
      62: invokevirtual #54                 // Method android/content/Intent.getStringExtra:(Ljava/lang/String;)Ljava/lang/String;
      65: astore_1
      66: aload_2
      67: ldc           #56                 // String ryey.easer.service.extra.NOTIFY_DATA
      69: invokevirtual #60                 // Method android/content/Intent.getParcelableExtra:(Ljava/lang/String;)Landroid/os/Parcelable;
      72: checkcast     #62                 // class android/net/Uri
      75: astore_3
      76: aload_0
      77: getfield      #12                 // Field a:Lryey/easer/core/EHService;
      80: ldc           #64                 // String [EHService]
      82: invokestatic  #67                 // Method ryey/easer/core/EHService.a:(Lryey/easer/core/EHService;Ljava/lang/String;)V
      85: ldc           #46                 // String ryey.easer.service.action.REGISTER_CONDITION_EVENT
      87: aload_2
      88: invokevirtual #24                 // Method android/content/Intent.getAction:()Ljava/lang/String;
      91: invokevirtual #41                 // Method java/lang/String.equals:(Ljava/lang/Object;)Z
      94: ifeq          110
      97: aload_0
      98: getfield      #12                 // Field a:Lryey/easer/core/EHService;
     101: getfield      #71                 // Field ryey/easer/core/EHService.b:Lryey/easer/core/ConditionHolderService$a;
     104: aload_1
     105: aload_3
     106: invokevirtual #76                 // Method ryey/easer/core/ConditionHolderService$a.a:(Ljava/lang/String;Landroid/net/Uri;)V
     109: return
     110: aload_0
     111: getfield      #12                 // Field a:Lryey/easer/core/EHService;
     114: getfield      #71                 // Field ryey/easer/core/EHService.b:Lryey/easer/core/ConditionHolderService$a;
     117: aload_1
     118: aload_3
     119: invokevirtual #78                 // Method ryey/easer/core/ConditionHolderService$a.b:(Ljava/lang/String;Landroid/net/Uri;)V
     122: return
}
