class ryey.easer.core.f$1 implements android.content.ServiceConnection {
  final ryey.easer.core.f a;

  ryey.easer.core.f$1(ryey.easer.core.f);
    Code:
       0: aload_0
       1: aload_1
       2: putfield      #14                 // Field a:Lryey/easer/core/f;
       5: aload_0
       6: invokespecial #17                 // Method java/lang/Object."<init>":()V
       9: return

  public void onServiceConnected(android.content.ComponentName, android.os.IBinder);
    Code:
       0: ldc           #22                 // String [RemotePluginCommunicationHelper:%s] onServiceConnected
       2: iconst_1
       3: anewarray     #4                  // class java/lang/Object
       6: dup
       7: iconst_0
       8: aload_0
       9: getfield      #14                 // Field a:Lryey/easer/core/f;
      12: invokestatic  #25                 // Method ryey/easer/core/f.a:(Lryey/easer/core/f;)Landroid/content/Context;
      15: aastore
      16: invokestatic  #30                 // Method com/b/a/i.a:(Ljava/lang/String;[Ljava/lang/Object;)V
      19: aload_0
      20: getfield      #14                 // Field a:Lryey/easer/core/f;
      23: new           #32                 // class android/os/Messenger
      26: dup
      27: aload_2
      28: invokespecial #35                 // Method android/os/Messenger."<init>":(Landroid/os/IBinder;)V
      31: invokestatic  #38                 // Method ryey/easer/core/f.a:(Lryey/easer/core/f;Landroid/os/Messenger;)Landroid/os/Messenger;
      34: pop
      35: aload_0
      36: getfield      #14                 // Field a:Lryey/easer/core/f;
      39: invokestatic  #42                 // Method ryey/easer/core/f.c:(Lryey/easer/core/f;)Lryey/easer/core/f$a;
      42: aload_0
      43: getfield      #14                 // Field a:Lryey/easer/core/f;
      46: invokestatic  #46                 // Method ryey/easer/core/f.b:(Lryey/easer/core/f;)Landroid/os/Messenger;
      49: invokevirtual #51                 // Method ryey/easer/core/f$a.a:(Landroid/os/Messenger;)V
      52: return

  public void onServiceDisconnected(android.content.ComponentName);
    Code:
       0: aload_0
       1: getfield      #14                 // Field a:Lryey/easer/core/f;
       4: invokestatic  #42                 // Method ryey/easer/core/f.c:(Lryey/easer/core/f;)Lryey/easer/core/f$a;
       7: invokevirtual #55                 // Method ryey/easer/core/f$a.a:()V
      10: aload_0
      11: getfield      #14                 // Field a:Lryey/easer/core/f;
      14: aconst_null
      15: invokestatic  #38                 // Method ryey/easer/core/f.a:(Lryey/easer/core/f;Landroid/os/Messenger;)Landroid/os/Messenger;
      18: pop
      19: return
}
