class ryey.easer.core.f$a$1 implements ryey.easer.core.f$c {
  final ryey.easer.core.f$a a;

  ryey.easer.core.f$a$1(ryey.easer.core.f$a);
    Code:
       0: aload_0
       1: aload_1
       2: putfield      #16                 // Field a:Lryey/easer/core/f$a;
       5: aload_0
       6: invokespecial #19                 // Method java/lang/Object."<init>":()V
       9: return

  public void a(android.os.Messenger);
    Code:
       0: aload_0
       1: getfield      #16                 // Field a:Lryey/easer/core/f$a;
       4: getfield      #26                 // Field ryey/easer/core/f$a.a:Ljava/util/concurrent/locks/Lock;
       7: invokeinterface #31,  1           // InterfaceMethod java/util/concurrent/locks/Lock.lock:()V
      12: aload_0
      13: getfield      #16                 // Field a:Lryey/easer/core/f$a;
      16: getfield      #35                 // Field ryey/easer/core/f$a.b:Ljava/util/List;
      19: invokeinterface #41,  1           // InterfaceMethod java/util/List.size:()I
      24: iconst_1
      25: isub
      26: istore_2
      27: iload_2
      28: iflt          84
      31: aload_0
      32: getfield      #16                 // Field a:Lryey/easer/core/f$a;
      35: getfield      #35                 // Field ryey/easer/core/f$a.b:Ljava/util/List;
      38: iload_2
      39: invokeinterface #45,  2           // InterfaceMethod java/util/List.get:(I)Ljava/lang/Object;
      44: checkcast     #47                 // class java/util/concurrent/Callable
      47: astore_1
      48: aload_1
      49: invokeinterface #51,  1           // InterfaceMethod java/util/concurrent/Callable.call:()Ljava/lang/Object;
      54: pop
      55: goto          63
      58: astore_1
      59: aload_1
      60: invokestatic  #56                 // Method com/google/a/a/a/a/a/a.a:(Ljava/lang/Throwable;)V
      63: aload_0
      64: getfield      #16                 // Field a:Lryey/easer/core/f$a;
      67: getfield      #35                 // Field ryey/easer/core/f$a.b:Ljava/util/List;
      70: iload_2
      71: invokeinterface #59,  2           // InterfaceMethod java/util/List.remove:(I)Ljava/lang/Object;
      76: pop
      77: iload_2
      78: iconst_1
      79: isub
      80: istore_2
      81: goto          27
      84: aload_0
      85: getfield      #16                 // Field a:Lryey/easer/core/f$a;
      88: getfield      #26                 // Field ryey/easer/core/f$a.a:Ljava/util/concurrent/locks/Lock;
      91: invokeinterface #62,  1           // InterfaceMethod java/util/concurrent/locks/Lock.unlock:()V
      96: return
      97: astore_1
      98: aload_0
      99: getfield      #16                 // Field a:Lryey/easer/core/f$a;
     102: getfield      #26                 // Field ryey/easer/core/f$a.a:Ljava/util/concurrent/locks/Lock;
     105: invokeinterface #62,  1           // InterfaceMethod java/util/concurrent/locks/Lock.unlock:()V
     110: aload_1
     111: athrow
    Exception table:
       from    to  target type
          12    27    97   any
          31    48    97   any
          48    55    58   Class java/lang/Exception
          48    55    97   any
          59    63    97   any
          63    77    97   any
}
