public final class ryey.easer.core.h {
  public static final ryey.easer.core.h$a a;

  static {};
    Code:
       0: new           #6                  // class ryey/easer/core/h$a
       3: dup
       4: aconst_null
       5: invokespecial #23                 // Method ryey/easer/core/h$a."<init>":(La/b/b/a;)V
       8: putstatic     #25                 // Field a:Lryey/easer/core/h$a;
      11: return

  public static final int a();
    Code:
       0: getstatic     #29                 // Field d:I
       3: ireturn

  public static final void a(int);
    Code:
       0: iload_0
       1: putstatic     #29                 // Field d:I
       4: return

  public static final int b();
    Code:
       0: getstatic     #32                 // Field c:I
       3: ireturn

  public static final void b(int);
    Code:
       0: iload_0
       1: putstatic     #34                 // Field e:I
       4: return

  public static final int c();
    Code:
       0: getstatic     #34                 // Field e:I
       3: ireturn
}
