public class ryey.easer.core.ui.data.a$b {
  public final java.lang.String a;

  final int b;

  public ryey.easer.core.ui.data.a$b(java.lang.String);
    Code:
       0: aload_0
       1: invokespecial #15                 // Method java/lang/Object."<init>":()V
       4: aload_0
       5: aload_1
       6: putfield      #17                 // Field a:Ljava/lang/String;
       9: aload_0
      10: ldc           #18                 // int 2131099697
      12: putfield      #20                 // Field b:I
      15: return

  public ryey.easer.core.ui.data.a$b(java.lang.String, int);
    Code:
       0: aload_0
       1: invokespecial #15                 // Method java/lang/Object."<init>":()V
       4: aload_0
       5: aload_1
       6: putfield      #17                 // Field a:Ljava/lang/String;
       9: aload_0
      10: iload_2
      11: putfield      #20                 // Field b:I
      14: return
}
