class ryey.easer.core.ui.data.b$3 implements android.content.DialogInterface$OnCancelListener {
  final ryey.easer.core.ui.data.b a;

  ryey.easer.core.ui.data.b$3(ryey.easer.core.ui.data.b);
    Code:
       0: aload_0
       1: aload_1
       2: putfield      #17                 // Field a:Lryey/easer/core/ui/data/b;
       5: aload_0
       6: invokespecial #20                 // Method java/lang/Object."<init>":()V
       9: return

  public void onCancel(android.content.DialogInterface);
    Code:
       0: aload_0
       1: getfield      #17                 // Field a:Lryey/easer/core/ui/data/b;
       4: invokevirtual #26                 // Method ryey/easer/core/ui/data/b.finish:()V
       7: return
}
