public class ryey.easer.plugins.a.a.c implements ryey.easer.commons.local_plugin.a.c<ryey.easer.plugins.a.a.a> {
  public ryey.easer.plugins.a.a.c();
    Code:
       0: aload_0
       1: invokespecial #11                 // Method java/lang/Object."<init>":()V
       4: return

  public java.lang.String a();
    Code:
       0: ldc           #16                 // String battery
       2: areturn

  public ryey.easer.commons.local_plugin.a.d a(android.content.Context, ryey.easer.commons.local_plugin.a.a, android.app.PendingIntent, android.app.PendingIntent);
    Code:
       0: aload_0
       1: aload_1
       2: aload_2
       3: checkcast     #19                 // class ryey/easer/plugins/a/a/a
       6: aload_3
       7: aload         4
       9: invokevirtual #22                 // Method a:(Landroid/content/Context;Lryey/easer/plugins/a/a/a;Landroid/app/PendingIntent;Landroid/app/PendingIntent;)Lryey/easer/commons/local_plugin/a/d;
      12: areturn

  public ryey.easer.commons.local_plugin.a.d<ryey.easer.plugins.a.a.a> a(android.content.Context, ryey.easer.plugins.a.a.a, android.app.PendingIntent, android.app.PendingIntent);
    Code:
       0: new           #24                 // class ryey/easer/plugins/a/a/e
       3: dup
       4: aload_1
       5: aload_2
       6: aload_3
       7: aload         4
       9: invokespecial #27                 // Method ryey/easer/plugins/a/a/e."<init>":(Landroid/content/Context;Lryey/easer/plugins/a/a/a;Landroid/app/PendingIntent;Landroid/app/PendingIntent;)V
      12: areturn

  public void a(android.app.Activity, int);
    Code:
       0: return

  public boolean a(android.content.Context);
    Code:
       0: iconst_1
       1: ireturn

  public int b();
    Code:
       0: ldc           #34                 // int 2131624053
       2: ireturn

  public boolean b(android.content.Context);
    Code:
       0: iconst_1
       1: ireturn

  public ryey.easer.commons.local_plugin.a c();
    Code:
       0: aload_0
       1: invokevirtual #40                 // Method e:()Lryey/easer/commons/local_plugin/a/b;
       4: areturn

  public ryey.easer.commons.local_plugin.e<ryey.easer.plugins.a.a.a> d();
    Code:
       0: new           #44                 // class ryey/easer/plugins/a/a/d
       3: dup
       4: invokespecial #45                 // Method ryey/easer/plugins/a/a/d."<init>":()V
       7: areturn

  public ryey.easer.commons.local_plugin.a.b<ryey.easer.plugins.a.a.a> e();
    Code:
       0: new           #48                 // class ryey/easer/plugins/a/a/b
       3: dup
       4: invokespecial #49                 // Method ryey/easer/plugins/a/a/b."<init>":()V
       7: areturn
}
